Workbook

Sheet Healthcare SG&A
A1: Sector | B1: Subsector | C1: Core Activity | D1: Effort Split | E1: Key Main Task | F1: % Effort | G1: Category | H1: AI Addressable | I1: Agentification Potential | J1: Actual Agentification Possible | K1: NA | L1: EU | M1: APAC ex India | N1: India
A2: Healthcare | B2: Providers | C2: Finance & Accounting | D2: 0.2 | E2: Transaction processing & reconciliation | F2: 0.3 | G2: Task Processing / Query Handling | H2: 0.9 | I2: =SUMPRODUCT(H2:H5,F2:F5)*D2 -> 0.1655 | J2: 0.62 | K2: 0.62 | L2: 0.58 | M2: 0.52 | N2: 0.45
A3: Healthcare | B3: Providers | C3: Finance & Accounting | D3: 0.2 | E3: Financial planning & analysis | F3: 0.25 | G3: Assessment & Analysis | H3: 0.6 | J3: 0.62 | K3: 0.62 | L3: 0.58 | M3: 0.52 | N3: 0.45
A4: Healthcare | B4: Providers | C4: Finance & Accounting | D4: 0.2 | E4: Budgeting & forecasting | F4: 0.2 | G4: Modelling (incl. Forecasting) | H4: 0.85 | J4: 0.62 | K4: 0.62 | L4: 0.58 | M4: 0.52 | N4: 0.45
A5: Healthcare | B5: Providers | C5: Finance & Accounting | D5: 0.2 | E5: Financial reporting | F5: 0.25 | G5: Document Generation & Management | H5: 0.95 | J5: 0.62 | K5: 0.62 | L5: 0.58 | M5: 0.52 | N5: 0.45
A6: Healthcare | B6: Providers | C6: Human Resources | D6: 0.2 | E6: Recruitment administration | F6: 0.25 | G6: Task Processing / Query Handling | H6: 0.9 | I6: =SUMPRODUCT(H6:H9,F6:F9)*D6 -> 0.124 | J6: 0.5 | K6: 0.5 | L6: 0.47 | M6: 0.42 | N6: 0.36
A7: Healthcare | B7: Providers | C7: Human Resources | D7: 0.2 | E7: Workforce planning | F7: 0.25 | G7: Task Planning & Management | H7: 0.7 | J7: 0.5 | K7: 0.5 | L7: 0.47 | M7: 0.42 | N7: 0.36
A8: Healthcare | B8: Providers | C8: Human Resources | D8: 0.2 | E8: Employee relations & support | F8: 0.3 | G8: Stakeholder / Relationship Management | H8: 0.1 | J8: 0.5 | K8: 0.5 | L8: 0.47 | M8: 0.42 | N8: 0.36
A9: Healthcare | B9: Providers | C9: Human Resources | D9: 0.2 | E9: HR documentation & reporting | F9: 0.2 | G9: Document Generation & Management | H9: 0.95 | J9: 0.5 | K9: 0.5 | L9: 0.47 | M9: 0.42 | N9: 0.36
A10: Healthcare | B10: Providers | C10: Revenue Cycle & Administrative Support | D10: 0.2 | E10: Billing administration | F10: 0.3 | G10: Task Processing / Query Handling | H10: 0.9 | I10: =SUMPRODUCT(H10:H13,F10:F13)*D10 -> 0.17 | J10: 0.68 | K10: 0.68 | L10: 0.63 | M10: 0.56 | N10: 0.48
A11: Healthcare | B11: Providers | C11: Revenue Cycle & Administrative Support | D11: 0.2 | E11: Claims & payment follow-up | F11: 0.3 | G11: Task Processing / Query Handling | H11: 0.9 | J11: 0.68 | K11: 0.68 | L11: 0.63 | M11: 0.56 | N11: 0.48
A12: Healthcare | B12: Providers | C12: Revenue Cycle & Administrative Support | D12: 0.2 | E12: Denial analysis | F12: 0.2 | G12: Assessment & Analysis | H12: 0.6 | J12: 0.68 | K12: 0.68 | L12: 0.63 | M12: 0.56 | N12: 0.48
A13: Healthcare | B13: Providers | C13: Revenue Cycle & Administrative Support | D13: 0.2 | E13: Administrative documentation | F13: 0.2 | G13: Document Generation & Management | H13: 0.95 | J13: 0.68 | K13: 0.68 | L13: 0.63 | M13: 0.56 | N13: 0.48
A14: Healthcare | B14: Providers | C14: Corporate IT & Enterprise Technology | D14: 0.15 | E14: IT service desk & user support | F14: 0.3 | G14: Task Processing / Query Handling | H14: 0.9 | I14: =SUMPRODUCT(H14:H17,F14:F17)*D14 -> 0.1215 | J14: 0.64 | K14: 0.64 | L14: 0.6 | M14: 0.54 | N14: 0.47
A15: Healthcare | B15: Providers | C15: Corporate IT & Enterprise Technology | D15: 0.15 | E15: Application & infrastructure monitoring | F15: 0.25 | G15: Monitoring | H15: 0.7 | J15: 0.64 | K15: 0.64 | L15: 0.6 | M15: 0.54 | N15: 0.47
A16: Healthcare | B16: Providers | C16: Corporate IT & Enterprise Technology | D16: 0.15 | E16: Technology planning & change coordination | F16: 0.25 | G16: Task Planning & Management | H16: 0.7 | J16: 0.64 | K16: 0.64 | L16: 0.6 | M16: 0.54 | N16: 0.47
A17: Healthcare | B17: Providers | C17: Corporate IT & Enterprise Technology | D17: 0.15 | E17: IT documentation | F17: 0.2 | G17: Document Generation & Management | H17: 0.95 | J17: 0.64 | K17: 0.64 | L17: 0.6 | M17: 0.54 | N17: 0.47
A18: Healthcare | B18: Providers | C18: Procurement & Vendor Management | D18: 0.1 | E18: Purchase administration | F18: 0.25 | G18: Task Processing / Query Handling | H18: 0.9 | I18: =SUMPRODUCT(H18:H21,F18:F21)*D18 -> 0.0595 | J18: 0.45 | K18: 0.45 | L18: 0.42 | M18: 0.37 | N18: 0.32
A19: Healthcare | B19: Providers | C19: Procurement & Vendor Management | D19: 0.1 | E19: Supplier evaluation & spend analysis | F19: 0.25 | G19: Assessment & Analysis | H19: 0.6 | J19: 0.45 | K19: 0.45 | L19: 0.42 | M19: 0.37 | N19: 0.32
A20: Healthcare | B20: Providers | C20: Procurement & Vendor Management | D20: 0.1 | E20: Vendor relationship management | F20: 0.3 | G20: Stakeholder / Relationship Management | H20: 0.1 | J20: 0.45 | K20: 0.45 | L20: 0.42 | M20: 0.37 | N20: 0.32
A21: Healthcare | B21: Providers | C21: Procurement & Vendor Management | D21: 0.1 | E21: Contract & procurement documentation | F21: 0.2 | G21: Document Generation & Management | H21: 0.95 | J21: 0.45 | K21: 0.45 | L21: 0.42 | M21: 0.37 | N21: 0.32
A22: Healthcare | B22: Providers | C22: Legal, Risk & Compliance | D22: 0.1 | E22: Compliance monitoring | F22: 0.25 | G22: Monitoring | H22: 0.7 | I22: =SUMPRODUCT(H22:H25,F22:F25)*D22 -> 0.05875 | J22: 0.45 | K22: 0.45 | L22: 0.42 | M22: 0.37 | N22: 0.32
A23: Healthcare | B23: Providers | C23: Legal, Risk & Compliance | D23: 0.1 | E23: Contract & policy review | F23: 0.25 | G23: Assessment & Analysis | H23: 0.6 | J23: 0.45 | K23: 0.45 | L23: 0.42 | M23: 0.37 | N23: 0.32
A24: Healthcare | B24: Providers | C24: Legal & Risk & Compliance | D24: 0.1 | E24: Regulatory stakeholder management | F24: 0.25 | G24: Stakeholder / Relationship Management | H24: 0.1 | J24: 0.45 | K24: 0.45 | L24: 0.42 | M24: 0.37 | N24: 0.32
A25: Healthcare | B25: Providers | C25: Legal, Risk & Compliance | D25: 0.1 | E25: Compliance documentation | F25: 0.25 | G25: Document Generation & Management | H25: 0.95 | J25: 0.45 | K25: 0.45 | L25: 0.42 | M25: 0.37 | N25: 0.32
A26: Healthcare | B26: Providers | C26: Corporate Strategy & General Administration | D26: 0.05 | E26: Strategic planning | F26: 0.3 | G26: Strategy & Design | H26: 0.3 | I26: =SUMPRODUCT(H26:H29,F26:F29)*D26 -> 0.02275 | J26: 0.38 | K26: 0.38 | L26: 0.35 | M26: 0.31 | N26: 0.27
A27: Healthcare | B27: Providers | C27: Corporate Strategy & General Administration | D27: 0.05 | E27: Management analysis | F27: 0.25 | G27: Assessment & Analysis | H27: 0.6 | J27: 0.38 | K27: 0.38 | L27: 0.35 | M27: 0.31 | N27: 0.27
A28: Healthcare | B28: Providers | C28: Corporate Strategy & General Administration | D28: 0.05 | E28: Executive stakeholder coordination | F28: 0.25 | G28: Stakeholder / Relationship Management | H28: 0.1 | J28: 0.38 | K28: 0.38 | L28: 0.35 | M28: 0.31 | N28: 0.27
A29: Healthcare | B29: Providers | C29: Corporate Strategy & General Administration | D29: 0.05 | E29: Corporate reporting | F29: 0.2 | G29: Document Generation & Management | H29: 0.95 | J29: 0.38 | K29: 0.38 | L29: 0.35 | M29: 0.31 | N29: 0.27
I30: =SUM(I2:I29) -> 0.722 | J30: =J2*$D2+J6*$D6+J10*$D10+J14*$D14+J18*$D18+J22*$D22+J26*$D26 -> 0.565 | K30: =K2*$D2+K6*$D6+K10*$D10+K14*$D14+K18*$D18+K22*$D22+K26*$D26 -> 0.565 | L30: =L2*$D2+L6*$D6+L10*$D10+L14*$D14+L18*$D18+L22*$D22+L26*$D26 -> 0.5275 | M30: =M2*$D2+M6*$D6+M10*$D10+M14*$D14+M18*$D18+M22*$D22+M26*$D26 -> 0.4705 | N30: =N2*$D2+N6*$D6+N10*$D10+N14*$D14+N18*$D18+N22*$D22+N26*$D26 -> 0.406
A32: Healthcare | B32: Payers | C32: Customer & Member Operations | D32: 0.2 | E32: Member queries & service requests | F32: 0.35 | G32: Task Processing / Query Handling | H32: 0.9 | I32: =SUMPRODUCT(H32:H35,F32:F35)*D32 -> 0.17 | J32: 0.66 | K32: 0.66 | L32: 0.62 | M32: 0.56 | N32: 0.48
A33: Healthcare | B33: Payers | C33: Customer & Member Operations | D33: 0.2 | E33: Enrollment & account administration | F33: 0.25 | G33: Task Processing / Query Handling | H33: 0.9 | J33: 0.66 | K33: 0.66 | L33: 0.62 | M33: 0.56 | N33: 0.48
A34: Healthcare | B34: Payers | C34: Customer & Member Operations | D34: 0.2 | E34: Member issue assessment | F34: 0.2 | G34: Assessment & Analysis | H34: 0.6 | J34: 0.66 | K34: 0.66 | L34: 0.62 | M34: 0.56 | N34: 0.48
A35: Healthcare | B35: Payers | C35: Customer & Member Operations | D35: 0.2 | E35: Member communications | F35: 0.2 | G35: Document Generation & Management | H35: 0.95 | J35: 0.66 | K35: 0.66 | L35: 0.62 | M35: 0.56 | N35: 0.48
A36: Healthcare | B36: Payers | C36: Sales & Distribution | D36: 0.15 | E36: Sales planning & targeting | F36: 0.25 | G36: Task Planning & Management | H36: 0.7 | I36: =SUMPRODUCT(H36:H39,F36:F39)*D36 -> 0.078 | J36: 0.44 | K36: 0.44 | L36: 0.41 | M36: 0.36 | N36: 0.31
A37: Healthcare | B37: Payers | C37: Sales & Distribution | D37: 0.15 | E37: Broker / employer relationship management | F37: 0.35 | G37: Stakeholder / Relationship Management | H37: 0.1 | J37: 0.44 | K37: 0.44 | L37: 0.41 | M37: 0.36 | N37: 0.31
A38: Healthcare | B38: Payers | C38: Sales & Distribution | D38: 0.15 | E38: Proposal & quote support | F38: 0.2 | G38: Document Generation & Management | H38: 0.95 | J38: 0.44 | K38: 0.44 | L38: 0.41 | M38: 0.36 | N38: 0.31
A39: Healthcare | B39: Payers | C39: Sales & Distribution | D39: 0.15 | E39: Sales performance analysis | F39: 0.2 | G39: Assessment & Analysis | H39: 0.6 | J39: 0.44 | K39: 0.44 | L39: 0.41 | M39: 0.36 | N39: 0.31
A40: Healthcare | B40: Payers | C40: Finance & Accounting | D40: 0.15 | E40: Transaction processing & reconciliation | F40: 0.3 | G40: Task Processing / Query Handling | H40: 0.9 | I40: =SUMPRODUCT(H40:H43,F40:F43)*D40 -> 0.124125 | J40: 0.62 | K40: 0.62 | L40: 0.58 | M40: 0.52 | N40: 0.45
A41: Healthcare | B41: Payers | C41: Finance & Accounting | D41: 0.15 | E41: Financial planning & analysis | F41: 0.25 | G41: Assessment & Analysis | H41: 0.6 | J41: 0.62 | K41: 0.62 | L41: 0.58 | M41: 0.52 | N41: 0.45
A42: Healthcare | B42: Payers | C42: Finance & Accounting | D42: 0.15 | E42: Budgeting & forecasting | F42: 0.2 | G42: Modelling (incl. Forecasting) | H42: 0.85 | J42: 0.62 | K42: 0.62 | L42: 0.58 | M42: 0.52 | N42: 0.45
A43: Healthcare | B43: Payers | C43: Finance & Accounting | D43: 0.15 | E43: Financial reporting | F43: 0.25 | G43: Document Generation & Management | H43: 0.95 | J43: 0.62 | K43: 0.62 | L43: 0.58 | M43: 0.52 | N43: 0.45
A44: Healthcare | B44: Payers | C44: Human Resources | D44: 0.1 | E44: Recruitment administration | F44: 0.25 | G44: Task Processing / Query Handling | H44: 0.9 | I44: =SUMPRODUCT(H44:H47,F44:F47)*D44 -> 0.062 | J44: 0.5 | K44: 0.5 | L44: 0.47 | M44: 0.42 | N44: 0.36
A45: Healthcare | B45: Payers | C45: Human Resources | D45: 0.1 | E45: Workforce planning | F45: 0.25 | G45: Task Planning & Management | H45: 0.7 | J45: 0.5 | K45: 0.5 | L45: 0.47 | M45: 0.42 | N45: 0.36
A46: Healthcare | B46: Payers | C46: Human Resources | D46: 0.1 | E46: Employee relations & support | F46: 0.3 | G46: Stakeholder / Relationship Management | H46: 0.1 | J46: 0.5 | K46: 0.5 | L46: 0.47 | M46: 0.42 | N46: 0.36
A47: Healthcare | B47: Payers | C47: Human Resources | D47: 0.1 | E47: HR documentation & reporting | F47: 0.2 | G47: Document Generation & Management | H47: 0.95 | J47: 0.5 | K47: 0.5 | L47: 0.47 | M47: 0.42 | N47: 0.36
A48: Healthcare | B48: Payers | C48: Marketing & Member Engagement | D48: 0.1 | E48: Campaign & content development | F48: 0.3 | G48: Content Generation | H48: 0.7 | I48: =SUMPRODUCT(H48:H51,F48:F51)*D48 -> 0.0525 | J48: 0.5 | K48: 0.5 | L48: 0.47 | M48: 0.42 | N48: 0.36
A49: Healthcare | B49: Payers | C49: Marketing & Member Engagement | D49: 0.1 | E49: Member segmentation & analytics | F49: 0.25 | G49: Assessment & Analysis | H49: 0.6 | J49: 0.5 | K49: 0.5 | L49: 0.47 | M49: 0.42 | N49: 0.36
A50: Healthcare | B50: Payers | C50: Marketing & Member Engagement | D50: 0.1 | E50: Campaign planning | F50: 0.2 | G50: Task Planning & Management | H50: 0.7 | J50: 0.5 | K50: 0.5 | L50: 0.47 | M50: 0.42 | N50: 0.36
A51: Healthcare | B51: Payers | C51: Marketing & Member Engagement | D51: 0.1 | E51: Agency / channel coordination | F51: 0.25 | G51: Stakeholder / Relationship Management | H51: 0.1 | J51: 0.5 | K51: 0.5 | L51: 0.47 | M51: 0.42 | N51: 0.36
A52: Healthcare | B52: Payers | C52: Corporate IT & Enterprise Technology | D52: 0.15 | E52: IT service desk & user support | F52: 0.3 | G52: Task Processing / Query Handling | H52: 0.9 | I52: =SUMPRODUCT(H52:H55,F52:F55)*D52 -> 0.1215 | J52: 0.64 | K52: 0.64 | L52: 0.6 | M52: 0.54 | N52: 0.47
A53: Healthcare | B53: Payers | C53: Corporate IT & Enterprise Technology | D53: 0.15 | E53: Application & infrastructure monitoring | F53: 0.25 | G53: Monitoring | H53: 0.7 | J53: 0.64 | K53: 0.64 | L53: 0.6 | M53: 0.54 | N53: 0.47
A54: Healthcare | B54: Payers | C54: Corporate IT & Enterprise Technology | D54: 0.15 | E54: Technology planning & change coordination | F54: 0.25 | G54: Task Planning & Management | H54: 0.7 | J54: 0.64 | K54: 0.64 | L54: 0.6 | M54: 0.54 | N54: 0.47
A55: Healthcare | B55: Payers | C55: Corporate IT & Enterprise Technology | D55: 0.15 | E55: IT documentation | F55: 0.2 | G55: Document Generation & Management | H55: 0.95 | J55: 0.64 | K55: 0.64 | L55: 0.6 | M55: 0.54 | N55: 0.47
A56: Healthcare | B56: Payers | C56: Legal, Risk & Compliance | D56: 0.1 | E56: Compliance monitoring | F56: 0.25 | G56: Monitoring | H56: 0.7 | I56: =SUMPRODUCT(H56:H59,F56:F59)*D56 -> 0.05875 | J56: 0.45 | K56: 0.45 | L56: 0.42 | M56: 0.37 | N56: 0.32
A57: Healthcare | B57: Payers | C57: Legal, Risk & Compliance | D57: 0.1 | E57: Contract & policy review | F57: 0.25 | G57: Assessment & Analysis | H57: 0.6 | J57: 0.45 | K57: 0.45 | L57: 0.42 | M57: 0.37 | N57: 0.32
A58: Healthcare | B58: Payers | C58: Legal, Risk & Compliance | D58: 0.1 | E58: Regulatory stakeholder management | F58: 0.25 | G58: Stakeholder / Relationship Management | H58: 0.1 | J58: 0.45 | K58: 0.45 | L58: 0.42 | M58: 0.37 | N58: 0.32
A59: Healthcare | B59: Payers | C59: Legal, Risk & Compliance | D59: 0.1 | E59: Compliance documentation | F59: 0.25 | G59: Document Generation & Management | H59: 0.95 | J59: 0.45 | K59: 0.45 | L59: 0.42 | M59: 0.37 | N59: 0.32
A60: Healthcare | B60: Payers | C60: Corporate Strategy & General Administration | D60: 0.05 | E60: Strategic planning | F60: 0.3 | G60: Strategy & Design | H60: 0.3 | I60: =SUMPRODUCT(H60:H63,F60:F63)*D60 -> 0.02275 | J60: 0.38 | K60: 0.38 | L60: 0.35 | M60: 0.31 | N60: 0.27
A61: Healthcare | B61: Payers | C61: Corporate Strategy & General Administration | D61: 0.05 | E61: Management analysis | F61: 0.25 | G61: Assessment & Analysis | H61: 0.6 | J61: 0.38 | K61: 0.38 | L61: 0.35 | M61: 0.31 | N61: 0.27
A62: Healthcare | B62: Payers | C62: Corporate Strategy & General Administration | D62: 0.05 | E62: Executive stakeholder coordination | F62: 0.25 | G62: Stakeholder / Relationship Management | H62: 0.1 | J62: 0.38 | K62: 0.38 | L62: 0.35 | M62: 0.31 | N62: 0.27
A63: Healthcare | B63: Payers | C63: Corporate Strategy & General Administration | D63: 0.05 | E63: Corporate reporting | F63: 0.2 | G63: Document Generation & Management | H63: 0.95 | J63: 0.38 | K63: 0.38 | L63: 0.35 | M63: 0.31 | N63: 0.27
I64: =SUM(I36:I63) -> 0.519625 | J64: =J36*$D36+J40*$D40+J44*$D44+J48*$D48+J52*$D52+J56*$D56+J60*$D60 -> 0.419 | K64: =K36*$D36+K40*$D40+K44*$D44+K48*$D48+K52*$D52+K56*$D56+K60*$D60 -> 0.419 | L64: =L36*$D36+L40*$D40+L44*$D44+L48*$D48+L52*$D52+L56*$D56+L60*$D60 -> 0.392 | M64: =M36*$D36+M40*$D40+M44*$D44+M48*$D48+M52*$D52+M56*$D56+M60*$D60 -> 0.3495 | N64: =N36*$D36+N40*$D40+N44*$D44+N48*$D48+N52*$D52+N56*$D56+N60*$D60 -> 0.302
A66: Healthcare | B66: Pharma | C66: Sales & Commercial Operations | D66: 0.35 | E66: Sales planning & targeting | F66: 0.25 | G66: Task Planning & Management | H66: 0.7 | I66: =SUMPRODUCT(H66:H69,F66:F69)*D66 -> 0.182 | J66: 0.45 | K66: 0.45 | L66: 0.42 | M66: 0.37 | N66: 0.32
A67: Healthcare | B67: Pharma | C67: Sales & Commercial Operations | D67: 0.35 | E67: HCP / account engagement | F67: 0.35 | G67: Stakeholder / Relationship Management | H67: 0.1 | J67: 0.45 | K67: 0.45 | L67: 0.42 | M67: 0.37 | N67: 0.32
A68: Healthcare | B68: Pharma | C68: Sales & Commercial Operations | D68: 0.35 | E68: Sales analytics & next-best-action | F68: 0.2 | G68: Assessment & Analysis | H68: 0.6 | J68: 0.45 | K68: 0.45 | L68: 0.42 | M68: 0.37 | N68: 0.32
A69: Healthcare | B69: Pharma | C69: Sales & Commercial Operations | D69: 0.35 | E69: Commercial administration & reporting | F69: 0.2 | G69: Document Generation & Management | H69: 0.95 | J69: 0.45 | K69: 0.45 | L69: 0.42 | M69: 0.37 | N69: 0.32
A70: Healthcare | B70: Pharma | C70: Marketing & Brand Management | D70: 0.2 | E70: Content development | F70: 0.3 | G70: Content Generation | H70: 0.7 | I70: =SUMPRODUCT(H70:H73,F70:F73)*D70 -> 0.091 | J70: 0.48 | K70: 0.48 | L70: 0.45 | M70: 0.4 | N70: 0.34
A71: Healthcare | B71: Pharma | C71: Marketing & Brand Management | D71: 0.2 | E71: Market & customer analytics | F71: 0.25 | G71: Assessment & Analysis | H71: 0.6 | J71: 0.48 | K71: 0.48 | L71: 0.45 | M71: 0.4 | N71: 0.34
A72: Healthcare | B72: Pharma | C72: Marketing & Brand Management | D72: 0.2 | E72: Brand & campaign planning | F72: 0.25 | G72: Strategy & Design | H72: 0.3 | J72: 0.48 | K72: 0.48 | L72: 0.45 | M72: 0.4 | N72: 0.34
A73: Healthcare | B73: Pharma | C73: Marketing & Brand Management | D73: 0.2 | E73: Agency / stakeholder coordination | F73: 0.2 | G73: Stakeholder / Relationship Management | H73: 0.1 | J73: 0.48 | K73: 0.48 | L73: 0.45 | M73: 0.4 | N73: 0.34
A74: Healthcare | B74: Pharma | C74: Finance & Accounting | D74: 0.1 | E74: Transaction processing & reconciliation | F74: 0.3 | G74: Task Processing / Query Handling | H74: 0.9 | I74: =SUMPRODUCT(H74:H77,F74:F77)*D74 -> 0.08275 | J74: 0.62 | K74: 0.62 | L74: 0.58 | M74: 0.52 | N74: 0.45
A75: Healthcare | B75: Pharma | C75: Finance & Accounting | D75: 0.1 | E75: Financial planning & analysis | F75: 0.25 | G75: Assessment & Analysis | H75: 0.6 | J75: 0.62 | K75: 0.62 | L75: 0.58 | M75: 0.52 | N75: 0.45
A76: Healthcare | B76: Pharma | C76: Finance & Accounting | D76: 0.1 | E76: Budgeting & forecasting | F76: 0.2 | G76: Modelling (incl. Forecasting) | H76: 0.85 | J76: 0.62 | K76: 0.62 | L76: 0.58 | M76: 0.52 | N76: 0.45
A77: Healthcare | B77: Pharma | C77: Finance & Accounting | D77: 0.1 | E77: Financial reporting | F77: 0.25 | G77: Document Generation & Management | H77: 0.95 | J77: 0.62 | K77: 0.62 | L77: 0.58 | M77: 0.52 | N77: 0.45
A78: Healthcare | B78: Pharma | C78: Human Resources | D78: 0.08 | E78: Recruitment administration | F78: 0.25 | G78: Task Processing / Query Handling | H78: 0.9 | I78: =SUMPRODUCT(H78:H81,F78:F81)*D78 -> 0.0496 | J78: 0.5 | K78: 0.5 | L78: 0.47 | M78: 0.42 | N78: 0.36
A79: Healthcare | B79: Pharma | C79: Human Resources | D79: 0.08 | E79: Workforce planning | F79: 0.25 | G79: Task Planning & Management | H79: 0.7 | J79: 0.5 | K79: 0.5 | L79: 0.47 | M79: 0.42 | N79: 0.36
A80: Healthcare | B80: Pharma | C80: Human Resources | D80: 0.08 | E80: Employee relations & support | F80: 0.3 | G80: Stakeholder / Relationship Management | H80: 0.1 | J80: 0.5 | K80: 0.5 | L80: 0.47 | M80: 0.42 | N80: 0.36
A81: Healthcare | B81: Pharma | C81: Human Resources | D81: 0.08 | E81: HR documentation & reporting | F81: 0.2 | G81: Document Generation & Management | H81: 0.95 | J81: 0.5 | K81: 0.5 | L81: 0.47 | M81: 0.42 | N81: 0.36
A82: Healthcare | B82: Pharma | C82: Corporate IT & Enterprise Technology | D82: 0.1 | E82: IT service desk & user support | F82: 0.3 | G82: Task Processing / Query Handling | H82: 0.9 | I82: =SUMPRODUCT(H82:H85,F82:F85)*D82 -> 0.081 | J82: 0.64 | K82: 0.64 | L82: 0.6 | M82: 0.54 | N82: 0.47
A83: Healthcare | B83: Pharma | C83: Corporate IT & Enterprise Technology | D83: 0.1 | E83: Application & infrastructure monitoring | F83: 0.25 | G83: Monitoring | H83: 0.7 | J83: 0.64 | K83: 0.64 | L83: 0.6 | M83: 0.54 | N83: 0.47
A84: Healthcare | B84: Pharma | C84: Corporate IT & Enterprise Technology | D84: 0.1 | E84: Technology planning & change coordination | F84: 0.25 | G84: Task Planning & Management | H84: 0.7 | J84: 0.64 | K84: 0.64 | L84: 0.6 | M84: 0.54 | N84: 0.47
A85: Healthcare | B85: Pharma | C85: Corporate IT & Enterprise Technology | D85: 0.1 | E85: IT documentation | F85: 0.2 | G85: Document Generation & Management | H85: 0.95 | J85: 0.64 | K85: 0.64 | L85: 0.6 | M85: 0.54 | N85: 0.47
A86: Healthcare | B86: Pharma | C86: Legal, Risk & Compliance | D86: 0.1 | E86: Compliance monitoring | F86: 0.25 | G86: Monitoring | H86: 0.7 | I86: =SUMPRODUCT(H86:H89,F86:F89)*D86 -> 0.05875 | J86: 0.45 | K86: 0.45 | L86: 0.42 | M86: 0.37 | N86: 0.32
A87: Healthcare | B87: Pharma | C87: Legal, Risk & Compliance | D87: 0.1 | E87: Contract & policy review | F87: 0.25 | G87: Assessment & Analysis | H87: 0.6 | J87: 0.45 | K87: 0.45 | L87: 0.42 | M87: 0.37 | N87: 0.32
A88: Healthcare | B88: Pharma | C88: Legal, Risk & Compliance | D88: 0.1 | E88: Regulatory stakeholder management | F88: 0.25 | G88: Stakeholder / Relationship Management | H88: 0.1 | J88: 0.45 | K88: 0.45 | L88: 0.42 | M88: 0.37 | N88: 0.32
A89: Healthcare | B89: Pharma | C89: Legal, Risk & Compliance | D89: 0.1 | E89: Compliance documentation | F89: 0.25 | G89: Document Generation & Management | H89: 0.95 | J89: 0.45 | K89: 0.45 | L89: 0.42 | M89: 0.37 | N89: 0.32
A90: Healthcare | B90: Pharma | C90: Corporate Strategy & General Administration | D90: 0.07 | E90: Strategic planning | F90: 0.3 | G90: Strategy & Design | H90: 0.3 | I90: =SUMPRODUCT(H90:H93,F90:F93)*D90 -> 0.03185 | J90: 0.38 | K90: 0.38 | L90: 0.35 | M90: 0.31 | N90: 0.27
A91: Healthcare | B91: Pharma | C91: Corporate Strategy & General Administration | D91: 0.07 | E91: Management analysis | F91: 0.25 | G91: Assessment & Analysis | H91: 0.6 | J91: 0.38 | K91: 0.38 | L91: 0.35 | M91: 0.31 | N91: 0.27
A92: Healthcare | B92: Pharma | C92: Corporate Strategy & General Administration | D92: 0.07 | E92: Executive stakeholder coordination | F92: 0.25 | G92: Stakeholder / Relationship Management | H92: 0.1 | J92: 0.38 | K92: 0.38 | L92: 0.35 | M92: 0.31 | N92: 0.27
A93: Healthcare | B93: Pharma | C93: Corporate Strategy & General Administration | D93: 0.07 | E93: Corporate reporting | F93: 0.2 | G93: Document Generation & Management | H93: 0.95 | J93: 0.38 | K93: 0.38 | L93: 0.35 | M93: 0.31 | N93: 0.27
I94: =SUM(I66:I93) -> 0.57695 | J94: =J66*$D66+J70*$D70+J74*$D74+J78*$D78+J82*$D82+J86*$D86+J90*$D90 -> 0.4911 | K94: =K66*$D66+K70*$D70+K74*$D74+K78*$D78+K82*$D82+K86*$D86+K90*$D90 -> 0.4911 | L94: =L66*$D66+L70*$D70+L74*$D74+L78*$D78+L82*$D82+L86*$D86+L90*$D90 -> 0.4591 | M94: =M66*$D66+M70*$D70+M74*$D74+M78*$D78+M82*$D82+M86*$D86+M90*$D90 -> 0.4078 | N94: =N66*$D66+N70*$D70+N74*$D74+N78*$D78+N82*$D82+N86*$D86+N90*$D90 -> 0.3517
A96: Healthcare | B96: Medical Devices | C96: Sales & Commercial Operations | D96: 0.3 | E96: Sales planning & targeting | F96: 0.25 | G96: Task Planning & Management | H96: 0.7 | I96: =SUMPRODUCT(H96:H99,F96:F99)*D96 -> 0.156 | J96: 0.45 | K96: 0.45 | L96: 0.42 | M96: 0.37 | N96: 0.32
A97: Healthcare | B97: Medical Devices | C97: Sales & Commercial Operations | D97: 0.3 | E97: Physician / hospital account engagement | F97: 0.35 | G97: Stakeholder / Relationship Management | H97: 0.1 | J97: 0.45 | K97: 0.45 | L97: 0.42 | M97: 0.37 | N97: 0.32
A98: Healthcare | B98: Medical Devices | C98: Sales & Commercial Operations | D98: 0.3 | E98: Sales & account analytics | F98: 0.2 | G98: Assessment & Analysis | H98: 0.6 | J98: 0.45 | K98: 0.45 | L98: 0.42 | M98: 0.37 | N98: 0.32
A99: Healthcare | B99: Medical Devices | C99: Sales & Commercial Operations | D99: 0.3 | E99: Commercial administration & reporting | F99: 0.2 | G99: Document Generation & Management | H99: 0.95 | J99: 0.45 | K99: 0.45 | L99: 0.42 | M99: 0.37 | N99: 0.32
A100: Healthcare | B100: Medical Devices | C100: Marketing & Product Management | D100: 0.15 | E100: Product & campaign planning | F100: 0.25 | G100: Strategy & Design | H100: 0.3 | I100: =SUMPRODUCT(H100:H103,F100:F103)*D100 -> 0.06825 | J100: 0.48 | K100: 0.48 | L100: 0.45 | M100: 0.4 | N100: 0.34
A101: Healthcare | B101: Medical Devices | C101: Marketing & Product Management | D101: 0.15 | E101: Market & customer analytics | F101: 0.25 | G101: Assessment & Analysis | H101: 0.6 | J101: 0.48 | K101: 0.48 | L101: 0.45 | M101: 0.4 | N101: 0.34
A102: Healthcare | B102: Medical Devices | C102: Marketing & Product Management | D102: 0.15 | E102: Content development | F102: 0.3 | G102: Content Generation | H102: 0.7 | J102: 0.48 | K102: 0.48 | L102: 0.45 | M102: 0.4 | N102: 0.34
A103: Healthcare | B103: Medical Devices | C103: Marketing & Product Management | D103: 0.15 | E103: KOL / channel coordination | F103: 0.2 | G103: Stakeholder / Relationship Management | H103: 0.1 | J103: 0.48 | K103: 0.48 | L103: 0.45 | M103: 0.4 | N103: 0.34
...

Sheet Communications
A1: Sector | B1: Subsector | C1: Core Activity | D1: Effort Split | E1: Key Main Task | F1: % Effort | G1: Category | H1: AI Addressable | I1: Agentification Potential | J1: Actual Agentification Possible | K1: NA | L1: EU | M1: APAC ex India | N1: India
A2: Communications | B2: Advertising & Marketing Services | C2: New Business & Sales | D2: 0.3 | E2: Lead & opportunity targeting | F2: 0.25 | G2: Assessment & Analysis | H2: 0.6 | I2: =SUMPRODUCT(H2:H5,F2:F5)*D2 -> 0.135 | J2: 0.43 | K2: 0.43 | L2: 0.4 | M2: 0.36 | N2: 0.31
A3: Communications | B3: Advertising & Marketing Services | C3: New Business & Sales | D3: 0.3 | E3: Prospect relationship management | F3: 0.35 | G3: Stakeholder / Relationship Management | H3: 0.1
A4: Communications | B4: Advertising & Marketing Services | C4: New Business & Sales | D4: 0.3 | E4: Pitch & proposal development | F4: 0.25 | G4: Content Generation | H4: 0.7
A5: Communications | B5: Advertising & Marketing Services | C5: New Business & Sales | D5: 0.3 | E5: Pipeline analytics & reporting | F5: 0.15 | G5: Assessment & Analysis | H5: 0.6
A6: Communications | B6: Advertising & Marketing Services | C6: Finance & Accounting | D6: 0.2 | E6: Transaction processing & reconciliation | F6: 0.3 | G6: Task Processing / Query Handling | H6: 0.9 | I6: =SUMPRODUCT(H6:H9,F6:F9)*D6 -> 0.1655 | J6: 0.68 | K6: 0.68 | L6: 0.63 | M6: 0.58 | N6: 0.52
A7: Communications | B7: Advertising & Marketing Services | C7: Finance & Accounting | D7: 0.2 | E7: Financial planning & analysis | F7: 0.25 | G7: Assessment & Analysis | H7: 0.6
A8: Communications | B8: Advertising & Marketing Services | C8: Finance & Accounting | D8: 0.2 | E8: Budgeting & forecasting | F8: 0.2 | G8: Modelling (incl. Forecasting) | H8: 0.85
A9: Communications | B9: Advertising & Marketing Services | C9: Finance & Accounting | D9: 0.2 | E9: Financial reporting | F9: 0.25 | G9: Document Generation & Management | H9: 0.95
A10: Communications | B10: Advertising & Marketing Services | C10: Human Resources | D10: 0.15 | E10: Recruitment administration | F10: 0.25 | G10: Task Processing / Query Handling | H10: 0.9 | I10: =SUMPRODUCT(H10:H13,F10:F13)*D10 -> 0.093 | J10: 0.48 | K10: 0.48 | L10: 0.45 | M10: 0.41 | N10: 0.37
A11: Communications | B11: Advertising & Marketing Services | C11: Human Resources | D11: 0.15 | E11: Workforce / freelancer planning | F11: 0.25 | G11: Task Planning & Management | H11: 0.7
A12: Communications | B12: Advertising & Marketing Services | C12: Human Resources | D12: 0.15 | E12: Employee & talent relations | F12: 0.3 | G12: Stakeholder / Relationship Management | H12: 0.1
A13: Communications | B13: Advertising & Marketing Services | C13: Human Resources | D13: 0.15 | E13: HR documentation & reporting | F13: 0.2 | G13: Document Generation & Management | H13: 0.95
A14: Communications | B14: Advertising & Marketing Services | C14: Corporate IT & Technology | D14: 0.15 | E14: IT service desk & user support | F14: 0.3 | G14: Task Processing / Query Handling | H14: 0.9 | I14: =SUMPRODUCT(H14:H17,F14:F17)*D14 -> 0.1215 | J14: 0.68 | K14: 0.68 | L14: 0.64 | M14: 0.59 | N14: 0.54
A15: Communications | B15: Advertising & Marketing Services | C15: Corporate IT & Technology | D15: 0.15 | E15: Application & infrastructure monitoring | F15: 0.25 | G15: Monitoring | H15: 0.7
A16: Communications | B16: Advertising & Marketing Services | C16: Corporate IT & Technology | D16: 0.15 | E16: Technology planning & change coordination | F16: 0.25 | G16: Task Planning & Management | H16: 0.7
A17: Communications | B17: Advertising & Marketing Services | C17: Corporate IT & Technology | D17: 0.15 | E17: IT documentation | F17: 0.2 | G17: Document Generation & Management | H17: 0.95
A18: Communications | B18: Advertising & Marketing Services | C18: Legal & Corporate Administration | D18: 0.2 | E18: Contract & policy review | F18: 0.3 | G18: Assessment & Analysis | H18: 0.6 | I18: =SUMPRODUCT(H18:H21,F18:F21)*D18 -> 0.094 | J18: 0.35 | K18: 0.35 | L18: 0.33 | M18: 0.3 | N18: 0.26
A19: Communications | B19: Advertising & Marketing Services | C19: Legal & Corporate Administration | D19: 0.2 | E19: Legal / client stakeholder coordination | F19: 0.25 | G19: Stakeholder / Relationship Management | H19: 0.1
A20: Communications | B20: Advertising & Marketing Services | C20: Legal & Corporate Administration | D20: 0.2 | E20: Corporate & strategic planning | F20: 0.25 | G20: Strategy & Design | H20: 0.3
A21: Communications | B21: Advertising & Marketing Services | C21: Legal & Corporate Administration | D21: 0.2 | E21: Legal & corporate documentation | F21: 0.2 | G21: Document Generation & Management | H21: 0.95
I22: =SUM(I2:I21) -> 0.609 | J22: =+J2*$D2+J6*$D6+J10*$D10+J14*$D14+J18*$D18 -> 0.509 | K22: =+K2*$D2+K6*$D6+K10*$D10+K14*$D14+K18*$D18 -> 0.509 | L22: =+L2*$D2+L6*$D6+L10*$D10+L14*$D14+L18*$D18 -> 0.4755 | M22: =+M2*$D2+M6*$D6+M10*$D10+M14*$D14+M18*$D18 -> 0.434 | N22: =+N2*$D2+N6*$D6+N10*$D10+N14*$D14+N18*$D18 -> 0.3855
A24: Communications | B24: Pay TV & Distribution | C24: Sales & Channel Management | D24: 0.25 | E24: Sales & channel planning | F24: 0.25 | G24: Task Planning & Management | H24: 0.7 | I24: =SUMPRODUCT(H24:H27,F24:F27)*D24 -> 0.13 | J24: 0.4 | K24: 0.4 | L24: 0.37 | M24: 0.33 | N24: 0.29
A25: Communications | B25: Pay TV & Distribution | C25: Sales & Channel Management | D25: 0.25 | E25: Affiliate / channel relationship management | F25: 0.35 | G25: Stakeholder / Relationship Management | H25: 0.1 | J25: 0.4 | K25: 0.4 | L25: 0.37 | M25: 0.33 | N25: 0.29
A26: Communications | B26: Pay TV & Distribution | C26: Sales & Channel Management | D26: 0.25 | E26: Pricing & account analytics | F26: 0.2 | G26: Assessment & Analysis | H26: 0.6 | J26: 0.4 | K26: 0.4 | L26: 0.37 | M26: 0.33 | N26: 0.29
A27: Communications | B27: Pay TV & Distribution | C27: Sales & Channel Management | D27: 0.25 | E27: Sales administration & reporting | F27: 0.2 | G27: Document Generation & Management | H27: 0.95 | J27: 0.4 | K27: 0.4 | L27: 0.37 | M27: 0.33 | N27: 0.29
A28: Communications | B28: Pay TV & Distribution | C28: Marketing & Subscriber Growth | D28: 0.2 | E28: Campaign & content development | F28: 0.3 | G28: Content Generation | H28: 0.7 | I28: =SUMPRODUCT(H28:H31,F28:F31)*D28 -> 0.091 | J28: 0.36 | K28: 0.36 | L28: 0.33 | M28: 0.3 | N28: 0.27
A29: Communications | B29: Pay TV & Distribution | C29: Marketing & Subscriber Growth | D29: 0.2 | E29: Subscriber segmentation & churn analytics | F29: 0.25 | G29: Assessment & Analysis | H29: 0.6 | J29: 0.36 | K29: 0.36 | L29: 0.33 | M29: 0.3 | N29: 0.27
A30: Communications | B30: Pay TV & Distribution | C30: Marketing & Subscriber Growth | D30: 0.2 | E30: Campaign / proposition planning | F30: 0.25 | G30: Strategy & Design | H30: 0.3 | J30: 0.36 | K30: 0.36 | L30: 0.33 | M30: 0.3 | N30: 0.27
A31: Communications | B31: Pay TV & Distribution | C31: Marketing & Subscriber Growth | D31: 0.2 | E31: Agency / channel coordination | F31: 0.2 | G31: Stakeholder / Relationship Management | H31: 0.1 | J31: 0.36 | K31: 0.36 | L31: 0.33 | M31: 0.3 | N31: 0.27
A32: Communications | B32: Pay TV & Distribution | C32: Finance & Accounting | D32: 0.2 | E32: Transaction processing & reconciliation | F32: 0.3 | G32: Task Processing / Query Handling | H32: 0.9 | I32: =SUMPRODUCT(H32:H35,F32:F35)*D32 -> 0.1655 | J32: 0.68 | K32: 0.68 | L32: 0.63 | M32: 0.58 | N32: 0.52
A33: Communications | B33: Pay TV & Distribution | C33: Finance & Accounting | D33: 0.2 | E33: Financial planning & analysis | F33: 0.25 | G33: Assessment & Analysis | H33: 0.6 | J33: 0.68 | K33: 0.68 | L33: 0.63 | M33: 0.58 | N33: 0.52
A34: Communications | B34: Pay TV & Distribution | C34: Finance & Accounting | D34: 0.2 | E34: Budgeting & forecasting | F34: 0.2 | G34: Modelling (incl. Forecasting) | H34: 0.85 | J34: 0.68 | K34: 0.68 | L34: 0.63 | M34: 0.58 | N34: 0.52
A35: Communications | B35: Pay TV & Distribution | C35: Finance & Accounting | D35: 0.2 | E35: Financial reporting | F35: 0.25 | G35: Document Generation & Management | H35: 0.95 | J35: 0.68 | K35: 0.68 | L35: 0.63 | M35: 0.58 | N35: 0.52
A36: Communications | B36: Pay TV & Distribution | C36: Human Resources | D36: 0.1 | E36: Recruitment administration | F36: 0.25 | G36: Task Processing / Query Handling | H36: 0.9 | I36: =SUMPRODUCT(H36:H39,F36:F39)*D36 -> 0.062 | J36: 0.48 | K36: 0.48 | L36: 0.45 | M36: 0.41 | N36: 0.37
A37: Communications | B37: Pay TV & Distribution | C37: Human Resources | D37: 0.1 | E37: Workforce planning | F37: 0.25 | G37: Task Planning & Management | H37: 0.7 | J37: 0.48 | K37: 0.48 | L37: 0.45 | M37: 0.41 | N37: 0.37
A38: Communications | B38: Pay TV & Distribution | C38: Human Resources | D38: 0.1 | E38: Employee relations & support | F38: 0.3 | G38: Stakeholder / Relationship Management | H38: 0.1 | J38: 0.48 | K38: 0.48 | L38: 0.45 | M38: 0.41 | N38: 0.37
A39: Communications | B39: Pay TV & Distribution | C39: Human Resources | D39: 0.1 | E39: HR documentation & reporting | F39: 0.2 | G39: Document Generation & Management | H39: 0.95 | J39: 0.48 | K39: 0.48 | L39: 0.45 | M39: 0.41 | N39: 0.37
A40: Communications | B40: Pay TV & Distribution | C40: Corporate IT & Technology | D40: 0.1 | E40: IT support & user services | F40: 0.3 | G40: Task Processing / Query Handling | H40: 0.9 | I40: =SUMPRODUCT(H40:H43,F40:F43)*D40 -> 0.081 | J40: 0.68 | K40: 0.68 | L40: 0.64 | M40: 0.59 | N40: 0.54
A41: Communications | B41: Pay TV & Distribution | C41: Corporate IT & Technology | D41: 0.1 | E41: Enterprise system monitoring | F41: 0.25 | G41: Monitoring | H41: 0.7 | J41: 0.68 | K41: 0.68 | L41: 0.64 | M41: 0.59 | N41: 0.54
A42: Communications | B42: Pay TV & Distribution | C42: Corporate IT & Technology | D42: 0.1 | E42: Technology planning & coordination | F42: 0.25 | G42: Task Planning & Management | H42: 0.7 | J42: 0.68 | K42: 0.68 | L42: 0.64 | M42: 0.59 | N42: 0.54
A43: Communications | B43: Pay TV & Distribution | C43: Corporate IT & Technology | D43: 0.1 | E43: IT documentation | F43: 0.2 | G43: Document Generation & Management | H43: 0.95 | J43: 0.68 | K43: 0.68 | L43: 0.64 | M43: 0.59 | N43: 0.54
A44: Communications | B44: Pay TV & Distribution | C44: Legal, Regulatory & Corporate Administration | D44: 0.15 | E44: Regulatory / rights monitoring | F44: 0.25 | G44: Monitoring | H44: 0.7 | I44: =SUMPRODUCT(H44:H47,F44:F47)*D44 -> 0.088125 | J44: 0.45 | K44: 0.45 | L44: 0.42 | M44: 0.38 | N44: 0.33
A45: Communications | B45: Pay TV & Distribution | C45: Legal, Regulatory & Corporate Administration | D45: 0.15 | E45: Contract & policy review | F45: 0.25 | G45: Assessment & Analysis | H45: 0.6 | J45: 0.45 | K45: 0.45 | L45: 0.42 | M45: 0.38 | N45: 0.33
A46: Communications | B46: Pay TV & Distribution | C46: Legal, Regulatory & Corporate Administration | D46: 0.15 | E46: Regulatory / partner coordination | F46: 0.25 | G46: Stakeholder / Relationship Management | H46: 0.1 | J46: 0.45 | K46: 0.45 | L46: 0.42 | M46: 0.38 | N46: 0.33
A47: Communications | B47: Pay TV & Distribution | C47: Legal, Regulatory & Corporate Administration | D47: 0.15 | E47: Compliance documentation | F47: 0.25 | G47: Document Generation & Management | H47: 0.95 | J47: 0.45 | K47: 0.45 | L47: 0.42 | M47: 0.38 | N47: 0.33
I48: =SUM(I24:I47) -> 0.617625 | J48: =+J28*$D28+J32*$D32+J36*$D36+J40*$D40+J44*$D44+J24*$D24 -> 0.4915 | K48: =+K28*$D28+K32*$D32+K36*$D36+K40*$D40+K44*$D44+K24*$D24 -> 0.4915 | L48: =+L28*$D28+L32*$D32+L36*$D36+L40*$D40+L44*$D44+L24*$D24 -> 0.4565 | M48: =+M28*$D28+M32*$D32+M36*$D36+M40*$D40+M44*$D44+M24*$D24 -> 0.4155 | N48: =+N28*$D28+N32*$D32+N36*$D36+N40*$D40+N44*$D44+N24*$D24 -> 0.371
A50: Communications | B50: Content Production & Distribution | C50: Sales & Distribution Partnerships | D50: 0.25 | E50: Distribution opportunity targeting | F50: 0.25 | G50: Assessment & Analysis | H50: 0.6 | I50: =SUMPRODUCT(H50:H53,F50:F53)*D50 -> 0.12375 | J50: 0.4 | K50: 0.4 | L50: 0.37 | M50: 0.33 | N50: 0.28
A51: Communications | B51: Content Production & Distribution | C51: Sales & Distribution Partnerships | D51: 0.25 | E51: Studio / platform relationship management | F51: 0.35 | G51: Stakeholder / Relationship Management | H51: 0.1 | J51: 0.4 | K51: 0.4 | L51: 0.37 | M51: 0.33 | N51: 0.28
A52: Communications | B52: Content Production & Distribution | C52: Sales & Distribution Partnerships | D52: 0.25 | E52: Deal economics & performance analysis | F52: 0.2 | G52: Assessment & Analysis | H52: 0.6 | J52: 0.4 | K52: 0.4 | L52: 0.37 | M52: 0.33 | N52: 0.28
A53: Communications | B53: Content Production & Distribution | C53: Sales & Distribution Partnerships | D53: 0.25 | E53: Proposal & sales reporting | F53: 0.2 | G53: Document Generation & Management | H53: 0.95 | J53: 0.4 | K53: 0.4 | L53: 0.37 | M53: 0.33 | N53: 0.28
A54: Communications | B54: Content Production & Distribution | C54: Marketing & Publicity | D54: 0.15 | E54: Promotional content development | F54: 0.3 | G54: Content Generation | H54: 0.7 | I54: =SUMPRODUCT(H54:H57,F54:F57)*D54 -> 0.06825 | J54: 0.36 | K54: 0.36 | L54: 0.33 | M54: 0.3 | N54: 0.26
A55: Communications | B55: Content Production & Distribution | C55: Marketing & Publicity | D55: 0.15 | E55: Audience / campaign analytics | F55: 0.25 | G55: Assessment & Analysis | H55: 0.6 | J55: 0.36 | K55: 0.36 | L55: 0.33 | M55: 0.3 | N55: 0.26
A56: Communications | B56: Content Production & Distribution | C56: Marketing & Publicity | D56: 0.15 | E56: Release / campaign planning | F56: 0.25 | G56: Strategy & Design | H56: 0.3 | J56: 0.36 | K56: 0.36 | L56: 0.33 | M56: 0.3 | N56: 0.26
A57: Communications | B57: Content Production & Distribution | C57: Marketing & Publicity | D57: 0.15 | E57: Talent / agency coordination | F57: 0.2 | G57: Stakeholder / Relationship Management | H57: 0.1 | J57: 0.36 | K57: 0.36 | L57: 0.33 | M57: 0.3 | N57: 0.26
A58: Communications | B58: Content Production & Distribution | C58: Finance & Accounting | D58: 0.2 | E58: Transaction & royalty reconciliation | F58: 0.3 | G58: Task Processing / Query Handling | H58: 0.9 | I58: =SUMPRODUCT(H58:H61,F58:F61)*D58 -> 0.1655 | J58: 0.68 | K58: 0.68 | L58: 0.63 | M58: 0.58 | N58: 0.51
A59: Communications | B59: Content Production & Distribution | C59: Finance & Accounting | D59: 0.2 | E59: Financial planning & analysis | F59: 0.25 | G59: Assessment & Analysis | H59: 0.6 | J59: 0.68 | K59: 0.68 | L59: 0.63 | M59: 0.58 | N59: 0.51
A60: Communications | B60: Content Production & Distribution | C60: Finance & Accounting | D60: 0.2 | E60: Budgeting & forecasting | F60: 0.2 | G60: Modelling (incl. Forecasting) | H60: 0.85 | J60: 0.68 | K60: 0.68 | L60: 0.63 | M60: 0.58 | N60: 0.51
A61: Communications | B61: Content Production & Distribution | C61: Finance & Accounting | D61: 0.2 | E61: Financial reporting | F61: 0.25 | G61: Document Generation & Management | H61: 0.95 | J61: 0.68 | K61: 0.68 | L61: 0.63 | M61: 0.58 | N61: 0.51
A62: Communications | B62: Content Production & Distribution | C62: Human Resources & Talent | D62: 0.15 | E62: Crew / talent administration | F62: 0.25 | G62: Task Processing / Query Handling | H62: 0.9 | I62: =SUMPRODUCT(H62:H65,F62:F65)*D62 -> 0.093 | J62: 0.48 | K62: 0.48 | L62: 0.45 | M62: 0.41 | N62: 0.36
A63: Communications | B63: Content Production & Distribution | C63: Human Resources & Talent | D63: 0.15 | E63: Workforce & production talent planning | F63: 0.25 | G63: Task Planning & Management | H63: 0.7 | J63: 0.48 | K63: 0.48 | L63: 0.45 | M63: 0.41 | N63: 0.36
A64: Communications | B64: Content Production & Distribution | C64: Human Resources & Talent | D64: 0.15 | E64: Talent / employee relations | F64: 0.3 | G64: Stakeholder / Relationship Management | H64: 0.1 | J64: 0.48 | K64: 0.48 | L64: 0.45 | M64: 0.41 | N64: 0.36
A65: Communications | B65: Content Production & Distribution | C65: Human Resources & Talent | D65: 0.15 | E65: HR / talent documentation | F65: 0.2 | G65: Document Generation & Management | H65: 0.95 | J65: 0.48 | K65: 0.48 | L65: 0.45 | M65: 0.41 | N65: 0.36
A66: Communications | B66: Content Production & Distribution | C66: Corporate IT & Technology | D66: 0.1 | E66: IT service desk & support | F66: 0.3 | G66: Task Processing / Query Handling | H66: 0.9 | I66: =SUMPRODUCT(H66:H69,F66:F69)*D66 -> 0.081 | J66: 0.68 | K66: 0.68 | L66: 0.64 | M66: 0.59 | N66: 0.53
A67: Communications | B67: Content Production & Distribution | C67: Corporate IT & Technology | D67: 0.1 | E67: System / infrastructure monitoring | F67: 0.25 | G67: Monitoring | H67: 0.7 | J67: 0.68 | K67: 0.68 | L67: 0.64 | M67: 0.59 | N67: 0.53
A68: Communications | B68: Content Production & Distribution | C68: Corporate IT & Technology | D68: 0.1 | E68: Technology planning | F68: 0.25 | G68: Task Planning & Management | H68: 0.7 | J68: 0.68 | K68: 0.68 | L68: 0.64 | M68: 0.59 | N68: 0.53
A69: Communications | B69: Content Production & Distribution | C69: Corporate IT & Technology | D69: 0.1 | E69: IT documentation | F69: 0.2 | G69: Document Generation & Management | H69: 0.95 | J69: 0.68 | K69: 0.68 | L69: 0.64 | M69: 0.59 | N69: 0.53
A70: Communications | B70: Content Production & Distribution | C70: Legal, Rights & Corporate Administration | D70: 0.15 | E70: Rights / compliance monitoring | F70: 0.25 | G70: Monitoring | H70: 0.7 | I70: =SUMPRODUCT(H70:H73,F70:F73)*D70 -> 0.088125 | J70: 0.45 | K70: 0.45 | L70: 0.42 | M70: 0.38 | N70: 0.32
A71: Communications | B71: Content Production & Distribution | C71: Legal, Rights & Corporate Administration | D71: 0.15 | E71: Licensing / contract review | F71: 0.25 | G71: Assessment & Analysis | H71: 0.6 | J71: 0.45 | K71: 0.45 | L71: 0.42 | M71: 0.38 | N71: 0.32
A72: Communications | B72: Content Production & Distribution | C72: Legal, Rights & Corporate Administration | D72: 0.15 | E72: Rights-holder / legal coordination | F72: 0.25 | G72: Stakeholder / Relationship Management | H72: 0.1 | J72: 0.45 | K72: 0.45 | L72: 0.42 | M72: 0.38 | N72: 0.32
A73: Communications | B73: Content Production & Distribution | C73: Legal, Rights & Corporate Administration | D73: 0.15 | E73: Rights & corporate documentation | F73: 0.25 | G73: Document Generation & Management | H73: 0.95 | J73: 0.45 | K73: 0.45 | L73: 0.42 | M73: 0.38 | N73: 0.32
I74: =SUM(I50:I73) -> 0.619625 | J74: =+J54*$D54+J58*$D58+J62*$D62+J66*$D66+J70*$D70+J50*$D50 -> 0.4975 | K74: =+K54*$D54+K58*$D58+K62*$D62+K66*$D66+K70*$D70+K50*$D50 -> 0.4975 | L74: =+L54*$D54+L58*$D58+L62*$D62+L66*$D66+L70*$D70+L50*$D50 -> 0.4625 | M74: =+M54*$D54+M58*$D58+M62*$D62+M66*$D66+M70*$D70+M50*$D50 -> 0.421 | N74: =+N54*$D54+N58*$D58+N62*$D62+N66*$D66+N70*$D70+N50*$D50 -> 0.366
A76: Communications | B76: Gaming | C76: Publishing & Commercial Operations | D76: 0.2 | E76: Commercial planning & targeting | F76: 0.25 | G76: Task Planning & Management | H76: 0.7 | I76: =SUMPRODUCT(H76:H79,F76:F79)*D76 -> 0.109 | J76: 0.44 | K76: 0.44 | L76: 0.41 | M76: 0.37 | N76: 0.33
A77: Communications | B77: Gaming | C77: Publishing & Commercial Operations | D77: 0.2 | E77: Platform / ecosystem relationships | F77: 0.3 | G77: Stakeholder / Relationship Management | H77: 0.1 | J77: 0.44 | K77: 0.44 | L77: 0.41 | M77: 0.37 | N77: 0.33
A78: Communications | B78: Gaming | C78: Publishing & Commercial Operations | D78: 0.2 | E78: Pricing & monetization analytics | F78: 0.25 | G78: Assessment & Analysis | H78: 0.6 | J78: 0.44 | K78: 0.44 | L78: 0.41 | M78: 0.37 | N78: 0.33
A79: Communications | B79: Gaming | C79: Publishing & Commercial Operations | D79: 0.2 | E79: Commercial reporting | F79: 0.2 | G79: Document Generation & Management | H79: 0.95 | J79: 0.44 | K79: 0.44 | L79: 0.41 | M79: 0.37 | N79: 0.33
A80: Communications | B80: Gaming | C80: User Acquisition & Marketing | D80: 0.25 | E80: Campaign / creative development | F80: 0.3 | G80: Content Generation | H80: 0.7 | I80: =SUMPRODUCT(H80:H83,F80:F83)*D80 -> 0.18 | J80: 0.58 | K80: 0.58 | L80: 0.54 | M80: 0.5 | N80: 0.45
A81: Communications | B81: Gaming | C81: User Acquisition & Marketing | D81: 0.25 | E81: Player / acquisition analytics | F81: 0.3 | G81: Assessment & Analysis | H81: 0.6 | J81: 0.58 | K81: 0.58 | L81: 0.54 | M81: 0.5 | N81: 0.45
A82: Communications | B82: Gaming | C82: User Acquisition & Marketing | D82: 0.25 | E82: User acquisition planning | F82: 0.2 | G82: Task Planning & Management | H82: 0.7 | J82: 0.58 | K82: 0.58 | L82: 0.54 | M82: 0.5 | N82: 0.45
A83: Communications | B83: Gaming | C83: User Acquisition & Marketing | D83: 0.25 | E83: Marketing reporting | F83: 0.2 | G83: Document Generation & Management | H83: 0.95 | J83: 0.58 | K83: 0.58 | L83: 0.54 | M83: 0.5 | N83: 0.45
A84: Communications | B84: Gaming | C84: Finance & Accounting | D84: 0.15 | E84: Transaction processing & reconciliation | F84: 0.3 | G84: Task Processing / Query Handling | H84: 0.9 | I84: =SUMPRODUCT(H84:H87,F84:F87)*D84 -> 0.124125 | J84: 0.68 | K84: 0.68 | L84: 0.63 | M84: 0.58 | N84: 0.52
A85: Communications | B85: Gaming | C85: Finance & Accounting | D85: 0.15 | E85: Financial planning & analysis | F85: 0.25 | G85: Assessment & Analysis | H85: 0.6 | J85: 0.68 | K85: 0.68 | L85: 0.63 | M85: 0.58 | N85: 0.52
A86: Communications | B86: Gaming | C86: Finance & Accounting | D86: 0.15 | E86: Revenue forecasting | F86: 0.2 | G86: Modelling (incl. Forecasting) | H86: 0.85 | J86: 0.68 | K86: 0.68 | L86: 0.63 | M86: 0.58 | N86: 0.52
A87: Communications | B87: Gaming | C87: Finance & Accounting | D87: 0.15 | E87: Financial reporting | F87: 0.25 | G87: Document Generation & Management | H87: 0.95 | J87: 0.68 | K87: 0.68 | L87: 0.63 | M87: 0.58 | N87: 0.52
A88: Communications | B88: Gaming | C88: Human Resources | D88: 0.15 | E88: Recruitment administration | F88: 0.25 | G88: Task Processing / Query Handling | H88: 0.9 | I88: =SUMPRODUCT(H88:H91,F88:F91)*D88 -> 0.093 | J88: 0.48 | K88: 0.48 | L88: 0.45 | M88: 0.41 | N88: 0.37
A89: Communications | B89: Gaming | C89: Human Resources | D89: 0.15 | E89: Workforce planning | F89: 0.25 | G89: Task Planning & Management | H89: 0.7 | J89: 0.48 | K89: 0.48 | L89: 0.45 | M89: 0.41 | N89: 0.37
A90: Communications | B90: Gaming | C90: Human Resources | D90: 0.15 | E90: Employee / developer relations | F90: 0.3 | G90: Stakeholder / Relationship Management | H90: 0.1 | J90: 0.48 | K90: 0.48 | L90: 0.45 | M90: 0.41 | N90: 0.37
A91: Communications | B91: Gaming | C91: Human Resources | D91: 0.15 | E91: HR documentation & reporting | F91: 0.2 | G91: Document Generation & Management | H91: 0.95 | J91: 0.48 | K91: 0.48 | L91: 0.45 | M91: 0.41 | N91: 0.37
A92: Communications | B92: Gaming | C92: Corporate IT & Technology | D92: 0.1 | E92: IT support | F92: 0.3 | G92: Task Processing / Query Handling | H92: 0.9 | I92: =SUMPRODUCT(H92:H95,F92:F95)*D92 -> 0.081 | J92: 0.68 | K92: 0.68 | L92: 0.64 | M92: 0.59 | N92: 0.54
A93: Communications | B93: Gaming | C93: Corporate IT & Technology | D93: 0.1 | E93: System monitoring | F93: 0.25 | G93: Monitoring | H93: 0.7 | J93: 0.68 | K93: 0.68 | L93: 0.64 | M93: 0.59 | N93: 0.54
A94: Communications | B94: Gaming | C94: Corporate IT & Technology | D94: 0.1 | E94: Technology planning | F94: 0.25 | G94: Task Planning & Management | H94: 0.7 | J94: 0.68 | K94: 0.68 | L94: 0.64 | M94: 0.59 | N94: 0.54
A95: Communications | B95: Gaming | C95: Corporate IT & Technology | D95: 0.1 | E95: IT documentation | F95: 0.2 | G95: Document Generation & Management | H95: 0.95 | J95: 0.68 | K95: 0.68 | L95: 0.64 | M95: 0.59 | N95: 0.54
A96: Communications | B96: Gaming | C96: Legal & Corporate Administration | D96: 0.15 | E96: Platform / regulatory monitoring | F96: 0.25 | G96: Monitoring | H96: 0.7 | I96: =SUMPRODUCT(H96:H99,F96:F99)*D96 -> 0.088125 | J96: 0.45 | K96: 0.45 | L96: 0.42 | M96: 0.38 | N96: 0.34
A97: Communications | B97: Gaming | C97: Legal & Corporate Administration | D97: 0.15 | E97: IP / contract review | F97: 0.25 | G97: Assessment & Analysis | H97: 0.6 | J97: 0.45 | K97: 0.45 | L97: 0.42 | M97: 0.38 | N97: 0.34
A98: Communications | B98: Gaming | C98: Legal & Corporate Administration | D98: 0.15 | E98: Publisher / legal coordination | F98: 0.25 | G98: Stakeholder / Relationship Management | H98: 0.1 | J98: 0.45 | K98: 0.45 | L98: 0.42 | M98: 0.38 | N98: 0.34
A99: Communications | B99: Gaming | C99: Legal & Corporate Administration | D99: 0.15 | E99: Legal & compliance documentation | F99: 0.25 | G99: Document Generation & Management | H99: 0.95 | J99: 0.45 | K99: 0.45 | L99: 0.42 | M99: 0.38 | N99: 0.34
I100: =SUM(I76:I99) -> 0.67525 | J100: =+J80*$D80+J84*$D84+J88*$D88+J92*$D92+J96*$D96+J76*$D76 -> 0.5425 | K100: =+K80*$D80+K84*$D84+K88*$D88+K92*$D92+K96*$D96+K76*$D76 -> 0.5425 | L100: =+L80*$D80+L84*$D84+L88*$D88+L92*$D92+L96*$D96+L76*$D76 -> 0.506 | M100: =+M80*$D80+M84*$D84+M88*$D88+M92*$D92+M96*$D96+M76*$D76 -> 0.4635 | N100: =+N80*$D80+N84*$D84+N88*$D88+N92*$D92+N96*$D96+N76*$D76 -> 0.417
A102: Communications | B102: Digital Platforms & Internet Media | C102: Monetization & Commercial Operations | D102: 0.25 | E102: Commercial / inventory planning | F102: 0.25 | G102: Task Planning & Management | H102: 0.7 | I102: =SUMPRODUCT(H102:H105,F102:F105)*D102 -> 0.1925 | J102: 0.65 | K102: 0.65 | L102: 0.61 | M102: 0.57 | N102: 0.52
A103: Communications | B103: Digital Platforms & Internet Media | C103: Monetization & Commercial Operations | D103: 0.25 | E103: Pricing & monetization analytics | F103: 0.25 | G103: Assessment & Analysis | H103: 0.6 | J103: 0.65 | K103: 0.65 | L103: 0.61 | M103: 0.57 | N103: 0.52
A104: Communications | B104: Digital Platforms & Internet Media | C104: Monetization & Commercial Operations | D104: 0.25 | E104: Revenue & demand forecasting | F104: 0.3 | G104: Modelling (incl. Forecasting) | H104: 0.85 | J104: 0.65 | K104: 0.65 | L104: 0.61 | M104: 0.57 | N104: 0.52
...

Sheet Consumer Staples
A1: Sector | B1: Subsector | C1: Core Activity | D1: Effort Split | E1: Key Main Task | F1: % Effort | G1: Category | H1: AI Addressable | I1: Agentification Potential | J1: Actual Agentification Possible | K1: NA | L1: EU | M1: APAC ex India | N1: India
A2: Consumer Staples | B2: Beverages | C2: Sales & Channel Management | D2: 0.3 | E2: Sales planning & account targeting | F2: 0.25 | G2: Task Planning & Management | H2: 0.7 | I2: =SUMPRODUCT(H2:H5,F2:F5)*D2 -> 0.156 | J2: 0.4 | K2: 0.4 | L2: 0.37 | M2: 0.32 | N2: 0.24
A3: Consumer Staples | B3: Beverages | C3: Sales & Channel Management | D3: 0.3 | E3: Distributor / retailer relationship management | F3: 0.35 | G3: Stakeholder / Relationship Management | H3: 0.1 | J3: 0.4 | K3: 0.4 | L3: 0.37 | M3: 0.32 | N3: 0.24
A4: Consumer Staples | B4: Beverages | C4: Sales & Channel Management | D4: 0.3 | E4: Pricing & account analytics | F4: 0.2 | G4: Assessment & Analysis | H4: 0.6 | J4: 0.4 | K4: 0.4 | L4: 0.37 | M4: 0.32 | N4: 0.24
A5: Consumer Staples | B5: Beverages | C5: Sales & Channel Management | D5: 0.3 | E5: Sales administration & reporting | F5: 0.2 | G5: Document Generation & Management | H5: 0.95 | J5: 0.4 | K5: 0.4 | L5: 0.37 | M5: 0.32 | N5: 0.24
A6: Consumer Staples | B6: Beverages | C6: Marketing & Brand Management | D6: 0.2 | E6: Campaign & content development | F6: 0.3 | G6: Content Generation | H6: 0.7 | I6: =SUMPRODUCT(H6:H9,F6:F9)*D6 -> 0.091 | J6: 0.34 | K6: 0.34 | L6: 0.31 | M6: 0.27 | N6: 0.18
A7: Consumer Staples | B7: Beverages | C7: Marketing & Brand Management | D7: 0.2 | E7: Consumer & market analytics | F7: 0.25 | G7: Assessment & Analysis | H7: 0.6 | J7: 0.34 | K7: 0.34 | L7: 0.31 | M7: 0.27 | N7: 0.18
A8: Consumer Staples | B8: Beverages | C8: Marketing & Brand Management | D8: 0.2 | E8: Brand / campaign planning | F8: 0.25 | G8: Strategy & Design | H8: 0.3 | J8: 0.34 | K8: 0.34 | L8: 0.31 | M8: 0.27 | N8: 0.18
A9: Consumer Staples | B9: Beverages | C9: Marketing & Brand Management | D9: 0.2 | E9: Agency / sponsorship coordination | F9: 0.2 | G9: Stakeholder / Relationship Management | H9: 0.1 | J9: 0.34 | K9: 0.34 | L9: 0.31 | M9: 0.27 | N9: 0.18
A10: Consumer Staples | B10: Beverages | C10: Finance & Accounting | D10: 0.2 | E10: Transaction processing & reconciliation | F10: 0.3 | G10: Task Processing / Query Handling | H10: 0.9 | I10: =SUMPRODUCT(H10:H13,F10:F13)*D10 -> 0.1655 | J10: 0.64 | K10: 0.64 | L10: 0.59 | M10: 0.52 | N10: 0.4
A11: Consumer Staples | B11: Beverages | C11: Finance & Accounting | D11: 0.2 | E11: Financial planning & analysis | F11: 0.25 | G11: Assessment & Analysis | H11: 0.6 | J11: 0.64 | K11: 0.64 | L11: 0.59 | M11: 0.52 | N11: 0.4
A12: Consumer Staples | B12: Beverages | C12: Finance & Accounting | D12: 0.2 | E12: Budgeting & forecasting | F12: 0.2 | G12: Modelling (incl. Forecasting) | H12: 0.85 | J12: 0.64 | K12: 0.64 | L12: 0.59 | M12: 0.52 | N12: 0.4
A13: Consumer Staples | B13: Beverages | C13: Finance & Accounting | D13: 0.2 | E13: Financial reporting | F13: 0.25 | G13: Document Generation & Management | H13: 0.95 | J13: 0.64 | K13: 0.64 | L13: 0.59 | M13: 0.52 | N13: 0.4
A14: Consumer Staples | B14: Beverages | C14: Human Resources | D14: 0.1 | E14: Recruitment administration | F14: 0.25 | G14: Task Processing / Query Handling | H14: 0.9 | I14: =SUMPRODUCT(H14:H17,F14:F17)*D14 -> 0.062 | J14: 0.43 | K14: 0.43 | L14: 0.4 | M14: 0.35 | N14: 0.25
A15: Consumer Staples | B15: Beverages | C15: Human Resources | D15: 0.1 | E15: Workforce planning | F15: 0.25 | G15: Task Planning & Management | H15: 0.7 | J15: 0.43 | K15: 0.43 | L15: 0.4 | M15: 0.35 | N15: 0.25
A16: Consumer Staples | B16: Beverages | C16: Human Resources | D16: 0.1 | E16: Employee relations & support | F16: 0.3 | G16: Stakeholder / Relationship Management | H16: 0.1 | J16: 0.43 | K16: 0.43 | L16: 0.4 | M16: 0.35 | N16: 0.25
A17: Consumer Staples | B17: Beverages | C17: Human Resources | D17: 0.1 | E17: HR documentation & reporting | F17: 0.2 | G17: Document Generation & Management | H17: 0.95 | J17: 0.43 | K17: 0.43 | L17: 0.4 | M17: 0.35 | N17: 0.25
A18: Consumer Staples | B18: Beverages | C18: Corporate IT & Enterprise Technology | D18: 0.1 | E18: IT service desk & user support | F18: 0.3 | G18: Task Processing / Query Handling | H18: 0.9 | I18: =SUMPRODUCT(H18:H21,F18:F21)*D18 -> 0.081 | J18: 0.63 | K18: 0.63 | L18: 0.59 | M18: 0.53 | N18: 0.41
A19: Consumer Staples | B19: Beverages | C19: Corporate IT & Enterprise Technology | D19: 0.1 | E19: Application & infrastructure monitoring | F19: 0.25 | G19: Monitoring | H19: 0.7 | J19: 0.63 | K19: 0.63 | L19: 0.59 | M19: 0.53 | N19: 0.41
A20: Consumer Staples | B20: Beverages | C20: Corporate IT & Enterprise Technology | D20: 0.1 | E20: Technology planning & change coordination | F20: 0.25 | G20: Task Planning & Management | H20: 0.7 | J20: 0.63 | K20: 0.63 | L20: 0.59 | M20: 0.53 | N20: 0.41
A21: Consumer Staples | B21: Beverages | C21: Corporate IT & Enterprise Technology | D21: 0.1 | E21: IT documentation | F21: 0.2 | G21: Document Generation & Management | H21: 0.95 | J21: 0.63 | K21: 0.63 | L21: 0.59 | M21: 0.53 | N21: 0.41
A22: Consumer Staples | B22: Beverages | C22: Legal, Regulatory & Corporate Administration | D22: 0.1 | E22: Regulatory / policy monitoring | F22: 0.25 | G22: Monitoring | H22: 0.7 | I22: =SUMPRODUCT(H22:H25,F22:F25)*D22 -> 0.05875 | J22: 0.41 | K22: 0.41 | L22: 0.38 | M22: 0.33 | N22: 0.24
A23: Consumer Staples | B23: Beverages | C23: Legal, Regulatory & Corporate Administration | D23: 0.1 | E23: Contract / policy review | F23: 0.25 | G23: Assessment & Analysis | H23: 0.6 | J23: 0.41 | K23: 0.41 | L23: 0.38 | M23: 0.33 | N23: 0.24
A24: Consumer Staples | B24: Beverages | C24: Legal, Regulatory & Corporate Administration | D24: 0.1 | E24: Regulator / legal stakeholder management | F24: 0.25 | G24: Stakeholder / Relationship Management | H24: 0.1 | J24: 0.41 | K24: 0.41 | L24: 0.38 | M24: 0.33 | N24: 0.24
A25: Consumer Staples | B25: Beverages | C25: Legal, Regulatory & Corporate Administration | D25: 0.1 | E25: Compliance documentation | F25: 0.25 | G25: Document Generation & Management | H25: 0.95 | J25: 0.41 | K25: 0.41 | L25: 0.38 | M25: 0.33 | N25: 0.24
I26: =SUM(I2:I25) -> 0.61425 | J26: =+J6*$D6+J10*$D10+J14*$D14+J18*$D18+J22*$D22+$D2*J2 -> 0.463 | K26: =+K6*$D6+K10*$D10+K14*$D14+K18*$D18+K22*$D22+$D2*K2 -> 0.463 | L26: =+L6*$D6+L10*$D10+L14*$D14+L18*$D18+L22*$D22+$D2*L2 -> 0.428 | M26: =+M6*$D6+M10*$D10+M14*$D14+M18*$D18+M22*$D22+$D2*M2 -> 0.375 | N26: =+N6*$D6+N10*$D10+N14*$D14+N18*$D18+N22*$D22+$D2*N2 -> 0.278
A28: Consumer Staples | B28: Food & Agriculture | C28: Sales & Channel Management | D28: 0.25 | E28: Sales / channel planning | F28: 0.25 | G28: Task Planning & Management | H28: 0.7 | I28: =SUMPRODUCT(H28:H31,F28:F31)*D28 -> 0.13 | J28: 0.38 | K28: 0.38 | L28: 0.35 | M28: 0.3 | N28: 0.21
A29: Consumer Staples | B29: Food & Agriculture | C29: Sales & Channel Management | D29: 0.25 | E29: Retailer / distributor relationship management | F29: 0.35 | G29: Stakeholder / Relationship Management | H29: 0.1 | J29: 0.38 | K29: 0.38 | L29: 0.35 | M29: 0.3 | N29: 0.21
A30: Consumer Staples | B30: Food & Agriculture | C30: Sales & Channel Management | D30: 0.25 | E30: Pricing & account analytics | F30: 0.2 | G30: Assessment & Analysis | H30: 0.6 | J30: 0.38 | K30: 0.38 | L30: 0.35 | M30: 0.3 | N30: 0.21
A31: Consumer Staples | B31: Food & Agriculture | C31: Sales & Channel Management | D31: 0.25 | E31: Sales administration & reporting | F31: 0.2 | G31: Document Generation & Management | H31: 0.95 | J31: 0.38 | K31: 0.38 | L31: 0.35 | M31: 0.3 | N31: 0.21
A32: Consumer Staples | B32: Food & Agriculture | C32: Marketing & Brand Management | D32: 0.15 | E32: Campaign / content development | F32: 0.3 | G32: Content Generation | H32: 0.7 | I32: =SUMPRODUCT(H32:H35,F32:F35)*D32 -> 0.06825 | J32: 0.32 | K32: 0.32 | L32: 0.29 | M32: 0.25 | N32: 0.16
A33: Consumer Staples | B33: Food & Agriculture | C33: Marketing & Brand Management | D33: 0.15 | E33: Consumer / category analytics | F33: 0.25 | G33: Assessment & Analysis | H33: 0.6 | J33: 0.32 | K33: 0.32 | L33: 0.29 | M33: 0.25 | N33: 0.16
A34: Consumer Staples | B34: Food & Agriculture | C34: Marketing & Brand Management | D34: 0.15 | E34: Brand & campaign planning | F34: 0.25 | G34: Strategy & Design | H34: 0.3 | J34: 0.32 | K34: 0.32 | L34: 0.29 | M34: 0.25 | N34: 0.16
A35: Consumer Staples | B35: Food & Agriculture | C35: Marketing & Brand Management | D35: 0.15 | E35: Agency / channel coordination | F35: 0.2 | G35: Stakeholder / Relationship Management | H35: 0.1 | J35: 0.32 | K35: 0.32 | L35: 0.29 | M35: 0.25 | N35: 0.16
A36: Consumer Staples | B36: Food & Agriculture | C36: Finance & Accounting | D36: 0.2 | E36: Transaction processing & reconciliation | F36: 0.3 | G36: Task Processing / Query Handling | H36: 0.9 | I36: =SUMPRODUCT(H36:H39,F36:F39)*D36 -> 0.1655 | J36: 0.61 | K36: 0.61 | L36: 0.56 | M36: 0.49 | N36: 0.36
A37: Consumer Staples | B37: Food & Agriculture | C37: Finance & Accounting | D37: 0.2 | E37: Financial planning & analysis | F37: 0.25 | G37: Assessment & Analysis | H37: 0.6 | J37: 0.61 | K37: 0.61 | L37: 0.56 | M37: 0.49 | N37: 0.36
A38: Consumer Staples | B38: Food & Agriculture | C38: Finance & Accounting | D38: 0.2 | E38: Budgeting & forecasting | F38: 0.2 | G38: Modelling (incl. Forecasting) | H38: 0.85 | J38: 0.61 | K38: 0.61 | L38: 0.56 | M38: 0.49 | N38: 0.36
A39: Consumer Staples | B39: Food & Agriculture | C39: Finance & Accounting | D39: 0.2 | E39: Financial reporting | F39: 0.25 | G39: Document Generation & Management | H39: 0.95 | J39: 0.61 | K39: 0.61 | L39: 0.56 | M39: 0.49 | N39: 0.36
A40: Consumer Staples | B40: Food & Agriculture | C40: Human Resources | D40: 0.15 | E40: Recruitment administration | F40: 0.25 | G40: Task Processing / Query Handling | H40: 0.9 | I40: =SUMPRODUCT(H40:H43,F40:F43)*D40 -> 0.093 | J40: 0.4 | K40: 0.4 | L40: 0.37 | M40: 0.32 | N40: 0.22
A41: Consumer Staples | B41: Food & Agriculture | C41: Human Resources | D41: 0.15 | E41: Workforce planning | F41: 0.25 | G41: Task Planning & Management | H41: 0.7 | J41: 0.4 | K41: 0.4 | L41: 0.37 | M41: 0.32 | N41: 0.22
A42: Consumer Staples | B42: Food & Agriculture | C42: Human Resources | D42: 0.15 | E42: Employee / labour relations | F42: 0.3 | G42: Stakeholder / Relationship Management | H42: 0.1 | J42: 0.4 | K42: 0.4 | L42: 0.37 | M42: 0.32 | N42: 0.22
A43: Consumer Staples | B43: Food & Agriculture | C43: Human Resources | D43: 0.15 | E43: HR documentation & reporting | F43: 0.2 | G43: Document Generation & Management | H43: 0.95 | J43: 0.4 | K43: 0.4 | L43: 0.37 | M43: 0.32 | N43: 0.22
A44: Consumer Staples | B44: Food & Agriculture | C44: Corporate IT & Enterprise Technology | D44: 0.1 | E44: IT service desk & user support | F44: 0.3 | G44: Task Processing / Query Handling | H44: 0.9 | I44: =SUMPRODUCT(H44:H47,F44:F47)*D44 -> 0.081 | J44: 0.6 | K44: 0.6 | L44: 0.56 | M44: 0.49 | N44: 0.37
A45: Consumer Staples | B45: Food & Agriculture | C45: Corporate IT & Enterprise Technology | D45: 0.1 | E45: Application & infrastructure monitoring | F45: 0.25 | G45: Monitoring | H45: 0.7 | J45: 0.6 | K45: 0.6 | L45: 0.56 | M45: 0.49 | N45: 0.37
A46: Consumer Staples | B46: Food & Agriculture | C46: Corporate IT & Enterprise Technology | D46: 0.1 | E46: Technology planning & change coordination | F46: 0.25 | G46: Task Planning & Management | H46: 0.7 | J46: 0.6 | K46: 0.6 | L46: 0.56 | M46: 0.49 | N46: 0.37
A47: Consumer Staples | B47: Food & Agriculture | C47: Corporate IT & Enterprise Technology | D47: 0.1 | E47: IT documentation | F47: 0.2 | G47: Document Generation & Management | H47: 0.95 | J47: 0.6 | K47: 0.6 | L47: 0.56 | M47: 0.49 | N47: 0.37
A48: Consumer Staples | B48: Food & Agriculture | C48: Legal, Regulatory & Corporate Administration | D48: 0.15 | E48: Food / agricultural regulatory monitoring | F48: 0.25 | G48: Monitoring | H48: 0.7 | I48: =SUMPRODUCT(H48:H51,F48:F51)*D48 -> 0.088125 | J48: 0.4 | K48: 0.4 | L48: 0.37 | M48: 0.32 | N48: 0.22
A49: Consumer Staples | B49: Food & Agriculture | C49: Legal, Regulatory & Corporate Administration | D49: 0.15 | E49: Contract / policy review | F49: 0.25 | G49: Assessment & Analysis | H49: 0.6 | J49: 0.4 | K49: 0.4 | L49: 0.37 | M49: 0.32 | N49: 0.22
A50: Consumer Staples | B50: Food & Agriculture | C50: Legal, Regulatory & Corporate Administration | D50: 0.15 | E50: Regulator / stakeholder management | F50: 0.25 | G50: Stakeholder / Relationship Management | H50: 0.1 | J50: 0.4 | K50: 0.4 | L50: 0.37 | M50: 0.32 | N50: 0.22
A51: Consumer Staples | B51: Food & Agriculture | C51: Legal, Regulatory & Corporate Administration | D51: 0.15 | E51: Compliance documentation | F51: 0.25 | G51: Document Generation & Management | H51: 0.95 | J51: 0.4 | K51: 0.4 | L51: 0.37 | M51: 0.32 | N51: 0.22
I52: =SUM(I28:I51) -> 0.625875 | J52: =+J32*$D32+J36*$D36+J40*$D40+J44*$D44+J48*$D48+$D28*J28 -> 0.445 | K52: =+K32*$D32+K36*$D36+K40*$D40+K44*$D44+K48*$D48+$D28*K28 -> 0.445 | L52: =+L32*$D32+L36*$D36+L40*$D40+L44*$D44+L48*$D48+$D28*L28 -> 0.41 | M52: =+M32*$D32+M36*$D36+M40*$D40+M44*$D44+M48*$D48+$D28*M28 -> 0.3555 | N52: =+N32*$D32+N36*$D36+N40*$D40+N44*$D44+N48*$D48+$D28*N28 -> 0.2515
A54: Consumer Staples | B54: Household & Personal Care Products | C54: Sales & Channel Management | D54: 0.25 | E54: Sales planning & account targeting | F54: 0.25 | G54: Task Planning & Management | H54: 0.7 | I54: =SUMPRODUCT(H54:H57,F54:F57)*D54 -> 0.13 | J54: 0.4 | K54: 0.4 | L54: 0.37 | M54: 0.32 | N54: 0.23
A55: Consumer Staples | B55: Household & Personal Care Products | C55: Sales & Channel Management | D55: 0.25 | E55: Retailer / distributor relationship management | F55: 0.35 | G55: Stakeholder / Relationship Management | H55: 0.1 | J55: 0.4 | K55: 0.4 | L55: 0.37 | M55: 0.32 | N55: 0.23
A56: Consumer Staples | B56: Household & Personal Care Products | C56: Sales & Channel Management | D56: 0.25 | E56: Pricing & account analytics | F56: 0.2 | G56: Assessment & Analysis | H56: 0.6 | J56: 0.4 | K56: 0.4 | L56: 0.37 | M56: 0.32 | N56: 0.23
A57: Consumer Staples | B57: Household & Personal Care Products | C57: Sales & Channel Management | D57: 0.25 | E57: Sales administration & reporting | F57: 0.2 | G57: Document Generation & Management | H57: 0.95 | J57: 0.4 | K57: 0.4 | L57: 0.37 | M57: 0.32 | N57: 0.23
A58: Consumer Staples | B58: Household & Personal Care Products | C58: Marketing & Brand Management | D58: 0.25 | E58: Campaign & content development | F58: 0.3 | G58: Content Generation | H58: 0.7 | I58: =SUMPRODUCT(H58:H61,F58:F61)*D58 -> 0.11375 | J58: 0.35 | K58: 0.35 | L58: 0.32 | M58: 0.28 | N58: 0.18
A59: Consumer Staples | B59: Household & Personal Care Products | C59: Marketing & Brand Management | D59: 0.25 | E59: Consumer / market analytics | F59: 0.25 | G59: Assessment & Analysis | H59: 0.6 | J59: 0.35 | K59: 0.35 | L59: 0.32 | M59: 0.28 | N59: 0.18
A60: Consumer Staples | B60: Household & Personal Care Products | C60: Marketing & Brand Management | D60: 0.25 | E60: Brand / campaign planning | F60: 0.25 | G60: Strategy & Design | H60: 0.3 | J60: 0.35 | K60: 0.35 | L60: 0.32 | M60: 0.28 | N60: 0.18
A61: Consumer Staples | B61: Household & Personal Care Products | C61: Marketing & Brand Management | D61: 0.25 | E61: Agency / influencer coordination | F61: 0.2 | G61: Stakeholder / Relationship Management | H61: 0.1 | J61: 0.35 | K61: 0.35 | L61: 0.32 | M61: 0.28 | N61: 0.18
A62: Consumer Staples | B62: Household & Personal Care Products | C62: Finance & Accounting | D62: 0.15 | E62: Transaction processing & reconciliation | F62: 0.3 | G62: Task Processing / Query Handling | H62: 0.9 | I62: =SUMPRODUCT(H62:H65,F62:F65)*D62 -> 0.124125 | J62: 0.64 | K62: 0.64 | L62: 0.59 | M62: 0.52 | N62: 0.4
A63: Consumer Staples | B63: Household & Personal Care Products | C63: Finance & Accounting | D63: 0.15 | E63: Financial planning & analysis | F63: 0.25 | G63: Assessment & Analysis | H63: 0.6 | J63: 0.64 | K63: 0.64 | L63: 0.59 | M63: 0.52 | N63: 0.4
A64: Consumer Staples | B64: Household & Personal Care Products | C64: Finance & Accounting | D64: 0.15 | E64: Budgeting & forecasting | F64: 0.2 | G64: Modelling (incl. Forecasting) | H64: 0.85 | J64: 0.64 | K64: 0.64 | L64: 0.59 | M64: 0.52 | N64: 0.4
A65: Consumer Staples | B65: Household & Personal Care Products | C65: Finance & Accounting | D65: 0.15 | E65: Financial reporting | F65: 0.25 | G65: Document Generation & Management | H65: 0.95 | J65: 0.64 | K65: 0.64 | L65: 0.59 | M65: 0.52 | N65: 0.4
A66: Consumer Staples | B66: Household & Personal Care Products | C66: Human Resources | D66: 0.1 | E66: Recruitment administration | F66: 0.25 | G66: Task Processing / Query Handling | H66: 0.9 | I66: =SUMPRODUCT(H66:H69,F66:F69)*D66 -> 0.062 | J66: 0.43 | K66: 0.43 | L66: 0.4 | M66: 0.35 | N66: 0.25
A67: Consumer Staples | B67: Household & Personal Care Products | C67: Human Resources | D67: 0.1 | E67: Workforce planning | F67: 0.25 | G67: Task Planning & Management | H67: 0.7 | J67: 0.43 | K67: 0.43 | L67: 0.4 | M67: 0.35 | N67: 0.25
A68: Consumer Staples | B68: Household & Personal Care Products | C68: Human Resources | D68: 0.1 | E68: Employee relations & support | F68: 0.3 | G68: Stakeholder / Relationship Management | H68: 0.1 | J68: 0.43 | K68: 0.43 | L68: 0.4 | M68: 0.35 | N68: 0.25
A69: Consumer Staples | B69: Household & Personal Care Products | C69: Human Resources | D69: 0.1 | E69: HR documentation & reporting | F69: 0.2 | G69: Document Generation & Management | H69: 0.95 | J69: 0.43 | K69: 0.43 | L69: 0.4 | M69: 0.35 | N69: 0.25
A70: Consumer Staples | B70: Household & Personal Care Products | C70: Corporate IT & Enterprise Technology | D70: 0.1 | E70: IT service desk & user support | F70: 0.3 | G70: Task Processing / Query Handling | H70: 0.9 | I70: =SUMPRODUCT(H70:H73,F70:F73)*D70 -> 0.081 | J70: 0.63 | K70: 0.63 | L70: 0.59 | M70: 0.53 | N70: 0.41
A71: Consumer Staples | B71: Household & Personal Care Products | C71: Corporate IT & Enterprise Technology | D71: 0.1 | E71: Application & infrastructure monitoring | F71: 0.25 | G71: Monitoring | H71: 0.7 | J71: 0.63 | K71: 0.63 | L71: 0.59 | M71: 0.53 | N71: 0.41
A72: Consumer Staples | B72: Household & Personal Care Products | C72: Corporate IT & Enterprise Technology | D72: 0.1 | E72: Technology planning & change coordination | F72: 0.25 | G72: Task Planning & Management | H72: 0.7 | J72: 0.63 | K72: 0.63 | L72: 0.59 | M72: 0.53 | N72: 0.41
A73: Consumer Staples | B73: Household & Personal Care Products | C73: Corporate IT & Enterprise Technology | D73: 0.1 | E73: IT documentation | F73: 0.2 | G73: Document Generation & Management | H73: 0.95 | J73: 0.63 | K73: 0.63 | L73: 0.59 | M73: 0.53 | N73: 0.41
A74: Consumer Staples | B74: Household & Personal Care Products | C74: Legal, Regulatory & Corporate Administration | D74: 0.15 | E74: Product / regulatory monitoring | F74: 0.25 | G74: Monitoring | H74: 0.7 | I74: =SUMPRODUCT(H74:H77,F74:F77)*D74 -> 0.088125 | J74: 0.41 | K74: 0.41 | L74: 0.38 | M74: 0.33 | N74: 0.23
A75: Consumer Staples | B75: Household & Personal Care Products | C75: Legal, Regulatory & Corporate Administration | D75: 0.15 | E75: Contract / claims review | F75: 0.25 | G75: Assessment & Analysis | H75: 0.6 | J75: 0.41 | K75: 0.41 | L75: 0.38 | M75: 0.33 | N75: 0.23
A76: Consumer Staples | B76: Household & Personal Care Products | C76: Legal, Regulatory & Corporate Administration | D76: 0.15 | E76: Regulator / legal stakeholder management | F76: 0.25 | G76: Stakeholder / Relationship Management | H76: 0.1 | J76: 0.41 | K76: 0.41 | L76: 0.38 | M76: 0.33 | N76: 0.23
A77: Consumer Staples | B77: Household & Personal Care Products | C77: Legal, Regulatory & Corporate Administration | D77: 0.15 | E77: Compliance documentation | F77: 0.25 | G77: Document Generation & Management | H77: 0.95 | J77: 0.41 | K77: 0.41 | L77: 0.38 | M77: 0.33 | N77: 0.23
I78: =SUM(I54:I77) -> 0.599 | J78: =+J58*$D58+J62*$D62+J66*$D66+J70*$D70+J74*$D74+$D54*J54 -> 0.451 | K78: =+K58*$D58+K62*$D62+K66*$D66+K70*$D70+K74*$D74+$D54*K54 -> 0.451 | L78: =+L58*$D58+L62*$D62+L66*$D66+L70*$D70+L74*$D74+$D54*L54 -> 0.417 | M78: =+M58*$D58+M62*$D62+M66*$D66+M70*$D70+M74*$D74+$D54*M54 -> 0.3655 | N78: =+N58*$D58+N62*$D62+N66*$D66+N70*$D70+N74*$D74+$D54*N54 -> 0.263
A80: Consumer Staples | B80: Tobacco & Cannabis | C80: Sales & Channel Management | D80: 0.25 | E80: Sales / channel planning | F80: 0.25 | G80: Task Planning & Management | H80: 0.7 | I80: =SUMPRODUCT(H80:H83,F80:F83)*D80 -> 0.13 | J80: 0.38 | K80: 0.38 | L80: 0.35 | M80: 0.3 | N80: 0.21
A81: Consumer Staples | B81: Tobacco & Cannabis | C81: Sales & Channel Management | D81: 0.25 | E81: Distributor / retailer relationship management | F81: 0.35 | G81: Stakeholder / Relationship Management | H81: 0.1 | J81: 0.38 | K81: 0.38 | L81: 0.35 | M81: 0.3 | N81: 0.21
A82: Consumer Staples | B82: Tobacco & Cannabis | C82: Sales & Channel Management | D82: 0.25 | E82: Pricing & channel analytics | F82: 0.2 | G82: Assessment & Analysis | H82: 0.6 | J82: 0.38 | K82: 0.38 | L82: 0.35 | M82: 0.3 | N82: 0.21
A83: Consumer Staples | B83: Tobacco & Cannabis | C83: Sales & Channel Management | D83: 0.25 | E83: Sales administration & reporting | F83: 0.2 | G83: Document Generation & Management | H83: 0.95 | J83: 0.38 | K83: 0.38 | L83: 0.35 | M83: 0.3 | N83: 0.21
A84: Consumer Staples | B84: Tobacco & Cannabis | C84: Marketing & Consumer Insights | D84: 0.1 | E84: Permitted content / communication development | F84: 0.3 | G84: Content Generation | H84: 0.7 | I84: =SUMPRODUCT(H84:H87,F84:F87)*D84 -> 0.047 | J84: 0.3 | K84: 0.3 | L84: 0.27 | M84: 0.23 | N84: 0.15
A85: Consumer Staples | B85: Tobacco & Cannabis | C85: Marketing & Consumer Insights | D85: 0.1 | E85: Consumer / category analytics | F85: 0.3 | G85: Assessment & Analysis | H85: 0.6 | J85: 0.3 | K85: 0.3 | L85: 0.27 | M85: 0.23 | N85: 0.15
A86: Consumer Staples | B86: Tobacco & Cannabis | C86: Marketing & Consumer Insights | D86: 0.1 | E86: Market / portfolio planning | F86: 0.2 | G86: Strategy & Design | H86: 0.3 | J86: 0.3 | K86: 0.3 | L86: 0.27 | M86: 0.23 | N86: 0.15
A87: Consumer Staples | B87: Tobacco & Cannabis | C87: Marketing & Consumer Insights | D87: 0.1 | E87: Channel coordination | F87: 0.2 | G87: Stakeholder / Relationship Management | H87: 0.1 | J87: 0.3 | K87: 0.3 | L87: 0.27 | M87: 0.23 | N87: 0.15
A88: Consumer Staples | B88: Tobacco & Cannabis | C88: Finance & Accounting | D88: 0.15 | E88: Transaction processing & reconciliation | F88: 0.3 | G88: Task Processing / Query Handling | H88: 0.9 | I88: =SUMPRODUCT(H88:H91,F88:F91)*D88 -> 0.124125 | J88: 0.62 | K88: 0.62 | L88: 0.57 | M88: 0.5 | N88: 0.37
A89: Consumer Staples | B89: Tobacco & Cannabis | C89: Finance & Accounting | D89: 0.15 | E89: Financial planning & analysis | F89: 0.25 | G89: Assessment & Analysis | H89: 0.6 | J89: 0.62 | K89: 0.62 | L89: 0.57 | M89: 0.5 | N89: 0.37
A90: Consumer Staples | B90: Tobacco & Cannabis | C90: Finance & Accounting | D90: 0.15 | E90: Budgeting & forecasting | F90: 0.2 | G90: Modelling (incl. Forecasting) | H90: 0.85 | J90: 0.62 | K90: 0.62 | L90: 0.57 | M90: 0.5 | N90: 0.37
A91: Consumer Staples | B91: Tobacco & Cannabis | C91: Finance & Accounting | D91: 0.15 | E91: Financial reporting | F91: 0.25 | G91: Document Generation & Management | H91: 0.95 | J91: 0.62 | K91: 0.62 | L91: 0.57 | M91: 0.5 | N91: 0.37
A92: Consumer Staples | B92: Tobacco & Cannabis | C92: Human Resources | D92: 0.1 | E92: Recruitment administration | F92: 0.25 | G92: Task Processing / Query Handling | H92: 0.9 | I92: =SUMPRODUCT(H92:H95,F92:F95)*D92 -> 0.062 | J92: 0.42 | K92: 0.42 | L92: 0.39 | M92: 0.34 | N92: 0.24
A93: Consumer Staples | B93: Tobacco & Cannabis | C93: Human Resources | D93: 0.1 | E93: Workforce planning | F93: 0.25 | G93: Task Planning & Management | H93: 0.7 | J93: 0.42 | K93: 0.42 | L93: 0.39 | M93: 0.34 | N93: 0.24
A94: Consumer Staples | B94: Tobacco & Cannabis | C94: Human Resources | D94: 0.1 | E94: Employee relations & support | F94: 0.3 | G94: Stakeholder / Relationship Management | H94: 0.1 | J94: 0.42 | K94: 0.42 | L94: 0.39 | M94: 0.34 | N94: 0.24
A95: Consumer Staples | B95: Tobacco & Cannabis | C95: Human Resources | D95: 0.1 | E95: HR documentation & reporting | F95: 0.2 | G95: Document Generation & Management | H95: 0.95 | J95: 0.42 | K95: 0.42 | L95: 0.39 | M95: 0.34 | N95: 0.24
A96: Consumer Staples | B96: Tobacco & Cannabis | C96: Corporate IT & Enterprise Technology | D96: 0.1 | E96: IT service desk & user support | F96: 0.3 | G96: Task Processing / Query Handling | H96: 0.9 | I96: =SUMPRODUCT(H96:H99,F96:F99)*D96 -> 0.081 | J96: 0.62 | K96: 0.62 | L96: 0.58 | M96: 0.51 | N96: 0.38
A97: Consumer Staples | B97: Tobacco & Cannabis | C97: Corporate IT & Enterprise Technology | D97: 0.1 | E97: Application & infrastructure monitoring | F97: 0.25 | G97: Monitoring | H97: 0.7 | J97: 0.62 | K97: 0.62 | L97: 0.58 | M97: 0.51 | N97: 0.38
A98: Consumer Staples | B98: Tobacco & Cannabis | C98: Corporate IT & Enterprise Technology | D98: 0.1 | E98: Technology planning & change coordination | F98: 0.25 | G98: Task Planning & Management | H98: 0.7 | J98: 0.62 | K98: 0.62 | L98: 0.58 | M98: 0.51 | N98: 0.38
A99: Consumer Staples | B99: Tobacco & Cannabis | C99: Corporate IT & Enterprise Technology | D99: 0.1 | E99: IT documentation | F99: 0.2 | G99: Document Generation & Management | H99: 0.95 | J99: 0.62 | K99: 0.62 | L99: 0.58 | M99: 0.51 | N99: 0.38
A100: Consumer Staples | B100: Tobacco & Cannabis | C100: Legal, Regulatory & Corporate Administration | D100: 0.3 | E100: Regulatory / compliance monitoring | F100: 0.25 | G100: Monitoring | H100: 0.7 | I100: =SUMPRODUCT(H100:H103,F100:F103)*D100 -> 0.17625 | J100: 0.42 | K100: 0.42 | L100: 0.39 | M100: 0.34 | N100: 0.24
A101: Consumer Staples | B101: Tobacco & Cannabis | C101: Legal, Regulatory & Corporate Administration | D101: 0.3 | E101: Product / contract / policy review | F101: 0.25 | G101: Assessment & Analysis | H101: 0.6 | J101: 0.42 | K101: 0.42 | L101: 0.39 | M101: 0.34 | N101: 0.24
A102: Consumer Staples | B102: Tobacco & Cannabis | C102: Legal, Regulatory & Corporate Administration | D102: 0.3 | E102: Regulator / legal stakeholder management | F102: 0.25 | G102: Stakeholder / Relationship Management | H102: 0.1 | J102: 0.42 | K102: 0.42 | L102: 0.39 | M102: 0.34 | N102: 0.24
A103: Consumer Staples | B103: Tobacco & Cannabis | C103: Legal, Regulatory & Corporate Administration | D103: 0.3 | E103: Regulatory documentation & filings | F103: 0.25 | G103: Document Generation & Management | H103: 0.95 | J103: 0.42 | K103: 0.42 | L103: 0.39 | M103: 0.34 | N103: 0.24
...

Sheet Financials
A1: Sector | B1: Subsector | C1: Core Activity | D1: Effort Split | E1: Key Main Task | F1: % Effort | G1: Category | H1: AI Addressable | I1: Agentification Potential | J1: Actual Agentification Possible | K1: NA | L1: EU | M1: APAC ex India | N1: India
A2: Financials | B2: Retail Banking | C2: Marketing & Corporate Communications | D2: 0.15 | E2: Campaign & content development | F2: 0.3 | G2: Content Generation | H2: 0.7 | I2: =SUMPRODUCT(H2:H5,F2:F5)*D2 -> 0.06825 | J2: 0.36 | K2: 0.36 | L2: 0.32 | M2: 0.29 | N2: 0.31
A3: Financials | B3: Retail Banking | C3: Marketing & Corporate Communications | D3: 0.15 | E3: Customer / market analytics | F3: 0.25 | G3: Assessment & Analysis | H3: 0.6 | J3: 0.36 | K3: 0.36 | L3: 0.32 | M3: 0.29 | N3: 0.31
A4: Financials | B4: Retail Banking | C4: Marketing & Corporate Communications | D4: 0.15 | E4: Campaign / proposition planning | F4: 0.25 | G4: Strategy & Design | H4: 0.3 | J4: 0.36 | K4: 0.36 | L4: 0.32 | M4: 0.29 | N4: 0.31
A5: Financials | B5: Retail Banking | C5: Marketing & Corporate Communications | D5: 0.15 | E5: Agency / external stakeholder coordination | F5: 0.2 | G5: Stakeholder / Relationship Management | H5: 0.1 | J5: 0.36 | K5: 0.36 | L5: 0.32 | M5: 0.29 | N5: 0.31
A6: Financials | B6: Retail Banking | C6: Finance & Accounting | D6: 0.2 | E6: Transaction processing & reconciliation | F6: 0.3 | G6: Task Processing / Query Handling | H6: 0.9 | I6: =SUMPRODUCT(H6:H9,F6:F9)*D6 -> 0.1655 | J6: 0.68 | K6: 0.68 | L6: 0.64 | M6: 0.61 | N6: 0.63
A7: Financials | B7: Retail Banking | C7: Finance & Accounting | D7: 0.2 | E7: Financial planning & analysis | F7: 0.25 | G7: Assessment & Analysis | H7: 0.6 | J7: 0.68 | K7: 0.68 | L7: 0.64 | M7: 0.61 | N7: 0.63
A8: Financials | B8: Retail Banking | C8: Finance & Accounting | D8: 0.2 | E8: Budgeting & forecasting | F8: 0.2 | G8: Modelling (incl. Forecasting) | H8: 0.85 | J8: 0.68 | K8: 0.68 | L8: 0.64 | M8: 0.61 | N8: 0.63
A9: Financials | B9: Retail Banking | C9: Finance & Accounting | D9: 0.2 | E9: Financial reporting | F9: 0.25 | G9: Document Generation & Management | H9: 0.95 | J9: 0.68 | K9: 0.68 | L9: 0.64 | M9: 0.61 | N9: 0.63
A10: Financials | B10: Retail Banking | C10: Human Resources | D10: 0.15 | E10: Recruitment administration | F10: 0.25 | G10: Task Processing / Query Handling | H10: 0.9 | I10: =SUMPRODUCT(H10:H13,F10:F13)*D10 -> 0.093 | J10: 0.48 | K10: 0.48 | L10: 0.44 | M10: 0.41 | N10: 0.43
A11: Financials | B11: Retail Banking | C11: Human Resources | D11: 0.15 | E11: Workforce planning | F11: 0.25 | G11: Task Planning & Management | H11: 0.7 | J11: 0.48 | K11: 0.48 | L11: 0.44 | M11: 0.41 | N11: 0.43
A12: Financials | B12: Retail Banking | C12: Human Resources | D12: 0.15 | E12: Employee relations & support | F12: 0.3 | G12: Stakeholder / Relationship Management | H12: 0.1 | J12: 0.48 | K12: 0.48 | L12: 0.44 | M12: 0.41 | N12: 0.43
A13: Financials | B13: Retail Banking | C13: Human Resources | D13: 0.15 | E13: HR documentation & reporting | F13: 0.2 | G13: Document Generation & Management | H13: 0.95 | J13: 0.48 | K13: 0.48 | L13: 0.44 | M13: 0.41 | N13: 0.43
A14: Financials | B14: Retail Banking | C14: Corporate IT & Enterprise Technology | D14: 0.2 | E14: IT service desk & user support | F14: 0.3 | G14: Task Processing / Query Handling | H14: 0.9 | I14: =SUMPRODUCT(H14:H17,F14:F17)*D14 -> 0.162 | J14: 0.68 | K14: 0.68 | L14: 0.64 | M14: 0.61 | N14: 0.63
A15: Financials | B15: Retail Banking | C15: Corporate IT & Enterprise Technology | D15: 0.2 | E15: Application, infrastructure & security monitoring | F15: 0.25 | G15: Monitoring | H15: 0.7 | J15: 0.68 | K15: 0.68 | L15: 0.64 | M15: 0.61 | N15: 0.63
A16: Financials | B16: Retail Banking | C16: Corporate IT & Enterprise Technology | D16: 0.2 | E16: Technology planning & change coordination | F16: 0.25 | G16: Task Planning & Management | H16: 0.7 | J16: 0.68 | K16: 0.68 | L16: 0.64 | M16: 0.61 | N16: 0.63
A17: Financials | B17: Retail Banking | C17: Corporate IT & Enterprise Technology | D17: 0.2 | E17: IT documentation | F17: 0.2 | G17: Document Generation & Management | H17: 0.95 | J17: 0.68 | K17: 0.68 | L17: 0.64 | M17: 0.61 | N17: 0.63
A18: Financials | B18: Retail Banking | C18: Legal, Regulatory & Corporate Administration | D18: 0.2 | E18: Regulatory / policy monitoring | F18: 0.25 | G18: Monitoring | H18: 0.7 | I18: =SUMPRODUCT(H18:H21,F18:F21)*D18 -> 0.1175 | J18: 0.45 | K18: 0.45 | L18: 0.41 | M18: 0.38 | N18: 0.4
A19: Financials | B19: Retail Banking | C19: Legal, Regulatory & Corporate Administration | D19: 0.2 | E19: Contract & policy review | F19: 0.25 | G19: Assessment & Analysis | H19: 0.6 | J19: 0.45 | K19: 0.45 | L19: 0.41 | M19: 0.38 | N19: 0.4
A20: Financials | B20: Retail Banking | C20: Legal, Regulatory & Corporate Administration | D20: 0.2 | E20: Regulator / legal stakeholder management | F20: 0.25 | G20: Stakeholder / Relationship Management | H20: 0.1 | J20: 0.45 | K20: 0.45 | L20: 0.41 | M20: 0.38 | N20: 0.4
A21: Financials | B21: Retail Banking | C21: Legal, Regulatory & Corporate Administration | D21: 0.2 | E21: Compliance & corporate documentation | F21: 0.25 | G21: Document Generation & Management | H21: 0.95 | J21: 0.45 | K21: 0.45 | L21: 0.41 | M21: 0.38 | N21: 0.4
A22: Financials | B22: Retail Banking | C22: Corporate Strategy & Management | D22: 0.1 | E22: Strategic planning | F22: 0.3 | G22: Strategy & Design | H22: 0.3 | I22: =SUMPRODUCT(H22:H25,F22:F25)*D22 -> 0.0455 | J22: 0.35 | K22: 0.35 | L22: 0.31 | M22: 0.28 | N22: 0.3
A23: Financials | B23: Retail Banking | C23: Corporate Strategy & Management | D23: 0.1 | E23: Management / market analysis | F23: 0.25 | G23: Assessment & Analysis | H23: 0.6 | J23: 0.35 | K23: 0.35 | L23: 0.31 | M23: 0.28 | N23: 0.3
A24: Financials | B24: Retail Banking | C24: Corporate Strategy & Management | D24: 0.1 | E24: Executive stakeholder coordination | F24: 0.25 | G24: Stakeholder / Relationship Management | H24: 0.1 | J24: 0.35 | K24: 0.35 | L24: 0.31 | M24: 0.28 | N24: 0.3
A25: Financials | B25: Retail Banking | C25: Corporate Strategy & Management | D25: 0.1 | E25: Corporate reporting | F25: 0.2 | G25: Document Generation & Management | H25: 0.95 | J25: 0.35 | K25: 0.35 | L25: 0.31 | M25: 0.28 | N25: 0.3
I26: =SUM(I2:I25) -> 0.65175 | J26: =+J6*$D6+J10*$D10+J14*$D14+J18*$D18+J22*$D22+$D2*J2 -> 0.523 | K26: =+K6*$D6+K10*$D10+K14*$D14+K18*$D18+K22*$D22+$D2*K2 -> 0.523 | L26: =+L6*$D6+L10*$D10+L14*$D14+L18*$D18+L22*$D22+$D2*L2 -> 0.483 | M26: =+M6*$D6+M10*$D10+M14*$D14+M18*$D18+M22*$D22+$D2*M2 -> 0.453 | N26: =+N6*$D6+N10*$D10+N14*$D14+N18*$D18+N22*$D22+$D2*N2 -> 0.473
A28: Financials | B28: Private Equity | C28: Finance & Accounting | D28: 0.2 | E28: Transaction processing & reconciliation | F28: 0.3 | G28: Task Processing / Query Handling | H28: 0.9 | I28: =SUMPRODUCT(H28:H31,F28:F31)*D28 -> 0.1655 | J28: 0.68 | K28: 0.68 | L28: 0.65 | M28: 0.61 | N28: 0.58
A29: Financials | B29: Private Equity | C29: Finance & Accounting | D29: 0.2 | E29: Financial planning & analysis | F29: 0.25 | G29: Assessment & Analysis | H29: 0.6 | J29: 0.68 | K29: 0.68 | L29: 0.65 | M29: 0.61 | N29: 0.58
A30: Financials | B30: Private Equity | C30: Finance & Accounting | D30: 0.2 | E30: Budgeting & forecasting | F30: 0.2 | G30: Modelling (incl. Forecasting) | H30: 0.85 | J30: 0.68 | K30: 0.68 | L30: 0.65 | M30: 0.61 | N30: 0.58
A31: Financials | B31: Private Equity | C31: Finance & Accounting | D31: 0.2 | E31: Financial reporting | F31: 0.25 | G31: Document Generation & Management | H31: 0.95 | J31: 0.68 | K31: 0.68 | L31: 0.65 | M31: 0.61 | N31: 0.58
A32: Financials | B32: Private Equity | C32: Human Resources | D32: 0.15 | E32: Recruitment administration | F32: 0.25 | G32: Task Processing / Query Handling | H32: 0.9 | I32: =SUMPRODUCT(H32:H35,F32:F35)*D32 -> 0.093 | J32: 0.48 | K32: 0.48 | L32: 0.45 | M32: 0.41 | N32: 0.38
A33: Financials | B33: Private Equity | C33: Human Resources | D33: 0.15 | E33: Workforce planning | F33: 0.25 | G33: Task Planning & Management | H33: 0.7 | J33: 0.48 | K33: 0.48 | L33: 0.45 | M33: 0.41 | N33: 0.38
A34: Financials | B34: Private Equity | C34: Human Resources | D34: 0.15 | E34: Employee relations & support | F34: 0.3 | G34: Stakeholder / Relationship Management | H34: 0.1 | J34: 0.48 | K34: 0.48 | L34: 0.45 | M34: 0.41 | N34: 0.38
A35: Financials | B35: Private Equity | C35: Human Resources | D35: 0.15 | E35: HR documentation & reporting | F35: 0.2 | G35: Document Generation & Management | H35: 0.95 | J35: 0.48 | K35: 0.48 | L35: 0.45 | M35: 0.41 | N35: 0.38
A36: Financials | B36: Private Equity | C36: Corporate IT & Enterprise Technology | D36: 0.15 | E36: IT service desk & user support | F36: 0.3 | G36: Task Processing / Query Handling | H36: 0.9 | I36: =SUMPRODUCT(H36:H39,F36:F39)*D36 -> 0.1215 | J36: 0.68 | K36: 0.68 | L36: 0.65 | M36: 0.61 | N36: 0.58
A37: Financials | B37: Private Equity | C37: Corporate IT & Enterprise Technology | D37: 0.15 | E37: Application, infrastructure & security monitoring | F37: 0.25 | G37: Monitoring | H37: 0.7 | J37: 0.68 | K37: 0.68 | L37: 0.65 | M37: 0.61 | N37: 0.58
A38: Financials | B38: Private Equity | C38: Corporate IT & Enterprise Technology | D38: 0.15 | E38: Technology planning & change coordination | F38: 0.25 | G38: Task Planning & Management | H38: 0.7 | J38: 0.68 | K38: 0.68 | L38: 0.65 | M38: 0.61 | N38: 0.58
A39: Financials | B39: Private Equity | C39: Corporate IT & Enterprise Technology | D39: 0.15 | E39: IT documentation | F39: 0.2 | G39: Document Generation & Management | H39: 0.95 | J39: 0.68 | K39: 0.68 | L39: 0.65 | M39: 0.61 | N39: 0.58
A40: Financials | B40: Private Equity | C40: Legal, Regulatory & Corporate Administration | D40: 0.25 | E40: Regulatory / policy monitoring | F40: 0.25 | G40: Monitoring | H40: 0.7 | I40: =SUMPRODUCT(H40:H43,F40:F43)*D40 -> 0.146875 | J40: 0.45 | K40: 0.45 | L40: 0.42 | M40: 0.38 | N40: 0.35
A41: Financials | B41: Private Equity | C41: Legal, Regulatory & Corporate Administration | D41: 0.25 | E41: Contract & policy review | F41: 0.25 | G41: Assessment & Analysis | H41: 0.6 | J41: 0.45 | K41: 0.45 | L41: 0.42 | M41: 0.38 | N41: 0.35
A42: Financials | B42: Private Equity | C42: Legal, Regulatory & Corporate Administration | D42: 0.25 | E42: Regulator / legal stakeholder management | F42: 0.25 | G42: Stakeholder / Relationship Management | H42: 0.1 | J42: 0.45 | K42: 0.45 | L42: 0.42 | M42: 0.38 | N42: 0.35
A43: Financials | B43: Private Equity | C43: Legal, Regulatory & Corporate Administration | D43: 0.25 | E43: Compliance & corporate documentation | F43: 0.25 | G43: Document Generation & Management | H43: 0.95 | J43: 0.45 | K43: 0.45 | L43: 0.42 | M43: 0.38 | N43: 0.35
A44: Financials | B44: Private Equity | C44: Corporate Strategy & Management | D44: 0.2 | E44: Strategic planning | F44: 0.3 | G44: Strategy & Design | H44: 0.3 | I44: =SUMPRODUCT(H44:H47,F44:F47)*D44 -> 0.091 | J44: 0.35 | K44: 0.35 | L44: 0.32 | M44: 0.28 | N44: 0.25
A45: Financials | B45: Private Equity | C45: Corporate Strategy & Management | D45: 0.2 | E45: Management / market analysis | F45: 0.25 | G45: Assessment & Analysis | H45: 0.6 | J45: 0.35 | K45: 0.35 | L45: 0.32 | M45: 0.28 | N45: 0.25
A46: Financials | B46: Private Equity | C46: Corporate Strategy & Management | D46: 0.2 | E46: Executive stakeholder coordination | F46: 0.25 | G46: Stakeholder / Relationship Management | H46: 0.1 | J46: 0.35 | K46: 0.35 | L46: 0.32 | M46: 0.28 | N46: 0.25
A47: Financials | B47: Private Equity | C47: Corporate Strategy & Management | D47: 0.2 | E47: Corporate reporting | F47: 0.2 | G47: Document Generation & Management | H47: 0.95 | J47: 0.35 | K47: 0.35 | L47: 0.32 | M47: 0.28 | N47: 0.25
A48: Financials | B48: Private Equity | C48: Procurement & Vendor Management | D48: 0.05 | E48: Purchase & vendor administration | F48: 0.25 | G48: Task Processing / Query Handling | H48: 0.9 | I48: =SUMPRODUCT(H48:H51,F48:F51)*D48 -> 0.02975 | J48: 0.45 | K48: 0.45 | L48: 0.42 | M48: 0.38 | N48: 0.35
A49: Financials | B49: Private Equity | C49: Procurement & Vendor Management | D49: 0.05 | E49: Vendor / spend analysis | F49: 0.25 | G49: Assessment & Analysis | H49: 0.6 | J49: 0.45 | K49: 0.45 | L49: 0.42 | M49: 0.38 | N49: 0.35
A50: Financials | B50: Private Equity | C50: Procurement & Vendor Management | D50: 0.05 | E50: Vendor relationship management | F50: 0.3 | G50: Stakeholder / Relationship Management | H50: 0.1 | J50: 0.45 | K50: 0.45 | L50: 0.42 | M50: 0.38 | N50: 0.35
A51: Financials | B51: Private Equity | C51: Procurement & Vendor Management | D51: 0.05 | E51: Contract & procurement documentation | F51: 0.2 | G51: Document Generation & Management | H51: 0.95 | J51: 0.45 | K51: 0.45 | L51: 0.42 | M51: 0.38 | N51: 0.35
I52: =SUM(I28:I51) -> 0.647625 | J52: =+J32*$D32+J36*$D36+J40*$D40+J44*$D44+J48*$D48+$D28*J28 -> 0.515 | K52: =+K32*$D32+K36*$D36+K40*$D40+K44*$D44+K48*$D48+$D28*K28 -> 0.515 | L52: =+L32*$D32+L36*$D36+L40*$D40+L44*$D44+L48*$D48+$D28*L28 -> 0.485 | M52: =+M32*$D32+M36*$D36+M40*$D40+M44*$D44+M48*$D48+$D28*M28 -> 0.445 | N52: =+N32*$D32+N36*$D36+N40*$D40+N44*$D44+N48*$D48+$D28*N28 -> 0.415
A54: Financials | B54: Asset Management | C54: Marketing & Corporate Communications | D54: 0.15 | E54: Campaign & content development | F54: 0.3 | G54: Content Generation | H54: 0.7 | I54: =SUMPRODUCT(H54:H57,F54:F57)*D54 -> 0.06825 | J54: 0.36 | K54: 0.36 | L54: 0.33 | M54: 0.29 | N54: 0.27
A55: Financials | B55: Asset Management | C55: Marketing & Corporate Communications | D55: 0.15 | E55: Customer / market analytics | F55: 0.25 | G55: Assessment & Analysis | H55: 0.6 | J55: 0.36 | K55: 0.36 | L55: 0.33 | M55: 0.29 | N55: 0.27
A56: Financials | B56: Asset Management | C56: Marketing & Corporate Communications | D56: 0.15 | E56: Campaign / proposition planning | F56: 0.25 | G56: Strategy & Design | H56: 0.3 | J56: 0.36 | K56: 0.36 | L56: 0.33 | M56: 0.29 | N56: 0.27
A57: Financials | B57: Asset Management | C57: Marketing & Corporate Communications | D57: 0.15 | E57: Agency / external stakeholder coordination | F57: 0.2 | G57: Stakeholder / Relationship Management | H57: 0.1 | J57: 0.36 | K57: 0.36 | L57: 0.33 | M57: 0.29 | N57: 0.27
A58: Financials | B58: Asset Management | C58: Finance & Accounting | D58: 0.2 | E58: Transaction processing & reconciliation | F58: 0.3 | G58: Task Processing / Query Handling | H58: 0.9 | I58: =SUMPRODUCT(H58:H61,F58:F61)*D58 -> 0.1655 | J58: 0.68 | K58: 0.68 | L58: 0.65 | M58: 0.61 | N58: 0.59
A59: Financials | B59: Asset Management | C59: Finance & Accounting | D59: 0.2 | E59: Financial planning & analysis | F59: 0.25 | G59: Assessment & Analysis | H59: 0.6 | J59: 0.68 | K59: 0.68 | L59: 0.65 | M59: 0.61 | N59: 0.59
A60: Financials | B60: Asset Management | C60: Finance & Accounting | D60: 0.2 | E60: Budgeting & forecasting | F60: 0.2 | G60: Modelling (incl. Forecasting) | H60: 0.85 | J60: 0.68 | K60: 0.68 | L60: 0.65 | M60: 0.61 | N60: 0.59
A61: Financials | B61: Asset Management | C61: Finance & Accounting | D61: 0.2 | E61: Financial reporting | F61: 0.25 | G61: Document Generation & Management | H61: 0.95 | J61: 0.68 | K61: 0.68 | L61: 0.65 | M61: 0.61 | N61: 0.59
A62: Financials | B62: Asset Management | C62: Human Resources | D62: 0.15 | E62: Recruitment administration | F62: 0.25 | G62: Task Processing / Query Handling | H62: 0.9 | I62: =SUMPRODUCT(H62:H65,F62:F65)*D62 -> 0.093 | J62: 0.48 | K62: 0.48 | L62: 0.45 | M62: 0.41 | N62: 0.39
A63: Financials | B63: Asset Management | C63: Human Resources | D63: 0.15 | E63: Workforce planning | F63: 0.25 | G63: Task Planning & Management | H63: 0.7 | J63: 0.48 | K63: 0.48 | L63: 0.45 | M63: 0.41 | N63: 0.39
A64: Financials | B64: Asset Management | C64: Human Resources | D64: 0.15 | E64: Employee relations & support | F64: 0.3 | G64: Stakeholder / Relationship Management | H64: 0.1 | J64: 0.48 | K64: 0.48 | L64: 0.45 | M64: 0.41 | N64: 0.39
A65: Financials | B65: Asset Management | C65: Human Resources | D65: 0.15 | E65: HR documentation & reporting | F65: 0.2 | G65: Document Generation & Management | H65: 0.95 | J65: 0.48 | K65: 0.48 | L65: 0.45 | M65: 0.41 | N65: 0.39
A66: Financials | B66: Asset Management | C66: Corporate IT & Enterprise Technology | D66: 0.2 | E66: IT service desk & user support | F66: 0.3 | G66: Task Processing / Query Handling | H66: 0.9 | I66: =SUMPRODUCT(H66:H69,F66:F69)*D66 -> 0.162 | J66: 0.68 | K66: 0.68 | L66: 0.65 | M66: 0.61 | N66: 0.59
A67: Financials | B67: Asset Management | C67: Corporate IT & Enterprise Technology | D67: 0.2 | E67: Application, infrastructure & security monitoring | F67: 0.25 | G67: Monitoring | H67: 0.7 | J67: 0.68 | K67: 0.68 | L67: 0.65 | M67: 0.61 | N67: 0.59
A68: Financials | B68: Asset Management | C68: Corporate IT & Enterprise Technology | D68: 0.2 | E68: Technology planning & change coordination | F68: 0.25 | G68: Task Planning & Management | H68: 0.7 | J68: 0.68 | K68: 0.68 | L68: 0.65 | M68: 0.61 | N68: 0.59
A69: Financials | B69: Asset Management | C69: Corporate IT & Enterprise Technology | D69: 0.2 | E69: IT documentation | F69: 0.2 | G69: Document Generation & Management | H69: 0.95 | J69: 0.68 | K69: 0.68 | L69: 0.65 | M69: 0.61 | N69: 0.59
A70: Financials | B70: Asset Management | C70: Legal, Regulatory & Corporate Administration | D70: 0.2 | E70: Regulatory / policy monitoring | F70: 0.25 | G70: Monitoring | H70: 0.7 | I70: =SUMPRODUCT(H70:H73,F70:F73)*D70 -> 0.1175 | J70: 0.45 | K70: 0.45 | L70: 0.42 | M70: 0.38 | N70: 0.36
A71: Financials | B71: Asset Management | C71: Legal, Regulatory & Corporate Administration | D71: 0.2 | E71: Contract & policy review | F71: 0.25 | G71: Assessment & Analysis | H71: 0.6 | J71: 0.45 | K71: 0.45 | L71: 0.42 | M71: 0.38 | N71: 0.36
A72: Financials | B72: Asset Management | C72: Legal, Regulatory & Corporate Administration | D72: 0.2 | E72: Regulator / legal stakeholder management | F72: 0.25 | G72: Stakeholder / Relationship Management | H72: 0.1 | J72: 0.45 | K72: 0.45 | L72: 0.42 | M72: 0.38 | N72: 0.36
A73: Financials | B73: Asset Management | C73: Legal, Regulatory & Corporate Administration | D73: 0.2 | E73: Compliance & corporate documentation | F73: 0.25 | G73: Document Generation & Management | H73: 0.95 | J73: 0.45 | K73: 0.45 | L73: 0.42 | M73: 0.38 | N73: 0.36
A74: Financials | B74: Asset Management | C74: Corporate Strategy & Management | D74: 0.1 | E74: Strategic planning | F74: 0.3 | G74: Strategy & Design | H74: 0.3 | I74: =SUMPRODUCT(H74:H77,F74:F77)*D74 -> 0.0455 | J74: 0.35 | K74: 0.35 | L74: 0.32 | M74: 0.28 | N74: 0.26
A75: Financials | B75: Asset Management | C75: Corporate Strategy & Management | D75: 0.1 | E75: Management / market analysis | F75: 0.25 | G75: Assessment & Analysis | H75: 0.6 | J75: 0.35 | K75: 0.35 | L75: 0.32 | M75: 0.28 | N75: 0.26
A76: Financials | B76: Asset Management | C76: Corporate Strategy & Management | D76: 0.1 | E76: Executive stakeholder coordination | F76: 0.25 | G76: Stakeholder / Relationship Management | H76: 0.1 | J76: 0.35 | K76: 0.35 | L76: 0.32 | M76: 0.28 | N76: 0.26
A77: Financials | B77: Asset Management | C77: Corporate Strategy & Management | D77: 0.1 | E77: Corporate reporting | F77: 0.2 | G77: Document Generation & Management | H77: 0.95 | J77: 0.35 | K77: 0.35 | L77: 0.32 | M77: 0.28 | N77: 0.26
I78: =SUM(I54:I77) -> 0.65175 | J78: =+J58*$D58+J62*$D62+J66*$D66+J70*$D70+J74*$D74+$D54*J54 -> 0.523 | K78: =+K58*$D58+K62*$D62+K66*$D66+K70*$D70+K74*$D74+$D54*K54 -> 0.523 | L78: =+L58*$D58+L62*$D62+L66*$D66+L70*$D70+L74*$D74+$D54*L54 -> 0.493 | M78: =+M58*$D58+M62*$D62+M66*$D66+M70*$D70+M74*$D74+$D54*M54 -> 0.453 | N78: =+N58*$D58+N62*$D62+N66*$D66+N70*$D70+N74*$D74+$D54*N54 -> 0.433
A80: Financials | B80: Capital Markets / Investment Banking | C80: Finance & Accounting | D80: 0.2 | E80: Transaction processing & reconciliation | F80: 0.3 | G80: Task Processing / Query Handling | H80: 0.9 | I80: =SUMPRODUCT(H80:H83,F80:F83)*D80 -> 0.1655 | J80: 0.68 | K80: 0.68 | L80: 0.65 | M80: 0.61 | N80: 0.58
A81: Financials | B81: Capital Markets / Investment Banking | C81: Finance & Accounting | D81: 0.2 | E81: Financial planning & analysis | F81: 0.25 | G81: Assessment & Analysis | H81: 0.6 | J81: 0.68 | K81: 0.68 | L81: 0.65 | M81: 0.61 | N81: 0.58
A82: Financials | B82: Capital Markets / Investment Banking | C82: Finance & Accounting | D82: 0.2 | E82: Budgeting & forecasting | F82: 0.2 | G82: Modelling (incl. Forecasting) | H82: 0.85 | J82: 0.68 | K82: 0.68 | L82: 0.65 | M82: 0.61 | N82: 0.58
A83: Financials | B83: Capital Markets / Investment Banking | C83: Finance & Accounting | D83: 0.2 | E83: Financial reporting | F83: 0.25 | G83: Document Generation & Management | H83: 0.95 | J83: 0.68 | K83: 0.68 | L83: 0.65 | M83: 0.61 | N83: 0.58
A84: Financials | B84: Capital Markets / Investment Banking | C84: Human Resources | D84: 0.2 | E84: Recruitment administration | F84: 0.25 | G84: Task Processing / Query Handling | H84: 0.9 | I84: =SUMPRODUCT(H84:H87,F84:F87)*D84 -> 0.124 | J84: 0.48 | K84: 0.48 | L84: 0.45 | M84: 0.41 | N84: 0.38
A85: Financials | B85: Capital Markets / Investment Banking | C85: Human Resources | D85: 0.2 | E85: Workforce planning | F85: 0.25 | G85: Task Planning & Management | H85: 0.7 | J85: 0.48 | K85: 0.48 | L85: 0.45 | M85: 0.41 | N85: 0.38
A86: Financials | B86: Capital Markets / Investment Banking | C86: Human Resources | D86: 0.2 | E86: Employee relations & support | F86: 0.3 | G86: Stakeholder / Relationship Management | H86: 0.1 | J86: 0.48 | K86: 0.48 | L86: 0.45 | M86: 0.41 | N86: 0.38
A87: Financials | B87: Capital Markets / Investment Banking | C87: Human Resources | D87: 0.2 | E87: HR documentation & reporting | F87: 0.2 | G87: Document Generation & Management | H87: 0.95 | J87: 0.48 | K87: 0.48 | L87: 0.45 | M87: 0.41 | N87: 0.38
A88: Financials | B88: Capital Markets / Investment Banking | C88: Corporate IT & Enterprise Technology | D88: 0.2 | E88: IT service desk & user support | F88: 0.3 | G88: Task Processing / Query Handling | H88: 0.9 | I88: =SUMPRODUCT(H88:H91,F88:F91)*D88 -> 0.162 | J88: 0.68 | K88: 0.68 | L88: 0.65 | M88: 0.61 | N88: 0.58
A89: Financials | B89: Capital Markets / Investment Banking | C89: Corporate IT & Enterprise Technology | D89: 0.2 | E89: Application, infrastructure & security monitoring | F89: 0.25 | G89: Monitoring | H89: 0.7 | J89: 0.68 | K89: 0.68 | L89: 0.65 | M89: 0.61 | N89: 0.58
A90: Financials | B90: Capital Markets / Investment Banking | C90: Corporate IT & Enterprise Technology | D90: 0.2 | E90: Technology planning & change coordination | F90: 0.25 | G90: Task Planning & Management | H90: 0.7 | J90: 0.68 | K90: 0.68 | L90: 0.65 | M90: 0.61 | N90: 0.58
A91: Financials | B91: Capital Markets / Investment Banking | C91: Corporate IT & Enterprise Technology | D91: 0.2 | E91: IT documentation | F91: 0.2 | G91: Document Generation & Management | H91: 0.95 | J91: 0.68 | K91: 0.68 | L91: 0.65 | M91: 0.61 | N91: 0.58
A92: Financials | B92: Capital Markets / Investment Banking | C92: Legal, Regulatory & Corporate Administration | D92: 0.25 | E92: Regulatory / policy monitoring | F92: 0.25 | G92: Monitoring | H92: 0.7 | I92: =SUMPRODUCT(H92:H95,F92:F95)*D92 -> 0.146875 | J92: 0.45 | K92: 0.45 | L92: 0.42 | M92: 0.38 | N92: 0.35
A93: Financials | B93: Capital Markets / Investment Banking | C93: Legal, Regulatory & Corporate Administration | D93: 0.25 | E93: Contract & policy review | F93: 0.25 | G93: Assessment & Analysis | H93: 0.6 | J93: 0.45 | K93: 0.45 | L93: 0.42 | M93: 0.38 | N93: 0.35
A94: Financials | B94: Capital Markets / Investment Banking | C94: Legal, Regulatory & Corporate Administration | D94: 0.25 | E94: Regulator / legal stakeholder management | F94: 0.25 | G94: Stakeholder / Relationship Management | H94: 0.1 | J94: 0.45 | K94: 0.45 | L94: 0.42 | M94: 0.38 | N94: 0.35
A95: Financials | B95: Capital Markets / Investment Banking | C95: Legal, Regulatory & Corporate Administration | D95: 0.25 | E95: Compliance & corporate documentation | F95: 0.25 | G95: Document Generation & Management | H95: 0.95 | J95: 0.45 | K95: 0.45 | L95: 0.42 | M95: 0.38 | N95: 0.35
A96: Financials | B96: Capital Markets / Investment Banking | C96: Corporate Strategy & Management | D96: 0.15 | E96: Strategic planning | F96: 0.3 | G96: Strategy & Design | H96: 0.3 | I96: =SUMPRODUCT(H96:H99,F96:F99)*D96 -> 0.06825 | J96: 0.35 | K96: 0.35 | L96: 0.32 | M96: 0.28 | N96: 0.25
A97: Financials | B97: Capital Markets / Investment Banking | C97: Corporate Strategy & Management | D97: 0.15 | E97: Management / market analysis | F97: 0.25 | G97: Assessment & Analysis | H97: 0.6 | J97: 0.35 | K97: 0.35 | L97: 0.32 | M97: 0.28 | N97: 0.25
A98: Financials | B98: Capital Markets / Investment Banking | C98: Corporate Strategy & Management | D98: 0.15 | E98: Executive stakeholder coordination | F98: 0.25 | G98: Stakeholder / Relationship Management | H98: 0.1 | J98: 0.35 | K98: 0.35 | L98: 0.32 | M98: 0.28 | N98: 0.25
A99: Financials | B99: Capital Markets / Investment Banking | C99: Corporate Strategy & Management | D99: 0.15 | E99: Corporate reporting | F99: 0.2 | G99: Document Generation & Management | H99: 0.95 | J99: 0.35 | K99: 0.35 | L99: 0.32 | M99: 0.28 | N99: 0.25
I100: =SUM(I80:I98) -> 0.666625 | J100: =+J80*$D80+J84*$D84+J88*$D88+J92*$D92+J96*$D96+$D76*J76 -> 0.568 | K100: =+K80*$D80+K84*$D84+K88*$D88+K92*$D92+K96*$D96+$D76*K76 -> 0.568 | L100: =+L80*$D80+L84*$D84+L88*$D88+L92*$D92+L96*$D96+$D76*L76 -> 0.535 | M100: =+M80*$D80+M84*$D84+M88*$D88+M92*$D92+M96*$D96+$D76*M76 -> 0.491 | N100: =+N80*$D80+N84*$D84+N88*$D88+N92*$D92+N96*$D96+$D76*N76 -> 0.459
A102: Financials | B102: Insurance | C102: Marketing & Corporate Communications | D102: 0.15 | E102: Campaign & content development | F102: 0.3 | G102: Content Generation | H102: 0.7 | I102: =SUMPRODUCT(H102:H105,F102:F105)*D102 -> 0.06825 | J102: 0.36 | K102: 0.36 | L102: 0.32 | M102: 0.28 | N102: 0.28
A103: Financials | B103: Insurance | C103: Marketing & Corporate Communications | D103: 0.15 | E103: Customer / market analytics | F103: 0.25 | G103: Assessment & Analysis | H103: 0.6 | J103: 0.36 | K103: 0.36 | L103: 0.32 | M103: 0.28 | N103: 0.28
A104: Financials | B104: Insurance | C104: Marketing & Corporate Communications | D104: 0.15 | E104: Campaign / proposition planning | F104: 0.25 | G104: Strategy & Design | H104: 0.3 | J104: 0.36 | K104: 0.36 | L104: 0.32 | M104: 0.28 | N104: 0.28
...

Sheet CD
A1: Sector | B1: Subsector | C1: Core Activity | D1: Effort Split | E1: Key Main Task | F1: % Effort | G1: Category | H1: AI Addressable | I1: Agentification Potential | J1: Actual Agentification Possible | K1: NA | L1: EU | M1: APAC ex India | N1: India
A2: Consumer Discretionary | B2: Consumer Products Manufacturing | C2: Sales & Channel Management | D2: 0.25 | E2: Sales planning & account targeting | F2: 0.25 | G2: Task Planning & Management | H2: 0.7 | I2: =SUMPRODUCT(H2:H5,F2:F5)*D2 -> 0.13 | J2: 0.4 | K2: 0.4 | L2: 0.37 | M2: 0.33 | N2: 0.28
A3: Consumer Discretionary | B3: Consumer Products Manufacturing | C3: Sales & Channel Management | D3: 0.25 | E3: Retailer / distributor relationship management | F3: 0.35 | G3: Stakeholder / Relationship Management | H3: 0.1 | J3: 0.4 | K3: 0.4 | L3: 0.37 | M3: 0.33 | N3: 0.28
A4: Consumer Discretionary | B4: Consumer Products Manufacturing | C4: Sales & Channel Management | D4: 0.25 | E4: Pricing & account analytics | F4: 0.2 | G4: Assessment & Analysis | H4: 0.6 | J4: 0.4 | K4: 0.4 | L4: 0.37 | M4: 0.33 | N4: 0.28
A5: Consumer Discretionary | B5: Consumer Products Manufacturing | C5: Sales & Channel Management | D5: 0.25 | E5: Sales administration & reporting | F5: 0.2 | G5: Document Generation & Management | H5: 0.95 | J5: 0.4 | K5: 0.4 | L5: 0.37 | M5: 0.33 | N5: 0.28
A6: Consumer Discretionary | B6: Consumer Products Manufacturing | C6: Marketing & Brand Management | D6: 0.2 | E6: Campaign & content development | F6: 0.3 | G6: Content Generation | H6: 0.7 | I6: =SUMPRODUCT(H6:H9,F6:F9)*D6 -> 0.091 | J6: 0.35 | K6: 0.35 | L6: 0.32 | M6: 0.28 | N6: 0.2
A7: Consumer Discretionary | B7: Consumer Products Manufacturing | C7: Marketing & Brand Management | D7: 0.2 | E7: Consumer & market analytics | F7: 0.25 | G7: Assessment & Analysis | H7: 0.6 | J7: 0.35 | K7: 0.35 | L7: 0.32 | M7: 0.28 | N7: 0.2
A8: Consumer Discretionary | B8: Consumer Products Manufacturing | C8: Marketing & Brand Management | D8: 0.2 | E8: Brand & campaign planning | F8: 0.25 | G8: Strategy & Design | H8: 0.3 | J8: 0.35 | K8: 0.35 | L8: 0.32 | M8: 0.28 | N8: 0.2
A9: Consumer Discretionary | B9: Consumer Products Manufacturing | C9: Marketing & Brand Management | D9: 0.2 | E9: Agency / stakeholder coordination | F9: 0.2 | G9: Stakeholder / Relationship Management | H9: 0.1 | J9: 0.35 | K9: 0.35 | L9: 0.32 | M9: 0.28 | N9: 0.2
A10: Consumer Discretionary | B10: Consumer Products Manufacturing | C10: Finance & Accounting | D10: 0.2 | E10: Transaction processing & reconciliation | F10: 0.3 | G10: Task Processing / Query Handling | H10: 0.9 | I10: =SUMPRODUCT(H10:H13,F10:F13)*D10 -> 0.1655 | J10: 0.65 | K10: 0.65 | L10: 0.6 | M10: 0.54 | N10: 0.42
A11: Consumer Discretionary | B11: Consumer Products Manufacturing | C11: Finance & Accounting | D11: 0.2 | E11: Financial planning & analysis | F11: 0.25 | G11: Assessment & Analysis | H11: 0.6 | J11: 0.65 | K11: 0.65 | L11: 0.6 | M11: 0.54 | N11: 0.42
A12: Consumer Discretionary | B12: Consumer Products Manufacturing | C12: Finance & Accounting | D12: 0.2 | E12: Budgeting & forecasting | F12: 0.2 | G12: Modelling (incl. Forecasting) | H12: 0.85 | J12: 0.65 | K12: 0.65 | L12: 0.6 | M12: 0.54 | N12: 0.42
A13: Consumer Discretionary | B13: Consumer Products Manufacturing | C13: Finance & Accounting | D13: 0.2 | E13: Financial reporting | F13: 0.25 | G13: Document Generation & Management | H13: 0.95 | J13: 0.65 | K13: 0.65 | L13: 0.6 | M13: 0.54 | N13: 0.42
A14: Consumer Discretionary | B14: Consumer Products Manufacturing | C14: Human Resources | D14: 0.1 | E14: Recruitment administration | F14: 0.25 | G14: Task Processing / Query Handling | H14: 0.9 | I14: =SUMPRODUCT(H14:H17,F14:F17)*D14 -> 0.062 | J14: 0.45 | K14: 0.45 | L14: 0.42 | M14: 0.37 | N14: 0.28
A15: Consumer Discretionary | B15: Consumer Products Manufacturing | C15: Human Resources | D15: 0.1 | E15: Workforce planning | F15: 0.25 | G15: Task Planning & Management | H15: 0.7 | J15: 0.45 | K15: 0.45 | L15: 0.42 | M15: 0.37 | N15: 0.28
A16: Consumer Discretionary | B16: Consumer Products Manufacturing | C16: Human Resources | D16: 0.1 | E16: Employee relations & support | F16: 0.3 | G16: Stakeholder / Relationship Management | H16: 0.1 | J16: 0.45 | K16: 0.45 | L16: 0.42 | M16: 0.37 | N16: 0.28
A17: Consumer Discretionary | B17: Consumer Products Manufacturing | C17: Human Resources | D17: 0.1 | E17: HR documentation & reporting | F17: 0.2 | G17: Document Generation & Management | H17: 0.95 | J17: 0.45 | K17: 0.45 | L17: 0.42 | M17: 0.37 | N17: 0.28
A18: Consumer Discretionary | B18: Consumer Products Manufacturing | C18: Corporate IT & Enterprise Technology | D18: 0.1 | E18: IT service desk & user support | F18: 0.3 | G18: Task Processing / Query Handling | H18: 0.9 | I18: =SUMPRODUCT(H18:H21,F18:F21)*D18 -> 0.081 | J18: 0.65 | K18: 0.65 | L18: 0.61 | M18: 0.55 | N18: 0.43
A19: Consumer Discretionary | B19: Consumer Products Manufacturing | C19: Corporate IT & Enterprise Technology | D19: 0.1 | E19: Application & infrastructure monitoring | F19: 0.25 | G19: Monitoring | H19: 0.7 | J19: 0.65 | K19: 0.65 | L19: 0.61 | M19: 0.55 | N19: 0.43
A20: Consumer Discretionary | B20: Consumer Products Manufacturing | C20: Corporate IT & Enterprise Technology | D20: 0.1 | E20: Technology planning & change coordination | F20: 0.25 | G20: Task Planning & Management | H20: 0.7 | J20: 0.65 | K20: 0.65 | L20: 0.61 | M20: 0.55 | N20: 0.43
A21: Consumer Discretionary | B21: Consumer Products Manufacturing | C21: Corporate IT & Enterprise Technology | D21: 0.1 | E21: IT documentation | F21: 0.2 | G21: Document Generation & Management | H21: 0.95 | J21: 0.65 | K21: 0.65 | L21: 0.61 | M21: 0.55 | N21: 0.43
A22: Consumer Discretionary | B22: Consumer Products Manufacturing | C22: Legal & Corporate Administration | D22: 0.15 | E22: Compliance / policy monitoring | F22: 0.25 | G22: Monitoring | H22: 0.7 | I22: =SUMPRODUCT(H22:H25,F22:F25)*D22 -> 0.088125 | J22: 0.42 | K22: 0.42 | L22: 0.39 | M22: 0.34 | N22: 0.25
A23: Consumer Discretionary | B23: Consumer Products Manufacturing | C23: Legal & Corporate Administration | D23: 0.15 | E23: Contract & policy review | F23: 0.25 | G23: Assessment & Analysis | H23: 0.6 | J23: 0.42 | K23: 0.42 | L23: 0.39 | M23: 0.34 | N23: 0.25
A24: Consumer Discretionary | B24: Consumer Products Manufacturing | C24: Legal & Corporate Administration | D24: 0.15 | E24: Legal / external stakeholder management | F24: 0.25 | G24: Stakeholder / Relationship Management | H24: 0.1 | J24: 0.42 | K24: 0.42 | L24: 0.39 | M24: 0.34 | N24: 0.25
A25: Consumer Discretionary | B25: Consumer Products Manufacturing | C25: Legal & Corporate Administration | D25: 0.15 | E25: Legal & compliance documentation | F25: 0.25 | G25: Document Generation & Management | H25: 0.95 | J25: 0.42 | K25: 0.42 | L25: 0.39 | M25: 0.34 | N25: 0.25
I26: =SUM(I2:I25) -> 0.617625 | J26: =+J6*$D6+J10*$D10+J14*$D14+J18*$D18+J22*$D22+$D2*J2 -> 0.473 | K26: =+K6*$D6+K10*$D10+K14*$D14+K18*$D18+K22*$D22+$D2*K2 -> 0.473 | L26: =+L6*$D6+L10*$D10+L14*$D14+L18*$D18+L22*$D22+$D2*L2 -> 0.438 | M26: =+M6*$D6+M10*$D10+M14*$D14+M18*$D18+M22*$D22+$D2*M2 -> 0.3895 | N26: =+N6*$D6+N10*$D10+N14*$D14+N18*$D18+N22*$D22+$D2*N2 -> 0.3025
A28: Consumer Discretionary | B28: Automotive | C28: Sales & Dealer Management | D28: 0.25 | E28: Sales & demand planning | F28: 0.25 | G28: Task Planning & Management | H28: 0.7 | I28: =SUMPRODUCT(H28:H31,F28:F31)*D28 -> 0.13 | J28: 0.4 | K28: 0.4 | L28: 0.37 | M28: 0.33 | N28: 0.27
A29: Consumer Discretionary | B29: Automotive | C29: Sales & Dealer Management | D29: 0.25 | E29: Dealer / fleet relationship management | F29: 0.35 | G29: Stakeholder / Relationship Management | H29: 0.1 | J29: 0.4 | K29: 0.4 | L29: 0.37 | M29: 0.33 | N29: 0.27
A30: Consumer Discretionary | B30: Automotive | C30: Sales & Dealer Management | D30: 0.25 | E30: Pricing & dealer performance analytics | F30: 0.2 | G30: Assessment & Analysis | H30: 0.6 | J30: 0.4 | K30: 0.4 | L30: 0.37 | M30: 0.33 | N30: 0.27
A31: Consumer Discretionary | B31: Automotive | C31: Sales & Dealer Management | D31: 0.25 | E31: Sales administration & reporting | F31: 0.2 | G31: Document Generation & Management | H31: 0.95 | J31: 0.4 | K31: 0.4 | L31: 0.37 | M31: 0.33 | N31: 0.27
A32: Consumer Discretionary | B32: Automotive | C32: Marketing & Customer Growth | D32: 0.15 | E32: Campaign & content development | F32: 0.3 | G32: Content Generation | H32: 0.7 | I32: =SUMPRODUCT(H32:H35,F32:F35)*D32 -> 0.06825 | J32: 0.35 | K32: 0.35 | L32: 0.32 | M32: 0.28 | N32: 0.2
A33: Consumer Discretionary | B33: Automotive | C33: Marketing & Customer Growth | D33: 0.15 | E33: Customer / market analytics | F33: 0.25 | G33: Assessment & Analysis | H33: 0.6 | J33: 0.35 | K33: 0.35 | L33: 0.32 | M33: 0.28 | N33: 0.2
A34: Consumer Discretionary | B34: Automotive | C34: Marketing & Customer Growth | D34: 0.15 | E34: Brand & campaign planning | F34: 0.25 | G34: Strategy & Design | H34: 0.3 | J34: 0.35 | K34: 0.35 | L34: 0.32 | M34: 0.28 | N34: 0.2
A35: Consumer Discretionary | B35: Automotive | C35: Marketing & Customer Growth | D35: 0.15 | E35: Agency / dealer coordination | F35: 0.2 | G35: Stakeholder / Relationship Management | H35: 0.1 | J35: 0.35 | K35: 0.35 | L35: 0.32 | M35: 0.28 | N35: 0.2
A36: Consumer Discretionary | B36: Automotive | C36: Finance & Accounting | D36: 0.2 | E36: Transaction processing & reconciliation | F36: 0.3 | G36: Task Processing / Query Handling | H36: 0.9 | I36: =SUMPRODUCT(H36:H39,F36:F39)*D36 -> 0.1655 | J36: 0.65 | K36: 0.65 | L36: 0.6 | M36: 0.54 | N36: 0.43
A37: Consumer Discretionary | B37: Automotive | C37: Finance & Accounting | D37: 0.2 | E37: Financial planning & analysis | F37: 0.25 | G37: Assessment & Analysis | H37: 0.6 | J37: 0.65 | K37: 0.65 | L37: 0.6 | M37: 0.54 | N37: 0.43
A38: Consumer Discretionary | B38: Automotive | C38: Finance & Accounting | D38: 0.2 | E38: Budgeting & forecasting | F38: 0.2 | G38: Modelling (incl. Forecasting) | H38: 0.85 | J38: 0.65 | K38: 0.65 | L38: 0.6 | M38: 0.54 | N38: 0.43
A39: Consumer Discretionary | B39: Automotive | C39: Finance & Accounting | D39: 0.2 | E39: Financial reporting | F39: 0.25 | G39: Document Generation & Management | H39: 0.95 | J39: 0.65 | K39: 0.65 | L39: 0.6 | M39: 0.54 | N39: 0.43
A40: Consumer Discretionary | B40: Automotive | C40: Human Resources | D40: 0.15 | E40: Recruitment administration | F40: 0.25 | G40: Task Processing / Query Handling | H40: 0.9 | I40: =SUMPRODUCT(H40:H43,F40:F43)*D40 -> 0.093 | J40: 0.45 | K40: 0.45 | L40: 0.42 | M40: 0.37 | N40: 0.29
A41: Consumer Discretionary | B41: Automotive | C41: Human Resources | D41: 0.15 | E41: Workforce planning | F41: 0.25 | G41: Task Planning & Management | H41: 0.7 | J41: 0.45 | K41: 0.45 | L41: 0.42 | M41: 0.37 | N41: 0.29
A42: Consumer Discretionary | B42: Automotive | C42: Human Resources | D42: 0.15 | E42: Employee / labour relations | F42: 0.3 | G42: Stakeholder / Relationship Management | H42: 0.1 | J42: 0.45 | K42: 0.45 | L42: 0.42 | M42: 0.37 | N42: 0.29
A43: Consumer Discretionary | B43: Automotive | C43: Human Resources | D43: 0.15 | E43: HR documentation & reporting | F43: 0.2 | G43: Document Generation & Management | H43: 0.95 | J43: 0.45 | K43: 0.45 | L43: 0.42 | M43: 0.37 | N43: 0.29
A44: Consumer Discretionary | B44: Automotive | C44: Corporate IT & Enterprise Technology | D44: 0.1 | E44: IT service desk & user support | F44: 0.3 | G44: Task Processing / Query Handling | H44: 0.9 | I44: =SUMPRODUCT(H44:H47,F44:F47)*D44 -> 0.081 | J44: 0.65 | K44: 0.65 | L44: 0.61 | M44: 0.55 | N44: 0.44
A45: Consumer Discretionary | B45: Automotive | C45: Corporate IT & Enterprise Technology | D45: 0.1 | E45: Application & infrastructure monitoring | F45: 0.25 | G45: Monitoring | H45: 0.7 | J45: 0.65 | K45: 0.65 | L45: 0.61 | M45: 0.55 | N45: 0.44
A46: Consumer Discretionary | B46: Automotive | C46: Corporate IT & Enterprise Technology | D46: 0.1 | E46: Technology planning & change coordination | F46: 0.25 | G46: Task Planning & Management | H46: 0.7 | J46: 0.65 | K46: 0.65 | L46: 0.61 | M46: 0.55 | N46: 0.44
A47: Consumer Discretionary | B47: Automotive | C47: Corporate IT & Enterprise Technology | D47: 0.1 | E47: IT documentation | F47: 0.2 | G47: Document Generation & Management | H47: 0.95 | J47: 0.65 | K47: 0.65 | L47: 0.61 | M47: 0.55 | N47: 0.44
A48: Consumer Discretionary | B48: Automotive | C48: Legal, Regulatory & Corporate Administration | D48: 0.15 | E48: Regulatory / compliance monitoring | F48: 0.25 | G48: Monitoring | H48: 0.7 | I48: =SUMPRODUCT(H48:H51,F48:F51)*D48 -> 0.088125 | J48: 0.42 | K48: 0.42 | L48: 0.39 | M48: 0.34 | N48: 0.26
A49: Consumer Discretionary | B49: Automotive | C49: Legal, Regulatory & Corporate Administration | D49: 0.15 | E49: Contract / policy review | F49: 0.25 | G49: Assessment & Analysis | H49: 0.6 | J49: 0.42 | K49: 0.42 | L49: 0.39 | M49: 0.34 | N49: 0.26
A50: Consumer Discretionary | B50: Automotive | C50: Legal, Regulatory & Corporate Administration | D50: 0.15 | E50: Regulator / legal stakeholder management | F50: 0.25 | G50: Stakeholder / Relationship Management | H50: 0.1 | J50: 0.42 | K50: 0.42 | L50: 0.39 | M50: 0.34 | N50: 0.26
A51: Consumer Discretionary | B51: Automotive | C51: Legal, Regulatory & Corporate Administration | D51: 0.15 | E51: Compliance documentation | F51: 0.25 | G51: Document Generation & Management | H51: 0.95 | J51: 0.42 | K51: 0.42 | L51: 0.39 | M51: 0.34 | N51: 0.26
I52: =SUM(I28:I51) -> 0.625875 | J52: =+J32*$D32+J36*$D36+J40*$D40+J44*$D44+J48*$D48+$D28*J28 -> 0.478 | K52: =+K32*$D32+K36*$D36+K40*$D40+K44*$D44+K48*$D48+$D28*K28 -> 0.478 | L52: =+L32*$D32+L36*$D36+L40*$D40+L44*$D44+L48*$D48+$D28*L28 -> 0.443 | M52: =+M32*$D32+M36*$D36+M40*$D40+M44*$D44+M48*$D48+$D28*M28 -> 0.394 | N52: =+N32*$D32+N36*$D36+N40*$D40+N44*$D44+N48*$D48+$D28*N28 -> 0.31
A54: Consumer Discretionary | B54: Homebuilding & Home Products | C54: Sales & Channel Management | D54: 0.3 | E54: Sales / project targeting | F54: 0.25 | G54: Task Planning & Management | H54: 0.7 | I54: =SUMPRODUCT(H54:H57,F54:F57)*D54 -> 0.156 | J54: 0.38 | K54: 0.38 | L54: 0.35 | M54: 0.31 | N54: 0.24
A55: Consumer Discretionary | B55: Homebuilding & Home Products | C55: Sales & Channel Management | D55: 0.3 | E55: Dealer / broker / customer relationships | F55: 0.35 | G55: Stakeholder / Relationship Management | H55: 0.1 | J55: 0.38 | K55: 0.38 | L55: 0.35 | M55: 0.31 | N55: 0.24
A56: Consumer Discretionary | B56: Homebuilding & Home Products | C56: Sales & Channel Management | D56: 0.3 | E56: Pricing & sales analytics | F56: 0.2 | G56: Assessment & Analysis | H56: 0.6 | J56: 0.38 | K56: 0.38 | L56: 0.35 | M56: 0.31 | N56: 0.24
A57: Consumer Discretionary | B57: Homebuilding & Home Products | C57: Sales & Channel Management | D57: 0.3 | E57: Sales administration & reporting | F57: 0.2 | G57: Document Generation & Management | H57: 0.95 | J57: 0.38 | K57: 0.38 | L57: 0.35 | M57: 0.31 | N57: 0.24
A58: Consumer Discretionary | B58: Homebuilding & Home Products | C58: Marketing & Customer Acquisition | D58: 0.15 | E58: Campaign / listing content development | F58: 0.3 | G58: Content Generation | H58: 0.7 | I58: =SUMPRODUCT(H58:H61,F58:F61)*D58 -> 0.06825 | J58: 0.33 | K58: 0.33 | L58: 0.3 | M58: 0.26 | N58: 0.19
A59: Consumer Discretionary | B59: Homebuilding & Home Products | C59: Marketing & Customer Acquisition | D59: 0.15 | E59: Customer & market analytics | F59: 0.25 | G59: Assessment & Analysis | H59: 0.6 | J59: 0.33 | K59: 0.33 | L59: 0.3 | M59: 0.26 | N59: 0.19
A60: Consumer Discretionary | B60: Homebuilding & Home Products | C60: Marketing & Customer Acquisition | D60: 0.15 | E60: Campaign / market planning | F60: 0.25 | G60: Strategy & Design | H60: 0.3 | J60: 0.33 | K60: 0.33 | L60: 0.3 | M60: 0.26 | N60: 0.19
A61: Consumer Discretionary | B61: Homebuilding & Home Products | C61: Marketing & Customer Acquisition | D61: 0.15 | E61: Agency / channel coordination | F61: 0.2 | G61: Stakeholder / Relationship Management | H61: 0.1 | J61: 0.33 | K61: 0.33 | L61: 0.3 | M61: 0.26 | N61: 0.19
A62: Consumer Discretionary | B62: Homebuilding & Home Products | C62: Finance & Accounting | D62: 0.2 | E62: Transaction processing & reconciliation | F62: 0.3 | G62: Task Processing / Query Handling | H62: 0.9 | I62: =SUMPRODUCT(H62:H65,F62:F65)*D62 -> 0.1655 | J62: 0.62 | K62: 0.62 | L62: 0.57 | M62: 0.51 | N62: 0.39
A63: Consumer Discretionary | B63: Homebuilding & Home Products | C63: Finance & Accounting | D63: 0.2 | E63: Financial planning & analysis | F63: 0.25 | G63: Assessment & Analysis | H63: 0.6 | J63: 0.62 | K63: 0.62 | L63: 0.57 | M63: 0.51 | N63: 0.39
A64: Consumer Discretionary | B64: Homebuilding & Home Products | C64: Finance & Accounting | D64: 0.2 | E64: Budgeting & forecasting | F64: 0.2 | G64: Modelling (incl. Forecasting) | H64: 0.85 | J64: 0.62 | K64: 0.62 | L64: 0.57 | M64: 0.51 | N64: 0.39
A65: Consumer Discretionary | B65: Homebuilding & Home Products | C65: Finance & Accounting | D65: 0.2 | E65: Financial reporting | F65: 0.25 | G65: Document Generation & Management | H65: 0.95 | J65: 0.62 | K65: 0.62 | L65: 0.57 | M65: 0.51 | N65: 0.39
A66: Consumer Discretionary | B66: Homebuilding & Home Products | C66: Human Resources | D66: 0.1 | E66: Recruitment administration | F66: 0.25 | G66: Task Processing / Query Handling | H66: 0.9 | I66: =SUMPRODUCT(H66:H69,F66:F69)*D66 -> 0.062 | J66: 0.43 | K66: 0.43 | L66: 0.4 | M66: 0.35 | N66: 0.26
A67: Consumer Discretionary | B67: Homebuilding & Home Products | C67: Human Resources | D67: 0.1 | E67: Workforce planning | F67: 0.25 | G67: Task Planning & Management | H67: 0.7 | J67: 0.43 | K67: 0.43 | L67: 0.4 | M67: 0.35 | N67: 0.26
A68: Consumer Discretionary | B68: Homebuilding & Home Products | C68: Human Resources | D68: 0.1 | E68: Employee relations & support | F68: 0.3 | G68: Stakeholder / Relationship Management | H68: 0.1 | J68: 0.43 | K68: 0.43 | L68: 0.4 | M68: 0.35 | N68: 0.26
A69: Consumer Discretionary | B69: Homebuilding & Home Products | C69: Human Resources | D69: 0.1 | E69: HR documentation & reporting | F69: 0.2 | G69: Document Generation & Management | H69: 0.95 | J69: 0.43 | K69: 0.43 | L69: 0.4 | M69: 0.35 | N69: 0.26
A70: Consumer Discretionary | B70: Homebuilding & Home Products | C70: Corporate IT & Enterprise Technology | D70: 0.1 | E70: IT service desk & user support | F70: 0.3 | G70: Task Processing / Query Handling | H70: 0.9 | I70: =SUMPRODUCT(H70:H73,F70:F73)*D70 -> 0.081 | J70: 0.62 | K70: 0.62 | L70: 0.58 | M70: 0.52 | N70: 0.4
A71: Consumer Discretionary | B71: Homebuilding & Home Products | C71: Corporate IT & Enterprise Technology | D71: 0.1 | E71: Application & infrastructure monitoring | F71: 0.25 | G71: Monitoring | H71: 0.7 | J71: 0.62 | K71: 0.62 | L71: 0.58 | M71: 0.52 | N71: 0.4
A72: Consumer Discretionary | B72: Homebuilding & Home Products | C72: Corporate IT & Enterprise Technology | D72: 0.1 | E72: Technology planning & coordination | F72: 0.25 | G72: Task Planning & Management | H72: 0.7 | J72: 0.62 | K72: 0.62 | L72: 0.58 | M72: 0.52 | N72: 0.4
A73: Consumer Discretionary | B73: Homebuilding & Home Products | C73: Corporate IT & Enterprise Technology | D73: 0.1 | E73: IT documentation | F73: 0.2 | G73: Document Generation & Management | H73: 0.95 | J73: 0.62 | K73: 0.62 | L73: 0.58 | M73: 0.52 | N73: 0.4
A74: Consumer Discretionary | B74: Homebuilding & Home Products | C74: Legal & Corporate Administration | D74: 0.15 | E74: Compliance / policy monitoring | F74: 0.25 | G74: Monitoring | H74: 0.7 | I74: =SUMPRODUCT(H74:H77,F74:F77)*D74 -> 0.090375 | J74: 0.4 | K74: 0.4 | L74: 0.37 | M74: 0.32 | N74: 0.24
A75: Consumer Discretionary | B75: Homebuilding & Home Products | C75: Legal & Corporate Administration | D75: 0.15 | E75: Contract & policy review | F75: 0.25 | G75: Assessment & Analysis | H75: 0.6 | J75: 0.4 | K75: 0.4 | L75: 0.37 | M75: 0.32 | N75: 0.24
A76: Consumer Discretionary | B76: Homebuilding & Home Products | C76: Legal & external stakeholder coordination | D76: 0.25 | E76: Stakeholder / Relationship Management | F76: 0.1 | G76: 0.59 | H76: 0.4 | J76: 0.37 | K76: 0.32 | L76: 0.24
A77: Consumer Discretionary | B77: Homebuilding & Home Products | C77: Legal & Corporate Administration | D77: 0.15 | E77: Legal & compliance documentation | F77: 0.25 | G77: Document Generation & Management | H77: 0.95 | J77: 0.4 | K77: 0.4 | L77: 0.37 | M77: 0.32 | N77: 0.24
I78: =SUM(I54:I77) -> 0.623125 | J78: =+J58*$D58+J62*$D62+J66*$D66+J70*$D70+J74*$D74+$D54*J54 -> 0.4525 | K78: =+K58*$D58+K62*$D62+K66*$D66+K70*$D70+K74*$D74+$D54*K54 -> 0.4525 | L78: =+L58*$D58+L62*$D62+L66*$D66+L70*$D70+L74*$D74+$D54*L54 -> 0.4175 | M78: =+M58*$D58+M62*$D62+M66*$D66+M70*$D70+M74*$D74+$D54*M54 -> 0.369 | N78: =+N58*$D58+N62*$D62+N66*$D66+N70*$D70+N74*$D74+$D54*N54 -> 0.2805
A80: Consumer Discretionary | B80: Consumer Services | C80: Customer & Member Operations | D80: 0.3 | E80: Customer queries & service requests | F80: 0.35 | G80: Task Processing / Query Handling | H80: 0.9 | I80: =SUMPRODUCT(H80:H83,F80:F83)*D80 -> 0.255 | J80: 0.65 | K80: 0.65 | L80: 0.6 | M80: 0.53 | N80: 0.4
A81: Consumer Discretionary | B81: Consumer Services | C81: Customer & Member Operations | D81: 0.3 | E81: Account / booking administration | F81: 0.25 | G81: Task Processing / Query Handling | H81: 0.9 | J81: 0.65 | K81: 0.65 | L81: 0.6 | M81: 0.53 | N81: 0.4
A82: Consumer Discretionary | B82: Consumer Services | C82: Customer & Member Operations | D82: 0.3 | E82: Customer issue assessment | F82: 0.2 | G82: Assessment & Analysis | H82: 0.6 | J82: 0.65 | K82: 0.65 | L82: 0.6 | M82: 0.53 | N82: 0.4
A83: Consumer Discretionary | B83: Consumer Services | C83: Customer & Member Operations | D83: 0.3 | E83: Customer communications & documentation | F83: 0.2 | G83: Document Generation & Management | H83: 0.95 | J83: 0.65 | K83: 0.65 | L83: 0.6 | M83: 0.53 | N83: 0.4
A84: Consumer Discretionary | B84: Consumer Services | C84: Sales & Marketing | D84: 0.2 | E84: Sales / customer targeting | F84: 0.25 | G84: Task Planning & Management | H84: 0.7 | I84: =SUMPRODUCT(H84:H87,F84:F87)*D84 -> 0.094 | J84: 0.38 | K84: 0.38 | L84: 0.35 | M84: 0.3 | N84: 0.22
A85: Consumer Discretionary | B85: Consumer Services | C85: Sales & Marketing | D85: 0.2 | E85: Customer / partner relationship management | F85: 0.35 | G85: Stakeholder / Relationship Management | H85: 0.1 | J85: 0.38 | K85: 0.38 | L85: 0.35 | M85: 0.3 | N85: 0.22
A86: Consumer Discretionary | B86: Consumer Services | C86: Sales & Marketing | D86: 0.2 | E86: Customer & campaign analytics | F86: 0.2 | G86: Assessment & Analysis | H86: 0.6 | J86: 0.38 | K86: 0.38 | L86: 0.35 | M86: 0.3 | N86: 0.22
A87: Consumer Discretionary | B87: Consumer Services | C87: Sales & Marketing | D87: 0.2 | E87: Marketing content & reporting | F87: 0.2 | G87: Content Generation | H87: 0.7 | J87: 0.38 | K87: 0.38 | L87: 0.35 | M87: 0.3 | N87: 0.22
A88: Consumer Discretionary | B88: Consumer Services | C88: Finance & Accounting | D88: 0.2 | E88: Transaction processing & reconciliation | F88: 0.3 | G88: Task Processing / Query Handling | H88: 0.9 | I88: =SUMPRODUCT(H88:H91,F88:F91)*D88 -> 0.1655 | J88: 0.62 | K88: 0.62 | L88: 0.57 | M88: 0.5 | N88: 0.38
A89: Consumer Discretionary | B89: Consumer Services | C89: Finance & Accounting | D89: 0.2 | E89: Financial planning & analysis | F89: 0.25 | G89: Assessment & Analysis | H89: 0.6 | J89: 0.62 | K89: 0.62 | L89: 0.57 | M89: 0.5 | N89: 0.38
A90: Consumer Discretionary | B90: Consumer Services | C90: Finance & Accounting | D90: 0.2 | E90: Budgeting & forecasting | F90: 0.2 | G90: Modelling (incl. Forecasting) | H90: 0.85 | J90: 0.62 | K90: 0.62 | L90: 0.57 | M90: 0.5 | N90: 0.38
A91: Consumer Discretionary | B91: Consumer Services | C91: Finance & Accounting | D91: 0.2 | E91: Financial reporting | F91: 0.25 | G91: Document Generation & Management | H91: 0.95 | J91: 0.62 | K91: 0.62 | L91: 0.57 | M91: 0.5 | N91: 0.38
A92: Consumer Discretionary | B92: Consumer Services | C92: Human Resources | D92: 0.15 | E92: Recruitment administration | F92: 0.25 | G92: Task Processing / Query Handling | H92: 0.9 | I92: =SUMPRODUCT(H92:H95,F92:F95)*D92 -> 0.093 | J92: 0.43 | K92: 0.43 | L92: 0.4 | M92: 0.35 | N92: 0.25
A93: Consumer Discretionary | B93: Consumer Services | C93: Human Resources | D93: 0.15 | E93: Workforce planning | F93: 0.25 | G93: Task Planning & Management | H93: 0.7 | J93: 0.43 | K93: 0.43 | L93: 0.4 | M93: 0.35 | N93: 0.25
A94: Consumer Discretionary | B94: Consumer Services | C94: Human Resources | D94: 0.15 | E94: Employee relations & support | F94: 0.3 | G94: Stakeholder / Relationship Management | H94: 0.1 | J94: 0.43 | K94: 0.43 | L94: 0.4 | M94: 0.35 | N94: 0.25
A95: Consumer Discretionary | B95: Consumer Services | C95: Human Resources | D95: 0.15 | E95: HR documentation & reporting | F95: 0.2 | G95: Document Generation & Management | H95: 0.95 | J95: 0.43 | K95: 0.43 | L95: 0.4 | M95: 0.35 | N95: 0.25
A96: Consumer Discretionary | B96: Consumer Services | C96: Corporate IT & Administration | D96: 0.15 | E96: IT support & user services | F96: 0.3 | G96: Task Processing / Query Handling | H96: 0.9 | I96: =SUMPRODUCT(H96:H99,F96:F99)*D96 -> 0.1215 | J96: 0.62 | K96: 0.62 | L96: 0.58 | M96: 0.51 | N96: 0.39
A97: Consumer Discretionary | B97: Consumer Services | C97: Corporate IT & Administration | D97: 0.15 | E97: System monitoring | F97: 0.25 | G97: Monitoring | H97: 0.7 | J97: 0.62 | K97: 0.62 | L97: 0.58 | M97: 0.51 | N97: 0.39
A98: Consumer Discretionary | B98: Consumer Services | C98: Corporate IT & Administration | D98: 0.15 | E98: Technology / corporate planning | F98: 0.25 | G98: Task Planning & Management | H98: 0.7 | J98: 0.62 | K98: 0.62 | L98: 0.58 | M98: 0.51 | N98: 0.39
A99: Consumer Discretionary | B99: Consumer Services | C99: Corporate IT & Administration | D99: 0.15 | E99: IT / corporate documentation | F99: 0.2 | G99: Document Generation & Management | H99: 0.95 | J99: 0.62 | K99: 0.62 | L99: 0.58 | M99: 0.51 | N99: 0.39
I100: =SUM(I80:I96) -> 0.729 | J100: =+J80*$D80+J84*$D84+J88*$D88+J92*$D92+J96*$D96 -> 0.5525 | K100: =+K80*$D80+K84*$D84+K88*$D88+K92*$D92+K96*$D96 -> 0.5525 | L100: =+L80*$D80+L84*$D84+L88*$D88+L92*$D92+L96*$D96 -> 0.511 | M100: =+M80*$D80+M84*$D84+M88*$D88+M92*$D92+M96*$D96 -> 0.448 | N100: =+N80*$D80+N84*$D84+N88*$D88+N92*$D92+N96*$D96 -> 0.336
A102: Consumer Discretionary | B102: Travel & Leisure | C102: Customer, Booking & Loyalty Operations | D102: 0.3 | E102: Booking / customer query processing | F102: 0.35 | G102: Task Processing / Query Handling | H102: 0.9 | I102: =SUMPRODUCT(H102:H105,F102:F105)*D102 -> 0.255 | J102: 0.68 | K102: 0.68 | L102: 0.63 | M102: 0.57 | N102: 0.47
A103: Consumer Discretionary | B103: Travel & Leisure | C103: Customer, Booking & Loyalty Operations | D103: 0.3 | E103: Booking changes & account administration | F103: 0.25 | G103: Task Processing / Query Handling | H103: 0.9 | J103: 0.68 | K103: 0.68 | L103: 0.63 | M103: 0.57 | N103: 0.47
A104: Consumer Discretionary | B104: Travel & Leisure | C104: Customer, Booking & Loyalty Operations | D104: 0.3 | E104: Service disruption / issue assessment | F104: 0.2 | G104: Assessment & Analysis | H104: 0.6 | J104: 0.68 | K104: 0.68 | L104: 0.63 | M104: 0.57 | N104: 0.47
...

Sheet Energy
A1: Sector | B1: Subsector | C1: Core Activity | D1: Effort Split | E1: Key Main Task | F1: % Effort | G1: Category | H1: AI Addressable | I1: Agentification Potential | J1: Actual Agentification Possible | K1: NA | L1: EU | M1: APAC ex India | N1: India
A2: Energy | B2: Upstream Oil & Gas | C2: Finance & Accounting | D2: 0.2 | E2: Transaction processing & reconciliation | F2: 0.3 | G2: Task Processing / Query Handling | H2: 0.9 | I2: =SUMPRODUCT(H2:H5,F2:F5)*D2 -> 0.1655 | J2: 0.66 | K2: 0.66 | L2: 0.63 | M2: 0.58 | N2: 0.55
A3: Energy | B3: Upstream Oil & Gas | C3: Finance & Accounting | D3: 0.2 | E3: Financial planning & analysis | F3: 0.25 | G3: Assessment & Analysis | H3: 0.6 | J3: 0.66 | K3: 0.66 | L3: 0.63 | M3: 0.58 | N3: 0.55
A4: Energy | B4: Upstream Oil & Gas | C4: Finance & Accounting | D4: 0.2 | E4: Budgeting & forecasting | F4: 0.2 | G4: Modelling (incl. Forecasting) | H4: 0.85 | J4: 0.66 | K4: 0.66 | L4: 0.63 | M4: 0.58 | N4: 0.55
A5: Energy | B5: Upstream Oil & Gas | C5: Finance & Accounting | D5: 0.2 | E5: Financial reporting | F5: 0.25 | G5: Document Generation & Management | H5: 0.95 | J5: 0.66 | K5: 0.66 | L5: 0.63 | M5: 0.58 | N5: 0.55
A6: Energy | B6: Upstream Oil & Gas | C6: Human Resources | D6: 0.15 | E6: Recruitment administration | F6: 0.25 | G6: Task Processing / Query Handling | H6: 0.9 | I6: =SUMPRODUCT(H6:H9,F6:F9)*D6 -> 0.093 | J6: 0.46 | K6: 0.46 | L6: 0.43 | M6: 0.38 | N6: 0.36
A7: Energy | B7: Upstream Oil & Gas | C7: Human Resources | D7: 0.15 | E7: Workforce planning | F7: 0.25 | G7: Task Planning & Management | H7: 0.7 | J7: 0.46 | K7: 0.46 | L7: 0.43 | M7: 0.38 | N7: 0.36
A8: Energy | B8: Upstream Oil & Gas | C8: Human Resources | D8: 0.15 | E8: Employee relations & support | F8: 0.3 | G8: Stakeholder / Relationship Management | H8: 0.1 | J8: 0.46 | K8: 0.46 | L8: 0.43 | M8: 0.38 | N8: 0.36
A9: Energy | B9: Upstream Oil & Gas | C9: Human Resources | D9: 0.15 | E9: HR documentation & reporting | F9: 0.2 | G9: Document Generation & Management | H9: 0.95 | J9: 0.46 | K9: 0.46 | L9: 0.43 | M9: 0.38 | N9: 0.36
A10: Energy | B10: Upstream Oil & Gas | C10: Corporate IT & Enterprise Technology | D10: 0.15 | E10: IT service desk & user support | F10: 0.3 | G10: Task Processing / Query Handling | H10: 0.9 | I10: =SUMPRODUCT(H10:H13,F10:F13)*D10 -> 0.1215 | J10: 0.65 | K10: 0.65 | L10: 0.62 | M10: 0.57 | N10: 0.54
A11: Energy | B11: Upstream Oil & Gas | C11: Corporate IT & Enterprise Technology | D11: 0.15 | E11: Application, infrastructure & security monitoring | F11: 0.25 | G11: Monitoring | H11: 0.7 | J11: 0.65 | K11: 0.65 | L11: 0.62 | M11: 0.57 | N11: 0.54
A12: Energy | B12: Upstream Oil & Gas | C12: Corporate IT & Enterprise Technology | D12: 0.15 | E12: Technology planning & change coordination | F12: 0.25 | G12: Task Planning & Management | H12: 0.7 | J12: 0.65 | K12: 0.65 | L12: 0.62 | M12: 0.57 | N12: 0.54
A13: Energy | B13: Upstream Oil & Gas | C13: Corporate IT & Enterprise Technology | D13: 0.15 | E13: IT documentation | F13: 0.2 | G13: Document Generation & Management | H13: 0.95 | J13: 0.65 | K13: 0.65 | L13: 0.62 | M13: 0.57 | N13: 0.54
A14: Energy | B14: Upstream Oil & Gas | C14: Legal, Regulatory & Corporate Administration | D14: 0.25 | E14: Regulatory / policy monitoring | F14: 0.25 | G14: Monitoring | H14: 0.7 | I14: =SUMPRODUCT(H14:H17,F14:F17)*D14 -> 0.146875 | J14: 0.43 | K14: 0.43 | L14: 0.4 | M14: 0.35 | N14: 0.32
A15: Energy | B15: Upstream Oil & Gas | C15: Legal, Regulatory & Corporate Administration | D15: 0.25 | E15: Contract & policy review | F15: 0.25 | G15: Assessment & Analysis | H15: 0.6 | J15: 0.43 | K15: 0.43 | L15: 0.4 | M15: 0.35 | N15: 0.32
A16: Energy | B16: Upstream Oil & Gas | C16: Legal, Regulatory & Corporate Administration | D16: 0.25 | E16: Regulator / legal stakeholder management | F16: 0.25 | G16: Stakeholder / Relationship Management | H16: 0.1 | J16: 0.43 | K16: 0.43 | L16: 0.4 | M16: 0.35 | N16: 0.32
A17: Energy | B17: Upstream Oil & Gas | C17: Legal, Regulatory & Corporate Administration | D17: 0.25 | E17: Compliance & corporate documentation | F17: 0.25 | G17: Document Generation & Management | H17: 0.95 | J17: 0.43 | K17: 0.43 | L17: 0.4 | M17: 0.35 | N17: 0.32
A18: Energy | B18: Upstream Oil & Gas | C18: Procurement & Vendor Management | D18: 0.15 | E18: Purchase & vendor administration | F18: 0.25 | G18: Task Processing / Query Handling | H18: 0.9 | I18: =SUMPRODUCT(H18:H21,F18:F21)*D18 -> 0.08925 | J18: 0.46 | K18: 0.46 | L18: 0.43 | M18: 0.38 | N18: 0.35
A19: Energy | B19: Upstream Oil & Gas | C19: Procurement & Vendor Management | D19: 0.15 | E19: Vendor / spend analysis | F19: 0.25 | G19: Assessment & Analysis | H19: 0.6 | J19: 0.46 | K19: 0.46 | L19: 0.43 | M19: 0.38 | N19: 0.35
A20: Energy | B20: Upstream Oil & Gas | C20: Procurement & Vendor Management | D20: 0.15 | E20: Vendor relationship management | F20: 0.3 | G20: Stakeholder / Relationship Management | H20: 0.1 | J20: 0.46 | K20: 0.46 | L20: 0.43 | M20: 0.38 | N20: 0.35
A21: Energy | B21: Upstream Oil & Gas | C21: Procurement & Vendor Management | D21: 0.15 | E21: Contract & procurement documentation | F21: 0.2 | G21: Document Generation & Management | H21: 0.95 | J21: 0.46 | K21: 0.46 | L21: 0.43 | M21: 0.38 | N21: 0.35
A22: Energy | B22: Upstream Oil & Gas | C22: Corporate Strategy & Management | D22: 0.1 | E22: Strategic planning | F22: 0.3 | G22: Strategy & Design | H22: 0.3 | I22: =SUMPRODUCT(H22:H25,F22:F25)*D22 -> 0.0455 | J22: 0.34 | K22: 0.34 | L22: 0.31 | M22: 0.27 | N22: 0.24
A23: Energy | B23: Upstream Oil & Gas | C23: Corporate Strategy & Management | D23: 0.1 | E23: Management / market analysis | F23: 0.25 | G23: Assessment & Analysis | H23: 0.6 | J23: 0.34 | K23: 0.34 | L23: 0.31 | M23: 0.27 | N23: 0.24
A24: Energy | B24: Upstream Oil & Gas | C24: Corporate Strategy & Management | D24: 0.1 | E24: Executive stakeholder coordination | F24: 0.25 | G24: Stakeholder / Relationship Management | H24: 0.1 | J24: 0.34 | K24: 0.34 | L24: 0.31 | M24: 0.27 | N24: 0.24
A25: Energy | B25: Upstream Oil & Gas | C25: Corporate Strategy & Management | D25: 0.1 | E25: Corporate reporting | F25: 0.2 | G25: Document Generation & Management | H25: 0.95 | J25: 0.34 | K25: 0.34 | L25: 0.31 | M25: 0.27 | N25: 0.24
I26: =SUM(I2:I25) -> 0.661625 | J26: =+J6*$D6+J10*$D10+J14*$D14+J18*$D18+J22*$D22+$D2*J2 -> 0.509 | K26: =+K6*$D6+K10*$D10+K14*$D14+K18*$D18+K22*$D22+$D2*K2 -> 0.509 | L26: =+L6*$D6+L10*$D10+L14*$D14+L18*$D18+L22*$D22+$D2*L2 -> 0.479 | M26: =+M6*$D6+M10*$D10+M14*$D14+M18*$D18+M22*$D22+$D2*M2 -> 0.43 | N26: =+N6*$D6+N10*$D10+N14*$D14+N18*$D18+N22*$D22+$D2*N2 -> 0.4015
A28: Energy | B28: Integrated Oil & Gas | C28: Finance & Accounting | D28: 0.2 | E28: Transaction processing & reconciliation | F28: 0.3 | G28: Task Processing / Query Handling | H28: 0.9 | I28: =SUMPRODUCT(H28:H31,F28:F31)*D28 -> 0.1655 | J28: 0.67 | K28: 0.67 | L28: 0.64 | M28: 0.59 | N28: 0.56
A29: Energy | B29: Integrated Oil & Gas | C29: Finance & Accounting | D29: 0.2 | E29: Financial planning & analysis | F29: 0.25 | G29: Assessment & Analysis | H29: 0.6 | J29: 0.67 | K29: 0.67 | L29: 0.64 | M29: 0.59 | N29: 0.56
A30: Energy | B30: Integrated Oil & Gas | C30: Finance & Accounting | D30: 0.2 | E30: Budgeting & forecasting | F30: 0.2 | G30: Modelling (incl. Forecasting) | H30: 0.85 | J30: 0.67 | K30: 0.67 | L30: 0.64 | M30: 0.59 | N30: 0.56
A31: Energy | B31: Integrated Oil & Gas | C31: Finance & Accounting | D31: 0.2 | E31: Financial reporting | F31: 0.25 | G31: Document Generation & Management | H31: 0.95 | J31: 0.67 | K31: 0.67 | L31: 0.64 | M31: 0.59 | N31: 0.56
A32: Energy | B32: Integrated Oil & Gas | C32: Human Resources | D32: 0.15 | E32: Recruitment administration | F32: 0.25 | G32: Task Processing / Query Handling | H32: 0.9 | I32: =SUMPRODUCT(H32:H35,F32:F35)*D32 -> 0.093 | J32: 0.47 | K32: 0.47 | L32: 0.44 | M32: 0.39 | N32: 0.37
A33: Energy | B33: Integrated Oil & Gas | C33: Human Resources | D33: 0.15 | E33: Workforce planning | F33: 0.25 | G33: Task Planning & Management | H33: 0.7 | J33: 0.47 | K33: 0.47 | L33: 0.44 | M33: 0.39 | N33: 0.37
A34: Energy | B34: Integrated Oil & Gas | C34: Human Resources | D34: 0.15 | E34: Employee relations & support | F34: 0.3 | G34: Stakeholder / Relationship Management | H34: 0.1 | J34: 0.47 | K34: 0.47 | L34: 0.44 | M34: 0.39 | N34: 0.37
A35: Energy | B35: Integrated Oil & Gas | C35: Human Resources | D35: 0.15 | E35: HR documentation & reporting | F35: 0.2 | G35: Document Generation & Management | H35: 0.95 | J35: 0.47 | K35: 0.47 | L35: 0.44 | M35: 0.39 | N35: 0.37
A36: Energy | B36: Integrated Oil & Gas | C36: Corporate IT & Enterprise Technology | D36: 0.2 | E36: IT service desk & user support | F36: 0.3 | G36: Task Processing / Query Handling | H36: 0.9 | I36: =SUMPRODUCT(H36:H39,F36:F39)*D36 -> 0.162 | J36: 0.66 | K36: 0.66 | L36: 0.63 | M36: 0.58 | N36: 0.55
A37: Energy | B37: Integrated Oil & Gas | C37: Corporate IT & Enterprise Technology | D37: 0.2 | E37: Application, infrastructure & security monitoring | F37: 0.25 | G37: Monitoring | H37: 0.7 | J37: 0.66 | K37: 0.66 | L37: 0.63 | M37: 0.58 | N37: 0.55
A38: Energy | B38: Integrated Oil & Gas | C38: Corporate IT & Enterprise Technology | D38: 0.2 | E38: Technology planning & change coordination | F38: 0.25 | G38: Task Planning & Management | H38: 0.7 | J38: 0.66 | K38: 0.66 | L38: 0.63 | M38: 0.58 | N38: 0.55
A39: Energy | B39: Integrated Oil & Gas | C39: Corporate IT & Enterprise Technology | D39: 0.2 | E39: IT documentation | F39: 0.2 | G39: Document Generation & Management | H39: 0.95 | J39: 0.66 | K39: 0.66 | L39: 0.63 | M39: 0.58 | N39: 0.55
A40: Energy | B40: Integrated Oil & Gas | C40: Legal, Regulatory & Corporate Administration | D40: 0.2 | E40: Regulatory / policy monitoring | F40: 0.25 | G40: Monitoring | H40: 0.7 | I40: =SUMPRODUCT(H40:H43,F40:F43)*D40 -> 0.1175 | J40: 0.44 | K40: 0.44 | L40: 0.41 | M40: 0.36 | N40: 0.33
A41: Energy | B41: Integrated Oil & Gas | C41: Legal, Regulatory & Corporate Administration | D41: 0.2 | E41: Contract & policy review | F41: 0.25 | G41: Assessment & Analysis | H41: 0.6 | J41: 0.44 | K41: 0.44 | L41: 0.41 | M41: 0.36 | N41: 0.33
A42: Energy | B42: Integrated Oil & Gas | C42: Legal, Regulatory & Corporate Administration | D42: 0.2 | E42: Regulator / legal stakeholder management | F42: 0.25 | G42: Stakeholder / Relationship Management | H42: 0.1 | J42: 0.44 | K42: 0.44 | L42: 0.41 | M42: 0.36 | N42: 0.33
A43: Energy | B43: Integrated Oil & Gas | C43: Legal, Regulatory & Corporate Administration | D43: 0.2 | E43: Compliance & corporate documentation | F43: 0.25 | G43: Document Generation & Management | H43: 0.95 | J43: 0.44 | K43: 0.44 | L43: 0.41 | M43: 0.36 | N43: 0.33
A44: Energy | B44: Integrated Oil & Gas | C44: Procurement & Vendor Management | D44: 0.15 | E44: Purchase & vendor administration | F44: 0.25 | G44: Task Processing / Query Handling | H44: 0.9 | I44: =SUMPRODUCT(H44:H47,F44:F47)*D44 -> 0.08925 | J44: 0.47 | K44: 0.47 | L44: 0.44 | M44: 0.39 | N44: 0.36
A45: Energy | B45: Integrated Oil & Gas | C45: Procurement & Vendor Management | D45: 0.15 | E45: Vendor / spend analysis | F45: 0.25 | G45: Assessment & Analysis | H45: 0.6 | J45: 0.47 | K45: 0.47 | L45: 0.44 | M45: 0.39 | N45: 0.36
A46: Energy | B46: Integrated Oil & Gas | C46: Procurement & Vendor Management | D46: 0.15 | E46: Vendor relationship management | F46: 0.3 | G46: Stakeholder / Relationship Management | H46: 0.1 | J46: 0.47 | K46: 0.47 | L46: 0.44 | M46: 0.39 | N46: 0.36
A47: Energy | B47: Integrated Oil & Gas | C47: Procurement & Vendor Management | D47: 0.15 | E47: Contract & procurement documentation | F47: 0.2 | G47: Document Generation & Management | H47: 0.95 | J47: 0.47 | K47: 0.47 | L47: 0.44 | M47: 0.39 | N47: 0.36
A48: Energy | B48: Integrated Oil & Gas | C48: Corporate Strategy & Management | D48: 0.1 | E48: Strategic planning | F48: 0.3 | G48: Strategy & Design | H48: 0.3 | I48: =SUMPRODUCT(H48:H51,F48:F51)*D48 -> 0.0455 | J48: 0.35 | K48: 0.35 | L48: 0.32 | M48: 0.28 | N48: 0.25
A49: Energy | B49: Integrated Oil & Gas | C49: Corporate Strategy & Management | D49: 0.1 | E49: Management / market analysis | F49: 0.25 | G49: Assessment & Analysis | H49: 0.6 | J49: 0.35 | K49: 0.35 | L49: 0.32 | M49: 0.28 | N49: 0.25
A50: Energy | B50: Integrated Oil & Gas | C50: Corporate Strategy & Management | D50: 0.1 | E50: Executive stakeholder coordination | F50: 0.25 | G50: Stakeholder / Relationship Management | H50: 0.1 | J50: 0.35 | K50: 0.35 | L50: 0.32 | M50: 0.28 | N50: 0.25
A51: Energy | B51: Integrated Oil & Gas | C51: Corporate Strategy & Management | D51: 0.1 | E51: Corporate reporting | F51: 0.2 | G51: Document Generation & Management | H51: 0.95 | J51: 0.35 | K51: 0.35 | L51: 0.32 | M51: 0.28 | N51: 0.25
I52: =SUM(I28:I51) -> 0.67275 | J52: =+J32*$D32+J36*$D36+J40*$D40+J44*$D44+J48*$D48+$D28*J28 -> 0.53 | K52: =+K32*$D32+K36*$D36+K40*$D40+K44*$D44+K48*$D48+$D28*K28 -> 0.53 | L52: =+L32*$D32+L36*$D36+L40*$D40+L44*$D44+L48*$D48+$D28*L28 -> 0.5 | M52: =+M32*$D32+M36*$D36+M40*$D40+M44*$D44+M48*$D48+$D28*M28 -> 0.451 | N52: =+N32*$D32+N36*$D36+N40*$D40+N44*$D44+N48*$D48+$D28*N28 -> 0.4225
A54: Energy | B54: Midstream Oil & Gas | C54: Finance & Accounting | D54: 0.2 | E54: Transaction processing & reconciliation | F54: 0.3 | G54: Task Processing / Query Handling | H54: 0.9 | I54: =SUMPRODUCT(H54:H57,F54:F57)*D54 -> 0.1655 | J54: 0.67 | K54: 0.67 | L54: 0.64 | M54: 0.59 | N54: 0.57
A55: Energy | B55: Midstream Oil & Gas | C55: Finance & Accounting | D55: 0.2 | E55: Financial planning & analysis | F55: 0.25 | G55: Assessment & Analysis | H55: 0.6 | J55: 0.67 | K55: 0.67 | L55: 0.64 | M55: 0.59 | N55: 0.57
A56: Energy | B56: Midstream Oil & Gas | C56: Finance & Accounting | D56: 0.2 | E56: Budgeting & forecasting | F56: 0.2 | G56: Modelling (incl. Forecasting) | H56: 0.85 | J56: 0.67 | K56: 0.67 | L56: 0.64 | M56: 0.59 | N56: 0.57
A57: Energy | B57: Midstream Oil & Gas | C57: Finance & Accounting | D57: 0.2 | E57: Financial reporting | F57: 0.25 | G57: Document Generation & Management | H57: 0.95 | J57: 0.67 | K57: 0.67 | L57: 0.64 | M57: 0.59 | N57: 0.57
A58: Energy | B58: Midstream Oil & Gas | C58: Human Resources | D58: 0.15 | E58: Recruitment administration | F58: 0.25 | G58: Task Processing / Query Handling | H58: 0.9 | I58: =SUMPRODUCT(H58:H61,F58:F61)*D58 -> 0.093 | J58: 0.47 | K58: 0.47 | L58: 0.44 | M58: 0.39 | N58: 0.38
A59: Energy | B59: Midstream Oil & Gas | C59: Human Resources | D59: 0.15 | E59: Workforce planning | F59: 0.25 | G59: Task Planning & Management | H59: 0.7 | J59: 0.47 | K59: 0.47 | L59: 0.44 | M59: 0.39 | N59: 0.38
A60: Energy | B60: Midstream Oil & Gas | C60: Human Resources | D60: 0.15 | E60: Employee relations & support | F60: 0.3 | G60: Stakeholder / Relationship Management | H60: 0.1 | J60: 0.47 | K60: 0.47 | L60: 0.44 | M60: 0.39 | N60: 0.38
A61: Energy | B61: Midstream Oil & Gas | C61: Human Resources | D61: 0.15 | E61: HR documentation & reporting | F61: 0.2 | G61: Document Generation & Management | H61: 0.95 | J61: 0.47 | K61: 0.47 | L61: 0.44 | M61: 0.39 | N61: 0.38
A62: Energy | B62: Midstream Oil & Gas | C62: Corporate IT & Enterprise Technology | D62: 0.2 | E62: IT service desk & user support | F62: 0.3 | G62: Task Processing / Query Handling | H62: 0.9 | I62: =SUMPRODUCT(H62:H65,F62:F65)*D62 -> 0.162 | J62: 0.66 | K62: 0.66 | L62: 0.63 | M62: 0.58 | N62: 0.56
A63: Energy | B63: Midstream Oil & Gas | C63: Corporate IT & Enterprise Technology | D63: 0.2 | E63: Application, infrastructure & security monitoring | F63: 0.25 | G63: Monitoring | H63: 0.7 | J63: 0.66 | K63: 0.66 | L63: 0.63 | M63: 0.58 | N63: 0.56
A64: Energy | B64: Midstream Oil & Gas | C64: Corporate IT & Enterprise Technology | D64: 0.2 | E64: Technology planning & change coordination | F64: 0.25 | G64: Task Planning & Management | H64: 0.7 | J64: 0.66 | K64: 0.66 | L64: 0.63 | M64: 0.58 | N64: 0.56
A65: Energy | B65: Midstream Oil & Gas | C65: Corporate IT & Enterprise Technology | D65: 0.2 | E65: IT documentation | F65: 0.2 | G65: Document Generation & Management | H65: 0.95 | J65: 0.66 | K65: 0.66 | L65: 0.63 | M65: 0.58 | N65: 0.56
A66: Energy | B66: Midstream Oil & Gas | C66: Legal, Regulatory & Corporate Administration | D66: 0.2 | E66: Regulatory / policy monitoring | F66: 0.25 | G66: Monitoring | H66: 0.7 | I66: =SUMPRODUCT(H66:H69,F66:F69)*D66 -> 0.1175 | J66: 0.44 | K66: 0.44 | L66: 0.41 | M66: 0.36 | N66: 0.34
A67: Energy | B67: Midstream Oil & Gas | C67: Legal, Regulatory & Corporate Administration | D67: 0.2 | E67: Contract & policy review | F67: 0.25 | G67: Assessment & Analysis | H67: 0.6 | J67: 0.44 | K67: 0.44 | L67: 0.41 | M67: 0.36 | N67: 0.34
A68: Energy | B68: Midstream Oil & Gas | C68: Legal, Regulatory & Corporate Administration | D68: 0.2 | E68: Regulator / legal stakeholder management | F68: 0.25 | G68: Stakeholder / Relationship Management | H68: 0.1 | J68: 0.44 | K68: 0.44 | L68: 0.41 | M68: 0.36 | N68: 0.34
A69: Energy | B69: Midstream Oil & Gas | C69: Legal, Regulatory & Corporate Administration | D69: 0.2 | E69: Compliance & corporate documentation | F69: 0.25 | G69: Document Generation & Management | H69: 0.95 | J69: 0.44 | K69: 0.44 | L69: 0.41 | M69: 0.36 | N69: 0.34
A70: Energy | B70: Midstream Oil & Gas | C70: Procurement & Vendor Management | D70: 0.15 | E70: Purchase & vendor administration | F70: 0.25 | G70: Task Processing / Query Handling | H70: 0.9 | I70: =SUMPRODUCT(H70:H73,F70:F73)*D70 -> 0.08925 | J70: 0.47 | K70: 0.47 | L70: 0.44 | M70: 0.39 | N70: 0.37
A71: Energy | B71: Midstream Oil & Gas | C71: Procurement & Vendor Management | D71: 0.15 | E71: Vendor / spend analysis | F71: 0.25 | G71: Assessment & Analysis | H71: 0.6 | J71: 0.47 | K71: 0.47 | L71: 0.44 | M71: 0.39 | N71: 0.37
A72: Energy | B72: Midstream Oil & Gas | C72: Procurement & Vendor Management | D72: 0.15 | E72: Vendor relationship management | F72: 0.3 | G72: Stakeholder / Relationship Management | H72: 0.1 | J72: 0.47 | K72: 0.47 | L72: 0.44 | M72: 0.39 | N72: 0.37
A73: Energy | B73: Midstream Oil & Gas | C73: Procurement & Vendor Management | D73: 0.15 | E73: Contract & procurement documentation | F73: 0.2 | G73: Document Generation & Management | H73: 0.95 | J73: 0.47 | K73: 0.47 | L73: 0.44 | M73: 0.39 | N73: 0.37
A74: Energy | B74: Midstream Oil & Gas | C74: Corporate Strategy & Management | D74: 0.1 | E74: Strategic planning | F74: 0.3 | G74: Strategy & Design | H74: 0.3 | I74: =SUMPRODUCT(H74:H77,F74:F77)*D74 -> 0.0455 | J74: 0.35 | K74: 0.35 | L74: 0.32 | M74: 0.28 | N74: 0.26
A75: Energy | B75: Midstream Oil & Gas | C75: Corporate Strategy & Management | D75: 0.1 | E75: Management / market analysis | F75: 0.25 | G75: Assessment & Analysis | H75: 0.6 | J75: 0.35 | K75: 0.35 | L75: 0.32 | M75: 0.28 | N75: 0.26
A76: Energy | B76: Midstream Oil & Gas | C76: Corporate Strategy & Management | D76: 0.1 | E76: Executive stakeholder coordination | F76: 0.25 | G76: Stakeholder / Relationship Management | H76: 0.1 | J76: 0.35 | K76: 0.35 | L76: 0.32 | M76: 0.28 | N76: 0.26
A77: Energy | B77: Midstream Oil & Gas | C77: Corporate Strategy & Management | D77: 0.1 | E77: Corporate reporting | F77: 0.2 | G77: Document Generation & Management | H77: 0.95 | J77: 0.35 | K77: 0.35 | L77: 0.32 | M77: 0.28 | N77: 0.26
I78: =SUM(I54:I77) -> 0.67275 | J78: =+J58*$D58+J62*$D62+J66*$D66+J70*$D70+J74*$D74+$D54*J54 -> 0.53 | K78: =+K58*$D58+K62*$D62+K66*$D66+K70*$D70+K74*$D74+$D54*K54 -> 0.53 | L78: =+L58*$D58+L62*$D62+L66*$D66+L70*$D70+L74*$D74+$D54*L54 -> 0.5 | M78: =+M58*$D58+M62*$D62+M66*$D66+M70*$D70+M74*$D74+$D54*M54 -> 0.451 | N78: =+N58*$D58+N62*$D62+N66*$D66+N70*$D70+N74*$D74+$D54*N54 -> 0.4325
A80: Energy | B80: Downstream Oil & Gas | C80: Marketing & Corporate Communications | D80: 0.1 | E80: Campaign & content development | F80: 0.3 | G80: Content Generation | H80: 0.7 | I80: =SUMPRODUCT(H80:H83,F80:F83)*D80 -> 0.0455 | J80: 0.36 | K80: 0.36 | L80: 0.33 | M80: 0.29 | N80: 0.27
A81: Energy | B81: Downstream Oil & Gas | C81: Marketing & Corporate Communications | D81: 0.1 | E81: Customer / market analytics | F81: 0.25 | G81: Assessment & Analysis | H81: 0.6 | J81: 0.36 | K81: 0.36 | L81: 0.33 | M81: 0.29 | N81: 0.27
A82: Energy | B82: Downstream Oil & Gas | C82: Marketing & Corporate Communications | D82: 0.1 | E82: Campaign / proposition planning | F82: 0.25 | G82: Strategy & Design | H82: 0.3 | J82: 0.36 | K82: 0.36 | L82: 0.33 | M82: 0.29 | N82: 0.27
A83: Energy | B83: Downstream Oil & Gas | C83: Marketing & Corporate Communications | D83: 0.1 | E83: Agency / external stakeholder coordination | F83: 0.2 | G83: Stakeholder / Relationship Management | H83: 0.1 | J83: 0.36 | K83: 0.36 | L83: 0.33 | M83: 0.29 | N83: 0.27
A84: Energy | B84: Downstream Oil & Gas | C84: Finance & Accounting | D84: 0.2 | E84: Transaction processing & reconciliation | F84: 0.3 | G84: Task Processing / Query Handling | H84: 0.9 | I84: =SUMPRODUCT(H84:H87,F84:F87)*D84 -> 0.1655 | J84: 0.68 | K84: 0.68 | L84: 0.65 | M84: 0.61 | N84: 0.59
A85: Energy | B85: Downstream Oil & Gas | C85: Finance & Accounting | D85: 0.2 | E85: Financial planning & analysis | F85: 0.25 | G85: Assessment & Analysis | H85: 0.6 | J85: 0.68 | K85: 0.68 | L85: 0.65 | M85: 0.61 | N85: 0.59
A86: Energy | B86: Downstream Oil & Gas | C86: Finance & Accounting | D86: 0.2 | E86: Budgeting & forecasting | F86: 0.2 | G86: Modelling (incl. Forecasting) | H86: 0.85 | J86: 0.68 | K86: 0.68 | L86: 0.65 | M86: 0.61 | N86: 0.59
A87: Energy | B87: Downstream Oil & Gas | C87: Finance & Accounting | D87: 0.2 | E87: Financial reporting | F87: 0.25 | G87: Document Generation & Management | H87: 0.95 | J87: 0.68 | K87: 0.68 | L87: 0.65 | M87: 0.61 | N87: 0.59
A88: Energy | B88: Downstream Oil & Gas | C88: Human Resources | D88: 0.15 | E88: Recruitment administration | F88: 0.25 | G88: Task Processing / Query Handling | H88: 0.9 | I88: =SUMPRODUCT(H88:H91,F88:F91)*D88 -> 0.093 | J88: 0.48 | K88: 0.48 | L88: 0.45 | M88: 0.41 | N88: 0.39
A89: Energy | B89: Downstream Oil & Gas | C89: Human Resources | D89: 0.15 | E89: Workforce planning | F89: 0.25 | G89: Task Planning & Management | H89: 0.7 | J89: 0.48 | K89: 0.48 | L89: 0.45 | M89: 0.41 | N89: 0.39
A90: Energy | B90: Downstream Oil & Gas | C90: Human Resources | D90: 0.15 | E90: Employee relations & support | F90: 0.3 | G90: Stakeholder / Relationship Management | H90: 0.1 | J90: 0.48 | K90: 0.48 | L90: 0.45 | M90: 0.41 | N90: 0.39
A91: Energy | B91: Downstream Oil & Gas | C91: Human Resources | D91: 0.15 | E91: HR documentation & reporting | F91: 0.2 | G91: Document Generation & Management | H91: 0.95 | J91: 0.48 | K91: 0.48 | L91: 0.45 | M91: 0.41 | N91: 0.39
A92: Energy | B92: Downstream Oil & Gas | C92: Corporate IT & Enterprise Technology | D92: 0.2 | E92: IT service desk & user support | F92: 0.3 | G92: Task Processing / Query Handling | H92: 0.9 | I92: =SUMPRODUCT(H92:H95,F92:F95)*D92 -> 0.162 | J92: 0.68 | K92: 0.68 | L92: 0.65 | M92: 0.61 | N92: 0.59
A93: Energy | B93: Downstream Oil & Gas | C93: Corporate IT & Enterprise Technology | D93: 0.2 | E93: Application, infrastructure & security monitoring | F93: 0.25 | G93: Monitoring | H93: 0.7 | J93: 0.68 | K93: 0.68 | L93: 0.65 | M93: 0.61 | N93: 0.59
A94: Energy | B94: Downstream Oil & Gas | C94: Corporate IT & Enterprise Technology | D94: 0.2 | E94: Technology planning & change coordination | F94: 0.25 | G94: Task Planning & Management | H94: 0.7 | J94: 0.68 | K94: 0.68 | L94: 0.65 | M94: 0.61 | N94: 0.59
A95: Energy | B95: Downstream Oil & Gas | C95: Corporate IT & Enterprise Technology | D95: 0.2 | E95: IT documentation | F95: 0.2 | G95: Document Generation & Management | H95: 0.95 | J95: 0.68 | K95: 0.68 | L95: 0.65 | M95: 0.61 | N95: 0.59
A96: Energy | B96: Downstream Oil & Gas | C96: Legal, Regulatory & Corporate Administration | D96: 0.2 | E96: Regulatory / policy monitoring | F96: 0.25 | G96: Monitoring | H96: 0.7 | I96: =SUMPRODUCT(H96:H99,F96:F99)*D96 -> 0.1175 | J96: 0.45 | K96: 0.45 | L96: 0.42 | M96: 0.38 | N96: 0.36
A97: Energy | B97: Downstream Oil & Gas | C97: Legal, Regulatory & Corporate Administration | D97: 0.2 | E97: Contract & policy review | F97: 0.25 | G97: Assessment & Analysis | H97: 0.6 | J97: 0.45 | K97: 0.45 | L97: 0.42 | M97: 0.38 | N97: 0.36
A98: Energy | B98: Downstream Oil & Gas | C98: Legal, Regulatory & Corporate Administration | D98: 0.2 | E98: Regulator / legal stakeholder management | F98: 0.25 | G98: Stakeholder / Relationship Management | H98: 0.1 | J98: 0.45 | K98: 0.45 | L98: 0.42 | M98: 0.38 | N98: 0.36
A99: Energy | B99: Downstream Oil & Gas | C99: Legal, Regulatory & Corporate Administration | D99: 0.2 | E99: Compliance & corporate documentation | F99: 0.25 | G99: Document Generation & Management | H99: 0.95 | J99: 0.45 | K99: 0.45 | L99: 0.42 | M99: 0.38 | N99: 0.36
A100: Energy | B100: Downstream Oil & Gas | C100: Procurement & Vendor Management | D100: 0.1 | E100: Purchase & vendor administration | F100: 0.25 | G100: Task Processing / Query Handling | H100: 0.9 | I100: =SUMPRODUCT(H100:H103,F100:F103)*D100 -> 0.0595 | J100: 0.47 | K100: 0.47 | L100: 0.44 | M100: 0.4 | N100: 0.38
A101: Energy | B101: Downstream Oil & Gas | C101: Procurement & Vendor Management | D101: 0.1 | E101: Vendor / spend analysis | F101: 0.25 | G101: Assessment & Analysis | H101: 0.6 | J101: 0.47 | K101: 0.47 | L101: 0.44 | M101: 0.4 | N101: 0.38
A102: Energy | B102: Downstream Oil & Gas | C102: Procurement & Vendor Management | D102: 0.1 | E102: Vendor relationship management | F102: 0.3 | G102: Stakeholder / Relationship Management | H102: 0.1 | J102: 0.47 | K102: 0.47 | L102: 0.44 | M102: 0.4 | N102: 0.38
A103: Energy | B103: Downstream Oil & Gas | C103: Procurement & Vendor Management | D103: 0.1 | E103: Contract & procurement documentation | F103: 0.2 | G103: Document Generation & Management | H103: 0.95 | J103: 0.47 | K103: 0.47 | L103: 0.44 | M103: 0.4 | N103: 0.38
...

Sheet Govt
A1: Sector | B1: Subsector | C1: Core Activity | D1: Effort Split | E1: Key Main Task | F1: % Effort | G1: Category | H1: AI Addressable | I1: Agentification Potential | J1: Actual Agentification Possible | K1: NA | L1: EU | M1: APAC ex India | N1: India
A2: Government | B2: Governmental Banks | C2: Finance & Accounting | D2: 0.2 | E2: Transaction processing & reconciliation | F2: 0.3 | G2: Task Processing / Query Handling | H2: 0.9 | I2: =SUMPRODUCT(H2:H5,F2:F5)*D2 -> 0.1655 | J2: 0.64 | K2: 0.64 | L2: 0.61 | M2: 0.55 | N2: 0.52
A3: Government | B3: Governmental Banks | C3: Finance & Accounting | D3: 0.2 | E3: Financial planning & analysis | F3: 0.25 | G3: Assessment & Analysis | H3: 0.6 | J3: 0.64 | K3: 0.64 | L3: 0.61 | M3: 0.55 | N3: 0.52
A4: Government | B4: Governmental Banks | C4: Finance & Accounting | D4: 0.2 | E4: Budgeting & forecasting | F4: 0.2 | G4: Modelling (incl. Forecasting) | H4: 0.85 | J4: 0.64 | K4: 0.64 | L4: 0.61 | M4: 0.55 | N4: 0.52
A5: Government | B5: Governmental Banks | C5: Finance & Accounting | D5: 0.2 | E5: Financial reporting | F5: 0.25 | G5: Document Generation & Management | H5: 0.95 | J5: 0.64 | K5: 0.64 | L5: 0.61 | M5: 0.55 | N5: 0.52
A6: Government | B6: Governmental Banks | C6: Human Resources | D6: 0.15 | E6: Recruitment administration | F6: 0.25 | G6: Task Processing / Query Handling | H6: 0.9 | I6: =SUMPRODUCT(H6:H9,F6:F9)*D6 -> 0.093 | J6: 0.44 | K6: 0.44 | L6: 0.41 | M6: 0.36 | N6: 0.33
A7: Government | B7: Governmental Banks | C7: Human Resources | D7: 0.15 | E7: Workforce planning | F7: 0.25 | G7: Task Planning & Management | H7: 0.7 | J7: 0.44 | K7: 0.44 | L7: 0.41 | M7: 0.36 | N7: 0.33
A8: Government | B8: Governmental Banks | C8: Human Resources | D8: 0.15 | E8: Employee relations & support | F8: 0.3 | G8: Stakeholder / Relationship Management | H8: 0.1 | J8: 0.44 | K8: 0.44 | L8: 0.41 | M8: 0.36 | N8: 0.33
A9: Government | B9: Governmental Banks | C9: Human Resources | D9: 0.15 | E9: HR documentation & reporting | F9: 0.2 | G9: Document Generation & Management | H9: 0.95 | J9: 0.44 | K9: 0.44 | L9: 0.41 | M9: 0.36 | N9: 0.33
A10: Government | B10: Governmental Banks | C10: Corporate IT & Enterprise Technology | D10: 0.2 | E10: IT service desk & user support | F10: 0.3 | G10: Task Processing / Query Handling | H10: 0.9 | I10: =SUMPRODUCT(H10:H13,F10:F13)*D10 -> 0.162 | J10: 0.64 | K10: 0.64 | L10: 0.61 | M10: 0.56 | N10: 0.53
A11: Government | B11: Governmental Banks | C11: Corporate IT & Enterprise Technology | D11: 0.2 | E11: Application, infrastructure & security monitoring | F11: 0.25 | G11: Monitoring | H11: 0.7 | J11: 0.64 | K11: 0.64 | L11: 0.61 | M11: 0.56 | N11: 0.53
A12: Government | B12: Governmental Banks | C12: Corporate IT & Enterprise Technology | D12: 0.2 | E12: Technology planning & change coordination | F12: 0.25 | G12: Task Planning & Management | H12: 0.7 | J12: 0.64 | K12: 0.64 | L12: 0.61 | M12: 0.56 | N12: 0.53
A13: Government | B13: Governmental Banks | C13: Corporate IT & Enterprise Technology | D13: 0.2 | E13: IT documentation | F13: 0.2 | G13: Document Generation & Management | H13: 0.95 | J13: 0.64 | K13: 0.64 | L13: 0.61 | M13: 0.56 | N13: 0.53
A14: Government | B14: Governmental Banks | C14: Legal, Risk & Compliance | D14: 0.25 | E14: Compliance / policy monitoring | F14: 0.25 | G14: Monitoring | H14: 0.7 | I14: =SUMPRODUCT(H14:H17,F14:F17)*D14 -> 0.146875 | J14: 0.43 | K14: 0.43 | L14: 0.4 | M14: 0.35 | N14: 0.32
A15: Government | B15: Governmental Banks | C15: Legal, Risk & Compliance | D15: 0.25 | E15: Contract & policy review | F15: 0.25 | G15: Assessment & Analysis | H15: 0.6 | J15: 0.43 | K15: 0.43 | L15: 0.4 | M15: 0.35 | N15: 0.32
A16: Government | B16: Governmental Banks | C16: Legal, Risk & Compliance | D16: 0.25 | E16: Regulator / legal stakeholder management | F16: 0.25 | G16: Stakeholder / Relationship Management | H16: 0.1 | J16: 0.43 | K16: 0.43 | L16: 0.4 | M16: 0.35 | N16: 0.32
A17: Government | B17: Governmental Banks | C17: Legal, Risk & Compliance | D17: 0.25 | E17: Compliance documentation | F17: 0.25 | G17: Document Generation & Management | H17: 0.95 | J17: 0.43 | K17: 0.43 | L17: 0.4 | M17: 0.35 | N17: 0.32
A18: Government | B18: Governmental Banks | C18: Procurement & Vendor Management | D18: 0.1 | E18: Purchase & vendor administration | F18: 0.25 | G18: Task Processing / Query Handling | H18: 0.9 | I18: =SUMPRODUCT(H18:H21,F18:F21)*D18 -> 0.0595 | J18: 0.44 | K18: 0.44 | L18: 0.41 | M18: 0.36 | N18: 0.33
A19: Government | B19: Governmental Banks | C19: Procurement & Vendor Management | D19: 0.1 | E19: Vendor & spend analysis | F19: 0.25 | G19: Assessment & Analysis | H19: 0.6 | J19: 0.44 | K19: 0.44 | L19: 0.41 | M19: 0.36 | N19: 0.33
A20: Government | B20: Governmental Banks | C20: Procurement & Vendor Management | D20: 0.1 | E20: Vendor relationship management | F20: 0.3 | G20: Stakeholder / Relationship Management | H20: 0.1 | J20: 0.44 | K20: 0.44 | L20: 0.41 | M20: 0.36 | N20: 0.33
A21: Government | B21: Governmental Banks | C21: Procurement & Vendor Management | D21: 0.1 | E21: Procurement documentation | F21: 0.2 | G21: Document Generation & Management | H21: 0.95 | J21: 0.44 | K21: 0.44 | L21: 0.41 | M21: 0.36 | N21: 0.33
A22: Government | B22: Governmental Banks | C22: Corporate Strategy & Administration | D22: 0.1 | E22: Strategic planning | F22: 0.3 | G22: Strategy & Design | H22: 0.3 | I22: =SUMPRODUCT(H22:H25,F22:F25)*D22 -> 0.0455 | J22: 0.33 | K22: 0.33 | L22: 0.3 | M22: 0.26 | N22: 0.23
A23: Government | B23: Governmental Banks | C23: Corporate Strategy & Administration | D23: 0.1 | E23: Management & economic analysis | F23: 0.25 | G23: Assessment & Analysis | H23: 0.6 | J23: 0.33 | K23: 0.33 | L23: 0.3 | M23: 0.26 | N23: 0.23
A24: Government | B24: Governmental Banks | C24: Corporate Strategy & Administration | D24: 0.1 | E24: Executive / institutional coordination | F24: 0.25 | G24: Stakeholder / Relationship Management | H24: 0.1 | J24: 0.33 | K24: 0.33 | L24: 0.3 | M24: 0.26 | N24: 0.23
A25: Government | B25: Governmental Banks | C25: Corporate Strategy & Administration | D25: 0.1 | E25: Corporate reporting | F25: 0.2 | G25: Document Generation & Management | H25: 0.95 | J25: 0.33 | K25: 0.33 | L25: 0.3 | M25: 0.26 | N25: 0.23
I26: =SUM(I2:I22) -> 0.672375 | J26: =+J6*$D6+J10*$D10+J14*$D14+J18*$D18+J22*$D22+$D2*J2 -> 0.5065 | K26: =+K6*$D6+K10*$D10+K14*$D14+K18*$D18+K22*$D22+$D2*K2 -> 0.5065 | L26: =+L6*$D6+L10*$D10+L14*$D14+L18*$D18+L22*$D22+$D2*L2 -> 0.4765 | M26: =+M6*$D6+M10*$D10+M14*$D14+M18*$D18+M22*$D22+$D2*M2 -> 0.4255 | N26: =+N6*$D6+N10*$D10+N14*$D14+N18*$D18+N22*$D22+$D2*N2 -> 0.3955
A28: Government | B28: National Government & Agencies | C28: Finance & Budget Administration | D28: 0.2 | E28: Transaction & expenditure administration | F28: 0.3 | G28: Task Processing / Query Handling | H28: 0.9 | I28: =SUMPRODUCT(H28:H31,F28:F31)*D28 -> 0.1655 | J28: 0.6 | K28: 0.6 | L28: 0.57 | M28: 0.5 | N28: 0.44
A29: Government | B29: National Government & Agencies | C29: Finance & Budget Administration | D29: 0.2 | E29: Budget analysis | F29: 0.25 | G29: Assessment & Analysis | H29: 0.6 | J29: 0.6 | K29: 0.6 | L29: 0.57 | M29: 0.5 | N29: 0.44
A30: Government | B30: National Government & Agencies | C30: Finance & Budget Administration | D30: 0.2 | E30: Budgeting & expenditure forecasting | F30: 0.2 | G30: Modelling (incl. Forecasting) | H30: 0.85 | J30: 0.6 | K30: 0.6 | L30: 0.57 | M30: 0.5 | N30: 0.44
A31: Government | B31: National Government & Agencies | C31: Finance & Budget Administration | D31: 0.2 | E31: Financial & budget reporting | F31: 0.25 | G31: Document Generation & Management | H31: 0.95 | J31: 0.6 | K31: 0.6 | L31: 0.57 | M31: 0.5 | N31: 0.44
A32: Government | B32: National Government & Agencies | C32: Human Resources | D32: 0.2 | E32: Recruitment & personnel administration | F32: 0.25 | G32: Task Processing / Query Handling | H32: 0.9 | I32: =SUMPRODUCT(H32:H35,F32:F35)*D32 -> 0.126 | J32: 0.4 | K32: 0.4 | L32: 0.37 | M32: 0.31 | N32: 0.27
A33: Government | B33: National Government & Agencies | C33: Human Resources | D33: 0.2 | E33: Workforce planning | F33: 0.25 | G33: Task Planning & Management | H33: 0.7 | J33: 0.4 | K33: 0.4 | L33: 0.37 | M33: 0.31 | N33: 0.27
A34: Government | B34: National Government & Agencies | C34: Employee / civil service relations | D34: 0.3 | E34: Stakeholder / Relationship Management | F34: 0.1 | G34: 0.62 | H34: 0.4 | J34: 0.37 | K34: 0.31 | L34: 0.27
A35: Government | B35: National Government & Agencies | C35: Human Resources | D35: 0.2 | E35: Personnel documentation & reporting | F35: 0.2 | G35: Document Generation & Management | H35: 0.95 | J35: 0.4 | K35: 0.4 | L35: 0.37 | M35: 0.31 | N35: 0.27
A36: Government | B36: National Government & Agencies | C36: Corporate IT & Digital Administration | D36: 0.2 | E36: IT service desk & user support | F36: 0.3 | G36: Task Processing / Query Handling | H36: 0.9 | I36: =SUMPRODUCT(H36:H39,F36:F39)*D36 -> 0.162 | J36: 0.58 | K36: 0.58 | L36: 0.55 | M36: 0.48 | N36: 0.43
A37: Government | B37: National Government & Agencies | C37: Corporate IT & Digital Administration | D37: 0.2 | E37: System, infrastructure & security monitoring | F37: 0.25 | G37: Monitoring | H37: 0.7 | J37: 0.58 | K37: 0.58 | L37: 0.55 | M37: 0.48 | N37: 0.43
A38: Government | B38: National Government & Agencies | C38: Corporate IT & Digital Administration | D38: 0.2 | E38: Technology planning & change coordination | F38: 0.25 | G38: Task Planning & Management | H38: 0.7 | J38: 0.58 | K38: 0.58 | L38: 0.55 | M38: 0.48 | N38: 0.43
A39: Government | B39: National Government & Agencies | C39: Corporate IT & Digital Administration | D39: 0.2 | E39: Technology documentation | F39: 0.2 | G39: Document Generation & Management | H39: 0.95 | J39: 0.58 | K39: 0.58 | L39: 0.55 | M39: 0.48 | N39: 0.43
A40: Government | B40: National Government & Agencies | C40: Procurement & Contract Administration | D40: 0.15 | E40: Purchase / tender administration | F40: 0.3 | G40: Task Processing / Query Handling | H40: 0.9 | I40: =SUMPRODUCT(H40:H43,F40:F43)*D40 -> 0.09525 | J40: 0.42 | K40: 0.42 | L40: 0.39 | M40: 0.33 | N40: 0.28
A41: Government | B41: National Government & Agencies | C41: Procurement & Contract Administration | D41: 0.15 | E41: Bid / vendor assessment | F41: 0.25 | G41: Assessment & Analysis | H41: 0.6 | J41: 0.42 | K41: 0.42 | L41: 0.39 | M41: 0.33 | N41: 0.28
A42: Government | B42: National Government & Agencies | C42: Procurement & Contract Administration | D42: 0.15 | E42: Vendor & contractor management | F42: 0.25 | G42: Stakeholder / Relationship Management | H42: 0.1 | J42: 0.42 | K42: 0.42 | L42: 0.39 | M42: 0.33 | N42: 0.28
A43: Government | B43: National Government & Agencies | C43: Procurement & Contract Administration | D43: 0.15 | E43: Tender & contract documentation | F43: 0.2 | G43: Document Generation & Management | H43: 0.95 | J43: 0.42 | K43: 0.42 | L43: 0.39 | M43: 0.33 | N43: 0.28
A44: Government | B44: National Government & Agencies | C44: Legal, Ethics & Internal Compliance | D44: 0.15 | E44: Legal / ethics monitoring | F44: 0.25 | G44: Monitoring | H44: 0.7 | I44: =SUMPRODUCT(H44:H47,F44:F47)*D44 -> 0.088125 | J44: 0.4 | K44: 0.4 | L44: 0.37 | M44: 0.31 | N44: 0.26
A45: Government | B45: National Government & Agencies | C45: Legal, Ethics & Internal Compliance | D45: 0.15 | E45: Policy & legal review | F45: 0.25 | G45: Assessment & Analysis | H45: 0.6 | J45: 0.4 | K45: 0.4 | L45: 0.37 | M45: 0.31 | N45: 0.26
A46: Government | B46: National Government & Agencies | C46: Legal, Ethics & Internal Compliance | D46: 0.15 | E46: Legal / oversight stakeholder coordination | F46: 0.25 | G46: Stakeholder / Relationship Management | H46: 0.1 | J46: 0.4 | K46: 0.4 | L46: 0.37 | M46: 0.31 | N46: 0.26
A47: Government | B47: National Government & Agencies | C47: Legal, Ethics & Internal Compliance | D47: 0.15 | E47: Legal & compliance documentation | F47: 0.25 | G47: Document Generation & Management | H47: 0.95 | J47: 0.4 | K47: 0.4 | L47: 0.37 | M47: 0.31 | N47: 0.26
A48: Government | B48: National Government & Agencies | C48: Executive & General Administration | D48: 0.1 | E48: Executive planning | F48: 0.3 | G48: Strategy & Design | H48: 0.3 | I48: =SUMPRODUCT(H48:H51,F48:F51)*D48 -> 0.0455 | J48: 0.3 | K48: 0.3 | L48: 0.27 | M48: 0.22 | N48: 0.19
A49: Government | B49: National Government & Agencies | C49: Executive & General Administration | D49: 0.1 | E49: Management analysis & briefing | F49: 0.25 | G49: Assessment & Analysis | H49: 0.6 | J49: 0.3 | K49: 0.3 | L49: 0.27 | M49: 0.22 | N49: 0.19
A50: Government | B50: National Government & Agencies | C50: Executive & General Administration | D50: 0.1 | E50: Inter-agency / executive coordination | F50: 0.25 | G50: Stakeholder / Relationship Management | H50: 0.1 | J50: 0.3 | K50: 0.3 | L50: 0.27 | M50: 0.22 | N50: 0.19
A51: Government | B51: National Government & Agencies | C51: Executive & General Administration | D51: 0.1 | E51: Executive documentation & reporting | F51: 0.2 | G51: Document Generation & Management | H51: 0.95 | J51: 0.3 | K51: 0.3 | L51: 0.27 | M51: 0.22 | N51: 0.19
I52: =SUM(I28:I48) -> 0.682375 | J52: =+J32*$D32+J36*$D36+J40*$D40+J44*$D44+J48*$D48+$D28*J28 -> 0.469 | K52: =+K32*$D32+K36*$D36+K40*$D40+K44*$D44+K48*$D48+$D28*K28 -> 0.469 | L52: =+L32*$D32+L36*$D36+L40*$D40+L44*$D44+L48*$D48+$D28*L28 -> 0.439 | M52: =+M32*$D32+M36*$D36+M40*$D40+M44*$D44+M48*$D48+$D28*M28 -> 0.376 | N52: =+N32*$D32+N36*$D36+N40*$D40+N44*$D44+N48*$D48+$D28*N28 -> 0.328
A54: Government | B54: Local & Regional Government | C54: Finance & Accounting | D54: 0.2 | E54: Transaction & payment processing | F54: 0.3 | G54: Task Processing / Query Handling | H54: 0.9 | I54: =SUMPRODUCT(H54:H57,F54:F57)*D54 -> 0.1655 | J54: 0.57 | K54: 0.57 | L54: 0.53 | M54: 0.46 | N54: 0.39
A55: Government | B55: Local & Regional Government | C55: Finance & Accounting | D55: 0.2 | E55: Financial planning & analysis | F55: 0.25 | G55: Assessment & Analysis | H55: 0.6 | J55: 0.57 | K55: 0.57 | L55: 0.53 | M55: 0.46 | N55: 0.39
A56: Government | B56: Local & Regional Government | C56: Finance & Accounting | D56: 0.2 | E56: Budgeting & revenue forecasting | F56: 0.2 | G56: Modelling (incl. Forecasting) | H56: 0.85 | J56: 0.57 | K56: 0.57 | L56: 0.53 | M56: 0.46 | N56: 0.39
A57: Government | B57: Local & Regional Government | C57: Finance & Accounting | D57: 0.2 | E57: Financial reporting | F57: 0.25 | G57: Document Generation & Management | H57: 0.95 | J57: 0.57 | K57: 0.57 | L57: 0.53 | M57: 0.46 | N57: 0.39
A58: Government | B58: Local & Regional Government | C58: Human Resources | D58: 0.2 | E58: Recruitment & personnel administration | F58: 0.25 | G58: Task Processing / Query Handling | H58: 0.9 | I58: =SUMPRODUCT(H58:H61,F58:F61)*D58 -> 0.124 | J58: 0.38 | K58: 0.38 | L58: 0.35 | M58: 0.29 | N58: 0.24
A59: Government | B59: Local & Regional Government | C59: Human Resources | D59: 0.2 | E59: Workforce planning | F59: 0.25 | G59: Task Planning & Management | H59: 0.7 | J59: 0.38 | K59: 0.38 | L59: 0.35 | M59: 0.29 | N59: 0.24
A60: Government | B60: Local & Regional Government | C60: Human Resources | D60: 0.2 | E60: Employee / labour relations | F60: 0.3 | G60: Stakeholder / Relationship Management | H60: 0.1 | J60: 0.38 | K60: 0.38 | L60: 0.35 | M60: 0.29 | N60: 0.24
A61: Government | B61: Local & Regional Government | C61: Human Resources | D61: 0.2 | E61: HR documentation & reporting | F61: 0.2 | G61: Document Generation & Management | H61: 0.95 | J61: 0.38 | K61: 0.38 | L61: 0.35 | M61: 0.29 | N61: 0.24
A62: Government | B62: Local & Regional Government | C62: Corporate IT & Digital Administration | D62: 0.15 | E62: IT service desk & user support | F62: 0.3 | G62: Task Processing / Query Handling | H62: 0.9 | I62: =SUMPRODUCT(H62:H65,F62:F65)*D62 -> 0.1215 | J62: 0.53 | K62: 0.53 | L62: 0.5 | M62: 0.43 | N62: 0.37
A63: Government | B63: Local & Regional Government | C63: Corporate IT & Digital Administration | D63: 0.15 | E63: System, infrastructure & security monitoring | F63: 0.25 | G63: Monitoring | H63: 0.7 | J63: 0.53 | K63: 0.53 | L63: 0.5 | M63: 0.43 | N63: 0.37
A64: Government | B64: Local & Regional Government | C64: Corporate IT & Digital Administration | D64: 0.15 | E64: Technology planning & change coordination | F64: 0.25 | G64: Task Planning & Management | H64: 0.7 | J64: 0.53 | K64: 0.53 | L64: 0.5 | M64: 0.43 | N64: 0.37
A65: Government | B65: Local & Regional Government | C65: Corporate IT & Digital Administration | D65: 0.15 | E65: IT documentation | F65: 0.2 | G65: Document Generation & Management | H65: 0.95 | J65: 0.53 | K65: 0.53 | L65: 0.5 | M65: 0.43 | N65: 0.37
A66: Government | B66: Local & Regional Government | C66: Procurement & Vendor Management | D66: 0.15 | E66: Purchase / tender administration | F66: 0.3 | G66: Task Processing / Query Handling | H66: 0.9 | I66: =SUMPRODUCT(H66:H69,F66:F69)*D66 -> 0.09525 | J66: 0.39 | K66: 0.39 | L66: 0.36 | M66: 0.3 | N66: 0.25
A67: Government | B67: Local & Regional Government | C67: Procurement & Vendor Management | D67: 0.15 | E67: Vendor / bid assessment | F67: 0.25 | G67: Assessment & Analysis | H67: 0.6 | J67: 0.39 | K67: 0.39 | L67: 0.36 | M67: 0.3 | N67: 0.25
A68: Government | B68: Local & Regional Government | C68: Procurement & Vendor Management | D68: 0.15 | E68: Vendor / contractor management | F68: 0.25 | G68: Stakeholder / Relationship Management | H68: 0.1 | J68: 0.39 | K68: 0.39 | L68: 0.36 | M68: 0.3 | N68: 0.25
A69: Government | B69: Local & Regional Government | C69: Procurement & Vendor Management | D69: 0.15 | E69: Tender & procurement documentation | F69: 0.2 | G69: Document Generation & Management | H69: 0.95 | J69: 0.39 | K69: 0.39 | L69: 0.36 | M69: 0.3 | N69: 0.25
A70: Government | B70: Local & Regional Government | C70: Legal, Risk & Compliance | D70: 0.15 | E70: Compliance / policy monitoring | F70: 0.25 | G70: Monitoring | H70: 0.7 | I70: =SUMPRODUCT(H70:H73,F70:F73)*D70 -> 0.088125 | J70: 0.37 | K70: 0.37 | L70: 0.34 | M70: 0.28 | N70: 0.23
A71: Government | B71: Local & Regional Government | C71: Legal, Risk & Compliance | D71: 0.15 | E71: Contract & policy review | F71: 0.25 | G71: Assessment & Analysis | H71: 0.6 | J71: 0.37 | K71: 0.37 | L71: 0.34 | M71: 0.28 | N71: 0.23
A72: Government | B72: Local & Regional Government | C72: Legal, Risk & Compliance | D72: 0.15 | E72: Legal / oversight stakeholder coordination | F72: 0.25 | G72: Stakeholder / Relationship Management | H72: 0.1 | J72: 0.37 | K72: 0.37 | L72: 0.34 | M72: 0.28 | N72: 0.23
A73: Government | B73: Local & Regional Government | C73: Legal, Risk & Compliance | D73: 0.15 | E73: Compliance documentation | F73: 0.25 | G73: Document Generation & Management | H73: 0.95 | J73: 0.37 | K73: 0.37 | L73: 0.34 | M73: 0.28 | N73: 0.23
A74: Government | B74: Local & Regional Government | C74: General Administration & Management | D74: 0.15 | E74: Administrative / strategic planning | F74: 0.3 | G74: Strategy & Design | H74: 0.3 | I74: =SUMPRODUCT(H74:H77,F74:F77)*D74 -> 0.06825 | J74: 0.28 | K74: 0.28 | L74: 0.25 | M74: 0.21 | N74: 0.17
A75: Government | B75: Local & Regional Government | C75: General Administration & Management | D75: 0.15 | E75: Performance / management analysis | F75: 0.25 | G75: Assessment & Analysis | H75: 0.6 | J75: 0.28 | K75: 0.28 | L75: 0.25 | M75: 0.21 | N75: 0.17
A76: Government | B76: Local & Regional Government | C76: General Administration & Management | D76: 0.15 | E76: Executive / departmental coordination | F76: 0.25 | G76: Stakeholder / Relationship Management | H76: 0.1 | J76: 0.28 | K76: 0.28 | L76: 0.25 | M76: 0.21 | N76: 0.17
A77: Government | B77: Local & Regional Government | C77: General Administration & Management | D77: 0.15 | E77: Administrative reporting | F77: 0.2 | G77: Document Generation & Management | H77: 0.95 | J77: 0.28 | K77: 0.28 | L77: 0.25 | M77: 0.21 | N77: 0.17
A78: Government | B78: Local & Regional Government | C78: Communications & Public Engagement | D78: 0.15 | E78: Public information content | F78: 0.3 | G78: Content Generation | H78: 0.7 | I78: =SUMPRODUCT(H78:H81,F78:F81)*D78 -> 0.07875 | J78: 0.32 | K78: 0.32 | L78: 0.29 | M78: 0.24 | N78: 0.2
A79: Government | B79: Local & Regional Government | C79: Communications & Public Engagement | D79: 0.15 | E79: Citizen / community sentiment analysis | F79: 0.25 | G79: Assessment & Analysis | H79: 0.6 | J79: 0.32 | K79: 0.32 | L79: 0.29 | M79: 0.24 | N79: 0.2
A80: Government | B80: Local & Regional Government | C80: Communications & Public Engagement | D80: 0.15 | E80: Engagement planning | F80: 0.2 | G80: Task Planning & Management | H80: 0.7 | J80: 0.32 | K80: 0.32 | L80: 0.29 | M80: 0.24 | N80: 0.2
A81: Government | B81: Local & Regional Government | C81: Communications & Public Engagement | D81: 0.15 | E81: Community / stakeholder coordination | F81: 0.25 | G81: Stakeholder / Relationship Management | H81: 0.1 | J81: 0.32 | K81: 0.32 | L81: 0.29 | M81: 0.24 | N81: 0.2
I82: =SUM(I54:I78) -> 0.741375 | J82: =+J62*$D62+J66*$D66+J70*$D70+J74*$D74+J78*$D78+$D58*J58+$D54*J54 -> 0.4735 | K82: =+K62*$D62+K66*$D66+K70*$D70+K74*$D74+K78*$D78+$D58*K58+$D54*K54 -> 0.4735 | L82: =+L62*$D62+L66*$D66+L70*$D70+L74*$D74+L78*$D78+$D58*L58+$D54*L54 -> 0.437 | M82: =+M62*$D62+M66*$D66+M70*$D70+M74*$D74+M78*$D78+$D58*M58+$D54*M54 -> 0.369 | N82: =+N62*$D62+N66*$D66+N70*$D70+N74*$D74+N78*$D78+$D58*N58+$D54*N54 -> 0.309

Sheet Real Estate
A1: Sector | B1: Subsector | C1: Core Activity | D1: Effort Split | E1: Key Main Task | F1: % Effort | G1: Category | H1: AI Addressable | I1: Agentification Potential | J1: Actual Agentification Possible | K1: NA | L1: EU | M1: APAC ex India | N1: India
A2: Real Estate | B2: Traditional REITs | C2: Finance & Accounting | D2: 0.25 | E2: Transaction processing & reconciliation | F2: 0.3 | G2: Task Processing / Query Handling | H2: 0.9 | I2: =SUMPRODUCT(H2:H5,F2:F5)*D2 -> 0.206875 | J2: 0.66 | K2: 0.66 | L2: 0.63 | M2: 0.57 | N2: 0.52
A3: Real Estate | B3: Traditional REITs | C3: Finance & Accounting | D3: 0.25 | E3: Financial planning & analysis | F3: 0.25 | G3: Assessment & Analysis | H3: 0.6 | J3: 0.66 | K3: 0.66 | L3: 0.63 | M3: 0.57 | N3: 0.52
A4: Real Estate | B4: Traditional REITs | C4: Finance & Accounting | D4: 0.25 | E4: Budgeting & forecasting | F4: 0.2 | G4: Modelling (incl. Forecasting) | H4: 0.85 | J4: 0.66 | K4: 0.66 | L4: 0.63 | M4: 0.57 | N4: 0.52
A5: Real Estate | B5: Traditional REITs | C5: Finance & Accounting | D5: 0.25 | E5: Financial reporting | F5: 0.25 | G5: Document Generation & Management | H5: 0.95 | J5: 0.66 | K5: 0.66 | L5: 0.63 | M5: 0.57 | N5: 0.52
A6: Real Estate | B6: Traditional REITs | C6: Investor Relations & Capital Markets | D6: 0.15 | E6: Investor materials preparation | F6: 0.25 | G6: Document Generation & Management | H6: 0.95 | I6: =SUMPRODUCT(H6:H9,F6:F9)*D6 -> 0.091125 | J6: 0.43 | K6: 0.43 | L6: 0.4 | M6: 0.35 | N6: 0.31
A7: Real Estate | B7: Traditional REITs | C7: Investor Relations & Capital Markets | D7: 0.15 | E7: Investor / market analysis | F7: 0.25 | G7: Assessment & Analysis | H7: 0.6 | J7: 0.43 | K7: 0.43 | L7: 0.4 | M7: 0.35 | N7: 0.31
A8: Real Estate | B8: Traditional REITs | C8: Investor Relations & Capital Markets | D8: 0.15 | E8: Investor & lender relationship management | F8: 0.3 | G8: Stakeholder / Relationship Management | H8: 0.1 | J8: 0.43 | K8: 0.43 | L8: 0.4 | M8: 0.35 | N8: 0.31
A9: Real Estate | B9: Traditional REITs | C9: Investor Relations & Capital Markets | D9: 0.15 | E9: Disclosure & investor reporting | F9: 0.2 | G9: Document Generation & Management | H9: 0.95 | J9: 0.43 | K9: 0.43 | L9: 0.4 | M9: 0.35 | N9: 0.31
A10: Real Estate | B10: Traditional REITs | C10: Human Resources | D10: 0.1 | E10: Recruitment administration | F10: 0.25 | G10: Task Processing / Query Handling | H10: 0.9 | I10: =SUMPRODUCT(H10:H13,F10:F13)*D10 -> 0.062 | J10: 0.45 | K10: 0.45 | L10: 0.42 | M10: 0.37 | N10: 0.32
A11: Real Estate | B11: Traditional REITs | C11: Human Resources | D11: 0.1 | E11: Workforce planning | F11: 0.25 | G11: Task Planning & Management | H11: 0.7 | J11: 0.45 | K11: 0.45 | L11: 0.42 | M11: 0.37 | N11: 0.32
A12: Real Estate | B12: Traditional REITs | C12: Human Resources | D12: 0.1 | E12: Employee relations & support | F12: 0.3 | G12: Stakeholder / Relationship Management | H12: 0.1 | J12: 0.45 | K12: 0.45 | L12: 0.42 | M12: 0.37 | N12: 0.32
A13: Real Estate | B13: Traditional REITs | C13: Human Resources | D13: 0.1 | E13: HR documentation & reporting | F13: 0.2 | G13: Document Generation & Management | H13: 0.95 | J13: 0.45 | K13: 0.45 | L13: 0.42 | M13: 0.37 | N13: 0.32
A14: Real Estate | B14: Traditional REITs | C14: Corporate IT & Enterprise Technology | D14: 0.15 | E14: IT service desk & user support | F14: 0.3 | G14: Task Processing / Query Handling | H14: 0.9 | I14: =SUMPRODUCT(H14:H17,F14:F17)*D14 -> 0.1215 | J14: 0.65 | K14: 0.65 | L14: 0.62 | M14: 0.57 | N14: 0.52
A15: Real Estate | B15: Traditional REITs | C15: Corporate IT & Enterprise Technology | D15: 0.15 | E15: Application & infrastructure monitoring | F15: 0.25 | G15: Monitoring | H15: 0.7 | J15: 0.65 | K15: 0.65 | L15: 0.62 | M15: 0.57 | N15: 0.52
A16: Real Estate | B16: Traditional REITs | C16: Corporate IT & Enterprise Technology | D16: 0.15 | E16: Technology planning & change coordination | F16: 0.25 | G16: Task Planning & Management | H16: 0.7 | J16: 0.65 | K16: 0.65 | L16: 0.62 | M16: 0.57 | N16: 0.52
A17: Real Estate | B17: Traditional REITs | C17: Corporate IT & Enterprise Technology | D17: 0.15 | E17: IT documentation | F17: 0.2 | G17: Document Generation & Management | H17: 0.95 | J17: 0.65 | K17: 0.65 | L17: 0.62 | M17: 0.57 | N17: 0.52
A18: Real Estate | B18: Traditional REITs | C18: Legal, Risk & Compliance | D18: 0.2 | E18: Regulatory / compliance monitoring | F18: 0.25 | G18: Monitoring | H18: 0.7 | I18: =SUMPRODUCT(H18:H21,F18:F21)*D18 -> 0.1175 | J18: 0.43 | K18: 0.43 | L18: 0.4 | M18: 0.35 | N18: 0.3
A19: Real Estate | B19: Traditional REITs | C19: Legal, Risk & Compliance | D19: 0.2 | E19: Lease / corporate contract review | F19: 0.25 | G19: Assessment & Analysis | H19: 0.6 | J19: 0.43 | K19: 0.43 | L19: 0.4 | M19: 0.35 | N19: 0.3
A20: Real Estate | B20: Traditional REITs | C20: Legal, Risk & Compliance | D20: 0.2 | E20: Legal / regulatory stakeholder management | F20: 0.25 | G20: Stakeholder / Relationship Management | H20: 0.1 | J20: 0.43 | K20: 0.43 | L20: 0.4 | M20: 0.35 | N20: 0.3
A21: Real Estate | B21: Traditional REITs | C21: Legal, Risk & Compliance | D21: 0.2 | E21: Compliance documentation | F21: 0.25 | G21: Document Generation & Management | H21: 0.95 | J21: 0.43 | K21: 0.43 | L21: 0.4 | M21: 0.35 | N21: 0.3
A22: Real Estate | B22: Traditional REITs | C22: Corporate Strategy & Administration | D22: 0.15 | E22: Portfolio / corporate strategic planning | F22: 0.3 | G22: Strategy & Design | H22: 0.3 | I22: =SUMPRODUCT(H22:H25,F22:F25)*D22 -> 0.06825 | J22: 0.34 | K22: 0.34 | L22: 0.31 | M22: 0.27 | N22: 0.23
A23: Real Estate | B23: Traditional REITs | C23: Corporate Strategy & Administration | D23: 0.15 | E23: Management & market analysis | F23: 0.25 | G23: Assessment & Analysis | H23: 0.6 | J23: 0.34 | K23: 0.34 | L23: 0.31 | M23: 0.27 | N23: 0.23
A24: Real Estate | B24: Traditional REITs | C24: Corporate Strategy & Administration | D24: 0.15 | E24: Executive stakeholder coordination | F24: 0.25 | G24: Stakeholder / Relationship Management | H24: 0.1 | J24: 0.34 | K24: 0.34 | L24: 0.31 | M24: 0.27 | N24: 0.23
A25: Real Estate | B25: Traditional REITs | C25: Corporate Strategy & Administration | D25: 0.15 | E25: Corporate reporting | F25: 0.2 | G25: Document Generation & Management | H25: 0.95 | J25: 0.34 | K25: 0.34 | L25: 0.31 | M25: 0.27 | N25: 0.23
I26: =SUM(I2:I22) -> 0.66725 | J26: =+J6*$D6+J10*$D10+J14*$D14+J18*$D18+J22*$D22+$D2*J2 -> 0.509 | K26: =+K6*$D6+K10*$D10+K14*$D14+K18*$D18+K22*$D22+$D2*K2 -> 0.509 | L26: =+L6*$D6+L10*$D10+L14*$D14+L18*$D18+L22*$D22+$D2*L2 -> 0.479 | M26: =+M6*$D6+M10*$D10+M14*$D14+M18*$D18+M22*$D22+$D2*M2 -> 0.428 | N26: =+N6*$D6+N10*$D10+N14*$D14+N18*$D18+N22*$D22+$D2*N2 -> 0.381
A28: Real Estate | B28: Hospitality REITs | C28: Finance & Accounting | D28: 0.25 | E28: Transaction processing & reconciliation | F28: 0.3 | G28: Task Processing / Query Handling | H28: 0.9 | I28: =SUMPRODUCT(H28:H31,F28:F31)*D28 -> 0.206875 | J28: 0.65 | K28: 0.65 | L28: 0.62 | M28: 0.56 | N28: 0.5
A29: Real Estate | B29: Hospitality REITs | C29: Finance & Accounting | D29: 0.25 | E29: Financial planning & analysis | F29: 0.25 | G29: Assessment & Analysis | H29: 0.6 | J29: 0.65 | K29: 0.65 | L29: 0.62 | M29: 0.56 | N29: 0.5
A30: Real Estate | B30: Hospitality REITs | C30: Finance & Accounting | D30: 0.25 | E30: Budgeting & forecasting | F30: 0.2 | G30: Modelling (incl. Forecasting) | H30: 0.85 | J30: 0.65 | K30: 0.65 | L30: 0.62 | M30: 0.56 | N30: 0.5
A31: Real Estate | B31: Hospitality REITs | C31: Finance & Accounting | D31: 0.25 | E31: Financial reporting | F31: 0.25 | G31: Document Generation & Management | H31: 0.95 | J31: 0.65 | K31: 0.65 | L31: 0.62 | M31: 0.56 | N31: 0.5
A32: Real Estate | B32: Hospitality REITs | C32: Investor Relations & Capital Markets | D32: 0.15 | E32: Investor materials preparation | F32: 0.25 | G32: Document Generation & Management | H32: 0.95 | I32: =SUMPRODUCT(H32:H35,F32:F35)*D32 -> 0.091125 | J32: 0.42 | K32: 0.42 | L32: 0.39 | M32: 0.34 | N32: 0.29
A33: Real Estate | B33: Hospitality REITs | C33: Investor Relations & Capital Markets | D33: 0.15 | E33: Investor / market analysis | F33: 0.25 | G33: Assessment & Analysis | H33: 0.6 | J33: 0.42 | K33: 0.42 | L33: 0.39 | M33: 0.34 | N33: 0.29
A34: Real Estate | B34: Hospitality REITs | C34: Investor Relations & Capital Markets | D34: 0.15 | E34: Investor & lender relationship management | F34: 0.3 | G34: Stakeholder / Relationship Management | H34: 0.1 | J34: 0.42 | K34: 0.42 | L34: 0.39 | M34: 0.34 | N34: 0.29
A35: Real Estate | B35: Hospitality REITs | C35: Investor Relations & Capital Markets | D35: 0.15 | E35: Disclosure & investor reporting | F35: 0.2 | G35: Document Generation & Management | H35: 0.95 | J35: 0.42 | K35: 0.42 | L35: 0.39 | M35: 0.34 | N35: 0.29
A36: Real Estate | B36: Hospitality REITs | C36: Human Resources | D36: 0.1 | E36: Recruitment administration | F36: 0.25 | G36: Task Processing / Query Handling | H36: 0.9 | I36: =SUMPRODUCT(H36:H39,F36:F39)*D36 -> 0.062 | J36: 0.43 | K36: 0.43 | L36: 0.4 | M36: 0.35 | N36: 0.29
A37: Real Estate | B37: Hospitality REITs | C37: Human Resources | D37: 0.1 | E37: Corporate workforce planning | F37: 0.25 | G37: Task Planning & Management | H37: 0.7 | J37: 0.43 | K37: 0.43 | L37: 0.4 | M37: 0.35 | N37: 0.29
A38: Real Estate | B38: Hospitality REITs | C38: Human Resources | D38: 0.1 | E38: Employee relations & support | F38: 0.3 | G38: Stakeholder / Relationship Management | H38: 0.1 | J38: 0.43 | K38: 0.43 | L38: 0.4 | M38: 0.35 | N38: 0.29
A39: Real Estate | B39: Hospitality REITs | C39: Human Resources | D39: 0.1 | E39: HR documentation & reporting | F39: 0.2 | G39: Document Generation & Management | H39: 0.95 | J39: 0.43 | K39: 0.43 | L39: 0.4 | M39: 0.35 | N39: 0.29
A40: Real Estate | B40: Hospitality REITs | C40: Corporate IT & Enterprise Technology | D40: 0.15 | E40: IT service desk & user support | F40: 0.3 | G40: Task Processing / Query Handling | H40: 0.9 | I40: =SUMPRODUCT(H40:H43,F40:F43)*D40 -> 0.1215 | J40: 0.63 | K40: 0.63 | L40: 0.6 | M40: 0.54 | N40: 0.48
A41: Real Estate | B41: Hospitality REITs | C41: Corporate IT & Enterprise Technology | D41: 0.15 | E41: Application & infrastructure monitoring | F41: 0.25 | G41: Monitoring | H41: 0.7 | J41: 0.63 | K41: 0.63 | L41: 0.6 | M41: 0.54 | N41: 0.48
A42: Real Estate | B42: Hospitality REITs | C42: Corporate IT & Enterprise Technology | D42: 0.15 | E42: Technology planning & change coordination | F42: 0.25 | G42: Task Planning & Management | H42: 0.7 | J42: 0.63 | K42: 0.63 | L42: 0.6 | M42: 0.54 | N42: 0.48
A43: Real Estate | B43: Hospitality REITs | C43: Corporate IT & Enterprise Technology | D43: 0.15 | E43: IT documentation | F43: 0.2 | G43: Document Generation & Management | H43: 0.95 | J43: 0.63 | K43: 0.63 | L43: 0.6 | M43: 0.54 | N43: 0.48
A44: Real Estate | B44: Hospitality REITs | C44: Legal, Risk & Compliance | D44: 0.2 | E44: Regulatory / compliance monitoring | F44: 0.25 | G44: Monitoring | H44: 0.7 | I44: =SUMPRODUCT(H44:H47,F44:F47)*D44 -> 0.1175 | J44: 0.42 | K44: 0.42 | L44: 0.39 | M44: 0.34 | N44: 0.28
A45: Real Estate | B45: Hospitality REITs | C45: Legal, Risk & Compliance | D45: 0.2 | E45: Contract & policy review | F45: 0.25 | G45: Assessment & Analysis | H45: 0.6 | J45: 0.42 | K45: 0.42 | L45: 0.39 | M45: 0.34 | N45: 0.28
A46: Real Estate | B46: Hospitality REITs | C46: Legal, Risk & Compliance | D46: 0.2 | E46: Legal / regulatory stakeholder management | F46: 0.25 | G46: Stakeholder / Relationship Management | H46: 0.1 | J46: 0.42 | K46: 0.42 | L46: 0.39 | M46: 0.34 | N46: 0.28
A47: Real Estate | B47: Hospitality REITs | C47: Legal, Risk & Compliance | D47: 0.2 | E47: Compliance documentation | F47: 0.25 | G47: Document Generation & Management | H47: 0.95 | J47: 0.42 | K47: 0.42 | L47: 0.39 | M47: 0.34 | N47: 0.28
A48: Real Estate | B48: Hospitality REITs | C48: Corporate Strategy & Administration | D48: 0.15 | E48: Portfolio / corporate strategic planning | F48: 0.3 | G48: Strategy & Design | H48: 0.3 | I48: =SUMPRODUCT(H48:H51,F48:F51)*D48 -> 0.06825 | J48: 0.33 | K48: 0.33 | L48: 0.3 | M48: 0.26 | N48: 0.21
A49: Real Estate | B49: Hospitality REITs | C49: Corporate Strategy & Administration | D49: 0.15 | E49: Management & market analysis | F49: 0.25 | G49: Assessment & Analysis | H49: 0.6 | J49: 0.33 | K49: 0.33 | L49: 0.3 | M49: 0.26 | N49: 0.21
A50: Real Estate | B50: Hospitality REITs | C50: Corporate Strategy & Administration | D50: 0.15 | E50: Executive / operator stakeholder coordination | F50: 0.25 | G50: Stakeholder / Relationship Management | H50: 0.1 | J50: 0.33 | K50: 0.33 | L50: 0.3 | M50: 0.26 | N50: 0.21
A51: Real Estate | B51: Hospitality REITs | C51: Corporate Strategy & Administration | D51: 0.15 | E51: Corporate reporting | F51: 0.2 | G51: Document Generation & Management | H51: 0.95 | J51: 0.33 | K51: 0.33 | L51: 0.3 | M51: 0.26 | N51: 0.21
I52: =SUM(I28:I48) -> 0.66725 | J52: =+J32*$D32+J36*$D36+J40*$D40+J44*$D44+J48*$D48+$D28*J28 -> 0.4965 | K52: =+K32*$D32+K36*$D36+K40*$D40+K44*$D44+K48*$D48+$D28*K28 -> 0.4965 | L52: =+L32*$D32+L36*$D36+L40*$D40+L44*$D44+L48*$D48+$D28*L28 -> 0.4665 | M52: =+M32*$D32+M36*$D36+M40*$D40+M44*$D44+M48*$D48+$D28*M28 -> 0.414 | N52: =+N32*$D32+N36*$D36+N40*$D40+N44*$D44+N48*$D48+$D28*N28 -> 0.357
A54: Real Estate | B54: Specialized REITs | C54: Finance & Accounting | D54: 0.25 | E54: Transaction processing & reconciliation | F54: 0.3 | G54: Task Processing / Query Handling | H54: 0.9 | I54: =SUMPRODUCT(H54:H57,F54:F57)*D54 -> 0.206875 | J54: 0.67 | K54: 0.67 | L54: 0.64 | M54: 0.59 | N54: 0.55
A55: Real Estate | B55: Specialized REITs | C55: Finance & Accounting | D55: 0.25 | E55: Financial planning & analysis | F55: 0.25 | G55: Assessment & Analysis | H55: 0.6 | J55: 0.67 | K55: 0.67 | L55: 0.64 | M55: 0.59 | N55: 0.55
A56: Real Estate | B56: Specialized REITs | C56: Finance & Accounting | D56: 0.25 | E56: Budgeting & forecasting | F56: 0.2 | G56: Modelling (incl. Forecasting) | H56: 0.85 | J56: 0.67 | K56: 0.67 | L56: 0.64 | M56: 0.59 | N56: 0.55
A57: Real Estate | B57: Specialized REITs | C57: Finance & Accounting | D57: 0.25 | E57: Financial reporting | F57: 0.25 | G57: Document Generation & Management | H57: 0.95 | J57: 0.67 | K57: 0.67 | L57: 0.64 | M57: 0.59 | N57: 0.55
A58: Real Estate | B58: Specialized REITs | C58: Investor Relations & Capital Markets | D58: 0.15 | E58: Investor materials preparation | F58: 0.25 | G58: Document Generation & Management | H58: 0.95 | I58: =SUMPRODUCT(H58:H61,F58:F61)*D58 -> 0.091125 | J58: 0.44 | K58: 0.44 | L58: 0.41 | M58: 0.36 | N58: 0.32
A59: Real Estate | B59: Specialized REITs | C59: Investor Relations & Capital Markets | D59: 0.15 | E59: Investor / market analysis | F59: 0.25 | G59: Assessment & Analysis | H59: 0.6 | J59: 0.44 | K59: 0.44 | L59: 0.41 | M59: 0.36 | N59: 0.32
A60: Real Estate | B60: Specialized REITs | C60: Investor Relations & Capital Markets | D60: 0.15 | E60: Investor & lender relationship management | F60: 0.3 | G60: Stakeholder / Relationship Management | H60: 0.1 | J60: 0.44 | K60: 0.44 | L60: 0.41 | M60: 0.36 | N60: 0.32
A61: Real Estate | B61: Specialized REITs | C61: Investor Relations & Capital Markets | D61: 0.15 | E61: Disclosure & investor reporting | F61: 0.2 | G61: Document Generation & Management | H61: 0.95 | J61: 0.44 | K61: 0.44 | L61: 0.41 | M61: 0.36 | N61: 0.32
A62: Real Estate | B62: Specialized REITs | C62: Human Resources | D62: 0.1 | E62: Recruitment administration | F62: 0.25 | G62: Task Processing / Query Handling | H62: 0.9 | I62: =SUMPRODUCT(H62:H65,F62:F65)*D62 -> 0.062 | J62: 0.46 | K62: 0.46 | L62: 0.43 | M62: 0.38 | N62: 0.34
A63: Real Estate | B63: Specialized REITs | C63: Human Resources | D63: 0.1 | E63: Workforce planning | F63: 0.25 | G63: Task Planning & Management | H63: 0.7 | J63: 0.46 | K63: 0.46 | L63: 0.43 | M63: 0.38 | N63: 0.34
A64: Real Estate | B64: Specialized REITs | C64: Human Resources | D64: 0.1 | E64: Employee relations & support | F64: 0.3 | G64: Stakeholder / Relationship Management | H64: 0.1 | J64: 0.46 | K64: 0.46 | L64: 0.43 | M64: 0.38 | N64: 0.34
A65: Real Estate | B65: Specialized REITs | C65: Human Resources | D65: 0.1 | E65: HR documentation & reporting | F65: 0.2 | G65: Document Generation & Management | H65: 0.95 | J65: 0.46 | K65: 0.46 | L65: 0.43 | M65: 0.38 | N65: 0.34
A66: Real Estate | B66: Specialized REITs | C66: Corporate IT & Enterprise Technology | D66: 0.2 | E66: IT service desk & user support | F66: 0.3 | G66: Task Processing / Query Handling | H66: 0.9 | I66: =SUMPRODUCT(H66:H69,F66:F69)*D66 -> 0.162 | J66: 0.68 | K66: 0.68 | L66: 0.65 | M66: 0.6 | N66: 0.57
A67: Real Estate | B67: Specialized REITs | C67: Corporate IT & Enterprise Technology | D67: 0.2 | E67: Application, infrastructure & asset-system monitoring | F67: 0.25 | G67: Monitoring | H67: 0.7 | J67: 0.68 | K67: 0.68 | L67: 0.65 | M67: 0.6 | N67: 0.57
A68: Real Estate | B68: Specialized REITs | C68: Corporate IT & Enterprise Technology | D68: 0.2 | E68: Technology planning & change coordination | F68: 0.25 | G68: Task Planning & Management | H68: 0.7 | J68: 0.68 | K68: 0.68 | L68: 0.65 | M68: 0.6 | N68: 0.57
A69: Real Estate | B69: Specialized REITs | C69: Corporate IT & Enterprise Technology | D69: 0.2 | E69: IT documentation | F69: 0.2 | G69: Document Generation & Management | H69: 0.95 | J69: 0.68 | K69: 0.68 | L69: 0.65 | M69: 0.6 | N69: 0.57
A70: Real Estate | B70: Specialized REITs | C70: Legal, Risk & Compliance | D70: 0.15 | E70: Regulatory / compliance monitoring | F70: 0.25 | G70: Monitoring | H70: 0.7 | I70: =SUMPRODUCT(H70:H73,F70:F73)*D70 -> 0.088125 | J70: 0.44 | K70: 0.44 | L70: 0.41 | M70: 0.36 | N70: 0.32
A71: Real Estate | B71: Specialized REITs | C71: Legal, Risk & Compliance | D71: 0.15 | E71: Contract & policy review | F71: 0.25 | G71: Assessment & Analysis | H71: 0.6 | J71: 0.44 | K71: 0.44 | L71: 0.41 | M71: 0.36 | N71: 0.32
A72: Real Estate | B72: Specialized REITs | C72: Legal, Risk & Compliance | D72: 0.15 | E72: Legal / regulatory stakeholder management | F72: 0.25 | G72: Stakeholder / Relationship Management | H72: 0.1 | J72: 0.44 | K72: 0.44 | L72: 0.41 | M72: 0.36 | N72: 0.32
A73: Real Estate | B73: Specialized REITs | C73: Legal, Risk & Compliance | D73: 0.15 | E73: Compliance documentation | F73: 0.25 | G73: Document Generation & Management | H73: 0.95 | J73: 0.44 | K73: 0.44 | L73: 0.41 | M73: 0.36 | N73: 0.32
A74: Real Estate | B74: Specialized REITs | C74: Corporate Strategy & Administration | D74: 0.15 | E74: Portfolio / asset strategic planning | F74: 0.3 | G74: Strategy & Design | H74: 0.3 | I74: =SUMPRODUCT(H74:H77,F74:F77)*D74 -> 0.06825 | J74: 0.35 | K74: 0.35 | L74: 0.32 | M74: 0.28 | N74: 0.25
A75: Real Estate | B75: Specialized REITs | C75: Corporate Strategy & Administration | D75: 0.15 | E75: Management / asset-market analysis | F75: 0.25 | G75: Assessment & Analysis | H75: 0.6 | J75: 0.35 | K75: 0.35 | L75: 0.32 | M75: 0.28 | N75: 0.25
A76: Real Estate | B76: Specialized REITs | C76: Corporate Strategy & Administration | D76: 0.15 | E76: Executive stakeholder coordination | F76: 0.25 | G76: Stakeholder / Relationship Management | H76: 0.1 | J76: 0.35 | K76: 0.35 | L76: 0.32 | M76: 0.28 | N76: 0.25
A77: Real Estate | B77: Specialized REITs | C77: Corporate Strategy & Administration | D77: 0.15 | E77: Corporate reporting | F77: 0.2 | G77: Document Generation & Management | H77: 0.95 | J77: 0.35 | K77: 0.35 | L77: 0.32 | M77: 0.28 | N77: 0.25
I78: =SUM(I54:I74) -> 0.678375 | J78: =+J58*$D58+J62*$D62+J66*$D66+J70*$D70+J74*$D74+$D54*J54 -> 0.534 | K78: =+K58*$D58+K62*$D62+K66*$D66+K70*$D70+K74*$D74+$D54*K54 -> 0.534 | L78: =+L58*$D58+L62*$D62+L66*$D66+L70*$D70+L74*$D74+$D54*L54 -> 0.504 | M78: =+M58*$D58+M62*$D62+M66*$D66+M70*$D70+M74*$D74+$D54*M54 -> 0.4555 | N78: =+N58*$D58+N62*$D62+N66*$D66+N70*$D70+N74*$D74+$D54*N54 -> 0.419
A80: Real Estate | B80: Owners & Developers | C80: Finance & Accounting | D80: 0.25 | E80: Transaction processing & reconciliation | F80: 0.3 | G80: Task Processing / Query Handling | H80: 0.9 | I80: =SUMPRODUCT(H80:H83,F80:F83)*D80 -> 0.206875 | J80: 0.62 | K80: 0.62 | L80: 0.58 | M80: 0.51 | N80: 0.42
A81: Real Estate | B81: Owners & Developers | C81: Finance & Accounting | D81: 0.25 | E81: Financial planning & analysis | F81: 0.25 | G81: Assessment & Analysis | H81: 0.6 | J81: 0.62 | K81: 0.62 | L81: 0.58 | M81: 0.51 | N81: 0.42
A82: Real Estate | B82: Owners & Developers | C82: Finance & Accounting | D82: 0.25 | E82: Budgeting & forecasting | F82: 0.2 | G82: Modelling (incl. Forecasting) | H82: 0.85 | J82: 0.62 | K82: 0.62 | L82: 0.58 | M82: 0.51 | N82: 0.42
A83: Real Estate | B83: Owners & Developers | C83: Finance & Accounting | D83: 0.25 | E83: Financial reporting | F83: 0.25 | G83: Document Generation & Management | H83: 0.95 | J83: 0.62 | K83: 0.62 | L83: 0.58 | M83: 0.51 | N83: 0.42
