Workbook

Sheet Cover
A1: Coforge Integrated Financial Model
A2: Official-source build | Quarterly P&L FY16–Q1FY27 | Annual three statements FY16–FY30E | INR million unless stated
A4: OUTPERFORM framework: order-book conversion, Encora, client mining, people productivity, AI uplift and acquisition deleveraging
A6: Model scope | B6: Quarterly P&L only; annual P&L, detailed balance sheet and cash flow
A7: Historical period | B7: FY16–FY26 plus Q1 FY27 actual
A8: Forecast period | B8: FY27E–FY30E
A9: Source policy | B9: Official Coforge annual reports, quarterly factsheets and investor presentations
A10: Revenue architecture | B10: Retained base + executable-order-book conversion + fresh-order realization + client farming + AI uplift − T&M deflation + Encora − portfolio exits
A11: AI policy | B11: Service category “AI-led Engineering” is not treated as pure AI revenue; only incremental scenario uplift is modeled as AI revenue
A12: Acquisition policy | B12: Encora revenue, PPA, share consideration, acquisition debt, interest and principal are separated
A13: Cash policy | B13: Historical closing cash is anchored to the reported balance sheet; forecast cash is CFO + CFI + CFF
A14: Circularity policy | B14: One-way flow: assumptions / drivers → P&L → non-cash BS schedules → cash flow → cash → balance sheet
A15: Formatting | B15: Aptos Narrow 10; hardcoded actuals medium blue; formulas black; forecast columns pale green
A16: House view | B16: OUTPERFORM
A17: Model status | B17: =Checks!B6 -> OK

Sheet Summary
A1: Coforge Financial Summary
A2: OUTPERFORM: operating momentum, Encora integration, cash generation, deleveraging and valuation
A5: Metric | B5: FY16A | C5: FY17A | D5: FY18A | E5: FY19A | F5: FY20A | G5: FY21A | H5: FY22A | I5: FY23A | J5: FY24A | K5: FY25A | L5: FY26A | M5: FY27E | N5: FY28E | O5: FY29E | P5: FY30E
A7: Revenue | B7: ='Annual P&L'!C7 -> 26824.049 | C7: ='Annual P&L'!D7 -> 28021 | D7: ='Annual P&L'!E7 -> 29914 | E7: ='Annual P&L'!F7 -> 36762 | F7: ='Annual P&L'!G7 -> 41839 | G7: ='Annual P&L'!H7 -> 46628 | H7: ='Annual P&L'!I7 -> 64320 | I7: ='Annual P&L'!J7 -> 80146 | ... P7: ='Annual P&L'!Q7 -> 457101.52
A8: Revenue growth | B8: ='Annual P&L'!C8 -> 0 | C8: ='Annual P&L'!D8 -> 0.044622317 | D8: ='Annual P&L'!E8 -> 0.067556476 | E8: ='Annual P&L'!F8 -> 0.22892291 | F8: ='Annual P&L'!G8 -> 0.13810456 | G8: ='Annual P&L'!H8 -> 0.11446258 | H8: ='Annual P&L'!I8 -> 0.37942867 | I8: ='Annual P&L'!J8 -> 0.246051 | ... P8: ='Annual P&L'!Q8 -> 0.2366927
A9: Revenue | B9: ='Order Book & Revenue'!C33 -> 0 | C9: ='Order Book & Revenue'!D33 -> 0 | D9: ='Order Book & Revenue'!E33 -> 0 | E9: ='Order Book & Revenue'!F33 -> 0 | F9: ='Order Book & Revenue'!G33 -> 0 | G9: ='Order Book & Revenue'!H33 -> 0 | H9: ='Order Book & Revenue'!I33 -> 866.5 | I9: ='Order Book & Revenue'!J33 -> 1001.7 | ... P9: ='Order Book & Revenue'!Q33 -> 4712.3868
A10: Executable order book | B10: ='Order Book & Revenue'!C10 -> 301 | C10: ='Order Book & Revenue'!D10 -> 320 | D10: ='Order Book & Revenue'!E10 -> 339 | E10: ='Order Book & Revenue'!F10 -> 390 | F10: ='Order Book & Revenue'!G10 -> 468 | G10: ='Order Book & Revenue'!H10 -> 520 | H10: ='Order Book & Revenue'!I10 -> 720 | I10: ='Order Book & Revenue'!J10 -> 869 | ... P10: ='Order Book & Revenue'!Q10 -> 2903.2106
A11: Fresh order intake | B11: ='Order Book & Revenue'!C15 -> 420 | C11: ='Order Book & Revenue'!D15 -> 457 | D11: ='Order Book & Revenue'!E15 -> 507 | E11: ='Order Book & Revenue'!F15 -> 646 | F11: ='Order Book & Revenue'!G15 -> 748 | G11: ='Order Book & Revenue'!H15 -> 781 | H11: ='Order Book & Revenue'!I15 -> 1151 | I11: ='Order Book & Revenue'!J15 -> 1265 | ... P11: ='Order Book & Revenue'!Q15 -> 3222.0199
A12: Gross margin | B12: ='Annual P&L'!C11 -> 0.41489825 | C12: ='Annual P&L'!D11 -> 0.40566004 | D12: ='Annual P&L'!E11 -> 0.40101625 | E12: ='Annual P&L'!F11 -> 0.40637071 | F12: ='Annual P&L'!G11 -> 0.37517627 | G12: ='Annual P&L'!H11 -> 0.35461525 | H12: ='Annual P&L'!I11 -> 0.37702114 | I12: ='Annual P&L'!J11 -> 0.39072443 | ... P12: ='Annual P&L'!Q11 -> 0.353
A13: Adjusted EBITDA margin | B13: ='Annual P&L'!C14 -> 0.18049929 | C13: ='Annual P&L'!D14 -> 0.17108597 | D13: ='Annual P&L'!E14 -> 0.1675804 | E13: ='Annual P&L'!F14 -> 0.17640498 | F13: ='Annual P&L'!G14 -> 0.17287698 | G13: ='Annual P&L'!H14 -> 0.16717423 | H13: ='Annual P&L'!I14 -> 0.1713153 | I13: ='Annual P&L'!J14 -> 0.15979587 | ... P13: ='Annual P&L'!Q14 -> 0.223
A14: EBITDA | B14: ='Annual P&L'!C16 -> 4841.7219 | C14: ='Annual P&L'!D16 -> 4794 | D14: ='Annual P&L'!E16 -> 5013 | E14: ='Annual P&L'!F16 -> 6485 | F14: ='Annual P&L'!G16 -> 7233 | G14: ='Annual P&L'!H16 -> 7795 | H14: ='Annual P&L'!I16 -> 11019 | I14: ='Annual P&L'!J16 -> 12807 | ... P14: ='Annual P&L'!Q16 -> 99191.03
A15: EBIT margin | B15: ='Annual P&L'!C20 -> 0.13944309 | C15: ='Annual P&L'!D20 -> 0.12551301 | D15: ='Annual P&L'!E20 -> 0.12499164 | E15: ='Annual P&L'!F20 -> 0.14245688 | F15: ='Annual P&L'!G20 -> 0.131528 | G15: ='Annual P&L'!H20 -> 0.12779875 | H15: ='Annual P&L'!I20 -> 0.13599192 | I15: ='Annual P&L'!J20 -> 0.12754224 | ... P15: ='Annual P&L'!Q20 -> 0.177
A16: Net income | B16: ='Annual P&L'!C30 -> 2799.6308 | C16: ='Annual P&L'!D30 -> 2501 | D16: ='Annual P&L'!E30 -> 2802 | E16: ='Annual P&L'!F30 -> 4033 | F16: ='Annual P&L'!G30 -> 4440 | G16: ='Annual P&L'!H30 -> 4556 | H16: ='Annual P&L'!I30 -> 6617 | I16: ='Annual P&L'!J30 -> 6938 | ... P16: ='Annual P&L'!Q30 -> 61734.403
A17: Diluted EPS | B17: ='Annual P&L'!C35 -> 9.11 | C17: ='Annual P&L'!D35 -> 8.142 | D17: ='Annual P&L'!E35 -> 9.068 | E17: ='Annual P&L'!F35 -> 12.946 | F17: ='Annual P&L'!G35 -> 14.194 | G17: ='Annual P&L'!H35 -> 14.658 | H17: ='Annual P&L'!I35 -> 21.304 | I17: ='Annual P&L'!J35 -> 22.306 | ... P17: ='Annual P&L'!Q35 -> 145.25742
A18: CFO | B18: ='Annual Cash Flow'!C19 -> 3602.9216 | C18: ='Annual Cash Flow'!D19 -> 4723 | D18: ='Annual Cash Flow'!E19 -> 3824 | E18: ='Annual Cash Flow'!F19 -> 4527 | F18: ='Annual Cash Flow'!G19 -> 2969 | G18: ='Annual Cash Flow'!H19 -> 7623 | H18: ='Annual Cash Flow'!I19 -> 7656 | I18: ='Annual Cash Flow'!J19 -> 9505 | ... P18: ='Annual Cash Flow'!Q19 -> 67071.397
A19: Free cash flow | B19: ='Annual Cash Flow'!C44 -> 1993.805 | C19: ='Annual Cash Flow'!D44 -> 4723 | D19: ='Annual Cash Flow'!E44 -> 3824 | E19: ='Annual Cash Flow'!F44 -> 4527 | F19: ='Annual Cash Flow'!G44 -> 2969 | G19: ='Annual Cash Flow'!H44 -> 7623 | H19: ='Annual Cash Flow'!I44 -> 6115 | I19: ='Annual Cash Flow'!J44 -> 7923 | ... P19: ='Annual Cash Flow'!Q44 -> 53358.352
A20: Closing cash | B20: ='Annual Cash Flow'!C41 -> 2878.6273 | C20: ='Annual Cash Flow'!D41 -> 3502 | D20: ='Annual Cash Flow'!E41 -> 4102 | E20: ='Annual Cash Flow'!F41 -> 5194 | F20: ='Annual Cash Flow'!G41 -> 8195 | G20: ='Annual Cash Flow'!H41 -> 7999 | H20: ='Annual Cash Flow'!I41 -> 4468 | I20: ='Annual Cash Flow'!J41 -> 5699 | ... P20: ='Annual Cash Flow'!Q41 -> 29969.931
A21: Acquisition debt | M21: ='Acquisition & Debt'!C17 -> 490 | N21: ='Acquisition & Debt'!D17 -> 270 | O21: ='Acquisition & Debt'!E17 -> 0 | P21: ='Acquisition & Debt'!F17 -> 0
A22: Headcount | B22: ='People & AI'!C7 -> 9476 | C22: ='People & AI'!D7 -> 8853 | D22: ='People & AI'!E7 -> 9423 | E22: ='People & AI'!F7 -> 10263 | F22: ='People & AI'!G7 -> 11156 | G22: ='People & AI'!H7 -> 12391 | H22: ='People & AI'!I7 -> 22500 | I22: ='People & AI'!J7 -> 23224 | ... P22: ='People & AI'!Q7 -> 58687.431
A23: Billable headcount | B23: ='People & AI'!C10 -> 8743 | C23: ='People & AI'!D10 -> 8066 | D23: ='People & AI'!E10 -> 8588 | E23: ='People & AI'!F10 -> 9363 | F23: ='People & AI'!G10 -> 10274 | G23: ='People & AI'!H10 -> 11469 | H23: ='People & AI'!I10 -> 21294 | I23: ='People & AI'!J10 -> 21815 | ... P23: ='People & AI'!Q10 -> 55186.887
A24: Revenue / IT billable | B24: ='People & AI'!C14 -> 0 | C24: ='People & AI'!D14 -> 0 | D24: ='People & AI'!E14 -> 0 | E24: ='People & AI'!F14 -> 0 | F24: ='People & AI'!G14 -> 0 | G24: ='People & AI'!H14 -> 0 | H24: ='People & AI'!I14 -> 0 | I24: ='People & AI'!J14 -> 0 | ... P24: ='People & AI'!Q14 -> 113852.82
A25: Incremental AI revenue | B25: ='People & AI'!C21 -> 0 | C25: ='People & AI'!D21 -> 0 | D25: ='People & AI'!E21 -> 0 | E25: ='People & AI'!F21 -> 0 | F25: ='People & AI'!G21 -> 0 | G25: ='People & AI'!H21 -> 0 | H25: ='People & AI'!I21 -> 0 | I25: ='People & AI'!J21 -> 0 | ... P25: ='People & AI'!Q21 -> 148.15445
A26: T&M AI deflation drag | B26: ='People & AI'!C20 -> 0 | C26: ='People & AI'!D20 -> 0 | D26: ='People & AI'!E20 -> 0 | E26: ='People & AI'!F20 -> 0 | F26: ='People & AI'!G20 -> 0 | G26: ='People & AI'!H20 -> 0 | H26: ='People & AI'!I20 -> 0 | I26: ='People & AI'!J20 -> 0 | ... P26: ='People & AI'!Q20 -> -10.000425
A27: Reference market price | B27: =Valuation!C7 -> 99.339996 | C27: =Valuation!D7 -> 87.120003 | D27: =Valuation!E7 -> 173 | E27: =Valuation!F7 -> 266.79001 | F27: =Valuation!G7 -> 229.55 | G27: =Valuation!H7 -> 585.39001 | H27: =Valuation!I7 -> 891.5 | I27: =Valuation!J7 -> 762.82001 | ... P27: =Valuation!Q7 -> 1981.5
A28: P/E | B28: =Valuation!C14 -> 10.9045 | C28: =Valuation!D14 -> 10.700074 | D28: =Valuation!E14 -> 19.078077 | E28: =Valuation!F14 -> 20.60791 | F28: =Valuation!G14 -> 16.172327 | G28: =Valuation!H14 -> 39.936554 | H28: =Valuation!I14 -> 41.846602 | I28: =Valuation!J14 -> 34.197974 | ... P28: =Valuation!Q14 -> 13.6413
A29: EV / EBITDA | B29: =Valuation!C16 -> 5.6241178 | C29: =Valuation!D16 -> 4.7475772 | D29: =Valuation!E16 -> 9.8649055 | E29: =Valuation!F16 -> 11.971581 | F29: =Valuation!G16 -> 8.6850726 | G29: =Valuation!H16 -> 22.300698 | H29: =Valuation!I16 -> 25.039383 | I29: =Valuation!J16 -> 18.339466 | ... P29: =Valuation!Q16 -> 8.250774
A30: Blended target price | B30: =Valuation!C32 -> 0 | C30: =Valuation!D32 -> 0 | D30: =Valuation!E32 -> 0 | E30: =Valuation!F32 -> 0 | F30: =Valuation!G32 -> 0 | G30: =Valuation!H32 -> 0 | H30: =Valuation!I32 -> 0 | I30: =Valuation!J32 -> 0 | ... P30: =Valuation!Q32 -> 3981.1948
A31: Upside / (downside) | B31: =Valuation!C33 -> 0 | C31: =Valuation!D33 -> 0 | D31: =Valuation!E33 -> 0 | E31: =Valuation!F33 -> 0 | F31: =Valuation!G33 -> 0 | G31: =Valuation!H33 -> 0 | H31: =Valuation!I33 -> 0 | I31: =Valuation!J33 -> 0 | ... P31: =Valuation!Q33 -> 1.0091823
A32: Rating | B32: =Valuation!C34 -> 0 | C32: =Valuation!D34 -> 0 | D32: =Valuation!E34 -> 0 | E32: =Valuation!F34 -> 0 | F32: =Valuation!G34 -> 0 | G32: =Valuation!H34 -> 0 | H32: =Valuation!I34 -> 0 | I32: =Valuation!J34 -> 0 | ... P32: =Valuation!Q34 -> OUTPERFORM

Sheet Sources
A1: Sources & Data Conventions
A2: Primary-source register; non-disclosed metrics remain blank and forecast assumptions are visibly editable
A5: ID | B5: Data / period | C5: Units | D5: Primary source | E5: Model use | F5: Status | G5: Notes
A6: S1 | B6: Annual reports FY16–FY26 | C6: ₹m | D6: https://investors.coforge.com/annual-report | E6: Audited P&L, balance sheet and cash flow | F6: Loaded | G6: Latest comparative presentation used where applicable
A7: S2 | B7: Quarterly factsheets FY16–FY25 | C7: ₹m / $m / % / # | D7: https://investors.coforge.com/quarter-reports | E7: Quarterly P&L and operating KPI history | F7: Loaded | G7: Reported figures retained; annual restatement bridge shown separately
A8: S3 | B8: Q4 FY26 presentation | C8: $m / ₹m / % / # | D8: https://investors.coforge.com/hubfs/Investor-Presentation-and-Factsheet-Q4FY26.pdf | E8: FY26 operations, order intake, order book, clients, people and mix | F8: Loaded | G8: FY26 revenue ₹164,027m / $1,870m
A9: S4 | B9: Q1 FY27 presentation | C9: $m / ₹m / % / # | D9: https://investors.coforge.com/hubfs/Investor-Presentation-Q1-FY27.pdf | E9: Q1 actuals, Encora, PPA, debt, operating metrics | F9: Loaded | G9: Encora consolidated from 1 May 2026
A10: S5 | B10: Q1 FY27 results | C10: ₹m | D10: https://investors.coforge.com/quarter-reports | E10: Q1 reported P&L | F10: Loaded | G10: Revenue ₹55,277m; attributable PAT ₹5,186m
A11: S6 | B11: Continuous NIIT Technologies / Coforge prices from listing | C11: ₹ / share | D11: https://finance.yahoo.com/quote/COFORGE.NS/history/ | E11: Daily price history, FY05–FY26 year-end prices and valuation reference price | F11: Loaded | G11: Continuous backfilled listed-company series. NSE states NIITTECH traded from Aug-2004 to Aug-2020 and COFORGE since Aug-2020: https://nsearchives.nseindia.com/corporate/COFORGE_16112021040103_SEIntimation.pdf
A12: S7 | B12: Historical AI revenue | C12: n/a | D12: n/a | E12: Forecast policy | F12: Not disclosed | G12: AI-led Engineering mix is not equated to pure AI revenue
A13: S8 | B13: Historical cash-flow residuals | C13: ₹m | D13: Audited CFS totals | E13: Line-by-line reconciliation | F13: Calculated | G13: Reported residual/reclassification is formula-derived; forecast residual is zero
A14: S9 | B14: Assets / liabilities held for sale | C14: ₹m | D14: Audited balance-sheet totals | E14: Historical classification bridge | F14: Calculated | G14: Derived from reported subtotals when PDF extraction obscures the row

Sheet Assumptions
A1: Forecast Assumptions
A2: Blue text on yellow = editable; all forecast financials and valuations are calculated
A5: Driver | B5: Units | C5: FY27E | D5: FY28E | E5: FY29E | F5: FY30E | G5: Logic / interpretation
A6: Repeat / retained base | B6: % | C6: 0.955 | D6: 0.957 | E6: 0.96 | F6: 0.962 | G6: Prior-year revenue retained before incremental drivers
A7: Executable order book growth | B7: % | C7: 0.12 | D7: 0.1 | E7: 0.09 | F7: 0.08 | G7: Next-12-month executable order book
A8: Incremental order-book realization | B8: % | C8: 0.04 | D8: 0.042 | E8: 0.044 | F8: 0.045 | G8: Current-year revenue from EOB expansion
A9: Fresh order intake growth | B9: % | C9: 0.1 | D9: 0.1 | E9: 0.09 | F9: 0.08 | G9: Annual order-intake scenario
A10: Fresh order first-year realization | B10: % | C10: 0.06 | D10: 0.062 | E10: 0.065 | F10: 0.067 | G10: Current-year revenue from incremental order intake
A11: Client farming / pricing uplift | B11: % | C11: 0.01 | D11: 0.015 | E11: 0.015 | F11: 0.015 | G11: Mining, pricing and cross-sell uplift on retained base
A12: T&M mix | B12: % | C12: 0.57 | D12: 0.56 | E12: 0.55 | F12: 0.54 | G12: Q1 FY27 actual is 57%
A13: AI deflation on T&M revenue | B13: % | C13: 0.01 | D13: 0.01 | E13: 0.008 | F13: 0.005 | G13: Productivity / rate drag on the T&M pool
A14: Outcome-pricing offset | B14: % | C14: 0.008 | D14: 0.01 | E14: 0.012 | F14: 0.013 | G14: Value capture from fixed/outcome pricing
A15: Incremental AI uplift | B15: % | C15: 0.02 | D15: 0.03 | E15: 0.035 | F15: 0.04 | G15: Incremental AI-led revenue; not a historical disclosure
A16: Portfolio exits | B16: $m | C16: 19 | D16: 0 | E16: 0 | F16: 0 | G16: $15m India Government portfolio + $4m data-center impact
A17: Encora monthly run-rate | B17: $m | C17: 50.35 | G17: Q1 FY27 disclosed $100.7m for two months
A18: Encora growth | B18: % | C18: 0.05 | D18: 0.1 | E18: 0.1 | F18: 0.09 | G18: Separate acquired-revenue growth
A19: Average INR / USD | B19: ₹ / $ | C19: 94 | D19: 95 | E19: 96 | F19: 97 | G19: Forecast translation rate
A20: Gross margin | B20: % | C20: 0.343 | D20: 0.347 | E20: 0.35 | F20: 0.353 | G20: Scale, offshore and portfolio mix
A21: SG&A / revenue | B21: % | C21: 0.138 | D21: 0.135 | E21: 0.132 | F21: 0.13 | G21: Selling / general administration
A22: SBC / revenue | B22: % | C22: 0.006 | D22: 0.006 | E22: 0.006 | F22: 0.006 | G22: Share-based compensation
A23: D&A / revenue | B23: % | C23: 0.049 | D23: 0.046 | E23: 0.043 | F23: 0.04 | G23: Includes Encora intangible amortization
A24: Other income / revenue | B24: % | C24: 0.005 | D24: 0.005 | E24: 0.005 | F24: 0.005 | G24: Non-operating income excluding financing cost
A25: Effective tax rate | B25: % | C25: 0.25 | D25: 0.25 | E25: 0.25 | F25: 0.25 | G25: P&L tax rate
A26: NCI share of post-tax profit | B26: % | C26: 0.02 | D26: 0.015 | E26: 0.01 | F26: 0.01 | G26: Minority share
A27: Billed receivable days | B27: days | C27: 65 | D27: 64 | E27: 63 | F27: 62 | G27: Closing billed receivables
A28: Unbilled + contract asset days | B28: days | C28: 39 | D28: 37 | E28: 35 | F28: 33 | G28: Q1 FY27: 24 unbilled + 15 contract asset days
A29: Contract cost / revenue | B29: % | C29: 0.03 | D29: 0.028 | E29: 0.026 | F29: 0.024 | G29: Capitalized contract acquisition / fulfilment costs
... A54: DCF valuation weight | B54: % | C54: 0.3 | D54: 0.3 | E54: 0.3 | F54: 0.3 | G54: Blended target weight
A55: Reference market price | B55: ₹ / share | C55: ='COFORGE Prices'!D5445 -> 1981.5 | D55: ='COFORGE Prices'!D5445 -> 1981.5 | E55: ='COFORGE Prices'!D5445 -> 1981.5 | F55: ='COFORGE Prices'!D5445 -> 1981.5 | G55: User input; FY27–FY30 carried unless explicitly changed
A56: FY27 Q1 actual net cash change | B56: ₹m | C56: 2947 | G56: Reported balance-sheet cash movement: ₹13,883m − ₹10,936m
A57: FY27 Q1 actual CFO | B57: ₹m | C57: 5374 | G57: $57.6m translated at Q1 average rate
A58: FY27 Q1 acquisition cash flow | B58: ₹m | C58: -46939 | G58: $503.1m translated at Q1 average rate
A59: FY27 Q1 debt / credit-line inflow | B59: ₹m | C59: 46547 | G59: $498.9m translated at Q1 average rate
A60: FY27 Q1 lease principal | B60: ₹m | C60: -317 | G60: $3.4m translated
A61: FY27 Q1 interest paid | B61: ₹m | C61: -728 | G61: $7.8m translated
A62: FY27 Q1 capex | B62: ₹m | C62: -438 | G62: $4.7m translated
A63: OCI / other reserve movement | B63: ₹m | C63: 0 | D63: 0 | E63: 0 | F63: 0 | G63: Editable reserve movement

Sheet Raw Financials
A1: Raw Reported Financials — Source Layer
A2: Hardcoded official reported inputs only; calculations live downstream
A4: Annual reported P&L
A5: Metric | B5: Units | C5: FY16A | D5: FY17A | E5: FY18A | F5: FY19A | G5: FY20A | H5: FY21A | I5: FY22A | J5: FY23A | K5: FY24A | L5: FY25A | M5: FY26A
A6: Revenue | B6: ₹m | C6: 26824.049 | D6: 28021 | E6: 29914 | F6: 36762 | G6: 41839 | H6: 46628 | I6: 64320 | J6: 80146 | K6: 91790 | L6: 120733 | M6: 164027
A7: Other income | B7: ₹m | C7: 205.4828 | D7: 269 | E7: 391 | F7: 535 | G7: 677 | H7: 326 | I7: 518 | J7: 619 | K7: 614 | L7: 1647 | M7: 732
A8: Total income | B8: ₹m | C8: 27029.532 | D8: 28290 | E8: 30305 | F8: 37297 | G8: 42516 | H8: 46954 | I8: 64838 | J8: 80765 | K8: 92404 | L8: 122380 | M8: 164759
A9: Purchases / stock | B9: ₹m | C9: 308.69553 | D9: 141 | E9: 317 | F9: 291 | G9: 844 | H9: 1935 | I9: 1724 | J9: 551 | K9: 94 | L9: 101 | M9: 65
A10: Employee benefits | B10: ₹m | C10: 15386.102 | D10: 16513 | E10: 17601 | F10: 21532 | G10: 25298 | H10: 28158 | I10: 38346 | J10: 48280 | K10: 55069 | L10: 72241 | M10: 92161
A11: Professional charges | B11: ₹m | L11: 13902 | M11: 21918
A12: Other production expenses | B12: ₹m | L12: 9149 | M12: 12045
A13: Other expenses | B13: ₹m | C13: 6287.5291 | D13: 6573 | E13: 6983 | F13: 8454 | G13: 8464 | H13: 8740 | I13: 13231 | J13: 18508 | K13: 22350 | L13: 8122 | M13: 7374
A14: Finance costs | B14: ₹m | C14: 48.795223 | D14: 60 | E14: 94 | F14: 92 | G14: 155 | H14: 143 | I14: 650 | J14: 806 | K14: 1256 | L14: 1347 | M14: 1686
A15: D&A | B15: ₹m | C15: 1101.2935 | D15: 1277 | E15: 1274 | F15: 1248 | G15: 1730 | H15: 1836 | I15: 2272 | J15: 2585 | K15: 3186 | L15: 4276 | M15: 6819
A16: PBT pre-exceptional | B16: ₹m | C16: 3814.5324 | D16: 3727 | E16: 4036 | F16: 5680 | G16: 6025 | H16: 6142 | I16: 8615 | J16: 10035 | K16: 10449 | L16: 12961 | M16: 21588
A17: Exceptional items | B17: ₹m | C17: 13.156528 | D17: 221 | E17: 0 | F17: 56 | G17: 71 | H17: 180 | I17: 0 | J17: 523 | K17: 0 | L17: 0 | M17: 2260
A18: PBT | B18: ₹m | C18: 3801.3759 | D18: 3506 | E18: 4036 | F18: 5624 | G18: 5954 | H18: 5962 | I18: 8615 | J18: 9512 | K18: 10449 | L18: 12961 | M18: 19328
A19: Current tax | B19: ₹m | C19: 872.66633 | D19: 922 | E19: 1084 | F19: 1387 | G19: 1551 | H19: 1608 | I19: 1774 | J19: 2492 | K19: 2493 | L19: 4033 | M19: 5024
A20: Deferred tax | B20: ₹m | C20: -40.98601 | D20: -137 | E20: -135 | F20: 16 | G20: -273 | H20: -306 | I20: -306 | J20: -431 | K20: -400 | L20: -707 | M20: -2441
A21: Tax | B21: ₹m | C21: 831.68032 | D21: 785 | E21: 949 | F21: 1403 | G21: 1278 | H21: 1302 | I21: 1468 | J21: 2061 | K21: 2093 | L21: 3326 | M21: 2583
A22: Profit incl. NCI | B22: ₹m | C22: 2969.6955 | D22: 2721 | E22: 3087 | F22: 4221 | G22: 4676 | H22: 4660 | I22: 7147 | J22: 7451 | K22: 8356 | L22: 9361 | M22: 17447
A23: NCI | B23: ₹m | C23: 170.06476 | D23: 220 | E23: 285 | F23: 188 | G23: 236 | H23: 104 | I23: 530 | J23: 513 | K23: 276 | L23: 1240 | M23: 1890
A24: Net income attributable | B24: ₹m | C24: 2799.6308 | D24: 2501 | E24: 2802 | F24: 4033 | G24: 4440 | H24: 4556 | I24: 6617 | J24: 6938 | K24: 8080 | L24: 8121 | M24: 15557
... A26: Diluted EPS | B26: ₹ / share | C26: 9.11 | D26: 8.142 | E26: 9.068 | F26: 12.946 | G26: 14.194 | H26: 14.658 | I26: 21.304 | J26: 22.306 | K26: 25.918 | L26: 24.41 | M26: 45.9
A30: Quarterly reported P&L
A31: Metric | B31: Units | C31: Q1 FY16A | D31: Q2 FY16A | E31: Q3 FY16A | F31: Q4 FY16A | G31: Q1 FY17A | H31: Q2 FY17A | I31: Q3 FY17A | J31: Q4 FY17A | K31: Q1 FY18A | L31: Q2 FY18A | M31: Q3 FY18A | N31: Q4 FY18A | O31: Q1 FY19A | P31: Q2 FY19A | Q31: Q3 FY19A | R31: Q4 FY19A | S31: Q1 FY20A | T31: Q2 FY20A | U31: Q3 FY20A | V31: Q4 FY20A | W31: Q1 FY21A | X31: Q2 FY21A | Y31: Q3 FY21A | Z31: Q4 FY21A | AA31: Q1 FY22A | AB31: Q2 FY22A | AC31: Q3 FY22A | AD31: Q4 FY22A | AE31: Q1 FY23A | AF31: Q2 FY23A | AG31: Q3 FY23A | AH31: Q4 FY23A | AI31: Q1 FY24A | AJ31: Q2 FY24A | AK31: Q3 FY24A | AL31: Q4 FY24A | AM31: Q1 FY25A | AN31: Q2 FY25A | AO31: Q3 FY25A | AP31: Q4 FY25A | AQ31: Q1 FY26A | AR31: Q2 FY26A | AS31: Q3 FY26A | AT31: Q4 FY26A | AU31: Q1 FY27A
A32: Revenue | B32: ₹m | C32: 6411 | D32: 6779 | E32: 6787 | F32: 6847 | G32: 6707 | H32: 6929 | I32: 6938 | J32: 7447 | K32: 7089 | L32: 7372 | M32: 7565 | N32: 7888 | O32: 8249 | P32: 9074 | Q32: 9717 | R32: 9722 | S32: 9597 | T32: 10385 | U32: 10734 | V32: 11093 | W32: 10570 | X32: 11537 | Y32: 11906 | Z32: 12615 | AA32: 14616 | AB32: 15694 | AC32: 16581 | AD32: 17429 | AE32: 18294 | AF32: 19594 | AG32: 20558 | AH32: 21700 | AI32: 22210 | AJ32: 22762 | AK32: 23233 | AL32: 23585 | AM32: 24008 | AN32: 30623 | AO32: 33182 | AP32: 34222 | AQ32: 36886 | AR32: 39857 | AS32: 41881 | AT32: 44504 | AU32: 55277
A33: Cost of revenue | B33: ₹m | C33: 4081 | D33: 4256 | E33: 4255 | F33: 4304 | G33: 4356 | H33: 4481 | I33: 4441 | J33: 4625 | K33: 4577 | L33: 4790 | M33: 4812 | N33: 5000 | O33: 5438 | P33: 5897 | Q33: 6280 | R33: 6294 | S33: 6348 | T33: 6796 | U33: 7068 | V33: 7289 | W33: 7241 | X33: 7776 | Y33: 8096 | Z33: 8580 | AA33: 10250 | AB33: 10656 | AC33: 11210 | AD33: 11620 | AE33: 12739 | AF33: 13317 | AG33: 13698 | AH33: 14306 | AI33: 15391.53 | AJ33: 15374 | AK33: 15542.877 | AL33: 15545 | AM33: 16097 | AN33: 20701.148 | AO33: 22165.576 | AP33: 22483 | AQ33: 24326 | AR33: 26299 | AS33: 28112 | AT33: 29204 | AU33: 36343
A34: Gross profit | B34: ₹m | C34: 2330 | D34: 2523 | E34: 2532 | F34: 2543 | G34: 2351 | H34: 2448 | I34: 2497 | J34: 2822 | K34: 2512 | L34: 2582 | M34: 2753 | N34: 2888 | O34: 2811 | P34: 3177 | Q34: 3437 | R34: 3428 | S34: 3249 | T34: 3589 | U34: 3666 | V34: 3804 | W34: 3329 | X34: 3761 | Y34: 3810 | Z34: 4035 | AA34: 4366 | AB34: 5038 | AC34: 5371 | AD34: 5809 | AE34: 5555 | AF34: 6277 | AG34: 6860 | AH34: 7394 | AI34: 6818.47 | AJ34: 7388 | AK34: 7690.123 | AL34: 8040 | AM34: 7911 | AN34: 9921.852 | AO34: 11016.424 | AP34: 11739 | AQ34: 12560 | AR34: 13558 | AS34: 13769 | AT34: 15300 | AU34: 18934
A35: Gross margin | B35: % | C35: 0.364 | D35: 0.372 | E35: 0.373 | F35: 0.371 | G35: 0.351 | H35: 0.353 | I35: 0.36 | J35: 0.379 | K35: 0.354 | L35: 0.35 | M35: 0.364 | N35: 0.366 | O35: 0.341 | P35: 0.35 | Q35: 0.354 | R35: 0.353 | S35: 0.339 | T35: 0.346 | U35: 0.341 | V35: 0.343 | W35: 0.315 | X35: 0.326 | Y35: 0.32 | Z35: 0.32 | AA35: 0.299 | AB35: 0.321 | AC35: 0.324 | AD35: 0.333 | AE35: 0.304 | AF35: 0.32 | AG35: 0.334 | AH35: 0.341 | AI35: 0.307 | AJ35: 0.325 | AK35: 0.331 | AL35: 0.341 | AM35: 0.32951516 | AN35: 0.324 | AO35: 0.332 | AP35: 0.343 | AQ35: 0.341 | AR35: 0.34 | AS35: 0.329 | AT35: 0.344 | AU35: 0.343
A36: SG&A | B36: ₹m | C36: 1288 | D36: 1329 | E36: 1296 | F36: 1282 | G36: 1336 | H36: 1303 | I36: 1335 | J36: 1298 | K36: 1404 | L36: 1391 | M36: 1458 | N36: 1470 | O36: 1505 | P36: 1543 | Q36: 1632 | R36: 1722 | S36: 1843 | T36: 1691 | U36: 1725 | V36: 1816 | W36: 1523 | X36: 1589 | Y36: 1665 | Z36: 1767 | AA36: 2007 | AB36: 2115 | AC36: 2145 | AD36: 2260 | AE36: 2543 | AF36: 2682 | AG36: 3063 | AH36: 3150 | AI36: 3264 | AJ36: 3392 | AK36: 3508 | AL36: 3561 | AM36: 3625 | AN36: 4858.852 | AO36: 5126.424 | AP36: 5868 | AQ36: 6118 | AR36: 6276 | AS36: 6468 | AT36: 6132 | AU36: 7701
A37: Adjusted EBITDA | B37: ₹m | C37: 1042 | D37: 1194 | E37: 1236 | F37: 1261 | G37: 1015 | H37: 1145 | I37: 1162 | J37: 1523 | K37: 1108 | L37: 1191 | M37: 1295 | N37: 1417 | O37: 1306 | P37: 1634 | Q37: 1805 | R37: 1706 | S37: 1406 | T37: 1898 | U37: 1941 | V37: 1988 | W37: 1806 | X37: 2172 | Y37: 2145 | Z37: 2268 | AA37: 2359 | AB37: 2923 | AC37: 3226 | AD37: 3549 | AE37: 3012 | AF37: 3596 | AG37: 3797 | AH37: 4244 | AI37: 3545 | AJ37: 3997 | AK37: 4170 | AL37: 4473 | AM37: 4286 | AN37: 5063 | AO37: 5890 | AP37: 5871 | AQ37: 6442 | AR37: 7282 | AS37: 7301 | AT37: 9168 | AU37: 11233
A38: ESOP | B38: ₹m | C38: 0 | D38: 0 | E38: 0 | F38: 0 | G38: 0 | H38: 0 | I38: 0 | J38: 0 | K38: 0 | L38: 0 | M38: 0 | N38: 0 | O38: 0 | P38: 0 | Q38: 0 | R38: 0 | S38: 0 | T38: 0 | U38: 0 | V38: 17 | W38: 120 | X38: 124 | Y38: 136 | Z38: 100 | AA38: 159 | AB38: 135 | AC38: 158 | AD38: 210 | AE38: 90 | AF38: 147 | AG38: 182 | AH38: 168 | AI38: 216 | AJ38: 519 | AK38: 0 | AL38: 222 | AM38: 199 | AN38: 222 | AO38: 700 | AP38: 616 | AQ38: 593 | AR38: 561 | AS38: 444 | AT38: 381 | AU38: 457
A39: EBITDA | B39: ₹m | C39: 1042 | D39: 1194 | E39: 1236 | F39: 1261 | G39: 1015 | H39: 1145 | I39: 1162 | J39: 1523 | K39: 1108 | L39: 1191 | M39: 1295 | N39: 1417 | O39: 1306 | P39: 1634 | Q39: 1805 | R39: 1706 | S39: 1406 | T39: 1898 | U39: 1940 | V39: 1988 | W39: 1806 | X39: 2172 | Y39: 2145 | Z39: 2268 | AA39: 2359 | AB39: 2923 | AC39: 3020 | AD39: 3293 | AE39: 2918 | AF39: 3444 | AG39: 3615 | AH39: 4076 | AI39: 3316 | AJ39: 3474 | AK39: 4012 | AL39: 4251 | AM39: 4087 | AN39: 4841 | AO39: 5190 | AP39: 5871 | AQ39: 6442 | AR39: 7282 | AS39: 7302 | AT39: 9168 | AU39: 11233
A40: D&A | B40: ₹m | C40: 276 | D40: 265 | E40: 273 | F40: 287 | G40: 326 | H40: 317 | I40: 321 | J40: 312 | K40: 316 | L40: 341 | M40: 311 | N40: 305 | O40: 312 | P40: 319 | Q40: 314 | R40: 303 | S40: 401 | T40: 447 | U40: 449 | V40: 433 | W40: 465 | X40: 460 | Y40: 462 | Z40: 449 | AA40: 524 | AB40: 598 | AC40: 566 | AD40: 584 | AE40: 630 | AF40: 614 | AG40: 624 | AH40: 717 | AI40: 757 | AJ40: 772 | AK40: 811 | AL40: 846 | AM40: 815 | AN40: 0 | AO40: 0 | AP40: 1254 | AQ40: 1592 | AR40: 1719 | AS40: 1708 | AT40: 1800 | AU40: 2411
A41: EBIT | B41: ₹m | C41: 766 | D41: 929 | E41: 963 | F41: 974 | G41: 689 | H41: 828 | I41: 841 | J41: 1211 | K41: 792 | L41: 850 | M41: 984 | N41: 1112 | O41: 994 | P41: 1315 | Q41: 1491 | R41: 1403 | S41: 1005 | T41: 1451 | U41: 1491 | V41: 1555 | W41: 1341 | X41: 1712 | Y41: 1683 | Z41: 1819 | AA41: 1835 | AB41: 2325 | AC41: 2454 | AD41: 2709 | AE41: 2288 | AF41: 2830 | AG41: 2991 | AH41: 3359 | AI41: 2559 | AJ41: 2702 | AK41: 3201 | AL41: 3405 | AM41: 3272 | AN41: 3598 | AO41: 3922 | AP41: 4195 | AQ41: 4858 | AR41: 5563 | AS41: 5594 | AT41: 7368 | AU41: 8822
A42: Other income, net | B42: ₹m | C42: 79 | D42: 13 | E42: 52 | F42: 39 | G42: 83 | H42: 29 | I42: 59 | J42: -12 | K42: 58 | L42: 87 | M42: 5 | N42: 148 | O42: 209 | P42: 215 | Q42: 5 | R42: 47 | S42: 171 | T42: 76 | U42: 130 | V42: 180 | W42: 48 | X42: -63 | Y42: 19 | Z42: 109 | AA42: 52 | AB42: -77 | AC42: -122 | AD42: -119 | AE42: -76 | AF42: -150 | AG42: 83 | AH42: -487 | AI42: -152 | AJ42: -295 | AK42: -257 | AL42: -452 | AM42: -272 | AO42: -327 | AP42: -92 | AR42: -292 | AS42: -208 | AT42: -179 | AU42: -598
A43: FX gain / loss | B43: ₹m | AP43: -170 | AQ43: -44 | AR43: 310 | AS43: -68 | AT43: -403 | AU43: -653
A44: PBT pre-exceptional | B44: ₹m | C44: 845 | D44: 942 | E44: 1015 | F44: 1013 | G44: 772 | H44: 857 | I44: 900 | J44: 1199 | K44: 849 | L44: 937 | M44: 989 | N44: 1261 | O44: 1203 | P44: 1530 | Q44: 1496 | R44: 1451 | S44: 1176 | T44: 1527 | U44: 1621 | V44: 1718 | W44: 1269 | X44: 1525 | Y44: 1566 | Z44: 1782 | AA44: 1632 | AB44: 2248 | AC44: 2332 | AD44: 2590 | AE44: 2212 | AF44: 2680 | AG44: 3074 | AH44: 2872 | AI44: 2407 | AJ44: 2407 | AK44: 2944 | AL44: 2953 | AM44: 3000 | AN44: 3598 | AO44: 3595 | AP44: 3933 | AQ44: 4402 | AR44: 5582 | AS44: 5318 | AT44: 6786 | AU44: 7571
A45: Exceptional items | B45: ₹m | C45: 800 | D45: 0 | E45: 13 | F45: 13 | G45: 361 | H45: 361 | I45: 13 | J45: -140 | K45: -140 | L45: 0 | M45: 0 | N45: -140 | O45: 0 | P45: 0 | Q45: 0 | R45: 56 | S45: -57 | T45: -57 | U45: 0 | V45: 128 | W45: 180 | X45: 0 | Y45: 0 | Z45: 0 | AA45: 0 | AB45: 0 | AC45: 0 | AD45: 0 | AE45: 0 | AF45: 0 | AG45: 0 | AH45: 0 | AI45: 0 | AJ45: 0 | AK45: 0 | AL45: 97 | AM45: 953 | AN45: 201 | AO45: 0 | AP45: 0 | AQ45: 248 | AR45: 0 | AS45: 1476 | AT45: 536 | AU45: 550
A46: PBT | B46: ₹m | C46: 844 | D46: 942 | E46: 1002 | F46: 1013 | G46: 411 | H46: 856 | I46: 900 | J46: 1339 | K46: 849 | L46: 937 | M46: 989 | N46: 1261 | O46: 1203 | P46: 1530 | Q46: 1496 | R46: 1395 | S46: 1233 | T46: 1527 | U46: 1621 | V46: 1590 | W46: 1089 | X46: 1525 | Y46: 1566 | Z46: 1782 | AA46: 1632 | AB46: 2061 | AC46: 2332 | AD46: 2590 | AE46: 2212 | AF46: 2680 | AG46: 3074 | AH46: 2872 | AI46: 2242 | AJ46: 2407 | AK46: 2944 | AL46: 2856 | AM46: 2047 | AN46: 3135 | AO46: 3433 | AP46: 3933 | AQ46: 3654 | AR46: 5582 | AS46: 3842 | AT46: 6250 | AU46: 7021
A47: Tax | B47: ₹m | C47: 219 | D47: 216 | E47: 212 | F47: 184 | G47: 80 | H47: 213 | I47: 228 | J47: 265 | K47: 295 | L47: 204 | M47: 163 | N47: 288 | O47: 300 | P47: 363 | Q47: 445 | R47: 296 | S47: 318 | T47: 276 | U47: 336 | V47: 348 | W47: 260 | X47: 303 | Y47: 331 | Z47: 408 | AA47: 320 | AB47: 446 | AC47: 360 | AD47: 342 | AE47: 493 | AF47: 474 | AG47: 715 | AH47: 526 | AI47: 485 | AJ47: 528 | AK47: 516 | AL47: 564 | AM47: 654 | AO47: 874 | AP47: 874 | AQ47: 792 | AR47: 1328 | AS47: 875 | AT47: -412 | AU47: 1704
A48: Profit incl. NCI | B48: ₹m | C48: 625 | D48: 726 | E48: 790 | F48: 829 | G48: 331 | H48: 643 | I48: 672 | J48: 1075 | K48: 555 | L48: 733 | M48: 826 | N48: 973 | O48: 904 | P48: 1167 | Q48: 1051 | R48: 1099 | S48: 914 | T48: 1251 | U48: 1285 | V48: 1242 | W48: 829 | X48: 1222 | Y48: 1235 | Z48: 1374 | AA48: 1312 | AB48: 1615 | AC48: 1972 | AD48: 2248 | AE48: 1719 | AF48: 2206 | AG48: 2359 | AH48: 2346 | AI48: 1757 | AJ48: 1879 | AK48: 2428 | AL48: 2292 | AM48: 1393 | AO48: 2559 | AP48: 3073 | AQ48: 3564 | AR48: 4254 | AS48: 2967 | AT48: 6662 | AU48: 5317
A49: NCI | B49: ₹m | C49: 40 | D49: 43 | E49: 48 | F49: 39 | G49: 46 | H49: 54 | I49: 48 | J49: 72 | K49: 42 | L49: 61 | M49: 70 | N49: 112 | O49: 46 | P49: 49 | Q49: 49 | R49: 44 | S49: 24 | T49: 56 | U49: 52 | V49: 106 | W49: 30 | X49: 15 | Y49: 15 | Z49: 44 | AA49: 76 | AB49: 148 | AC49: 135 | AD49: 171 | AE49: 222 | AF49: 195 | AG49: 77 | AH49: 19 | AI49: 104 | AJ49: 69 | AK49: 48 | AL49: 55 | AM49: 61 | AN49: 314 | AO49: 404 | AP49: 461 | AQ49: 390 | AR49: 496 | AS49: 465 | AT49: 539 | AU49: 131
A50: Net income attributable | B50: ₹m | C50: 585 | D50: 683 | E50: 742 | F50: 790 | G50: 285 | H50: 589 | I50: 624 | J50: 1003 | K50: 513 | L50: 672 | M50: 756 | N50: 861 | O50: 858 | P50: 1118 | Q50: 1002 | R50: 1055 | S50: 890 | T50: 1195 | U50: 1233 | V50: 1136 | W50: 799 | X50: 1207 | Y50: 1220 | Z50: 1330 | AA50: 1236 | AB50: 1467 | AC50: 1837 | AD50: 2077 | AE50: 1497 | AF50: 2011 | AG50: 2282 | AH50: 2327 | AI50: 1653 | AJ50: 1810 | AK50: 2380 | AL50: 2237 | AM50: 1332 | AO50: 2155 | AP50: 2612 | AQ50: 3174 | AR50: 3758 | AS50: 2502 | AT50: 6123 | AU50: 5186
A51: Basic EPS | B51: ₹ / share | C51: 9.6 | D51: 11.2 | E51: 12.1 | F51: 12.9 | G51: 4.7 | H51: 9.6 | I51: 10.1 | J51: 16.3 | K51: 8.4 | L51: 11 | M51: 12.3 | N51: 14 | O51: 14 | P51: 18.2 | Q51: 16.3 | R51: 17.1 | S51: 14.4 | T51: 19.3 | U51: 19.8 | V51: 18.2 | W51: 12.8 | X51: 19.9 | Y51: 20.1 | Z51: 21.9 | AA51: 20.4 | AB51: 24.2 | AC51: 30.3 | AD51: 34.1 | AE51: 24.6 | AF51: 33 | AG51: 37.4 | AH51: 38.1 | AI51: 27 | AJ51: 29.6 | AK51: 38.6 | AL51: 36.2 | AM51: 20.9 | AN51: 30.3 | AO51: 32.3 | AP51: 7.5 | AQ51: 7.4 | AR51: 11.2 | AS51: 7.5 | AT51: 18.2 | AU51: 12.3
A55: Annual reported balance sheet
A56: Metric | B56: Units | C56: FY16A | D56: FY17A | E56: FY18A | F56: FY19A | G56: FY20A | H56: FY21A | I56: FY22A | J56: FY23A | K56: FY24A | L56: FY25A | M56: FY26A
A57: PPE | B57: ₹m | C57: 5067.2475 | D57: 4802 | E57: 4500 | F57: 4191 | G57: 4013 | I57: 4452 | J57: 4455 | K57: 4470 | L57: 7682 | M57: 9425
A58: ROU assets | B58: ₹m | D58: 0 | G58: 37 | H58: 614 | I58: 1476 | J58: 2365 | K58: 2927 | L58: 3554 | M58: 3056
A59: CWIP | B59: ₹m | C59: 167.30215 | D59: 0 | E59: 3 | F59: 14 | G59: 3 | H59: 2 | I59: 86 | J59: 46 | K59: 232 | L59: 24 | M59: 33
A60: Goodwill | B60: ₹m | C60: 0 | D60: 1848 | E60: 2430 | F60: 2448 | G60: 4091 | H60: 4226 | I60: 10708 | J60: 11665 | K60: 11738 | L60: 38430 | M60: 41671
A61: Intangibles | B61: ₹m | C61: 3137.3103 | D61: 1826 | E61: 1863 | F61: 1548 | G61: 1897 | H61: 1464 | I61: 4031 | J61: 4634 | K61: 4395 | L61: 11296 | M61: 13443
A62: Non-current investments | B62: ₹m | C62: 0.00012 | D62: 0 | E62: 0 | F62: 0 | G62: 5 | H62: 0 | I62: 5 | J62: 0 | K62: 0
A63: Non-current receivables | B63: ₹m | E63: 53 | F63: 45 | G63: 5 | I63: 1691 | J63: 1772 | K63: 1464 | L63: 3911 | M63: 8477
A64: Other non-current financial assets | B64: ₹m | D64: 205 | E64: 301 | F64: 243 | G64: 650 | H64: 1829 | I64: 421 | J64: 479 | K64: 590 | L64: 893 | M64: 980
A65: Deferred tax assets | B65: ₹m | C65: 258.73942 | D65: 971 | E65: 1231 | F65: 1032 | G65: 1302 | I65: 2736 | J65: 3757 | K65: 5583 | L65: 5470 | M65: 6870
A66: Non-current tax assets | B66: ₹m | I66: 607 | J66: 233 | K66: 285 | L66: 119 | M66: 7
A67: Other non-current assets | B67: ₹m | C67: 1086.3025 | D67: 120 | E67: 134 | F67: 77 | G67: 140 | H67: 254 | I67: 1045 | J67: 1364 | K67: 3368 | L67: 5913 | M67: 5801
A68: Total non-current assets | B68: ₹m | C68: 9716.9019 | D68: 9772 | E68: 10519 | F68: 9598 | G68: 12888 | H68: 13839 | I68: 27335 | J68: 30770 | K68: 35052 | L68: 77292 | M68: 89756
A69: Inventories | B69: ₹m | C69: 2.547213 | D69: 3 | E69: 3 | F69: 8
A70: Contract assets | B70: ₹m | I70: 1184 | J70: 1512 | K70: 1791 | L70: 2426 | M70: 3339
A71: Current investments | B71: ₹m | C71: 740 | D71: 3158 | E71: 3652 | F71: 3651 | G71: 137 | H71: 124 | I71: 5 | L71: 5 | M71: 5
A72: Trade receivables | B72: ₹m | C72: 5900.5955 | D72: 4903 | E72: 5858 | F72: 5877 | G72: 8565 | H72: 8895 | I72: 13894 | J72: 16131 | K72: 18039 | L72: 25771 | M72: 39700
A73: Cash & equivalents | B73: ₹m | C73: 2878.6273 | D73: 3502 | E73: 4102 | F73: 5079 | G73: 8195 | H73: 7999 | I73: 4468 | J73: 5699 | K73: 3213 | L73: 7956 | M73: 10936
A74: Other bank balances | B74: ₹m | C74: 483.32441 | D74: 573 | E74: 81 | F74: 497 | G74: 839 | H74: 123 | I74: 67 | J74: 88 | K74: 139 | L74: 876 | M74: 56
A75: Other current financial assets | B75: ₹m | D75: 1155 | E75: 828 | F75: 1549 | G75: 2427 | H75: 2717 | I75: 662 | J75: 187 | K75: 178 | L75: 535 | M75: 118
A76: Current tax assets | B76: ₹m | D76: 624 | E76: 650 | F76: 203 | G76: 411 | H76: 358
A77: Other current assets | B77: ₹m | C77: 2769.2553 | D77: 958 | E77: 1005 | F77: 1136 | G77: 936 | H77: 1079 | I77: 1934 | J77: 2447 | K77: 2665 | L77: 4487 | M77: 4909
A78: Total current assets | B78: ₹m | C78: 12774.35 | D78: 14876 | E78: 16179 | F78: 17992 | G78: 21510 | H78: 21295 | I78: 22209 | J78: 26064 | K78: 26025 | L78: 43508 | M78: 59058
A79: Assets held for sale | B79: ₹m | F79: 34 | G79: 34 | L79: 32 | M79: 36
A80: Total assets | B80: ₹m | C80: 22491.252 | D80: 24648 | E80: 26698 | F80: 28734 | G80: 34398 | H80: 35134 | I80: 49544 | J80: 56834 | K80: 61077 | L80: 124907 | M80: 148814
A81: Share capital | B81: ₹m | C81: 611.86524 | D81: 614 | E81: 615 | F81: 618 | G81: 625 | H81: 606 | I81: 609 | J81: 611 | K81: 618 | L81: 669 | M81: 672
A82: Other equity | B82: ₹m | C82: 15295.607 | D82: 16251 | E82: 17125 | F82: 105 | G82: 23340 | H82: 24041 | I82: 26722 | J82: 30214 | K82: 35648 | L82: 63123 | M82: 94704
A83: Equity attributable | B83: ₹m | C83: 15907.472 | D83: 16865 | E83: 17740 | F83: 723 | G83: 23965 | H83: 24647 | I83: 27331 | J83: 30825 | K83: 36266 | L83: 63792 | M83: 95376
A84: NCI | B84: ₹m | C84: 645.16793 | D84: 237 | E84: 222 | F84: 75 | G84: 14 | H84: 14 | I84: 12 | J84: 874 | K84: 1003 | L84: 19498 | M84: 1430
A85: Total equity | B85: ₹m | C85: 16552.64 | D85: 17102 | E85: 17962 | F85: 20798 | G85: 23965 | H85: 24661 | I85: 28314 | J85: 31699 | K85: 37269 | L85: 83290 | M85: 96806
A86: Long-term borrowings | B86: ₹m | C86: 63.791706 | D86: 74 | E86: 179 | F86: 100 | G86: 48 | H86: 5 | I86: 3365 | J86: 3382 | K86: 3399 | L86: 67 | M86: 1167
A87: Non-current lease liabilities | B87: ₹m | K87: 2317 | L87: 2735 | M87: 2187
A88: Non-current trade payables | B88: ₹m | D88: 140 | G88: 15 | H88: 325 | I88: 364 | J88: 332 | K88: 627 | L88: 1844 | M88: 2040
A89: Other NC financial liabilities | B89: ₹m | D89: 1416 | E89: 1483 | F89: 538 | G89: 1247 | H89: 546 | I89: 13 | J89: 324 | K89: 253 | L89: 3653 | M89: 4534
A90: Non-current provisions | B90: ₹m | D90: 858 | E90: 741 | F90: 725 | G90: 593 | H90: 696 | I90: 14 | J90: 1276 | K90: 1304 | L90: 1743 | M90: 3189
A91: Deferred tax liabilities | B91: ₹m | D91: 387 | E91: 455 | F91: 395 | G91: 397 | I91: 766 | J91: 583 | K91: 466 | L91: 2184 | M91: 353
A92: Other NC liabilities | B92: ₹m | D92: 82 | E92: 17 | F92: 12 | G92: 17 | H92: 17 | I92: 51 | J92: 59 | K92: 127 | L92: 1591 | M92: 1844
A93: Total non-current liabilities | B93: ₹m | C93: 911.72297 | D93: 2957 | E93: 2889 | F93: 1770 | G93: 2491 | H93: 2048 | I93: 9438 | J93: 7742 | K93: 8493 | L93: 13817 | M93: 15314
A94: Short-term borrowings | B94: ₹m | D94: 0 | I94: 180 | J94: 13 | K94: 13 | L94: 6938 | M94: 2830
A95: Current lease liabilities | B95: ₹m | K95: 577 | L95: 964 | M95: 1094
A96: Trade payables | B96: ₹m | C96: 1654.202 | D96: 1237 | E96: 1453 | F96: 1647 | G96: 2634 | H96: 3398 | I96: 6160 | J96: 6481 | K96: 8062 | L96: 9883 | M96: 17754
A97: Other current financial liabilities | B97: ₹m | D97: 1034 | E97: 1733 | F97: 1587 | G97: 2406 | H97: 1195 | I97: 2398 | J97: 7377 | K97: 2375 | L97: 4554 | M97: 7188
A98: Current provisions | B98: ₹m | C98: 1340.9939 | D98: 642 | E98: 709 | F98: 334 | G98: 329 | H98: 225 | I98: 14 | J98: 360 | K98: 417 | L98: 706 | M98: 987
A99: Current tax liabilities | B99: ₹m | M99: 14
A100: Other current liabilities | B100: ₹m | C100: 2031.693 | D100: 1676 | E100: 1952 | F100: 2265 | G100: 2573 | H100: 3607 | I100: 2324 | J100: 2721 | K100: 2917 | L100: 4330 | M100: 6077
A101: Total current liabilities | B101: ₹m | C101: 5026.8889 | D101: 4589 | E101: 5847 | F101: 5833 | G101: 7942 | H101: 8425 | I101: 11792 | J101: 17393 | K101: 15315 | L101: 27375 | M101: 36694
A102: Liabilities held for sale | B102: ₹m | F102: 34 | G102: 34 | L102: 32 | M102: 36
A103: Total liabilities | B103: ₹m | C103: 5938.6119 | D103: 7546 | E103: 8736 | F103: 7603 | G103: 10433 | H103: 10473 | I103: 21230 | J103: 25135 | K103: 23808 | L103: 41192 | M103: 52008
A107: Annual reported cash flow
A108: Metric | B108: Units | C108: FY16A | D108: FY17A | E108: FY18A | F108: FY19A | G108: FY20A | H108: FY21A | I108: FY22A | J108: FY23A | K108: FY24A | L108: FY25A | M108: FY26A
A109: PBT | B109: ₹m | C109: 3814.5324 | E109: 4036 | H109: 5962 | I109: 8615 | J109: 9512 | K109: 10449
A110: D&A | B110: ₹m | C110: 1101.2935 | E110: 1274 | I110: 2272 | J110: 2585 | K110: 3186 | L110: 4683 | M110: 6819
A111: Share-based payments | B111: ₹m | C111: 17.546337 | E111: 97 | I111: 355 | J111: 544 | K111: 810 | L111: 1700 | M111: 1909
...

Sheet Raw Operating
A1: Raw Reported Operating KPIs
A2: Official disclosures; blanks mean the KPI was not disclosed in that period
A5: Metric | B5: Units | C5: FY16A | D5: FY17A | E5: FY18A | F5: FY19A | G5: FY20A | H5: FY21A | I5: FY22A | J5: FY23A | K5: FY24A | L5: FY25A | M5: FY26A | N5: FY27E | O5: FY28E | P5: FY29E | Q5: FY30E
A7: Revenue | B7: $m | I7: 866.5 | J7: 1001.7 | K7: 1118.7 | L7: 1448 | M7: 1870
A8: Revenue | B8: ₹m | I8: 64320 | J8: 80146 | K8: 91790 | L8: 120733 | M8: 164027
A9: Fresh order intake | B9: $m | C9: 420 | D9: 457 | E9: 507 | F9: 646 | G9: 748 | H9: 781 | I9: 1151 | J9: 1265 | K9: 1973 | L9: 3456 | M9: 2262
A10: Executable order book (next 12m) | B10: $m | C10: 301 | D10: 320 | E10: 339 | F10: 390 | G10: 468 | H10: 520 | I10: 720 | J10: 869 | K10: 1019 | L10: 1505 | M10: 1752
A11: BFS mix | B11: % | C11: 0.17 | D11: 0.19 | E11: 0.17 | F11: 0.16 | G11: 0.16 | H11: 0.17 | I11: 0.255 | J11: 0.307 | K11: 0.322 | L11: 0.305 | M11: 0.265
A12: Insurance mix | B12: % | C12: 0.21 | D12: 0.23 | E12: 0.26 | F12: 0.29 | G12: 0.3 | H12: 0.32 | I12: 0.283 | J12: 0.226 | K12: 0.222 | L12: 0.185 | M12: 0.15
A13: TTH mix | B13: % | C13: 0.35 | D13: 0.32 | E13: 0.27 | F13: 0.27 | G13: 0.28 | H13: 0.19 | I13: 0.19 | J13: 0.191 | K13: 0.18 | L13: 0.183 | M13: 0.23
A14: Government mix | B14: % | C14: 0.04 | D14: 0.03 | E14: 0.01 | L14: 0.077 | M14: 0.07
A15: Healthcare & HiTech mix | B15: % | L15: 0.07 | M15: 0.108
A16: Manufacturing mix | B16: % | C16: 0.08
A17: Others mix | B17: % | C17: 0.15 | F17: 0.28 | G17: 0.26 | H17: 0.31 | J17: 0.275 | K17: 0.276 | L17: 0.179 | M17: 0.177
A18: Americas mix | B18: % | C18: 0.46 | D18: 0.48 | E18: 0.49 | F18: 0.49 | G18: 0.48 | H18: 0.48 | I18: 0.518 | J18: 0.499 | K18: 0.483 | L18: 0.548 | M18: 0.569
A19: EMEA mix | B19: % | C19: 0.34 | D19: 0.33 | E19: 0.31 | F19: 0.33 | G19: 0.37 | H19: 0.37 | I19: 0.354 | J19: 0.389 | K19: 0.394 | L19: 0.337 | M19: 0.289
A20: ROW mix | B20: % | C20: 0.2 | D20: 0.19 | E20: 0.2 | F20: 0.18 | G20: 0.15 | H20: 0.15 | I20: 0.128 | J20: 0.112 | K20: 0.123 | L20: 0.115 | M20: 0.142
A21: Onsite mix | B21: % | C21: 0.59 | D21: 0.6 | E21: 0.61 | F21: 0.65 | G21: 0.64 | H21: 0.62 | I21: 0.56 | J21: 0.501 | K21: 0.483 | L21: 0.468 | M21: 0.476
A22: Offshore mix | B22: % | C22: 0.41 | D22: 0.4 | E22: 0.39 | F22: 0.35 | G22: 0.36 | H22: 0.38 | I22: 0.44 | J22: 0.499 | K22: 0.517 | L22: 0.532 | M22: 0.524
A23: Fixed-price mix | B23: % | C23: 0.45 | D23: 0.48 | E23: 0.46 | F23: 0.47 | G23: 0.48 | H23: 0.54 | I23: 0.54 | J23: 0.52 | K23: 0.504 | L23: 0.462 | M23: 0.469
A24: T&M mix | B24: % | C24: 0.55 | D24: 0.52 | E24: 0.54 | F24: 0.53 | G24: 0.52 | H24: 0.46 | I24: 0.46 | J24: 0.48 | K24: 0.496 | L24: 0.538 | M24: 0.531
A25: Repeat business | B25: % | C25: 0.91 | D25: 0.91 | E25: 0.89 | F25: 0.9 | G25: 0.89 | H25: 0.89 | I25: 0.93 | J25: 0.92 | K25: 0.92 | L25: 0.94 | M25: 0.955
A26: Top 5 clients | B26: % | C26: 0.32 | D26: 0.33 | E26: 0.3 | F26: 0.28 | G26: 0.28 | H26: 0.24 | I26: 0.229 | J26: 0.232 | K26: 0.235 | L26: 0.186 | M26: 0.21
A27: Top 10 clients | B27: % | C27: 0.44 | D27: 0.45 | E27: 0.42 | F27: 0.39 | G27: 0.38 | H27: 0.34 | I27: 0.34 | J27: 0.355 | K27: 0.345 | L27: 0.284 | M27: 0.308
A28: New clients | B28: # | C28: 28 | D28: 15 | E28: 31 | F28: 40 | G28: 41 | H28: 45 | I28: 47 | J28: 44 | K28: 29 | L28: 47 | M28: 31
A29: Average INR / USD | B29: ₹ / $ | C29: 65.32 | D29: 67.08 | E29: 64.54 | F29: 69.55 | G29: 70.54 | H29: 74.32 | I29: 74.18 | J29: 80.05 | K29: 82.78 | L29: 86.6 | M29: 87.8
A30: AI-led Engineering / Engineering mix | B30: % | J30: 0.363 | K30: 0.352 | L30: 0.413 | M30: 0.441
A31: Intelligent Automation mix | B31: % | H31: 0.15 | I31: 0.138 | J31: 0.12 | K31: 0.115 | L31: 0.092 | M31: 0.082
A32: Data mix | B32: % | I32: 0.208 | J32: 0.235 | K32: 0.249 | L32: 0.235 | M32: 0.215
A33: Cloud mix | B33: % | I33: 0.179 | J33: 0.183 | K33: 0.191 | L33: 0.179 | M33: 0.184
A34: BPM mix | B34: % | C34: 0.05 | D34: 0.05 | E34: 0.04 | F34: 0.04 | G34: 0.03 | H34: 0.03 | I34: 0.107 | J34: 0.099 | K34: 0.094 | L34: 0.081 | M34: 0.079
A35: ADM mix | B35: % | C35: 0.65 | D35: 0.67 | E35: 0.66 | F35: 0.69 | G35: 0.73 | H35: 0.7
A36: IP Assets mix | B36: % | C36: 0.08 | D36: 0.07 | E36: 0.07 | F36: 0.06 | G36: 0.06 | H36: 0.07
A37: Managed Services mix | B37: % | C37: 0.17 | D37: 0.18 | E37: 0.19 | F37: 0.18 | G37: 0.17 | H37: 0.17
A38: SI & PI mix | B38: % | C38: 0.05 | D38: 0.04 | E38: 0.04 | F38: 0.04 | G38: 0.01 | H38: 0.04
A39: Product Engineering mix | B39: % | H39: 0.16 | I39: 0.12 | J39: 0.101 | K39: 0.085
A40: Software Engineering mix | B40: % | J40: 0.262 | K40: 0.267
A41: Gross margin | B41: % | C41: 0.357 | D41: 44 | E41: 0.379 | F41: -36 | G41: 0.344 | H41: -218 | I41: 0.32 | J41: 71 | K41: 0.326 | L41: 0.337 | M41: 0.338
A42: Adjusted EBITDA margin | B42: % | C42: 0.163 | D42: 106 | E42: 0.205 | F42: -112 | I42: 0.187 | J42: 109 | K42: 0.176 | L42: 0.143 | M42: 0.186
A43: Headcount | B43: # | C43: 9476 | D43: 8853 | E43: 9423 | F43: 10263 | G43: 11156 | H43: 12391 | I43: 22500 | J43: 23224 | K43: 24726 | L43: 33497 | M43: 35777
A44: IT billable | B44: # | I44: 14903 | J44: 16182 | K44: 16930 | L44: 23510 | M44: 25062
A45: BPS billable | B45: # | I45: 6391 | J45: 5633 | K45: 6313 | L45: 7844 | M45: 8581
A46: Total billable | B46: # | C46: 8743 | D46: 8066 | E46: 8588 | F46: 9363 | G46: 10274 | H46: 11469 | I46: 21294 | J46: 21815 | K46: 23243 | L46: 31354 | M46: 33643
A47: Revenue per IT billable | B47: $ / FTE | M47: 71795
A48: Utilization | B48: % | C48: 0.79 | D48: 0.81 | E48: 0.795 | F48: 0.793 | G48: 0.781 | H48: 0.81 | I48: 0.761 | J48: 0.815 | K48: 0.817 | L48: 0.82 | M48: 0.825
A49: Attrition | B49: % | C49: 0.127 | D49: 0.127 | E49: 0.105 | F49: 0.122 | G49: 0.118 | H49: 0.105 | I49: 0.177 | J49: 0.141 | K49: 0.115 | L49: 0.109 | M49: 0.108
A50: Billed DSO | B50: days | C50: 80 | D50: 64 | E50: 70 | F50: 62 | G50: 74 | H50: 70 | I50: 63 | J50: 61 | K50: 56 | L50: 60 | M50: 69
A51: Unbilled DSO | B51: days | M51: 25
A52: Contract-asset DSO | B52: days | M52: 13
A53: Clients $1–5m | B53: # | C53: 51 | D53: 55 | E53: 60 | F53: 66 | G53: 80 | H53: 88 | I53: 100 | J53: 101 | K53: 112 | L53: 173 | M53: 167
A54: Clients $5–10m | B54: # | C54: 16 | D54: 10 | E54: 13 | F54: 16 | G54: 15 | H54: 16 | I54: 19 | J54: 23 | K54: 24 | L54: 35 | M54: 42
A55: Clients $10–20m | B55: # | M55: 23
A56: Clients $20–50m | B56: # | M56: 9
A57: Clients $50–100m | B57: # | M57: 3
A58: Clients >$100m | B58: # | M58: 1
A59: Clients >$10m | B59: # | C59: 6 | D59: 8 | E59: 7 | F59: 8 | I59: 18 | J59: 21 | K59: 24 | L59: 31

Sheet Quarterly P&L
A1: Quarterly Profit & Loss
A2: Reported quarters only; annual restatement / classification differences are shown as a bridge, not forced into Q4
A5: Metric | B5: Units | C5: Q1 FY16A | D5: Q2 FY16A | E5: Q3 FY16A | F5: Q4 FY16A | G5: Q1 FY17A | H5: Q2 FY17A | I5: Q3 FY17A | J5: Q4 FY17A | K5: Q1 FY18A | L5: Q2 FY18A | M5: Q3 FY18A | N5: Q4 FY18A | O5: Q1 FY19A | P5: Q2 FY19A | Q5: Q3 FY19A | R5: Q4 FY19A | S5: Q1 FY20A | T5: Q2 FY20A | U5: Q3 FY20A | V5: Q4 FY20A | W5: Q1 FY21A | X5: Q2 FY21A | Y5: Q3 FY21A | Z5: Q4 FY21A | AA5: Q1 FY22A | AB5: Q2 FY22A | AC5: Q3 FY22A | AD5: Q4 FY22A | AE5: Q1 FY23A | AF5: Q2 FY23A | AG5: Q3 FY23A | AH5: Q4 FY23A | AI5: Q1 FY24A | AJ5: Q2 FY24A | AK5: Q3 FY24A | AL5: Q4 FY24A | AM5: Q1 FY25A | AN5: Q2 FY25A | AO5: Q3 FY25A | AP5: Q4 FY25A | AQ5: Q1 FY26A | AR5: Q2 FY26A | AS5: Q3 FY26A | AT5: Q4 FY26A | AU5: Q1 FY27A
A6: Revenue | B6: ₹m | C6: ='Raw Financials'!C32 -> 6411 | D6: ='Raw Financials'!D32 -> 6779 | E6: ='Raw Financials'!E32 -> 6787 | F6: ='Raw Financials'!F32 -> 6847 | G6: ='Raw Financials'!G32 -> 6707 | H6: ='Raw Financials'!H32 -> 6929 | I6: ='Raw Financials'!I32 -> 6938 | J6: ='Raw Financials'!J32 -> 7447 | ... AU6: ='Raw Financials'!AU32 -> 55277
A7: Revenue growth QoQ | B7: % | D7: =IFERROR(D6/C6-1,"") -> 0.057401341 | E7: =IFERROR(E6/D6-1,"") -> 0.0011801151 | F7: =IFERROR(F6/E6-1,"") -> 0.0088404302 | G7: =IFERROR(G6/F6-1,"") -> -0.020446911 | H7: =IFERROR(H6/G6-1,"") -> 0.033099747 | I7: =IFERROR(I6/H6-1,"") -> 0.0012988887 | J7: =IFERROR(J6/I6-1,"") -> 0.073364082 | K7: =IFERROR(K6/J6-1,"") -> -0.04807305 | ... AU7: =IFERROR(AU6/AT6-1,"") -> 0.24206813
A8: Cost of revenue | B8: ₹m | C8: ='Raw Financials'!C33 -> 4081 | D8: ='Raw Financials'!D33 -> 4256 | E8: ='Raw Financials'!E33 -> 4255 | F8: ='Raw Financials'!F33 -> 4304 | G8: ='Raw Financials'!G33 -> 4356 | H8: ='Raw Financials'!H33 -> 4481 | I8: ='Raw Financials'!I33 -> 4441 | J8: ='Raw Financials'!J33 -> 4625 | ... AU8: ='Raw Financials'!AU33 -> 36343
A9: Gross profit | B9: ₹m | C9: ='Raw Financials'!C34 -> 2330 | D9: ='Raw Financials'!D34 -> 2523 | E9: ='Raw Financials'!E34 -> 2532 | F9: ='Raw Financials'!F34 -> 2543 | G9: ='Raw Financials'!G34 -> 2351 | H9: ='Raw Financials'!H34 -> 2448 | I9: ='Raw Financials'!I34 -> 2497 | J9: ='Raw Financials'!J34 -> 2822 | ... AU9: ='Raw Financials'!AU34 -> 18934
A10: Gross margin | B10: % | C10: ='Raw Financials'!C35 -> 0.364 | D10: ='Raw Financials'!D35 -> 0.372 | E10: ='Raw Financials'!E35 -> 0.373 | F10: ='Raw Financials'!F35 -> 0.371 | G10: ='Raw Financials'!G35 -> 0.351 | H10: ='Raw Financials'!H35 -> 0.353 | I10: ='Raw Financials'!I35 -> 0.36 | J10: ='Raw Financials'!J35 -> 0.379 | ... AU10: ='Raw Financials'!AU35 -> 0.343
A11: SG&A | B11: ₹m | C11: ='Raw Financials'!C36 -> 1288 | D11: ='Raw Financials'!D36 -> 1329 | E11: ='Raw Financials'!E36 -> 1296 | F11: ='Raw Financials'!F36 -> 1282 | G11: ='Raw Financials'!G36 -> 1336 | H11: ='Raw Financials'!H36 -> 1303 | I11: ='Raw Financials'!I36 -> 1335 | J11: ='Raw Financials'!J36 -> 1298 | ... AU11: ='Raw Financials'!AU36 -> 7701
A12: Adjusted EBITDA | B12: ₹m | C12: ='Raw Financials'!C37 -> 1042 | D12: ='Raw Financials'!D37 -> 1194 | E12: ='Raw Financials'!E37 -> 1236 | F12: ='Raw Financials'!F37 -> 1261 | G12: ='Raw Financials'!G37 -> 1015 | H12: ='Raw Financials'!H37 -> 1145 | I12: ='Raw Financials'!I37 -> 1162 | J12: ='Raw Financials'!J37 -> 1523 | ... AU12: ='Raw Financials'!AU37 -> 11233
A13: Adjusted EBITDA margin | B13: % | C13: =IFERROR(C12/C6,"") -> 0.16253315 | D13: =IFERROR(D12/D6,"") -> 0.17613217 | E13: =IFERROR(E12/E6,"") -> 0.18211286 | F13: =IFERROR(F12/F6,"") -> 0.18416825 | G13: =IFERROR(G12/G6,"") -> 0.15133443 | H13: =IFERROR(H12/H6,"") -> 0.16524751 | I13: =IFERROR(I12/I6,"") -> 0.16748342 | J13: =IFERROR(J12/J6,"") -> 0.20451188 | ... AU13: =IFERROR(AU12/AU6,"") -> 0.20321291
A14: ESOP | B14: ₹m | C14: ='Raw Financials'!C38 -> 0 | D14: ='Raw Financials'!D38 -> 0 | E14: ='Raw Financials'!E38 -> 0 | F14: ='Raw Financials'!F38 -> 0 | G14: ='Raw Financials'!G38 -> 0 | H14: ='Raw Financials'!H38 -> 0 | I14: ='Raw Financials'!I38 -> 0 | J14: ='Raw Financials'!J38 -> 0 | ... AU14: ='Raw Financials'!AU38 -> 457
A15: EBITDA | B15: ₹m | C15: ='Raw Financials'!C39 -> 1042 | D15: ='Raw Financials'!D39 -> 1194 | E15: ='Raw Financials'!E39 -> 1236 | F15: ='Raw Financials'!F39 -> 1261 | G15: ='Raw Financials'!G39 -> 1015 | H15: ='Raw Financials'!H39 -> 1145 | I15: ='Raw Financials'!I39 -> 1162 | J15: ='Raw Financials'!J39 -> 1523 | ... AU15: ='Raw Financials'!AU39 -> 11233
A16: EBITDA margin | B16: % | C16: =IFERROR(C15/C6,"") -> 0.16253315 | D16: =IFERROR(D15/D6,"") -> 0.17613217 | E16: =IFERROR(E15/E6,"") -> 0.18211286 | F16: =IFERROR(F15/F6,"") -> 0.18416825 | G16: =IFERROR(G15/G6,"") -> 0.15133443 | H16: =IFERROR(H15/H6,"") -> 0.16524751 | I16: =IFERROR(I15/I6,"") -> 0.16748342 | J16: =IFERROR(J15/J6,"") -> 0.20451188 | ... AU16: =IFERROR(AU15/AU6,"") -> 0.20321291
A17: D&A | B17: ₹m | C17: ='Raw Financials'!C40 -> 276 | D17: ='Raw Financials'!D40 -> 265 | E17: ='Raw Financials'!E40 -> 273 | F17: ='Raw Financials'!F40 -> 287 | G17: ='Raw Financials'!G40 -> 326 | H17: ='Raw Financials'!H40 -> 317 | I17: ='Raw Financials'!I40 -> 321 | J17: ='Raw Financials'!J40 -> 312 | ... AU17: ='Raw Financials'!AU40 -> 2411
A18: EBIT | B18: ₹m | C18: ='Raw Financials'!C41 -> 766 | D18: ='Raw Financials'!D41 -> 929 | E18: ='Raw Financials'!E41 -> 963 | F18: ='Raw Financials'!F41 -> 974 | G18: ='Raw Financials'!G41 -> 689 | H18: ='Raw Financials'!H41 -> 828 | I18: ='Raw Financials'!I41 -> 841 | J18: ='Raw Financials'!J41 -> 1211 | ... AU18: ='Raw Financials'!AU41 -> 8822
A19: EBIT margin | B19: % | C19: =IFERROR(C18/C6,"") -> 0.11948214 | D19: =IFERROR(D18/D6,"") -> 0.13704086 | E19: =IFERROR(E18/E6,"") -> 0.14188891 | F19: =IFERROR(F18/F6,"") -> 0.14225208 | G19: =IFERROR(G18/G6,"") -> 0.10272849 | H19: =IFERROR(H18/H6,"") -> 0.11949776 | I19: =IFERROR(I18/I6,"") -> 0.12121649 | J19: =IFERROR(J18/J6,"") -> 0.16261582 | ... AU19: =IFERROR(AU18/AU6,"") -> 0.15959622
A20: Other income, net | B20: ₹m | C20: ='Raw Financials'!C42 -> 79 | D20: ='Raw Financials'!D42 -> 13 | E20: ='Raw Financials'!E42 -> 52 | F20: ='Raw Financials'!F42 -> 39 | G20: ='Raw Financials'!G42 -> 83 | H20: ='Raw Financials'!H42 -> 29 | I20: ='Raw Financials'!I42 -> 59 | J20: ='Raw Financials'!J42 -> -12 | ... AU20: ='Raw Financials'!AU42 -> -598
A21: FX gain / loss | B21: ₹m | C21: ='Raw Financials'!C43 -> 0 | D21: ='Raw Financials'!D43 -> 0 | E21: ='Raw Financials'!E43 -> 0 | F21: ='Raw Financials'!F43 -> 0 | G21: ='Raw Financials'!G43 -> 0 | H21: ='Raw Financials'!H43 -> 0 | I21: ='Raw Financials'!I43 -> 0 | J21: ='Raw Financials'!J43 -> 0 | ... AU21: ='Raw Financials'!AU43 -> -653
A22: PBT pre-exceptional | B22: ₹m | C22: ='Raw Financials'!C44 -> 845 | D22: ='Raw Financials'!D44 -> 942 | E22: ='Raw Financials'!E44 -> 1015 | F22: ='Raw Financials'!F44 -> 1013 | G22: ='Raw Financials'!G44 -> 772 | H22: ='Raw Financials'!H44 -> 857 | I22: ='Raw Financials'!I44 -> 900 | J22: ='Raw Financials'!J44 -> 1199 | ... AU22: ='Raw Financials'!AU44 -> 7571
A23: Exceptional items | B23: ₹m | C23: ='Raw Financials'!C45 -> 800 | D23: ='Raw Financials'!D45 -> 0 | E23: ='Raw Financials'!E45 -> 13 | F23: ='Raw Financials'!F45 -> 13 | G23: ='Raw Financials'!G45 -> 361 | H23: ='Raw Financials'!H45 -> 361 | I23: ='Raw Financials'!I45 -> 13 | J23: ='Raw Financials'!J45 -> -140 | ... AU23: ='Raw Financials'!AU45 -> 550
A24: PBT | B24: ₹m | C24: ='Raw Financials'!C46 -> 844 | D24: ='Raw Financials'!D46 -> 942 | E24: ='Raw Financials'!E46 -> 1002 | F24: ='Raw Financials'!F46 -> 1013 | G24: ='Raw Financials'!G46 -> 411 | H24: ='Raw Financials'!H46 -> 856 | I24: ='Raw Financials'!I46 -> 900 | J24: ='Raw Financials'!J46 -> 1339 | ... AU24: ='Raw Financials'!AU46 -> 7021
A25: Tax | B25: ₹m | C25: ='Raw Financials'!C47 -> 219 | D25: ='Raw Financials'!D47 -> 216 | E25: ='Raw Financials'!E47 -> 212 | F25: ='Raw Financials'!F47 -> 184 | G25: ='Raw Financials'!G47 -> 80 | H25: ='Raw Financials'!H47 -> 213 | I25: ='Raw Financials'!I47 -> 228 | J25: ='Raw Financials'!J47 -> 265 | ... AU25: ='Raw Financials'!AU47 -> 1704
A26: Profit incl. NCI | B26: ₹m | C26: ='Raw Financials'!C48 -> 625 | D26: ='Raw Financials'!D48 -> 726 | E26: ='Raw Financials'!E48 -> 790 | F26: ='Raw Financials'!F48 -> 829 | G26: ='Raw Financials'!G48 -> 331 | H26: ='Raw Financials'!H48 -> 643 | I26: ='Raw Financials'!I48 -> 672 | J26: ='Raw Financials'!J48 -> 1075 | ... AU26: ='Raw Financials'!AU48 -> 5317
A27: NCI | B27: ₹m | C27: ='Raw Financials'!C49 -> 40 | D27: ='Raw Financials'!D49 -> 43 | E27: ='Raw Financials'!E49 -> 48 | F27: ='Raw Financials'!F49 -> 39 | G27: ='Raw Financials'!G49 -> 46 | H27: ='Raw Financials'!H49 -> 54 | I27: ='Raw Financials'!I49 -> 48 | J27: ='Raw Financials'!J49 -> 72 | ... AU27: ='Raw Financials'!AU49 -> 131
A28: Net income attributable | B28: ₹m | C28: ='Raw Financials'!C50 -> 585 | D28: ='Raw Financials'!D50 -> 683 | E28: ='Raw Financials'!E50 -> 742 | F28: ='Raw Financials'!F50 -> 790 | G28: ='Raw Financials'!G50 -> 285 | H28: ='Raw Financials'!H50 -> 589 | I28: ='Raw Financials'!I50 -> 624 | J28: ='Raw Financials'!J50 -> 1003 | ... AU28: ='Raw Financials'!AU50 -> 5186
A29: Net margin | B29: % | C29: =IFERROR(C28/C6,"") -> 0.091249415 | D29: =IFERROR(D28/D6,"") -> 0.10075232 | E29: =IFERROR(E28/E6,"") -> 0.10932665 | F29: =IFERROR(F28/F6,"") -> 0.115379 | G29: =IFERROR(G28/G6,"") -> 0.042492918 | H29: =IFERROR(H28/H6,"") -> 0.085005051 | I29: =IFERROR(I28/I6,"") -> 0.089939464 | J29: =IFERROR(J28/J6,"") -> 0.13468511 | ... AU29: =IFERROR(AU28/AU6,"") -> 0.093818405
A30: Basic EPS | B30: ₹ / share | C30: ='Raw Financials'!C51 -> 9.6 | D30: ='Raw Financials'!D51 -> 11.2 | E30: ='Raw Financials'!E51 -> 12.1 | F30: ='Raw Financials'!F51 -> 12.9 | G30: ='Raw Financials'!G51 -> 4.7 | H30: ='Raw Financials'!H51 -> 9.6 | I30: ='Raw Financials'!I51 -> 10.1 | J30: ='Raw Financials'!J51 -> 16.3 | ... AU30: ='Raw Financials'!AU51 -> 12.3

Sheet Annual P&L
A1: Annual Profit & Loss
A2: Audited history and formula-driven FY27E–FY30E forecast
A5: Metric | B5: Units | C5: FY16A | D5: FY17A | E5: FY18A | F5: FY19A | G5: FY20A | H5: FY21A | I5: FY22A | J5: FY23A | K5: FY24A | L5: FY25A | M5: FY26A | N5: FY27E | O5: FY28E | P5: FY29E | Q5: FY30E
A7: Revenue | B7: ₹m | C7: ='Raw Financials'!C6 -> 26824.049 | D7: ='Raw Financials'!D6 -> 28021 | E7: ='Raw Financials'!E6 -> 29914 | F7: ='Raw Financials'!F6 -> 36762 | G7: ='Raw Financials'!G6 -> 41839 | H7: ='Raw Financials'!H6 -> 46628 | I7: ='Raw Financials'!I6 -> 64320 | J7: ='Raw Financials'!J6 -> 80146 | ... M7: ='Raw Financials'!M6 -> 164027 | N7: ='Order Book & Revenue'!N31 -> 228523.77 | O7: ='Order Book & Revenue'!O31 -> 293835.96 | P7: ='Order Book & Revenue'!P31 -> 369616.09 | Q7: ='Order Book & Revenue'!Q31 -> 457101.52
A8: Revenue growth | B8: % | D8: =IFERROR(D7/C7-1,"") -> 0.044622317 | E8: =IFERROR(E7/D7-1,"") -> 0.067556476 | F8: =IFERROR(F7/E7-1,"") -> 0.22892291 | G8: =IFERROR(G7/F7-1,"") -> 0.13810456 | H8: =IFERROR(H7/G7-1,"") -> 0.11446258 | I8: =IFERROR(I7/H7-1,"") -> 0.37942867 | J8: =IFERROR(J7/I7-1,"") -> 0.246051 | K8: =IFERROR(K7/J7-1,"") -> 0.14528486 | ... Q8: =IFERROR(Q7/P7-1,"") -> 0.2366927
A9: Cost of revenue | B9: ₹m | C9: =SUM('Raw Financials'!C9,'Raw Financials'!C10,'Raw Financials'!C11,'Raw Financials'!C12) -> 15694.798 | D9: =SUM('Raw Financials'!D9,'Raw Financials'!D10,'Raw Financials'!D11,'Raw Financials'!D12) -> 16654 | E9: =SUM('Raw Financials'!E9,'Raw Financials'!E10,'Raw Financials'!E11,'Raw Financials'!E12) -> 17918 | F9: =SUM('Raw Financials'!F9,'Raw Financials'!F10,'Raw Financials'!F11,'Raw Financials'!F12) -> 21823 | G9: =SUM('Raw Financials'!G9,'Raw Financials'!G10,'Raw Financials'!G11,'Raw Financials'!G12) -> 26142 | H9: =SUM('Raw Financials'!H9,'Raw Financials'!H10,'Raw Financials'!H11,'Raw Financials'!H12) -> 30093 | I9: =SUM('Raw Financials'!I9,'Raw Financials'!I10,'Raw Financials'!I11,'Raw Financials'!I12) -> 40070 | J9: =SUM('Raw Financials'!J9,'Raw Financials'!J10,'Raw Financials'!J11,'Raw Financials'!J12) -> 48831 | K9: =K7-K10 -> 61866.46 | L9: =L7-L10 -> 80045.979 | M9: =M7-M10 -> 108585.87 | N9: =N7-N10 -> 150140.12 | O9: =O7-O10 -> 191874.88 | P9: =P7-P10 -> 240250.46 | Q9: =Q7-Q10 -> 295744.68
A10: Gross profit | B10: ₹m | C10: =C7-C9 -> 11129.251 | D10: =D7-D9 -> 11367 | E10: =E7-E9 -> 11996 | F10: =F7-F9 -> 14939 | G10: =G7-G9 -> 15697 | H10: =H7-H9 -> 16535 | I10: =I7-I9 -> 24250 | J10: =J7-J9 -> 31315 | K10: =K7*'Raw Operating'!K41 -> 29923.54 | L10: =L7*'Raw Operating'!L41 -> 40687.021 | M10: =M7*'Raw Operating'!M41 -> 55441.126 | N10: =N7*Assumptions!C20 -> 78383.654 | O10: =O7*Assumptions!D20 -> 101961.08 | P10: =P7*Assumptions!E20 -> 129365.63 | Q10: =Q7*Assumptions!F20 -> 161356.84
A11: Gross margin | B11: % | C11: =IFERROR(C10/C7,"") -> 0.41489825 | D11: =IFERROR(D10/D7,"") -> 0.40566004 | E11: =IFERROR(E10/E7,"") -> 0.40101625 | F11: =IFERROR(F10/F7,"") -> 0.40637071 | G11: =IFERROR(G10/G7,"") -> 0.37517627 | H11: =IFERROR(H10/H7,"") -> 0.35461525 | I11: =IFERROR(I10/I7,"") -> 0.37702114 | J11: =IFERROR(J10/J7,"") -> 0.39072443 | K11: =K10/K7 -> 0.326 | L11: =L10/L7 -> 0.337 | M11: =M10/M7 -> 0.338 | N11: =N10/N7 -> 0.343 | O11: =O10/O7 -> 0.347 | P11: =P10/P7 -> 0.35 | Q11: =Q10/Q7 -> 0.353
A12: SG&A | B12: ₹m | C12: ='Raw Financials'!C13 -> 6287.5291 | D12: ='Raw Financials'!D13 -> 6573 | E12: ='Raw Financials'!E13 -> 6983 | F12: ='Raw Financials'!F13 -> 8454 | G12: ='Raw Financials'!G13 -> 8464 | H12: ='Raw Financials'!H13 -> 8740 | I12: ='Raw Financials'!I13 -> 13231 | J12: ='Raw Financials'!J13 -> 18508 | K12: =K10-K13 -> 13768.5 | L12: =L10-L13 -> 23422.202 | M12: =M10-M13 -> 24932.104 | N12: =N7*Assumptions!C21 -> 31536.281 | O12: =O7*Assumptions!D21 -> 39667.855 | P12: =P7*Assumptions!E21 -> 48789.324 | Q12: =Q7*Assumptions!F21 -> 59423.198
A13: Adjusted EBITDA | B13: ₹m | C13: =C10-C12 -> 4841.7219 | D13: =D10-D12 -> 4794 | E13: =E10-E12 -> 5013 | F13: =F10-F12 -> 6485 | G13: =G10-G12 -> 7233 | H13: =H10-H12 -> 7795 | I13: =I10-I12 -> 11019 | J13: =J10-J12 -> 12807 | K13: =K7*'Raw Operating'!K42 -> 16155.04 | L13: =L7*'Raw Operating'!L42 -> 17264.819 | M13: =M7*'Raw Operating'!M42 -> 30509.022 | N13: =N10-N12 -> 46847.374 | O13: =O10-O12 -> 62293.224 | P13: =P10-P12 -> 80576.308 | Q13: =Q10-Q12 -> 101933.64
A14: Adjusted EBITDA margin | B14: % | C14: =IFERROR(C13/C7,"") -> 0.18049929 | D14: =IFERROR(D13/D7,"") -> 0.17108597 | E14: =IFERROR(E13/E7,"") -> 0.1675804 | F14: =IFERROR(F13/F7,"") -> 0.17640498 | G14: =IFERROR(G13/G7,"") -> 0.17287698 | H14: =IFERROR(H13/H7,"") -> 0.16717423 | I14: =IFERROR(I13/I7,"") -> 0.1713153 | J14: =IFERROR(J13/J7,"") -> 0.15979587 | K14: =K13/K7 -> 0.176 | L14: =L13/L7 -> 0.143 | M14: =M13/M7 -> 0.186 | N14: =N13/N7 -> 0.205 | O14: =O13/O7 -> 0.212 | P14: =P13/P7 -> 0.218 | Q14: =Q13/Q7 -> 0.223
A15: Share-based compensation | B15: ₹m | C15: =0 -> 0 | D15: =0 -> 0 | E15: =0 -> 0 | F15: =0 -> 0 | G15: =0 -> 0 | H15: =0 -> 0 | I15: =0 -> 0 | J15: =0 -> 0 | ... M15: =0 -> 0 | N15: =N7*Assumptions!C22 -> 1371.1426 | O15: =O7*Assumptions!D22 -> 1763.0158 | P15: =P7*Assumptions!E22 -> 2217.6966 | Q15: =Q7*Assumptions!F22 -> 2742.6091
A16: EBITDA | B16: ₹m | C16: =C13-C15 -> 4841.7219 | D16: =D13-D15 -> 4794 | E16: =E13-E15 -> 5013 | F16: =F13-F15 -> 6485 | G16: =G13-G15 -> 7233 | H16: =H13-H15 -> 7795 | I16: =I13-I15 -> 11019 | J16: =J13-J15 -> 12807 | ... Q16: =Q13-Q15 -> 99191.03
A17: EBITDA margin | B17: % | C17: =IFERROR(C16/C7,"") -> 0.18049929 | D17: =IFERROR(D16/D7,"") -> 0.17108597 | E17: =IFERROR(E16/E7,"") -> 0.1675804 | F17: =IFERROR(F16/F7,"") -> 0.17640498 | G17: =IFERROR(G16/G7,"") -> 0.17287698 | H17: =IFERROR(H16/H7,"") -> 0.16717423 | I17: =IFERROR(I16/I7,"") -> 0.1713153 | J17: =IFERROR(J16/J7,"") -> 0.15979587 | K17: =K16/K7 -> 0.176 | L17: =L16/L7 -> 0.143 | M17: =M16/M7 -> 0.186 | N17: =N16/N7 -> 0.199 | O17: =O16/O7 -> 0.206 | P17: =P16/P7 -> 0.212 | Q17: =Q16/Q7 -> 0.217
A18: D&A | B18: ₹m | C18: ='Raw Financials'!C15 -> 1101.2935 | D18: ='Raw Financials'!D15 -> 1277 | E18: ='Raw Financials'!E15 -> 1274 | F18: ='Raw Financials'!F15 -> 1248 | G18: ='Raw Financials'!G15 -> 1730 | H18: ='Raw Financials'!H15 -> 1836 | I18: ='Raw Financials'!I15 -> 2272 | J18: ='Raw Financials'!J15 -> 2585 | ... M18: ='Raw Financials'!M15 -> 6819 | N18: =N7*Assumptions!C23 -> 11197.665 | O18: =O7*Assumptions!D23 -> 13516.454 | P18: =P7*Assumptions!E23 -> 15893.492 | Q18: =Q7*Assumptions!F23 -> 18284.061
A19: EBIT | B19: ₹m | C19: =C16-C18 -> 3740.4283 | D19: =D16-D18 -> 3517 | E19: =E16-E18 -> 3739 | F19: =F16-F18 -> 5237 | G19: =G16-G18 -> 5503 | H19: =H16-H18 -> 5959 | I19: =I16-I18 -> 8747 | J19: =J16-J18 -> 10222 | ... Q19: =Q16-Q18 -> 80906.969
A20: EBIT margin | B20: % | C20: =IFERROR(C19/C7,"") -> 0.13944309 | D20: =IFERROR(D19/D7,"") -> 0.12551301 | E20: =IFERROR(E19/E7,"") -> 0.12499164 | F20: =IFERROR(F19/F7,"") -> 0.14245688 | G20: =IFERROR(G19/G7,"") -> 0.131528 | H20: =IFERROR(H19/H7,"") -> 0.12779875 | I20: =IFERROR(I19/I7,"") -> 0.13599192 | J20: =IFERROR(J19/J7,"") -> 0.12754224 | K20: =K19/K7 -> 0.14129034 | L20: =L19/L7 -> 0.10758301 | M20: =M19/M7 -> 0.14442758 | N20: =N19/N7 -> 0.15 | O20: =O19/O7 -> 0.16 | P20: =P19/P7 -> 0.169 | Q20: =Q19/Q7 -> 0.177
A21: Other income | B21: ₹m | C21: ='Raw Financials'!C7 -> 205.4828 | D21: ='Raw Financials'!D7 -> 269 | E21: ='Raw Financials'!E7 -> 391 | F21: ='Raw Financials'!F7 -> 535 | G21: ='Raw Financials'!G7 -> 677 | H21: ='Raw Financials'!H7 -> 326 | I21: ='Raw Financials'!I7 -> 518 | J21: ='Raw Financials'!J7 -> 619 | ... M21: ='Raw Financials'!M7 -> 732 | N21: =N7*Assumptions!C24 -> 1142.6189 | O21: =O7*Assumptions!D24 -> 1469.1798 | P21: =P7*Assumptions!E24 -> 1848.0805 | Q21: =Q7*Assumptions!F24 -> 2285.5076
A22: Finance costs | B22: ₹m | C22: ='Raw Financials'!C14 -> 48.795223 | D22: ='Raw Financials'!D14 -> 60 | E22: ='Raw Financials'!E14 -> 94 | F22: ='Raw Financials'!F14 -> 92 | G22: ='Raw Financials'!G14 -> 155 | H22: ='Raw Financials'!H14 -> 143 | I22: ='Raw Financials'!I14 -> 650 | J22: ='Raw Financials'!J14 -> 806 | ... M22: ='Raw Financials'!M14 -> 1686 | N22: ='Acquisition & Debt'!C22 -> 2218.4 | O22: ='Acquisition & Debt'!D22 -> 1814.5 | P22: ='Acquisition & Debt'!E22 -> 739.2 | Q22: ='Acquisition & Debt'!F22 -> 48.5
A23: PBT pre-exceptional | B23: ₹m | C23: ='Raw Financials'!C16 -> 3814.5324 | D23: ='Raw Financials'!D16 -> 3727 | E23: ='Raw Financials'!E16 -> 4036 | F23: ='Raw Financials'!F16 -> 5680 | G23: ='Raw Financials'!G16 -> 6025 | H23: ='Raw Financials'!H16 -> 6142 | I23: ='Raw Financials'!I16 -> 8615 | J23: ='Raw Financials'!J16 -> 10035 | ... M23: ='Raw Financials'!M16 -> 21588 | N23: =N19+N21-N22 -> 33202.785 | O23: =O19+O21-O22 -> 46668.433 | P23: =P19+P21-P22 -> 63574 | Q23: =Q19+Q21-Q22 -> 83143.977
A24: Exceptional items | B24: ₹m | C24: ='Raw Financials'!C17 -> 13.156528 | D24: ='Raw Financials'!D17 -> 221 | E24: ='Raw Financials'!E17 -> 0 | F24: ='Raw Financials'!F17 -> 56 | G24: ='Raw Financials'!G17 -> 71 | H24: ='Raw Financials'!H17 -> 180 | I24: ='Raw Financials'!I17 -> 0 | J24: ='Raw Financials'!J17 -> 523 | ... M24: ='Raw Financials'!M17 -> 2260 | N24: =0 -> 0 | O24: =0 -> 0 | P24: =0 -> 0 | Q24: =0 -> 0
A25: PBT | B25: ₹m | C25: ='Raw Financials'!C18 -> 3801.3759 | D25: ='Raw Financials'!D18 -> 3506 | E25: ='Raw Financials'!E18 -> 4036 | F25: ='Raw Financials'!F18 -> 5624 | G25: ='Raw Financials'!G18 -> 5954 | H25: ='Raw Financials'!H18 -> 5962 | I25: ='Raw Financials'!I18 -> 8615 | J25: ='Raw Financials'!J18 -> 9512 | ... M25: ='Raw Financials'!M18 -> 19328 | N25: =N23-N24 -> 33202.785 | O25: =O23-O24 -> 46668.433 | P25: =P23-P24 -> 63574 | Q25: =Q23-Q24 -> 83143.977
A26: Tax | B26: ₹m | C26: ='Raw Financials'!C21 -> 831.68032 | D26: ='Raw Financials'!D21 -> 785 | E26: ='Raw Financials'!E21 -> 949 | F26: ='Raw Financials'!F21 -> 1403 | G26: ='Raw Financials'!G21 -> 1278 | H26: ='Raw Financials'!H21 -> 1302 | I26: ='Raw Financials'!I21 -> 1468 | J26: ='Raw Financials'!J21 -> 2061 | ... M26: ='Raw Financials'!M21 -> 2583 | N26: =N25*Assumptions!C25 -> 8300.6962 | O26: =O25*Assumptions!D25 -> 11667.108 | P26: =P25*Assumptions!E25 -> 15893.5 | Q26: =Q25*Assumptions!F25 -> 20785.994
A27: Effective tax rate | B27: % | C27: =IFERROR(C26/C25,"") -> 0.21878403 | D27: =IFERROR(D26/D25,"") -> 0.22390188 | E27: =IFERROR(E26/E25,"") -> 0.2351338 | F27: =IFERROR(F26/F25,"") -> 0.24946657 | G27: =IFERROR(G26/G25,"") -> 0.21464562 | H27: =IFERROR(H26/H25,"") -> 0.21838309 | I27: =IFERROR(I26/I25,"") -> 0.17040046 | J27: =IFERROR(J26/J25,"") -> 0.21667368 | ... M27: =IFERROR(M26/M25,"") -> 0.13364031 | N27: =N26/N25 -> 0.25 | O27: =O26/O25 -> 0.25 | P27: =P26/P25 -> 0.25 | Q27: =Q26/Q25 -> 0.25
A28: Profit incl. NCI | B28: ₹m | C28: ='Raw Financials'!C22 -> 2969.6955 | D28: ='Raw Financials'!D22 -> 2721 | E28: ='Raw Financials'!E22 -> 3087 | F28: ='Raw Financials'!F22 -> 4221 | G28: ='Raw Financials'!G22 -> 4676 | H28: ='Raw Financials'!H22 -> 4660 | I28: ='Raw Financials'!I22 -> 7147 | J28: ='Raw Financials'!J22 -> 7451 | ... M28: ='Raw Financials'!M22 -> 17447 | N28: =N25-N26 -> 24902.089 | O28: =O25-O26 -> 35001.325 | P28: =P25-P26 -> 47680.5 | Q28: =Q25-Q26 -> 62357.983
A29: NCI | B29: ₹m | C29: ='Raw Financials'!C23 -> 170.06476 | D29: ='Raw Financials'!D23 -> 220 | E29: ='Raw Financials'!E23 -> 285 | F29: ='Raw Financials'!F23 -> 188 | G29: ='Raw Financials'!G23 -> 236 | H29: ='Raw Financials'!H23 -> 104 | I29: ='Raw Financials'!I23 -> 530 | J29: ='Raw Financials'!J23 -> 513 | ... M29: ='Raw Financials'!M23 -> 1890 | N29: =N28*Assumptions!C26 -> 498.04177 | O29: =O28*Assumptions!D26 -> 525.01988 | P29: =P28*Assumptions!E26 -> 476.805 | Q29: =Q28*Assumptions!F26 -> 623.57983
A30: Net income attributable | B30: ₹m | C30: ='Raw Financials'!C24 -> 2799.6308 | D30: ='Raw Financials'!D24 -> 2501 | E30: ='Raw Financials'!E24 -> 2802 | F30: ='Raw Financials'!F24 -> 4033 | G30: ='Raw Financials'!G24 -> 4440 | H30: ='Raw Financials'!H24 -> 4556 | I30: ='Raw Financials'!I24 -> 6617 | J30: ='Raw Financials'!J24 -> 6938 | ... M30: ='Raw Financials'!M24 -> 15557 | N30: =N28-N29 -> 24404.047 | O30: =O28-O29 -> 34476.305 | P30: =P28-P29 -> 47203.695 | Q30: =Q28-Q29 -> 61734.403
A31: Net margin | B31: % | C31: =IFERROR(C30/C7,"") -> 0.10437018 | D31: =IFERROR(D30/D7,"") -> 0.089254488 | E31: =IFERROR(E30/E7,"") -> 0.093668516 | F31: =IFERROR(F30/F7,"") -> 0.10970567 | G31: =IFERROR(G30/G7,"") -> 0.10612108 | H31: =IFERROR(H30/H7,"") -> 0.097709531 | I31: =IFERROR(I30/I7,"") -> 0.10287624 | J31: =IFERROR(J30/J7,"") -> 0.086567015 | ... M31: =IFERROR(M30/M7,"") -> 0.094844142 | N31: =N30/N7 -> 0.10678997 | O31: =O30/O7 -> 0.11733181 | P31: =P30/P7 -> 0.12771006 | Q31: =Q30/Q7 -> 0.13505622
A32: Basic weighted shares | B32: m | C32: =IFERROR(C30/C34,"") -> 305.50314 | D32: =IFERROR(D30/D34,"") -> 306.4951 | E32: =IFERROR(E30/E34,"") -> 307.03485 | F32: =IFERROR(F30/F34,"") -> 307.9096 | G32: =IFERROR(G30/G34,"") -> 310.96792 | H32: =IFERROR(H30/H34,"") -> 305.03482 | I32: =IFERROR(I30/I34,"") -> 303.47643 | J32: =IFERROR(J30/J34,"") -> 304.91342 | ... M32: =IFERROR(M30/M34,"") -> 334.99139 | N32: =N33*0.995 -> 422.875 | O32: =O33*0.995 -> 422.875 | P32: =P33*0.995 -> 422.875 | Q32: =Q33*0.995 -> 422.875
A33: Diluted weighted shares | B33: m | C33: =IFERROR(C30/C35,"") -> 307.31403 | D33: =IFERROR(D30/D35,"") -> 307.17268 | E33: =IFERROR(E30/E35,"") -> 308.99868 | F33: =IFERROR(F30/F35,"") -> 311.5248 | G33: =IFERROR(G30/G35,"") -> 312.80823 | H33: =IFERROR(H30/H35,"") -> 310.82003 | I33: =IFERROR(I30/I35,"") -> 310.59895 | J33: =IFERROR(J30/J35,"") -> 311.03739 | ... M33: =IFERROR(M30/M35,"") -> 338.93246 | N33: =Assumptions!C47 -> 425 | O33: =Assumptions!D47 -> 425 | P33: =Assumptions!E47 -> 425 | Q33: =Assumptions!F47 -> 425
A34: Basic EPS | B34: ₹ / share | C34: ='Raw Financials'!C25 -> 9.164 | D34: ='Raw Financials'!D25 -> 8.16 | E34: ='Raw Financials'!E25 -> 9.126 | F34: ='Raw Financials'!F25 -> 13.098 | G34: ='Raw Financials'!G25 -> 14.278 | H34: ='Raw Financials'!H25 -> 14.936 | I34: ='Raw Financials'!I25 -> 21.804 | J34: ='Raw Financials'!J25 -> 22.754 | ... M34: ='Raw Financials'!M25 -> 46.44 | N34: =N30/N32 -> 57.709836 | O34: =O30/O32 -> 81.52836 | P34: =P30/P32 -> 111.62565 | Q34: =Q30/Q32 -> 145.98736
A35: Diluted EPS | B35: ₹ / share | C35: ='Raw Financials'!C26 -> 9.11 | D35: ='Raw Financials'!D26 -> 8.142 | E35: ='Raw Financials'!E26 -> 9.068 | F35: ='Raw Financials'!F26 -> 12.946 | G35: ='Raw Financials'!G26 -> 14.194 | H35: ='Raw Financials'!H26 -> 14.658 | I35: ='Raw Financials'!I26 -> 21.304 | J35: ='Raw Financials'!J26 -> 22.306 | ... M35: ='Raw Financials'!M26 -> 45.9 | N35: =N30/N33 -> 57.421287 | O35: =O30/O33 -> 81.120718 | P35: =P30/P33 -> 111.06752 | Q35: =Q30/Q33 -> 145.25742
A36: Dividend paid | B36: ₹m | C36: =-'Raw Financials'!C133 -> 731.36613 | D36: =-'Raw Financials'!D133 -> 0 | E36: =-'Raw Financials'!E133 -> 613 | F36: =-'Raw Financials'!F133 -> 0 | G36: =-'Raw Financials'!G133 -> 0 | H36: =-'Raw Financials'!H133 -> 686 | I36: =-'Raw Financials'!I133 -> 3152 | J36: =-'Raw Financials'!J133 -> 3534 | ... M36: =-'Raw Financials'!M133 -> 5277 | N36: =N30*Assumptions!C44 -> 8541.4164 | O36: =O30*Assumptions!D44 -> 12756.233 | P36: =P30*Assumptions!E44 -> 18409.441 | Q36: =Q30*Assumptions!F44 -> 24693.761
A37: Dividend per share | B37: ₹ / share | C37: =IFERROR(C36/C32,"") -> 2.3939726 | D37: =IFERROR(D36/D32,"") -> 0 | E37: =IFERROR(E36/E32,"") -> 1.9965161 | F37: =IFERROR(F36/F32,"") -> 0 | G37: =IFERROR(G36/G32,"") -> 0 | H37: =IFERROR(H36/H32,"") -> 2.2489236 | I37: =IFERROR(I36/I32,"") -> 10.386309 | J37: =IFERROR(J36/J32,"") -> 11.590175 | ... M37: =IFERROR(M36/M32,"") -> 15.752644 | N37: =N36/N32 -> 20.198443 | O37: =O36/O32 -> 30.165493 | P37: =P36/P32 -> 43.534002 | Q37: =Q36/Q32 -> 58.394942

Sheet Annual Balance Sheet
A1: Annual Balance Sheet
A2: Historical reported statement; forecast rolls from the Q1 FY27 acquisition anchor with cash linked only from the cash flow statement
A5: Metric | B5: Units | C5: FY16A | D5: FY17A | E5: FY18A | F5: FY19A | G5: FY20A | H5: FY21A | I5: FY22A | J5: FY23A | K5: FY24A | L5: FY25A | M5: FY26A | N5: FY27E | O5: FY28E | P5: FY29E | Q5: FY30E
A7: PPE / fixed assets | B7: ₹m | C7: ='Raw Financials'!C57 -> 5067.2475 | D7: ='Raw Financials'!D57 -> 4802 | E7: ='Raw Financials'!E57 -> 4500 | F7: ='Raw Financials'!F57 -> 4191 | G7: ='Raw Financials'!G57 -> 4013 | H7: ='Raw Financials'!H57 -> 0 | I7: ='Raw Financials'!I57 -> 4452 | J7: ='Raw Financials'!J57 -> 4455 | ... M7: ='Raw Financials'!M57 -> 9425 | N7: ='Acquisition & Debt'!C23+('Annual P&L'!N7-'Quarterly P&L'!AU6)*Assumptions!C38*(1-Assumptions!C39)-('Annual P&L'!N18-'Quarterly P&L'!AU17)*Assumptions!C40 -> 16363.91 | O7: =N7+'Annual P&L'!O7*Assumptions!D38*(1-Assumptions!D39)-'Annual P&L'!O18*Assumptions!D40 -> 17803.707 | P7: =O7+'Annual P&L'!P7*Assumptions!E38*(1-Assumptions!E39)-'Annual P&L'!P18*Assumptions!E40 -> 19522.421 | Q7: =P7+'Annual P&L'!Q7*Assumptions!F38*(1-Assumptions!F39)-'Annual P&L'!Q18*Assumptions!F40 -> 22265.031
A8: ROU assets | B8: ₹m | C8: ='Raw Financials'!C58 -> 0 | D8: ='Raw Financials'!D58 -> 0 | E8: ='Raw Financials'!E58 -> 0 | F8: ='Raw Financials'!F58 -> 0 | G8: ='Raw Financials'!G58 -> 37 | H8: ='Raw Financials'!H58 -> 614 | I8: ='Raw Financials'!I58 -> 1476 | J8: ='Raw Financials'!J58 -> 2365 | ... M8: ='Raw Financials'!M58 -> 3056 | N8: =0 -> 0 | O8: =0 -> 0 | P8: =0 -> 0 | Q8: =0 -> 0
A9: CWIP | B9: ₹m | C9: ='Raw Financials'!C59 -> 167.30215 | D9: ='Raw Financials'!D59 -> 0 | E9: ='Raw Financials'!E59 -> 3 | F9: ='Raw Financials'!F59 -> 14 | G9: ='Raw Financials'!G59 -> 3 | H9: ='Raw Financials'!H59 -> 2 | I9: ='Raw Financials'!I59 -> 86 | J9: ='Raw Financials'!J59 -> 46 | ... M9: ='Raw Financials'!M59 -> 33 | N9: =0 -> 0 | O9: =0 -> 0 | P9: =0 -> 0 | Q9: =0 -> 0
A10: Goodwill | B10: ₹m | C10: ='Raw Financials'!C60 -> 0 | D10: ='Raw Financials'!D60 -> 1848 | E10: ='Raw Financials'!E60 -> 2430 | F10: ='Raw Financials'!F60 -> 2448 | G10: ='Raw Financials'!G60 -> 4091 | H10: ='Raw Financials'!H60 -> 4226 | I10: ='Raw Financials'!I60 -> 10708 | J10: ='Raw Financials'!J60 -> 11665 | ... M10: ='Raw Financials'!M60 -> 41671 | N10: ='Acquisition & Debt'!C24 -> 163729 | O10: =N10 -> 163729 | P10: =O10 -> 163729 | Q10: =P10 -> 163729
A11: Intangibles | B11: ₹m | C11: ='Raw Financials'!C61 -> 3137.3103 | D11: ='Raw Financials'!D61 -> 1826 | E11: ='Raw Financials'!E61 -> 1863 | F11: ='Raw Financials'!F61 -> 1548 | G11: ='Raw Financials'!G61 -> 1897 | H11: ='Raw Financials'!H61 -> 1464 | I11: ='Raw Financials'!I61 -> 4031 | J11: ='Raw Financials'!J61 -> 4634 | ... M11: ='Raw Financials'!M61 -> 13443 | N11: ='Acquisition & Debt'!C25+('Annual P&L'!N7-'Quarterly P&L'!AU6)*Assumptions!C38*Assumptions!C39-('Annual P&L'!N18-'Quarterly P&L'!AU17)*Assumptions!C41 -> 53249.062 | O11: =N11+'Annual P&L'!O7*Assumptions!D38*Assumptions!D39-'Annual P&L'!O18*Assumptions!D41 -> 47695.562 | P11: =O11+'Annual P&L'!P7*Assumptions!E38*Assumptions!E39-'Annual P&L'!P18*Assumptions!E41 -> 41171.838 | Q11: =P11+'Annual P&L'!Q7*Assumptions!F38*Assumptions!F39-'Annual P&L'!Q18*Assumptions!F41 -> 33858.214
A12: Non-current investments / receivables | B12: ₹m | C12: =SUM('Raw Financials'!C62,'Raw Financials'!C63,'Raw Financials'!C64) -> 0.00012 | D12: =SUM('Raw Financials'!D62,'Raw Financials'!D63,'Raw Financials'!D64) -> 205 | E12: =SUM('Raw Financials'!E62,'Raw Financials'!E63,'Raw Financials'!E64) -> 354 | F12: =SUM('Raw Financials'!F62,'Raw Financials'!F63,'Raw Financials'!F64) -> 288 | G12: =SUM('Raw Financials'!G62,'Raw Financials'!G63,'Raw Financials'!G64) -> 660 | H12: =SUM('Raw Financials'!H62,'Raw Financials'!H63,'Raw Financials'!H64) -> 1829 | I12: =SUM('Raw Financials'!I62,'Raw Financials'!I63,'Raw Financials'!I64) -> 2117 | J12: =SUM('Raw Financials'!J62,'Raw Financials'!J63,'Raw Financials'!J64) -> 2251 | ... M12: =SUM('Raw Financials'!M62,'Raw Financials'!M63,'Raw Financials'!M64) -> 9457 | N12: =0 -> 0 | O12: =0 -> 0 | P12: =0 -> 0 | Q12: =0 -> 0
A13: Deferred tax assets | B13: ₹m | C13: ='Raw Financials'!C65 -> 258.73942 | D13: ='Raw Financials'!D65 -> 971 | E13: ='Raw Financials'!E65 -> 1231 | F13: ='Raw Financials'!F65 -> 1032 | G13: ='Raw Financials'!G65 -> 1302 | H13: ='Raw Financials'!H65 -> 0 | I13: ='Raw Financials'!I65 -> 2736 | J13: ='Raw Financials'!J65 -> 3757 | ... M13: ='Raw Financials'!M65 -> 6870 | N13: ='Annual P&L'!N7*Assumptions!C33 -> 9140.951 | O13: ='Annual P&L'!O7*Assumptions!D33 -> 11165.767 | P13: ='Annual P&L'!P7*Assumptions!E33 -> 13306.179 | Q13: ='Annual P&L'!Q7*Assumptions!F33 -> 15541.452
A14: Non-current tax assets | B14: ₹m | C14: ='Raw Financials'!C66 -> 0 | D14: ='Raw Financials'!D66 -> 0 | E14: ='Raw Financials'!E66 -> 0 | F14: ='Raw Financials'!F66 -> 0 | G14: ='Raw Financials'!G66 -> 0 | H14: ='Raw Financials'!H66 -> 0 | I14: ='Raw Financials'!I66 -> 607 | J14: ='Raw Financials'!J66 -> 233 | ... M14: ='Raw Financials'!M66 -> 7 | N14: =0 -> 0 | O14: =0 -> 0 | P14: =0 -> 0 | Q14: =0 -> 0
A15: Other non-current assets | B15: ₹m | C15: ='Raw Financials'!C67 -> 1086.3025 | D15: ='Raw Financials'!D67 -> 120 | E15: ='Raw Financials'!E67 -> 134 | F15: ='Raw Financials'!F67 -> 77 | G15: ='Raw Financials'!G67 -> 140 | H15: ='Raw Financials'!H67 -> 254 | I15: ='Raw Financials'!I67 -> 1045 | J15: ='Raw Financials'!J67 -> 1364 | ... M15: ='Raw Financials'!M67 -> 5801 | N15: ='Annual P&L'!N7*Assumptions!C32 -> 5713.0944 | O15: ='Annual P&L'!O7*Assumptions!D32 -> 7052.0631 | P15: ='Annual P&L'!P7*Assumptions!E32 -> 8501.1701 | Q15: ='Annual P&L'!Q7*Assumptions!F32 -> 10056.233
A16: Total non-current assets | B16: ₹m | C16: ='Raw Financials'!C68 -> 9716.9019 | D16: ='Raw Financials'!D68 -> 9772 | E16: ='Raw Financials'!E68 -> 10519 | F16: ='Raw Financials'!F68 -> 9598 | G16: ='Raw Financials'!G68 -> 12888 | H16: ='Raw Financials'!H68 -> 13839 | I16: ='Raw Financials'!I68 -> 27335 | J16: ='Raw Financials'!J68 -> 30770 | ... M16: ='Raw Financials'!M68 -> 89756 | N16: =SUM(N7:N15) -> 248196.02 | O16: =SUM(O7:O15) -> 247446.1 | P16: =SUM(P7:P15) -> 246230.61 | Q16: =SUM(Q7:Q15) -> 245449.93
A17: Inventories | B17: ₹m | C17: ='Raw Financials'!C69 -> 2.547213 | D17: ='Raw Financials'!D69 -> 3 | E17: ='Raw Financials'!E69 -> 3 | F17: ='Raw Financials'!F69 -> 8 | G17: ='Raw Financials'!G69 -> 0 | H17: ='Raw Financials'!H69 -> 0 | I17: ='Raw Financials'!I69 -> 0 | J17: ='Raw Financials'!J69 -> 0 | ... M17: ='Raw Financials'!M69 -> 0 | N17: =0 -> 0 | O17: =0 -> 0 | P17: =0 -> 0 | Q17: =0 -> 0
A18: Contract / unbilled assets | B18: ₹m | C18: ='Raw Financials'!C70 -> 0 | D18: ='Raw Financials'!D70 -> 0 | E18: ='Raw Financials'!E70 -> 0 | F18: ='Raw Financials'!F70 -> 0 | G18: ='Raw Financials'!G70 -> 0 | H18: ='Raw Financials'!H70 -> 0 | I18: ='Raw Financials'!I70 -> 1184 | J18: ='Raw Financials'!J70 -> 1512 | ... M18: ='Raw Financials'!M70 -> 3339 | N18: ='Annual P&L'!N7/365*Assumptions!C28 -> 24417.609 | O18: ='Annual P&L'!O7/365*Assumptions!D28 -> 29786.111 | P18: ='Annual P&L'!P7/365*Assumptions!E28 -> 35442.639 | Q18: ='Annual P&L'!Q7/365*Assumptions!F28 -> 41326.987
A19: Current investments | B19: ₹m | C19: ='Raw Financials'!C71 -> 740 | D19: ='Raw Financials'!D71 -> 3158 | E19: ='Raw Financials'!E71 -> 3652 | F19: ='Raw Financials'!F71 -> 3651 | G19: ='Raw Financials'!G71 -> 137 | H19: ='Raw Financials'!H71 -> 124 | I19: ='Raw Financials'!I71 -> 5 | J19: ='Raw Financials'!J71 -> 0 | ... M19: ='Raw Financials'!M71 -> 5 | N19: =0 -> 0 | O19: =0 -> 0 | P19: =0 -> 0 | Q19: =0 -> 0
A20: Trade receivables | B20: ₹m | C20: ='Raw Financials'!C72 -> 5900.5955 | D20: ='Raw Financials'!D72 -> 4903 | E20: ='Raw Financials'!E72 -> 5858 | F20: ='Raw Financials'!F72 -> 5877 | G20: ='Raw Financials'!G72 -> 8565 | H20: ='Raw Financials'!H72 -> 8895 | I20: ='Raw Financials'!I72 -> 13894 | J20: ='Raw Financials'!J72 -> 16131 | ... M20: ='Raw Financials'!M72 -> 39700 | N20: ='Annual P&L'!N7/365*Assumptions!C27 -> 40696.015 | O20: ='Annual P&L'!O7/365*Assumptions!D27 -> 51521.922 | P20: ='Annual P&L'!P7/365*Assumptions!E27 -> 63796.75 | Q20: ='Annual P&L'!Q7/365*Assumptions!F27 -> 77644.642
A21: Cash & equivalents | B21: ₹m | C21: ='Raw Financials'!C73 -> 2878.6273 | D21: ='Raw Financials'!D73 -> 3502 | E21: ='Raw Financials'!E73 -> 4102 | F21: ='Raw Financials'!F73 -> 5079 | G21: ='Raw Financials'!G73 -> 8195 | H21: ='Raw Financials'!H73 -> 7999 | I21: ='Raw Financials'!I73 -> 4468 | J21: ='Raw Financials'!J73 -> 5699 | ... M21: ='Raw Financials'!M73 -> 10936 | N21: ='Annual Cash Flow'!N41 -> 13436.219 | O21: ='Annual Cash Flow'!O41 -> 8327.8618 | P21: ='Annual Cash Flow'!P41 -> 3716.7487 | Q21: ='Annual Cash Flow'!Q41 -> 29969.931
A22: Cash held for sale | B22: ₹m | C22: 0 | D22: 0 | E22: 0 | F22: 115 | G22: 0 | H22: 0 | I22: 0 | J22: 0 | K22: 0 | L22: 0 | M22: 0 | N22: =0 -> 0 | O22: =0 -> 0 | P22: =0 -> 0 | Q22: =0 -> 0
A23: Other bank balances | B23: ₹m | C23: ='Raw Financials'!C74 -> 483.32441 | D23: ='Raw Financials'!D74 -> 573 | E23: ='Raw Financials'!E74 -> 81 | F23: ='Raw Financials'!F74 -> 497 | G23: ='Raw Financials'!G74 -> 839 | H23: ='Raw Financials'!H74 -> 123 | I23: ='Raw Financials'!I74 -> 67 | J23: ='Raw Financials'!J74 -> 88 | ... M23: ='Raw Financials'!M74 -> 56 | N23: ='Annual P&L'!N7*Assumptions!C31 -> 0 | O23: ='Annual P&L'!O7*Assumptions!D31 -> 0 | P23: ='Annual P&L'!P7*Assumptions!E31 -> 0 | Q23: ='Annual P&L'!Q7*Assumptions!F31 -> 0
A24: Other current financial assets | B24: ₹m | C24: ='Raw Financials'!C75 -> 0 | D24: ='Raw Financials'!D75 -> 1155 | E24: ='Raw Financials'!E75 -> 828 | F24: ='Raw Financials'!F75 -> 1549 | G24: ='Raw Financials'!G75 -> 2427 | H24: ='Raw Financials'!H75 -> 2717 | I24: ='Raw Financials'!I75 -> 662 | J24: ='Raw Financials'!J75 -> 187 | ... M24: ='Raw Financials'!M75 -> 118 | N24: =0 -> 0 | O24: =0 -> 0 | P24: =0 -> 0 | Q24: =0 -> 0
A25: Current tax assets | B25: ₹m | C25: ='Raw Financials'!C76 -> 0 | D25: ='Raw Financials'!D76 -> 624 | E25: ='Raw Financials'!E76 -> 650 | F25: ='Raw Financials'!F76 -> 203 | G25: ='Raw Financials'!G76 -> 411 | H25: ='Raw Financials'!H76 -> 358 | I25: ='Raw Financials'!I76 -> 0 | J25: ='Raw Financials'!J76 -> 0 | ... M25: ='Raw Financials'!M76 -> 0 | N25: =0 -> 0 | O25: =0 -> 0 | P25: =0 -> 0 | Q25: =0 -> 0
A26: Contract costs and other current assets | B26: ₹m | C26: ='Raw Financials'!C77 -> 2769.2553 | D26: ='Raw Financials'!D77 -> 958 | E26: ='Raw Financials'!E77 -> 1005 | F26: ='Raw Financials'!F77 -> 1136 | G26: ='Raw Financials'!G77 -> 936 | H26: ='Raw Financials'!H77 -> 1079 | I26: ='Raw Financials'!I77 -> 1934 | J26: ='Raw Financials'!J77 -> 2447 | ... M26: ='Raw Financials'!M77 -> 4909 | N26: ='Annual P&L'!N7*(Assumptions!C29+Assumptions!C30) -> 12568.808 | O26: ='Annual P&L'!O7*(Assumptions!D29+Assumptions!D30) -> 15279.47 | P26: ='Annual P&L'!P7*(Assumptions!E29+Assumptions!E30) -> 18111.189 | Q26: ='Annual P&L'!Q7*(Assumptions!F29+Assumptions!F30) -> 21026.67
A27: Held for sale / reported classification residual | B27: ₹m | C27: ='Raw Financials'!C80-'Raw Financials'!C68-'Raw Financials'!C78 -> 0.00012 | D27: ='Raw Financials'!D80-'Raw Financials'!D68-'Raw Financials'!D78 -> 0 | E27: ='Raw Financials'!E80-'Raw Financials'!E68-'Raw Financials'!E78 -> 0 | F27: ='Raw Financials'!F80-'Raw Financials'!F68-'Raw Financials'!F78 -> 1144 | G27: ='Raw Financials'!G80-'Raw Financials'!G68-'Raw Financials'!G78 -> 0 | H27: ='Raw Financials'!H80-'Raw Financials'!H68-'Raw Financials'!H78 -> 0 | I27: ='Raw Financials'!I80-'Raw Financials'!I68-'Raw Financials'!I78 -> 0 | J27: ='Raw Financials'!J80-'Raw Financials'!J68-'Raw Financials'!J78 -> 0 | ... M27: ='Raw Financials'!M80-'Raw Financials'!M68-'Raw Financials'!M78 -> 0 | N27: =0 -> 0 | O27: =0 -> 0 | P27: =0 -> 0 | Q27: =0 -> 0
A28: Total current assets | B28: ₹m | C28: ='Raw Financials'!C78 -> 12774.35 | D28: ='Raw Financials'!D78 -> 14876 | E28: ='Raw Financials'!E78 -> 16179 | F28: ='Raw Financials'!F78 -> 17992 | G28: ='Raw Financials'!G78 -> 21510 | H28: ='Raw Financials'!H78 -> 21295 | I28: ='Raw Financials'!I78 -> 22209 | J28: ='Raw Financials'!J78 -> 26064 | ... M28: ='Raw Financials'!M78 -> 59058 | N28: =SUM(N17:N27) -> 91118.65 | O28: =SUM(O17:O27) -> 104915.36 | P28: =SUM(P17:P27) -> 121067.33 | Q28: =SUM(Q17:Q27) -> 169968.23
A29: Total assets | B29: ₹m | C29: ='Raw Financials'!C80 -> 22491.252 | D29: ='Raw Financials'!D80 -> 24648 | E29: ='Raw Financials'!E80 -> 26698 | F29: ='Raw Financials'!F80 -> 28734 | G29: ='Raw Financials'!G80 -> 34398 | H29: ='Raw Financials'!H80 -> 35134 | I29: ='Raw Financials'!I80 -> 49544 | J29: ='Raw Financials'!J80 -> 56834 | ... M29: ='Raw Financials'!M80 -> 148814 | N29: =N16+N28 -> 339314.67 | O29: =O16+O28 -> 352361.46 | P29: =P16+P28 -> 367297.94 | Q29: =Q16+Q28 -> 415418.16
A30: Share capital | B30: ₹m | C30: ='Raw Financials'!C81 -> 611.86524 | D30: ='Raw Financials'!D81 -> 614 | E30: ='Raw Financials'!E81 -> 615 | F30: ='Raw Financials'!F81 -> 618 | G30: ='Raw Financials'!G81 -> 625 | H30: ='Raw Financials'!H81 -> 606 | I30: ='Raw Financials'!I81 -> 609 | J30: ='Raw Financials'!J81 -> 611 | ... M30: ='Raw Financials'!M81 -> 672 | N30: ='Acquisition & Debt'!C34 -> 885 | O30: =N30 -> 885 | P30: =O30 -> 885 | Q30: =P30 -> 885
A31: Other equity / reserves | B31: ₹m | C31: ='Raw Financials'!C82 -> 15295.607 | D31: ='Raw Financials'!D82 -> 16251 | E31: ='Raw Financials'!E82 -> 17125 | F31: ='Raw Financials'!F82 -> 105 | G31: ='Raw Financials'!G82 -> 23340 | H31: ='Raw Financials'!H82 -> 24041 | I31: ='Raw Financials'!I82 -> 26722 | J31: ='Raw Financials'!J82 -> 30214 | ... M31: ='Raw Financials'!M82 -> 94704 | N31: ='Acquisition & Debt'!C35+('Annual P&L'!N30-'Quarterly P&L'!AU28)+('Annual P&L'!N15-'Quarterly P&L'!AU14)-'Annual P&L'!N36+Assumptions!C63 -> 227896.77 | O31: =N31+'Annual P&L'!O30+'Annual P&L'!O15-'Annual P&L'!O36+Assumptions!D63 -> 251379.86 | P31: =O31+'Annual P&L'!P30+'Annual P&L'!P15-'Annual P&L'!P36+Assumptions!E63 -> 282391.81 | Q31: =P31+'Annual P&L'!Q30+'Annual P&L'!Q15-'Annual P&L'!Q36+Assumptions!F63 -> 322175.06
A32: Equity attributable | B32: ₹m | C32: ='Raw Financials'!C83 -> 15907.472 | D32: ='Raw Financials'!D83 -> 16865 | E32: ='Raw Financials'!E83 -> 17740 | F32: ='Raw Financials'!F83 -> 723 | G32: ='Raw Financials'!G83 -> 23965 | H32: ='Raw Financials'!H83 -> 24647 | I32: ='Raw Financials'!I83 -> 27331 | J32: ='Raw Financials'!J83 -> 30825 | ... M32: ='Raw Financials'!M83 -> 95376 | N32: =N30+N31 -> 228781.77 | O32: =O30+O31 -> 252264.86 | P32: =P30+P31 -> 283276.81 | Q32: =Q30+Q31 -> 323060.06
A33: NCI | B33: ₹m | C33: ='Raw Financials'!C84 -> 645.16793 | D33: ='Raw Financials'!D84 -> 237 | E33: ='Raw Financials'!E84 -> 222 | F33: ='Raw Financials'!F84 -> 75 | G33: ='Raw Financials'!G84 -> 14 | H33: ='Raw Financials'!H84 -> 14 | I33: ='Raw Financials'!I84 -> 12 | J33: ='Raw Financials'!J84 -> 874 | ... M33: ='Raw Financials'!M84 -> 1430 | N33: ='Acquisition & Debt'!C36+('Annual P&L'!N29-'Quarterly P&L'!AU27)-'Annual P&L'!N29*Assumptions!C45 -> 1792.6292 | O33: =N33+'Annual P&L'!O29-'Annual P&L'!O29*Assumptions!D45 -> 2160.1432 | P33: =O33+'Annual P&L'!P29-'Annual P&L'!P29*Assumptions!E45 -> 2493.9067 | Q33: =P33+'Annual P&L'!Q29-'Annual P&L'!Q29*Assumptions!F45 -> 2930.4125
A34: Total equity | B34: ₹m | C34: ='Raw Financials'!C85 -> 16552.64 | D34: ='Raw Financials'!D85 -> 17102 | E34: ='Raw Financials'!E85 -> 17962 | F34: ='Raw Financials'!F85 -> 20798 | G34: ='Raw Financials'!G85 -> 23965 | H34: ='Raw Financials'!H85 -> 24661 | I34: ='Raw Financials'!I85 -> 28314 | J34: ='Raw Financials'!J85 -> 31699 | ... M34: ='Raw Financials'!M85 -> 96806 | N34: =N32+N33 -> 230574.4 | O34: =O32+O33 -> 254425 | P34: =P32+P33 -> 285770.72 | Q34: =Q32+Q33 -> 325990.48
A35: Long-term borrowings | B35: ₹m | C35: ='Raw Financials'!C86 -> 63.791706 | D35: ='Raw Financials'!D86 -> 74 | E35: ='Raw Financials'!E86 -> 179 | F35: ='Raw Financials'!F86 -> 100 | G35: ='Raw Financials'!G86 -> 48 | H35: ='Raw Financials'!H86 -> 5 | I35: ='Raw Financials'!I86 -> 3365 | J35: ='Raw Financials'!J86 -> 3382 | ... M35: ='Raw Financials'!M86 -> 1167 | N35: =0 -> 0 | O35: =0 -> 0 | P35: =0 -> 0 | Q35: =0 -> 0
A36: Non-current lease liabilities | B36: ₹m | C36: ='Raw Financials'!C87 -> 0 | D36: ='Raw Financials'!D87 -> 0 | E36: ='Raw Financials'!E87 -> 0 | F36: ='Raw Financials'!F87 -> 0 | G36: ='Raw Financials'!G87 -> 0 | H36: ='Raw Financials'!H87 -> 0 | I36: ='Raw Financials'!I87 -> 0 | J36: ='Raw Financials'!J87 -> 0 | ... M36: ='Raw Financials'!M87 -> 2187 | N36: =0 -> 0 | O36: =0 -> 0 | P36: =0 -> 0 | Q36: =0 -> 0
A37: Other non-current financial / trade liabilities | B37: ₹m | C37: =SUM('Raw Financials'!C88,'Raw Financials'!C89) -> 0 | D37: =SUM('Raw Financials'!D88,'Raw Financials'!D89) -> 1556 | E37: =SUM('Raw Financials'!E88,'Raw Financials'!E89) -> 1483 | F37: =SUM('Raw Financials'!F88,'Raw Financials'!F89) -> 538 | G37: =SUM('Raw Financials'!G88,'Raw Financials'!G89) -> 1262 | H37: =SUM('Raw Financials'!H88,'Raw Financials'!H89) -> 871 | I37: =SUM('Raw Financials'!I88,'Raw Financials'!I89) -> 377 | J37: =SUM('Raw Financials'!J88,'Raw Financials'!J89) -> 656 | ... M37: =SUM('Raw Financials'!M88,'Raw Financials'!M89) -> 6574 | N37: =0 -> 0 | O37: =0 -> 0 | P37: =0 -> 0 | Q37: =0 -> 0
A38: Non-current provisions | B38: ₹m | C38: ='Raw Financials'!C90 -> 0 | D38: ='Raw Financials'!D90 -> 858 | E38: ='Raw Financials'!E90 -> 741 | F38: ='Raw Financials'!F90 -> 725 | G38: ='Raw Financials'!G90 -> 593 | H38: ='Raw Financials'!H90 -> 696 | I38: ='Raw Financials'!I90 -> 14 | J38: ='Raw Financials'!J90 -> 1276 | ... M38: ='Raw Financials'!M90 -> 3189 | N38: =0 -> 0 | O38: =0 -> 0 | P38: =0 -> 0 | Q38: =0 -> 0
A39: Deferred tax liabilities | B39: ₹m | C39: ='Raw Financials'!C91 -> 0 | D39: ='Raw Financials'!D91 -> 387 | E39: ='Raw Financials'!E91 -> 455 | F39: ='Raw Financials'!F91 -> 395 | G39: ='Raw Financials'!G91 -> 397 | H39: ='Raw Financials'!H91 -> 0 | I39: ='Raw Financials'!I91 -> 766 | J39: ='Raw Financials'!J91 -> 583 | ... M39: ='Raw Financials'!M91 -> 353 | N39: ='Annual P&L'!N7*Assumptions!C37 -> 9597.9985 | O39: ='Annual P&L'!O7*Assumptions!D37 -> 11165.767 | P39: ='Annual P&L'!P7*Assumptions!E37 -> 12566.947 | Q39: ='Annual P&L'!Q7*Assumptions!F37 -> 13713.046
A40: Other non-current liabilities / acquisition consideration | B40: ₹m | C40: ='Raw Financials'!C92 -> 0 | D40: ='Raw Financials'!D92 -> 82 | E40: ='Raw Financials'!E92 -> 17 | F40: ='Raw Financials'!F92 -> 12 | G40: ='Raw Financials'!G92 -> 17 | H40: ='Raw Financials'!H92 -> 17 | I40: ='Raw Financials'!I92 -> 51 | J40: ='Raw Financials'!J92 -> 59 | ... M40: ='Raw Financials'!M92 -> 1844 | N40: ='Acquisition & Debt'!C40*(1-Assumptions!C46) -> 1888.5 | O40: =N40*(1-Assumptions!D46) -> 1321.95 | P40: =O40*(1-Assumptions!E46) -> 859.2675 | Q40: =P40*(1-Assumptions!F46) -> 0
A41: Total non-current liabilities | B41: ₹m | C41: ='Raw Financials'!C93 -> 911.72297 | D41: ='Raw Financials'!D93 -> 2957 | E41: ='Raw Financials'!E93 -> 2889 | F41: ='Raw Financials'!F93 -> 1770 | G41: ='Raw Financials'!G93 -> 2491 | H41: ='Raw Financials'!H93 -> 2048 | I41: ='Raw Financials'!I93 -> 9438 | J41: ='Raw Financials'!J93 -> 7742 | ... M41: ='Raw Financials'!M93 -> 15314 | N41: =SUM(N35:N40) -> 11486.499 | O41: =SUM(O35:O40) -> 12487.717 | P41: =SUM(P35:P40) -> 13426.215 | Q41: =SUM(Q35:Q40) -> 13713.046
A42: Short-term borrowings | B42: ₹m | C42: ='Raw Financials'!C94 -> 0 | D42: ='Raw Financials'!D94 -> 0 | E42: ='Raw Financials'!E94 -> 0 | F42: ='Raw Financials'!F94 -> 0 | G42: ='Raw Financials'!G94 -> 0 | H42: ='Raw Financials'!H94 -> 0 | I42: ='Raw Financials'!I94 -> 180 | J42: ='Raw Financials'!J94 -> 13 | ... M42: ='Raw Financials'!M94 -> 2830 | N42: ='Acquisition & Debt'!C21 -> 46060 | O42: ='Acquisition & Debt'!D21 -> 25650 | P42: ='Acquisition & Debt'!E21 -> 0 | Q42: ='Acquisition & Debt'!F21 -> 0
A43: Current lease liabilities | B43: ₹m | C43: ='Raw Financials'!C95 -> 0 | D43: ='Raw Financials'!D95 -> 0 | E43: ='Raw Financials'!E95 -> 0 | F43: ='Raw Financials'!F95 -> 0 | G43: ='Raw Financials'!G95 -> 0 | H43: ='Raw Financials'!H95 -> 0 | I43: ='Raw Financials'!I95 -> 0 | J43: ='Raw Financials'!J95 -> 0 | ... M43: ='Raw Financials'!M95 -> 1094 | N43: ='Acquisition & Debt'!C41*(1-Assumptions!C42)+'Annual P&L'!N7*Assumptions!C43 -> 4117.8689 | O43: =N43*(1-Assumptions!D42)+'Annual P&L'!O7*Assumptions!D43 -> 4557.5815 | P43: =O43*(1-Assumptions!E42)+'Annual P&L'!P7*Assumptions!E43 -> 5266.2666 | Q43: =P43*(1-Assumptions!F42)+'Annual P&L'!Q7*Assumptions!F43 -> 6235.2075
A44: Trade payables and other financial liabilities | B44: ₹m | C44: =SUM('Raw Financials'!C96,'Raw Financials'!C97) -> 1654.202 | D44: =SUM('Raw Financials'!D96,'Raw Financials'!D97) -> 2271 | E44: =SUM('Raw Financials'!E96,'Raw Financials'!E97) -> 3186 | F44: =SUM('Raw Financials'!F96,'Raw Financials'!F97) -> 3234 | G44: =SUM('Raw Financials'!G96,'Raw Financials'!G97) -> 5040 | H44: =SUM('Raw Financials'!H96,'Raw Financials'!H97) -> 4593 | I44: =SUM('Raw Financials'!I96,'Raw Financials'!I97) -> 8558 | J44: =SUM('Raw Financials'!J96,'Raw Financials'!J97) -> 13858 | ... M44: =SUM('Raw Financials'!M96,'Raw Financials'!M97) -> 24942 | N44: ='Annual P&L'!N7*Assumptions!C36 -> 35421.185 | O44: ='Annual P&L'!O7*Assumptions!D36 -> 41137.034 | P44: ='Annual P&L'!P7*Assumptions!E36 -> 46202.012 | Q44: ='Annual P&L'!Q7*Assumptions!F36 -> 50281.167
A45: Current provisions | B45: ₹m | C45: ='Raw Financials'!C98 -> 1340.9939 | D45: ='Raw Financials'!D98 -> 642 | E45: ='Raw Financials'!E98 -> 709 | F45: ='Raw Financials'!F98 -> 334 | G45: ='Raw Financials'!G98 -> 329 | H45: ='Raw Financials'!H98 -> 225 | I45: ='Raw Financials'!I98 -> 14 | J45: ='Raw Financials'!J98 -> 360 | ... M45: ='Raw Financials'!M98 -> 987 | N45: ='Annual P&L'!N7*Assumptions!C35 -> 6398.6657 | O45: ='Annual P&L'!O7*Assumptions!D35 -> 7639.735 | P45: ='Annual P&L'!P7*Assumptions!E35 -> 8870.7862 | Q45: ='Annual P&L'!Q7*Assumptions!F35 -> 10056.233
A46: Current tax liabilities | B46: ₹m | C46: ='Raw Financials'!C99 -> 0 | D46: ='Raw Financials'!D99 -> 0 | E46: ='Raw Financials'!E99 -> 0 | F46: ='Raw Financials'!F99 -> 0 | G46: ='Raw Financials'!G99 -> 0 | H46: ='Raw Financials'!H99 -> 0 | I46: ='Raw Financials'!I99 -> 0 | J46: ='Raw Financials'!J99 -> 0 | ... M46: ='Raw Financials'!M99 -> 14 | N46: =0 -> 0 | O46: =0 -> 0 | P46: =0 -> 0 | Q46: =0 -> 0
A47: Deferred revenue / other current liabilities | B47: ₹m | C47: ='Raw Financials'!C100 -> 2031.693 | D47: ='Raw Financials'!D100 -> 1676 | E47: ='Raw Financials'!E100 -> 1952 | F47: ='Raw Financials'!F100 -> 2265 | G47: ='Raw Financials'!G100 -> 2573 | H47: ='Raw Financials'!H100 -> 3607 | I47: ='Raw Financials'!I100 -> 2324 | J47: ='Raw Financials'!J100 -> 2721 | ... M47: ='Raw Financials'!M100 -> 6077 | N47: ='Annual P&L'!N7*Assumptions!C34 -> 5256.0468 | O47: ='Annual P&L'!O7*Assumptions!D34 -> 6464.3911 | P47: ='Annual P&L'!P7*Assumptions!E34 -> 7761.9379 | Q47: ='Annual P&L'!Q7*Assumptions!F34 -> 9142.0304
A48: Held for sale / reported classification residual | B48: ₹m | C48: ='Raw Financials'!C80-'Raw Financials'!C85-'Raw Financials'!C103 -> 0 | D48: ='Raw Financials'!D80-'Raw Financials'!D85-'Raw Financials'!D103 -> 0 | E48: ='Raw Financials'!E80-'Raw Financials'!E85-'Raw Financials'!E103 -> 0 | F48: ='Raw Financials'!F80-'Raw Financials'!F85-'Raw Financials'!F103 -> 333 | G48: ='Raw Financials'!G80-'Raw Financials'!G85-'Raw Financials'!G103 -> 0 | H48: ='Raw Financials'!H80-'Raw Financials'!H85-'Raw Financials'!H103 -> 0 | I48: ='Raw Financials'!I80-'Raw Financials'!I85-'Raw Financials'!I103 -> 0 | J48: ='Raw Financials'!J80-'Raw Financials'!J85-'Raw Financials'!J103 -> 0 | ... M48: ='Raw Financials'!M80-'Raw Financials'!M85-'Raw Financials'!M103 -> 0 | N48: =0 -> 0 | O48: =0 -> 0 | P48: =0 -> 0 | Q48: =0 -> 0
A49: Total current liabilities | B49: ₹m | C49: ='Raw Financials'!C101 -> 5026.8889 | D49: ='Raw Financials'!D101 -> 4589 | E49: ='Raw Financials'!E101 -> 5847 | F49: ='Raw Financials'!F101 -> 5833 | G49: ='Raw Financials'!G101 -> 7942 | H49: ='Raw Financials'!H101 -> 8425 | I49: ='Raw Financials'!I101 -> 11792 | J49: ='Raw Financials'!J101 -> 17393 | ... M49: ='Raw Financials'!M101 -> 36694 | N49: =SUM(N42:N48) -> 97253.766 | O49: =SUM(O42:O48) -> 85448.742 | P49: =SUM(P42:P48) -> 68101.002 | Q49: =SUM(Q42:Q48) -> 75714.639
A50: Total liabilities | B50: ₹m | C50: ='Raw Financials'!C103 -> 5938.6119 | D50: ='Raw Financials'!D103 -> 7546 | E50: ='Raw Financials'!E103 -> 8736 | F50: ='Raw Financials'!F103 -> 7603 | G50: ='Raw Financials'!G103 -> 10433 | H50: ='Raw Financials'!H103 -> 10473 | I50: ='Raw Financials'!I103 -> 21230 | J50: ='Raw Financials'!J103 -> 25135 | ... M50: ='Raw Financials'!M103 -> 52008 | N50: =N41+N49 -> 108740.26 | O50: =O41+O49 -> 97936.459 | P50: =P41+P49 -> 81527.217 | Q50: =Q41+Q49 -> 89427.685
A51: Total equity & liabilities | B51: ₹m | C51: =C34+C50+C48 -> 22491.252 | D51: =D34+D50+D48 -> 24648 | E51: =E34+E50+E48 -> 26698 | F51: =F34+F50+F48 -> 28734 | G51: =G34+G50+G48 -> 34398 | H51: =H34+H50+H48 -> 35134 | I51: =I34+I50+I48 -> 49544 | J51: =J34+J50+J48 -> 56834 | ... M51: =M34+M50+M48 -> 148814 | N51: =N34+N50 -> 339314.67 | O51: =O34+O50 -> 352361.46 | P51: =P34+P50 -> 367297.94 | Q51: =Q34+Q50 -> 415418.16
A52: Balance check | B52: ₹m | C52: =C29-C51 -> 0 | D52: =D29-D51 -> 0 | E52: =E29-E51 -> 0 | F52: =F29-F51 -> 0 | G52: =G29-G51 -> 0 | H52: =H29-H51 -> 0 | I52: =I29-I51 -> 0 | J52: =J29-J51 -> 0 | ... Q52: =Q29-Q51 -> 0
A53: Closing cash check | B53: ₹m | C53: =C21+C22-'Annual Cash Flow'!C41 -> 0 | D53: =D21+D22-'Annual Cash Flow'!D41 -> 0 | E53: =E21+E22-'Annual Cash Flow'!E41 -> 0 | F53: =F21+F22-'Annual Cash Flow'!F41 -> 0 | G53: =G21+G22-'Annual Cash Flow'!G41 -> 0 | H53: =H21+H22-'Annual Cash Flow'!H41 -> 0 | I53: =I21+I22-'Annual Cash Flow'!I41 -> 0 | J53: =J21+J22-'Annual Cash Flow'!J41 -> 0 | ... Q53: =Q21+Q22-'Annual Cash Flow'!Q41 -> 0

Sheet Annual Cash Flow
A1: Annual Cash Flow Statement
A2: Historical totals reconciled line by line; forecast cash rolls mechanically and anchors the balance sheet
A5: Metric | B5: Units | C5: FY16A | D5: FY17A | E5: FY18A | F5: FY19A | G5: FY20A | H5: FY21A | I5: FY22A | J5: FY23A | K5: FY24A | L5: FY25A | M5: FY26A | N5: FY27E | O5: FY28E | P5: FY29E | Q5: FY30E
A7: Net income incl. NCI | B7: ₹m | C7: ='Annual P&L'!C28 -> 2969.6955 | D7: ='Annual P&L'!D28 -> 2721 | E7: ='Annual P&L'!E28 -> 3087 | F7: ='Annual P&L'!F28 -> 4221 | G7: ='Annual P&L'!G28 -> 4676 | H7: ='Annual P&L'!H28 -> 4660 | I7: ='Annual P&L'!I28 -> 7147 | J7: ='Annual P&L'!J28 -> 7451 | ... M7: ='Annual P&L'!M28 -> 17447 | N7: ='Annual P&L'!N28-'Quarterly P&L'!AU26 -> 19585.089 | O7: ='Annual P&L'!O28 -> 35001.325 | P7: ='Annual P&L'!P28 -> 47680.5 | Q7: ='Annual P&L'!Q28 -> 62357.983
A8: D&A | B8: ₹m | C8: ='Raw Financials'!C110 -> 1101.2935 | D8: ='Raw Financials'!D110 -> 0 | E8: ='Raw Financials'!E110 -> 1274 | F8: ='Raw Financials'!F110 -> 0 | G8: ='Raw Financials'!G110 -> 0 | H8: ='Raw Financials'!H110 -> 0 | I8: ='Raw Financials'!I110 -> 2272 | J8: ='Raw Financials'!J110 -> 2585 | ... M8: ='Raw Financials'!M110 -> 6819 | N8: ='Annual P&L'!N18-'Quarterly P&L'!AU17 -> 8786.6649 | O8: ='Annual P&L'!O18 -> 13516.454 | P8: ='Annual P&L'!P18 -> 15893.492 | Q8: ='Annual P&L'!Q18 -> 18284.061
A9: Share-based compensation | B9: ₹m | C9: ='Raw Financials'!C111 -> 17.546337 | D9: ='Raw Financials'!D111 -> 0 | E9: ='Raw Financials'!E111 -> 97 | F9: ='Raw Financials'!F111 -> 0 | G9: ='Raw Financials'!G111 -> 0 | H9: ='Raw Financials'!H111 -> 0 | I9: ='Raw Financials'!I111 -> 355 | J9: ='Raw Financials'!J111 -> 544 | ... M9: ='Raw Financials'!M111 -> 1909 | N9: ='Annual P&L'!N15-'Quarterly P&L'!AU14 -> 914.14264 | O9: ='Annual P&L'!O15 -> 1763.0158 | P9: ='Annual P&L'!P15 -> 2217.6966 | Q9: ='Annual P&L'!Q15 -> 2742.6091
A10: Finance cost add-back | B10: ₹m | C10: ='Raw Financials'!C112 -> 23.123343 | D10: ='Raw Financials'!D112 -> 0 | E10: ='Raw Financials'!E112 -> 13 | F10: ='Raw Financials'!F112 -> 0 | G10: ='Raw Financials'!G112 -> 0 | H10: ='Raw Financials'!H112 -> 0 | I10: ='Raw Financials'!I112 -> 609 | J10: ='Raw Financials'!J112 -> 768 | ... M10: ='Raw Financials'!M112 -> 1581 | N10: ='Annual P&L'!N22-'Quarterly P&L'!AU20 -> 2816.4 | O10: ='Annual P&L'!O22 -> 1814.5 | P10: ='Annual P&L'!P22 -> 739.2 | Q10: ='Annual P&L'!Q22 -> 48.5
A11: Deferred tax / other non-cash | B11: ₹m | C11: =0 -> 0 | D11: =0 -> 0 | E11: =0 -> 0 | F11: =0 -> 0 | G11: =0 -> 0 | H11: =0 -> 0 | I11: =0 -> 0 | J11: =0 -> 0 | ... M11: =0 -> 0 | N11: =-('Annual Balance Sheet'!N13-'Acquisition & Debt'!C31)+('Annual Balance Sheet'!N39-'Acquisition & Debt'!C39) -> -775.95245 | O11: =-('Annual Balance Sheet'!O13-'Annual Balance Sheet'!N13)+('Annual Balance Sheet'!O39-'Annual Balance Sheet'!N39) -> -457.04755 | P11: =-('Annual Balance Sheet'!P13-'Annual Balance Sheet'!O13)+('Annual Balance Sheet'!P39-'Annual Balance Sheet'!O39) -> -739.23218 | Q11: =-('Annual Balance Sheet'!Q13-'Annual Balance Sheet'!P13)+('Annual Balance Sheet'!Q39-'Annual Balance Sheet'!P39) -> -1089.1739
A12: Change in trade receivables | B12: ₹m | C12: ='Raw Financials'!C114 -> 267.87401 | D12: ='Raw Financials'!D114 -> 0 | E12: ='Raw Financials'!E114 -> -832 | F12: ='Raw Financials'!F114 -> 0 | G12: ='Raw Financials'!G114 -> 0 | H12: ='Raw Financials'!H114 -> 0 | I12: ='Raw Financials'!I114 -> -3152 | J12: ='Raw Financials'!J114 -> -2126 | ... M12: ='Raw Financials'!M114 -> -15516 | N12: =-('Annual Balance Sheet'!N20-'Acquisition & Debt'!C28) -> 282.98545 | O12: =-('Annual Balance Sheet'!O20-'Annual Balance Sheet'!N20) -> -10825.907 | P12: =-('Annual Balance Sheet'!P20-'Annual Balance Sheet'!O20) -> -12274.828 | Q12: =-('Annual Balance Sheet'!Q20-'Annual Balance Sheet'!P20) -> -13847.892
A13: Change in contract / unbilled assets | B13: ₹m | C13: =0 -> 0 | D13: =0 -> 0 | E13: =0 -> 0 | F13: =0 -> 0 | G13: =0 -> 0 | H13: =0 -> 0 | I13: =0 -> 0 | J13: =0 -> 0 | ... M13: =0 -> 0 | N13: =-('Annual Balance Sheet'!N18-'Acquisition & Debt'!C29) -> -3448.6087 | O13: =-('Annual Balance Sheet'!O18-'Annual Balance Sheet'!N18) -> -5368.5023 | P13: =-('Annual Balance Sheet'!P18-'Annual Balance Sheet'!O18) -> -5656.5279 | Q13: =-('Annual Balance Sheet'!Q18-'Annual Balance Sheet'!P18) -> -5884.348
A14: Change in contract costs / other assets | B14: ₹m | C14: ='Raw Financials'!C115 -> 0 | D14: ='Raw Financials'!D115 -> 0 | E14: ='Raw Financials'!E115 -> -84 | F14: ='Raw Financials'!F115 -> 0 | G14: ='Raw Financials'!G115 -> 0 | H14: ='Raw Financials'!H115 -> 0 | I14: ='Raw Financials'!I115 -> -1276 | J14: ='Raw Financials'!J115 -> -769 | ... M14: ='Raw Financials'!M115 -> 685 | N14: =-('Annual Balance Sheet'!N15+'Annual Balance Sheet'!N26-'Acquisition & Debt'!C32-'Acquisition & Debt'!C30) -> -7196.9019 | O14: =-('Annual Balance Sheet'!O15+'Annual Balance Sheet'!O26-'Annual Balance Sheet'!N15-'Annual Balance Sheet'!N26) -> -4049.6311 | P14: =-('Annual Balance Sheet'!P15+'Annual Balance Sheet'!P26-'Annual Balance Sheet'!O15-'Annual Balance Sheet'!O26) -> -4280.8256 | Q14: =-('Annual Balance Sheet'!Q15+'Annual Balance Sheet'!Q26-'Annual Balance Sheet'!P15-'Annual Balance Sheet'!P26) -> -4470.5449
A15: Change in deferred revenue | B15: ₹m | C15: =0 -> 0 | D15: =0 -> 0 | E15: =0 -> 0 | F15: =0 -> 0 | G15: =0 -> 0 | H15: =0 -> 0 | I15: =0 -> 0 | J15: =0 -> 0 | ... M15: =0 -> 0 | N15: ='Annual Balance Sheet'!N47-'Acquisition & Debt'!C38 -> 65.046803 | O15: ='Annual Balance Sheet'!O47-'Annual Balance Sheet'!N47 -> 1208.3443 | P15: ='Annual Balance Sheet'!P47-'Annual Balance Sheet'!O47 -> 1297.5468 | Q15: ='Annual Balance Sheet'!Q47-'Annual Balance Sheet'!P47 -> 1380.0925
A16: Change in employee benefits | B16: ₹m | C16: ='Raw Financials'!C116 -> -490.59606 | D16: ='Raw Financials'!D116 -> 0 | E16: ='Raw Financials'!E116 -> 217 | F16: ='Raw Financials'!F116 -> 0 | G16: ='Raw Financials'!G116 -> 0 | H16: ='Raw Financials'!H116 -> 0 | I16: ='Raw Financials'!I116 -> 2153 | J16: ='Raw Financials'!J116 -> 175 | ... M16: ='Raw Financials'!M116 -> 6097 | N16: ='Annual Balance Sheet'!N45-'Acquisition & Debt'!C42 -> 106.66567 | O16: ='Annual Balance Sheet'!O45-'Annual Balance Sheet'!N45 -> 1241.0693 | P16: ='Annual Balance Sheet'!P45-'Annual Balance Sheet'!O45 -> 1231.0512 | Q16: ='Annual Balance Sheet'!Q45-'Annual Balance Sheet'!P45 -> 1185.4473
A17: Change in trade / other liabilities | B17: ₹m | C17: ='Raw Financials'!C117 -> -348.39083 | D17: ='Raw Financials'!D117 -> 0 | E17: ='Raw Financials'!E117 -> 0 | F17: ='Raw Financials'!F117 -> 0 | G17: ='Raw Financials'!G117 -> 0 | H17: ='Raw Financials'!H117 -> 0 | I17: ='Raw Financials'!I117 -> 0 | J17: ='Raw Financials'!J117 -> 0 | ... M17: ='Raw Financials'!M117 -> -430 | N17: ='Annual Balance Sheet'!N44-'Acquisition & Debt'!C43 -> 180.18497 | O17: ='Annual Balance Sheet'!O44-'Annual Balance Sheet'!N44 -> 5715.8495 | P17: ='Annual Balance Sheet'!P44-'Annual Balance Sheet'!O44 -> 5064.977 | Q17: ='Annual Balance Sheet'!Q44-'Annual Balance Sheet'!P44 -> 4079.1559
A18: Other operating / integration / classification | B18: ₹m | C18: ='Raw Financials'!C119-SUM(C7:C17) -> 62.3757 | D18: ='Raw Financials'!D119-SUM(D7:D17) -> 2002 | E18: ='Raw Financials'!E119-SUM(E7:E17) -> 52 | F18: ='Raw Financials'!F119-SUM(F7:F17) -> 306 | G18: ='Raw Financials'!G119-SUM(G7:G17) -> -1707 | H18: ='Raw Financials'!H119-SUM(H7:H17) -> 2963 | I18: ='Raw Financials'!I119-SUM(I7:I17) -> -452 | J18: ='Raw Financials'!J119-SUM(J7:J17) -> 877 | ... M18: ='Raw Financials'!M119-SUM(M7:M17) -> -675 | N18: =('Annual Balance Sheet'!N51-SUM('Annual Balance Sheet'!N16,'Annual Balance Sheet'!N17:'Annual Balance Sheet'!N20,'Annual Balance Sheet'!N22:'Annual Balance Sheet'!N27))-(N40+Assumptions!C56+SUM(N7:N17)+N26-Assumptions!C58-Assumptions!C62+N36-Assumptions!C59-Assumptions!C60-Assumptions!C61) -> -1900.3811 | O18: =('Annual Balance Sheet'!O51-SUM('Annual Balance Sheet'!O16,'Annual Balance Sheet'!O17:'Annual Balance Sheet'!O20,'Annual Balance Sheet'!O22:'Annual Balance Sheet'!O27))-(O40+SUM(O7:O17)+O26+O36) -> 1959.1798 | P18: =('Annual Balance Sheet'!P51-SUM('Annual Balance Sheet'!P16,'Annual Balance Sheet'!P17:'Annual Balance Sheet'!P20,'Annual Balance Sheet'!P22:'Annual Balance Sheet'!P27))-(P40+SUM(P7:P17)+P26+P36) -> 2118.0805 | Q18: =('Annual Balance Sheet'!Q51-SUM('Annual Balance Sheet'!Q16,'Annual Balance Sheet'!Q17:'Annual Balance Sheet'!Q20,'Annual Balance Sheet'!Q22:'Annual Balance Sheet'!Q27))-(Q40+SUM(Q7:Q17)+Q26+Q36) -> 2285.5076
A19: Cash flow from operations | B19: ₹m | C19: ='Raw Financials'!C119 -> 3602.9216 | D19: ='Raw Financials'!D119 -> 4723 | E19: ='Raw Financials'!E119 -> 3824 | F19: ='Raw Financials'!F119 -> 4527 | G19: ='Raw Financials'!G119 -> 2969 | H19: ='Raw Financials'!H119 -> 7623 | I19: ='Raw Financials'!I119 -> 7656 | J19: ='Raw Financials'!J119 -> 9505 | ... M19: ='Raw Financials'!M119 -> 17917 | N19: =Assumptions!C57+SUM(N7:N18) -> 24789.335 | O19: =SUM(O7:O18) -> 41518.65 | P19: =SUM(P7:P18) -> 53291.13 | Q19: =SUM(Q7:Q18) -> 67071.397
A20: CFO / net income | B20: x | C20: =IFERROR(C19/C7,"") -> 1.2132293 | D20: =IFERROR(D19/D7,"") -> 1.7357589 | E20: =IFERROR(E19/E7,"") -> 1.2387431 | F20: =IFERROR(F19/F7,"") -> 1.0724947 | G20: =IFERROR(G19/G7,"") -> 0.6349444 | H20: =IFERROR(H19/H7,"") -> 1.6358369 | I20: =IFERROR(I19/I7,"") -> 1.0712187 | J20: =IFERROR(J19/J7,"") -> 1.2756677 | ... Q20: =IFERROR(Q19/Q7,"") -> 1.0755864
A21: Capex | B21: ₹m | C21: ='Raw Financials'!C120 -> -1609.1165 | D21: ='Raw Financials'!D120 -> 0 | E21: ='Raw Financials'!E120 -> 0 | F21: ='Raw Financials'!F120 -> 0 | G21: ='Raw Financials'!G120 -> 0 | H21: ='Raw Financials'!H120 -> 0 | I21: ='Raw Financials'!I120 -> -1541 | J21: ='Raw Financials'!J120 -> -1582 | ... M21: ='Raw Financials'!M120 -> -7425 | N21: =Assumptions!C62-('Annual P&L'!N7-'Quarterly P&L'!AU6)*Assumptions!C38 -> -6501.6371 | O21: =-'Annual P&L'!O7*Assumptions!D38 -> -9402.7507 | P21: =-'Annual P&L'!P7*Assumptions!E38 -> -11088.483 | Q21: =-'Annual P&L'!Q7*Assumptions!F38 -> -13713.046
A22: Acquisitions | B22: ₹m | C22: ='Raw Financials'!C122 -> 0 | D22: ='Raw Financials'!D122 -> 0 | E22: ='Raw Financials'!E122 -> 0 | F22: ='Raw Financials'!F122 -> 0 | G22: ='Raw Financials'!G122 -> 0 | H22: ='Raw Financials'!H122 -> 0 | I22: ='Raw Financials'!I122 -> -8557 | J22: ='Raw Financials'!J122 -> -1222 | ... M22: ='Raw Financials'!M122 -> -3206 | N22: =Assumptions!C58 -> -46939 | O22: =0 -> 0 | P22: =0 -> 0 | Q22: =0 -> 0
A23: Change in investments / bank balances | B23: ₹m | C23: =SUM('Raw Financials'!C123,'Raw Financials'!C124) -> 0 | D23: =SUM('Raw Financials'!D123,'Raw Financials'!D124) -> 0 | E23: =SUM('Raw Financials'!E123,'Raw Financials'!E124) -> -331 | F23: =SUM('Raw Financials'!F123,'Raw Financials'!F124) -> 0 | G23: =SUM('Raw Financials'!G123,'Raw Financials'!G124) -> 0 | H23: =SUM('Raw Financials'!H123,'Raw Financials'!H124) -> 0 | I23: =SUM('Raw Financials'!I123,'Raw Financials'!I124) -> 450 | J23: =SUM('Raw Financials'!J123,'Raw Financials'!J124) -> 450 | ... M23: =SUM('Raw Financials'!M123,'Raw Financials'!M124) -> 1551 | N23: =-('Annual Balance Sheet'!N23-'Acquisition & Debt'!C27) -> 4030 | O23: =-('Annual Balance Sheet'!O23-'Annual Balance Sheet'!N23) -> 0 | P23: =-('Annual Balance Sheet'!P23-'Annual Balance Sheet'!O23) -> 0 | Q23: =-('Annual Balance Sheet'!Q23-'Annual Balance Sheet'!P23) -> 0
A24: PPE sale / interest / dividends received | B24: ₹m | C24: =SUM('Raw Financials'!C121,'Raw Financials'!C125,'Raw Financials'!C126) -> 65.216349 | D24: =SUM('Raw Financials'!D121,'Raw Financials'!D125,'Raw Financials'!D126) -> 0 | E24: =SUM('Raw Financials'!E121,'Raw Financials'!E125,'Raw Financials'!E126) -> 104 | F24: =SUM('Raw Financials'!F121,'Raw Financials'!F125,'Raw Financials'!F126) -> 0 | G24: =SUM('Raw Financials'!G121,'Raw Financials'!G125,'Raw Financials'!G126) -> 0 | H24: =SUM('Raw Financials'!H121,'Raw Financials'!H125,'Raw Financials'!H126) -> 0 | I24: =SUM('Raw Financials'!I121,'Raw Financials'!I125,'Raw Financials'!I126) -> 84 | J24: =SUM('Raw Financials'!J121,'Raw Financials'!J125,'Raw Financials'!J126) -> 88 | ... M24: =SUM('Raw Financials'!M121,'Raw Financials'!M125,'Raw Financials'!M126) -> 1734 | N24: =0 -> 0 | O24: =0 -> 0 | P24: =0 -> 0 | Q24: =0 -> 0
A25: Historical investing residual / reclassification | B25: ₹m | C25: ='Raw Financials'!C127-SUM(C21:C24) -> -1496.664 | D25: ='Raw Financials'!D127-SUM(D21:D24) -> -3063 | E25: ='Raw Financials'!E127-SUM(E21:E24) -> -2477 | F25: ='Raw Financials'!F127-SUM(F21:F24) -> -2300 | G25: ='Raw Financials'!G127-SUM(G21:G24) -> 1123 | H25: ='Raw Financials'!H127-SUM(H21:H24) -> -2354 | I25: ='Raw Financials'!I127-SUM(I21:I24) -> 0 | J25: ='Raw Financials'!J127-SUM(J21:J24) -> -450 | ... M25: ='Raw Financials'!M127-SUM(M21:M24) -> 2998 | N25: =0 -> 0 | O25: =0 -> 0 | P25: =0 -> 0 | Q25: =0 -> 0
A26: Cash flow from investing | B26: ₹m | C26: ='Raw Financials'!C127 -> -3040.5642 | D26: ='Raw Financials'!D127 -> -3063 | E26: ='Raw Financials'!E127 -> -2704 | F26: ='Raw Financials'!F127 -> -2300 | G26: ='Raw Financials'!G127 -> 1123 | H26: ='Raw Financials'!H127 -> -2354 | I26: ='Raw Financials'!I127 -> -9564 | J26: ='Raw Financials'!J127 -> -2716 | ... M26: ='Raw Financials'!M127 -> -4348 | N26: =SUM(N21:N25) -> -49410.637 | O26: =SUM(O21:O25) -> -9402.7507 | P26: =SUM(P21:P25) -> -11088.483 | Q26: =SUM(Q21:Q25) -> -13713.046
A27: Equity issuance | B27: ₹m | C27: ='Raw Financials'!C128 -> 14.599244 | D27: ='Raw Financials'!D128 -> 0 | E27: ='Raw Financials'!E128 -> 0 | F27: ='Raw Financials'!F128 -> 0 | G27: ='Raw Financials'!G128 -> 0 | H27: ='Raw Financials'!H128 -> 18 | I27: ='Raw Financials'!I128 -> 51 | J27: ='Raw Financials'!J128 -> 18 | ... M27: ='Raw Financials'!M128 -> 3 | N27: =0 -> 0 | O27: =0 -> 0 | P27: =0 -> 0 | Q27: =0 -> 0
A28: Borrowing proceeds | B28: ₹m | C28: ='Raw Financials'!C129 -> 62.461007 | D28: ='Raw Financials'!D129 -> 0 | E28: ='Raw Financials'!E129 -> 0 | F28: ='Raw Financials'!F129 -> 0 | G28: ='Raw Financials'!G129 -> 0 | H28: ='Raw Financials'!H129 -> 281 | I28: ='Raw Financials'!I129 -> 3578 | J28: ='Raw Financials'!J129 -> 3578 | ... M28: ='Raw Financials'!M129 -> 1976 | N28: =Assumptions!C59 -> 46547 | O28: =0 -> 0 | P28: =0 -> 0 | Q28: =0 -> 0
A29: Borrowing repayment | B29: ₹m | C29: ='Raw Financials'!C130 -> -48.009766 | D29: ='Raw Financials'!D130 -> 0 | E29: ='Raw Financials'!E130 -> 0 | F29: ='Raw Financials'!F130 -> 0 | G29: ='Raw Financials'!G130 -> 0 | H29: ='Raw Financials'!H130 -> -306 | I29: ='Raw Financials'!I130 -> -59 | J29: ='Raw Financials'!J130 -> -180 | ... M29: ='Raw Financials'!M130 -> -5154 | N29: =-('Acquisition & Debt'!C20-10*Assumptions!C19) -> -4700 | O29: =-'Acquisition & Debt'!D20 -> -20900 | P29: =-'Acquisition & Debt'!E20 -> -25920 | Q29: =-'Acquisition & Debt'!F20 -> 0
A30: Lease principal | B30: ₹m | C30: ='Raw Financials'!C131 -> 0 | D30: ='Raw Financials'!D131 -> 0 | E30: ='Raw Financials'!E131 -> 0 | F30: ='Raw Financials'!F131 -> 0 | G30: ='Raw Financials'!G131 -> 0 | H30: ='Raw Financials'!H131 -> 0 | I30: ='Raw Financials'!I131 -> -386 | J30: ='Raw Financials'!J131 -> -421 | ... M30: ='Raw Financials'!M131 -> -1048 | N30: =Assumptions!C60-'Acquisition & Debt'!C41*Assumptions!C42 -> -1308.75 | O30: =-'Annual Balance Sheet'!N43*Assumptions!D42 -> -1029.4672 | P30: =-'Annual Balance Sheet'!O43*Assumptions!E42 -> -1139.3954 | Q30: =-'Annual Balance Sheet'!P43*Assumptions!F42 -> -1316.5666
A31: Interest paid | B31: ₹m | C31: ='Raw Financials'!C132 -> -28.391909 | D31: ='Raw Financials'!D132 -> 0 | E31: ='Raw Financials'!E132 -> -13 | F31: ='Raw Financials'!F132 -> 0 | G31: ='Raw Financials'!G132 -> 0 | H31: ='Raw Financials'!H132 -> -79 | I31: ='Raw Financials'!I132 -> -265 | J31: ='Raw Financials'!J132 -> -714 | ... M31: ='Raw Financials'!M132 -> -1169 | N31: =Assumptions!C61-('Annual P&L'!N22-'Quarterly P&L'!AU20) -> -3544.4 | O31: =-'Annual P&L'!O22 -> -1814.5 | P31: =-'Annual P&L'!P22 -> -739.2 | Q31: =-'Annual P&L'!Q22 -> -48.5
A32: Dividends paid | B32: ₹m | C32: ='Raw Financials'!C133 -> -731.36613 | D32: ='Raw Financials'!D133 -> 0 | E32: ='Raw Financials'!E133 -> -613 | F32: ='Raw Financials'!F133 -> 0 | G32: ='Raw Financials'!G133 -> 0 | H32: ='Raw Financials'!H133 -> -686 | I32: ='Raw Financials'!I133 -> -3152 | J32: ='Raw Financials'!J133 -> -3534 | ... M32: ='Raw Financials'!M133 -> -5277 | N32: =-'Annual P&L'!N36 -> -8541.4164 | O32: =-'Annual P&L'!O36 -> -12756.233 | P32: =-'Annual P&L'!P36 -> -18409.441 | Q32: =-'Annual P&L'!Q36 -> -24693.761
A33: NCI dividends | B33: ₹m | C33: ='Raw Financials'!C134 -> 0 | D33: ='Raw Financials'!D134 -> 0 | E33: ='Raw Financials'!E134 -> 0 | F33: ='Raw Financials'!F134 -> 0 | G33: ='Raw Financials'!G134 -> 0 | H33: ='Raw Financials'!H134 -> 0 | I33: ='Raw Financials'!I134 -> -596 | J33: ='Raw Financials'!J134 -> -751 | ... M33: ='Raw Financials'!M134 -> -154 | N33: =-'Annual P&L'!N29*Assumptions!C45 -> -149.41253 | O33: =-'Annual P&L'!O29*Assumptions!D45 -> -157.50596 | P33: =-'Annual P&L'!P29*Assumptions!E45 -> -143.0415 | Q33: =-'Annual P&L'!Q29*Assumptions!F45 -> -187.07395
A34: Acquisition liability settlement | B34: ₹m | C34: =0 -> 0 | D34: =0 -> 0 | E34: =0 -> 0 | F34: =0 -> 0 | G34: =0 -> 0 | H34: =0 -> 0 | I34: =0 -> 0 | J34: =0 -> 0 | ... M34: =0 -> 0 | N34: =-('Acquisition & Debt'!C40-'Annual Balance Sheet'!N40) -> -629.5 | O34: =-('Annual Balance Sheet'!N40-'Annual Balance Sheet'!O40) -> -566.55 | P34: =-('Annual Balance Sheet'!O40-'Annual Balance Sheet'!P40) -> -462.6825 | Q34: =-('Annual Balance Sheet'!P40-'Annual Balance Sheet'!Q40) -> -859.2675
A35: Historical financing residual / reclassification | B35: ₹m | C35: ='Raw Financials'!C135-SUM(C27:C34) -> 3.72146 | D35: ='Raw Financials'!D135-SUM(D27:D34) -> -669 | E35: ='Raw Financials'!E135-SUM(E27:E34) -> -118 | F35: ='Raw Financials'!F135-SUM(F27:F34) -> -1063 | G35: ='Raw Financials'!G135-SUM(G27:G34) -> -1327 | H35: ='Raw Financials'!H135-SUM(H27:H34) -> -4759 | I35: ='Raw Financials'!I135-SUM(I27:I34) -> -729 | J35: ='Raw Financials'!J135-SUM(J27:J34) -> -3578 | ... M35: ='Raw Financials'!M135-SUM(M27:M34) -> -114 | N35: =0 -> 0 | O35: =0 -> 0 | P35: =0 -> 0 | Q35: =0 -> 0
A36: Cash flow from financing | B36: ₹m | C36: ='Raw Financials'!C135 -> -726.9861 | D36: ='Raw Financials'!D135 -> -669 | E36: ='Raw Financials'!E135 -> -744 | F36: ='Raw Financials'!F135 -> -1063 | G36: ='Raw Financials'!G135 -> -1327 | H36: ='Raw Financials'!H135 -> -5531 | I36: ='Raw Financials'!I135 -> -1558 | J36: ='Raw Financials'!J135 -> -5582 | ... M36: ='Raw Financials'!M135 -> -10937 | N36: =SUM(N27:N35) -> 27673.521 | O36: =SUM(O27:O35) -> -37224.256 | P36: =SUM(P27:P35) -> -46813.76 | Q36: =SUM(Q27:Q35) -> -27105.169
A37: Net cash change before FX | B37: ₹m | C37: =SUM(C19,C26,C36) -> -164.62872 | D37: =SUM(D19,D26,D36) -> 991 | E37: =SUM(E19,E26,E36) -> 376 | F37: =SUM(F19,F26,F36) -> 1164 | G37: =SUM(G19,G26,G36) -> 2765 | H37: =SUM(H19,H26,H36) -> -262 | I37: =SUM(I19,I26,I36) -> -3466 | J37: =SUM(J19,J26,J36) -> 1207 | ... Q37: =SUM(Q19,Q26,Q36) -> 26253.182
A38: FX effect | B38: ₹m | C38: ='Raw Financials'!C138 -> 155.10373 | D38: =D39-D37 -> -367.62726 | E38: =E39-E37 -> 224 | F38: =F39-F37 -> -72 | G38: =G39-G37 -> 236 | H38: =H39-H37 -> 66 | I38: =I39-I37 -> -65 | J38: =J39-J37 -> 24 | K38: =K39-K37 -> -172 | ... M38: =M39-M37 -> 348 | N38: =0 -> 0 | O38: =0 -> 0 | P38: =0 -> 0 | Q38: =0 -> 0
A39: Net cash change | B39: ₹m | C39: =C37+C38 -> -9.52499 | D39: =D41-D40 -> 623.37274 | E39: =E41-E40 -> 600 | F39: =F41-F40 -> 1092 | G39: =G41-G40 -> 3001 | H39: =H41-H40 -> -196 | I39: =I41-I40 -> -3531 | J39: =J41-J40 -> 1231 | K39: =K41-K40 -> -2486 | ... M39: =M41-M40 -> 2980 | N39: =Assumptions!C56+SUM(N19,N26,N36)-Assumptions!C57-Assumptions!C58-Assumptions!C59-Assumptions!C60-Assumptions!C61-Assumptions!C62 -> 2500.2189 | O39: =O37+O38 -> -5108.3571 | P39: =P37+P38 -> -4611.1131 | Q39: =Q37+Q38 -> 26253.182
A40: Opening cash | B40: ₹m | C40: ='Raw Financials'!C137 -> 2237.7961 | D40: =C41 -> 2878.6273 | E40: =D41 -> 3502 | F40: =E41 -> 4102 | G40: =F41 -> 5194 | H40: =G41 -> 8195 | I40: =H41 -> 7999 | J40: =I41 -> 4468 | K40: =J41 -> 5699 | ... M40: =L41 -> 7956 | N40: ='Annual Balance Sheet'!M21 -> 10936 | O40: =N41 -> 13436.219 | P40: =O41 -> 8327.8618 | Q40: =P41 -> 3716.7487
A41: Closing cash | B41: ₹m | C41: ='Raw Financials'!C139 -> 2878.6273 | D41: ='Raw Financials'!D139 -> 3502 | E41: ='Raw Financials'!E139 -> 4102 | F41: ='Raw Financials'!F139 -> 5194 | G41: ='Raw Financials'!G139 -> 8195 | H41: ='Raw Financials'!H139 -> 7999 | I41: ='Raw Financials'!I139 -> 4468 | J41: ='Raw Financials'!J139 -> 5699 | ... M41: ='Raw Financials'!M139 -> 10936 | N41: =N40+N39 -> 13436.219 | O41: =O40+O39 -> 8327.8618 | P41: =P40+P39 -> 3716.7487 | Q41: =Q40+Q39 -> 29969.931
A42: Balance-sheet cash + held-for-sale cash | B42: ₹m | C42: ='Annual Balance Sheet'!C21+'Annual Balance Sheet'!C22 -> 2878.6273 | D42: ='Annual Balance Sheet'!D21+'Annual Balance Sheet'!D22 -> 3502 | E42: ='Annual Balance Sheet'!E21+'Annual Balance Sheet'!E22 -> 4102 | F42: ='Annual Balance Sheet'!F21+'Annual Balance Sheet'!F22 -> 5194 | G42: ='Annual Balance Sheet'!G21+'Annual Balance Sheet'!G22 -> 8195 | H42: ='Annual Balance Sheet'!H21+'Annual Balance Sheet'!H22 -> 7999 | I42: ='Annual Balance Sheet'!I21+'Annual Balance Sheet'!I22 -> 4468 | J42: ='Annual Balance Sheet'!J21+'Annual Balance Sheet'!J22 -> 5699 | ... Q42: ='Annual Balance Sheet'!Q21+'Annual Balance Sheet'!Q22 -> 29969.931
A43: Cash check | B43: ₹m | C43: =C41-C42 -> 0 | D43: =D41-D42 -> 0 | E43: =E41-E42 -> 0 | F43: =F41-F42 -> 0 | G43: =G41-G42 -> 0 | H43: =H41-H42 -> 0 | I43: =I41-I42 -> 0 | J43: =J41-J42 -> 0 | ... Q43: =Q41-Q42 -> 0
A44: Free cash flow | B44: ₹m | C44: =C19+C21 -> 1993.805 | D44: =D19+D21 -> 4723 | E44: =E19+E21 -> 3824 | F44: =F19+F21 -> 4527 | G44: =G19+G21 -> 2969 | H44: =H19+H21 -> 7623 | I44: =I19+I21 -> 6115 | J44: =J19+J21 -> 7923 | ... Q44: =Q19+Q21 -> 53358.352
A45: FCF margin | B45: % | C45: =IFERROR(C44/'Annual P&L'!C7,"") -> 0.074329012 | D45: =IFERROR(D44/'Annual P&L'!D7,"") -> 0.16855216 | E45: =IFERROR(E44/'Annual P&L'!E7,"") -> 0.12783312 | F45: =IFERROR(F44/'Annual P&L'!F7,"") -> 0.12314346 | G45: =IFERROR(G44/'Annual P&L'!G7,"") -> 0.070962499 | H45: =IFERROR(H44/'Annual P&L'!H7,"") -> 0.16348546 | I45: =IFERROR(I44/'Annual P&L'!I7,"") -> 0.095071517 | J45: =IFERROR(J44/'Annual P&L'!J7,"") -> 0.098857086 | ... M45: =IFERROR(M44/'Annual P&L'!M7,"") -> 0.063965079 | N45: =N44/'Annual P&L'!N7 -> 0.080025363 | O45: =O44/'Annual P&L'!O7 -> 0.10929874 | P45: =P44/'Annual P&L'!P7 -> 0.11417968 | Q45: =Q44/'Annual P&L'!Q7 -> 0.11673195

Sheet Acquisition & Debt
A1: Encora Acquisition & Debt Schedule
A2: Encora PPA, Q1 FY27 balance-sheet anchor and disclosed principal / interest repayment schedule
A5: Metric | B5: Units | C5: FY27E | D5: FY28E | E5: FY29E | F5: FY30E | G5: Source / logic
A6: Encora two-month Q1 revenue | B6: $m | C6: 100.7 | G6: Q1 FY27 investor presentation / disclosed schedule
A7: Encora monthly run-rate | B7: $m | C7: =Assumptions!C17 -> 50.35 | D7: =C8/12 -> 48.461875 | E7: =D8/12 -> 53.308063 | F7: =E8/12 -> 58.638869 | G7: Q1 FY27 investor presentation / disclosed schedule
A8: Encora annual contribution | B8: $m | C8: =C7*11*(1+Assumptions!C18) -> 581.5425 | D8: =C8*(1+Assumptions!D18) -> 639.69675 | E8: =D8*(1+Assumptions!E18) -> 703.66643 | F8: =E8*(1+Assumptions!F18) -> 766.9964 | G8: Q1 FY27 investor presentation / disclosed schedule
A9: Share-swap consideration | B9: ₹m | C9: 114488 | G9: Q1 FY27 investor presentation / disclosed schedule
A10: Cash consideration | B10: ₹m | C10: 25327 | G10: Q1 FY27 investor presentation / disclosed schedule
A11: Total consideration | B11: ₹m | C11: 139815 | G11: Q1 FY27 investor presentation / disclosed schedule
A12: Customer intangibles recognized | B12: ₹m | C12: 45026 | G12: Q1 FY27 investor presentation / disclosed schedule
A13: Deferred tax liability recognized | B13: ₹m | C13: 11257 | G13: Q1 FY27 investor presentation / disclosed schedule
A14: Goodwill recognized | B14: ₹m | C14: 120890 | G14: Q1 FY27 investor presentation / disclosed schedule
A15: Acquisition debt principal | B15: $m | C15: 550 | G15: Q1 FY27 investor presentation / disclosed schedule
A16: Principal repayment | B16: $m | C16: 60 | D16: 220 | E16: 270 | F16: 0
A17: Closing acquisition debt | B17: $m | C17: =C15-C16 -> 490 | D17: =C17-D16 -> 270 | E17: =D17-E16 -> 0 | F17: =E17-F16 -> 0
A18: Interest payment | B18: $m | C18: 23.6 | D18: 19.1 | E18: 7.7 | F18: 0.5
A19: Average INR / USD | B19: ₹ / $ | C19: =Assumptions!C19 -> 94 | D19: =Assumptions!D19 -> 95 | E19: =Assumptions!E19 -> 96 | F19: =Assumptions!F19 -> 97
A20: Principal repayment | B20: ₹m | C20: =C16*C19 -> 5640 | D20: =D16*D19 -> 20900 | E20: =E16*E19 -> 25920 | F20: =F16*F19 -> 0
A21: Closing acquisition debt | B21: ₹m | C21: =C17*C19 -> 46060 | D21: =D17*D19 -> 25650 | E21: =E17*E19 -> 0 | F21: =F17*F19 -> 0
A22: Interest / finance cost | B22: ₹m | C22: =C18*C19 -> 2218.4 | D22: =D18*D19 -> 1814.5 | E22: =E18*E19 -> 739.2 | F22: =F18*F19 -> 48.5
A23: Q1 FY27 fixed assets | B23: ₹m | C23: 15467
A24: Q1 FY27 goodwill | B24: ₹m | C24: 163729
A25: Q1 FY27 acquired intangibles | B25: ₹m | C25: 56869
A26: Q1 FY27 cash | B26: ₹m | C26: 13883
A27: Q1 FY27 other bank balances | B27: ₹m | C27: 4030
A28: Q1 FY27 debtors | B28: ₹m | C28: 40979
A29: Q1 FY27 unbilled / contract assets | B29: ₹m | C29: 20969
A30: Q1 FY27 contract cost | B30: ₹m | C30: 5554
A31: Q1 FY27 deferred tax asset | B31: ₹m | C31: 8394
A32: Q1 FY27 other assets | B32: ₹m | C32: 5531
A33: Q1 FY27 total assets | B33: ₹m | C33: 335405
A34: Q1 FY27 share capital | B34: ₹m | C34: 885
... A44: Q1 FY27 total funding | B44: ₹m | C44: 335405
A45: Q1 FY27 balance check | B45: ₹m | C45: =C33-C44 -> 0

Sheet Order Book & Revenue
A1: Order Book & Revenue Drivers
A2: Coforge-specific bridge: order-book conversion, fresh intake, mining, AI, T&M deflation, outcome pricing, Encora and portfolio exits
A5: Metric | B5: Units | C5: FY16A | D5: FY17A | E5: FY18A | F5: FY19A | G5: FY20A | H5: FY21A | I5: FY22A | J5: FY23A | K5: FY24A | L5: FY25A | M5: FY26A | N5: FY27E | O5: FY28E | P5: FY29E | Q5: FY30E
A7: Prior-year revenue | B7: $m | N7: =M33 -> 1870 | O7: =N33 -> 2431.104 | P7: =O33 -> 3093.0101 | Q7: =P33 -> 3850.1676
A8: Repeat / retained base | B8: % | N8: =Assumptions!C6 -> 0.955 | O8: =Assumptions!D6 -> 0.957 | P8: =Assumptions!E6 -> 0.96 | Q8: =Assumptions!F6 -> 0.962
A9: Retained organic revenue | B9: $m | N9: =N7*N8 -> 1785.85 | O9: =O7*O8 -> 2326.5665 | P9: =P7*P8 -> 2969.2897 | Q9: =Q7*Q8 -> 3703.8613
A10: Executable order book | B10: $m | C10: ='Raw Operating'!C10 -> 301 | D10: ='Raw Operating'!D10 -> 320 | E10: ='Raw Operating'!E10 -> 339 | F10: ='Raw Operating'!F10 -> 390 | G10: ='Raw Operating'!G10 -> 468 | H10: ='Raw Operating'!H10 -> 520 | I10: ='Raw Operating'!I10 -> 720 | J10: ='Raw Operating'!J10 -> 869 | ... M10: ='Raw Operating'!M10 -> 1752 | N10: ='Acquisition & Debt'!C17+'Raw Operating'!M10 -> 2242 | O10: =N10*(1+Assumptions!D7) -> 2466.2 | P10: =O10*(1+Assumptions!E7) -> 2688.158 | Q10: =P10*(1+Assumptions!F7) -> 2903.2106
A11: Executable order book growth | B11: % | N11: =Assumptions!C7 -> 0.12 | O11: =Assumptions!D7 -> 0.1 | P11: =Assumptions!E7 -> 0.09 | Q11: =Assumptions!F7 -> 0.08
A12: EOB expansion | B12: $m | N12: =N10-M10 -> 490 | O12: =O10-N10 -> 224.2 | P12: =P10-O10 -> 221.958 | Q12: =Q10-P10 -> 215.05264
A13: EOB expansion realization | B13: % | N13: =Assumptions!C8 -> 0.04 | O13: =Assumptions!D8 -> 0.042 | P13: =Assumptions!E8 -> 0.044 | Q13: =Assumptions!F8 -> 0.045
A14: Revenue from EOB expansion | B14: $m | N14: =N12*N13 -> 19.6 | O14: =O12*O13 -> 9.4164 | P14: =P12*P13 -> 9.766152 | Q14: =Q12*Q13 -> 9.6773688
A15: Fresh order intake | B15: $m | C15: ='Raw Operating'!C9 -> 420 | D15: ='Raw Operating'!D9 -> 457 | E15: ='Raw Operating'!E9 -> 507 | F15: ='Raw Operating'!F9 -> 646 | G15: ='Raw Operating'!G9 -> 748 | H15: ='Raw Operating'!H9 -> 781 | I15: ='Raw Operating'!I9 -> 1151 | J15: ='Raw Operating'!J9 -> 1265 | ... M15: ='Raw Operating'!M9 -> 2262 | N15: ='Raw Operating'!M9*(1+Assumptions!C9) -> 2488.2 | O15: =N15*(1+Assumptions!D9) -> 2737.02 | P15: =O15*(1+Assumptions!E9) -> 2983.3518 | Q15: =P15*(1+Assumptions!F9) -> 3222.0199
A16: Fresh order intake growth | B16: % | N16: =Assumptions!C9 -> 0.1 | O16: =Assumptions!D9 -> 0.1 | P16: =Assumptions!E9 -> 0.09 | Q16: =Assumptions!F9 -> 0.08
A17: Incremental fresh order intake | B17: $m | N17: =N15-M15 -> 226.2 | O17: =O15-N15 -> 248.82 | P17: =P15-O15 -> 246.3318 | Q17: =Q15-P15 -> 238.66814
A18: First-year realization | B18: % | N18: =Assumptions!C10 -> 0.06 | O18: =Assumptions!D10 -> 0.062 | P18: =Assumptions!E10 -> 0.065 | Q18: =Assumptions!F10 -> 0.067
A19: Revenue from fresh orders | B19: $m | N19: =N17*N18 -> 13.572 | O19: =O17*O18 -> 15.42684 | P19: =P17*P18 -> 16.011567 | Q19: =Q17*Q18 -> 15.990766
A20: Client farming / pricing uplift | B20: % | N20: =Assumptions!C11 -> 0.01 | O20: =Assumptions!D11 -> 0.015 | P20: =Assumptions!E11 -> 0.015 | Q20: =Assumptions!F11 -> 0.015
A21: Client farming / pricing revenue | B21: $m | N21: =N9*N20 -> 17.8585 | O21: =O9*O20 -> 34.898498 | P21: =P9*P20 -> 44.539346 | Q21: =Q9*Q20 -> 55.557919
A22: T&M mix | B22: % | N22: =Assumptions!C12 -> 0.57 | O22: =Assumptions!D12 -> 0.56 | P22: =Assumptions!E12 -> 0.55 | Q22: =Assumptions!F12 -> 0.54
A23: AI deflation on T&M | B23: % | N23: =Assumptions!C13 -> 0.01 | O23: =Assumptions!D13 -> 0.01 | P23: =Assumptions!E13 -> 0.008 | Q23: =Assumptions!F13 -> 0.005
A24: T&M AI deflation drag | B24: $m | N24: =-N9*N22*N23 -> -10.179345 | O24: =-O9*O22*O23 -> -13.028772 | P24: =-P9*P22*P23 -> -13.064875 | Q24: =-Q9*Q22*Q23 -> -10.000425
A25: Outcome-pricing offset | B25: % | N25: =Assumptions!C14 -> 0.008 | O25: =Assumptions!D14 -> 0.01 | P25: =Assumptions!E14 -> 0.012 | Q25: =Assumptions!F14 -> 0.013
A26: Outcome-pricing uplift | B26: $m | N26: =N9*(1-N22)*N25 -> 6.143324 | O26: =O9*(1-O22)*O25 -> 10.236893 | P26: =P9*(1-P22)*P25 -> 16.034164 | Q26: =Q9*(1-Q22)*Q25 -> 22.14909
A27: Incremental AI uplift | B27: % | N27: =Assumptions!C15 -> 0.02 | O27: =Assumptions!D15 -> 0.03 | P27: =Assumptions!E15 -> 0.035 | Q27: =Assumptions!F15 -> 0.04
A28: Incremental AI revenue | B28: $m | N28: =N9*N27 -> 35.717 | O28: =O9*O27 -> 69.796995 | P28: =P9*P27 -> 103.92514 | Q28: =Q9*Q27 -> 148.15445
A29: Encora revenue contribution | B29: $m | N29: ='Acquisition & Debt'!C8 -> 581.5425 | O29: ='Acquisition & Debt'!D8 -> 639.69675 | P29: ='Acquisition & Debt'!E8 -> 703.66643 | Q29: ='Acquisition & Debt'!F8 -> 766.9964
A30: Portfolio exits | B30: $m | N30: =-Assumptions!C16 -> -19 | O30: =-Assumptions!D16 -> 0 | P30: =-Assumptions!E16 -> 0 | Q30: =-Assumptions!F16 -> 0
A31: Forecast / reported revenue | B31: $m | C31: ='Annual P&L'!C7 -> 26824.049 | D31: ='Annual P&L'!D7 -> 28021 | E31: ='Annual P&L'!E7 -> 29914 | F31: ='Annual P&L'!F7 -> 36762 | G31: ='Annual P&L'!G7 -> 41839 | H31: ='Annual P&L'!H7 -> 46628 | I31: ='Annual P&L'!I7 -> 64320 | J31: ='Annual P&L'!J7 -> 80146 | ... M31: ='Annual P&L'!M7 -> 164027 | N31: =N33*N34 -> 228523.77 | O31: =O33*O34 -> 293835.96 | P31: =P33*P34 -> 369616.09 | Q31: =Q33*Q34 -> 457101.52
A32: Revenue growth | B32: % | C32: =0 -> 0 | D32: =0 -> 0 | E32: =0 -> 0 | F32: =0 -> 0 | G32: =0 -> 0 | H32: =0 -> 0 | I32: =0 -> 0 | J32: =0 -> 0 | ... M32: =0 -> 0 | N32: =N31-'Annual P&L'!N7 -> 0 | O32: =O31-'Annual P&L'!O7 -> 0 | P32: =P31-'Annual P&L'!P7 -> 0 | Q32: =Q31-'Annual P&L'!Q7 -> 0
A33: Average INR / USD | B33: ₹ / $ | C33: =IFERROR('Raw Operating'!C7,C31/'Raw Operating'!C29) -> 0 | D33: =IFERROR('Raw Operating'!D7,D31/'Raw Operating'!D29) -> 0 | E33: =IFERROR('Raw Operating'!E7,E31/'Raw Operating'!E29) -> 0 | F33: =IFERROR('Raw Operating'!F7,F31/'Raw Operating'!F29) -> 0 | G33: =IFERROR('Raw Operating'!G7,G31/'Raw Operating'!G29) -> 0 | H33: =IFERROR('Raw Operating'!H7,H31/'Raw Operating'!H29) -> 0 | I33: =IFERROR('Raw Operating'!I7,I31/'Raw Operating'!I29) -> 866.5 | J33: =IFERROR('Raw Operating'!J7,J31/'Raw Operating'!J29) -> 1001.7 | ... M33: =IFERROR('Raw Operating'!M7,M31/'Raw Operating'!M29) -> 1870 | N33: =SUM(N9,N14,N19,N21,N24,N26,N28:N30) -> 2431.104 | O33: =SUM(O9,O14,O19,O21,O24,O26,O28:O30) -> 3093.0101 | P33: =SUM(P9,P14,P19,P21,P24,P26,P28:P30) -> 3850.1676 | Q33: =SUM(Q9,Q14,Q19,Q21,Q24,Q26,Q28:Q30) -> 4712.3868
A34: Revenue | B34: ₹m | C34: =IFERROR(C31/C33,"") | D34: =IFERROR(D31/D33,"") | E34: =IFERROR(E31/E33,"") | F34: =IFERROR(F31/F33,"") | G34: =IFERROR(G31/G33,"") | H34: =IFERROR(H31/H33,"") | I34: =IFERROR(I31/I33,"") -> 74.22966 | J34: =IFERROR(J31/J33,"") -> 80.009983 | ... M34: =IFERROR(M31/M33,"") -> 87.714973 | N34: =Assumptions!C19 -> 94 | O34: =Assumptions!D19 -> 95 | P34: =Assumptions!E19 -> 96 | Q34: =Assumptions!F19 -> 97
A35: Revenue growth | B35: % | D35: =IFERROR(D33/C33-1,"") | E35: =IFERROR(E33/D33-1,"") | F35: =IFERROR(F33/E33-1,"") | G35: =IFERROR(G33/F33-1,"") | H35: =IFERROR(H33/G33-1,"") | I35: =IFERROR(I33/H33-1,"") | J35: =IFERROR(J33/I33-1,"") -> 0.15603001 | K35: =IFERROR(K33/J33-1,"") -> 0.11680144 | ... Q35: =IFERROR(Q33/P33-1,"") -> 0.22394329
A36: Revenue-driver check | B36: ₹m | D36: =IFERROR(D31/C31-1,"") -> 0.044622317 | E36: =IFERROR(E31/D31-1,"") -> 0.067556476 | F36: =IFERROR(F31/E31-1,"") -> 0.22892291 | G36: =IFERROR(G31/F31-1,"") -> 0.13810456 | H36: =IFERROR(H31/G31-1,"") -> 0.11446258 | I36: =IFERROR(I31/H31-1,"") -> 0.37942867 | J36: =IFERROR(J31/I31-1,"") -> 0.246051 | K36: =IFERROR(K31/J31-1,"") -> 0.14528486 | ... Q36: =IFERROR(Q31/P31-1,"") -> 0.2366927

Sheet Vertical & Services
A1: Vertical and Service Mix
A2: Revenue absolutes are calculated from reported / forecast mix; taxonomy changes remain visible
A5: Metric | B5: Units | C5: FY16A | D5: FY17A | E5: FY18A | F5: FY19A | G5: FY20A | H5: FY21A | I5: FY22A | J5: FY23A | K5: FY24A | L5: FY25A | M5: FY26A | N5: FY27E | O5: FY28E | P5: FY29E | Q5: FY30E
A7: Industry verticals
A8: BFS mix | B8: % | C8: ='Raw Operating'!C11 -> 0.17 | D8: ='Raw Operating'!D11 -> 0.19 | E8: ='Raw Operating'!E11 -> 0.17 | F8: ='Raw Operating'!F11 -> 0.16 | G8: ='Raw Operating'!G11 -> 0.16 | H8: ='Raw Operating'!H11 -> 0.17 | I8: ='Raw Operating'!I11 -> 0.255 | J8: ='Raw Operating'!J11 -> 0.307 | ... M8: ='Raw Operating'!M11 -> 0.265 | N8: =M8 -> 0.265 | O8: =N8 -> 0.265 | P8: =O8 -> 0.265 | Q8: =P8 -> 0.265
A9: BFS revenue | B9: ₹m | C9: =IF(C8="","",C8*'Annual P&L'!C7) -> 4560.0883 | D9: =IF(D8="","",D8*'Annual P&L'!D7) -> 5323.99 | E9: =IF(E8="","",E8*'Annual P&L'!E7) -> 5085.38 | F9: =IF(F8="","",F8*'Annual P&L'!F7) -> 5881.92 | G9: =IF(G8="","",G8*'Annual P&L'!G7) -> 6694.24 | H9: =IF(H8="","",H8*'Annual P&L'!H7) -> 7926.76 | I9: =IF(I8="","",I8*'Annual P&L'!I7) -> 16401.6 | J9: =IF(J8="","",J8*'Annual P&L'!J7) -> 24604.822 | ... Q9: =IF(Q8="","",Q8*'Annual P&L'!Q7) -> 121131.9
A10: Insurance mix | B10: % | C10: ='Raw Operating'!C12 -> 0.21 | D10: ='Raw Operating'!D12 -> 0.23 | E10: ='Raw Operating'!E12 -> 0.26 | F10: ='Raw Operating'!F12 -> 0.29 | G10: ='Raw Operating'!G12 -> 0.3 | H10: ='Raw Operating'!H12 -> 0.32 | I10: ='Raw Operating'!I12 -> 0.283 | J10: ='Raw Operating'!J12 -> 0.226 | ... M10: ='Raw Operating'!M12 -> 0.15 | N10: =M10 -> 0.15 | O10: =N10 -> 0.15 | P10: =O10 -> 0.15 | Q10: =P10 -> 0.15
A11: Insurance revenue | B11: ₹m | C11: =IF(C10="","",C10*'Annual P&L'!C7) -> 5633.0502 | D11: =IF(D10="","",D10*'Annual P&L'!D7) -> 6444.83 | E11: =IF(E10="","",E10*'Annual P&L'!E7) -> 7777.64 | F11: =IF(F10="","",F10*'Annual P&L'!F7) -> 10660.98 | G11: =IF(G10="","",G10*'Annual P&L'!G7) -> 12551.7 | H11: =IF(H10="","",H10*'Annual P&L'!H7) -> 14920.96 | I11: =IF(I10="","",I10*'Annual P&L'!I7) -> 18202.56 | J11: =IF(J10="","",J10*'Annual P&L'!J7) -> 18112.996 | ... Q11: =IF(Q10="","",Q10*'Annual P&L'!Q7) -> 68565.228
A12: Travel, Transport & Hospitality mix | B12: % | C12: ='Raw Operating'!C13 -> 0.35 | D12: ='Raw Operating'!D13 -> 0.32 | E12: ='Raw Operating'!E13 -> 0.27 | F12: ='Raw Operating'!F13 -> 0.27 | G12: ='Raw Operating'!G13 -> 0.28 | H12: ='Raw Operating'!H13 -> 0.19 | I12: ='Raw Operating'!I13 -> 0.19 | J12: ='Raw Operating'!J13 -> 0.191 | ... M12: ='Raw Operating'!M13 -> 0.23 | N12: =M12 -> 0.23 | O12: =N12 -> 0.23 | P12: =O12 -> 0.23 | Q12: =P12 -> 0.23
A13: Travel, Transport & Hospitality revenue | B13: ₹m | C13: =IF(C12="","",C12*'Annual P&L'!C7) -> 9388.4171 | D13: =IF(D12="","",D12*'Annual P&L'!D7) -> 8966.72 | E13: =IF(E12="","",E12*'Annual P&L'!E7) -> 8076.78 | F13: =IF(F12="","",F12*'Annual P&L'!F7) -> 9925.74 | G13: =IF(G12="","",G12*'Annual P&L'!G7) -> 11714.92 | H13: =IF(H12="","",H12*'Annual P&L'!H7) -> 8859.32 | I13: =IF(I12="","",I12*'Annual P&L'!I7) -> 12220.8 | J13: =IF(J12="","",J12*'Annual P&L'!J7) -> 15307.886 | ... Q13: =IF(Q12="","",Q12*'Annual P&L'!Q7) -> 105133.35
A14: Healthcare & HiTech mix | B14: % | C14: ='Raw Operating'!C15 -> 0 | D14: ='Raw Operating'!D15 -> 0 | E14: ='Raw Operating'!E15 -> 0 | F14: ='Raw Operating'!F15 -> 0 | G14: ='Raw Operating'!G15 -> 0 | H14: ='Raw Operating'!H15 -> 0 | I14: ='Raw Operating'!I15 -> 0 | J14: ='Raw Operating'!J15 -> 0 | ... M14: ='Raw Operating'!M15 -> 0.108 | N14: =M14 -> 0.108 | O14: =N14 -> 0.108 | P14: =O14 -> 0.108 | Q14: =P14 -> 0.108
A15: Healthcare & HiTech revenue | B15: ₹m | C15: =IF(C14="","",C14*'Annual P&L'!C7) -> 0 | D15: =IF(D14="","",D14*'Annual P&L'!D7) -> 0 | E15: =IF(E14="","",E14*'Annual P&L'!E7) -> 0 | F15: =IF(F14="","",F14*'Annual P&L'!F7) -> 0 | G15: =IF(G14="","",G14*'Annual P&L'!G7) -> 0 | H15: =IF(H14="","",H14*'Annual P&L'!H7) -> 0 | I15: =IF(I14="","",I14*'Annual P&L'!I7) -> 0 | J15: =IF(J14="","",J14*'Annual P&L'!J7) -> 0 | ... Q15: =IF(Q14="","",Q14*'Annual P&L'!Q7) -> 49366.964
A16: Government outside India mix | B16: % | C16: ='Raw Operating'!C14 -> 0.04 | D16: ='Raw Operating'!D14 -> 0.03 | E16: ='Raw Operating'!E14 -> 0.01 | F16: ='Raw Operating'!F14 -> 0 | G16: ='Raw Operating'!G14 -> 0 | H16: ='Raw Operating'!H14 -> 0 | I16: ='Raw Operating'!I14 -> 0 | J16: ='Raw Operating'!J14 -> 0 | ... M16: ='Raw Operating'!M14 -> 0.07 | N16: =M16 -> 0.07 | O16: =N16 -> 0.07 | P16: =O16 -> 0.07 | Q16: =P16 -> 0.07
A17: Government outside India revenue | B17: ₹m | C17: =IF(C16="","",C16*'Annual P&L'!C7) -> 1072.962 | D17: =IF(D16="","",D16*'Annual P&L'!D7) -> 840.63 | E17: =IF(E16="","",E16*'Annual P&L'!E7) -> 299.14 | F17: =IF(F16="","",F16*'Annual P&L'!F7) -> 0 | G17: =IF(G16="","",G16*'Annual P&L'!G7) -> 0 | H17: =IF(H16="","",H16*'Annual P&L'!H7) -> 0 | I17: =IF(I16="","",I16*'Annual P&L'!I7) -> 0 | J17: =IF(J16="","",J16*'Annual P&L'!J7) -> 0 | ... Q17: =IF(Q16="","",Q16*'Annual P&L'!Q7) -> 31997.107
A18: Manufacturing mix | B18: % | C18: ='Raw Operating'!C16 -> 0.08 | D18: ='Raw Operating'!D16 -> 0 | E18: ='Raw Operating'!E16 -> 0 | F18: ='Raw Operating'!F16 -> 0 | G18: ='Raw Operating'!G16 -> 0 | H18: ='Raw Operating'!H16 -> 0 | I18: ='Raw Operating'!I16 -> 0 | J18: ='Raw Operating'!J16 -> 0 | ... M18: ='Raw Operating'!M16 -> 0 | N18: =M18 -> 0 | O18: =N18 -> 0 | P18: =O18 -> 0 | Q18: =P18 -> 0
A19: Manufacturing revenue | B19: ₹m | C19: =IF(C18="","",C18*'Annual P&L'!C7) -> 2145.9239 | D19: =IF(D18="","",D18*'Annual P&L'!D7) -> 0 | E19: =IF(E18="","",E18*'Annual P&L'!E7) -> 0 | F19: =IF(F18="","",F18*'Annual P&L'!F7) -> 0 | G19: =IF(G18="","",G18*'Annual P&L'!G7) -> 0 | H19: =IF(H18="","",H18*'Annual P&L'!H7) -> 0 | I19: =IF(I18="","",I18*'Annual P&L'!I7) -> 0 | J19: =IF(J18="","",J18*'Annual P&L'!J7) -> 0 | ... Q19: =IF(Q18="","",Q18*'Annual P&L'!Q7) -> 0
A20: Others mix | B20: % | C20: ='Raw Operating'!C17 -> 0.15 | D20: ='Raw Operating'!D17 -> 0 | E20: ='Raw Operating'!E17 -> 0 | F20: ='Raw Operating'!F17 -> 0.28 | G20: ='Raw Operating'!G17 -> 0.26 | H20: ='Raw Operating'!H17 -> 0.31 | I20: ='Raw Operating'!I17 -> 0 | J20: ='Raw Operating'!J17 -> 0.275 | ... M20: ='Raw Operating'!M17 -> 0.177 | N20: =M20 -> 0.177 | O20: =N20 -> 0.177 | P20: =O20 -> 0.177 | Q20: =P20 -> 0.177
A21: Others revenue | B21: ₹m | C21: =IF(C20="","",C20*'Annual P&L'!C7) -> 4023.6073 | D21: =IF(D20="","",D20*'Annual P&L'!D7) -> 0 | E21: =IF(E20="","",E20*'Annual P&L'!E7) -> 0 | F21: =IF(F20="","",F20*'Annual P&L'!F7) -> 10293.36 | G21: =IF(G20="","",G20*'Annual P&L'!G7) -> 10878.14 | H21: =IF(H20="","",H20*'Annual P&L'!H7) -> 14454.68 | I21: =IF(I20="","",I20*'Annual P&L'!I7) -> 0 | J21: =IF(J20="","",J20*'Annual P&L'!J7) -> 22040.15 | ... Q21: =IF(Q20="","",Q20*'Annual P&L'!Q7) -> 80906.969
A22: Mix check | B22: % | C22: =IF(COUNT(C8,C10,C12,C14,C16,C18,C20)=0,"",SUM(C8,C10,C12,C14,C16,C18,C20)) -> 1 | D22: =IF(COUNT(D8,D10,D12,D14,D16,D18,D20)=0,"",SUM(D8,D10,D12,D14,D16,D18,D20)) -> 0.77 | E22: =IF(COUNT(E8,E10,E12,E14,E16,E18,E20)=0,"",SUM(E8,E10,E12,E14,E16,E18,E20)) -> 0.71 | F22: =IF(COUNT(F8,F10,F12,F14,F16,F18,F20)=0,"",SUM(F8,F10,F12,F14,F16,F18,F20)) -> 1 | G22: =IF(COUNT(G8,G10,G12,G14,G16,G18,G20)=0,"",SUM(G8,G10,G12,G14,G16,G18,G20)) -> 1 | H22: =IF(COUNT(H8,H10,H12,H14,H16,H18,H20)=0,"",SUM(H8,H10,H12,H14,H16,H18,H20)) -> 0.99 | I22: =IF(COUNT(I8,I10,I12,I14,I16,I18,I20)=0,"",SUM(I8,I10,I12,I14,I16,I18,I20)) -> 0.728 | J22: =IF(COUNT(J8,J10,J12,J14,J16,J18,J20)=0,"",SUM(J8,J10,J12,J14,J16,J18,J20)) -> 0.999 | ... Q22: =IF(COUNT(Q8,Q10,Q12,Q14,Q16,Q18,Q20)=0,"",SUM(Q8,Q10,Q12,Q14,Q16,Q18,Q20)) -> 1
A23: Calculated vertical revenue | B23: ₹m | C23: =SUM(C9,C11,C13,C15,C17,C19,C21) -> 26824.049 | D23: =SUM(D9,D11,D13,D15,D17,D19,D21) -> 21576.17 | E23: =SUM(E9,E11,E13,E15,E17,E19,E21) -> 21238.94 | F23: =SUM(F9,F11,F13,F15,F17,F19,F21) -> 36762 | G23: =SUM(G9,G11,G13,G15,G17,G19,G21) -> 41839 | H23: =SUM(H9,H11,H13,H15,H17,H19,H21) -> 46161.72 | I23: =SUM(I9,I11,I13,I15,I17,I19,I21) -> 46824.96 | J23: =SUM(J9,J11,J13,J15,J17,J19,J21) -> 80065.854 | ... Q23: =SUM(Q9,Q11,Q13,Q15,Q17,Q19,Q21) -> 457101.52
A24: Annual revenue | B24: ₹m | C24: ='Annual P&L'!C7 -> 26824.049 | D24: ='Annual P&L'!D7 -> 28021 | E24: ='Annual P&L'!E7 -> 29914 | F24: ='Annual P&L'!F7 -> 36762 | G24: ='Annual P&L'!G7 -> 41839 | H24: ='Annual P&L'!H7 -> 46628 | I24: ='Annual P&L'!I7 -> 64320 | J24: ='Annual P&L'!J7 -> 80146 | ... Q24: ='Annual P&L'!Q7 -> 457101.52
A25: Revenue check | B25: ₹m | C25: =IF(C22="","",C23-C24) -> 0 | D25: =IF(D22="","",D23-D24) -> -6444.83 | E25: =IF(E22="","",E23-E24) -> -8675.06 | F25: =IF(F22="","",F23-F24) -> 0 | G25: =IF(G22="","",G23-G24) -> 0 | H25: =IF(H22="","",H23-H24) -> -466.28 | I25: =IF(I22="","",I23-I24) -> -17495.04 | J25: =IF(J22="","",J23-J24) -> -80.146 | ... Q25: =IF(Q22="","",Q23-Q24) -> 5.8207661e-11
A28: Service lines — disclosed taxonomy
A29: AI-led Engineering / Engineering mix | B29: % | C29: ='Raw Operating'!C30 -> 0 | D29: ='Raw Operating'!D30 -> 0 | E29: ='Raw Operating'!E30 -> 0 | F29: ='Raw Operating'!F30 -> 0 | G29: ='Raw Operating'!G30 -> 0 | H29: ='Raw Operating'!H30 -> 0 | I29: ='Raw Operating'!I30 -> 0 | J29: ='Raw Operating'!J30 -> 0.363 | ... M29: ='Raw Operating'!M30 -> 0.441 | N29: =M29 -> 0.441 | O29: =N29 -> 0.441 | P29: =O29 -> 0.441 | Q29: =P29 -> 0.441
A30: AI-led Engineering / Engineering revenue | B30: ₹m | C30: =IF(C29="","",C29*'Annual P&L'!C7) -> 0 | D30: =IF(D29="","",D29*'Annual P&L'!D7) -> 0 | E30: =IF(E29="","",E29*'Annual P&L'!E7) -> 0 | F30: =IF(F29="","",F29*'Annual P&L'!F7) -> 0 | G30: =IF(G29="","",G29*'Annual P&L'!G7) -> 0 | H30: =IF(H29="","",H29*'Annual P&L'!H7) -> 0 | I30: =IF(I29="","",I29*'Annual P&L'!I7) -> 0 | J30: =IF(J29="","",J29*'Annual P&L'!J7) -> 29092.998 | ... Q30: =IF(Q29="","",Q29*'Annual P&L'!Q7) -> 201581.77
A31: Intelligent Automation mix | B31: % | C31: ='Raw Operating'!C31 -> 0 | D31: ='Raw Operating'!D31 -> 0 | E31: ='Raw Operating'!E31 -> 0 | F31: ='Raw Operating'!F31 -> 0 | G31: ='Raw Operating'!G31 -> 0 | H31: ='Raw Operating'!H31 -> 0.15 | I31: ='Raw Operating'!I31 -> 0.138 | J31: ='Raw Operating'!J31 -> 0.12 | ... M31: ='Raw Operating'!M31 -> 0.082 | N31: =M31 -> 0.082 | O31: =N31 -> 0.082 | P31: =O31 -> 0.082 | Q31: =P31 -> 0.082
A32: Intelligent Automation revenue | B32: ₹m | C32: =IF(C31="","",C31*'Annual P&L'!C7) -> 0 | D32: =IF(D31="","",D31*'Annual P&L'!D7) -> 0 | E32: =IF(E31="","",E31*'Annual P&L'!E7) -> 0 | F32: =IF(F31="","",F31*'Annual P&L'!F7) -> 0 | G32: =IF(G31="","",G31*'Annual P&L'!G7) -> 0 | H32: =IF(H31="","",H31*'Annual P&L'!H7) -> 6994.2 | I32: =IF(I31="","",I31*'Annual P&L'!I7) -> 8876.16 | J32: =IF(J31="","",J31*'Annual P&L'!J7) -> 9617.52 | ... Q32: =IF(Q31="","",Q31*'Annual P&L'!Q7) -> 37482.325
A33: Data mix | B33: % | C33: ='Raw Operating'!C32 -> 0 | D33: ='Raw Operating'!D32 -> 0 | E33: ='Raw Operating'!E32 -> 0 | F33: ='Raw Operating'!F32 -> 0 | G33: ='Raw Operating'!G32 -> 0 | H33: ='Raw Operating'!H32 -> 0 | I33: ='Raw Operating'!I32 -> 0.208 | J33: ='Raw Operating'!J32 -> 0.235 | ... M33: ='Raw Operating'!M32 -> 0.215 | N33: =M33 -> 0.215 | O33: =N33 -> 0.215 | P33: =O33 -> 0.215 | Q33: =P33 -> 0.215
A34: Data revenue | B34: ₹m | C34: =IF(C33="","",C33*'Annual P&L'!C7) -> 0 | D34: =IF(D33="","",D33*'Annual P&L'!D7) -> 0 | E34: =IF(E33="","",E33*'Annual P&L'!E7) -> 0 | F34: =IF(F33="","",F33*'Annual P&L'!F7) -> 0 | G34: =IF(G33="","",G33*'Annual P&L'!G7) -> 0 | H34: =IF(H33="","",H33*'Annual P&L'!H7) -> 0 | I34: =IF(I33="","",I33*'Annual P&L'!I7) -> 13378.56 | J34: =IF(J33="","",J33*'Annual P&L'!J7) -> 18834.31 | ... Q34: =IF(Q33="","",Q33*'Annual P&L'!Q7) -> 98276.827
A35: Cloud mix | B35: % | C35: ='Raw Operating'!C33 -> 0 | D35: ='Raw Operating'!D33 -> 0 | E35: ='Raw Operating'!E33 -> 0 | F35: ='Raw Operating'!F33 -> 0 | G35: ='Raw Operating'!G33 -> 0 | H35: ='Raw Operating'!H33 -> 0 | I35: ='Raw Operating'!I33 -> 0.179 | J35: ='Raw Operating'!J33 -> 0.183 | ... M35: ='Raw Operating'!M33 -> 0.184 | N35: =M35 -> 0.184 | O35: =N35 -> 0.184 | P35: =O35 -> 0.184 | Q35: =P35 -> 0.184
A36: Cloud revenue | B36: ₹m | C36: =IF(C35="","",C35*'Annual P&L'!C7) -> 0 | D36: =IF(D35="","",D35*'Annual P&L'!D7) -> 0 | E36: =IF(E35="","",E35*'Annual P&L'!E7) -> 0 | F36: =IF(F35="","",F35*'Annual P&L'!F7) -> 0 | G36: =IF(G35="","",G35*'Annual P&L'!G7) -> 0 | H36: =IF(H35="","",H35*'Annual P&L'!H7) -> 0 | I36: =IF(I35="","",I35*'Annual P&L'!I7) -> 11513.28 | J36: =IF(J35="","",J35*'Annual P&L'!J7) -> 14666.718 | ... Q36: =IF(Q35="","",Q35*'Annual P&L'!Q7) -> 84106.68
A37: BPM mix | B37: % | C37: ='Raw Operating'!C34 -> 0.05 | D37: ='Raw Operating'!D34 -> 0.05 | E37: ='Raw Operating'!E34 -> 0.04 | F37: ='Raw Operating'!F34 -> 0.04 | G37: ='Raw Operating'!G34 -> 0.03 | H37: ='Raw Operating'!H34 -> 0.03 | I37: ='Raw Operating'!I34 -> 0.107 | J37: ='Raw Operating'!J34 -> 0.099 | ... M37: ='Raw Operating'!M34 -> 0.079 | N37: =M37 -> 0.079 | O37: =N37 -> 0.079 | P37: =O37 -> 0.079 | Q37: =P37 -> 0.079
A38: BPM revenue | B38: ₹m | C38: =IF(C37="","",C37*'Annual P&L'!C7) -> 1341.2024 | D38: =IF(D37="","",D37*'Annual P&L'!D7) -> 1401.05 | E38: =IF(E37="","",E37*'Annual P&L'!E7) -> 1196.56 | F38: =IF(F37="","",F37*'Annual P&L'!F7) -> 1470.48 | G38: =IF(G37="","",G37*'Annual P&L'!G7) -> 1255.17 | H38: =IF(H37="","",H37*'Annual P&L'!H7) -> 1398.84 | I38: =IF(I37="","",I37*'Annual P&L'!I7) -> 6882.24 | J38: =IF(J37="","",J37*'Annual P&L'!J7) -> 7934.454 | ... Q38: =IF(Q37="","",Q37*'Annual P&L'!Q7) -> 36111.02
A39: Service mix check | B39: % | C39: =IF(COUNT(C29,C31,C33,C35,C37)=0,"",SUM(C29,C31,C33,C35,C37)) -> 0.05 | D39: =IF(COUNT(D29,D31,D33,D35,D37)=0,"",SUM(D29,D31,D33,D35,D37)) -> 0.05 | E39: =IF(COUNT(E29,E31,E33,E35,E37)=0,"",SUM(E29,E31,E33,E35,E37)) -> 0.04 | F39: =IF(COUNT(F29,F31,F33,F35,F37)=0,"",SUM(F29,F31,F33,F35,F37)) -> 0.04 | G39: =IF(COUNT(G29,G31,G33,G35,G37)=0,"",SUM(G29,G31,G33,G35,G37)) -> 0.03 | H39: =IF(COUNT(H29,H31,H33,H35,H37)=0,"",SUM(H29,H31,H33,H35,H37)) -> 0.18 | I39: =IF(COUNT(I29,I31,I33,I35,I37)=0,"",SUM(I29,I31,I33,I35,I37)) -> 0.632 | J39: =IF(COUNT(J29,J31,J33,J35,J37)=0,"",SUM(J29,J31,J33,J35,J37)) -> 1 | ... Q39: =IF(COUNT(Q29,Q31,Q33,Q35,Q37)=0,"",SUM(Q29,Q31,Q33,Q35,Q37)) -> 1.001
A40: Calculated service revenue | B40: ₹m | C40: =SUM(C30,C32,C34,C36,C38) -> 1341.2024 | D40: =SUM(D30,D32,D34,D36,D38) -> 1401.05 | E40: =SUM(E30,E32,E34,E36,E38) -> 1196.56 | F40: =SUM(F30,F32,F34,F36,F38) -> 1470.48 | G40: =SUM(G30,G32,G34,G36,G38) -> 1255.17 | H40: =SUM(H30,H32,H34,H36,H38) -> 8393.04 | I40: =SUM(I30,I32,I34,I36,I38) -> 40650.24 | J40: =SUM(J30,J32,J34,J36,J38) -> 80146 | ... Q40: =SUM(Q30,Q32,Q34,Q36,Q38) -> 457558.62
A41: Annual revenue | B41: ₹m | C41: ='Annual P&L'!C7 -> 26824.049 | D41: ='Annual P&L'!D7 -> 28021 | E41: ='Annual P&L'!E7 -> 29914 | F41: ='Annual P&L'!F7 -> 36762 | G41: ='Annual P&L'!G7 -> 41839 | H41: ='Annual P&L'!H7 -> 46628 | I41: ='Annual P&L'!I7 -> 64320 | J41: ='Annual P&L'!J7 -> 80146 | ... Q41: ='Annual P&L'!Q7 -> 457101.52
A42: Revenue check | B42: ₹m | C42: =IF(C39="","",C40-C41) -> -25482.846 | D42: =IF(D39="","",D40-D41) -> -26619.95 | E42: =IF(E39="","",E40-E41) -> -28717.44 | F42: =IF(F39="","",F40-F41) -> -35291.52 | G42: =IF(G39="","",G40-G41) -> -40583.83 | H42: =IF(H39="","",H40-H41) -> -38234.96 | I42: =IF(I39="","",I40-I41) -> -23669.76 | J42: =IF(J39="","",J40-J41) -> -1.4551915e-11 | ... Q42: =IF(Q39="","",Q40-Q41) -> 457.10152
A43: Important AI note | B43: text | C43: “AI-led Engineering” is a company service classification, not disclosed pure AI revenue; incremental AI revenue is modeled only in People & AI / Order Book & Revenue.

Sheet Geography & Delivery
A1: Geography, Delivery and Contract Mix
A2: Revenue is calculated from mix; delivery / contract mix drives the AI deflation and outcome-pricing scenario
A5: Metric | B5: Units | C5: FY16A | D5: FY17A | E5: FY18A | F5: FY19A | G5: FY20A | H5: FY21A | I5: FY22A | J5: FY23A | K5: FY24A | L5: FY25A | M5: FY26A | N5: FY27E | O5: FY28E | P5: FY29E | Q5: FY30E
A7: Americas mix | B7: % | C7: ='Raw Operating'!C18 -> 0.46 | D7: ='Raw Operating'!D18 -> 0.48 | E7: ='Raw Operating'!E18 -> 0.49 | F7: ='Raw Operating'!F18 -> 0.49 | G7: ='Raw Operating'!G18 -> 0.48 | H7: ='Raw Operating'!H18 -> 0.48 | I7: ='Raw Operating'!I18 -> 0.518 | J7: ='Raw Operating'!J18 -> 0.499 | ... M7: ='Raw Operating'!M18 -> 0.569 | N7: =M7 -> 0.569 | O7: =N7 -> 0.569 | P7: =O7 -> 0.569 | Q7: =P7 -> 0.569
A8: Americas revenue | B8: ₹m | C8: =IF(C7="","",C7*'Annual P&L'!C7) -> 12339.062 | D8: =IF(D7="","",D7*'Annual P&L'!D7) -> 13450.08 | E8: =IF(E7="","",E7*'Annual P&L'!E7) -> 14657.86 | F8: =IF(F7="","",F7*'Annual P&L'!F7) -> 18013.38 | G8: =IF(G7="","",G7*'Annual P&L'!G7) -> 20082.72 | H8: =IF(H7="","",H7*'Annual P&L'!H7) -> 22381.44 | I8: =IF(I7="","",I7*'Annual P&L'!I7) -> 33317.76 | J8: =IF(J7="","",J7*'Annual P&L'!J7) -> 39992.854 | ... Q8: =IF(Q7="","",Q7*'Annual P&L'!Q7) -> 260090.77
A9: EMEA mix | B9: % | C9: ='Raw Operating'!C19 -> 0.34 | D9: ='Raw Operating'!D19 -> 0.33 | E9: ='Raw Operating'!E19 -> 0.31 | F9: ='Raw Operating'!F19 -> 0.33 | G9: ='Raw Operating'!G19 -> 0.37 | H9: ='Raw Operating'!H19 -> 0.37 | I9: ='Raw Operating'!I19 -> 0.354 | J9: ='Raw Operating'!J19 -> 0.389 | ... M9: ='Raw Operating'!M19 -> 0.289 | N9: =M9 -> 0.289 | O9: =N9 -> 0.289 | P9: =O9 -> 0.289 | Q9: =P9 -> 0.289
A10: EMEA revenue | B10: ₹m | C10: =IF(C9="","",C9*'Annual P&L'!C7) -> 9120.1766 | D10: =IF(D9="","",D9*'Annual P&L'!D7) -> 9246.93 | E10: =IF(E9="","",E9*'Annual P&L'!E7) -> 9273.34 | F10: =IF(F9="","",F9*'Annual P&L'!F7) -> 12131.46 | G10: =IF(G9="","",G9*'Annual P&L'!G7) -> 15480.43 | H10: =IF(H9="","",H9*'Annual P&L'!H7) -> 17252.36 | I10: =IF(I9="","",I9*'Annual P&L'!I7) -> 22769.28 | J10: =IF(J9="","",J9*'Annual P&L'!J7) -> 31176.794 | ... Q10: =IF(Q9="","",Q9*'Annual P&L'!Q7) -> 132102.34
A11: Rest of World mix | B11: % | C11: ='Raw Operating'!C20 -> 0.2 | D11: ='Raw Operating'!D20 -> 0.19 | E11: ='Raw Operating'!E20 -> 0.2 | F11: ='Raw Operating'!F20 -> 0.18 | G11: ='Raw Operating'!G20 -> 0.15 | H11: ='Raw Operating'!H20 -> 0.15 | I11: ='Raw Operating'!I20 -> 0.128 | J11: ='Raw Operating'!J20 -> 0.112 | ... M11: ='Raw Operating'!M20 -> 0.142 | N11: =M11 -> 0.142 | O11: =N11 -> 0.142 | P11: =O11 -> 0.142 | Q11: =P11 -> 0.142
A12: Rest of World revenue | B12: ₹m | C12: =IF(C11="","",C11*'Annual P&L'!C7) -> 5364.8098 | D12: =IF(D11="","",D11*'Annual P&L'!D7) -> 5323.99 | E12: =IF(E11="","",E11*'Annual P&L'!E7) -> 5982.8 | F12: =IF(F11="","",F11*'Annual P&L'!F7) -> 6617.16 | G12: =IF(G11="","",G11*'Annual P&L'!G7) -> 6275.85 | H12: =IF(H11="","",H11*'Annual P&L'!H7) -> 6994.2 | I12: =IF(I11="","",I11*'Annual P&L'!I7) -> 8232.96 | J12: =IF(J11="","",J11*'Annual P&L'!J7) -> 8976.352 | ... Q12: =IF(Q11="","",Q11*'Annual P&L'!Q7) -> 64908.416
A13: Geography mix check | B13: % | C13: =IF(COUNT(C7,C9,C11)=0,"",SUM(C7,C9,C11)) -> 1 | D13: =IF(COUNT(D7,D9,D11)=0,"",SUM(D7,D9,D11)) -> 1 | E13: =IF(COUNT(E7,E9,E11)=0,"",SUM(E7,E9,E11)) -> 1 | F13: =IF(COUNT(F7,F9,F11)=0,"",SUM(F7,F9,F11)) -> 1 | G13: =IF(COUNT(G7,G9,G11)=0,"",SUM(G7,G9,G11)) -> 1 | H13: =IF(COUNT(H7,H9,H11)=0,"",SUM(H7,H9,H11)) -> 1 | I13: =IF(COUNT(I7,I9,I11)=0,"",SUM(I7,I9,I11)) -> 1 | J13: =IF(COUNT(J7,J9,J11)=0,"",SUM(J7,J9,J11)) -> 1 | ... Q13: =IF(COUNT(Q7,Q9,Q11)=0,"",SUM(Q7,Q9,Q11)) -> 1
A14: Onsite mix | B14: % | C14: ='Raw Operating'!C21 -> 0.59 | D14: ='Raw Operating'!D21 -> 0.6 | E14: ='Raw Operating'!E21 -> 0.61 | F14: ='Raw Operating'!F21 -> 0.65 | G14: ='Raw Operating'!G21 -> 0.64 | H14: ='Raw Operating'!H21 -> 0.62 | I14: ='Raw Operating'!I21 -> 0.56 | J14: ='Raw Operating'!J21 -> 0.501 | ... M14: ='Raw Operating'!M21 -> 0.476 | N14: =M14 -> 0.476 | O14: =N14 -> 0.476 | P14: =O14 -> 0.476 | Q14: =P14 -> 0.476
A15: Offshore mix | B15: % | C15: ='Raw Operating'!C22 -> 0.41 | D15: ='Raw Operating'!D22 -> 0.4 | E15: ='Raw Operating'!E22 -> 0.39 | F15: ='Raw Operating'!F22 -> 0.35 | G15: ='Raw Operating'!G22 -> 0.36 | H15: ='Raw Operating'!H22 -> 0.38 | I15: ='Raw Operating'!I22 -> 0.44 | J15: ='Raw Operating'!J22 -> 0.499 | ... M15: ='Raw Operating'!M22 -> 0.524 | N15: =1-N14 -> 0.524 | O15: =1-O14 -> 0.524 | P15: =1-P14 -> 0.524 | Q15: =1-Q14 -> 0.524
A16: Delivery mix check | B16: % | C16: =IF(COUNT(C14:C15)=0,"",SUM(C14:C15)) -> 1 | D16: =IF(COUNT(D14:D15)=0,"",SUM(D14:D15)) -> 1 | E16: =IF(COUNT(E14:E15)=0,"",SUM(E14:E15)) -> 1 | F16: =IF(COUNT(F14:F15)=0,"",SUM(F14:F15)) -> 1 | G16: =IF(COUNT(G14:G15)=0,"",SUM(G14:G15)) -> 1 | H16: =IF(COUNT(H14:H15)=0,"",SUM(H14:H15)) -> 1 | I16: =IF(COUNT(I14:I15)=0,"",SUM(I14:I15)) -> 1 | J16: =IF(COUNT(J14:J15)=0,"",SUM(J14:J15)) -> 1 | ... Q16: =IF(COUNT(Q14:Q15)=0,"",SUM(Q14:Q15)) -> 1
A17: Fixed-price mix | B17: % | C17: ='Raw Operating'!C23 -> 0.45 | D17: ='Raw Operating'!D23 -> 0.48 | E17: ='Raw Operating'!E23 -> 0.46 | F17: ='Raw Operating'!F23 -> 0.47 | G17: ='Raw Operating'!G23 -> 0.48 | H17: ='Raw Operating'!H23 -> 0.54 | I17: ='Raw Operating'!I23 -> 0.54 | J17: ='Raw Operating'!J23 -> 0.52 | ... M17: ='Raw Operating'!M23 -> 0.469 | N17: =1-N18 -> 0.43 | O17: =1-O18 -> 0.44 | P17: =1-P18 -> 0.45 | Q17: =1-Q18 -> 0.46
A18: T&M mix | B18: % | C18: ='Raw Operating'!C24 -> 0.55 | D18: ='Raw Operating'!D24 -> 0.52 | E18: ='Raw Operating'!E24 -> 0.54 | F18: ='Raw Operating'!F24 -> 0.53 | G18: ='Raw Operating'!G24 -> 0.52 | H18: ='Raw Operating'!H24 -> 0.46 | I18: ='Raw Operating'!I24 -> 0.46 | J18: ='Raw Operating'!J24 -> 0.48 | ... M18: ='Raw Operating'!M24 -> 0.531 | N18: =Assumptions!C12 -> 0.57 | O18: =Assumptions!D12 -> 0.56 | P18: =Assumptions!E12 -> 0.55 | Q18: =Assumptions!F12 -> 0.54
A19: Contract mix check | B19: % | C19: =IF(COUNT(C17:C18)=0,"",SUM(C17:C18)) -> 1 | D19: =IF(COUNT(D17:D18)=0,"",SUM(D17:D18)) -> 1 | E19: =IF(COUNT(E17:E18)=0,"",SUM(E17:E18)) -> 1 | F19: =IF(COUNT(F17:F18)=0,"",SUM(F17:F18)) -> 1 | G19: =IF(COUNT(G17:G18)=0,"",SUM(G17:G18)) -> 1 | H19: =IF(COUNT(H17:H18)=0,"",SUM(H17:H18)) -> 1 | I19: =IF(COUNT(I17:I18)=0,"",SUM(I17:I18)) -> 1 | J19: =IF(COUNT(J17:J18)=0,"",SUM(J17:J18)) -> 1 | ... Q19: =IF(COUNT(Q17:Q18)=0,"",SUM(Q17:Q18)) -> 1
A20: T&M revenue | B20: ₹m | C20: =C18*'Annual P&L'!C7 -> 14753.227 | D20: =D18*'Annual P&L'!D7 -> 14570.92 | E20: =E18*'Annual P&L'!E7 -> 16153.56 | F20: =F18*'Annual P&L'!F7 -> 19483.86 | G20: =G18*'Annual P&L'!G7 -> 21756.28 | H20: =H18*'Annual P&L'!H7 -> 21448.88 | I20: =I18*'Annual P&L'!I7 -> 29587.2 | J20: =J18*'Annual P&L'!J7 -> 38470.08 | ... Q20: =Q18*'Annual P&L'!Q7 -> 246834.82
A21: Fixed / outcome revenue | B21: ₹m | C21: =C17*'Annual P&L'!C7 -> 12070.822 | D21: =D17*'Annual P&L'!D7 -> 13450.08 | E21: =E17*'Annual P&L'!E7 -> 13760.44 | F21: =F17*'Annual P&L'!F7 -> 17278.14 | G21: =G17*'Annual P&L'!G7 -> 20082.72 | H21: =H17*'Annual P&L'!H7 -> 25179.12 | I21: =I17*'Annual P&L'!I7 -> 34732.8 | J21: =J17*'Annual P&L'!J7 -> 41675.92 | ... Q21: =Q17*'Annual P&L'!Q7 -> 210266.7

Sheet Client Metrics
A1: Client Metrics
A2: Revenue-band disclosures, concentration, client farming and revenue per client
A5: Metric | B5: Units | C5: FY16A | D5: FY17A | E5: FY18A | F5: FY19A | G5: FY20A | H5: FY21A | I5: FY22A | J5: FY23A | K5: FY24A | L5: FY25A | M5: FY26A | N5: FY27E | O5: FY28E | P5: FY29E | Q5: FY30E
A7: Clients $1–5m | B7: # | C7: ='Raw Operating'!C53 -> 51 | D7: ='Raw Operating'!D53 -> 55 | E7: ='Raw Operating'!E53 -> 60 | F7: ='Raw Operating'!F53 -> 66 | G7: ='Raw Operating'!G53 -> 80 | H7: ='Raw Operating'!H53 -> 88 | I7: ='Raw Operating'!I53 -> 100 | J7: ='Raw Operating'!J53 -> 101 | ... M7: ='Raw Operating'!M53 -> 167 | N7: =ROUND(M7*(1+'Annual P&L'!N8),0) -> 233 | O7: =ROUND(N7*(1+'Annual P&L'!O8),0) -> 300 | P7: =ROUND(O7*(1+'Annual P&L'!P8),0) -> 377 | Q7: =ROUND(P7*(1+'Annual P&L'!Q8),0) -> 466
A8: Clients $5–10m | B8: # | C8: ='Raw Operating'!C54 -> 16 | D8: ='Raw Operating'!D54 -> 10 | E8: ='Raw Operating'!E54 -> 13 | F8: ='Raw Operating'!F54 -> 16 | G8: ='Raw Operating'!G54 -> 15 | H8: ='Raw Operating'!H54 -> 16 | I8: ='Raw Operating'!I54 -> 19 | J8: ='Raw Operating'!J54 -> 23 | ... M8: ='Raw Operating'!M54 -> 42 | N8: =ROUND(M8*(1+'Annual P&L'!N8),0) -> 59 | O8: =ROUND(N8*(1+'Annual P&L'!O8),0) -> 76 | P8: =ROUND(O8*(1+'Annual P&L'!P8),0) -> 96 | Q8: =ROUND(P8*(1+'Annual P&L'!Q8),0) -> 119
A9: Clients $10–20m | B9: # | C9: ='Raw Operating'!C55 -> 0 | D9: ='Raw Operating'!D55 -> 0 | E9: ='Raw Operating'!E55 -> 0 | F9: ='Raw Operating'!F55 -> 0 | G9: ='Raw Operating'!G55 -> 0 | H9: ='Raw Operating'!H55 -> 0 | I9: ='Raw Operating'!I55 -> 0 | J9: ='Raw Operating'!J55 -> 0 | ... M9: ='Raw Operating'!M55 -> 23 | N9: =ROUND(M9*(1+'Annual P&L'!N8),0) -> 32 | O9: =ROUND(N9*(1+'Annual P&L'!O8),0) -> 41 | P9: =ROUND(O9*(1+'Annual P&L'!P8),0) -> 52 | Q9: =ROUND(P9*(1+'Annual P&L'!Q8),0) -> 64
A10: Clients $20–50m | B10: # | C10: ='Raw Operating'!C56 -> 0 | D10: ='Raw Operating'!D56 -> 0 | E10: ='Raw Operating'!E56 -> 0 | F10: ='Raw Operating'!F56 -> 0 | G10: ='Raw Operating'!G56 -> 0 | H10: ='Raw Operating'!H56 -> 0 | I10: ='Raw Operating'!I56 -> 0 | J10: ='Raw Operating'!J56 -> 0 | ... M10: ='Raw Operating'!M56 -> 9 | N10: =ROUND(M10*(1+'Annual P&L'!N8),0) -> 13 | O10: =ROUND(N10*(1+'Annual P&L'!O8),0) -> 17 | P10: =ROUND(O10*(1+'Annual P&L'!P8),0) -> 21 | Q10: =ROUND(P10*(1+'Annual P&L'!Q8),0) -> 26
A11: Clients $50–100m | B11: # | C11: ='Raw Operating'!C57 -> 0 | D11: ='Raw Operating'!D57 -> 0 | E11: ='Raw Operating'!E57 -> 0 | F11: ='Raw Operating'!F57 -> 0 | G11: ='Raw Operating'!G57 -> 0 | H11: ='Raw Operating'!H57 -> 0 | I11: ='Raw Operating'!I57 -> 0 | J11: ='Raw Operating'!J57 -> 0 | ... M11: ='Raw Operating'!M57 -> 3 | N11: =ROUND(M11*(1+'Annual P&L'!N8),0) -> 4 | O11: =ROUND(N11*(1+'Annual P&L'!O8),0) -> 5 | P11: =ROUND(O11*(1+'Annual P&L'!P8),0) -> 6 | Q11: =ROUND(P11*(1+'Annual P&L'!Q8),0) -> 7
A12: Clients >$100m | B12: # | C12: ='Raw Operating'!C58 -> 0 | D12: ='Raw Operating'!D58 -> 0 | E12: ='Raw Operating'!E58 -> 0 | F12: ='Raw Operating'!F58 -> 0 | G12: ='Raw Operating'!G58 -> 0 | H12: ='Raw Operating'!H58 -> 0 | I12: ='Raw Operating'!I58 -> 0 | J12: ='Raw Operating'!J58 -> 0 | ... M12: ='Raw Operating'!M58 -> 1 | N12: =ROUND(M12*(1+'Annual P&L'!N8),0) -> 1 | O12: =ROUND(N12*(1+'Annual P&L'!O8),0) -> 1 | P12: =ROUND(O12*(1+'Annual P&L'!P8),0) -> 1 | Q12: =ROUND(P12*(1+'Annual P&L'!Q8),0) -> 1
A13: Clients >$10m | B13: # | C13: ='Raw Operating'!C59 -> 6 | D13: ='Raw Operating'!D59 -> 8 | E13: ='Raw Operating'!E59 -> 7 | F13: ='Raw Operating'!F59 -> 8 | G13: ='Raw Operating'!G59 -> 0 | H13: ='Raw Operating'!H59 -> 0 | I13: ='Raw Operating'!I59 -> 18 | J13: ='Raw Operating'!J59 -> 21 | ... M13: ='Raw Operating'!M59 -> 0 | N13: =ROUND(M13*(1+'Annual P&L'!N8),0) -> 0 | O13: =ROUND(N13*(1+'Annual P&L'!O8),0) -> 0 | P13: =ROUND(O13*(1+'Annual P&L'!P8),0) -> 0 | Q13: =ROUND(P13*(1+'Annual P&L'!Q8),0) -> 0
A14: Total disclosed band clients | B14: # | C14: =SUM(C7:C12) -> 67 | D14: =SUM(D7:D12) -> 65 | E14: =SUM(E7:E12) -> 73 | F14: =SUM(F7:F12) -> 82 | G14: =SUM(G7:G12) -> 95 | H14: =SUM(H7:H12) -> 104 | I14: =SUM(I7:I12) -> 119 | J14: =SUM(J7:J12) -> 124 | ... Q14: =SUM(Q7:Q12) -> 683
A15: Top 5 contribution | B15: % | C15: ='Raw Operating'!C26 -> 0.32 | D15: ='Raw Operating'!D26 -> 0.33 | E15: ='Raw Operating'!E26 -> 0.3 | F15: ='Raw Operating'!F26 -> 0.28 | G15: ='Raw Operating'!G26 -> 0.28 | H15: ='Raw Operating'!H26 -> 0.24 | I15: ='Raw Operating'!I26 -> 0.229 | J15: ='Raw Operating'!J26 -> 0.232 | ... M15: ='Raw Operating'!M26 -> 0.21 | N15: =M15 -> 0.21 | O15: =N15 -> 0.21 | P15: =O15 -> 0.21 | Q15: =P15 -> 0.21
A16: Top 10 contribution | B16: % | C16: ='Raw Operating'!C27 -> 0.44 | D16: ='Raw Operating'!D27 -> 0.45 | E16: ='Raw Operating'!E27 -> 0.42 | F16: ='Raw Operating'!F27 -> 0.39 | G16: ='Raw Operating'!G27 -> 0.38 | H16: ='Raw Operating'!H27 -> 0.34 | I16: ='Raw Operating'!I27 -> 0.34 | J16: ='Raw Operating'!J27 -> 0.355 | ... M16: ='Raw Operating'!M27 -> 0.308 | N16: =M16 -> 0.308 | O16: =N16 -> 0.308 | P16: =O16 -> 0.308 | Q16: =P16 -> 0.308
A17: Repeat business | B17: % | C17: ='Raw Operating'!C25 -> 0.91 | D17: ='Raw Operating'!D25 -> 0.91 | E17: ='Raw Operating'!E25 -> 0.89 | F17: ='Raw Operating'!F25 -> 0.9 | G17: ='Raw Operating'!G25 -> 0.89 | H17: ='Raw Operating'!H25 -> 0.89 | I17: ='Raw Operating'!I25 -> 0.93 | J17: ='Raw Operating'!J25 -> 0.92 | ... M17: ='Raw Operating'!M25 -> 0.955 | N17: =Assumptions!C6 -> 0.955 | O17: =Assumptions!D6 -> 0.957 | P17: =Assumptions!E6 -> 0.96 | Q17: =Assumptions!F6 -> 0.962
A18: New clients | B18: # | C18: ='Raw Operating'!C28 -> 28 | D18: ='Raw Operating'!D28 -> 15 | E18: ='Raw Operating'!E28 -> 31 | F18: ='Raw Operating'!F28 -> 40 | G18: ='Raw Operating'!G28 -> 41 | H18: ='Raw Operating'!H28 -> 45 | I18: ='Raw Operating'!I28 -> 47 | J18: ='Raw Operating'!J28 -> 44 | ... M18: ='Raw Operating'!M28 -> 31 | N18: =ROUND(M18*(1+'Annual P&L'!N8),0) -> 43 | O18: =ROUND(N18*(1+'Annual P&L'!O8),0) -> 55 | P18: =ROUND(O18*(1+'Annual P&L'!P8),0) -> 69 | Q18: =ROUND(P18*(1+'Annual P&L'!Q8),0) -> 85
A19: Revenue per disclosed client | B19: $m | C19: =IFERROR('Order Book & Revenue'!C33/C14,"") -> 0 | D19: =IFERROR('Order Book & Revenue'!D33/D14,"") -> 0 | E19: =IFERROR('Order Book & Revenue'!E33/E14,"") -> 0 | F19: =IFERROR('Order Book & Revenue'!F33/F14,"") -> 0 | G19: =IFERROR('Order Book & Revenue'!G33/G14,"") -> 0 | H19: =IFERROR('Order Book & Revenue'!H33/H14,"") -> 0 | I19: =IFERROR('Order Book & Revenue'!I33/I14,"") -> 7.2815126 | J19: =IFERROR('Order Book & Revenue'!J33/J14,"") -> 8.0782258 | ... Q19: =IFERROR('Order Book & Revenue'!Q33/Q14,"") -> 6.8995415
A20: Revenue per >$10m client | B20: $m | C20: =IFERROR('Order Book & Revenue'!C33/C13,"") -> 0 | D20: =IFERROR('Order Book & Revenue'!D33/D13,"") -> 0 | E20: =IFERROR('Order Book & Revenue'!E33/E13,"") -> 0 | F20: =IFERROR('Order Book & Revenue'!F33/F13,"") -> 0 | G20: =IFERROR('Order Book & Revenue'!G33/G13,"") | H20: =IFERROR('Order Book & Revenue'!H33/H13,"") | I20: =IFERROR('Order Book & Revenue'!I33/I13,"") -> 48.138889 | J20: =IFERROR('Order Book & Revenue'!J33/J13,"") -> 47.7 | ... Q20: =IFERROR('Order Book & Revenue'!Q33/Q13,"")
A21: Order intake | B21: $m | C21: ='Order Book & Revenue'!C15 -> 420 | D21: ='Order Book & Revenue'!D15 -> 457 | E21: ='Order Book & Revenue'!E15 -> 507 | F21: ='Order Book & Revenue'!F15 -> 646 | G21: ='Order Book & Revenue'!G15 -> 748 | H21: ='Order Book & Revenue'!H15 -> 781 | I21: ='Order Book & Revenue'!I15 -> 1151 | J21: ='Order Book & Revenue'!J15 -> 1265 | ... Q21: ='Order Book & Revenue'!Q15 -> 3222.0199
A22: Order intake / revenue | B22: x | C22: =IFERROR(C21/'Order Book & Revenue'!C33,"") | D22: =IFERROR(D21/'Order Book & Revenue'!D33,"") | E22: =IFERROR(E21/'Order Book & Revenue'!E33,"") | F22: =IFERROR(F21/'Order Book & Revenue'!F33,"") | G22: =IFERROR(G21/'Order Book & Revenue'!G33,"") | H22: =IFERROR(H21/'Order Book & Revenue'!H33,"") | I22: =IFERROR(I21/'Order Book & Revenue'!I33,"") -> 1.3283324 | J22: =IFERROR(J21/'Order Book & Revenue'!J33,"") -> 1.2628531 | ... Q22: =IFERROR(Q21/'Order Book & Revenue'!Q33,"") -> 0.68373418
A23: Executable order book | B23: $m | C23: ='Order Book & Revenue'!C10 -> 301 | D23: ='Order Book & Revenue'!D10 -> 320 | E23: ='Order Book & Revenue'!E10 -> 339 | F23: ='Order Book & Revenue'!F10 -> 390 | G23: ='Order Book & Revenue'!G10 -> 468 | H23: ='Order Book & Revenue'!H10 -> 520 | I23: ='Order Book & Revenue'!I10 -> 720 | J23: ='Order Book & Revenue'!J10 -> 869 | ... Q23: ='Order Book & Revenue'!Q10 -> 2903.2106
A24: EOB / revenue | B24: x | C24: =IFERROR(C23/'Order Book & Revenue'!C33,"") | D24: =IFERROR(D23/'Order Book & Revenue'!D33,"") | E24: =IFERROR(E23/'Order Book & Revenue'!E33,"") | F24: =IFERROR(F23/'Order Book & Revenue'!F33,"") | G24: =IFERROR(G23/'Order Book & Revenue'!G33,"") | H24: =IFERROR(H23/'Order Book & Revenue'!H33,"") | I24: =IFERROR(I23/'Order Book & Revenue'!I33,"") -> 0.83092902 | J24: =IFERROR(J23/'Order Book & Revenue'!J33,"") -> 0.86752521 | ... Q24: =IFERROR(Q23/'Order Book & Revenue'!Q33,"") -> 0.61608071

Sheet People & AI
A1: People, Productivity and AI
A2: Headcount is a capacity / margin constraint, not the sole revenue driver; AI uplift is separated from T&M deflation
A5: Metric | B5: Units | C5: FY16A | D5: FY17A | E5: FY18A | F5: FY19A | G5: FY20A | H5: FY21A | I5: FY22A | J5: FY23A | K5: FY24A | L5: FY25A | M5: FY26A | N5: FY27E | O5: FY28E | P5: FY29E | Q5: FY30E
A7: Total headcount | B7: # | C7: ='Raw Operating'!C43 -> 9476 | D7: ='Raw Operating'!D43 -> 8853 | E7: ='Raw Operating'!E43 -> 9423 | F7: ='Raw Operating'!F43 -> 10263 | G7: ='Raw Operating'!G43 -> 11156 | H7: ='Raw Operating'!H43 -> 12391 | I7: ='Raw Operating'!I43 -> 22500 | J7: ='Raw Operating'!J43 -> 23224 | ... M7: ='Raw Operating'!M43 -> 35777 | N7: =M7*(1+MAX(0,'Annual P&L'!N8*0.45)) -> 42107.516 | O7: =N7*(1+MAX(0,'Annual P&L'!O8*0.45)) -> 47522.971 | P7: =O7*(1+MAX(0,'Annual P&L'!P8*0.45)) -> 53038.237 | Q7: =P7*(1+MAX(0,'Annual P&L'!Q8*0.45)) -> 58687.431
A8: IT billable | B8: # | C8: ='Raw Operating'!C44 -> 0 | D8: ='Raw Operating'!D44 -> 0 | E8: ='Raw Operating'!E44 -> 0 | F8: ='Raw Operating'!F44 -> 0 | G8: ='Raw Operating'!G44 -> 0 | H8: ='Raw Operating'!H44 -> 0 | I8: ='Raw Operating'!I44 -> 14903 | J8: ='Raw Operating'!J44 -> 16182 | ... M8: ='Raw Operating'!M44 -> 25062 | N8: =N10*0.75 -> 29696.938 | O8: =O10*0.75 -> 33516.267 | P8: =P10*0.75 -> 37405.989 | Q8: =Q10*0.75 -> 41390.165
A9: BPS billable | B9: # | C9: ='Raw Operating'!C45 -> 0 | D9: ='Raw Operating'!D45 -> 0 | E9: ='Raw Operating'!E45 -> 0 | F9: ='Raw Operating'!F45 -> 0 | G9: ='Raw Operating'!G45 -> 0 | H9: ='Raw Operating'!H45 -> 0 | I9: ='Raw Operating'!I45 -> 6391 | J9: ='Raw Operating'!J45 -> 5633 | ... M9: ='Raw Operating'!M45 -> 8581 | N9: =N10-N8 -> 9898.9794 | O9: =O10-O8 -> 11172.089 | P9: =P10-P8 -> 12468.663 | Q9: =Q10-Q8 -> 13796.722
A10: Total billable | B10: # | C10: ='Raw Operating'!C46 -> 8743 | D10: ='Raw Operating'!D46 -> 8066 | E10: ='Raw Operating'!E46 -> 8588 | F10: ='Raw Operating'!F46 -> 9363 | G10: ='Raw Operating'!G46 -> 10274 | H10: ='Raw Operating'!H46 -> 11469 | I10: ='Raw Operating'!I46 -> 21294 | J10: ='Raw Operating'!J46 -> 21815 | ... M10: ='Raw Operating'!M46 -> 33643 | N10: =N7*M11 -> 39595.918 | O10: =O7*N11 -> 44688.356 | P10: =P7*O11 -> 49874.652 | Q10: =Q7*P11 -> 55186.887
A11: Billable / headcount | B11: % | C11: =IFERROR(C10/C7,"") -> 0.92264669 | D11: =IFERROR(D10/D7,"") -> 0.91110358 | E11: =IFERROR(E10/E7,"") -> 0.91138703 | F11: =IFERROR(F10/F7,"") -> 0.91230634 | G11: =IFERROR(G10/G7,"") -> 0.9209394 | H11: =IFERROR(H10/H7,"") -> 0.92559115 | I11: =IFERROR(I10/I7,"") -> 0.9464 | J11: =IFERROR(J10/J7,"") -> 0.93933 | ... Q11: =IFERROR(Q10/Q7,"") -> 0.94035274
A12: Utilization | B12: % | C12: ='Raw Operating'!C48 -> 0.79 | D12: ='Raw Operating'!D48 -> 0.81 | E12: ='Raw Operating'!E48 -> 0.795 | F12: ='Raw Operating'!F48 -> 0.793 | G12: ='Raw Operating'!G48 -> 0.781 | H12: ='Raw Operating'!H48 -> 0.81 | I12: ='Raw Operating'!I48 -> 0.761 | J12: ='Raw Operating'!J48 -> 0.815 | ... M12: ='Raw Operating'!M48 -> 0.825 | N12: =MIN(0.85,M12+0.005) -> 0.83 | O12: =MIN(0.85,N12+0.005) -> 0.835 | P12: =MIN(0.85,O12+0.005) -> 0.84 | Q12: =MIN(0.85,P12+0.005) -> 0.845
A13: Attrition | B13: % | C13: ='Raw Operating'!C49 -> 0.127 | D13: ='Raw Operating'!D49 -> 0.127 | E13: ='Raw Operating'!E49 -> 0.105 | F13: ='Raw Operating'!F49 -> 0.122 | G13: ='Raw Operating'!G49 -> 0.118 | H13: ='Raw Operating'!H49 -> 0.105 | I13: ='Raw Operating'!I49 -> 0.177 | J13: ='Raw Operating'!J49 -> 0.141 | ... M13: ='Raw Operating'!M49 -> 0.108 | N13: =MAX(0.09,M13-0.003) -> 0.105 | O13: =MAX(0.09,N13-0.003) -> 0.102 | P13: =MAX(0.09,O13-0.003) -> 0.099 | Q13: =MAX(0.09,P13-0.003) -> 0.096
A14: Revenue per IT billable | B14: $ / FTE | C14: ='Raw Operating'!C47 -> 0 | D14: ='Raw Operating'!D47 -> 0 | E14: ='Raw Operating'!E47 -> 0 | F14: ='Raw Operating'!F47 -> 0 | G14: ='Raw Operating'!G47 -> 0 | H14: ='Raw Operating'!H47 -> 0 | I14: ='Raw Operating'!I47 -> 0 | J14: ='Raw Operating'!J47 -> 0 | ... M14: ='Raw Operating'!M47 -> 71795 | N14: =IFERROR('Order Book & Revenue'!N33*1000000/N8,"") -> 81863.792 | O14: =IFERROR('Order Book & Revenue'!O33*1000000/O8,"") -> 92283.849 | P14: =IFERROR('Order Book & Revenue'!P33*1000000/P8,"") -> 102929.18 | Q14: =IFERROR('Order Book & Revenue'!Q33*1000000/Q8,"") -> 113852.82
A15: Revenue per total billable | B15: $ / FTE | C15: =IFERROR('Order Book & Revenue'!C33*1000000/C10,"") -> 0 | D15: =IFERROR('Order Book & Revenue'!D33*1000000/D10,"") -> 0 | E15: =IFERROR('Order Book & Revenue'!E33*1000000/E10,"") -> 0 | F15: =IFERROR('Order Book & Revenue'!F33*1000000/F10,"") -> 0 | G15: =IFERROR('Order Book & Revenue'!G33*1000000/G10,"") -> 0 | H15: =IFERROR('Order Book & Revenue'!H33*1000000/H10,"") -> 0 | I15: =IFERROR('Order Book & Revenue'!I33*1000000/I10,"") -> 40692.214 | J15: =IFERROR('Order Book & Revenue'!J33*1000000/J10,"") -> 45917.946 | ... Q15: =IFERROR('Order Book & Revenue'!Q33*1000000/Q10,"") -> 85389.612
A16: Headcount growth | B16: % | D16: =IFERROR(D7/C7-1,"") -> -0.06574504 | E16: =IFERROR(E7/D7-1,"") -> 0.064384954 | F16: =IFERROR(F7/E7-1,"") -> 0.089143585 | G16: =IFERROR(G7/F7-1,"") -> 0.087011595 | H16: =IFERROR(H7/G7-1,"") -> 0.11070276 | I16: =IFERROR(I7/H7-1,"") -> 0.81583407 | J16: =IFERROR(J7/I7-1,"") -> 0.032177778 | K16: =IFERROR(K7/J7-1,"") -> 0.064674475 | ... Q16: =IFERROR(Q7/P7-1,"") -> 0.10651171
A17: Revenue growth | B17: % | D17: ='Annual P&L'!D8 -> 0.044622317 | E17: ='Annual P&L'!E8 -> 0.067556476 | F17: ='Annual P&L'!F8 -> 0.22892291 | G17: ='Annual P&L'!G8 -> 0.13810456 | H17: ='Annual P&L'!H8 -> 0.11446258 | I17: ='Annual P&L'!I8 -> 0.37942867 | J17: ='Annual P&L'!J8 -> 0.246051 | K17: ='Annual P&L'!K8 -> 0.14528486 | ... Q17: ='Annual P&L'!Q8 -> 0.2366927
A18: Revenue growth less headcount growth | B18: ppt | D18: =D17-D16 -> 0.11036736 | E18: =E17-E16 -> 0.0031715212 | F18: =F17-F16 -> 0.13977933 | G18: =G17-G16 -> 0.051092969 | H18: =H17-H16 -> 0.0037598219 | I18: =I17-I16 -> -0.4364054 | J18: =J17-J16 -> 0.21387322 | K18: =K17-K16 -> 0.08061038 | ... Q18: =Q17-Q16 -> 0.13018098
A19: T&M revenue | B19: $m | C19: ='Order Book & Revenue'!C9*'Order Book & Revenue'!C22 -> 0 | D19: ='Order Book & Revenue'!D9*'Order Book & Revenue'!D22 -> 0 | E19: ='Order Book & Revenue'!E9*'Order Book & Revenue'!E22 -> 0 | F19: ='Order Book & Revenue'!F9*'Order Book & Revenue'!F22 -> 0 | G19: ='Order Book & Revenue'!G9*'Order Book & Revenue'!G22 -> 0 | H19: ='Order Book & Revenue'!H9*'Order Book & Revenue'!H22 -> 0 | I19: ='Order Book & Revenue'!I9*'Order Book & Revenue'!I22 -> 0 | J19: ='Order Book & Revenue'!J9*'Order Book & Revenue'!J22 -> 0 | ... Q19: ='Order Book & Revenue'!Q9*'Order Book & Revenue'!Q22 -> 2000.0851
A20: T&M AI deflation drag | B20: $m | C20: ='Order Book & Revenue'!C24 -> 0 | D20: ='Order Book & Revenue'!D24 -> 0 | E20: ='Order Book & Revenue'!E24 -> 0 | F20: ='Order Book & Revenue'!F24 -> 0 | G20: ='Order Book & Revenue'!G24 -> 0 | H20: ='Order Book & Revenue'!H24 -> 0 | I20: ='Order Book & Revenue'!I24 -> 0 | J20: ='Order Book & Revenue'!J24 -> 0 | ... Q20: ='Order Book & Revenue'!Q24 -> -10.000425
A21: Incremental AI uplift | B21: $m | C21: ='Order Book & Revenue'!C28 -> 0 | D21: ='Order Book & Revenue'!D28 -> 0 | E21: ='Order Book & Revenue'!E28 -> 0 | F21: ='Order Book & Revenue'!F28 -> 0 | G21: ='Order Book & Revenue'!G28 -> 0 | H21: ='Order Book & Revenue'!H28 -> 0 | I21: ='Order Book & Revenue'!I28 -> 0 | J21: ='Order Book & Revenue'!J28 -> 0 | ... Q21: ='Order Book & Revenue'!Q28 -> 148.15445
A22: Net AI / productivity contribution | B22: $m | C22: =SUM(C20:C21) -> 0 | D22: =SUM(D20:D21) -> 0 | E22: =SUM(E20:E21) -> 0 | F22: =SUM(F20:F21) -> 0 | G22: =SUM(G20:G21) -> 0 | H22: =SUM(H20:H21) -> 0 | I22: =SUM(I20:I21) -> 0 | J22: =SUM(J20:J21) -> 0 | ... Q22: =SUM(Q20:Q21) -> 138.15402
A23: AI-led Engineering service mix | B23: % | C23: ='Raw Operating'!C30 -> 0 | D23: ='Raw Operating'!D30 -> 0 | E23: ='Raw Operating'!E30 -> 0 | F23: ='Raw Operating'!F30 -> 0 | G23: ='Raw Operating'!G30 -> 0 | H23: ='Raw Operating'!H30 -> 0 | I23: ='Raw Operating'!I30 -> 0 | J23: ='Raw Operating'!J30 -> 0.363 | ... M23: ='Raw Operating'!M30 -> 0.441 | N23: ='Vertical & Services'!N29 -> 0.441 | O23: ='Vertical & Services'!O29 -> 0.441 | P23: ='Vertical & Services'!P29 -> 0.441 | Q23: ='Vertical & Services'!Q29 -> 0.441
A24: AI Mod Squad accounts in rollout | B24: # | M24: 40
A25: AI Mod Squad programs | B25: # | M25: 50
A26: AI agents live / in build | B26: # | M26: 150
A27: Measured productivity gains | B27: range | M27: 22%–50%
A28: Interpretation | B28: text | C28: Coforge disclosed 40+ rollout accounts, 50+ programs and 150+ agents live / in build. These activity KPIs support the forecast AI uplift assumption; they are not booked as historical AI revenue.

Sheet Valuation
A1: Valuation
A2: FY-end and latest market prices; forward P/E, EV/EBITDA and DCF calculate independently and blend into an OUTPERFORM target
A5: Metric | B5: Units | C5: FY16A | D5: FY17A | E5: FY18A | F5: FY19A | G5: FY20A | H5: FY21A | I5: FY22A | J5: FY23A | K5: FY24A | L5: FY25A | M5: FY26A | N5: FY27E | O5: FY28E | P5: FY29E | Q5: FY30E
A7: Reference market price | B7: ₹ / share | C7: 99.339996 | D7: 87.120003 | E7: 173 | F7: 266.79001 | G7: 229.55 | H7: 585.39001 | I7: 891.5 | J7: 762.82001 | K7: 1100.49 | L7: 1621.84 | M7: 1114.7 | N7: =Assumptions!C55 -> 1981.5 | O7: =Assumptions!D55 -> 1981.5 | P7: =Assumptions!E55 -> 1981.5 | Q7: =Assumptions!F55 -> 1981.5
A8: Diluted shares | B8: m | C8: ='Annual P&L'!C33 -> 307.31403 | D8: ='Annual P&L'!D33 -> 307.17268 | E8: ='Annual P&L'!E33 -> 308.99868 | F8: ='Annual P&L'!F33 -> 311.5248 | G8: ='Annual P&L'!G33 -> 312.80823 | H8: ='Annual P&L'!H33 -> 310.82003 | I8: ='Annual P&L'!I33 -> 310.59895 | J8: ='Annual P&L'!J33 -> 311.03739 | ... Q8: ='Annual P&L'!Q33 -> 425
A9: Market capitalization | B9: ₹m | C9: =IF(C7="","",C7*C8) -> 30528.574 | D9: =IF(D7="","",D7*D8) -> 26760.885 | E9: =IF(E7="","",E7*E8) -> 53456.771 | F9: =IF(F7="","",F7*F8) -> 83111.703 | G9: =IF(G7="","",G7*G8) -> 71805.13 | H9: =IF(H7="","",H7*H8) -> 181950.94 | I9: =IF(I7="","",I7*I8) -> 276898.96 | J9: =IF(J7="","",J7*J8) -> 237265.54 | ... Q9: =IF(Q7="","",Q7*Q8) -> 842137.5
A10: Cash + bank balances | B10: ₹m | C10: =SUM('Annual Balance Sheet'!C21,'Annual Balance Sheet'!C23) -> 3361.9517 | D10: =SUM('Annual Balance Sheet'!D21,'Annual Balance Sheet'!D23) -> 4075 | E10: =SUM('Annual Balance Sheet'!E21,'Annual Balance Sheet'!E23) -> 4183 | F10: =SUM('Annual Balance Sheet'!F21,'Annual Balance Sheet'!F23) -> 5576 | G10: =SUM('Annual Balance Sheet'!G21,'Annual Balance Sheet'!G23) -> 9034 | H10: =SUM('Annual Balance Sheet'!H21,'Annual Balance Sheet'!H23) -> 8122 | I10: =SUM('Annual Balance Sheet'!I21,'Annual Balance Sheet'!I23) -> 4535 | J10: =SUM('Annual Balance Sheet'!J21,'Annual Balance Sheet'!J23) -> 5787 | ... Q10: =SUM('Annual Balance Sheet'!Q21,'Annual Balance Sheet'!Q23) -> 29969.931
A11: Debt + lease liabilities | B11: ₹m | C11: =SUM('Annual Balance Sheet'!C35,'Annual Balance Sheet'!C36,'Annual Balance Sheet'!C42,'Annual Balance Sheet'!C43) -> 63.791706 | D11: =SUM('Annual Balance Sheet'!D35,'Annual Balance Sheet'!D36,'Annual Balance Sheet'!D42,'Annual Balance Sheet'!D43) -> 74 | E11: =SUM('Annual Balance Sheet'!E35,'Annual Balance Sheet'!E36,'Annual Balance Sheet'!E42,'Annual Balance Sheet'!E43) -> 179 | F11: =SUM('Annual Balance Sheet'!F35,'Annual Balance Sheet'!F36,'Annual Balance Sheet'!F42,'Annual Balance Sheet'!F43) -> 100 | G11: =SUM('Annual Balance Sheet'!G35,'Annual Balance Sheet'!G36,'Annual Balance Sheet'!G42,'Annual Balance Sheet'!G43) -> 48 | H11: =SUM('Annual Balance Sheet'!H35,'Annual Balance Sheet'!H36,'Annual Balance Sheet'!H42,'Annual Balance Sheet'!H43) -> 5 | I11: =SUM('Annual Balance Sheet'!I35,'Annual Balance Sheet'!I36,'Annual Balance Sheet'!I42,'Annual Balance Sheet'!I43) -> 3545 | J11: =SUM('Annual Balance Sheet'!J35,'Annual Balance Sheet'!J36,'Annual Balance Sheet'!J42,'Annual Balance Sheet'!J43) -> 3395 | ... Q11: =SUM('Annual Balance Sheet'!Q35,'Annual Balance Sheet'!Q36,'Annual Balance Sheet'!Q42,'Annual Balance Sheet'!Q43) -> 6235.2075
A12: Enterprise value | B12: ₹m | C12: =IF(C9="","",C9-C10+C11) -> 27230.414 | D12: =IF(D9="","",D9-D10+D11) -> 22759.885 | E12: =IF(E9="","",E9-E10+E11) -> 49452.771 | F12: =IF(F9="","",F9-F10+F11) -> 77635.703 | G12: =IF(G9="","",G9-G10+G11) -> 62819.13 | H12: =IF(H9="","",H9-H10+H11) -> 173833.94 | I12: =IF(I9="","",I9-I10+I11) -> 275908.96 | J12: =IF(J9="","",J9-J10+J11) -> 234873.54 | ... Q12: =IF(Q9="","",Q9-Q10+Q11) -> 818402.78
A13: Diluted EPS | B13: ₹ / share | C13: ='Annual P&L'!C35 -> 9.11 | D13: ='Annual P&L'!D35 -> 8.142 | E13: ='Annual P&L'!E35 -> 9.068 | F13: ='Annual P&L'!F35 -> 12.946 | G13: ='Annual P&L'!G35 -> 14.194 | H13: ='Annual P&L'!H35 -> 14.658 | I13: ='Annual P&L'!I35 -> 21.304 | J13: ='Annual P&L'!J35 -> 22.306 | ... Q13: ='Annual P&L'!Q35 -> 145.25742
A14: P/E | B14: x | C14: =IFERROR(C7/C13,"") -> 10.9045 | D14: =IFERROR(D7/D13,"") -> 10.700074 | E14: =IFERROR(E7/E13,"") -> 19.078077 | F14: =IFERROR(F7/F13,"") -> 20.60791 | G14: =IFERROR(G7/G13,"") -> 16.172327 | H14: =IFERROR(H7/H13,"") -> 39.936554 | I14: =IFERROR(I7/I13,"") -> 41.846602 | J14: =IFERROR(J7/J13,"") -> 34.197974 | ... Q14: =IFERROR(Q7/Q13,"") -> 13.6413
A15: EBITDA | B15: ₹m | C15: ='Annual P&L'!C16 -> 4841.7219 | D15: ='Annual P&L'!D16 -> 4794 | E15: ='Annual P&L'!E16 -> 5013 | F15: ='Annual P&L'!F16 -> 6485 | G15: ='Annual P&L'!G16 -> 7233 | H15: ='Annual P&L'!H16 -> 7795 | I15: ='Annual P&L'!I16 -> 11019 | J15: ='Annual P&L'!J16 -> 12807 | ... Q15: ='Annual P&L'!Q16 -> 99191.03
A16: EV / EBITDA | B16: x | C16: =IFERROR(C12/C15,"") -> 5.6241178 | D16: =IFERROR(D12/D15,"") -> 4.7475772 | E16: =IFERROR(E12/E15,"") -> 9.8649055 | F16: =IFERROR(F12/F15,"") -> 11.971581 | G16: =IFERROR(G12/G15,"") -> 8.6850726 | H16: =IFERROR(H12/H15,"") -> 22.300698 | I16: =IFERROR(I12/I15,"") -> 25.039383 | J16: =IFERROR(J12/J15,"") -> 18.339466 | ... Q16: =IFERROR(Q12/Q15,"") -> 8.250774
A17: Dividend per share | B17: ₹ / share | C17: ='Annual P&L'!C37 -> 2.3939726 | D17: ='Annual P&L'!D37 -> 0 | E17: ='Annual P&L'!E37 -> 1.9965161 | F17: ='Annual P&L'!F37 -> 0 | G17: ='Annual P&L'!G37 -> 0 | H17: ='Annual P&L'!H37 -> 2.2489236 | I17: ='Annual P&L'!I37 -> 10.386309 | J17: ='Annual P&L'!J37 -> 11.590175 | ... Q17: ='Annual P&L'!Q37 -> 58.394942
A18: Dividend yield | B18: % | C18: =IFERROR(C17/C7,"") -> 0.024098778 | D18: =IFERROR(D17/D7,"") -> 0 | E18: =IFERROR(E17/E7,"") -> 0.011540555 | F18: =IFERROR(F17/F7,"") -> 0 | G18: =IFERROR(G17/G7,"") -> 0 | H18: =IFERROR(H17/H7,"") -> 0.0038417526 | I18: =IFERROR(I17/I7,"") -> 0.011650375 | J18: =IFERROR(J17/J7,"") -> 0.015193853 | ... Q18: =IFERROR(Q17/Q7,"") -> 0.029470069
A19: Target P/E | B19: x | N19: =Assumptions!C48 -> 39 | O19: =Assumptions!D48 -> 36 | P19: =Assumptions!E48 -> 33 | Q19: =Assumptions!F48 -> 31
A20: P/E implied equity value / share | B20: ₹ / share | N20: =N13*N19 -> 2239.4302 | O20: =O13*O19 -> 2920.3459 | P20: =P13*P19 -> 3665.2281 | Q20: =Q13*Q19 -> 4502.98
A21: Target EV / EBITDA | B21: x | N21: =Assumptions!C49 -> 22 | O21: =Assumptions!D49 -> 20 | P21: =Assumptions!E49 -> 18.5 | Q21: =Assumptions!F49 -> 17.5
A22: EV / EBITDA implied equity value / share | B22: ₹ / share | N22: =(N15*N21+N10-N11)/N8 -> 2267.6128 | O22: =(O15*O21+O10-O11)/O8 -> 2796.9987 | P22: =(P15*P21+P10-P11)/P8 -> 3407.2583 | Q22: =(Q15*Q21+Q10-Q11)/Q8 -> 4140.183
A23: FCFF | B23: ₹m
A24: WACC | B24: % | N24: ='Annual P&L'!N19*(1-'Annual P&L'!N27)+'Annual P&L'!N18+'Annual Cash Flow'!N21 -> 30404.952 | O24: ='Annual P&L'!O19*(1-'Annual P&L'!O27)+'Annual P&L'!O18+'Annual Cash Flow'!O21 -> 39374.019 | P24: ='Annual P&L'!P19*(1-'Annual P&L'!P27)+'Annual P&L'!P18+'Annual Cash Flow'!P21 -> 51653.849 | Q24: ='Annual P&L'!Q19*(1-'Annual P&L'!Q27)+'Annual P&L'!Q18+'Annual Cash Flow'!Q21 -> 65251.242
A25: Terminal growth | B25: % | N25: =Assumptions!C50 -> 0.105 | O25: =Assumptions!D50 -> 0.105 | P25: =Assumptions!E50 -> 0.105 | Q25: =Assumptions!F50 -> 0.105
A26: DCF enterprise value | B26: ₹m | N26: =Assumptions!C51 -> 0.055 | O26: =Assumptions!D51 -> 0.055 | P26: =Assumptions!E51 -> 0.055 | Q26: =Assumptions!F51 -> 0.055
A27: DCF equity value / share | B27: ₹ / share | N27: =SUMPRODUCT(N24:$Q$24,1/(1+N25)^(COLUMN(N24:$Q$24)-COLUMN(N24)+1))+$Q$24*(1+$Q$26)/($Q$25-$Q$26)/(1+$Q$25)^(COLUMN($Q$24)-COLUMN(N24)+1) -> 1065281.2 | O27: =SUMPRODUCT(O24:$Q$24,1/(1+O25)^(COLUMN(O24:$Q$24)-COLUMN(O24)+1))+$Q$24*(1+$Q$26)/($Q$25-$Q$26)/(1+$Q$25)^(COLUMN($Q$24)-COLUMN(O24)+1) -> 1146730.8 | P27: =SUMPRODUCT(P24:$Q$24,1/(1+P25)^(COLUMN(P24:$Q$24)-COLUMN(P24)+1))+$Q$24*(1+$Q$26)/($Q$25-$Q$26)/(1+$Q$25)^(COLUMN($Q$24)-COLUMN(P24)+1) -> 1227763.5 | Q27: =SUMPRODUCT(Q24:$Q$24,1/(1+Q25)^(COLUMN(Q24:$Q$24)-COLUMN(Q24)+1))+$Q$24*(1+$Q$26)/($Q$25-$Q$26)/(1+$Q$25)^(COLUMN($Q$24)-COLUMN(Q24)+1) -> 1305024.8
A28: P/E weight | B28: % | N28: =(N27+N10-N11)/N8 -> 2420.0931 | O28: =(O27+O10-O11)/O8 -> 2646.7084 | P28: =(P27+P10-P11)/P8 -> 2885.2094 | Q28: =(Q27+Q10-Q11)/Q8 -> 3126.4931
A29: EV / EBITDA weight | B29: % | N29: =Assumptions!C52 -> 0.4 | O29: =Assumptions!D52 -> 0.4 | P29: =Assumptions!E52 -> 0.4 | Q29: =Assumptions!F52 -> 0.4
A30: DCF weight | B30: % | N30: =Assumptions!C53 -> 0.3 | O30: =Assumptions!D53 -> 0.3 | P30: =Assumptions!E53 -> 0.3 | Q30: =Assumptions!F53 -> 0.3
A31: Blended target price | B31: ₹ / share | N31: =Assumptions!C54 -> 0.3 | O31: =Assumptions!D54 -> 0.3 | P31: =Assumptions!E54 -> 0.3 | Q31: =Assumptions!F54 -> 0.3
A32: Upside / (downside) | B32: % | N32: =SUMPRODUCT(N20,N29)+SUMPRODUCT(N22,N30)+SUMPRODUCT(N28,N31) -> 2302.0839 | O32: =SUMPRODUCT(O20,O29)+SUMPRODUCT(O22,O30)+SUMPRODUCT(O28,O31) -> 2801.2505 | P32: =SUMPRODUCT(P20,P29)+SUMPRODUCT(P22,P30)+SUMPRODUCT(P28,P31) -> 3353.8316 | Q32: =SUMPRODUCT(Q20,Q29)+SUMPRODUCT(Q22,Q30)+SUMPRODUCT(Q28,Q31) -> 3981.1948
A33: Implied rating | B33: text | N33: =IFERROR(N32/N7-1,"") -> 0.16178847 | O33: =IFERROR(O32/O7-1,"") -> 0.41370198 | P33: =IFERROR(P32/P7-1,"") -> 0.69257207 | Q33: =IFERROR(Q32/Q7-1,"") -> 1.0091823
N34: =IF(N7="","ENTER PRICE",IF(N33>=0.15,"OUTPERFORM",IF(N33>=-0.05,"NEUTRAL","UNDERPERFORM"))) -> OUTPERFORM | O34: =IF(O7="","ENTER PRICE",IF(O33>=0.15,"OUTPERFORM",IF(O33>=-0.05,"NEUTRAL","UNDERPERFORM"))) -> OUTPERFORM | P34: =IF(P7="","ENTER PRICE",IF(P33>=0.15,"OUTPERFORM",IF(P33>=-0.05,"NEUTRAL","UNDERPERFORM"))) -> OUTPERFORM | Q34: =IF(Q7="","ENTER PRICE",IF(Q33>=0.15,"OUTPERFORM",IF(Q33>=-0.05,"NEUTRAL","UNDERPERFORM"))) -> OUTPERFORM

Sheet COFORGE Prices
A1: NIIT Technologies / Coforge Prices
A2: Continuous listed-company series from August 2004; daily close drives FY-end and reference-price valuation
A3: Corporate continuity: NIIT Technologies Limited was renamed Coforge Limited effective 3 Aug 2020. NSE symbol: NIITTECH from Aug-2004 through Aug-2020; COFORGE since Aug-2020.
A5: Date | B5: Company | C5: NSE symbol | D5: Close | E5: Adjusted close | F5: Volume | G5: Fiscal year | H5: Source | J5: Fiscal year | K5: FY-end date | L5: FY-end close | M5: Corporate identity
A6: 38229.156 | B6: NIIT Technologies Limited | C6: NIITTECH | D6: 25.946667 | E6: 15.333723 | F6: 26236432 | G6: FY05 | H6: https://finance.yahoo.com/quote/COFORGE.NS/history/ | J6: FY05A | K6: 38442.156 | L6: 16.866667 | M6: NIITTECH — NIIT Technologies
A7: 38230.156 | B7: NIIT Technologies Limited | C7: NIITTECH | D7: 24.92 | E7: 14.726996 | F7: 5131147 | G7: FY05 | H7: https://finance.yahoo.com/quote/COFORGE.NS/history/ | J7: FY06A | K7: 38807.156 | L7: 30.473333 | M7: NIITTECH — NIIT Technologies
A8: 38231.156 | B8: NIIT Technologies Limited | C8: NIITTECH | D8: 24.299999 | E8: 14.360597 | F8: 2990947 | G8: FY05 | H8: https://finance.yahoo.com/quote/COFORGE.NS/history/ | J8: FY07A | K8: 39171.156 | L8: 58.560001 | M8: NIITTECH — NIIT Technologies
A9: 38232.156 | B9: NIIT Technologies Limited | C9: NIITTECH | D9: 23.639999 | E9: 13.970551 | F9: 2615782 | G9: FY05 | H9: https://finance.yahoo.com/quote/COFORGE.NS/history/ | J9: FY08A | K9: 39538.156 | L9: 20.379999 | M9: NIITTECH — NIIT Technologies
A10: 38233.156 | B10: NIIT Technologies Limited | C10: NIITTECH | D10: 23.633333 | E10: 13.966617 | F10: 2077365 | G10: FY05 | H10: https://finance.yahoo.com/quote/COFORGE.NS/history/ | J10: FY09A | K10: 39903.156 | L10: 10.56 | M10: NIITTECH — NIIT Technologies
A11: 38236.156 | B11: NIIT Technologies Limited | C11: NIITTECH | D11: 22.959999 | E11: 13.56869 | F11: 2076652 | G11: FY05 | H11: https://finance.yahoo.com/quote/COFORGE.NS/history/ | J11: FY10A | K11: 40268.156 | L11: 33.950001 | M11: NIITTECH — NIIT Technologies
A12: 38237.156 | B12: NIIT Technologies Limited | C12: NIITTECH | D12: 23.106667 | E12: 13.655372 | F12: 1473630 | G12: FY05 | H12: https://finance.yahoo.com/quote/COFORGE.NS/history/ | J12: FY11A | K12: 40633.156 | L12: 36.900002 | M12: NIITTECH — NIIT Technologies
A13: 38238.156 | B13: NIIT Technologies Limited | C13: NIITTECH | D13: 22.806665 | E13: 13.478079 | F13: 987772 | G13: FY05 | H13: https://finance.yahoo.com/quote/COFORGE.NS/history/ | J13: FY12A | K13: 40998.156 | L13: 54.52 | M13: NIITTECH — NIIT Technologies
A14: 38239.156 | B14: NIIT Technologies Limited | C14: NIITTECH | D14: 22.26 | E14: 13.155009 | F14: 1111845 | G14: FY05 | H14: https://finance.yahoo.com/quote/COFORGE.NS/history/ | J14: FY13A | K14: 41361.156 | L14: 56.48 | M14: NIITTECH — NIIT Technologies
A15: 38240.156 | B15: NIIT Technologies Limited | C15: NIITTECH | D15: 22.526667 | E15: 13.31261 | F15: 1373212 | G15: FY05 | H15: https://finance.yahoo.com/quote/COFORGE.NS/history/ | J15: FY14A | K15: 41729.156 | L15: 80.510002 | M15: NIITTECH — NIIT Technologies
A16: 38243.156 | B16: NIIT Technologies Limited | C16: NIITTECH | D16: 23.893333 | E16: 14.120265 | F16: 4477672 | G16: FY05 | H16: https://finance.yahoo.com/quote/COFORGE.NS/history/ | J16: FY15A | K16: 42094.156 | L16: 69.860001 | M16: NIITTECH — NIIT Technologies
A17: 38244.156 | B17: NIIT Technologies Limited | C17: NIITTECH | D17: 24.02 | E17: 14.195125 | F17: 2353867 | G17: FY05 | H17: https://finance.yahoo.com/quote/COFORGE.NS/history/ | J17: FY16A | K17: 42460.156 | L17: 99.339996 | M17: NIITTECH — NIIT Technologies
... A27: 38258.156 | B27: NIIT Technologies Limited | C27: NIITTECH | D27: 21.9 | E27: 12.942264 | F27: 418020 | G27: FY05 | H27: https://finance.yahoo.com/quote/COFORGE.NS/history/ | J27: FY26A | K27: 46111.156 | L27: 1114.7 | M27: COFORGE — Coforge
A28: 38259.156 | B28: NIIT Technologies Limited | C28: NIITTECH | D28: 22.006666 | E28: 13.005299 | F28: 379320 | G28: FY05 | H28: https://finance.yahoo.com/quote/COFORGE.NS/history/
A29: 38260.156 | B29: NIIT Technologies Limited | C29: NIITTECH | D29: 22.219999 | E29: 13.131375 | F29: 536137 | G29: FY05 | H29: https://finance.yahoo.com/quote/COFORGE.NS/history/
A30: 38261.156 | B30: NIIT Technologies Limited | C30: NIITTECH | D30: 22.366667 | E30: 13.218055 | F30: 478177 | G30: FY05 | H30: https://finance.yahoo.com/quote/COFORGE.NS/history/
A31: 38264.156 | B31: NIIT Technologies Limited | C31: NIITTECH | D31: 22.440001 | E31: 13.261387 | F31: 612765 | G31: FY05 | H31: https://finance.yahoo.com/quote/COFORGE.NS/history/
A32: 38265.156 | B32: NIIT Technologies Limited | C32: NIITTECH | D32: 22.586666 | E32: 13.348059 | F32: 658177 | G32: FY05 | H32: https://finance.yahoo.com/quote/COFORGE.NS/history/
A33: 38266.156 | B33: NIIT Technologies Limited | C33: NIITTECH | D33: 22.573334 | E33: 13.340188 | F33: 1273372 | G33: FY05 | H33: https://finance.yahoo.com/quote/COFORGE.NS/history/
A34: 38267.156 | B34: NIIT Technologies Limited | C34: NIITTECH | D34: 22.526667 | E34: 13.31261 | F34: 375022 | G34: FY05 | H34: https://finance.yahoo.com/quote/COFORGE.NS/history/
A35: 38268.156 | B35: NIIT Technologies Limited | C35: NIITTECH | D35: 22.66 | E35: 13.391403 | F35: 892350 | G35: FY05 | H35: https://finance.yahoo.com/quote/COFORGE.NS/history/
A36: 38271.156 | B36: NIIT Technologies Limited | C36: NIITTECH | D36: 22.486666 | E36: 13.288964 | F36: 583492 | G36: FY05 | H36: https://finance.yahoo.com/quote/COFORGE.NS/history/
A37: 38272.156 | B37: NIIT Technologies Limited | C37: NIITTECH | D37: 22.233334 | E37: 13.139251 | F37: 398715 | G37: FY05 | H37: https://finance.yahoo.com/quote/COFORGE.NS/history/
A38: 38273.156 | B38: NIIT Technologies Limited | C38: NIITTECH | D38: 22.233334 | E38: 13.139251 | F38: 0 | G38: FY05 | H38: https://finance.yahoo.com/quote/COFORGE.NS/history/
A39: 38274.156 | B39: NIIT Technologies Limited | C39: NIITTECH | D39: 22.606667 | E39: 13.359883 | F39: 642742 | G39: FY05 | H39: https://finance.yahoo.com/quote/COFORGE.NS/history/
... A5445: 46265.156 | B5445: Coforge Limited | C5445: COFORGE | D5445: 1981.5 | E5445: 1981.5 | F5445: 1354247 | G5445: FY27 | H5445: https://finance.yahoo.com/quote/COFORGE.NS/history/

Sheet Checks
A1: Model Checks
A2: Accounting, cash, spot-check, mix, forecast-driver, valuation and static circular-reference controls
A5: Check | B5: Status | C5: Calculated | D5: Control | E5: Difference | F5: Tolerance
A6: OVERALL MODEL STATUS | B6: =IF(COUNTIF(B7:B74,"FAIL")=0,"OK","REVIEW") -> OK
A7: FY16A balance sheet | B7: =IF(ABS(E7)<=F7,"OK","FAIL") -> OK | C7: ='Annual Balance Sheet'!C29 -> 22491.252 | D7: ='Annual Balance Sheet'!C51 -> 22491.252 | E7: =C7-D7 -> 0 | F7: 1
A8: FY16A cash tie | B8: =IF(ABS(E8)<=F8,"OK","FAIL") -> OK | C8: ='Annual Cash Flow'!C41 -> 2878.6273 | D8: ='Annual Cash Flow'!C42 -> 2878.6273 | E8: =C8-D8 -> 0 | F8: 1
A9: FY17A balance sheet | B9: =IF(ABS(E9)<=F9,"OK","FAIL") -> OK | C9: ='Annual Balance Sheet'!D29 -> 24648 | D9: ='Annual Balance Sheet'!D51 -> 24648 | E9: =C9-D9 -> 0 | F9: 1
A10: FY17A cash tie | B10: =IF(ABS(E10)<=F10,"OK","FAIL") -> OK | C10: ='Annual Cash Flow'!D41 -> 3502 | D10: ='Annual Cash Flow'!D42 -> 3502 | E10: =C10-D10 -> 0 | F10: 1
A11: FY18A balance sheet | B11: =IF(ABS(E11)<=F11,"OK","FAIL") -> OK | C11: ='Annual Balance Sheet'!E29 -> 26698 | D11: ='Annual Balance Sheet'!E51 -> 26698 | E11: =C11-D11 -> 0 | F11: 1
A12: FY18A cash tie | B12: =IF(ABS(E12)<=F12,"OK","FAIL") -> OK | C12: ='Annual Cash Flow'!E41 -> 4102 | D12: ='Annual Cash Flow'!E42 -> 4102 | E12: =C12-D12 -> 0 | F12: 1
A13: FY19A balance sheet | B13: =IF(ABS(E13)<=F13,"OK","FAIL") -> OK | C13: ='Annual Balance Sheet'!F29 -> 28734 | D13: ='Annual Balance Sheet'!F51 -> 28734 | E13: =C13-D13 -> 0 | F13: 1
A14: FY19A cash tie | B14: =IF(ABS(E14)<=F14,"OK","FAIL") -> OK | C14: ='Annual Cash Flow'!F41 -> 5194 | D14: ='Annual Cash Flow'!F42 -> 5194 | E14: =C14-D14 -> 0 | F14: 1
A15: FY20A balance sheet | B15: =IF(ABS(E15)<=F15,"OK","FAIL") -> OK | C15: ='Annual Balance Sheet'!G29 -> 34398 | D15: ='Annual Balance Sheet'!G51 -> 34398 | E15: =C15-D15 -> 0 | F15: 1
A16: FY20A cash tie | B16: =IF(ABS(E16)<=F16,"OK","FAIL") -> OK | C16: ='Annual Cash Flow'!G41 -> 8195 | D16: ='Annual Cash Flow'!G42 -> 8195 | E16: =C16-D16 -> 0 | F16: 1
A17: FY21A balance sheet | B17: =IF(ABS(E17)<=F17,"OK","FAIL") -> OK | C17: ='Annual Balance Sheet'!H29 -> 35134 | D17: ='Annual Balance Sheet'!H51 -> 35134 | E17: =C17-D17 -> 0 | F17: 1
A18: FY21A cash tie | B18: =IF(ABS(E18)<=F18,"OK","FAIL") -> OK | C18: ='Annual Cash Flow'!H41 -> 7999 | D18: ='Annual Cash Flow'!H42 -> 7999 | E18: =C18-D18 -> 0 | F18: 1
A19: FY22A balance sheet | B19: =IF(ABS(E19)<=F19,"OK","FAIL") -> OK | C19: ='Annual Balance Sheet'!I29 -> 49544 | D19: ='Annual Balance Sheet'!I51 -> 49544 | E19: =C19-D19 -> 0 | F19: 1
A20: FY22A cash tie | B20: =IF(ABS(E20)<=F20,"OK","FAIL") -> OK | C20: ='Annual Cash Flow'!I41 -> 4468 | D20: ='Annual Cash Flow'!I42 -> 4468 | E20: =C20-D20 -> 0 | F20: 1
A21: FY23A balance sheet | B21: =IF(ABS(E21)<=F21,"OK","FAIL") -> OK | C21: ='Annual Balance Sheet'!J29 -> 56834 | D21: ='Annual Balance Sheet'!J51 -> 56834 | E21: =C21-D21 -> 0 | F21: 1
A22: FY23A cash tie | B22: =IF(ABS(E22)<=F22,"OK","FAIL") -> OK | C22: ='Annual Cash Flow'!J41 -> 5699 | D22: ='Annual Cash Flow'!J42 -> 5699 | E22: =C22-D22 -> 0 | F22: 1
A23: FY24A balance sheet | B23: =IF(ABS(E23)<=F23,"OK","FAIL") -> OK | C23: ='Annual Balance Sheet'!K29 -> 61077 | D23: ='Annual Balance Sheet'!K51 -> 61077 | E23: =C23-D23 -> 0 | F23: 1
A24: FY24A cash tie | B24: =IF(ABS(E24)<=F24,"OK","FAIL") -> OK | C24: ='Annual Cash Flow'!K41 -> 3213 | D24: ='Annual Cash Flow'!K42 -> 3213 | E24: =C24-D24 -> 0 | F24: 1
A25: FY25A balance sheet | B25: =IF(ABS(E25)<=F25,"OK","FAIL") -> OK | C25: ='Annual Balance Sheet'!L29 -> 124907 | D25: ='Annual Balance Sheet'!L51 -> 124907 | E25: =C25-D25 -> 0 | F25: 1
A26: FY25A cash tie | B26: =IF(ABS(E26)<=F26,"OK","FAIL") -> OK | C26: ='Annual Cash Flow'!L41 -> 7956 | D26: ='Annual Cash Flow'!L42 -> 7956 | E26: =C26-D26 -> 0 | F26: 1
A27: FY26A balance sheet | B27: =IF(ABS(E27)<=F27,"OK","FAIL") -> OK | C27: ='Annual Balance Sheet'!M29 -> 148814 | D27: ='Annual Balance Sheet'!M51 -> 148814 | E27: =C27-D27 -> 0 | F27: 1
A28: FY26A cash tie | B28: =IF(ABS(E28)<=F28,"OK","FAIL") -> OK | C28: ='Annual Cash Flow'!M41 -> 10936 | D28: ='Annual Cash Flow'!M42 -> 10936 | E28: =C28-D28 -> 0 | F28: 1
A29: FY27E balance sheet | B29: =IF(ABS(E29)<=F29,"OK","FAIL") -> OK | C29: ='Annual Balance Sheet'!N29 -> 339314.67 | D29: ='Annual Balance Sheet'!N51 -> 339314.67 | E29: =C29-D29 -> 0 | F29: 1
A30: FY27E cash tie | B30: =IF(ABS(E30)<=F30,"OK","FAIL") -> OK | C30: ='Annual Cash Flow'!N41 -> 13436.219 | D30: ='Annual Cash Flow'!N42 -> 13436.219 | E30: =C30-D30 -> 0 | F30: 1
A31: FY28E balance sheet | B31: =IF(ABS(E31)<=F31,"OK","FAIL") -> OK | C31: ='Annual Balance Sheet'!O29 -> 352361.46 | D31: ='Annual Balance Sheet'!O51 -> 352361.46 | E31: =C31-D31 -> 0 | F31: 1
A32: FY28E cash tie | B32: =IF(ABS(E32)<=F32,"OK","FAIL") -> OK | C32: ='Annual Cash Flow'!O41 -> 8327.8618 | D32: ='Annual Cash Flow'!O42 -> 8327.8618 | E32: =C32-D32 -> 0 | F32: 1
A33: FY29E balance sheet | B33: =IF(ABS(E33)<=F33,"OK","FAIL") -> OK | C33: ='Annual Balance Sheet'!P29 -> 367297.94 | D33: ='Annual Balance Sheet'!P51 -> 367297.94 | E33: =C33-D33 -> 0 | F33: 1
A34: FY29E cash tie | B34: =IF(ABS(E34)<=F34,"OK","FAIL") -> OK | C34: ='Annual Cash Flow'!P41 -> 3716.7487 | D34: ='Annual Cash Flow'!P42 -> 3716.7487 | E34: =C34-D34 -> 0 | F34: 1
A35: FY30E balance sheet | B35: =IF(ABS(E35)<=F35,"OK","FAIL") -> OK | C35: ='Annual Balance Sheet'!Q29 -> 415418.16 | D35: ='Annual Balance Sheet'!Q51 -> 415418.16 | E35: =C35-D35 -> 0 | F35: 1
A36: FY30E cash tie | B36: =IF(ABS(E36)<=F36,"OK","FAIL") -> OK | C36: ='Annual Cash Flow'!Q41 -> 29969.931 | D36: ='Annual Cash Flow'!Q42 -> 29969.931 | E36: =C36-D36 -> 0 | F36: 1
A37: Q1 FY27 revenue spot check | B37: =IF(ABS(E37)<=F37,"OK","FAIL") -> OK | C37: ='Quarterly P&L'!AU6 -> 55277 | D37: =55277 -> 55277 | E37: =C37-D37 -> 0 | F37: 0.1
A38: Q1 FY27 PBT spot check | B38: =IF(ABS(E38)<=F38,"OK","FAIL") -> OK | C38: ='Quarterly P&L'!AU24 -> 7021 | D38: =7021 -> 7021 | E38: =C38-D38 -> 0 | F38: 0.1
A39: Q1 FY27 attributable NI spot check | B39: =IF(ABS(E39)<=F39,"OK","FAIL") -> OK | C39: ='Quarterly P&L'!AU28 -> 5186 | D39: =5186 -> 5186 | E39: =C39-D39 -> 0 | F39: 0.1
A40: Q1 FY27 balance-sheet anchor | B40: =IF(ABS(E40)<=F40,"OK","FAIL") -> OK | C40: ='Acquisition & Debt'!C33 -> 335405 | D40: ='Acquisition & Debt'!C44 -> 335405 | E40: =C40-D40 -> 0 | F40: 0.1
A41: FY16 quarterly revenue vs audited annual bridge | B41: =IF(ABS(E41)<=F41,"OK","FAIL") -> OK | C41: =SUM('Quarterly P&L'!C6:F6) -> 26824 | D41: ='Annual P&L'!C7 -> 26824.049 | E41: =C41-D41 -> -0.048784 | F41: 1500
A42: FY17 quarterly revenue vs audited annual bridge | B42: =IF(ABS(E42)<=F42,"OK","FAIL") -> OK | C42: =SUM('Quarterly P&L'!G6:J6) -> 28021 | D42: ='Annual P&L'!D7 -> 28021 | E42: =C42-D42 -> 0 | F42: 1500
A43: FY18 quarterly revenue vs audited annual bridge | B43: =IF(ABS(E43)<=F43,"OK","FAIL") -> OK | C43: =SUM('Quarterly P&L'!K6:N6) -> 29914 | D43: ='Annual P&L'!E7 -> 29914 | E43: =C43-D43 -> 0 | F43: 1500
A44: FY19 quarterly revenue vs audited annual bridge | B44: =IF(ABS(E44)<=F44,"OK","FAIL") -> OK | C44: =SUM('Quarterly P&L'!O6:R6) -> 36762 | D44: ='Annual P&L'!F7 -> 36762 | E44: =C44-D44 -> 0 | F44: 1500
A45: FY20 quarterly revenue vs audited annual bridge | B45: =IF(ABS(E45)<=F45,"OK","FAIL") -> OK | C45: =SUM('Quarterly P&L'!S6:V6) -> 41809 | D45: ='Annual P&L'!G7 -> 41839 | E45: =C45-D45 -> -30 | F45: 1500
A46: FY21 quarterly revenue vs audited annual bridge | B46: =IF(ABS(E46)<=F46,"OK","FAIL") -> OK | C46: =SUM('Quarterly P&L'!W6:Z6) -> 46628 | D46: ='Annual P&L'!H7 -> 46628 | E46: =C46-D46 -> 0 | F46: 1500
A47: FY22 quarterly revenue vs audited annual bridge | B47: =IF(ABS(E47)<=F47,"OK","FAIL") -> OK | C47: =SUM('Quarterly P&L'!AA6:AD6) -> 64320 | D47: ='Annual P&L'!I7 -> 64320 | E47: =C47-D47 -> 0 | F47: 1500
A48: FY23 quarterly revenue vs audited annual bridge | B48: =IF(ABS(E48)<=F48,"OK","FAIL") -> OK | C48: =SUM('Quarterly P&L'!AE6:AH6) -> 80146 | D48: ='Annual P&L'!J7 -> 80146 | E48: =C48-D48 -> 0 | F48: 1500
A49: FY24 quarterly revenue vs audited annual bridge | B49: =IF(ABS(E49)<=F49,"OK","FAIL") -> OK | C49: =SUM('Quarterly P&L'!AI6:AL6) -> 91790 | D49: ='Annual P&L'!K7 -> 91790 | E49: =C49-D49 -> 0 | F49: 1500
A50: FY25 quarterly revenue vs audited annual bridge | B50: =IF(ABS(E50)<=F50,"OK","FAIL") -> OK | C50: =SUM('Quarterly P&L'!AM6:AP6) -> 122035 | D50: ='Annual P&L'!L7 -> 120733 | E50: =C50-D50 -> 1302 | F50: 1500
A51: FY26 quarterly revenue vs audited annual bridge | B51: =IF(ABS(E51)<=F51,"OK","FAIL") -> OK | C51: =SUM('Quarterly P&L'!AQ6:AT6) -> 163128 | D51: ='Annual P&L'!M7 -> 164027 | E51: =C51-D51 -> -899 | F51: 1500
A52: FY27E revenue-driver tie | B52: =IF(ABS(E52)<=F52,"OK","FAIL") -> OK | C52: ='Order Book & Revenue'!N31 -> 228523.77 | D52: ='Annual P&L'!N7 -> 228523.77 | E52: =C52-D52 -> 0 | F52: 0.1
A53: FY27E contract mix | B53: =IF(ABS(E53)<=F53,"OK","FAIL") -> OK | C53: ='Geography & Delivery'!N19 -> 1 | D53: =1 -> 1 | E53: =C53-D53 -> 0 | F53: 0.001
A54: FY27E non-negative cash | B54: =IF(ABS(E54)<=F54,"OK","FAIL") -> OK | C54: =MIN(0,'Annual Cash Flow'!N41) -> 0 | D54: =0 -> 0 | E54: =C54-D54 -> 0 | F54: 0.1
A55: FY27E debt schedule | B55: =IF(ABS(E55)<=F55,"OK","FAIL") -> OK | C55: ='Annual Balance Sheet'!N42 -> 46060 | D55: ='Acquisition & Debt'!C21 -> 46060 | E55: =C55-D55 -> 0 | F55: 0.1
A56: FY27E valuation weights | B56: =IF(ABS(E56)<=F56,"OK","FAIL") -> OK | C56: =SUM(Valuation!N29:N31) -> 1 | D56: =1 -> 1 | E56: =C56-D56 -> 0 | F56: 0.001
A57: FY28E revenue-driver tie | B57: =IF(ABS(E57)<=F57,"OK","FAIL") -> OK | C57: ='Order Book & Revenue'!O31 -> 293835.96 | D57: ='Annual P&L'!O7 -> 293835.96 | E57: =C57-D57 -> 0 | F57: 0.1
A58: FY28E contract mix | B58: =IF(ABS(E58)<=F58,"OK","FAIL") -> OK | C58: ='Geography & Delivery'!O19 -> 1 | D58: =1 -> 1 | E58: =C58-D58 -> 0 | F58: 0.001
