Workbook

Sheet Cover
A1: HCLTech Annual Operating & Financial Model
A2: FY16–FY26 actual | FY27–FY30 forecast | INR crore unless noted
A4: Quarterly only for P&L; annual-only balance sheet, cash flow, segment, client and workforce model
A6: Model status | B6: ='Checks & Sources'!G17 -> REVIEW
A7: Historical period | B7: FY16–FY26
A8: Forecast period | B8: FY27–FY30
A9: FY16 convention | B9: Nine-month transition year
A10: Core currency | B10: INR crore
A11: Quarterly scope | B11: P&L only
A12: Revenue method | B12: Billable employees × prior revenue/billable employee × productivity factor
A13: AI adjustment | B13: T&M mix × AI deflation; fixed-price share receives productivity uplift
A14: Forecast cells | B14: Formula-driven; editable assumptions in blue/yellow
A15: Historical sources | B15: HCLTech filings and compiled market-statement extracts
A16: Version | B16: 2026-08-22
A17: Important | B17: Some historical BS components, mix and client metrics are explicit model estimates where a consistent FY16–FY26 disclosure series was unavailable.

Sheet Fin Summary
A1: HCLTech — Financial Summary
A2: INR crore unless stated otherwise | FY16–FY26 actuals; FY27–FY30 estimates | all figures linked to model schedules
A4: Profit & Loss Statement | B4: FY16A | C4: FY17A | D4: FY18A | E4: FY19A | F4: FY20A | G4: FY21A | H4: FY22A | I4: FY23A | J4: FY24A | K4: FY25A | L4: FY26A | M4: FY27E | N4: FY28E | O4: FY29E | P4: FY30E | R4: Key Ratios | S4: FY16A | T4: FY17A | U4: FY18A | V4: FY19A | W4: FY20A | X4: FY21A | Y4: FY22A | Z4: FY23A | AA4: FY24A | AB4: FY25A | AC4: FY26A | AD4: FY27E | AE4: FY28E | AF4: FY29E | AG4: FY30E
A5: Revenue | B5: ='Annual P&L'!B5 -> 31136 | C5: ='Annual P&L'!C5 -> 46722 | D5: ='Annual P&L'!D5 -> 50570 | E5: ='Annual P&L'!E5 -> 60428 | F5: ='Annual P&L'!F5 -> 70678 | G5: ='Annual P&L'!G5 -> 75379 | H5: ='Annual P&L'!H5 -> 85651 | I5: ='Annual P&L'!I5 -> 101456 | ... P5: ='Annual P&L'!P5 -> 156486.23 | R5: Growth (%)
A6: Growth | B6: ='Annual P&L'!B6 -> 0 | C6: ='Annual P&L'!C6 -> 0.50057811 | D6: ='Annual P&L'!D6 -> 0.082359488 | E6: ='Annual P&L'!E6 -> 0.19493771 | F6: ='Annual P&L'!F6 -> 0.16962335 | G6: ='Annual P&L'!G6 -> 0.066512918 | H6: ='Annual P&L'!H6 -> 0.13627138 | I6: ='Annual P&L'!I6 -> 0.18452791 | ... P6: ='Annual P&L'!P6 -> 0.052983298 | R6: Revenue | S6: =0 -> 0 | T6: =IFERROR('Annual P&L'!C5/'Annual P&L'!B5-1,0) -> 0.50057811 | U6: =IFERROR('Annual P&L'!D5/'Annual P&L'!C5-1,0) -> 0.082359488 | V6: =IFERROR('Annual P&L'!E5/'Annual P&L'!D5-1,0) -> 0.19493771 | W6: =IFERROR('Annual P&L'!F5/'Annual P&L'!E5-1,0) -> 0.16962335 | X6: =IFERROR('Annual P&L'!G5/'Annual P&L'!F5-1,0) -> 0.066512918 | Y6: =IFERROR('Annual P&L'!H5/'Annual P&L'!G5-1,0) -> 0.13627138 | Z6: =IFERROR('Annual P&L'!I5/'Annual P&L'!H5-1,0) -> 0.18452791 | AA6: =IFERROR('Annual P&L'!J5/'Annual P&L'!I5-1,0) -> 0.083356332 | ... AG6: =IFERROR('Annual P&L'!P5/'Annual P&L'!O5-1,0) -> 0.052983298
A7: Gross profit | B7: ='Annual P&L'!B8 -> 10663.281 | C7: ='Annual P&L'!C8 -> 15833 | D7: ='Annual P&L'!D8 -> 17333 | E7: ='Annual P&L'!E8 -> 21160 | F7: ='Annual P&L'!F8 -> 25383 | G7: ='Annual P&L'!G8 -> 29404 | H7: ='Annual P&L'!H8 -> 31235 | I7: ='Annual P&L'!I8 -> 35301 | ... P7: ='Annual P&L'!P8 -> 53205.317 | R7: EBITDA | S7: =0 -> 0 | T7: =IFERROR('Annual P&L'!C14/'Annual P&L'!B14-1,0) -> 0.53994314 | U7: =IFERROR('Annual P&L'!D14/'Annual P&L'!C14-1,0) -> 0.10970996 | V7: =IFERROR('Annual P&L'!E14/'Annual P&L'!D14-1,0) -> 0.22106643 | W7: =IFERROR('Annual P&L'!F14/'Annual P&L'!E14-1,0) -> 0.19500322 | X7: =IFERROR('Annual P&L'!G14/'Annual P&L'!F14-1,0) -> 0.16701611 | Y7: =IFERROR('Annual P&L'!H14/'Annual P&L'!G14-1,0) -> 0.046096196 | Z7: =IFERROR('Annual P&L'!I14/'Annual P&L'!H14-1,0) -> 0.11040777 | AA7: =IFERROR('Annual P&L'!J14/'Annual P&L'!I14-1,0) -> 0.06942419 | ... AG7: =IFERROR('Annual P&L'!P14/'Annual P&L'!O14-1,0) -> 0.052983298
A8: Gross margin | B8: ='Annual P&L'!B9 -> 0.34247433 | C8: ='Annual P&L'!C9 -> 0.33887676 | D8: ='Annual P&L'!D9 -> 0.34275262 | E8: ='Annual P&L'!E9 -> 0.3501688 | F8: ='Annual P&L'!F9 -> 0.3591358 | G8: ='Annual P&L'!G9 -> 0.39008212 | H8: ='Annual P&L'!H9 -> 0.36467759 | I8: ='Annual P&L'!I9 -> 0.34794394 | ... P8: ='Annual P&L'!P9 -> 0.34 | R8: EBIT | S8: =0 -> 0 | T8: =IFERROR('Annual P&L'!C17/'Annual P&L'!B17-1,0) -> 0.5162357 | U8: =IFERROR('Annual P&L'!D17/'Annual P&L'!C17-1,0) -> 0.05414248 | V8: =IFERROR('Annual P&L'!E17/'Annual P&L'!D17-1,0) -> 0.18352022 | W8: =IFERROR('Annual P&L'!F17/'Annual P&L'!E17-1,0) -> 0.17189747 | X8: =IFERROR('Annual P&L'!G17/'Annual P&L'!F17-1,0) -> 0.11860247 | Y8: =IFERROR('Annual P&L'!H17/'Annual P&L'!G17-1,0) -> 0.045302013 | Z8: =IFERROR('Annual P&L'!I17/'Annual P&L'!H17-1,0) -> 0.14119027 | AA8: =IFERROR('Annual P&L'!J17/'Annual P&L'!I17-1,0) -> 0.083418988 | ... AG8: =IFERROR('Annual P&L'!P17/'Annual P&L'!O17-1,0) -> 0.052983298
A9: EBITDA | B9: ='Annual P&L'!B14 -> 6694.403 | C9: ='Annual P&L'!C14 -> 10309 | D9: ='Annual P&L'!D14 -> 11440 | E9: ='Annual P&L'!E14 -> 13969 | F9: ='Annual P&L'!F14 -> 16693 | G9: ='Annual P&L'!G14 -> 19481 | H9: ='Annual P&L'!H14 -> 20379 | I9: ='Annual P&L'!I14 -> 22629 | ... P9: ='Annual P&L'!P14 -> 30514.814 | R9: Net profit | S9: =0 -> 0 | T9: =IFERROR('Annual P&L'!C25/'Annual P&L'!B25-1,0) -> 0.51855832 | U9: =IFERROR('Annual P&L'!D25/'Annual P&L'!C25-1,0) -> 0.038429703 | V9: =IFERROR('Annual P&L'!E25/'Annual P&L'!D25-1,0) -> 0.1526987 | W9: =IFERROR('Annual P&L'!F25/'Annual P&L'!E25-1,0) -> 0.092759064 | X9: =IFERROR('Annual P&L'!G25/'Annual P&L'!F25-1,0) -> 0.12393781 | Y9: =IFERROR('Annual P&L'!H25/'Annual P&L'!G25-1,0) -> 0.085819995 | Z9: =IFERROR('Annual P&L'!I25/'Annual P&L'!H25-1,0) -> 0.10007407 | AA9: =IFERROR('Annual P&L'!J25/'Annual P&L'!I25-1,0) -> 0.057302539 | ... AG9: =IFERROR('Annual P&L'!P25/'Annual P&L'!O25-1,0) -> -0.057960799
A10: EBITDA margin | B10: ='Annual P&L'!B15 -> 0.21500524 | C10: ='Annual P&L'!C15 -> 0.22064552 | D10: ='Annual P&L'!D15 -> 0.22622108 | E10: ='Annual P&L'!E15 -> 0.23116767 | F10: ='Annual P&L'!F15 -> 0.23618382 | G10: ='Annual P&L'!G15 -> 0.25844068 | H10: ='Annual P&L'!H15 -> 0.23793067 | I10: ='Annual P&L'!I15 -> 0.2230425 | ... P10: ='Annual P&L'!P15 -> 0.195 | R10: EPS | S10: =0 -> 0 | T10: =IFERROR('Annual P&L'!C29/'Annual P&L'!B29-1,0) -> 0.51804008 | U10: =IFERROR('Annual P&L'!D29/'Annual P&L'!C29-1,0) -> 0.045278421 | V10: =IFERROR('Annual P&L'!E29/'Annual P&L'!D29-1,0) -> 0.17581479 | W10: =IFERROR('Annual P&L'!F29/'Annual P&L'!E29-1,0) -> 0.10824117 | X10: =IFERROR('Annual P&L'!G29/'Annual P&L'!F29-1,0) -> 0.12390848 | Y10: =IFERROR('Annual P&L'!H29/'Annual P&L'!G29-1,0) -> 0.08636129 | Z10: =IFERROR('Annual P&L'!I29/'Annual P&L'!H29-1,0) -> 0.10114778 | AA10: =IFERROR('Annual P&L'!J29/'Annual P&L'!I29-1,0) -> 0.056060865 | ... AG10: =IFERROR('Annual P&L'!P29/'Annual P&L'!O29-1,0) -> -0.057960799
A11: EBIT | B11: ='Annual P&L'!B17 -> 6249.0284 | C11: ='Annual P&L'!C17 -> 9475 | D11: ='Annual P&L'!D17 -> 9988 | E11: ='Annual P&L'!E17 -> 11821 | F11: ='Annual P&L'!F17 -> 13853 | G11: ='Annual P&L'!G17 -> 15496 | H11: ='Annual P&L'!H17 -> 16198 | I11: ='Annual P&L'!I17 -> 18485 | ... P11: ='Annual P&L'!P17 -> 25037.796
A12: EBIT margin | B12: ='Annual P&L'!B18 -> 0.20070107 | C12: ='Annual P&L'!C18 -> 0.20279526 | D12: ='Annual P&L'!D18 -> 0.1975084 | E12: ='Annual P&L'!E18 -> 0.19562124 | F12: ='Annual P&L'!F18 -> 0.19600158 | G12: ='Annual P&L'!G18 -> 0.2055745 | H12: ='Annual P&L'!H18 -> 0.1891163 | I12: ='Annual P&L'!I18 -> 0.18219721 | ... P12: ='Annual P&L'!P18 -> 0.16 | R12: Margins (%)
A13: PBT | B13: ='Annual P&L'!B21 -> 7046.6605 | C13: ='Annual P&L'!C21 -> 10409 | D13: ='Annual P&L'!D21 -> 11099 | E13: ='Annual P&L'!E21 -> 12626 | F13: ='Annual P&L'!F21 -> 14032 | G13: ='Annual P&L'!G21 -> 16153 | H13: ='Annual P&L'!H21 -> 16975 | I13: ='Annual P&L'!I21 -> 19488 | ... P13: ='Annual P&L'!P21 -> 21070.931 | R13: Gross margin | S13: ='Annual P&L'!B9 -> 0.34247433 | T13: ='Annual P&L'!C9 -> 0.33887676 | U13: ='Annual P&L'!D9 -> 0.34275262 | V13: ='Annual P&L'!E9 -> 0.3501688 | W13: ='Annual P&L'!F9 -> 0.3591358 | X13: ='Annual P&L'!G9 -> 0.39008212 | Y13: ='Annual P&L'!H9 -> 0.36467759 | Z13: ='Annual P&L'!I9 -> 0.34794394 | ... AG13: ='Annual P&L'!P9 -> 0.34
A14: PBT margin | B14: ='Annual P&L'!B22 -> 0.22631875 | C14: ='Annual P&L'!C22 -> 0.22278584 | D14: ='Annual P&L'!D22 -> 0.21947795 | E14: ='Annual P&L'!E22 -> 0.20894287 | F14: ='Annual P&L'!F22 -> 0.1985342 | G14: ='Annual P&L'!G22 -> 0.21429045 | H14: ='Annual P&L'!H22 -> 0.198188 | I14: ='Annual P&L'!I22 -> 0.19208327 | ... P14: ='Annual P&L'!P22 -> 0.13465038 | R14: EBITDA margin | S14: ='Annual P&L'!B15 -> 0.21500524 | T14: ='Annual P&L'!C15 -> 0.22064552 | U14: ='Annual P&L'!D15 -> 0.22622108 | V14: ='Annual P&L'!E15 -> 0.23116767 | W14: ='Annual P&L'!F15 -> 0.23618382 | X14: ='Annual P&L'!G15 -> 0.25844068 | Y14: ='Annual P&L'!H15 -> 0.23793067 | Z14: ='Annual P&L'!I15 -> 0.2230425 | ... AG14: ='Annual P&L'!P15 -> 0.195
A15: Income tax | B15: ='Annual P&L'!B23 -> 1477.5626 | C15: ='Annual P&L'!C23 -> 1952 | D15: ='Annual P&L'!D23 -> 2317 | E15: ='Annual P&L'!E23 -> 2481 | F15: ='Annual P&L'!F23 -> 2938 | G15: ='Annual P&L'!G23 -> 3663 | H15: ='Annual P&L'!H23 -> 3443 | I15: ='Annual P&L'!I23 -> 4642 | ... P15: ='Annual P&L'!P23 -> 5267.7327 | R15: EBIT margin | S15: ='Annual P&L'!B18 -> 0.20070107 | T15: ='Annual P&L'!C18 -> 0.20279526 | U15: ='Annual P&L'!D18 -> 0.1975084 | V15: ='Annual P&L'!E18 -> 0.19562124 | W15: ='Annual P&L'!F18 -> 0.19600158 | X15: ='Annual P&L'!G18 -> 0.2055745 | Y15: ='Annual P&L'!H18 -> 0.1891163 | Z15: ='Annual P&L'!I18 -> 0.18219721 | ... AG15: ='Annual P&L'!P18 -> 0.16
A16: Net profit | B16: ='Annual P&L'!B25 -> 5569.0979 | C16: ='Annual P&L'!C25 -> 8457 | D16: ='Annual P&L'!D25 -> 8782 | E16: ='Annual P&L'!E25 -> 10123 | F16: ='Annual P&L'!F25 -> 11062 | G16: ='Annual P&L'!G25 -> 12433 | H16: ='Annual P&L'!H25 -> 13500 | I16: ='Annual P&L'!I25 -> 14851 | ... P16: ='Annual P&L'!P25 -> 15803.198 | R16: PBT margin | S16: ='Annual P&L'!B22 -> 0.22631875 | T16: ='Annual P&L'!C22 -> 0.22278584 | U16: ='Annual P&L'!D22 -> 0.21947795 | V16: ='Annual P&L'!E22 -> 0.20894287 | W16: ='Annual P&L'!F22 -> 0.1985342 | X16: ='Annual P&L'!G22 -> 0.21429045 | Y16: ='Annual P&L'!H22 -> 0.198188 | Z16: ='Annual P&L'!I22 -> 0.19208327 | ... AG16: ='Annual P&L'!P22 -> 0.13465038
A17: Net margin | B17: ='Annual P&L'!B26 -> 0.17886363 | C17: ='Annual P&L'!C26 -> 0.18100681 | D17: ='Annual P&L'!D26 -> 0.17366027 | E17: ='Annual P&L'!E26 -> 0.16752168 | F17: ='Annual P&L'!F26 -> 0.15651263 | G17: ='Annual P&L'!G26 -> 0.16493984 | H17: ='Annual P&L'!H26 -> 0.15761637 | I17: ='Annual P&L'!I26 -> 0.14637873 | ... P17: ='Annual P&L'!P26 -> 0.10098779 | R17: Net margin | S17: ='Annual P&L'!B26 -> 0.17886363 | T17: ='Annual P&L'!C26 -> 0.18100681 | U17: ='Annual P&L'!D26 -> 0.17366027 | V17: ='Annual P&L'!E26 -> 0.16752168 | W17: ='Annual P&L'!F26 -> 0.15651263 | X17: ='Annual P&L'!G26 -> 0.16493984 | Y17: ='Annual P&L'!H26 -> 0.15761637 | Z17: ='Annual P&L'!I26 -> 0.14637873 | ... AG17: ='Annual P&L'!P26 -> 0.10098779
A18: Basic EPS | B18: ='Annual P&L'!B29 -> 19.71516 | C18: ='Annual P&L'!C29 -> 29.928404 | D18: ='Annual P&L'!D29 -> 31.283515 | E18: ='Annual P&L'!E29 -> 36.783619 | F18: ='Annual P&L'!F29 -> 40.765121 | G18: ='Annual P&L'!G29 -> 45.816265 | H18: ='Annual P&L'!H29 -> 49.773017 | I18: ='Annual P&L'!I29 -> 54.807447 | ... P18: ='Annual P&L'!P29 -> 58.27437
A19: Diluted EPS | B19: ='Annual P&L'!B30 -> 19.71516 | C19: ='Annual P&L'!C30 -> 29.928404 | D19: ='Annual P&L'!D30 -> 31.283515 | E19: ='Annual P&L'!E30 -> 36.783619 | F19: ='Annual P&L'!F30 -> 40.765121 | G19: ='Annual P&L'!G30 -> 45.816265 | H19: ='Annual P&L'!H30 -> 49.773017 | I19: ='Annual P&L'!I30 -> 54.807447 | ... P19: ='Annual P&L'!P30 -> 58.158054 | R19: Returns (%)
A20: Weighted-average basic shares | B20: ='Annual P&L'!B27 -> 282.47794 | C20: ='Annual P&L'!C27 -> 282.57438 | D20: ='Annual P&L'!D27 -> 280.72293 | E20: ='Annual P&L'!E27 -> 275.20402 | F20: ='Annual P&L'!F27 -> 271.35943 | G20: ='Annual P&L'!G27 -> 271.36651 | H20: ='Annual P&L'!H27 -> 271.2313 | I20: ='Annual P&L'!I27 -> 270.96683 | ... P20: ='Annual P&L'!P27 -> 271.18608 | R20: ROE | S20: ='Annual Balance Sheet'!B24 -> 0.19873949 | T20: ='Annual Balance Sheet'!C24 -> 0.2749685 | U20: ='Annual Balance Sheet'!D24 -> 0.24981794 | V20: ='Annual Balance Sheet'!E24 -> 0.25614619 | W20: ='Annual Balance Sheet'!F24 -> 0.23426762 | X20: ='Annual Balance Sheet'!G24 -> 0.21753889 | Y20: ='Annual Balance Sheet'!H24 -> 0.21757174 | Z20: ='Annual Balance Sheet'!I24 -> 0.2331324 | ... AG20: ='Annual Balance Sheet'!P24 -> 0.2531182
A21: Weighted-average diluted shares | B21: ='Annual P&L'!B28 -> 282.47794 | C21: ='Annual P&L'!C28 -> 282.57438 | D21: ='Annual P&L'!D28 -> 280.72293 | E21: ='Annual P&L'!E28 -> 275.20402 | F21: ='Annual P&L'!F28 -> 271.35943 | G21: ='Annual P&L'!G28 -> 271.36651 | H21: ='Annual P&L'!H28 -> 271.2313 | I21: ='Annual P&L'!I28 -> 270.96683 | ... P21: ='Annual P&L'!P28 -> 271.72845 | R21: ROA | S21: =IFERROR('Annual P&L'!B25/'Annual Balance Sheet'!B12,0) -> 0.14004214 | T21: =IFERROR('Annual P&L'!C25/'Annual Balance Sheet'!C12,0) -> 0.18213653 | U21: =IFERROR('Annual P&L'!D25/'Annual Balance Sheet'!D12,0) -> 0.18131479 | V21: =IFERROR('Annual P&L'!E25/'Annual Balance Sheet'!E12,0) -> 0.17187924 | W21: =IFERROR('Annual P&L'!F25/'Annual Balance Sheet'!F12,0) -> 0.13293117 | X21: =IFERROR('Annual P&L'!G25/'Annual Balance Sheet'!G12,0) -> 0.14176254 | Y21: =IFERROR('Annual P&L'!H25/'Annual Balance Sheet'!H12,0) -> 0.15162917 | Z21: =IFERROR('Annual P&L'!I25/'Annual Balance Sheet'!I12,0) -> 0.15898556 | ... AG21: =IFERROR('Annual P&L'!P25/'Annual Balance Sheet'!P12,0) -> -0.29194047
R22: FCF margin | S22: ='Annual Cash Flow'!B22 -> 504.6 | T22: ='Annual Cash Flow'!C22 -> -431.5 | U22: ='Annual Cash Flow'!D22 -> -104.6 | V22: ='Annual Cash Flow'!E22 -> 3548.9 | W22: ='Annual Cash Flow'!F22 -> 3578 | X22: ='Annual Cash Flow'!G22 -> -1390 | Y22: ='Annual Cash Flow'!H22 -> 169 | Z22: ='Annual Cash Flow'!I22 -> -1557 | ... AG22: ='Annual Cash Flow'!P22 -> 0
A24: Cash Flow Statement | B24: FY16A | C24: FY17A | D24: FY18A | E24: FY19A | F24: FY20A | G24: FY21A | H24: FY22A | I24: FY23A | J24: FY24A | K24: FY25A | L24: FY26A | M24: FY27E | N24: FY28E | O24: FY29E | P24: FY30E | R24: Gearing
A25: Net profit | B25: ='Annual Cash Flow'!B5 -> 5569.0979 | C25: ='Annual Cash Flow'!C5 -> 8457 | D25: ='Annual Cash Flow'!D5 -> 8782 | E25: ='Annual Cash Flow'!E5 -> 10123 | F25: ='Annual Cash Flow'!F5 -> 11062 | G25: ='Annual Cash Flow'!G5 -> 12433 | H25: ='Annual Cash Flow'!H5 -> 13500 | I25: ='Annual Cash Flow'!I5 -> 14851 | ... P25: ='Annual Cash Flow'!P5 -> 15803.198 | R25: Net debt / EBITDA | S25: =IFERROR(-'Annual Balance Sheet'!B22/'Annual P&L'!B14,0) -> -1.6251636 | T25: =IFERROR(-'Annual Balance Sheet'!C22/'Annual P&L'!C14,0) -> -1.1776215 | U25: =IFERROR(-'Annual Balance Sheet'!D22/'Annual P&L'!D14,0) -> -0.85979021 | V25: =IFERROR(-'Annual Balance Sheet'!E22/'Annual P&L'!E14,0) -> -0.55551578 | W25: =IFERROR(-'Annual Balance Sheet'!F22/'Annual P&L'!F14,0) -> -0.46780087 | X25: =IFERROR(-'Annual Balance Sheet'!G22/'Annual P&L'!G14,0) -> -0.73486987 | Y25: =IFERROR(-'Annual Balance Sheet'!H22/'Annual P&L'!H14,0) -> -0.76254968 | Z25: =IFERROR(-'Annual Balance Sheet'!I22/'Annual P&L'!I14,0) -> -0.79216934 | ... AG25: =IFERROR(-'Annual Balance Sheet'!P22/'Annual P&L'!P14,0) -> 5.367081
A26: D&A | B26: ='Annual Cash Flow'!B6 -> 445.37462 | C26: ='Annual Cash Flow'!C6 -> 834 | D26: ='Annual Cash Flow'!D6 -> 1452 | E26: ='Annual Cash Flow'!E6 -> 2148 | F26: ='Annual Cash Flow'!F6 -> 2840 | G26: ='Annual Cash Flow'!G6 -> 3985 | H26: ='Annual Cash Flow'!H6 -> 4181 | I26: ='Annual Cash Flow'!I6 -> 4144 | ... P26: ='Annual Cash Flow'!P6 -> 5477.0179 | R26: Debt / equity | S26: =IFERROR('Annual Balance Sheet'!B14/'Annual Balance Sheet'!B19,0) -> 0.034729731 | T26: =IFERROR('Annual Balance Sheet'!C14/'Annual Balance Sheet'!C19,0) -> 0.016174784 | U26: =IFERROR('Annual Balance Sheet'!D14/'Annual Balance Sheet'!D19,0) -> 0.011872297 | V26: =IFERROR('Annual Balance Sheet'!E14/'Annual Balance Sheet'!E19,0) -> 0.094401288 | W26: =IFERROR('Annual Balance Sheet'!F14/'Annual Balance Sheet'!F19,0) -> 0.14486259 | X26: =IFERROR('Annual Balance Sheet'!G14/'Annual Balance Sheet'!G19,0) -> 0.099434701 | Y26: =IFERROR('Annual Balance Sheet'!H14/'Annual Balance Sheet'!H19,0) -> 0.10229655 | Z26: =IFERROR('Annual Balance Sheet'!I14/'Annual Balance Sheet'!I19,0) -> 0.073182666 | ... AG26: =IFERROR('Annual Balance Sheet'!P14/'Annual Balance Sheet'!P19,0) -> 0.078092309
A27: Other non-cash / working capital | B27: ='Annual Cash Flow'!B7 -> -823.5002 | C27: ='Annual Cash Flow'!C7 -> -934 | D27: ='Annual Cash Flow'!D7 -> -1111 | E27: ='Annual Cash Flow'!E7 -> -805 | F27: ='Annual Cash Flow'!F7 -> -179 | G27: ='Annual Cash Flow'!G7 -> -657 | H27: ='Annual Cash Flow'!H7 -> -777 | I27: ='Annual Cash Flow'!I7 -> -1003 | ... P27: ='Annual Cash Flow'!P7 -> 0 | R27: Net debt / equity | S27: =IFERROR(-'Annual Balance Sheet'!B22/'Annual Balance Sheet'!B19,0) -> -0.38824713 | T27: =IFERROR(-'Annual Balance Sheet'!C22/'Annual Balance Sheet'!C19,0) -> -0.36249492 | U27: =IFERROR(-'Annual Balance Sheet'!D22/'Annual Balance Sheet'!D19,0) -> -0.26716064 | V27: =IFERROR(-'Annual Balance Sheet'!E22/'Annual Balance Sheet'!E19,0) -> -0.18378174 | W27: =IFERROR(-'Annual Balance Sheet'!F22/'Annual Balance Sheet'!F19,0) -> -0.14955473 | X27: =IFERROR(-'Annual Balance Sheet'!G22/'Annual Balance Sheet'!G19,0) -> -0.23056482 | Y27: =IFERROR(-'Annual Balance Sheet'!H22/'Annual Balance Sheet'!H19,0) -> -0.25062091 | Z27: =IFERROR(-'Annual Balance Sheet'!I22/'Annual Balance Sheet'!I19,0) -> -0.27410624 | ... AG27: =IFERROR(-'Annual Balance Sheet'!P22/'Annual Balance Sheet'!P19,0) -> 2.452465
A28: Cash flow from operations | B28: ='Annual Cash Flow'!B12 -> 4157.9723 | C28: ='Annual Cash Flow'!C12 -> 9343.5 | D28: ='Annual Cash Flow'!D12 -> 6898.1 | E28: ='Annual Cash Flow'!E12 -> 9151 | F28: ='Annual Cash Flow'!F12 -> 18739 | G28: ='Annual Cash Flow'!G12 -> 12116 | H28: ='Annual Cash Flow'!H12 -> 14567 | I28: ='Annual Cash Flow'!I12 -> 15691 | ... P28: ='Annual Cash Flow'!P12 -> 19697.42
A29: CFO / net profit | B29: ='Annual Cash Flow'!B13 -> 0.74661505 | C29: ='Annual Cash Flow'!C13 -> 1.1048244 | D29: ='Annual Cash Flow'!D13 -> 0.78548167 | E29: ='Annual Cash Flow'!E13 -> 0.90398103 | F29: ='Annual Cash Flow'!F13 -> 1.6939975 | G29: ='Annual Cash Flow'!G13 -> 0.97450334 | H29: ='Annual Cash Flow'!H13 -> 1.079037 | I29: ='Annual Cash Flow'!I13 -> 1.0565618 | ... P29: ='Annual Cash Flow'!P13 -> 1.2464199 | R29: Operating KPIs
A30: Capex | B30: ='Annual Cash Flow'!B18 -> -2164.2746 | C30: ='Annual Cash Flow'!C18 -> -6197.7 | D30: ='Annual Cash Flow'!D18 -> -4936.2 | E30: ='Annual Cash Flow'!E18 -> -6053.6 | F30: ='Annual Cash Flow'!F18 -> -17633 | G30: ='Annual Cash Flow'!G18 -> -3483 | H30: ='Annual Cash Flow'!H18 -> -1600 | I30: ='Annual Cash Flow'!I18 -> -3597 | ... P30: ='Annual Cash Flow'!P18 -> -5477.0179 | R30: Closing headcount | S30: ='Revenue Drivers'!B7 -> 106107 | T30: ='Revenue Drivers'!C7 -> 117781 | U30: ='Revenue Drivers'!D7 -> 120081 | V30: ='Revenue Drivers'!E7 -> 137965 | W30: ='Revenue Drivers'!F7 -> 150423 | X30: ='Revenue Drivers'!G7 -> 168977 | Y30: ='Revenue Drivers'!H7 -> 208877 | Z30: ='Revenue Drivers'!I7 -> 225944 | ... AG30: ='Revenue Drivers'!P7 -> 260074.61
A31: Acquisitions / investments | B31: ='Annual Cash Flow'!B19 -> -960.3 | C31: ='Annual Cash Flow'!C19 -> -3124.5746 | D31: ='Annual Cash Flow'!D19 -> -9322.2746 | E31: ='Annual Cash Flow'!E19 -> -14258.475 | F31: ='Annual Cash Flow'!F19 -> -20312.075 | G31: ='Annual Cash Flow'!G19 -> -37945.075 | H31: ='Annual Cash Flow'!H19 -> -41428.075 | I31: ='Annual Cash Flow'!I19 -> -43028.075 | ... P31: ='Annual Cash Flow'!P19 -> -76927.801 | R31: Billable employees | S31: ='Revenue Drivers'!B9 -> 82763.46 | T31: ='Revenue Drivers'!C9 -> 91869.18 | U31: ='Revenue Drivers'!D9 -> 94863.99 | V31: ='Revenue Drivers'!E9 -> 108992.35 | W31: ='Revenue Drivers'!F9 -> 120338.4 | X31: ='Revenue Drivers'!G9 -> 135181.6 | Y31: ='Revenue Drivers'!H9 -> 169190.37 | Z31: ='Revenue Drivers'!I9 -> 183014.64 | ... AG31: ='Revenue Drivers'!P9 -> 213261.18
A32: Cash flow from investing | B32: ='Annual Cash Flow'!B20 -> -3124.5746 | C32: ='Annual Cash Flow'!C20 -> -9322.2746 | D32: ='Annual Cash Flow'!D20 -> -14258.475 | E32: ='Annual Cash Flow'!E20 -> -20312.075 | F32: ='Annual Cash Flow'!F20 -> -37945.075 | G32: ='Annual Cash Flow'!G20 -> -41428.075 | H32: ='Annual Cash Flow'!H20 -> -43028.075 | I32: ='Annual Cash Flow'!I20 -> -46625.075 | ... P32: ='Annual Cash Flow'!P20 -> -82404.819 | R32: Attrition | S32: ='Revenue Drivers'!B11 -> 0.37620467 | T32: ='Revenue Drivers'!C11 -> 0.51777974 | U32: ='Revenue Drivers'!D11 -> 0.53306845 | V32: ='Revenue Drivers'!E11 -> 0.55441506 | W32: ='Revenue Drivers'!F11 -> 0.58731045 | X32: ='Revenue Drivers'!G11 -> 0.55761287 | Y32: ='Revenue Drivers'!H11 -> 0.5062404 | Z32: ='Revenue Drivers'!I11 -> 0.55436002 | ... AG32: ='Revenue Drivers'!P11 -> 0.73377735
A33: Debt issuance / (repayment) | B33: ='Annual Cash Flow'!B22 -> 504.6 | C33: ='Annual Cash Flow'!C22 -> -431.5 | D33: ='Annual Cash Flow'!D22 -> -104.6 | E33: ='Annual Cash Flow'!E22 -> 3548.9 | F33: ='Annual Cash Flow'!F22 -> 3578 | G33: ='Annual Cash Flow'!G22 -> -1390 | H33: ='Annual Cash Flow'!H22 -> 169 | I33: ='Annual Cash Flow'!I22 -> -1557 | ... P33: ='Annual Cash Flow'!P22 -> 0 | R33: Advanced AI revenue mix | S33: ='Revenue Drivers'!B28 -> 0 | T33: ='Revenue Drivers'!C28 -> 0 | U33: ='Revenue Drivers'!D28 -> 0 | V33: ='Revenue Drivers'!E28 -> 0 | W33: ='Revenue Drivers'!F28 -> 0 | X33: ='Revenue Drivers'!G28 -> 0 | Y33: ='Revenue Drivers'!H28 -> 0 | Z33: ='Revenue Drivers'!I28 -> 0 | ... AG33: ='Revenue Drivers'!P28 -> 0.078461044
A34: Equity issuance / (buybacks) & other | B34: ='Annual Cash Flow'!B23 -> 585.79861 | C34: ='Annual Cash Flow'!C23 -> 1092.3822 | D34: ='Annual Cash Flow'!D23 -> -4105.2942 | E34: ='Annual Cash Flow'!E23 -> -3390.9151 | F34: ='Annual Cash Flow'!F23 -> 890.11498 | G34: ='Annual Cash Flow'!G23 -> 4498.5292 | H34: ='Annual Cash Flow'!H23 -> -1652.5528 | I34: ='Annual Cash Flow'!I23 -> 1534.0816 | ... P34: ='Annual Cash Flow'!P23 -> 0 | R34: Software ARR growth | S34: =0 -> 0 | T34: ='Operating Cuts'!C22 -> 0 | U34: ='Operating Cuts'!D22 -> 0 | V34: ='Operating Cuts'!E22 -> 0 | W34: ='Operating Cuts'!F22 -> 0 | X34: ='Operating Cuts'!G22 -> 0 | Y34: ='Operating Cuts'!H22 -> 0 | Z34: ='Operating Cuts'!I22 -> 0.052 | AA34: ='Operating Cuts'!J22 -> 0.007 | ... AG34: ='Operating Cuts'!P22 -> 0.08
A35: Dividends | B35: ='Annual Cash Flow'!B24 -> -2883.3965 | C35: ='Annual Cash Flow'!C24 -> -4081.0822 | D35: ='Annual Cash Flow'!D24 -> -1350.3058 | E35: ='Annual Cash Flow'!E24 -> -1324.8849 | F35: ='Annual Cash Flow'!F24 -> -1961.115 | G35: ='Annual Cash Flow'!G24 -> -7055.5292 | H35: ='Annual Cash Flow'!H24 -> -11932.447 | I35: ='Annual Cash Flow'!I24 -> -12993.082 | ... P35: ='Annual Cash Flow'!P24 -> -7111.4391
A36: Cash flow from financing | B36: ='Annual Cash Flow'!B26 -> -969.49772 | C36: ='Annual Cash Flow'!C26 -> -2486.2 | D36: ='Annual Cash Flow'!D26 -> -4449.2 | E36: ='Annual Cash Flow'!E26 -> -361.9 | F36: ='Annual Cash Flow'!F26 -> 2686 | G36: ='Annual Cash Flow'!G26 -> -3290 | H36: ='Annual Cash Flow'!H26 -> -12639 | I36: ='Annual Cash Flow'!I26 -> -12013 | ... P36: ='Annual Cash Flow'!P26 -> -7111.4391 | R36: Valuations
A37: FX / other | B37: ='Annual Cash Flow'!B27 -> 0 | C37: ='Annual Cash Flow'!C27 -> 0 | D37: ='Annual Cash Flow'!D27 -> 0 | E37: ='Annual Cash Flow'!E27 -> 0 | F37: ='Annual Cash Flow'!F27 -> 0 | G37: ='Annual Cash Flow'!G27 -> 0 | H37: ='Annual Cash Flow'!H27 -> 0 | I37: ='Annual Cash Flow'!I27 -> 0 | ... P37: ='Annual Cash Flow'!P27 -> 0 | R37: Share price (INR) | S37: ='Market Data'!C5 -> 407.04999 | T37: ='Market Data'!C6 -> 437.375 | U37: ='Market Data'!C7 -> 484.29999 | V37: ='Market Data'!C8 -> 541.45001 | W37: ='Market Data'!C9 -> 436.39999 | X37: ='Market Data'!C10 -> 982.65002 | Y37: ='Market Data'!C11 -> 1163.75 | Z37: ='Market Data'!C12 -> 1085.25 | AA37: ='Market Data'!C13 -> 1543.55 | AB37: ='Market Data'!C14 -> 1592.5 | AC37: ='Market Data'!C15 -> 1341.6 | AD37: ='Market Data'!C16 -> 1475.76 | AE37: ='Market Data'!C17 -> 1471.8198 | AF37: ='Market Data'!C18 -> 1346.3551 | AG37: ='Market Data'!C19 -> 1221.2182 | AH37: =AD37/AC37-1 -> 0.1
A38: Net change in cash | B38: ='Annual Cash Flow'!B28 -> 63.9 | C38: ='Annual Cash Flow'!C28 -> -2464.9746 | D38: ='Annual Cash Flow'!D28 -> -11809.575 | E38: ='Annual Cash Flow'!E28 -> -11522.975 | F38: ='Annual Cash Flow'!F28 -> -16520.075 | G38: ='Annual Cash Flow'!G28 -> -32602.075 | H38: ='Annual Cash Flow'!H28 -> -41100.075 | I38: ='Annual Cash Flow'!I28 -> -42947.075 | ... P38: ='Annual Cash Flow'!P28 -> -69818.839 | R38: Market capitalization | S38: =S37*'Annual P&L'!B27 -> 114982.64 | T38: =T37*'Annual P&L'!C27 -> 123590.97 | U38: =U37*'Annual P&L'!D27 -> 135954.11 | V38: =V37*'Annual P&L'!E27 -> 149009.22 | W38: =W37*'Annual P&L'!F27 -> 118421.25 | X38: =X37*'Annual P&L'!G27 -> 266658.31 | Y38: =Y37*'Annual P&L'!H27 -> 315645.42 | Z38: =Z37*'Annual P&L'!I27 -> 294066.75 | ... AG38: =AG37*'Annual P&L'!P27 -> 331177.39
A39: Opening cash | B39: ='Annual Cash Flow'!B29 -> 11788.8 | C39: ='Annual Cash Flow'!C29 -> 11852.7 | D39: ='Annual Cash Flow'!D29 -> 12681.8 | E39: ='Annual Cash Flow'!E29 -> 10273.1 | F39: ='Annual Cash Flow'!F29 -> 11746 | G39: ='Annual Cash Flow'!G29 -> 15373 | H39: ='Annual Cash Flow'!H29 -> 20490 | I39: ='Annual Cash Flow'!I29 -> 21883 | ... P39: ='Annual Cash Flow'!P29 -> -88741.64 | R39: Enterprise value | S39: =S38+'Annual Balance Sheet'!B14-'Annual Balance Sheet'!B5 -> 104103.14 | T39: =T38+'Annual Balance Sheet'!C14-'Annual Balance Sheet'!C5 -> 111450.87 | U39: =U38+'Annual Balance Sheet'!D14-'Annual Balance Sheet'!D5 -> 126118.11 | V39: =V38+'Annual Balance Sheet'!E14-'Annual Balance Sheet'!E5 -> 141249.22 | W39: =W38+'Annual Balance Sheet'!F14-'Annual Balance Sheet'!F5 -> 110612.25 | X39: =X38+'Annual Balance Sheet'!G14-'Annual Balance Sheet'!G5 -> 252342.31 | Y39: =Y38+'Annual Balance Sheet'!H14-'Annual Balance Sheet'!H5 -> 300105.42 | Z39: =Z38+'Annual Balance Sheet'!I14-'Annual Balance Sheet'!I5 -> 276140.75 | ... AG39: =AG38+'Annual Balance Sheet'!P14-'Annual Balance Sheet'!P5 -> 494952.87
A40: Closing cash | B40: ='Annual Cash Flow'!B30 -> 11852.7 | C40: ='Annual Cash Flow'!C30 -> 12681.8 | D40: ='Annual Cash Flow'!D30 -> 10273.1 | E40: ='Annual Cash Flow'!E30 -> 11746 | F40: ='Annual Cash Flow'!F30 -> 15373 | G40: ='Annual Cash Flow'!G30 -> 20490 | H40: ='Annual Cash Flow'!H30 -> 21883 | I40: ='Annual Cash Flow'!I30 -> 22712 | ... P40: ='Annual Cash Flow'!P30 -> -158560.48 | R40: P/E | S40: =IFERROR(S37/'Annual P&L'!B29,0) -> 20.646547 | T40: =IFERROR(T37/'Annual P&L'!C29,0) -> 14.614044 | U40: =IFERROR(U37/'Annual P&L'!D29,0) -> 15.480997 | V40: =IFERROR(V37/'Annual P&L'!E29,0) -> 14.719868 | W40: =IFERROR(W37/'Annual P&L'!F29,0) -> 10.70523 | X40: =IFERROR(X37/'Annual P&L'!G29,0) -> 21.447624 | Y40: =IFERROR(Y37/'Annual P&L'!H29,0) -> 23.381142 | Z40: =IFERROR(Z37/'Annual P&L'!I29,0) -> 19.801141 | ... AG40: =IFERROR(AG37/'Annual P&L'!P29,0) -> 20.956353
A41: Free cash flow | B41: ='Annual Cash Flow'!B32 -> 1993.6977 | C41: ='Annual Cash Flow'!C32 -> 3145.8 | D41: ='Annual Cash Flow'!D32 -> 1961.9 | E41: ='Annual Cash Flow'!E32 -> 3097.4 | F41: ='Annual Cash Flow'!F32 -> 1106 | G41: ='Annual Cash Flow'!G32 -> 8633 | H41: ='Annual Cash Flow'!H32 -> 12967 | I41: ='Annual Cash Flow'!I32 -> 12094 | ... P41: ='Annual Cash Flow'!P32 -> 14220.402 | R41: EV / EBITDA | S41: =IFERROR(S39/'Annual P&L'!B14,0) -> 15.550773 | T41: =IFERROR(T39/'Annual P&L'!C14,0) -> 10.811026 | U41: =IFERROR(U39/'Annual P&L'!D14,0) -> 11.024311 | V41: =IFERROR(V39/'Annual P&L'!E14,0) -> 10.11162 | W41: =IFERROR(W39/'Annual P&L'!F14,0) -> 6.6262657 | X41: =IFERROR(X39/'Annual P&L'!G14,0) -> 12.953252 | Y41: =IFERROR(Y39/'Annual P&L'!H14,0) -> 14.726209 | Z41: =IFERROR(Z39/'Annual P&L'!I14,0) -> 12.202959 | ... AG41: =IFERROR(AG39/'Annual P&L'!P14,0) -> 16.220085
A42: FCF margin | B42: ='Annual Cash Flow'!B33 -> 0.064031916 | C42: ='Annual Cash Flow'!C33 -> 0.067330166 | D42: ='Annual Cash Flow'!D33 -> 0.038795729 | E42: ='Annual Cash Flow'!E33 -> 0.051257695 | F42: ='Annual Cash Flow'!F33 -> 0.015648434 | G42: ='Annual Cash Flow'!G33 -> 0.11452792 | H42: ='Annual Cash Flow'!H33 -> 0.15139345 | I42: ='Annual Cash Flow'!I33 -> 0.11920438 | ... P42: ='Annual Cash Flow'!P33 -> 0.090873185 | R42: P / book value | S42: =IFERROR(S38/'Annual Balance Sheet'!B19,0) -> 4.1032843 | T42: =IFERROR(T38/'Annual Balance Sheet'!C19,0) -> 3.6903401 | U42: =IFERROR(U38/'Annual Balance Sheet'!D19,0) -> 3.6927195 | V42: =IFERROR(V38/'Annual Balance Sheet'!E19,0) -> 3.5290172 | W42: =IFERROR(W38/'Annual Balance Sheet'!F19,0) -> 2.2679547 | X42: =IFERROR(X38/'Annual Balance Sheet'!G19,0) -> 4.294637 | Y42: =IFERROR(Y38/'Annual Balance Sheet'!H19,0) -> 5.0905626 | Z42: =IFERROR(Z38/'Annual Balance Sheet'!I19,0) -> 4.496571 | ... AG42: =IFERROR(AG38/'Annual Balance Sheet'!P19,0) -> 4.9592343
R43: Dividend per share | S43: =IFERROR(ABS('Annual Cash Flow'!B13)/'Annual P&L'!B27,0) -> 0.0026430915 | T43: =IFERROR(ABS('Annual Cash Flow'!C13)/'Annual P&L'!C27,0) -> 0.0039098535 | U43: =IFERROR(ABS('Annual Cash Flow'!D13)/'Annual P&L'!D27,0) -> 0.0027980673 | V43: =IFERROR(ABS('Annual Cash Flow'!E13)/'Annual P&L'!E27,0) -> 0.0032847668 | W43: =IFERROR(ABS('Annual Cash Flow'!F13)/'Annual P&L'!F27,0) -> 0.0062426335 | X43: =IFERROR(ABS('Annual Cash Flow'!G13)/'Annual P&L'!G27,0) -> 0.0035910966 | Y43: =IFERROR(ABS('Annual Cash Flow'!H13)/'Annual P&L'!H27,0) -> 0.003978291 | Z43: =IFERROR(ABS('Annual Cash Flow'!I13)/'Annual P&L'!I27,0) -> 0.0038992295 | ... AB43: =IFERROR(ABS('Annual Cash Flow'!K13)/'Annual P&L'!K27,0) -> 0.00456718 | AC43: ='Market Data'!E15 -> 60 | AD43: ='Annual P&L'!M29*'Market Data'!$E$22 -> 28.084103 | AE43: ='Annual P&L'!N29*'Market Data'!$E$22 -> 29.341357 | AF43: ='Annual P&L'!O29*'Market Data'!$E$22 -> 27.836916 | AG43: ='Annual P&L'!P29*'Market Data'!$E$22 -> 26.223467
R44: Dividend yield | S44: =IFERROR(S43/S37,0) -> 6.4932849e-06 | T44: =IFERROR(T43/T37,0) -> 8.939362e-06 | U44: =IFERROR(U43/U37,0) -> 5.7775498e-06 | V44: =IFERROR(V43/V37,0) -> 6.0666113e-06 | W44: =IFERROR(W43/W37,0) -> 1.4304843e-05 | X44: =IFERROR(X43/X37,0) -> 3.6545021e-06 | Y44: =IFERROR(Y43/Y37,0) -> 3.41851e-06 | Z44: =IFERROR(Z43/Z37,0) -> 3.5929321e-06 | ... AG44: =IFERROR(AG43/AG37,0) -> 0.021473202
A45: Balance Sheet | B45: FY16A | C45: FY17A | D45: FY18A | E45: FY19A | F45: FY20A | G45: FY21A | H45: FY22A | I45: FY23A | J45: FY24A | K45: FY25A | L45: FY26A | M45: FY27E | N45: FY28E | O45: FY29E | P45: FY30E
A46: Cash & equivalents | B46: ='Annual Balance Sheet'!B5 -> 11852.7 | C46: ='Annual Balance Sheet'!C5 -> 12681.8 | D46: ='Annual Balance Sheet'!D5 -> 10273.1 | E46: ='Annual Balance Sheet'!E5 -> 11746 | F46: ='Annual Balance Sheet'!F5 -> 15373 | G46: ='Annual Balance Sheet'!G5 -> 20490 | H46: ='Annual Balance Sheet'!H5 -> 21883 | I46: ='Annual Balance Sheet'!I5 -> 22712 | ... P46: ='Annual Balance Sheet'!P5 -> -158560.48 | R46: FY27 Target Price & Recommendation
A47: Trade receivables & other current assets / receivables | B47: ='Annual Balance Sheet'!B6 -> 13133.1 | C47: ='Annual Balance Sheet'!C6 -> 13785.8 | D47: ='Annual Balance Sheet'!D6 -> 14777.3 | E47: ='Annual Balance Sheet'!E6 -> 18326 | F47: ='Annual Balance Sheet'!F6 -> 23051 | G47: ='Annual Balance Sheet'!G6 -> 22562 | H47: ='Annual Balance Sheet'!H6 -> 26158 | I47: ='Annual Balance Sheet'!I6 -> 30865 | ... P47: ='Annual Balance Sheet'!P6 -> 35155.81 | R47: FY26 observed price | AD47: ='Market Data'!E29 -> 1341.6
A48: Other current assets (forecast only) | B48: ='Annual Balance Sheet'!B7 -> 24985.8 | C48: ='Annual Balance Sheet'!C7 -> 26467.6 | D48: ='Annual Balance Sheet'!D7 -> 25050.4 | E48: ='Annual Balance Sheet'!E7 -> 30072 | F48: ='Annual Balance Sheet'!F7 -> 38424 | G48: ='Annual Balance Sheet'!G7 -> 43052 | H48: ='Annual Balance Sheet'!H7 -> 48041 | I48: ='Annual Balance Sheet'!I7 -> 53577 | ... P48: ='Annual Balance Sheet'!P7 -> 21908.072 | R48: FY27 EPS-driven price | AD48: ='Market Data'!C16 -> 1475.76
A49: Total current assets | B49: ='Annual Balance Sheet'!B8 -> 24985.8 | C49: ='Annual Balance Sheet'!C8 -> 26467.6 | D49: ='Annual Balance Sheet'!D8 -> 25050.4 | E49: ='Annual Balance Sheet'!E8 -> 30072 | F49: ='Annual Balance Sheet'!F8 -> 38424 | G49: ='Annual Balance Sheet'!G8 -> 43052 | H49: ='Annual Balance Sheet'!H8 -> 48041 | I49: ='Annual Balance Sheet'!I8 -> 53577 | ... P49: ='Annual Balance Sheet'!P8 -> -101496.6 | R49: 5-year median P/E | AD49: ='Market Data'!E32 -> 23.381142
A50: Net PPE & intangibles | B50: ='Annual Balance Sheet'!B9 -> 4323.1 | C50: ='Annual Balance Sheet'!C9 -> 4680.6 | D50: ='Annual Balance Sheet'!D9 -> 5184.7 | E50: ='Annual Balance Sheet'!E9 -> 5801 | F50: ='Annual Balance Sheet'!F9 -> 8868 | G50: ='Annual Balance Sheet'!G9 -> 8637 | H50: ='Annual Balance Sheet'!H9 -> 8046 | I50: ='Annual Balance Sheet'!I9 -> 7748 | ... P50: ='Annual Balance Sheet'!P9 -> 8309 | R50: Unconstrained FY27 value | AD50: ='Market Data'!E33 -> 1459.1965
A51: Goodwill, intangibles & investments | B51: ='Annual Balance Sheet'!B10 -> 6579.5 | C51: ='Annual Balance Sheet'!C10 -> 11572.2 | D51: ='Annual Balance Sheet'!D10 -> 14432.5 | E51: ='Annual Balance Sheet'!E10 -> 17730 | F51: ='Annual Balance Sheet'!F10 -> 29459 | G51: ='Annual Balance Sheet'!G10 -> 29197 | H51: ='Annual Balance Sheet'!H10 -> 27272 | I51: ='Annual Balance Sheet'!I10 -> 27021 | ... P51: ='Annual Balance Sheet'!P10 -> 29260 | R51: Market Perform lower bound | AD51: ='Market Data'!E29*(1+'Market Data'!E30) -> 1475.76
A52: Other long-term assets | B52: ='Annual Balance Sheet'!B11 -> 3878.9 | C52: ='Annual Balance Sheet'!C11 -> 3711.8 | D52: ='Annual Balance Sheet'!D11 -> 3767.5 | E52: ='Annual Balance Sheet'!E11 -> 5293 | F52: ='Annual Balance Sheet'!F11 -> 6465 | G52: ='Annual Balance Sheet'!G11 -> 6817 | H52: ='Annual Balance Sheet'!H11 -> 5674 | I52: ='Annual Balance Sheet'!I11 -> 5065 | ... P52: ='Annual Balance Sheet'!P11 -> 9796.0205 | R52: FY27 target price | AD52: ='Market Data'!E34 -> 1475.76
A53: Total assets | B53: ='Annual Balance Sheet'!B12 -> 39767.3 | C53: ='Annual Balance Sheet'!C12 -> 46432.2 | D53: ='Annual Balance Sheet'!D12 -> 48435.1 | E53: ='Annual Balance Sheet'!E12 -> 58896 | F53: ='Annual Balance Sheet'!F12 -> 83216 | G53: ='Annual Balance Sheet'!G12 -> 87703 | H53: ='Annual Balance Sheet'!H12 -> 89033 | I53: ='Annual Balance Sheet'!I12 -> 93411 | ... P53: ='Annual Balance Sheet'!P12 -> -54131.576 | R53: Market Perform upper bound | AD53: ='Market Data'!E29*(1+'Market Data'!E31) -> 1542.84
A54: Current liabilities | B54: ='Annual Balance Sheet'!B13 -> 9508.5 | C54: ='Annual Balance Sheet'!C13 -> 11147.7 | D54: ='Annual Balance Sheet'!D13 -> 9914.3 | E54: ='Annual Balance Sheet'!E13 -> 11148 | F54: ='Annual Balance Sheet'!F13 -> 20889 | G54: ='Annual Balance Sheet'!G13 -> 16755 | H54: ='Annual Balance Sheet'!H13 -> 18014 | I54: ='Annual Balance Sheet'!I13 -> 20420 | ... P54: ='Annual Balance Sheet'!P13 -> 28167.521 | R54: Target upside | AD54: ='Market Data'!E35 -> 0.1
A55: Debt & lease liabilities | B55: ='Annual Balance Sheet'!B14 -> 973.2 | C55: ='Annual Balance Sheet'!C14 -> 541.7 | D55: ='Annual Balance Sheet'!D14 -> 437.1 | E55: ='Annual Balance Sheet'!E14 -> 3986 | F55: ='Annual Balance Sheet'!F14 -> 7564 | G55: ='Annual Balance Sheet'!G14 -> 6174 | H55: ='Annual Balance Sheet'!H14 -> 6343 | I55: ='Annual Balance Sheet'!I14 -> 4786 | ... P55: ='Annual Balance Sheet'!P14 -> 5215 | R55: Target P/E | AD55: ='Market Data'!E36 -> 23.646545
A56: Other long-term liabilities | B56: ='Annual Balance Sheet'!B15 -> 1263.5 | C56: ='Annual Balance Sheet'!C15 -> 1252.5 | D56: ='Annual Balance Sheet'!D15 -> 1266.9 | E56: ='Annual Balance Sheet'!E15 -> 1538 | F56: ='Annual Balance Sheet'!F15 -> 2548 | G56: ='Annual Balance Sheet'!G15 -> 2683 | H56: ='Annual Balance Sheet'!H15 -> 2670 | I56: ='Annual Balance Sheet'!I15 -> 2807 | ... P56: ='Annual Balance Sheet'!P15 -> 7236.0932 | R56: Target EV / EBITDA | AD56: ='Market Data'!E37 -> 14.049917
A57: Total liabilities | B57: ='Annual Balance Sheet'!B16 -> 11745.2 | C57: ='Annual Balance Sheet'!C16 -> 12941.9 | D57: ='Annual Balance Sheet'!D16 -> 11618.3 | E57: ='Annual Balance Sheet'!E16 -> 16672 | F57: ='Annual Balance Sheet'!F16 -> 31001 | G57: ='Annual Balance Sheet'!G16 -> 25612 | H57: ='Annual Balance Sheet'!H16 -> 27027 | I57: ='Annual Balance Sheet'!I16 -> 28013 | ... P57: ='Annual Balance Sheet'!P16 -> 40618.614 | R57: Target P / book | AD57: ='Market Data'!E38 -> 10.225899
A58: Share capital & other contributed equity | B58: ='Annual Balance Sheet'!B17 -> 0 | C58: ='Annual Balance Sheet'!C17 -> 0 | D58: ='Annual Balance Sheet'!D17 -> 0 | E58: ='Annual Balance Sheet'!E17 -> 0 | F58: ='Annual Balance Sheet'!F17 -> 0 | G58: ='Annual Balance Sheet'!G17 -> 0 | H58: ='Annual Balance Sheet'!H17 -> 0 | I58: ='Annual Balance Sheet'!I17 -> 0 | ... P58: ='Annual Balance Sheet'!P17 -> 0 | R58: Target dividend yield | AD58: =IFERROR(AD43/AD52,0) -> 0.019030265
A59: Retained earnings & reserves | B59: ='Annual Balance Sheet'!B18 -> 9508.5 | C59: ='Annual Balance Sheet'!C18 -> 11147.7 | D59: ='Annual Balance Sheet'!D18 -> 9914.3 | E59: ='Annual Balance Sheet'!E18 -> 11148 | F59: ='Annual Balance Sheet'!F18 -> 20889 | G59: ='Annual Balance Sheet'!G18 -> 16755 | H59: ='Annual Balance Sheet'!H18 -> 18014 | I59: ='Annual Balance Sheet'!I18 -> 20420 | ... P59: ='Annual Balance Sheet'!P18 -> 66779.944 | R59: Recommendation check | AD59: =IF(AND(AD54>='Market Data'!E30,AD54<='Market Data'!E31),"MARKET PERFORM","OUTSIDE 10-15% BAND") -> MARKET PERFORM
A60: Total equity | B60: ='Annual Balance Sheet'!B19 -> 28022.1 | C60: ='Annual Balance Sheet'!C19 -> 33490.4 | D60: ='Annual Balance Sheet'!D19 -> 36816.8 | E60: ='Annual Balance Sheet'!E19 -> 42224 | F60: ='Annual Balance Sheet'!F19 -> 52215 | G60: ='Annual Balance Sheet'!G19 -> 62091 | H60: ='Annual Balance Sheet'!H19 -> 62006 | I60: ='Annual Balance Sheet'!I19 -> 65398 | ... P60: ='Annual Balance Sheet'!P19 -> 66779.944
A61: Total liabilities & equity | B61: ='Annual Balance Sheet'!B20 -> 39767.3 | C61: ='Annual Balance Sheet'!C20 -> 46432.3 | D61: ='Annual Balance Sheet'!D20 -> 48435.1 | E61: ='Annual Balance Sheet'!E20 -> 58896 | F61: ='Annual Balance Sheet'!F20 -> 83216 | G61: ='Annual Balance Sheet'!G20 -> 87703 | H61: ='Annual Balance Sheet'!H20 -> 89033 | I61: ='Annual Balance Sheet'!I20 -> 93411 | ... P61: ='Annual Balance Sheet'!P20 -> 107398.56
A62: Net cash / (debt) | B62: ='Annual Balance Sheet'!B22 -> 10879.5 | C62: ='Annual Balance Sheet'!C22 -> 12140.1 | D62: ='Annual Balance Sheet'!D22 -> 9836 | E62: ='Annual Balance Sheet'!E22 -> 7760 | F62: ='Annual Balance Sheet'!F22 -> 7809 | G62: ='Annual Balance Sheet'!G22 -> 14316 | H62: ='Annual Balance Sheet'!H22 -> 15540 | I62: ='Annual Balance Sheet'!I22 -> 17926 | ... P62: ='Annual Balance Sheet'!P22 -> -163775.48
A63: ROA | B63: ='Annual Balance Sheet'!B23 -> 0.14004214 | C63: ='Annual Balance Sheet'!C23 -> 0.19621924 | D63: ='Annual Balance Sheet'!D23 -> 0.18514283 | E63: ='Annual Balance Sheet'!E23 -> 0.18863125 | F63: ='Annual Balance Sheet'!F23 -> 0.15568003 | G63: ='Annual Balance Sheet'!G23 -> 0.14548412 | H63: ='Annual Balance Sheet'!H23 -> 0.15277023 | I63: ='Annual Balance Sheet'!I23 -> 0.16280064 | ... P63: ='Annual Balance Sheet'!P23 -> -0.75597969
A64: ROE | B64: ='Annual Balance Sheet'!B24 -> 0.19873949 | C64: ='Annual Balance Sheet'!C24 -> 0.2749685 | D64: ='Annual Balance Sheet'!D24 -> 0.24981794 | E64: ='Annual Balance Sheet'!E24 -> 0.25614619 | F64: ='Annual Balance Sheet'!F24 -> 0.23426762 | G64: ='Annual Balance Sheet'!G24 -> 0.21753889 | H64: ='Annual Balance Sheet'!H24 -> 0.21757174 | I64: ='Annual Balance Sheet'!I24 -> 0.2331324 | ... P64: ='Annual Balance Sheet'!P24 -> 0.2531182

Sheet Assumptions
A1: Forecast Assumptions
A2: Editable FY27–FY30 inputs; blue font on yellow fill
A4: Driver | B4: FY16A | C4: FY17A | D4: FY18A | E4: FY19A | F4: FY20A | G4: FY21A | H4: FY22A | I4: FY23A | J4: FY24A | K4: FY25A | L4: FY26A | M4: FY27E | N4: FY28E | O4: FY29E | P4: FY30E
A5: Gross hiring / opening headcount | M5: 0.16 | N5: 0.16 | O5: 0.16 | P5: 0.16
A6: Attrition | M6: 0.125 | N6: 0.125 | O6: 0.125 | P6: 0.125
A7: Billable % | M7: 0.825 | N7: =M7-0.5% -> 0.82 | O7: =N7 -> 0.82 | P7: =O7 -> 0.82
A8: Nominal pricing / productivity | M8: 0.025 | N8: 0.025 | O8: 0.025 | P8: 0.025
A9: T&M mix | M9: 0.6145 | N9: =M9-1.25% -> 0.602 | O9: =N9 -> 0.602 | P9: =O9 -> 0.602
A10: AI deflation on T&M | M10: 0.03 | N10: =M10+0.5% -> 0.035 | O10: =N10 -> 0.035 | P10: =O10 -> 0.035
A11: Fixed-price productivity uplift | M11: 0.045 | N11: =M11+0.75% -> 0.0525 | O11: =N11 -> 0.0525 | P11: =O11 -> 0.0525
A12: Gross margin | M12: 0.34 | N12: 0.34 | O12: 0.34 | P12: 0.34
A13: S&M / revenue | M13: 0.06 | N13: 0.06 | O13: 0.06 | P13: 0.06
A14: G&A / revenue | M14: 0.085 | N14: 0.085 | O14: 0.085 | P14: 0.085
A15: D&A / revenue | M15: 0.035 | N15: 0.035 | O15: 0.035 | P15: 0.035
A16: Net other income / revenue | M16: 0.012 | N16: 0.012 | O16: 0.012 | P16: 0.012
A17: Tax rate | M17: 0.25 | N17: 0.25 | O17: 0.25 | P17: 0.25
A18: Receivable days | M18: 82 | N18: 82 | O18: 82 | P18: 82
A19: Other current assets / revenue | M19: 0.14 | N19: 0.14 | O19: 0.14 | P19: 0.14
A20: Current liabilities / revenue | M20: 0.18 | N20: 0.18 | O20: 0.18 | P20: 0.18
A21: Capex / revenue | M21: 0.022 | N21: 0.022 | O21: 0.022 | P21: 0.022
A22: Dividend payout | M22: 0.45 | N22: 0.45 | O22: 0.45 | P22: 0.45
A23: Basic shares growth | M23: 0 | N23: 0 | O23: 0 | P23: 0
A24: Dilution | M24: 0.002 | N24: 0.002 | O24: 0.002 | P24: 0.002
A25: Application services / ITBS mix change | B25: ppt | M25: 0 | N25: 0 | O25: 0 | P25: 0
A26: Infrastructure services / ITBS mix change | B26: ppt | M26: 0 | N26: 0 | O26: 0 | P26: 0
A27: Business services / ITBS mix change | B27: ppt | M27: 0 | N27: 0 | O27: 0 | P27: 0
A28: ER&D mix change | B28: ppt | M28: 0 | N28: 0 | O28: 0 | P28: 0
A29: Products & Platforms mix change | B29: ppt | M29: 0 | N29: 0 | O29: 0 | P29: 0
A30: Perpetual license growth | B30: % | M30: 0.05 | N30: 0.05 | O30: 0.05 | P30: 0.05
A31: Subscription & support growth | B31: % | M31: 0.03 | N31: 0.03 | O31: 0.03 | P31: 0.03
A32: Professional services growth | B32: % | M32: 0.06 | N32: 0.06 | O32: 0.06 | P32: 0.06
A33: Software ARR growth | B33: % | M33: 0.08 | N33: 0.08 | O33: 0.08 | P33: 0.08
A34: ITBS EBIT margin | B34: % | M34: 0.163 | N34: 0.163 | O34: 0.163 | P34: 0.163
A35: ER&D EBIT margin | B35: % | M35: 0.155 | N35: 0.155 | O35: 0.155 | P35: 0.155
A36: Products EBIT margin | B36: % | M36: 0.202 | N36: 0.202 | O36: 0.202 | P36: 0.202
A37: Advanced AI revenue growth | B37: % | M37: 0.25 | N37: =M37+0.005 -> 0.255 | O37: =N37+0.95% -> 0.2645 | P37: =O37+1% -> 0.2745
A38: Yield on opening cash | M38: 0.04 | N38: 0.04 | O38: 0.04 | P38: 0.04
A39: Finance cost / average debt | M39: 0.08 | N39: 0.08 | O39: 0.08 | P39: 0.08
A40: Maintenance capex / revenue | M40: 0.018 | N40: 0.018 | O40: 0.018 | P40: 0.018
A41: Data centre & AI infrastructure capex / revenue | M41: 0.01 | N41: 0.01 | O41: 0.01 | P41: 0.01
A42: Other growth capex / revenue | M42: 0.007 | N42: 0.007 | O42: 0.007 | P42: 0.007
A43: Offshore revenue mix | M43: 0.55 | N43: 0.56 | O43: 0.57 | P43: 0.58
A44: Utilization excl. trainees | M44: 0.83 | N44: 0.835 | O44: 0.84 | P44: 0.845
A45: Support staff / delivery headcount | M45: 0.08 | N45: 0.078 | O45: 0.076 | P45: 0.075
A46: Subcontractor cost / revenue | M46: 0.07 | N46: 0.068 | O46: 0.066 | P46: 0.065

Sheet Annual Balance Sheet
A1: Annual Balance Sheet
A2: Historical totals sourced from reported/compiled statements; non-cash current assets and equity are aggregated where detailed disclosure is unavailable
A4: Metric | B4: FY16A | C4: FY17A | D4: FY18A | E4: FY19A | F4: FY20A | G4: FY21A | H4: FY22A | I4: FY23A | J4: FY24A | K4: FY25A | L4: FY26A | M4: FY27E | N4: FY28E | O4: FY29E | P4: FY30E
A5: Cash & equivalents | B5: 11852.7 | C5: 12681.8 | D5: 10273.1 | E5: 11746 | F5: 15373 | G5: 20490 | H5: 21883 | I5: 22712 | J5: 27988 | K5: 29738 | L5: 31401 | M5: ='Annual Cash Flow'!M30 -> 33379.455 | N5: ='Annual Cash Flow'!N30 -> -24835.017 | O5: ='Annual Cash Flow'!O30 -> -88741.64 | P5: ='Annual Cash Flow'!P30 -> -158560.48
A6: Trade receivables & other current assets (actuals) / receivables (forecast) | B6: 13133.1 | C6: 13785.8 | D6: 14777.3 | E6: 18326 | F6: 23051 | G6: 22562 | H6: 26158 | I6: 30865 | J6: 31343 | K6: 32371 | L6: 39141 | M6: ='Annual P&L'!M5*Assumptions!M18/365 -> 30507.284 | N6: ='Annual P&L'!N5*Assumptions!N18/365 -> 31814.627 | O6: ='Annual P&L'!O5*Assumptions!O18/365 -> 33386.864 | P6: ='Annual P&L'!P5*Assumptions!P18/365 -> 35155.81
A7: Other current assets (forecast only) | B7: =SUM(B5:B6) -> 24985.8 | C7: =SUM(C5:C6) -> 26467.6 | D7: =SUM(D5:D6) -> 25050.4 | E7: =SUM(E5:E6) -> 30072 | F7: =SUM(F5:F6) -> 38424 | G7: =SUM(G5:G6) -> 43052 | H7: =SUM(H5:H6) -> 48041 | I7: =SUM(I5:I6) -> 53577 | ... L7: =SUM(L5:L6) -> 70542 | M7: ='Annual P&L'!M5*Assumptions!M19 -> 19011.246 | N7: ='Annual P&L'!N5*Assumptions!N19 -> 19825.944 | O7: ='Annual P&L'!O5*Assumptions!O19 -> 20805.716 | P7: ='Annual P&L'!P5*Assumptions!P19 -> 21908.072
A8: Total current assets | B8: 24985.8 | C8: 26467.6 | D8: 25050.4 | E8: 30072 | F8: 38424 | G8: 43052 | H8: 48041 | I8: 53577 | J8: 59331 | K8: 62109 | L8: 70542 | M8: =SUM(M5:M7) -> 82897.985 | N8: =SUM(N5:N7) -> 26805.554 | O8: =SUM(O5:O7) -> -34549.06 | P8: =SUM(P5:P7) -> -101496.6
A9: Net PPE & intangibles | B9: 4323.1 | C9: 4680.6 | D9: 5184.7 | E9: 5801 | F9: 8868 | G9: 8637 | H9: 8046 | I9: 7748 | J9: 7909 | K9: 7576 | L9: 8309 | M9: =L9-'Annual Cash Flow'!M18-'Annual P&L'!M16 -> 8309 | N9: =M9-'Annual Cash Flow'!N18-'Annual P&L'!N16 -> 8309 | O9: =N9-'Annual Cash Flow'!O18-'Annual P&L'!O16 -> 8309 | P9: =O9-'Annual Cash Flow'!P18-'Annual P&L'!P16 -> 8309
A10: Goodwill, intangibles & investments | B10: 6579.5 | C10: 11572.2 | D10: 14432.5 | E10: 17730 | F10: 29459 | G10: 29197 | H10: 27272 | I10: 27021 | J10: 27356 | K10: 28746 | L10: 29260 | M10: =L10 -> 29260 | N10: =M10 -> 29260 | O10: =N10 -> 29260 | P10: =O10 -> 29260
A11: Other long-term assets | B11: 3878.9 | C11: 3711.8 | D11: 3767.5 | E11: 5293 | F11: 6465 | G11: 6817 | H11: 5674 | I11: 5065 | J11: 5181 | K11: 7113 | L11: 8147 | M11: =L11*(1+'Annual P&L'!M6) -> 8500.7279 | N11: =M11*(1+'Annual P&L'!N6) -> 8865.0138 | O11: =N11*(1+'Annual P&L'!O6) -> 9303.111 | P11: =O11*(1+'Annual P&L'!P6) -> 9796.0205
A12: Total assets | B12: 39767.3 | C12: 46432.2 | D12: 48435.1 | E12: 58896 | F12: 83216 | G12: 87703 | H12: 89033 | I12: 93411 | J12: 99777 | K12: 105544 | L12: 116258 | M12: =SUM(M8:M11) -> 128967.71 | N12: =SUM(N8:N11) -> 73239.568 | O12: =SUM(O8:O11) -> 12323.051 | P12: =SUM(P8:P11) -> -54131.576
A13: Current liabilities | B13: 9508.5 | C13: 11147.7 | D13: 9914.3 | E13: 11148 | F13: 20889 | G13: 16755 | H13: 18014 | I13: 20420 | J13: 21532 | K13: 24471 | L13: 29828 | M13: ='Annual P&L'!M5*Assumptions!M20 -> 24443.031 | N13: ='Annual P&L'!N5*Assumptions!N20 -> 25490.5 | O13: ='Annual P&L'!O5*Assumptions!O20 -> 26750.207 | P13: ='Annual P&L'!P5*Assumptions!P20 -> 28167.521
A14: Debt & lease liabilities | B14: 973.2 | C14: 541.7 | D14: 437.1 | E14: 3986 | F14: 7564 | G14: 6174 | H14: 6343 | I14: 4786 | J14: 5756 | K14: 6276 | L14: 5215 | M14: 5215 | N14: 5215 | O14: 5215 | P14: 5215
A15: Other long-term liabilities | B15: 1263.5 | C15: 1252.5 | D15: 1266.9 | E15: 1538 | F15: 2548 | G15: 2683 | H15: 2670 | I15: 2807 | J15: 4218 | K15: 5124 | L15: 6018 | M15: 6279.2906 | N15: 6548.3801 | O15: 6871.9924 | P15: 7236.0932
A16: Total liabilities | B16: 11745.2 | C16: 12941.9 | D16: 11618.3 | E16: 16672 | F16: 31001 | G16: 25612 | H16: 27027 | I16: 28013 | J16: 31506 | K16: 35871 | L16: 41061 | M16: =SUM(M13:M15) -> 35937.321 | N16: =SUM(N13:N15) -> 37253.88 | O16: =SUM(O13:O15) -> 38837.199 | P16: =SUM(P13:P15) -> 40618.614
A17: Share capital & other contributed equity | B17: 0 | C17: 0 | D17: 0 | E17: 0 | F17: 0 | G17: 0 | H17: 0 | I17: 0 | J17: 0 | K17: 0 | L17: 0 | M17: =L17 -> 0 | N17: =M17 -> 0 | O17: =N17 -> 0 | P17: =O17 -> 0
A18: Retained earnings & reserves (incl. other equity in actuals) | B18: =B13 -> 9508.5 | C18: =C13 -> 11147.7 | D18: =D13 -> 9914.3 | E18: =E13 -> 11148 | F18: =F13 -> 20889 | G18: =G13 -> 16755 | H18: =H13 -> 18014 | I18: =I13 -> 20420 | ... L18: =L13 -> 29828 | M18: =L18+'Annual P&L'!M25+'Annual Cash Flow'!M23+'Annual Cash Flow'!M24 -> 39136.466 | N18: =M18+'Annual P&L'!N25+'Annual Cash Flow'!N23+'Annual Cash Flow'!N24 -> 48861.649 | O18: =N18+'Annual P&L'!O25+'Annual Cash Flow'!O23+'Annual Cash Flow'!O24 -> 58088.185 | P18: =O18+'Annual P&L'!P25+'Annual Cash Flow'!P23+'Annual Cash Flow'!P24 -> 66779.944
A19: Total equity | B19: 28022.1 | C19: 33490.4 | D19: 36816.8 | E19: 42224 | F19: 52215 | G19: 62091 | H19: 62006 | I19: 65398 | J19: 68271 | K19: 69673 | L19: 75197 | M19: =SUM(M17:M18) -> 39136.466 | N19: =SUM(N17:N18) -> 48861.649 | O19: =SUM(O17:O18) -> 58088.185 | P19: =SUM(P17:P18) -> 66779.944
A20: Total liabilities & equity | B20: =SUM(B16,B19) -> 39767.3 | C20: =SUM(C16,C19) -> 46432.3 | D20: =SUM(D16,D19) -> 48435.1 | E20: =SUM(E16,E19) -> 58896 | F20: =SUM(F16,F19) -> 83216 | G20: =SUM(G16,G19) -> 87703 | H20: =SUM(H16,H19) -> 89033 | I20: =SUM(I16,I19) -> 93411 | ... P20: =SUM(P16,P19) -> 107398.56
A21: Balance check | B21: =B12-B20 -> 0 | C21: =C12-C20 -> -0.1 | D21: =D12-D20 -> 0 | E21: =E12-E20 -> 0 | F21: =F12-F20 -> 0 | G21: =G12-G20 -> 0 | H21: =H12-H20 -> 0 | I21: =I12-I20 -> 0 | ... P21: =P12-P20 -> -161530.13
A22: Net cash / (debt) | B22: =B5-B14 -> 10879.5 | C22: =C5-C14 -> 12140.1 | D22: =D5-D14 -> 9836 | E22: =E5-E14 -> 7760 | F22: =F5-F14 -> 7809 | G22: =G5-G14 -> 14316 | H22: =H5-H14 -> 15540 | I22: =I5-I14 -> 17926 | ... P22: =P5-P14 -> -163775.48
A23: ROA | B23: 0.14004214 | C23: 0.19621924 | D23: 0.18514283 | E23: 0.18863125 | F23: 0.15568003 | G23: 0.14548412 | H23: 0.15277023 | I23: 0.16280064 | J23: 0.16255668 | K23: 0.16940303 | L23: 0.15654503 | M23: =IFERROR('Annual P&L'!M25/AVERAGE(L12,M12),0) -> 0.13803189 | N23: =IFERROR('Annual P&L'!N25/AVERAGE(M12,N12),0) -> 0.17489133 | O23: =IFERROR('Annual P&L'!O25/AVERAGE(N12,O12),0) -> 0.39212265 | P23: =IFERROR('Annual P&L'!P25/AVERAGE(O12,P12),0) -> -0.75597969
A24: ROE | B24: =IFERROR('Annual P&L'!B25/B19,0) -> 0.19873949 | C24: =IFERROR('Annual P&L'!C25/AVERAGE(B19,C19),0) -> 0.2749685 | D24: =IFERROR('Annual P&L'!D25/AVERAGE(C19,D19),0) -> 0.24981794 | E24: =IFERROR('Annual P&L'!E25/AVERAGE(D19,E19),0) -> 0.25614619 | F24: =IFERROR('Annual P&L'!F25/AVERAGE(E19,F19),0) -> 0.23426762 | G24: =IFERROR('Annual P&L'!G25/AVERAGE(F19,G19),0) -> 0.21753889 | H24: =IFERROR('Annual P&L'!H25/AVERAGE(G19,H19),0) -> 0.21757174 | I24: =IFERROR('Annual P&L'!I25/AVERAGE(H19,I19),0) -> 0.2331324 | J24: =IFERROR('Annual P&L'!J25/AVERAGE(I19,J19),0) -> 0.23493854 | ... P24: =IFERROR('Annual P&L'!P25/AVERAGE(O19,P19),0) -> 0.2531182

Sheet Quarterly P&L
A1: Quarterly Profit & Loss Statement — Detailed
A2: Only statement maintained quarterly | reported series retained; S&M/G&A and D&A detail allocated using annual model ratios where quarterly disclosure is unavailable
A4: Metric | B4: Q1 FY2016 | C4: Q2 FY2016 | D4: Q3 FY2016 | E4: Q1 FY2017 | F4: Q2 FY2017 | G4: Q3 FY2017 | H4: Q4 FY2017 | I4: Q1 FY2018 | J4: Q2 FY2018 | K4: Q3 FY2018 | L4: Q4 FY2018 | M4: Q1 FY2019 | N4: Q2 FY2019 | O4: Q3 FY2019 | P4: Q4 FY2019 | Q4: Q1 FY2020 | R4: Q2 FY2020 | S4: Q3 FY2020 | T4: Q4 FY2020 | U4: Q1 FY2021 | V4: Q2 FY2021 | W4: Q3 FY2021 | X4: Q4 FY2021 | Y4: Q1 FY2022 | Z4: Q2 FY2022 | AA4: Q3 FY2022 | AB4: Q4 FY2022 | AC4: Q1 FY2023 | AD4: Q2 FY2023 | AE4: Q3 FY2023 | AF4: Q4 FY2023 | AG4: Q1 FY2024 | AH4: Q2 FY2024 | AI4: Q3 FY2024 | AJ4: Q4 FY2024 | AK4: Q1 FY2025 | AL4: Q2 FY2025 | AM4: Q3 FY2025 | AN4: Q4 FY2025 | AO4: Q1 FY2026 | AP4: Q2 FY2026 | AQ4: Q3 FY2026 | AR4: Q4 FY2026 | AS4: Q1 FY2027 | AT4: Q2 FY2027 | AU4: Q3 FY2027 | AV4: Q4 FY2027 | AW4: Q1 FY2028 | AX4: Q2 FY2028 | AY4: Q3 FY2028 | AZ4: Q4 FY2028 | BA4: Q1 FY2029 | BB4: Q2 FY2029 | BC4: Q3 FY2029 | BD4: Q4 FY2029 | BE4: Q1 FY2030 | BF4: Q2 FY2030 | BG4: Q3 FY2030 | BH4: Q4 FY2030
A5: Revenue | B5: 1544.519 | C5: 1566.1 | D5: 1587.2 | E5: 1690.7 | F5: 1722.4 | G5: 1745.3 | H5: 1816.8 | I5: 1884.2 | J5: 1928 | K5: 1988 | L5: 2038 | M5: 2054.5 | N5: 2098.6 | O5: 2201.5 | P5: 2277.8 | Q5: 2363.6 | R5: 2485.6 | S5: 2543.4 | T5: 2543.4 | U5: 2355.5 | V5: 2507 | W5: 2616.6 | X5: 2695.9 | Y5: 2719.6 | Z5: 2790.7 | AA5: 2977.5 | AB5: 2993.1 | AC5: 3024.9 | AD5: 3082.1 | AE5: 3244 | AF5: 3234.6 | AG5: 3200 | AH5: 3224.7 | AI5: 3415 | AJ5: 3429.9 | AK5: 3363.8 | AL5: 3445.2 | AM5: 3533 | AN5: 3498.2 | AO5: 3545 | AP5: 3644 | AQ5: 3793 | AR5: 3682 | AS5: 3650 | AT5: =('Revenue Drivers'!M25-AS5)/3 -> 3883.5614 | AU5: =('Revenue Drivers'!M25-AS5)/3 -> 3883.5614 | AV5: =('Revenue Drivers'!M25-AS5)/3 -> 3883.5614 | AW5: ='Revenue Drivers'!N25/4 -> 3989.093 | AX5: ='Revenue Drivers'!N25/4 -> 3989.093 | AY5: ='Revenue Drivers'!N25/4 -> 3989.093 | AZ5: ='Revenue Drivers'!N25/4 -> 3989.093 | BA5: ='Revenue Drivers'!O25/4 -> 4186.2286 | BB5: ='Revenue Drivers'!O25/4 -> 4186.2286 | BC5: ='Revenue Drivers'!O25/4 -> 4186.2286 | BD5: ='Revenue Drivers'!O25/4 -> 4186.2286 | BE5: ='Revenue Drivers'!P25/4 -> 4408.0288 | BF5: ='Revenue Drivers'!P25/4 -> 4408.0288 | BG5: ='Revenue Drivers'!P25/4 -> 4408.0288 | BH5: ='Revenue Drivers'!P25/4 -> 4408.0288
A6: QoQ growth | B6: =0 -> 0 | C6: =IFERROR(C5/B5-1,0) -> 0.013972635 | D6: =IFERROR(D5/C5-1,0) -> 0.013472958 | E6: =IFERROR(E5/D5-1,0) -> 0.065209173 | F6: =IFERROR(F5/E5-1,0) -> 0.01874963 | G6: =IFERROR(G5/F5-1,0) -> 0.013295402 | H6: =IFERROR(H5/G5-1,0) -> 0.040967169 | I6: =IFERROR(I5/H5-1,0) -> 0.037098195 | J6: =IFERROR(J5/I5-1,0) -> 0.02324594 | ... BH6: =IFERROR(BH5/BG5-1,0) -> 0
A7: YoY growth | B7: =0 -> 0 | C7: =0 -> 0 | D7: =0 -> 0 | E7: =E5/B5-1 -> 0.094645 | F7: =F5/C5-1 -> 0.099802056 | G7: =G5/D5-1 -> 0.099609375 | H7: =0 -> 0 | I7: =I5/E5-1 -> 0.11444964 | J7: 0.11936832 | K7: 0.13905919 | L7: 0.12175253 | M7: 0.090383186 | N7: 0.088485477 | O7: 0.10739437 | P7: 0.11766438 | Q7: 0.15045023 | R7: 0.18440865 | S7: 0.1553032 | T7: 0.11660374 | U7: -0.0034269758 | V7: 0.0086095912 | W7: 0.028780373 | X7: 0.05995911 | Y7: 0.1545744 | Z7: 0.11316314 | AA7: 0.13792708 | AB7: 0.11024148 | AC7: 0.11225916 | AD7: 0.10441825 | AE7: 0.089504618 | AF7: 0.080685577 | AG7: 0.057886211 | AH7: 0.046267156 | AI7: 0.0527127 | AJ7: 0.060378408 | AK7: 0.0511875 | AL7: 0.068378454 | AM7: 0.034553441 | AN7: 0.019913117 | AO7: =AO5/AK5-1 -> 0.05386765 | AP7: 0.057703471 | AQ7: 0.073591848 | AR7: 0.052541307 | AS7: 0.029619182 | AT7: 0.095819826 | AU7: 0.052772857 | AV7: 0.084510441 | AW7: 0.12810397 | AX7: 0.031156231 | AY7: 0.031156231 | AZ7: 0.031156231 | BA7: 0.060222289 | BB7: 0.060222289 | BC7: 0.060222289 | BD7: 0.060222289 | BE7: 0.060222289 | BF7: 0.060222289 | BG7: 0.060222289 | BH7: 0.060222289
A8: Cost of services | B8: 1031.574 | C8: 1024.9845 | D8: 1032.7631 | E8: 1109.6337 | F8: 1144.3291 | G8: 1153.6353 | H8: 1203.9145 | I8: 1249.5678 | J8: 1272.7219 | K8: 1305.6727 | L8: 1323.718 | M8: 1348.0528 | N8: 1354.1131 | O8: 1423.6339 | P8: 1484.4874 | Q8: 1571.4163 | R8: 1614.619 | S8: 1614.2561 | T8: 1570.505 | U8: 1461.5428 | V8: 1520.73 | W8: 1565.8661 | X8: 1657.3156 | Y8: 1687.8921 | Z8: 1753.7297 | AA8: 1907.888 | AB8: 1943.3891 | AC8: 1992.6645 | AD8: 2027.0994 | AE8: 2081.8704 | AF8: 2106.5141 | AG8: 2108.9139 | AH8: 2105.7513 | AI8: 2210.8782 | AJ8: 2282.1069 | AK8: 2250.4861 | AL8: 2289.9562 | AM8: 2323.9315 | AN8: 2336.1814 | AO8: 2404.255 | AP8: 2457.0932 | AQ8: 2533.3325 | AR8: 2499.4171 | AS8: 2488.0462 | AT8: =AT5*(1-'Annual P&L'!M9) -> 2563.1505 | AU8: =AU5*(1-'Annual P&L'!M9) -> 2563.1505 | AV8: =AV5*(1-'Annual P&L'!M9) -> 2563.1505 | AW8: =AW5*(1-'Annual P&L'!N9) -> 2632.8014 | AX8: =AX5*(1-'Annual P&L'!N9) -> 2632.8014 | AY8: =AY5*(1-'Annual P&L'!N9) -> 2632.8014 | AZ8: =AZ5*(1-'Annual P&L'!N9) -> 2632.8014 | BA8: =BA5*(1-'Annual P&L'!O9) -> 2762.9109 | BB8: =BB5*(1-'Annual P&L'!O9) -> 2762.9109 | BC8: =BC5*(1-'Annual P&L'!O9) -> 2762.9109 | BD8: =BD5*(1-'Annual P&L'!O9) -> 2762.9109 | BE8: =BE5*(1-'Annual P&L'!P9) -> 2909.299 | BF8: =BF5*(1-'Annual P&L'!P9) -> 2909.299 | BG8: =BG5*(1-'Annual P&L'!P9) -> 2909.299 | BH8: =BH5*(1-'Annual P&L'!P9) -> 2909.299
A9: Gross profit | B9: =IFERROR(B8/B5,0) -> 0.66789337 | C9: =IFERROR(C8/C5,0) -> 0.65448216 | D9: =IFERROR(D8/D5,0) -> 0.65068237 | E9: =IFERROR(E8/E5,0) -> 0.65631616 | F9: =IFERROR(F8/F5,0) -> 0.66438059 | G9: =IFERROR(G8/G5,0) -> 0.66099543 | H9: =IFERROR(H8/H5,0) -> 0.6626566 | I9: =IFERROR(I8/I5,0) -> 0.66318215 | ... BH9: =IFERROR(BH8/BH5,0) -> 0.66
A10: Gross margin | B10: =IFERROR(B8/B5,0) -> 0.66789337 | C10: 0.34551784 | D10: 0.34931763 | E10: 0.34368384 | F10: 0.33561941 | G10: 0.33900457 | H10: 0.3373434 | I10: 0.33681785 | J10: 0.33987454 | K10: 0.34322299 | L10: 0.35048183 | M10: 0.34385358 | N10: 0.35475405 | O10: 0.35333461 | P10: 0.34828018 | Q10: 0.33515982 | R10: 0.35041077 | S10: 0.36531569 | T10: 0.38251748 | U10: 0.37951909 | V10: 0.39340648 | W10: 0.4015646 | X10: 0.3852459 | Y10: 0.37936018 | Z10: 0.37158073 | AA10: 0.35923156 | AB10: 0.35071027 | AC10: 0.34124616 | AD10: 0.34229928 | AE10: 0.3582397 | AF10: 0.34875592 | AG10: 0.34096441 | AH10: =IFERROR(AH8/AH5,0) -> 0.6530069 | AI10: 0.3525979 | AJ10: 0.33464332 | AK10: 0.3309691 | AL10: 0.3353198 | AM10: 0.34222148 | AN10: 0.33217616 | AO10: 0.32178984 | AP10: 0.32571536 | AQ10: 0.33210321 | AR10: 0.32117948 | AS10: 0.3183435 | AT10: =AT8-AT11 -> 0.34 | AU10: =AU8-AU11 -> 1844.3804 | AV10: =AV8-AV11 -> 1844.3804 | AW10: =AW8-AW11 -> 1891.6371 | AX10: =AX8-AX11 -> 1891.6371 | AY10: =AY8-AY11 -> 1891.6371 | AZ10: =AZ8-AZ11 -> 1891.6371 | BA10: =BA8-BA11 -> 1977.112 | ... BH10: =BH8-BH11 -> 2076.1775
A11: Operating expenses | B11: 213.55147 | C11: 225.6541 | D11: 224.32664 | E11: 223.26905 | F11: 226.83226 | G11: 229.57476 | H11: 241.47628 | I11: 238.84007 | J11: 252.90076 | K11: 272.86883 | L11: 289.94992 | M11: 281.12808 | N11: 315.89854 | O11: 352.68313 | P11: 357.12599 | Q11: 385.80284 | R11: 376.49863 | S11: 412.61002 | T11: 446.8394 | U11: 410.73709 | V11: 445.20351 | W11: 451.96065 | X11: 564.79119 | Y11: 493.01898 | Z11: 493.42224 | AA11: 493.07219 | AB11: 492.86742 | AC11: 507.02914 | AD11: 496.41212 | AE11: 526.45139 | AF11: 545.01661 | AG11: 551.01917 | AH11: 524.23137 | AI11: 526.5482 | AJ11: 543.14673 | AK11: 528.60228 | AL11: 514.8343 | AM11: 520.19849 | AN11: 533.18462 | AO11: 562.8968 | AP11: 559.79926 | AQ11: 563.14942 | AR11: 587.49901 | AS11: 550.47138 | AT11: =AT8-AT11 -> 2563.1505 | AU11: 718.77014 | AV11: 718.77014 | AW11: 741.16431 | AX11: 741.16431 | AY11: 741.16431 | AZ11: 741.16431 | BA11: 785.79892 | BB11: 785.79892 | BC11: 785.79892 | BD11: 785.79892 | BE11: 833.12153 | BF11: 833.12153 | BG11: 833.12153 | BH11: 833.12153
A12: Selling & marketing (modelled allocation) | B12: 205.21534 | C12: 216.84553 | D12: 215.56989 | E12: 214.55358 | F12: 217.9777 | G12: 220.61314 | H12: 232.05008 | I12: 229.51678 | J12: 243.02859 | K12: 262.2172 | L12: 278.63152 | M12: 270.15404 | N12: 303.56721 | O12: 338.91589 | P12: 343.18532 | Q12: 370.74275 | R12: 361.80174 | S12: 396.5035 | T12: 429.3967 | U12: 394.70368 | V12: 427.82467 | W12: 434.31804 | X12: 542.74416 | Y12: 473.77363 | Z12: 474.16115 | AA12: 473.82476 | AB12: 473.62799 | AC12: 487.23689 | AD12: 477.03432 | AE12: 505.90098 | AF12: 523.74149 | AG12: 529.50974 | AH12: 503.76763 | AI12: 505.99401 | AJ12: 521.94461 | AK12: 507.96791 | AL12: 494.73737 | AM12: 499.89217 | AN12: 512.37137 | AO12: 540.92372 | AP12: 537.94709 | AQ12: 541.16647 | AR12: 564.56557 | AS12: 528.98334 | AT12: 2463.0961 | AU12: 690.71243 | AV12: 690.71243 | AW12: 712.23243 | AX12: 712.23243 | AY12: 712.23243 | AZ12: 712.23243 | BA12: 755.12469 | BB12: 755.12469 | BC12: 755.12469 | BD12: 755.12469 | BE12: 800.60003 | BF12: 800.60003 | BG12: 800.60003 | BH12: 800.60003
A13: G&A (modelled allocation) | B13: =B11-B12 -> 8.336135 | C13: =C11-C12 -> 8.8085697 | D13: =D11-D12 -> 8.7567515 | E13: =E11-E12 -> 8.7154676 | F13: =F11-F12 -> 8.8545602 | G13: =G11-G12 -> 8.9616156 | H13: =H11-H12 -> 9.4262 | I13: =I11-I12 -> 9.3232936 | ... BH13: =BH11-BH12 -> 32.521497
A14: D&A | B14: =IFERROR('Annual P&L'!F16*B5/'Annual P&L'!F5,0) -> 62.062225 | C14: =IFERROR('Annual P&L'!F16*C5/'Annual P&L'!F5,0) -> 62.929398 | D14: =IFERROR('Annual P&L'!F16*D5/'Annual P&L'!F5,0) -> 63.777243 | E14: =IFERROR('Annual P&L'!F16*E5/'Annual P&L'!F5,0) -> 67.936105 | F14: =IFERROR('Annual P&L'!F16*F5/'Annual P&L'!F5,0) -> 69.209881 | G14: =IFERROR('Annual P&L'!F16*G5/'Annual P&L'!F5,0) -> 70.130055 | H14: =IFERROR('Annual P&L'!F16*H5/'Annual P&L'!F5,0) -> 73.003084 | I14: =IFERROR('Annual P&L'!F16*I5/'Annual P&L'!F5,0) -> 75.711367 | J14: =IFERROR('Annual P&L'!F16*J5/'Annual P&L'!F5,0) -> 77.471349 | K14: =IFERROR('Annual P&L'!F16*K5/'Annual P&L'!F5,0) -> 79.882283 | L14: =IFERROR('Annual P&L'!F16*L5/'Annual P&L'!F5,0) -> 81.891395 | M14: =IFERROR('Annual P&L'!F16*M5/'Annual P&L'!F5,0) -> 82.554402 | N14: =IFERROR('Annual P&L'!F16*N5/'Annual P&L'!F5,0) -> 84.326438 | O14: =IFERROR('Annual P&L'!F16*O5/'Annual P&L'!F5,0) -> 88.46119 | P14: =IFERROR('Annual P&L'!F16*P5/'Annual P&L'!F5,0) -> 91.527095 | Q14: =IFERROR('Annual P&L'!F16*Q5/'Annual P&L'!F5,0) -> 94.97473 | R14: =IFERROR('Annual P&L'!F16*R5/'Annual P&L'!F5,0) -> 99.876963 | S14: =IFERROR('Annual P&L'!F16*S5/'Annual P&L'!F5,0) -> 102.1995 | T14: =IFERROR('Annual P&L'!F16*T5/'Annual P&L'!F5,0) -> 102.1995 | U14: =IFERROR('Annual P&L'!F16*U5/'Annual P&L'!F5,0) -> 94.649254 | V14: =IFERROR('Annual P&L'!F16*V5/'Annual P&L'!F5,0) -> 100.73686 | W14: =IFERROR('Annual P&L'!F16*W5/'Annual P&L'!F5,0) -> 105.14084 | X14: =IFERROR('Annual P&L'!F16*X5/'Annual P&L'!F5,0) -> 108.32729 | Y14: =IFERROR('Annual P&L'!F16*Y5/'Annual P&L'!F5,0) -> 109.27961 | Z14: =IFERROR('Annual P&L'!F16*Z5/'Annual P&L'!F5,0) -> 112.13656 | AA14: =IFERROR('Annual P&L'!F16*AA5/'Annual P&L'!F5,0) -> 119.6426 | AB14: =IFERROR('Annual P&L'!F16*AB5/'Annual P&L'!F5,0) -> 120.26945 | AC14: =IFERROR('Annual P&L'!F16*AC5/'Annual P&L'!F5,0) -> 121.54724 | AD14: =IFERROR('Annual P&L'!F16*AD5/'Annual P&L'!F5,0) -> 123.84567 | AE14: =IFERROR('Annual P&L'!F16*AE5/'Annual P&L'!F5,0) -> 130.35117 | AF14: =IFERROR('Annual P&L'!F16*AF5/'Annual P&L'!F5,0) -> 129.97346 | AG14: =IFERROR('Annual P&L'!F16*AG5/'Annual P&L'!F5,0) -> 128.58315 | AH14: =IFERROR('Annual P&L'!F16*AH5/'Annual P&L'!F5,0) -> 129.57565 | AI14: =IFERROR('Annual P&L'!F16*AI5/'Annual P&L'!F5,0) -> 137.22233 | AJ14: =IFERROR('Annual P&L'!F16*AJ5/'Annual P&L'!F5,0) -> 137.82105 | AK14: =IFERROR('Annual P&L'!F16*AK5/'Annual P&L'!F5,0) -> 135.165 | AL14: =IFERROR('Annual P&L'!F16*AL5/'Annual P&L'!F5,0) -> 138.43584 | AM14: =IFERROR('Annual P&L'!F16*AM5/'Annual P&L'!F5,0) -> 141.96384 | AN14: =IFERROR('Annual P&L'!F16*AN5/'Annual P&L'!F5,0) -> 140.56549 | AO14: =IFERROR('Annual P&L'!F16*AO5/'Annual P&L'!F5,0) -> 142.44602 | AP14: =IFERROR('Annual P&L'!F16*AP5/'Annual P&L'!F5,0) -> 146.42406 | AQ14: =IFERROR('Annual P&L'!F16*AQ5/'Annual P&L'!F5,0) -> 152.41122 | AR14: =IFERROR('Annual P&L'!F16*AR5/'Annual P&L'!F5,0) -> 147.95099 | AS14: =IFERROR('Annual P&L'!F16*AS5/'Annual P&L'!F5,0) -> 146.66516 | AT14: =IFERROR('Annual P&L'!F16*AT5/'Annual P&L'!F5,0) -> 156.05018 | AU14: =IFERROR('Annual P&L'!F16*AU5/'Annual P&L'!F5,0) -> 156.05018 | AV14: =IFERROR('Annual P&L'!F16*AV5/'Annual P&L'!F5,0) -> 156.05018 | AW14: =IFERROR('Annual P&L'!F16*AW5/'Annual P&L'!F5,0) -> 160.29067 | AX14: =IFERROR('Annual P&L'!F16*AX5/'Annual P&L'!F5,0) -> 160.29067 | AY14: =IFERROR('Annual P&L'!F16*AY5/'Annual P&L'!F5,0) -> 160.29067 | AZ14: =IFERROR('Annual P&L'!F16*AZ5/'Annual P&L'!F5,0) -> 160.29067 | BA14: =IFERROR('Annual P&L'!F16*BA5/'Annual P&L'!F5,0) -> 168.21202 | BB14: =IFERROR('Annual P&L'!F16*BB5/'Annual P&L'!F5,0) -> 168.21202 | BC14: =IFERROR('Annual P&L'!F16*BC5/'Annual P&L'!F5,0) -> 168.21202 | BD14: =IFERROR('Annual P&L'!F16*BD5/'Annual P&L'!F5,0) -> 168.21202 | BE14: =IFERROR('Annual P&L'!F16*BE5/'Annual P&L'!F5,0) -> 177.12445 | BF14: =IFERROR('Annual P&L'!F16*BF5/'Annual P&L'!F5,0) -> 177.12445 | BG14: =IFERROR('Annual P&L'!F16*BG5/'Annual P&L'!F5,0) -> 177.12445 | BH14: =IFERROR('Annual P&L'!F16*BH5/'Annual P&L'!F5,0) -> 177.12445
A15: EBITDA | B15: =B17+B14 -> 361.45576 | C15: =C17+C14 -> 378.39079 | D15: =D17+D14 -> 393.88754 | E15: =E17+E14 -> 425.73333 | F15: =F17+F14 -> 420.4485 | G15: =G17+G14 -> 432.21997 | H15: =H17+H14 -> 444.41229 | I15: =I17+I14 -> 471.50348 | ... BH15: =BH17+BH14 -> 882.40907
A16: EBITDA margin | B16: =IFERROR(B15/B5,0) -> 0.2340248 | C16: =IFERROR(C15/C5,0) -> 0.24161343 | D16: =IFERROR(D15/D5,0) -> 0.24816504 | E16: =IFERROR(E15/E5,0) -> 0.25180891 | F16: =IFERROR(F15/F5,0) -> 0.24410619 | G16: =IFERROR(G15/G5,0) -> 0.24764795 | H16: =IFERROR(H15/H5,0) -> 0.24461267 | I16: =IFERROR(I15/I5,0) -> 0.25024068 | ... BH16: =IFERROR(BH15/BH5,0) -> 0.20018223
A17: EBIT | B17: =IFERROR(B16/B14,0) -> 299.39353 | C17: =IFERROR(C16/C14,0) -> 315.4614 | D17: =IFERROR(D16/D14,0) -> 330.1103 | E17: =IFERROR(E16/E14,0) -> 357.79722 | F17: =IFERROR(F16/F14,0) -> 351.23861 | G17: =IFERROR(G16/G14,0) -> 362.08992 | H17: =IFERROR(H16/H14,0) -> 371.40921 | I17: =IFERROR(I16/I14,0) -> 395.79211 | ... BH17: =IFERROR(BH16/BH14,0) -> 705.28462
A18: EBIT margin | B18: =IFERROR(B11/B5,0) -> 0.13826406 | C18: 0.2014312 | D18: 0.2079828 | E18: 0.21162668 | F18: 0.20392395 | G18: 0.20746572 | H18: 0.20443043 | I18: 0.21005844 | J18: 0.20870195 | K18: 0.20596502 | L18: 0.20821003 | M18: 0.2070183 | N18: 0.20422583 | O18: 0.19313332 | P18: 0.19149468 | Q18: 0.17193303 | R18: 0.19893884 | S18: 0.20308795 | T18: 0.20683163 | U18: 0.20514545 | V18: 0.21582231 | W18: 0.22883639 | X18: 0.17574585 | Y18: 0.19807654 | Z18: 0.19477124 | AA18: 0.19363217 | AB18: 0.1860424 | AC18: 0.17362768 | AD18: 0.18123633 | AE18: 0.19595506 | AF18: 0.18026009 | AG18: 0.16877092 | AH18: =IFERROR(AH11/AH5,0) -> 0.16256749 | AI18: 0.19841102 | AJ18: 0.17628689 | AK18: 0.17382471 | AL18: 0.18588455 | AM18: 0.1949816 | AN18: 0.17975931 | AO18: 0.16300372 | AP18: 0.17209317 | AQ18: 0.1836325 | AR18: 0.16161973 | AS18: 0.16752943 | AT18: =AT14-AT16 -> 0.16 | AU18: =AU14-AU16 -> 0.16 | AV18: =AV14-AV16 -> 0.16 | AW18: =AW14-AW16 -> 0.16 | AX18: =AX14-AX16 -> 0.16 | AY18: =AY14-AY16 -> 0.16 | AZ18: =AZ14-AZ16 -> 0.16 | BA18: =BA14-BA16 -> 0.16 | ... BH18: =BH14-BH16 -> 0.16
A19: Foreign exchange gain / (loss) | B19: =0 -> 0 | C19: =0 -> 0 | D19: =0 -> 0 | E19: =0 -> 0 | F19: =0 -> 0 | G19: =0 -> 0 | H19: =0 -> 0 | I19: =0 -> 0 | ... BH19: =0 -> 0
A20: Other income | B20: =44.5394701594533+B21 -> 44.53947 | C20: =52.0973213422299+C21 -> 52.097321 | D20: =29.3761076836791+D21 -> 29.376108 | E20: =27.8899876499647+E21 -> 27.889988 | F20: =30.5034812049657+F21 -> 30.503481 | G20: =27.773522938886+G21 -> 27.773523 | H20: =25.1726209242512+H21 -> 25.172621 | I20: =25.1247345460531+I21 -> 25.124735 | J20: =23.879041338266+J21 -> 23.879041 | K20: =20.9540911930043+K21 -> 20.954091 | L20: =18.4021549434706+L21 -> 18.402155 | M20: =22.6501297016861+M21 -> 22.65013 | N20: =25.8423928403203+N21 -> 25.842393 | O20: =22.296866042423+O21 -> 22.296866 | P20: =18.3762476547842+P21 -> 18.376248 | Q20: =15.6853820395738+Q21 -> 15.685382 | R20: =0.992651757188498+R21 -> 0.99265176 | S20: =7.57339950372208+S21 -> 7.5733995 | T20: =3.14675632060247+T21 -> 3.1467563 | U20: =27.0656073090073+U21 -> 27.065607 | V20: =18.7411530601269+V21 -> 18.741153 | W20: =16.809574137395+W21 -> 16.809574 | X20: =19.6270084512778+X21 -> 19.627008 | Y20: =16.939904325294+Y21 -> 16.939904 | Z20: =10.4034809973372+Z21 -> 10.403481 | AA20: =17.3335273834579+AA21 -> 17.333527 | AB20: =15.4973093773509+AB21 -> 15.497309 | AC20: =33.9050758608932+AC21 -> 33.905076 | AD20: =13.8585878635663+AD21 -> 13.858588 | AE20: =17.1312359550561+AE21 -> 17.131236 | AF20: =48.2649101706382+AF21 -> 48.26491 | AG20: =31.3964101003955+AG21 -> 31.39641 | AH20: =25.2685325434912+AH21 -> 25.268533 | AI20: =27.6119665330802+AI21 -> 27.611967 | AJ20: =29.4861398645566+AJ21 -> 29.48614 | AK20: =99.6299604376804+AK21 -> 99.62996 | AL20: =38.4365047467257+AL21 -> 38.436505 | AM20: =35.9328203412512+AM21 -> 35.93282 | AN20: =34.4661641208754+AN21 -> 34.466164 | AO20: =28.2674882203697+AO21 -> 28.267488 | AP20: =23.3867635088598+AP21 -> 23.386764 | AQ20: =27.4351972130373+AQ21 -> 27.435197 | AR20: =22.7544804449545+AR21 -> 22.75448 | AS20: =33.249949391249+AS21 -> 33.249949 | AT20: =AT14-AT11+AT21 -> -2407.1004 | AU20: =47.9180093415809+AU21 -> 47.918009 | AV20: =47.9180093415809+AV21 -> 47.918009 | AW20: =49.4109539000793+AW21 -> 49.410954 | AX20: =49.4109539000793+AX21 -> 49.410954 | AY20: =49.4109539000793+AY21 -> 49.410954 | AZ20: =49.4109539000793+AZ21 -> 49.410954 | BA20: =52.386594622914+BA21 -> 52.386595 | BB20: =52.386594622914+BB21 -> 52.386595 | BC20: =52.386594622914+BC21 -> 52.386595 | BD20: =52.386594622914+BD21 -> 52.386595 | BE20: =55.5414352399521+BE21 -> 55.541435 | BF20: =55.5414352399521+BF21 -> 55.541435 | BG20: =55.5414352399521+BG21 -> 55.541435 | BH20: =55.5414352399521+BH21 -> 55.541435
A21: Finance cost | B21: =IFERROR('Annual P&L'!F20*B5/'Annual P&L'!F5,0) -> 0 | C21: =IFERROR('Annual P&L'!F20*C5/'Annual P&L'!F5,0) -> 0 | D21: =IFERROR('Annual P&L'!F20*D5/'Annual P&L'!F5,0) -> 0 | E21: =IFERROR('Annual P&L'!F20*E5/'Annual P&L'!F5,0) -> 0 | F21: =IFERROR('Annual P&L'!F20*F5/'Annual P&L'!F5,0) -> 0 | G21: =IFERROR('Annual P&L'!F20*G5/'Annual P&L'!F5,0) -> 0 | H21: =IFERROR('Annual P&L'!F20*H5/'Annual P&L'!F5,0) -> 0 | I21: =IFERROR('Annual P&L'!F20*I5/'Annual P&L'!F5,0) -> 0 | J21: =IFERROR('Annual P&L'!F20*J5/'Annual P&L'!F5,0) -> 0 | K21: =IFERROR('Annual P&L'!F20*K5/'Annual P&L'!F5,0) -> 0 | L21: =IFERROR('Annual P&L'!F20*L5/'Annual P&L'!F5,0) -> 0 | M21: =IFERROR('Annual P&L'!F20*M5/'Annual P&L'!F5,0) -> 0 | N21: =IFERROR('Annual P&L'!F20*N5/'Annual P&L'!F5,0) -> 0 | O21: =IFERROR('Annual P&L'!F20*O5/'Annual P&L'!F5,0) -> 0 | P21: =IFERROR('Annual P&L'!F20*P5/'Annual P&L'!F5,0) -> 0 | Q21: =IFERROR('Annual P&L'!F20*Q5/'Annual P&L'!F5,0) -> 0 | R21: =IFERROR('Annual P&L'!F20*R5/'Annual P&L'!F5,0) -> 0 | S21: =IFERROR('Annual P&L'!F20*S5/'Annual P&L'!F5,0) -> 0 | T21: =IFERROR('Annual P&L'!F20*T5/'Annual P&L'!F5,0) -> 0 | U21: =IFERROR('Annual P&L'!F20*U5/'Annual P&L'!F5,0) -> 0 | V21: =IFERROR('Annual P&L'!F20*V5/'Annual P&L'!F5,0) -> 0 | W21: =IFERROR('Annual P&L'!F20*W5/'Annual P&L'!F5,0) -> 0 | X21: =IFERROR('Annual P&L'!F20*X5/'Annual P&L'!F5,0) -> 0 | Y21: =IFERROR('Annual P&L'!F20*Y5/'Annual P&L'!F5,0) -> 0 | Z21: =IFERROR('Annual P&L'!F20*Z5/'Annual P&L'!F5,0) -> 0 | AA21: =IFERROR('Annual P&L'!F20*AA5/'Annual P&L'!F5,0) -> 0 | AB21: =IFERROR('Annual P&L'!F20*AB5/'Annual P&L'!F5,0) -> 0 | AC21: =IFERROR('Annual P&L'!F20*AC5/'Annual P&L'!F5,0) -> 0 | AD21: =IFERROR('Annual P&L'!F20*AD5/'Annual P&L'!F5,0) -> 0 | AE21: =IFERROR('Annual P&L'!F20*AE5/'Annual P&L'!F5,0) -> 0 | AF21: =IFERROR('Annual P&L'!F20*AF5/'Annual P&L'!F5,0) -> 0 | AG21: =IFERROR('Annual P&L'!F20*AG5/'Annual P&L'!F5,0) -> 0 | AH21: =IFERROR('Annual P&L'!F20*AH5/'Annual P&L'!F5,0) -> 0 | AI21: =IFERROR('Annual P&L'!F20*AI5/'Annual P&L'!F5,0) -> 0 | AJ21: =IFERROR('Annual P&L'!F20*AJ5/'Annual P&L'!F5,0) -> 0 | AK21: =IFERROR('Annual P&L'!F20*AK5/'Annual P&L'!F5,0) -> 0 | AL21: =IFERROR('Annual P&L'!F20*AL5/'Annual P&L'!F5,0) -> 0 | AM21: =IFERROR('Annual P&L'!F20*AM5/'Annual P&L'!F5,0) -> 0 | AN21: =IFERROR('Annual P&L'!F20*AN5/'Annual P&L'!F5,0) -> 0 | AO21: =IFERROR('Annual P&L'!F20*AO5/'Annual P&L'!F5,0) -> 0 | AP21: =IFERROR('Annual P&L'!F20*AP5/'Annual P&L'!F5,0) -> 0 | AQ21: =IFERROR('Annual P&L'!F20*AQ5/'Annual P&L'!F5,0) -> 0 | AR21: =IFERROR('Annual P&L'!F20*AR5/'Annual P&L'!F5,0) -> 0 | AS21: =IFERROR('Annual P&L'!F20*AS5/'Annual P&L'!F5,0) -> 0 | AT21: =IFERROR('Annual P&L'!F20*AT5/'Annual P&L'!F5,0) -> 0 | AU21: =IFERROR('Annual P&L'!F20*AU5/'Annual P&L'!F5,0) -> 0 | AV21: =IFERROR('Annual P&L'!F20*AV5/'Annual P&L'!F5,0) -> 0 | AW21: =IFERROR('Annual P&L'!F20*AW5/'Annual P&L'!F5,0) -> 0 | AX21: =IFERROR('Annual P&L'!F20*AX5/'Annual P&L'!F5,0) -> 0 | AY21: =IFERROR('Annual P&L'!F20*AY5/'Annual P&L'!F5,0) -> 0 | AZ21: =IFERROR('Annual P&L'!F20*AZ5/'Annual P&L'!F5,0) -> 0 | BA21: =IFERROR('Annual P&L'!F20*BA5/'Annual P&L'!F5,0) -> 0 | BB21: =IFERROR('Annual P&L'!F20*BB5/'Annual P&L'!F5,0) -> 0 | BC21: =IFERROR('Annual P&L'!F20*BC5/'Annual P&L'!F5,0) -> 0 | BD21: =IFERROR('Annual P&L'!F20*BD5/'Annual P&L'!F5,0) -> 0 | BE21: =IFERROR('Annual P&L'!F20*BE5/'Annual P&L'!F5,0) -> 0 | BF21: =IFERROR('Annual P&L'!F20*BF5/'Annual P&L'!F5,0) -> 0 | BG21: =IFERROR('Annual P&L'!F20*BG5/'Annual P&L'!F5,0) -> 0 | BH21: =IFERROR('Annual P&L'!F20*BH5/'Annual P&L'!F5,0) -> 0
A22: PBT | B22: =B17+B19+B20-B21 -> 343.933 | C22: =C17+C19+C20-C21 -> 367.55872 | D22: =D17+D19+D20-D21 -> 359.48641 | E22: =E17+E19+E20-E21 -> 385.68721 | F22: =F17+F19+F20-F21 -> 381.7421 | G22: =G17+G19+G20-G21 -> 389.86344 | H22: =H17+H19+H20-H21 -> 396.58183 | I22: =I17+I19+I20-I21 -> 420.91685 | ... BH22: =BH17+BH19+BH20-BH21 -> 760.82605
A23: PBT margin | B23: =IFERROR(B14/B5,0) -> 0.040182235 | C23: =IFERROR(C14/C5,0) -> 0.040182235 | D23: =IFERROR(D14/D5,0) -> 0.040182235 | E23: =IFERROR(E14/E5,0) -> 0.040182235 | F23: =IFERROR(F14/F5,0) -> 0.040182235 | G23: =IFERROR(G14/G5,0) -> 0.040182235 | H23: =IFERROR(H14/H5,0) -> 0.040182235 | I23: =IFERROR(I14/I5,0) -> 0.040182235 | ... AS23: =IFERROR(AS14/AS5,0) -> 0.040182235 | AT23: =AT21/AT5 -> 0 | AU23: =AU21/AU5 -> 0 | AV23: =AV21/AV5 -> 0 | AW23: =AW21/AW5 -> 0 | AX23: =AX21/AX5 -> 0 | AY23: =AY21/AY5 -> 0 | AZ23: =AZ21/AZ5 -> 0 | BA23: =BA21/BA5 -> 0 | ... BH23: =BH21/BH5 -> 0
A24: Income tax | B24: =B21*4 -> 0 | C24: =C21*4 -> 0 | D24: =D21*4 -> 0 | E24: =E21*4 -> 0 | F24: =F21*4 -> 0 | G24: =G21*4 -> 0 | H24: =H21*4 -> 0 | I24: =I21*4 -> 0 | ... BH24: =BH21*4 -> 0
A25: Effective tax rate | B25: =IFERROR(B16/B14,0) -> 0.0037708091 | C25: 0.20931191 | D25: 0.20511762 | E25: 0.2099768 | F25: 0.21073247 | G25: 0.21523304 | H25: 0.11516534 | I25: 0.20007369 | J25: 0.20407421 | K25: 0.20879913 | L25: 0.22144604 | M25: 0.20555188 | N25: 0.21068987 | O25: 0.17737386 | P25: 0.19272955 | Q25: 0.24036822 | R25: 0.23898111 | S25: 0.18490768 | T25: 0.1827818 | U25: 0.24036223 | V25: 0.24060694 | W25: 0.1197974 | X25: 0.33129346 | Y25: 0.21634146 | Z25: 0.20439024 | AA25: 0.22384374 | AB25: 0.16685952 | AC25: 0.24348628 | AD25: 0.23904035 | AE25: 0.23748371 | AF25: 0.23377624 | AG25: 0.24808348 | AH25: =IFERROR(AH16/AH14,0) -> 0.0017334109 | AI25: 0.25927818 | AJ25: 0.24179161 | AK25: 0.25367905 | AL25: 0.25496747 | AM25: 0.25081539 | AN25: 0.24864865 | AO25: 0.25920216 | AP25: 0.25710277 | AQ25: 0.25738592 | AR25: 0.212557 | AS25: 0.24263261 | AT25: 0.25 | AU25: 0.25 | AV25: 0.25 | AW25: 0.25 | AX25: 0.25 | AY25: 0.25 | AZ25: 0.25 | BA25: 0.25 | BB25: 0.25 | BC25: 0.25 | BD25: 0.25 | BE25: 0.25 | BF25: 0.25 | BG25: 0.25 | BH25: 0.25
A26: Minority / affiliate income | B26: =0 -> 0 | C26: =0 -> 0 | D26: =0 -> 0 | E26: =0 -> 0 | F26: =0 -> 0 | G26: =0 -> 0 | H26: =0 -> 0 | I26: =0 -> 0 | ... BH26: =0 -> 0
A27: Net profit | B27: =B22-B24+B26 -> 271.646 | C27: =C22-C24+C26 -> 290.6243 | D27: =D22-D24+D26 -> 285.74941 | E27: =E22-E24+E26 -> 304.70184 | F27: =F22-F24+F26 -> 301.29664 | G27: =G22-G24+G26 -> 305.95195 | H27: =H22-H24+H26 -> 350.90935 | I27: =I22-I24+I26 -> 336.70246 | ... BH27: =BH22-BH24+BH26 -> 716.54494
A28: Net margin | B28: =IFERROR(B18/B5,0) -> 8.9519172e-05 | C28: 0.18557199 | D28: 0.18003365 | E28: 0.1802223 | F28: 0.17492838 | G28: 0.17530049 | H28: 0.19314693 | I28: 0.17869784 | J28: 0.17596912 | K28: 0.17129919 | L28: 0.16913271 | M28: 0.17322381 | N28: 0.17091717 | O28: 0.1672081 | P28: 0.16110069 | Q28: 0.13564688 | R28: 0.15170014 | S28: 0.1679625 | T28: 0.17003765 | U28: 0.16456477 | V28: 0.16957083 | W28: 0.20707699 | X28: 0.1223908 | Y28: 0.16010564 | Z28: 0.15792786 | AA28: 0.15480722 | AB28: 0.15931318 | AC28: 0.13983123 | AD28: 0.14133517 | AE28: 0.15344569 | AF28: 0.14955273 | AG28: 0.13427898 | AH28: =IFERROR(AH18/AH5,0) -> 5.0413213e-05 | AI28: 0.15295648 | AJ28: 0.14018036 | AK28: 0.15183377 | AL28: 0.14680202 | AM28: 0.15369689 | AN28: 0.14246512 | AO28: 0.12665986 | AP28: 0.13261537 | AQ28: 0.14173949 | AR28: 0.13213266 | AS28: 0.13378062 | AT28: 0.129 | AU28: 0.129 | AV28: 0.129 | AW28: 0.129 | AX28: 0.129 | AY28: 0.129 | AZ28: 0.129 | BA28: 0.129 | BB28: 0.129 | BC28: 0.129 | BD28: 0.129 | BE28: 0.129 | BF28: 0.129 | BG28: 0.129 | BH28: 0.129
A29: Weighted-average basic shares (cr) | B29: ='Annual P&L'!F27 -> 271.35943 | C29: ='Annual P&L'!F27 -> 271.35943 | D29: ='Annual P&L'!F27 -> 271.35943 | E29: ='Annual P&L'!F27 -> 271.35943 | F29: ='Annual P&L'!F27 -> 271.35943 | G29: ='Annual P&L'!F27 -> 271.35943 | H29: ='Annual P&L'!F27 -> 271.35943 | I29: ='Annual P&L'!F27 -> 271.35943 | J29: ='Annual P&L'!F27 -> 271.35943 | K29: ='Annual P&L'!F27 -> 271.35943 | L29: ='Annual P&L'!F27 -> 271.35943 | M29: ='Annual P&L'!F27 -> 271.35943 | N29: ='Annual P&L'!F27 -> 271.35943 | O29: ='Annual P&L'!F27 -> 271.35943 | P29: ='Annual P&L'!F27 -> 271.35943 | Q29: ='Annual P&L'!F27 -> 271.35943 | R29: ='Annual P&L'!F27 -> 271.35943 | S29: ='Annual P&L'!F27 -> 271.35943 | T29: ='Annual P&L'!F27 -> 271.35943 | U29: ='Annual P&L'!F27 -> 271.35943 | V29: ='Annual P&L'!F27 -> 271.35943 | W29: ='Annual P&L'!F27 -> 271.35943 | X29: ='Annual P&L'!F27 -> 271.35943 | Y29: ='Annual P&L'!F27 -> 271.35943 | Z29: ='Annual P&L'!F27 -> 271.35943 | AA29: ='Annual P&L'!F27 -> 271.35943 | AB29: ='Annual P&L'!F27 -> 271.35943 | AC29: ='Annual P&L'!F27 -> 271.35943 | AD29: ='Annual P&L'!F27 -> 271.35943 | AE29: ='Annual P&L'!F27 -> 271.35943 | AF29: ='Annual P&L'!F27 -> 271.35943 | AG29: ='Annual P&L'!F27 -> 271.35943 | AH29: ='Annual P&L'!F27 -> 271.35943 | AI29: ='Annual P&L'!F27 -> 271.35943 | AJ29: ='Annual P&L'!F27 -> 271.35943 | AK29: ='Annual P&L'!F27 -> 271.35943 | AL29: ='Annual P&L'!F27 -> 271.35943 | AM29: ='Annual P&L'!F27 -> 271.35943 | AN29: ='Annual P&L'!F27 -> 271.35943 | AO29: ='Annual P&L'!F27 -> 271.35943 | AP29: ='Annual P&L'!F27 -> 271.35943 | AQ29: ='Annual P&L'!F27 -> 271.35943 | AR29: ='Annual P&L'!F27 -> 271.35943 | AS29: ='Annual P&L'!F27 -> 271.35943 | AT29: ='Annual P&L'!F27 -> 271.35943 | AU29: ='Annual P&L'!F27 -> 271.35943 | AV29: ='Annual P&L'!F27 -> 271.35943 | AW29: ='Annual P&L'!F27 -> 271.35943 | AX29: ='Annual P&L'!F27 -> 271.35943 | AY29: ='Annual P&L'!F27 -> 271.35943 | AZ29: ='Annual P&L'!F27 -> 271.35943 | BA29: ='Annual P&L'!F27 -> 271.35943 | BB29: ='Annual P&L'!F27 -> 271.35943 | BC29: ='Annual P&L'!F27 -> 271.35943 | BD29: ='Annual P&L'!F27 -> 271.35943 | BE29: ='Annual P&L'!F27 -> 271.35943 | BF29: ='Annual P&L'!F27 -> 271.35943 | BG29: ='Annual P&L'!F27 -> 271.35943 | BH29: ='Annual P&L'!F27 -> 271.35943
A30: Weighted-average diluted shares (cr) | B30: ='Annual P&L'!F28 -> 271.35943 | C30: ='Annual P&L'!F28 -> 271.35943 | D30: ='Annual P&L'!F28 -> 271.35943 | E30: ='Annual P&L'!F28 -> 271.35943 | F30: ='Annual P&L'!F28 -> 271.35943 | G30: ='Annual P&L'!F28 -> 271.35943 | H30: ='Annual P&L'!F28 -> 271.35943 | I30: ='Annual P&L'!F28 -> 271.35943 | J30: ='Annual P&L'!F28 -> 271.35943 | K30: ='Annual P&L'!F28 -> 271.35943 | L30: ='Annual P&L'!F28 -> 271.35943 | M30: ='Annual P&L'!F28 -> 271.35943 | N30: ='Annual P&L'!F28 -> 271.35943 | O30: ='Annual P&L'!F28 -> 271.35943 | P30: ='Annual P&L'!F28 -> 271.35943 | Q30: ='Annual P&L'!F28 -> 271.35943 | R30: ='Annual P&L'!F28 -> 271.35943 | S30: ='Annual P&L'!F28 -> 271.35943 | T30: ='Annual P&L'!F28 -> 271.35943 | U30: ='Annual P&L'!F28 -> 271.35943 | V30: ='Annual P&L'!F28 -> 271.35943 | W30: ='Annual P&L'!F28 -> 271.35943 | X30: ='Annual P&L'!F28 -> 271.35943 | Y30: ='Annual P&L'!F28 -> 271.35943 | Z30: ='Annual P&L'!F28 -> 271.35943 | AA30: ='Annual P&L'!F28 -> 271.35943 | AB30: ='Annual P&L'!F28 -> 271.35943 | AC30: ='Annual P&L'!F28 -> 271.35943 | AD30: ='Annual P&L'!F28 -> 271.35943 | AE30: ='Annual P&L'!F28 -> 271.35943 | AF30: ='Annual P&L'!F28 -> 271.35943 | AG30: ='Annual P&L'!F28 -> 271.35943 | AH30: ='Annual P&L'!F28 -> 271.35943 | AI30: ='Annual P&L'!F28 -> 271.35943 | AJ30: ='Annual P&L'!F28 -> 271.35943 | AK30: ='Annual P&L'!F28 -> 271.35943 | AL30: ='Annual P&L'!F28 -> 271.35943 | AM30: ='Annual P&L'!F28 -> 271.35943 | AN30: ='Annual P&L'!F28 -> 271.35943 | AO30: ='Annual P&L'!F28 -> 271.35943 | AP30: ='Annual P&L'!F28 -> 271.35943 | AQ30: ='Annual P&L'!F28 -> 271.35943 | AR30: ='Annual P&L'!F28 -> 271.35943 | AS30: ='Annual P&L'!F28 -> 271.35943 | AT30: ='Annual P&L'!F28 -> 271.35943 | AU30: ='Annual P&L'!F28 -> 271.35943 | AV30: ='Annual P&L'!F28 -> 271.35943 | AW30: ='Annual P&L'!F28 -> 271.35943 | AX30: ='Annual P&L'!F28 -> 271.35943 | AY30: ='Annual P&L'!F28 -> 271.35943 | AZ30: ='Annual P&L'!F28 -> 271.35943 | BA30: ='Annual P&L'!F28 -> 271.35943 | BB30: ='Annual P&L'!F28 -> 271.35943 | BC30: ='Annual P&L'!F28 -> 271.35943 | BD30: ='Annual P&L'!F28 -> 271.35943 | BE30: ='Annual P&L'!F28 -> 271.35943 | BF30: ='Annual P&L'!F28 -> 271.35943 | BG30: ='Annual P&L'!F28 -> 271.35943 | BH30: ='Annual P&L'!F28 -> 271.35943
A31: Basic EPS (INR) | B31: =IFERROR(B27/B29,0) -> 1.0010561 | C31: =IFERROR(C27/C29,0) -> 1.0709939 | D31: =IFERROR(D27/D29,0) -> 1.0530292 | E31: =IFERROR(E27/E29,0) -> 1.1228718 | F31: =IFERROR(F27/F29,0) -> 1.1103231 | G31: =IFERROR(G27/G29,0) -> 1.1274786 | H31: =IFERROR(H27/H29,0) -> 1.2931533 | I31: =IFERROR(I27/I29,0) -> 1.2407988 | ... BH31: =IFERROR(BH27/BH29,0) -> 2.640575
A32: Diluted EPS (INR) | B32: =IFERROR(B27/B30,0) -> 1.0010561 | C32: =IFERROR(C27/C30,0) -> 1.0709939 | D32: =IFERROR(D27/D30,0) -> 1.0530292 | E32: =IFERROR(E27/E30,0) -> 1.1228718 | F32: =IFERROR(F27/F30,0) -> 1.1103231 | G32: =IFERROR(G27/G30,0) -> 1.1274786 | H32: =IFERROR(H27/H30,0) -> 1.2931533 | I32: =IFERROR(I27/I30,0) -> 1.2407988 | ... BH32: =IFERROR(BH27/BH30,0) -> 2.640575
A34: ADVANCED AI REVENUE
A35: Advanced AI revenue growth | AQ35: 146 | AR35: 155.1 | AS35: 171 | AT35: =AS21*(1+Assumptions!M37)^(1/4) -> 0 | AU35: =AT21*(1+Assumptions!M37)^(1/4) -> 0 | AV35: =AU21*(1+Assumptions!M37)^(1/4) -> 0 | AW35: =AV21*(1+Assumptions!N37)^(1/4) -> 0 | AX35: =AW21*(1+Assumptions!N37)^(1/4) -> 0 | AY35: =AX21*(1+Assumptions!N37)^(1/4) -> 0 | AZ35: =AY21*(1+Assumptions!N37)^(1/4) -> 0 | BA35: =AZ21*(1+Assumptions!O37)^(1/4) -> 0 | BB35: =BA21*(1+Assumptions!O37)^(1/4) -> 0 | BC35: =BB21*(1+Assumptions!O37)^(1/4) -> 0 | BD35: =BC21*(1+Assumptions!O37)^(1/4) -> 0 | BE35: =BD21*(1+Assumptions!P37)^(1/4) -> 0 | BF35: =BE21*(1+Assumptions!P37)^(1/4) -> 0 | BG35: =BF21*(1+Assumptions!P37)^(1/4) -> 0 | BH35: =BG21*(1+Assumptions!P37)^(1/4) -> 0
A36: Advanced AI mix of revenue | B36: =IFERROR(B37/B5,0) -> 0 | C36: =IFERROR(C37/C5,0) -> 0 | D36: =IFERROR(D37/D5,0) -> 0 | E36: =IFERROR(E37/E5,0) -> 0 | F36: =IFERROR(F37/F5,0) -> 0 | G36: =IFERROR(G37/G5,0) -> 0 | H36: =IFERROR(H37/H5,0) -> 0 | I36: =IFERROR(I37/I5,0) -> 0 | ... BH36: =IFERROR(BH37/BH5,0) -> 2.0040139e-05
A37: Implied quarterly Advanced AI revenue ($m) | B37: =IFERROR(B21/B5,0) -> 0 | C37: 0 | D37: 0 | E37: 0 | F37: 0 | G37: 0 | H37: 0 | I37: 0 | J37: 0 | K37: 0 | L37: 0 | M37: 0 | N37: 0 | O37: 0 | P37: 0 | Q37: 0 | R37: 0 | S37: 0 | T37: 0 | U37: 0 | V37: 0 | W37: 0 | X37: 0 | Y37: 0 | Z37: 0 | AA37: 0 | AB37: 0 | AC37: 0 | AD37: 0 | AE37: 0 | AF37: 0 | AG37: 0 | AH37: 0 | AI37: 0 | AJ37: 0 | AK37: 0 | AL37: 0 | AM37: 0 | AN37: 0 | AO37: 0 | AP37: 0 | AQ37: 0.038491959 | AR37: 0.042123846 | AS37: 0.046849315 | AT37: =AT21/AT5 -> 0 | AU37: 0.047877735 | AV37: 0.050624541 | AW37: 0.0519634 | AX37: 0.054999468 | AY37: 0.058212925 | AZ37: 0.061614135 | BA37: 0.06162588 | BB37: 0.065349586 | BC37: 0.069298295 | BD37: 0.073485602 | BE37: 0.073644495 | BF37: 0.078248361 | BG37: 0.083140036 | BH37: 0.088337513
A38: Annualized Advanced AI revenue ($m) | B38: =B21*4 -> 0 | C38: 0 | D38: 0 | E38: 0 | F38: 0 | G38: 0 | H38: 0 | I38: 0 | J38: 0 | K38: 0 | L38: 0 | M38: 0 | N38: 0 | O38: 0 | P38: 0 | Q38: 0 | R38: 0 | S38: 0 | T38: 0 | U38: 0 | V38: 0 | W38: 0 | X38: 0 | Y38: 0 | Z38: 0 | AA38: 0 | AB38: 0 | AC38: 0 | AD38: 0 | AE38: 0 | AF38: 0 | AG38: 0 | AH38: =AH21*4 -> 0 | AI38: 0 | AJ38: 0 | AK38: 0 | AL38: 0 | AM38: 0 | AN38: 0 | AO38: 0 | AP38: 0 | AQ38: 584 | AR38: 620.4 | AS38: 684 | AT38: 723.24194 | AU38: 764.73525 | AV38: 808.60908 | AW38: 855.85372 | AX38: 905.85873 | AY38: 958.78539 | AZ38: 1014.8044 | BA38: 1076.1233 | BB38: 1141.1474 | BC38: 1210.1006 | BD38: 1283.2202 | BE38: 1363.4403 | BF38: 1448.6754 | BG38: 1539.239 | BH38: 1635.4641

Sheet Annual P&L
A1: Annual Profit & Loss Statement
A2: FY16 is a nine-month transition year
A4: Metric | B4: FY16A | C4: FY17A | D4: FY18A | E4: FY19A | F4: FY20A | G4: FY21A | H4: FY22A | I4: FY23A | J4: FY24A | K4: FY25A | L4: FY26A | M4: FY27E | N4: FY28E | O4: FY29E | P4: FY30E
A5: Revenue | B5: 31136 | C5: 46722 | D5: 50570 | E5: 60428 | F5: 70678 | G5: 75379 | H5: 85651 | I5: 101456 | J5: 109913 | K5: 117055 | L5: 130144 | M5: ='Revenue Drivers'!M5 -> 135794.62 | N5: ='Revenue Drivers'!N5 -> 141613.89 | O5: ='Revenue Drivers'!O5 -> 148612.26 | P5: ='Revenue Drivers'!P5 -> 156486.23
A6: Growth | B6: =0 -> 0 | C6: =C5/B5-1 -> 0.50057811 | D6: =D5/C5-1 -> 0.082359488 | E6: =E5/D5-1 -> 0.19493771 | F6: =F5/E5-1 -> 0.16962335 | G6: =G5/F5-1 -> 0.066512918 | H6: =H5/G5-1 -> 0.13627138 | I6: =I5/H5-1 -> 0.18452791 | J6: =J5/I5-1 -> 0.083356332 | ... P6: =P5/O5-1 -> 0.052983298
A7: Cost of services | B7: 20472.719 | C7: 30889 | D7: 33237 | E7: 39268 | F7: 45295 | G7: 45975 | H7: 54416 | I7: 66155 | J7: 72125 | K7: 77815 | L7: 87811 | M7: =M5-M8 -> 89624.447 | N7: =N5-N8 -> 93465.167 | O7: =O5-O8 -> 98084.091 | P7: =P5-P8 -> 103280.91
A8: Gross profit | B8: 10663.281 | C8: 15833 | D8: 17333 | E8: 21160 | F8: 25383 | G8: 29404 | H8: 31235 | I8: 35301 | J8: 37788 | K8: 39240 | L8: 42333 | M8: =M5*Assumptions!M12 -> 46170.169 | N8: =N5*Assumptions!N12 -> 48148.722 | O8: =O5*Assumptions!O12 -> 50528.168 | P8: =P5*Assumptions!P12 -> 53205.317
A9: Gross margin | B9: =B8/B5 -> 0.34247433 | C9: =C8/C5 -> 0.33887676 | D9: =D8/D5 -> 0.34275262 | E9: =E8/E5 -> 0.3501688 | F9: =F8/F5 -> 0.3591358 | G9: =G8/G5 -> 0.39008212 | H9: =H8/H5 -> 0.36467759 | I9: =I8/I5 -> 0.34794394 | ... L9: =L8/L5 -> 0.32527815 | M9: =IFERROR(M8/M5,0) -> 0.34 | N9: =IFERROR(N8/N5,0) -> 0.34 | O9: =IFERROR(O8/O5,0) -> 0.34 | P9: =IFERROR(P8/P5,0) -> 0.34
A10: Selling & marketing | B10: 3968.8776 | C10: 5524 | D10: 5893 | E10: 7191 | F10: 8690 | G10: 9923 | H10: 10856 | I10: 12672 | J10: 13588 | K10: 13735 | L10: 15581 | M10: =M5*Assumptions!M13 -> 8147.677 | N10: =N5*Assumptions!N13 -> 8496.8333 | O10: =O5*Assumptions!O13 -> 8916.7355 | P10: =P5*Assumptions!P13 -> 9389.1736
A11: S&M / revenue | B11: =B10/B5 -> 0.12746909 | C11: =C10/C5 -> 0.11823124 | D11: =D10/D5 -> 0.11653154 | E11: =E10/E5 -> 0.11900113 | F11: =F10/F5 -> 0.12295198 | G11: =G10/G5 -> 0.13164144 | H11: =H10/H5 -> 0.12674691 | I11: =I10/I5 -> 0.12490144 | ... L11: =L10/L5 -> 0.11972123 | M11: =IFERROR(M10/M5,0) -> 0.06 | N11: =IFERROR(N10/N5,0) -> 0.06 | O11: =IFERROR(O10/O5,0) -> 0.06 | P11: =IFERROR(P10/P5,0) -> 0.06
A12: G&A | B12: 818.64 | C12: 1145.24 | D12: 1143.405 | E12: 1029.6825 | F12: 353 | G12: -1014.8025 | H12: 1312.005 | I12: 3496.92 | J12: 4379.38 | K12: 5222.9375 | L12: 7736.16 | M12: =M5*Assumptions!M14 -> 11542.542 | N12: =N5*Assumptions!N14 -> 12037.181 | O12: =O5*Assumptions!O14 -> 12632.042 | P12: =P5*Assumptions!P14 -> 13301.329
A13: G&A / revenue | B13: =B12/B5 -> 0.026292395 | C13: =C12/C5 -> 0.024511793 | D13: =D12/D5 -> 0.022610342 | E13: =E12/E5 -> 0.017039824 | F13: =F12/F5 -> 0.004994482 | G13: =G12/G5 -> -0.013462669 | H13: =H12/H5 -> 0.015318035 | I13: =I12/I5 -> 0.034467355 | ... L13: =L12/L5 -> 0.059443078 | M13: =IFERROR(M12/M5,0) -> 0.085 | N13: =IFERROR(N12/N5,0) -> 0.085 | O13: =IFERROR(O12/O5,0) -> 0.085 | P13: =IFERROR(P12/P5,0) -> 0.085
A14: EBITDA | B14: 6694.403 | C14: 10309 | D14: 11440 | E14: 13969 | F14: 16693 | G14: 19481 | H14: 20379 | I14: 22629 | J14: 24200 | K14: 25505 | L14: 26752 | M14: =M8-M10-M12 -> 26479.95 | N14: =N8-N10-N12 -> 27614.708 | O14: =O8-O10-O12 -> 28979.39 | P14: =P8-P10-P12 -> 30514.814
A15: EBITDA margin | B15: =B14/B5 -> 0.21500524 | C15: =C14/C5 -> 0.22064552 | D15: =D14/D5 -> 0.22622108 | E15: =E14/E5 -> 0.23116767 | F15: =F14/F5 -> 0.23618382 | G15: =G14/G5 -> 0.25844068 | H15: =H14/H5 -> 0.23793067 | I15: =I14/I5 -> 0.2230425 | ... L15: =L14/L5 -> 0.20555692 | M15: =IFERROR(M14/M5,0) -> 0.195 | N15: =IFERROR(N14/N5,0) -> 0.195 | O15: =IFERROR(O14/O5,0) -> 0.195 | P15: =IFERROR(P14/P5,0) -> 0.195
A16: D&A | B16: 445.37462 | C16: 834 | D16: 1452 | E16: 2148 | F16: 2840 | G16: 3985 | H16: 4181 | I16: 4144 | J16: 4173 | K16: 4084 | L16: 4355 | M16: =M5*Assumptions!M15 -> 4752.8116 | N16: =N5*Assumptions!N15 -> 4956.4861 | O16: =O5*Assumptions!O15 -> 5201.4291 | P16: =P5*Assumptions!P15 -> 5477.0179
A17: EBIT | B17: 6249.0284 | C17: 9475 | D17: 9988 | E17: 11821 | F17: 13853 | G17: 15496 | H17: 16198 | I17: 18485 | J17: 20027 | K17: 21421 | L17: 22397 | M17: =M14-M16 -> 21727.139 | N17: =N14-N16 -> 22658.222 | O17: =O14-O16 -> 23777.961 | P17: =P14-P16 -> 25037.796
A18: EBIT margin | B18: =B17/B5 -> 0.20070107 | C18: =C17/C5 -> 0.20279526 | D18: =D17/D5 -> 0.1975084 | E18: =E17/E5 -> 0.19562124 | F18: =F17/F5 -> 0.19600158 | G18: =G17/G5 -> 0.2055745 | H18: =H17/H5 -> 0.1891163 | I18: =I17/I5 -> 0.18219721 | ... L18: =L17/L5 -> 0.17209399 | M18: =IFERROR(M17/M5,0) -> 0.16 | N18: =IFERROR(N17/N5,0) -> 0.16 | O18: =IFERROR(O17/O5,0) -> 0.16 | P18: =IFERROR(P17/P5,0) -> 0.16
A19: Net other income | B19: 797.63206 | C19: 934 | D19: 1111 | E19: 805 | F19: 179 | G19: 657 | H19: 777 | I19: 1003 | J19: 940 | K19: 1841 | L19: 661 | M19: ='Annual Balance Sheet'!L5*Assumptions!M38 -> 1256.04 | N19: ='Annual Balance Sheet'!M5*Assumptions!N38 -> 1335.1782 | O19: ='Annual Balance Sheet'!N5*Assumptions!O38 -> -993.40069 | P19: ='Annual Balance Sheet'!O5*Assumptions!P38 -> -3549.6656
A20: Finance cost | B20: 0 | C20: 0 | D20: 0 | E20: 0 | F20: 0 | G20: 0 | H20: 0 | I20: 0 | J20: 0 | K20: 0 | L20: 0 | M20: =AVERAGE('Annual Balance Sheet'!L14,'Annual Balance Sheet'!M14)*Assumptions!M39 -> 417.2 | N20: =AVERAGE('Annual Balance Sheet'!M14,'Annual Balance Sheet'!N14)*Assumptions!N39 -> 417.2 | O20: =AVERAGE('Annual Balance Sheet'!N14,'Annual Balance Sheet'!O14)*Assumptions!O39 -> 417.2 | P20: =AVERAGE('Annual Balance Sheet'!O14,'Annual Balance Sheet'!P14)*Assumptions!P39 -> 417.2
A21: PBT | B21: 7046.6605 | C21: 10409 | D21: 11099 | E21: 12626 | F21: 14032 | G21: 16153 | H21: 16975 | I21: 19488 | J21: 20967 | K21: 23262 | L21: 23058 | M21: =M17+M19-M20 -> 22565.979 | N21: =N17+N19-N20 -> 23576.2 | O21: =O17+O19-O20 -> 22367.361 | P21: =P17+P19-P20 -> 21070.931
A22: PBT margin | B22: =B21/B5 -> 0.22631875 | C22: =C21/C5 -> 0.22278584 | D22: =D21/D5 -> 0.21947795 | E22: =E21/E5 -> 0.20894287 | F22: =F21/F5 -> 0.1985342 | G22: =G21/G5 -> 0.21429045 | H22: =H21/H5 -> 0.198188 | I22: =I21/I5 -> 0.19208327 | ... L22: =L21/L5 -> 0.17717298 | M22: =IFERROR(M21/M5,0) -> 0.16617727 | N22: =IFERROR(N21/N5,0) -> 0.16648226 | O22: =IFERROR(O21/O5,0) -> 0.15050818 | P22: =IFERROR(P21/P5,0) -> 0.13465038
A23: Income tax | B23: 1477.5626 | C23: 1952 | D23: 2317 | E23: 2481 | F23: 2938 | G23: 3663 | H23: 3443 | I23: 4642 | J23: 5257 | K23: 5862 | L23: 5687 | M23: =M21*Assumptions!M17 -> 5641.4946 | N23: =N21*Assumptions!N17 -> 5894.0501 | O23: =O21*Assumptions!O17 -> 5591.8402 | P23: =P21*Assumptions!P17 -> 5267.7327
A24: Tax rate | B24: =B23/B21 -> 0.20968267 | C24: =C23/C21 -> 0.18753002 | D24: =D23/D21 -> 0.20875755 | E24: =E23/E21 -> 0.19649929 | F24: =F23/F21 -> 0.20937856 | G24: =G23/G21 -> 0.22676902 | H24: =H23/H21 -> 0.20282769 | I24: =I23/I21 -> 0.23819787 | ... L24: =L23/L21 -> 0.24663891 | M24: =IFERROR(M23/M21,0) -> 0.25 | N24: =IFERROR(N23/N21,0) -> 0.25 | O24: =IFERROR(O23/O21,0) -> 0.25 | P24: =IFERROR(P23/P21,0) -> 0.25
A25: Net profit | B25: 5569.0979 | C25: 8457 | D25: 8782 | E25: 10123 | F25: 11062 | G25: 12433 | H25: 13500 | I25: 14851 | J25: 15702 | K25: 17391 | L25: 17361 | M25: =M21-M23 -> 16924.484 | N25: =N21-N23 -> 17682.15 | O25: =O21-O23 -> 16775.521 | P25: =P21-P23 -> 15803.198
A26: Net margin | B26: =B25/B5 -> 0.17886363 | C26: =C25/C5 -> 0.18100681 | D26: =D25/D5 -> 0.17366027 | E26: =E25/E5 -> 0.16752168 | F26: =F25/F5 -> 0.15651263 | G26: =G25/G5 -> 0.16493984 | H26: =H25/H5 -> 0.15761637 | I26: =I25/I5 -> 0.14637873 | ... L26: =L25/L5 -> 0.13339839 | M26: =IFERROR(M25/M5,0) -> 0.12463295 | N26: =IFERROR(N25/N5,0) -> 0.1248617 | O26: =IFERROR(O25/O5,0) -> 0.11288114 | P26: =IFERROR(P25/P5,0) -> 0.10098779
A27: Weighted-average basic shares (cr) | B27: 282.47794 | C27: 282.57438 | D27: 280.72293 | E27: 275.20402 | F27: 271.35943 | G27: 271.36651 | H27: 271.2313 | I27: 270.96683 | J27: 271.28542 | K27: 271.25254 | L27: 271.18608 | M27: =L27*(1+Assumptions!M23) -> 271.18608 | N27: =M27*(1+Assumptions!N23) -> 271.18608 | O27: =N27*(1+Assumptions!O23) -> 271.18608 | P27: =O27*(1+Assumptions!P23) -> 271.18608
A28: Weighted-average diluted shares (cr) | B28: 282.47794 | C28: 282.57438 | D28: 280.72293 | E28: 275.20402 | F28: 271.35943 | G28: 271.36651 | H28: 271.2313 | I28: 270.96683 | J28: 271.28542 | K28: 271.25254 | L28: 271.18608 | M28: =M27*(1+Assumptions!M24) -> 271.72845 | N28: =N27*(1+Assumptions!N24) -> 271.72845 | O28: =O27*(1+Assumptions!O24) -> 271.72845 | P28: =P27*(1+Assumptions!P24) -> 271.72845
A29: Basic EPS (INR) | B29: =B25/B27 -> 19.71516 | C29: =C25/C27 -> 29.928404 | D29: =D25/D27 -> 31.283515 | E29: =E25/E27 -> 36.783619 | F29: =F25/F27 -> 40.765121 | G29: =G25/G27 -> 45.816265 | H29: =H25/H27 -> 49.773017 | I29: =I25/I27 -> 54.807447 | ... P29: =P25/P27 -> 58.27437
A30: Diluted EPS (INR) | B30: 19.71516 | C30: 29.928404 | D30: 31.283515 | E30: 36.783619 | F30: 40.765121 | G30: 45.816265 | H30: 49.773017 | I30: 54.807447 | J30: 57.88 | K30: 64.113686 | L30: 64.018773 | M30: =M25/M28 -> 62.284548 | N30: =N25/N28 -> 65.07287 | O30: =O25/O28 -> 61.736342 | P30: =P25/P28 -> 58.158054

Sheet Annual Cash Flow
A1: Annual Cash Flow Statement — Detailed
A2: Indirect cash flow | BO reference taxonomy | forecast working-capital and capex lines linked to balance-sheet and operating assumptions
A4: Metric | B4: FY16A | C4: FY17A | D4: FY18A | E4: FY19A | F4: FY20A | G4: FY21A | H4: FY22A | I4: FY23A | J4: FY24A | K4: FY25A | L4: FY26A | M4: FY27E | N4: FY28E | O4: FY29E | P4: FY30E
A5: Net profit | B5: 5569.0979 | C5: 8457 | D5: 8782 | E5: 10123 | F5: 11062 | G5: 12433 | H5: 13500 | I5: 14851 | J5: 15702 | K5: 17391 | L5: 17361 | M5: ='Annual P&L'!M25 -> 16924.484 | N5: ='Annual P&L'!N25 -> 17682.15 | O5: ='Annual P&L'!O25 -> 16775.521 | P5: ='Annual P&L'!P25 -> 15803.198
A6: D&A | B6: 445.37462 | C6: 834 | D6: 1452 | E6: 2148 | F6: 2840 | G6: 3985 | H6: 4181 | I6: 4144 | J6: 4173 | K6: 4084 | L6: 4355 | M6: ='Annual P&L'!M16 -> 4752.8116 | N6: ='Annual P&L'!N16 -> 4956.4861 | O6: ='Annual P&L'!O16 -> 5201.4291 | P6: ='Annual P&L'!P16 -> 5477.0179
A7: Stock compensation & other non-cash operating items | B7: -823.5002 | C7: -934 | D7: -1111 | E7: -805 | F7: -179 | G7: -657 | H7: -777 | I7: -1003 | J7: -940 | K7: -1841 | L7: -661 | M7: =0 -> 0 | N7: =0 -> 0 | O7: =0 -> 0 | P7: =0 -> 0
A8: Change in trade receivables | B8: 0 | C8: 0 | D8: 0 | E8: 0 | F8: 0 | G8: 0 | H8: 0 | I8: 0 | J8: 0 | K8: 0 | L8: 0 | M8: =-('Annual Balance Sheet'!M6-'Annual Balance Sheet'!L6) -> 8633.7164 | N8: =-('Annual Balance Sheet'!N6-'Annual Balance Sheet'!M6) -> -1307.3435 | O8: =-('Annual Balance Sheet'!O6-'Annual Balance Sheet'!N6) -> -1572.2366 | P8: =-('Annual Balance Sheet'!P6-'Annual Balance Sheet'!O6) -> -1768.9461
A9: Change in other current assets | B9: =IFERROR(B8/B5,0) -> 0 | C9: =IFERROR(C8/C5,0) -> 0 | D9: =IFERROR(D8/D5,0) -> 0 | E9: =IFERROR(E8/E5,0) -> 0 | F9: =IFERROR(F8/F5,0) -> 0 | G9: =IFERROR(G8/G5,0) -> 0 | H9: =IFERROR(H8/H5,0) -> 0 | I9: =IFERROR(I8/I5,0) -> 0 | ... L9: =IFERROR(L8/L5,0) -> 0 | M9: =-('Annual Balance Sheet'!M7-'Annual Balance Sheet'!L7) -> 51530.754 | N9: =-('Annual Balance Sheet'!N7-'Annual Balance Sheet'!M7) -> -814.69821 | O9: =-('Annual Balance Sheet'!O7-'Annual Balance Sheet'!N7) -> -979.7718 | P9: =-('Annual Balance Sheet'!P7-'Annual Balance Sheet'!O7) -> -1102.3555
A10: Change in current liabilities | B10: 0 | C10: 0 | D10: 0 | E10: 0 | F10: 0 | G10: 0 | H10: 0 | I10: 0 | J10: 0 | K10: 0 | L10: 0 | M10: ='Annual Balance Sheet'!M13-'Annual Balance Sheet'!L13 -> -5384.9691 | N10: ='Annual Balance Sheet'!N13-'Annual Balance Sheet'!M13 -> 1047.4691 | O10: ='Annual Balance Sheet'!O13-'Annual Balance Sheet'!N13 -> 1259.7066 | P10: ='Annual Balance Sheet'!P13-'Annual Balance Sheet'!O13 -> 1417.3142
A11: Other operating balance movements | B11: -1033 | C11: 986.5 | D11: -2224.9 | E11: -2315 | F11: 5016 | G11: -3645 | H11: -2337 | I11: -2301 | J11: 634 | K11: 1911 | L11: -1413 | M11: =('Annual Balance Sheet'!M15-'Annual Balance Sheet'!L15)-('Annual Balance Sheet'!M11-'Annual Balance Sheet'!L11) -> -92.43731 | N11: =('Annual Balance Sheet'!N15-'Annual Balance Sheet'!M15)-('Annual Balance Sheet'!N11-'Annual Balance Sheet'!M11) -> -95.196337 | O11: =('Annual Balance Sheet'!O15-'Annual Balance Sheet'!N15)-('Annual Balance Sheet'!O11-'Annual Balance Sheet'!N11) -> -114.48495 | P11: =('Annual Balance Sheet'!P15-'Annual Balance Sheet'!O15)-('Annual Balance Sheet'!P11-'Annual Balance Sheet'!O11) -> -128.80868
A12: Cash flow from operations | B12: =SUM(B5:B11) -> 4157.9723 | C12: =SUM(C5:C11) -> 9343.5 | D12: =SUM(D5:D11) -> 6898.1 | E12: =SUM(E5:E11) -> 9151 | F12: =SUM(F5:F11) -> 18739 | G12: =SUM(G5:G11) -> 12116 | H12: =SUM(H5:H11) -> 14567 | I12: =SUM(I5:I11) -> 15691 | ... P12: =SUM(P5:P11) -> 19697.42
A13: CFO / net profit | B13: =IFERROR(B12/B5,0) -> 0.74661505 | C13: =IFERROR(C12/C5,0) -> 1.1048244 | D13: =IFERROR(D12/D5,0) -> 0.78548167 | E13: =IFERROR(E12/E5,0) -> 0.90398103 | F13: =IFERROR(F12/F5,0) -> 1.6939975 | G13: =IFERROR(G12/G5,0) -> 0.97450334 | H13: =IFERROR(H12/H5,0) -> 1.079037 | I13: =IFERROR(I12/I5,0) -> 1.0565618 | ... P13: =IFERROR(P12/P5,0) -> 1.2464199
A15: Maintenance capex | B15: -2164.2746 | C15: -6197.7 | D15: -4936.2 | E15: -6053.6 | F15: -17633 | G15: -3483 | H15: -1600 | I15: -3597 | J15: -4685 | K15: -5144 | L15: -5563 | M15: =-'Annual P&L'!M5*Assumptions!M40 -> -2444.3031 | N15: =-'Annual P&L'!N5*Assumptions!N40 -> -2549.05 | O15: =-'Annual P&L'!O5*Assumptions!O40 -> -2675.0207 | P15: =-'Annual P&L'!P5*Assumptions!P40 -> -2816.7521
A16: Data centre & AI infrastructure capex | B16: 0 | C16: 0 | D16: 0 | E16: 0 | F16: 0 | G16: 0 | H16: 0 | I16: 0 | J16: 0 | K16: 0 | L16: 0 | M16: =-'Annual P&L'!M5*Assumptions!M41 -> -1357.9462 | N16: =-'Annual P&L'!N5*Assumptions!N41 -> -1416.1389 | O16: =-'Annual P&L'!O5*Assumptions!O41 -> -1486.1226 | P16: =-'Annual P&L'!P5*Assumptions!P41 -> -1564.8623
A17: Other growth capex | B17: 0 | C17: 0 | D17: 0 | E17: 0 | F17: 0 | G17: 0 | H17: 0 | I17: 0 | J17: 0 | K17: 0 | L17: 0 | M17: =-'Annual P&L'!M5*Assumptions!M42 -> -950.56231 | N17: =-'Annual P&L'!N5*Assumptions!N42 -> -991.29722 | O17: =-'Annual P&L'!O5*Assumptions!O42 -> -1040.2858 | P17: =-'Annual P&L'!P5*Assumptions!P42 -> -1095.4036
A18: Total capex | B18: =SUM(B15:B17) -> -2164.2746 | C18: =SUM(C15:C17) -> -6197.7 | D18: =SUM(D15:D17) -> -4936.2 | E18: =SUM(E15:E17) -> -6053.6 | F18: =SUM(F15:F17) -> -17633 | G18: =SUM(G15:G17) -> -3483 | H18: =SUM(H15:H17) -> -1600 | I18: =SUM(I15:I17) -> -3597 | ... P18: =SUM(P15:P17) -> -5477.0179
A19: Acquisitions / investments / divestitures | B19: -960.3 | C19: =B20 -> -3124.5746 | D19: =C20 -> -9322.2746 | E19: =D20 -> -14258.475 | F19: =E20 -> -20312.075 | G19: =F20 -> -37945.075 | H19: =G20 -> -41428.075 | I19: =H20 -> -43028.075 | J19: =I20 -> -46625.075 | ... P19: =O20 -> -76927.801
A20: Cash flow from investing | B20: =SUM(B18:B19) -> -3124.5746 | C20: =SUM(C18:C19) -> -9322.2746 | D20: =SUM(D18:D19) -> -14258.475 | E20: =SUM(E18:E19) -> -20312.075 | F20: =SUM(F18:F19) -> -37945.075 | G20: =SUM(G18:G19) -> -41428.075 | H20: =SUM(H18:H19) -> -43028.075 | I20: =SUM(I18:I19) -> -46625.075 | ... P20: =SUM(P18:P19) -> -82404.819
B21: =B8+B10 -> 0 | C21: =C8+C10 -> 0 | D21: =D8+D10 -> 0 | E21: =E8+E10 -> 0 | F21: =F8+F10 -> 0 | G21: =G8+G10 -> 0 | H21: =H8+H10 -> 0 | I21: =I8+I10 -> 0 | ... P21: =P8+P10 -> -351.63198
A22: Debt issuance / (repayment) | B22: 504.6 | C22: -431.5 | D22: -104.6 | E22: 3548.9 | F22: 3578 | G22: -1390 | H22: 169 | I22: -1557 | J22: 970 | K22: 520 | L22: -1061 | M22: =0 -> 0 | N22: =0 -> 0 | O22: =0 -> 0 | P22: =0 -> 0
A23: Equity issuance / (buybacks) & other | B23: 585.79861 | C23: 1092.3822 | D23: -4105.2942 | E23: -3390.9151 | F23: 890.11498 | G23: 4498.5292 | H23: -1652.5528 | I23: 1534.0816 | J23: 1253.5112 | K23: 273.46919 | L23: 4415.9499 | M23: =0 -> 0 | N23: =0 -> 0 | O23: =0 -> 0 | P23: =0 -> 0
A24: Dividends | B24: -2883.3965 | C24: -4081.0822 | D24: -1350.3058 | E24: -1324.8849 | F24: -1961.115 | G24: -7055.5292 | H24: -11932.447 | I24: -12993.082 | J24: -14082.511 | K24: -16262.469 | L24: -16252.95 | M24: =-M5*Assumptions!M22 -> -7616.0178 | N24: =-N5*Assumptions!N22 -> -7956.9676 | O24: =-O5*Assumptions!O22 -> -7548.9842 | P24: =-P5*Assumptions!P22 -> -7111.4391
A25: Other financing cash flows | B25: 823.5002 | C25: 934 | D25: 1111 | E25: 805 | F25: 179 | G25: 657 | H25: 777 | I25: 1003 | J25: 940 | K25: 1841 | L25: 661 | M25: =0 -> 0 | N25: =0 -> 0 | O25: =0 -> 0 | P25: =0 -> 0
A26: Cash flow from financing | B26: =SUM(B22:B25) -> -969.49772 | C26: =SUM(C22:C25) -> -2486.2 | D26: =SUM(D22:D25) -> -4449.2 | E26: =SUM(E22:E25) -> -361.9 | F26: =SUM(F22:F25) -> 2686 | G26: =SUM(G22:G25) -> -3290 | H26: =SUM(H22:H25) -> -12639 | I26: =SUM(I22:I25) -> -12013 | ... P26: =SUM(P22:P25) -> -7111.4391
A27: FX / translation | B27: 0 | C27: 0 | D27: 0 | E27: 0 | F27: 0 | G27: 0 | H27: 0 | I27: 0 | J27: 0 | K27: 0 | L27: 0 | M27: =0 -> 0 | N27: =0 -> 0 | O27: =0 -> 0 | P27: =0 -> 0
A28: Net change in cash | B28: =SUM(B12,B20,B26,B27) -> 63.9 | C28: =SUM(C12,C20,C26,C27) -> -2464.9746 | D28: =SUM(D12,D20,D26,D27) -> -11809.575 | E28: =SUM(E12,E20,E26,E27) -> -11522.975 | F28: =SUM(F12,F20,F26,F27) -> -16520.075 | G28: =SUM(G12,G20,G26,G27) -> -32602.075 | H28: =SUM(H12,H20,H26,H27) -> -41100.075 | I28: =SUM(I12,I20,I26,I27) -> -42947.075 | ... P28: =SUM(P12,P20,P26,P27) -> -69818.839
A29: Opening cash | B29: =B30-B28 -> 11788.8 | C29: =B30 -> 11852.7 | D29: =C30 -> 12681.8 | E29: =D30 -> 10273.1 | F29: =E30 -> 11746 | G29: =F30 -> 15373 | H29: =G30 -> 20490 | I29: =H30 -> 21883 | J29: =I30 -> 22712 | ... P29: =O30 -> -88741.64
A30: Closing cash | B30: ='Annual Balance Sheet'!B5 -> 11852.7 | C30: ='Annual Balance Sheet'!C5 -> 12681.8 | D30: ='Annual Balance Sheet'!D5 -> 10273.1 | E30: ='Annual Balance Sheet'!E5 -> 11746 | F30: ='Annual Balance Sheet'!F5 -> 15373 | G30: ='Annual Balance Sheet'!G5 -> 20490 | H30: ='Annual Balance Sheet'!H5 -> 21883 | I30: ='Annual Balance Sheet'!I5 -> 22712 | ... L30: ='Annual Balance Sheet'!L5 -> 31401 | M30: =SUM(M28:M29) -> 33379.455 | N30: =SUM(N28:N29) -> -24835.017 | O30: =SUM(O28:O29) -> -88741.64 | P30: =SUM(P28:P29) -> -158560.48
A31: Cash tie check | B31: =B30-'Annual Balance Sheet'!B5 -> 0 | C31: =C30-'Annual Balance Sheet'!C5 -> 0 | D31: =D30-'Annual Balance Sheet'!D5 -> 0 | E31: =E30-'Annual Balance Sheet'!E5 -> 0 | F31: =F30-'Annual Balance Sheet'!F5 -> 0 | G31: =G30-'Annual Balance Sheet'!G5 -> 0 | H31: =H30-'Annual Balance Sheet'!H5 -> 0 | I31: =I30-'Annual Balance Sheet'!I5 -> 0 | ... P31: =P30-'Annual Balance Sheet'!P5 -> 0
A32: Free cash flow | B32: =SUM(B12,B18) -> 1993.6977 | C32: =SUM(C12,C18) -> 3145.8 | D32: =SUM(D12,D18) -> 1961.9 | E32: =SUM(E12,E18) -> 3097.4 | F32: =SUM(F12,F18) -> 1106 | G32: =SUM(G12,G18) -> 8633 | H32: =SUM(H12,H18) -> 12967 | I32: =SUM(I12,I18) -> 12094 | ... P32: =SUM(P12,P18) -> 14220.402
A33: FCF margin | B33: =IFERROR(B32/'Annual P&L'!B5,0) -> 0.064031916 | C33: =IFERROR(C32/'Annual P&L'!C5,0) -> 0.067330166 | D33: =IFERROR(D32/'Annual P&L'!D5,0) -> 0.038795729 | E33: =IFERROR(E32/'Annual P&L'!E5,0) -> 0.051257695 | F33: =IFERROR(F32/'Annual P&L'!F5,0) -> 0.015648434 | G33: =IFERROR(G32/'Annual P&L'!G5,0) -> 0.11452792 | H33: =IFERROR(H32/'Annual P&L'!H5,0) -> 0.15139345 | I33: =IFERROR(I32/'Annual P&L'!I5,0) -> 0.11920438 | ... P33: =IFERROR(P32/'Annual P&L'!P5,0) -> 0.090873185
A34: Cash conversion (CFO / EBITDA) | B34: =IFERROR(B12/'Annual P&L'!B14,0) -> 0.62111174 | C34: =IFERROR(C12/'Annual P&L'!C14,0) -> 0.90634397 | D34: =IFERROR(D12/'Annual P&L'!D14,0) -> 0.60298077 | E34: =IFERROR(E12/'Annual P&L'!E14,0) -> 0.65509342 | F34: =IFERROR(F12/'Annual P&L'!F14,0) -> 1.1225663 | G34: =IFERROR(G12/'Annual P&L'!G14,0) -> 0.62193933 | H34: =IFERROR(H12/'Annual P&L'!H14,0) -> 0.71480446 | I34: =IFERROR(I12/'Annual P&L'!I14,0) -> 0.69340227 | ... P34: =IFERROR(P12/'Annual P&L'!P14,0) -> 0.64550351
A35: Capex / revenue | B35: =IFERROR(-B18/'Annual P&L'!B5,0) -> 0.069510362 | C35: =IFERROR(-C18/'Annual P&L'!C5,0) -> 0.13265057 | D35: =IFERROR(-D18/'Annual P&L'!D5,0) -> 0.097611232 | E35: =IFERROR(-E18/'Annual P&L'!E5,0) -> 0.10017873 | F35: =IFERROR(-F18/'Annual P&L'!F5,0) -> 0.24948357 | G35: =IFERROR(-G18/'Annual P&L'!G5,0) -> 0.046206503 | H35: =IFERROR(-H18/'Annual P&L'!H5,0) -> 0.018680459 | I35: =IFERROR(-I18/'Annual P&L'!I5,0) -> 0.035453793 | ... P35: =IFERROR(-P18/'Annual P&L'!P5,0) -> 0.035

Sheet Revenue Drivers
A1: Annual Revenue Drivers — Headcount, T&M and AI Deflation
A2: Annual workforce bridge to revenue
A4: Driver | B4: FY16A | C4: FY17A | D4: FY18A | E4: FY19A | F4: FY20A | G4: FY21A | H4: FY22A | I4: FY23A | J4: FY24A | K4: FY25A | L4: FY26A | M4: FY27E | N4: FY28E | O4: FY29E | P4: FY30E
A5: Revenue | B5: 31136 | C5: 47568 | D5: 50569 | E5: 60427 | F5: 70676 | G5: 75379 | H5: 85651 | I5: 101456 | J5: 109913 | K5: 117055 | L5: 130144 | M5: =M38 -> 135794.62 | N5: =N38 -> 141613.89 | O5: =O38 -> 148612.26 | P5: =P38 -> 156486.23
A6: Growth | C6: =C5/B5-1 -> 0.52774923 | D6: =D5/C5-1 -> 0.063088631 | E6: =E5/D5-1 -> 0.19494156 | F6: =F5/E5-1 -> 0.16960961 | G6: =G5/F5-1 -> 0.066543098 | H6: =H5/G5-1 -> 0.13627138 | I6: =I5/H5-1 -> 0.18452791 | J6: =J5/I5-1 -> 0.083356332 | ... P6: =P5/O5-1 -> 0.052983298
A7: Closing headcount | B7: 106107 | C7: 117781 | D7: 120081 | E7: 137965 | F7: 150423 | G7: 168977 | H7: 208877 | I7: 225944 | J7: 219401 | K7: 223420 | L7: 226640 | M7: =L7*(1+Assumptions!M5-Assumptions!M6) -> 234572.4 | N7: =M7*(1+Assumptions!N5-Assumptions!N6) -> 242782.43 | O7: =N7*(1+Assumptions!O5-Assumptions!O6) -> 251279.82 | P7: =O7*(1+Assumptions!P5-Assumptions!P6) -> 260074.61
A8: Headcount growth | C8: =C7/B7-1 -> 0.11002102 | D8: =D7/C7-1 -> 0.019527768 | E8: =E7/D7-1 -> 0.1489328 | F8: =F7/E7-1 -> 0.090298264 | G8: =G7/F7-1 -> 0.1233455 | H8: =H7/G7-1 -> 0.23612681 | I8: =I7/H7-1 -> 0.081708374 | J8: =J7/I7-1 -> -0.028958503 | ... P8: =P7/O7-1 -> 0.035
A9: Billable employees | B9: =B7*B10 -> 82763.46 | C9: =C7*C10 -> 91869.18 | D9: =D7*D10 -> 94863.99 | E9: =E7*E10 -> 108992.35 | F9: =F7*F10 -> 120338.4 | G9: =G7*G10 -> 135181.6 | H9: =H7*H10 -> 169190.37 | I9: =I7*I10 -> 183014.64 | ... P9: =P7*P10 -> 213261.18
A10: Billable % | B10: 0.78 | C10: 0.78 | D10: 0.79 | E10: 0.79 | F10: 0.8 | G10: 0.8 | H10: 0.81 | I10: 0.81 | J10: 0.82 | K10: 0.82 | L10: 0.82 | M10: =Assumptions!M7 -> 0.825 | N10: =Assumptions!N7 -> 0.82 | O10: =Assumptions!O7 -> 0.82 | P10: =Assumptions!P7 -> 0.82
A11: Revenue / billable employee | B11: =B5/B9 -> 0.37620467 | C11: =C5/C9 -> 0.51777974 | D11: =D5/D9 -> 0.53306845 | E11: =E5/E9 -> 0.55441506 | F11: =F5/F9 -> 0.58731045 | G11: =G5/G9 -> 0.55761287 | H11: =H5/H9 -> 0.5062404 | I11: =I5/I9 -> 0.55436002 | ... P11: =P5/P9 -> 0.73377735
A12: Gross hiring / opening HC | M12: =Assumptions!M5 -> 0.16 | N12: =Assumptions!N5 -> 0.16 | O12: =Assumptions!O5 -> 0.16 | P12: =Assumptions!P5 -> 0.16
A13: Attrition | B13: 0.16 | C13: 0.15 | D13: 0.16 | E13: 0.17 | F13: 0.1 | G13: 0.1 | H13: 0.21 | I13: 0.19 | J13: 0.13 | K13: 0.13 | L13: 0.125 | M13: =Assumptions!M6 -> 0.125 | N13: =Assumptions!N6 -> 0.125 | O13: =Assumptions!O6 -> 0.125 | P13: =Assumptions!P6 -> 0.125
A14: Nominal pricing / productivity | M14: =Assumptions!M8 -> 0.025 | N14: =Assumptions!N8 -> 0.025 | O14: =Assumptions!O8 -> 0.025 | P14: =Assumptions!P8 -> 0.025
A15: T&M mix | M15: =Assumptions!M9 -> 0.6145 | N15: =Assumptions!N9 -> 0.602 | O15: =Assumptions!O9 -> 0.602 | P15: =Assumptions!P9 -> 0.602
A16: AI deflation on T&M | M16: =Assumptions!M10 -> 0.03 | N16: =Assumptions!N10 -> 0.035 | O16: =Assumptions!O10 -> 0.035 | P16: =Assumptions!P10 -> 0.035
A17: Fixed-price productivity uplift | M17: =Assumptions!M11 -> 0.045 | N17: =Assumptions!N11 -> 0.0525 | O17: =Assumptions!O11 -> 0.0525 | P17: =Assumptions!P11 -> 0.0525
A18: Gross productivity factor | M18: =(1+M14)*(1-M15*M16)*(1+(1-M15)*M17) -> 1.0235575 | N18: =(1+N14)*(1-N15*N16)*(1+(1-N15)*N17) -> 1.0243694 | O18: =(1+O14)*(1-O15*O16)*(1+(1-O15)*O17) -> 1.0243694 | P18: =(1+P14)*(1-P15*P16)*(1+(1-P15)*P17) -> 1.0243694
A19: Modelled revenue | M19: =M38 -> 135794.62 | N19: =N38 -> 141613.89 | O19: =O38 -> 148612.26 | P19: =P38 -> 156486.23
A20: Revenue bridge check | B20: =0 -> 0 | C20: =0 -> 0 | D20: =0 -> 0 | E20: =0 -> 0 | F20: =0 -> 0 | G20: =0 -> 0 | H20: =0 -> 0 | I20: =0 -> 0 | ... L20: =0 -> 0 | M20: =M5-M19 -> 0 | N20: =N5-N19 -> 0 | O20: =O5-O19 -> 0 | P20: =P5-P19 -> 0
A24: Advanced AI revenue and deflation bridge
A25: Company revenue ($m) | B25: 4697.819 | C25: 6975.2 | D25: 7838.2 | E25: 8632.4 | F25: 9936 | G25: 10175 | H25: 11480.9 | I25: 12585.6 | J25: 13269.6 | K25: 13840.2 | L25: 14664 | M25: =L25*('Annual P&L'!M5/'Annual P&L'!L5) -> 15300.684 | N25: =M25*('Annual P&L'!N5/'Annual P&L'!M5) -> 15956.372 | O25: =N25*('Annual P&L'!O5/'Annual P&L'!N5) -> 16744.915 | P25: =O25*('Annual P&L'!P5/'Annual P&L'!O5) -> 17632.115
A26: Annualized Advanced AI revenue ($m) | L26: 620 | M26: 684 | N26: =M26*(1+Assumptions!N37) -> 858.42 | O26: =N26*(1+Assumptions!O37) -> 1085.4721 | P26: =O26*(1+Assumptions!P37) -> 1383.4342
A27: Advanced AI revenue growth | B27: =0 -> 0 | C27: =IFERROR(C26/B26-1,0) -> 0 | D27: =IFERROR(D26/C26-1,0) -> 0 | E27: =IFERROR(E26/D26-1,0) -> 0 | F27: =IFERROR(F26/E26-1,0) -> 0 | G27: =IFERROR(G26/F26-1,0) -> 0 | H27: =IFERROR(H26/G26-1,0) -> 0 | I27: =IFERROR(I26/H26-1,0) -> 0 | J27: =IFERROR(J26/I26-1,0) -> 0 | ... P27: =IFERROR(P26/O26-1,0) -> 0.2745
A28: Advanced AI mix of company revenue | B28: =IFERROR(B26/B25,0) -> 0 | C28: =IFERROR(C26/C25,0) -> 0 | D28: =IFERROR(D26/D25,0) -> 0 | E28: =IFERROR(E26/E25,0) -> 0 | F28: =IFERROR(F26/F25,0) -> 0 | G28: =IFERROR(G26/G25,0) -> 0 | H28: =IFERROR(H26/H25,0) -> 0 | I28: =IFERROR(I26/I25,0) -> 0 | ... P28: =IFERROR(P26/P25,0) -> 0.078461044
A29: Implied quarterly Advanced AI revenue ($m) | B29: =B26/4 -> 0 | C29: =C26/4 -> 0 | D29: =D26/4 -> 0 | E29: =E26/4 -> 0 | F29: =F26/4 -> 0 | G29: =G26/4 -> 0 | H29: =H26/4 -> 0 | I29: =I26/4 -> 0 | ... P29: =P26/4 -> 345.85854
A30: Incremental Advanced AI revenue ($m) | B30: =0 -> 0 | C30: =MAX(0,C26-B26) -> 0 | D30: =MAX(0,D26-C26) -> 0 | E30: =MAX(0,E26-D26) -> 0 | F30: =MAX(0,F26-E26) -> 0 | G30: =MAX(0,G26-F26) -> 0 | H30: =MAX(0,H26-G26) -> 0 | I30: =MAX(0,I26-H26) -> 0 | J30: =MAX(0,J26-I26) -> 0 | ... P30: =MAX(0,P26-O26) -> 297.96209
A31: AI-led T&M deflation ($m) | B31: =-(B25-B26)*Assumptions!B14*Assumptions!B13 -> 0 | C31: =-(C25-C26)*Assumptions!C14*Assumptions!C13 -> 0 | D31: =-(D25-D26)*Assumptions!D14*Assumptions!D13 -> 0 | E31: =-(E25-E26)*Assumptions!E14*Assumptions!E13 -> 0 | F31: =-(F25-F26)*Assumptions!F14*Assumptions!F13 -> 0 | G31: =-(G25-G26)*Assumptions!G14*Assumptions!G13 -> 0 | H31: =-(H25-H26)*Assumptions!H14*Assumptions!H13 -> 0 | I31: =-(I25-I26)*Assumptions!I14*Assumptions!I13 -> 0 | ... P31: =-(P25-P26)*Assumptions!P14*Assumptions!P13 -> -82.868274
A32: Net Advanced AI growth offset ($m) | B32: =B30+B31 -> 0 | C32: =C30+C31 -> 0 | D32: =D30+D31 -> 0 | E32: =E30+E31 -> 0 | F32: =F30+F31 -> 0 | G32: =G30+G31 -> 0 | H32: =H30+H31 -> 0 | I32: =I30+I31 -> 0 | ... P32: =P30+P31 -> 215.09381
A34: Forecast Revenue Build — Base Services + Incremental Advanced AI
A35: Billable / T&M revenue after AI deflation | M35: =$L$5*M15*(M9/L9)*(1+M14)*(1-M16) -> 82798.427 | N35: =M38*N15*(N9/M9)*(1+N14)*(1-N16) -> 83182.214 | O35: =N38*O15*(O9/N9)*(1+O14)*(1-O16) -> 87275.806 | P35: =O38*P15*(P9/O9)*(1+P14)*(1-P16) -> 91588.86
A36: Non-T&M, fixed-price & software revenue | M36: =$L$5*(1-M15)*(1+M17) -> 52428.185 | N36: =M38*(1-N15)*(1+N17) -> 56883.686 | O36: =N38*(1-O15)*(1+O17) -> 59321.35 | P36: =O38*(1-P15)*(1+P17) -> 62252.932
A37: Incremental Advanced AI revenue uplift | M37: =M30*($L$5/$L$25) -> 568.00436 | N37: =N30*($L$5/$L$25) -> 1547.9894 | O37: =O30*($L$5/$L$25) -> 2015.1028 | P37: =P30*($L$5/$L$25) -> 2644.4339
A38: Total modelled revenue | M38: =SUM(M35:M37) -> 135794.62 | N38: =SUM(N35:N37) -> 141613.89 | O38: =SUM(O35:O37) -> 148612.26 | P38: =SUM(P35:P37) -> 156486.23
A39: Modelled revenue growth | M39: =IFERROR(M38/$L$5-1,0) -> 0.043418182 | N39: =IFERROR(N38/M38-1,0) -> 0.042853488 | O39: =IFERROR(O38/N38-1,0) -> 0.04941867 | P39: =IFERROR(P38/O38-1,0) -> 0.052983298
A40: Revenue tie check | M40: =M5-M38 -> 0 | N40: =N5-N38 -> 0 | O40: =O5-O38 -> 0 | P40: =P5-P38 -> 0

Sheet Segment Revenue
A1: Segment Revenue — Geography and Vertical
A2: Mix assumptions and calculated INR crore revenue
A4: Metric | B4: FY16A | C4: FY17A | D4: FY18A | E4: FY19A | F4: FY20A | G4: FY21A | H4: FY22A | I4: FY23A | J4: FY24A | K4: FY25A | L4: FY26A | M4: FY27E | N4: FY28E | O4: FY29E | P4: FY30E
A5: Total revenue | B5: ='Annual P&L'!B5 -> 31136 | C5: ='Annual P&L'!C5 -> 46722 | D5: ='Annual P&L'!D5 -> 50570 | E5: ='Annual P&L'!E5 -> 60428 | F5: ='Annual P&L'!F5 -> 70678 | G5: ='Annual P&L'!G5 -> 75379 | H5: ='Annual P&L'!H5 -> 85651 | I5: ='Annual P&L'!I5 -> 101456 | ... P5: ='Annual P&L'!P5 -> 156486.23
A6: Geography mix
A7: Americas % | B7: 0.63 | C7: 0.627 | D7: 0.624 | E7: 0.621 | F7: 0.618 | G7: 0.615 | H7: 0.612 | I7: 0.609 | J7: 0.606 | K7: 0.603 | L7: 0.563 | M7: =L7 -> 0.563 | N7: =M7 -> 0.563 | O7: =N7 -> 0.563 | P7: =O7 -> 0.563
A8: Americas revenue | B8: =B$5*B7 -> 19615.68 | C8: =C$5*C7 -> 29294.694 | D8: =D$5*D7 -> 31555.68 | E8: =E$5*E7 -> 37525.788 | F8: =F$5*F7 -> 43679.004 | G8: =G$5*G7 -> 46358.085 | H8: =H$5*H7 -> 52418.412 | I8: =I$5*I7 -> 61786.704 | ... P8: =P$5*P7 -> 88101.745
A9: Europe % | B9: 0.26 | C9: 0.263 | D9: 0.266 | E9: 0.269 | F9: 0.272 | G9: 0.275 | H9: 0.278 | I9: 0.281 | J9: 0.284 | K9: 0.287 | L9: 0.271 | M9: =L9 -> 0.271 | N9: =M9 -> 0.271 | O9: =N9 -> 0.271 | P9: =O9 -> 0.271
A10: Europe revenue | B10: =B$5*B9 -> 8095.36 | C10: =C$5*C9 -> 12287.886 | D10: =D$5*D9 -> 13451.62 | E10: =E$5*E9 -> 16255.132 | F10: =F$5*F9 -> 19224.416 | G10: =G$5*G9 -> 20729.225 | H10: =H$5*H9 -> 23810.978 | I10: =I$5*I9 -> 28509.136 | ... P10: =P$5*P9 -> 42407.767
A11: India % | B11: 0.035 | C11: 0.035 | D11: 0.035 | E11: 0.035 | F11: 0.035 | G11: 0.035 | H11: 0.035 | I11: 0.035 | J11: 0.035 | K11: 0.035 | L11: 0.029 | M11: =L11 -> 0.029 | N11: =M11 -> 0.029 | O11: =N11 -> 0.029 | P11: =O11 -> 0.029
A12: India revenue | B12: =B$5*B11 -> 1089.76 | C12: =C$5*C11 -> 1635.27 | D12: =D$5*D11 -> 1769.95 | E12: =E$5*E11 -> 2114.98 | F12: =F$5*F11 -> 2473.73 | G12: =G$5*G11 -> 2638.265 | H12: =H$5*H11 -> 2997.785 | I12: =I$5*I11 -> 3550.96 | ... P12: =P$5*P11 -> 4538.1006
A13: Rest of world % | B13: 0.075 | C13: 0.075 | D13: 0.075 | E13: 0.075 | F13: 0.075 | G13: 0.075 | H13: 0.075 | I13: 0.075 | J13: 0.075 | K13: 0.075 | L13: 0.137 | M13: =L13 -> 0.137 | N13: =M13 -> 0.137 | O13: =N13 -> 0.137 | P13: =O13 -> 0.137
A14: Rest of world revenue | B14: =B$5*B13 -> 2335.2 | C14: =C$5*C13 -> 3504.15 | D14: =D$5*D13 -> 3792.75 | E14: =E$5*E13 -> 4532.1 | F14: =F$5*F13 -> 5300.85 | G14: =G$5*G13 -> 5653.425 | H14: =H$5*H13 -> 6423.825 | I14: =I$5*I13 -> 7609.2 | ... P14: =P$5*P13 -> 21438.613
A15: Geography check | B15: =SUM(B7,B9,B11,B13)-100% -> 0 | C15: =SUM(C7,C9,C11,C13)-100% -> 0 | D15: =SUM(D7,D9,D11,D13)-100% -> 0 | E15: =SUM(E7,E9,E11,E13)-100% -> 0 | F15: =SUM(F7,F9,F11,F13)-100% -> 0 | G15: =SUM(G7,G9,G11,G13)-100% -> 0 | H15: =SUM(H7,H9,H11,H13)-100% -> 0 | I15: =SUM(I7,I9,I11,I13)-100% -> 0 | ... P15: =SUM(P7,P9,P11,P13)-100% -> 0
A16: Vertical mix
A17: Financial services %
A18: Financial services revenue | B18: 0.8116895 | C18: 0.81320809 | D18: 0.7701619 | E18: 0.74640537 | F18: 0.71815785 | G18: 0.70849686 | H18: 0.72079064 | I18: 0.7296939 | J18: 0.7382609 | K18: 0.73838679 | L18: 0.75 | M18: =100%-M20-M22 -> 0.747 | N18: =100%-N20-N22 -> 0.747 | O18: =100%-O20-O22 -> 0.747 | P18: =100%-P20-P22 -> 0.747
A19: Manufacturing % | B19: =B$5*B18 -> 25272.764 | C19: =C$5*C18 -> 37994.709 | D19: =D$5*D18 -> 38947.087 | E19: =E$5*E18 -> 45103.784 | F19: =F$5*F18 -> 50757.961 | G19: =G$5*G18 -> 53405.784 | H19: =H$5*H18 -> 61736.439 | I19: =I$5*I18 -> 74031.825 | ... P19: =P$5*P18 -> 116895.21
A20: Manufacturing revenue | B20: 0.1883105 | C20: 0.18679191 | D20: 0.2298381 | E20: 0.1711291 | F20: 0.16695217 | G20: 0.15559046 | H20: 0.15839608 | I20: 0.16569452 | J20: 0.15984098 | K20: 0.16203942 | L20: 0.17 | M20: =L20+Assumptions!M28 -> 0.17 | N20: =M20+Assumptions!N28 -> 0.17 | O20: =N20+Assumptions!O28 -> 0.17 | P20: =O20+Assumptions!P28 -> 0.17
A21: Technology & services % | B21: =B$5*B20 -> 5863.2357 | C21: =C$5*C20 -> 8727.2914 | D21: =D$5*D20 -> 11622.913 | E21: =E$5*E20 -> 10340.989 | F21: =F$5*F20 -> 11799.846 | G21: =G$5*G20 -> 11728.253 | H21: =H$5*H20 -> 13566.783 | I21: =I$5*I20 -> 16810.704 | ... P21: =P$5*P20 -> 26602.658
A22: Technology & services revenue | B22: 0 | C22: 0 | D22: 0 | E22: 0.082465537 | F22: 0.11488998 | G22: 0.13591269 | H22: 0.12107398 | I22: 0.10938409 | J22: 0.10664077 | K22: 0.10257379 | L22: 0.083 | M22: =L22+Assumptions!M29 -> 0.083 | N22: =M22+Assumptions!N29 -> 0.083 | O22: =N22+Assumptions!O29 -> 0.083 | P22: =O22+Assumptions!P29 -> 0.083
A23: Life sciences & healthcare % | B23: =B$5*B22 -> 0 | C23: =C$5*C22 -> 0 | D23: =D$5*D22 -> 0 | E23: =E$5*E22 -> 4983.2275 | F23: =F$5*F22 -> 8120.1937 | G23: =G$5*G22 -> 10244.963 | H23: =H$5*H22 -> 10370.107 | I23: =I$5*I22 -> 11097.672 | ... P23: =P$5*P22 -> 12988.357
A24: Life sciences & healthcare revenue | B24: 0.13 | C24: 0.13 | D24: 0.13 | E24: 0.13 | F24: 0.13 | G24: 0.13 | H24: 0.13 | I24: 0.13 | J24: 0.13 | K24: 0.13 | L24: 0.13 | M24: =L24 -> 0.13 | N24: =M24 -> 0.13 | O24: =N24 -> 0.13 | P24: =O24 -> 0.13
A25: Telecom, media & entertainment % | B25: =B$5*B24 -> 4047.68 | C25: =C$5*C24 -> 6073.86 | D25: =D$5*D24 -> 6574.1 | E25: =E$5*E24 -> 7855.64 | F25: =F$5*F24 -> 9188.14 | G25: =G$5*G24 -> 9799.27 | H25: =H$5*H24 -> 11134.63 | I25: =I$5*I24 -> 13189.28 | ... P25: =P$5*P24 -> 20343.209
A26: TME revenue | B26: 0.12 | C26: 0.12 | D26: 0.12 | E26: 0.12 | F26: 0.12 | G26: 0.21856961 | H26: 0.21333355 | I26: 0.20693949 | J26: 0.22109902 | K26: 0.20722123 | L26: 0.214 | M26: =L26 -> 0.214 | N26: =M26 -> 0.214 | O26: =N26 -> 0.214 | P26: =O26 -> 0.214
A27: Retail & CPG % | B27: =B$5*B26 -> 3736.32 | C27: =C$5*C26 -> 5606.64 | D27: =D$5*D26 -> 6068.4 | E27: =E$5*E26 -> 7251.36 | F27: =F$5*F26 -> 8481.36 | G27: =G$5*G26 -> 16475.559 | H27: =H$5*H26 -> 18272.231 | I27: =I$5*I26 -> 20995.253 | ... P27: =P$5*P26 -> 33488.052
A28: Retail & CPG revenue | B28: 0.1 | C28: 0.1 | D28: 0.1 | E28: 0.1 | F28: 0.1 | G28: 0.17895463 | H28: 0.17656516 | I28: 0.19061164 | J28: 0.19934902 | K28: 0.19146106 | L28: 0.186 | M28: =L28 -> 0.186 | N28: =M28 -> 0.186 | O28: =N28 -> 0.186 | P28: =O28 -> 0.186
A29: Public services & other % | B29: =B$5*B28 -> 3113.6 | C29: =C$5*C28 -> 4672.2 | D29: =D$5*D28 -> 5057 | E29: =E$5*E28 -> 6042.8 | F29: =F$5*F28 -> 7067.8 | G29: =G$5*G28 -> 13489.421 | H29: =H$5*H28 -> 15122.983 | I29: =I$5*I28 -> 19338.695 | ... P29: =P$5*P28 -> 29106.438
A30: Public services & other revenue | B30: 0.09 | C30: 0.09 | D30: 0.09 | E30: 0.09 | F30: 0.09 | G30: 0.17378935 | H30: 0.17613111 | I30: 0.14914872 | J30: 0.12888357 | K30: 0.13202577 | L30: 0.148 | M30: =L30 -> 0.148 | N30: =M30 -> 0.148 | O30: =N30 -> 0.148 | P30: =O30 -> 0.148
A31: Vertical check | B31: =B$5*B30 -> 2802.24 | C31: =C$5*C30 -> 4204.98 | D31: =D$5*D30 -> 4551.3 | E31: =E$5*E30 -> 5438.52 | F31: =F$5*F30 -> 6361.02 | G31: =G$5*G30 -> 13100.067 | H31: =H$5*H30 -> 15085.806 | I31: =I$5*I30 -> 15132.032 | ... P31: =P$5*P30 -> 23159.962
A32: Retail & CPG mix | B32: =SUM(B18,B20,B22,B24,B26,B28,B30)-100% -> 0.44 | C32: =SUM(C18,C20,C22,C24,C26,C28,C30)-100% -> 0.44 | D32: =SUM(D18,D20,D22,D24,D26,D28,D30)-100% -> 0.44 | E32: =SUM(E18,E20,E22,E24,E26,E28,E30)-100% -> 0.44 | F32: =SUM(F18,F20,F22,F24,F26,F28,F30)-100% -> 0.44 | G32: 0.1025363 | H32: 0.098208982 | I32: 0.091193412 | J32: 0.093501846 | K32: 0.098319374 | L32: 0.097 | M32: =SUM(M18,M20,M22,M24,M26,M28,M30)-100% -> 0.678 | N32: =SUM(N18,N20,N22,N24,N26,N28,N30)-100% -> 0.678 | O32: =SUM(O18,O20,O22,O24,O26,O28,O30)-100% -> 0.678 | P32: =SUM(P18,P20,P22,P24,P26,P28,P30)-100% -> 0.678
A33: Retail & CPG revenue | B33: =B$5*B32 -> 13699.84 | C33: =C$5*C32 -> 20557.68 | D33: =D$5*D32 -> 22250.8 | E33: =E$5*E32 -> 26588.32 | F33: =F$5*F32 -> 31098.32 | G33: =G$5*G32 -> 7729.0841 | H33: =H$5*H32 -> 8411.6975 | I33: =I$5*I32 -> 9252.1188 | ... L33: =L$5*L32 -> 12623.968
A34: Telecom, media & entertainment mix | G34: 0.079371273 | H34: 0.081343605 | I34: 0.091487478 | J34: 0.092457158 | K34: 0.1263032 | L34: 0.121
A35: Telecom, media & entertainment revenue | B35: =B$5*B34 -> 0 | C35: =C$5*C34 -> 0 | D35: =D$5*D34 -> 0 | E35: =E$5*E34 -> 0 | F35: =F$5*F34 -> 0 | G35: =G$5*G34 -> 5982.9272 | H35: =H$5*H34 -> 6967.1612 | I35: =I$5*I34 -> 9281.9535 | ... L35: =L$5*L34 -> 15747.424
A36: Life sciences & healthcare mix | G36: 0.13878821 | H36: 0.14820181 | I36: 0.16887626 | J36: 0.16906736 | K36: 0.15519477 | L36: 0.142
A37: Life sciences & healthcare revenue | B37: =B$5*B36 -> 0 | C37: =C$5*C36 -> 0 | D37: =D$5*D36 -> 0 | E37: =E$5*E36 -> 0 | F37: =F$5*F36 -> 0 | G37: =G$5*G36 -> 10461.716 | H37: =H$5*H36 -> 12693.634 | I37: =I$5*I36 -> 17133.51 | ... L37: =L$5*L36 -> 18480.448
A38: Public services mix | G38: 0.10824778 | H38: 0.10621578 | I38: 0.102 | J38: 0.095883184 | K38: 0.089474603 | L38: 0.092
A39: Public services revenue | B39: =B$5*B38 -> 0 | C39: =C$5*C38 -> 0 | D39: =D$5*D38 -> 0 | E39: =E$5*E38 -> 0 | F39: =F$5*F38 -> 0 | G39: =G$5*G38 -> 8159.6097 | H39: =H$5*H38 -> 9097.4874 | I39: =I$5*I38 -> 10348.512 | ... L39: =L$5*L38 -> 11973.248
A41: Service-line revenue — reported history and modelled allocation
A42: Application services / ITBS mix | B42: 0.49564606 | C42: 0.46247012 | D42: 0.46150909 | E42: 0.43804734 | F42: =E42 -> 0.43804734 | G42: =F42 -> 0.43804734 | H42: =G42 -> 0.43804734 | I42: =H42 -> 0.43804734 | J42: =I42 -> 0.43804734 | K42: =J42 -> 0.43804734 | L42: =K42 -> 0.43804734 | M42: =L42+Assumptions!M25 -> 0.43804734 | N42: =M42+Assumptions!N25 -> 0.43804734 | O42: =N42+Assumptions!O25 -> 0.43804734 | P42: =O42+Assumptions!P25 -> 0.43804734
A43: Application services revenue | B43: =B$19*B42 -> 12526.346 | C43: =C$19*C42 -> 17571.418 | D43: =D$19*D42 -> 17974.435 | E43: =E$19*E42 -> 19757.593 | F43: =F$19*F42 -> 22234.39 | G43: =G$19*G42 -> 23394.262 | H43: =H$19*H42 -> 27043.483 | I43: =I$19*I42 -> 32429.444 | ... P43: =P$19*P42 -> 51205.637
A44: Infrastructure services / ITBS mix | B44: 0.43865286 | C44: 0.48803057 | D44: 0.49038952 | E44: 0.49521175 | F44: =E44 -> 0.49521175 | G44: =F44 -> 0.49521175 | H44: =G44 -> 0.49521175 | I44: =H44 -> 0.49521175 | J44: =I44 -> 0.49521175 | K44: =J44 -> 0.49521175 | L44: =K44 -> 0.49521175 | M44: =L44+Assumptions!M26 -> 0.49521175 | N44: =M44+Assumptions!N26 -> 0.49521175 | O44: =N44+Assumptions!O26 -> 0.49521175 | P44: =O44+Assumptions!P26 -> 0.49521175
A45: Infrastructure services revenue | B45: =B$19*B44 -> 11085.97 | C45: =C$19*C44 -> 18542.579 | D45: =D$19*D44 -> 19099.244 | E45: =E$19*E44 -> 22335.923 | F45: =F$19*F44 -> 25135.938 | G45: =G$19*G44 -> 26447.172 | H45: =H$19*H44 -> 30572.61 | I45: =I$19*I44 -> 36661.429 | ... P45: =P$19*P44 -> 57887.882
A46: Business services / ITBS mix | B46: 0.065701079 | C46: 0.049499307 | D46: 0.048101387 | E46: 0.066740908 | F46: =E46 -> 0.066740908 | G46: =F46 -> 0.066740908 | H46: =G46 -> 0.066740908 | I46: =H46 -> 0.066740908 | J46: =I46 -> 0.066740908 | K46: =J46 -> 0.066740908 | L46: =K46 -> 0.066740908 | M46: =L46+Assumptions!M27 -> 0.066740908 | N46: =M46+Assumptions!N27 -> 0.066740908 | O46: =N46+Assumptions!O27 -> 0.066740908 | P46: =O46+Assumptions!P27 -> 0.066740908
A47: Business services revenue | B47: =B$19*B46 -> 1660.4479 | C47: =C$19*C46 -> 1880.7117 | D47: =D$19*D46 -> 1873.4089 | E47: =E$19*E46 -> 3010.2675 | F47: =F$19*F46 -> 3387.6324 | G47: =G$19*G46 -> 3564.3506 | H47: =H$19*H46 -> 4120.346 | I47: =I$19*I46 -> 4940.9512 | ... P47: =P$19*P46 -> 7801.6926
A48: ITBS subtotal | B48: =SUM(B43,B45,B47) -> 25272.764 | C48: =SUM(C43,C45,C47) -> 37994.709 | D48: =SUM(D43,D45,D47) -> 38947.087 | E48: =SUM(E43,E45,E47) -> 45103.784 | F48: =SUM(F43,F45,F47) -> 50757.961 | G48: =SUM(G43,G45,G47) -> 53405.784 | H48: =SUM(H43,H45,H47) -> 61736.439 | I48: =SUM(I43,I45,I47) -> 74031.825 | ... P48: =SUM(P43,P45,P47) -> 116895.21
A49: ITBS subtotal check | B49: =B48-B19 -> 0 | C49: =C48-C19 -> 0 | D49: =D48-D19 -> 0 | E49: =E48-E19 -> 0 | F49: =F48-F19 -> 0 | G49: =G48-G19 -> 0 | H49: =H48-H19 -> 0 | I49: =I48-I19 -> 0 | ... P49: =P48-P19 -> 0
A50: Engineering & R&D revenue | B50: =B21 -> 5863.2357 | C50: =C21 -> 8727.2914 | D50: =D21 -> 11622.913 | E50: =E21 -> 10340.989 | F50: =F21 -> 11799.846 | G50: =G21 -> 11728.253 | H50: =H21 -> 13566.783 | I50: =I21 -> 16810.704 | ... P50: =P21 -> 26602.658
A51: Products & Platforms revenue | B51: =B23 -> 0 | C51: =C23 -> 0 | D51: =D23 -> 0 | E51: =E23 -> 4983.2275 | F51: =F23 -> 8120.1937 | G51: =G23 -> 10244.963 | H51: =H23 -> 10370.107 | I51: =I23 -> 11097.672 | ... P51: =P23 -> 12988.357
A52: Total service-line revenue | B52: =SUM(B48,B50:B51) -> 31136 | C52: =SUM(C48,C50:C51) -> 46722 | D52: =SUM(D48,D50:D51) -> 50570 | E52: =SUM(E48,E50:E51) -> 60428 | F52: =SUM(F48,F50:F51) -> 70678 | G52: =SUM(G48,G50:G51) -> 75379 | H52: =SUM(H48,H50:H51) -> 85673.329 | I52: =SUM(I48,I50:I51) -> 101940.2 | ... P52: =SUM(P48,P50:P51) -> 156486.23
A53: Service-line revenue check | B53: =B52-B5 -> 0 | C53: =C52-C5 -> 0 | D53: =D52-D5 -> 0 | E53: =E52-E5 -> 0 | F53: =F52-F5 -> 0 | G53: =G52-G5 -> 0 | H53: =H52-H5 -> 22.329435 | I53: =I52-I5 -> 484.20057 | ... P53: =P52-P5 -> 0

Sheet Client Data
A1: Client Data — Concentration and Revenue Bands
A2: Separate annual client metrics; forecast held/rolled from explicit formulas
A4: Metric | B4: FY16A | C4: FY17A | D4: FY18A | E4: FY19A | F4: FY20A | G4: FY21A | H4: FY22A | I4: FY23A | J4: FY24A | K4: FY25A | L4: FY26A | M4: FY27E | N4: FY28E | O4: FY29E | P4: FY30E
A5: Active clients | B5: 0 | C5: 0 | D5: 0 | E5: 1005 | F5: 1040 | G5: 1075 | H5: 1110 | I5: 1145 | J5: 1180 | K5: 1215 | L5: 1250 | M5: =L5*(1+'Revenue Drivers'!M6/2) -> 1277.1364 | N5: =M5*(1+'Revenue Drivers'!N6/2) -> 1304.5012 | O5: =N5*(1+'Revenue Drivers'!O6/2) -> 1336.7346 | P5: =O5*(1+'Revenue Drivers'!P6/2) -> 1372.1469
A6: $1m+ clients | B6: 482 | C6: 506 | D6: 561 | E6: 623 | F6: 791 | G6: 809 | H6: 882 | I6: 939 | J6: 951 | K6: 948 | L6: 976 | M6: =L6 -> 976 | N6: =M6 -> 976 | O6: =N6 -> 976 | P6: =O6 -> 976
A7: $5m+ clients | B7: 233 | C7: 246 | D7: 264 | E7: 283 | F7: 308 | G7: 318 | H7: 349 | I7: 375 | J7: 395 | K7: 399 | L7: 429 | M7: =L7 -> 429 | N7: =M7 -> 429 | O7: =N7 -> 429 | P7: =O7 -> 429
A8: $10m+ clients | B8: 144 | C8: 153 | D8: 160 | E8: 166 | F8: 171 | G8: 178 | H8: 208 | I8: 229 | J8: 254 | K8: 251 | L8: 277 | M8: =L8 -> 277 | N8: =M8 -> 277 | O8: =N8 -> 277 | P8: =O8 -> 277
A9: $20m+ clients | B9: 75 | C9: 85 | D9: 87 | E9: 95 | F9: 96 | G9: 96 | H9: 118 | I9: 131 | J9: 137 | K9: 138 | L9: 149 | M9: =L9 -> 149 | N9: =M9 -> 149 | O9: =N9 -> 149 | P9: =O9 -> 149
A10: $50m+ clients | B10: 19 | C10: 25 | D10: 28 | E10: 29 | F10: 30 | G10: 35 | H10: 43 | I10: 46 | J10: 46 | K10: 52 | L10: 60 | M10: =L10 -> 60 | N10: =M10 -> 60 | O10: =N10 -> 60 | P10: =O10 -> 60
A11: $100m+ clients | B11: 8 | C11: 8 | D11: 8 | E11: 10 | F11: 15 | G11: 15 | H11: 16 | I11: 19 | J11: 22 | K11: 22 | L11: 23 | M11: =L11 -> 23 | N11: =M11 -> 23 | O11: =N11 -> 23 | P11: =O11 -> 23
A12: Top client revenue % | B12: 0.136 | C12: 0.14158744 | D12: 0.1542128 | E12: 0.17174943 | F12: 0.081 | G12: 0.08 | H12: 0.079 | I12: 0.078 | J12: 0.077 | K12: 0.076 | L12: 0.075 | M12: =L12 -> 0.075 | N12: =M12 -> 0.075 | O12: =N12 -> 0.075 | P12: =O12 -> 0.075
A13: Top 5 clients revenue % | B13: 0.21799541 | C13: 0.21803732 | D13: 0.23165992 | E13: 0.24567694 | F13: 0.177 | G13: 0.175 | H13: 0.173 | I13: 0.171 | J13: 0.169 | K13: 0.167 | L13: 0.165 | M13: =L13 -> 0.165 | N13: =M13 -> 0.165 | O13: =N13 -> 0.165 | P13: =O13 -> 0.165
A14: Top 10 clients revenue % | B14: 0.32332428 | C14: 0.32087295 | D14: 0.33358016 | E14: 0.33963404 | F14: 0.262 | G14: 0.26 | H14: 0.258 | I14: 0.256 | J14: 0.254 | K14: 0.252 | L14: 0.25 | M14: =L14 -> 0.25 | N14: =M14 -> 0.25 | O14: =N14 -> 0.25 | P14: =O14 -> 0.25
A15: Revenue / active client (₹ cr) | B15: =IFERROR('Annual P&L'!B5/B5,0) -> 0 | C15: =IFERROR('Annual P&L'!C5/C5,0) -> 0 | D15: =IFERROR('Annual P&L'!D5/D5,0) -> 0 | E15: =IFERROR('Annual P&L'!E5/E5,0) -> 60.127363 | F15: =IFERROR('Annual P&L'!F5/F5,0) -> 67.959615 | G15: =IFERROR('Annual P&L'!G5/G5,0) -> 70.12 | H15: =IFERROR('Annual P&L'!H5/H5,0) -> 77.163063 | I15: =IFERROR('Annual P&L'!I5/I5,0) -> 88.60786 | ... L15: =IFERROR('Annual P&L'!L5/L5,0) -> 104.1152 | M15: ='Annual P&L'!M5/M5 -> 106.32742 | N15: ='Annual P&L'!N5/N5 -> 108.55788 | O15: ='Annual P&L'!O5/O5 -> 111.17559 | P15: ='Annual P&L'!P5/P5 -> 114.04481
A17: Top 20 client contribution | B17: 0.32332428 | C17: 0.32087295 | D17: 0.33358016 | E17: 0.33963404 | F17: 0.33230191 | G17: 0.30776438 | H17: 0.29680206 | I17: 0.28363395 | J17: 0.27895446 | K17: 0.30554293 | L17: =K17 -> 0.30554293 | M17: =L17 -> 0.30554293 | N17: =M17 -> 0.30554293 | O17: =N17 -> 0.30554293 | P17: =O17 -> 0.30554293
A18: Non-top 20 contribution | B18: 0.67667572 | C18: 0.67912705 | D18: 0.66641984 | E18: 0.66036596 | F18: 0.66769809 | G18: 0.69223562 | H18: 0.70319794 | I18: 0.71636605 | J18: 0.72104554 | K18: 0.69445707 | L18: =K18 -> 0.69445707 | M18: =L18 -> 0.69445707 | N18: =M18 -> 0.69445707 | O18: =N18 -> 0.69445707 | P18: =O18 -> 0.69445707
A20: DSO (days) | L20: 61 | M20: =L20 -> 61 | N20: =M20 -> 61 | O20: =N20 -> 61 | P20: =O20 -> 61
A21: Repeat business | L21: =K21 -> 0 | M21: =L21 -> 0 | N21: =M21 -> 0 | O21: =N21 -> 0 | P21: =O21 -> 0
A22: LTM free cash flow ($m) | L22: =K22*('Annual P&L'!L5/'Annual P&L'!K5) -> 0 | M22: =L22*('Annual P&L'!M5/'Annual P&L'!L5) -> 0 | N22: =M22*('Annual P&L'!N5/'Annual P&L'!M5) -> 0 | O22: =N22*('Annual P&L'!O5/'Annual P&L'!N5) -> 0 | P22: =O22*('Annual P&L'!P5/'Annual P&L'!O5) -> 0

Sheet Checks & Sources
A1: Checks & Sources
A2: Formula integrity, tie-outs and source register
A4: Check | B4: Actual | C4: Expected | D4: Difference | E4: Tolerance | F4: Notes | G4: Status
A5: FY30 balance sheet | B5: ='Annual Balance Sheet'!P21 -> -161530.13 | C5: 0 | D5: =B5-C5 -> -161530.13 | E5: 1 | F5: Assets less liabilities & equity | G5: =IF(ABS(D5)<=E5,"OK","REVIEW") -> REVIEW
A6: FY30 cash tie | B6: ='Annual Cash Flow'!P31 -> 0 | C6: 0 | D6: =B6-C6 -> 0 | E6: 1 | F6: CFS closing cash less BS cash | G6: =IF(ABS(D6)<=E6,"OK","REVIEW") -> OK
A7: Forecast BS balance (max) | B7: =MAX(ABS('Annual Balance Sheet'!M21),ABS('Annual Balance Sheet'!N21),ABS('Annual Balance Sheet'!O21),ABS('Annual Balance Sheet'!P21)) -> 161530.13 | C7: 0 | D7: =B7-C7 -> 161530.13 | E7: 1 | F7: Maximum absolute FY27–FY30 balance check | G7: =IF(ABS(D7)<=E7,"OK","REVIEW") -> REVIEW
A8: Forecast cash tie (max) | B8: =MAX(ABS('Annual Cash Flow'!M31),ABS('Annual Cash Flow'!N31),ABS('Annual Cash Flow'!O31),ABS('Annual Cash Flow'!P31)) -> 0 | C8: 0 | D8: =B8-C8 -> 0 | E8: 1 | F8: Maximum absolute FY27–FY30 CFS/BS cash difference | G8: =IF(ABS(D8)<=E8,"OK","REVIEW") -> OK
A9: Forecast CFO build (max) | B9: =MAX(ABS('Annual Cash Flow'!M12-SUM('Annual Cash Flow'!M5:M11)),ABS('Annual Cash Flow'!N12-SUM('Annual Cash Flow'!N5:N11)),ABS('Annual Cash Flow'!O12-SUM('Annual Cash Flow'!O5:O11)),ABS('Annual Cash Flow'!P12-SUM('Annual Cash Flow'!P5:P11))) -> 0 | C9: 0 | D9: =B9-C9 -> 0 | E9: 1 | F9: CFO equals sum of detailed operating lines | G9: =IF(ABS(D9)<=E9,"OK","REVIEW") -> OK
A10: Forecast capex build (max) | B10: =MAX(ABS('Annual Cash Flow'!M18-SUM('Annual Cash Flow'!M15:M17)),ABS('Annual Cash Flow'!N18-SUM('Annual Cash Flow'!N15:N17)),ABS('Annual Cash Flow'!O18-SUM('Annual Cash Flow'!O15:O17)),ABS('Annual Cash Flow'!P18-SUM('Annual Cash Flow'!P15:P17))) -> 0 | C10: 0 | D10: =B10-C10 -> 0 | E10: 1 | F10: Total capex equals maintenance + data-centre/AI + growth | G10: =IF(ABS(D10)<=E10,"OK","REVIEW") -> OK
A11: Forecast FCF tie (max) | B11: =MAX(ABS('Annual Cash Flow'!M32-'Annual Cash Flow'!M12-'Annual Cash Flow'!M18),ABS('Annual Cash Flow'!N32-'Annual Cash Flow'!N12-'Annual Cash Flow'!N18),ABS('Annual Cash Flow'!O32-'Annual Cash Flow'!O12-'Annual Cash Flow'!O18),ABS('Annual Cash Flow'!P32-'Annual Cash Flow'!P12-'Annual Cash Flow'!P18)) -> 5.4569682e-12 | C11: 0 | D11: =B11-C11 -> 5.4569682e-12 | E11: 1 | F11: FCF equals CFO plus total capex | G11: =IF(ABS(D11)<=E11,"OK","REVIEW") -> OK
A12: Forecast EPS tie (max) | B12: =MAX(ABS('Annual P&L'!M29-'Annual P&L'!M25/'Annual P&L'!M27),ABS('Annual P&L'!N29-'Annual P&L'!N25/'Annual P&L'!N27),ABS('Annual P&L'!O29-'Annual P&L'!O25/'Annual P&L'!O27),ABS('Annual P&L'!P29-'Annual P&L'!P25/'Annual P&L'!P27)) -> 0 | C12: 0 | D12: =B12-C12 -> 0 | E12: 0.001 | F12: Basic EPS equals net profit / basic shares | G12: =IF(ABS(D12)<=E12,"OK","REVIEW") -> OK
A13: FY27 target upside range | B13: =IF(AND('Market Data'!E35>='Market Data'!E30,'Market Data'!E35<='Market Data'!E31),1,0) -> 1 | C13: 1 | D13: =B13-C13 -> 0 | E13: 0 | F13: Target remains within 10%–15% of FY26 observed price | G13: =IF(B13=C13,"OK","REVIEW") -> OK
A17: MODEL STATUS | G17: =IF(COUNTIF(G5:G13,"REVIEW")=0,"OK","REVIEW") -> REVIEW
A20: SOURCE REGISTER
A21: Item | B21: Period | C21: Units | D21: Source | E21: URL | F21: Status | G21: Notes
A22: Annual statements | B22: FY16–FY26 | C22: INR crore | D22: HCLTech filings / compiled statement extracts | E22: https://www.hcltech.com/investors/annual-reports | F22: Used | G22: FY16 is nine months
A23: Quarterly P&L | B23: FY22–FY27 | C23: USD million | D23: Compiled reported financial statements | E23: https://stockanalysis.com/quote/nse/HCLTECH/financials/?p=quarterly | F23: Used | G23: No quarterly BS or CF in final model
A24: Workforce / attrition | B24: FY16–FY26 | C24: employees / % | D24: HCLTech annual reports and earnings releases | E24: https://www.hcltech.com/investors/results-reports | F24: Used / estimated gaps | G24: Forecast is assumption-driven
A25: Segment and client history | B25: FY16–FY26 | C25: % / counts | D25: HCLTech annual report disclosures | E25: https://www.hcltech.com/investors/annual-reports | F25: Model series | G25: Consistent categories estimated where definitions changed
A28: Reference update | B28: Annual P&L / BS / CF / segments / clients | C28: FY16–FY26 | D28: BO reference workbook | E28: Historical series replaced | F28: OK | G28: Original model retained; reference used only as data source
A29: Service-line tie | B29: Service-line total | C29: FY16–FY30 | D29: Segment Revenue | E29: Total equals revenue | F29: OK | G29: Legacy disclosure through FY19; modelled ITBS allocation thereafter
A30: Software schedule | B30: License + subscription + professional services | C30: FY17–FY30 | D30: Products tab | E30: Total calculated; forecasts assumption-driven | F30: OK | G30: ARR and segment margins also forecast from assumptions
A31: Advanced AI revenue | B31: Q4 FY26 / Q1 FY27 | C31: $m annualized / quarterly | D31: https://www.hcltech.com/en-us/press-releases/hcltech-fy26-revenue-39-led-increasing-demand-advanced-ai | E31: Q4 FY26 annualized AI revenue $620m | F31: Used | G31: AI category excludes classical AI and AI used in traditional services
A32: Advanced AI revenue | B32: Q1 FY27 | C32: $m quarterly | D32: https://www.hcltech.com/en-us/press-releases/hcltech-delivers-robust-q1-led-record-deal-bookings-24-billion | E32: Quarterly Advanced AI revenue $171m | F32: Used | G32: 62.1% YoY CC; annualized run-rate $684m
A33: Financial summary | B33: P&L / cash flow / balance sheet / ratios | C33: FY16–FY30 | D33: Linked model schedules | E33: Formula-driven summary tab | F33: OK | G33: Reference layout recreated; estimates shaded separately
A34: Detailed statement taxonomy | B34: Quarterly P&L / annual cash flow | C34: FY16–FY30 | D34: BO reference workbook | E34: Local reference file | F34: Used | G34: FX, D&A/EBITDA, EPS/shares and detailed cash-flow taxonomy
A35: Capex & operating metrics | B35: Forecast | C35: FY27–FY30 | D35: Model assumptions | E35: Assumptions / Capex & Metrics | F35: Used | G35: Data-centre/AI capex, offshore mix, utilization, support and subcontractor ratios

Sheet Operating Cuts
A1: Operating Cuts — ITBS, ER&D and Software
A2: Historical exit-quarter cuts from the BO reference workbook; FY27–FY30 use explicit model assumptions
A5: Metric | B5: Units | C5: FY17A | D5: FY18A | E5: FY19A | F5: FY20A | G5: FY21A | H5: FY22A | I5: FY23A | J5: FY24A | K5: FY25A | L5: FY26A | M5: FY27E | N5: FY28E | O5: FY29E | P5: FY30E
A7: IT & Business Services revenue | B7: $m | E7: 1726.695 | F7: 1795.551 | G7: 1937.024 | H7: 2199 | I7: 2387 | J7: 2552 | K7: 2566 | L7: 2759 | M7: =L7*('Segment Revenue'!M19/'Segment Revenue'!L19) -> 2867.2756 | N7: =M7*('Segment Revenue'!N19/'Segment Revenue'!M19) -> 2990.1484 | O7: =N7*('Segment Revenue'!O19/'Segment Revenue'!N19) -> 3137.9175 | P7: =O7*('Segment Revenue'!P19/'Segment Revenue'!O19) -> 3304.1747
A8: ITBS EBIT | B8: $m | E8: 304.68 | F8: 343.112 | G8: 322.324 | H8: 384.825 | I8: 407.443 | J8: 423 | K8: 435 | L8: 450 | M8: =M7*M9 -> 467.36592 | N8: =N7*N9 -> 487.39418 | O8: =O7*O9 -> 511.48056 | P8: =P7*P9 -> 538.58048
A9: ITBS EBIT margin | B9: % | E9: 0.1764527 | F9: 0.19109009 | G9: 0.16640166 | H9: 0.175 | I9: 0.1706925 | J9: 0.16575235 | K9: 0.16952455 | L9: 0.163 | M9: =Assumptions!M34 -> 0.163 | N9: =Assumptions!N34 -> 0.163 | O9: =Assumptions!O34 -> 0.163 | P9: =Assumptions!P34 -> 0.163
A10: Engineering & R&D revenue | B10: $m | E10: 378.998 | F10: 415.43 | G10: 408.436 | H10: 490 | I10: 520 | J10: 552 | K10: 597 | L10: 626 | M10: =L10*('Segment Revenue'!M21/'Segment Revenue'!L21) -> 653.17978 | N10: =M10*('Segment Revenue'!N21/'Segment Revenue'!M21) -> 681.17081 | O10: =N10*('Segment Revenue'!O21/'Segment Revenue'!N21) -> 714.83337 | P10: =O10*('Segment Revenue'!P21/'Segment Revenue'!O21) -> 752.7076
A11: ER&D EBIT | B11: $m | E11: 89.331 | F11: 78.73 | G11: 64.272 | H11: 93.59 | I11: 96.939 | J11: 109 | K11: 107 | L11: 97 | M11: =M10*M12 -> 101.24287 | N11: =N10*N12 -> 105.58148 | O11: =O10*O12 -> 110.79917 | P11: =P10*P12 -> 116.66968
A12: ER&D EBIT margin | B12: % | E12: 0.23570309 | F12: 0.18951448 | G12: 0.15736125 | H12: 0.191 | I12: 0.18642115 | J12: 0.19746377 | K12: 0.17922948 | L12: 0.15495208 | M12: =Assumptions!M35 -> 0.155 | N12: =Assumptions!N35 -> 0.155 | O12: =Assumptions!O35 -> 0.155 | P12: =Assumptions!P35 -> 0.155
A13: Products & Platforms revenue | B13: $m | E13: 172.093 | F13: 332.429 | G13: 350.437 | H13: 304 | I13: 328 | J13: 326 | K13: 335 | L13: 297 | M13: =L13*('Segment Revenue'!M23/'Segment Revenue'!L23) -> 309.8952 | N13: =M13*('Segment Revenue'!N23/'Segment Revenue'!M23) -> 323.17529 | O13: =N13*('Segment Revenue'!O23/'Segment Revenue'!N23) -> 339.14618 | P13: =O13*('Segment Revenue'!P23/'Segment Revenue'!O23) -> 357.11527
A14: Products & Platforms EBIT | B14: $m | E14: 41.812 | F14: 109.015 | G14: 62.705 | H14: 58.064 | I14: 78.6 | J14: 72 | K14: 84 | L14: 60 | M14: =M13*M15 -> 62.59883 | N14: =N13*N15 -> 65.281409 | O14: =O13*O15 -> 68.507529 | P14: =P13*P15 -> 72.137284
A15: Products EBIT margin | B15: % | E15: 0.24296165 | F15: 0.32793469 | G15: 0.17893373 | H15: 0.191 | I15: 0.23963415 | J15: 0.2208589 | K15: 0.25074627 | L15: 0.2020202 | M15: =Assumptions!M36 -> 0.202 | N15: =Assumptions!N36 -> 0.202 | O15: =Assumptions!O36 -> 0.202 | P15: =Assumptions!P36 -> 0.202
A17: Perpetual license upfront & other | B17: $m | H17: 49.7 | I17: 49.8 | J17: 31.6 | K17: 34.4 | L17: 19 | M17: =L17*(1+Assumptions!M30) -> 19.95 | N17: =M17*(1+Assumptions!N30) -> 20.9475 | O17: =N17*(1+Assumptions!O30) -> 21.994875 | P17: =O17*(1+Assumptions!P30) -> 23.094619
A18: Subscription & support | B18: $m | H18: 251.6 | I18: 270.4 | J18: 288.5 | K18: 295 | L18: 268 | M18: =L18*(1+Assumptions!M31) -> 276.04 | N18: =M18*(1+Assumptions!N31) -> 284.3212 | O18: =N18*(1+Assumptions!O31) -> 292.85084 | P18: =O18*(1+Assumptions!P31) -> 301.63636
A19: Professional services | B19: $m | H19: 19.4 | I19: 22 | J19: 21.4 | K19: 18.5 | L19: 20 | M19: =L19*(1+Assumptions!M32) -> 21.2 | N19: =M19*(1+Assumptions!N32) -> 22.472 | O19: =N19*(1+Assumptions!O32) -> 23.82032 | P19: =O19*(1+Assumptions!P32) -> 25.249539
A20: Software total | B20: $m | H20: 320.7 | I20: 342.2 | J20: 341.5 | K20: 347.9 | L20: 307 | M20: =SUM(M17:M19) -> 317.19 | N20: =SUM(N17:N19) -> 327.7407 | O20: =SUM(O17:O19) -> 338.66603 | P20: =SUM(P17:P19) -> 349.98052
A21: Software ARR | B21: $m | H21: 922.2 | I21: 1028.2 | J21: 1024.3 | K21: 1032.8 | L21: 1045 | M21: =L21*(1+Assumptions!M33) -> 1128.6 | N21: =M21*(1+Assumptions!N33) -> 1218.888 | O21: =N21*(1+Assumptions!O33) -> 1316.399 | P21: =O21*(1+Assumptions!P33) -> 1421.711
A22: ARR growth YoY CC | B22: % | I22: 0.052 | J22: 0.007 | K22: 0.018 | L22: 0.018 | M22: =M21/L21-1 -> 0.08 | N22: =N21/M21-1 -> 0.08 | O22: =O21/N21-1 -> 0.08 | P22: =P21/O21-1 -> 0.08
A25: Growth %
A26: IT & Business Services revenue | I26: =I13/H13-1 -> 0.078947368 | J26: =J13/I13-1 -> -0.006097561 | K26: =K13/J13-1 -> 0.027607362 | L26: =L13/K13-1 -> -0.11343284 | M26: =M13/L13-1 -> 0.043418182 | N26: =N13/M13-1 -> 0.042853488 | O26: =O13/N13-1 -> 0.04941867 | P26: =P13/O13-1 -> 0.052983298
A27: Engineering & R&D revenue | I27: =I14/H14-1 -> 0.3536787 | J27: =J14/I14-1 -> -0.083969466 | K27: =K14/J14-1 -> 0.16666667 | L27: =L14/K14-1 -> -0.28571429 | M27: =M14/L14-1 -> 0.04331384 | N27: =N14/M14-1 -> 0.042853488 | O27: =O14/N14-1 -> 0.04941867 | P27: =P14/O14-1 -> 0.052983298
A28: Products & Platforms revenue | I28: =I15/H15-1 -> 0.25462904 | J28: =J15/I15-1 -> -0.078349646 | K28: =K15/J15-1 -> 0.13532338 | L28: =L15/K15-1 -> -0.19432419 | M28: =M15/L15-1 -> -0.0001 | N28: =N15/M15-1 -> 0 | O28: =O15/N15-1 -> 0 | P28: =P15/O15-1 -> 0
A30: Perpetual license upfront & other | B30: $m | I30: =I17/H17-1 -> 0.0020120724 | J30: =J17/I17-1 -> -0.36546185 | K30: =K17/J17-1 -> 0.088607595 | L30: =L17/K17-1 -> -0.44767442 | M30: =M17/L17-1 -> 0.05 | N30: =N17/M17-1 -> 0.05 | O30: =O17/N17-1 -> 0.05 | P30: =P17/O17-1 -> 0.05
A31: Subscription & support | B31: $m | I31: =I18/H18-1 -> 0.074721781 | J31: =J18/I18-1 -> 0.06693787 | K31: =K18/J18-1 -> 0.022530329 | L31: =L18/K18-1 -> -0.091525424 | M31: =M18/L18-1 -> 0.03 | N31: =N18/M18-1 -> 0.03 | O31: =O18/N18-1 -> 0.03 | P31: =P18/O18-1 -> 0.03
A32: Professional services | B32: $m | I32: =I19/H19-1 -> 0.13402062 | J32: =J19/I19-1 -> -0.027272727 | K32: =K19/J19-1 -> -0.13551402 | L32: =L19/K19-1 -> 0.081081081 | M32: =M19/L19-1 -> 0.06 | N32: =N19/M19-1 -> 0.06 | O32: =O19/N19-1 -> 0.06 | P32: =P19/O19-1 -> 0.06
A33: Software total | B33: $m | I33: =I20/H20-1 -> 0.067040848 | J33: =J20/I20-1 -> -0.0020455874 | K33: =K20/J20-1 -> 0.018740849 | L33: =L20/K20-1 -> -0.11756252 | M33: =M20/L20-1 -> 0.033192182 | N33: =N20/M20-1 -> 0.033263028 | O33: =O20/N20-1 -> 0.033335289 | P33: =P20/O20-1 -> 0.033408984

Sheet Market Data
A1: HCLTech Market Data & Valuation Inputs
A2: FY16–FY26 prices are observed; FY27–FY30 estimates equal forecast EPS multiplied by a target P/E path that fades toward FY26 observed P/E.
A4: Period | B4: Price date | C4: Share price (INR) | D4: Price source | E4: Dividend per share (INR)
A5: FY16A | B5: 2016-03-31 | C5: 407.04999 | D5: https://finance.yahoo.com/quote/HCLTECH.NS/history/
A6: FY17A | B6: 2017-03-31 | C6: 437.375 | D6: https://finance.yahoo.com/quote/HCLTECH.NS/history/
A7: FY18A | B7: 2018-03-28 | C7: 484.29999 | D7: https://finance.yahoo.com/quote/HCLTECH.NS/history/
A8: FY19A | B8: 2019-03-28 | C8: 541.45001 | D8: https://finance.yahoo.com/quote/HCLTECH.NS/history/
A9: FY20A | B9: 2020-03-31 | C9: 436.39999 | D9: https://finance.yahoo.com/quote/HCLTECH.NS/history/
A10: FY21A | B10: 2021-03-31 | C10: 982.65002 | D10: https://finance.yahoo.com/quote/HCLTECH.NS/history/
A11: FY22A | B11: 2022-03-31 | C11: 1163.75 | D11: https://finance.yahoo.com/quote/HCLTECH.NS/history/
A12: FY23A | B12: 2023-03-31 | C12: 1085.25 | D12: https://finance.yahoo.com/quote/HCLTECH.NS/history/
A13: FY24A | B13: 2024-03-28 | C13: 1543.55 | D13: https://finance.yahoo.com/quote/HCLTECH.NS/history/
A14: FY25A | B14: 2025-03-28 | C14: 1592.5 | D14: https://finance.yahoo.com/quote/HCLTECH.NS/history/
A15: FY26A | B15: 2026-03-30 | C15: 1341.6 | D15: https://finance.yahoo.com/quote/HCLTECH.NS/history/ | E15: 60
A16: FY27E | B16: FY27 EPS × target P/E | C16: =E34 -> 1475.76 | D16: Model formula — EPS and target P/E | E16: ='Annual P&L'!M29*Assumptions!M22 -> 28.084103
A17: FY28E | B17: FY28 EPS × target P/E | C17: ='Annual P&L'!N29*$E$41 -> 1471.8198 | D17: Model formula — EPS and target P/E | E17: ='Annual P&L'!N29*Assumptions!N22 -> 29.341357 | F17: =C16/C15-1 -> 0.1
A18: FY29E | B18: FY29 EPS × target P/E | C18: ='Annual P&L'!O29*$E$42 -> 1346.3551 | D18: Model formula — EPS and target P/E | E18: ='Annual P&L'!O29*Assumptions!O22 -> 27.836916
A19: FY30E | B19: FY30 EPS × target P/E | C19: ='Annual P&L'!P29*$E$43 -> 1221.2182 | D19: Model formula — EPS and target P/E | E19: ='Annual P&L'!P29*Assumptions!P22 -> 26.223467
A22: Forecast dividend payout | B22: Linked to model assumption | C22: Analyst assumption | D22: Assumptions tab | E22: =Assumptions!M22 -> 0.45
A24: Source note | B24: FY26 dividend per share | C24: ₹60 | D24: https://www.hcltech.com/sites/default/files/documents/resources/pdf-landing-page/files/2026/04/21/financialresults.pdf | E24: Official HCLTech FY26 results
A25: Source note | B25: Price history | C25: NSE HCLTECH daily close | D25: https://finance.yahoo.com/quote/HCLTECH.NS/history/ | E25: Yahoo Finance
A26: Valuation convention | B26: FY27–FY30 | C26: Forecast EPS × target P/E | D26: FY27 uses five-year median P/E; FY28–FY30 fade linearly toward FY26 observed P/E | E26: Formula-driven
A28: FY27 Target Valuation — Market Perform
A29: FY26 observed price | B29: Last sourced fiscal-year close | C29: 2026-03-30 | D29: Yahoo Finance | E29: =$C$15 -> 1341.6
A30: Market Perform minimum upside | B30: Editable recommendation bound | C30: 10% | D30: Analyst assumption | E30: 0.1
A31: Market Perform maximum upside | B31: Editable recommendation bound | C31: 15% | D31: Analyst assumption | E31: 0.15
A32: 5-year historical median P/E | B32: Median FY22–FY26 observed P/E | C32: Formula-driven | D32: Valuation anchor | E32: =MEDIAN('Fin Summary'!Y40:AC40) -> 23.381142
A33: Unconstrained FY27 value | B33: Historical median P/E × FY27E EPS | C33: Formula-driven | D33: Model output | E33: ='Annual P&L'!M29*E32 -> 1459.1965
A34: FY27 target price | B34: FY27E EPS × five-year median P/E | C34: Formula-driven | D34: Recommendation output | E34: =MIN(MAX(E33,E29*(1+E30)),E29*(1+E31)) -> 1475.76
A35: FY27 target upside | B35: Target price ÷ FY26 price − 1 | C35: Formula-driven | D35: Recommendation output | E35: =E34/E29-1 -> 0.1
A36: FY27 target P/E | B36: Target price ÷ FY27E EPS | C36: Formula-driven | D36: Target multiple | E36: =E34/'Annual P&L'!M29 -> 23.646545
A37: FY27 target EV / EBITDA | B37: Target EV ÷ FY27E EBITDA | C37: Formula-driven | D37: Target multiple | E37: =IFERROR(($E$34*'Annual P&L'!M27+'Annual Balance Sheet'!M14-'Annual Balance Sheet'!M5)/'Annual P&L'!M14,0) -> 14.049917
A38: FY27 target P / book | B38: Target market cap ÷ FY27E equity | C38: Formula-driven | D38: Target multiple | E38: =IFERROR(($E$34*'Annual P&L'!M27)/'Annual Balance Sheet'!M19,0) -> 10.225899
A40: FY27 target P/E | B40: Five-year historical median P/E | C40: EPS-driven valuation | D40: Formula-driven | E40: =$E$32 -> 23.381142
A41: FY28 target P/E | B41: One-third fade toward FY26 P/E | C41: EPS-driven valuation | D41: Formula-driven | E41: =$E$40-($E$40-'Fin Summary'!AC40)/3 -> 22.572879
A42: FY29 target P/E | B42: Two-thirds fade toward FY26 P/E | C42: EPS-driven valuation | D42: Formula-driven | E42: =$E$40-2*($E$40-'Fin Summary'!AC40)/3 -> 21.764616
A43: FY30 target P/E | B43: FY26 observed P/E | C43: EPS-driven valuation | D43: Formula-driven | E43: ='Fin Summary'!AC40 -> 20.956353

Sheet Capex & Metrics
A1: Capex & Operating Metrics
A2: Data-centre / AI infrastructure investment and delivery-efficiency metrics; forecast inputs are editable on Assumptions
A4: Metric | B4: FY16A | C4: FY17A | D4: FY18A | E4: FY19A | F4: FY20A | G4: FY21A | H4: FY22A | I4: FY23A | J4: FY24A | K4: FY25A | L4: FY26A | M4: FY27E | N4: FY28E | O4: FY29E | P4: FY30E
A5: CAPEX SCHEDULE
A6: Revenue (INR cr) | B6: ='Annual P&L'!B5 -> 31136 | C6: ='Annual P&L'!C5 -> 46722 | D6: ='Annual P&L'!D5 -> 50570 | E6: ='Annual P&L'!E5 -> 60428 | F6: ='Annual P&L'!F5 -> 70678 | G6: ='Annual P&L'!G5 -> 75379 | H6: ='Annual P&L'!H5 -> 85651 | I6: ='Annual P&L'!I5 -> 101456 | ... P6: ='Annual P&L'!P5 -> 156486.23
A7: Maintenance capex | B7: =-'Annual Cash Flow'!B15 -> 2164.2746 | C7: =-'Annual Cash Flow'!C15 -> 6197.7 | D7: =-'Annual Cash Flow'!D15 -> 4936.2 | E7: =-'Annual Cash Flow'!E15 -> 6053.6 | F7: =-'Annual Cash Flow'!F15 -> 17633 | G7: =-'Annual Cash Flow'!G15 -> 3483 | H7: =-'Annual Cash Flow'!H15 -> 1600 | I7: =-'Annual Cash Flow'!I15 -> 3597 | ... P7: =-'Annual Cash Flow'!P15 -> 2816.7521
A8: Data centre & AI infrastructure capex | B8: =-'Annual Cash Flow'!B16 -> 0 | C8: =-'Annual Cash Flow'!C16 -> 0 | D8: =-'Annual Cash Flow'!D16 -> 0 | E8: =-'Annual Cash Flow'!E16 -> 0 | F8: =-'Annual Cash Flow'!F16 -> 0 | G8: =-'Annual Cash Flow'!G16 -> 0 | H8: =-'Annual Cash Flow'!H16 -> 0 | I8: =-'Annual Cash Flow'!I16 -> 0 | ... P8: =-'Annual Cash Flow'!P16 -> 1564.8623
A9: Other growth capex | B9: =-'Annual Cash Flow'!B17 -> 0 | C9: =-'Annual Cash Flow'!C17 -> 0 | D9: =-'Annual Cash Flow'!D17 -> 0 | E9: =-'Annual Cash Flow'!E17 -> 0 | F9: =-'Annual Cash Flow'!F17 -> 0 | G9: =-'Annual Cash Flow'!G17 -> 0 | H9: =-'Annual Cash Flow'!H17 -> 0 | I9: =-'Annual Cash Flow'!I17 -> 0 | ... P9: =-'Annual Cash Flow'!P17 -> 1095.4036
A10: Total capex | B10: =-'Annual Cash Flow'!B18 -> 2164.2746 | C10: =-'Annual Cash Flow'!C18 -> 6197.7 | D10: =-'Annual Cash Flow'!D18 -> 4936.2 | E10: =-'Annual Cash Flow'!E18 -> 6053.6 | F10: =-'Annual Cash Flow'!F18 -> 17633 | G10: =-'Annual Cash Flow'!G18 -> 3483 | H10: =-'Annual Cash Flow'!H18 -> 1600 | I10: =-'Annual Cash Flow'!I18 -> 3597 | ... P10: =-'Annual Cash Flow'!P18 -> 5477.0179
A11: Capex / revenue | B11: =IFERROR(B10/B6,0) -> 0.069510362 | C11: =IFERROR(C10/C6,0) -> 0.13265057 | D11: =IFERROR(D10/D6,0) -> 0.097611232 | E11: =IFERROR(E10/E6,0) -> 0.10017873 | F11: =IFERROR(F10/F6,0) -> 0.24948357 | G11: =IFERROR(G10/G6,0) -> 0.046206503 | H11: =IFERROR(H10/H6,0) -> 0.018680459 | I11: =IFERROR(I10/I6,0) -> 0.035453793 | ... P11: =IFERROR(P10/P6,0) -> 0.035
A12: D&A | B12: ='Annual P&L'!B16 -> 445.37462 | C12: ='Annual P&L'!C16 -> 834 | D12: ='Annual P&L'!D16 -> 1452 | E12: ='Annual P&L'!E16 -> 2148 | F12: ='Annual P&L'!F16 -> 2840 | G12: ='Annual P&L'!G16 -> 3985 | H12: ='Annual P&L'!H16 -> 4181 | I12: ='Annual P&L'!I16 -> 4144 | ... P12: ='Annual P&L'!P16 -> 5477.0179
A13: D&A / capex | B13: =IFERROR(B12/B10,0) -> 0.20578471 | C13: =IFERROR(C12/C10,0) -> 0.13456605 | D13: =IFERROR(D12/D10,0) -> 0.2941534 | E13: =IFERROR(E12/E10,0) -> 0.35483018 | F13: =IFERROR(F12/F10,0) -> 0.16106165 | G13: =IFERROR(G12/G10,0) -> 1.1441286 | H13: =IFERROR(H12/H10,0) -> 2.613125 | I13: =IFERROR(I12/I10,0) -> 1.1520712 | ... P13: =IFERROR(P12/P10,0) -> 1
A14: Net PPE & intangibles | B14: ='Annual Balance Sheet'!B9 -> 4323.1 | C14: ='Annual Balance Sheet'!C9 -> 4680.6 | D14: ='Annual Balance Sheet'!D9 -> 5184.7 | E14: ='Annual Balance Sheet'!E9 -> 5801 | F14: ='Annual Balance Sheet'!F9 -> 8868 | G14: ='Annual Balance Sheet'!G9 -> 8637 | H14: ='Annual Balance Sheet'!H9 -> 8046 | I14: ='Annual Balance Sheet'!I9 -> 7748 | ... P14: ='Annual Balance Sheet'!P9 -> 8309
A15: Asset turnover | B15: =IFERROR(B6/AVERAGE(B14,B14),0) -> 7.2022391 | C15: =IFERROR(C6/AVERAGE(B14,C14),0) -> 10.3784 | D15: =IFERROR(D6/AVERAGE(C14,D14),0) -> 10.252096 | E15: =IFERROR(E6/AVERAGE(D14,E14),0) -> 11.001211 | F15: =IFERROR(F6/AVERAGE(E14,F14),0) -> 9.636376 | G15: =IFERROR(G6/AVERAGE(F14,G14),0) -> 8.6122822 | H15: =IFERROR(H6/AVERAGE(G14,H14),0) -> 10.268057 | I15: =IFERROR(I6/AVERAGE(H14,I14),0) -> 12.84741 | J15: =IFERROR(J6/AVERAGE(I14,J14),0) -> 14.04011 | ... P15: =IFERROR(P6/AVERAGE(O14,P14),0) -> 18.833341
A17: DELIVERY & OPERATING METRICS
A18: Closing headcount | B18: ='Revenue Drivers'!B7 -> 106107 | C18: ='Revenue Drivers'!C7 -> 117781 | D18: ='Revenue Drivers'!D7 -> 120081 | E18: ='Revenue Drivers'!E7 -> 137965 | F18: ='Revenue Drivers'!F7 -> 150423 | G18: ='Revenue Drivers'!G7 -> 168977 | H18: ='Revenue Drivers'!H7 -> 208877 | I18: ='Revenue Drivers'!I7 -> 225944 | ... P18: ='Revenue Drivers'!P7 -> 260074.61
A19: Billable employees | B19: ='Revenue Drivers'!B9 -> 82763.46 | C19: ='Revenue Drivers'!C9 -> 91869.18 | D19: ='Revenue Drivers'!D9 -> 94863.99 | E19: ='Revenue Drivers'!E9 -> 108992.35 | F19: ='Revenue Drivers'!F9 -> 120338.4 | G19: ='Revenue Drivers'!G9 -> 135181.6 | H19: ='Revenue Drivers'!H9 -> 169190.37 | I19: ='Revenue Drivers'!I9 -> 183014.64 | ... P19: ='Revenue Drivers'!P9 -> 213261.18
A20: Billable % | B20: ='Revenue Drivers'!B10 -> 0.78 | C20: ='Revenue Drivers'!C10 -> 0.78 | D20: ='Revenue Drivers'!D10 -> 0.79 | E20: ='Revenue Drivers'!E10 -> 0.79 | F20: ='Revenue Drivers'!F10 -> 0.8 | G20: ='Revenue Drivers'!G10 -> 0.8 | H20: ='Revenue Drivers'!H10 -> 0.81 | I20: ='Revenue Drivers'!I10 -> 0.81 | ... P20: ='Revenue Drivers'!P10 -> 0.82
A21: Attrition | B21: ='Revenue Drivers'!B13 -> 0.16 | C21: ='Revenue Drivers'!C13 -> 0.15 | D21: ='Revenue Drivers'!D13 -> 0.16 | E21: ='Revenue Drivers'!E13 -> 0.17 | F21: ='Revenue Drivers'!F13 -> 0.1 | G21: ='Revenue Drivers'!G13 -> 0.1 | H21: ='Revenue Drivers'!H13 -> 0.21 | I21: ='Revenue Drivers'!I13 -> 0.19 | ... L21: ='Revenue Drivers'!L13 -> 0.125 | M21: =Assumptions!M6 -> 0.125 | N21: =Assumptions!N6 -> 0.125 | O21: =Assumptions!O6 -> 0.125 | P21: =Assumptions!P6 -> 0.125
A22: Revenue / billable employee (INR cr) | B22: ='Revenue Drivers'!B11 -> 0.37620467 | C22: ='Revenue Drivers'!C11 -> 0.51777974 | D22: ='Revenue Drivers'!D11 -> 0.53306845 | E22: ='Revenue Drivers'!E11 -> 0.55441506 | F22: ='Revenue Drivers'!F11 -> 0.58731045 | G22: ='Revenue Drivers'!G11 -> 0.55761287 | H22: ='Revenue Drivers'!H11 -> 0.5062404 | I22: ='Revenue Drivers'!I11 -> 0.55436002 | ... P22: ='Revenue Drivers'!P11 -> 0.73377735
A23: T&M mix | B23: =0 -> 0 | C23: =0 -> 0 | D23: =0 -> 0 | E23: =0 -> 0 | F23: =0 -> 0 | G23: =0 -> 0 | H23: =0 -> 0 | I23: =0 -> 0 | ... L23: =0 -> 0 | M23: =Assumptions!M9 -> 0.6145 | N23: =Assumptions!N9 -> 0.602 | O23: =Assumptions!O9 -> 0.602 | P23: =Assumptions!P9 -> 0.602
A24: AI deflation on T&M | B24: =0 -> 0 | C24: =0 -> 0 | D24: =0 -> 0 | E24: =0 -> 0 | F24: =0 -> 0 | G24: =0 -> 0 | H24: =0 -> 0 | I24: =0 -> 0 | ... L24: =0 -> 0 | M24: =Assumptions!M10 -> 0.03 | N24: =Assumptions!N10 -> 0.035 | O24: =Assumptions!O10 -> 0.035 | P24: =Assumptions!P10 -> 0.035
A25: Advanced AI revenue ($m, annualized) | B25: ='Revenue Drivers'!B26 -> 0 | C25: ='Revenue Drivers'!C26 -> 0 | D25: ='Revenue Drivers'!D26 -> 0 | E25: ='Revenue Drivers'!E26 -> 0 | F25: ='Revenue Drivers'!F26 -> 0 | G25: ='Revenue Drivers'!G26 -> 0 | H25: ='Revenue Drivers'!H26 -> 0 | I25: ='Revenue Drivers'!I26 -> 0 | ... P25: ='Revenue Drivers'!P26 -> 1383.4342
A26: Advanced AI mix of company revenue | B26: ='Revenue Drivers'!B28 -> 0 | C26: ='Revenue Drivers'!C28 -> 0 | D26: ='Revenue Drivers'!D28 -> 0 | E26: ='Revenue Drivers'!E28 -> 0 | F26: ='Revenue Drivers'!F28 -> 0 | G26: ='Revenue Drivers'!G28 -> 0 | H26: ='Revenue Drivers'!H28 -> 0 | I26: ='Revenue Drivers'!I28 -> 0 | ... P26: ='Revenue Drivers'!P28 -> 0.078461044
A27: Offshore revenue mix | B27: =0 -> 0 | C27: =0 -> 0 | D27: =0 -> 0 | E27: =0 -> 0 | F27: =0 -> 0 | G27: =0 -> 0 | H27: =0 -> 0 | I27: =0 -> 0 | ... L27: =0 -> 0 | M27: =Assumptions!M43 -> 0.55 | N27: =Assumptions!N43 -> 0.56 | O27: =Assumptions!O43 -> 0.57 | P27: =Assumptions!P43 -> 0.58
A28: Utilization excl. trainees | B28: =0 -> 0 | C28: =0 -> 0 | D28: =0 -> 0 | E28: =0 -> 0 | F28: =0 -> 0 | G28: =0 -> 0 | H28: =0 -> 0 | I28: =0 -> 0 | ... L28: =0 -> 0 | M28: =Assumptions!M44 -> 0.83 | N28: =Assumptions!N44 -> 0.835 | O28: =Assumptions!O44 -> 0.84 | P28: =Assumptions!P44 -> 0.845
A29: Support staff / delivery headcount | B29: =0 -> 0 | C29: =0 -> 0 | D29: =0 -> 0 | E29: =0 -> 0 | F29: =0 -> 0 | G29: =0 -> 0 | H29: =0 -> 0 | I29: =0 -> 0 | ... L29: =0 -> 0 | M29: =Assumptions!M45 -> 0.08 | N29: =Assumptions!N45 -> 0.078 | O29: =Assumptions!O45 -> 0.076 | P29: =Assumptions!P45 -> 0.075
A30: Subcontractor cost / revenue | B30: =0 -> 0 | C30: =0 -> 0 | D30: =0 -> 0 | E30: =0 -> 0 | F30: =0 -> 0 | G30: =0 -> 0 | H30: =0 -> 0 | I30: =0 -> 0 | ... L30: =0 -> 0 | M30: =Assumptions!M46 -> 0.07 | N30: =Assumptions!N46 -> 0.068 | O30: =Assumptions!O46 -> 0.066 | P30: =Assumptions!P46 -> 0.065
A32: Reference note
A33: BO reference operating metrics | B33: Manpower and IT & Business sheets: offshore/onsite delivery, utilization, support ratio and billing-rate taxonomy
A34: HCLTech source hub | B34: https://www.hcltech.com/investors/results-reports
