Workbook

Sheet Cover
A1: HCLTech Fresh Integrated Financial Model
A2: Fresh-source build | Quarterly P&L FY16–FY26 | Annual three statements FY16–FY30E | INR crore unless stated
A4: Operating model, cash-anchored three statements, client mining, AI revenue and valuation
A6: Model scope | B6: Quarterly P&L only; annual P&L, balance sheet and cash flow
A7: Historical period | B7: FY16–FY26
A8: Forecast period | B8: FY27E–FY30E
A9: Source policy | B9: Official HCLTech results / annual reports; market prices from HCLTECH.NS history
A10: FY16 convention | B10: 12-month comparable P&L; statutory FY16 BS/CFS reflects the 9-month transition year
A11: Cash policy | B11: Historical closing cash is linked to the reported annual balance sheet; differences versus audited CFS cash sit in an explicit basis / FX reconciliation line
A12: Forecast revenue | B12: Core services capacity and pricing, T&M mix / AI deflation, Advanced AI recognized revenue, and HCLSoftware
A13: Billable FTE policy | B13: Historical implied billable FTE only where utilization was reported; later years remain blank rather than invented
A14: Client metric | B14: Revenue per $1m+ client is a proxy; total active client count is not assumed
A15: Formatting | B15: Aptos Narrow 10; reported actuals medium blue; formulas black; forecast columns pale green
A16: Model status | B16: =Checks!B6 -> OK

Sheet Summary
A1: HCLTech Financial Summary
A2: Integrated view of financials, operating drivers, cash generation and valuation
A5: Metric | B5: Units | C5: FY16A | D5: FY17A | E5: FY18A | F5: FY19A | G5: FY20A | H5: FY21A | I5: FY22A | J5: FY23A | K5: FY24A | L5: FY25A | M5: FY26A | N5: FY27E | O5: FY28E | P5: FY29E | Q5: FY30E
A7: Revenue | B7: ₹ cr | C7: ='Annual P&L'!C7 -> 40913 | D7: ='Annual P&L'!D7 -> 46723 | E7: ='Annual P&L'!E7 -> 50570 | F7: ='Annual P&L'!F7 -> 60427 | G7: ='Annual P&L'!G7 -> 70678 | H7: ='Annual P&L'!H7 -> 75379 | I7: ='Annual P&L'!I7 -> 85651 | J7: ='Annual P&L'!J7 -> 101456 | ... Q7: ='Annual P&L'!Q7 -> 175279.02
A8: Revenue growth | B8: % | C8: ='Annual P&L'!C8 -> 0 | D8: ='Annual P&L'!D8 -> 0.14200865 | E8: ='Annual P&L'!E8 -> 0.082336323 | F8: ='Annual P&L'!F8 -> 0.19491794 | G8: ='Annual P&L'!G8 -> 0.16964271 | H8: ='Annual P&L'!H8 -> 0.066512918 | I8: ='Annual P&L'!I8 -> 0.13627138 | J8: ='Annual P&L'!J8 -> 0.18452791 | ... Q8: ='Annual P&L'!Q8 -> 0.081531488
A9: EBITDA | B9: ₹ cr | C9: ='Annual P&L'!C17 -> 8732 | D9: ='Annual P&L'!D17 -> 10309 | E9: ='Annual P&L'!E17 -> 11440 | F9: ='Annual P&L'!F17 -> 13967 | G9: ='Annual P&L'!G17 -> 16694 | H9: ='Annual P&L'!H17 -> 19955 | I9: ='Annual P&L'!I17 -> 20530 | J9: ='Annual P&L'!J17 -> 22628 | ... Q9: ='Annual P&L'!Q17 -> 37684.989
A10: EBITDA margin | B10: % | C10: ='Annual P&L'!C18 -> 0.21342849 | D10: ='Annual P&L'!D18 -> 0.2206408 | E10: ='Annual P&L'!E18 -> 0.22622108 | F10: ='Annual P&L'!F18 -> 0.2311384 | G10: ='Annual P&L'!G18 -> 0.23619797 | H10: ='Annual P&L'!H18 -> 0.2647289 | I10: ='Annual P&L'!I18 -> 0.23969364 | J10: ='Annual P&L'!J18 -> 0.22303264 | ... Q10: ='Annual P&L'!Q18 -> 0.215
A11: EBIT | B11: ₹ cr | C11: ='Annual P&L'!C20 -> 8226 | D11: ='Annual P&L'!D20 -> 9474 | E11: ='Annual P&L'!E20 -> 9987 | F11: ='Annual P&L'!F20 -> 11820 | G11: ='Annual P&L'!G20 -> 13853 | H11: ='Annual P&L'!H20 -> 15344 | I11: ='Annual P&L'!I20 -> 16204 | J11: ='Annual P&L'!J20 -> 18483 | ... Q11: ='Annual P&L'!Q20 -> 32426.619
A12: EBIT margin | B12: % | C12: ='Annual P&L'!C21 -> 0.20106079 | D12: ='Annual P&L'!D21 -> 0.20276951 | E12: ='Annual P&L'!E21 -> 0.19748863 | F12: ='Annual P&L'!F21 -> 0.19560792 | G12: ='Annual P&L'!G21 -> 0.19600158 | H12: ='Annual P&L'!H21 -> 0.20355802 | I12: ='Annual P&L'!I21 -> 0.18918635 | J12: ='Annual P&L'!J21 -> 0.1821775 | ... Q12: ='Annual P&L'!Q21 -> 0.185
A13: Net income | B13: ₹ cr | C13: ='Annual P&L'!C29 -> 7354 | D13: ='Annual P&L'!D29 -> 8457 | E13: ='Annual P&L'!E29 -> 8780 | F13: ='Annual P&L'!F29 -> 10123 | G13: ='Annual P&L'!G29 -> 11062 | H13: ='Annual P&L'!H29 -> 11145 | I13: ='Annual P&L'!I29 -> 13499 | J13: ='Annual P&L'!J29 -> 14851 | ... Q13: ='Annual P&L'!Q29 -> 25300.616
A14: Net margin | B14: % | C14: ='Annual P&L'!C30 -> 0.17974727 | D14: ='Annual P&L'!D30 -> 0.18100293 | E14: ='Annual P&L'!E30 -> 0.17362072 | F14: ='Annual P&L'!F30 -> 0.16752445 | G14: ='Annual P&L'!G30 -> 0.15651263 | H14: ='Annual P&L'!H30 -> 0.14785285 | I14: ='Annual P&L'!I30 -> 0.1576047 | J14: ='Annual P&L'!J30 -> 0.14637873 | ... Q14: ='Annual P&L'!Q30 -> 0.14434481
A15: Diluted EPS | B15: ₹ / share | C15: ='Annual P&L'!C34 -> 27.084561 | D15: ='Annual P&L'!D34 -> 31.146877 | E15: ='Annual P&L'!E34 -> 32.336476 | F15: ='Annual P&L'!F34 -> 37.282705 | G15: ='Annual P&L'!G34 -> 40.741014 | H15: ='Annual P&L'!H34 -> 41.0467 | I15: ='Annual P&L'!I34 -> 49.716411 | J15: ='Annual P&L'!J34 -> 54.695787 | ... Q15: ='Annual P&L'!Q34 -> 93.18141
A16: CFO | B16: ₹ cr | C16: ='Annual Cash Flow'!C15 -> 3823 | D16: ='Annual Cash Flow'!D15 -> 8995 | E16: ='Annual Cash Flow'!E15 -> 8328 | F16: ='Annual Cash Flow'!F15 -> 8971 | G16: ='Annual Cash Flow'!G15 -> 13359 | H16: ='Annual Cash Flow'!H15 -> 19618 | I16: ='Annual Cash Flow'!I15 -> 16900 | J16: ='Annual Cash Flow'!J15 -> 18009 | ... Q16: ='Annual Cash Flow'!Q15 -> 29887.889
A17: FCF | B17: ₹ cr | C17: ='Annual Cash Flow'!C38 -> 2881 | D17: ='Annual Cash Flow'!D38 -> 5073 | E17: ='Annual Cash Flow'!E38 -> 3007 | F17: ='Annual Cash Flow'!F38 -> 5537 | G17: ='Annual Cash Flow'!G38 -> 11493 | H17: ='Annual Cash Flow'!H38 -> 17714 | I17: ='Annual Cash Flow'!I38 -> 15255 | J17: ='Annual Cash Flow'!J38 -> 16348 | ... Q17: ='Annual Cash Flow'!Q38 -> 27433.982
A18: Closing cash | B18: ₹ cr | C18: ='Annual Balance Sheet'!C7 -> 729.3 | D18: ='Annual Balance Sheet'!D7 -> 1316.5 | E18: ='Annual Balance Sheet'!E7 -> 1693.9 | F18: ='Annual Balance Sheet'!F7 -> 5929 | G18: ='Annual Balance Sheet'!G7 -> 4843 | H18: ='Annual Balance Sheet'!H7 -> 6515 | I18: ='Annual Balance Sheet'!I7 -> 10510 | J18: ='Annual Balance Sheet'!J7 -> 9065 | ... Q18: ='Annual Balance Sheet'!Q7 -> 16169.033
A19: Net cash / (debt) | B19: ₹ cr | C19: ='Annual Balance Sheet'!C34 -> -243.9 | D19: ='Annual Balance Sheet'!D34 -> 774.8 | E19: ='Annual Balance Sheet'!E34 -> 1256.8 | F19: ='Annual Balance Sheet'!F34 -> 1943 | G19: ='Annual Balance Sheet'!G34 -> -249 | H19: ='Annual Balance Sheet'!H34 -> 2608 | I19: ='Annual Balance Sheet'!I34 -> 6525 | J19: ='Annual Balance Sheet'!J34 -> 6814 | ... Q19: ='Annual Balance Sheet'!Q34 -> 16169.033
A20: Total headcount | B20: # | C20: ='Revenue Drivers'!C6 -> 104896 | D20: ='Revenue Drivers'!D6 -> 115973 | E20: ='Revenue Drivers'!E6 -> 120081 | F20: ='Revenue Drivers'!F6 -> 137965 | G20: ='Revenue Drivers'!G6 -> 150423 | H20: ='Revenue Drivers'!H6 -> 168977 | I20: ='Revenue Drivers'!I6 -> 208877 | J20: ='Revenue Drivers'!J6 -> 225944 | ... Q20: ='Revenue Drivers'!Q6 -> 261948.71
A21: Billable FTE | B21: # | C21: ='Revenue Drivers'!C11 -> 81875.544 | D21: ='Revenue Drivers'!D11 -> 90453.779 | E21: ='Revenue Drivers'!E11 -> 94116.335 | F21: ='Revenue Drivers'!F11 -> 108216.32 | G21: ='Revenue Drivers'!G11 -> 0 | H21: ='Revenue Drivers'!H11 -> 0 | I21: ='Revenue Drivers'!I11 -> 0 | J21: ='Revenue Drivers'!J11 -> 0 | ... Q21: ='Revenue Drivers'!Q11 -> 209297.02
A22: Advanced AI recognized revenue / FY26 run-rate proxy | B22: $m | C22: ='Revenue Drivers'!C21 -> 0 | D22: ='Revenue Drivers'!D21 -> 0 | E22: ='Revenue Drivers'!E21 -> 0 | F22: ='Revenue Drivers'!F21 -> 0 | G22: ='Revenue Drivers'!G21 -> 0 | H22: ='Revenue Drivers'!H21 -> 0 | I22: ='Revenue Drivers'!I21 -> 0 | J22: ='Revenue Drivers'!J21 -> 0 | ... Q22: ='Revenue Drivers'!Q21 -> 1049.8488
A23: TCV | B23: $m | C23: ='Client Data'!C21 -> 0 | D23: ='Client Data'!D21 -> 0 | E23: ='Client Data'!E21 -> 0 | F23: ='Client Data'!F21 -> 0 | G23: ='Client Data'!G21 -> 0 | H23: ='Client Data'!H21 -> 7300 | I23: ='Client Data'!I21 -> 8308 | J23: ='Client Data'!J21 -> 8850 | ... Q23: ='Client Data'!Q21 -> 12556.294
A24: Revenue / $1m+ client proxy | B24: $m | C24: ='Client Data'!C19 -> 12.936515 | D24: ='Client Data'!D19 -> 13.903162 | E24: ='Client Data'!E19 -> 13.97148 | F24: ='Client Data'!F19 -> 13.855538 | G24: ='Client Data'!G19 -> 12.561315 | H24: ='Client Data'!H19 -> 12.577256 | I24: ='Client Data'!I19 -> 13.017007 | J24: ='Client Data'!J19 -> 13.453674 | ... Q24: ='Client Data'!Q19 -> 13.611579
A25: Share price / implied target | B25: ₹ / share | C25: =Valuation!C7 -> 407.04999 | D25: =Valuation!D7 -> 437.375 | E25: =Valuation!E7 -> 484.29999 | F25: =Valuation!F7 -> 541.45001 | G25: =Valuation!G7 -> 436.39999 | H25: =Valuation!H7 -> 982.65002 | I25: =Valuation!I7 -> 1163.75 | J25: =Valuation!J7 -> 1085.25 | ... Q25: =Valuation!Q7 -> 1956.8096
A26: P/E | B26: x | C26: =Valuation!C13 -> 15.028857 | D26: =Valuation!D13 -> 14.042339 | E26: =Valuation!E13 -> 14.976894 | F26: =Valuation!F13 -> 14.52282 | G26: =Valuation!G13 -> 10.711564 | H26: =Valuation!H13 -> 23.939806 | I26: =Valuation!I13 -> 23.407764 | J26: =Valuation!J13 -> 19.841565 | ... Q26: =Valuation!Q13 -> 21
A27: EV / EBITDA | B27: x | C27: =Valuation!C14 -> 11.404198 | D27: =Valuation!D14 -> 10.335663 | E27: =Valuation!E14 -> 10.671669 | F27: =Valuation!F14 -> 9.9898539 | G27: =Valuation!G14 -> 6.4780679 | H27: =Valuation!H14 -> 12.532134 | I27: =Valuation!I14 -> 14.510903 | J27: =Valuation!J14 -> 12.110805 | ... Q27: =Valuation!Q14 -> 12.847995
A28: Dividend yield | B28: % | C28: =Valuation!C17 -> 0.024415823 | D28: =Valuation!D17 -> 0.034274029 | E28: =Valuation!E17 -> 0.015453741 | F28: =Valuation!F17 -> 0.0089904745 | G28: =Valuation!G17 -> 0.013721664 | H28: =Valuation!H17 -> 0.012210226 | I28: =Valuation!I17 -> 0.036063184 | J28: =Valuation!J17 -> 0.044124994 | ... Q28: =Valuation!Q17 -> 0.042880832

Sheet Sources
A1: Sources & Data Conventions
A2: Primary-source register and transparent treatment of unavailable disclosures
A5: ID | B5: Data / Period | C5: Units | D5: Primary source | E5: Use in model | F5: Status | G5: Notes
A6: S1 | B6: Quarterly / annual investor releases FY16–FY26 | C6: ₹ cr / $m | D6: https://www.hcltech.com/en-us/investor-relations/financial-results | E6: Quarterly P&L, management P&L, segments, clients, AI, headcount | F6: Loaded | G6: Official company archive
A7: S2 | B7: Annual reports FY16–FY26 | C7: ₹ cr | D7: https://www.hcltech.com/en-us/investor-relations/annual-report | E7: Audited CFS controls and accounting cross-checks | F7: Loaded | G7: FY16 was a 9-month statutory transition period
A8: S3 | B8: FY26 Q4 investor release | C8: ₹ cr / $m | D8: https://www.hcltech.com/sites/default/files/document/open/quarter-results/2026-04/hcltech-q4-fy26-investor-release.pdf | E8: FY26 P&L, BS, CFS, AI, segments and clients | F8: Loaded | G8: Advanced AI Q4 recognized revenue $155m; exit annualized revenue $620m
A9: S4 | B9: FY26 annual report | C9: ₹ cr | D9: https://www.hcltech.com/sites/default/files/document/open/annual-report/2026-07/AGM-Notice-Annual-Report-FY-2025-26.pdf | E9: Audited FY26 cash flow and balances | F9: Loaded | G9: CFS ending cash differs from investor-release BS cash; explicit reconciliation retained
A10: S5 | B10: HCLTECH.NS price history | C10: ₹ / share | D10: https://query1.finance.yahoo.com/v8/finance/chart/HCLTECH.NS | E10: Daily prices and FY-end share prices | F10: Loaded | G10: Market-price source only; no valuation opinions fetched
A11: S6 | B11: Advanced AI Q1 FY27 update | C11: $m | D11: https://www.hcltech.com/en-us/investor-relations/financial-results | E11: Q1 FY27 recognized AI revenue | F11: Loaded | G11: $171m reported
A12: S7 | B12: FY17–FY23 quarterly investor releases | C12: % / # | D12: https://www.hcltech.com/en-us/investor-relations/financial-results | E12: Historical vertical, geography, contract mix, client bands and FY23 quarterly P&L | F12: Loaded | G12: Annual operating mix loaded only where disclosed; recast quarter lines may differ modestly from annual controls
A13: S8 | B13: FY17–FY26 annual reports | C13: ₹ cr / % | D13: https://www.hcltech.com/en-us/investor-relations/annual-report | E13: Audited cash flows, segment restatements and financial controls | F13: Loaded | G13: Gross cash capex and acquisition lines retained separately from total CFI
A14: S9 | B14: FY23 large-deal announcement | C14: $m | D14: https://www.hcltech.com/en-us/press-releases/hcltech-delivers-another-year-stellar-growth-robust-deal-pipeline | E14: FY23 new-deal TCV | F14: Loaded | G14: $8.85bn
A15: S10 | B15: Unavailable disclosures | C15: n/a | D15: n/a | E15: Blanks retained | F15: Policy | G15: No total active clients and no utilization / billable FTE reported after FY19; FY20 annual operational mix not disclosed

Sheet Assumptions
A1: Forecast Assumptions
A2: Blue text on yellow = editable forecast input; all forecast outputs are formula-linked
A5: Driver | B5: Units | C5: FY27E | D5: FY28E | E5: FY29E | F5: FY30E
A6: Total headcount growth | B6: % | C6: 0.03 | D6: 0.035 | E6: 0.04 | F6: 0.04
A7: Service employee share | B7: % | C7: 0.94 | D7: 0.94 | E7: 0.94 | F7: 0.94
A8: Blended utilization / billable rate | B8: % | C8: 0.84 | D8: 0.845 | E8: 0.85 | F8: 0.85
A9: Revenue per billable FTE pricing / productivity | B9: % | C9: 0.03 | D9: 0.035 | E9: 0.04 | F9: 0.04
A10: T&M mix | B10: % | C10: 0.34 | D10: 0.33 | E10: 0.32 | F10: 0.31
A11: AI deflation on T&M revenue | B11: % | C11: 0.01 | D11: 0.013 | E11: 0.015 | F11: 0.015
A12: Advanced AI recognized revenue growth | B12: % | D12: 0.15 | E12: 0.12 | F12: 0.1
A13: HCLSoftware revenue growth | B13: % | C13: 0.04 | D13: 0.05 | E13: 0.06 | F13: 0.06
A14: USD / INR average | B14: ₹ / $ | C14: 95 | D14: 96 | E14: 97 | F14: 98
A15: Gross margin | B15: % | C15: 0.342 | D15: 0.344 | E15: 0.346 | F15: 0.347
A16: R&D / revenue | B16: % | C16: 0.015 | D16: 0.015 | E16: 0.015 | F16: 0.015
A17: D&A / revenue | B17: % | C17: 0.033 | D17: 0.032 | E17: 0.031 | F17: 0.03
A18: EBIT margin | B18: % | C18: 0.18 | D18: 0.182 | E18: 0.184 | F18: 0.185
A19: Effective tax rate | B19: % | C19: 0.25 | D19: 0.25 | E19: 0.25 | F19: 0.25
A20: Other income yield on cash + investments | B20: % | C20: 0.03 | D20: 0.03 | E20: 0.03 | F20: 0.03
A21: Receivable days | B21: days | C21: 64 | D21: 63 | E21: 62 | F21: 61
A22: Unbilled days | B22: days | C22: 22 | D22: 22 | E22: 21 | F22: 21
A23: Other current assets / revenue | B23: % | C23: 0.058 | D23: 0.057 | E23: 0.056 | F23: 0.055
A24: Current operating liabilities / revenue | B24: % | C24: 0.225 | D24: 0.223 | E24: 0.221 | F24: 0.22
... A39: LTM attrition | B39: % | C39: 0.125 | D39: 0.123 | E39: 0.12 | F39: 0.12
A40: Advanced AI recognized revenue | B40: $m | C40: 741

Sheet Raw Financials
A1: Raw Reported Financials — Source Layer
A2: Hardcoded reported inputs only; actual values in medium blue; calculations live in downstream tabs
A4: Annual reported financials (INR crore unless stated)
A5: Metric | B5: Units | C5: FY16A | D5: FY17A | E5: FY18A | F5: FY19A | G5: FY20A | H5: FY21A | I5: FY22A | J5: FY23A | K5: FY24A | L5: FY25A | M5: FY26A
A6: Revenue | B6: ₹ cr | C6: 40913 | D6: 46723 | E6: 50570 | F6: 60427 | G6: 70678 | H6: 75379 | I6: 85651 | J6: 101456 | K6: 109913 | L6: 117055 | M6: 130144
A7: Direct costs | B7: ₹ cr | C7: 26901 | D7: 30890 | E7: 33237 | F7: 39268 | G7: 44018 | H7: 44591 | I7: 52760 | J7: 64523 | K7: 70474 | L7: 76157 | M7: 85811
A8: Reported gross profit | B8: ₹ cr | C8: 14012 | D8: 15833 | E8: 17333 | F8: 21159 | G8: 26659 | H8: 30788 | I8: 32891 | J8: 36933 | K8: 39439 | L8: 40898 | M8: 44333
A9: R&D | B9: ₹ cr | G9: 1276 | H9: 1383 | I9: 1526 | J9: 1632 | K9: 1651 | L9: 1658 | M9: 2000
A10: SG&A | B10: ₹ cr | C10: 5217 | D10: 5524 | E10: 5894 | F10: 7191 | G10: 8690 | H10: 9348 | I10: 10835 | J10: 12673 | K10: 13588 | L10: 13736 | M10: 15581
A11: Reported EBITDA | B11: ₹ cr | C11: 8795 | D11: 10309 | E11: 11440 | F11: 13967 | G11: 16694 | H11: 20057 | I11: 20530 | J11: 22628 | K11: 24200 | L11: 25504 | M11: 26752
A12: D&A | B12: ₹ cr | C12: 506 | D12: 835 | E12: 1453 | F12: 2147 | G12: 2841 | H12: 4611 | I12: 4326 | J12: 4145 | K12: 4173 | L12: 4084 | M12: 4355
A13: EBIT | B13: ₹ cr | C13: 8226 | D13: 9474 | E13: 9987 | F13: 11820 | G13: 13853 | H13: 15344 | I13: 16204 | J13: 18483 | K13: 20027 | L13: 21420 | M13: 22397
A14: FX gain / (loss) | B14: ₹ cr | C14: 72 | D14: 188 | E14: 541 | F14: 182 | G14: -15 | H14: 46 | I14: 328 | J14: 91 | K14: -2 | L14: 86 | M14: -241
A15: Other income, net | B15: ₹ cr | C15: 937 | D15: 746 | E15: 570 | F15: 623 | G15: 193 | H15: 463 | I15: 419 | J15: 914 | K15: 942 | L15: 1755 | M15: 902
A16: Tax | B16: ₹ cr | C16: 1883 | D16: 1952 | E16: 2316 | F16: 2481 | G16: 2938 | H16: 4684 | I16: 3428 | J16: 4643 | K16: 5257 | L16: 5862 | M16: 5687
A17: NCI / other attribution | B17: ₹ cr | G17: 31 | H17: 24 | I17: 24 | J17: -6 | K17: 8 | L17: 9
A18: Net income attributable | B18: ₹ cr | C18: 7354 | D18: 8457 | E18: 8780 | F18: 10123 | G18: 11062 | H18: 11145 | I18: 13499 | J18: 14851 | K18: 15702 | L18: 17390 | M18: 17361
A19: USD revenue | B19: $m | C19: 6235.4 | D19: 7035 | E19: 7838 | F19: 8632 | G19: 9936 | H19: 10175 | I19: 11481 | J19: 12633 | K19: 13269 | L19: 13840 | M19: 14664
A20: Headcount | B20: # | C20: 104896 | D20: 115973 | E20: 120081 | F20: 137965 | G20: 150423 | H20: 168977 | I20: 208877 | J20: 225944 | K20: 227481 | L20: 223420 | M20: 227181
A21: Reported utilization | B21: % | C21: 0.856 | D21: 0.857 | E21: 0.859 | F21: 0.854
A22: TCV | B22: $m | H22: 7300 | I22: 8308 | J22: 8850 | K22: 9759 | L22: 9268 | M22: 9323
A23: Cash flow from operations | B23: ₹ cr | C23: 3823 | D23: 8995 | E23: 8328 | F23: 8971 | G23: 13359 | H23: 19618 | I23: 16900 | J23: 18009 | K23: 22448 | L23: 22261 | M23: 19975
A24: Cash flow from investing | B24: ₹ cr | C24: -2189 | D24: -3817 | E24: -2283 | F24: -3073 | G24: -12374 | H24: -5730 | I24: 1477 | J24: -3931 | K24: -6723 | L24: -4914 | M24: -1473
A25: Cash flow from financing | B25: ₹ cr | C25: -2237 | D25: -4533 | E25: -5714 | F25: -1462 | G25: -3168 | H25: -11192 | I25: -14508 | J25: -15881 | K25: -15464 | L25: -18561 | M25: -19369
A26: Cash dividends paid | B26: ₹ cr | C26: -2697 | D26: -4068 | E26: -2031 | F26: -1321 | G26: -1625 | H26: -3256 | I26: -11389 | J26: -12995 | K26: -14073 | L26: -16250 | M26: -14618
A27: Capex | B27: ₹ cr | C27: -942 | D27: -3922 | E27: -5321 | F27: -3434 | G27: -1866 | H27: -1904 | I27: -1645 | J27: -1661 | K27: -1048 | L27: -1108 | M27: -1422
A28: Acquisitions / cash acquired | B28: ₹ cr | C28: -1183 | D28: -488 | E28: -107 | F28: -2828 | G28: -6091 | H28: -1211 | I28: 40 | J28: -738 | K28: -2048 | L28: -2032 | M28: -160
A29: Cash & equivalents | B29: ₹ cr | C29: 729.3 | D29: 1316.5 | E29: 1693.9 | F29: 5929 | G29: 4843 | H29: 6515 | I29: 10510 | J29: 9065 | K29: 9456 | L29: 8245 | M29: 8265
A30: Receivables | B30: ₹ cr | C30: 7721.3 | D30: 8301.4 | E30: 9639.4 | F30: 11706 | G30: 14134 | H30: 13663 | I30: 15476 | J30: 19572 | K30: 19483 | L30: 19523 | M30: 23585
A31: Unbilled receivables | B31: ₹ cr | C31: 3001.5 | D31: 2501.2 | E31: 2618.1 | G31: 3638 | H31: 3862 | I31: 5195 | J31: 5934 | K31: 6038 | L31: 6319 | M31: 7956
A32: Treasury / current investments | B32: ₹ cr | C32: 11123.6 | D32: 11365.3 | E32: 8083.8 | F32: 5462 | G32: 10530 | H32: 13975 | I32: 11373 | J32: 13647 | K32: 18532 | L32: 21493 | M32: 23136
A33: Other current assets | B33: ₹ cr | C33: 2410.3 | D33: 2983.2 | E33: 2519.8 | F33: 3716 | G33: 5188 | H33: 4943 | I33: 5326 | J33: 5359 | K33: 5822 | L33: 6529 | M33: 7600
A34: Total current assets | B34: ₹ cr | C34: 24985.9 | D34: 26467.6 | E34: 24555 | F34: 29717 | G34: 38425 | H34: 43052 | I34: 48041 | J34: 53577 | K34: 59331 | L34: 62109 | M34: 70542
A35: PPE | B35: ₹ cr | C35: 4323.1 | D35: 4680.6 | E35: 5184.7 | F35: 5801 | G35: 6244 | H35: 6245 | I35: 5741 | J35: 5411 | K35: 4999 | L35: 4560 | M35: 4717
A36: ROU assets | B36: ₹ cr | I36: 2305 | J36: 2337 | K36: 2910 | L36: 3016 | M36: 3592
A37: Goodwill & intangibles | B37: ₹ cr | C37: 6419.4 | D37: 7358.3 | E37: 14405.7 | F37: 17695 | G37: 29421 | H37: 29150 | I37: 27160 | J37: 26911 | K37: 27262 | L37: 28655 | M37: 29130
A38: Other non-current assets reported | B38: ₹ cr | C38: 3878.9 | D38: 3711.8 | E38: 3767.5 | F38: 5293 | G38: 4149 | H38: 4389 | I38: 4298 | J38: 3435 | K38: 3863 | L38: 4843 | M38: 4955
A39: Total assets | B39: ₹ cr | C39: 39767.3 | D39: 46432.3 | E39: 48435.1 | F39: 58897 | G39: 83216 | H39: 87702 | I39: 89033 | J39: 93411 | K39: 99777 | L39: 105544 | M39: 116258
A40: Current operating liabilities | B40: ₹ cr | C40: 9508.5 | D40: 11147.7 | E40: 9914.3 | F40: 11148 | G40: 20889 | H40: 16755 | I40: 18014 | J40: 20420 | K40: 21532 | L40: 24471 | M40: 29828
A41: Short-term borrowings | B41: ₹ cr
A42: Long-term borrowings | B42: ₹ cr
A43: Borrowings — split not reported | B43: ₹ cr | C43: 973.2 | D43: 541.7 | E43: 437.1 | F43: 3986 | G43: 5092 | H43: 3907 | I43: 3985 | J43: 2251 | K43: 2327 | L43: 2291 | M43: 159
A44: Lease liabilities | B44: ₹ cr | I44: 2358 | J44: 2535 | K44: 3429 | L44: 3985 | M44: 5056
A45: Other non-current liabilities | B45: ₹ cr | C45: 1263.5 | D45: 1252.5 | E45: 1266.9 | F45: 1538 | G45: 2548 | H45: 2683 | I45: 2670 | J45: 2807 | K45: 4218 | L45: 5124 | M45: 6018
A46: Total liabilities | B46: ₹ cr | C46: 11745.2 | D46: 12941.9 | E46: 11618.3 | F46: 16672 | G46: 31002 | H46: 25612 | I46: 27027 | J46: 28013 | K46: 31506 | L46: 35871 | M46: 41061
A47: Share capital | B47: ₹ cr
A48: Stockholders equity | B48: ₹ cr | C48: 28022.1 | D48: 33490.4 | E48: 36816.8 | F48: 41770 | G48: 51686 | H48: 61506 | I48: 61914 | J48: 65405 | K48: 68263 | L48: 69655 | M48: 75165
A49: Total liabilities & equity | B49: ₹ cr | C49: 39767.3 | D49: 46432.3 | E49: 48435.1 | J49: 93411 | K49: 99777 | L49: 105544 | M49: 116258
A50: Technical employees | B50: # | C50: 95649 | D50: 105547 | E50: 109565 | F50: 126717 | G50: 139302 | H50: 156580 | I50: 195195 | J50: 211445 | K50: 213059 | L50: 209182 | M50: 212779
A51: LTM attrition | B51: % | C51: 0.173 | D51: 0.169 | E51: 0.155 | F51: 0.177 | G51: 0.163 | H51: 0.099 | I51: 0.219 | J51: 0.195 | K51: 0.124 | L51: 0.13 | M51: 0.125
A52: T&M mix | B52: % | D52: 0.382 | E52: 0.393 | F52: 0.373 | H52: 0.324 | I52: 0.35
A53: Managed / fixed-price mix | B53: % | D53: 0.618 | E53: 0.607 | F53: 0.627 | H53: 0.676 | I53: 0.65
A54: Quarterly reported P&L — 12-month comparable basis for FY16
A55: Metric | B55: Units | C55: Q1 FY16A | D55: Q2 FY16A | E55: Q3 FY16A | F55: Q4 FY16A | G55: Q1 FY17A | H55: Q2 FY17A | I55: Q3 FY17A | J55: Q4 FY17A | K55: Q1 FY18A | L55: Q2 FY18A | M55: Q3 FY18A | N55: Q4 FY18A | O55: Q1 FY19A | P55: Q2 FY19A | Q55: Q3 FY19A | R55: Q4 FY19A | S55: Q1 FY20A | T55: Q2 FY20A | U55: Q3 FY20A | V55: Q4 FY20A | W55: Q1 FY21A | X55: Q2 FY21A | Y55: Q3 FY21A | Z55: Q4 FY21A | AA55: Q1 FY22A | AB55: Q2 FY22A | AC55: Q3 FY22A | AD55: Q4 FY22A | AE55: Q1 FY23A | AF55: Q2 FY23A | AG55: Q3 FY23A | AH55: Q4 FY23A | AI55: Q1 FY24A | AJ55: Q2 FY24A | AK55: Q3 FY24A | AL55: Q4 FY24A | AM55: Q1 FY25A | AN55: Q2 FY25A | AO55: Q3 FY25A | AP55: Q4 FY25A | AQ55: Q1 FY26A | AR55: Q2 FY26A | AS55: Q3 FY26A | AT55: Q4 FY26A
A56: Revenue | B56: ₹ cr | C56: 9777 | D56: 10097 | E56: 10341 | F56: 10698 | G56: 11336 | H56: 11519 | I56: 11814 | J56: 12053 | K56: 12149 | L56: 12434 | M56: 12808 | N56: 13179 | O56: 13878 | P56: 14861 | Q56: 15699 | R56: 15990 | S56: 16425 | T56: 17528 | U56: 18135 | V56: 18590 | W56: 17841 | X56: 18594 | Y56: 19302 | Z56: 19642 | AA56: 20068 | AB56: 20655 | AC56: 22331 | AD56: 22597 | AE56: 23464 | AF56: 24686 | AG56: 26700 | AH56: 26606 | AI56: 26296 | AJ56: 26672 | AK56: 28446 | AL56: 28499 | AM56: 28057 | AN56: 28862 | AO56: 29890 | AP56: 30246 | AQ56: 30349 | AR56: 31942 | AS56: 33872 | AT56: 33981
A57: Direct costs | B57: ₹ cr | C57: 6430 | D57: 6742 | E57: 6768 | F57: 6961 | G57: 7440 | H57: 7653 | I57: 7809 | J57: 7987 | K57: 8057 | L57: 8208 | M57: 8412 | N57: 8560 | O57: 9106 | P57: 9589 | Q57: 10152 | R57: 10421 | S57: 10631 | T57: 11061 | U57: 11176 | V57: 11151 | W57: 10728 | X57: 10929 | Y57: 11195 | Z57: 11740 | AA57: 12197 | AB57: 12758 | AC57: 13798 | AD57: 14292 | AE57: 15066 | AF57: 15848 | AG57: 16720 | AH57: 16889 | AI57: 16936 | AJ57: 17013 | AK57: 17998 | AL57: 18527 | AM57: 18364 | AN57: 18789 | AO57: 19262 | AP57: 19742 | AQ57: 20128 | AR57: 21044 | AS57: 22102 | AT57: 22537
A58: Gross profit | B58: ₹ cr | C58: 3347 | D58: 3355 | E58: 3573 | F58: 3737 | G58: 3896 | H58: 3866 | I58: 4005 | J58: 4066 | K58: 4092 | L58: 4226 | M58: 4397 | N58: 4618 | O58: 4771 | P58: 5272 | Q58: 5547 | R58: 5568 | S58: 5794 | T58: 6467 | U58: 6959 | V58: 7439 | W58: 7113 | X58: 7665 | Y58: 8108 | Z58: 7902 | AA58: 7871 | AB58: 7897 | AC58: 8533 | AD58: 8305 | AE58: 8398 | AF58: 8837 | AG58: 9980 | AH58: 9717 | AI58: 9360 | AJ58: 9659 | AK58: 10448 | AL58: 9972 | AM58: 9692 | AN58: 10074 | AO58: 10628 | AP58: 10504 | AQ58: 10221 | AR58: 10898 | AS58: 11770 | AT58: 11444
A59: R&D | B59: ₹ cr | S59: 289 | T59: 325 | U59: 334 | V59: 328 | W59: 342 | X59: 350 | Y59: 356 | Z59: 335 | AA59: 396 | AB59: 369 | AC59: 381 | AD59: 380 | AE59: 391 | AF59: 388 | AG59: 415 | AH59: 438 | AI59: 394 | AJ59: 404 | AK59: 418 | AL59: 435 | AM59: 407 | AN59: 395 | AO59: 399 | AP59: 457 | AQ59: 455 | AR59: 494 | AS59: 521 | AT59: 530
A60: SG&A | B60: ₹ cr | C60: 1248 | D60: 1263 | E60: 1348 | F60: 1358 | G60: 1375 | H60: 1355 | I60: 1377 | J60: 1417 | K60: 1411 | L60: 1467 | M60: 1432 | N60: 1583 | O60: 1546 | P60: 1773 | Q60: 1900 | R60: 1972 | S60: 2105 | T60: 2039 | U60: 2155 | V60: 2391 | W60: 2205 | X60: 2364 | Y60: 2309 | Z60: 2470 | AA60: 2567 | AB60: 2690 | AC60: 2759 | AD60: 2872 | AE60: 3032 | AF60: 3024 | AG60: 3200 | AH60: 3416 | AI60: 3579 | AJ60: 3311 | AK60: 3272 | AL60: 3426 | AM60: 3492 | AN60: 3309 | AO60: 3369 | AP60: 3565 | AQ60: 3731 | AR60: 3811 | AS60: 3837 | AT60: 4202
A61: EBITDA | B61: ₹ cr | C61: 2100 | D61: 2092 | E61: 2225 | F61: 2378 | G61: 2521 | H61: 2511 | I61: 2628 | J61: 2649 | K61: 2681 | L61: 2759 | M61: 2964 | N61: 3036 | O61: 3225 | P61: 3499 | Q61: 3647 | R61: 3596 | S61: 3401 | T61: 4103 | U61: 4470 | V61: 4720 | W61: 4566 | X61: 4951 | Y61: 5443 | Z61: 5097 | AA61: 4908 | AB61: 4838 | AC61: 5393 | AD61: 5053 | AE61: 4975 | AF61: 5425 | AG61: 6365 | AH61: 5863 | AI61: 5387 | AJ61: 5944 | AK61: 6758 | AL61: 6111 | AM61: 5793 | AN61: 6369 | AO61: 6860 | AP61: 6482 | AQ61: 6035 | AR61: 6593 | AS61: 7412 | AT61: 6712
A62: D&A | B62: ₹ cr | C62: 111 | D62: 122 | E62: 134 | F62: 139 | G62: 169 | H62: 172 | I62: 220 | J62: 233 | K62: 236 | L62: 308 | M62: 455 | N62: 453 | O62: 496 | P62: 533 | Q62: 561 | R62: 558 | S62: 595 | T62: 606 | U62: 800 | V62: 839 | W62: 906 | X62: 935 | Y62: 1027 | Z62: 1117 | AA62: 977 | AB62: 922 | AC62: 1136 | AD62: 984 | AE62: 983 | AF62: 998 | AG62: 1136 | AH62: 1027 | AI62: 927 | AJ62: 1010 | AK62: 1143 | AL62: 1093 | AM62: 998 | AN62: 1007 | AO62: 1039 | AP62: 1040 | AQ62: 1093 | AR62: 1043 | AS62: 1127 | AT62: 1092
A63: EBIT | B63: ₹ cr | C63: 1975 | D63: 1957 | E63: 2072 | F63: 2222 | G63: 2333 | H63: 2318 | I63: 2408 | J63: 2416 | K63: 2444 | L63: 2451 | M63: 2510 | N63: 2583 | O63: 2729 | P63: 2966 | Q63: 3086 | R63: 3039 | S63: 2806 | T63: 3497 | U63: 3670 | V63: 3881 | W63: 3660 | X63: 4016 | Y63: 4416 | Z63: 3252 | AA63: 3931 | AB63: 3916 | AC63: 4257 | AD63: 4069 | AE63: 3992 | AF63: 4427 | AG63: 5228 | AH63: 4862 | AI63: 4460 | AJ63: 4934 | AK63: 5615 | AL63: 5018 | AM63: 4795 | AN63: 5362 | AO63: 5821 | AP63: 5442 | AQ63: 4942 | AR63: 5550 | AS63: 6285 | AT63: 5620
A64: FX gain / (loss) | B64: ₹ cr | C64: 36 | D64: 22 | E64: 11 | F64: 3 | G64: 66 | H64: 31 | I64: 43 | J64: 48 | K64: 107 | L64: 144 | M64: 129 | N64: 161 | O64: 143 | P64: 69 | Q64: -54 | R64: 23 | S64: 19 | T64: -10 | U64: 13 | V64: -36 | W64: 0 | X64: -3 | Y64: 2 | Z64: 47 | AA64: 41 | AB64: 79 | AC64: 73 | AD64: 135 | AE64: 82 | AF64: 46 | AG64: 3 | AH64: -40 | AI64: -22 | AJ64: -15 | AK64: 29 | AL64: 6 | AM64: 81 | AN64: 3 | AO64: 7 | AP64: -5 | AQ64: 5 | AR64: -53 | AS64: -65 | AT64: -128
A65: Other income, net | B65: ₹ cr | C65: 177 | D65: 219 | E65: 344 | F65: 197 | G65: 187 | H65: 204 | I65: 188 | J65: 167 | K65: 162 | L65: 154 | M65: 135 | N65: 119 | O65: 153 | P65: 183 | Q65: 159 | R65: 129 | S65: 109 | T65: 7 | U65: 54 | V65: 23 | W65: 205 | X65: 139 | Y65: 124 | Z65: 143 | AA65: 153 | AB65: 128 | AC65: 100 | AD65: 117 | AE65: 263 | AF65: 111 | AG65: 141 | AH65: 397 | AI65: 258 | AJ65: 209 | AK65: 230 | AL65: 245 | AM65: 831 | AN65: 322 | AO65: 304 | AP65: 298 | AQ65: 242 | AR65: 205 | AS65: 245 | AT65: 210
A66: Tax | B66: ₹ cr | C66: 406 | D66: 472 | E66: 508 | F66: 497 | G66: 543 | H66: 538 | I66: 568 | J66: 303 | K66: 543 | L66: 561 | M66: 579 | N66: 634 | O66: 622 | P66: 678 | Q66: 566 | R66: 615 | S66: 705 | T66: 835 | U66: 691 | V66: 707 | W66: 929 | X66: 999 | Y66: 544 | Z66: 1191 | AA66: 894 | AB66: 846 | AC66: 982 | AD66: 721 | AE66: 1056 | AF66: 1096 | AG66: 1276 | AH66: 1214 | AI66: 1165 | AJ66: 1295 | AK66: 1523 | AL66: 1274 | AM66: 1448 | AN66: 1450 | AO66: 1538 | AP66: 1426 | AQ66: 1345 | AR66: 1466 | AS66: 1664 | AT66: 1212
A67: NCI / other attribution | B67: ₹ cr | S67: 8 | T67: 2540 | U67: 8 | V67: 8 | W67: 13 | X67: 11 | Y67: 16 | Z67: 17 | AA67: 16 | AB67: 13 | AC67: 6 | AD67: 6 | AE67: -2 | AF67: -1 | AG67: 0 | AH67: -2 | AI67: -3 | AJ67: 1 | AK67: 1 | AL67: 9 | AM67: 2 | AN67: 2 | AO67: 3 | AP67: 2 | AQ67: 1 | AR67: 1 | AS67: 6 | AT67: 2
A68: Net income attributable | B68: ₹ cr | C68: 1782 | D68: 1726 | E68: 1920 | F68: 1926 | G68: 2047 | H68: 2014 | I68: 2070 | J68: 2325 | K68: 2171 | L68: 2188 | M68: 2194 | N68: 2227 | O68: 2403 | P68: 2540 | Q68: 2611 | R68: 2568 | S68: 2220 | T68: 2651 | U68: 3037 | V68: 3154 | W68: 2925 | X68: 3142 | Y68: 3982 | Z68: 1096 | AA68: 3214 | AB68: 3265 | AC68: 3442 | AD68: 3593 | AE68: 3283 | AF68: 3489 | AG68: 4096 | AH68: 3983 | AI68: 3534 | AJ68: 3832 | AK68: 4350 | AL68: 3986 | AM68: 4257 | AN68: 4235 | AO68: 4591 | AP68: 4307 | AQ68: 3843 | AR68: 4235 | AS68: 4795 | AT68: 4488

Sheet Quarterly P&L
A1: Quarterly Profit & Loss
A2: Reported quarterly P&L only | FY16 is 12-month comparable, with Q1 derived as annual less Q2–Q4
A5: Metric | B5: Units | C5: Q1 FY16A | D5: Q2 FY16A | E5: Q3 FY16A | F5: Q4 FY16A | G5: Q1 FY17A | H5: Q2 FY17A | I5: Q3 FY17A | J5: Q4 FY17A | K5: Q1 FY18A | L5: Q2 FY18A | M5: Q3 FY18A | N5: Q4 FY18A | O5: Q1 FY19A | P5: Q2 FY19A | Q5: Q3 FY19A | R5: Q4 FY19A | S5: Q1 FY20A | T5: Q2 FY20A | U5: Q3 FY20A | V5: Q4 FY20A | W5: Q1 FY21A | X5: Q2 FY21A | Y5: Q3 FY21A | Z5: Q4 FY21A | AA5: Q1 FY22A | AB5: Q2 FY22A | AC5: Q3 FY22A | AD5: Q4 FY22A | AE5: Q1 FY23A | AF5: Q2 FY23A | AG5: Q3 FY23A | AH5: Q4 FY23A | AI5: Q1 FY24A | AJ5: Q2 FY24A | AK5: Q3 FY24A | AL5: Q4 FY24A | AM5: Q1 FY25A | AN5: Q2 FY25A | AO5: Q3 FY25A | AP5: Q4 FY25A | AQ5: Q1 FY26A | AR5: Q2 FY26A | AS5: Q3 FY26A | AT5: Q4 FY26A
A6: Revenue | B6: ₹ cr | C6: ='Raw Financials'!C56 -> 9777 | D6: ='Raw Financials'!D56 -> 10097 | E6: ='Raw Financials'!E56 -> 10341 | F6: ='Raw Financials'!F56 -> 10698 | G6: ='Raw Financials'!G56 -> 11336 | H6: ='Raw Financials'!H56 -> 11519 | I6: ='Raw Financials'!I56 -> 11814 | J6: ='Raw Financials'!J56 -> 12053 | ... AT6: ='Raw Financials'!AT56 -> 33981
A7: QoQ growth | B7: % | D7: =IFERROR(D6/C6-1,"") -> 0.032729876 | E7: =IFERROR(E6/D6-1,"") -> 0.024165594 | F7: =IFERROR(F6/E6-1,"") -> 0.034522773 | G7: =IFERROR(G6/F6-1,"") -> 0.059637315 | H7: =IFERROR(H6/G6-1,"") -> 0.01614326 | I7: =IFERROR(I6/H6-1,"") -> 0.025609862 | J7: =IFERROR(J6/I6-1,"") -> 0.020230235 | K7: =IFERROR(K6/J6-1,"") -> 0.007964822 | ... AT7: =IFERROR(AT6/AS6-1,"") -> 0.0032179972
A8: YoY growth | B8: % | G8: =IFERROR(G6/C6-1,"") -> 0.15945587 | H8: =IFERROR(H6/D6-1,"") -> 0.14083391 | I8: =IFERROR(I6/E6-1,"") -> 0.1424427 | J8: =IFERROR(J6/F6-1,"") -> 0.12665919 | K8: =IFERROR(K6/G6-1,"") -> 0.071718419 | L8: =IFERROR(L6/H6-1,"") -> 0.079433979 | M8: =IFERROR(M6/I6-1,"") -> 0.084137464 | N8: =IFERROR(N6/J6-1,"") -> 0.093420725 | ... AT8: =IFERROR(AT6/AP6-1,"") -> 0.1234874
A9: Direct costs | B9: ₹ cr | C9: ='Raw Financials'!C57 -> 6430 | D9: ='Raw Financials'!D57 -> 6742 | E9: ='Raw Financials'!E57 -> 6768 | F9: ='Raw Financials'!F57 -> 6961 | G9: ='Raw Financials'!G57 -> 7440 | H9: ='Raw Financials'!H57 -> 7653 | I9: ='Raw Financials'!I57 -> 7809 | J9: ='Raw Financials'!J57 -> 7987 | ... AT9: ='Raw Financials'!AT57 -> 22537
A10: Gross profit | B10: ₹ cr | C10: =IF(OR(C6="",C9=""),"",C6-C9) -> 3347 | D10: =IF(OR(D6="",D9=""),"",D6-D9) -> 3355 | E10: =IF(OR(E6="",E9=""),"",E6-E9) -> 3573 | F10: =IF(OR(F6="",F9=""),"",F6-F9) -> 3737 | G10: =IF(OR(G6="",G9=""),"",G6-G9) -> 3896 | H10: =IF(OR(H6="",H9=""),"",H6-H9) -> 3866 | I10: =IF(OR(I6="",I9=""),"",I6-I9) -> 4005 | J10: =IF(OR(J6="",J9=""),"",J6-J9) -> 4066 | ... AT10: =IF(OR(AT6="",AT9=""),"",AT6-AT9) -> 11444
A11: Gross margin | B11: % | C11: =IFERROR(C10/C6,"") -> 0.34233405 | D11: =IFERROR(D10/D6,"") -> 0.33227691 | E11: =IFERROR(E10/E6,"") -> 0.34551784 | F11: =IFERROR(F10/F6,"") -> 0.34931763 | G11: =IFERROR(G10/G6,"") -> 0.34368384 | H11: =IFERROR(H10/H6,"") -> 0.33561941 | I11: =IFERROR(I10/I6,"") -> 0.33900457 | J11: =IFERROR(J10/J6,"") -> 0.3373434 | ... AT11: =IFERROR(AT10/AT6,"") -> 0.33677643
A12: R&D | B12: ₹ cr | C12: ='Raw Financials'!C59 -> 0 | D12: ='Raw Financials'!D59 -> 0 | E12: ='Raw Financials'!E59 -> 0 | F12: ='Raw Financials'!F59 -> 0 | G12: ='Raw Financials'!G59 -> 0 | H12: ='Raw Financials'!H59 -> 0 | I12: ='Raw Financials'!I59 -> 0 | J12: ='Raw Financials'!J59 -> 0 | ... AT12: ='Raw Financials'!AT59 -> 530
A13: SG&A | B13: ₹ cr | C13: ='Raw Financials'!C60 -> 1248 | D13: ='Raw Financials'!D60 -> 1263 | E13: ='Raw Financials'!E60 -> 1348 | F13: ='Raw Financials'!F60 -> 1358 | G13: ='Raw Financials'!G60 -> 1375 | H13: ='Raw Financials'!H60 -> 1355 | I13: ='Raw Financials'!I60 -> 1377 | J13: ='Raw Financials'!J60 -> 1417 | ... AT13: ='Raw Financials'!AT60 -> 4202
A14: Other operating / reclassification | B14: ₹ cr | C14: =IF(OR(C10="",C12="",C13="",C16=""),"",C10-C12-C13-C16) -> 13 | D14: =IF(OR(D10="",D12="",D13="",D16=""),"",D10-D12-D13-D16) -> 13 | E14: =IF(OR(E10="",E12="",E13="",E16=""),"",E10-E12-E13-E16) -> 19 | F14: =IF(OR(F10="",F12="",F13="",F16=""),"",F10-F12-F13-F16) -> 18 | G14: =IF(OR(G10="",G12="",G13="",G16=""),"",G10-G12-G13-G16) -> 19 | H14: =IF(OR(H10="",H12="",H13="",H16=""),"",H10-H12-H13-H16) -> 21 | I14: =IF(OR(I10="",I12="",I13="",I16=""),"",I10-I12-I13-I16) -> 0 | J14: =IF(OR(J10="",J12="",J13="",J16=""),"",J10-J12-J13-J16) -> 0 | ... AT14: =IF(OR(AT10="",AT12="",AT13="",AT16=""),"",AT10-AT12-AT13-AT16) -> 0
A15: EBITDA | B15: ₹ cr | C15: =IFERROR(C16/C6,"") -> 0.21335788 | D15: =IFERROR(D16/D6,"") -> 0.20590274 | E15: =IFERROR(E16/E6,"") -> 0.2133256 | F15: =IFERROR(F16/F6,"") -> 0.22069546 | G15: =IFERROR(G16/G6,"") -> 0.22071277 | H15: =IFERROR(H16/H6,"") -> 0.2161646 | I15: =IFERROR(I16/I6,"") -> 0.22244794 | J15: =IFERROR(J16/J6,"") -> 0.21977931 | ... AT15: =IFERROR(AT16/AT6,"") -> 0.19752214
A16: EBITDA margin | B16: % | C16: =IF(OR(C18="",C17=""),"",C18+C17) -> 2086 | D16: =IF(OR(D18="",D17=""),"",D18+D17) -> 2079 | E16: =IF(OR(E18="",E17=""),"",E18+E17) -> 2206 | F16: =IF(OR(F18="",F17=""),"",F18+F17) -> 2361 | G16: =IF(OR(G18="",G17=""),"",G18+G17) -> 2502 | H16: =IF(OR(H18="",H17=""),"",H18+H17) -> 2490 | I16: =IF(OR(I18="",I17=""),"",I18+I17) -> 2628 | J16: =IF(OR(J18="",J17=""),"",J18+J17) -> 2649 | ... AT16: =IF(OR(AT18="",AT17=""),"",AT18+AT17) -> 6712
A17: D&A | B17: ₹ cr | C17: ='Raw Financials'!C62 -> 111 | D17: ='Raw Financials'!D62 -> 122 | E17: ='Raw Financials'!E62 -> 134 | F17: ='Raw Financials'!F62 -> 139 | G17: ='Raw Financials'!G62 -> 169 | H17: ='Raw Financials'!H62 -> 172 | I17: ='Raw Financials'!I62 -> 220 | J17: ='Raw Financials'!J62 -> 233 | ... AT17: ='Raw Financials'!AT62 -> 1092
A18: EBIT | B18: ₹ cr | C18: ='Raw Financials'!C63 -> 1975 | D18: ='Raw Financials'!D63 -> 1957 | E18: ='Raw Financials'!E63 -> 2072 | F18: ='Raw Financials'!F63 -> 2222 | G18: ='Raw Financials'!G63 -> 2333 | H18: ='Raw Financials'!H63 -> 2318 | I18: ='Raw Financials'!I63 -> 2408 | J18: ='Raw Financials'!J63 -> 2416 | ... AT18: ='Raw Financials'!AT63 -> 5620
A19: EBIT margin | B19: % | C19: =IFERROR(C18/C6,"") -> 0.2020047 | D19: =IFERROR(D18/D6,"") -> 0.19381995 | E19: =IFERROR(E18/E6,"") -> 0.20036747 | F19: =IFERROR(F18/F6,"") -> 0.20770237 | G19: =IFERROR(G18/G6,"") -> 0.20580452 | H19: =IFERROR(H18/H6,"") -> 0.20123275 | I19: =IFERROR(I18/I6,"") -> 0.20382597 | J19: =IFERROR(J18/J6,"") -> 0.20044802 | ... AT19: =IFERROR(AT18/AT6,"") -> 0.16538654
A20: FX gain / (loss) | B20: ₹ cr | C20: ='Raw Financials'!C64 -> 36 | D20: ='Raw Financials'!D64 -> 22 | E20: ='Raw Financials'!E64 -> 11 | F20: ='Raw Financials'!F64 -> 3 | G20: ='Raw Financials'!G64 -> 66 | H20: ='Raw Financials'!H64 -> 31 | I20: ='Raw Financials'!I64 -> 43 | J20: ='Raw Financials'!J64 -> 48 | ... AT20: ='Raw Financials'!AT64 -> -128
A21: Other income, net | B21: ₹ cr | C21: ='Raw Financials'!C65 -> 177 | D21: ='Raw Financials'!D65 -> 219 | E21: ='Raw Financials'!E65 -> 344 | F21: ='Raw Financials'!F65 -> 197 | G21: ='Raw Financials'!G65 -> 187 | H21: ='Raw Financials'!H65 -> 204 | I21: ='Raw Financials'!I65 -> 188 | J21: ='Raw Financials'!J65 -> 167 | ... AT21: ='Raw Financials'!AT65 -> 210
A22: PBT | B22: ₹ cr | C22: =IF(OR(C18="",C20="",C21=""),"",SUM(C18,C20,C21)) -> 2188 | D22: =IF(OR(D18="",D20="",D21=""),"",SUM(D18,D20,D21)) -> 2198 | E22: =IF(OR(E18="",E20="",E21=""),"",SUM(E18,E20,E21)) -> 2427 | F22: =IF(OR(F18="",F20="",F21=""),"",SUM(F18,F20,F21)) -> 2422 | G22: =IF(OR(G18="",G20="",G21=""),"",SUM(G18,G20,G21)) -> 2586 | H22: =IF(OR(H18="",H20="",H21=""),"",SUM(H18,H20,H21)) -> 2553 | I22: =IF(OR(I18="",I20="",I21=""),"",SUM(I18,I20,I21)) -> 2639 | J22: =IF(OR(J18="",J20="",J21=""),"",SUM(J18,J20,J21)) -> 2631 | ... AT22: =IF(OR(AT18="",AT20="",AT21=""),"",SUM(AT18,AT20,AT21)) -> 5702
A23: Tax | B23: ₹ cr | C23: ='Raw Financials'!C66 -> 406 | D23: ='Raw Financials'!D66 -> 472 | E23: ='Raw Financials'!E66 -> 508 | F23: ='Raw Financials'!F66 -> 497 | G23: ='Raw Financials'!G66 -> 543 | H23: ='Raw Financials'!H66 -> 538 | I23: ='Raw Financials'!I66 -> 568 | J23: ='Raw Financials'!J66 -> 303 | ... AT23: ='Raw Financials'!AT66 -> 1212
A24: NCI / other attribution | B24: ₹ cr | C24: ='Raw Financials'!C67 -> 0 | D24: ='Raw Financials'!D67 -> 0 | E24: ='Raw Financials'!E67 -> 0 | F24: ='Raw Financials'!F67 -> 0 | G24: ='Raw Financials'!G67 -> 0 | H24: ='Raw Financials'!H67 -> 0 | I24: ='Raw Financials'!I67 -> 0 | J24: ='Raw Financials'!J67 -> 0 | ... AT24: ='Raw Financials'!AT67 -> 2
A25: Net income attributable | B25: ₹ cr | C25: ='Raw Financials'!C68 -> 1782 | D25: ='Raw Financials'!D68 -> 1726 | E25: ='Raw Financials'!E68 -> 1920 | F25: ='Raw Financials'!F68 -> 1926 | G25: ='Raw Financials'!G68 -> 2047 | H25: ='Raw Financials'!H68 -> 2014 | I25: ='Raw Financials'!I68 -> 2070 | J25: ='Raw Financials'!J68 -> 2325 | ... AT25: ='Raw Financials'!AT68 -> 4488
A26: Net margin | B26: % | C26: =IFERROR(C25/C6,"") -> 0.1822645 | D26: =IFERROR(D25/D6,"") -> 0.17094186 | E26: =IFERROR(E25/E6,"") -> 0.1856687 | F26: =IFERROR(F25/F6,"") -> 0.18003365 | G26: =IFERROR(G25/G6,"") -> 0.18057516 | H26: =IFERROR(H25/H6,"") -> 0.17484157 | I26: =IFERROR(I25/I6,"") -> 0.17521585 | J26: =IFERROR(J25/J6,"") -> 0.19289803 | ... AT26: =IFERROR(AT25/AT6,"") -> 0.13207381

Sheet Annual P&L
A1: Annual Profit & Loss
A2: Actuals link to raw reported data; FY27E–FY30E are formula-driven from operating assumptions
A5: Metric | B5: Units | C5: FY16A | D5: FY17A | E5: FY18A | F5: FY19A | G5: FY20A | H5: FY21A | I5: FY22A | J5: FY23A | K5: FY24A | L5: FY25A | M5: FY26A | N5: FY27E | O5: FY28E | P5: FY29E | Q5: FY30E
A7: Revenue | B7: ₹ cr | C7: ='Raw Financials'!C6 -> 40913 | D7: ='Raw Financials'!D6 -> 46723 | E7: ='Raw Financials'!E6 -> 50570 | F7: ='Raw Financials'!F6 -> 60427 | G7: ='Raw Financials'!G6 -> 70678 | H7: ='Raw Financials'!H6 -> 75379 | I7: ='Raw Financials'!I6 -> 85651 | J7: ='Raw Financials'!J6 -> 101456 | ... M7: ='Raw Financials'!M6 -> 130144 | N7: ='Revenue Drivers'!N26 -> 138192.4 | O7: ='Revenue Drivers'!O26 -> 149041.66 | P7: ='Revenue Drivers'!P26 -> 162065.57 | Q7: ='Revenue Drivers'!Q26 -> 175279.02
A8: YoY growth | B8: % | D8: =IFERROR(D7/C7-1,"") -> 0.14200865 | E8: =IFERROR(E7/D7-1,"") -> 0.082336323 | F8: =IFERROR(F7/E7-1,"") -> 0.19491794 | G8: =IFERROR(G7/F7-1,"") -> 0.16964271 | H8: =IFERROR(H7/G7-1,"") -> 0.066512918 | I8: =IFERROR(I7/H7-1,"") -> 0.13627138 | J8: =IFERROR(J7/I7-1,"") -> 0.18452791 | K8: =IFERROR(K7/J7-1,"") -> 0.083356332 | ... Q8: =IFERROR(Q7/P7-1,"") -> 0.081531488
A9: Direct costs | B9: ₹ cr | C9: ='Raw Financials'!C7 -> 26901 | D9: ='Raw Financials'!D7 -> 30890 | E9: ='Raw Financials'!E7 -> 33237 | F9: ='Raw Financials'!F7 -> 39268 | G9: ='Raw Financials'!G7 -> 44018 | H9: ='Raw Financials'!H7 -> 44591 | I9: ='Raw Financials'!I7 -> 52760 | J9: ='Raw Financials'!J7 -> 64523 | ... M9: ='Raw Financials'!M7 -> 85811 | N9: =N7*(1-Assumptions!C15) -> 90930.602 | O9: =O7*(1-Assumptions!D15) -> 97771.332 | P9: =P7*(1-Assumptions!E15) -> 105990.88 | Q9: =Q7*(1-Assumptions!F15) -> 114457.2
A10: Gross profit | B10: ₹ cr | C10: =C7-C9 -> 14012 | D10: =D7-D9 -> 15833 | E10: =E7-E9 -> 17333 | F10: =F7-F9 -> 21159 | G10: =G7-G9 -> 26660 | H10: =H7-H9 -> 30788 | I10: =I7-I9 -> 32891 | J10: =J7-J9 -> 36933 | ... Q10: =Q7-Q9 -> 60821.82
A11: Gross margin | B11: % | C11: =IFERROR(C10/C7,"") -> 0.34248283 | D11: =IFERROR(D10/D7,"") -> 0.33886951 | E11: =IFERROR(E10/E7,"") -> 0.34275262 | F11: =IFERROR(F10/F7,"") -> 0.35015804 | G11: =IFERROR(G10/G7,"") -> 0.37720366 | H11: =IFERROR(H10/H7,"") -> 0.40844267 | I11: =IFERROR(I10/I7,"") -> 0.38401186 | J11: =IFERROR(J10/J7,"") -> 0.36402973 | ... Q11: =IFERROR(Q10/Q7,"") -> 0.347
A12: Reported gross profit control | B12: ₹ cr | C12: ='Raw Financials'!C8 -> 14012 | D12: ='Raw Financials'!D8 -> 15833 | E12: ='Raw Financials'!E8 -> 17333 | F12: ='Raw Financials'!F8 -> 21159 | G12: ='Raw Financials'!G8 -> 26659 | H12: ='Raw Financials'!H8 -> 30788 | I12: ='Raw Financials'!I8 -> 32891 | J12: ='Raw Financials'!J8 -> 36933 | ... M12: ='Raw Financials'!M8 -> 44333 | N12: =N10 -> 47261.802 | O12: =O10 -> 51270.333 | P12: =P10 -> 56074.688 | Q12: =Q10 -> 60821.82
A13: Gross profit check | B13: ₹ cr | C13: =C10-C12 -> 0 | D13: =D10-D12 -> 0 | E13: =E10-E12 -> 0 | F13: =F10-F12 -> 0 | G13: =G10-G12 -> 1 | H13: =H10-H12 -> 0 | I13: =I10-I12 -> 0 | J13: =J10-J12 -> 0 | ... Q13: =Q10-Q12 -> 0
A14: R&D | B14: ₹ cr | C14: ='Raw Financials'!C9 -> 0 | D14: ='Raw Financials'!D9 -> 0 | E14: ='Raw Financials'!E9 -> 0 | F14: ='Raw Financials'!F9 -> 0 | G14: ='Raw Financials'!G9 -> 1276 | H14: ='Raw Financials'!H9 -> 1383 | I14: ='Raw Financials'!I9 -> 1526 | J14: ='Raw Financials'!J9 -> 1632 | ... M14: ='Raw Financials'!M9 -> 2000 | N14: =N7*Assumptions!C16 -> 2072.8861 | O14: =O7*Assumptions!D16 -> 2235.625 | P14: =P7*Assumptions!E16 -> 2430.9836 | Q14: =Q7*Assumptions!F16 -> 2629.1853
A15: SG&A + other operating costs | B15: ₹ cr | C15: =IF(OR(C10="",C14="",C17=""),"",C10-C14-C17) -> 5280 | D15: =IF(OR(D10="",D14="",D17=""),"",D10-D14-D17) -> 5524 | E15: =IF(OR(E10="",E14="",E17=""),"",E10-E14-E17) -> 5893 | F15: =IF(OR(F10="",F14="",F17=""),"",F10-F14-F17) -> 7192 | G15: =IF(OR(G10="",G14="",G17=""),"",G10-G14-G17) -> 8690 | H15: =IF(OR(H10="",H14="",H17=""),"",H10-H14-H17) -> 9450 | I15: =IF(OR(I10="",I14="",I17=""),"",I10-I14-I17) -> 10835 | J15: =IF(OR(J10="",J14="",J17=""),"",J10-J14-J17) -> 12673 | ... M15: =IF(OR(M10="",M14="",M17=""),"",M10-M14-M17) -> 15581 | N15: =N10-N14-N17 -> 15753.934 | O15: =O10-O14-O17 -> 17139.791 | P15: =P10-P14-P17 -> 18799.606 | Q15: =Q10-Q14-Q17 -> 20507.645
A16: Reported EBITDA control | B16: ₹ cr | C16: ='Raw Financials'!C11 -> 8795 | D16: ='Raw Financials'!D11 -> 10309 | E16: ='Raw Financials'!E11 -> 11440 | F16: ='Raw Financials'!F11 -> 13967 | G16: ='Raw Financials'!G11 -> 16694 | H16: ='Raw Financials'!H11 -> 20057 | I16: ='Raw Financials'!I11 -> 20530 | J16: ='Raw Financials'!J11 -> 22628 | ... M16: ='Raw Financials'!M11 -> 26752 | N16: =N17 -> 29434.982 | O16: =O17 -> 31894.916 | P16: =P17 -> 34844.098 | Q16: =Q17 -> 37684.989
A17: EBITDA | B17: ₹ cr | C17: =C20+C19 -> 8732 | D17: =D20+D19 -> 10309 | E17: =E20+E19 -> 11440 | F17: =F20+F19 -> 13967 | G17: =G20+G19 -> 16694 | H17: =H20+H19 -> 19955 | I17: =I20+I19 -> 20530 | J17: =J20+J19 -> 22628 | ... Q17: =Q20+Q19 -> 37684.989
A18: EBITDA margin | B18: % | C18: =IFERROR(C17/C7,"") -> 0.21342849 | D18: =IFERROR(D17/D7,"") -> 0.2206408 | E18: =IFERROR(E17/E7,"") -> 0.22622108 | F18: =IFERROR(F17/F7,"") -> 0.2311384 | G18: =IFERROR(G17/G7,"") -> 0.23619797 | H18: =IFERROR(H17/H7,"") -> 0.2647289 | I18: =IFERROR(I17/I7,"") -> 0.23969364 | J18: =IFERROR(J17/J7,"") -> 0.22303264 | ... Q18: =IFERROR(Q17/Q7,"") -> 0.215
A19: D&A | B19: ₹ cr | C19: ='Raw Financials'!C12 -> 506 | D19: ='Raw Financials'!D12 -> 835 | E19: ='Raw Financials'!E12 -> 1453 | F19: ='Raw Financials'!F12 -> 2147 | G19: ='Raw Financials'!G12 -> 2841 | H19: ='Raw Financials'!H12 -> 4611 | I19: ='Raw Financials'!I12 -> 4326 | J19: ='Raw Financials'!J12 -> 4145 | ... M19: ='Raw Financials'!M12 -> 4355 | N19: =N7*Assumptions!C17 -> 4560.3493 | O19: =O7*Assumptions!D17 -> 4769.3333 | P19: =P7*Assumptions!E17 -> 5024.0327 | Q19: =Q7*Assumptions!F17 -> 5258.3706
A20: EBIT | B20: ₹ cr | C20: ='Raw Financials'!C13 -> 8226 | D20: ='Raw Financials'!D13 -> 9474 | E20: ='Raw Financials'!E13 -> 9987 | F20: ='Raw Financials'!F13 -> 11820 | G20: ='Raw Financials'!G13 -> 13853 | H20: ='Raw Financials'!H13 -> 15344 | I20: ='Raw Financials'!I13 -> 16204 | J20: ='Raw Financials'!J13 -> 18483 | ... M20: ='Raw Financials'!M13 -> 22397 | N20: =N7*Assumptions!C18 -> 24874.633 | O20: =O7*Assumptions!D18 -> 27125.583 | P20: =P7*Assumptions!E18 -> 29820.065 | Q20: =Q7*Assumptions!F18 -> 32426.619
A21: EBIT margin | B21: % | C21: =IFERROR(C20/C7,"") -> 0.20106079 | D21: =IFERROR(D20/D7,"") -> 0.20276951 | E21: =IFERROR(E20/E7,"") -> 0.19748863 | F21: =IFERROR(F20/F7,"") -> 0.19560792 | G21: =IFERROR(G20/G7,"") -> 0.19600158 | H21: =IFERROR(H20/H7,"") -> 0.20355802 | I21: =IFERROR(I20/I7,"") -> 0.18918635 | J21: =IFERROR(J20/J7,"") -> 0.1821775 | ... Q21: =IFERROR(Q20/Q7,"") -> 0.185
A22: FX gain / (loss) | B22: ₹ cr | C22: ='Raw Financials'!C14 -> 72 | D22: ='Raw Financials'!D14 -> 188 | E22: ='Raw Financials'!E14 -> 541 | F22: ='Raw Financials'!F14 -> 182 | G22: ='Raw Financials'!G14 -> -15 | H22: ='Raw Financials'!H14 -> 46 | I22: ='Raw Financials'!I14 -> 328 | J22: ='Raw Financials'!J14 -> 91 | ... M22: ='Raw Financials'!M14 -> -241 | N22: =0 -> 0 | O22: =0 -> 0 | P22: =0 -> 0 | Q22: =0 -> 0
A23: Other income, net | B23: ₹ cr | C23: ='Raw Financials'!C15 -> 937 | D23: ='Raw Financials'!D15 -> 746 | E23: ='Raw Financials'!E15 -> 570 | F23: ='Raw Financials'!F15 -> 623 | G23: ='Raw Financials'!G15 -> 193 | H23: ='Raw Financials'!H15 -> 463 | I23: ='Raw Financials'!I15 -> 419 | J23: ='Raw Financials'!J15 -> 914 | ... M23: ='Raw Financials'!M15 -> 902 | N23: =SUM('Annual Balance Sheet'!M7,'Annual Balance Sheet'!M10)*Assumptions!C20 -> 942.03 | O23: =SUM('Annual Balance Sheet'!N7,'Annual Balance Sheet'!N10)*Assumptions!D20 -> 1122.9522 | P23: =SUM('Annual Balance Sheet'!O7,'Annual Balance Sheet'!O10)*Assumptions!E20 -> 1207.903 | Q23: =SUM('Annual Balance Sheet'!P7,'Annual Balance Sheet'!P10)*Assumptions!F20 -> 1307.5365
A24: PBT | B24: ₹ cr | C24: =SUM(C20,C22,C23) -> 9235 | D24: =SUM(D20,D22,D23) -> 10408 | E24: =SUM(E20,E22,E23) -> 11098 | F24: =SUM(F20,F22,F23) -> 12625 | G24: =SUM(G20,G22,G23) -> 14031 | H24: =SUM(H20,H22,H23) -> 15853 | I24: =SUM(I20,I22,I23) -> 16951 | J24: =SUM(J20,J22,J23) -> 19488 | ... Q24: =SUM(Q20,Q22,Q23) -> 33734.155
A25: PBT margin | B25: % | C25: =IFERROR(C24/C7,"") -> 0.22572288 | D25: =IFERROR(D24/D7,"") -> 0.22275967 | E25: =IFERROR(E24/E7,"") -> 0.21945818 | F25: =IFERROR(F24/F7,"") -> 0.20892978 | G25: =IFERROR(G24/G7,"") -> 0.19852005 | H25: =IFERROR(H24/H7,"") -> 0.21031056 | I25: =IFERROR(I24/I7,"") -> 0.19790779 | J25: =IFERROR(J24/J7,"") -> 0.19208327 | ... Q25: =IFERROR(Q24/Q7,"") -> 0.19245974
A26: Tax | B26: ₹ cr | C26: ='Raw Financials'!C16 -> 1883 | D26: ='Raw Financials'!D16 -> 1952 | E26: ='Raw Financials'!E16 -> 2316 | F26: ='Raw Financials'!F16 -> 2481 | G26: ='Raw Financials'!G16 -> 2938 | H26: ='Raw Financials'!H16 -> 4684 | I26: ='Raw Financials'!I16 -> 3428 | J26: ='Raw Financials'!J16 -> 4643 | ... M26: ='Raw Financials'!M16 -> 5687 | N26: =N24*Assumptions!C19 -> 6454.1657 | O26: =O24*Assumptions!D19 -> 7062.1338 | P26: =P24*Assumptions!E19 -> 7756.9921 | Q26: =Q24*Assumptions!F19 -> 8433.5388
A27: Effective tax rate | B27: % | C27: =IFERROR(C26/C24,"") -> 0.20389821 | D27: =IFERROR(D26/D24,"") -> 0.18754804 | E27: =IFERROR(E26/E24,"") -> 0.20868625 | F27: =IFERROR(F26/F24,"") -> 0.19651485 | G27: =IFERROR(G26/G24,"") -> 0.20939349 | H27: =IFERROR(H26/H24,"") -> 0.29546458 | I27: =IFERROR(I26/I24,"") -> 0.20222996 | J27: =IFERROR(J26/J24,"") -> 0.23824918 | ... Q27: =IFERROR(Q26/Q24,"") -> 0.25
A28: NCI / other attribution | B28: ₹ cr | C28: ='Raw Financials'!C17 -> 0 | D28: ='Raw Financials'!D17 -> 0 | E28: ='Raw Financials'!E17 -> 0 | F28: ='Raw Financials'!F17 -> 0 | G28: ='Raw Financials'!G17 -> 31 | H28: ='Raw Financials'!H17 -> 24 | I28: ='Raw Financials'!I17 -> 24 | J28: ='Raw Financials'!J17 -> -6 | ... M28: ='Raw Financials'!M17 -> 0 | N28: =0 -> 0 | O28: =0 -> 0 | P28: =0 -> 0 | Q28: =0 -> 0
A29: Net income attributable | B29: ₹ cr | C29: ='Raw Financials'!C18 -> 7354 | D29: ='Raw Financials'!D18 -> 8457 | E29: ='Raw Financials'!E18 -> 8780 | F29: ='Raw Financials'!F18 -> 10123 | G29: ='Raw Financials'!G18 -> 11062 | H29: ='Raw Financials'!H18 -> 11145 | I29: ='Raw Financials'!I18 -> 13499 | J29: ='Raw Financials'!J18 -> 14851 | ... M29: ='Raw Financials'!M18 -> 17361 | N29: =N24-N26-N28 -> 19362.497 | O29: =O24-O26-O28 -> 21186.401 | P29: =P24-P26-P28 -> 23270.976 | Q29: =Q24-Q26-Q28 -> 25300.616
A30: Net margin | B30: % | C30: =IFERROR(C29/C7,"") -> 0.17974727 | D30: =IFERROR(D29/D7,"") -> 0.18100293 | E30: =IFERROR(E29/E7,"") -> 0.17362072 | F30: =IFERROR(F29/F7,"") -> 0.16752445 | G30: =IFERROR(G29/G7,"") -> 0.15651263 | H30: =IFERROR(H29/H7,"") -> 0.14785285 | I30: =IFERROR(I29/I7,"") -> 0.1576047 | J30: =IFERROR(J29/J7,"") -> 0.14637873 | ... Q30: =IFERROR(Q29/Q7,"") -> 0.14434481
A31: Basic shares outstanding | B31: m | C31: =2713.7 -> 2713.7 | D31: =2713.7 -> 2713.7 | E31: =2713.7 -> 2713.7 | F31: =2713.7 -> 2713.7 | G31: =2713.7 -> 2713.7 | H31: =2713.7 -> 2713.7 | I31: =2713.7 -> 2713.7 | J31: =2713.7 -> 2713.7 | ... M31: =2713.7 -> 2713.7 | N31: =M31*(1+Assumptions!C37) -> 2713.7 | O31: =N31*(1+Assumptions!D37) -> 2713.7 | P31: =O31*(1+Assumptions!E37) -> 2713.7 | Q31: =P31*(1+Assumptions!F37) -> 2713.7
A32: Diluted shares outstanding | B32: m | C32: =C31+1.5 -> 2715.2 | D32: =D31+1.5 -> 2715.2 | E32: =E31+1.5 -> 2715.2 | F32: =F31+1.5 -> 2715.2 | G32: =G31+1.5 -> 2715.2 | H32: =H31+1.5 -> 2715.2 | I32: =I31+1.5 -> 2715.2 | J32: =J31+1.5 -> 2715.2 | ... M32: =M31+1.5 -> 2715.2 | N32: =M32*(1+Assumptions!C37) -> 2715.2 | O32: =N32*(1+Assumptions!D37) -> 2715.2 | P32: =O32*(1+Assumptions!E37) -> 2715.2 | Q32: =P32*(1+Assumptions!F37) -> 2715.2
A33: Basic EPS | B33: ₹ / share | C33: =IFERROR(C29*10/C31,"") -> 27.099532 | D33: =IFERROR(D29*10/D31,"") -> 31.164093 | E33: =IFERROR(E29*10/E31,"") -> 32.35435 | F33: =IFERROR(F29*10/F31,"") -> 37.303313 | G33: =IFERROR(G29*10/G31,"") -> 40.763533 | H33: =IFERROR(H29*10/H31,"") -> 41.069389 | I33: =IFERROR(I29*10/I31,"") -> 49.743892 | J33: =IFERROR(J29*10/J31,"") -> 54.72602 | ... Q33: =IFERROR(Q29*10/Q31,"") -> 93.232916
A34: Diluted EPS | B34: ₹ / share | C34: =IFERROR(C29*10/C32,"") -> 27.084561 | D34: =IFERROR(D29*10/D32,"") -> 31.146877 | E34: =IFERROR(E29*10/E32,"") -> 32.336476 | F34: =IFERROR(F29*10/F32,"") -> 37.282705 | G34: =IFERROR(G29*10/G32,"") -> 40.741014 | H34: =IFERROR(H29*10/H32,"") -> 41.0467 | I34: =IFERROR(I29*10/I32,"") -> 49.716411 | J34: =IFERROR(J29*10/J32,"") -> 54.695787 | ... Q34: =IFERROR(Q29*10/Q32,"") -> 93.18141
A35: Dividend per share | B35: ₹ / share | C35: =IFERROR(-'Annual Cash Flow'!C28*10/C31,"") -> 9.9384604 | D35: =IFERROR(-'Annual Cash Flow'!D28*10/D31,"") -> 14.990603 | E35: =IFERROR(-'Annual Cash Flow'!E28*10/E31,"") -> 7.4842466 | F35: =IFERROR(-'Annual Cash Flow'!F28*10/F31,"") -> 4.8678925 | G35: =IFERROR(-'Annual Cash Flow'!G28*10/G31,"") -> 5.9881343 | H35: =IFERROR(-'Annual Cash Flow'!H28*10/H31,"") -> 11.998379 | I35: =IFERROR(-'Annual Cash Flow'!I28*10/I31,"") -> 41.96853 | J35: =IFERROR(-'Annual Cash Flow'!J28*10/J31,"") -> 47.886649 | ... M35: =IFERROR(-'Annual Cash Flow'!M28*10/M31,"") -> 53.867413 | N35: =N33*Assumptions!C35 -> 64.215821 | O35: =O33*Assumptions!D35 -> 70.264809 | P35: =P33*Assumptions!E35 -> 77.178312 | Q35: =Q33*Assumptions!F35 -> 83.909624
A36: Dividend payout | B36: % | C36: =IFERROR(C35/C33,"") -> 0.36673919 | D36: =IFERROR(D35/D33,"") -> 0.48102164 | E36: =IFERROR(E35/E33,"") -> 0.23132118 | F36: =IFERROR(F35/F33,"") -> 0.13049491 | G36: =IFERROR(G35/G33,"") -> 0.14689929 | H36: =IFERROR(H35/H33,"") -> 0.29214895 | I36: =IFERROR(I35/I33,"") -> 0.84369213 | J36: =IFERROR(J35/J33,"") -> 0.87502525 | ... Q36: =IFERROR(Q35/Q33,"") -> 0.9

Sheet Annual Balance Sheet
A1: Annual Balance Sheet
A2: Historical balances from reported annual releases; borrowings remain unallocated where no maturity split was reported
A5: Metric | B5: Units | C5: FY16A | D5: FY17A | E5: FY18A | F5: FY19A | G5: FY20A | H5: FY21A | I5: FY22A | J5: FY23A | K5: FY24A | L5: FY25A | M5: FY26A | N5: FY27E | O5: FY28E | P5: FY29E | Q5: FY30E
A7: Cash & equivalents | B7: ₹ cr | C7: ='Raw Financials'!C29 -> 729.3 | D7: ='Raw Financials'!D29 -> 1316.5 | E7: ='Raw Financials'!E29 -> 1693.9 | F7: ='Raw Financials'!F29 -> 5929 | G7: ='Raw Financials'!G29 -> 4843 | H7: ='Raw Financials'!H29 -> 6515 | I7: ='Raw Financials'!I29 -> 10510 | J7: ='Raw Financials'!J29 -> 9065 | ... M7: ='Raw Financials'!M29 -> 8265 | N7: ='Annual Cash Flow'!N35 -> 11175.182 | O7: ='Annual Cash Flow'!O35 -> 12690.724 | P7: ='Annual Cash Flow'!P35 -> 14412.746 | Q7: ='Annual Cash Flow'!Q35 -> 16169.033
A8: Trade receivables | B8: ₹ cr | C8: ='Raw Financials'!C30 -> 7721.3 | D8: ='Raw Financials'!D30 -> 8301.4 | E8: ='Raw Financials'!E30 -> 9639.4 | F8: ='Raw Financials'!F30 -> 11706 | G8: ='Raw Financials'!G30 -> 14134 | H8: ='Raw Financials'!H30 -> 13663 | I8: ='Raw Financials'!I30 -> 15476 | J8: ='Raw Financials'!J30 -> 19572 | ... M8: ='Raw Financials'!M30 -> 23585 | N8: ='Annual P&L'!N7/365*Assumptions!C21 -> 24230.997 | O8: ='Annual P&L'!O7/365*Assumptions!D21 -> 25725 | P8: ='Annual P&L'!P7/365*Assumptions!E21 -> 27528.947 | Q8: ='Annual P&L'!Q7/365*Assumptions!F21 -> 29293.206
A9: Unbilled receivables | B9: ₹ cr | C9: ='Raw Financials'!C31 -> 3001.5 | D9: ='Raw Financials'!D31 -> 2501.2 | E9: ='Raw Financials'!E31 -> 2618.1 | F9: ='Raw Financials'!F31 -> 0 | G9: ='Raw Financials'!G31 -> 3638 | H9: ='Raw Financials'!H31 -> 3862 | I9: ='Raw Financials'!I31 -> 5195 | J9: ='Raw Financials'!J31 -> 5934 | ... M9: ='Raw Financials'!M31 -> 7956 | N9: ='Annual P&L'!N7/365*Assumptions!C22 -> 8329.4052 | O9: ='Annual P&L'!O7/365*Assumptions!D22 -> 8983.3332 | P9: ='Annual P&L'!P7/365*Assumptions!E22 -> 9324.3206 | Q9: ='Annual P&L'!Q7/365*Assumptions!F22 -> 10084.546
A10: Treasury investments | B10: ₹ cr | C10: ='Raw Financials'!C32 -> 11123.6 | D10: ='Raw Financials'!D32 -> 11365.3 | E10: ='Raw Financials'!E32 -> 8083.8 | F10: ='Raw Financials'!F32 -> 5462 | G10: ='Raw Financials'!G32 -> 10530 | H10: ='Raw Financials'!H32 -> 13975 | I10: ='Raw Financials'!I32 -> 11373 | J10: ='Raw Financials'!J32 -> 13647 | ... M10: ='Raw Financials'!M32 -> 23136 | N10: ='Annual P&L'!N7*Assumptions!C26 -> 26256.557 | O10: ='Annual P&L'!O7*Assumptions!D26 -> 27572.708 | P10: ='Annual P&L'!P7*Assumptions!E26 -> 29171.803 | Q10: ='Annual P&L'!Q7*Assumptions!F26 -> 30673.828
A11: Other current assets | B11: ₹ cr | C11: =C12-SUM(C7:C10) -> 2410.2 | D11: =D12-SUM(D7:D10) -> 2983.2 | E11: =E12-SUM(E7:E10) -> 2519.8 | F11: =F12-SUM(F7:F10) -> 6620 | G11: =G12-SUM(G7:G10) -> 5280 | H11: =H12-SUM(H7:H10) -> 5037 | I11: =I12-SUM(I7:I10) -> 5487 | J11: =J12-SUM(J7:J10) -> 5359 | ... M11: =M12-SUM(M7:M10) -> 7600 | N11: ='Annual P&L'!N7*Assumptions!C23 -> 8015.1594 | O11: ='Annual P&L'!O7*Assumptions!D23 -> 8495.3749 | P11: ='Annual P&L'!P7*Assumptions!E23 -> 9075.6721 | Q11: ='Annual P&L'!Q7*Assumptions!F23 -> 9640.3461
A12: Total current assets | B12: ₹ cr | C12: ='Raw Financials'!C34 -> 24985.9 | D12: ='Raw Financials'!D34 -> 26467.6 | E12: ='Raw Financials'!E34 -> 24555 | F12: ='Raw Financials'!F34 -> 29717 | G12: ='Raw Financials'!G34 -> 38425 | H12: ='Raw Financials'!H34 -> 43052 | I12: ='Raw Financials'!I34 -> 48041 | J12: ='Raw Financials'!J34 -> 53577 | ... M12: ='Raw Financials'!M34 -> 70542 | N12: =SUM(N7:N11) -> 78007.3 | O12: =SUM(O7:O11) -> 83467.14 | P12: =SUM(P7:P11) -> 89513.488 | Q12: =SUM(Q7:Q11) -> 95860.96
A13: PPE | B13: ₹ cr | C13: ='Raw Financials'!C35 -> 4323.1 | D13: ='Raw Financials'!D35 -> 4680.6 | E13: ='Raw Financials'!E35 -> 5184.7 | F13: ='Raw Financials'!F35 -> 5801 | G13: ='Raw Financials'!G35 -> 6244 | H13: ='Raw Financials'!H35 -> 6245 | I13: ='Raw Financials'!I35 -> 5741 | J13: ='Raw Financials'!J35 -> 5411 | ... M13: ='Raw Financials'!M35 -> 4717 | N13: =M13-'Annual Cash Flow'!N17-'Annual P&L'!N19*Assumptions!C28 -> 3915.4841 | O13: =N13-'Annual Cash Flow'!O17-'Annual P&L'!O19*Assumptions!D28 -> 3140.4674 | P13: =O13-'Annual Cash Flow'!P17-'Annual P&L'!P19*Assumptions!E28 -> 2394.9658 | Q13: =P13-'Annual Cash Flow'!Q17-'Annual P&L'!Q19*Assumptions!F28 -> 1693.8497
A14: ROU assets | B14: ₹ cr | C14: ='Raw Financials'!C36 -> 0 | D14: ='Raw Financials'!D36 -> 0 | E14: ='Raw Financials'!E36 -> 0 | F14: ='Raw Financials'!F36 -> 0 | G14: ='Raw Financials'!G36 -> 0 | H14: ='Raw Financials'!H36 -> 0 | I14: ='Raw Financials'!I36 -> 2305 | J14: ='Raw Financials'!J36 -> 2337 | ... M14: ='Raw Financials'!M36 -> 3592 | N14: =M14+'Annual Cash Flow'!N25-'Annual P&L'!N19*Assumptions!C30 -> 4338.239 | O14: =N14+'Annual Cash Flow'!O25-'Annual P&L'!O19*Assumptions!D30 -> 5172.8723 | P14: =O14+'Annual Cash Flow'!P25-'Annual P&L'!P19*Assumptions!E30 -> 6112.8526 | Q14: =P14+'Annual Cash Flow'!Q25-'Annual P&L'!Q19*Assumptions!F30 -> 7164.5267
A15: Goodwill & intangibles | B15: ₹ cr | C15: ='Raw Financials'!C37 -> 6419.4 | D15: ='Raw Financials'!D37 -> 7358.3 | E15: ='Raw Financials'!E37 -> 14405.7 | F15: ='Raw Financials'!F37 -> 17695 | G15: ='Raw Financials'!G37 -> 29421 | H15: ='Raw Financials'!H37 -> 29150 | I15: ='Raw Financials'!I37 -> 27160 | J15: ='Raw Financials'!J37 -> 26911 | ... M15: ='Raw Financials'!M37 -> 29130 | N15: =M15-'Annual Cash Flow'!N19-'Annual P&L'!N19*(1-Assumptions!C28-Assumptions!C30) -> 28217.93 | O15: =N15-'Annual Cash Flow'!O19-'Annual P&L'!O19*(1-Assumptions!D28-Assumptions!D30) -> 27264.063 | P15: =O15-'Annual Cash Flow'!P19-'Annual P&L'!P19*(1-Assumptions!E28-Assumptions!E30) -> 26259.257 | Q15: =P15-'Annual Cash Flow'!Q19-'Annual P&L'!Q19*(1-Assumptions!F28-Assumptions!F30) -> 25207.583
A16: Other non-current assets | B16: ₹ cr | C16: =IF(OR('Raw Financials'!C39="",C12=""),"",'Raw Financials'!C39-SUM(C12:C15)) -> 4038.9 | D16: =IF(OR('Raw Financials'!D39="",D12=""),"",'Raw Financials'!D39-SUM(D12:D15)) -> 7925.8 | E16: =IF(OR('Raw Financials'!E39="",E12=""),"",'Raw Financials'!E39-SUM(E12:E15)) -> 4289.7 | F16: =IF(OR('Raw Financials'!F39="",F12=""),"",'Raw Financials'!F39-SUM(F12:F15)) -> 5684 | G16: =IF(OR('Raw Financials'!G39="",G12=""),"",'Raw Financials'!G39-SUM(G12:G15)) -> 9126 | H16: =IF(OR('Raw Financials'!H39="",H12=""),"",'Raw Financials'!H39-SUM(H12:H15)) -> 9255 | I16: =IF(OR('Raw Financials'!I39="",I12=""),"",'Raw Financials'!I39-SUM(I12:I15)) -> 5786 | J16: =IF(OR('Raw Financials'!J39="",J12=""),"",'Raw Financials'!J39-SUM(J12:J15)) -> 5175 | ... M16: =IF(OR('Raw Financials'!M39="",M12=""),"",'Raw Financials'!M39-SUM(M12:M15)) -> 8277 | N16: ='Annual P&L'!N7*Assumptions!C25 -> 5527.6962 | O16: ='Annual P&L'!O7*Assumptions!D25 -> 5812.6249 | P16: ='Annual P&L'!P7*Assumptions!E25 -> 6158.4917 | Q16: ='Annual P&L'!Q7*Assumptions!F25 -> 6485.3237
A17: Total assets | B17: ₹ cr | C17: ='Raw Financials'!C39 -> 39767.3 | D17: ='Raw Financials'!D39 -> 46432.3 | E17: ='Raw Financials'!E39 -> 48435.1 | F17: ='Raw Financials'!F39 -> 58897 | G17: ='Raw Financials'!G39 -> 83216 | H17: ='Raw Financials'!H39 -> 87702 | I17: ='Raw Financials'!I39 -> 89033 | J17: ='Raw Financials'!J39 -> 93411 | ... M17: ='Raw Financials'!M39 -> 116258 | N17: =SUM(N12:N16) -> 120006.65 | O17: =SUM(O12:O16) -> 124857.17 | P17: =SUM(P12:P16) -> 130439.06 | Q17: =SUM(Q12:Q16) -> 136412.24
A18: Current operating liabilities | B18: ₹ cr | C18: ='Raw Financials'!C40 -> 9508.5 | D18: ='Raw Financials'!D40 -> 11147.7 | E18: ='Raw Financials'!E40 -> 9914.3 | F18: ='Raw Financials'!F40 -> 11148 | G18: ='Raw Financials'!G40 -> 20889 | H18: ='Raw Financials'!H40 -> 16755 | I18: ='Raw Financials'!I40 -> 18014 | J18: ='Raw Financials'!J40 -> 20420 | ... M18: ='Raw Financials'!M40 -> 29828 | N18: ='Annual P&L'!N7*Assumptions!C24 -> 31093.291 | O18: ='Annual P&L'!O7*Assumptions!D24 -> 33236.291 | P18: ='Annual P&L'!P7*Assumptions!E24 -> 35816.491 | Q18: ='Annual P&L'!Q7*Assumptions!F24 -> 38561.384
A19: Short-term borrowings | B19: ₹ cr | C19: ='Raw Financials'!C41 -> 0 | D19: ='Raw Financials'!D41 -> 0 | E19: ='Raw Financials'!E41 -> 0 | F19: ='Raw Financials'!F41 -> 0 | G19: ='Raw Financials'!G41 -> 0 | H19: ='Raw Financials'!H41 -> 0 | I19: ='Raw Financials'!I41 -> 0 | J19: ='Raw Financials'!J41 -> 0 | ... M19: ='Raw Financials'!M41 -> 0 | N19: =N22*Assumptions!C34 -> 11.8 | O19: =O22*Assumptions!D34 -> 0 | P19: =P22*Assumptions!E34 -> 0 | Q19: =Q22*Assumptions!F34 -> 0
A20: Long-term borrowings | B20: ₹ cr | C20: ='Raw Financials'!C42 -> 0 | D20: ='Raw Financials'!D42 -> 0 | E20: ='Raw Financials'!E42 -> 0 | F20: ='Raw Financials'!F42 -> 0 | G20: ='Raw Financials'!G42 -> 0 | H20: ='Raw Financials'!H42 -> 0 | I20: ='Raw Financials'!I42 -> 0 | J20: ='Raw Financials'!J42 -> 0 | ... M20: ='Raw Financials'!M42 -> 0 | N20: =N22-N19 -> 47.2 | O20: =O22-O19 -> 0 | P20: =P22-P19 -> 0 | Q20: =Q22-Q19 -> 0
A21: Borrowings — maturity split not reported | B21: ₹ cr | C21: ='Raw Financials'!C43 -> 973.2 | D21: ='Raw Financials'!D43 -> 541.7 | E21: ='Raw Financials'!E43 -> 437.1 | F21: ='Raw Financials'!F43 -> 3986 | G21: ='Raw Financials'!G43 -> 5092 | H21: ='Raw Financials'!H43 -> 3907 | I21: ='Raw Financials'!I43 -> 3985 | J21: ='Raw Financials'!J43 -> 2251 | ... M21: ='Raw Financials'!M43 -> 159 | N21: =0 -> 0 | O21: =0 -> 0 | P21: =0 -> 0 | Q21: =0 -> 0
A22: Total borrowings | B22: ₹ cr | C22: =SUM(C19:C21) -> 973.2 | D22: =SUM(D19:D21) -> 541.7 | E22: =SUM(E19:E21) -> 437.1 | F22: =SUM(F19:F21) -> 3986 | G22: =SUM(G19:G21) -> 5092 | H22: =SUM(H19:H21) -> 3907 | I22: =SUM(I19:I21) -> 3985 | J22: =SUM(J19:J21) -> 2251 | ... M22: =SUM(M19:M21) -> 159 | N22: =MAX(0,M22+Assumptions!C33) -> 59 | O22: =MAX(0,N22+Assumptions!D33) -> 0 | P22: =MAX(0,O22+Assumptions!E33) -> 0 | Q22: =MAX(0,P22+Assumptions!F33) -> 0
A23: Lease liabilities | B23: ₹ cr | C23: ='Raw Financials'!C44 -> 0 | D23: ='Raw Financials'!D44 -> 0 | E23: ='Raw Financials'!E44 -> 0 | F23: ='Raw Financials'!F44 -> 0 | G23: ='Raw Financials'!G44 -> 0 | H23: ='Raw Financials'!H44 -> 0 | I23: ='Raw Financials'!I44 -> 2358 | J23: ='Raw Financials'!J44 -> 2535 | ... M23: ='Raw Financials'!M44 -> 5056 | N23: =M23+'Annual Cash Flow'!N25+'Annual Cash Flow'!N26 -> 5703.1089 | O23: =N23+'Annual Cash Flow'!O25+'Annual Cash Flow'!O26 -> 6350.9871 | P23: =O23+'Annual Cash Flow'!P25+'Annual Cash Flow'!P26 -> 7025.5765 | Q23: =P23+'Annual Cash Flow'!Q25+'Annual Cash Flow'!Q26 -> 7723.8094
A24: Other non-current liabilities | B24: ₹ cr | C24: ='Raw Financials'!C45 -> 1263.5 | D24: ='Raw Financials'!D45 -> 1252.5 | E24: ='Raw Financials'!E45 -> 1266.9 | F24: ='Raw Financials'!F45 -> 1538 | G24: ='Raw Financials'!G45 -> 2548 | H24: ='Raw Financials'!H45 -> 2683 | I24: ='Raw Financials'!I45 -> 2670 | J24: ='Raw Financials'!J45 -> 2807 | ... M24: ='Raw Financials'!M45 -> 6018 | N24: =M24 -> 6018 | O24: =N24 -> 6018 | P24: =O24 -> 6018 | Q24: =P24 -> 6018
A25: Total liabilities | B25: ₹ cr | C25: =IF('Raw Financials'!C46="",C17-'Raw Financials'!C48,'Raw Financials'!C46) -> 11745.2 | D25: =IF('Raw Financials'!D46="",D17-'Raw Financials'!D48,'Raw Financials'!D46) -> 12941.9 | E25: =IF('Raw Financials'!E46="",E17-'Raw Financials'!E48,'Raw Financials'!E46) -> 11618.3 | F25: =IF('Raw Financials'!F46="",F17-'Raw Financials'!F48,'Raw Financials'!F46) -> 16672 | G25: =IF('Raw Financials'!G46="",G17-'Raw Financials'!G48,'Raw Financials'!G46) -> 31002 | H25: =IF('Raw Financials'!H46="",H17-'Raw Financials'!H48,'Raw Financials'!H46) -> 25612 | I25: =IF('Raw Financials'!I46="",I17-'Raw Financials'!I48,'Raw Financials'!I46) -> 27027 | J25: =IF('Raw Financials'!J46="",J17-'Raw Financials'!J48,'Raw Financials'!J46) -> 28013 | ... M25: =IF('Raw Financials'!M46="",M17-'Raw Financials'!M48,'Raw Financials'!M46) -> 41061 | N25: =SUM(N18,N22:N24) -> 42873.4 | O25: =SUM(O18,O22:O24) -> 45605.278 | P25: =SUM(P18,P22:P24) -> 48860.068 | Q25: =SUM(Q18,Q22:Q24) -> 52303.194
A26: Share capital | B26: ₹ cr | C26: ='Raw Financials'!C47 -> 0 | D26: ='Raw Financials'!D47 -> 0 | E26: ='Raw Financials'!E47 -> 0 | F26: ='Raw Financials'!F47 -> 0 | G26: ='Raw Financials'!G47 -> 0 | H26: ='Raw Financials'!H47 -> 0 | I26: ='Raw Financials'!I47 -> 0 | J26: ='Raw Financials'!J47 -> 0 | ... M26: ='Raw Financials'!M47 -> 0 | N26: =M26 -> 0 | O26: =N26 -> 0 | P26: =O26 -> 0 | Q26: =P26 -> 0
A27: Retained earnings / cumulative profit proxy | B27: ₹ cr | C27: =SUM('Annual P&L'!$C$29:C29)+SUM('Annual Cash Flow'!$C$28:C28) -> 4657 | D27: =SUM('Annual P&L'!$C$29:D29)+SUM('Annual Cash Flow'!$C$28:D28) -> 9046 | E27: =SUM('Annual P&L'!$C$29:E29)+SUM('Annual Cash Flow'!$C$28:E28) -> 15795 | F27: =SUM('Annual P&L'!$C$29:F29)+SUM('Annual Cash Flow'!$C$28:F28) -> 24597 | G27: =SUM('Annual P&L'!$C$29:G29)+SUM('Annual Cash Flow'!$C$28:G28) -> 34034 | H27: =SUM('Annual P&L'!$C$29:H29)+SUM('Annual Cash Flow'!$C$28:H28) -> 41923 | I27: =SUM('Annual P&L'!$C$29:I29)+SUM('Annual Cash Flow'!$C$28:I28) -> 44033 | J27: =SUM('Annual P&L'!$C$29:J29)+SUM('Annual Cash Flow'!$C$28:J28) -> 45889 | ... M27: =SUM('Annual P&L'!$C$29:M29)+SUM('Annual Cash Flow'!$C$28:M28) -> 51401 | N27: =M27+'Annual P&L'!N29+'Annual Cash Flow'!N28 -> 53337.25 | O27: =N27+'Annual P&L'!O29+'Annual Cash Flow'!O28 -> 55455.89 | P27: =O27+'Annual P&L'!P29+'Annual Cash Flow'!P28 -> 57782.987 | Q27: =P27+'Annual P&L'!Q29+'Annual Cash Flow'!Q28 -> 60313.049
A28: Other reserves / equity | B28: ₹ cr | C28: =C29-C26-C27 -> 23365.1 | D28: =D29-D26-D27 -> 24444.4 | E28: =E29-E26-E27 -> 21021.8 | F28: =F29-F26-F27 -> 17173 | G28: =G29-G26-G27 -> 17652 | H28: =H29-H26-H27 -> 19583 | I28: =I29-I26-I27 -> 17881 | J28: =J29-J26-J27 -> 19516 | ... M28: =M29-M26-M27 -> 23764 | N28: =M28+Assumptions!C36 -> 23764 | O28: =N28+Assumptions!D36 -> 23764 | P28: =O28+Assumptions!E36 -> 23764 | Q28: =P28+Assumptions!F36 -> 23764
A29: Stockholders equity | B29: ₹ cr | C29: ='Raw Financials'!C48 -> 28022.1 | D29: ='Raw Financials'!D48 -> 33490.4 | E29: ='Raw Financials'!E48 -> 36816.8 | F29: ='Raw Financials'!F48 -> 41770 | G29: ='Raw Financials'!G48 -> 51686 | H29: ='Raw Financials'!H48 -> 61506 | I29: ='Raw Financials'!I48 -> 61914 | J29: ='Raw Financials'!J48 -> 65405 | ... M29: ='Raw Financials'!M48 -> 75165 | N29: =SUM(N26:N28) -> 77101.25 | O29: =SUM(O26:O28) -> 79219.89 | P29: =SUM(P26:P28) -> 81546.987 | Q29: =SUM(Q26:Q28) -> 84077.049
A30: Non-controlling interests | B30: ₹ cr | C30: =C17-C25-C29 -> 0 | D30: =D17-D25-D29 -> 0 | E30: =E17-E25-E29 -> 0 | F30: =F17-F25-F29 -> 455 | G30: =G17-G25-G29 -> 528 | H30: =H17-H25-H29 -> 584 | I30: =I17-I25-I29 -> 92 | J30: =J17-J25-J29 -> -7 | ... M30: =M17-M25-M29 -> 32 | N30: =M30 -> 32 | O30: =N30 -> 32 | P30: =O30 -> 32 | Q30: =P30 -> 32
A31: Total equity | B31: ₹ cr | C31: =SUM(C29:C30) -> 28022.1 | D31: =SUM(D29:D30) -> 33490.4 | E31: =SUM(E29:E30) -> 36816.8 | F31: =SUM(F29:F30) -> 42225 | G31: =SUM(G29:G30) -> 52214 | H31: =SUM(H29:H30) -> 62090 | I31: =SUM(I29:I30) -> 62006 | J31: =SUM(J29:J30) -> 65398 | ... Q31: =SUM(Q29:Q30) -> 84109.049
A32: Total liabilities & equity | B32: ₹ cr | C32: =C25+C31 -> 39767.3 | D32: =D25+D31 -> 46432.3 | E32: =E25+E31 -> 48435.1 | F32: =F25+F31 -> 58897 | G32: =G25+G31 -> 83216 | H32: =H25+H31 -> 87702 | I32: =I25+I31 -> 89033 | J32: =J25+J31 -> 93411 | ... M32: =M25+M31 -> 116258 | N32: =SUM(N25,N31) -> 120006.65 | O32: =SUM(O25,O31) -> 124857.17 | P32: =SUM(P25,P31) -> 130439.06 | Q32: =SUM(Q25,Q31) -> 136412.24
A33: Balance check | B33: ₹ cr | C33: =ROUND(C17-C32,1) -> 0 | D33: =ROUND(D17-D32,1) -> 0 | E33: =ROUND(E17-E32,1) -> 0 | F33: =ROUND(F17-F32,1) -> 0 | G33: =ROUND(G17-G32,1) -> 0 | H33: =ROUND(H17-H32,1) -> 0 | I33: =ROUND(I17-I32,1) -> 0 | J33: =ROUND(J17-J32,1) -> 0 | ... Q33: =ROUND(Q17-Q32,1) -> 0
A34: Net cash / (debt) | B34: ₹ cr | C34: =C7-C22 -> -243.9 | D34: =D7-D22 -> 774.8 | E34: =E7-E22 -> 1256.8 | F34: =F7-F22 -> 1943 | G34: =G7-G22 -> -249 | H34: =H7-H22 -> 2608 | I34: =I7-I22 -> 6525 | J34: =J7-J22 -> 6814 | ... Q34: =Q7-Q22 -> 16169.033

Sheet Annual Cash Flow
A1: Annual Cash Flow Statement
A2: Historical totals are reported controls; closing cash is anchored to the annual balance sheet
A5: Metric | B5: Units | C5: FY16A | D5: FY17A | E5: FY18A | F5: FY19A | G5: FY20A | H5: FY21A | I5: FY22A | J5: FY23A | K5: FY24A | L5: FY25A | M5: FY26A | N5: FY27E | O5: FY28E | P5: FY29E | Q5: FY30E
A7: Net income attributable | B7: ₹ cr | C7: ='Annual P&L'!C29 -> 7354 | D7: ='Annual P&L'!D29 -> 8457 | E7: ='Annual P&L'!E29 -> 8780 | F7: ='Annual P&L'!F29 -> 10123 | G7: ='Annual P&L'!G29 -> 11062 | H7: ='Annual P&L'!H29 -> 11145 | I7: ='Annual P&L'!I29 -> 13499 | J7: ='Annual P&L'!J29 -> 14851 | ... Q7: ='Annual P&L'!Q29 -> 25300.616
A8: D&A | B8: ₹ cr | C8: ='Annual P&L'!C19 -> 506 | D8: ='Annual P&L'!D19 -> 835 | E8: ='Annual P&L'!E19 -> 1453 | F8: ='Annual P&L'!F19 -> 2147 | G8: ='Annual P&L'!G19 -> 2841 | H8: ='Annual P&L'!H19 -> 4611 | I8: ='Annual P&L'!I19 -> 4326 | J8: ='Annual P&L'!J19 -> 4145 | ... Q8: ='Annual P&L'!Q19 -> 5258.3706
A9: Other non-cash items / operating reconciliation | B9: ₹ cr | C9: =C15-SUM(C7:C8,C10:C14) -> -4037 | D9: =D15-SUM(D7:D8,D10:D14) -> 2614.5 | E9: =E15-SUM(E7:E8,E10:E14) -> -3330.6 | F9: =F15-SUM(F7:F8,F10:F14) -> 139.2 | G9: =G15-SUM(G7:G8,G10:G14) -> -3127 | H9: =H15-SUM(H7:H8,H10:H14) -> 7500 | I9: =I15-SUM(I7:I8,I10:I14) -> -2044 | J9: =J15-SUM(J7:J8,J10:J14) -> 566 | ... M9: =M15-SUM(M7:M8,M10:M14) -> -149 | N9: =0 -> 0 | O9: =0 -> 0 | P9: =0 -> 0 | Q9: =0 -> 0
A10: Change in trade receivables | B10: ₹ cr | C10: =0 -> 0 | D10: =-('Annual Balance Sheet'!D8-'Annual Balance Sheet'!C8) -> -580.1 | E10: =-('Annual Balance Sheet'!E8-'Annual Balance Sheet'!D8) -> -1338 | F10: =-('Annual Balance Sheet'!F8-'Annual Balance Sheet'!E8) -> -2066.6 | G10: =-('Annual Balance Sheet'!G8-'Annual Balance Sheet'!F8) -> -2428 | H10: =-('Annual Balance Sheet'!H8-'Annual Balance Sheet'!G8) -> 471 | I10: =-('Annual Balance Sheet'!I8-'Annual Balance Sheet'!H8) -> -1813 | J10: =-('Annual Balance Sheet'!J8-'Annual Balance Sheet'!I8) -> -4096 | K10: =-('Annual Balance Sheet'!K8-'Annual Balance Sheet'!J8) -> 89 | ... Q10: =-('Annual Balance Sheet'!Q8-'Annual Balance Sheet'!P8) -> -1764.2595
A11: Change in unbilled receivables | B11: ₹ cr | C11: =0 -> 0 | D11: =-('Annual Balance Sheet'!D9-'Annual Balance Sheet'!C9) -> 500.3 | E11: =-('Annual Balance Sheet'!E9-'Annual Balance Sheet'!D9) -> -116.9 | F11: =-('Annual Balance Sheet'!F9-'Annual Balance Sheet'!E9) -> 2618.1 | G11: =-('Annual Balance Sheet'!G9-'Annual Balance Sheet'!F9) -> -3638 | H11: =-('Annual Balance Sheet'!H9-'Annual Balance Sheet'!G9) -> -224 | I11: =-('Annual Balance Sheet'!I9-'Annual Balance Sheet'!H9) -> -1333 | J11: =-('Annual Balance Sheet'!J9-'Annual Balance Sheet'!I9) -> -739 | K11: =-('Annual Balance Sheet'!K9-'Annual Balance Sheet'!J9) -> -104 | ... Q11: =-('Annual Balance Sheet'!Q9-'Annual Balance Sheet'!P9) -> -760.22573
A12: Change in other current assets | B12: ₹ cr | C12: =0 -> 0 | D12: =-('Annual Balance Sheet'!D11-'Annual Balance Sheet'!C11) -> -573 | E12: =-('Annual Balance Sheet'!E11-'Annual Balance Sheet'!D11) -> 463.4 | F12: =-('Annual Balance Sheet'!F11-'Annual Balance Sheet'!E11) -> -4100.2 | G12: =-('Annual Balance Sheet'!G11-'Annual Balance Sheet'!F11) -> 1340 | H12: =-('Annual Balance Sheet'!H11-'Annual Balance Sheet'!G11) -> 243 | I12: =-('Annual Balance Sheet'!I11-'Annual Balance Sheet'!H11) -> -450 | J12: =-('Annual Balance Sheet'!J11-'Annual Balance Sheet'!I11) -> 128 | K12: =-('Annual Balance Sheet'!K11-'Annual Balance Sheet'!J11) -> -463 | ... Q12: =-('Annual Balance Sheet'!Q11-'Annual Balance Sheet'!P11) -> -564.67403
A13: Change in current operating liabilities | B13: ₹ cr | C13: =0 -> 0 | D13: =+('Annual Balance Sheet'!D18-'Annual Balance Sheet'!C18) -> 1639.2 | E13: =+('Annual Balance Sheet'!E18-'Annual Balance Sheet'!D18) -> -1233.4 | F13: =+('Annual Balance Sheet'!F18-'Annual Balance Sheet'!E18) -> 1233.7 | G13: =+('Annual Balance Sheet'!G18-'Annual Balance Sheet'!F18) -> 9741 | H13: =+('Annual Balance Sheet'!H18-'Annual Balance Sheet'!G18) -> -4134 | I13: =+('Annual Balance Sheet'!I18-'Annual Balance Sheet'!H18) -> 1259 | J13: =+('Annual Balance Sheet'!J18-'Annual Balance Sheet'!I18) -> 2406 | K13: =+('Annual Balance Sheet'!K18-'Annual Balance Sheet'!J18) -> 1112 | ... M13: =+('Annual Balance Sheet'!M18-'Annual Balance Sheet'!L18) -> 5357 | N13: ='Annual Balance Sheet'!N18-'Annual Balance Sheet'!M18 -> 1265.2909 | O13: ='Annual Balance Sheet'!O18-'Annual Balance Sheet'!N18 -> 2143.0002 | P13: ='Annual Balance Sheet'!P18-'Annual Balance Sheet'!O18 -> 2580.2004 | Q13: ='Annual Balance Sheet'!Q18-'Annual Balance Sheet'!P18 -> 2744.8928
A14: Change in other non-current operating assets / liabilities | B14: ₹ cr | C14: =0 -> 0 | D14: =-('Annual Balance Sheet'!D16-'Annual Balance Sheet'!C16)+('Annual Balance Sheet'!D24-'Annual Balance Sheet'!C24) -> -3897.9 | E14: =-('Annual Balance Sheet'!E16-'Annual Balance Sheet'!D16)+('Annual Balance Sheet'!E24-'Annual Balance Sheet'!D24) -> 3650.5 | F14: =-('Annual Balance Sheet'!F16-'Annual Balance Sheet'!E16)+('Annual Balance Sheet'!F24-'Annual Balance Sheet'!E24) -> -1123.2 | G14: =-('Annual Balance Sheet'!G16-'Annual Balance Sheet'!F16)+('Annual Balance Sheet'!G24-'Annual Balance Sheet'!F24) -> -2432 | H14: =-('Annual Balance Sheet'!H16-'Annual Balance Sheet'!G16)+('Annual Balance Sheet'!H24-'Annual Balance Sheet'!G24) -> 6 | I14: =-('Annual Balance Sheet'!I16-'Annual Balance Sheet'!H16)+('Annual Balance Sheet'!I24-'Annual Balance Sheet'!H24) -> 3456 | J14: =-('Annual Balance Sheet'!J16-'Annual Balance Sheet'!I16)+('Annual Balance Sheet'!J24-'Annual Balance Sheet'!I24) -> 748 | K14: =-('Annual Balance Sheet'!K16-'Annual Balance Sheet'!J16)+('Annual Balance Sheet'!K24-'Annual Balance Sheet'!J24) -> 1311 | ... Q14: =-('Annual Balance Sheet'!Q16-'Annual Balance Sheet'!P16)+('Annual Balance Sheet'!Q24-'Annual Balance Sheet'!P24) -> -326.83198
A15: Cash flow from operations | B15: ₹ cr | C15: ='Raw Financials'!C23 -> 3823 | D15: ='Raw Financials'!D23 -> 8995 | E15: ='Raw Financials'!E23 -> 8328 | F15: ='Raw Financials'!F23 -> 8971 | G15: ='Raw Financials'!G23 -> 13359 | H15: ='Raw Financials'!H23 -> 19618 | I15: ='Raw Financials'!I23 -> 16900 | J15: ='Raw Financials'!J23 -> 18009 | ... M15: ='Raw Financials'!M23 -> 19975 | N15: =SUM(N7:N14) -> 26502.88 | O15: =SUM(O7:O14) -> 25185.66 | P15: =SUM(P7:P14) -> 27804.111 | Q15: =SUM(Q7:Q14) -> 29887.889
A16: CFO / net income | B16: x | C16: =IFERROR(C15/C7,"") -> 0.51985314 | D16: =IFERROR(D15/D7,"") -> 1.0636159 | E16: =IFERROR(E15/E7,"") -> 0.94851936 | F16: =IFERROR(F15/F7,"") -> 0.88619974 | G16: =IFERROR(G15/G7,"") -> 1.2076478 | H16: =IFERROR(H15/H7,"") -> 1.7602512 | I16: =IFERROR(I15/I7,"") -> 1.2519446 | J16: =IFERROR(J15/J7,"") -> 1.2126456 | ... M16: =IFERROR(M15/M7,"") -> 1.1505674 | N16: =N15/N7 -> 1.3687738 | O16: =O15/O7 -> 1.1887654 | P16: =P15/P7 -> 1.1947978 | Q16: =Q15/Q7 -> 1.1813107
A17: Capex | B17: ₹ cr | C17: ='Raw Financials'!C27 -> -942 | D17: ='Raw Financials'!D27 -> -3922 | E17: ='Raw Financials'!E27 -> -5321 | F17: ='Raw Financials'!F27 -> -3434 | G17: ='Raw Financials'!G27 -> -1866 | H17: ='Raw Financials'!H27 -> -1904 | I17: ='Raw Financials'!I27 -> -1645 | J17: ='Raw Financials'!J27 -> -1661 | ... M17: ='Raw Financials'!M27 -> -1422 | N17: =-'Annual P&L'!N7*Assumptions!C27 -> -1934.6937 | O17: =-'Annual P&L'!O7*Assumptions!D27 -> -2086.5833 | P17: =-'Annual P&L'!P7*Assumptions!E27 -> -2268.918 | Q17: =-'Annual P&L'!Q7*Assumptions!F27 -> -2453.9063
A18: Reported capex control | B18: ₹ cr | C18: =C17 -> -942 | D18: =D17 -> -3922 | E18: =E17 -> -5321 | F18: =F17 -> -3434 | G18: =G17 -> -1866 | H18: =H17 -> -1904 | I18: =I17 -> -1645 | J18: =J17 -> -1661 | ... Q18: =Q17 -> -2453.9063
A19: Acquisitions / net cash acquired | B19: ₹ cr | C19: ='Raw Financials'!C28 -> -1183 | D19: ='Raw Financials'!D28 -> -488 | E19: ='Raw Financials'!E28 -> -107 | F19: ='Raw Financials'!F28 -> -2828 | G19: ='Raw Financials'!G28 -> -6091 | H19: ='Raw Financials'!H28 -> -1211 | I19: ='Raw Financials'!I28 -> 40 | J19: ='Raw Financials'!J28 -> -738 | ... M19: ='Raw Financials'!M28 -> -160 | N19: =-Assumptions!C32 -> 0 | O19: =-Assumptions!D32 -> 0 | P19: =-Assumptions!E32 -> 0 | Q19: =-Assumptions!F32 -> 0
A20: Change in treasury investments | B20: ₹ cr | C20: =0 -> 0 | D20: =-('Annual Balance Sheet'!D10-'Annual Balance Sheet'!C10) -> -241.7 | E20: =-('Annual Balance Sheet'!E10-'Annual Balance Sheet'!D10) -> 3281.5 | F20: =-('Annual Balance Sheet'!F10-'Annual Balance Sheet'!E10) -> 2621.8 | G20: =-('Annual Balance Sheet'!G10-'Annual Balance Sheet'!F10) -> -5068 | H20: =-('Annual Balance Sheet'!H10-'Annual Balance Sheet'!G10) -> -3445 | I20: =-('Annual Balance Sheet'!I10-'Annual Balance Sheet'!H10) -> 2602 | J20: =-('Annual Balance Sheet'!J10-'Annual Balance Sheet'!I10) -> -2274 | K20: =-('Annual Balance Sheet'!K10-'Annual Balance Sheet'!J10) -> -4885 | ... Q20: =-('Annual Balance Sheet'!Q10-'Annual Balance Sheet'!P10) -> -1502.0254
A21: Other investing / reclassification | B21: ₹ cr | C21: =C22-SUM(C17,C19,C20) -> -64 | D21: =D22-SUM(D17,D19,D20) -> 834.7 | E21: =E22-SUM(E17,E19,E20) -> -136.5 | F21: =F22-SUM(F17,F19,F20) -> 567.2 | G21: =G22-SUM(G17,G19,G20) -> 651 | H21: =H22-SUM(H17,H19,H20) -> 830 | I21: =I22-SUM(I17,I19,I20) -> 480 | J21: =J22-SUM(J17,J19,J20) -> 742 | ... M21: =M22-SUM(M17,M19,M20) -> 1752 | N21: =0 -> 0 | O21: =0 -> 0 | P21: =0 -> 0 | Q21: =0 -> 0
A22: Cash flow from investing | B22: ₹ cr | C22: ='Raw Financials'!C24 -> -2189 | D22: ='Raw Financials'!D24 -> -3817 | E22: ='Raw Financials'!E24 -> -2283 | F22: ='Raw Financials'!F24 -> -3073 | G22: ='Raw Financials'!G24 -> -12374 | H22: ='Raw Financials'!H24 -> -5730 | I22: ='Raw Financials'!I24 -> 1477 | J22: ='Raw Financials'!J24 -> -3931 | ... M22: ='Raw Financials'!M24 -> -1473 | N22: =SUM(N17,N19:N21) -> -5055.2505 | O22: =SUM(O17,O19:O21) -> -3402.7344 | P22: =SUM(P17,P19:P21) -> -3868.0132 | Q22: =SUM(Q17,Q19:Q21) -> -3955.9317
A23: Short-term borrowings change | B23: ₹ cr | C23: =0 -> 0 | D23: ='Annual Balance Sheet'!D19-'Annual Balance Sheet'!C19 -> 0 | E23: ='Annual Balance Sheet'!E19-'Annual Balance Sheet'!D19 -> 0 | F23: ='Annual Balance Sheet'!F19-'Annual Balance Sheet'!E19 -> 0 | G23: ='Annual Balance Sheet'!G19-'Annual Balance Sheet'!F19 -> 0 | H23: ='Annual Balance Sheet'!H19-'Annual Balance Sheet'!G19 -> 0 | I23: ='Annual Balance Sheet'!I19-'Annual Balance Sheet'!H19 -> 0 | J23: ='Annual Balance Sheet'!J19-'Annual Balance Sheet'!I19 -> 0 | K23: ='Annual Balance Sheet'!K19-'Annual Balance Sheet'!J19 -> 0 | ... Q23: ='Annual Balance Sheet'!Q19-'Annual Balance Sheet'!P19 -> 0
A24: Long-term / unallocated borrowings change | B24: ₹ cr | C24: =0 -> 0 | D24: =('Annual Balance Sheet'!D20+'Annual Balance Sheet'!D21)-('Annual Balance Sheet'!C20+'Annual Balance Sheet'!C21) -> -431.5 | E24: =('Annual Balance Sheet'!E20+'Annual Balance Sheet'!E21)-('Annual Balance Sheet'!D20+'Annual Balance Sheet'!D21) -> -104.6 | F24: =('Annual Balance Sheet'!F20+'Annual Balance Sheet'!F21)-('Annual Balance Sheet'!E20+'Annual Balance Sheet'!E21) -> 3548.9 | G24: =('Annual Balance Sheet'!G20+'Annual Balance Sheet'!G21)-('Annual Balance Sheet'!F20+'Annual Balance Sheet'!F21) -> 1106 | H24: =('Annual Balance Sheet'!H20+'Annual Balance Sheet'!H21)-('Annual Balance Sheet'!G20+'Annual Balance Sheet'!G21) -> -1185 | I24: =('Annual Balance Sheet'!I20+'Annual Balance Sheet'!I21)-('Annual Balance Sheet'!H20+'Annual Balance Sheet'!H21) -> 78 | J24: =('Annual Balance Sheet'!J20+'Annual Balance Sheet'!J21)-('Annual Balance Sheet'!I20+'Annual Balance Sheet'!I21) -> -1734 | K24: =('Annual Balance Sheet'!K20+'Annual Balance Sheet'!K21)-('Annual Balance Sheet'!J20+'Annual Balance Sheet'!J21) -> 76 | ... M24: =('Annual Balance Sheet'!M20+'Annual Balance Sheet'!M21)-('Annual Balance Sheet'!L20+'Annual Balance Sheet'!L21) -> -2132 | N24: ='Annual Balance Sheet'!N22-'Annual Balance Sheet'!M22-N23 -> -111.8 | O24: ='Annual Balance Sheet'!O22-'Annual Balance Sheet'!N22-O23 -> -47.2 | P24: ='Annual Balance Sheet'!P22-'Annual Balance Sheet'!O22-P23 -> 0 | Q24: ='Annual Balance Sheet'!Q22-'Annual Balance Sheet'!P22-Q23 -> 0
A25: ROU asset additions (non-cash reference) | B25: ₹ cr | C25: =0 -> 0 | D25: =0 -> 0 | E25: =0 -> 0 | F25: =0 -> 0 | G25: =0 -> 0 | H25: =0 -> 0 | I25: =0 -> 0 | J25: =0 -> 0 | ... M25: =0 -> 0 | N25: ='Annual P&L'!N7*Assumptions!C29 -> 1658.3089 | O25: ='Annual P&L'!O7*Assumptions!D29 -> 1788.5 | P25: ='Annual P&L'!P7*Assumptions!E29 -> 1944.7869 | Q25: ='Annual P&L'!Q7*Assumptions!F29 -> 2103.3482
A26: Lease principal paid | B26: ₹ cr | C26: =0 -> 0 | D26: =0 -> 0 | E26: =0 -> 0 | F26: =0 -> 0 | G26: =0 -> 0 | H26: =0 -> 0 | I26: =0 -> 0 | J26: =0 -> 0 | ... M26: =0 -> 0 | N26: =-'Annual Balance Sheet'!M23*Assumptions!C31 -> -1011.2 | O26: =-'Annual Balance Sheet'!N23*Assumptions!D31 -> -1140.6218 | P26: =-'Annual Balance Sheet'!O23*Assumptions!E31 -> -1270.1974 | Q26: =-'Annual Balance Sheet'!P23*Assumptions!F31 -> -1405.1153
A27: Equity issuance / buybacks | B27: ₹ cr | C27: =0 -> 0 | D27: =0 -> 0 | E27: =0 -> 0 | F27: =0 -> 0 | G27: =0 -> 0 | H27: =0 -> 0 | I27: =0 -> 0 | J27: =0 -> 0 | ... Q27: =0 -> 0
A28: Dividends paid | B28: ₹ cr | C28: ='Raw Financials'!C26 -> -2697 | D28: ='Raw Financials'!D26 -> -4068 | E28: ='Raw Financials'!E26 -> -2031 | F28: ='Raw Financials'!F26 -> -1321 | G28: ='Raw Financials'!G26 -> -1625 | H28: ='Raw Financials'!H26 -> -3256 | I28: ='Raw Financials'!I26 -> -11389 | J28: ='Raw Financials'!J26 -> -12995 | ... M28: ='Raw Financials'!M26 -> -14618 | N28: =-'Annual P&L'!N35*'Annual P&L'!N31/10 -> -17426.247 | O28: =-'Annual P&L'!O35*'Annual P&L'!O31/10 -> -19067.761 | P28: =-'Annual P&L'!P35*'Annual P&L'!P31/10 -> -20943.879 | Q28: =-'Annual P&L'!Q35*'Annual P&L'!Q31/10 -> -22770.555
A29: Other financing / reclassification | B29: ₹ cr | C29: =C30-SUM(C23:C28) -> 460 | D29: =D30-SUM(D23:D28) -> -33.5 | E29: =E30-SUM(E23:E28) -> -3578.4 | F29: =F30-SUM(F23:F28) -> -3689.9 | G29: =G30-SUM(G23:G28) -> -2649 | H29: =H30-SUM(H23:H28) -> -6751 | I29: =I30-SUM(I23:I28) -> -3197 | J29: =J30-SUM(J23:J28) -> -1152 | ... M29: =M30-SUM(M23:M28) -> -2619 | N29: =0 -> 0 | O29: =0 -> 0 | P29: =0 -> 0 | Q29: =0 -> 0
A30: Cash flow from financing | B30: ₹ cr | C30: ='Raw Financials'!C25 -> -2237 | D30: ='Raw Financials'!D25 -> -4533 | E30: ='Raw Financials'!E25 -> -5714 | F30: ='Raw Financials'!F25 -> -1462 | G30: ='Raw Financials'!G25 -> -3168 | H30: ='Raw Financials'!H25 -> -11192 | I30: ='Raw Financials'!I25 -> -14508 | J30: ='Raw Financials'!J25 -> -15881 | ... M30: ='Raw Financials'!M25 -> -19369 | N30: =SUM(N23:N24,N26:N29) -> -18537.447 | O30: =SUM(O23:O24,O26:O29) -> -20267.383 | P30: =SUM(P23:P24,P26:P29) -> -22214.076 | Q30: =SUM(Q23:Q24,Q26:Q29) -> -24175.67
A31: Net cash flow before FX / basis | B31: ₹ cr | C31: =SUM(C15,C22,C30) -> -603 | D31: =SUM(D15,D22,D30) -> 645 | E31: =SUM(E15,E22,E30) -> 331 | F31: =SUM(F15,F22,F30) -> 4436 | G31: =SUM(G15,G22,G30) -> -2183 | H31: =SUM(H15,H22,H30) -> 2696 | I31: =SUM(I15,I22,I30) -> 3869 | J31: =SUM(J15,J22,J30) -> -1803 | ... Q31: =SUM(Q15,Q22,Q30) -> 1756.2869
A32: FX / accounting-basis cash reconciliation | B32: ₹ cr | C32: =C36-C34-C31 -> 603 | D32: =D36-D34-D31 -> -57.8 | E32: =E36-E34-E31 -> 46.4 | F32: =F36-F34-F31 -> -200.9 | G32: =G36-G34-G31 -> 1097 | H32: =H36-H34-H31 -> -1024 | I32: =I36-I34-I31 -> 126 | J32: =J36-J34-J31 -> 358 | ... M32: =M36-M34-M31 -> 887 | N32: =0 -> 0 | O32: =0 -> 0 | P32: =0 -> 0 | Q32: =0 -> 0
A33: Net change in cash | B33: ₹ cr | C33: =C31+C32 -> 0 | D33: =D31+D32 -> 587.2 | E33: =E31+E32 -> 377.4 | F33: =F31+F32 -> 4235.1 | G33: =G31+G32 -> -1086 | H33: =H31+H32 -> 1672 | I33: =I31+I32 -> 3995 | J33: =J31+J32 -> -1445 | ... Q33: =Q31+Q32 -> 1756.2869
A34: Opening cash | B34: ₹ cr | C34: ='Annual Balance Sheet'!C7-C33 -> 729.3 | D34: ='Annual Balance Sheet'!C7 -> 729.3 | E34: ='Annual Balance Sheet'!D7 -> 1316.5 | F34: ='Annual Balance Sheet'!E7 -> 1693.9 | G34: ='Annual Balance Sheet'!F7 -> 5929 | H34: ='Annual Balance Sheet'!G7 -> 4843 | I34: ='Annual Balance Sheet'!H7 -> 6515 | J34: ='Annual Balance Sheet'!I7 -> 10510 | K34: ='Annual Balance Sheet'!J7 -> 9065 | ... M34: ='Annual Balance Sheet'!L7 -> 8245 | N34: =M35 -> 8265 | O34: =N35 -> 11175.182 | P34: =O35 -> 12690.724 | Q34: =P35 -> 14412.746
A35: Closing cash per cash flow | B35: ₹ cr | C35: =C34+C33 -> 729.3 | D35: =D34+D33 -> 1316.5 | E35: =E34+E33 -> 1693.9 | F35: =F34+F33 -> 5929 | G35: =G34+G33 -> 4843 | H35: =H34+H33 -> 6515 | I35: =I34+I33 -> 10510 | J35: =J34+J33 -> 9065 | ... Q35: =Q34+Q33 -> 16169.033
A36: Closing cash per balance sheet | B36: ₹ cr | C36: ='Annual Balance Sheet'!C7 -> 729.3 | D36: ='Annual Balance Sheet'!D7 -> 1316.5 | E36: ='Annual Balance Sheet'!E7 -> 1693.9 | F36: ='Annual Balance Sheet'!F7 -> 5929 | G36: ='Annual Balance Sheet'!G7 -> 4843 | H36: ='Annual Balance Sheet'!H7 -> 6515 | I36: ='Annual Balance Sheet'!I7 -> 10510 | J36: ='Annual Balance Sheet'!J7 -> 9065 | ... Q36: ='Annual Balance Sheet'!Q7 -> 16169.033
A37: Cash tie-out | B37: ₹ cr | C37: =ROUND(C35-C36,1) -> 0 | D37: =ROUND(D35-D36,1) -> 0 | E37: =ROUND(E35-E36,1) -> 0 | F37: =ROUND(F35-F36,1) -> 0 | G37: =ROUND(G35-G36,1) -> 0 | H37: =ROUND(H35-H36,1) -> 0 | I37: =ROUND(I35-I36,1) -> 0 | J37: =ROUND(J35-J36,1) -> 0 | ... Q37: =ROUND(Q35-Q36,1) -> 0
A38: Free cash flow | B38: ₹ cr | C38: =C15+C17 -> 2881 | D38: =D15+D17 -> 5073 | E38: =E15+E17 -> 3007 | F38: =F15+F17 -> 5537 | G38: =G15+G17 -> 11493 | H38: =H15+H17 -> 17714 | I38: =I15+I17 -> 15255 | J38: =J15+J17 -> 16348 | ... Q38: =Q15+Q17 -> 27433.982

Sheet Segment Revenue
A1: Segment Revenue
A2: Reported/restated mix FY19–FY26; revenues calculated from mix; forecasts link to the revenue-driver build
A5: Metric | B5: Units | C5: FY16A | D5: FY17A | E5: FY18A | F5: FY19A | G5: FY20A | H5: FY21A | I5: FY22A | J5: FY23A | K5: FY24A | L5: FY25A | M5: FY26A | N5: FY27E | O5: FY28E | P5: FY29E | Q5: FY30E
A7: IT & Business Services mix | B7: % | F7: 0.746 | G7: 0.718 | H7: 0.708 | I7: 0.721 | J7: 0.73 | K7: 0.738 | L7: 0.738 | M7: 0.738 | N7: =IFERROR(('Revenue Drivers'!N20*73.8%/90.8%+'Revenue Drivers'!N23)/'Annual P&L'!N7,"") -> 0.74913283 | O7: =IFERROR(('Revenue Drivers'!O20*73.8%/90.8%+'Revenue Drivers'!O23)/'Annual P&L'!O7,"") -> 0.75187109 | P7: =IFERROR(('Revenue Drivers'!P20*73.8%/90.8%+'Revenue Drivers'!P23)/'Annual P&L'!P7,"") -> 0.75414377 | Q7: =IFERROR(('Revenue Drivers'!Q20*73.8%/90.8%+'Revenue Drivers'!Q23)/'Annual P&L'!Q7,"") -> 0.7558674
A8: IT & Business Services revenue | B8: ₹ cr | C8: =IF(C7="","",C7*'Annual P&L'!C7) | D8: =IF(D7="","",D7*'Annual P&L'!D7) | E8: =IF(E7="","",E7*'Annual P&L'!E7) | F8: =IF(F7="","",F7*'Annual P&L'!F7) -> 45078.542 | G8: =IF(G7="","",G7*'Annual P&L'!G7) -> 50746.804 | H8: =IF(H7="","",H7*'Annual P&L'!H7) -> 53368.332 | I8: =IF(I7="","",I7*'Annual P&L'!I7) -> 61754.371 | J8: =IF(J7="","",J7*'Annual P&L'!J7) -> 74062.88 | ... Q8: =IF(Q7="","",Q7*'Annual P&L'!Q7) -> 132487.7
A9: Engineering & R&D Services mix | B9: % | F9: 0.171 | G9: 0.167 | H9: 0.156 | I9: 0.158 | J9: 0.166 | K9: 0.16 | L9: 0.162 | M9: 0.17 | N9: =IFERROR('Revenue Drivers'!N20/'Annual P&L'!N7*17%/90.8%,"") -> 0.16083036 | O9: =IFERROR('Revenue Drivers'!O20/'Annual P&L'!O7*17%/90.8%,"") -> 0.1605516 | P9: =IFERROR('Revenue Drivers'!P20/'Annual P&L'!P7*17%/90.8%,"") -> 0.16056022 | Q9: =IFERROR('Revenue Drivers'!Q20/'Annual P&L'!Q7*17%/90.8%,"") -> 0.16059459
A10: Engineering & R&D Services revenue | B10: ₹ cr | C10: =IF(C9="","",C9*'Annual P&L'!C7) | D10: =IF(D9="","",D9*'Annual P&L'!D7) | E10: =IF(E9="","",E9*'Annual P&L'!E7) | F10: =IF(F9="","",F9*'Annual P&L'!F7) -> 10333.017 | G10: =IF(G9="","",G9*'Annual P&L'!G7) -> 11803.226 | H10: =IF(H9="","",H9*'Annual P&L'!H7) -> 11759.124 | I10: =IF(I9="","",I9*'Annual P&L'!I7) -> 13532.858 | J10: =IF(J9="","",J9*'Annual P&L'!J7) -> 16841.696 | ... Q10: =IF(Q9="","",Q9*'Annual P&L'!Q7) -> 28148.862
A11: HCLSoftware / P&P mix | B11: % | F11: 0.083 | G11: 0.115 | H11: 0.136 | I11: 0.121 | J11: 0.109 | K11: 0.106 | L11: 0.103 | M11: 0.095 | N11: =IFERROR('Revenue Drivers'!N24/'Annual P&L'!N7,"") -> 0.093045832 | O11: =IFERROR('Revenue Drivers'!O24/'Annual P&L'!O7,"") -> 0.090586338 | P11: =IFERROR('Revenue Drivers'!P24/'Annual P&L'!P7,"") -> 0.08830504 | Q11: =IFERROR('Revenue Drivers'!Q24/'Annual P&L'!Q7,"") -> 0.086547034
A12: HCLSoftware / P&P revenue | B12: ₹ cr | C12: =IF(C11="","",C11*'Annual P&L'!C7) | D12: =IF(D11="","",D11*'Annual P&L'!D7) | E12: =IF(E11="","",E11*'Annual P&L'!E7) | F12: =IF(F11="","",F11*'Annual P&L'!F7) -> 5015.441 | G12: =IF(G11="","",G11*'Annual P&L'!G7) -> 8127.97 | H12: =IF(H11="","",H11*'Annual P&L'!H7) -> 10251.544 | I12: =IF(I11="","",I11*'Annual P&L'!I7) -> 10363.771 | J12: =IF(J11="","",J11*'Annual P&L'!J7) -> 11058.704 | ... Q12: =IF(Q11="","",Q11*'Annual P&L'!Q7) -> 15169.879
A13: Inter-segment mix | B13: % | F13: 0 | G13: 0 | H13: 0 | I13: 0 | J13: -0.005 | K13: -0.004 | L13: -0.003 | M13: -0.003 | N13: =IFERROR('Revenue Drivers'!N25/'Annual P&L'!N7,"") -> -0.0030090271 | O13: =IFERROR('Revenue Drivers'!O25/'Annual P&L'!O7,"") -> -0.0030090271 | P13: =IFERROR('Revenue Drivers'!P25/'Annual P&L'!P7,"") -> -0.0030090271 | Q13: =IFERROR('Revenue Drivers'!Q25/'Annual P&L'!Q7,"") -> -0.0030090271
A14: Inter-segment eliminations | B14: ₹ cr | C14: =IF(C13="","",C13*'Annual P&L'!C7) | D14: =IF(D13="","",D13*'Annual P&L'!D7) | E14: =IF(E13="","",E13*'Annual P&L'!E7) | F14: =IF(F13="","",F13*'Annual P&L'!F7) -> 0 | G14: =IF(G13="","",G13*'Annual P&L'!G7) -> 0 | H14: =IF(H13="","",H13*'Annual P&L'!H7) -> 0 | I14: =IF(I13="","",I13*'Annual P&L'!I7) -> 0 | J14: =IF(J13="","",J13*'Annual P&L'!J7) -> -507.28 | ... Q14: =IF(Q13="","",Q13*'Annual P&L'!Q7) -> -527.41932
A15: Total segment revenue | B15: ₹ cr | C15: =SUM(C8,C10,C12,C14) -> 0 | D15: =SUM(D8,D10,D12,D14) -> 0 | E15: =SUM(E8,E10,E12,E14) -> 0 | F15: =SUM(F8,F10,F12,F14) -> 60427 | G15: =SUM(G8,G10,G12,G14) -> 70678 | H15: =SUM(H8,H10,H12,H14) -> 75379 | I15: =SUM(I8,I10,I12,I14) -> 85651 | J15: =SUM(J8,J10,J12,J14) -> 101456 | ... Q15: =SUM(Q8,Q10,Q12,Q14) -> 175279.02
A16: Annual P&L revenue | B16: ₹ cr | C16: ='Annual P&L'!C7 -> 40913 | D16: ='Annual P&L'!D7 -> 46723 | E16: ='Annual P&L'!E7 -> 50570 | F16: ='Annual P&L'!F7 -> 60427 | G16: ='Annual P&L'!G7 -> 70678 | H16: ='Annual P&L'!H7 -> 75379 | I16: ='Annual P&L'!I7 -> 85651 | J16: ='Annual P&L'!J7 -> 101456 | ... Q16: ='Annual P&L'!Q7 -> 175279.02
A17: Revenue check | B17: ₹ cr | C17: =IF(C15="","",C15-C16) -> -40913 | D17: =IF(D15="","",D15-D16) -> -46723 | E17: =IF(E15="","",E15-E16) -> -50570 | F17: =IF(F15="","",F15-F16) -> 0 | G17: =IF(G15="","",G15-G16) -> 0 | H17: =IF(H15="","",H15-H16) -> -1.4551915e-11 | I17: =IF(I15="","",I15-I16) -> -1.4551915e-11 | J17: =IF(J15="","",J15-J16) -> 0 | ... Q17: =IF(Q15="","",Q15-Q16) -> 0

Sheet Geography & Verticals
A1: Revenue Mix — Geography & Verticals
A2: Operational/company, services-only and IFRS geography are kept separate; blanks mean annual disclosure was unavailable
A5: Metric | B5: Units | C5: FY16A | D5: FY17A | E5: FY18A | F5: FY19A | G5: FY20A | H5: FY21A | I5: FY22A | J5: FY23A | K5: FY24A | L5: FY25A | M5: FY26A | N5: FY27E | O5: FY28E | P5: FY29E | Q5: FY30E
A7: Operational geography mix — Americas / Europe / RoW
A8: Americas | B8: % | D8: 0.616 | E8: 0.625 | F8: 0.644 | H8: 0.628 | I8: 0.629 | J8: 0.641 | K8: 0.647 | L8: 0.651 | N8: =M8 -> 0 | O8: =N8 -> 0 | P8: =O8 -> 0 | Q8: =P8 -> 0
A9: Europe | B9: % | D9: 0.295 | E9: 0.288 | F9: 0.282 | H9: 0.288 | I9: 0.282 | J9: 0.284 | K9: 0.288 | L9: 0.284 | N9: =M9 -> 0 | O9: =N9 -> 0 | P9: =O9 -> 0 | Q9: =P9 -> 0
A10: Rest of World | B10: % | D10: 0.089 | E10: 0.086 | F10: 0.074 | H10: 0.084 | I10: 0.089 | J10: 0.076 | K10: 0.065 | L10: 0.065 | N10: =M10 -> 0 | O10: =N10 -> 0 | P10: =O10 -> 0 | Q10: =P10 -> 0
A11: Mix check | B11: % | C11: =IF(COUNT(C8:C10)=0,"",SUM(C8:C10)) | D11: =IF(COUNT(D8:D10)=0,"",SUM(D8:D10)) -> 1 | E11: =IF(COUNT(E8:E10)=0,"",SUM(E8:E10)) -> 0.999 | F11: =IF(COUNT(F8:F10)=0,"",SUM(F8:F10)) -> 1 | G11: =IF(COUNT(G8:G10)=0,"",SUM(G8:G10)) | H11: =IF(COUNT(H8:H10)=0,"",SUM(H8:H10)) -> 1 | I11: =IF(COUNT(I8:I10)=0,"",SUM(I8:I10)) -> 1 | J11: =IF(COUNT(J8:J10)=0,"",SUM(J8:J10)) -> 1.001 | ... Q11: =IF(COUNT(Q8:Q10)=0,"",SUM(Q8:Q10)) -> 0
A12: Applicable revenue basis | B12: ₹ cr | D12: ='Annual P&L'!D7 -> 46723 | E12: ='Annual P&L'!E7 -> 50570 | F12: ='Annual P&L'!F7 -> 60427 | G12: ='Annual P&L'!G7 -> 70678 | H12: ='Annual P&L'!H7 -> 75379 | I12: ='Annual P&L'!I7 -> 85651 | J12: ='Segment Revenue'!J8+'Segment Revenue'!J10 -> 90904.576 | K12: ='Segment Revenue'!K8+'Segment Revenue'!K10 -> 98701.874 | L12: ='Segment Revenue'!L8+'Segment Revenue'!L10 -> 105349.5 | N12: ='Segment Revenue'!N8+'Segment Revenue'!N10 -> 125750 | O12: ='Segment Revenue'!O8+'Segment Revenue'!O10 -> 135989 | P12: ='Segment Revenue'!P8+'Segment Revenue'!P10 -> 148242.03 | Q12: ='Segment Revenue'!Q8+'Segment Revenue'!Q10 -> 160636.56
A13: Americas revenue | B13: ₹ cr | C13: =IF(C8="","",C8*C12) | D13: =IF(D8="","",D8*D12) -> 28781.368 | E13: =IF(E8="","",E8*E12) -> 31606.25 | F13: =IF(F8="","",F8*F12) -> 38914.988 | G13: =IF(G8="","",G8*G12) | H13: =IF(H8="","",H8*H12) -> 47338.012 | I13: =IF(I8="","",I8*I12) -> 53874.479 | J13: =IF(J8="","",J8*J12) -> 58269.833 | ... Q13: =IF(Q8="","",Q8*Q12) -> 0
A14: Europe revenue | B14: ₹ cr | C14: =IF(C9="","",C9*C12) | D14: =IF(D9="","",D9*D12) -> 13783.285 | E14: =IF(E9="","",E9*E12) -> 14564.16 | F14: =IF(F9="","",F9*F12) -> 17040.414 | G14: =IF(G9="","",G9*G12) | H14: =IF(H9="","",H9*H12) -> 21709.152 | I14: =IF(I9="","",I9*I12) -> 24153.582 | J14: =IF(J9="","",J9*J12) -> 25816.9 | ... Q14: =IF(Q9="","",Q9*Q12) -> 0
A15: Rest of World revenue | B15: ₹ cr | C15: =IF(C10="","",C10*C12) | D15: =IF(D10="","",D10*D12) -> 4158.347 | E15: =IF(E10="","",E10*E12) -> 4349.02 | F15: =IF(F10="","",F10*F12) -> 4471.598 | G15: =IF(G10="","",G10*G12) | H15: =IF(H10="","",H10*H12) -> 6331.836 | I15: =IF(I10="","",I10*I12) -> 7622.939 | J15: =IF(J10="","",J10*J12) -> 6908.7478 | ... Q15: =IF(Q10="","",Q10*Q12) -> 0
A17: IFRS geography mix — total company revenue
A18: USA | B18: % | F18: 0.596 | G18: 0.578 | K18: 0.584 | L18: 0.588 | M18: 0.563 | N18: =M18 -> 0.563 | O18: =N18 -> 0.563 | P18: =O18 -> 0.563 | Q18: =P18 -> 0.563
A19: Europe | B19: % | F19: 0.267 | G19: 0.274 | K19: 0.265 | L19: 0.266 | M19: 0.278 | N19: =M19 -> 0.278 | O19: =N19 -> 0.278 | P19: =O19 -> 0.278 | Q19: =P19 -> 0.278
A20: India | B20: % | F20: 0.035 | G20: 0.033 | K20: 0.037 | L20: 0.033 | M20: 0.032 | N20: =M20 -> 0.032 | O20: =N20 -> 0.032 | P20: =O20 -> 0.032 | Q20: =P20 -> 0.032
A21: Rest of World | B21: % | F21: 0.102 | G21: 0.115 | K21: 0.115 | L21: 0.113 | M21: 0.127 | N21: =M21 -> 0.127 | O21: =N21 -> 0.127 | P21: =O21 -> 0.127 | Q21: =P21 -> 0.127
A22: Mix check | B22: % | C22: =IF(COUNT(C18:C21)=0,"",SUM(C18:C21)) | D22: =IF(COUNT(D18:D21)=0,"",SUM(D18:D21)) | E22: =IF(COUNT(E18:E21)=0,"",SUM(E18:E21)) | F22: =IF(COUNT(F18:F21)=0,"",SUM(F18:F21)) -> 1 | G22: =IF(COUNT(G18:G21)=0,"",SUM(G18:G21)) -> 1 | H22: =IF(COUNT(H18:H21)=0,"",SUM(H18:H21)) | I22: =IF(COUNT(I18:I21)=0,"",SUM(I18:I21)) | J22: =IF(COUNT(J18:J21)=0,"",SUM(J18:J21)) | ... Q22: =IF(COUNT(Q18:Q21)=0,"",SUM(Q18:Q21)) -> 1
A23: Applicable revenue basis | B23: ₹ cr | C23: ='Annual P&L'!C7 -> 40913 | D23: ='Annual P&L'!D7 -> 46723 | E23: ='Annual P&L'!E7 -> 50570 | F23: ='Annual P&L'!F7 -> 60427 | G23: ='Annual P&L'!G7 -> 70678 | H23: ='Annual P&L'!H7 -> 75379 | I23: ='Annual P&L'!I7 -> 85651 | J23: ='Annual P&L'!J7 -> 101456 | ... Q23: ='Annual P&L'!Q7 -> 175279.02
A24: USA revenue | B24: ₹ cr | C24: =IF(C18="","",C18*C23) | D24: =IF(D18="","",D18*D23) | E24: =IF(E18="","",E18*E23) | F24: =IF(F18="","",F18*F23) -> 36014.492 | G24: =IF(G18="","",G18*G23) -> 40851.884 | H24: =IF(H18="","",H18*H23) | I24: =IF(I18="","",I18*I23) | J24: =IF(J18="","",J18*J23) | ... Q24: =IF(Q18="","",Q18*Q23) -> 98682.088
A25: Europe revenue | B25: ₹ cr | C25: =IF(C19="","",C19*C23) | D25: =IF(D19="","",D19*D23) | E25: =IF(E19="","",E19*E23) | F25: =IF(F19="","",F19*F23) -> 16134.009 | G25: =IF(G19="","",G19*G23) -> 19365.772 | H25: =IF(H19="","",H19*H23) | I25: =IF(I19="","",I19*I23) | J25: =IF(J19="","",J19*J23) | ... Q25: =IF(Q19="","",Q19*Q23) -> 48727.567
A26: India revenue | B26: ₹ cr | C26: =IF(C20="","",C20*C23) | D26: =IF(D20="","",D20*D23) | E26: =IF(E20="","",E20*E23) | F26: =IF(F20="","",F20*F23) -> 2114.945 | G26: =IF(G20="","",G20*G23) -> 2332.374 | H26: =IF(H20="","",H20*H23) | I26: =IF(I20="","",I20*I23) | J26: =IF(J20="","",J20*J23) | ... Q26: =IF(Q20="","",Q20*Q23) -> 5608.9286
A27: Rest of World revenue | B27: ₹ cr | C27: =IF(C21="","",C21*C23) | D27: =IF(D21="","",D21*D23) | E27: =IF(E21="","",E21*E23) | F27: =IF(F21="","",F21*F23) -> 6163.554 | G27: =IF(G21="","",G21*G23) -> 8127.97 | H27: =IF(H21="","",H21*H23) | I27: =IF(I21="","",I21*I23) | J27: =IF(J21="","",J21*J23) | ... Q27: =IF(Q21="","",Q21*Q23) -> 22260.435
A29: Vertical mix — company basis through FY22; Services basis from FY23
A30: Financial Services | B30: % | D30: 0.241 | E30: 0.249 | F30: 0.223 | H30: 0.219 | I30: 0.213 | J30: 0.207 | K30: 0.221 | L30: 0.207 | M30: 0.215 | N30: =M30 -> 0.215 | O30: =N30 -> 0.215 | P30: =O30 -> 0.215 | Q30: =P30 -> 0.215
A31: Manufacturing | B31: % | D31: 0.335 | E31: 0.357 | F31: 0.179 | H31: 0.179 | I31: 0.177 | J31: 0.191 | K31: 0.199 | L31: 0.191 | M31: 0.186 | N31: =M31 -> 0.186 | O31: =N31 -> 0.186 | P31: =O31 -> 0.186 | Q31: =P31 -> 0.186
A32: Technology & Services / Other | B32: % | D32: 0.004 | E32: 0 | F32: 0.185 | H32: 0.174 | I32: 0.176 | J32: 0.149 | K32: 0.129 | L32: 0.132 | M32: 0.143 | N32: =M32 -> 0.143 | O32: =N32 -> 0.143 | P32: =O32 -> 0.143 | Q32: =P32 -> 0.143
A33: Life Sciences & Healthcare | B33: % | D33: 0.12 | E33: 0.116 | F33: 0.129 | H33: 0.139 | I33: 0.148 | J33: 0.169 | K33: 0.169 | L33: 0.155 | M33: 0.144 | N33: =M33 -> 0.144 | O33: =N33 -> 0.144 | P33: =O33 -> 0.144 | Q33: =P33 -> 0.144
A34: Telecom, Media, Publishing & Entertainment | B34: % | D34: 0.089 | E34: 0.077 | F34: 0.081 | H34: 0.079 | I34: 0.081 | J34: 0.092 | K34: 0.092 | L34: 0.126 | M34: 0.126 | N34: =M34 -> 0.126 | O34: =N34 -> 0.126 | P34: =O34 -> 0.126 | Q34: =P34 -> 0.126
A35: Retail & CPG | B35: % | D35: 0.097 | E35: 0.095 | F35: 0.099 | H35: 0.102 | I35: 0.098 | J35: 0.091 | K35: 0.093 | L35: 0.098 | M35: 0.097 | N35: =M35 -> 0.097 | O35: =N35 -> 0.097 | P35: =O35 -> 0.097 | Q35: =P35 -> 0.097
A36: Public Services | B36: % | D36: 0.114 | E36: 0.106 | F36: 0.105 | H36: 0.108 | I36: 0.106 | J36: 0.102 | K36: 0.096 | L36: 0.089 | M36: 0.089 | N36: =M36 -> 0.089 | O36: =N36 -> 0.089 | P36: =O36 -> 0.089 | Q36: =P36 -> 0.089
A37: Mix check | B37: % | C37: =IF(COUNT(C30:C36)=0,"",SUM(C30:C36)) | D37: =IF(COUNT(D30:D36)=0,"",SUM(D30:D36)) -> 1 | E37: =IF(COUNT(E30:E36)=0,"",SUM(E30:E36)) -> 1 | F37: =IF(COUNT(F30:F36)=0,"",SUM(F30:F36)) -> 1.001 | G37: =IF(COUNT(G30:G36)=0,"",SUM(G30:G36)) | H37: =IF(COUNT(H30:H36)=0,"",SUM(H30:H36)) -> 1 | I37: =IF(COUNT(I30:I36)=0,"",SUM(I30:I36)) -> 0.999 | J37: =IF(COUNT(J30:J36)=0,"",SUM(J30:J36)) -> 1.001 | ... Q37: =IF(COUNT(Q30:Q36)=0,"",SUM(Q30:Q36)) -> 1
A38: Applicable revenue basis | B38: ₹ cr | D38: ='Annual P&L'!D7 -> 46723 | E38: ='Annual P&L'!E7 -> 50570 | F38: ='Annual P&L'!F7 -> 60427 | H38: ='Annual P&L'!H7 -> 75379 | I38: ='Annual P&L'!I7 -> 85651 | J38: ='Segment Revenue'!J8+'Segment Revenue'!J10 -> 90904.576 | K38: ='Segment Revenue'!K8+'Segment Revenue'!K10 -> 98701.874 | L38: ='Segment Revenue'!L8+'Segment Revenue'!L10 -> 105349.5 | M38: ='Segment Revenue'!M8+'Segment Revenue'!M10 -> 118170.75 | N38: ='Segment Revenue'!N8+'Segment Revenue'!N10 -> 125750 | O38: ='Segment Revenue'!O8+'Segment Revenue'!O10 -> 135989 | P38: ='Segment Revenue'!P8+'Segment Revenue'!P10 -> 148242.03 | Q38: ='Segment Revenue'!Q8+'Segment Revenue'!Q10 -> 160636.56
A39: Financial Services revenue | B39: ₹ cr | C39: =IF(C30="","",C30*C38) | D39: =IF(D30="","",D30*D38) -> 11260.243 | E39: =IF(E30="","",E30*E38) -> 12591.93 | F39: =IF(F30="","",F30*F38) -> 13475.221 | G39: =IF(G30="","",G30*G38) | H39: =IF(H30="","",H30*H38) -> 16508.001 | I39: =IF(I30="","",I30*I38) -> 18243.663 | J39: =IF(J30="","",J30*J38) -> 18817.247 | ... Q39: =IF(Q30="","",Q30*Q38) -> 34536.86
A40: Manufacturing revenue | B40: ₹ cr | C40: =IF(C31="","",C31*C38) | D40: =IF(D31="","",D31*D38) -> 15652.205 | E40: =IF(E31="","",E31*E38) -> 18053.49 | F40: =IF(F31="","",F31*F38) -> 10816.433 | G40: =IF(G31="","",G31*G38) | H40: =IF(H31="","",H31*H38) -> 13492.841 | I40: =IF(I31="","",I31*I38) -> 15160.227 | J40: =IF(J31="","",J31*J38) -> 17362.774 | ... Q40: =IF(Q31="","",Q31*Q38) -> 29878.4
A41: Technology & Services / Other revenue | B41: ₹ cr | C41: =IF(C32="","",C32*C38) | D41: =IF(D32="","",D32*D38) -> 186.892 | E41: =IF(E32="","",E32*E38) -> 0 | F41: =IF(F32="","",F32*F38) -> 11178.995 | G41: =IF(G32="","",G32*G38) | H41: =IF(H32="","",H32*H38) -> 13115.946 | I41: =IF(I32="","",I32*I38) -> 15074.576 | J41: =IF(J32="","",J32*J38) -> 13544.782 | ... Q41: =IF(Q32="","",Q32*Q38) -> 22971.028
A42: Life Sciences & Healthcare revenue | B42: ₹ cr | C42: =IF(C33="","",C33*C38) | D42: =IF(D33="","",D33*D38) -> 5606.76 | E42: =IF(E33="","",E33*E38) -> 5866.12 | F42: =IF(F33="","",F33*F38) -> 7795.083 | G42: =IF(G33="","",G33*G38) | H42: =IF(H33="","",H33*H38) -> 10477.681 | I42: =IF(I33="","",I33*I38) -> 12676.348 | J42: =IF(J33="","",J33*J38) -> 15362.873 | ... Q42: =IF(Q33="","",Q33*Q38) -> 23131.665
A43: Telecom / Media revenue | B43: ₹ cr | C43: =IF(C34="","",C34*C38) | D43: =IF(D34="","",D34*D38) -> 4158.347 | E43: =IF(E34="","",E34*E38) -> 3893.89 | F43: =IF(F34="","",F34*F38) -> 4894.587 | G43: =IF(G34="","",G34*G38) | H43: =IF(H34="","",H34*H38) -> 5954.941 | I43: =IF(I34="","",I34*I38) -> 6937.731 | J43: =IF(J34="","",J34*J38) -> 8363.221 | ... Q43: =IF(Q34="","",Q34*Q38) -> 20240.207
A44: Retail & CPG revenue | B44: ₹ cr | C44: =IF(C35="","",C35*C38) | D44: =IF(D35="","",D35*D38) -> 4532.131 | E44: =IF(E35="","",E35*E38) -> 4804.15 | F44: =IF(F35="","",F35*F38) -> 5982.273 | G44: =IF(G35="","",G35*G38) | H44: =IF(H35="","",H35*H38) -> 7688.658 | I44: =IF(I35="","",I35*I38) -> 8393.798 | J44: =IF(J35="","",J35*J38) -> 8272.3164 | ... Q44: =IF(Q35="","",Q35*Q38) -> 15581.746
A45: Public Services revenue | B45: ₹ cr | C45: =IF(C36="","",C36*C38) | D45: =IF(D36="","",D36*D38) -> 5326.422 | E45: =IF(E36="","",E36*E38) -> 5360.42 | F45: =IF(F36="","",F36*F38) -> 6344.835 | G45: =IF(G36="","",G36*G38) | H45: =IF(H36="","",H36*H38) -> 8140.932 | I45: =IF(I36="","",I36*I38) -> 9079.006 | J45: =IF(J36="","",J36*J38) -> 9272.2668 | ... Q45: =IF(Q36="","",Q36*Q38) -> 14296.654

Sheet Client Data
A1: Client Data & Revenue per Client
A2: Client bands and concentration; revenue per $1m+ client is a disclosed-band proxy, not average revenue per total client
A5: Metric | B5: Units | C5: FY16A | D5: FY17A | E5: FY18A | F5: FY19A | G5: FY20A | H5: FY21A | I5: FY22A | J5: FY23A | K5: FY24A | L5: FY25A | M5: FY26A | N5: FY27E | O5: FY28E | P5: FY29E | Q5: FY30E
A10: $100m+ clients | B10: # | C10: 8 | D10: 8 | E10: 8 | F10: 10 | G10: 15 | H10: 15 | I10: 16 | J10: 19 | K10: 22 | L10: 22 | M10: 23 | N10: =ROUND(M10*(1+'Annual P&L'!N8),0) -> 24 | O10: =ROUND(N10*(1+'Annual P&L'!O8),0) -> 26 | P10: =ROUND(O10*(1+'Annual P&L'!P8),0) -> 28 | Q10: =ROUND(P10*(1+'Annual P&L'!Q8),0) -> 30
A11: $50m+ clients | B11: # | C11: 19 | D11: 25 | E11: 28 | F11: 29 | G11: 30 | H11: 35 | I11: 43 | J11: 46 | K11: 46 | L11: 52 | M11: 60 | N11: =ROUND(M11*(1+'Annual P&L'!N8),0) -> 64 | O11: =ROUND(N11*(1+'Annual P&L'!O8),0) -> 69 | P11: =ROUND(O11*(1+'Annual P&L'!P8),0) -> 75 | Q11: =ROUND(P11*(1+'Annual P&L'!Q8),0) -> 81
A12: $20m+ clients | B12: # | C12: 75 | D12: 85 | E12: 87 | F12: 95 | G12: 96 | H12: 96 | I12: 118 | J12: 131 | K12: 137 | L12: 138 | M12: 149 | N12: =ROUND(M12*(1+'Annual P&L'!N8),0) -> 158 | O12: =ROUND(N12*(1+'Annual P&L'!O8),0) -> 170 | P12: =ROUND(O12*(1+'Annual P&L'!P8),0) -> 185 | Q12: =ROUND(P12*(1+'Annual P&L'!Q8),0) -> 200
A13: $10m+ clients | B13: # | C13: 144 | D13: 153 | E13: 160 | F13: 166 | G13: 171 | H13: 178 | I13: 208 | J13: 229 | K13: 254 | L13: 251 | M13: 277 | N13: =ROUND(M13*(1+'Annual P&L'!N8),0) -> 294 | O13: =ROUND(N13*(1+'Annual P&L'!O8),0) -> 317 | P13: =ROUND(O13*(1+'Annual P&L'!P8),0) -> 345 | Q13: =ROUND(P13*(1+'Annual P&L'!Q8),0) -> 373
A14: $5m+ clients | B14: # | C14: 233 | D14: 246 | E14: 264 | F14: 283 | G14: 308 | H14: 318 | I14: 349 | J14: 375 | K14: 395 | L14: 399 | M14: 429 | N14: =ROUND(M14*(1+'Annual P&L'!N8),0) -> 456 | O14: =ROUND(N14*(1+'Annual P&L'!O8),0) -> 492 | P14: =ROUND(O14*(1+'Annual P&L'!P8),0) -> 535 | Q14: =ROUND(P14*(1+'Annual P&L'!Q8),0) -> 579
A15: $1m+ clients | B15: # | C15: 482 | D15: 506 | E15: 561 | F15: 623 | G15: 791 | H15: 809 | I15: 882 | J15: 939 | K15: 951 | L15: 948 | M15: 976 | N15: =ROUND(M15*(1+'Annual P&L'!N8),0) -> 1036 | O15: =ROUND(N15*(1+'Annual P&L'!O8),0) -> 1117 | P15: =ROUND(O15*(1+'Annual P&L'!P8),0) -> 1215 | Q15: =ROUND(P15*(1+'Annual P&L'!Q8),0) -> 1314
A16: Top 5 client contribution | B16: % | C16: 0.136 | D16: 0.147 | E16: 0.163 | F16: 0.17 | G16: 0.151 | H16: 0.132 | I16: 0.116 | J16: 0.101 | K16: 0.104 | L16: 0.127 | M16: 0.119 | N16: =M16 -> 0.119 | O16: =N16 -> 0.119 | P16: =O16 -> 0.119 | Q16: =P16 -> 0.119
A17: Top 10 client contribution | B17: % | C17: 0.218 | D17: 0.221 | E17: 0.238 | F17: 0.241 | G17: 0.22 | H17: 0.209 | I17: 0.198 | J17: 0.177 | K17: 0.188 | L17: 0.202 | M17: 0.191 | N17: =M17 -> 0.191 | O17: =N17 -> 0.191 | P17: =O17 -> 0.191 | Q17: =P17 -> 0.191
A18: Top 20 client contribution | B18: % | C18: 0.322 | D18: 0.329 | E18: 0.337 | F18: 0.334 | G18: 0.321 | H18: 0.308 | I18: 0.291 | J18: 0.278 | K18: 0.29 | L18: 0.304 | M18: 0.285 | N18: =M18 -> 0.285 | O18: =N18 -> 0.285 | P18: =O18 -> 0.285 | Q18: =P18 -> 0.285
A19: Revenue per $1m+ client proxy | B19: $m | C19: =IFERROR('Raw Financials'!C19/C15,"") -> 12.936515 | D19: =IFERROR('Raw Financials'!D19/D15,"") -> 13.903162 | E19: =IFERROR('Raw Financials'!E19/E15,"") -> 13.97148 | F19: =IFERROR('Raw Financials'!F19/F15,"") -> 13.855538 | G19: =IFERROR('Raw Financials'!G19/G15,"") -> 12.561315 | H19: =IFERROR('Raw Financials'!H19/H15,"") -> 12.577256 | I19: =IFERROR('Raw Financials'!I19/I15,"") -> 13.017007 | J19: =IFERROR('Raw Financials'!J19/J15,"") -> 13.453674 | ... M19: =IFERROR('Raw Financials'!M19/M15,"") -> 15.02459 | N19: =IFERROR('Annual P&L'!N7*10/'Revenue Drivers'!N22/N15,"") -> 14.04109 | O19: =IFERROR('Annual P&L'!O7*10/'Revenue Drivers'!O22/O15,"") -> 13.898991 | P19: =IFERROR('Annual P&L'!P7*10/'Revenue Drivers'!P22/P15,"") -> 13.751268 | Q19: =IFERROR('Annual P&L'!Q7*10/'Revenue Drivers'!Q22/Q15,"") -> 13.611579
A20: Incremental $1m+ clients | B20: # | D20: =IF(OR(D15="",C15=""),"",D15-C15) -> 24 | E20: =IF(OR(E15="",D15=""),"",E15-D15) -> 55 | F20: =IF(OR(F15="",E15=""),"",F15-E15) -> 62 | G20: =IF(OR(G15="",F15=""),"",G15-F15) -> 168 | H20: =IF(OR(H15="",G15=""),"",H15-G15) -> 18 | I20: =IF(OR(I15="",H15=""),"",I15-H15) -> 73 | J20: =IF(OR(J15="",I15=""),"",J15-I15) -> 57 | K20: =IF(OR(K15="",J15=""),"",K15-J15) -> 12 | ... Q20: =IF(OR(Q15="",P15=""),"",Q15-P15) -> 99
A21: TCV | B21: $m | C21: ='Raw Financials'!C22 -> 0 | D21: ='Raw Financials'!D22 -> 0 | E21: ='Raw Financials'!E22 -> 0 | F21: ='Raw Financials'!F22 -> 0 | G21: ='Raw Financials'!G22 -> 0 | H21: ='Raw Financials'!H22 -> 7300 | I21: ='Raw Financials'!I22 -> 8308 | J21: ='Raw Financials'!J22 -> 8850 | ... M21: ='Raw Financials'!M22 -> 9323 | N21: =M21*(1+'Annual P&L'!N8) -> 9899.5558 | O21: =N21*(1+'Annual P&L'!O8) -> 10676.754 | P21: =O21*(1+'Annual P&L'!P8) -> 11609.735 | Q21: =P21*(1+'Annual P&L'!Q8) -> 12556.294
A22: TCV / USD revenue | B22: x | C22: =IFERROR(C21/'Raw Financials'!C19,"") -> 0 | D22: =IFERROR(D21/'Raw Financials'!D19,"") -> 0 | E22: =IFERROR(E21/'Raw Financials'!E19,"") -> 0 | F22: =IFERROR(F21/'Raw Financials'!F19,"") -> 0 | G22: =IFERROR(G21/'Raw Financials'!G19,"") -> 0 | H22: =IFERROR(H21/'Raw Financials'!H19,"") -> 0.71744472 | I22: =IFERROR(I21/'Raw Financials'!I19,"") -> 0.72363035 | J22: =IFERROR(J21/'Raw Financials'!J19,"") -> 0.70054619 | ... M22: =IFERROR(M21/'Raw Financials'!M19,"") -> 0.63577469 | N22: =IFERROR(N21/('Annual P&L'!N7*10/'Revenue Drivers'!N22),"") -> 0.68054232 | O22: =IFERROR(O21/('Annual P&L'!O7*10/'Revenue Drivers'!O22),"") -> 0.68770593 | P22: =IFERROR(P21/('Annual P&L'!P7*10/'Revenue Drivers'!P22),"") -> 0.69486953 | Q22: =IFERROR(Q21/('Annual P&L'!Q7*10/'Revenue Drivers'!Q22),"") -> 0.70203313

Sheet Revenue Drivers
A1: Revenue Drivers — Billable FTE, T&M Deflation and Advanced AI
A2: Historical utilization stays blank when not disclosed; FY26 AI baseline is a run-rate proxy, not reported full-year revenue
A5: Metric | B5: Units | C5: FY16A | D5: FY17A | E5: FY18A | F5: FY19A | G5: FY20A | H5: FY21A | I5: FY22A | J5: FY23A | K5: FY24A | L5: FY25A | M5: FY26A | N5: FY27E | O5: FY28E | P5: FY29E | Q5: FY30E
A6: Total headcount | B6: # | C6: ='Raw Financials'!C20 -> 104896 | D6: ='Raw Financials'!D20 -> 115973 | E6: ='Raw Financials'!E20 -> 120081 | F6: ='Raw Financials'!F20 -> 137965 | G6: ='Raw Financials'!G20 -> 150423 | H6: ='Raw Financials'!H20 -> 168977 | I6: ='Raw Financials'!I20 -> 208877 | J6: ='Raw Financials'!J20 -> 225944 | ... M6: ='Raw Financials'!M20 -> 227181 | N6: =M6*(1+Assumptions!C6) -> 233996.43 | O6: =N6*(1+Assumptions!D6) -> 242186.31 | P6: =O6*(1+Assumptions!E6) -> 251873.76 | Q6: =P6*(1+Assumptions!F6) -> 261948.71
A7: Headcount growth | B7: % | D7: =IFERROR(D6/C6-1,"") -> 0.10559983 | E7: =IFERROR(E6/D6-1,"") -> 0.035422038 | F7: =IFERROR(F6/E6-1,"") -> 0.1489328 | G7: =IFERROR(G6/F6-1,"") -> 0.090298264 | H7: =IFERROR(H6/G6-1,"") -> 0.1233455 | I7: =IFERROR(I6/H6-1,"") -> 0.23612681 | J7: =IFERROR(J6/I6-1,"") -> 0.081708374 | K7: =IFERROR(K6/J6-1,"") -> 0.0068025705 | ... M7: =IFERROR(M6/L6-1,"") -> 0.016833766 | N7: =Assumptions!C6 -> 0.03 | O7: =Assumptions!D6 -> 0.035 | P7: =Assumptions!E6 -> 0.04 | Q7: =Assumptions!F6 -> 0.04
A8: Technical / service employee share | B8: % | C8: =IFERROR('Raw Financials'!C50/C6,"") -> 0.91184602 | D8: =IFERROR('Raw Financials'!D50/D6,"") -> 0.91009976 | E8: =IFERROR('Raw Financials'!E50/E6,"") -> 0.91242578 | F8: =IFERROR('Raw Financials'!F50/F6,"") -> 0.91847208 | G8: =IFERROR('Raw Financials'!G50/G6,"") -> 0.92606849 | H8: =IFERROR('Raw Financials'!H50/H6,"") -> 0.92663499 | I8: =IFERROR('Raw Financials'!I50/I6,"") -> 0.93449734 | J8: =IFERROR('Raw Financials'!J50/J6,"") -> 0.93582923 | ... M8: =IFERROR('Raw Financials'!M50/M6,"") -> 0.93660561 | N8: =Assumptions!C7 -> 0.94 | O8: =Assumptions!D7 -> 0.94 | P8: =Assumptions!E7 -> 0.94 | Q8: =Assumptions!F7 -> 0.94
A9: Technical / service employees | B9: # | C9: ='Raw Financials'!C50 -> 95649 | D9: ='Raw Financials'!D50 -> 105547 | E9: ='Raw Financials'!E50 -> 109565 | F9: ='Raw Financials'!F50 -> 126717 | G9: ='Raw Financials'!G50 -> 139302 | H9: ='Raw Financials'!H50 -> 156580 | I9: ='Raw Financials'!I50 -> 195195 | J9: ='Raw Financials'!J50 -> 211445 | ... M9: ='Raw Financials'!M50 -> 212779 | N9: =N6*N8 -> 219956.64 | O9: =O6*O8 -> 227655.13 | P9: =P6*P8 -> 236761.33 | Q9: =Q6*Q8 -> 246231.79
A10: Reported / assumed utilization | B10: % | C10: ='Raw Financials'!C21 -> 0.856 | D10: ='Raw Financials'!D21 -> 0.857 | E10: ='Raw Financials'!E21 -> 0.859 | F10: ='Raw Financials'!F21 -> 0.854 | G10: ='Raw Financials'!G21 -> 0 | H10: ='Raw Financials'!H21 -> 0 | I10: ='Raw Financials'!I21 -> 0 | J10: ='Raw Financials'!J21 -> 0 | ... M10: ='Raw Financials'!M21 -> 0 | N10: =Assumptions!C8 -> 0.84 | O10: =Assumptions!D8 -> 0.845 | P10: =Assumptions!E8 -> 0.85 | Q10: =Assumptions!F8 -> 0.85
A11: Implied / forecast billable FTE | B11: # | C11: =IF(C10="","",C9*C10) -> 81875.544 | D11: =IF(D10="","",D9*D10) -> 90453.779 | E11: =IF(E10="","",E9*E10) -> 94116.335 | F11: =IF(F10="","",F9*F10) -> 108216.32 | G11: =IF(G10="","",G9*G10) -> 0 | H11: =IF(H10="","",H9*H10) -> 0 | I11: =IF(I10="","",I9*I10) -> 0 | J11: =IF(J10="","",J9*J10) -> 0 | ... M11: =IF(M10="","",M9*M10) -> 0 | N11: =N9*N10 -> 184763.58 | O11: =O9*O10 -> 192368.58 | P11: =P9*P10 -> 201247.13 | Q11: =Q9*Q10 -> 209297.02
A12: Revenue per billable FTE | B12: ₹ cr | C12: =IFERROR('Annual P&L'!C7/C11,"") -> 0.49969744 | D12: =IFERROR('Annual P&L'!D7/D11,"") -> 0.51654006 | E12: =IFERROR('Annual P&L'!E7/E11,"") -> 0.53731374 | F12: =IFERROR('Annual P&L'!F7/F11,"") -> 0.55839083 | N12: =M20/(M6*Assumptions!C7*Assumptions!C8)*(1+Assumptions!C9) -> 0.64469141 | O12: =N12*(1+Assumptions!D9) -> 0.66725561 | P12: =O12*(1+Assumptions!E9) -> 0.69394584 | Q12: =P12*(1+Assumptions!F9) -> 0.72170367
A13: Pricing / productivity uplift | B13: % | N13: =Assumptions!C9 -> 0.03 | O13: =Assumptions!D9 -> 0.035 | P13: =Assumptions!E9 -> 0.04 | Q13: =Assumptions!F9 -> 0.04
A14: Capacity revenue before mix / AI deflation | B14: ₹ cr | N14: =N11*N12 -> 119115.49 | O14: =O11*O12 -> 128359.02 | P14: =P11*P12 -> 139654.61 | Q14: =Q11*Q12 -> 151050.43
A15: T&M mix | B15: % | C15: ='Raw Financials'!C52 -> 0 | D15: ='Raw Financials'!D52 -> 0.382 | E15: ='Raw Financials'!E52 -> 0.393 | F15: ='Raw Financials'!F52 -> 0.373 | G15: ='Raw Financials'!G52 -> 0 | H15: ='Raw Financials'!H52 -> 0.324 | I15: ='Raw Financials'!I52 -> 0.35 | J15: ='Raw Financials'!J52 -> 0 | ... M15: ='Raw Financials'!M52 -> 0 | N15: =Assumptions!C10 -> 0.34 | O15: =Assumptions!D10 -> 0.33 | P15: =Assumptions!E10 -> 0.32 | Q15: =Assumptions!F10 -> 0.31
A16: T&M revenue before AI deflation | B16: ₹ cr | N16: =N14*N15 -> 40499.268 | O16: =O14*O15 -> 42358.475 | P16: =P14*P15 -> 44689.475 | Q16: =Q14*Q15 -> 46825.632
A17: AI deflation rate | B17: % | N17: =Assumptions!C11 -> 0.01 | O17: =Assumptions!D11 -> 0.013 | P17: =Assumptions!E11 -> 0.015 | Q17: =Assumptions!F11 -> 0.015
A18: AI deflation drag | B18: ₹ cr | N18: =-N16*N17 -> -404.99268 | O18: =-O16*O17 -> -550.66018 | P18: =-P16*P17 -> -670.34213 | Q18: =-Q16*Q17 -> -702.38448
A19: Managed / fixed-price revenue | B19: ₹ cr | N19: =N14*(1-N15) -> 78616.226 | O19: =O14*(1-O15) -> 86000.541 | P19: =P14*(1-P15) -> 94965.135 | Q19: =Q14*(1-Q15) -> 104224.79
A20: Core services ex-AI | B20: ₹ cr | M20: =M27-M24-M23 -> 112277.78 | N20: =SUM(N16,N18,N19) -> 118710.5 | O20: =SUM(O16,O18,O19) -> 127808.36 | P20: =SUM(P16,P18,P19) -> 138984.27 | Q20: =SUM(Q16,Q18,Q19) -> 150348.04
A21: Advanced AI recognized revenue | B21: $m | M21: =155*4 -> 620 | N21: =Assumptions!C40 -> 741 | O21: =N21*(1+Assumptions!D12) -> 852.15 | P21: =O21*(1+Assumptions!E12) -> 954.408 | Q21: =P21*(1+Assumptions!F12) -> 1049.8488
A22: Advanced AI FX rate | B22: ₹ / $ | C22: =IFERROR('Annual P&L'!C7/'Raw Financials'!C19*10,"") -> 65.614074 | D22: =IFERROR('Annual P&L'!D7/'Raw Financials'!D19*10,"") -> 66.415068 | E22: =IFERROR('Annual P&L'!E7/'Raw Financials'!E19*10,"") -> 64.51901 | F22: =IFERROR('Annual P&L'!F7/'Raw Financials'!F19*10,"") -> 70.003475 | G22: =IFERROR('Annual P&L'!G7/'Raw Financials'!G19*10,"") -> 71.133253 | H22: =IFERROR('Annual P&L'!H7/'Raw Financials'!H19*10,"") -> 74.082555 | I22: =IFERROR('Annual P&L'!I7/'Raw Financials'!I19*10,"") -> 74.602387 | J22: =IFERROR('Annual P&L'!J7/'Raw Financials'!J19*10,"") -> 80.310298 | ... M22: =IFERROR('Annual P&L'!M7/'Raw Financials'!M19*10,"") -> 88.750682 | N22: =Assumptions!C14 -> 95 | O22: =Assumptions!D14 -> 96 | P22: =Assumptions!E14 -> 97 | Q22: =Assumptions!F14 -> 98
A23: Advanced AI recognized revenue | B23: ₹ cr | M23: =M21*M22/10 -> 5502.5423 | N23: =N21*N22/10 -> 7039.5 | O23: =O21*O22/10 -> 8180.64 | P23: =P21*P22/10 -> 9257.7576 | Q23: =Q21*Q22/10 -> 10288.518
A24: HCLSoftware / P&P revenue | B24: ₹ cr | C24: =IFERROR('Segment Revenue'!C12,"") | D24: =IFERROR('Segment Revenue'!D12,"") | E24: =IFERROR('Segment Revenue'!E12,"") | F24: =IFERROR('Segment Revenue'!F12,"") -> 5015.441 | G24: =IFERROR('Segment Revenue'!G12,"") -> 8127.97 | H24: =IFERROR('Segment Revenue'!H12,"") -> 10251.544 | I24: =IFERROR('Segment Revenue'!I12,"") -> 10363.771 | J24: =IFERROR('Segment Revenue'!J12,"") -> 11058.704 | ... L24: =IFERROR('Segment Revenue'!L12,"") -> 12056.665 | M24: ='Segment Revenue'!M12 -> 12363.68 | N24: =M24*(1+Assumptions!C13) -> 12858.227 | O24: =N24*(1+Assumptions!D13) -> 13501.139 | P24: =O24*(1+Assumptions!E13) -> 14311.207 | Q24: =P24*(1+Assumptions!F13) -> 15169.879
A25: Inter-segment eliminations | B25: ₹ cr | M25: =M27-M20-M23-M24 -> 0 | N25: =-0.3%*SUM(N20,N23,N24) -> -415.82469 | O25: =-0.3%*SUM(O20,O23,O24) -> -448.4704 | P25: =-0.3%*SUM(P20,P23,P24) -> -487.6597 | Q25: =-0.3%*SUM(Q20,Q23,Q24) -> -527.41932
A26: Total modeled revenue | B26: ₹ cr | M26: =SUM(M20,M23:M25) -> 130144 | N26: =SUM(N20,N23:N25) -> 138192.4 | O26: =SUM(O20,O23:O25) -> 149041.66 | P26: =SUM(P20,P23:P25) -> 162065.57 | Q26: =SUM(Q20,Q23:Q25) -> 175279.02
A27: Reported / Annual P&L revenue | B27: ₹ cr | C27: ='Annual P&L'!C7 -> 40913 | D27: ='Annual P&L'!D7 -> 46723 | E27: ='Annual P&L'!E7 -> 50570 | F27: ='Annual P&L'!F7 -> 60427 | G27: ='Annual P&L'!G7 -> 70678 | H27: ='Annual P&L'!H7 -> 75379 | I27: ='Annual P&L'!I7 -> 85651 | J27: ='Annual P&L'!J7 -> 101456 | ... Q27: ='Annual P&L'!Q7 -> 175279.02
A28: Revenue bridge check | B28: ₹ cr | M28: =M26-M27 -> 0 | N28: =N26-N27 -> 0 | O28: =O26-O27 -> 0 | P28: =P26-P27 -> 0 | Q28: =Q26-Q27 -> 0
A29: TCV | B29: $m | C29: ='Raw Financials'!C22 -> 0 | D29: ='Raw Financials'!D22 -> 0 | E29: ='Raw Financials'!E22 -> 0 | F29: ='Raw Financials'!F22 -> 0 | G29: ='Raw Financials'!G22 -> 0 | H29: ='Raw Financials'!H22 -> 7300 | I29: ='Raw Financials'!I22 -> 8308 | J29: ='Raw Financials'!J22 -> 8850 | ... M29: ='Raw Financials'!M22 -> 9323 | N29: =M29*(1+'Annual P&L'!N8) -> 9899.5558 | O29: =N29*(1+'Annual P&L'!O8) -> 10676.754 | P29: =O29*(1+'Annual P&L'!P8) -> 11609.735 | Q29: =P29*(1+'Annual P&L'!Q8) -> 12556.294
A30: Revenue per $1m+ client proxy | B30: $m | C30: =IFERROR('Raw Financials'!C19/'Client Data'!C15,"") -> 12.936515 | D30: =IFERROR('Raw Financials'!D19/'Client Data'!D15,"") -> 13.903162 | E30: =IFERROR('Raw Financials'!E19/'Client Data'!E15,"") -> 13.97148 | F30: =IFERROR('Raw Financials'!F19/'Client Data'!F15,"") -> 13.855538 | G30: =IFERROR('Raw Financials'!G19/'Client Data'!G15,"") -> 12.561315 | H30: =IFERROR('Raw Financials'!H19/'Client Data'!H15,"") -> 12.577256 | I30: =IFERROR('Raw Financials'!I19/'Client Data'!I15,"") -> 13.017007 | J30: =IFERROR('Raw Financials'!J19/'Client Data'!J15,"") -> 13.453674 | ... M30: =IFERROR('Raw Financials'!M19/'Client Data'!M15,"") -> 15.02459 | N30: ='Client Data'!N19 -> 14.04109 | O30: ='Client Data'!O19 -> 13.898991 | P30: ='Client Data'!P19 -> 13.751268 | Q30: ='Client Data'!Q19 -> 13.611579
A31: AI note | B31: text | C31: ="" | D31: ="" | E31: ="" | F31: ="" | G31: ="" | H31: ="" | I31: ="" | J31: ="" | ... L31: ="" | M31: ="FY26 AI proxy is the disclosed Q4 recognized revenue annualized; FY27 is a separate editable recognized-revenue assumption" -> FY26 AI proxy is the disclosed Q4 recognized revenue annualized; FY27 is a separate editable recognized-revenue assumption | N31: ="AI uplift modeled separately from core capacity and T&M deflation" -> AI uplift modeled separately from core capacity and T&M deflation | O31: ="" | P31: ="" | Q31: =""
A32: LTM attrition | B32: % | C32: ='Raw Financials'!C51 -> 0.173 | D32: ='Raw Financials'!D51 -> 0.169 | E32: ='Raw Financials'!E51 -> 0.155 | F32: ='Raw Financials'!F51 -> 0.177 | G32: ='Raw Financials'!G51 -> 0.163 | H32: ='Raw Financials'!H51 -> 0.099 | I32: ='Raw Financials'!I51 -> 0.219 | J32: ='Raw Financials'!J51 -> 0.195 | ... M32: ='Raw Financials'!M51 -> 0.125 | N32: =Assumptions!C39 -> 0.125 | O32: =Assumptions!D39 -> 0.123 | P32: =Assumptions!E39 -> 0.12 | Q32: =Assumptions!F39 -> 0.12
A33: Implied separations | B33: # | D33: =C6*D32 -> 17727.424 | E33: =D6*E32 -> 17975.815 | F33: =E6*F32 -> 21254.337 | G33: =F6*G32 -> 22488.295 | H33: =G6*H32 -> 14891.877 | I33: =H6*I32 -> 37005.963 | J33: =I6*J32 -> 40731.015 | K33: =J6*K32 -> 28017.056 | ... Q33: =P6*Q32 -> 30224.851
A34: Implied gross additions | B34: # | D34: =D6-C6+D33 -> 28804.424 | E34: =E6-D6+E33 -> 22083.815 | F34: =F6-E6+F33 -> 39138.337 | G34: =G6-F6+G33 -> 34946.295 | H34: =H6-G6+H33 -> 33445.877 | I34: =I6-H6+I33 -> 76905.963 | J34: =J6-I6+J33 -> 57798.015 | K34: =K6-J6+K33 -> 29554.056 | ... Q34: =Q6-P6+Q33 -> 40299.801
A35: Managed / fixed-price mix | B35: % | C35: ='Raw Financials'!C53 -> 0 | D35: ='Raw Financials'!D53 -> 0.618 | E35: ='Raw Financials'!E53 -> 0.607 | F35: ='Raw Financials'!F53 -> 0.627 | G35: ='Raw Financials'!G53 -> 0 | H35: ='Raw Financials'!H53 -> 0.676 | I35: ='Raw Financials'!I53 -> 0.65 | J35: ='Raw Financials'!J53 -> 0 | ... M35: ='Raw Financials'!M53 -> 0 | N35: =1-N15 -> 0.66 | O35: =1-O15 -> 0.67 | P35: =1-P15 -> 0.68 | Q35: =1-Q15 -> 0.69

Sheet HCLT Prices
A1: HCLT Prices
A2: Daily HCLTECH.NS close and adjusted close; annual FY-end prices are linked into Valuation
A5: Date | B5: Close | C5: Adjusted close | D5: Volume | E5: Fiscal year | F5: Source
A6: 2015-01-01 | B6: 401.70001 | C6: 287.8678 | D6: 1336492 | E6: FY15 | F6: HCLTECH.NS
A7: 2015-01-02 | B7: 401.3125 | C7: 287.59021 | D7: 933372 | E7: FY15 | F7: HCLTECH.NS
A8: 2015-01-05 | B8: 394.5625 | C8: 282.75293 | D8: 2012624 | E8: FY15 | F8: HCLTECH.NS
A9: 2015-01-06 | B9: 384.02499 | C9: 275.2016 | D9: 3470408 | E9: FY15 | F9: HCLTECH.NS
A10: 2015-01-07 | B10: 374.89999 | C10: 268.66232 | D10: 3540560 | E10: FY15 | F10: HCLTECH.NS
A11: 2015-01-08 | B11: 383.57501 | C11: 274.87906 | D11: 3906036 | E11: FY15 | F11: HCLTECH.NS
A12: 2015-01-09 | B12: 386.38751 | C12: 276.89453 | D12: 6164448 | E12: FY15 | F12: HCLTECH.NS
A13: 2015-01-12 | B13: 393.88751 | C13: 282.26929 | D13: 2661684 | E13: FY15 | F13: HCLTECH.NS
A14: 2015-01-13 | B14: 395.89999 | C14: 283.7114 | D14: 2916072 | E14: FY15 | F14: HCLTECH.NS
A15: 2015-01-14 | B15: 394.70001 | C15: 282.85141 | D15: 4133276 | E15: FY15 | F15: HCLTECH.NS
A16: 2015-01-15 | B16: 398.3125 | C16: 285.44028 | D16: 3658976 | E16: FY15 | F16: HCLTECH.NS
A17: 2015-01-16 | B17: 409.75 | C17: 293.63663 | D17: 3185348 | E17: FY15 | F17: HCLTECH.NS
... A45: 2015-02-27 | B45: 505.5 | C45: 363.78491 | D45: 4808820 | E45: FY15 | F45: HCLTECH.NS
A46: 2015-02-28 | E46: FY15 | F46: HCLTECH.NS
A47: 2015-03-02 | B47: 506.21249 | C47: 364.29776 | D47: 4098336 | E47: FY15 | F47: HCLTECH.NS
A48: 2015-03-03 | B48: 507.79999 | C48: 365.44006 | D48: 4306688 | E48: FY15 | F48: HCLTECH.NS
A49: 2015-03-04 | B49: 509 | C49: 366.3038 | D49: 3430308 | E49: FY15 | F49: HCLTECH.NS
A50: 2015-03-05 | B50: 516.25 | C50: 371.52124 | D50: 3448716 | E50: FY15 | F50: HCLTECH.NS
A51: 2015-03-09 | B51: 516.42499 | C51: 371.64713 | D51: 6555768 | E51: FY15 | F51: HCLTECH.NS
A52: 2015-03-10 | B52: 511.03751 | C52: 367.77008 | D52: 5425488 | E52: FY15 | F52: HCLTECH.NS
A53: 2015-03-11 | B53: 514.76251 | C53: 370.45078 | D53: 10074260 | E53: FY15 | F53: HCLTECH.NS
A54: 2015-03-12 | B54: 513.17499 | C54: 369.30826 | D54: 4880440 | E54: FY15 | F54: HCLTECH.NS
A55: 2015-03-13 | B55: 503.14999 | C55: 362.09369 | D55: 6368968 | E55: FY15 | F55: HCLTECH.NS
A56: 2015-03-16 | B56: 514.25 | C56: 370.08191 | D56: 7937836 | E56: FY15 | F56: HCLTECH.NS
A57: 2015-03-17 | B57: 509.77499 | C57: 366.86142 | D57: 10007444 | E57: FY15 | F57: HCLTECH.NS
A58: 2015-03-18 | B58: 501.63751 | C58: 361.00531 | D58: 18927840 | E58: FY15 | F58: HCLTECH.NS
... A2885: 2026-08-25 | B2885: 1315.8 | C2885: 1315.8 | D2885: 1314187 | E2885: FY27 | F2885: HCLTECH.NS

Sheet Valuation
A1: Valuation
A2: Historical FY-end prices; forecast share price = diluted EPS × target P/E assumption
A5: Metric | B5: Units | C5: FY16A | D5: FY17A | E5: FY18A | F5: FY19A | G5: FY20A | H5: FY21A | I5: FY22A | J5: FY23A | K5: FY24A | L5: FY25A | M5: FY26A | N5: FY27E | O5: FY28E | P5: FY29E | Q5: FY30E
A7: Share price | B7: ₹ / share | C7: 407.04999 | D7: 437.375 | E7: 484.29999 | F7: 541.45001 | G7: 436.39999 | H7: 982.65002 | I7: 1163.75 | J7: 1085.25 | K7: 1543.55 | L7: 1592.5 | M7: 1341.6 | N7: ='Annual P&L'!N34*N18 -> 1426.2299 | O7: ='Annual P&L'!O34*O18 -> 1599.592 | P7: ='Annual P&L'!P34*P18 -> 1799.8324 | Q7: ='Annual P&L'!Q34*Q18 -> 1956.8096
A8: Basic shares outstanding | B8: m | C8: ='Annual P&L'!C31 -> 2713.7 | D8: ='Annual P&L'!D31 -> 2713.7 | E8: ='Annual P&L'!E31 -> 2713.7 | F8: ='Annual P&L'!F31 -> 2713.7 | G8: ='Annual P&L'!G31 -> 2713.7 | H8: ='Annual P&L'!H31 -> 2713.7 | I8: ='Annual P&L'!I31 -> 2713.7 | J8: ='Annual P&L'!J31 -> 2713.7 | ... Q8: ='Annual P&L'!Q31 -> 2713.7
A9: Market capitalization | B9: ₹ cr | C9: =C7*C8/10 -> 110461.16 | D9: =D7*D8/10 -> 118690.45 | E9: =E7*E8/10 -> 131424.49 | F9: =F7*F8/10 -> 146933.29 | G9: =G7*G8/10 -> 118425.87 | H9: =H7*H8/10 -> 266661.74 | I9: =I7*I8/10 -> 315806.84 | J9: =J7*J8/10 -> 294504.29 | ... Q9: =Q7*Q8/10 -> 531019.42
A10: Cash & treasury investments | B10: ₹ cr | C10: ='Annual Balance Sheet'!C7+'Annual Balance Sheet'!C10 -> 11852.9 | D10: ='Annual Balance Sheet'!D7+'Annual Balance Sheet'!D10 -> 12681.8 | E10: ='Annual Balance Sheet'!E7+'Annual Balance Sheet'!E10 -> 9777.7 | F10: ='Annual Balance Sheet'!F7+'Annual Balance Sheet'!F10 -> 11391 | G10: ='Annual Balance Sheet'!G7+'Annual Balance Sheet'!G10 -> 15373 | H10: ='Annual Balance Sheet'!H7+'Annual Balance Sheet'!H10 -> 20490 | I10: ='Annual Balance Sheet'!I7+'Annual Balance Sheet'!I10 -> 21883 | J10: ='Annual Balance Sheet'!J7+'Annual Balance Sheet'!J10 -> 22712 | ... Q10: ='Annual Balance Sheet'!Q7+'Annual Balance Sheet'!Q10 -> 46842.861
A11: Total borrowings | B11: ₹ cr | C11: ='Annual Balance Sheet'!C22 -> 973.2 | D11: ='Annual Balance Sheet'!D22 -> 541.7 | E11: ='Annual Balance Sheet'!E22 -> 437.1 | F11: ='Annual Balance Sheet'!F22 -> 3986 | G11: ='Annual Balance Sheet'!G22 -> 5092 | H11: ='Annual Balance Sheet'!H22 -> 3907 | I11: ='Annual Balance Sheet'!I22 -> 3985 | J11: ='Annual Balance Sheet'!J22 -> 2251 | ... Q11: ='Annual Balance Sheet'!Q22 -> 0
A12: Enterprise value | B12: ₹ cr | C12: =C9-C10+C11 -> 99581.455 | D12: =D9-D10+D11 -> 106550.35 | E12: =E9-E10+E11 -> 122083.89 | F12: =F9-F10+F11 -> 139528.29 | G12: =G9-G10+G11 -> 108144.87 | H12: =H9-H10+H11 -> 250078.74 | I12: =I9-I10+I11 -> 297908.84 | J12: =J9-J10+J11 -> 274043.29 | ... Q12: =Q9-Q10+Q11 -> 484176.56
A13: P/E | B13: x | C13: =IFERROR(C7/'Annual P&L'!C34,"") -> 15.028857 | D13: =IFERROR(D7/'Annual P&L'!D34,"") -> 14.042339 | E13: =IFERROR(E7/'Annual P&L'!E34,"") -> 14.976894 | F13: =IFERROR(F7/'Annual P&L'!F34,"") -> 14.52282 | G13: =IFERROR(G7/'Annual P&L'!G34,"") -> 10.711564 | H13: =IFERROR(H7/'Annual P&L'!H34,"") -> 23.939806 | I13: =IFERROR(I7/'Annual P&L'!I34,"") -> 23.407764 | J13: =IFERROR(J7/'Annual P&L'!J34,"") -> 19.841565 | ... Q13: =IFERROR(Q7/'Annual P&L'!Q34,"") -> 21
A14: EV / EBITDA | B14: x | C14: =IFERROR(C12/'Annual P&L'!C17,"") -> 11.404198 | D14: =IFERROR(D12/'Annual P&L'!D17,"") -> 10.335663 | E14: =IFERROR(E12/'Annual P&L'!E17,"") -> 10.671669 | F14: =IFERROR(F12/'Annual P&L'!F17,"") -> 9.9898539 | G14: =IFERROR(G12/'Annual P&L'!G17,"") -> 6.4780679 | H14: =IFERROR(H12/'Annual P&L'!H17,"") -> 12.532134 | I14: =IFERROR(I12/'Annual P&L'!I17,"") -> 14.510903 | J14: =IFERROR(J12/'Annual P&L'!J17,"") -> 12.110805 | ... Q14: =IFERROR(Q12/'Annual P&L'!Q17,"") -> 12.847995
A15: P / book | B15: x | C15: =IFERROR(C9/'Annual Balance Sheet'!C31,"") -> 3.9419299 | D15: =IFERROR(D9/'Annual Balance Sheet'!D31,"") -> 3.5440142 | E15: =IFERROR(E9/'Annual Balance Sheet'!E31,"") -> 3.569688 | F15: =IFERROR(F9/'Annual Balance Sheet'!F31,"") -> 3.47977 | G15: =IFERROR(G9/'Annual Balance Sheet'!G31,"") -> 2.2680865 | H15: =IFERROR(H9/'Annual Balance Sheet'!H31,"") -> 4.2947614 | I15: =IFERROR(I9/'Annual Balance Sheet'!I31,"") -> 5.0931658 | J15: =IFERROR(J9/'Annual Balance Sheet'!J31,"") -> 4.5032615 | ... Q15: =IFERROR(Q9/'Annual Balance Sheet'!Q31,"") -> 6.3134636
A16: Dividend per share | B16: ₹ / share | C16: ='Annual P&L'!C35 -> 9.9384604 | D16: ='Annual P&L'!D35 -> 14.990603 | E16: ='Annual P&L'!E35 -> 7.4842466 | F16: ='Annual P&L'!F35 -> 4.8678925 | G16: ='Annual P&L'!G35 -> 5.9881343 | H16: ='Annual P&L'!H35 -> 11.998379 | I16: ='Annual P&L'!I35 -> 41.96853 | J16: ='Annual P&L'!J35 -> 47.886649 | ... Q16: ='Annual P&L'!Q35 -> 83.909624
A17: Dividend yield | B17: % | C17: =IFERROR(C16/C7,"") -> 0.024415823 | D17: =IFERROR(D16/D7,"") -> 0.034274029 | E17: =IFERROR(E16/E7,"") -> 0.015453741 | F17: =IFERROR(F16/F7,"") -> 0.0089904745 | G17: =IFERROR(G16/G7,"") -> 0.013721664 | H17: =IFERROR(H16/H7,"") -> 0.012210226 | I17: =IFERROR(I16/I7,"") -> 0.036063184 | J17: =IFERROR(J16/J7,"") -> 0.044124994 | ... Q17: =IFERROR(Q16/Q7,"") -> 0.042880832
A18: Target P/E assumption | B18: x | N18: =Assumptions!C38 -> 20 | O18: =Assumptions!D38 -> 20.5 | P18: =Assumptions!E38 -> 21 | Q18: =Assumptions!F38 -> 21
A19: Implied share price | B19: ₹ / share | N19: =N7 -> 1426.2299 | O19: =O7 -> 1599.592 | P19: =P7 -> 1799.8324 | Q19: =Q7 -> 1956.8096
A20: Upside / (downside) vs prior FY-end | B20: % | N20: =IFERROR(N19/M7-1,"") -> 0.063081337 | O20: =IFERROR(O19/N7-1,"") -> 0.12155272 | P20: =IFERROR(P19/O7-1,"") -> 0.12518217 | Q20: =IFERROR(Q19/P7-1,"") -> 0.087217661

Sheet Checks
A1: Model Checks
A2: All critical accounting, cash and operating reconciliations
A5: Check | B5: Status | C5: Actual / Calc | D5: Control | E5: Difference | F5: Tolerance
A6: OVERALL MODEL STATUS | B6: =IF(COUNTIF(B7:B141,"FAIL")=0,"OK","REVIEW") -> OK
A7: FY16A balance sheet | B7: =IF(ABS('Annual Balance Sheet'!C33)<=0.5,"OK","FAIL") -> OK | C7: ='Annual Balance Sheet'!C17 -> 39767.3 | D7: ='Annual Balance Sheet'!C32 -> 39767.3 | E7: ='Annual Balance Sheet'!C33 -> 0 | F7: 0.5
A8: FY16A cash tie | B8: =IF(ABS('Annual Cash Flow'!C37)<=0.5,"OK","FAIL") -> OK | C8: ='Annual Cash Flow'!C35 -> 729.3 | D8: ='Annual Cash Flow'!C36 -> 729.3 | E8: ='Annual Cash Flow'!C37 -> 0 | F8: 0.5
A9: FY17A balance sheet | B9: =IF(ABS('Annual Balance Sheet'!D33)<=0.5,"OK","FAIL") -> OK | C9: ='Annual Balance Sheet'!D17 -> 46432.3 | D9: ='Annual Balance Sheet'!D32 -> 46432.3 | E9: ='Annual Balance Sheet'!D33 -> 0 | F9: 0.5
A10: FY17A cash tie | B10: =IF(ABS('Annual Cash Flow'!D37)<=0.5,"OK","FAIL") -> OK | C10: ='Annual Cash Flow'!D35 -> 1316.5 | D10: ='Annual Cash Flow'!D36 -> 1316.5 | E10: ='Annual Cash Flow'!D37 -> 0 | F10: 0.5
A11: FY18A balance sheet | B11: =IF(ABS('Annual Balance Sheet'!E33)<=0.5,"OK","FAIL") -> OK | C11: ='Annual Balance Sheet'!E17 -> 48435.1 | D11: ='Annual Balance Sheet'!E32 -> 48435.1 | E11: ='Annual Balance Sheet'!E33 -> 0 | F11: 0.5
A12: FY18A cash tie | B12: =IF(ABS('Annual Cash Flow'!E37)<=0.5,"OK","FAIL") -> OK | C12: ='Annual Cash Flow'!E35 -> 1693.9 | D12: ='Annual Cash Flow'!E36 -> 1693.9 | E12: ='Annual Cash Flow'!E37 -> 0 | F12: 0.5
A13: FY19A balance sheet | B13: =IF(ABS('Annual Balance Sheet'!F33)<=0.5,"OK","FAIL") -> OK | C13: ='Annual Balance Sheet'!F17 -> 58897 | D13: ='Annual Balance Sheet'!F32 -> 58897 | E13: ='Annual Balance Sheet'!F33 -> 0 | F13: 0.5
A14: FY19A cash tie | B14: =IF(ABS('Annual Cash Flow'!F37)<=0.5,"OK","FAIL") -> OK | C14: ='Annual Cash Flow'!F35 -> 5929 | D14: ='Annual Cash Flow'!F36 -> 5929 | E14: ='Annual Cash Flow'!F37 -> 0 | F14: 0.5
A15: FY20A balance sheet | B15: =IF(ABS('Annual Balance Sheet'!G33)<=0.5,"OK","FAIL") -> OK | C15: ='Annual Balance Sheet'!G17 -> 83216 | D15: ='Annual Balance Sheet'!G32 -> 83216 | E15: ='Annual Balance Sheet'!G33 -> 0 | F15: 0.5
A16: FY20A cash tie | B16: =IF(ABS('Annual Cash Flow'!G37)<=0.5,"OK","FAIL") -> OK | C16: ='Annual Cash Flow'!G35 -> 4843 | D16: ='Annual Cash Flow'!G36 -> 4843 | E16: ='Annual Cash Flow'!G37 -> 0 | F16: 0.5
A17: FY21A balance sheet | B17: =IF(ABS('Annual Balance Sheet'!H33)<=0.5,"OK","FAIL") -> OK | C17: ='Annual Balance Sheet'!H17 -> 87702 | D17: ='Annual Balance Sheet'!H32 -> 87702 | E17: ='Annual Balance Sheet'!H33 -> 0 | F17: 0.5
A18: FY21A cash tie | B18: =IF(ABS('Annual Cash Flow'!H37)<=0.5,"OK","FAIL") -> OK | C18: ='Annual Cash Flow'!H35 -> 6515 | D18: ='Annual Cash Flow'!H36 -> 6515 | E18: ='Annual Cash Flow'!H37 -> 0 | F18: 0.5
A19: FY22A balance sheet | B19: =IF(ABS('Annual Balance Sheet'!I33)<=0.5,"OK","FAIL") -> OK | C19: ='Annual Balance Sheet'!I17 -> 89033 | D19: ='Annual Balance Sheet'!I32 -> 89033 | E19: ='Annual Balance Sheet'!I33 -> 0 | F19: 0.5
A20: FY22A cash tie | B20: =IF(ABS('Annual Cash Flow'!I37)<=0.5,"OK","FAIL") -> OK | C20: ='Annual Cash Flow'!I35 -> 10510 | D20: ='Annual Cash Flow'!I36 -> 10510 | E20: ='Annual Cash Flow'!I37 -> 0 | F20: 0.5
A21: FY23A balance sheet | B21: =IF(ABS('Annual Balance Sheet'!J33)<=0.5,"OK","FAIL") -> OK | C21: ='Annual Balance Sheet'!J17 -> 93411 | D21: ='Annual Balance Sheet'!J32 -> 93411 | E21: ='Annual Balance Sheet'!J33 -> 0 | F21: 0.5
A22: FY23A cash tie | B22: =IF(ABS('Annual Cash Flow'!J37)<=0.5,"OK","FAIL") -> OK | C22: ='Annual Cash Flow'!J35 -> 9065 | D22: ='Annual Cash Flow'!J36 -> 9065 | E22: ='Annual Cash Flow'!J37 -> 0 | F22: 0.5
A23: FY24A balance sheet | B23: =IF(ABS('Annual Balance Sheet'!K33)<=0.5,"OK","FAIL") -> OK | C23: ='Annual Balance Sheet'!K17 -> 99777 | D23: ='Annual Balance Sheet'!K32 -> 99777 | E23: ='Annual Balance Sheet'!K33 -> 0 | F23: 0.5
A24: FY24A cash tie | B24: =IF(ABS('Annual Cash Flow'!K37)<=0.5,"OK","FAIL") -> OK | C24: ='Annual Cash Flow'!K35 -> 9456 | D24: ='Annual Cash Flow'!K36 -> 9456 | E24: ='Annual Cash Flow'!K37 -> 0 | F24: 0.5
A25: FY25A balance sheet | B25: =IF(ABS('Annual Balance Sheet'!L33)<=0.5,"OK","FAIL") -> OK | C25: ='Annual Balance Sheet'!L17 -> 105544 | D25: ='Annual Balance Sheet'!L32 -> 105544 | E25: ='Annual Balance Sheet'!L33 -> 0 | F25: 0.5
A26: FY25A cash tie | B26: =IF(ABS('Annual Cash Flow'!L37)<=0.5,"OK","FAIL") -> OK | C26: ='Annual Cash Flow'!L35 -> 8245 | D26: ='Annual Cash Flow'!L36 -> 8245 | E26: ='Annual Cash Flow'!L37 -> 0 | F26: 0.5
A27: FY26A balance sheet | B27: =IF(ABS('Annual Balance Sheet'!M33)<=0.5,"OK","FAIL") -> OK | C27: ='Annual Balance Sheet'!M17 -> 116258 | D27: ='Annual Balance Sheet'!M32 -> 116258 | E27: ='Annual Balance Sheet'!M33 -> 0 | F27: 0.5
A28: FY26A cash tie | B28: =IF(ABS('Annual Cash Flow'!M37)<=0.5,"OK","FAIL") -> OK | C28: ='Annual Cash Flow'!M35 -> 8265 | D28: ='Annual Cash Flow'!M36 -> 8265 | E28: ='Annual Cash Flow'!M37 -> 0 | F28: 0.5
A29: FY27E balance sheet | B29: =IF(ABS('Annual Balance Sheet'!N33)<=0.5,"OK","FAIL") -> OK | C29: ='Annual Balance Sheet'!N17 -> 120006.65 | D29: ='Annual Balance Sheet'!N32 -> 120006.65 | E29: ='Annual Balance Sheet'!N33 -> 0 | F29: 0.5
A30: FY27E cash tie | B30: =IF(ABS('Annual Cash Flow'!N37)<=0.5,"OK","FAIL") -> OK | C30: ='Annual Cash Flow'!N35 -> 11175.182 | D30: ='Annual Cash Flow'!N36 -> 11175.182 | E30: ='Annual Cash Flow'!N37 -> 0 | F30: 0.5
A31: FY28E balance sheet | B31: =IF(ABS('Annual Balance Sheet'!O33)<=0.5,"OK","FAIL") -> OK | C31: ='Annual Balance Sheet'!O17 -> 124857.17 | D31: ='Annual Balance Sheet'!O32 -> 124857.17 | E31: ='Annual Balance Sheet'!O33 -> 0 | F31: 0.5
A32: FY28E cash tie | B32: =IF(ABS('Annual Cash Flow'!O37)<=0.5,"OK","FAIL") -> OK | C32: ='Annual Cash Flow'!O35 -> 12690.724 | D32: ='Annual Cash Flow'!O36 -> 12690.724 | E32: ='Annual Cash Flow'!O37 -> 0 | F32: 0.5
A33: FY29E balance sheet | B33: =IF(ABS('Annual Balance Sheet'!P33)<=0.5,"OK","FAIL") -> OK | C33: ='Annual Balance Sheet'!P17 -> 130439.06 | D33: ='Annual Balance Sheet'!P32 -> 130439.06 | E33: ='Annual Balance Sheet'!P33 -> 0 | F33: 0.5
A34: FY29E cash tie | B34: =IF(ABS('Annual Cash Flow'!P37)<=0.5,"OK","FAIL") -> OK | C34: ='Annual Cash Flow'!P35 -> 14412.746 | D34: ='Annual Cash Flow'!P36 -> 14412.746 | E34: ='Annual Cash Flow'!P37 -> 0 | F34: 0.5
A35: FY30E balance sheet | B35: =IF(ABS('Annual Balance Sheet'!Q33)<=0.5,"OK","FAIL") -> OK | C35: ='Annual Balance Sheet'!Q17 -> 136412.24 | D35: ='Annual Balance Sheet'!Q32 -> 136412.24 | E35: ='Annual Balance Sheet'!Q33 -> 0 | F35: 0.5
A36: FY30E cash tie | B36: =IF(ABS('Annual Cash Flow'!Q37)<=0.5,"OK","FAIL") -> OK | C36: ='Annual Cash Flow'!Q35 -> 16169.033 | D36: ='Annual Cash Flow'!Q36 -> 16169.033 | E36: ='Annual Cash Flow'!Q37 -> 0 | F36: 0.5
A37: FY16 quarterly revenue roll-up | B37: =IF(ABS(E37)<=F37,"OK","FAIL") -> OK | C37: =SUM('Quarterly P&L'!C6:F6) -> 40913 | D37: ='Annual P&L'!C7 -> 40913 | E37: =C37-D37 -> 0 | F37: 1.5
A38: FY16 quarterly EBIT roll-up | B38: =IF(ABS(E38)<=F38,"OK","FAIL") -> OK | C38: =SUM('Quarterly P&L'!C18:F18) -> 8226 | D38: ='Annual P&L'!C20 -> 8226 | E38: =C38-D38 -> 0 | F38: 1.5
A39: FY16 quarterly NI roll-up | B39: =IF(ABS(E39)<=F39,"OK","FAIL") -> OK | C39: =SUM('Quarterly P&L'!C25:F25) -> 7354 | D39: ='Annual P&L'!C29 -> 7354 | E39: =C39-D39 -> 0 | F39: 1.5
A40: FY17 quarterly revenue roll-up | B40: =IF(ABS(E40)<=F40,"OK","FAIL") -> OK | C40: =SUM('Quarterly P&L'!G6:J6) -> 46722 | D40: ='Annual P&L'!D7 -> 46723 | E40: =C40-D40 -> -1 | F40: 1.5
A41: FY17 quarterly EBIT roll-up | B41: =IF(ABS(E41)<=F41,"OK","FAIL") -> OK | C41: =SUM('Quarterly P&L'!G18:J18) -> 9475 | D41: ='Annual P&L'!D20 -> 9474 | E41: =C41-D41 -> 1 | F41: 1.5
A42: FY17 quarterly NI roll-up | B42: =IF(ABS(E42)<=F42,"OK","FAIL") -> OK | C42: =SUM('Quarterly P&L'!G25:J25) -> 8456 | D42: ='Annual P&L'!D29 -> 8457 | E42: =C42-D42 -> -1 | F42: 1.5
A43: FY18 quarterly revenue roll-up | B43: =IF(ABS(E43)<=F43,"OK","FAIL") -> OK | C43: =SUM('Quarterly P&L'!K6:N6) -> 50570 | D43: ='Annual P&L'!E7 -> 50570 | E43: =C43-D43 -> 0 | F43: 1.5
A44: FY18 quarterly EBIT roll-up | B44: =IF(ABS(E44)<=F44,"OK","FAIL") -> OK | C44: =SUM('Quarterly P&L'!K18:N18) -> 9988 | D44: ='Annual P&L'!E20 -> 9987 | E44: =C44-D44 -> 1 | F44: 1.5
A45: FY18 quarterly NI roll-up | B45: =IF(ABS(E45)<=F45,"OK","FAIL") -> OK | C45: =SUM('Quarterly P&L'!K25:N25) -> 8780 | D45: ='Annual P&L'!E29 -> 8780 | E45: =C45-D45 -> 0 | F45: 1.5
A46: FY19 quarterly revenue roll-up | B46: =IF(ABS(E46)<=F46,"OK","FAIL") -> OK | C46: =SUM('Quarterly P&L'!O6:R6) -> 60428 | D46: ='Annual P&L'!F7 -> 60427 | E46: =C46-D46 -> 1 | F46: 1.5
A47: FY19 quarterly EBIT roll-up | B47: =IF(ABS(E47)<=F47,"OK","FAIL") -> OK | C47: =SUM('Quarterly P&L'!O18:R18) -> 11820 | D47: ='Annual P&L'!F20 -> 11820 | E47: =C47-D47 -> 0 | F47: 1.5
A48: FY19 quarterly NI roll-up | B48: =IF(ABS(E48)<=F48,"OK","FAIL") -> OK | C48: =SUM('Quarterly P&L'!O25:R25) -> 10122 | D48: ='Annual P&L'!F29 -> 10123 | E48: =C48-D48 -> -1 | F48: 1.5
A49: FY20 quarterly revenue roll-up | B49: =IF(ABS(E49)<=F49,"OK","FAIL") -> OK | C49: =SUM('Quarterly P&L'!S6:V6) -> 70678 | D49: ='Annual P&L'!G7 -> 70678 | E49: =C49-D49 -> 0 | F49: 1.5
A50: FY20 quarterly EBIT roll-up | B50: =IF(ABS(E50)<=F50,"OK","FAIL") -> OK | C50: =SUM('Quarterly P&L'!S18:V18) -> 13854 | D50: ='Annual P&L'!G20 -> 13853 | E50: =C50-D50 -> 1 | F50: 1.5
A51: FY20 quarterly NI roll-up | B51: =IF(ABS(E51)<=F51,"OK","FAIL") -> OK | C51: =SUM('Quarterly P&L'!S25:V25) -> 11062 | D51: ='Annual P&L'!G29 -> 11062 | E51: =C51-D51 -> 0 | F51: 1.5
A52: FY21 quarterly revenue roll-up | B52: =IF(ABS(E52)<=F52,"OK","FAIL") -> OK | C52: =SUM('Quarterly P&L'!W6:Z6) -> 75379 | D52: ='Annual P&L'!H7 -> 75379 | E52: =C52-D52 -> 0 | F52: 1.5
A53: FY21 quarterly EBIT roll-up | B53: =IF(ABS(E53)<=F53,"OK","FAIL") -> OK | C53: =SUM('Quarterly P&L'!W18:Z18) -> 15344 | D53: ='Annual P&L'!H20 -> 15344 | E53: =C53-D53 -> 0 | F53: 1.5
A54: FY21 quarterly NI roll-up | B54: =IF(ABS(E54)<=F54,"OK","FAIL") -> OK | C54: =SUM('Quarterly P&L'!W25:Z25) -> 11145 | D54: ='Annual P&L'!H29 -> 11145 | E54: =C54-D54 -> 0 | F54: 1.5
A55: FY22 quarterly revenue roll-up | B55: =IF(ABS(E55)<=F55,"OK","FAIL") -> OK | C55: =SUM('Quarterly P&L'!AA6:AD6) -> 85651 | D55: ='Annual P&L'!I7 -> 85651 | E55: =C55-D55 -> 0 | F55: 1.5
A56: FY22 quarterly EBIT roll-up | B56: =IF(ABS(E56)<=F56,"OK","FAIL") -> OK | C56: =SUM('Quarterly P&L'!AA18:AD18) -> 16173 | D56: ='Annual P&L'!I20 -> 16204 | E56: =C56-D56 -> -31 | F56: 50
A57: FY22 quarterly NI roll-up | B57: =IF(ABS(E57)<=F57,"OK","FAIL") -> OK | C57: =SUM('Quarterly P&L'!AA25:AD25) -> 13514 | D57: ='Annual P&L'!I29 -> 13499 | E57: =C57-D57 -> 15 | F57: 50
A58: FY23 quarterly revenue roll-up | B58: =IF(ABS(E58)<=F58,"OK","FAIL") -> OK | C58: =SUM('Quarterly P&L'!AE6:AH6) -> 101456 | D58: ='Annual P&L'!J7 -> 101456 | E58: =C58-D58 -> 0 | F58: 1.5
A59: FY23 quarterly EBIT roll-up | B59: =IF(ABS(E59)<=F59,"OK","FAIL") -> OK | C59: =SUM('Quarterly P&L'!AE18:AH18) -> 18509 | D59: ='Annual P&L'!J20 -> 18483 | E59: =C59-D59 -> 26 | F59: 50
A60: FY23 quarterly NI roll-up | B60: =IF(ABS(E60)<=F60,"OK","FAIL") -> OK | C60: =SUM('Quarterly P&L'!AE25:AH25) -> 14851 | D60: ='Annual P&L'!J29 -> 14851 | E60: =C60-D60 -> 0 | F60: 1.5
A61: FY24 quarterly revenue roll-up | B61: =IF(ABS(E61)<=F61,"OK","FAIL") -> OK | C61: =SUM('Quarterly P&L'!AI6:AL6) -> 109913 | D61: ='Annual P&L'!K7 -> 109913 | E61: =C61-D61 -> 0 | F61: 1.5
A62: FY24 quarterly EBIT roll-up | B62: =IF(ABS(E62)<=F62,"OK","FAIL") -> OK | C62: =SUM('Quarterly P&L'!AI18:AL18) -> 20027 | D62: ='Annual P&L'!K20 -> 20027 | E62: =C62-D62 -> 0 | F62: 1.5
A63: FY24 quarterly NI roll-up | B63: =IF(ABS(E63)<=F63,"OK","FAIL") -> OK | C63: =SUM('Quarterly P&L'!AI25:AL25) -> 15702 | D63: ='Annual P&L'!K29 -> 15702 | E63: =C63-D63 -> 0 | F63: 1.5
A64: FY25 quarterly revenue roll-up | B64: =IF(ABS(E64)<=F64,"OK","FAIL") -> OK | C64: =SUM('Quarterly P&L'!AM6:AP6) -> 117055 | D64: ='Annual P&L'!L7 -> 117055 | E64: =C64-D64 -> 0 | F64: 1.5
A65: FY25 quarterly EBIT roll-up | B65: =IF(ABS(E65)<=F65,"OK","FAIL") -> OK | C65: =SUM('Quarterly P&L'!AM18:AP18) -> 21420 | D65: ='Annual P&L'!L20 -> 21420 | E65: =C65-D65 -> 0 | F65: 1.5
A66: FY25 quarterly NI roll-up | B66: =IF(ABS(E66)<=F66,"OK","FAIL") -> OK | C66: =SUM('Quarterly P&L'!AM25:AP25) -> 17390 | D66: ='Annual P&L'!L29 -> 17390 | E66: =C66-D66 -> 0 | F66: 1.5
A67: FY26 quarterly revenue roll-up | B67: =IF(ABS(E67)<=F67,"OK","FAIL") -> OK | C67: =SUM('Quarterly P&L'!AQ6:AT6) -> 130144 | D67: ='Annual P&L'!M7 -> 130144 | E67: =C67-D67 -> 0 | F67: 1.5
A68: FY26 quarterly EBIT roll-up | B68: =IF(ABS(E68)<=F68,"OK","FAIL") -> OK | C68: =SUM('Quarterly P&L'!AQ18:AT18) -> 22397 | D68: ='Annual P&L'!M20 -> 22397 | E68: =C68-D68 -> 0 | F68: 1.5
A69: FY26 quarterly NI roll-up | B69: =IF(ABS(E69)<=F69,"OK","FAIL") -> OK | C69: =SUM('Quarterly P&L'!AQ25:AT25) -> 17361 | D69: ='Annual P&L'!M29 -> 17361 | E69: =C69-D69 -> 0 | F69: 1.5
A70: FY27E revenue driver tie | B70: =IF(ABS('Revenue Drivers'!N28)<=0.5,"OK","FAIL") -> OK | C70: ='Revenue Drivers'!N26 -> 138192.4 | D70: ='Annual P&L'!N7 -> 138192.4 | E70: ='Revenue Drivers'!N28 -> 0 | F70: 0.5
A71: FY27E segment tie | B71: =IF(ABS('Segment Revenue'!N17)<=0.5,"OK","FAIL") -> OK | C71: ='Segment Revenue'!N15 -> 138192.4 | D71: ='Segment Revenue'!N16 -> 138192.4 | E71: ='Segment Revenue'!N17 -> 0 | F71: 0.5
A72: FY28E revenue driver tie | B72: =IF(ABS('Revenue Drivers'!O28)<=0.5,"OK","FAIL") -> OK | C72: ='Revenue Drivers'!O26 -> 149041.66 | D72: ='Annual P&L'!O7 -> 149041.66 | E72: ='Revenue Drivers'!O28 -> 0 | F72: 0.5
A73: FY28E segment tie | B73: =IF(ABS('Segment Revenue'!O17)<=0.5,"OK","FAIL") -> OK | C73: ='Segment Revenue'!O15 -> 149041.66 | D73: ='Segment Revenue'!O16 -> 149041.66 | E73: ='Segment Revenue'!O17 -> 0 | F73: 0.5
A74: FY29E revenue driver tie | B74: =IF(ABS('Revenue Drivers'!P28)<=0.5,"OK","FAIL") -> OK | C74: ='Revenue Drivers'!P26 -> 162065.57 | D74: ='Annual P&L'!P7 -> 162065.57 | E74: ='Revenue Drivers'!P28 -> 0 | F74: 0.5
A75: FY29E segment tie | B75: =IF(ABS('Segment Revenue'!P17)<=0.5,"OK","FAIL") -> OK | C75: ='Segment Revenue'!P15 -> 162065.57 | D75: ='Segment Revenue'!P16 -> 162065.57 | E75: ='Segment Revenue'!P17 -> 0 | F75: 0.5
A76: FY30E revenue driver tie | B76: =IF(ABS('Revenue Drivers'!Q28)<=0.5,"OK","FAIL") -> OK | C76: ='Revenue Drivers'!Q26 -> 175279.02 | D76: ='Annual P&L'!Q7 -> 175279.02 | E76: ='Revenue Drivers'!Q28 -> 0 | F76: 0.5
A77: FY30E segment tie | B77: =IF(ABS('Segment Revenue'!Q17)<=0.5,"OK","FAIL") -> OK | C77: ='Segment Revenue'!Q15 -> 175279.02 | D77: ='Segment Revenue'!Q16 -> 175279.02 | E77: ='Segment Revenue'!Q17 -> 0 | F77: 0.5
A78: FY16 technical headcount <= total | B78: =IF(ABS(E78)<=F78,"OK","FAIL") -> OK | C78: =MAX(0,'Revenue Drivers'!C9-'Revenue Drivers'!C6) -> 0 | D78: =0 -> 0 | E78: =C78-D78 -> 0 | F78: 0
A79: FY16 billable FTE <= technical employees | B79: =IF(ABS(E79)<=F79,"OK","FAIL") -> OK | C79: =MAX(0,'Revenue Drivers'!C11-'Revenue Drivers'!C9) -> 0 | D79: =0 -> 0 | E79: =C79-D79 -> 0 | F79: 0
A80: FY17 operational geography mix | B80: =IF(ABS(E80)<=F80,"OK","FAIL") -> OK | C80: ='Geography & Verticals'!D11 -> 1 | D80: =1 -> 1 | E80: =C80-D80 -> 0 | F80: 0.002
A81: FY17 vertical mix | B81: =IF(ABS(E81)<=F81,"OK","FAIL") -> OK | C81: ='Geography & Verticals'!D37 -> 1 | D81: =1 -> 1 | E81: =C81-D81 -> 0 | F81: 0.002
A82: FY17 contract mix | B82: =IF(ABS(E82)<=F82,"OK","FAIL") -> OK | C82: ='Revenue Drivers'!D15+'Revenue Drivers'!D35 -> 1 | D82: =1 -> 1 | E82: =C82-D82 -> 0 | F82: 0.002
A83: FY17 technical headcount <= total | B83: =IF(ABS(E83)<=F83,"OK","FAIL") -> OK | C83: =MAX(0,'Revenue Drivers'!D9-'Revenue Drivers'!D6) -> 0 | D83: =0 -> 0 | E83: =C83-D83 -> 0 | F83: 0
A84: FY17 billable FTE <= technical employees | B84: =IF(ABS(E84)<=F84,"OK","FAIL") -> OK | C84: =MAX(0,'Revenue Drivers'!D11-'Revenue Drivers'!D9) -> 0 | D84: =0 -> 0 | E84: =C84-D84 -> 0 | F84: 0
A85: FY18 operational geography mix | B85: =IF(ABS(E85)<=F85,"OK","FAIL") -> OK | C85: ='Geography & Verticals'!E11 -> 0.999 | D85: =1 -> 1 | E85: =C85-D85 -> -0.001 | F85: 0.002
A86: FY18 vertical mix | B86: =IF(ABS(E86)<=F86,"OK","FAIL") -> OK | C86: ='Geography & Verticals'!E37 -> 1 | D86: =1 -> 1 | E86: =C86-D86 -> 0 | F86: 0.002
A87: FY18 contract mix | B87: =IF(ABS(E87)<=F87,"OK","FAIL") -> OK | C87: ='Revenue Drivers'!E15+'Revenue Drivers'!E35 -> 1 | D87: =1 -> 1 | E87: =C87-D87 -> 0 | F87: 0.002
A88: FY18 technical headcount <= total | B88: =IF(ABS(E88)<=F88,"OK","FAIL") -> OK | C88: =MAX(0,'Revenue Drivers'!E9-'Revenue Drivers'!E6) -> 0 | D88: =0 -> 0 | E88: =C88-D88 -> 0 | F88: 0
A89: FY18 billable FTE <= technical employees | B89: =IF(ABS(E89)<=F89,"OK","FAIL") -> OK | C89: =MAX(0,'Revenue Drivers'!E11-'Revenue Drivers'!E9) -> 0 | D89: =0 -> 0 | E89: =C89-D89 -> 0 | F89: 0
A90: FY19 segment mix | B90: =IF(ABS(E90)<=F90,"OK","FAIL") -> OK | C90: =SUM('Segment Revenue'!F7,'Segment Revenue'!F9,'Segment Revenue'!F11,'Segment Revenue'!F13) -> 1 | D90: =1 -> 1 | E90: =C90-D90 -> 0 | F90: 0.002
A91: FY19 operational geography mix | B91: =IF(ABS(E91)<=F91,"OK","FAIL") -> OK | C91: ='Geography & Verticals'!F11 -> 1 | D91: =1 -> 1 | E91: =C91-D91 -> 0 | F91: 0.002
A92: FY19 IFRS geography mix | B92: =IF(ABS(E92)<=F92,"OK","FAIL") -> OK | C92: ='Geography & Verticals'!F22 -> 1 | D92: =1 -> 1 | E92: =C92-D92 -> 0 | F92: 0.002
A93: FY19 vertical mix | B93: =IF(ABS(E93)<=F93,"OK","FAIL") -> OK | C93: ='Geography & Verticals'!F37 -> 1.001 | D93: =1 -> 1 | E93: =C93-D93 -> 0.001 | F93: 0.002
A94: FY19 contract mix | B94: =IF(ABS(E94)<=F94,"OK","FAIL") -> OK | C94: ='Revenue Drivers'!F15+'Revenue Drivers'!F35 -> 1 | D94: =1 -> 1 | E94: =C94-D94 -> 0 | F94: 0.002
A95: FY19 technical headcount <= total | B95: =IF(ABS(E95)<=F95,"OK","FAIL") -> OK | C95: =MAX(0,'Revenue Drivers'!F9-'Revenue Drivers'!F6) -> 0 | D95: =0 -> 0 | E95: =C95-D95 -> 0 | F95: 0
A96: FY19 billable FTE <= technical employees | B96: =IF(ABS(E96)<=F96,"OK","FAIL") -> OK | C96: =MAX(0,'Revenue Drivers'!F11-'Revenue Drivers'!F9) -> 0 | D96: =0 -> 0 | E96: =C96-D96 -> 0 | F96: 0
A97: FY20 segment mix | B97: =IF(ABS(E97)<=F97,"OK","FAIL") -> OK | C97: =SUM('Segment Revenue'!G7,'Segment Revenue'!G9,'Segment Revenue'!G11,'Segment Revenue'!G13) -> 1 | D97: =1 -> 1 | E97: =C97-D97 -> 0 | F97: 0.002
A98: FY20 IFRS geography mix | B98: =IF(ABS(E98)<=F98,"OK","FAIL") -> OK | C98: ='Geography & Verticals'!G22 -> 1 | D98: =1 -> 1 | E98: =C98-D98 -> 0 | F98: 0.002
A99: FY20 technical headcount <= total | B99: =IF(ABS(E99)<=F99,"OK","FAIL") -> OK | C99: =MAX(0,'Revenue Drivers'!G9-'Revenue Drivers'!G6) -> 0 | D99: =0 -> 0 | E99: =C99-D99 -> 0 | F99: 0
A100: FY21 segment mix | B100: =IF(ABS(E100)<=F100,"OK","FAIL") -> OK | C100: =SUM('Segment Revenue'!H7,'Segment Revenue'!H9,'Segment Revenue'!H11,'Segment Revenue'!H13) -> 1 | D100: =1 -> 1 | E100: =C100-D100 -> 0 | F100: 0.002
A101: FY21 operational geography mix | B101: =IF(ABS(E101)<=F101,"OK","FAIL") -> OK | C101: ='Geography & Verticals'!H11 -> 1 | D101: =1 -> 1 | E101: =C101-D101 -> 0 | F101: 0.002
A102: FY21 vertical mix | B102: =IF(ABS(E102)<=F102,"OK","FAIL") -> OK | C102: ='Geography & Verticals'!H37 -> 1 | D102: =1 -> 1 | E102: =C102-D102 -> 0 | F102: 0.002
...
