Workbook

Sheet Summary
A1: Persistent — Financial Summary
A4: Profit & Loss Statement | B4: FY16A | C4: FY17A | D4: FY18A | E4: FY19A | F4: FY20A | G4: FY21A | H4: FY22A | I4: FY23A | J4: FY24A | K4: FY25A | L4: FY26A | M4: FY27E | N4: FY28E | O4: FY29E | P4: FY30E | R4: Key Ratios | S4: FY16A | T4: FY17A | U4: FY18A | V4: FY19A | W4: FY20A | X4: FY21A | Y4: FY22A | Z4: FY23A | AA4: FY24A | AB4: FY25A | AC4: FY26A | AD4: FY27E | AE4: FY28E | AF4: FY29E | AG4: FY30E
A5: Revenue | B5: ='Annual P&L'!B5 -> 23123.31 | C5: ='Annual P&L'!C5 -> 28784.39 | D5: ='Annual P&L'!D5 -> 30337.03 | E5: ='Annual P&L'!E5 -> 33659.41 | F5: ='Annual P&L'!F5 -> 35658.08 | G5: ='Annual P&L'!G5 -> 41878.88 | H5: ='Annual P&L'!H5 -> 57107.46 | I5: ='Annual P&L'!I5 -> 83505.92 | ... P5: ='Annual P&L'!P5 -> 281990.34 | R5: Growth (%) | AJ5: =AC37*1.4 -> 6828.0803 | AK5: =AJ5*(1.15) -> 7852.2923 | AL5: =AK5*1.15 -> 9030.1362 | AM5: =AL5*1.1 -> 9933.1498
A6: Growth | B6: =[1]Annual_Statements!B6 -> 0 | C6: =[1]Annual_Statements!C6 -> 0.096795375 | D6: =[1]Annual_Statements!D6 -> 0.02974374 | E6: =[1]Annual_Statements!E6 -> 0.17234338 | F6: =[1]Annual_Statements!F6 -> 0.098154241 | G6: =[1]Annual_Statements!G6 -> 0.10664053 | H6: =[1]Annual_Statements!H6 -> 0.21068347 | I6: =[1]Annual_Statements!I6 -> 0.20655864 | ... P6: =[1]Annual_Statements!P6 -> 0.058461231 | R6: Revenue | S6: =0 -> 0 | T6: =IFERROR(C5/B5-1,0) -> 0.24482135 | U6: =IFERROR(D5/C5-1,0) -> 0.053940348 | V6: =IFERROR(E5/D5-1,0) -> 0.10951566 | W6: =IFERROR(F5/E5-1,0) -> 0.059379235 | X6: =IFERROR(G5/F5-1,0) -> 0.17445695 | Y6: =IFERROR(H5/G5-1,0) -> 0.36363389 | Z6: =IFERROR(I5/H5-1,0) -> 0.4622594 | AA6: =IFERROR(J5/I5-1,0) -> 0.17615458 | ... AG6: =IFERROR(P5/O5-1,0) -> 0.14041043 | AJ6: =AJ5/AC37-1 -> 0.4 | AK6: =AK5/AD37-1 -> 0.15 | AL6: =AL5/AE37-1 -> 0.15 | AM6: =AM5/AF37-1 -> 0.1
A7: Gross profit | B7: ='Annual P&L'!B10 -> 8818.51 | C7: ='Annual P&L'!C10 -> 10266.37 | D7: ='Annual P&L'!D10 -> 10632.91 | E7: ='Annual P&L'!E10 -> 12281.26 | F7: ='Annual P&L'!F10 -> 12163.75 | G7: ='Annual P&L'!G10 -> 14228.64 | H7: ='Annual P&L'!H10 -> 19212.523 | I7: ='Annual P&L'!I10 -> 28190.6 | ... P7: ='Annual P&L'!P10 -> 102080.5 | R7: EBITDA | S7: =0 -> 0 | T7: =IFERROR(C9/B9-1,0) -> 0.0882965 | U7: =IFERROR(D9/C9-1,0) -> 0.032570743 | V7: =IFERROR(E9/D9-1,0) -> 0.23855607 | W7: =IFERROR(F9/E9-1,0) -> -0.15086403 | X7: =IFERROR(G9/F9-1,0) -> 0.38555524 | Y7: =IFERROR(H9/G9-1,0) -> 0.40285513 | Z7: =IFERROR(I9/H9-1,0) -> 0.58544231 | AA7: =IFERROR(J9/I9-1,0) -> 0.13506262 | ... AG7: =IFERROR(P9/O9-1,0) -> 0.16877885
A8: Gross margin | B8: =B7/B5 -> 0.38136884 | C8: =C7/C5 -> 0.3566645 | D8: =D7/D5 -> 0.35049278 | E8: =E7/E5 -> 0.36486855 | F8: =F7/F5 -> 0.34112184 | G8: =G7/G5 -> 0.33975694 | H8: =H7/H5 -> 0.33642755 | I8: =I7/I5 -> 0.33758804 | ... P8: =P7/P5 -> 0.362 | R8: EBIT | S8: =0 -> 0 | T8: =IFERROR(C11/B11-1,0) -> -0.048884869 | U8: =IFERROR(D11/C11-1,0) -> 0.017430916 | V8: =IFERROR(E11/D11-1,0) -> 0.36440998 | W8: =IFERROR(F11/E11-1,0) -> -0.22748975 | X8: =IFERROR(G11/F11-1,0) -> 0.5519187 | Y8: =IFERROR(H11/G11-1,0) -> 0.56101229 | Z8: =IFERROR(I11/H11-1,0) -> 0.57446907 | AA8: =IFERROR(J11/I11-1,0) -> 0.13445716 | ... AG8: =IFERROR(P11/O11-1,0) -> 0.17928806
A9: EBITDA | B9: ='Annual P&L'!B13 -> 4171.06 | C9: ='Annual P&L'!C13 -> 4539.35 | D9: ='Annual P&L'!D13 -> 4687.2 | E9: ='Annual P&L'!E13 -> 5805.36 | F9: ='Annual P&L'!F13 -> 4929.54 | G9: ='Annual P&L'!G13 -> 6830.15 | H9: ='Annual P&L'!H13 -> 9581.711 | I9: ='Annual P&L'!I13 -> 15191.25 | ... P9: ='Annual P&L'!P13 -> 58090.011 | R9: Net profit | S9: =0 -> 0 | T9: =IFERROR(C16/B16-1,0) -> 0.013801406 | U9: =IFERROR(D16/C16-1,0) -> 0.071726403 | V9: =IFERROR(E16/D16-1,0) -> 0.088492918 | W9: =IFERROR(F16/E16-1,0) -> -0.03238749 | X9: =IFERROR(G16/F16-1,0) -> 0.32439485 | Y9: =IFERROR(H16/G16-1,0) -> 0.53188647 | Z9: =IFERROR(I16/H16-1,0) -> 0.33417103 | AA9: =IFERROR(J16/I16-1,0) -> 0.18716677 | ... AG9: =IFERROR(P16/O16-1,0) -> 0.17906841
A10: EBITDA margin | B10: =B9/B5 -> 0.18038334 | C10: =C9/C5 -> 0.1577018 | D10: =D9/D5 -> 0.15450425 | E10: =E9/E5 -> 0.17247361 | F10: =F9/F5 -> 0.13824468 | G10: =G9/G5 -> 0.16309295 | H10: =H9/H5 -> 0.16778388 | I10: =I9/I5 -> 0.18191824 | ... P10: =P9/P5 -> 0.206 | R10: EPS | S10: =0 -> 0 | T10: =IFERROR(C18/B18-1,0) -> 0.011272142 | U10: =IFERROR(D18/C18-1,0) -> 0.071921444 | V10: =IFERROR(E18/D18-1,0) -> 0.089130973 | W10: =IFERROR(F18/E18-1,0) -> 0.0088656513 | X10: =IFERROR(G18/F18-1,0) -> 0.32875169 | Y10: =IFERROR(H18/G18-1,0) -> 0.53196541 | Z10: =IFERROR(I18/H18-1,0) -> 0.36960372 | AA10: =IFERROR(J18/I18-1,0) -> -0.41453164 | ... AG10: =IFERROR(P18/O18-1,0) -> 0.17906841
A11: EBIT | B11: ='Annual P&L'!B16 -> 3205.9 | C11: ='Annual P&L'!C16 -> 3049.18 | D11: ='Annual P&L'!D16 -> 3102.33 | E11: ='Annual P&L'!E16 -> 4232.85 | F11: ='Annual P&L'!F16 -> 3269.92 | G11: ='Annual P&L'!G16 -> 5074.65 | H11: ='Annual P&L'!H16 -> 7921.591 | I11: ='Annual P&L'!I16 -> 12472.3 | ... P11: ='Annual P&L'!P16 -> 51322.242
A12: EBIT margin | B12: =B11/B5 -> 0.13864365 | C12: =C11/C5 -> 0.10593172 | D12: =D11/D5 -> 0.10226215 | E12: =E11/E5 -> 0.12575532 | F12: =F11/F5 -> 0.091702077 | G12: =G11/G5 -> 0.12117444 | H12: =H11/H5 -> 0.13871377 | I12: =I11/I5 -> 0.14935827 | ... P12: =P11/P5 -> 0.182 | R12: Margins (%)
A13: PBT | B13: ='Annual P&L'!B21 -> 3956.27 | C13: ='Annual P&L'!C21 -> 4006.73 | D13: ='Annual P&L'!D21 -> 4292.61 | E13: ='Annual P&L'!E21 -> 4863.39 | F13: ='Annual P&L'!F21 -> 4523.42 | G13: ='Annual P&L'!G21 -> 6094.43 | H13: ='Annual P&L'!H21 -> 9242.79 | I13: ='Annual P&L'!I21 -> 12408.52 | ... P13: ='Annual P&L'!P21 -> 51604.233 | R13: Gross margin | S13: =B8 -> 0.38136884 | T13: =C8 -> 0.3566645 | U13: =D8 -> 0.35049278 | V13: =E8 -> 0.36486855 | W13: =F8 -> 0.34112184 | X13: =G8 -> 0.33975694 | Y13: =H8 -> 0.33642755 | Z13: =I8 -> 0.33758804 | ... AG13: =P8 -> 0.362
A14: PBT margin | B14: =B13/B5 -> 0.17109445 | C14: =C13/C5 -> 0.13919802 | D14: =D13/D5 -> 0.14149737 | E14: =E13/E5 -> 0.14448827 | F14: =F13/F5 -> 0.1268554 | G14: =G13/G5 -> 0.14552514 | H14: =H13/H5 -> 0.16184908 | I14: =I13/I5 -> 0.14859449 | ... P14: =P13/P5 -> 0.183 | R14: EBITDA margin | S14: =B10 -> 0.18038334 | T14: =C10 -> 0.1577018 | U14: =D10 -> 0.15450425 | V14: =E10 -> 0.17247361 | W14: =F10 -> 0.13824468 | X14: =G10 -> 0.16309295 | Y14: =H10 -> 0.16778388 | Z14: =I10 -> 0.18191824 | ... AG14: =P10 -> 0.206
A15: Income tax | B15: ='Annual P&L'!B23 -> 982.66 | C15: ='Annual P&L'!C23 -> 992.08 | D15: ='Annual P&L'!D23 -> 1061.73 | E15: ='Annual P&L'!E23 -> 1346.6 | F15: ='Annual P&L'!F23 -> 1120.53 | G15: ='Annual P&L'!G23 -> 1587.66 | H15: ='Annual P&L'!H23 -> 2338.93 | I15: ='Annual P&L'!I23 -> 3197.59 | ... P15: ='Annual P&L'!P23 -> 11868.974 | R15: EBIT margin | S15: =B12 -> 0.13864365 | T15: =C12 -> 0.10593172 | U15: =D12 -> 0.10226215 | V15: =E12 -> 0.12575532 | W15: =F12 -> 0.091702077 | X15: =G12 -> 0.12117444 | Y15: =H12 -> 0.13871377 | Z15: =I12 -> 0.14935827 | ... AG15: =P12 -> 0.182
A16: Net profit | B16: ='Annual P&L'!B25 -> 2973.61 | C16: ='Annual P&L'!C25 -> 3014.65 | D16: ='Annual P&L'!D25 -> 3230.88 | E16: ='Annual P&L'!E25 -> 3516.79 | F16: ='Annual P&L'!F25 -> 3402.89 | G16: ='Annual P&L'!G25 -> 4506.77 | H16: ='Annual P&L'!H25 -> 6903.86 | I16: ='Annual P&L'!I25 -> 9210.93 | ... P16: ='Annual P&L'!P25 -> 39735.259 | R16: PBT margin | S16: =B14 -> 0.17109445 | T16: =C14 -> 0.13919802 | U16: =D14 -> 0.14149737 | V16: =E14 -> 0.14448827 | W16: =F14 -> 0.1268554 | X16: =G14 -> 0.14552514 | Y16: =H14 -> 0.16184908 | Z16: =I14 -> 0.14859449 | ... AG16: =P14 -> 0.183
A17: Net margin | B17: =B16/B5 -> 0.12859794 | C17: =C16/C5 -> 0.10473211 | D17: =D16/D5 -> 0.10649955 | E17: =E16/E5 -> 0.10448163 | F17: =F16/F5 -> 0.095431106 | G17: =G16/G5 -> 0.10761439 | H17: =H16/H5 -> 0.12089244 | I17: =I16/I5 -> 0.11030272 | ... P17: =P16/P5 -> 0.14091 | R17: Net margin | S17: =B17 -> 0.12859794 | T17: =C17 -> 0.10473211 | U17: =D17 -> 0.10649955 | V17: =E17 -> 0.10448163 | W17: =F17 -> 0.095431106 | X17: =G17 -> 0.10761439 | Y17: =H17 -> 0.12089244 | Z17: =I17 -> 0.11030272 | ... AG17: =P17 -> 0.14091
A18: Basic EPS | B18: ='Annual P&L'!B29 -> 37.26 | C18: ='Annual P&L'!C29 -> 37.68 | D18: ='Annual P&L'!D29 -> 40.39 | E18: ='Annual P&L'!E29 -> 43.99 | F18: ='Annual P&L'!F29 -> 44.38 | G18: ='Annual P&L'!G29 -> 58.97 | H18: ='Annual P&L'!H29 -> 90.34 | I18: ='Annual P&L'!I29 -> 123.73 | ... P18: ='Annual P&L'!P29 -> 255.09886
A19: Diluted EPS | B19: ='Annual P&L'!B30 -> 37.17 | C19: ='Annual P&L'!C30 -> 37.68 | D19: ='Annual P&L'!D30 -> 40.39 | E19: ='Annual P&L'!E30 -> 43.99 | F19: ='Annual P&L'!F30 -> 44.38 | G19: ='Annual P&L'!G30 -> 58.97 | H19: ='Annual P&L'!H30 -> 90.34 | I19: ='Annual P&L'!I30 -> 120.52 | ... P19: ='Annual P&L'!P30 -> 253.24538 | R19: Returns (%)
A20: Weighted-average basic shares | B20: ='Annual P&L'!B27 -> 79.807032 | C20: ='Annual P&L'!C27 -> 80.006635 | D20: ='Annual P&L'!D27 -> 79.992077 | E20: ='Annual P&L'!E27 -> 79.945215 | F20: ='Annual P&L'!F27 -> 76.676205 | G20: ='Annual P&L'!G27 -> 76.424792 | H20: ='Annual P&L'!H27 -> 76.420855 | I20: ='Annual P&L'!I27 -> 74.443789 | ... P20: ='Annual P&L'!P27 -> 155.76416 | R20: ROE | S20: =B63 -> 0.18139555 | T20: =C63 -> 0.15872736 | U20: =D63 -> 0.15188424 | V20: =E63 -> 0.14999019 | W20: =F63 -> 0.14263367 | X20: =G63 -> 0.16120559 | Y20: =H63 -> 0.20497058 | Z20: =I63 -> 0.23230136 | ... AG20: =P63 -> 0.24164377
A21: Weighted-average diluted shares | B21: ='Annual P&L'!B28 -> 80.000269 | C21: ='Annual P&L'!C28 -> 80.006635 | D21: ='Annual P&L'!D28 -> 79.992077 | E21: ='Annual P&L'!E28 -> 79.945215 | F21: ='Annual P&L'!F28 -> 76.676205 | G21: ='Annual P&L'!G28 -> 76.424792 | H21: ='Annual P&L'!H28 -> 76.420855 | I21: ='Annual P&L'!I28 -> 76.426568 | ... P21: ='Annual P&L'!P28 -> 156.90418 | R21: ROA | S21: =IFERROR(B16/B53,0) -> 0.14116066 | T21: =IFERROR(C16/AVERAGE(B53,C53),0) -> 0.13540116 | U21: =IFERROR(D16/AVERAGE(C53,D53),0) -> 0.12910003 | V21: =IFERROR(E16/AVERAGE(D53,E53),0) -> 0.12754791 | W21: =IFERROR(F16/AVERAGE(E53,F53),0) -> 0.11442578 | X21: =IFERROR(G16/AVERAGE(F53,G53),0) -> 0.13338191 | Y21: =IFERROR(H16/AVERAGE(G53,H53),0) -> 0.15198998 | Z21: =IFERROR(I16/AVERAGE(H53,I53),0) -> 0.15234522 | AA21: =IFERROR(J16/AVERAGE(I53,J53),0) -> 0.15520732 | ... AG21: =IFERROR(P16/AVERAGE(O53,P53),0) -> 0.18905066
R22: FCF margin | S22: =B42 -> 0.038110893 | T22: =C42 -> 0.023914351 | U22: =D42 -> 0.11726164 | V22: =E42 -> 0.11717615 | W22: =F42 -> 0.069263124 | X22: =G42 -> 0.14513784 | Y22: =H42 -> 0.080477927 | Z22: =I42 -> 0.062565983 | ... AG22: =P42 -> 0.15061894
A24: Cash Flow Statement | B24: FY16A | C24: FY17A | D24: FY18A | E24: FY19A | F24: FY20A | G24: FY21A | H24: FY22A | I24: FY23A | J24: FY24A | K24: FY25A | L24: FY26A | M24: FY27E | N24: FY28E | O24: FY29E | P24: FY30E | R24: Gearing
A25: Net profit | B25: =B16 -> 2973.61 | C25: =C16 -> 3014.65 | D25: =D16 -> 3230.88 | E25: =E16 -> 3516.79 | F25: =F16 -> 3402.89 | G25: =G16 -> 4506.77 | H25: =H16 -> 6903.86 | I25: =I16 -> 9210.93 | ... P25: =P16 -> 39735.259 | R25: Net debt / EBITDA | S25: =IFERROR((B55-B46)/B9,0) -> -0.32982024 | T25: =IFERROR((C55-C46)/C9,0) -> -0.31715334 | U25: =IFERROR((D55-D46)/D9,0) -> -0.28314772 | V25: =IFERROR((E55-E46)/E9,0) -> -0.29756639 | W25: =IFERROR((F55-F46)/F9,0) -> -0.3043712 | X25: =IFERROR((G55-G46)/G9,0) -> -0.24258618 | Y25: =IFERROR((H55-H46)/H9,0) -> 0.25691132 | Z25: =IFERROR((I55-I46)/I9,0) -> 0.08090381 | ... AG25: =IFERROR((P55-P46)/P9,0) -> -0.99435193
A26: D&A | B26: ='Annual P&L'!B95 -> 965.16 | C26: ='Annual P&L'!C95 -> 1490.17 | D26: ='Annual P&L'!D95 -> 1584.87 | E26: ='Annual P&L'!E95 -> 1572.51 | F26: ='Annual P&L'!F95 -> 1659.62 | G26: ='Annual P&L'!G95 -> 1755.5 | H26: ='Annual P&L'!H95 -> 1660.12 | I26: ='Annual P&L'!I95 -> 2718.95 | ... P26: ='Annual P&L'!P95 -> 6767.7682 | R26: Debt / equity | S26: =IFERROR(B55/B60,0) -> 0.0015677462 | T26: =IFERROR(C55/C60,0) -> 0.001143075 | U26: =IFERROR(D55/D60,0) -> 0.00077801842 | V26: =IFERROR(E55/E60,0) -> 0.00051051743 | W26: =IFERROR(F55/F60,0) -> 0.016748576 | X26: =IFERROR(G55/G60,0) -> 0.027270783 | Y26: =IFERROR(H55/H60,0) -> 0.16149895 | Z26: =IFERROR(I55/I60,0) -> 0.14877765 | ... AG26: =IFERROR(P55/P60,0) -> 0.029181252
A27: Other non-cash / working capital | B27: =B28-B25-B26 -> -1398.17 | C27: =C28-C25-C26 -> -1640.72 | D27: =D28-D25-D26 -> -603.82 | E27: =E28-E25-E26 -> -766.16 | F27: =F28-F25-F26 -> -1834.33 | G27: =G28-G25-G26 -> 1096.98 | H27: =H28-H25-H26 -> -114.12 | I27: =I28-I25-I26 -> -2372.26 | ... P27: =P28-P25-P26 -> -82.076421 | R27: Net debt / equity | S27: =IFERROR((B55-B46)/B60,0) -> -0.083920171 | T27: =IFERROR((C55-C46)/C60,0) -> -0.075801508 | U27: =IFERROR((D55-D46)/D60,0) -> -0.062390496 | V27: =IFERROR((E55-E46)/E60,0) -> -0.073676578 | W27: =IFERROR((F55-F46)/F60,0) -> -0.062890364 | X27: =IFERROR((G55-G46)/G60,0) -> -0.059266736 | Y27: =IFERROR((H55-H46)/H60,0) -> 0.073084597 | Z27: =IFERROR((I55-I46)/I60,0) -> 0.030996364 | ... AG27: =IFERROR((P55-P46)/P60,0) -> -0.35127005
A28: Cash flow from operations | B28: ='Annual P&L'!B108 -> 2540.6 | C28: ='Annual P&L'!C108 -> 2864.1 | D28: ='Annual P&L'!D108 -> 4211.93 | E28: ='Annual P&L'!E108 -> 4323.14 | F28: ='Annual P&L'!F108 -> 3228.18 | G28: ='Annual P&L'!G108 -> 7359.25 | H28: ='Annual P&L'!H108 -> 8449.86 | I28: ='Annual P&L'!I108 -> 9557.62 | ... P28: ='Annual P&L'!P108 -> 46420.951 | AD28: =AJ5 -> 6828.0803
A29: CFO margin | B29: =B28/B25 -> 0.85438238 | C29: =C28/C25 -> 0.95006054 | D29: =D28/D25 -> 1.3036479 | E29: =E28/E25 -> 1.2292858 | F29: =F28/F25 -> 0.94865835 | G29: =G28/G25 -> 1.6329322 | H29: =H28/H25 -> 1.2239327 | I29: =I28/I25 -> 1.037639 | ... P29: =P28/P25 -> 1.1682559 | R29: Operating KPIs
A30: Capex | B30: ='Annual P&L'!B111 -> -1659.35 | C30: ='Annual P&L'!C111 -> -2175.74 | D30: ='Annual P&L'!D111 -> -654.56 | E30: ='Annual P&L'!E111 -> -379.06 | F30: ='Annual P&L'!F111 -> -758.39 | G30: ='Annual P&L'!G111 -> -1281.04 | H30: ='Annual P&L'!H111 -> -3853.97 | I30: ='Annual P&L'!I111 -> -4332.99 | ... P30: ='Annual P&L'!P111 -> -3947.8648 | R30: Closing headcount | S30: ='People & AI'!B5 -> 9264 | T30: ='People & AI'!C5 -> 9460 | U30: ='People & AI'!D5 -> 8976 | V30: ='People & AI'!E5 -> 9962 | W30: ='People & AI'!F5 -> 10632 | X30: ='People & AI'!G5 -> 13680 | Y30: ='People & AI'!H5 -> 18599 | Z30: ='People & AI'!I5 -> 22889 | ... AG30: ='People & AI'!P5 -> 35100.1
A31: Acquisitions / investments | B31: =B32-B30 -> 1289.42 | C31: =C32-C30 -> -43.61 | D31: =D32-D30 -> -2819.34 | E31: =E32-E30 -> -1879.93 | F31: =F32-F30 -> 609.95 | G31: =G32-G30 -> -4135.69 | H31: =H32-H30 -> -5919.46 | I31: =I32-I30 -> 119.89 | ... P31: =P32-P30 -> -3948.7042 | R31: Billable employees | S31: ='People & AI'!B6 -> 0 | T31: ='People & AI'!C6 -> 0 | U31: ='People & AI'!D6 -> 0 | V31: ='People & AI'!E6 -> 0 | W31: ='People & AI'!F6 -> 0 | X31: ='People & AI'!G6 -> 0 | Y31: ='People & AI'!H6 -> 0 | Z31: ='People & AI'!I6 -> 0 | ... AG31: ='People & AI'!P6 -> 33204.694
A32: Cash flow from investing | B32: ='Annual P&L'!B116 -> -369.93 | C32: ='Annual P&L'!C116 -> -2219.35 | D32: ='Annual P&L'!D116 -> -3473.9 | E32: ='Annual P&L'!E116 -> -2258.99 | F32: ='Annual P&L'!F116 -> -148.44 | G32: ='Annual P&L'!G116 -> -5416.73 | H32: ='Annual P&L'!H116 -> -9773.43 | I32: ='Annual P&L'!I116 -> -4213.1 | ... P32: ='Annual P&L'!P116 -> -7896.569 | R32: Attrition | S32: ='People & AI'!B9 -> 0.164 | T32: ='People & AI'!C9 -> 0.157 | U32: ='People & AI'!D9 -> 0.147 | V32: ='People & AI'!E9 -> 0.167 | W32: ='People & AI'!F9 -> 0.143 | X32: ='People & AI'!G9 -> 0.117 | Y32: ='People & AI'!H9 -> 0.266 | Z32: ='People & AI'!I9 -> 0.198 | ... AG32: ='People & AI'!P9 -> 0.118
A33: Dividends | B33: ='Annual P&L'!B122 -> -1039.51 | C33: ='Annual P&L'!C122 -> -480.01 | D33: ='Annual P&L'!D122 -> -799.79 | E33: ='Annual P&L'!E122 -> -879.14 | F33: ='Annual P&L'!F122 -> -1146.38 | G33: ='Annual P&L'!G122 -> -1069.95 | H33: ='Annual P&L'!H122 -> -1987.05 | I33: ='Annual P&L'!I122 -> -2980.58 | ... P33: ='Annual P&L'!P122 -> -15496.751 | R33: AI revenue mix | S33: ='Bookings & Revenue'!B22/'Bookings & Revenue'!B27 -> 0 | T33: ='Bookings & Revenue'!C22/'Bookings & Revenue'!C27 -> 0 | U33: ='Bookings & Revenue'!D22/'Bookings & Revenue'!D27 -> 0 | V33: ='Bookings & Revenue'!E22/'Bookings & Revenue'!E27 -> 0 | W33: ='Bookings & Revenue'!F22/'Bookings & Revenue'!F27 -> 0 | X33: ='Bookings & Revenue'!G22/'Bookings & Revenue'!G27 -> 0 | Y33: ='Bookings & Revenue'!H22/'Bookings & Revenue'!H27 -> 0 | Z33: ='Bookings & Revenue'!I22/'Bookings & Revenue'!I27 -> 0 | ... AG33: ='Bookings & Revenue'!P22/'Bookings & Revenue'!P27 -> 0.02034478
A34: Buybacks / other financing | B34: ='Annual P&L'!B124 -> -226.78 | C34: ='Annual P&L'!C124 -> -104.07 | D34: ='Annual P&L'!D124 -> -156.35 | E34: ='Annual P&L'!E124 -> -717.06 | F34: ='Annual P&L'!F124 -> -1856.94 | G34: ='Annual P&L'!G124 -> -372.66 | H34: ='Annual P&L'!H124 -> 3809.94 | I34: ='Annual P&L'!I124 -> -1058.87 | ... P34: ='Annual P&L'!P124 -> 0 | R34: Revenue / billable employee | S34: =IFERROR('Annual P&L'!B5/Summary!S31,"") | T34: =IFERROR('Annual P&L'!C5/Summary!T31,"") | U34: =IFERROR('Annual P&L'!D5/Summary!U31,"") | V34: =IFERROR('Annual P&L'!E5/Summary!V31,"") | W34: =IFERROR('Annual P&L'!F5/Summary!W31,"") | X34: =IFERROR('Annual P&L'!G5/Summary!X31,"") | Y34: =IFERROR('Annual P&L'!H5/Summary!Y31,"") | Z34: =IFERROR('Annual P&L'!I5/Summary!Z31,"") | ... AG34: =IFERROR('Annual P&L'!P5/Summary!AG31,"") -> 8.4924843
A35: Debt issuance / repayment | B35: =B36-B33-B34 -> 0 | C35: =C36-C33-C34 -> 0 | D35: =D36-D33-D34 -> 0 | E35: =E36-E33-E34 -> 0 | F35: =F36-F33-F34 -> 0 | G35: =G36-G33-G34 -> 0 | H35: =H36-H33-H34 -> 0 | I35: =I36-I33-I34 -> 0 | ... P35: =P36-P33-P34 -> -3365.2596 | R35: FY26 / current market price (INPUT) | S35: =AC37 -> 4877.2002
A36: Cash flow from financing | B36: ='Annual P&L'!B125 -> -1266.29 | C36: ='Annual P&L'!C125 -> -584.08 | D36: ='Annual P&L'!D125 -> -956.14 | E36: ='Annual P&L'!E125 -> -1596.2 | F36: ='Annual P&L'!F125 -> -3003.32 | G36: ='Annual P&L'!G125 -> -1442.61 | H36: ='Annual P&L'!H125 -> 1822.89 | I36: ='Annual P&L'!I125 -> -4039.45 | ... P36: ='Annual P&L'!P125 -> -18862.011 | R36: Valuations
A37: FX / other | B37: ='Annual P&L'!B128 -> -491.11 | C37: ='Annual P&L'!C128 -> -0.69 | D37: ='Annual P&L'!D128 -> 100.45 | E37: ='Annual P&L'!E128 -> -72.22 | F37: ='Annual P&L'!F128 -> 84.12 | G37: ='Annual P&L'!G128 -> 19.4 | H37: ='Annual P&L'!H128 -> 59.37 | I37: ='Annual P&L'!I128 -> 387.06 | ... P37: ='Annual P&L'!P128 -> 0 | R37: Share price (INR) | S37: 381.07501 | T37: 297.85001 | U37: 347.02499 | V37: 318.39999 | W37: 275.47501 | X37: 961.02502 | Y37: 2382.6499 | Z37: 2304.75 | AA37: 3984.55 | AB37: 5513.75 | AC37: 4877.2002 | AD37: =AJ5 -> 6828.0803 | AE37: =AK5 -> 7852.2923 | AF37: =AL5 -> 9030.1362 | AG37: =AM5 -> 9933.1498
A38: Net change in cash | B38: ='Annual P&L'!B127+'Annual P&L'!B128 -> 413.27 | C38: ='Annual P&L'!C127+'Annual P&L'!C128 -> 59.98 | D38: ='Annual P&L'!D127+'Annual P&L'!D128 -> -117.66 | E38: ='Annual P&L'!E127+'Annual P&L'!E128 -> 395.73 | F38: ='Annual P&L'!F127+'Annual P&L'!F128 -> 160.54 | G38: ='Annual P&L'!G127+'Annual P&L'!G128 -> 519.31 | H38: ='Annual P&L'!H127+'Annual P&L'!H128 -> 558.69 | I38: ='Annual P&L'!I127+'Annual P&L'!I128 -> 1692.13 | ... P38: ='Annual P&L'!P127+'Annual P&L'!P128 -> 19662.371 | R38: Market capitalization | S38: =IF(S37>0,S37*B21,0) -> 30486.103 | T38: =IF(T37>0,T37*C21,0) -> 23829.977 | U38: =IF(U37>0,U37*D21,0) -> 27759.25 | V38: =IF(V37>0,V37*E21,0) -> 25454.556 | W38: =IF(W37>0,W37*F21,0) -> 21122.378 | X38: =IF(X37>0,X37*G21,0) -> 73446.138 | Y38: =IF(Y37>0,Y37*H21,0) -> 182084.14 | Z38: =IF(Z37>0,Z37*I21,0) -> 176144.13 | ... AG38: =IF(AG37>0,AG37*P21,0) -> 1558552.7
A39: Opening cash | B39: ='Annual P&L'!B129 -> 988.13 | C39: ='Annual P&L'!C129 -> 1401.4 | D39: ='Annual P&L'!D129 -> 1461.38 | E39: ='Annual P&L'!E129 -> 1343.72 | F39: ='Annual P&L'!F129 -> 1739.45 | G39: ='Annual P&L'!G129 -> 1899.99 | H39: ='Annual P&L'!H129 -> 2419.3 | I39: ='Annual P&L'!I129 -> 2977.99 | ... P39: ='Annual P&L'!P129 -> 42898.03 | R39: Enterprise value | S39: =IF(S37>0,S38+B55-B46,0) -> 29110.403 | T39: =IF(T37>0,T38+C55-C46,0) -> 22390.307 | U39: =IF(U37>0,U38+D55-D46,0) -> 26432.08 | V39: =IF(V37>0,V38+E55-E46,0) -> 23727.076 | W39: =IF(W37>0,W38+F55-F46,0) -> 19621.968 | X39: =IF(X37>0,X38+G55-G46,0) -> 71789.238 | Y39: =IF(Y37>0,Y38+H55-H46,0) -> 184545.79 | Z39: =IF(Z37>0,Z38+I55-I46,0) -> 177373.16 | ... AG39: =IF(AG37>0,AG38+P55-P46,0) -> 1500790.8
A40: Closing cash | B40: =[1]Annual_Statements!B97 -> 326970 | C40: =[1]Annual_Statements!C97 -> 226250 | D40: =[1]Annual_Statements!D97 -> 198180 | E40: =[1]Annual_Statements!E97 -> 195680 | F40: =[1]Annual_Statements!F97 -> 186490 | G40: =[1]Annual_Statements!G97 -> 247140 | H40: =[1]Annual_Statements!H97 -> 174720 | I40: =[1]Annual_Statements!I97 -> 121730 | ... P40: =[1]Annual_Statements!P97 -> 441280.72 | R40: P / E | S40: =IF(S37>0,IFERROR(S37/B19,0),0) -> 10.25222 | T40: =IF(T37>0,IFERROR(T37/C19,0),0) -> 7.9047242 | U40: =IF(U37>0,IFERROR(U37/D19,0),0) -> 8.5918543 | V40: =IF(V37>0,IFERROR(V37/E19,0),0) -> 7.2380085 | W40: =IF(W37>0,IFERROR(W37/F19,0),0) -> 6.2071881 | X40: =IF(X37>0,IFERROR(X37/G19,0),0) -> 16.296846 | Y40: =IF(Y37>0,IFERROR(Y37/H19,0),0) -> 26.374252 | Z40: =IF(Z37>0,IFERROR(Z37/I19,0),0) -> 19.123382 | ... AG40: =IF(AG37>0,IFERROR(AG37/P19,0),0) -> 39.223419
A41: Free cash flow | B41: =B28+B30 -> 881.25 | C41: =C28+C30 -> 688.36 | D41: =D28+D30 -> 3557.37 | E41: =E28+E30 -> 3944.08 | F41: =F28+F30 -> 2469.79 | G41: =G28+G30 -> 6078.21 | H41: =H28+H30 -> 4595.89 | I41: =I28+I30 -> 5224.63 | ... P41: =P28+P30 -> 42473.086 | R41: EV / EBITDA | S41: =IF(S37>0,IFERROR(S39/B9,0),0) -> 6.979138 | T41: =IF(T37>0,IFERROR(T39/C9,0),0) -> 4.9324918 | U41: =IF(U37>0,IFERROR(U39/D9,0),0) -> 5.6392047 | V41: =IF(V37>0,IFERROR(V39/E9,0),0) -> 4.0870981 | W41: =IF(W37>0,IFERROR(W39/F9,0),0) -> 3.9804867 | X41: =IF(X37>0,IFERROR(X39/G9,0),0) -> 10.510639 | Y41: =IF(Y37>0,IFERROR(Y39/H9,0),0) -> 19.260213 | Z41: =IF(Z37>0,IFERROR(Z39/I9,0),0) -> 11.676008 | ... AG41: =IF(AG37>0,IFERROR(AG39/P9,0),0) -> 25.835609
A42: FCF margin | B42: =IFERROR(B41/B5,0) -> 0.038110893 | C42: =IFERROR(C41/C5,0) -> 0.023914351 | D42: =IFERROR(D41/D5,0) -> 0.11726164 | E42: =IFERROR(E41/E5,0) -> 0.11717615 | F42: =IFERROR(F41/F5,0) -> 0.069263124 | G42: =IFERROR(G41/G5,0) -> 0.14513784 | H42: =IFERROR(H41/H5,0) -> 0.080477927 | I42: =IFERROR(I41/I5,0) -> 0.062565983 | ... P42: =IFERROR(P41/P5,0) -> 0.15061894 | R42: P / book value | S42: =IF(S37>0,IFERROR(S38/B60,0),0) -> 1.8597071 | T42: =IF(T37>0,IFERROR(T38/C60,0),0) -> 1.254696 | U42: =IF(U37>0,IFERROR(U38/D60,0),0) -> 1.3049672 | V42: =IF(V37>0,IFERROR(V38/E60,0),0) -> 1.0856303 | W42: =IF(W37>0,IFERROR(W38/F60,0),0) -> 0.88535404 | X42: =IF(X37>0,IFERROR(X38/G60,0),0) -> 2.6271428 | Y42: =IF(Y37>0,IFERROR(Y38/H60,0),0) -> 5.4059456 | Z42: =IF(Z37>0,IFERROR(Z38/I60,0),0) -> 4.4423876 | ... AG42: =IF(AG37>0,IFERROR(AG38/P60,0),0) -> 9.4780948
R43: Dividend per share | S43: ='[1]Market data'!E5 -> 12.13 | T43: ='[1]Market data'!E6 -> 12.88 | U43: ='[1]Market data'!E7 -> 21.75 | V43: ='[1]Market data'!E8 -> 21.5 | W43: ='[1]Market data'!E9 -> 17.5 | X43: ='[1]Market data'!E10 -> 27 | Y43: ='[1]Market data'!E11 -> 31 | Z43: ='[1]Market data'!E12 -> 34 | AA43: ='[1]Market data'!E13 -> 46 | AB43: ='[1]Market data'!E14 -> 43 | AC43: ='[1]Market data'!E15 -> 48 | AD43: ='[1]Market data'!E16 -> 49.097915 | AE43: ='[1]Market data'!E17 -> 53.821716 | AF43: ='[1]Market data'!E18 -> 57.394577 | AG43: ='[1]Market data'!E19 -> 60.674359
R44: Dividend yield | S44: =IF(S37>0,IFERROR(S43/S37,0),0) -> 0.031831003 | T44: =IF(T37>0,IFERROR(T43/T37,0),0) -> 0.043243242 | U44: =IF(U37>0,IFERROR(U43/U37,0),0) -> 0.062675601 | V44: =IF(V37>0,IFERROR(V43/V37,0),0) -> 0.067525127 | W44: =IF(W37>0,IFERROR(W43/W37,0),0) -> 0.063526634 | X44: =IF(X37>0,IFERROR(X43/X37,0),0) -> 0.028095002 | Y44: =IF(Y37>0,IFERROR(Y43/Y37,0),0) -> 0.013010724 | Z44: =IF(Z37>0,IFERROR(Z43/Z37,0),0) -> 0.014752142 | ... AG44: =IF(AG37>0,IFERROR(AG43/AG37,0),0) -> 0.0061082698
A45: Balance Sheet | B45: FY16A | C45: FY17A | D45: FY18A | E45: FY19A | F45: FY20A | G45: FY21A | H45: FY22A | I45: FY23A | J45: FY24A | K45: FY25A | L45: FY26A | M45: FY27E | N45: FY28E | O45: FY29E | P45: FY30E
A46: Cash & equivalents | B46: ='Annual P&L'!B55 -> 1401.4 | C46: ='Annual P&L'!C55 -> 1461.38 | D46: ='Annual P&L'!D55 -> 1343.72 | E46: ='Annual P&L'!E55 -> 1739.45 | F46: ='Annual P&L'!F55 -> 1899.99 | G46: ='Annual P&L'!G55 -> 2419.3 | H46: ='Annual P&L'!H55 -> 2977.99 | I46: ='Annual P&L'!I55 -> 4670.12 | ... P46: ='Annual P&L'!P55 -> 62560.402 | R46: Revenue Build — Core ex-AI + AI Revenue
A47: Trade receivables | B47: ='Annual P&L'!B54 -> 4275.49 | C47: ='Annual P&L'!C54 -> 4753.83 | D47: ='Annual P&L'!D54 -> 4847.4 | E47: ='Annual P&L'!E54 -> 4923.01 | F47: ='Annual P&L'!F54 -> 5921.96 | G47: ='Annual P&L'!G54 -> 5708.97 | H47: ='Annual P&L'!H54 -> 9484.29 | I47: ='Annual P&L'!I54 -> 15253.22 | ... P47: ='Annual P&L'!P54 -> 44036.848 | R47: Core ex-AI / billable revenue | S47: ='[1]Revenue Drivers'!B18 -> 624410 | T47: ='[1]Revenue Drivers'!C18 -> 684850 | U47: ='[1]Revenue Drivers'!D18 -> 705220 | V47: ='[1]Revenue Drivers'!E18 -> 826760 | W47: ='[1]Revenue Drivers'!F18 -> 907910 | X47: ='[1]Revenue Drivers'!G18 -> 1004730 | Y47: ='[1]Revenue Drivers'!H18 -> 1216410 | Z47: ='[1]Revenue Drivers'!I18 -> 1467670 | ... AG47: ='[1]Revenue Drivers'!P18 -> 2233599.6
A48: Other current assets | B48: ='Annual P&L'!B59 -> 1787.77 | C48: ='Annual P&L'!C59 -> 855.39 | D48: ='Annual P&L'!D59 -> 1563.41 | E48: ='Annual P&L'!E59 -> 1387.79 | F48: ='Annual P&L'!F59 -> 1950.52 | G48: ='Annual P&L'!G59 -> 2083.72 | H48: ='Annual P&L'!H59 -> 2002.94 | I48: ='Annual P&L'!I59 -> 3418.26 | ... P48: ='Annual P&L'!P59 -> 23969.179 | R48: AI revenue | S48: ='[1]Revenue Drivers'!B19 -> 0 | T48: ='[1]Revenue Drivers'!C19 -> 0 | U48: ='[1]Revenue Drivers'!D19 -> 0 | V48: ='[1]Revenue Drivers'!E19 -> 0 | W48: ='[1]Revenue Drivers'!F19 -> 0 | X48: ='[1]Revenue Drivers'!G19 -> 0 | Y48: ='[1]Revenue Drivers'!H19 -> 0 | Z48: ='[1]Revenue Drivers'!I19 -> 0 | ... AG48: ='[1]Revenue Drivers'!P19 -> 151700.66
A49: Total current assets | B49: ='Annual P&L'!B61 -> 13135.63 | C49: ='Annual P&L'!C61 -> 14038.74 | D49: ='Annual P&L'!D61 -> 17619.96 | E49: ='Annual P&L'!E61 -> 18900.1 | F49: ='Annual P&L'!F61 -> 19855.61 | G49: ='Annual P&L'!G61 -> 26703.13 | H49: ='Annual P&L'!H61 -> 28389.29 | I49: ='Annual P&L'!I61 -> 34466.11 | ... P49: ='Annual P&L'!P61 -> 170527.94 | R49: Total modelled revenue | S49: ='[1]Revenue Drivers'!B20 -> 624410 | T49: ='[1]Revenue Drivers'!C20 -> 684850 | U49: ='[1]Revenue Drivers'!D20 -> 705220 | V49: ='[1]Revenue Drivers'!E20 -> 826760 | W49: ='[1]Revenue Drivers'!F20 -> 907910 | X49: ='[1]Revenue Drivers'!G20 -> 1004730 | Y49: ='[1]Revenue Drivers'!H20 -> 1216410 | Z49: ='[1]Revenue Drivers'!I20 -> 1467670 | ... AG49: ='[1]Revenue Drivers'!P20 -> 2385300.2
A50: Net PPE & intangibles | B50: ='Annual P&L'!B39+'Annual P&L'!B43 -> 4429.46 | C50: ='Annual P&L'!C39+'Annual P&L'!C43 -> 5524.54 | D50: ='Annual P&L'!D39+'Annual P&L'!D43 -> 5089.56 | E50: ='Annual P&L'!E39+'Annual P&L'!E43 -> 4230.19 | F50: ='Annual P&L'!F39+'Annual P&L'!F43 -> 3796.73 | G50: ='Annual P&L'!G39+'Annual P&L'!G43 -> 3630.9 | H50: ='Annual P&L'!H39+'Annual P&L'!H43 -> 11187.3 | I50: ='Annual P&L'!I39+'Annual P&L'!I43 -> 14031.37 | ... P50: ='Annual P&L'!P39+'Annual P&L'!P43 -> 10877.71 | R50: AI revenue / total revenue | S50: =IFERROR(S48/S49,0) -> 0 | T50: =IFERROR(T48/T49,0) -> 0 | U50: =IFERROR(U48/U49,0) -> 0 | V50: =IFERROR(V48/V49,0) -> 0 | W50: =IFERROR(W48/W49,0) -> 0 | X50: =IFERROR(X48/X49,0) -> 0 | Y50: =IFERROR(Y48/Y49,0) -> 0 | Z50: =IFERROR(Z48/Z49,0) -> 0 | ... AG50: =IFERROR(AG48/AG49,0) -> 0.063598142
A51: Goodwill & investments | B51: ='Annual P&L'!B42+'Annual P&L'!B44 -> 1522.8 | C51: ='Annual P&L'!C42+'Annual P&L'!C44 -> 2415.67 | D51: ='Annual P&L'!D42+'Annual P&L'!D44 -> 2957.65 | E51: ='Annual P&L'!E42+'Annual P&L'!E44 -> 4426.95 | F51: ='Annual P&L'!F42+'Annual P&L'!F44 -> 4709.91 | G51: ='Annual P&L'!G42+'Annual P&L'!G44 -> 3707.21 | H51: ='Annual P&L'!H42+'Annual P&L'!H44 -> 6667.94 | I51: ='Annual P&L'!I42+'Annual P&L'!I44 -> 11699.71 | ... P51: ='Annual P&L'!P42+'Annual P&L'!P44 -> 20598.26
A52: Other long-term assets | B52: ='Annual P&L'!B49 -> 870.1 | C52: ='Annual P&L'!C49 -> 71.85 | D52: ='Annual P&L'!D49 -> 91.57 | E52: ='Annual P&L'!E49 -> 68.31 | F52: ='Annual P&L'!F49 -> 331.31 | G52: ='Annual P&L'!G49 -> 441.52 | H52: ='Annual P&L'!H49 -> 531.61 | I52: ='Annual P&L'!I49 -> 959.29 | ... P52: ='Annual P&L'!P49 -> 6767.7682
A53: Total assets | B53: ='Annual P&L'!B62 -> 21065.43 | C53: ='Annual P&L'!C62 -> 23463.73 | D53: ='Annual P&L'!D62 -> 26588.62 | E53: ='Annual P&L'!E62 -> 28555.99 | F53: ='Annual P&L'!F62 -> 30921.69 | G53: ='Annual P&L'!G62 -> 36655.24 | H53: ='Annual P&L'!H62 -> 54191.01 | I53: ='Annual P&L'!I62 -> 66730.8 | ... P53: ='Annual P&L'!P62 -> 226621.56
A54: Current liabilities | B54: ='Annual P&L'!B85 -> 4521.15 | C54: ='Annual P&L'!C85 -> 4172.76 | D54: ='Annual P&L'!D85 -> 4869.92 | E54: ='Annual P&L'!E85 -> 4844.42 | F54: ='Annual P&L'!F85 -> 6473.81 | G54: ='Annual P&L'!G85 -> 7697.2 | H54: ='Annual P&L'!H85 -> 14259.59 | I54: ='Annual P&L'!I85 -> 20128.77 | ... P54: ='Annual P&L'!P85 -> 53906.043
A55: Debt & lease liabilities | B55: ='Annual P&L'!B69+'Annual P&L'!B77+'Annual P&L'!B68 -> 25.7 | C55: ='Annual P&L'!C69+'Annual P&L'!C77+'Annual P&L'!C68 -> 21.71 | D55: ='Annual P&L'!D69+'Annual P&L'!D77+'Annual P&L'!D68 -> 16.55 | E55: ='Annual P&L'!E69+'Annual P&L'!E77+'Annual P&L'!E68 -> 11.97 | F55: ='Annual P&L'!F69+'Annual P&L'!F77+'Annual P&L'!F68 -> 399.58 | G55: ='Annual P&L'!G69+'Annual P&L'!G77+'Annual P&L'!G68 -> 762.4 | H55: ='Annual P&L'!H69+'Annual P&L'!H77+'Annual P&L'!H68 -> 5439.64 | I55: ='Annual P&L'!I69+'Annual P&L'!I77+'Annual P&L'!I68 -> 5899.15 | ... P55: ='Annual P&L'!P69+'Annual P&L'!P77+'Annual P&L'!P68 -> 4798.4876
A56: Other long-term liabilities | B56: ='Annual P&L'!B75-'Annual P&L'!B68-'Annual P&L'!B69 -> 125.62 | C56: ='Annual P&L'!C75-'Annual P&L'!C68-'Annual P&L'!C69 -> 276.63 | D56: ='Annual P&L'!D75-'Annual P&L'!D68-'Annual P&L'!D69 -> 430.16 | E56: ='Annual P&L'!E75-'Annual P&L'!E68-'Annual P&L'!E69 -> 252.8 | F56: ='Annual P&L'!F75-'Annual P&L'!F68-'Annual P&L'!F69 -> 190.75 | G56: ='Annual P&L'!G75-'Annual P&L'!G68-'Annual P&L'!G69 -> 240.94 | H56: ='Annual P&L'!H75-'Annual P&L'!H68-'Annual P&L'!H69 -> 2334.14 | I56: ='Annual P&L'!I75-'Annual P&L'!I68-'Annual P&L'!I69 -> 3301.46 | ... P56: ='Annual P&L'!P75-'Annual P&L'!P68-'Annual P&L'!P69 -> 3479.6887
A57: Total liabilities | B57: ='Annual P&L'!B86 -> 4672.47 | C57: ='Annual P&L'!C86 -> 4471.1 | D57: ='Annual P&L'!D86 -> 5316.63 | E57: ='Annual P&L'!E86 -> 5109.19 | F57: ='Annual P&L'!F86 -> 7064.14 | G57: ='Annual P&L'!G86 -> 8698.58 | H57: ='Annual P&L'!H86 -> 20508.81 | I57: ='Annual P&L'!I86 -> 27080.02 | ... P57: ='Annual P&L'!P86 -> 62184.22
A58: Share capital | B58: ='Annual P&L'!B64 -> 800 | C58: ='Annual P&L'!C64 -> 800 | D58: ='Annual P&L'!D64 -> 800 | E58: ='Annual P&L'!E64 -> 791.19 | F58: ='Annual P&L'!F64 -> 764.25 | G58: ='Annual P&L'!G64 -> 764.25 | H58: ='Annual P&L'!H64 -> 764.25 | I58: ='Annual P&L'!I64 -> 764.25 | ... P58: ='Annual P&L'!P64 -> 788.75
A59: Retained earnings & reserves | B59: ='Annual P&L'!B65 -> 15592.96 | C59: ='Annual P&L'!C65 -> 18192.63 | D59: ='Annual P&L'!D65 -> 20471.99 | E59: ='Annual P&L'!E65 -> 22655.61 | F59: ='Annual P&L'!F65 -> 23093.3 | G59: ='Annual P&L'!G65 -> 27192.41 | H59: ='Annual P&L'!H65 -> 32917.95 | I59: ='Annual P&L'!I65 -> 38886.53 | ... P59: ='Annual P&L'!P65 -> 163648.59
A60: Total equity | B60: =B58+B59 -> 16392.96 | C60: =C58+C59 -> 18992.63 | D60: =D58+D59 -> 21271.99 | E60: =E58+E59 -> 23446.8 | F60: =F58+F59 -> 23857.55 | G60: =G58+G59 -> 27956.66 | H60: =H58+H59 -> 33682.2 | I60: =I58+I59 -> 39650.78 | ... P60: =P58+P59 -> 164437.34
A61: Total liabilities & equity | B61: =B60+B57 -> 21065.43 | C61: =C60+C57 -> 23463.73 | D61: =D60+D57 -> 26588.62 | E61: =E60+E57 -> 28555.99 | F61: =F60+F57 -> 30921.69 | G61: =G60+G57 -> 36655.24 | H61: =H60+H57 -> 54191.01 | I61: =I60+I57 -> 66730.8 | ... P61: =P60+P57 -> 226621.56
A62: Net cash / (debt) | B62: =B46-B55 -> 1375.7 | C62: =C46-C55 -> 1439.67 | D62: =D46-D55 -> 1327.17 | E62: =E46-E55 -> 1727.48 | F62: =F46-F55 -> 1500.41 | G62: =G46-G55 -> 1656.9 | H62: =H46-H55 -> -2461.65 | I62: =I46-I55 -> -1229.03 | ... P62: =P46-P55 -> 57761.914
A63: ROE | B63: =IFERROR(B16/B60,0) -> 0.18139555 | C63: =IFERROR(C16/C60,0) -> 0.15872736 | D63: =IFERROR(D16/D60,0) -> 0.15188424 | E63: =IFERROR(E16/E60,0) -> 0.14999019 | F63: =IFERROR(F16/F60,0) -> 0.14263367 | G63: =IFERROR(G16/G60,0) -> 0.16120559 | H63: =IFERROR(H16/H60,0) -> 0.20497058 | I63: =IFERROR(I16/I60,0) -> 0.23230136 | ... P63: =IFERROR(P16/P60,0) -> 0.24164377

Sheet PERSISTENT Prices
A1: Persistent Systems Market Prices
A2: Month-end price history from listing plus exact FY-end closes; latest available close drives the forecast reference price
A5: Date | B5: Close | C5: Adjusted close | D5: Volume | E5: Fiscal year | F5: Source | H5: Fiscal year | I5: FY-end date | J5: FY-end close
A6: 40298.156 | B6: 99.662498 | C6: 81.489655 | D6: 951820 | E6: FY11 | F6: https://finance.yahoo.com/quote/PERSISTENT.NS/history/ | H6: FY11A | I6: 40633.156 | J6: 91.8125
A7: 40329.156 | B7: 96.699997 | C7: 79.365997 | D7: 151008 | E7: FY11 | F7: https://finance.yahoo.com/quote/PERSISTENT.NS/history/ | H7: FY12A | I7: 40998.156 | J7: 79.262497
A8: 40359.156 | B8: 103 | C8: 84.536659 | D8: 198452 | E8: FY11 | F8: https://finance.yahoo.com/quote/PERSISTENT.NS/history/ | H8: FY13A | I8: 41361.156 | J8: 136
A9: 40389.156 | B9: 113.625 | C9: 93.451057 | D9: 228908 | E9: FY11 | F9: https://finance.yahoo.com/quote/PERSISTENT.NS/history/ | H9: FY14A | I9: 41729.156 | J9: 262.36249
A10: 40421.156 | B10: 113.5625 | C10: 93.399658 | D10: 206200 | E10: FY11 | F10: https://finance.yahoo.com/quote/PERSISTENT.NS/history/ | H10: FY15A | I10: 42094.156 | J10: 357.14999
A11: 40451.156 | B11: 111.5875 | C11: 91.775314 | D11: 555560 | E11: FY11 | F11: https://finance.yahoo.com/quote/PERSISTENT.NS/history/ | H11: FY16A | I11: 42460.156 | J11: 381.07501
A12: 40480.156 | B12: 100.8125 | C12: 82.913406 | D12: 183828 | E12: FY11 | F12: https://finance.yahoo.com/quote/PERSISTENT.NS/history/ | H12: FY17A | I12: 42825.156 | J12: 297.85001
A13: 40512.156 | B13: 95.612503 | C13: 78.636658 | D13: 40792 | E13: FY11 | F13: https://finance.yahoo.com/quote/PERSISTENT.NS/history/ | H13: FY18A | I13: 43187.156 | J13: 347.02499
A14: 40543.156 | B14: 107.425 | C14: 88.351852 | D14: 53560 | E14: FY11 | F14: https://finance.yahoo.com/quote/PERSISTENT.NS/history/ | H14: FY19A | I14: 43552.156 | J14: 318.39999
A15: 40574.156 | B15: 96.375 | C15: 80.081886 | D15: 35908 | E15: FY11 | F15: https://finance.yahoo.com/quote/PERSISTENT.NS/history/ | H15: FY20A | I15: 43921.156 | J15: 275.47501
A16: 40602.156 | B16: 94.362503 | C16: 78.409607 | D16: 63840 | E16: FY11 | F16: https://finance.yahoo.com/quote/PERSISTENT.NS/history/ | H16: FY21A | I16: 44286.156 | J16: 961.02502
A17: 40633.156 | B17: 91.8125 | C17: 76.290703 | D17: 187968 | E17: FY11 | F17: https://finance.yahoo.com/quote/PERSISTENT.NS/history/ | H17: FY22A | I17: 44651.156 | J17: 2382.6499
... A21: 40753.156 | B21: 88.837502 | C21: 74.117683 | D21: 16260 | E21: FY12 | F21: https://finance.yahoo.com/quote/PERSISTENT.NS/history/ | H21: FY26A | I21: 46111.156 | J21: 4877.2002
A22: 40785.156 | B22: 80.275002 | C22: 66.973923 | D22: 397204 | E22: FY12 | F22: https://finance.yahoo.com/quote/PERSISTENT.NS/history/
A23: 40816.156 | B23: 76.25 | C23: 63.615837 | D23: 50380 | E23: FY12 | F23: https://finance.yahoo.com/quote/PERSISTENT.NS/history/
A24: 40847.156 | B24: 79.800003 | C24: 66.577644 | D24: 42184 | E24: FY12 | F24: https://finance.yahoo.com/quote/PERSISTENT.NS/history/
A25: 40877.156 | B25: 79.775002 | C25: 66.556801 | D25: 38856 | E25: FY12 | F25: https://finance.yahoo.com/quote/PERSISTENT.NS/history/
A26: 40907.156 | B26: 82.112503 | C26: 68.506973 | D26: 19224 | E26: FY12 | F26: https://finance.yahoo.com/quote/PERSISTENT.NS/history/
A27: 40939.156 | B27: 80.8125 | C27: 68.141914 | D27: 22936 | E27: FY12 | F27: https://finance.yahoo.com/quote/PERSISTENT.NS/history/
A28: 40968.156 | B28: 77.237503 | C28: 65.127457 | D28: 14740 | E28: FY12 | F28: https://finance.yahoo.com/quote/PERSISTENT.NS/history/
A29: 40998.156 | B29: 79.262497 | C29: 66.834946 | D29: 23220 | E29: FY12 | F29: https://finance.yahoo.com/quote/PERSISTENT.NS/history/
A30: 41029.156 | B30: 89.949997 | C30: 75.846764 | D30: 71384 | E30: FY13 | F30: https://finance.yahoo.com/quote/PERSISTENT.NS/history/
A31: 41060.156 | B31: 85.849998 | C31: 72.389595 | D31: 17388 | E31: FY13 | F31: https://finance.yahoo.com/quote/PERSISTENT.NS/history/
A32: 41089.156 | B32: 99.112503 | C32: 83.572678 | D32: 43016 | E32: FY13 | F32: https://finance.yahoo.com/quote/PERSISTENT.NS/history/
A33: 41121.156 | B33: 96.212502 | C33: 81.650696 | D33: 35660 | E33: FY13 | F33: https://finance.yahoo.com/quote/PERSISTENT.NS/history/
... A202: 46265.156 | B202: 5594.5 | C202: 5594.5 | D202: 1111436 | E202: FY27 | F202: https://finance.yahoo.com/quote/PERSISTENT.NS/history/

Sheet Sources
A1: Sources & Data Conventions
A2: Primary-source register; non-disclosed metrics remain blank, derived classifications are explicit and forecast assumptions are editable
A5: ID | B5: Data / period | C5: Units | D5: Primary source | E5: Model use | F5: Status | G5: Notes
A6: S1 | B6: Annual reports FY16–FY25 | C6: ₹m | D6: https://www.persistent.com/investors/financial-results-and-reports/annual-reports/ | E6: Audited P&L, balance sheet and cash flow | F6: Loaded | G6: Annual comparatives used; explicit classification residuals preserve reported totals
A7: S2 | B7: FY26 audited consolidated statements | C7: ₹m | D7: https://www.persistent.com/wp-content/uploads/2026/04/Consolidated-Financial-Statements-FY2025-26.pdf | E7: FY26 annual three statements and segment note | F7: Loaded | G7: FY26 revenue ₹147,484.5m; PAT ₹18,651.2m
A8: S3 | B8: Quarterly archives FY16–FY20 | C8: ₹m / $m / % / # | D8: https://www.persistent.com/investors/quarterly-results/ | E8: Quarterly P&L and operating history | F8: Loaded | G8: Official ZIP archives
A9: S4 | B9: Quarterly factsheets FY21–FY26 | C9: ₹m / $m / % / # | D9: https://www.persistent.com/investors/quarterly-results/ | E9: Quarterly P&L, mix, clients, people and bookings | F9: Loaded | G9: Quarterly current-period column retained
A10: S5 | B10: Q1 FY27 presentation and FS | C10: ₹m / $m / % / # | D10: https://www.persistent.com/wp-content/uploads/2026/08/analyst-presentation-and-factsheet-q1fy27.pdf | E10: Q1 FY27 actuals, TCV/ACV and operating KPIs | F10: Loaded | G10: Revenue $452.4m; TCV $1,146.2m; ACV $536.8m
A11: S6 | B11: Nagarro transaction | C11: EUR / scenario | D11: https://www.persistent.com/investors/investors-communication/investor-events/ | E11: Default-off M&A scenario | F11: Loaded | G11: Pending transaction is not consolidated in base case
A12: S7 | B12: Market prices | C12: ₹ / share | D12: https://finance.yahoo.com/quote/PERSISTENT.NS/history/ | E12: Daily series downloaded; month-end history displayed with exact FY-end closes | F12: Loaded | G12: Third-party price series only; editable forecast reference price
A13: S8 | B13: Historical direct cost / gross profit | C13: ₹m | D13: Official quarterly factsheets | E13: Calculated annual operating lines | F13: Calculated | G13: Sum of four reported quarters; audited annual PBT/PAT remain source of truth
A14: S9 | B14: Historical cash-flow residuals | C14: ₹m | D14: Audited CFS totals | E14: Line-by-line reconciliation | F14: Calculated | G14: Residuals make reported totals transparent; forecast residual is zero
A15: S10 | B15: Historical AI revenue | C15: n/a | D15: n/a | E15: Forecast policy | F15: Not disclosed | G15: AI narrative/activity is not hardcoded as historical revenue

Sheet Assumptions
A1: Forecast Assumptions
A2: Blue text on yellow = editable; all forecast financials and valuation outputs are formula-driven
A5: Driver | B5: FY27E | C5: FY28E | D5: FY29E | E5: FY30E | F5: Logic / interpretation
A6: Revenue retention | B6: 0.97 | C6: 0.972 | D6: 0.974 | E6: 0.975 | F6: Retained prior-year organic revenue; FY27 uses Q1 annualized run-rate instead
A7: ACV growth | B7: 0.12 | C7: 0.1 | D7: 0.09 | E7: 0.08 | F7: Total ACV bookings
A8: New ACV share | B8: 0.55 | C8: 0.56 | D8: 0.57 | E8: 0.58 | F8: Scenario share of ACV representing new scope
A9: New ACV first-year realization | B9: 0.1 | C9: 0.16 | D9: 0.16 | E9: 0.16 | F9: Revenue recognized from new ACV
A10: Strategic mega-deal TCV | B10: 650 | C10: 650 | D10: 650 | E10: 650 | F10: Q1 FY27 disclosed strategic deal; no incremental undisclosed mega-deal added
A11: Strategic deal realization | B11: 0.08 | C11: 0.1 | D11: 0.12 | E11: 0.12 | F11: Annual revenue ramp from disclosed strategic TCV
A12: Client farming / pricing uplift | B12: 0.015 | C12: 0.015 | D12: 0.015 | E12: 0.015 | F12: Cross-sell, wallet-share and pricing on prior revenue
A13: T&M mix | B13: 0.6 | C13: 0.58 | D13: 0.56 | E13: 0.54 | F13: Model assumption; not a reported historical series
A14: AI deflation on T&M | B14: 0.01 | C14: 0.01 | D14: 0.008 | E14: 0.006 | F14: Productivity / rate deflation on T&M pool
A15: Incremental AI uplift | B15: 0.035 | C15: 0.04 | D15: 0.045 | E15: 0.045 | F15: Incremental AI-led demand; not historical disclosed AI revenue
A16: Average INR / USD | B16: 91 | C16: 95 | D16: 96 | E16: 97 | F16: Translation rate
A17: Gross margin | B17: 0.352 | C17: 0.356 | D17: 0.359 | E17: 0.362 | F17: Delivery leverage and mix
... A52: DCF weight | B52: 0.3 | C52: 0.3 | D52: 0.3 | E52: 0.3 | F52: Blended valuation
A53: Reference market price | B53: ='PERSISTENT Prices'!B202 -> 5594.5 | C53: ='PERSISTENT Prices'!B202 -> 5594.5 | D53: ='PERSISTENT Prices'!B202 -> 5594.5 | E53: ='PERSISTENT Prices'!B202 -> 5594.5 | F53: Latest historical close carried into FY27–FY30; editable
A54: Nagarro scenario toggle | B54: 0 | C54: 0 | D54: 0 | E54: 0 | F54: 0 = exclude; 1 = include scenario inputs
A55: Nagarro consolidation months | B55: 0 | C55: 12 | D55: 12 | E55: 12 | F55: User input after closing
A56: Nagarro annual revenue | B56: 0 | C56: 0 | D56: 0 | E56: 0 | F56: User input; no unreported revenue is hardcoded
A57: Nagarro revenue growth | B57: 0 | C57: 0 | D57: 0 | E57: 0 | F57: Scenario growth
A58: Nagarro cash consideration | B58: 0 | C58: 0 | D58: 0 | E58: 0 | F58: Cash acquisition outflow
A59: Nagarro share consideration | B59: 0 | C59: 0 | D59: 0 | E59: 0 | F59: Non-cash equity consideration
A60: Nagarro debt funding | B60: 0 | C60: 0 | D60: 0 | E60: 0 | F60: Acquisition financing
A61: Nagarro net assets acquired | B61: 0 | C61: 0 | D61: 0 | E61: 0 | F61: Scenario purchase-price allocation input

Sheet Raw Financials
A1: Raw Reported Financials — Source Layer
A2: Hardcoded official reported inputs only; calculations and classifications live downstream
A4: Annual reported P&L
A5: Metric | B5: Units | C5: FY16A | D5: FY17A | E5: FY18A | F5: FY19A | G5: FY20A | H5: FY21A | I5: FY22A | J5: FY23A | K5: FY24A | L5: FY25A | M5: FY26A
A6: Revenue | B6: ₹m | C6: 23123.31 | D6: 28784.39 | E6: 30337.03 | F6: 33659.41 | G6: 35658.08 | H6: 41878.88 | I6: 57107.46 | J6: 83505.92 | K6: 98215.87 | L6: 119387.17 | M6: 147484.49
A7: Other income | B7: ₹m | C7: 784.49 | D7: 958.45 | E7: 1191.01 | F7: 876.55 | G7: 1323.77 | H7: 1077.72 | I7: 1439.55 | J7: 706.17 | K7: 1280.2 | L7: 1381.54 | M7: 1804.26
A8: Total income | B8: ₹m | C8: 23907.8 | D8: 29742.84 | E8: 31528.04 | F8: 34535.96 | G8: 36981.85 | H8: 42956.6 | I8: 58547.01 | J8: 84212.09 | K8: 99496.07 | L8: 120768.71 | M8: 149288.75
A9: Employee benefits | B9: ₹m | C9: 13828.26 | D9: 17648.97 | E9: 18316.46 | F9: 19249.53 | G9: 21556.4 | H9: 25157.99 | I9: 34593.1 | J9: 49695.65 | K9: 59609.7 | L9: 68737.17 | M9: 79495.42
A10: Subcontracting / professionals | B10: ₹m | C10: 1586.63 | D10: 2177.66 | E10: 3180.63 | F10: 3490.45 | G10: 3918.94 | H10: 5563.68 | I10: 7974.18 | J10: 10426.01 | K10: 11492.7 | L10: 17491.65 | M10: 21986.14
A11: Finance costs | B11: ₹m | C11: 0.92 | D11: 0.91 | E11: 0.79 | F11: 3.05 | G11: 63.32 | H11: 57.94 | I11: 118.35 | J11: 473.4 | K11: 467.27 | L11: 671.29 | M11: 726.82
A12: D&A | B12: ₹m | C12: 965.16 | D12: 1490.17 | E12: 1584.87 | F12: 1572.51 | G12: 1659.62 | H12: 1755.5 | I12: 1660.12 | J12: 2718.95 | K12: 3093.73 | L12: 3069.1 | M12: 4029.5
A13: Other expenses | B13: ₹m | C13: 3570.56 | D13: 4304.29 | E13: 4152.68 | F13: 5357.03 | G13: 5260.15 | H13: 4327.06 | I13: 4958.47 | J13: 8193.01 | K13: 10356.61 | L13: 12576.42 | M13: 18048.5
A14: PBT pre-exceptional | B14: ₹m | C14: 3956.27 | D14: 4120.84 | E14: 4292.61 | F14: 4863.39 | G14: 4523.42 | H14: 6094.43 | I14: 9242.79 | J14: 12705.07 | K14: 14476.06 | L14: 18223.08 | M14: 25002.37
A15: Exceptional items | B15: ₹m | C15: 0 | D15: -114.11 | E15: 0 | F15: 0 | G15: 0 | H15: 0 | I15: 0 | J15: -296.55 | K15: 0 | L15: 0 | M15: -890.25
A16: PBT | B16: ₹m | C16: 3956.27 | D16: 4006.73 | E16: 4292.61 | F16: 4863.39 | G16: 4523.42 | H16: 6094.43 | I16: 9242.79 | J16: 12408.52 | K16: 14476.06 | L16: 18223.08 | M16: 24112.12
A17: Tax | B17: ₹m | C17: 982.66 | D17: 992.08 | E17: 1061.73 | F17: 1346.6 | G17: 1120.53 | H17: 1587.66 | I17: 2338.93 | J17: 3197.59 | K17: 3541.15 | L17: 4221.47 | M17: 5460.92
... A20: Diluted EPS | B20: ₹ / share | C20: 37.17 | D20: 37.68 | E20: 40.39 | F20: 43.99 | G20: 44.38 | H20: 58.97 | I20: 90.34 | J20: 120.52 | K20: 71.07 | L20: 90.24 | M20: 118.87
A24: Quarterly reported P&L
A25: Metric | B25: Units | C25: Q1 FY16A | D25: Q2 FY16A | E25: Q3 FY16A | F25: Q4 FY16A | G25: Q1 FY17A | H25: Q2 FY17A | I25: Q3 FY17A | J25: Q4 FY17A | K25: Q1 FY18A | L25: Q2 FY18A | M25: Q3 FY18A | N25: Q4 FY18A | O25: Q1 FY19A | P25: Q2 FY19A | Q25: Q3 FY19A | R25: Q4 FY19A | S25: Q1 FY20A | T25: Q2 FY20A | U25: Q3 FY20A | V25: Q4 FY20A | W25: Q1 FY21A | X25: Q2 FY21A | Y25: Q3 FY21A | Z25: Q4 FY21A | AA25: Q1 FY22A | AB25: Q2 FY22A | AC25: Q3 FY22A | AD25: Q4 FY22A | AE25: Q1 FY23A | AF25: Q2 FY23A | AG25: Q3 FY23A | AH25: Q4 FY23A | AI25: Q1 FY24A | AJ25: Q2 FY24A | AK25: Q3 FY24A | AL25: Q4 FY24A | AM25: Q1 FY25A | AN25: Q2 FY25A | AO25: Q3 FY25A | AP25: Q4 FY25A | AQ25: Q1 FY26A | AR25: Q2 FY26A | AS25: Q3 FY26A | AT25: Q4 FY26A | AU25: Q1 FY27A
A26: Revenue | B26: $m | C26: 78.61 | D26: 82.96 | E26: 89.65 | F26: 100.43 | G26: 104.76 | H26: 105.18 | I26: 110.03 | J26: 109.03 | K26: 112.97 | L26: 118.1 | M26: 122.53 | N26: 116.95 | O26: 123.6 | P26: 118.23 | Q26: 120.84 | R26: 118.3 | S26: 119.62 | T26: 125.51 | U26: 129.43 | V26: 127.05 | W26: 131.02 | X26: 136.09 | Y26: 146.15 | Z26: 152.82 | AA26: 144.93129 | AB26: 182.32 | AC26: 172.68 | AD26: 217.32 | AE26: 241.52 | AF26: 255.56 | AG26: 242.65 | AH26: 274.55 | AI26: 282.9 | AJ26: 291.71 | AK26: 300.55 | AL26: 310.89 | AM26: 328.2 | AN26: 345.5 | AO26: 360.2 | AP26: 375.2 | AQ26: 389.7 | AR26: 406.2 | AS26: 422.5 | AT26: 436 | AU26: 452.4
A27: Average FX | B27: ₹ / $ | C27: 63.66 | D27: 65.42 | E27: 66.04 | F27: 67.42 | G27: 66.99 | H27: 66.93 | I27: 67.76 | J27: 66.69 | K27: 64.44 | L27: 64.46 | M27: 64.63 | N27: 64.35 | O27: 67.5 | P27: 70.67 | Q27: 71.52 | R27: 70.32 | S27: 69.56 | T27: 70.48 | U27: 71.29 | V27: 72.91 | W27: 75.69 | X27: 74.05 | Y27: 73.58 | Z27: 72.85 | AA27: 73.7372 | AB27: 74.11 | AC27: 74.92 | AE27: 77.76 | AF27: 80.16 | AG27: 82.06 | AH27: 82.12 | AI27: 82.05 | AJ27: 82.67 | AK27: 83.12 | AL27: 83.33 | AM27: 83.4 | AN27: 83.9 | AO27: 85 | AP27: 86.4 | AQ27: 85.5 | AR27: 88.2 | AS27: 89.4 | AT27: 93 | AU27: 95.1
A28: Revenue | B28: ₹m | C28: 5004.16 | D28: 5427.31 | E28: 5920.74 | F28: 6771.1 | G28: 7017.77 | H28: 7040.19 | I28: 7455.35 | J28: 7271.08 | K28: 7280.15 | L28: 7612.52 | M28: 7918.9 | N28: 7525.46 | O28: 8342.81 | P28: 8355.57 | Q28: 8642.49 | R28: 8318.54 | S28: 8321.14 | T28: 8846 | U28: 9227.29 | V28: 9263.65 | W28: 9913.85 | X28: 10077.47 | Y28: 10753.98 | Z28: 11133.58 | AA28: 12299.261 | AB28: 13512.49 | AC28: 14917.17 | AD28: 16378.54 | AE28: 18781.11 | AF28: 20486.41 | AG28: 21693.68 | AH28: 22544.72 | AI28: 23211.75 | AJ28: 24116.7 | AK28: 24982.16 | AL28: 25905.26 | AM28: 27371.7 | AN28: 28971.5 | AO28: 30622.8 | AP28: 32421.1 | AQ28: 33335.9 | AR28: 35807.2 | AS28: 37782.1 | AT28: 40559.4 | AU28: 43032.3
A29: Cost of revenue | B29: ₹m | C29: 3015.2 | D29: 3313.74 | E29: 3622.39 | F29: 4353.47 | G29: 4584.52 | H29: 4538.51 | I29: 4751.02 | J29: 4643.97 | K29: 4783.17 | L29: 4994.06 | M29: 5008.9 | N29: 4917.99 | O29: 5372.82 | P29: 5409.62 | Q29: 5341.15 | R29: 5254.56 | S29: 5434.02 | T29: 5773.25 | U29: 6157.43 | V29: 6129.63 | W29: 6646.37 | X29: 6576.62 | Y29: 7064.21 | Z29: 7363.04 | AA29: 8173.087 | AB29: 8982.03 | AC29: 9880.34 | AD29: 10859.49 | AE29: 12433.14 | AF29: 13628.38 | AG29: 14360.05 | AH29: 14893.75 | AI29: 15278.46 | AJ29: 16127.2 | AK29: 16539.12 | AM29: 18328.7 | AN29: 19294 | AO29: 20000.4 | AP29: 21117 | AQ29: 21576.2 | AR29: 22923.8 | AS29: 25017.8 | AT29: 26246.9 | AU29: 27915.4
A30: Gross profit | B30: ₹m | C30: 1988.96 | D30: 2113.57 | E30: 2298.35 | F30: 2417.63 | G30: 2433.25 | H30: 2501.68 | I30: 2704.33 | J30: 2627.11 | K30: 2496.98 | L30: 2618.46 | M30: 2910 | N30: 2607.47 | O30: 2969.99 | P30: 2945.95 | Q30: 3301.34 | R30: 3063.98 | S30: 2887.12 | T30: 3072.75 | U30: 3069.86 | V30: 3134.02 | W30: 3267.48 | X30: 3500.85 | Y30: 3689.77 | Z30: 3770.54 | AA30: 4126.183 | AB30: 4530.46 | AC30: 5036.83 | AD30: 5519.05 | AE30: 6347.97 | AF30: 6858.03 | AG30: 7333.63 | AH30: 7650.97 | AI30: 7933.29 | AJ30: 7989.5 | AK30: 8443.04 | AL30: 8618.95 | AM30: 9043 | AN30: 9677.5 | AO30: 10622.5 | AP30: 11304.1 | AQ30: 11759.7 | AR30: 12883.4 | AS30: 12764.3 | AT30: 14312.4 | AU30: 15116.9
A31: Gross margin | B31: % | C31: 0.39746131 | D31: 0.38943233 | E31: 0.38818627 | F31: 0.35705129 | G31: 0.34672695 | H31: 0.35534268 | I31: 0.36273683 | J31: 0.36130946 | K31: 0.34298469 | L31: 0.34396757 | M31: 0.36747528 | N31: 0.34648646 | O31: 0.35599396 | P31: 0.35257319 | Q31: 0.38198945 | R31: 0.36833146 | S31: 0.34696207 | T31: 0.34736039 | U31: 0.33269356 | V31: 0.33831373 | W31: 0.3295874 | X31: 0.34739374 | Y31: 0.34310739 | Z31: 0.33866375 | AA31: 0.33548219 | AB31: 0.33527943 | AC31: 0.33765319 | AD31: 0.33696837 | AE31: 0.33799759 | AF31: 0.33475997 | AG31: 0.33805376 | AH31: 0.3393686 | AI31: 0.34177906 | AJ31: 0.33128496 | AK31: 0.33796277 | AL31: 0.33271042 | AM31: 0.33037773 | AN31: 0.33403517 | AO31: 0.34688206 | AP31: 0.34866491 | AQ31: 0.35276384 | AR31: 0.35979915 | AS31: 0.33783988 | AT31: 0.35287504 | AU31: 0.35129194
A32: SG&A | B32: ₹m | C32: 1019.88 | D32: 1096.06 | E32: 1187.9 | F32: 1343.61 | G32: 1375.74 | H32: 1393.89 | I32: 1517.78 | J32: 1439.61 | K32: 1453.4 | L32: 1460.64 | M32: 1534.83 | N32: 1496.84 | O32: 1569.53 | P32: 1509.72 | Q32: 1598.17 | R32: 1798.48 | S32: 1685.19 | T32: 1856.3 | U32: 1835.55 | V32: 1857.17 | W32: 1803.12 | X32: 1843.13 | Y32: 1864.99 | Z32: 1887.25 | AA32: 2110.981 | AB32: 2286.52 | AC32: 2526 | AD32: 2707.31 | AE32: 3015.05 | AF32: 3178.39 | AG32: 3318.08 | AH32: 3487.83 | AI32: 3703.85 | AJ32: 3937.88 | AK32: 4024.7 | AM32: 4490.9 | AN32: 4870.3 | AO32: 5244.1 | AP32: 5460.2 | AQ32: 5643.7 | AR32: 6045.5 | AS32: 6331 | AT32: 6635.4 | AU32: 7095.3
A33: EBITDA | B33: ₹m | C33: 969.08 | D33: 1017.51 | E33: 1110.45 | F33: 1074.02 | G33: 1057.51 | H33: 1107.79 | I33: 1186.55 | J33: 1187.5 | K33: 1043.58 | L33: 1157.82 | M33: 1375.17 | N33: 1110.63 | O33: 1400.46 | P33: 1436.23 | Q33: 1703.17 | R33: 1265.5 | S33: 1201.93 | T33: 1216.45 | U33: 1234.31 | V33: 1276.85 | W33: 1464.36 | X33: 1657.72 | Y33: 1824.78 | Z33: 1883.29 | AA33: 2015.201 | AB33: 2243.94 | AC33: 2510.83 | AD33: 2811.74 | AE33: 3332.92 | AF33: 3679.64 | AG33: 4015.55 | AH33: 4163.14 | AI33: 4229.44 | AJ33: 4051.62 | AK33: 4418.34 | AL33: 4543.62 | AM33: 4552.1 | AN33: 4807.3 | AO33: 5378.4 | AP33: 5843.9 | AQ33: 6115.9 | AR33: 6837.9 | AS33: 6433.3 | AT33: 7677 | AU33: 8021.6
A34: Depreciation | B34: ₹m | C34: 132.76 | D34: 141.3 | E34: 150.14 | F34: 144.33 | G34: 147.83 | H34: 139.26 | I34: 143.19 | J34: 142.09 | K34: 132.76 | L34: 130.01 | M34: 124.37 | N34: 133.77 | O34: 122.86 | P34: 119.72 | Q34: 115.83 | R34: 115.98 | S34: 110.2 | T34: 115.91 | U34: 116.24 | V34: 111.14 | W34: 109.8 | X34: 115.08 | Y34: 117.22 | Z34: 124.68 | AB34: 168.12 | AD34: 231.18 | AE34: 222.08 | AF34: 243.95 | AH34: 293.22 | AI34: 287.56 | AJ34: 297.09 | AK34: 303.21 | AL34: 299.65 | AM34: 211.5 | AN34: 226.9 | AO34: 242.4 | AP34: 239.9 | AQ34: 252.8 | AR34: 254.2 | AS34: 246.8 | AT34: 257.9 | AU34: 244.2
A35: Amortization | B35: ₹m | C35: 93.96 | D35: 94.75 | E35: 96.33 | F35: 111.59 | G35: 194.98 | H35: 227.45 | I35: 243.34 | J35: 252.03 | K35: 259.15 | L35: 249.43 | M35: 268.26 | N35: 287.12 | O35: 277.95 | P35: 278.86 | Q35: 280.49 | R35: 260.82 | S35: 275.97 | T35: 308.99 | U35: 312.06 | V35: 309.11 | W35: 325.81 | X35: 324.71 | Y35: 343.83 | Z35: 294.37 | AB35: 202.71 | AD35: 280.17 | AE35: 423.04 | AF35: 449.12 | AH35: 404.03 | AI35: 475.72 | AJ35: 446.88 | AK35: 484.1 | AL35: 499.52 | AM35: 500.5 | AN35: 518.1 | AO35: 578.8 | AP35: 551.2 | AQ35: 685.1 | AR35: 746.3 | AS35: 759.1 | AT35: 827.5 | AU35: 908.6
A36: D&A | B36: ₹m | C36: 226.72 | D36: 236.05 | E36: 246.47 | F36: 255.92 | G36: 342.81 | H36: 366.71 | I36: 386.53 | J36: 394.12 | K36: 391.91 | L36: 379.44 | M36: 392.63 | N36: 420.89 | O36: 400.81 | P36: 398.58 | Q36: 396.32 | R36: 376.8 | S36: 386.17 | T36: 424.9 | U36: 428.3 | V36: 420.25 | W36: 435.61 | X36: 439.79 | Y36: 461.05 | Z36: 419.05 | AB36: 370.83 | AD36: 511.35 | AE36: 645.12 | AF36: 693.07 | AH36: 697.25 | AI36: 763.28 | AJ36: 743.97 | AK36: 787.31 | AL36: 799.17 | AM36: 712 | AN36: 745 | AO36: 821.2 | AP36: 791.1 | AQ36: 937.9 | AR36: 1000.5 | AS36: 1005.9 | AT36: 1085.4 | AU36: 1152.8
A37: EBIT | B37: ₹m | C37: 742.36 | D37: 781.46 | E37: 863.98 | F37: 818.1 | G37: 714.7 | H37: 741.08 | I37: 800.02 | J37: 793.38 | K37: 651.67 | L37: 778.38 | M37: 982.54 | N37: 689.74 | O37: 999.65 | P37: 1037.65 | Q37: 1306.85 | R37: 888.7 | S37: 815.76 | T37: 791.55 | U37: 806.01 | V37: 856.6 | W37: 1028.75 | X37: 1217.93 | Y37: 1363.73 | Z37: 1464.24 | AA37: 1665.111 | AB37: 1873.11 | AC37: 2082.98 | AD37: 2300.39 | AE37: 2687.8 | AF37: 2986.57 | AG37: 3332.04 | AH37: 3465.89 | AI37: 3466.16 | AJ37: 3307.65 | AK37: 3631.03 | AL37: 3744.45 | AM37: 3840.2 | AN37: 4062.3 | AO37: 4557.3 | AP37: 5052.9 | AQ37: 5178.1 | AR37: 5837.4 | AS37: 5427.5 | AT37: 6591.6 | AU37: 6868.8
A38: Other income | B38: ₹m | C38: 128.36 | D38: 111.46 | E38: 118.51 | F38: 245.53 | G38: 172.44 | H38: 202.54 | I38: 143.33 | J38: 170.74 | K38: 183.28 | L38: 133.49 | M38: 142.99 | N38: 144.21 | O38: 165.97 | P38: 195.47 | Q38: 229.25 | R38: 282.94 | S38: 202.02 | T38: 226.16 | U38: 231.64 | V38: 229.33 | W38: 279.32 | X38: 207.77 | Y38: 288.11 | Z38: 210.77 | AA38: 256.3821 | AB38: 292.88 | AC38: 251.25 | AD38: 251.28 | AE38: 89.15 | AF38: 60.79 | AG38: 87.02 | AH38: 129.05 | AI38: 154.58 | AJ38: 166.28 | AK38: 181.08 | AL38: 226.02 | AM38: 172.5 | AN38: 176.9 | AO38: 118.4 | AP38: 153.5 | AQ38: 187.3 | AR38: 58.9 | AS38: 300.6 | AT38: 136.3 | AU38: 414.9
A39: FX gain / loss | B39: ₹m | C39: 69.38 | D39: 70.91 | E39: 41.95 | F39: -35.73 | G39: 80.86 | H39: 40.82 | I39: 174.44 | J39: -27.62 | K39: 184.45 | L39: 202.69 | M39: 49.63 | N39: 149.54 | O39: 20.63 | P39: 35.67 | Q39: -240.89 | R39: -58.5 | S39: 79.83 | T39: 137.92 | U39: 102.1 | V39: 44.5 | W39: -87.63 | X39: -50.59 | Y39: -1.74 | Z39: 173.77 | AA39: 109.03173 | AB39: 10.33 | AC39: 29.89 | AD39: 120.16 | AE39: 41.8 | AF39: -91.32 | AG39: 105.37 | AH39: -189.09 | AI39: -64.09 | AJ39: 83.7 | AK39: 80.9 | AL39: -15.54 | AM39: -7.3 | AN39: 106 | AO39: 144.7 | AP39: -154.3 | AQ39: 188.7 | AR39: 272 | AS39: -78.2 | AT39: 11.9 | AU39: -1052.7
A40: PBT | B40: ₹m | C40: 940.1 | D40: 963.83 | E40: 1024.44 | F40: 1027.9 | G40: 968 | H40: 984.44 | I40: 1117.79 | J40: 936.5 | K40: 1019.4 | L40: 1114.56 | M40: 1175.16 | N40: 983.49 | O40: 1186.25 | P40: 1268.79 | Q40: 1295.21 | R40: 1113.14 | S40: 1097.61 | T40: 1155.63 | U40: 1139.75 | V40: 1130.43 | W40: 1220.44 | X40: 1375.11 | Y40: 1650.1 | Z40: 1848.78 | AA40: 2030.521 | AB40: 2176.32 | AC40: 2364.12 | AD40: 2671.83 | AE40: 2818.75 | AF40: 2956.04 | AG40: 3227.88 | AH40: 3405.85 | AI40: 3070.49 | AJ40: 3557.63 | AK40: 3893.01 | AL40: 3954.93 | AM40: 4005.4 | AN40: 4345.2 | AO40: 4820.4 | AP40: 5052.1 | AQ40: 5554.1 | AR40: 6168.3 | AS40: 5649.9 | AT40: 6739.8 | AU40: 6231
A41: Tax | B41: ₹m | C41: 267.94 | D41: 245.34 | E41: 249.55 | F41: 219.83 | G41: 235.14 | H41: 249.51 | I41: 298.88 | J41: 208.55 | K41: 268.51 | L41: 288.33 | M41: 258.46 | N41: 246.43 | O41: 312.77 | P41: 387.38 | Q41: 378.04 | R41: 268.41 | S41: 272.91 | T41: 294.91 | U41: 260.49 | V41: 292.22 | W41: 320.36 | X41: 355.25 | Y41: 440.86 | Z41: 471.19 | AA41: 518.04471 | AB41: 558.79 | AC41: 600.17 | AD41: 661.93 | AE41: 702.63 | AF41: 755.9 | AG41: 848.34 | AH41: 890.72 | AI41: 782.81 | AJ41: 924.95 | AK41: 1031.67 | AL41: 801.71 | AM41: 941.3 | AN41: 1095.2 | AO41: 1090.5 | AP41: 1094.5 | AQ41: 1304.7 | AR41: 1453.6 | AS41: 1255.4 | AT41: 1447.2 | AU41: 1400.6
A42: PAT | B42: ₹m | C42: 672.16 | D42: 718.49 | E42: 774.89 | F42: 808.07 | G42: 732.86 | H42: 734.93 | I42: 818.91 | J42: 727.95 | K42: 750.89 | L42: 826.23 | M42: 916.7 | N42: 737.06 | O42: 873.48 | P42: 881.41 | Q42: 917.17 | R42: 844.73 | S42: 824.7 | T42: 860.72 | U42: 879.26 | V42: 838.21 | W42: 900.08 | X42: 1019.86 | Y42: 1209.24 | Z42: 1377.59 | AA42: 1512.481 | AB42: 1617.53 | AC42: 1763.95 | AD42: 2009.9 | AE42: 2116.12 | AF42: 2200.14 | AG42: 2379.54 | AH42: 2515.13 | AI42: 2287.68 | AJ42: 2632.68 | AK42: 2861.34 | AL42: 3153.22 | AM42: 3064.2 | AN42: 3250 | AO42: 3729.9 | AP42: 3957.6 | AQ42: 4249.4 | AR42: 4714.7 | AS42: 4394.5 | AT42: 5292.6 | AU42: 4830.4
A43: EPS | B43: ₹ / share | C43: 8.45 | AF43: 29.61 | AG43: 31.9 | AH43: 33.65 | AI43: 30.5 | AJ43: 35 | AK43: 37.83 | AL43: 41.46 | AM43: 20.1 | AN43: 21.2 | AO43: 24.3 | AP43: 25.6 | AQ43: 27.4 | AR43: 30.3 | AS43: 28.2 | AT43: 33.8 | AU43: 30.9
A48: Annual reported balance sheet
A49: Metric | B49: Units | C49: FY16A | D49: FY17A | E49: FY18A | F49: FY19A | G49: FY20A | H49: FY21A | I49: FY22A | J49: FY23A | K49: FY24A | L49: FY25A | M49: FY26A
A50: PPE | B50: ppe | C50: 3007.45 | D50: 2768.36 | E50: 2581.3 | F50: 2331.24 | G50: 2224.6 | H50: 2401.4 | I50: 2917.67 | J50: 4859.95 | K50: 4420.03 | L50: 4350.88 | M50: 3968.88
A51: CWIP | B51: cwip | C51: 23.64 | D51: 48.47 | E51: 7.71 | F51: 12.1 | G51: 166.18 | H51: 121.81 | I51: 1071.2 | J51: 161.38 | K51: 218.73 | L51: 41.84 | M51: 106.85
A52: ROU assets | B52: rou | C52: 0 | D52: 0 | E52: 0 | F52: 0 | G52: 566.81 | H52: 852.58 | I52: 1358.21 | J52: 2198.21 | K52: 2307.18 | L52: 3798.67 | M52: 5471.81
A53: Goodwill | B53: goodwill | C53: 174.88 | D53: 76.23 | E53: 76.61 | F53: 81.24 | G53: 88.94 | H53: 85.94 | I53: 2790.22 | J53: 7183.71 | K53: 10912.56 | L53: 12337.94 | M53: 13596.88
A54: Intangibles incl. development | B54: intangibles | C54: 1422.01 | D54: 2756.18 | E54: 2508.26 | F54: 1898.95 | G54: 1572.13 | H54: 1229.5 | I54: 8269.63 | J54: 9171.42 | K54: 4691.48 | L54: 5655.1 | M54: 5791.2
A55: Non-current investments | B55: nc_investments | C55: 1347.92 | D55: 2339.44 | E55: 2881.04 | F55: 4345.71 | G55: 4620.97 | H55: 3621.27 | I55: 3877.72 | J55: 4516 | K55: 5539.14 | L55: 6415.04 | M55: 7001.38
A56: Non-current receivables | B56: nc_receivables | C56: 0 | D56: 0 | E56: 0 | F56: 0 | G56: 0 | H56: 0 | I56: 0 | J56: 709.45 | K56: 730.18 | L56: 664.4 | M56: 0
A57: Other non-current financial / advances | B57: other_nc_financial | C57: 851.05 | D57: 1058.07 | E57: 180.16 | F57: 513.29 | G57: 535.06 | H57: 160.52 | I57: 3862.74 | J57: 919.6 | K57: 691.06 | L57: 773.81 | M57: 1012.99
A58: Deferred tax assets | B58: dta | C58: 232.75 | D58: 306.39 | E58: 642.01 | F58: 405.05 | G58: 960.08 | H58: 1037.57 | I58: 1122.72 | J58: 1133.97 | K58: 1462.8 | L58: 2024.24 | M58: 3459.97
A59: Non-current tax assets | B59: nc_tax | C59: 0 | D59: 0 | E59: 0 | F59: 0 | G59: 0 | H59: 0 | I59: 0 | J59: 451.71 | K59: 387.05 | L59: 787.55 | M59: 1032.97
A60: Other non-current assets | B60: other_nc_assets | C60: 870.1 | D60: 71.85 | E60: 91.57 | F60: 68.31 | G60: 331.31 | H60: 441.52 | I60: 531.61 | J60: 959.29 | K60: 1247.28 | L60: 257.02 | M60: 450.32
A61: Total non-current assets | B61: total_nc_assets | C61: 7929.8 | D61: 9424.99 | E61: 8968.66 | F61: 9655.89 | G61: 11066.08 | H61: 9952.11 | I61: 25801.72 | J61: 32264.69 | K61: 32607.49 | L61: 37106.49 | M61: 42792.61
... A90: Total equity & liabilities | B90: total_equity_liabilities | C90: 21065.43 | D90: 23463.73 | E90: 26588.62 | F90: 28555.99 | G90: 30921.69 | H90: 36655.24 | I90: 54191.01 | J90: 66730.8 | K90: 74176.34 | L90: 87366.02 | M90: 113765.44
A95: Annual reported cash flow totals
A96: Metric | B96: Units | C96: FY16A | D96: FY17A | E96: FY18A | F96: FY19A | G96: FY20A | H96: FY21A | I96: FY22A | J96: FY23A | K96: FY24A | L96: FY25A | M96: FY26A
A97: Cash flow from operations | B97: cfo | C97: 2540.6 | D97: 2864.1 | E97: 4211.93 | F97: 4323.14 | G97: 3228.18 | H97: 7359.25 | I97: 8449.86 | J97: 9557.62 | K97: 13021.09 | L97: 11569.16 | M97: 17671.3
A98: Cash flow from investing | B98: cfi | C98: -369.93 | D98: -2219.35 | E98: -3473.9 | F98: -2258.99 | G98: -148.44 | H98: -5416.73 | I98: -9773.43 | J98: -4213.1 | K98: -5620.9 | L98: -4344.34 | M98: -6099.03
A99: Cash flow from financing | B99: cff | C99: -1266.29 | D99: -584.08 | E99: -956.14 | F99: -1596.2 | G99: -3003.32 | H99: -1442.61 | I99: 1822.89 | J99: -4039.45 | K99: -5818.83 | L99: -6281.99 | M99: -7481.76
A100: Capex | B100: capex | C100: -1659.35 | D100: -2175.74 | E100: -654.56 | F100: -379.06 | G100: -758.39 | H100: -1281.04 | I100: -3853.97 | J100: -4332.99 | K100: -3580.33 | L100: -2366.91 | M100: -2085.81
A101: Acquisitions | B101: acquisitions | C101: -307.01 | D101: 0 | E101: -408.35 | F101: -148.17 | G101: -435.48 | H101: -448.47 | I101: -6154.02 | J101: -4310.57 | K101: 0 | L101: 0 | M101: 0
A102: Dividends | B102: dividends | C102: -1039.51 | D102: -480.01 | E102: -799.79 | F102: -879.14 | G102: -1146.38 | H102: -1069.95 | I102: -1987.05 | J102: -2980.58 | K102: -4083.62 | L102: -4600.06 | M102: -5790.41
A103: Other investing / classification residual | B103: other_investing | C103: 1596.43 | D103: -43.61 | E103: -2410.99 | F103: -1731.76 | G103: 1045.43 | H103: -3687.22 | I103: 234.56 | J103: 4430.46 | K103: -2040.57 | L103: -1977.43 | M103: -4013.22
A104: Other financing / classification residual | B104: other_financing | C104: -226.78 | D104: -104.07 | E104: -156.35 | F104: -717.06 | G104: -1856.94 | H104: -372.66 | I104: 3809.94 | J104: -1058.87 | K104: -1735.21 | L104: -1681.93 | M104: -1691.35
A105: Net change before FX / classification | B105: net_change | C105: 904.38 | D105: 60.67 | E105: -218.11 | F105: 467.95 | G105: 76.42 | H105: 499.91 | I105: 499.32 | J105: 1305.07 | K105: 1581.36 | L105: 942.83 | M105: 4090.51
A106: FX / classification / consolidation bridge | B106: fx_classification | C106: -491.11 | D106: -0.69 | E106: 100.45 | F106: -72.22 | G106: 84.12 | H106: 19.4 | I106: 59.37 | J106: 387.06 | K106: 373.67 | L106: -823.92 | M106: -85.42
A107: Opening cash | B107: opening_cash | C107: 988.13 | D107: 1401.4 | E107: 1461.38 | F107: 1343.72 | G107: 1739.45 | H107: 1899.99 | I107: 2419.3 | J107: 2977.99 | K107: 4670.12 | L107: 6625.15 | M107: 6744.06
A108: Closing cash — BS anchored | B108: closing_cash | C108: 1401.4 | D108: 1461.38 | E108: 1343.72 | F108: 1739.45 | G108: 1899.99 | H108: 2419.3 | I108: 2977.99 | J108: 4670.12 | K108: 6625.15 | L108: 6744.06 | M108: 10749.15

Sheet Raw Operating
A1: Raw Reported Operating Metrics
A2: Annual reported KPIs; blanks mean not disclosed under a comparable definition
A5: Metric | B5: Units | C5: FY16A | D5: FY17A | E5: FY18A | F5: FY19A | G5: FY20A | H5: FY21A | I5: FY22A | J5: FY23A | K5: FY24A | L5: FY25A | M5: FY26A | N5: FY27E | O5: FY28E | P5: FY29E | Q5: FY30E
A7: Revenue | B7: $m | C7: 352 | D7: 429 | E7: 471 | F7: 481 | G7: 502 | H7: 566 | I7: 766 | J7: 1036 | K7: 1186 | L7: 1409.1 | M7: 1654.4
A8: Headcount | B8: # | C8: 9264 | D8: 9460 | E8: 8976 | F8: 9962 | G8: 10632 | H8: 13680 | I8: 18599 | J8: 22889 | K8: 23850 | L8: 24594 | M8: 27502
A9: Technical employees | B9: # | L9: 23072 | M9: 25849
A10: Attrition | B10: % | C10: 0.164 | D10: 0.157 | E10: 0.147 | F10: 0.167 | G10: 0.143 | H10: 0.117 | I10: 0.266 | J10: 0.198 | K10: 0.115 | L10: 0.129 | M10: 0.13
A11: Utilization | B11: % | L11: 0.856 | M11: 0.883
A12: TCV bookings | B12: $m | I12: 1222.6 | J12: 1623.6 | K12: 1828.7 | L12: 2103.4 | M12: 2405.3
A13: ACV bookings | B13: $m | I13: 943.1 | J13: 1170.9 | K13: 1296.7 | L13: 1464.1 | M13: 1780.1
A14: North America mix | B14: % | C14: 0.855 | D14: 0.864 | E14: 0.835 | F14: 0.817 | G14: 0.81 | H14: 0.808 | I14: 0.788 | J14: 0.78 | K14: 0.796 | L14: 0.808 | M14: 0.806
A15: Europe mix | B15: % | C15: 0.065 | D15: 0.055 | E15: 0.075 | F15: 0.088 | G15: 0.095 | H15: 0.092 | I15: 0.087 | J15: 0.09 | K15: 0.09 | L15: 0.081 | M15: 0.087
A16: India mix | B16: % | L16: 0.094 | M16: 0.088
A17: ROW / residual mix | B17: % | C17: 0.08 | D17: 0.081 | E17: 0.09 | F17: 0.095 | G17: 0.095 | H17: 0.1 | I17: 0.125 | J17: 0.13 | K17: 0.114 | L17: 0.017 | M17: 0.019
A18: BFSI mix | B18: % | H18: 0.308 | I18: 0.316 | J18: 0.329 | K18: 0.319 | L18: 0.316 | M18: 0.346
A19: Healthcare & Life Sciences mix | B19: % | H19: 0.193 | I19: 0.208 | J19: 0.197 | K19: 0.21 | L19: 0.273 | M19: 0.256
A20: Software, Hi-Tech & Emerging mix | B20: % | H20: 0.499 | I20: 0.476 | J20: 0.474 | K20: 0.471 | L20: 0.411 | M20: 0.398
A21: Top 10 concentration | B21: % | C21: 0.455 | D21: 0.531 | E21: 0.535 | F21: 0.518 | G21: 0.517 | H21: 0.477 | I21: 0.446 | J21: 0.367 | K21: 0.39 | L21: 0.409 | M21: 0.416
A22: Clients $75m+ | B22: # | L22: 4 | M22: 4
A23: Clients $20–50m | B23: # | L23: 6 | M23: 8
A24: Clients $10–20m | B24: # | L24: 11 | M24: 17
A25: Clients $5–10m | B25: # | L25: 34 | M25: 33
A26: Clients $1–5m | B26: # | L26: 136 | M26: 139
A27: Clients $1m+ | B27: # | L27: 191 | M27: 201

Sheet Quarterly P&L
A1: Quarterly Profit & Loss
A4: Metric | B4: Q1 FY16A | C4: Q2 FY16A | D4: Q3 FY16A | E4: Q4 FY16A | F4: Q1 FY17A | G4: Q2 FY17A | H4: Q3 FY17A | I4: Q4 FY17A | J4: Q1 FY18A | K4: Q2 FY18A | L4: Q3 FY18A | M4: Q4 FY18A | N4: Q1 FY19A | O4: Q2 FY19A | P4: Q3 FY19A | Q4: Q4 FY19A | R4: Q1 FY20A | S4: Q2 FY20A | T4: Q3 FY20A | U4: Q4 FY20A | V4: Q1 FY21A | W4: Q2 FY21A | X4: Q3 FY21A | Y4: Q4 FY21A | Z4: Q1 FY22A | AA4: Q2 FY22A | AB4: Q3 FY22A | AC4: Q4 FY22A | AD4: Q1 FY23A | AE4: Q2 FY23A | AF4: Q3 FY23A | AG4: Q4 FY23A | AH4: Q1 FY24A | AI4: Q2 FY24A | AJ4: Q3 FY24A | AK4: Q4 FY24A | AL4: Q1 FY25A | AM4: Q2 FY25A | AN4: Q3 FY25A | AO4: Q4 FY25A | AP4: Q1 FY26A | AQ4: Q2 FY26A | AR4: Q3 FY26A | AS4: Q4 FY26A | AT4: Q1 FY27A
A5: Revenue | B5: 78.61 | C5: 82.96 | D5: 89.65 | E5: 100.43 | F5: 104.76 | G5: 105.18 | H5: 110.03 | I5: 109.03 | J5: 112.97 | K5: 118.1 | L5: 122.53 | M5: 116.95 | N5: 123.6 | O5: 118.23 | P5: 120.84 | Q5: 118.3 | R5: 119.62 | S5: 125.51 | T5: 129.43 | U5: 127.05 | V5: 131.02 | W5: 136.09 | X5: 146.15 | Y5: 152.82 | Z5: 144.93129 | AA5: 182.32 | AB5: 172.68 | AC5: 217.32 | AD5: 241.52 | AE5: 255.56 | AF5: 242.65 | AG5: 274.55 | AH5: 282.9 | AI5: 291.71 | AJ5: 300.55 | AK5: 310.89 | AL5: 328.2 | AM5: 345.5 | AN5: 360.2 | AO5: 375.2 | AP5: 389.7 | AQ5: 406.2 | AR5: 422.5 | AS5: 436 | AT5: 452.4
A6: Average FX | B6: 63.66 | C6: 65.42 | D6: 66.04 | E6: 67.42 | F6: 66.99 | G6: 66.93 | H6: 67.76 | I6: 66.69 | J6: 64.44 | K6: 64.46 | L6: 64.63 | M6: 64.35 | N6: 67.5 | O6: 70.67 | P6: 71.52 | Q6: 70.32 | R6: 69.56 | S6: 70.48 | T6: 71.29 | U6: 72.91 | V6: 75.69 | W6: 74.05 | X6: 73.58 | Y6: 72.85 | Z6: 73.7372 | AA6: 74.11 | AB6: 74.92 | AD6: 77.76 | AE6: 80.16 | AF6: 82.06 | AG6: 82.12 | AH6: 82.05 | AI6: 82.67 | AJ6: 83.12 | AK6: 83.33 | AL6: 83.4 | AM6: 83.9 | AN6: 85 | AO6: 86.4 | AP6: 85.5 | AQ6: 88.2 | AR6: 89.4 | AS6: 93 | AT6: 95.1
A7: Revenue | B7: 5004.16 | C7: 5427.31 | D7: 5920.74 | E7: 6771.1 | F7: 7017.77 | G7: 7040.19 | H7: 7455.35 | I7: 7271.08 | J7: 7280.15 | K7: 7612.52 | L7: 7918.9 | M7: 7525.46 | N7: 8342.81 | O7: 8355.57 | P7: 8642.49 | Q7: 8318.54 | R7: 8321.14 | S7: 8846 | T7: 9227.29 | U7: 9263.65 | V7: 9913.85 | W7: 10077.47 | X7: 10753.98 | Y7: 11133.58 | Z7: 12299.261 | AA7: 13512.49 | AB7: 14917.17 | AC7: 16378.54 | AD7: 18781.11 | AE7: 20486.41 | AF7: 21693.68 | AG7: 22544.72 | AH7: 23211.75 | AI7: 24116.7 | AJ7: 24982.16 | AK7: 25905.26 | AL7: 27371.7 | AM7: 28971.5 | AN7: 30622.8 | AO7: 32421.1 | AP7: 33335.9 | AQ7: 35807.2 | AR7: 37782.1 | AS7: 40559.4 | AT7: 43032.3
A8: QoQ growth | C8: 0.084559646 | D8: 0.090916126 | E8: 0.14362394 | F8: 0.036429827 | G8: 0.003194747 | H8: 0.058969999 | I8: -0.024716479 | J8: 0.0012474075 | K8: 0.045654279 | L8: 0.040246856 | M8: -0.049683668 | N8: 0.1086113 | O8: 0.0015294607 | P8: 0.03433877 | Q8: -0.03748341 | R8: 0.00031255485 | S8: 0.063075492 | T8: 0.043103097 | U8: 0.0039404852 | V8: 0.070188317 | W8: 0.016504184 | X8: 0.067130937 | Y8: 0.035298559 | Z8: 0.10469958 | AA8: 0.098642422 | AB8: 0.10395419 | AC8: 0.097965633 | AD8: 0.14669012 | AE8: 0.09079868 | AF8: 0.058930286 | AG8: 0.039229859 | AH8: 0.029586972 | AI8: 0.03898672 | AJ8: 0.035886336 | AK8: 0.036950368 | AL8: 0.056607809 | AM8: 0.058447228 | AN8: 0.056997394 | AO8: 0.058724219 | AP8: 0.028216193 | AQ8: 0.074133292 | AR8: 0.055153712 | AS8: 0.073508354 | AT8: 0.060969837
A9: YoY growth | F9: 0.40238721 | G9: 0.29717853 | H9: 0.25919226 | I9: 0.073840292 | J9: 0.037387945 | K9: 0.081294681 | L9: 0.062176826 | M9: 0.034985174 | N9: 0.14596677 | O9: 0.097608939 | P9: 0.091375065 | Q9: 0.10538625 | R9: -0.0025974462 | S9: 0.058694978 | T9: 0.067665684 | U9: 0.11361489 | V9: 0.19140526 | W9: 0.13921207 | X9: 0.16545378 | Y9: 0.20185672 | Z9: 0.240614 | AA9: 0.34086135 | AB9: 0.38713016 | AC9: 0.47109375 | AD9: 0.52701124 | AE9: 0.51610917 | AF9: 0.45427584 | AG9: 0.37647922 | AH9: 0.23590938 | AI9: 0.17720479 | AJ9: 0.15158701 | AK9: 0.14906107 | AL9: 0.17921742 | AM9: 0.20130449 | AN9: 0.22578672 | AO9: 0.25152575 | AP9: 0.21789659 | AQ9: 0.23594567 | AR9: 0.23378986 | AS9: 0.25101863 | AT9: 0.2908696
A10: Cost of revenue | B10: 3015.2 | C10: 3313.74 | D10: 3622.39 | E10: 4353.47 | F10: 4584.52 | G10: 4538.51 | H10: 4751.02 | I10: 4643.97 | J10: 4783.17 | K10: 4994.06 | L10: 5008.9 | M10: 4917.99 | N10: 5372.82 | O10: 5409.62 | P10: 5341.15 | Q10: 5254.56 | R10: 5434.02 | S10: 5773.25 | T10: 6157.43 | U10: 6129.63 | V10: 6646.37 | W10: 6576.62 | X10: 7064.21 | Y10: 7363.04 | Z10: 8173.087 | AA10: 8982.03 | AB10: 9880.34 | AC10: 10859.49 | AD10: 12433.14 | AE10: 13628.38 | AF10: 14360.05 | AG10: 14893.75 | AH10: 15278.46 | AI10: 16127.2 | AJ10: 16539.12 | AL10: 18328.7 | AM10: 19294 | AN10: 20000.4 | AO10: 21117 | AP10: 21576.2 | AQ10: 22923.8 | AR10: 25017.8 | AS10: 26246.9 | AT10: 27915.4
A11: Gross profit | B11: 1988.96 | C11: 2113.57 | D11: 2298.35 | E11: 2417.63 | F11: 2433.25 | G11: 2501.68 | H11: 2704.33 | I11: 2627.11 | J11: 2496.98 | K11: 2618.46 | L11: 2910 | M11: 2607.47 | N11: 2969.99 | O11: 2945.95 | P11: 3301.34 | Q11: 3063.98 | R11: 2887.12 | S11: 3072.75 | T11: 3069.86 | U11: 3134.02 | V11: 3267.48 | W11: 3500.85 | X11: 3689.77 | Y11: 3770.54 | Z11: 4126.183 | AA11: 4530.46 | AB11: 5036.83 | AC11: 5519.05 | AD11: 6347.97 | AE11: 6858.03 | AF11: 7333.63 | AG11: 7650.97 | AH11: 7933.29 | AI11: 7989.5 | AJ11: 8443.04 | AK11: 8618.95 | AL11: 9043 | AM11: 9677.5 | AN11: 10622.5 | AO11: 11304.1 | AP11: 11759.7 | AQ11: 12883.4 | AR11: 12764.3 | AS11: 14312.4 | AT11: 15116.9
A12: Gross margin | B12: 0.39746131 | C12: 0.38943233 | D12: 0.38818627 | E12: 0.35705129 | F12: 0.34672695 | G12: 0.35534268 | H12: 0.36273683 | I12: 0.36130946 | J12: 0.34298469 | K12: 0.34396757 | L12: 0.36747528 | M12: 0.34648646 | N12: 0.35599396 | O12: 0.35257319 | P12: 0.38198945 | Q12: 0.36833146 | R12: 0.34696207 | S12: 0.34736039 | T12: 0.33269356 | U12: 0.33831373 | V12: 0.3295874 | W12: 0.34739374 | X12: 0.34310739 | Y12: 0.33866375 | Z12: 0.33548219 | AA12: 0.33527943 | AB12: 0.33765319 | AC12: 0.33696837 | AD12: 0.33799759 | AE12: 0.33475997 | AF12: 0.33805376 | AG12: 0.3393686 | AH12: 0.34177906 | AI12: 0.33128496 | AJ12: 0.33796277 | AK12: 0.33271042 | AL12: 0.33037773 | AM12: 0.33403517 | AN12: 0.34688206 | AO12: 0.34866491 | AP12: 0.35276384 | AQ12: 0.35979915 | AR12: 0.33783988 | AS12: 0.35287504 | AT12: 0.35129194
A13: SG&A | B13: 1019.88 | C13: 1096.06 | D13: 1187.9 | E13: 1343.61 | F13: 1375.74 | G13: 1393.89 | H13: 1517.78 | I13: 1439.61 | J13: 1453.4 | K13: 1460.64 | L13: 1534.83 | M13: 1496.84 | N13: 1569.53 | O13: 1509.72 | P13: 1598.17 | Q13: 1798.48 | R13: 1685.19 | S13: 1856.3 | T13: 1835.55 | U13: 1857.17 | V13: 1803.12 | W13: 1843.13 | X13: 1864.99 | Y13: 1887.25 | Z13: 2110.981 | AA13: 2286.52 | AB13: 2526 | AC13: 2707.31 | AD13: 3015.05 | AE13: 3178.39 | AF13: 3318.08 | AG13: 3487.83 | AH13: 3703.85 | AI13: 3937.88 | AJ13: 4024.7 | AL13: 4490.9 | AM13: 4870.3 | AN13: 5244.1 | AO13: 5460.2 | AP13: 5643.7 | AQ13: 6045.5 | AR13: 6331 | AS13: 6635.4 | AT13: 7095.3
A14: EBITDA | B14: 969.08 | C14: 1017.51 | D14: 1110.45 | E14: 1074.02 | F14: 1057.51 | G14: 1107.79 | H14: 1186.55 | I14: 1187.5 | J14: 1043.58 | K14: 1157.82 | L14: 1375.17 | M14: 1110.63 | N14: 1400.46 | O14: 1436.23 | P14: 1703.17 | Q14: 1265.5 | R14: 1201.93 | S14: 1216.45 | T14: 1234.31 | U14: 1276.85 | V14: 1464.36 | W14: 1657.72 | X14: 1824.78 | Y14: 1883.29 | Z14: 2015.201 | AA14: 2243.94 | AB14: 2510.83 | AC14: 2811.74 | AD14: 3332.92 | AE14: 3679.64 | AF14: 4015.55 | AG14: 4163.14 | AH14: 4229.44 | AI14: 4051.62 | AJ14: 4418.34 | AK14: 4543.62 | AL14: 4552.1 | AM14: 4807.3 | AN14: 5378.4 | AO14: 5843.9 | AP14: 6115.9 | AQ14: 6837.9 | AR14: 6433.3 | AS14: 7677 | AT14: 8021.6
A15: EBITDA margin | B15: 0.19365488 | C15: 0.18747962 | D15: 0.18755257 | E15: 0.15861825 | F15: 0.15069032 | G15: 0.15735229 | H15: 0.15915416 | I15: 0.16331824 | J15: 0.14334595 | K15: 0.15209418 | L15: 0.17365669 | M15: 0.147583 | N15: 0.1678643 | O15: 0.17188893 | P15: 0.19706936 | Q15: 0.15213006 | R15: 0.14444295 | S15: 0.13751413 | T15: 0.13376734 | U15: 0.13783444 | V15: 0.14770851 | W15: 0.16449764 | X15: 0.16968415 | Y15: 0.16915404 | Z15: 0.16384732 | AA15: 0.16606414 | AB15: 0.16831812 | AC15: 0.1716722 | AD15: 0.17746129 | AE15: 0.1796137 | AF15: 0.1851023 | AG15: 0.18466142 | AH15: 0.18221116 | AI15: 0.1680006 | AJ15: 0.17685981 | AK15: 0.17539372 | AL15: 0.16630681 | AM15: 0.16593204 | AN15: 0.17563384 | AO15: 0.1802499 | AP15: 0.18346287 | AQ15: 0.19096439 | AR15: 0.17027375 | AS15: 0.18927795 | AT15: 0.18640881
A16: Depreciation | B16: 132.76 | C16: 141.3 | D16: 150.14 | E16: 144.33 | F16: 147.83 | G16: 139.26 | H16: 143.19 | I16: 142.09 | J16: 132.76 | K16: 130.01 | L16: 124.37 | M16: 133.77 | N16: 122.86 | O16: 119.72 | P16: 115.83 | Q16: 115.98 | R16: 110.2 | S16: 115.91 | T16: 116.24 | U16: 111.14 | V16: 109.8 | W16: 115.08 | X16: 117.22 | Y16: 124.68 | AA16: 168.12 | AC16: 231.18 | AD16: 222.08 | AE16: 243.95 | AG16: 293.22 | AH16: 287.56 | AI16: 297.09 | AJ16: 303.21 | AK16: 299.65 | AL16: 211.5 | AM16: 226.9 | AN16: 242.4 | AO16: 239.9 | AP16: 252.8 | AQ16: 254.2 | AR16: 246.8 | AS16: 257.9 | AT16: 244.2
A17: Amortization | B17: 93.96 | C17: 94.75 | D17: 96.33 | E17: 111.59 | F17: 194.98 | G17: 227.45 | H17: 243.34 | I17: 252.03 | J17: 259.15 | K17: 249.43 | L17: 268.26 | M17: 287.12 | N17: 277.95 | O17: 278.86 | P17: 280.49 | Q17: 260.82 | R17: 275.97 | S17: 308.99 | T17: 312.06 | U17: 309.11 | V17: 325.81 | W17: 324.71 | X17: 343.83 | Y17: 294.37 | AA17: 202.71 | AC17: 280.17 | AD17: 423.04 | AE17: 449.12 | AG17: 404.03 | AH17: 475.72 | AI17: 446.88 | AJ17: 484.1 | AK17: 499.52 | AL17: 500.5 | AM17: 518.1 | AN17: 578.8 | AO17: 551.2 | AP17: 685.1 | AQ17: 746.3 | AR17: 759.1 | AS17: 827.5 | AT17: 908.6
A18: D&A | B18: 226.72 | C18: 236.05 | D18: 246.47 | E18: 255.92 | F18: 342.81 | G18: 366.71 | H18: 386.53 | I18: 394.12 | J18: 391.91 | K18: 379.44 | L18: 392.63 | M18: 420.89 | N18: 400.81 | O18: 398.58 | P18: 396.32 | Q18: 376.8 | R18: 386.17 | S18: 424.9 | T18: 428.3 | U18: 420.25 | V18: 435.61 | W18: 439.79 | X18: 461.05 | Y18: 419.05 | AA18: 370.83 | AC18: 511.35 | AD18: 645.12 | AE18: 693.07 | AG18: 697.25 | AH18: 763.28 | AI18: 743.97 | AJ18: 787.31 | AK18: 799.17 | AL18: 712 | AM18: 745 | AN18: 821.2 | AO18: 791.1 | AP18: 937.9 | AQ18: 1000.5 | AR18: 1005.9 | AS18: 1085.4 | AT18: 1152.8
A19: EBIT | B19: 742.36 | C19: 781.46 | D19: 863.98 | E19: 818.1 | F19: 714.7 | G19: 741.08 | H19: 800.02 | I19: 793.38 | J19: 651.67 | K19: 778.38 | L19: 982.54 | M19: 689.74 | N19: 999.65 | O19: 1037.65 | P19: 1306.85 | Q19: 888.7 | R19: 815.76 | S19: 791.55 | T19: 806.01 | U19: 856.6 | V19: 1028.75 | W19: 1217.93 | X19: 1363.73 | Y19: 1464.24 | Z19: 1665.111 | AA19: 1873.11 | AB19: 2082.98 | AC19: 2300.39 | AD19: 2687.8 | AE19: 2986.57 | AF19: 3332.04 | AG19: 3465.89 | AH19: 3466.16 | AI19: 3307.65 | AJ19: 3631.03 | AK19: 3744.45 | AL19: 3840.2 | AM19: 4062.3 | AN19: 4557.3 | AO19: 5052.9 | AP19: 5178.1 | AQ19: 5837.4 | AR19: 5427.5 | AS19: 6591.6 | AT19: 6868.8
A20: EBIT margin | B20: 0.14834857 | C20: 0.14398662 | D20: 0.14592433 | E20: 0.12082232 | F20: 0.10184147 | G20: 0.1052642 | H20: 0.10730817 | I20: 0.10911446 | J20: 0.089513266 | K20: 0.10224998 | L20: 0.12407531 | M20: 0.091654198 | N20: 0.11982174 | O20: 0.12418662 | P20: 0.15121221 | Q20: 0.10683365 | R20: 0.098034644 | S20: 0.089481121 | T20: 0.087350674 | U20: 0.092468951 | V20: 0.10376897 | W20: 0.12085672 | X20: 0.12681165 | Y20: 0.13151565 | Z20: 0.13538301 | AA20: 0.13862064 | AB20: 0.13963641 | AC20: 0.14045147 | AD20: 0.14311188 | AE20: 0.14578298 | AF20: 0.15359496 | AG20: 0.153734 | AH20: 0.14932782 | AI20: 0.13715185 | AJ20: 0.14534492 | AK20: 0.144544 | AL20: 0.14029819 | AM20: 0.14021711 | AN20: 0.14882049 | AO20: 0.15585221 | AP20: 0.15533104 | AQ20: 0.16302308 | AR20: 0.14365268 | AS20: 0.1625172 | AT20: 0.15961963
A21: Other income | B21: 128.36 | C21: 111.46 | D21: 118.51 | E21: 245.53 | F21: 172.44 | G21: 202.54 | H21: 143.33 | I21: 170.74 | J21: 183.28 | K21: 133.49 | L21: 142.99 | M21: 144.21 | N21: 165.97 | O21: 195.47 | P21: 229.25 | Q21: 282.94 | R21: 202.02 | S21: 226.16 | T21: 231.64 | U21: 229.33 | V21: 279.32 | W21: 207.77 | X21: 288.11 | Y21: 210.77 | Z21: 256.3821 | AA21: 292.88 | AB21: 251.25 | AC21: 251.28 | AD21: 89.15 | AE21: 60.79 | AF21: 87.02 | AG21: 129.05 | AH21: 154.58 | AI21: 166.28 | AJ21: 181.08 | AK21: 226.02 | AL21: 172.5 | AM21: 176.9 | AN21: 118.4 | AO21: 153.5 | AP21: 187.3 | AQ21: 58.9 | AR21: 300.6 | AS21: 136.3 | AT21: 414.9
A22: FX gain / loss | B22: 69.38 | C22: 70.91 | D22: 41.95 | E22: -35.73 | F22: 80.86 | G22: 40.82 | H22: 174.44 | I22: -27.62 | J22: 184.45 | K22: 202.69 | L22: 49.63 | M22: 149.54 | N22: 20.63 | O22: 35.67 | P22: -240.89 | Q22: -58.5 | R22: 79.83 | S22: 137.92 | T22: 102.1 | U22: 44.5 | V22: -87.63 | W22: -50.59 | X22: -1.74 | Y22: 173.77 | Z22: 109.03173 | AA22: 10.33 | AB22: 29.89 | AC22: 120.16 | AD22: 41.8 | AE22: -91.32 | AF22: 105.37 | AG22: -189.09 | AH22: -64.09 | AI22: 83.7 | AJ22: 80.9 | AK22: -15.54 | AL22: -7.3 | AM22: 106 | AN22: 144.7 | AO22: -154.3 | AP22: 188.7 | AQ22: 272 | AR22: -78.2 | AS22: 11.9 | AT22: -1052.7
A23: PBT | B23: 940.1 | C23: 963.83 | D23: 1024.44 | E23: 1027.9 | F23: 968 | G23: 984.44 | H23: 1117.79 | I23: 936.5 | J23: 1019.4 | K23: 1114.56 | L23: 1175.16 | M23: 983.49 | N23: 1186.25 | O23: 1268.79 | P23: 1295.21 | Q23: 1113.14 | R23: 1097.61 | S23: 1155.63 | T23: 1139.75 | U23: 1130.43 | V23: 1220.44 | W23: 1375.11 | X23: 1650.1 | Y23: 1848.78 | Z23: 2030.521 | AA23: 2176.32 | AB23: 2364.12 | AC23: 2671.83 | AD23: 2818.75 | AE23: 2956.04 | AF23: 3227.88 | AG23: 3405.85 | AH23: 3070.49 | AI23: 3557.63 | AJ23: 3893.01 | AK23: 3954.93 | AL23: 4005.4 | AM23: 4345.2 | AN23: 4820.4 | AO23: 5052.1 | AP23: 5554.1 | AQ23: 6168.3 | AR23: 5649.9 | AS23: 6739.8 | AT23: 6231
A24: PBT margin | B24: 0.1878637 | C24: 0.1775889 | D24: 0.17302567 | E24: 0.15180694 | F24: 0.13793556 | G24: 0.13983145 | H24: 0.14993126 | I24: 0.12879792 | J24: 0.14002459 | K24: 0.14641144 | L24: 0.1483994 | M24: 0.13068836 | N24: 0.1421883 | O24: 0.1518496 | P24: 0.14986537 | Q24: 0.13381435 | R24: 0.13190621 | S24: 0.13063871 | T24: 0.12351947 | U24: 0.12202857 | V24: 0.12310455 | W24: 0.13645389 | X24: 0.15344087 | Y24: 0.1660544 | Z24: 0.16509293 | AA24: 0.16105988 | AB24: 0.15848314 | AC24: 0.16312992 | AD24: 0.15008431 | AE24: 0.14429273 | AF24: 0.14879357 | AG24: 0.15107085 | AH24: 0.13228171 | AI24: 0.14751728 | AJ24: 0.1558316 | AK24: 0.15266899 | AL24: 0.14633362 | AM24: 0.14998188 | AN24: 0.15741212 | AO24: 0.15582753 | AP24: 0.16661017 | AQ24: 0.17226424 | AR24: 0.14953907 | AS24: 0.1661711 | AT24: 0.14479821
A25: Tax | B25: 267.94 | C25: 245.34 | D25: 249.55 | E25: 219.83 | F25: 235.14 | G25: 249.51 | H25: 298.88 | I25: 208.55 | J25: 268.51 | K25: 288.33 | L25: 258.46 | M25: 246.43 | N25: 312.77 | O25: 387.38 | P25: 378.04 | Q25: 268.41 | R25: 272.91 | S25: 294.91 | T25: 260.49 | U25: 292.22 | V25: 320.36 | W25: 355.25 | X25: 440.86 | Y25: 471.19 | Z25: 518.04471 | AA25: 558.79 | AB25: 600.17 | AC25: 661.93 | AD25: 702.63 | AE25: 755.9 | AF25: 848.34 | AG25: 890.72 | AH25: 782.81 | AI25: 924.95 | AJ25: 1031.67 | AK25: 801.71 | AL25: 941.3 | AM25: 1095.2 | AN25: 1090.5 | AO25: 1094.5 | AP25: 1304.7 | AQ25: 1453.6 | AR25: 1255.4 | AS25: 1447.2 | AT25: 1400.6
A26: Effective tax rate | B26: 0.28501223 | C26: 0.25454696 | D26: 0.2435965 | E26: 0.21386322 | F26: 0.24291322 | G26: 0.25345374 | H26: 0.26738475 | I26: 0.22269087 | J26: 0.26340004 | K26: 0.25869401 | L26: 0.21993601 | M26: 0.25056686 | N26: 0.2636628 | O26: 0.30531451 | P26: 0.29187545 | Q26: 0.2411287 | R26: 0.24864023 | S26: 0.25519414 | T26: 0.22855012 | U26: 0.2585034 | V26: 0.26249549 | W26: 0.25834297 | X26: 0.26717169 | Y26: 0.25486537 | Z26: 0.25512896 | AA26: 0.25675912 | AB26: 0.25386613 | AC26: 0.24774406 | AD26: 0.24927007 | AE26: 0.25571373 | AF26: 0.26281646 | AG26: 0.26152649 | AH26: 0.25494628 | AI26: 0.2599905 | AJ26: 0.26500574 | AK26: 0.20271155 | AL26: 0.23500774 | AM26: 0.25204824 | AN26: 0.22622604 | AO26: 0.21664258 | AP26: 0.23490755 | AQ26: 0.2356565 | AR26: 0.22219862 | AS26: 0.21472447 | AT26: 0.22477933
A27: PAT | B27: 672.16 | C27: 718.49 | D27: 774.89 | E27: 808.07 | F27: 732.86 | G27: 734.93 | H27: 818.91 | I27: 727.95 | J27: 750.89 | K27: 826.23 | L27: 916.7 | M27: 737.06 | N27: 873.48 | O27: 881.41 | P27: 917.17 | Q27: 844.73 | R27: 824.7 | S27: 860.72 | T27: 879.26 | U27: 838.21 | V27: 900.08 | W27: 1019.86 | X27: 1209.24 | Y27: 1377.59 | Z27: 1512.481 | AA27: 1617.53 | AB27: 1763.95 | AC27: 2009.9 | AD27: 2116.12 | AE27: 2200.14 | AF27: 2379.54 | AG27: 2515.13 | AH27: 2287.68 | AI27: 2632.68 | AJ27: 2861.34 | AK27: 3153.22 | AL27: 3064.2 | AM27: 3250 | AN27: 3729.9 | AO27: 3957.6 | AP27: 4249.4 | AQ27: 4714.7 | AR27: 4394.5 | AS27: 5292.6 | AT27: 4830.4
A28: PAT margin | B28: 0.13432025 | C28: 0.13238418 | D28: 0.13087722 | E28: 0.11934102 | F28: 0.10442918 | G28: 0.10439065 | H28: 0.10984193 | I28: 0.1001158 | J28: 0.10314211 | K28: 0.10853568 | L28: 0.11576103 | M28: 0.097942186 | N28: 0.10469854 | O28: 0.10548772 | P28: 0.10612335 | Q28: 0.10154787 | R28: 0.099109016 | S28: 0.097300475 | T28: 0.095289083 | U28: 0.090483773 | V28: 0.090790157 | W28: 0.10120199 | X28: 0.11244581 | Y28: 0.12373289 | Z28: 0.12297332 | AA28: 0.11970629 | AB28: 0.11824964 | AC28: 0.12271546 | AD28: 0.11267279 | AE28: 0.1073951 | AF28: 0.10968817 | AG28: 0.11156182 | AH28: 0.098556981 | AI28: 0.10916419 | AJ28: 0.11453533 | AK28: 0.12172123 | AL28: 0.11194774 | AM28: 0.11217921 | AN28: 0.1218014 | AO28: 0.12206865 | AP28: 0.12747218 | AQ28: 0.13166905 | AR28: 0.11631169 | AS28: 0.1304901 | AT28: 0.11225057
A29: EPS | B29: 8.45 | AE29: 29.61 | AF29: 31.9 | AG29: 33.65 | AH29: 30.5 | AI29: 35 | AJ29: 37.83 | AK29: 41.46 | AL29: 20.1 | AM29: 21.2 | AN29: 24.3 | AO29: 25.6 | AP29: 27.4 | AQ29: 30.3 | AR29: 28.2 | AS29: 33.8 | AT29: 30.9

Sheet Annual P&L
A1: Annual Profit & Loss
A4: Metric | B4: FY16A | C4: FY17A | D4: FY18A | E4: FY19A | F4: FY20A | G4: FY21A | H4: FY22A | I4: FY23A | J4: FY24A | K4: FY25A | L4: FY26A | M4: FY27E | N4: FY28E | O4: FY29E | P4: FY30E
A5: Revenue | B5: ='Raw Financials'!C6 -> 23123.31 | C5: ='Raw Financials'!D6 -> 28784.39 | D5: ='Raw Financials'!E6 -> 30337.03 | E5: ='Raw Financials'!F6 -> 33659.41 | F5: ='Raw Financials'!G6 -> 35658.08 | G5: ='Raw Financials'!H6 -> 41878.88 | H5: ='Raw Financials'!I6 -> 57107.46 | I5: ='Raw Financials'!J6 -> 83505.92 | ... L5: ='Raw Financials'!M6 -> 147484.49 | M5: ='Bookings & Revenue'!M27 -> 181518.89 | N5: ='Bookings & Revenue'!N27 -> 216842.09 | O5: ='Bookings & Revenue'!O27 -> 247270.92 | P5: ='Bookings & Revenue'!P27 -> 281990.34
A6: Revenue growth | C6: =IFERROR(C5/B5-1,"") -> 0.24482135 | D6: =IFERROR(D5/C5-1,"") -> 0.053940348 | E6: =IFERROR(E5/D5-1,"") -> 0.10951566 | F6: =IFERROR(F5/E5-1,"") -> 0.059379235 | G6: =IFERROR(G5/F5-1,"") -> 0.17445695 | H6: =IFERROR(H5/G5-1,"") -> 0.36363389 | I6: =IFERROR(I5/H5-1,"") -> 0.4622594 | J6: =IFERROR(J5/I5-1,"") -> 0.17615458 | ... L6: =IFERROR(L5/K5-1,"") -> 0.23534623 | M6: ='Bookings & Revenue'!M8 -> 0.20570181 | N6: ='Bookings & Revenue'!N8 -> 0.14429906 | O6: ='Bookings & Revenue'!O8 -> 0.12844876 | P6: ='Bookings & Revenue'!P8 -> 0.12865362
A7: Revenue | B7: ='Raw Operating'!C7 -> 352 | C7: ='Raw Operating'!D7 -> 429 | D7: ='Raw Operating'!E7 -> 471 | E7: ='Raw Operating'!F7 -> 481 | F7: ='Raw Operating'!G7 -> 502 | G7: ='Raw Operating'!H7 -> 566 | H7: ='Raw Operating'!I7 -> 766 | I7: ='Raw Operating'!J7 -> 1036 | ... L7: ='Raw Operating'!M7 -> 1654.4 | M7: ='Bookings & Revenue'!M7 -> 1994.7131 | N7: ='Bookings & Revenue'!N7 -> 2282.5483 | O7: ='Bookings & Revenue'!O7 -> 2575.7388 | P7: ='Bookings & Revenue'!P7 -> 2907.1169
A8: Average INR / USD | B8: =IFERROR(B5/B7,"") -> 65.691222 | C8: =IFERROR(C5/C7,"") -> 67.09648 | D8: =IFERROR(D5/D7,"") -> 64.40983 | E8: =IFERROR(E5/E7,"") -> 69.977983 | F8: =IFERROR(F5/F7,"") -> 71.032032 | G8: =IFERROR(G5/G7,"") -> 73.990954 | H8: =IFERROR(H5/H7,"") -> 74.55282 | I8: =IFERROR(I5/I7,"") -> 80.60417 | ... L8: =IFERROR(L5/L7,"") -> 89.146815 | M8: ='Bookings & Revenue'!M26 -> 91 | N8: ='Bookings & Revenue'!N26 -> 95 | O8: ='Bookings & Revenue'!O26 -> 96 | P8: ='Bookings & Revenue'!P26 -> 97
A9: Cost of revenue | B9: =B5-B10 -> 14304.8 | C9: =C5-C10 -> 18518.02 | D9: =D5-D10 -> 19704.12 | E9: =E5-E10 -> 21378.15 | F9: =F5-F10 -> 23494.33 | G9: =G5-G10 -> 27650.24 | H9: =H5-H10 -> 37894.937 | I9: =I5-I10 -> 55315.32 | ... P9: =P5-P10 -> 179909.84
A10: Gross profit | B10: =SUM('Quarterly P&L'!B11:E11) -> 8818.51 | C10: =SUM('Quarterly P&L'!F11:I11) -> 10266.37 | D10: =SUM('Quarterly P&L'!J11:M11) -> 10632.91 | E10: =SUM('Quarterly P&L'!N11:Q11) -> 12281.26 | F10: =SUM('Quarterly P&L'!R11:U11) -> 12163.75 | G10: =SUM('Quarterly P&L'!V11:Y11) -> 14228.64 | H10: =SUM('Quarterly P&L'!Z11:AC11) -> 19212.523 | I10: =SUM('Quarterly P&L'!AD11:AG11) -> 28190.6 | J10: =SUM('Quarterly P&L'!AH11:AK11) -> 32984.78 | K10: =SUM('Quarterly P&L'!AL11:AO11) -> 40647.1 | L10: =SUM('Quarterly P&L'!AP11:AS11) -> 51719.8 | M10: =M5*Assumptions!B17 -> 63894.649 | N10: =N5*Assumptions!C17 -> 77195.784 | O10: =O5*Assumptions!D17 -> 88770.262 | P10: =P5*Assumptions!E17 -> 102080.5
A11: Gross margin | B11: =IFERROR(B10/B5,"") -> 0.38136884 | C11: =IFERROR(C10/C5,"") -> 0.3566645 | D11: =IFERROR(D10/D5,"") -> 0.35049278 | E11: =IFERROR(E10/E5,"") -> 0.36486855 | F11: =IFERROR(F10/F5,"") -> 0.34112184 | G11: =IFERROR(G10/G5,"") -> 0.33975694 | H11: =IFERROR(H10/H5,"") -> 0.33642755 | I11: =IFERROR(I10/I5,"") -> 0.33758804 | ... P11: =IFERROR(P10/P5,"") -> 0.362
A12: SG&A | B12: =B10-B13 -> 4647.45 | C12: =C10-C13 -> 5727.02 | D12: =D10-D13 -> 5945.71 | E12: =E10-E13 -> 6475.9 | F12: =F10-F13 -> 7234.21 | G12: =G10-G13 -> 7398.49 | H12: =H10-H13 -> 9630.812 | I12: =I10-I13 -> 12999.35 | ... L12: =L10-L13 -> 24655.7 | M12: =M5*Assumptions!B18 -> 29769.098 | N12: =N5*Assumptions!C18 -> 34911.576 | O12: =O5*Assumptions!D18 -> 39068.806 | P12: =P5*Assumptions!E18 -> 43990.493
A13: EBITDA | B13: =SUM('Quarterly P&L'!B14:E14) -> 4171.06 | C13: =SUM('Quarterly P&L'!F14:I14) -> 4539.35 | D13: =SUM('Quarterly P&L'!J14:M14) -> 4687.2 | E13: =SUM('Quarterly P&L'!N14:Q14) -> 5805.36 | F13: =SUM('Quarterly P&L'!R14:U14) -> 4929.54 | G13: =SUM('Quarterly P&L'!V14:Y14) -> 6830.15 | H13: =SUM('Quarterly P&L'!Z14:AC14) -> 9581.711 | I13: =SUM('Quarterly P&L'!AD14:AG14) -> 15191.25 | J13: =SUM('Quarterly P&L'!AH14:AK14) -> 17243.02 | K13: =SUM('Quarterly P&L'!AL14:AO14) -> 20581.7 | L13: =SUM('Quarterly P&L'!AP14:AS14) -> 27064.1 | M13: =M10-M12 -> 34125.551 | N13: =N10-N12 -> 42284.207 | O13: =O10-O12 -> 49701.456 | P13: =P10-P12 -> 58090.011
A14: EBITDA margin | B14: =IFERROR(B13/B5,"") -> 0.18038334 | C14: =IFERROR(C13/C5,"") -> 0.1577018 | D14: =IFERROR(D13/D5,"") -> 0.15450425 | E14: =IFERROR(E13/E5,"") -> 0.17247361 | F14: =IFERROR(F13/F5,"") -> 0.13824468 | G14: =IFERROR(G13/G5,"") -> 0.16309295 | H14: =IFERROR(H13/H5,"") -> 0.16778388 | I14: =IFERROR(I13/I5,"") -> 0.18191824 | ... P14: =IFERROR(P13/P5,"") -> 0.206
A15: D&A | B15: ='Raw Financials'!C12 -> 965.16 | C15: ='Raw Financials'!D12 -> 1490.17 | D15: ='Raw Financials'!E12 -> 1584.87 | E15: ='Raw Financials'!F12 -> 1572.51 | F15: ='Raw Financials'!G12 -> 1659.62 | G15: ='Raw Financials'!H12 -> 1755.5 | H15: ='Raw Financials'!I12 -> 1660.12 | I15: ='Raw Financials'!J12 -> 2718.95 | ... L15: ='Raw Financials'!M12 -> 4029.5 | M15: =M5*Assumptions!B19 -> 4901.01 | N15: =N5*Assumptions!C19 -> 5637.8943 | O15: =O5*Assumptions!D19 -> 6181.7731 | P15: =P5*Assumptions!E19 -> 6767.7682
A16: EBIT | B16: =B13-B15 -> 3205.9 | C16: =C13-C15 -> 3049.18 | D16: =D13-D15 -> 3102.33 | E16: =E13-E15 -> 4232.85 | F16: =F13-F15 -> 3269.92 | G16: =G13-G15 -> 5074.65 | H16: =H13-H15 -> 7921.591 | I16: =I13-I15 -> 12472.3 | ... P16: =P13-P15 -> 51322.242
A17: EBIT margin | B17: =IFERROR(B16/B5,"") -> 0.13864365 | C17: =IFERROR(C16/C5,"") -> 0.10593172 | D17: =IFERROR(D16/D5,"") -> 0.10226215 | E17: =IFERROR(E16/E5,"") -> 0.12575532 | F17: =IFERROR(F16/F5,"") -> 0.091702077 | G17: =IFERROR(G16/G5,"") -> 0.12117444 | H17: =IFERROR(H16/H5,"") -> 0.13871377 | I17: =IFERROR(I16/I5,"") -> 0.14935827 | ... P17: =IFERROR(P16/P5,"") -> 0.182
A18: Other income | B18: ='Raw Financials'!C7 -> 784.49 | C18: ='Raw Financials'!D7 -> 958.45 | D18: ='Raw Financials'!E7 -> 1191.01 | E18: ='Raw Financials'!F7 -> 876.55 | F18: ='Raw Financials'!G7 -> 1323.77 | G18: ='Raw Financials'!H7 -> 1077.72 | H18: ='Raw Financials'!I7 -> 1439.55 | I18: ='Raw Financials'!J7 -> 706.17 | ... L18: ='Raw Financials'!M7 -> 1804.26 | M18: =M5*Assumptions!B20 -> 1089.1133 | N18: =N5*Assumptions!C20 -> 1301.0525 | O18: =O5*Assumptions!D20 -> 1483.6255 | P18: =P5*Assumptions!E20 -> 1691.9421
A19: Finance costs | B19: ='Raw Financials'!C11 -> 0.92 | C19: ='Raw Financials'!D11 -> 0.91 | D19: ='Raw Financials'!E11 -> 0.79 | E19: ='Raw Financials'!F11 -> 3.05 | F19: ='Raw Financials'!G11 -> 63.32 | G19: ='Raw Financials'!H11 -> 57.94 | H19: ='Raw Financials'!I11 -> 118.35 | I19: ='Raw Financials'!J11 -> 473.4 | ... L19: ='Raw Financials'!M11 -> 726.82 | M19: =M5*Assumptions!B21 -> 1089.1133 | N19: =N5*Assumptions!C21 -> 1301.0525 | O19: =O5*Assumptions!D21 -> 1236.3546 | P19: =P5*Assumptions!E21 -> 1409.9517
A20: Exceptional items | B20: ='Raw Financials'!C15 -> 0 | C20: ='Raw Financials'!D15 -> -114.11 | D20: ='Raw Financials'!E15 -> 0 | E20: ='Raw Financials'!F15 -> 0 | F20: ='Raw Financials'!G15 -> 0 | G20: ='Raw Financials'!H15 -> 0 | H20: ='Raw Financials'!I15 -> 0 | I20: ='Raw Financials'!J15 -> -296.55 | ... L20: ='Raw Financials'!M15 -> -890.25 | M20: =0 -> 0 | N20: =0 -> 0 | O20: =0 -> 0 | P20: =0 -> 0
A21: PBT | B21: ='Raw Financials'!C16 -> 3956.27 | C21: ='Raw Financials'!D16 -> 4006.73 | D21: ='Raw Financials'!E16 -> 4292.61 | E21: ='Raw Financials'!F16 -> 4863.39 | F21: ='Raw Financials'!G16 -> 4523.42 | G21: ='Raw Financials'!H16 -> 6094.43 | H21: ='Raw Financials'!I16 -> 9242.79 | I21: ='Raw Financials'!J16 -> 12408.52 | ... L21: ='Raw Financials'!M16 -> 24112.12 | M21: =M16+M18-M19+M20 -> 29224.541 | N21: =N16+N18-N19+N20 -> 36646.313 | O21: =O16+O18-O19+O20 -> 43766.954 | P21: =P16+P18-P19+P20 -> 51604.233
A22: PBT margin | B22: =IFERROR(B21/B5,"") -> 0.17109445 | C22: =IFERROR(C21/C5,"") -> 0.13919802 | D22: =IFERROR(D21/D5,"") -> 0.14149737 | E22: =IFERROR(E21/E5,"") -> 0.14448827 | F22: =IFERROR(F21/F5,"") -> 0.1268554 | G22: =IFERROR(G21/G5,"") -> 0.14552514 | H22: =IFERROR(H21/H5,"") -> 0.16184908 | I22: =IFERROR(I21/I5,"") -> 0.14859449 | ... P22: =IFERROR(P21/P5,"") -> 0.183
A23: Tax | B23: ='Raw Financials'!C17 -> 982.66 | C23: ='Raw Financials'!D17 -> 992.08 | D23: ='Raw Financials'!E17 -> 1061.73 | E23: ='Raw Financials'!F17 -> 1346.6 | F23: ='Raw Financials'!G17 -> 1120.53 | G23: ='Raw Financials'!H17 -> 1587.66 | H23: ='Raw Financials'!I17 -> 2338.93 | I23: ='Raw Financials'!J17 -> 3197.59 | ... L23: ='Raw Financials'!M17 -> 5460.92 | M23: =M21*Assumptions!B22 -> 6721.6445 | N23: =N21*Assumptions!C22 -> 8428.652 | O23: =O21*Assumptions!D22 -> 10066.399 | P23: =P21*Assumptions!E22 -> 11868.974
A24: Effective tax rate | B24: =IFERROR(B23/B21,"") -> 0.24838042 | C24: =IFERROR(C23/C21,"") -> 0.24760341 | D24: =IFERROR(D23/D21,"") -> 0.24733903 | E24: =IFERROR(E23/E21,"") -> 0.27688505 | F24: =IFERROR(F23/F21,"") -> 0.24771744 | G24: =IFERROR(G23/G21,"") -> 0.26051001 | H24: =IFERROR(H23/H21,"") -> 0.25305454 | I24: =IFERROR(I23/I21,"") -> 0.2576931 | ... P24: =IFERROR(P23/P21,"") -> 0.23
A25: Net income | B25: ='Raw Financials'!C18 -> 2973.61 | C25: ='Raw Financials'!D18 -> 3014.65 | D25: ='Raw Financials'!E18 -> 3230.88 | E25: ='Raw Financials'!F18 -> 3516.79 | F25: ='Raw Financials'!G18 -> 3402.89 | G25: ='Raw Financials'!H18 -> 4506.77 | H25: ='Raw Financials'!I18 -> 6903.86 | I25: ='Raw Financials'!J18 -> 9210.93 | ... L25: ='Raw Financials'!M18 -> 18651.2 | M25: =M21-M23 -> 22502.897 | N25: =N21-N23 -> 28217.661 | O25: =O21-O23 -> 33700.554 | P25: =P21-P23 -> 39735.259
A26: Net margin | B26: =IFERROR(B25/B5,"") -> 0.12859794 | C26: =IFERROR(C25/C5,"") -> 0.10473211 | D26: =IFERROR(D25/D5,"") -> 0.10649955 | E26: =IFERROR(E25/E5,"") -> 0.10448163 | F26: =IFERROR(F25/F5,"") -> 0.095431106 | G26: =IFERROR(G25/G5,"") -> 0.10761439 | H26: =IFERROR(H25/H5,"") -> 0.12089244 | I26: =IFERROR(I25/I5,"") -> 0.11030272 | ... P26: =IFERROR(P25/P5,"") -> 0.14091
A27: Basic shares | B27: =IFERROR(B25/'Raw Financials'!C19,"") -> 79.807032 | C27: =IFERROR(C25/'Raw Financials'!D19,"") -> 80.006635 | D27: =IFERROR(D25/'Raw Financials'!E19,"") -> 79.992077 | E27: =IFERROR(E25/'Raw Financials'!F19,"") -> 79.945215 | F27: =IFERROR(F25/'Raw Financials'!G19,"") -> 76.676205 | G27: =IFERROR(G25/'Raw Financials'!H19,"") -> 76.424792 | H27: =IFERROR(H25/'Raw Financials'!I19,"") -> 76.420855 | I27: =IFERROR(I25/'Raw Financials'!J19,"") -> 74.443789 | ... L27: =IFERROR(L25/'Raw Financials'!M19,"") -> 155.76416 | M27: =L27 -> 155.76416 | N27: =M27 -> 155.76416 | O27: =N27 -> 155.76416 | P27: =O27 -> 155.76416
A28: Diluted shares | B28: =IFERROR(B25/'Raw Financials'!C20,"") -> 80.000269 | C28: =IFERROR(C25/'Raw Financials'!D20,"") -> 80.006635 | D28: =IFERROR(D25/'Raw Financials'!E20,"") -> 79.992077 | E28: =IFERROR(E25/'Raw Financials'!F20,"") -> 79.945215 | F28: =IFERROR(F25/'Raw Financials'!G20,"") -> 76.676205 | G28: =IFERROR(G25/'Raw Financials'!H20,"") -> 76.424792 | H28: =IFERROR(H25/'Raw Financials'!I20,"") -> 76.420855 | I28: =IFERROR(I25/'Raw Financials'!J20,"") -> 76.426568 | ... L28: =IFERROR(L25/'Raw Financials'!M20,"") -> 156.90418 | M28: =L28 -> 156.90418 | N28: =M28 -> 156.90418 | O28: =N28 -> 156.90418 | P28: =O28 -> 156.90418
A29: Basic EPS | B29: ='Raw Financials'!C19 -> 37.26 | C29: ='Raw Financials'!D19 -> 37.68 | D29: ='Raw Financials'!E19 -> 40.39 | E29: ='Raw Financials'!F19 -> 43.99 | F29: ='Raw Financials'!G19 -> 44.38 | G29: ='Raw Financials'!H19 -> 58.97 | H29: ='Raw Financials'!I19 -> 90.34 | I29: ='Raw Financials'!J19 -> 123.73 | ... L29: ='Raw Financials'!M19 -> 119.74 | M29: =M25/M27 -> 144.46775 | N29: =N25/N27 -> 181.15632 | O29: =O25/O27 -> 216.35629 | P29: =P25/P27 -> 255.09886
A30: Diluted EPS | B30: ='Raw Financials'!C20 -> 37.17 | C30: ='Raw Financials'!D20 -> 37.68 | D30: ='Raw Financials'!E20 -> 40.39 | E30: ='Raw Financials'!F20 -> 43.99 | F30: ='Raw Financials'!G20 -> 44.38 | G30: ='Raw Financials'!H20 -> 58.97 | H30: ='Raw Financials'!I20 -> 90.34 | I30: ='Raw Financials'!J20 -> 120.52 | ... L30: ='Raw Financials'!M20 -> 118.87 | M30: =M25/M28 -> 143.41808 | N30: =N25/N28 -> 179.84008 | O30: =O25/O28 -> 214.7843 | P30: =P25/P28 -> 253.24538
A31: Dividends | B31: =-'Raw Financials'!C102 -> 1039.51 | C31: =-'Raw Financials'!D102 -> 480.01 | D31: =-'Raw Financials'!E102 -> 799.79 | E31: =-'Raw Financials'!F102 -> 879.14 | F31: =-'Raw Financials'!G102 -> 1146.38 | G31: =-'Raw Financials'!H102 -> 1069.95 | H31: =-'Raw Financials'!I102 -> 1987.05 | I31: =-'Raw Financials'!J102 -> 2980.58 | ... L31: =-'Raw Financials'!M102 -> 5790.41 | M31: =M25*Assumptions!B44 -> 8101.0429 | N31: =N25*Assumptions!C44 -> 10440.535 | O31: =O25*Assumptions!D44 -> 12806.211 | P31: =P25*Assumptions!E44 -> 15496.751
A32: Dividend per share | B32: =IFERROR(B31/B28,"") -> 12.993831 | C32: =IFERROR(C31/C28,"") -> 5.9996274 | D32: =IFERROR(D31/D28,"") -> 9.9983652 | E32: =IFERROR(E31/E28,"") -> 10.996781 | F32: =IFERROR(F31/F28,"") -> 14.950922 | G32: =IFERROR(G31/G28,"") -> 14.000038 | H32: =IFERROR(H31/H28,"") -> 26.00141 | I32: =IFERROR(I31/I28,"") -> 38.999265 | ... P32: =IFERROR(P31/P28,"") -> 98.765699
A33: Dividend payout | B33: =IFERROR(B31/B25,"") -> 0.34957846 | C33: =IFERROR(C31/C25,"") -> 0.15922578 | D33: =IFERROR(D31/D25,"") -> 0.24754556 | E33: =IFERROR(E31/E25,"") -> 0.24998365 | F33: =IFERROR(F31/F25,"") -> 0.33688424 | G33: =IFERROR(G31/G25,"") -> 0.2374095 | H33: =IFERROR(H31/H25,"") -> 0.28781725 | I33: =IFERROR(I31/I25,"") -> 0.32359165 | ... P33: =IFERROR(P31/P25,"") -> 0.39
A35: Annual Balance Sheet
A38: Metric | B38: FY16A | C38: FY17A | D38: FY18A | E38: FY19A | F38: FY20A | G38: FY21A | H38: FY22A | I38: FY23A | J38: FY24A | K38: FY25A | L38: FY26A | M38: FY27E | N38: FY28E | O38: FY29E | P38: FY30E
A39: PPE | B39: ='Raw Financials'!C50 -> 3007.45 | C39: ='Raw Financials'!D50 -> 2768.36 | D39: ='Raw Financials'!E50 -> 2581.3 | E39: ='Raw Financials'!F50 -> 2331.24 | F39: ='Raw Financials'!G50 -> 2224.6 | G39: ='Raw Financials'!H50 -> 2401.4 | H39: ='Raw Financials'!I50 -> 2917.67 | I39: ='Raw Financials'!J50 -> 4859.95 | ... L39: ='Raw Financials'!M50 -> 3968.88 | M39: =L39-'Annual P&L'!M111-'Annual P&L'!M15*Assumptions!B32 -> 4976.3098 | N39: =M39-'Annual P&L'!N111-'Annual P&L'!N15*Assumptions!C32 -> 6038.8361 | O39: =N39-'Annual P&L'!O111-'Annual P&L'!O15*Assumptions!D32 -> 7337.0084 | P39: =O39-'Annual P&L'!P111-'Annual P&L'!P15*Assumptions!E32 -> 8916.1543
A40: CWIP | B40: ='Raw Financials'!C51 -> 23.64 | C40: ='Raw Financials'!D51 -> 48.47 | D40: ='Raw Financials'!E51 -> 7.71 | E40: ='Raw Financials'!F51 -> 12.1 | F40: ='Raw Financials'!G51 -> 166.18 | G40: ='Raw Financials'!H51 -> 121.81 | H40: ='Raw Financials'!I51 -> 1071.2 | I40: ='Raw Financials'!J51 -> 161.38 | ... L40: ='Raw Financials'!M51 -> 106.85 | M40: =L40 -> 106.85 | N40: =M40 -> 106.85 | O40: =N40 -> 106.85 | P40: =O40 -> 106.85
A41: ROU assets | B41: ='Raw Financials'!C52 -> 0 | C41: ='Raw Financials'!D52 -> 0 | D41: ='Raw Financials'!E52 -> 0 | E41: ='Raw Financials'!F52 -> 0 | F41: ='Raw Financials'!G52 -> 566.81 | G41: ='Raw Financials'!H52 -> 852.58 | H41: ='Raw Financials'!I52 -> 1358.21 | I41: ='Raw Financials'!J52 -> 2198.21 | ... L41: ='Raw Financials'!M52 -> 5471.81 | M41: =L41+'Annual P&L'!M120-'Annual P&L'!M15*Assumptions!B33 -> 6061.7464 | N41: =M41+'Annual P&L'!N120-'Annual P&L'!N15*Assumptions!C33 -> 6820.6937 | O41: =N41+'Annual P&L'!O120-'Annual P&L'!O15*Assumptions!D33 -> 7747.9597 | P41: =O41+'Annual P&L'!P120-'Annual P&L'!P15*Assumptions!E33 -> 8875.921
A42: Goodwill | B42: ='Raw Financials'!C53 -> 174.88 | C42: ='Raw Financials'!D53 -> 76.23 | D42: ='Raw Financials'!E53 -> 76.61 | E42: ='Raw Financials'!F53 -> 81.24 | F42: ='Raw Financials'!G53 -> 88.94 | G42: ='Raw Financials'!H53 -> 85.94 | H42: ='Raw Financials'!I53 -> 2790.22 | I42: ='Raw Financials'!J53 -> 7183.71 | ... L42: ='Raw Financials'!M53 -> 13596.88 | M42: =L42+'Nagarro Scenario'!C16 -> 13596.88 | N42: =M42+'Nagarro Scenario'!D16 -> 13596.88 | O42: =N42+'Nagarro Scenario'!E16 -> 13596.88 | P42: =O42+'Nagarro Scenario'!F16 -> 13596.88
A43: Intangibles incl. development | B43: ='Raw Financials'!C54 -> 1422.01 | C43: ='Raw Financials'!D54 -> 2756.18 | D43: ='Raw Financials'!E54 -> 2508.26 | E43: ='Raw Financials'!F54 -> 1898.95 | F43: ='Raw Financials'!G54 -> 1572.13 | G43: ='Raw Financials'!H54 -> 1229.5 | H43: ='Raw Financials'!I54 -> 8269.63 | I43: ='Raw Financials'!J54 -> 9171.42 | ... L43: ='Raw Financials'!M54 -> 5791.2 | M43: =L43-'Annual P&L'!M112-'Annual P&L'!M15*(1-Assumptions!B32-Assumptions!B33) -> 4919.9093 | N43: =M43-'Annual P&L'!N112-'Annual P&L'!N15*(1-Assumptions!C32-Assumptions!C33) -> 3965.8041 | O43: =N43-'Annual P&L'!O112-'Annual P&L'!O15*(1-Assumptions!D32-Assumptions!D33) -> 2976.7204 | P43: =O43-'Annual P&L'!P112-'Annual P&L'!P15*(1-Assumptions!E32-Assumptions!E33) -> 1961.5552
A44: Non-current investments | B44: ='Raw Financials'!C55 -> 1347.92 | C44: ='Raw Financials'!D55 -> 2339.44 | D44: ='Raw Financials'!E55 -> 2881.04 | E44: ='Raw Financials'!F55 -> 4345.71 | F44: ='Raw Financials'!G55 -> 4620.97 | G44: ='Raw Financials'!H55 -> 3621.27 | H44: ='Raw Financials'!I55 -> 3877.72 | I44: ='Raw Financials'!J55 -> 4516 | ... L44: ='Raw Financials'!M55 -> 7001.38 | M44: =L44 -> 7001.38 | N44: =M44 -> 7001.38 | O44: =N44 -> 7001.38 | P44: =O44 -> 7001.38
A45: Non-current receivables | B45: ='Raw Financials'!C56 -> 0 | C45: ='Raw Financials'!D56 -> 0 | D45: ='Raw Financials'!E56 -> 0 | E45: ='Raw Financials'!F56 -> 0 | F45: ='Raw Financials'!G56 -> 0 | G45: ='Raw Financials'!H56 -> 0 | H45: ='Raw Financials'!I56 -> 0 | I45: ='Raw Financials'!J56 -> 709.45 | ... L45: ='Raw Financials'!M56 -> 0 | M45: =L45 -> 0 | N45: =M45 -> 0 | O45: =N45 -> 0 | P45: =O45 -> 0
A46: Other non-current financial / advances | B46: ='Raw Financials'!C57 -> 851.05 | C46: ='Raw Financials'!D57 -> 1058.07 | D46: ='Raw Financials'!E57 -> 180.16 | E46: ='Raw Financials'!F57 -> 513.29 | F46: ='Raw Financials'!G57 -> 535.06 | G46: ='Raw Financials'!H57 -> 160.52 | H46: ='Raw Financials'!I57 -> 3862.74 | I46: ='Raw Financials'!J57 -> 919.6 | ... L46: ='Raw Financials'!M57 -> 1012.99 | M46: =L46 -> 1012.99 | N46: =M46 -> 1012.99 | O46: =N46 -> 1012.99 | P46: =O46 -> 1012.99
A47: Deferred tax assets | B47: ='Raw Financials'!C58 -> 232.75 | C47: ='Raw Financials'!D58 -> 306.39 | D47: ='Raw Financials'!E58 -> 642.01 | E47: ='Raw Financials'!F58 -> 405.05 | F47: ='Raw Financials'!G58 -> 960.08 | G47: ='Raw Financials'!H58 -> 1037.57 | H47: ='Raw Financials'!I58 -> 1122.72 | I47: ='Raw Financials'!J58 -> 1133.97 | ... L47: ='Raw Financials'!M58 -> 3459.97 | M47: ='Annual P&L'!M5*Assumptions!B29 -> 4356.4534 | N47: ='Annual P&L'!N5*Assumptions!C29 -> 4987.368 | O47: ='Annual P&L'!O5*Assumptions!D29 -> 5439.9603 | P47: ='Annual P&L'!P5*Assumptions!E29 -> 5921.7972
A48: Non-current tax assets | B48: ='Raw Financials'!C59 -> 0 | C48: ='Raw Financials'!D59 -> 0 | D48: ='Raw Financials'!E59 -> 0 | E48: ='Raw Financials'!F59 -> 0 | F48: ='Raw Financials'!G59 -> 0 | G48: ='Raw Financials'!H59 -> 0 | H48: ='Raw Financials'!I59 -> 0 | I48: ='Raw Financials'!J59 -> 451.71 | ... L48: ='Raw Financials'!M59 -> 1032.97 | M48: =L48 -> 1032.97 | N48: =M48 -> 1032.97 | O48: =N48 -> 1032.97 | P48: =O48 -> 1032.97
A49: Other non-current assets | B49: ='Raw Financials'!C60 -> 870.1 | C49: ='Raw Financials'!D60 -> 71.85 | D49: ='Raw Financials'!E60 -> 91.57 | E49: ='Raw Financials'!F60 -> 68.31 | F49: ='Raw Financials'!G60 -> 331.31 | G49: ='Raw Financials'!H60 -> 441.52 | H49: ='Raw Financials'!I60 -> 531.61 | I49: ='Raw Financials'!J60 -> 959.29 | ... L49: ='Raw Financials'!M60 -> 450.32 | M49: ='Annual P&L'!M5*Assumptions!B28+'Nagarro Scenario'!C15 -> 5445.5667 | N49: ='Annual P&L'!N5*Assumptions!C28+'Nagarro Scenario'!D15 -> 6071.5785 | O49: ='Annual P&L'!O5*Assumptions!D28+'Nagarro Scenario'!E15 -> 6429.044 | P49: ='Annual P&L'!P5*Assumptions!E28+'Nagarro Scenario'!F15 -> 6767.7682
A50: Historical classification / aggregation residual | B50: =B51-SUM(B39:B49) -> 0 | C50: =C51-SUM(C39:C49) -> 0 | D50: =D51-SUM(D39:D49) -> 0 | E50: =E51-SUM(E39:E49) -> 0 | F50: =F51-SUM(F39:F49) -> 0 | G50: =G51-SUM(G39:G49) -> 0 | H50: =H51-SUM(H39:H49) -> 0 | I50: =I51-SUM(I39:I49) -> 0 | ... L50: =L51-SUM(L39:L49) -> 899.36 | M50: =L50 -> 899.36 | N50: =M50 -> 899.36 | O50: =N50 -> 899.36 | P50: =O50 -> 899.36
A51: Total non-current assets | B51: ='Raw Financials'!C61 -> 7929.8 | C51: ='Raw Financials'!D61 -> 9424.99 | D51: ='Raw Financials'!E61 -> 8968.66 | E51: ='Raw Financials'!F61 -> 9655.89 | F51: ='Raw Financials'!G61 -> 11066.08 | G51: ='Raw Financials'!H61 -> 9952.11 | H51: ='Raw Financials'!I61 -> 25801.72 | I51: ='Raw Financials'!J61 -> 32264.69 | ... L51: ='Raw Financials'!M61 -> 42792.61 | M51: =SUM(M39:M50) -> 49410.416 | N51: =SUM(N39:N50) -> 51534.71 | O51: =SUM(O39:O50) -> 53581.123 | P51: =SUM(P39:P50) -> 56093.626
A53: Current investments | B53: ='Raw Financials'!C62 -> 4827.55 | C53: ='Raw Financials'!D62 -> 4499.66 | D53: ='Raw Financials'!E62 -> 5916.31 | E53: ='Raw Financials'!F62 -> 3295.53 | F53: ='Raw Financials'!G62 -> 5164.77 | G53: ='Raw Financials'!H62 -> 6374.95 | H53: ='Raw Financials'!I62 -> 4346.91 | I53: ='Raw Financials'!J62 -> 1879.66 | ... L53: ='Raw Financials'!M62 -> 9146.28 | M53: ='Annual P&L'!M5*Assumptions!B26 -> 9983.539 | N53: ='Annual P&L'!N5*Assumptions!C26 -> 11926.315 | O53: ='Annual P&L'!O5*Assumptions!D26 -> 13599.901 | P53: ='Annual P&L'!P5*Assumptions!E26 -> 15509.469
A54: Trade receivables | B54: ='Raw Financials'!C63 -> 4275.49 | C54: ='Raw Financials'!D63 -> 4753.83 | D54: ='Raw Financials'!E63 -> 4847.4 | E54: ='Raw Financials'!F63 -> 4923.01 | F54: ='Raw Financials'!G63 -> 5921.96 | G54: ='Raw Financials'!H63 -> 5708.97 | H54: ='Raw Financials'!I63 -> 9484.29 | I54: ='Raw Financials'!J63 -> 15253.22 | ... L54: ='Raw Financials'!M63 -> 21331.89 | M54: ='Annual P&L'!M5/365*Assumptions!B23 -> 29838.722 | N54: ='Annual P&L'!N5/365*Assumptions!C23 -> 35051.187 | O54: ='Annual P&L'!O5/365*Assumptions!D23 -> 39292.366 | P54: ='Annual P&L'!P5/365*Assumptions!E23 -> 44036.848
A55: Cash & equivalents | B55: ='Raw Financials'!C64 -> 1401.4 | C55: ='Raw Financials'!D64 -> 1461.38 | D55: ='Raw Financials'!E64 -> 1343.72 | E55: ='Raw Financials'!F64 -> 1739.45 | F55: ='Raw Financials'!G64 -> 1899.99 | G55: ='Raw Financials'!H64 -> 2419.3 | H55: ='Raw Financials'!I64 -> 2977.99 | I55: ='Raw Financials'!J64 -> 4670.12 | ... L55: ='Raw Financials'!M64 -> 10749.15 | M55: ='Annual P&L'!M130 -> 14138.685 | N55: ='Annual P&L'!N130 -> 26234.741 | O55: ='Annual P&L'!O130 -> 42898.03 | P55: ='Annual P&L'!P130 -> 62560.402
A56: Other bank balances | B56: ='Raw Financials'!C65 -> 30.98 | C56: ='Raw Financials'!D65 -> 48.25 | D56: ='Raw Financials'!E65 -> 1070.25 | E56: ='Raw Financials'!F65 -> 4984.39 | F56: ='Raw Financials'!G65 -> 2672.19 | G56: ='Raw Financials'!H65 -> 7389.7 | H56: ='Raw Financials'!I65 -> 6166.59 | I56: ='Raw Financials'!J65 -> 4362.68 | ... L56: ='Raw Financials'!M65 -> 1433.36 | M56: ='Annual P&L'!M5*Assumptions!B27 -> 1815.1889 | N56: ='Annual P&L'!N5*Assumptions!C27 -> 2168.4209 | O56: ='Annual P&L'!O5*Assumptions!D27 -> 2472.7092 | P56: ='Annual P&L'!P5*Assumptions!E27 -> 2819.9034
A57: Other current financial assets incl. unbilled | B57: ='Raw Financials'!C66 -> 812.44 | C57: ='Raw Financials'!D66 -> 2325.81 | D57: ='Raw Financials'!E66 -> 2764.88 | E57: ='Raw Financials'!F66 -> 2384.87 | F57: ='Raw Financials'!G66 -> 2082.25 | G57: ='Raw Financials'!H66 -> 2537.96 | H57: ='Raw Financials'!I66 -> 3231 | I57: ='Raw Financials'!J66 -> 4882.17 | ... L57: ='Raw Financials'!M66 -> 12085.43 | M57: ='Annual P&L'!M5/365*Assumptions!B24 -> 15416.673 | N57: ='Annual P&L'!N5/365*Assumptions!C24 -> 17822.637 | O57: ='Annual P&L'!O5/365*Assumptions!D24 -> 19646.183 | P57: ='Annual P&L'!P5/365*Assumptions!E24 -> 21632.136
A58: Current tax assets | B58: ='Raw Financials'!C67 -> 0 | C58: ='Raw Financials'!D67 -> 94.42 | D58: ='Raw Financials'!E67 -> 113.99 | E58: ='Raw Financials'!F67 -> 185.06 | F58: ='Raw Financials'!G67 -> 163.93 | G58: ='Raw Financials'!H67 -> 188 | H58: ='Raw Financials'!I67 -> 179.57 | I58: ='Raw Financials'!J67 -> 0 | ... L58: ='Raw Financials'!M67 -> 0 | M58: =0 -> 0 | N58: =0 -> 0 | O58: =0 -> 0 | P58: =0 -> 0
A59: Other current assets | B59: ='Raw Financials'!C68 -> 1787.77 | C59: ='Raw Financials'!D68 -> 855.39 | D59: ='Raw Financials'!E68 -> 1563.41 | E59: ='Raw Financials'!F68 -> 1387.79 | F59: ='Raw Financials'!G68 -> 1950.52 | G59: ='Raw Financials'!H68 -> 2083.72 | H59: ='Raw Financials'!I68 -> 2002.94 | I59: ='Raw Financials'!J68 -> 3418.26 | ... L59: ='Raw Financials'!M68 -> 16226.72 | M59: ='Annual P&L'!M5*Assumptions!B25 -> 18151.889 | N59: ='Annual P&L'!N5*Assumptions!C25 -> 20599.998 | O59: ='Annual P&L'!O5*Assumptions!D25 -> 22254.383 | P59: ='Annual P&L'!P5*Assumptions!E25 -> 23969.179
A60: Historical classification / aggregation residual | B60: =B61-SUM(B53:B59) -> 0 | C60: =C61-SUM(C53:C59) -> 0 | D60: =D61-SUM(D53:D59) -> 0 | E60: =E61-SUM(E53:E59) -> 0 | F60: =F61-SUM(F53:F59) -> 0 | G60: =G61-SUM(G53:G59) -> 0.53 | H60: =H61-SUM(H53:H59) -> 0 | I60: =I61-SUM(I53:I59) -> 0 | ... L60: =L61-SUM(L53:L59) -> 0 | M60: =0 -> 0 | N60: =0 -> 0 | O60: =0 -> 0 | P60: =0 -> 0
A61: Total current assets | B61: ='Raw Financials'!C69 -> 13135.63 | C61: ='Raw Financials'!D69 -> 14038.74 | D61: ='Raw Financials'!E69 -> 17619.96 | E61: ='Raw Financials'!F69 -> 18900.1 | F61: ='Raw Financials'!G69 -> 19855.61 | G61: ='Raw Financials'!H69 -> 26703.13 | H61: ='Raw Financials'!I69 -> 28389.29 | I61: ='Raw Financials'!J69 -> 34466.11 | ... L61: ='Raw Financials'!M69 -> 70972.83 | M61: =SUM(M53:M60) -> 89344.697 | N61: =SUM(N53:N60) -> 113803.3 | O61: =SUM(O53:O60) -> 140163.57 | P61: =SUM(P53:P60) -> 170527.94
A62: Total assets | B62: ='Raw Financials'!C70 -> 21065.43 | C62: ='Raw Financials'!D70 -> 23463.73 | D62: ='Raw Financials'!E70 -> 26588.62 | E62: ='Raw Financials'!F70 -> 28555.99 | F62: ='Raw Financials'!G70 -> 30921.69 | G62: ='Raw Financials'!H70 -> 36655.24 | H62: ='Raw Financials'!I70 -> 54191.01 | I62: ='Raw Financials'!J70 -> 66730.8 | ... L62: ='Raw Financials'!M70 -> 113765.44 | M62: =M51+M61 -> 138755.11 | N62: =N51+N61 -> 165338.01 | O62: =O51+O61 -> 193744.7 | P62: =P51+P61 -> 226621.56
A64: Share capital | B64: ='Raw Financials'!C71 -> 800 | C64: ='Raw Financials'!D71 -> 800 | D64: ='Raw Financials'!E71 -> 800 | E64: ='Raw Financials'!F71 -> 791.19 | F64: ='Raw Financials'!G71 -> 764.25 | G64: ='Raw Financials'!H71 -> 764.25 | H64: ='Raw Financials'!I71 -> 764.25 | I64: ='Raw Financials'!J71 -> 764.25 | ... L64: ='Raw Financials'!M71 -> 788.75 | M64: =L64 -> 788.75 | N64: =M64 -> 788.75 | O64: =N64 -> 788.75 | P64: =O64 -> 788.75
A65: Other equity | B65: ='Raw Financials'!C72 -> 15592.96 | C65: ='Raw Financials'!D72 -> 18192.63 | D65: ='Raw Financials'!E72 -> 20471.99 | E65: ='Raw Financials'!F72 -> 22655.61 | F65: ='Raw Financials'!G72 -> 23093.3 | G65: ='Raw Financials'!H72 -> 27192.41 | H65: ='Raw Financials'!I72 -> 32917.95 | I65: ='Raw Financials'!J72 -> 38886.53 | ... L65: ='Raw Financials'!M72 -> 77589.8 | M65: =L65+'Annual P&L'!M25+'Annual P&L'!M96+Assumptions!B45-'Annual P&L'!M31+'Nagarro Scenario'!C13 -> 93806.843 | N65: =M65+'Annual P&L'!N25+'Annual P&L'!N96+Assumptions!C45-'Annual P&L'!N31+'Nagarro Scenario'!D13 -> 113752.39 | O65: =N65+'Annual P&L'!O25+'Annual P&L'!O96+Assumptions!D45-'Annual P&L'!O31+'Nagarro Scenario'!E13 -> 136872.17 | P65: =O65+'Annual P&L'!P25+'Annual P&L'!P96+Assumptions!E45-'Annual P&L'!P31+'Nagarro Scenario'!F13 -> 163648.59
A66: Total equity | B66: ='Raw Financials'!C73 -> 16392.96 | C66: ='Raw Financials'!D73 -> 18992.63 | D66: ='Raw Financials'!E73 -> 21271.99 | E66: ='Raw Financials'!F73 -> 23446.8 | F66: ='Raw Financials'!G73 -> 23857.55 | G66: ='Raw Financials'!H73 -> 27956.66 | H66: ='Raw Financials'!I73 -> 33682.2 | I66: ='Raw Financials'!J73 -> 39650.78 | ... L66: ='Raw Financials'!M73 -> 78378.55 | M66: =M64+M65 -> 94595.593 | N66: =N64+N65 -> 114541.14 | O66: =O64+O65 -> 137660.92 | P66: =P64+P65 -> 164437.34
A68: Long-term borrowings | B68: ='Raw Financials'!C74 -> 25.7 | C68: ='Raw Financials'!D74 -> 21.71 | D68: ='Raw Financials'!E74 -> 16.55 | E68: ='Raw Financials'!F74 -> 11.97 | F68: ='Raw Financials'!G74 -> 46.22 | G68: ='Raw Financials'!H74 -> 44.27 | H68: ='Raw Financials'!I74 -> 2800.79 | I68: ='Raw Financials'!J74 -> 2057.59 | ... L68: ='Raw Financials'!M74 -> 0 | M68: =L68+'Nagarro Scenario'!C14 -> 0 | N68: =M68+'Nagarro Scenario'!D14 -> 0 | O68: =N68+'Nagarro Scenario'!E14 -> 0 | P68: =O68+'Nagarro Scenario'!F14 -> 0
A69: Non-current lease liabilities | B69: ='Raw Financials'!C75 -> 0 | C69: ='Raw Financials'!D75 -> 0 | D69: ='Raw Financials'!E75 -> 0 | E69: ='Raw Financials'!F75 -> 0 | F69: ='Raw Financials'!G75 -> 353.36 | G69: ='Raw Financials'!H75 -> 716.17 | H69: ='Raw Financials'!I75 -> 1114.29 | I69: ='Raw Financials'!J75 -> 1592.2 | ... L69: ='Raw Financials'!M75 -> 2996.7 | M69: =(L69+L78+'Annual P&L'!M120+'Annual P&L'!M119)*0.65 -> 3352.2612 | N69: =(M69+M78+'Annual P&L'!N120+'Annual P&L'!N119)*0.65 -> 3756.0564 | O69: =(N69+N78+'Annual P&L'!O120+'Annual P&L'!O119)*0.65 -> 4236.5005 | P69: =(O69+O78+'Annual P&L'!P120+'Annual P&L'!P119)*0.65 -> 4798.4876
A70: Other non-current financial liabilities | B70: ='Raw Financials'!C76 -> 1.21 | C70: ='Raw Financials'!D76 -> 19.74 | D70: ='Raw Financials'!E76 -> 0 | E70: ='Raw Financials'!F76 -> 0 | F70: ='Raw Financials'!G76 -> 7.96 | G70: ='Raw Financials'!H76 -> 0 | H70: ='Raw Financials'!I76 -> 2088.6 | I70: ='Raw Financials'!J76 -> 2888.92 | ... L70: ='Raw Financials'!M76 -> 157.14 | M70: =L70*0.8 -> 125.712 | N70: =M70*0.8 -> 100.5696 | O70: =N70*0.8 -> 80.45568 | P70: =O70*0.8 -> 64.364544
A71: Other non-current liabilities | B71: ='Raw Financials'!C77 -> 0 | C71: ='Raw Financials'!D77 -> 0 | D71: ='Raw Financials'!E77 -> 0 | E71: ='Raw Financials'!F77 -> 0 | F71: ='Raw Financials'!G77 -> 0 | G71: ='Raw Financials'!H77 -> 0 | H71: ='Raw Financials'!I77 -> 0 | I71: ='Raw Financials'!J77 -> 34.83 | ... L71: ='Raw Financials'!M77 -> 31.44 | M71: =L71 -> 31.44 | N71: =M71 -> 31.44 | O71: =N71 -> 31.44 | P71: =O71 -> 31.44
A72: Deferred tax liabilities | B72: ='Raw Financials'!C78 -> 0 | C72: ='Raw Financials'!D78 -> 110.75 | D72: ='Raw Financials'!E78 -> 270.41 | E72: ='Raw Financials'!F78 -> 0 | F72: ='Raw Financials'!G78 -> 0 | G72: ='Raw Financials'!H78 -> 0 | H72: ='Raw Financials'!I78 -> 0 | I72: ='Raw Financials'!J78 -> 4.68 | ... L72: ='Raw Financials'!M78 -> 326.28 | M72: ='Annual P&L'!M5*Assumptions!B41 -> 544.55667 | N72: ='Annual P&L'!N5*Assumptions!C41 -> 650.52627 | O72: ='Annual P&L'!O5*Assumptions!D41 -> 741.81277 | P72: ='Annual P&L'!P5*Assumptions!E41 -> 845.97103
A73: Non-current provisions | B73: ='Raw Financials'!C79 -> 124.41 | C73: ='Raw Financials'!D79 -> 146.14 | D73: ='Raw Financials'!E79 -> 159.75 | E73: ='Raw Financials'!F79 -> 252.8 | F73: ='Raw Financials'!G79 -> 182.79 | G73: ='Raw Financials'!H79 -> 240.94 | H73: ='Raw Financials'!I79 -> 245.54 | I73: ='Raw Financials'!J79 -> 373.03 | ... L73: ='Raw Financials'!M79 -> 2632.77 | M73: ='Annual P&L'!M5*Assumptions!B42 -> 2178.2267 | N73: ='Annual P&L'!N5*Assumptions!C42 -> 2385.263 | O73: ='Annual P&L'!O5*Assumptions!D42 -> 2472.7092 | P73: ='Annual P&L'!P5*Assumptions!E42 -> 2537.9131
A74: Historical classification / aggregation residual | B74: =B75-SUM(B68:B73) -> 0 | C74: =C75-SUM(C68:C73) -> 0 | D74: =D75-SUM(D68:D73) -> 0 | E74: =E75-SUM(E68:E73) -> 0 | F74: =F75-SUM(F68:F73) -> 0 | G74: =G75-SUM(G68:G73) -> 0 | H74: =H75-SUM(H68:H73) -> 0 | I74: =I75-SUM(I68:I73) -> 0 | ... L74: =L75-SUM(L68:L73) -> 0 | M74: =0 -> 0 | N74: =0 -> 0 | O74: =0 -> 0 | P74: =0 -> 0
A75: Total non-current liabilities | B75: ='Raw Financials'!C80 -> 151.32 | C75: ='Raw Financials'!D80 -> 298.34 | D75: ='Raw Financials'!E80 -> 446.71 | E75: ='Raw Financials'!F80 -> 264.77 | F75: ='Raw Financials'!G80 -> 590.33 | G75: ='Raw Financials'!H80 -> 1001.38 | H75: ='Raw Financials'!I80 -> 6249.22 | I75: ='Raw Financials'!J80 -> 6951.25 | ... L75: ='Raw Financials'!M80 -> 6144.33 | M75: =SUM(M68:M74) -> 6232.1965 | N75: =SUM(N68:N74) -> 6923.8552 | O75: =SUM(O68:O74) -> 7562.9182 | P75: =SUM(P68:P74) -> 8278.1762
A77: Short-term borrowings | B77: ='Raw Financials'!C81 -> 0 | C77: ='Raw Financials'!D81 -> 0 | D77: ='Raw Financials'!E81 -> 0 | E77: ='Raw Financials'!F81 -> 0 | F77: ='Raw Financials'!G81 -> 0 | G77: ='Raw Financials'!H81 -> 1.96 | H77: ='Raw Financials'!I81 -> 1524.56 | I77: ='Raw Financials'!J81 -> 2249.36 | ... L77: ='Raw Financials'!M81 -> 0 | M77: =0 -> 0 | N77: =0 -> 0 | O77: =0 -> 0 | P77: =0 -> 0
A78: Current lease liabilities | B78: ='Raw Financials'!C82 -> 0 | C78: ='Raw Financials'!D82 -> 0 | D78: ='Raw Financials'!E82 -> 0 | E78: ='Raw Financials'!F82 -> 0 | F78: ='Raw Financials'!G82 -> 309.06 | G78: ='Raw Financials'!H82 -> 222 | H78: ='Raw Financials'!I82 -> 342.58 | I78: ='Raw Financials'!J82 -> 676.39 | ... L78: ='Raw Financials'!M82 -> 1777.78 | M78: =(L69+L78+'Annual P&L'!M120+'Annual P&L'!M119)*0.35 -> 1805.0637 | N78: =(M69+M78+'Annual P&L'!N120+'Annual P&L'!N119)*0.35 -> 2022.4919 | O78: =(N69+N78+'Annual P&L'!O120+'Annual P&L'!O119)*0.35 -> 2281.1926 | P78: =(O69+O78+'Annual P&L'!P120+'Annual P&L'!P119)*0.35 -> 2583.801
A79: Trade payables | B79: ='Raw Financials'!C83 -> 1651.02 | C79: ='Raw Financials'!D83 -> 1209.36 | D79: ='Raw Financials'!E83 -> 1673.08 | E79: ='Raw Financials'!F83 -> 1517.07 | F79: ='Raw Financials'!G83 -> 2247.09 | G79: ='Raw Financials'!H83 -> 2733.44 | H79: ='Raw Financials'!I83 -> 4298.71 | I79: ='Raw Financials'!J83 -> 5689.08 | ... L79: ='Raw Financials'!M83 -> 11341.88 | M79: ='Annual P&L'!M5*Assumptions!B36 -> 13613.917 | N79: ='Annual P&L'!N5*Assumptions!C36 -> 15829.472 | O79: ='Annual P&L'!O5*Assumptions!D36 -> 17556.236 | P79: ='Annual P&L'!P5*Assumptions!E36 -> 19739.324
A80: Other current financial liabilities | B80: ='Raw Financials'!C84 -> 1646.5 | C80: ='Raw Financials'!D84 -> 453.58 | D80: ='Raw Financials'!E84 -> 396.33 | E80: ='Raw Financials'!F84 -> 441.93 | F80: ='Raw Financials'!G84 -> 854.38 | G80: ='Raw Financials'!H84 -> 388.21 | H80: ='Raw Financials'!I84 -> 2173.6 | I80: ='Raw Financials'!J84 -> 3922.85 | ... L80: ='Raw Financials'!M84 -> 8272.69 | M80: ='Annual P&L'!M5*Assumptions!B37 -> 9075.9445 | N80: ='Annual P&L'!N5*Assumptions!C37 -> 10408.42 | O80: ='Annual P&L'!O5*Assumptions!D37 -> 11374.463 | P80: ='Annual P&L'!P5*Assumptions!E37 -> 12407.575
A81: Other current liabilities | B81: ='Raw Financials'!C85 -> 0 | C81: ='Raw Financials'!D85 -> 1118.75 | D81: ='Raw Financials'!E85 -> 1201.02 | E81: ='Raw Financials'!F85 -> 1124.27 | F81: ='Raw Financials'!G85 -> 1320.13 | G81: ='Raw Financials'!H85 -> 1514.95 | H81: ='Raw Financials'!I85 -> 1621.76 | I81: ='Raw Financials'!J85 -> 2647.71 | ... L81: ='Raw Financials'!M85 -> 6805.36 | M81: ='Annual P&L'!M5*Assumptions!B38 -> 9075.9445 | N81: ='Annual P&L'!N5*Assumptions!C38 -> 10408.42 | O81: ='Annual P&L'!O5*Assumptions!D38 -> 11374.463 | P81: ='Annual P&L'!P5*Assumptions!E38 -> 12407.575
A82: Current provisions | B82: ='Raw Financials'!C86 -> 1223.63 | C82: ='Raw Financials'!D86 -> 1391.07 | D82: ='Raw Financials'!E86 -> 1599.49 | E82: ='Raw Financials'!F86 -> 1686.35 | F82: ='Raw Financials'!G86 -> 1610.99 | G82: ='Raw Financials'!H86 -> 2477.79 | H82: ='Raw Financials'!I86 -> 3949.66 | I82: ='Raw Financials'!J86 -> 4649.24 | ... L82: ='Raw Financials'!M86 -> 570.25 | M82: ='Annual P&L'!M5*Assumptions!B39 -> 3630.3778 | N82: ='Annual P&L'!N5*Assumptions!C39 -> 4336.8418 | O82: ='Annual P&L'!O5*Assumptions!D39 -> 4945.4185 | P82: ='Annual P&L'!P5*Assumptions!E39 -> 5639.8068
A83: Current tax liabilities | B83: ='Raw Financials'!C87 -> 0 | C83: ='Raw Financials'!D87 -> 0 | D83: ='Raw Financials'!E87 -> 0 | E83: ='Raw Financials'!F87 -> 74.8 | F83: ='Raw Financials'!G87 -> 132.16 | G83: ='Raw Financials'!H87 -> 358.85 | H83: ='Raw Financials'!I87 -> 348.72 | I83: ='Raw Financials'!J87 -> 294.14 | ... L83: ='Raw Financials'!M87 -> 474.6 | M83: ='Annual P&L'!M5*Assumptions!B40 -> 726.07556 | N83: ='Annual P&L'!N5*Assumptions!C40 -> 867.36835 | O83: ='Annual P&L'!O5*Assumptions!D40 -> 989.0837 | P83: ='Annual P&L'!P5*Assumptions!E40 -> 1127.9614
A84: Historical classification / aggregation residual | B84: =B85-SUM(B77:B83) -> 0 | C84: =C85-SUM(C77:C83) -> 0 | D84: =D85-SUM(D77:D83) -> 0 | E84: =E85-SUM(E77:E83) -> 0 | F84: =F85-SUM(F77:F83) -> 0 | G84: =G85-SUM(G77:G83) -> 0 | H84: =H85-SUM(H77:H83) -> 0 | I84: =I85-SUM(I77:I83) -> 0 | ... L84: =L85-SUM(L77:L83) -> 0 | M84: =0 -> 0 | N84: =0 -> 0 | O84: =0 -> 0 | P84: =0 -> 0
A85: Total current liabilities | B85: ='Raw Financials'!C88 -> 4521.15 | C85: ='Raw Financials'!D88 -> 4172.76 | D85: ='Raw Financials'!E88 -> 4869.92 | E85: ='Raw Financials'!F88 -> 4844.42 | F85: ='Raw Financials'!G88 -> 6473.81 | G85: ='Raw Financials'!H88 -> 7697.2 | H85: ='Raw Financials'!I88 -> 14259.59 | I85: ='Raw Financials'!J88 -> 20128.77 | ... L85: ='Raw Financials'!M88 -> 29242.56 | M85: =SUM(M77:M84) -> 37927.323 | N85: =SUM(N77:N84) -> 43873.015 | O85: =SUM(O77:O84) -> 48520.855 | P85: =SUM(P77:P84) -> 53906.043
A86: Total liabilities | B86: ='Raw Financials'!C89 -> 4672.47 | C86: ='Raw Financials'!D89 -> 4471.1 | D86: ='Raw Financials'!E89 -> 5316.63 | E86: ='Raw Financials'!F89 -> 5109.19 | F86: ='Raw Financials'!G89 -> 7064.14 | G86: ='Raw Financials'!H89 -> 8698.58 | H86: ='Raw Financials'!I89 -> 20508.81 | I86: ='Raw Financials'!J89 -> 27080.02 | ... L86: ='Raw Financials'!M89 -> 35386.89 | M86: =M75+M85 -> 44159.519 | N86: =N75+N85 -> 50796.87 | O86: =O75+O85 -> 56083.774 | P86: =P75+P85 -> 62184.22
A87: Total equity & liabilities | B87: ='Raw Financials'!C90 -> 21065.43 | C87: ='Raw Financials'!D90 -> 23463.73 | D87: ='Raw Financials'!E90 -> 26588.62 | E87: ='Raw Financials'!F90 -> 28555.99 | F87: ='Raw Financials'!G90 -> 30921.69 | G87: ='Raw Financials'!H90 -> 36655.24 | H87: ='Raw Financials'!I90 -> 54191.01 | I87: ='Raw Financials'!J90 -> 66730.8 | ... L87: ='Raw Financials'!M90 -> 113765.44 | M87: =M66+M86 -> 138755.11 | N87: =N66+N86 -> 165338.01 | O87: =O66+O86 -> 193744.7 | P87: =P66+P86 -> 226621.56
A88: Balance check | B88: =B62-B87 -> 0 | C88: =C62-C87 -> 0 | D88: =D62-D87 -> 0 | E88: =E62-E87 -> 0 | F88: =F62-F87 -> 0 | G88: =G62-G87 -> 0 | H88: =H62-H87 -> 0 | I88: =I62-I87 -> 0 | ... P88: =P62-P87 -> 0
A90: Annual Cash Flow Statement
A93: Metric | B93: FY16A | C93: FY17A | D93: FY18A | E93: FY19A | F93: FY20A | G93: FY21A | H93: FY22A | I93: FY23A | J93: FY24A | K93: FY25A | L93: FY26A | M93: FY27E | N93: FY28E | O93: FY29E | P93: FY30E
A94: Net income | B94: ='Annual P&L'!B25 -> 2973.61 | C94: ='Annual P&L'!C25 -> 3014.65 | D94: ='Annual P&L'!D25 -> 3230.88 | E94: ='Annual P&L'!E25 -> 3516.79 | F94: ='Annual P&L'!F25 -> 3402.89 | G94: ='Annual P&L'!G25 -> 4506.77 | H94: ='Annual P&L'!H25 -> 6903.86 | I94: ='Annual P&L'!I25 -> 9210.93 | ... P94: ='Annual P&L'!P25 -> 39735.259
A95: D&A | B95: ='Annual P&L'!B15 -> 965.16 | C95: ='Annual P&L'!C15 -> 1490.17 | D95: ='Annual P&L'!D15 -> 1584.87 | E95: ='Annual P&L'!E15 -> 1572.51 | F95: ='Annual P&L'!F15 -> 1659.62 | G95: ='Annual P&L'!G15 -> 1755.5 | H95: ='Annual P&L'!H15 -> 1660.12 | I95: ='Annual P&L'!I15 -> 2718.95 | ... P95: ='Annual P&L'!P15 -> 6767.7682
A96: Stock compensation / non-cash employee cost | M96: ='Annual P&L'!M5*Assumptions!B43 -> 1815.1889 | N96: ='Annual P&L'!N5*Assumptions!C43 -> 2168.4209 | O96: ='Annual P&L'!O5*Assumptions!D43 -> 2225.4383 | P96: ='Annual P&L'!P5*Assumptions!E43 -> 2537.9131
A97: Finance cost added back | B97: ='Annual P&L'!B19 -> 0.92 | C97: ='Annual P&L'!C19 -> 0.91 | D97: ='Annual P&L'!D19 -> 0.79 | E97: ='Annual P&L'!E19 -> 3.05 | F97: ='Annual P&L'!F19 -> 63.32 | G97: ='Annual P&L'!G19 -> 57.94 | H97: ='Annual P&L'!H19 -> 118.35 | I97: ='Annual P&L'!I19 -> 473.4 | ... P97: ='Annual P&L'!P19 -> 1409.9517
A98: Other non-cash / operating residual | M98: =0 -> 0 | N98: =0 -> 0 | O98: =0 -> 0 | P98: =0 -> 0
A99: Trade receivables change | M99: =-('Annual P&L'!M54-'Annual P&L'!L54) -> -8506.8317 | N99: =-('Annual P&L'!N54-'Annual P&L'!M54) -> -5212.4653 | O99: =-('Annual P&L'!O54-'Annual P&L'!N54) -> -4241.1792 | P99: =-('Annual P&L'!P54-'Annual P&L'!O54) -> -4744.4819
A100: Other current financial assets change | M100: =-('Annual P&L'!M57-'Annual P&L'!L57) -> -3331.2429 | N100: =-('Annual P&L'!N57-'Annual P&L'!M57) -> -2405.9646 | O100: =-('Annual P&L'!O57-'Annual P&L'!N57) -> -1823.5456 | P100: =-('Annual P&L'!P57-'Annual P&L'!O57) -> -1985.9528
A101: Other current assets / tax assets change | M101: =-SUM('Annual P&L'!M58-'Annual P&L'!L58,'Annual P&L'!M59-'Annual P&L'!L59) -> -1925.169 | N101: =-SUM('Annual P&L'!N58-'Annual P&L'!M58,'Annual P&L'!N59-'Annual P&L'!M59) -> -2448.1094 | O101: =-SUM('Annual P&L'!O58-'Annual P&L'!N58,'Annual P&L'!O59-'Annual P&L'!N59) -> -1654.3848 | P101: =-SUM('Annual P&L'!P58-'Annual P&L'!O58,'Annual P&L'!P59-'Annual P&L'!O59) -> -1714.7959
A102: Other non-current operating assets change | M102: =-SUM('Annual P&L'!M45-'Annual P&L'!L45,'Annual P&L'!M46-'Annual P&L'!L46,'Annual P&L'!M47-'Annual P&L'!L47,'Annual P&L'!M48-'Annual P&L'!L48,'Annual P&L'!M49-'Annual P&L'!L49) -> -5891.7301 | N102: =-SUM('Annual P&L'!N45-'Annual P&L'!M45,'Annual P&L'!N46-'Annual P&L'!M46,'Annual P&L'!N47-'Annual P&L'!M47,'Annual P&L'!N48-'Annual P&L'!M48,'Annual P&L'!N49-'Annual P&L'!M49) -> -1256.9265 | O102: =-SUM('Annual P&L'!O45-'Annual P&L'!N45,'Annual P&L'!O46-'Annual P&L'!N46,'Annual P&L'!O47-'Annual P&L'!N47,'Annual P&L'!O48-'Annual P&L'!N48,'Annual P&L'!O49-'Annual P&L'!N49) -> -810.05787 | P102: =-SUM('Annual P&L'!P45-'Annual P&L'!O45,'Annual P&L'!P46-'Annual P&L'!O46,'Annual P&L'!P47-'Annual P&L'!O47,'Annual P&L'!P48-'Annual P&L'!O48,'Annual P&L'!P49-'Annual P&L'!O49) -> -820.56102
A103: Trade payables change | M103: ='Annual P&L'!M79-'Annual P&L'!L79 -> 2272.0368 | N103: ='Annual P&L'!N79-'Annual P&L'!M79 -> 2215.5557 | O103: ='Annual P&L'!O79-'Annual P&L'!N79 -> 1726.7632 | P103: ='Annual P&L'!P79-'Annual P&L'!O79 -> 2183.0883
A104: Other current liabilities change | M104: =SUM('Annual P&L'!M80-'Annual P&L'!L80,'Annual P&L'!M81-'Annual P&L'!L81) -> 3073.839 | N104: =SUM('Annual P&L'!N80-'Annual P&L'!M80,'Annual P&L'!N81-'Annual P&L'!M81) -> 2664.9515 | O104: =SUM('Annual P&L'!O80-'Annual P&L'!N80,'Annual P&L'!O81-'Annual P&L'!N81) -> 1932.0846 | P104: =SUM('Annual P&L'!P80-'Annual P&L'!O80,'Annual P&L'!P81-'Annual P&L'!O81) -> 2066.2251
A105: Provisions and tax liabilities change | M105: =SUM('Annual P&L'!M82-'Annual P&L'!L82,'Annual P&L'!M83-'Annual P&L'!L83) -> 3311.6034 | N105: =SUM('Annual P&L'!N82-'Annual P&L'!M82,'Annual P&L'!N83-'Annual P&L'!M83) -> 847.75676 | O105: =SUM('Annual P&L'!O82-'Annual P&L'!N82,'Annual P&L'!O83-'Annual P&L'!N83) -> 730.29207 | P105: =SUM('Annual P&L'!P82-'Annual P&L'!O82,'Annual P&L'!P83-'Annual P&L'!O83) -> 833.26602
A106: Other non-current liabilities change | M106: =SUM('Annual P&L'!M70-'Annual P&L'!L70,'Annual P&L'!M71-'Annual P&L'!L71,'Annual P&L'!M72-'Annual P&L'!L72,'Annual P&L'!M73-'Annual P&L'!L73) -> -267.69465 | N106: =SUM('Annual P&L'!N70-'Annual P&L'!M70,'Annual P&L'!N71-'Annual P&L'!M71,'Annual P&L'!N72-'Annual P&L'!M72,'Annual P&L'!N73-'Annual P&L'!M73) -> 287.86349 | O106: =SUM('Annual P&L'!O70-'Annual P&L'!N70,'Annual P&L'!O71-'Annual P&L'!N71,'Annual P&L'!O72-'Annual P&L'!N72,'Annual P&L'!O73-'Annual P&L'!N73) -> 158.61886 | P106: =SUM('Annual P&L'!P70-'Annual P&L'!O70,'Annual P&L'!P71-'Annual P&L'!O71,'Annual P&L'!P72-'Annual P&L'!O72,'Annual P&L'!P73-'Annual P&L'!O73) -> 153.27095
A107: Cash taxes / classification residual | B107: =B108-SUM(B94:B106) -> -1399.09 | C107: =C108-SUM(C94:C106) -> -1641.63 | D107: =D108-SUM(D94:D106) -> -604.61 | E107: =E108-SUM(E94:E106) -> -769.21 | F107: =F108-SUM(F94:F106) -> -1897.65 | G107: =G108-SUM(G94:G106) -> 1039.04 | H107: =H108-SUM(H94:H106) -> -232.47 | I107: =I108-SUM(I94:I106) -> -2845.66 | ... L107: =L108-SUM(L94:L106) -> -5736.22 | M107: =0 -> 0 | N107: =0 -> 0 | O107: =0 -> 0 | P107: =0 -> 0
A108: Cash flow from operations | B108: ='Raw Financials'!C97 -> 2540.6 | C108: ='Raw Financials'!D97 -> 2864.1 | D108: ='Raw Financials'!E97 -> 4211.93 | E108: ='Raw Financials'!F97 -> 4323.14 | F108: ='Raw Financials'!G97 -> 3228.18 | G108: ='Raw Financials'!H97 -> 7359.25 | H108: ='Raw Financials'!I97 -> 8449.86 | I108: ='Raw Financials'!J97 -> 9557.62 | ... L108: ='Raw Financials'!M97 -> 17671.3 | M108: =SUM(M94:M107) -> 19043.02 | N108: =SUM(N94:N107) -> 32017.69 | O108: =SUM(O94:O107) -> 39362.712 | P108: =SUM(P94:P107) -> 46420.951
A109: CFO / net income | B109: =IFERROR(B108/B94,"") -> 0.85438238 | C109: =IFERROR(C108/C94,"") -> 0.95006054 | D109: =IFERROR(D108/D94,"") -> 1.3036479 | E109: =IFERROR(E108/E94,"") -> 1.2292858 | F109: =IFERROR(F108/F94,"") -> 0.94865835 | G109: =IFERROR(G108/G94,"") -> 1.6329322 | H109: =IFERROR(H108/H94,"") -> 1.2239327 | I109: =IFERROR(I108/I94,"") -> 1.037639 | ... P109: =IFERROR(P108/P94,"") -> 1.1682559
A111: PPE capex | B111: ='Raw Financials'!C100 -> -1659.35 | C111: ='Raw Financials'!D100 -> -2175.74 | D111: ='Raw Financials'!E100 -> -654.56 | E111: ='Raw Financials'!F100 -> -379.06 | F111: ='Raw Financials'!G100 -> -758.39 | G111: ='Raw Financials'!H100 -> -1281.04 | H111: ='Raw Financials'!I100 -> -3853.97 | I111: ='Raw Financials'!J100 -> -4332.99 | ... L111: ='Raw Financials'!M100 -> -2085.81 | M111: =-'Annual P&L'!M5*Assumptions!B30 -> -2722.7834 | N111: =-'Annual P&L'!N5*Assumptions!C30 -> -3035.7892 | O111: =-'Annual P&L'!O5*Assumptions!D30 -> -3461.7929 | P111: =-'Annual P&L'!P5*Assumptions!E30 -> -3947.8648
A112: Intangible capex | B112: =0 -> 0 | C112: =0 -> 0 | D112: =0 -> 0 | E112: =0 -> 0 | F112: =0 -> 0 | G112: =0 -> 0 | H112: =0 -> 0 | I112: =0 -> 0 | ... L112: =0 -> 0 | M112: =-'Annual P&L'!M5*Assumptions!B31 -> -1089.1133 | N112: =-'Annual P&L'!N5*Assumptions!C31 -> -1301.0525 | O112: =-'Annual P&L'!O5*Assumptions!D31 -> -1483.6255 | P112: =-'Annual P&L'!P5*Assumptions!E31 -> -1691.9421
A113: Acquisitions / contingent consideration | B113: ='Raw Financials'!C101 -> -307.01 | C113: ='Raw Financials'!D101 -> 0 | D113: ='Raw Financials'!E101 -> -408.35 | E113: ='Raw Financials'!F101 -> -148.17 | F113: ='Raw Financials'!G101 -> -435.48 | G113: ='Raw Financials'!H101 -> -448.47 | H113: ='Raw Financials'!I101 -> -6154.02 | I113: ='Raw Financials'!J101 -> -4310.57 | ... L113: ='Raw Financials'!M101 -> 0 | M113: =-'Nagarro Scenario'!C12 -> 0 | N113: =-'Nagarro Scenario'!D12 -> 0 | O113: =-'Nagarro Scenario'!E12 -> 0 | P113: =-'Nagarro Scenario'!F12 -> 0
...

Sheet Bookings & Revenue
A1: Bookings & Revenue Build
A2: ACV/TCV-led revenue architecture with Q1 run-rate, client mining, AI uplift, T&M deflation and optional M&A
A5: Metric | B5: FY16A | C5: FY17A | D5: FY18A | E5: FY19A | F5: FY20A | G5: FY21A | H5: FY22A | I5: FY23A | J5: FY24A | K5: FY25A | L5: FY26A | M5: FY27E | N5: FY28E | O5: FY29E | P5: FY30E
A7: Reported / forecast revenue | B7: ='Raw Operating'!C7 -> 352 | C7: ='Raw Operating'!D7 -> 429 | D7: ='Raw Operating'!E7 -> 471 | E7: ='Raw Operating'!F7 -> 481 | F7: ='Raw Operating'!G7 -> 502 | G7: ='Raw Operating'!H7 -> 566 | H7: ='Raw Operating'!I7 -> 766 | I7: ='Raw Operating'!J7 -> 1036 | ... L7: ='Raw Operating'!M7 -> 1654.4 | M7: =M24/M26 -> 1994.7131 | N7: =N24/N26 -> 2282.5483 | O7: =O24/O26 -> 2575.7388 | P7: =P24/P26 -> 2907.1169
A8: Revenue growth | C8: =IFERROR(C7/B7-1,"") -> 0.21875 | D8: =IFERROR(D7/C7-1,"") -> 0.097902098 | E8: =IFERROR(E7/D7-1,"") -> 0.021231423 | F8: =IFERROR(F7/E7-1,"") -> 0.043659044 | G8: =IFERROR(G7/F7-1,"") -> 0.12749004 | H8: =IFERROR(H7/G7-1,"") -> 0.35335689 | I8: =IFERROR(I7/H7-1,"") -> 0.35248042 | J8: =IFERROR(J7/I7-1,"") -> 0.14478764 | ... P8: =IFERROR(P7/O7-1,"") -> 0.12865362
A9: Q1 actual annualized run-rate | M9: ='Quarterly P&L'!AT5*4 -> 1809.6 | N9: =0 -> 0 | O9: =0 -> 0 | P9: =0 -> 0
A10: Capacity utilization revenue | L10: ='People & AI'!L6*'People & AI'!L8*'People & AI'!L11 -> 130228.8 | M10: ='People & AI'!M6*'People & AI'!M8*'People & AI'!M11 -> 180078.26 | N10: ='People & AI'!N6*'People & AI'!N8*'People & AI'!N11 -> 214482.78 | O10: ='People & AI'!O6*'People & AI'!O8*'People & AI'!O11 -> 243539.89 | P10: ='People & AI'!P6*'People & AI'!P8*'People & AI'!P11 -> 277151.28
A11: Total ACV bookings | B11: =IF('Raw Operating'!C13="","",'Raw Operating'!C13) | C11: =IF('Raw Operating'!D13="","",'Raw Operating'!D13) | D11: =IF('Raw Operating'!E13="","",'Raw Operating'!E13) | E11: =IF('Raw Operating'!F13="","",'Raw Operating'!F13) | F11: =IF('Raw Operating'!G13="","",'Raw Operating'!G13) | G11: =IF('Raw Operating'!H13="","",'Raw Operating'!H13) | H11: =IF('Raw Operating'!I13="","",'Raw Operating'!I13) -> 943.1 | I11: =IF('Raw Operating'!J13="","",'Raw Operating'!J13) -> 1170.9 | ... L11: =IF('Raw Operating'!M13="","",'Raw Operating'!M13) -> 1780.1 | M11: =L11*(1+Assumptions!B7) -> 1993.712 | N11: =M11*(1+Assumptions!C7) -> 2193.0832 | O11: =N11*(1+Assumptions!D7) -> 2390.4607 | P11: =O11*(1+Assumptions!E7) -> 2581.6975
A12: ACV growth | C12: =IFERROR(C11/B11-1,"") | D12: =IFERROR(D11/C11-1,"") | E12: =IFERROR(E11/D11-1,"") | F12: =IFERROR(F11/E11-1,"") | G12: =IFERROR(G11/F11-1,"") | H12: =IFERROR(H11/G11-1,"") | I12: =IFERROR(I11/H11-1,"") -> 0.24154384 | J12: =IFERROR(J11/I11-1,"") -> 0.10743872 | ... L12: =IFERROR(L11/K11-1,"") -> 0.21583225 | M12: =Assumptions!B7 -> 0.12 | N12: =Assumptions!C7 -> 0.1 | O12: =Assumptions!D7 -> 0.09 | P12: =Assumptions!E7 -> 0.08
A13: New ACV share | M13: =Assumptions!B8 -> 0.55 | N13: =Assumptions!C8 -> 0.56 | O13: =Assumptions!D8 -> 0.57 | P13: =Assumptions!E8 -> 0.58
A14: First-year realization | M14: =Assumptions!B9 -> 0.1 | N14: =Assumptions!C9 -> 0.16 | O14: =Assumptions!D9 -> 0.16 | P14: =Assumptions!E9 -> 0.16
A15: New ACV contribution | M15: =M11*M13*M14 -> 109.65416 | N15: =N11*N13*N14 -> 196.50025 | O15: =O11*O13*O14 -> 218.01001 | P15: =P11*P13*P14 -> 239.58153
A16: Strategic mega-deal TCV | M16: =Assumptions!B10 -> 650 | N16: =Assumptions!C10 -> 650 | O16: =Assumptions!D10 -> 650 | P16: =Assumptions!E10 -> 650
A17: Strategic realization | M17: =Assumptions!B11 -> 0.08 | N17: =Assumptions!C11 -> 0.1 | O17: =Assumptions!D11 -> 0.12 | P17: =Assumptions!E11 -> 0.12
A18: Strategic-deal contribution | M18: =M16*M17 -> 52 | N18: =N16*N17 -> 65 | O18: =O16*O17 -> 78 | P18: =P16*P17 -> 78
A19: Client farming / pricing | M19: =L7*Assumptions!B12 -> 24.816 | N19: =M7*Assumptions!C12 -> 29.920696 | O19: =N7*Assumptions!D12 -> 34.238225 | P19: =O7*Assumptions!E12 -> 38.636082
A20: T&M revenue pool | M20: =M10*Assumptions!B13 -> 108046.96 | N20: =N10*Assumptions!C13 -> 124400.01 | O20: =O10*Assumptions!D13 -> 136382.34 | P20: =P10*Assumptions!E13 -> 149661.69
A21: AI deflation drag | M21: =-M20*Assumptions!B14 -> -1080.4696 | N21: =-N20*Assumptions!C14 -> -1244.0001 | O21: =-O20*Assumptions!D14 -> -1091.0587 | P21: =-P20*Assumptions!E14 -> -897.97015
A22: Incremental AI uplift | M22: =M23*Assumptions!B15 -> 2521.0957 | N22: =N23*Assumptions!C15 -> 3603.3107 | O22: =O23*Assumptions!D15 -> 4822.0899 | P22: =P23*Assumptions!E15 -> 5737.0315
A23: Nagarro contribution | M23: =M10*(1-Assumptions!B13) -> 72031.306 | N23: =N10*(1-Assumptions!C13) -> 90082.767 | O23: =O10*(1-Assumptions!D13) -> 107157.55 | P23: =P10*(1-Assumptions!E13) -> 127489.59
A24: Calculated revenue | M24: =SUM(M20,M21,M22,M23) -> 181518.89 | N24: =SUM(N20,N21,N22,N23) -> 216842.09 | O24: =SUM(O20,O21,O22,O23) -> 247270.92 | P24: =SUM(P20,P21,P22,P23) -> 281990.34
A25: Revenue bridge check | M25: =M24-M7 -> 179524.18 | N25: =N24-N7 -> 214559.54 | O25: =O24-O7 -> 244695.19 | P25: =P24-P7 -> 279083.23
A26: Average INR / USD | B26: ='Annual P&L'!B8 -> 65.691222 | C26: ='Annual P&L'!C8 -> 67.09648 | D26: ='Annual P&L'!D8 -> 64.40983 | E26: ='Annual P&L'!E8 -> 69.977983 | F26: ='Annual P&L'!F8 -> 71.032032 | G26: ='Annual P&L'!G8 -> 73.990954 | H26: ='Annual P&L'!H8 -> 74.55282 | I26: ='Annual P&L'!I8 -> 80.60417 | ... L26: ='Annual P&L'!L8 -> 89.146815 | M26: =Assumptions!B16 -> 91 | N26: =Assumptions!C16 -> 95 | O26: =Assumptions!D16 -> 96 | P26: =Assumptions!E16 -> 97
A27: Revenue | B27: ='Annual P&L'!B5 -> 23123.31 | C27: ='Annual P&L'!C5 -> 28784.39 | D27: ='Annual P&L'!D5 -> 30337.03 | E27: ='Annual P&L'!E5 -> 33659.41 | F27: ='Annual P&L'!F5 -> 35658.08 | G27: ='Annual P&L'!G5 -> 41878.88 | H27: ='Annual P&L'!H5 -> 57107.46 | I27: ='Annual P&L'!I5 -> 83505.92 | ... L27: ='Annual P&L'!L5 -> 147484.49 | M27: =M7*M26 -> 181518.89 | N27: =N7*N26 -> 216842.09 | O27: =O7*O26 -> 247270.92 | P27: =P7*P26 -> 281990.34
A28: INR revenue check | M28: =M27-'Annual P&L'!M5 -> 0 | N28: =N27-'Annual P&L'!N5 -> 0 | O28: =O27-'Annual P&L'!O5 -> 0 | P28: =P27-'Annual P&L'!P5 -> 0
M29: 0.03 | N29: 0.035 | O29: 0.04 | P29: 0.04
M30: =M22/M24 -> 0.013888889

Sheet Industry Mix
A1: Industry Revenue Mix
A2: Reported comparable industry mix begins FY21; forecast mix and revenue are formula-driven
A5: Metric | B5: Units | C5: FY16A | D5: FY17A | E5: FY18A | F5: FY19A | G5: FY20A | H5: FY21A | I5: FY22A | J5: FY23A | K5: FY24A | L5: FY25A | M5: FY26A | N5: FY27E | O5: FY28E | P5: FY29E | Q5: FY30E
A7: BFSI mix | B7: % | C7: =IF('Raw Operating'!C18="","",'Raw Operating'!C18) | D7: =IF('Raw Operating'!D18="","",'Raw Operating'!D18) | E7: =IF('Raw Operating'!E18="","",'Raw Operating'!E18) | F7: =IF('Raw Operating'!F18="","",'Raw Operating'!F18) | G7: =IF('Raw Operating'!G18="","",'Raw Operating'!G18) | H7: =IF('Raw Operating'!H18="","",'Raw Operating'!H18) -> 0.308 | I7: =IF('Raw Operating'!I18="","",'Raw Operating'!I18) -> 0.316 | J7: =IF('Raw Operating'!J18="","",'Raw Operating'!J18) -> 0.329 | ... M7: =IF('Raw Operating'!M18="","",'Raw Operating'!M18) -> 0.346 | N7: =MIN(0.4,M7+0.005) -> 0.351 | O7: =MIN(0.4,N7+0.005) -> 0.356 | P7: =MIN(0.4,O7+0.005) -> 0.361 | Q7: =MIN(0.4,P7+0.005) -> 0.366
A8: BFSI revenue | B8: ₹m | C8: =IF(C7="","",C7*'Annual P&L'!B5) | D8: =IF(D7="","",D7*'Annual P&L'!C5) | E8: =IF(E7="","",E7*'Annual P&L'!D5) | F8: =IF(F7="","",F7*'Annual P&L'!E5) | G8: =IF(G7="","",G7*'Annual P&L'!F5) | H8: =IF(H7="","",H7*'Annual P&L'!G5) -> 12898.695 | I8: =IF(I7="","",I7*'Annual P&L'!H5) -> 18045.957 | J8: =IF(J7="","",J7*'Annual P&L'!I5) -> 27473.448 | ... Q8: =IF(Q7="","",Q7*'Annual P&L'!P5) -> 103208.47
A9: Healthcare & Life Sciences mix | B9: % | C9: =IF('Raw Operating'!C19="","",'Raw Operating'!C19) | D9: =IF('Raw Operating'!D19="","",'Raw Operating'!D19) | E9: =IF('Raw Operating'!E19="","",'Raw Operating'!E19) | F9: =IF('Raw Operating'!F19="","",'Raw Operating'!F19) | G9: =IF('Raw Operating'!G19="","",'Raw Operating'!G19) | H9: =IF('Raw Operating'!H19="","",'Raw Operating'!H19) -> 0.193 | I9: =IF('Raw Operating'!I19="","",'Raw Operating'!I19) -> 0.208 | J9: =IF('Raw Operating'!J19="","",'Raw Operating'!J19) -> 0.197 | ... M9: =IF('Raw Operating'!M19="","",'Raw Operating'!M19) -> 0.256 | N9: =MAX(0.23,M9-0.003) -> 0.253 | O9: =MAX(0.23,N9-0.003) -> 0.25 | P9: =MAX(0.23,O9-0.003) -> 0.247 | Q9: =MAX(0.23,P9-0.003) -> 0.244
A10: Healthcare & Life Sciences revenue | B10: ₹m | C10: =IF(C9="","",C9*'Annual P&L'!B5) | D10: =IF(D9="","",D9*'Annual P&L'!C5) | E10: =IF(E9="","",E9*'Annual P&L'!D5) | F10: =IF(F9="","",F9*'Annual P&L'!E5) | G10: =IF(G9="","",G9*'Annual P&L'!F5) | H10: =IF(H9="","",H9*'Annual P&L'!G5) -> 8082.6238 | I10: =IF(I9="","",I9*'Annual P&L'!H5) -> 11878.352 | J10: =IF(J9="","",J9*'Annual P&L'!I5) -> 16450.666 | ... Q10: =IF(Q9="","",Q9*'Annual P&L'!P5) -> 68805.644
A11: Software, Hi-Tech & Emerging mix | B11: % | C11: =IF('Raw Operating'!C20="","",'Raw Operating'!C20) | D11: =IF('Raw Operating'!D20="","",'Raw Operating'!D20) | E11: =IF('Raw Operating'!E20="","",'Raw Operating'!E20) | F11: =IF('Raw Operating'!F20="","",'Raw Operating'!F20) | G11: =IF('Raw Operating'!G20="","",'Raw Operating'!G20) | H11: =IF('Raw Operating'!H20="","",'Raw Operating'!H20) -> 0.499 | I11: =IF('Raw Operating'!I20="","",'Raw Operating'!I20) -> 0.476 | J11: =IF('Raw Operating'!J20="","",'Raw Operating'!J20) -> 0.474 | ... M11: =IF('Raw Operating'!M20="","",'Raw Operating'!M20) -> 0.398 | N11: =1-N7-N9 -> 0.396 | O11: =1-O7-O9 -> 0.394 | P11: =1-P7-P9 -> 0.392 | Q11: =1-Q7-Q9 -> 0.39
A12: Software, Hi-Tech & Emerging revenue | B12: ₹m | C12: =IF(C11="","",C11*'Annual P&L'!B5) | D12: =IF(D11="","",D11*'Annual P&L'!C5) | E12: =IF(E11="","",E11*'Annual P&L'!D5) | F12: =IF(F11="","",F11*'Annual P&L'!E5) | G12: =IF(G11="","",G11*'Annual P&L'!F5) | H12: =IF(H11="","",H11*'Annual P&L'!G5) -> 20897.561 | I12: =IF(I11="","",I11*'Annual P&L'!H5) -> 27183.151 | J12: =IF(J11="","",J11*'Annual P&L'!I5) -> 39581.806 | ... Q12: =IF(Q11="","",Q11*'Annual P&L'!P5) -> 109976.23
A13: Total mix | B13: % | C13: =IF(COUNT(C7,C9,C11)=0,"",SUM(C7,C9,C11)) | D13: =IF(COUNT(D7,D9,D11)=0,"",SUM(D7,D9,D11)) | E13: =IF(COUNT(E7,E9,E11)=0,"",SUM(E7,E9,E11)) | F13: =IF(COUNT(F7,F9,F11)=0,"",SUM(F7,F9,F11)) | G13: =IF(COUNT(G7,G9,G11)=0,"",SUM(G7,G9,G11)) | H13: =IF(COUNT(H7,H9,H11)=0,"",SUM(H7,H9,H11)) -> 1 | I13: =IF(COUNT(I7,I9,I11)=0,"",SUM(I7,I9,I11)) -> 1 | J13: =IF(COUNT(J7,J9,J11)=0,"",SUM(J7,J9,J11)) -> 1 | ... Q13: =IF(COUNT(Q7,Q9,Q11)=0,"",SUM(Q7,Q9,Q11)) -> 1

Sheet Geography
A1: Geography Revenue Mix
A2: Reported mix; India is separate only where disclosed, otherwise ROW remains the reported residual
A5: Metric | B5: Units | C5: FY16A | D5: FY17A | E5: FY18A | F5: FY19A | G5: FY20A | H5: FY21A | I5: FY22A | J5: FY23A | K5: FY24A | L5: FY25A | M5: FY26A | N5: FY27E | O5: FY28E | P5: FY29E | Q5: FY30E
A7: North America mix | B7: % | C7: =IF('Raw Operating'!C14="","",'Raw Operating'!C14) -> 0.855 | D7: =IF('Raw Operating'!D14="","",'Raw Operating'!D14) -> 0.864 | E7: =IF('Raw Operating'!E14="","",'Raw Operating'!E14) -> 0.835 | F7: =IF('Raw Operating'!F14="","",'Raw Operating'!F14) -> 0.817 | G7: =IF('Raw Operating'!G14="","",'Raw Operating'!G14) -> 0.81 | H7: =IF('Raw Operating'!H14="","",'Raw Operating'!H14) -> 0.808 | I7: =IF('Raw Operating'!I14="","",'Raw Operating'!I14) -> 0.788 | J7: =IF('Raw Operating'!J14="","",'Raw Operating'!J14) -> 0.78 | ... M7: =IF('Raw Operating'!M14="","",'Raw Operating'!M14) -> 0.806 | N7: =M7-0.005 -> 0.801 | O7: =N7-0.005 -> 0.796 | P7: =O7-0.005 -> 0.791 | Q7: =P7-0.005 -> 0.786
A8: North America revenue | B8: ₹m | C8: =IF(C7="","",C7*'Annual P&L'!B5) -> 19770.43 | D8: =IF(D7="","",D7*'Annual P&L'!C5) -> 24869.713 | E8: =IF(E7="","",E7*'Annual P&L'!D5) -> 25331.42 | F8: =IF(F7="","",F7*'Annual P&L'!E5) -> 27499.738 | G8: =IF(G7="","",G7*'Annual P&L'!F5) -> 28883.045 | H8: =IF(H7="","",H7*'Annual P&L'!G5) -> 33838.135 | I8: =IF(I7="","",I7*'Annual P&L'!H5) -> 45000.678 | J8: =IF(J7="","",J7*'Annual P&L'!I5) -> 65134.618 | ... Q8: =IF(Q7="","",Q7*'Annual P&L'!P5) -> 221644.41
A9: Europe mix | B9: % | C9: =IF('Raw Operating'!C15="","",'Raw Operating'!C15) -> 0.065 | D9: =IF('Raw Operating'!D15="","",'Raw Operating'!D15) -> 0.055 | E9: =IF('Raw Operating'!E15="","",'Raw Operating'!E15) -> 0.075 | F9: =IF('Raw Operating'!F15="","",'Raw Operating'!F15) -> 0.088 | G9: =IF('Raw Operating'!G15="","",'Raw Operating'!G15) -> 0.095 | H9: =IF('Raw Operating'!H15="","",'Raw Operating'!H15) -> 0.092 | I9: =IF('Raw Operating'!I15="","",'Raw Operating'!I15) -> 0.087 | J9: =IF('Raw Operating'!J15="","",'Raw Operating'!J15) -> 0.09 | ... M9: =IF('Raw Operating'!M15="","",'Raw Operating'!M15) -> 0.087 | N9: =MIN(0.13,M9+0.005) -> 0.092 | O9: =MIN(0.13,N9+0.005) -> 0.097 | P9: =MIN(0.13,O9+0.005) -> 0.102 | Q9: =MIN(0.13,P9+0.005) -> 0.107
A10: Europe revenue | B10: ₹m | C10: =IF(C9="","",C9*'Annual P&L'!B5) -> 1503.0152 | D10: =IF(D9="","",D9*'Annual P&L'!C5) -> 1583.1415 | E10: =IF(E9="","",E9*'Annual P&L'!D5) -> 2275.2772 | F10: =IF(F9="","",F9*'Annual P&L'!E5) -> 2962.0281 | G10: =IF(G9="","",G9*'Annual P&L'!F5) -> 3387.5176 | H10: =IF(H9="","",H9*'Annual P&L'!G5) -> 3852.857 | I10: =IF(I9="","",I9*'Annual P&L'!H5) -> 4968.349 | J10: =IF(J9="","",J9*'Annual P&L'!I5) -> 7515.5328 | ... Q10: =IF(Q9="","",Q9*'Annual P&L'!P5) -> 30172.967
A11: India mix | B11: % | C11: =IF('Raw Operating'!C16="","",'Raw Operating'!C16) | D11: =IF('Raw Operating'!D16="","",'Raw Operating'!D16) | E11: =IF('Raw Operating'!E16="","",'Raw Operating'!E16) | F11: =IF('Raw Operating'!F16="","",'Raw Operating'!F16) | G11: =IF('Raw Operating'!G16="","",'Raw Operating'!G16) | H11: =IF('Raw Operating'!H16="","",'Raw Operating'!H16) | I11: =IF('Raw Operating'!I16="","",'Raw Operating'!I16) | J11: =IF('Raw Operating'!J16="","",'Raw Operating'!J16) | ... M11: =IF('Raw Operating'!M16="","",'Raw Operating'!M16) -> 0.088 | N11: =IF(M11="",0.09,M11) -> 0.088 | O11: =IF(N11="",0.09,N11) -> 0.088 | P11: =IF(O11="",0.09,O11) -> 0.088 | Q11: =IF(P11="",0.09,P11) -> 0.088
A12: India revenue | B12: ₹m | C12: =IF(C11="","",C11*'Annual P&L'!B5) | D12: =IF(D11="","",D11*'Annual P&L'!C5) | E12: =IF(E11="","",E11*'Annual P&L'!D5) | F12: =IF(F11="","",F11*'Annual P&L'!E5) | G12: =IF(G11="","",G11*'Annual P&L'!F5) | H12: =IF(H11="","",H11*'Annual P&L'!G5) | I12: =IF(I11="","",I11*'Annual P&L'!H5) | J12: =IF(J11="","",J11*'Annual P&L'!I5) | ... Q12: =IF(Q11="","",Q11*'Annual P&L'!P5) -> 24815.15
A13: ROW / residual mix | B13: % | C13: =IF('Raw Operating'!C17="","",'Raw Operating'!C17) -> 0.08 | D13: =IF('Raw Operating'!D17="","",'Raw Operating'!D17) -> 0.081 | E13: =IF('Raw Operating'!E17="","",'Raw Operating'!E17) -> 0.09 | F13: =IF('Raw Operating'!F17="","",'Raw Operating'!F17) -> 0.095 | G13: =IF('Raw Operating'!G17="","",'Raw Operating'!G17) -> 0.095 | H13: =IF('Raw Operating'!H17="","",'Raw Operating'!H17) -> 0.1 | I13: =IF('Raw Operating'!I17="","",'Raw Operating'!I17) -> 0.125 | J13: =IF('Raw Operating'!J17="","",'Raw Operating'!J17) -> 0.13 | ... M13: =IF('Raw Operating'!M17="","",'Raw Operating'!M17) -> 0.019 | N13: =1-SUM(N7,N9,N11) -> 0.019 | O13: =1-SUM(O7,O9,O11) -> 0.019 | P13: =1-SUM(P7,P9,P11) -> 0.019 | Q13: =1-SUM(Q7,Q9,Q11) -> 0.019
A14: ROW / residual revenue | B14: ₹m | C14: =IF(C13="","",C13*'Annual P&L'!B5) -> 1849.8648 | D14: =IF(D13="","",D13*'Annual P&L'!C5) -> 2331.5356 | E14: =IF(E13="","",E13*'Annual P&L'!D5) -> 2730.3327 | F14: =IF(F13="","",F13*'Annual P&L'!E5) -> 3197.644 | G14: =IF(G13="","",G13*'Annual P&L'!F5) -> 3387.5176 | H14: =IF(H13="","",H13*'Annual P&L'!G5) -> 4187.888 | I14: =IF(I13="","",I13*'Annual P&L'!H5) -> 7138.4325 | J14: =IF(J13="","",J13*'Annual P&L'!I5) -> 10855.77 | ... Q14: =IF(Q13="","",Q13*'Annual P&L'!P5) -> 5357.8165
A15: Total mix | B15: % | C15: =IF(COUNT(C7,C9,C11,C13)=0,"",SUM(C7,C9,C11,C13)) -> 1 | D15: =IF(COUNT(D7,D9,D11,D13)=0,"",SUM(D7,D9,D11,D13)) -> 1 | E15: =IF(COUNT(E7,E9,E11,E13)=0,"",SUM(E7,E9,E11,E13)) -> 1 | F15: =IF(COUNT(F7,F9,F11,F13)=0,"",SUM(F7,F9,F11,F13)) -> 1 | G15: =IF(COUNT(G7,G9,G11,G13)=0,"",SUM(G7,G9,G11,G13)) -> 1 | H15: =IF(COUNT(H7,H9,H11,H13)=0,"",SUM(H7,H9,H11,H13)) -> 1 | I15: =IF(COUNT(I7,I9,I11,I13)=0,"",SUM(I7,I9,I11,I13)) -> 1 | J15: =IF(COUNT(J7,J9,J11,J13)=0,"",SUM(J7,J9,J11,J13)) -> 1 | ... Q15: =IF(COUNT(Q7,Q9,Q11,Q13)=0,"",SUM(Q7,Q9,Q11,Q13)) -> 1

Sheet Client Metrics
A1: Client Metrics
A2: Reported revenue bands, concentration and revenue per disclosed client; blank means no comparable disclosure
A5: Metric | B5: Units | C5: FY16A | D5: FY17A | E5: FY18A | F5: FY19A | G5: FY20A | H5: FY21A | I5: FY22A | J5: FY23A | K5: FY24A | L5: FY25A | M5: FY26A | N5: FY27E | O5: FY28E | P5: FY29E | Q5: FY30E
A7: Clients $75m+ | B7: # | C7: =IF('Raw Operating'!C22="","",'Raw Operating'!C22) | D7: =IF('Raw Operating'!D22="","",'Raw Operating'!D22) | E7: =IF('Raw Operating'!E22="","",'Raw Operating'!E22) | F7: =IF('Raw Operating'!F22="","",'Raw Operating'!F22) | G7: =IF('Raw Operating'!G22="","",'Raw Operating'!G22) | H7: =IF('Raw Operating'!H22="","",'Raw Operating'!H22) | I7: =IF('Raw Operating'!I22="","",'Raw Operating'!I22) | J7: =IF('Raw Operating'!J22="","",'Raw Operating'!J22) | ... M7: =IF('Raw Operating'!M22="","",'Raw Operating'!M22) -> 4 | N7: =ROUND(M7*(1+'Annual P&L'!M6*0.35),0) -> 4 | O7: =ROUND(N7*(1+'Annual P&L'!N6*0.35),0) -> 4 | P7: =ROUND(O7*(1+'Annual P&L'!O6*0.35),0) -> 4 | Q7: =ROUND(P7*(1+'Annual P&L'!P6*0.35),0) -> 4
A8: Clients $20–50m | B8: # | C8: =IF('Raw Operating'!C23="","",'Raw Operating'!C23) | D8: =IF('Raw Operating'!D23="","",'Raw Operating'!D23) | E8: =IF('Raw Operating'!E23="","",'Raw Operating'!E23) | F8: =IF('Raw Operating'!F23="","",'Raw Operating'!F23) | G8: =IF('Raw Operating'!G23="","",'Raw Operating'!G23) | H8: =IF('Raw Operating'!H23="","",'Raw Operating'!H23) | I8: =IF('Raw Operating'!I23="","",'Raw Operating'!I23) | J8: =IF('Raw Operating'!J23="","",'Raw Operating'!J23) | ... M8: =IF('Raw Operating'!M23="","",'Raw Operating'!M23) -> 8 | N8: =ROUND(M8*(1+'Annual P&L'!M6*0.35),0) -> 9 | O8: =ROUND(N8*(1+'Annual P&L'!N6*0.35),0) -> 9 | P8: =ROUND(O8*(1+'Annual P&L'!O6*0.35),0) -> 9 | Q8: =ROUND(P8*(1+'Annual P&L'!P6*0.35),0) -> 9
A9: Clients $10–20m | B9: # | C9: =IF('Raw Operating'!C24="","",'Raw Operating'!C24) | D9: =IF('Raw Operating'!D24="","",'Raw Operating'!D24) | E9: =IF('Raw Operating'!E24="","",'Raw Operating'!E24) | F9: =IF('Raw Operating'!F24="","",'Raw Operating'!F24) | G9: =IF('Raw Operating'!G24="","",'Raw Operating'!G24) | H9: =IF('Raw Operating'!H24="","",'Raw Operating'!H24) | I9: =IF('Raw Operating'!I24="","",'Raw Operating'!I24) | J9: =IF('Raw Operating'!J24="","",'Raw Operating'!J24) | ... M9: =IF('Raw Operating'!M24="","",'Raw Operating'!M24) -> 17 | N9: =ROUND(M9*(1+'Annual P&L'!M6*0.35),0) -> 18 | O9: =ROUND(N9*(1+'Annual P&L'!N6*0.35),0) -> 19 | P9: =ROUND(O9*(1+'Annual P&L'!O6*0.35),0) -> 20 | Q9: =ROUND(P9*(1+'Annual P&L'!P6*0.35),0) -> 21
A10: Clients $5–10m | B10: # | C10: =IF('Raw Operating'!C25="","",'Raw Operating'!C25) | D10: =IF('Raw Operating'!D25="","",'Raw Operating'!D25) | E10: =IF('Raw Operating'!E25="","",'Raw Operating'!E25) | F10: =IF('Raw Operating'!F25="","",'Raw Operating'!F25) | G10: =IF('Raw Operating'!G25="","",'Raw Operating'!G25) | H10: =IF('Raw Operating'!H25="","",'Raw Operating'!H25) | I10: =IF('Raw Operating'!I25="","",'Raw Operating'!I25) | J10: =IF('Raw Operating'!J25="","",'Raw Operating'!J25) | ... M10: =IF('Raw Operating'!M25="","",'Raw Operating'!M25) -> 33 | N10: =ROUND(M10*(1+'Annual P&L'!M6*0.35),0) -> 35 | O10: =ROUND(N10*(1+'Annual P&L'!N6*0.35),0) -> 37 | P10: =ROUND(O10*(1+'Annual P&L'!O6*0.35),0) -> 39 | Q10: =ROUND(P10*(1+'Annual P&L'!P6*0.35),0) -> 41
A11: Clients $1–5m | B11: # | C11: =IF('Raw Operating'!C26="","",'Raw Operating'!C26) | D11: =IF('Raw Operating'!D26="","",'Raw Operating'!D26) | E11: =IF('Raw Operating'!E26="","",'Raw Operating'!E26) | F11: =IF('Raw Operating'!F26="","",'Raw Operating'!F26) | G11: =IF('Raw Operating'!G26="","",'Raw Operating'!G26) | H11: =IF('Raw Operating'!H26="","",'Raw Operating'!H26) | I11: =IF('Raw Operating'!I26="","",'Raw Operating'!I26) | J11: =IF('Raw Operating'!J26="","",'Raw Operating'!J26) | ... M11: =IF('Raw Operating'!M26="","",'Raw Operating'!M26) -> 139 | N11: =ROUND(M11*(1+'Annual P&L'!M6*0.35),0) -> 149 | O11: =ROUND(N11*(1+'Annual P&L'!N6*0.35),0) -> 157 | P11: =ROUND(O11*(1+'Annual P&L'!O6*0.35),0) -> 164 | Q11: =ROUND(P11*(1+'Annual P&L'!P6*0.35),0) -> 171
A12: Total clients $1m+ | B12: # | C12: =IF('Raw Operating'!C27="","",'Raw Operating'!C27) | D12: =IF('Raw Operating'!D27="","",'Raw Operating'!D27) | E12: =IF('Raw Operating'!E27="","",'Raw Operating'!E27) | F12: =IF('Raw Operating'!F27="","",'Raw Operating'!F27) | G12: =IF('Raw Operating'!G27="","",'Raw Operating'!G27) | H12: =IF('Raw Operating'!H27="","",'Raw Operating'!H27) | I12: =IF('Raw Operating'!I27="","",'Raw Operating'!I27) | J12: =IF('Raw Operating'!J27="","",'Raw Operating'!J27) | ... M12: =IF('Raw Operating'!M27="","",'Raw Operating'!M27) -> 201 | N12: =ROUND(M12*(1+'Annual P&L'!M6*0.35),0) -> 215 | O12: =ROUND(N12*(1+'Annual P&L'!N6*0.35),0) -> 226 | P12: =ROUND(O12*(1+'Annual P&L'!O6*0.35),0) -> 236 | Q12: =ROUND(P12*(1+'Annual P&L'!P6*0.35),0) -> 247
A13: Top 10 concentration | B13: % | C13: =IF('Raw Operating'!C21="","",'Raw Operating'!C21) -> 0.455 | D13: =IF('Raw Operating'!D21="","",'Raw Operating'!D21) -> 0.531 | E13: =IF('Raw Operating'!E21="","",'Raw Operating'!E21) -> 0.535 | F13: =IF('Raw Operating'!F21="","",'Raw Operating'!F21) -> 0.518 | G13: =IF('Raw Operating'!G21="","",'Raw Operating'!G21) -> 0.517 | H13: =IF('Raw Operating'!H21="","",'Raw Operating'!H21) -> 0.477 | I13: =IF('Raw Operating'!I21="","",'Raw Operating'!I21) -> 0.446 | J13: =IF('Raw Operating'!J21="","",'Raw Operating'!J21) -> 0.367 | ... M13: =IF('Raw Operating'!M21="","",'Raw Operating'!M21) -> 0.416 | N13: =M13 -> 0.416 | O13: =N13 -> 0.416 | P13: =O13 -> 0.416 | Q13: =P13 -> 0.416
A14: Revenue per $1m+ client | B14: $m | C14: =IFERROR('Bookings & Revenue'!B7/C12,"") | D14: =IFERROR('Bookings & Revenue'!C7/D12,"") | E14: =IFERROR('Bookings & Revenue'!D7/E12,"") | F14: =IFERROR('Bookings & Revenue'!E7/F12,"") | G14: =IFERROR('Bookings & Revenue'!F7/G12,"") | H14: =IFERROR('Bookings & Revenue'!G7/H12,"") | I14: =IFERROR('Bookings & Revenue'!H7/I12,"") | J14: =IFERROR('Bookings & Revenue'!I7/J12,"") | ... Q14: =IFERROR('Bookings & Revenue'!P7/Q12,"") -> 11.769704
A15: Revenue per $5m+ client | B15: $m | C15: =IFERROR('Bookings & Revenue'!B7/SUM(C7:C10),"") | D15: =IFERROR('Bookings & Revenue'!C7/SUM(D7:D10),"") | E15: =IFERROR('Bookings & Revenue'!D7/SUM(E7:E10),"") | F15: =IFERROR('Bookings & Revenue'!E7/SUM(F7:F10),"") | G15: =IFERROR('Bookings & Revenue'!F7/SUM(G7:G10),"") | H15: =IFERROR('Bookings & Revenue'!G7/SUM(H7:H10),"") | I15: =IFERROR('Bookings & Revenue'!H7/SUM(I7:I10),"") | J15: =IFERROR('Bookings & Revenue'!I7/SUM(J7:J10),"") | ... Q15: =IFERROR('Bookings & Revenue'!P7/SUM(Q7:Q10),"") -> 38.761559
A16: ACV / revenue | B16: x | C16: =IFERROR('Bookings & Revenue'!B11/'Bookings & Revenue'!B7,"") | D16: =IFERROR('Bookings & Revenue'!C11/'Bookings & Revenue'!C7,"") | E16: =IFERROR('Bookings & Revenue'!D11/'Bookings & Revenue'!D7,"") | F16: =IFERROR('Bookings & Revenue'!E11/'Bookings & Revenue'!E7,"") | G16: =IFERROR('Bookings & Revenue'!F11/'Bookings & Revenue'!F7,"") | H16: =IFERROR('Bookings & Revenue'!G11/'Bookings & Revenue'!G7,"") | I16: =IFERROR('Bookings & Revenue'!H11/'Bookings & Revenue'!H7,"") -> 1.231201 | J16: =IFERROR('Bookings & Revenue'!I11/'Bookings & Revenue'!I7,"") -> 1.1302124 | ... Q16: =IFERROR('Bookings & Revenue'!P11/'Bookings & Revenue'!P7,"") -> 0.88806113
A17: TCV / revenue | B17: x | C17: =IF('Raw Operating'!C12="","",'Raw Operating'!C12/'Bookings & Revenue'!B7) | D17: =IF('Raw Operating'!D12="","",'Raw Operating'!D12/'Bookings & Revenue'!C7) | E17: =IF('Raw Operating'!E12="","",'Raw Operating'!E12/'Bookings & Revenue'!D7) | F17: =IF('Raw Operating'!F12="","",'Raw Operating'!F12/'Bookings & Revenue'!E7) | G17: =IF('Raw Operating'!G12="","",'Raw Operating'!G12/'Bookings & Revenue'!F7) | H17: =IF('Raw Operating'!H12="","",'Raw Operating'!H12/'Bookings & Revenue'!G7) | I17: =IF('Raw Operating'!I12="","",'Raw Operating'!I12/'Bookings & Revenue'!H7) -> 1.5960836 | J17: =IF('Raw Operating'!J12="","",'Raw Operating'!J12/'Bookings & Revenue'!I7) -> 1.5671815 | ... M17: =IF('Raw Operating'!M12="","",'Raw Operating'!M12/'Bookings & Revenue'!L7) -> 1.4538806 | N17: =IFERROR('Raw Operating'!N12/'Bookings & Revenue'!M7,"") -> 0 | O17: =IFERROR('Raw Operating'!O12/'Bookings & Revenue'!N7,"") -> 0 | P17: =IFERROR('Raw Operating'!P12/'Bookings & Revenue'!O7,"") -> 0 | Q17: =IFERROR('Raw Operating'!Q12/'Bookings & Revenue'!P7,"") -> 0

Sheet People & AI
A1: People, Productivity and AI
J3: =J5/I5-1 -> 0.041985233 | K3: =K5/J5-1 -> 0.031194969 | L3: =L5/K5-1 -> 0.11824022
A4: Metric | B4: FY16A | C4: FY17A | D4: FY18A | E4: FY19A | F4: FY20A | G4: FY21A | H4: FY22A | I4: FY23A | J4: FY24A | K4: FY25A | L4: FY26A | M4: FY27E | N4: FY28E | O4: FY29E | P4: FY30E
A5: Total headcount | B5: ='Raw Operating'!C8 -> 9264 | C5: ='Raw Operating'!D8 -> 9460 | D5: ='Raw Operating'!E8 -> 8976 | E5: ='Raw Operating'!F8 -> 9962 | F5: ='Raw Operating'!G8 -> 10632 | G5: ='Raw Operating'!H8 -> 13680 | H5: ='Raw Operating'!I8 -> 18599 | I5: ='Raw Operating'!J8 -> 22889 | ... L5: ='Raw Operating'!M8 -> 27502 | M5: =L5*(1+L3) -> 30753.843 | N5: =M5*(1.0675) -> 32829.727 | O5: =N5*1.034 -> 33945.938 | P5: =O5*1.034 -> 35100.1
A6: Technical employees | B6: ='Raw Operating'!C9 -> 0 | C6: ='Raw Operating'!D9 -> 0 | D6: ='Raw Operating'!E9 -> 0 | E6: ='Raw Operating'!F9 -> 0 | F6: ='Raw Operating'!G9 -> 0 | G6: ='Raw Operating'!H9 -> 0 | H6: ='Raw Operating'!I9 -> 0 | I6: ='Raw Operating'!J9 -> 0 | ... L6: ='Raw Operating'!M9 -> 25849 | M6: =M7*M5 -> 28970.12 | N6: =N7*N5 -> 30991.262 | O6: =O7*O5 -> 32112.857 | P6: =P7*P5 -> 33204.694
A7: Technical / headcount | B7: =IFERROR(B6/B5,"") -> 0 | C7: =IFERROR(C6/C5,"") -> 0 | D7: =IFERROR(D6/D5,"") -> 0 | E7: =IFERROR(E6/E5,"") -> 0 | F7: =IFERROR(F6/F5,"") -> 0 | G7: =IFERROR(G6/G5,"") -> 0 | H7: =IFERROR(H6/H5,"") -> 0 | I7: =IFERROR(I6/I5,"") -> 0 | ... L7: =IFERROR(L6/L5,"") -> 0.93989528 | M7: 0.942 | N7: 0.944 | O7: 0.946 | P7: =O7 -> 0.946
A8: Utilization | B8: ='Raw Operating'!C11 -> 0 | C8: ='Raw Operating'!D11 -> 0 | D8: ='Raw Operating'!E11 -> 0 | E8: ='Raw Operating'!F11 -> 0 | F8: ='Raw Operating'!G11 -> 0 | G8: ='Raw Operating'!H11 -> 0 | H8: ='Raw Operating'!I11 -> 0 | I8: ='Raw Operating'!J11 -> 0 | ... L8: ='Raw Operating'!M11 -> 0.883 | M8: =L8+0.5% -> 0.888 | N8: =M8+0.5% -> 0.893 | O8: =N8+0.45% -> 0.8975 | P8: =O8 -> 0.8975
A9: Attrition | B9: ='Raw Operating'!C10 -> 0.164 | C9: ='Raw Operating'!D10 -> 0.157 | D9: ='Raw Operating'!E10 -> 0.147 | E9: ='Raw Operating'!F10 -> 0.167 | F9: ='Raw Operating'!G10 -> 0.143 | G9: ='Raw Operating'!H10 -> 0.117 | H9: ='Raw Operating'!I10 -> 0.266 | I9: ='Raw Operating'!J10 -> 0.198 | ... L9: ='Raw Operating'!M10 -> 0.13 | M9: =MAX(0.1,L9-0.003) -> 0.127 | N9: =MAX(0.1,M9-0.003) -> 0.124 | O9: =MAX(0.1,N9-0.003) -> 0.121 | P9: =MAX(0.1,O9-0.003) -> 0.118
A10: Revenue per employee | B10: =IFERROR('Bookings & Revenue'!B7*1000000/B5,"") -> 37996.546 | C10: =IFERROR('Bookings & Revenue'!C7*1000000/C5,"") -> 45348.837 | D10: =IFERROR('Bookings & Revenue'!D7*1000000/D5,"") -> 52473.262 | E10: =IFERROR('Bookings & Revenue'!E7*1000000/E5,"") -> 48283.477 | F10: =IFERROR('Bookings & Revenue'!F7*1000000/F5,"") -> 47215.952 | G10: =IFERROR('Bookings & Revenue'!G7*1000000/G5,"") -> 41374.269 | H10: =IFERROR('Bookings & Revenue'!H7*1000000/H5,"") -> 41185.01 | I10: =IFERROR('Bookings & Revenue'!I7*1000000/I5,"") -> 45261.916 | ... P10: =IFERROR('Bookings & Revenue'!P7*1000000/P5,"") -> 82823.609
A11: Revenue per technical employee | B11: =IFERROR('Bookings & Revenue'!B7*1000000/B6,"") | C11: =IFERROR('Bookings & Revenue'!C7*1000000/C6,"") | D11: =IFERROR('Bookings & Revenue'!D7*1000000/D6,"") | E11: =IFERROR('Bookings & Revenue'!E7*1000000/E6,"") | F11: =IFERROR('Bookings & Revenue'!F7*1000000/F6,"") | G11: =IFERROR('Bookings & Revenue'!G7*1000000/G6,"") | H11: =IFERROR('Bookings & Revenue'!H7*1000000/H6,"") | I11: =IFERROR('Bookings & Revenue'!I7*1000000/I6,"") | J11: =IFERROR('Bookings & Revenue'!J7*1000000/J6,"") | K11: ='Annual P&L'!K5/'People & AI'!K6 -> 5.1745479 | L11: ='Annual P&L'!L5/'People & AI'!L6 -> 5.7056169 | M11: 7 | N11: 7.75 | O11: 8.45 | P11: 9.3
A12: Headcount growth | C12: =IFERROR(C5/B5-1,"") -> 0.021157168 | D12: =IFERROR(D5/C5-1,"") -> -0.051162791 | E12: =IFERROR(E5/D5-1,"") -> 0.10984848 | F12: =IFERROR(F5/E5-1,"") -> 0.067255571 | G12: =IFERROR(G5/F5-1,"") -> 0.28668172 | H12: =IFERROR(H5/G5-1,"") -> 0.35957602 | I12: =IFERROR(I5/H5-1,"") -> 0.23065756 | J12: =IFERROR(J5/I5-1,"") -> 0.041985233 | ... P12: =IFERROR(P5/O5-1,"") -> 0.034
A13: Revenue growth | C13: ='Annual P&L'!C6 -> 0.24482135 | D13: ='Annual P&L'!D6 -> 0.053940348 | E13: ='Annual P&L'!E6 -> 0.10951566 | F13: ='Annual P&L'!F6 -> 0.059379235 | G13: ='Annual P&L'!G6 -> 0.17445695 | H13: ='Annual P&L'!H6 -> 0.36363389 | I13: ='Annual P&L'!I6 -> 0.4622594 | J13: ='Annual P&L'!J6 -> 0.17615458 | ... P13: ='Annual P&L'!P6 -> 0.12865362
A14: Revenue growth less headcount growth | C14: =C13-C12 -> 0.22366418 | D14: =D13-D12 -> 0.10510314 | E14: =E13-E12 -> -0.00033282033 | F14: =F13-F12 -> -0.0078763367 | G14: =G13-G12 -> -0.11222476 | H14: =H13-H12 -> 0.0040578656 | I14: =I13-I12 -> 0.23160183 | J14: =J13-J12 -> 0.13416934 | ... P14: =P13-P12 -> 0.094653625
A15: T&M revenue pool | B15: ='Bookings & Revenue'!B20 -> 0 | C15: ='Bookings & Revenue'!C20 -> 0 | D15: ='Bookings & Revenue'!D20 -> 0 | E15: ='Bookings & Revenue'!E20 -> 0 | F15: ='Bookings & Revenue'!F20 -> 0 | G15: ='Bookings & Revenue'!G20 -> 0 | H15: ='Bookings & Revenue'!H20 -> 0 | I15: ='Bookings & Revenue'!I20 -> 0 | ... P15: ='Bookings & Revenue'!P20 -> 149661.69
A16: T&M AI deflation drag | B16: ='Bookings & Revenue'!B21 -> 0 | C16: ='Bookings & Revenue'!C21 -> 0 | D16: ='Bookings & Revenue'!D21 -> 0 | E16: ='Bookings & Revenue'!E21 -> 0 | F16: ='Bookings & Revenue'!F21 -> 0 | G16: ='Bookings & Revenue'!G21 -> 0 | H16: ='Bookings & Revenue'!H21 -> 0 | I16: ='Bookings & Revenue'!I21 -> 0 | ... P16: ='Bookings & Revenue'!P21 -> -897.97015
A17: Incremental AI uplift | B17: ='Bookings & Revenue'!B22 -> 0 | C17: ='Bookings & Revenue'!C22 -> 0 | D17: ='Bookings & Revenue'!D22 -> 0 | E17: ='Bookings & Revenue'!E22 -> 0 | F17: ='Bookings & Revenue'!F22 -> 0 | G17: ='Bookings & Revenue'!G22 -> 0 | H17: ='Bookings & Revenue'!H22 -> 0 | I17: ='Bookings & Revenue'!I22 -> 0 | ... P17: ='Bookings & Revenue'!P22 -> 5737.0315
A18: Net AI / productivity contribution | B18: =SUM(B16:B17) -> 0 | C18: =SUM(C16:C17) -> 0 | D18: =SUM(D16:D17) -> 0 | E18: =SUM(E16:E17) -> 0 | F18: =SUM(F16:F17) -> 0 | G18: =SUM(G16:G17) -> 0 | H18: =SUM(H16:H17) -> 0 | I18: =SUM(I16:I17) -> 0 | ... P18: =SUM(P16:P17) -> 4839.0614
A19: Q1 FY27 employees — North America | M19: 3241
A20: Q1 FY27 employees — Europe | M20: 318
A21: Q1 FY27 employees — India | M21: 24856
A22: Q1 FY27 employees — ROW | M22: 225
A23: Interpretation | B23: Persistent does not disclose annual AI revenue. The model therefore keeps incremental AI demand and T&M productivity deflation as separate, editable forecast drivers; headcount only constrains delivery capacity.

Sheet Nagarro Scenario
A1: Nagarro Transaction Scenario
A2: Pending transaction is excluded by default; user inputs flow only when the 0/1 toggle is enabled
A5: Metric | B5: Units | C5: FY27E | D5: FY28E | E5: FY29E | F5: FY30E | G5: Comment
A7: Scenario toggle | B7: 0 / 1 | C7: =Assumptions!B54 -> 0 | D7: =Assumptions!C54 -> 0 | E7: =Assumptions!D54 -> 0 | F7: =Assumptions!E54 -> 0 | G7: 0 excludes transaction
A8: Consolidation months | B8: months | C8: =Assumptions!B55 -> 0 | D8: =Assumptions!C55 -> 12 | E8: =Assumptions!D55 -> 12 | F8: =Assumptions!E55 -> 12 | G8: Enter post-close months
A9: Annual revenue | B9: $m | C9: =Assumptions!B56 -> 0 | D9: =Assumptions!C56 -> 0 | E9: =Assumptions!D56 -> 0 | F9: =Assumptions!E56 -> 0 | G9: No default estimate
A10: Revenue growth | B10: % | C10: =Assumptions!B57 -> 0 | D10: =Assumptions!C57 -> 0 | E10: =Assumptions!D57 -> 0 | F10: =Assumptions!E57 -> 0 | G10: Scenario input
A11: Revenue contribution | B11: $m | C11: =C7*C9*(1+C10)*C8/12 -> 0 | D11: =D7*D9*(1+D10)*D8/12 -> 0 | E11: =E7*E9*(1+E10)*E8/12 -> 0 | F11: =F7*F9*(1+F10)*F8/12 -> 0 | G11: Calculated
A12: Cash consideration | B12: ₹m | C12: =Assumptions!B58 -> 0 | D12: =Assumptions!C58 -> 0 | E12: =Assumptions!D58 -> 0 | F12: =Assumptions!E58 -> 0 | G12: Scenario input
A13: Share consideration | B13: ₹m | C13: =Assumptions!B59 -> 0 | D13: =Assumptions!C59 -> 0 | E13: =Assumptions!D59 -> 0 | F13: =Assumptions!E59 -> 0 | G13: Scenario input
A14: Debt funding | B14: ₹m | C14: =Assumptions!B60 -> 0 | D14: =Assumptions!C60 -> 0 | E14: =Assumptions!D60 -> 0 | F14: =Assumptions!E60 -> 0 | G14: Scenario input
A15: Net assets acquired | B15: ₹m | C15: =Assumptions!B61 -> 0 | D15: =Assumptions!C61 -> 0 | E15: =Assumptions!D61 -> 0 | F15: =Assumptions!E61 -> 0 | G15: Scenario input
A16: Implied goodwill | B16: ₹m | C16: =MAX(0,C7*(C12+C13-C15)) -> 0 | D16: =MAX(0,D7*(D12+D13-D15)) -> 0 | E16: =MAX(0,E7*(E12+E13-E15)) -> 0 | F16: =MAX(0,F7*(F12+F13-F15)) -> 0 | G16: Purchase consideration less net assets
A17: Funding check | B17: ₹m | C17: =C7*(C14+C13-C12-C13) -> 0 | D17: =D7*(D14+D13-D12-D13) -> 0 | E17: =E7*(E14+E13-E12-E13) -> 0 | F17: =F7*(F14+F13-F12-F13) -> 0 | G17: Debt funding less cash consideration
A18: Status | B18: text | C18: =IF(C7=0,"EXCLUDED",IF(ABS(C17)<1,"FUNDED","REVIEW FUNDING")) -> EXCLUDED | D18: =IF(D7=0,"EXCLUDED",IF(ABS(D17)<1,"FUNDED","REVIEW FUNDING")) -> EXCLUDED | E18: =IF(E7=0,"EXCLUDED",IF(ABS(E17)<1,"FUNDED","REVIEW FUNDING")) -> EXCLUDED | F18: =IF(F7=0,"EXCLUDED",IF(ABS(F17)<1,"FUNDED","REVIEW FUNDING")) -> EXCLUDED | G18: Control

Sheet Valuation
A1: Valuation
A2: Historical FY-end prices; forward P/E, EV/EBITDA and DCF calculate independently and blend into a target
A5: Metric | B5: Units | C5: FY16A | D5: FY17A | E5: FY18A | F5: FY19A | G5: FY20A | H5: FY21A | I5: FY22A | J5: FY23A | K5: FY24A | L5: FY25A | M5: FY26A | N5: FY27E | O5: FY28E | P5: FY29E | Q5: FY30E
A7: Reference market price | B7: ₹ / share | C7: 381.07501 | D7: 297.85001 | E7: 347.02499 | F7: 318.39999 | G7: 275.47501 | H7: 961.02502 | I7: 2382.6499 | J7: 2304.75 | K7: 3984.55 | L7: 5513.75 | M7: 4877.2002 | N7: =Assumptions!B53 -> 5594.5 | O7: =Assumptions!C53 -> 5594.5 | P7: =Assumptions!D53 -> 5594.5 | Q7: =Assumptions!E53 -> 5594.5
A8: Diluted shares | B8: m | C8: ='Annual P&L'!B28 -> 80.000269 | D8: ='Annual P&L'!C28 -> 80.006635 | E8: ='Annual P&L'!D28 -> 79.992077 | F8: ='Annual P&L'!E28 -> 79.945215 | G8: ='Annual P&L'!F28 -> 76.676205 | H8: ='Annual P&L'!G28 -> 76.424792 | I8: ='Annual P&L'!H28 -> 76.420855 | J8: ='Annual P&L'!I28 -> 76.426568 | ... Q8: ='Annual P&L'!P28 -> 156.90418
A9: Market capitalization | B9: ₹m | C9: =IF(C7="","",C7*C8) -> 30486.103 | D9: =IF(D7="","",D7*D8) -> 23829.977 | E9: =IF(E7="","",E7*E8) -> 27759.25 | F9: =IF(F7="","",F7*F8) -> 25454.556 | G9: =IF(G7="","",G7*G8) -> 21122.378 | H9: =IF(H7="","",H7*H8) -> 73446.138 | I9: =IF(I7="","",I7*I8) -> 182084.14 | J9: =IF(J7="","",J7*J8) -> 176144.13 | ... Q9: =IF(Q7="","",Q7*Q8) -> 877800.44
A10: Cash + investments + bank balances | B10: ₹m | C10: =SUM('Annual P&L'!B44,'Annual P&L'!B53,'Annual P&L'!B55,'Annual P&L'!B56) -> 7607.85 | D10: =SUM('Annual P&L'!C44,'Annual P&L'!C53,'Annual P&L'!C55,'Annual P&L'!C56) -> 8348.73 | E10: =SUM('Annual P&L'!D44,'Annual P&L'!D53,'Annual P&L'!D55,'Annual P&L'!D56) -> 11211.32 | F10: =SUM('Annual P&L'!E44,'Annual P&L'!E53,'Annual P&L'!E55,'Annual P&L'!E56) -> 14365.08 | G10: =SUM('Annual P&L'!F44,'Annual P&L'!F53,'Annual P&L'!F55,'Annual P&L'!F56) -> 14357.92 | H10: =SUM('Annual P&L'!G44,'Annual P&L'!G53,'Annual P&L'!G55,'Annual P&L'!G56) -> 19805.22 | I10: =SUM('Annual P&L'!H44,'Annual P&L'!H53,'Annual P&L'!H55,'Annual P&L'!H56) -> 17369.21 | J10: =SUM('Annual P&L'!I44,'Annual P&L'!I53,'Annual P&L'!I55,'Annual P&L'!I56) -> 15428.46 | ... Q10: =SUM('Annual P&L'!P44,'Annual P&L'!P53,'Annual P&L'!P55,'Annual P&L'!P56) -> 87891.154
A11: Borrowings + lease liabilities | B11: ₹m | C11: =SUM('Annual P&L'!B68,'Annual P&L'!B69,'Annual P&L'!B77,'Annual P&L'!B78) -> 25.7 | D11: =SUM('Annual P&L'!C68,'Annual P&L'!C69,'Annual P&L'!C77,'Annual P&L'!C78) -> 21.71 | E11: =SUM('Annual P&L'!D68,'Annual P&L'!D69,'Annual P&L'!D77,'Annual P&L'!D78) -> 16.55 | F11: =SUM('Annual P&L'!E68,'Annual P&L'!E69,'Annual P&L'!E77,'Annual P&L'!E78) -> 11.97 | G11: =SUM('Annual P&L'!F68,'Annual P&L'!F69,'Annual P&L'!F77,'Annual P&L'!F78) -> 708.64 | H11: =SUM('Annual P&L'!G68,'Annual P&L'!G69,'Annual P&L'!G77,'Annual P&L'!G78) -> 984.4 | I11: =SUM('Annual P&L'!H68,'Annual P&L'!H69,'Annual P&L'!H77,'Annual P&L'!H78) -> 5782.22 | J11: =SUM('Annual P&L'!I68,'Annual P&L'!I69,'Annual P&L'!I77,'Annual P&L'!I78) -> 6575.54 | ... Q11: =SUM('Annual P&L'!P68,'Annual P&L'!P69,'Annual P&L'!P77,'Annual P&L'!P78) -> 7382.2886
A12: Enterprise value | B12: ₹m | C12: =IF(C9="","",C9-C10+C11) -> 22903.953 | D12: =IF(D9="","",D9-D10+D11) -> 15502.957 | E12: =IF(E9="","",E9-E10+E11) -> 16564.48 | F12: =IF(F9="","",F9-F10+F11) -> 11101.446 | G12: =IF(G9="","",G9-G10+G11) -> 7473.0982 | H12: =IF(H9="","",H9-H10+H11) -> 54625.318 | I12: =IF(I9="","",I9-I10+I11) -> 170497.15 | J12: =IF(J9="","",J9-J10+J11) -> 167291.21 | ... Q12: =IF(Q9="","",Q9-Q10+Q11) -> 797291.58
A13: Diluted EPS | B13: ₹ / share | C13: ='Annual P&L'!B30 -> 37.17 | D13: ='Annual P&L'!C30 -> 37.68 | E13: ='Annual P&L'!D30 -> 40.39 | F13: ='Annual P&L'!E30 -> 43.99 | G13: ='Annual P&L'!F30 -> 44.38 | H13: ='Annual P&L'!G30 -> 58.97 | I13: ='Annual P&L'!H30 -> 90.34 | J13: ='Annual P&L'!I30 -> 120.52 | ... Q13: ='Annual P&L'!P30 -> 253.24538
A14: P/E | B14: x | C14: =IFERROR(C7/C13,"") -> 10.25222 | D14: =IFERROR(D7/D13,"") -> 7.9047242 | E14: =IFERROR(E7/E13,"") -> 8.5918543 | F14: =IFERROR(F7/F13,"") -> 7.2380085 | G14: =IFERROR(G7/G13,"") -> 6.2071881 | H14: =IFERROR(H7/H13,"") -> 16.296846 | I14: =IFERROR(I7/I13,"") -> 26.374252 | J14: =IFERROR(J7/J13,"") -> 19.123382 | ... Q14: =IFERROR(Q7/Q13,"") -> 22.091222
A15: EBITDA | B15: ₹m | C15: ='Annual P&L'!B13 -> 4171.06 | D15: ='Annual P&L'!C13 -> 4539.35 | E15: ='Annual P&L'!D13 -> 4687.2 | F15: ='Annual P&L'!E13 -> 5805.36 | G15: ='Annual P&L'!F13 -> 4929.54 | H15: ='Annual P&L'!G13 -> 6830.15 | I15: ='Annual P&L'!H13 -> 9581.711 | J15: ='Annual P&L'!I13 -> 15191.25 | ... Q15: ='Annual P&L'!P13 -> 58090.011
A16: EV / EBITDA | B16: x | C16: =IFERROR(C12/C15,"") -> 5.491159 | D16: =IFERROR(D12/D15,"") -> 3.4152371 | E16: =IFERROR(E12/E15,"") -> 3.5339819 | F16: =IFERROR(F12/F15,"") -> 1.9122752 | G16: =IFERROR(G12/G15,"") -> 1.5159829 | H16: =IFERROR(H12/H15,"") -> 7.9976747 | I16: =IFERROR(I12/I15,"") -> 17.794019 | J16: =IFERROR(J12/J15,"") -> 11.01234 | ... Q16: =IFERROR(Q12/Q15,"") -> 13.725106
A17: Dividend per share | B17: ₹ / share | C17: ='Annual P&L'!B32 -> 12.993831 | D17: ='Annual P&L'!C32 -> 5.9996274 | E17: ='Annual P&L'!D32 -> 9.9983652 | F17: ='Annual P&L'!E32 -> 10.996781 | G17: ='Annual P&L'!F32 -> 14.950922 | H17: ='Annual P&L'!G32 -> 14.000038 | I17: ='Annual P&L'!H32 -> 26.00141 | J17: ='Annual P&L'!I32 -> 38.999265 | ... Q17: ='Annual P&L'!P32 -> 98.765699
A18: Dividend yield | B18: % | C18: =IFERROR(C17/C7,"") -> 0.034097831 | D18: =IFERROR(D17/D7,"") -> 0.020143117 | E18: =IFERROR(E17/E7,"") -> 0.028811657 | F18: =IFERROR(F17/F7,"") -> 0.034537629 | G18: =IFERROR(G17/G7,"") -> 0.054273245 | H18: =IFERROR(H17/H7,"") -> 0.014567818 | I18: =IFERROR(I17/I7,"") -> 0.010912812 | J18: =IFERROR(J17/J7,"") -> 0.016921256 | ... Q18: =IFERROR(Q17/Q7,"") -> 0.017654071
A19: Target P/E | B19: x | N19: =Assumptions!B46 -> 46 | O19: =Assumptions!C46 -> 42 | P19: =Assumptions!D46 -> 39 | Q19: =Assumptions!E46 -> 36
A20: P/E implied value / share | B20: ₹ / share | N20: =N13*N19 -> 6597.2318 | O20: =O13*O19 -> 7553.2835 | P20: =P13*P19 -> 8376.5876 | Q20: =Q13*Q19 -> 9116.8337
A21: Target EV / EBITDA | B21: x | N21: =Assumptions!B47 -> 32 | O21: =Assumptions!C47 -> 29 | P21: =Assumptions!D47 -> 27 | Q21: =Assumptions!E47 -> 25
A22: EV / EBITDA implied value / share | B22: ₹ / share | N22: =(N15*N21+N10-N11)/N8 -> 7136.8341 | O22: =(O15*O21+O10-O11)/O8 -> 8080.0544 | P22: =(P15*P21+P10-P11)/P8 -> 8931.5251 | Q22: =(Q15*Q21+Q10-Q11)/Q8 -> 9768.759
A23: FCFF | B23: ₹m | N23: ='Annual P&L'!M133 -> 15231.123 | O23: ='Annual P&L'!N133 -> 27680.849 | P23: ='Annual P&L'!O133 -> 34417.293 | Q23: ='Annual P&L'!P133 -> 40781.144
A24: WACC | B24: % | N24: =Assumptions!B48 -> 0.1 | O24: =Assumptions!C48 -> 0.102 | P24: =Assumptions!D48 -> 0.103 | Q24: =Assumptions!E48 -> 0.104
A25: Terminal growth | B25: % | N25: =Assumptions!B49 -> 0.055 | O25: =Assumptions!C49 -> 0.055 | P25: =Assumptions!D49 -> 0.055 | Q25: =Assumptions!E49 -> 0.055
A26: DCF enterprise value | B26: ₹m | N26: =SUMPRODUCT(N23:$Q$23,1/(1+N24)^(COLUMN(N23:$Q$23)-COLUMN(N23)+1))+$Q$23*(1+$Q$25)/($Q$24-$Q$25)/(1+$Q$24)^(COLUMN($Q$23)-COLUMN(N23)+1) -> 681506.28 | O26: =SUMPRODUCT(O23:$Q$23,1/(1+O24)^(COLUMN(O23:$Q$23)-COLUMN(O23)+1))+$Q$23*(1+$Q$25)/($Q$24-$Q$25)/(1+$Q$24)^(COLUMN($Q$23)-COLUMN(O23)+1) -> 736474.73 | P26: =SUMPRODUCT(P23:$Q$23,1/(1+P24)^(COLUMN(P23:$Q$23)-COLUMN(P23)+1))+$Q$23*(1+$Q$25)/($Q$24-$Q$25)/(1+$Q$24)^(COLUMN($Q$23)-COLUMN(P23)+1) -> 785130.21 | Q26: =SUMPRODUCT(Q23:$Q$23,1/(1+Q24)^(COLUMN(Q23:$Q$23)-COLUMN(Q23)+1))+$Q$23*(1+$Q$25)/($Q$24-$Q$25)/(1+$Q$24)^(COLUMN($Q$23)-COLUMN(Q23)+1) -> 832268.25
A27: DCF equity value / share | B27: ₹ / share | N27: =(N26+N10-N11)/N8 -> 4520.5153 | O27: =(O26+O10-O11)/O8 -> 4958.6125 | P27: =(P26+P10-P11)/P8 -> 5382.8045 | Q27: =(Q26+Q10-Q11)/Q8 -> 5817.4174
A28: P/E weight | B28: % | N28: =Assumptions!B50 -> 0.4 | O28: =Assumptions!C50 -> 0.4 | P28: =Assumptions!D50 -> 0.4 | Q28: =Assumptions!E50 -> 0.4
A29: EV / EBITDA weight | B29: % | N29: =Assumptions!B51 -> 0.3 | O29: =Assumptions!C51 -> 0.3 | P29: =Assumptions!D51 -> 0.3 | Q29: =Assumptions!E51 -> 0.3
A30: DCF weight | B30: % | N30: =Assumptions!B52 -> 0.3 | O30: =Assumptions!C52 -> 0.3 | P30: =Assumptions!D52 -> 0.3 | Q30: =Assumptions!E52 -> 0.3
A31: Blended target price | B31: ₹ / share | N31: =SUMPRODUCT(N20,N28)+SUMPRODUCT(N22,N29)+SUMPRODUCT(N27,N30) -> 6136.0975 | O31: =SUMPRODUCT(O20,O28)+SUMPRODUCT(O22,O29)+SUMPRODUCT(O27,O30) -> 6932.9135 | P31: =SUMPRODUCT(P20,P28)+SUMPRODUCT(P22,P29)+SUMPRODUCT(P27,P30) -> 7644.9339 | Q31: =SUMPRODUCT(Q20,Q28)+SUMPRODUCT(Q22,Q29)+SUMPRODUCT(Q27,Q30) -> 8322.5864
A32: Upside / (downside) | B32: % | N32: =IFERROR(N31/N7-1,"") -> 0.096808928 | O32: =IFERROR(O31/O7-1,"") -> 0.23923737 | P32: =IFERROR(P31/P7-1,"") -> 0.36650888 | Q32: =IFERROR(Q31/Q7-1,"") -> 0.48763722
A33: Implied rating | B33: text | N33: =IF(N7="","ENTER PRICE",IF(N32>=0.15,"OUTPERFORM",IF(N32>=-0.05,"NEUTRAL","UNDERPERFORM"))) -> NEUTRAL | O33: =IF(O7="","ENTER PRICE",IF(O32>=0.15,"OUTPERFORM",IF(O32>=-0.05,"NEUTRAL","UNDERPERFORM"))) -> OUTPERFORM | P33: =IF(P7="","ENTER PRICE",IF(P32>=0.15,"OUTPERFORM",IF(P32>=-0.05,"NEUTRAL","UNDERPERFORM"))) -> OUTPERFORM | Q33: =IF(Q7="","ENTER PRICE",IF(Q32>=0.15,"OUTPERFORM",IF(Q32>=-0.05,"NEUTRAL","UNDERPERFORM"))) -> OUTPERFORM

Sheet Checks
A1: Model Checks
A2: Accounting, cash, quarterly-to-annual, mix, revenue-driver, M&A, valuation and static circular-reference controls
A5: Check | B5: Status | C5: Calculated | D5: Control | E5: Difference | F5: Tolerance
A6: OVERALL MODEL STATUS | B6: =IF(COUNTIF(B7:B88,"FAIL")=0,"OK","REVIEW") -> OK
A7: FY16A balance sheet | B7: =IF(ABS(E7)<=F7,"OK","FAIL") -> OK | C7: ='Annual P&L'!B62 -> 21065.43 | D7: ='Annual P&L'!B87 -> 21065.43 | E7: =C7-D7 -> 0 | F7: 1
A8: FY16A cash tie | B8: =IF(ABS(E8)<=F8,"OK","FAIL") -> OK | C8: ='Annual P&L'!B130 -> 1401.4 | D8: ='Annual P&L'!B131 -> 1401.4 | E8: =C8-D8 -> 0 | F8: 1
A9: FY17A balance sheet | B9: =IF(ABS(E9)<=F9,"OK","FAIL") -> OK | C9: ='Annual P&L'!C62 -> 23463.73 | D9: ='Annual P&L'!C87 -> 23463.73 | E9: =C9-D9 -> 0 | F9: 1
A10: FY17A cash tie | B10: =IF(ABS(E10)<=F10,"OK","FAIL") -> OK | C10: ='Annual P&L'!C130 -> 1461.38 | D10: ='Annual P&L'!C131 -> 1461.38 | E10: =C10-D10 -> 0 | F10: 1
A11: FY18A balance sheet | B11: =IF(ABS(E11)<=F11,"OK","FAIL") -> OK | C11: ='Annual P&L'!D62 -> 26588.62 | D11: ='Annual P&L'!D87 -> 26588.62 | E11: =C11-D11 -> 0 | F11: 1
A12: FY18A cash tie | B12: =IF(ABS(E12)<=F12,"OK","FAIL") -> OK | C12: ='Annual P&L'!D130 -> 1343.72 | D12: ='Annual P&L'!D131 -> 1343.72 | E12: =C12-D12 -> 0 | F12: 1
A13: FY19A balance sheet | B13: =IF(ABS(E13)<=F13,"OK","FAIL") -> OK | C13: ='Annual P&L'!E62 -> 28555.99 | D13: ='Annual P&L'!E87 -> 28555.99 | E13: =C13-D13 -> 0 | F13: 1
A14: FY19A cash tie | B14: =IF(ABS(E14)<=F14,"OK","FAIL") -> OK | C14: ='Annual P&L'!E130 -> 1739.45 | D14: ='Annual P&L'!E131 -> 1739.45 | E14: =C14-D14 -> 0 | F14: 1
A15: FY20A balance sheet | B15: =IF(ABS(E15)<=F15,"OK","FAIL") -> OK | C15: ='Annual P&L'!F62 -> 30921.69 | D15: ='Annual P&L'!F87 -> 30921.69 | E15: =C15-D15 -> 0 | F15: 1
A16: FY20A cash tie | B16: =IF(ABS(E16)<=F16,"OK","FAIL") -> OK | C16: ='Annual P&L'!F130 -> 1899.99 | D16: ='Annual P&L'!F131 -> 1899.99 | E16: =C16-D16 -> 0 | F16: 1
A17: FY21A balance sheet | B17: =IF(ABS(E17)<=F17,"OK","FAIL") -> OK | C17: ='Annual P&L'!G62 -> 36655.24 | D17: ='Annual P&L'!G87 -> 36655.24 | E17: =C17-D17 -> 0 | F17: 1
A18: FY21A cash tie | B18: =IF(ABS(E18)<=F18,"OK","FAIL") -> OK | C18: ='Annual P&L'!G130 -> 2419.3 | D18: ='Annual P&L'!G131 -> 2419.3 | E18: =C18-D18 -> 0 | F18: 1
A19: FY22A balance sheet | B19: =IF(ABS(E19)<=F19,"OK","FAIL") -> OK | C19: ='Annual P&L'!H62 -> 54191.01 | D19: ='Annual P&L'!H87 -> 54191.01 | E19: =C19-D19 -> 0 | F19: 1
A20: FY22A cash tie | B20: =IF(ABS(E20)<=F20,"OK","FAIL") -> OK | C20: ='Annual P&L'!H130 -> 2977.99 | D20: ='Annual P&L'!H131 -> 2977.99 | E20: =C20-D20 -> 0 | F20: 1
A21: FY23A balance sheet | B21: =IF(ABS(E21)<=F21,"OK","FAIL") -> OK | C21: ='Annual P&L'!I62 -> 66730.8 | D21: ='Annual P&L'!I87 -> 66730.8 | E21: =C21-D21 -> 0 | F21: 1
A22: FY23A cash tie | B22: =IF(ABS(E22)<=F22,"OK","FAIL") -> OK | C22: ='Annual P&L'!I130 -> 4670.12 | D22: ='Annual P&L'!I131 -> 4670.12 | E22: =C22-D22 -> 0 | F22: 1
A23: FY24A balance sheet | B23: =IF(ABS(E23)<=F23,"OK","FAIL") -> OK | C23: ='Annual P&L'!J62 -> 74176.34 | D23: ='Annual P&L'!J87 -> 74176.34 | E23: =C23-D23 -> 0 | F23: 1
A24: FY24A cash tie | B24: =IF(ABS(E24)<=F24,"OK","FAIL") -> OK | C24: ='Annual P&L'!J130 -> 6625.15 | D24: ='Annual P&L'!J131 -> 6625.15 | E24: =C24-D24 -> 0 | F24: 1
A25: FY25A balance sheet | B25: =IF(ABS(E25)<=F25,"OK","FAIL") -> OK | C25: ='Annual P&L'!K62 -> 87366.02 | D25: ='Annual P&L'!K87 -> 87366.02 | E25: =C25-D25 -> 0 | F25: 1
A26: FY25A cash tie | B26: =IF(ABS(E26)<=F26,"OK","FAIL") -> OK | C26: ='Annual P&L'!K130 -> 6744.06 | D26: ='Annual P&L'!K131 -> 6744.06 | E26: =C26-D26 -> 0 | F26: 1
A27: FY26A balance sheet | B27: =IF(ABS(E27)<=F27,"OK","FAIL") -> OK | C27: ='Annual P&L'!L62 -> 113765.44 | D27: ='Annual P&L'!L87 -> 113765.44 | E27: =C27-D27 -> 0 | F27: 1
A28: FY26A cash tie | B28: =IF(ABS(E28)<=F28,"OK","FAIL") -> OK | C28: ='Annual P&L'!L130 -> 10749.15 | D28: ='Annual P&L'!L131 -> 10749.15 | E28: =C28-D28 -> 0 | F28: 1
A29: FY27E balance sheet | B29: =IF(ABS(E29)<=F29,"OK","FAIL") -> OK | C29: ='Annual P&L'!M62 -> 138755.11 | D29: ='Annual P&L'!M87 -> 138755.11 | E29: =C29-D29 -> 0 | F29: 1
A30: FY27E cash tie | B30: =IF(ABS(E30)<=F30,"OK","FAIL") -> OK | C30: ='Annual P&L'!M130 -> 14138.685 | D30: ='Annual P&L'!M131 -> 14138.685 | E30: =C30-D30 -> 0 | F30: 1
A31: FY28E balance sheet | B31: =IF(ABS(E31)<=F31,"OK","FAIL") -> OK | C31: ='Annual P&L'!N62 -> 165338.01 | D31: ='Annual P&L'!N87 -> 165338.01 | E31: =C31-D31 -> 0 | F31: 1
A32: FY28E cash tie | B32: =IF(ABS(E32)<=F32,"OK","FAIL") -> OK | C32: ='Annual P&L'!N130 -> 26234.741 | D32: ='Annual P&L'!N131 -> 26234.741 | E32: =C32-D32 -> 0 | F32: 1
A33: FY29E balance sheet | B33: =IF(ABS(E33)<=F33,"OK","FAIL") -> OK | C33: ='Annual P&L'!O62 -> 193744.7 | D33: ='Annual P&L'!O87 -> 193744.7 | E33: =C33-D33 -> 0 | F33: 1
A34: FY29E cash tie | B34: =IF(ABS(E34)<=F34,"OK","FAIL") -> OK | C34: ='Annual P&L'!O130 -> 42898.03 | D34: ='Annual P&L'!O131 -> 42898.03 | E34: =C34-D34 -> 0 | F34: 1
A35: FY30E balance sheet | B35: =IF(ABS(E35)<=F35,"OK","FAIL") -> OK | C35: ='Annual P&L'!P62 -> 226621.56 | D35: ='Annual P&L'!P87 -> 226621.56 | E35: =C35-D35 -> 0 | F35: 1
A36: FY30E cash tie | B36: =IF(ABS(E36)<=F36,"OK","FAIL") -> OK | C36: ='Annual P&L'!P130 -> 62560.402 | D36: ='Annual P&L'!P131 -> 62560.402 | E36: =C36-D36 -> 0 | F36: 1
A37: FY16 quarterly revenue vs audited annual | B37: =IF(ABS(E37)<=F37,"OK","FAIL") -> OK | C37: =SUM('Quarterly P&L'!B7:E7) -> 23123.31 | D37: ='Annual P&L'!B5 -> 23123.31 | E37: =C37-D37 -> 0 | F37: 1
A38: FY16 quarterly PAT vs audited annual | B38: =IF(ABS(E38)<=F38,"OK","FAIL") -> OK | C38: =SUM('Quarterly P&L'!B27:E27) -> 2973.61 | D38: ='Annual P&L'!B25 -> 2973.61 | E38: =C38-D38 -> 0 | F38: 1
A39: FY17 quarterly revenue vs audited annual | B39: =IF(ABS(E39)<=F39,"OK","FAIL") -> OK | C39: =SUM('Quarterly P&L'!F7:I7) -> 28784.39 | D39: ='Annual P&L'!C5 -> 28784.39 | E39: =C39-D39 -> 0 | F39: 1
A40: FY17 quarterly PAT vs audited annual | B40: =IF(ABS(E40)<=F40,"OK","FAIL") -> OK | C40: =SUM('Quarterly P&L'!F27:I27) -> 3014.65 | D40: ='Annual P&L'!C25 -> 3014.65 | E40: =C40-D40 -> 0 | F40: 1
A41: FY18 quarterly revenue vs audited annual | B41: =IF(ABS(E41)<=F41,"OK","FAIL") -> OK | C41: =SUM('Quarterly P&L'!J7:M7) -> 30337.03 | D41: ='Annual P&L'!D5 -> 30337.03 | E41: =C41-D41 -> 0 | F41: 1
A42: FY18 quarterly PAT vs audited annual | B42: =IF(ABS(E42)<=F42,"OK","FAIL") -> OK | C42: =SUM('Quarterly P&L'!J27:M27) -> 3230.88 | D42: ='Annual P&L'!D25 -> 3230.88 | E42: =C42-D42 -> 0 | F42: 1
A43: FY19 quarterly revenue vs audited annual | B43: =IF(ABS(E43)<=F43,"OK","FAIL") -> OK | C43: =SUM('Quarterly P&L'!N7:Q7) -> 33659.41 | D43: ='Annual P&L'!E5 -> 33659.41 | E43: =C43-D43 -> 0 | F43: 1
A44: FY19 quarterly PAT vs audited annual | B44: =IF(ABS(E44)<=F44,"OK","FAIL") -> OK | C44: =SUM('Quarterly P&L'!N27:Q27) -> 3516.79 | D44: ='Annual P&L'!E25 -> 3516.79 | E44: =C44-D44 -> 0 | F44: 1
A45: FY20 quarterly revenue vs audited annual | B45: =IF(ABS(E45)<=F45,"OK","FAIL") -> OK | C45: =SUM('Quarterly P&L'!R7:U7) -> 35658.08 | D45: ='Annual P&L'!F5 -> 35658.08 | E45: =C45-D45 -> 0 | F45: 1
A46: FY20 quarterly PAT vs audited annual | B46: =IF(ABS(E46)<=F46,"OK","FAIL") -> OK | C46: =SUM('Quarterly P&L'!R27:U27) -> 3402.89 | D46: ='Annual P&L'!F25 -> 3402.89 | E46: =C46-D46 -> 0 | F46: 1
A47: FY21 quarterly revenue vs audited annual | B47: =IF(ABS(E47)<=F47,"OK","FAIL") -> OK | C47: =SUM('Quarterly P&L'!V7:Y7) -> 41878.88 | D47: ='Annual P&L'!G5 -> 41878.88 | E47: =C47-D47 -> 0 | F47: 1
A48: FY21 quarterly PAT vs audited annual | B48: =IF(ABS(E48)<=F48,"OK","FAIL") -> OK | C48: =SUM('Quarterly P&L'!V27:Y27) -> 4506.77 | D48: ='Annual P&L'!G25 -> 4506.77 | E48: =C48-D48 -> 0 | F48: 1
A49: FY22 quarterly revenue vs audited annual | B49: =IF(ABS(E49)<=F49,"OK","FAIL") -> OK | C49: =SUM('Quarterly P&L'!Z7:AC7) -> 57107.461 | D49: ='Annual P&L'!H5 -> 57107.46 | E49: =C49-D49 -> 0.0011 | F49: 1
A50: FY22 quarterly PAT vs audited annual | B50: =IF(ABS(E50)<=F50,"OK","FAIL") -> OK | C50: =SUM('Quarterly P&L'!Z27:AC27) -> 6903.861 | D50: ='Annual P&L'!H25 -> 6903.86 | E50: =C50-D50 -> 0.001 | F50: 1
A51: FY23 quarterly revenue vs audited annual | B51: =IF(ABS(E51)<=F51,"OK","FAIL") -> OK | C51: =SUM('Quarterly P&L'!AD7:AG7) -> 83505.92 | D51: ='Annual P&L'!I5 -> 83505.92 | E51: =C51-D51 -> 0 | F51: 1
A52: FY23 quarterly PAT vs audited annual | B52: =IF(ABS(E52)<=F52,"OK","FAIL") -> OK | C52: =SUM('Quarterly P&L'!AD27:AG27) -> 9210.93 | D52: ='Annual P&L'!I25 -> 9210.93 | E52: =C52-D52 -> 0 | F52: 1
A53: FY24 quarterly revenue vs audited annual | B53: =IF(ABS(E53)<=F53,"OK","FAIL") -> OK | C53: =SUM('Quarterly P&L'!AH7:AK7) -> 98215.87 | D53: ='Annual P&L'!J5 -> 98215.87 | E53: =C53-D53 -> 0 | F53: 1
A54: FY24 quarterly PAT vs audited annual | B54: =IF(ABS(E54)<=F54,"OK","FAIL") -> OK | C54: =SUM('Quarterly P&L'!AH27:AK27) -> 10934.92 | D54: ='Annual P&L'!J25 -> 10934.91 | E54: =C54-D54 -> 0.01 | F54: 1
A55: FY25 quarterly revenue vs audited annual | B55: =IF(ABS(E55)<=F55,"OK","FAIL") -> OK | C55: =SUM('Quarterly P&L'!AL7:AO7) -> 119387.1 | D55: ='Annual P&L'!K5 -> 119387.17 | E55: =C55-D55 -> -0.07 | F55: 1
A56: FY25 quarterly PAT vs audited annual | B56: =IF(ABS(E56)<=F56,"OK","FAIL") -> OK | C56: =SUM('Quarterly P&L'!AL27:AO27) -> 14001.7 | D56: ='Annual P&L'!K25 -> 14001.61 | E56: =C56-D56 -> 0.09 | F56: 1
A57: FY26 quarterly revenue vs audited annual | B57: =IF(ABS(E57)<=F57,"OK","FAIL") -> OK | C57: =SUM('Quarterly P&L'!AP7:AS7) -> 147484.6 | D57: ='Annual P&L'!L5 -> 147484.49 | E57: =C57-D57 -> 0.11 | F57: 1
A58: FY26 quarterly PAT vs audited annual | B58: =IF(ABS(E58)<=F58,"OK","FAIL") -> OK | C58: =SUM('Quarterly P&L'!AP27:AS27) -> 18651.2 | D58: ='Annual P&L'!L25 -> 18651.2 | E58: =C58-D58 -> 0 | F58: 1
A59: Q1 FY27 revenue spot check | B59: =IF(ABS(E59)<=F59,"OK","FAIL") -> OK | C59: ='Quarterly P&L'!AT7 -> 43032.3 | D59: =43032.3 -> 43032.3 | E59: =C59-D59 -> 0 | F59: 0.1
A60: Q1 FY27 PBT spot check | B60: =IF(ABS(E60)<=F60,"OK","FAIL") -> OK | C60: ='Quarterly P&L'!AT23 -> 6231 | D60: =6231 -> 6231 | E60: =C60-D60 -> 0 | F60: 0.1
A61: Q1 FY27 PAT spot check | B61: =IF(ABS(E61)<=F61,"OK","FAIL") -> OK | C61: ='Quarterly P&L'!AT27 -> 4830.4 | D61: =4830.4 -> 4830.4 | E61: =C61-D61 -> 0 | F61: 0.1
A62: FY27E revenue-driver tie | B62: =IF(ABS(E62)<=F62,"OK","FAIL") -> OK | C62: ='Bookings & Revenue'!M27 -> 181518.89 | D62: ='Annual P&L'!M5 -> 181518.89 | E62: =C62-D62 -> 0 | F62: 0.1
A63: FY27E industry mix | B63: =IF(ABS(E63)<=F63,"OK","FAIL") -> OK | C63: ='Industry Mix'!N13 -> 1 | D63: =1 -> 1 | E63: =C63-D63 -> 0 | F63: 0.001
A64: FY27E geography mix | B64: =IF(ABS(E64)<=F64,"OK","FAIL") -> OK | C64: =Geography!N15 -> 1 | D64: =1 -> 1 | E64: =C64-D64 -> 0 | F64: 0.001
A65: FY27E non-negative cash | B65: =IF(ABS(E65)<=F65,"OK","FAIL") -> OK | C65: =MIN(0,'Annual P&L'!M130) -> 0 | D65: =0 -> 0 | E65: =C65-D65 -> 0 | F65: 0.1
A66: FY27E valuation weights | B66: =IF(ABS(E66)<=F66,"OK","FAIL") -> OK | C66: =SUM(Valuation!N28:N30) -> 1 | D66: =1 -> 1 | E66: =C66-D66 -> 0 | F66: 0.001
A67: FY27E Nagarro funding | B67: =IF(ABS(E67)<=F67,"OK","FAIL") -> OK | C67: ='Nagarro Scenario'!C17 -> 0 | D67: =0 -> 0 | E67: =C67-D67 -> 0 | F67: 1
A68: FY28E revenue-driver tie | B68: =IF(ABS(E68)<=F68,"OK","FAIL") -> OK | C68: ='Bookings & Revenue'!N27 -> 216842.09 | D68: ='Annual P&L'!N5 -> 216842.09 | E68: =C68-D68 -> 0 | F68: 0.1
A69: FY28E industry mix | B69: =IF(ABS(E69)<=F69,"OK","FAIL") -> OK | C69: ='Industry Mix'!O13 -> 1 | D69: =1 -> 1 | E69: =C69-D69 -> 0 | F69: 0.001
A70: FY28E geography mix | B70: =IF(ABS(E70)<=F70,"OK","FAIL") -> OK | C70: =Geography!O15 -> 1 | D70: =1 -> 1 | E70: =C70-D70 -> 0 | F70: 0.001
A71: FY28E non-negative cash | B71: =IF(ABS(E71)<=F71,"OK","FAIL") -> OK | C71: =MIN(0,'Annual P&L'!N130) -> 0 | D71: =0 -> 0 | E71: =C71-D71 -> 0 | F71: 0.1
A72: FY28E valuation weights | B72: =IF(ABS(E72)<=F72,"OK","FAIL") -> OK | C72: =SUM(Valuation!O28:O30) -> 1 | D72: =1 -> 1 | E72: =C72-D72 -> 0 | F72: 0.001
A73: FY28E Nagarro funding | B73: =IF(ABS(E73)<=F73,"OK","FAIL") -> OK | C73: ='Nagarro Scenario'!D17 -> 0 | D73: =0 -> 0 | E73: =C73-D73 -> 0 | F73: 1
A74: FY29E revenue-driver tie | B74: =IF(ABS(E74)<=F74,"OK","FAIL") -> OK | C74: ='Bookings & Revenue'!O27 -> 247270.92 | D74: ='Annual P&L'!O5 -> 247270.92 | E74: =C74-D74 -> 0 | F74: 0.1
A75: FY29E industry mix | B75: =IF(ABS(E75)<=F75,"OK","FAIL") -> OK | C75: ='Industry Mix'!P13 -> 1 | D75: =1 -> 1 | E75: =C75-D75 -> 0 | F75: 0.001
A76: FY29E geography mix | B76: =IF(ABS(E76)<=F76,"OK","FAIL") -> OK | C76: =Geography!P15 -> 1 | D76: =1 -> 1 | E76: =C76-D76 -> 0 | F76: 0.001
A77: FY29E non-negative cash | B77: =IF(ABS(E77)<=F77,"OK","FAIL") -> OK | C77: =MIN(0,'Annual P&L'!O130) -> 0 | D77: =0 -> 0 | E77: =C77-D77 -> 0 | F77: 0.1
A78: FY29E valuation weights | B78: =IF(ABS(E78)<=F78,"OK","FAIL") -> OK | C78: =SUM(Valuation!P28:P30) -> 1 | D78: =1 -> 1 | E78: =C78-D78 -> 0 | F78: 0.001
A79: FY29E Nagarro funding | B79: =IF(ABS(E79)<=F79,"OK","FAIL") -> OK | C79: ='Nagarro Scenario'!E17 -> 0 | D79: =0 -> 0 | E79: =C79-D79 -> 0 | F79: 1
A80: FY30E revenue-driver tie | B80: =IF(ABS(E80)<=F80,"OK","FAIL") -> OK | C80: ='Bookings & Revenue'!P27 -> 281990.34 | D80: ='Annual P&L'!P5 -> 281990.34 | E80: =C80-D80 -> 0 | F80: 0.1
A81: FY30E industry mix | B81: =IF(ABS(E81)<=F81,"OK","FAIL") -> OK | C81: ='Industry Mix'!Q13 -> 1 | D81: =1 -> 1 | E81: =C81-D81 -> 0 | F81: 0.001
A82: FY30E geography mix | B82: =IF(ABS(E82)<=F82,"OK","FAIL") -> OK | C82: =Geography!Q15 -> 1 | D82: =1 -> 1 | E82: =C82-D82 -> 0 | F82: 0.001
A83: FY30E non-negative cash | B83: =IF(ABS(E83)<=F83,"OK","FAIL") -> OK | C83: =MIN(0,'Annual P&L'!P130) -> 0 | D83: =0 -> 0 | E83: =C83-D83 -> 0 | F83: 0.1
A84: FY30E valuation weights | B84: =IF(ABS(E84)<=F84,"OK","FAIL") -> OK | C84: =SUM(Valuation!Q28:Q30) -> 1 | D84: =1 -> 1 | E84: =C84-D84 -> 0 | F84: 0.001
A85: FY30E Nagarro funding | B85: =IF(ABS(E85)<=F85,"OK","FAIL") -> OK | C85: ='Nagarro Scenario'!F17 -> 0 | D85: =0 -> 0 | E85: =C85-D85 -> 0 | F85: 1
A86: Static circular-reference count | B86: =IF(C86=0,"OK","FAIL") -> OK | C86: 0 | D86: 0 | E86: =C86-D86 -> 0 | F86: 0
A87: INDIRECT / OFFSET formula count | B87: =IF(C87=0,"OK","FAIL") -> OK | C87: 0 | D87: 0 | E87: =C87-D87 -> 0 | F87: 0
A88: Formula error token count | B88: =IF(C88=0,"OK","FAIL") -> OK | C88: 0 | D88: 0 | E88: =C88-D88 -> 0 | F88: 0
