Workbook

Sheet Cover
A1: Tata Consultancy Services — Fresh Integrated Financial Model | B1: Tata Consultancy Services — Fresh Integrated Financial Model | C1: Tata Consultancy Services — Fresh Integrated Financial Model | D1: Tata Consultancy Services — Fresh Integrated Financial Model | E1: Tata Consultancy Services — Fresh Integrated Financial Model | F1: Tata Consultancy Services — Fresh Integrated Financial Model | G1: Tata Consultancy Services — Fresh Integrated Financial Model | H1: Tata Consultancy Services — Fresh Integrated Financial Model | I1: Tata Consultancy Services — Fresh Integrated Financial Model | J1: Tata Consultancy Services — Fresh Integrated Financial Model | K1: Tata Consultancy Services — Fresh Integrated Financial Model | L1: Tata Consultancy Services — Fresh Integrated Financial Model | M1: Tata Consultancy Services — Fresh Integrated Financial Model | N1: Tata Consultancy Services — Fresh Integrated Financial Model | O1: Tata Consultancy Services — Fresh Integrated Financial Model | P1: Tata Consultancy Services — Fresh Integrated Financial Model
A2: Tata Consultancy Services — Fresh Integrated Financial Model | B2: Tata Consultancy Services — Fresh Integrated Financial Model | C2: Tata Consultancy Services — Fresh Integrated Financial Model | D2: Tata Consultancy Services — Fresh Integrated Financial Model | E2: Tata Consultancy Services — Fresh Integrated Financial Model | F2: Tata Consultancy Services — Fresh Integrated Financial Model | G2: Tata Consultancy Services — Fresh Integrated Financial Model | H2: Tata Consultancy Services — Fresh Integrated Financial Model | I2: Tata Consultancy Services — Fresh Integrated Financial Model | J2: Tata Consultancy Services — Fresh Integrated Financial Model | K2: Tata Consultancy Services — Fresh Integrated Financial Model | L2: Tata Consultancy Services — Fresh Integrated Financial Model | M2: Tata Consultancy Services — Fresh Integrated Financial Model | N2: Tata Consultancy Services — Fresh Integrated Financial Model | O2: Tata Consultancy Services — Fresh Integrated Financial Model | P2: Tata Consultancy Services — Fresh Integrated Financial Model
A3: FY16A–FY26A historicals | FY27E–FY30E forecasts | INR million unless stated otherwise | B3: FY16A–FY26A historicals | FY27E–FY30E forecasts | INR million unless stated otherwise | C3: FY16A–FY26A historicals | FY27E–FY30E forecasts | INR million unless stated otherwise | D3: FY16A–FY26A historicals | FY27E–FY30E forecasts | INR million unless stated otherwise | E3: FY16A–FY26A historicals | FY27E–FY30E forecasts | INR million unless stated otherwise | F3: FY16A–FY26A historicals | FY27E–FY30E forecasts | INR million unless stated otherwise | G3: FY16A–FY26A historicals | FY27E–FY30E forecasts | INR million unless stated otherwise | H3: FY16A–FY26A historicals | FY27E–FY30E forecasts | INR million unless stated otherwise | I3: FY16A–FY26A historicals | FY27E–FY30E forecasts | INR million unless stated otherwise | J3: FY16A–FY26A historicals | FY27E–FY30E forecasts | INR million unless stated otherwise | K3: FY16A–FY26A historicals | FY27E–FY30E forecasts | INR million unless stated otherwise | L3: FY16A–FY26A historicals | FY27E–FY30E forecasts | INR million unless stated otherwise | M3: FY16A–FY26A historicals | FY27E–FY30E forecasts | INR million unless stated otherwise | N3: FY16A–FY26A historicals | FY27E–FY30E forecasts | INR million unless stated otherwise | O3: FY16A–FY26A historicals | FY27E–FY30E forecasts | INR million unless stated otherwise | P3: FY16A–FY26A historicals | FY27E–FY30E forecasts | INR million unless stated otherwise
A5: Built from scratch. No formulas, assumptions or outputs have been imported from the discarded TCS model.
A7: Model architecture | B7: Model architecture | C7: Model architecture | D7: Model architecture | E7: Model architecture | F7: Model architecture | G7: Model architecture | H7: Model architecture | I7: Model architecture | J7: Model architecture | K7: Model architecture | L7: Model architecture | M7: Model architecture | N7: Model architecture | O7: Model architecture | P7: Model architecture
A9: Tab | B9: Purpose
A10: Summary | B10: Executive financial, operating and valuation dashboard
A11: Sources | B11: Official reports and source notes
A12: Assumptions | B12: Editable forecast drivers and scenario assumptions
A13: Raw Financials | B13: Reported source layer; reported figures override ex-adjusted cells
A14: Quarterly P&L | B14: Quarterly profit and loss only; FY16–FY30
A15: Annual P&L | B15: Annual income statement, margins, EPS and dividends
A16: Annual Balance Sheet | B16: Detailed current/non-current assets and liabilities
A17: Annual Cash Flow | B17: Line-by-line cash flow with reported controls and cash anchoring
A18: Segment Revenue | B18: Geography and industry mix, absolutes and growth
A19: Currency Revenue | B19: USD/GBP/EUR/Other mix, absolute revenue and growth
A20: Client Data | B20: Client revenue bands and related operating metrics
... A24: Checks | B24: Accounting, cash, currency and formula integrity checks
A27: Formatting legend | B27: Formatting legend | C27: Formatting legend | D27: Formatting legend | E27: Formatting legend | F27: Formatting legend | G27: Formatting legend | H27: Formatting legend | I27: Formatting legend | J27: Formatting legend | K27: Formatting legend | L27: Formatting legend | M27: Formatting legend | N27: Formatting legend | O27: Formatting legend | P27: Formatting legend
A29: Blue font / yellow fill | B29: Editable assumption or input
A30: Green font | B30: Formula linking another tab
A31: Black font | B31: Formula calculated on the same tab
A32: Light green shading | B32: Forecast period
A33: Blue font in Raw Financials | B33: Reported source data

Sheet Summary
A1: TCS Financial Model Summary | B1: TCS Financial Model Summary | C1: TCS Financial Model Summary | D1: TCS Financial Model Summary | E1: TCS Financial Model Summary | F1: TCS Financial Model Summary | G1: TCS Financial Model Summary | H1: TCS Financial Model Summary | I1: TCS Financial Model Summary | J1: TCS Financial Model Summary | K1: TCS Financial Model Summary | L1: TCS Financial Model Summary | M1: TCS Financial Model Summary | N1: TCS Financial Model Summary
A2: TCS Financial Model Summary | B2: TCS Financial Model Summary | C2: TCS Financial Model Summary | D2: TCS Financial Model Summary | E2: TCS Financial Model Summary | F2: TCS Financial Model Summary | G2: TCS Financial Model Summary | H2: TCS Financial Model Summary | I2: TCS Financial Model Summary | J2: TCS Financial Model Summary | K2: TCS Financial Model Summary | L2: TCS Financial Model Summary | M2: TCS Financial Model Summary | N2: TCS Financial Model Summary
A3: Reported historicals, operating drivers, currency analysis, valuation and checks. | B3: Reported historicals, operating drivers, currency analysis, valuation and checks. | C3: Reported historicals, operating drivers, currency analysis, valuation and checks. | D3: Reported historicals, operating drivers, currency analysis, valuation and checks. | E3: Reported historicals, operating drivers, currency analysis, valuation and checks. | F3: Reported historicals, operating drivers, currency analysis, valuation and checks. | G3: Reported historicals, operating drivers, currency analysis, valuation and checks. | H3: Reported historicals, operating drivers, currency analysis, valuation and checks. | I3: Reported historicals, operating drivers, currency analysis, valuation and checks. | J3: Reported historicals, operating drivers, currency analysis, valuation and checks. | K3: Reported historicals, operating drivers, currency analysis, valuation and checks. | L3: Reported historicals, operating drivers, currency analysis, valuation and checks. | M3: Reported historicals, operating drivers, currency analysis, valuation and checks. | N3: Reported historicals, operating drivers, currency analysis, valuation and checks.
A5: Financial overview | B5: Financial overview | C5: Financial overview | D5: Financial overview | E5: Financial overview | F5: Financial overview | G5: Financial overview | H5: Financial overview | I5: Financial overview | J5: Financial overview | K5: Financial overview | L5: Financial overview | M5: Financial overview | N5: Financial overview
B6: FY22 | C6: FY23 | D6: FY24 | E6: FY25 | F6: FY26 | G6: FY27E | H6: FY28E | I6: FY29E | J6: FY30E
A7: Revenue | B7: ='Annual P&L'!$H$6 -> 1917540 | C7: ='Annual P&L'!$I$6 -> 2254580 | D7: ='Annual P&L'!$J$6 -> 2408930 | E7: ='Annual P&L'!$K$6 -> 2553240 | F7: ='Annual P&L'!$L$6 -> 2670210 | G7: ='Annual P&L'!$M$6 -> 2755881.9 | H7: ='Annual P&L'!$N$6 -> 2901779.8 | I7: ='Annual P&L'!$O$6 -> 3046126 | J7: ='Annual P&L'!$P$6 -> 3195140.9
A8: Revenue growth | B8: ='Annual P&L'!$H$7 -> 0.16797115 | C8: ='Annual P&L'!$I$7 -> 0.17576687 | D8: ='Annual P&L'!$J$7 -> 0.068460645 | E8: ='Annual P&L'!$K$7 -> 0.059906265 | F8: ='Annual P&L'!$L$7 -> 0.04581238 | G8: ='Annual P&L'!$M$7 -> 0.032084342 | H8: ='Annual P&L'!$N$7 -> 0.052940551 | I8: ='Annual P&L'!$O$7 -> 0.049744003 | J8: ='Annual P&L'!$P$7 -> 0.048919495
A9: Operating income | B9: ='Annual P&L'!$H$13 -> 484530 | C9: ='Annual P&L'!$I$13 -> 542370 | D9: ='Annual P&L'!$J$13 -> 583530 | E9: ='Annual P&L'!$K$13 -> 621650 | F9: ='Annual P&L'!$L$13 -> 623120 | G9: ='Annual P&L'!$M$13 -> 666923.43 | H9: ='Annual P&L'!$N$13 -> 710936.06 | I9: ='Annual P&L'!$O$13 -> 755439.24 | J9: ='Annual P&L'!$P$13 -> 798785.23
A10: Operating margin | B10: ='Annual P&L'!$H$14 -> 0.25268313 | C10: ='Annual P&L'!$I$14 -> 0.24056365 | D10: ='Annual P&L'!$J$14 -> 0.24223618 | E10: ='Annual P&L'!$K$14 -> 0.24347496 | F10: ='Annual P&L'!$L$14 -> 0.23335992 | G10: ='Annual P&L'!$M$14 -> 0.242 | H10: ='Annual P&L'!$N$14 -> 0.245 | I10: ='Annual P&L'!$O$14 -> 0.248 | J10: ='Annual P&L'!$P$14 -> 0.25
A11: Net income attributable | B11: ='Annual P&L'!$H$22 -> 383270 | C11: ='Annual P&L'!$I$22 -> 421470 | D11: ='Annual P&L'!$J$22 -> 459080 | E11: ='Annual P&L'!$K$22 -> 485530 | F11: ='Annual P&L'!$L$22 -> 492100 | G11: ='Annual P&L'!$M$22 -> 529993.58 | H11: ='Annual P&L'!$N$22 -> 564591.4 | I11: ='Annual P&L'!$O$22 -> 599541.41 | J11: ='Annual P&L'!$P$22 -> 633671.21
A12: Net margin | B12: ='Annual P&L'!$H$23 -> 0.19987588 | C12: ='Annual P&L'!$I$23 -> 0.18693947 | D12: ='Annual P&L'!$J$23 -> 0.19057424 | E12: ='Annual P&L'!$K$23 -> 0.1901623 | F12: ='Annual P&L'!$L$23 -> 0.18429262 | G12: ='Annual P&L'!$M$23 -> 0.1923136 | H12: ='Annual P&L'!$N$23 -> 0.19456727 | I12: ='Annual P&L'!$O$23 -> 0.19682095 | J12: ='Annual P&L'!$P$23 -> 0.1983234
A13: EPS — basic | B13: ='Annual P&L'!$H$24 -> 103.62 | C13: ='Annual P&L'!$I$24 -> 115.19 | D13: ='Annual P&L'!$J$24 -> 125.88 | E13: ='Annual P&L'!$K$24 -> 134.19 | F13: ='Annual P&L'!$L$24 -> 136.01 | G13: ='Annual P&L'!$M$24 -> 146.48445 | H13: ='Annual P&L'!$N$24 -> 156.04692 | I13: ='Annual P&L'!$O$24 -> 165.70672 | J13: ='Annual P&L'!$P$24 -> 175.13982
A14: DPS | B14: ='Annual P&L'!$H$27 -> 43 | C14: ='Annual P&L'!$I$27 -> 115 | D14: ='Annual P&L'!$J$27 -> 73 | E14: ='Annual P&L'!$K$27 -> 126 | F14: ='Annual P&L'!$L$27 -> 110 | G14: ='Annual P&L'!$M$27 -> 117.18756 | H14: ='Annual P&L'!$N$27 -> 124.83753 | I14: ='Annual P&L'!$O$27 -> 132.56537 | J14: ='Annual P&L'!$P$27 -> 140.11186
A15: CFO | B15: ='Annual P&L'!$H$111 -> 399490 | C15: ='Annual P&L'!$I$111 -> 419650 | D15: ='Annual P&L'!$J$111 -> 443380 | E15: ='Annual P&L'!$K$111 -> 489080 | F15: ='Annual P&L'!$L$111 -> 520940 | G15: ='Annual P&L'!$M$111 -> 596746.33 | H15: ='Annual P&L'!$N$111 -> 628674.18 | I15: ='Annual P&L'!$O$111 -> 671708.65 | J15: ='Annual P&L'!$P$111 -> 703967.19
A16: Free cash flow | B16: ='Annual P&L'!$H$141 -> 369540 | C16: ='Annual P&L'!$I$141 -> 388650 | D16: ='Annual P&L'!$J$141 -> 416640 | E16: ='Annual P&L'!$K$141 -> 449710 | F16: ='Annual P&L'!$L$141 -> 479480 | G16: ='Annual P&L'!$M$141 -> 552652.22 | H16: ='Annual P&L'!$N$141 -> 580794.82 | I16: ='Annual P&L'!$O$141 -> 619924.51 | J16: ='Annual P&L'!$P$141 -> 649649.8
A17: Closing cash | B17: ='Annual P&L'!$H$138 -> 124880 | C17: ='Annual P&L'!$I$138 -> 71230 | D17: ='Annual P&L'!$J$138 -> 90160 | E17: ='Annual P&L'!$K$138 -> 83420 | F17: ='Annual P&L'!$L$138 -> 64170 | G17: ='Annual P&L'!$M$138 -> 174267.74 | H17: ='Annual P&L'!$N$138 -> 284557.44 | I17: ='Annual P&L'!$O$138 -> 405688.2 | J17: ='Annual P&L'!$P$138 -> 528994.54
A20: Operating and demand indicators | B20: Operating and demand indicators | C20: Operating and demand indicators | D20: Operating and demand indicators | E20: Operating and demand indicators | F20: Operating and demand indicators | G20: Operating and demand indicators | H20: Operating and demand indicators | I20: Operating and demand indicators | J20: Operating and demand indicators | K20: Operating and demand indicators | L20: Operating and demand indicators | M20: Operating and demand indicators | N20: Operating and demand indicators
A21: Headcount | B21: ='Revenue Drivers'!$H$10 -> 592195 | C21: ='Revenue Drivers'!$I$10 -> 614795 | D21: ='Revenue Drivers'!$J$10 -> 601546 | E21: ='Revenue Drivers'!$K$10 -> 607979 | F21: ='Revenue Drivers'!$L$10 -> 584519 | G21: ='Revenue Drivers'!$M$10 -> 593286.78 | H21: ='Revenue Drivers'!$N$10 -> 605152.52 | I21: ='Revenue Drivers'!$O$10 -> 620281.33 | J21: ='Revenue Drivers'!$P$10 -> 635788.37
A22: Attrition | B22: ='Raw Financials'!$H$135 -> 0.174 | C22: ='Raw Financials'!$I$135 -> 0.201 | D22: ='Raw Financials'!$J$135 -> 0.125 | E22: ='Raw Financials'!$K$135 -> 0.133 | F22: ='Raw Financials'!$L$135 -> 0.137 | G22: ="" | H22: ="" | I22: ="" | J22: =""
A23: TCV (USD bn) | B23: ='Revenue Drivers'!$H$25 -> 34.6 | C23: ='Revenue Drivers'!$I$25 -> 34.1 | D23: ='Revenue Drivers'!$J$25 -> 42.7 | E23: ='Revenue Drivers'!$K$25 -> 39.4 | F23: ='Revenue Drivers'!$L$25 -> 40.7 | G23: ='Revenue Drivers'!$M$25 -> 0 | H23: ='Revenue Drivers'!$N$25 -> 0 | I23: ='Revenue Drivers'!$O$25 -> 0 | J23: ='Revenue Drivers'!$P$25 -> 0
A24: AI exit run-rate (USD bn) | B24: ='Revenue Drivers'!$H$19 -> 0 | C24: ='Revenue Drivers'!$I$19 -> 0 | D24: ='Revenue Drivers'!$J$19 -> 0 | E24: ='Revenue Drivers'!$K$19 -> 0 | F24: ='Revenue Drivers'!$L$19 -> 2.3 | G24: ='Revenue Drivers'!$M$19 -> 3.3 | H24: ='Revenue Drivers'!$N$19 -> 4.1 | I24: ='Revenue Drivers'!$O$19 -> 4.9 | J24: ='Revenue Drivers'!$P$19 -> 5.7
A25: AI revenue uplift (INR m) | B25: ='Revenue Drivers'!$H$22 -> 0 | C25: ='Revenue Drivers'!$I$22 -> 0 | D25: ='Revenue Drivers'!$J$22 -> 0 | E25: ='Revenue Drivers'!$K$22 -> 0 | F25: ='Revenue Drivers'!$L$22 -> 0 | G25: ='Revenue Drivers'!$M$22 -> 47000 | H25: ='Revenue Drivers'!$N$22 -> 133000 | I25: ='Revenue Drivers'!$O$22 -> 211200 | J25: ='Revenue Drivers'!$P$22 -> 291000
G28: =G30/F30-1 -> 0.03717843
A29: Valuation snapshot | B29: Valuation snapshot | C29: Valuation snapshot | D29: Valuation snapshot | E29: Valuation snapshot | F29: Valuation snapshot | G29: Valuation snapshot | H29: Valuation snapshot | I29: Valuation snapshot | J29: Valuation snapshot | K29: Valuation snapshot | L29: Valuation snapshot | M29: Valuation snapshot | N29: Valuation snapshot
A30: Share price | B30: =Valuation!$H$6 -> 3739.95 | C30: =Valuation!$I$6 -> 3205.8999 | D30: =Valuation!$J$6 -> 3876.3 | E30: =Valuation!$K$6 -> 3606.1499 | F30: =Valuation!$L$6 -> 2358.8999 | G30: =Valuation!$M$6 -> 2446.6001 | H30: =Valuation!$N$6 -> 2446.6001 | I30: =Valuation!$O$6 -> 2446.6001 | J30: =Valuation!$P$6 -> 2446.6001
A31: P/E | B31: =Valuation!$H$22 -> 36.092935 | C31: =Valuation!$I$22 -> 27.831408 | D31: =Valuation!$J$22 -> 30.793613 | E31: =Valuation!$K$22 -> 26.873462 | F31: =Valuation!$L$22 -> 17.343577 | G31: =Valuation!$M$22 -> 16.702114 | H31: =Valuation!$N$22 -> 15.678619 | I31: =Valuation!$O$22 -> 14.76464 | J31: =Valuation!$P$22 -> 13.96941
A32: EV / EBITDA | B32: =Valuation!$H$23 -> 25.2832 | C32: =Valuation!$I$23 -> 19.100561 | D32: =Valuation!$J$23 -> 21.706509 | E32: =Valuation!$K$23 -> 18.794763 | F32: =Valuation!$L$23 -> 12.182736 | G32: =Valuation!$M$23 -> 11.680838 | H32: =Valuation!$N$23 -> 10.801262 | I32: =Valuation!$O$23 -> 10.00411 | J32: =Valuation!$P$23 -> 9.3030466
A33: P/B | B33: =Valuation!$H$24 -> 15.158447 | C33: =Valuation!$I$24 -> 12.675923 | D33: =Valuation!$J$24 -> 15.263996 | E33: =Valuation!$K$24 -> 13.467276 | F33: =Valuation!$L$24 -> 7.8030887 | G33: =Valuation!$M$24 -> 7.2274822 | H33: =Valuation!$N$24 -> 6.454778 | I33: =Valuation!$O$24 -> 5.8086679 | J33: =Valuation!$P$24 -> 5.2534689
A34: Dividend yield | B34: =Valuation!$H$25 -> 0.01149748 | C34: =Valuation!$I$25 -> 0.035871363 | D34: =Valuation!$J$25 -> 0.018832391 | E34: =Valuation!$K$25 -> 0.034940311 | F34: =Valuation!$L$25 -> 0.046631907 | G34: =Valuation!$M$25 -> 0.047898127 | H34: =Valuation!$N$25 -> 0.051024903 | I34: =Valuation!$O$25 -> 0.054183508 | J34: =Valuation!$P$25 -> 0.057267986
A35: Average implied value | B35: =Valuation!$H$33 -> 0 | C35: =Valuation!$I$33 -> 0 | D35: =Valuation!$J$33 -> 0 | E35: =Valuation!$K$33 -> 0 | F35: =Valuation!$L$33 -> 0 | G35: =Valuation!$M$33 -> 3303.2545 | H35: =Valuation!$N$33 -> 3464.5241 | I35: =Valuation!$O$33 -> 3612.0175 | J35: =Valuation!$P$33 -> 3741.8277
A38: Model integrity | B38: Model integrity | C38: Model integrity | D38: Model integrity | E38: Model integrity | F38: Model integrity | G38: Model integrity | H38: Model integrity | I38: Model integrity | J38: Model integrity | K38: Model integrity | L38: Model integrity | M38: Model integrity | N38: Model integrity
A39: Overall model check | B39: =Checks!$B$8 -> PASS
A42: Period | B42: Revenue | C42: Operating income | D42: Net income
A43: FY22 | B43: ='Annual P&L'!$H$6 -> 1917540 | C43: ='Annual P&L'!$H$13 -> 484530 | D43: ='Annual P&L'!$H$22 -> 383270
A44: FY23 | B44: ='Annual P&L'!$I$6 -> 2254580 | C44: ='Annual P&L'!$I$13 -> 542370 | D44: ='Annual P&L'!$I$22 -> 421470
A45: FY24 | B45: ='Annual P&L'!$J$6 -> 2408930 | C45: ='Annual P&L'!$J$13 -> 583530 | D45: ='Annual P&L'!$J$22 -> 459080
A46: FY25 | B46: ='Annual P&L'!$K$6 -> 2553240 | C46: ='Annual P&L'!$K$13 -> 621650 | D46: ='Annual P&L'!$K$22 -> 485530
A47: FY26 | B47: ='Annual P&L'!$L$6 -> 2670210 | C47: ='Annual P&L'!$L$13 -> 623120 | D47: ='Annual P&L'!$L$22 -> 492100
A48: FY27E | B48: ='Annual P&L'!$M$6 -> 2755881.9 | C48: ='Annual P&L'!$M$13 -> 666923.43 | D48: ='Annual P&L'!$M$22 -> 529993.58
A49: FY28E | B49: ='Annual P&L'!$N$6 -> 2901779.8 | C49: ='Annual P&L'!$N$13 -> 710936.06 | D49: ='Annual P&L'!$N$22 -> 564591.4
A50: FY29E | B50: ='Annual P&L'!$O$6 -> 3046126 | C50: ='Annual P&L'!$O$13 -> 755439.24 | D50: ='Annual P&L'!$O$22 -> 599541.41
A51: FY30E | B51: ='Annual P&L'!$P$6 -> 3195140.9 | C51: ='Annual P&L'!$P$13 -> 798785.23 | D51: ='Annual P&L'!$P$22 -> 633671.21

Sheet Sources
A1: Sources and Model Notes | B1: Sources and Model Notes | C1: Sources and Model Notes | D1: Sources and Model Notes | E1: Sources and Model Notes | F1: Sources and Model Notes | G1: Sources and Model Notes | H1: Sources and Model Notes | I1: Sources and Model Notes | J1: Sources and Model Notes | K1: Sources and Model Notes | L1: Sources and Model Notes
A2: Sources and Model Notes | B2: Sources and Model Notes | C2: Sources and Model Notes | D2: Sources and Model Notes | E2: Sources and Model Notes | F2: Sources and Model Notes | G2: Sources and Model Notes | H2: Sources and Model Notes | I2: Sources and Model Notes | J2: Sources and Model Notes | K2: Sources and Model Notes | L2: Sources and Model Notes
A3: Primary-source hierarchy, accounting basis and forecast treatment | B3: Primary-source hierarchy, accounting basis and forecast treatment | C3: Primary-source hierarchy, accounting basis and forecast treatment | D3: Primary-source hierarchy, accounting basis and forecast treatment | E3: Primary-source hierarchy, accounting basis and forecast treatment | F3: Primary-source hierarchy, accounting basis and forecast treatment | G3: Primary-source hierarchy, accounting basis and forecast treatment | H3: Primary-source hierarchy, accounting basis and forecast treatment | I3: Primary-source hierarchy, accounting basis and forecast treatment | J3: Primary-source hierarchy, accounting basis and forecast treatment | K3: Primary-source hierarchy, accounting basis and forecast treatment | L3: Primary-source hierarchy, accounting basis and forecast treatment
A5: Primary sources | B5: Primary sources | C5: Primary sources | D5: Primary sources | E5: Primary sources | F5: Primary sources | G5: Primary sources | H5: Primary sources | I5: Primary sources | J5: Primary sources | K5: Primary sources | L5: Primary sources
A6: # | B6: Source | C6: URL | D6: Use
A7: 1 | B7: TCS Financial Statements | C7: https://www.tcs.com/investor-relations/financial-statements | D7: Official TCS source
A8: 2 | B8: TCS FY26 Annual Report | C8: https://www.tcs.com/content/dam/tcs/investor-relations/financial-statements/2025-26/ar/annual-report-2025-2026.pdf | D8: Official TCS source
A9: 3 | B9: TCS FY25 Annual Report | C9: https://www.tcs.com/content/dam/tcs/investor-relations/financial-statements/2024-25/ar/annual-report-2024-2025.pdf | D9: Official TCS source
A10: 4 | B10: TCS FY24 Annual Report | C10: https://www.tcs.com/content/dam/tcs/investor-relations/financial-statements/2023-24/ar/annual-report-2023-2024.pdf | D10: Official TCS source
A11: 5 | B11: TCS FY22 Annual Report | C11: https://www.tcs.com/content/dam/tcs/investor-relations/financial-statements/2021-22/ar/annual-report-2021-2022.pdf | D11: Official TCS source
A12: 6 | B12: TCS FY20 Annual Report | C12: https://www.tcs.com/content/dam/tcs/investor-relations/financial-statements/2019-20/ar/annual-report-2019-2020.pdf | D12: Official TCS source
A13: 7 | B13: TCS FY18 Annual Report | C13: https://www.tcs.com/content/dam/tcs/investor-relations/financial-statements/2017-18/ar/annual-report-2017-2018.pdf | D13: Official TCS source
A14: 8 | B14: TCS FY16 Annual Report | C14: https://www.tcs.com/content/dam/tcs/pdf/discover-tcs/investor-relations/key-events/TCS_Annual_Report_2015-2016.pdf | D14: Official TCS source
A15: 9 | B15: TCS Q1 FY27 Results | C15: https://www.tcs.com/who-we-are/newsroom/press-release/tcs-financial-results-q1-fy-2027 | D15: Official TCS source
A18: Model policies | B18: Model policies | C18: Model policies | D18: Model policies | E18: Model policies | F18: Model policies | G18: Model policies | H18: Model policies | I18: Model policies | J18: Model policies | K18: Model policies | L18: Model policies
A19: Topic | B19: Policy
A20: Reported vs adjusted | B20: Historical P&L uses reported figures. Where the official data sheet stores an ex-adjusted cell and the reported figure in the comment, the reported comment value is used.
A21: Cash flow basis | B21: Historical CFO/CFI/CFF controls are taken from consolidated annual cash-flow statements. Detailed working-capital lines are calculated from the balance sheet; a clearly labelled residual captures translation/reclassification differences.
A22: Cash anchoring | B22: Historical closing cash is linked to reported balance-sheet cash. Forecast balance-sheet cash links to the cash-flow roll-forward.
A23: Segment classifications | B23: Industry classifications changed over time. The model does not manufacture a restated series; separate disclosed classification blocks are retained.
A24: AI revenue | B24: TCS discloses annualised AI run-rate, not reported AI revenue. Forecast AI uplift is time-weighted from opening/closing run-rate and shown separately from core billable revenue.
A25: T&M mix | B25: Recent T&M mix is not disclosed. FY26 base and forecast T&M mix are explicit editable assumptions, not historical facts.
A26: Market price | B26: TCS Prices contains the TCS.NS source series. Valuation price assumptions are formula-linked and separately visible.

Sheet Assumptions
A1: Forecast Assumptions | B1: Forecast Assumptions | C1: Forecast Assumptions | D1: Forecast Assumptions | E1: Forecast Assumptions | F1: Forecast Assumptions | G1: Forecast Assumptions | H1: Forecast Assumptions | I1: Forecast Assumptions | J1: Forecast Assumptions | K1: Forecast Assumptions | L1: Forecast Assumptions | M1: Forecast Assumptions | N1: Forecast Assumptions | O1: Forecast Assumptions | P1: Forecast Assumptions
A2: Forecast Assumptions | B2: Forecast Assumptions | C2: Forecast Assumptions | D2: Forecast Assumptions | E2: Forecast Assumptions | F2: Forecast Assumptions | G2: Forecast Assumptions | H2: Forecast Assumptions | I2: Forecast Assumptions | J2: Forecast Assumptions | K2: Forecast Assumptions | L2: Forecast Assumptions | M2: Forecast Assumptions | N2: Forecast Assumptions | O2: Forecast Assumptions | P2: Forecast Assumptions
A3: Blue-font/yellow-fill cells are editable. Historical metrics are formula-linked and are not forecast inputs. | B3: Blue-font/yellow-fill cells are editable. Historical metrics are formula-linked and are not forecast inputs. | C3: Blue-font/yellow-fill cells are editable. Historical metrics are formula-linked and are not forecast inputs. | D3: Blue-font/yellow-fill cells are editable. Historical metrics are formula-linked and are not forecast inputs. | E3: Blue-font/yellow-fill cells are editable. Historical metrics are formula-linked and are not forecast inputs. | F3: Blue-font/yellow-fill cells are editable. Historical metrics are formula-linked and are not forecast inputs. | G3: Blue-font/yellow-fill cells are editable. Historical metrics are formula-linked and are not forecast inputs. | H3: Blue-font/yellow-fill cells are editable. Historical metrics are formula-linked and are not forecast inputs. | I3: Blue-font/yellow-fill cells are editable. Historical metrics are formula-linked and are not forecast inputs. | J3: Blue-font/yellow-fill cells are editable. Historical metrics are formula-linked and are not forecast inputs. | K3: Blue-font/yellow-fill cells are editable. Historical metrics are formula-linked and are not forecast inputs. | L3: Blue-font/yellow-fill cells are editable. Historical metrics are formula-linked and are not forecast inputs. | M3: Blue-font/yellow-fill cells are editable. Historical metrics are formula-linked and are not forecast inputs. | N3: Blue-font/yellow-fill cells are editable. Historical metrics are formula-linked and are not forecast inputs. | O3: Blue-font/yellow-fill cells are editable. Historical metrics are formula-linked and are not forecast inputs. | P3: Blue-font/yellow-fill cells are editable. Historical metrics are formula-linked and are not forecast inputs.
B5: FY16 | C5: FY17 | D5: FY18 | E5: FY19 | F5: FY20 | G5: FY21 | H5: FY22 | I5: FY23 | J5: FY24 | K5: FY25 | L5: FY26 | M5: FY27E | N5: FY28E | O5: FY29E | P5: FY30E
A7: Revenue and operating drivers | B7: Revenue and operating drivers | C7: Revenue and operating drivers | D7: Revenue and operating drivers | E7: Revenue and operating drivers | F7: Revenue and operating drivers | G7: Revenue and operating drivers | H7: Revenue and operating drivers | I7: Revenue and operating drivers | J7: Revenue and operating drivers | K7: Revenue and operating drivers | L7: Revenue and operating drivers | M7: Revenue and operating drivers | N7: Revenue and operating drivers | O7: Revenue and operating drivers | P7: Revenue and operating drivers
A8: Revenue growth | B8: ="" | C8: =IFERROR(C7/B7-1,"") | D8: =IFERROR(D7/C7-1,"") | E8: =IFERROR(E7/D7-1,"") | F8: =IFERROR(F7/E7-1,"") | G8: =IFERROR(G7/F7-1,"") | H8: =IFERROR(H7/G7-1,"") | I8: =IFERROR(I7/H7-1,"") | J8: =IFERROR(J7/I7-1,"") | ... L8: =IFERROR(L7/K7-1,"") | M8: ='Annual P&L'!$M$7 -> 0.032084342 | N8: ='Annual P&L'!$N$7 -> 0.052940551 | O8: ='Annual P&L'!$O$7 -> 0.049744003 | P8: ='Annual P&L'!$P$7 -> 0.048919495
A9: Headcount growth | B9: ="" | C9: =IFERROR('Raw Financials'!$C$133/'Raw Financials'!$B$133-1,"") -> 0.094335623 | D9: =IFERROR('Raw Financials'!$D$133/'Raw Financials'!$C$133-1,"") -> 0.020078869 | E9: =IFERROR('Raw Financials'!$E$133/'Raw Financials'!$D$133-1,"") -> 0.074144679 | F9: =IFERROR('Raw Financials'!$F$133/'Raw Financials'!$E$133-1,"") -> 0.056987638 | G9: =IFERROR('Raw Financials'!$G$133/'Raw Financials'!$F$133-1,"") -> 0.089605855 | H9: =IFERROR('Raw Financials'!$H$133/'Raw Financials'!$G$133-1,"") -> 0.21190261 | I9: =IFERROR('Raw Financials'!$I$133/'Raw Financials'!$H$133-1,"") -> 0.038163105 | J9: =IFERROR('Raw Financials'!$J$133/'Raw Financials'!$I$133-1,"") -> -0.021550273 | K9: =IFERROR('Raw Financials'!$K$133/'Raw Financials'!$J$133-1,"") -> 0.010694112 | L9: =IFERROR('Raw Financials'!$L$133/'Raw Financials'!$K$133-1,"") -> -0.038586859 | M9: 0.015 | N9: 0.02 | O9: 0.025 | P9: 0.025
A10: Billable employee share (model assumption) | L10: 0.82 | M10: 0.82 | N10: 0.815 | O10: 0.81 | P10: 0.805
A11: T&M mix (model assumption) | L11: 0.55 | M11: 0.53 | N11: 0.51 | O11: 0.49 | P11: 0.47
A12: Pricing / productivity uplift | M12: 0.015 | N12: 0.018 | O12: 0.02 | P12: 0.02
A13: AI deflation on T&M work | M13: 0.015 | N13: 0.02 | O13: 0.025 | P13: 0.03
A14: AI annualised exit run-rate (USD bn) | B14: ='Raw Financials'!$B$139 -> 0 | C14: ='Raw Financials'!$C$139 -> 0 | D14: ='Raw Financials'!$D$139 -> 0 | E14: ='Raw Financials'!$E$139 -> 0 | F14: ='Raw Financials'!$F$139 -> 0 | G14: ='Raw Financials'!$G$139 -> 0 | H14: ='Raw Financials'!$H$139 -> 0 | I14: ='Raw Financials'!$I$139 -> 0 | J14: ='Raw Financials'!$J$139 -> 0 | K14: ='Raw Financials'!$K$139 -> 0 | L14: ='Raw Financials'!$L$139 -> 2.3 | M14: 3.3 | N14: 4.1 | O14: 4.9 | P14: 5.7
A15: Average USD/INR | B15: ='Raw Financials'!$B$151 -> 65.676638 | C15: ='Raw Financials'!$C$151 -> 67.130765 | D15: ='Raw Financials'!$D$151 -> 64.49 | E15: ='Raw Financials'!$E$151 -> 70.07 | F15: ='Raw Financials'!$F$151 -> 71.23 | G15: ='Raw Financials'!$G$151 -> 74.06 | H15: ='Raw Financials'!$H$151 -> 74.61 | I15: ='Raw Financials'!$I$151 -> 80.74 | J15: ='Raw Financials'!$J$151 -> 82.83 | K15: ='Raw Financials'!$K$151 -> 84.59 | L15: ='Raw Financials'!$L$151 -> 88.94 | M15: 94 | N15: 95 | O15: 96 | P15: 97
A16: Average GBP/INR | B16: ='Raw Financials'!$B$152 -> 98.658158 | C16: ='Raw Financials'!$C$152 -> 87.346492 | D16: ='Raw Financials'!$D$152 -> 86.05 | E16: ='Raw Financials'!$E$152 -> 91.6 | F16: ='Raw Financials'!$F$152 -> 90.15 | G16: ='Raw Financials'!$G$152 -> 97.32 | H16: ='Raw Financials'!$H$152 -> 101.5 | I16: ='Raw Financials'!$I$152 -> 96.98 | J16: ='Raw Financials'!$J$152 -> 104.07 | K16: ='Raw Financials'!$K$152 -> 108.26 | L16: ='Raw Financials'!$L$152 -> 119.42 | M16: 126 | N16: 128 | O16: 130 | P16: 132
A17: Average EUR/INR | B17: ='Raw Financials'!$B$153 -> 72.540871 | C17: ='Raw Financials'!$C$153 -> 73.265561 | D17: ='Raw Financials'!$D$153 -> 76.16 | E17: ='Raw Financials'!$E$153 -> 80.82 | F17: ='Raw Financials'!$F$153 -> 78.94 | G17: ='Raw Financials'!$G$153 -> 86.69 | H17: ='Raw Financials'!$H$153 -> 86.36 | I17: ='Raw Financials'!$I$153 -> 84.01 | J17: ='Raw Financials'!$J$153 -> 89.8 | K17: ='Raw Financials'!$K$153 -> 90.81 | L17: ='Raw Financials'!$L$153 -> 103.26 | M17: 110 | N17: 112 | O17: 114 | P17: 116
A18: Client-band growth | M18: 0.03 | N18: 0.03 | O18: 0.025 | P18: 0.025
A21: P&L assumptions | B21: P&L assumptions | C21: P&L assumptions | D21: P&L assumptions | E21: P&L assumptions | F21: P&L assumptions | G21: P&L assumptions | H21: P&L assumptions | I21: P&L assumptions | J21: P&L assumptions | K21: P&L assumptions | L21: P&L assumptions | M21: P&L assumptions | N21: P&L assumptions | O21: P&L assumptions | P21: P&L assumptions
A22: Operating margin | B22: ='Annual P&L'!B$14 -> 0.26498936 | C22: ='Annual P&L'!C$14 -> 0.25705712 | D22: ='Annual P&L'!D$14 -> 0.24777424 | E22: ='Annual P&L'!E$14 -> 0.25569598 | F22: ='Annual P&L'!F$14 -> 0.24581233 | G22: ='Annual P&L'!G$14 -> 0.25875123 | H22: ='Annual P&L'!H$14 -> 0.25268313 | I22: ='Annual P&L'!I$14 -> 0.24056365 | ... L22: ='Annual P&L'!L$14 -> 0.23335992 | M22: 0.242 | N22: 0.245 | O22: 0.248 | P22: 0.25
A23: Cost of revenue / revenue | B23: =IFERROR('Annual P&L'!B$8/'Annual P&L'!B$6,"") -> 0.56053193 | C23: =IFERROR('Annual P&L'!C$8/'Annual P&L'!C$6,"") -> 0.56700236 | D23: =IFERROR('Annual P&L'!D$8/'Annual P&L'!D$6,"") -> 0.5790876 | E23: =IFERROR('Annual P&L'!E$8/'Annual P&L'!E$6,"") -> 0.58143012 | F23: =IFERROR('Annual P&L'!F$8/'Annual P&L'!F$6,"") -> 0.5882293 | G23: =IFERROR('Annual P&L'!G$8/'Annual P&L'!G$6,"") -> 0.59166631 | H23: =IFERROR('Annual P&L'!H$8/'Annual P&L'!H$6,"") -> 0.59775024 | I23: =IFERROR('Annual P&L'!I$8/'Annual P&L'!I$6,"") -> 0.60440526 | ... L23: =IFERROR('Annual P&L'!L$8/'Annual P&L'!L$6,"") -> 0.73074028 | M23: 0.725 | N23: 0.723 | O23: 0.721 | P23: 0.72
A24: Other income / revenue | B24: ='Annual P&L'!B15/'Annual P&L'!B6 -> 0.028074334 | C24: ='Annual P&L'!C15/'Annual P&L'!C6 -> 0.035510232 | D24: ='Annual P&L'!D15/'Annual P&L'!D6 -> 0.029162334 | E24: ='Annual P&L'!E15/'Annual P&L'!E6 -> 0.028082178 | F24: ='Annual P&L'!F15/'Annual P&L'!F6 -> 0.023370649 | G24: ='Annual P&L'!G15/'Annual P&L'!G6 -> 0.015209195 | H24: ='Annual P&L'!H15/'Annual P&L'!H6 -> 0.016865359 | I24: ='Annual P&L'!I15/'Annual P&L'!I6 -> 0.01184256 | ... L24: ='Annual P&L'!L15/'Annual P&L'!L6 -> 0.011890451 | M24: 0.014 | N24: 0.014 | O24: 0.014 | P24: 0.014
A25: Effective tax rate | B25: ='Annual P&L'!B19 -> 0.23563375 | C25: ='Annual P&L'!C19 -> 0.23631675 | D25: ='Annual P&L'!D19 -> 0.24087763 | E25: ='Annual P&L'!E19 -> 0.24062267 | F25: ='Annual P&L'!F19 -> 0.23198731 | G25: ='Annual P&L'!G19 -> 0.25474677 | H25: ='Annual P&L'!H19 -> 0.25611856 | I25: ='Annual P&L'!I19 -> 0.25662924 | ... L25: ='Annual P&L'!L19 -> 0.24482722 | M25: 0.245 | N25: 0.245 | O25: 0.245 | P25: 0.245
A26: NCI / net profit incl. NCI | B26: ='Annual P&L'!B21/'Annual P&L'!B20 -> -0.0050432212 | C26: ='Annual P&L'!C21/'Annual P&L'!C20 -> -0.0025799598 | D26: ='Annual P&L'!D21/'Annual P&L'!D20 -> -0.0020865533 | E26: ='Annual P&L'!E21/'Annual P&L'!E20 -> -0.0028515303 | F26: ='Annual P&L'!F21/'Annual P&L'!F20 -> -0.0032976855 | G26: ='Annual P&L'!G21/'Annual P&L'!G20 -> -0.0039379475 | H26: ='Annual P&L'!H21/'Annual P&L'!H20 -> -0.0031730344 | I26: ='Annual P&L'!I21/'Annual P&L'!I20 -> -0.0036876817 | ... L26: ='Annual P&L'!L21/'Annual P&L'!L20 -> -0.0049338779 | M26: 0.005 | N26: 0.005 | O26: 0.005 | P26: 0.005
A27: D&A / revenue | B27: ='Raw Financials'!B14/'Raw Financials'!B7 -> 0.017376952 | C27: ='Raw Financials'!C14/'Raw Financials'!C7 -> 0.016843836 | D27: ='Raw Financials'!D14/'Raw Financials'!D7 -> 0.016360151 | E27: ='Raw Financials'!E14/'Raw Financials'!E7 -> 0.014030847 | F27: ='Raw Financials'!F14/'Raw Financials'!F7 -> 0.022491383 | G27: ='Raw Financials'!G14/'Raw Financials'!G7 -> 0.024759863 | H27: ='Raw Financials'!H14/'Raw Financials'!H7 -> 0.024009929 | I27: ='Raw Financials'!I14/'Raw Financials'!I7 -> 0.022279094 | ... L27: ='Raw Financials'!L14/'Raw Financials'!L7 -> 0.017830058 | M27: 0.018 | N27: 0.018 | O27: 0.018 | P27: 0.018
A28: Dividend payout ratio | B28: =-'Annual P&L'!B129/'Annual P&L'!B99 -> 0.39134517 | C28: =-'Annual P&L'!C129/'Annual P&L'!C99 -> 0.41533558 | D28: =-'Annual P&L'!D129/'Annual P&L'!D99 -> 0.41445131 | E28: =-'Annual P&L'!E129/'Annual P&L'!E99 -> 0.36195425 | F28: =-'Annual P&L'!F129/'Annual P&L'!F99 -> 1.1598607 | G28: =-'Annual P&L'!G129/'Annual P&L'!G99 -> 0.32368735 | H28: =-'Annual P&L'!H129/'Annual P&L'!H99 -> 0.34635491 | I28: =-'Annual P&L'!I129/'Annual P&L'!I99 -> 0.97740113 | ... L28: =-'Annual P&L'!L129/'Annual P&L'!L99 -> 0.79744813 | M28: 0.8 | N28: 0.8 | O28: 0.8 | P28: 0.8
A31: Balance-sheet assumptions | B31: Balance-sheet assumptions | C31: Balance-sheet assumptions | D31: Balance-sheet assumptions | E31: Balance-sheet assumptions | F31: Balance-sheet assumptions | G31: Balance-sheet assumptions | H31: Balance-sheet assumptions | I31: Balance-sheet assumptions | J31: Balance-sheet assumptions | K31: Balance-sheet assumptions | L31: Balance-sheet assumptions | M31: Balance-sheet assumptions | N31: Balance-sheet assumptions | O31: Balance-sheet assumptions | P31: Balance-sheet assumptions
A32: Trade receivables / revenue | B32: =IFERROR('Raw Financials'!$B$76/'Annual P&L'!$B$6,"") -> 0.22157239 | C32: =IFERROR('Raw Financials'!$C$76/'Annual P&L'!$C$6,"") -> 0.19172473 | D32: =IFERROR('Raw Financials'!$D$76/'Annual P&L'!$D$6,"") -> 0.2026173 | E32: =IFERROR('Raw Financials'!$E$76/'Annual P&L'!$E$6,"") -> 0.18670927 | F32: =IFERROR('Raw Financials'!$F$76/'Annual P&L'!$F$6,"") -> 0.19453453 | G32: =IFERROR('Raw Financials'!$G$76/'Annual P&L'!$G$6,"") -> 0.1832108 | H32: =IFERROR('Raw Financials'!$H$76/'Annual P&L'!$H$6,"") -> 0.17769642 | I32: =IFERROR('Raw Financials'!$I$76/'Annual P&L'!$I$6,"") -> 0.18206939 | J32: =IFERROR('Raw Financials'!$J$76/'Annual P&L'!$J$6,"") -> 0.18445534 | K32: =IFERROR('Raw Financials'!$K$76/'Annual P&L'!$K$6,"") -> 0.19638577 | L32: =IFERROR('Raw Financials'!$L$76/'Annual P&L'!$L$6,"") -> 0.21582572 | M32: 0.215 | N32: 0.213 | O32: 0.211 | P32: 0.21
A33: Unbilled receivables / revenue | B33: =IFERROR('Raw Financials'!$B$79/'Annual P&L'!$B$6,"") -> 0.036743113 | C33: =IFERROR('Raw Financials'!$C$79/'Annual P&L'!$C$6,"") -> 0.044148314 | D33: =IFERROR('Raw Financials'!$D$79/'Annual P&L'!$D$6,"") -> 0.054311801 | E33: =IFERROR('Raw Financials'!$E$79/'Annual P&L'!$E$6,"") -> 0.035210258 | F33: =IFERROR('Raw Financials'!$F$79/'Annual P&L'!$F$6,"") -> 0.036521418 | G33: =IFERROR('Raw Financials'!$G$79/'Annual P&L'!$G$6,"") -> 0.040096969 | H33: =IFERROR('Raw Financials'!$H$79/'Annual P&L'!$H$6,"") -> 0.040343357 | I33: =IFERROR('Raw Financials'!$I$79/'Annual P&L'!$I$6,"") -> 0.039497379 | J33: =IFERROR('Raw Financials'!$J$79/'Annual P&L'!$J$6,"") -> 0.037954611 | K33: =IFERROR('Raw Financials'!$K$79/'Annual P&L'!$K$6,"") -> 0.034873337 | L33: =IFERROR('Raw Financials'!$L$79/'Annual P&L'!$L$6,"") -> 0.03776482 | M33: 0.038 | N33: 0.038 | O33: 0.037 | P33: 0.037
A34: Bank deposits / revenue | B34: =IFERROR(('Raw Financials'!$B$75+'Raw Financials'!$B$83)/'Annual P&L'!$B$6,"") -> 0.0043075594 | C34: =IFERROR(('Raw Financials'!$C$75+'Raw Financials'!$C$83)/'Annual P&L'!$C$6,"") -> 0.0036451181 | D34: =IFERROR(('Raw Financials'!$D$75+'Raw Financials'!$D$83)/'Annual P&L'!$D$6,"") -> 0.016701326 | E34: =IFERROR(('Raw Financials'!$E$75+'Raw Financials'!$E$83)/'Annual P&L'!$E$6,"") -> 0.037060555 | F34: =IFERROR(('Raw Financials'!$F$75+'Raw Financials'!$F$83)/'Annual P&L'!$F$6,"") -> 0.0073463354 | G34: =IFERROR(('Raw Financials'!$G$75+'Raw Financials'!$G$83)/'Annual P&L'!$G$6,"") -> 0.018157233 | H34: =IFERROR(('Raw Financials'!$H$75+'Raw Financials'!$H$83)/'Annual P&L'!$H$6,"") -> 0.035143987 | I34: =IFERROR(('Raw Financials'!$I$75+'Raw Financials'!$I$83)/'Annual P&L'!$I$6,"") -> 0.020216626 | J34: =IFERROR(('Raw Financials'!$J$75+'Raw Financials'!$J$83)/'Annual P&L'!$J$6,"") -> 0.025102431 | K34: =IFERROR(('Raw Financials'!$K$75+'Raw Financials'!$K$83)/'Annual P&L'!$K$6,"") -> 0.031035077 | L34: =IFERROR(('Raw Financials'!$L$75+'Raw Financials'!$L$83)/'Annual P&L'!$L$6,"") -> 0.027024092 | M34: 0.027 | N34: 0.027 | O34: 0.027 | P34: 0.027
A35: Current investments / revenue | B35: =IFERROR('Raw Financials'!$B$77/'Annual P&L'!$B$6,"") -> 0.20690091 | C35: =IFERROR('Raw Financials'!$C$77/'Annual P&L'!$C$6,"") -> 0.35294915 | D35: =IFERROR('Raw Financials'!$D$77/'Annual P&L'!$D$6,"") -> 0.29005556 | E35: =IFERROR('Raw Financials'!$E$77/'Annual P&L'!$E$6,"") -> 0.19862354 | F35: =IFERROR('Raw Financials'!$F$77/'Annual P&L'!$F$6,"") -> 0.16655092 | G35: =IFERROR('Raw Financials'!$G$77/'Annual P&L'!$G$6,"") -> 0.17761319 | H35: =IFERROR('Raw Financials'!$H$77/'Annual P&L'!$H$6,"") -> 0.15781679 | I35: =IFERROR('Raw Financials'!$I$77/'Annual P&L'!$I$6,"") -> 0.16365354 | J35: =IFERROR('Raw Financials'!$J$77/'Annual P&L'!$J$6,"") -> 0.13068458 | K35: =IFERROR('Raw Financials'!$K$77/'Annual P&L'!$K$6,"") -> 0.1201963 | L35: =IFERROR('Raw Financials'!$L$77/'Annual P&L'!$L$6,"") -> 0.12646945 | M35: 0.126 | N35: 0.125 | O35: 0.124 | P35: 0.123
A36: Other current assets / revenue | B36: =IFERROR(('Raw Financials'!$B$78+'Raw Financials'!$B$80+'Raw Financials'!$B$81)/'Annual P&L'!$B$6,"") -> 0.058179664 | C36: =IFERROR(('Raw Financials'!$C$78+'Raw Financials'!$C$80+'Raw Financials'!$C$81)/'Annual P&L'!$C$6,"") -> 0.057881084 | D36: =IFERROR(('Raw Financials'!$D$78+'Raw Financials'!$D$80+'Raw Financials'!$D$81)/'Annual P&L'!$D$6,"") -> 0.056448206 | E36: =IFERROR(('Raw Financials'!$E$78+'Raw Financials'!$E$80+'Raw Financials'!$E$81)/'Annual P&L'!$E$6,"") -> 0.12211275 | F36: =IFERROR(('Raw Financials'!$F$78+'Raw Financials'!$F$80+'Raw Financials'!$F$81)/'Annual P&L'!$F$6,"") -> 0.11712085 | G36: =IFERROR(('Raw Financials'!$G$78+'Raw Financials'!$G$80+'Raw Financials'!$G$81)/'Annual P&L'!$G$6,"") -> 0.14824245 | H36: =IFERROR(('Raw Financials'!$H$78+'Raw Financials'!$H$80+'Raw Financials'!$H$81)/'Annual P&L'!$H$6,"") -> 0.09513752 | I36: =IFERROR(('Raw Financials'!$I$78+'Raw Financials'!$I$80+'Raw Financials'!$I$81)/'Annual P&L'!$I$6,"") -> 0.057979757 | J36: =IFERROR(('Raw Financials'!$J$78+'Raw Financials'!$J$80+'Raw Financials'!$J$81)/'Annual P&L'!$J$6,"") -> 0.062729095 | K36: =IFERROR(('Raw Financials'!$K$78+'Raw Financials'!$K$80+'Raw Financials'!$K$81)/'Annual P&L'!$K$6,"") -> 0.07331469 | L36: =IFERROR(('Raw Financials'!$L$78+'Raw Financials'!$L$80+'Raw Financials'!$L$81)/'Annual P&L'!$L$6,"") -> 0.082098412 | M36: 0.082 | N36: 0.08 | O36: 0.078 | P36: 0.076
A37: PPE / revenue | B37: =IFERROR('Raw Financials'!$B$87/'Annual P&L'!$B$6,"") -> 0.10851736 | C37: =IFERROR('Raw Financials'!$C$87/'Annual P&L'!$C$6,"") -> 0.099528678 | D37: =IFERROR('Raw Financials'!$D$87/'Annual P&L'!$D$6,"") -> 0.09422927 | E37: =IFERROR('Raw Financials'!$E$87/'Annual P&L'!$E$6,"") -> 0.079542273 | F37: =IFERROR('Raw Financials'!$F$87/'Annual P&L'!$F$6,"") -> 0.076062925 | G37: =IFERROR('Raw Financials'!$G$87/'Annual P&L'!$G$6,"") -> 0.073914129 | H37: =IFERROR('Raw Financials'!$H$87/'Annual P&L'!$H$6,"") -> 0.062997382 | I37: =IFERROR('Raw Financials'!$I$87/'Annual P&L'!$I$6,"") -> 0.051428647 | J37: =IFERROR('Raw Financials'!$J$87/'Annual P&L'!$J$6,"") -> 0.046593301 | K37: =IFERROR('Raw Financials'!$K$87/'Annual P&L'!$K$6,"") -> 0.050649371 | L37: =IFERROR('Raw Financials'!$L$87/'Annual P&L'!$L$6,"") -> 0.053104437 | M37: 0.053 | N37: 0.053 | O37: 0.053 | P37: 0.053
A38: ROU assets / revenue | B38: =IFERROR('Raw Financials'!$B$88/'Annual P&L'!$B$6,"") -> 0 | C38: =IFERROR('Raw Financials'!$C$88/'Annual P&L'!$C$6,"") -> 0 | D38: =IFERROR('Raw Financials'!$D$88/'Annual P&L'!$D$6,"") -> 0 | E38: =IFERROR('Raw Financials'!$E$88/'Annual P&L'!$E$6,"") -> 0 | F38: =IFERROR('Raw Financials'!$F$88/'Annual P&L'!$F$6,"") -> 0.050933743 | G38: =IFERROR('Raw Financials'!$G$88/'Annual P&L'!$G$6,"") -> 0.046492505 | H38: =IFERROR('Raw Financials'!$H$88/'Annual P&L'!$H$6,"") -> 0.039821855 | I38: =IFERROR('Raw Financials'!$I$88/'Annual P&L'!$I$6,"") -> 0.033531744 | J38: =IFERROR('Raw Financials'!$J$88/'Annual P&L'!$J$6,"") -> 0.032736526 | K38: =IFERROR('Raw Financials'!$K$88/'Annual P&L'!$K$6,"") -> 0.036326393 | L38: =IFERROR('Raw Financials'!$L$88/'Annual P&L'!$L$6,"") -> 0.041296377 | M38: 0.041 | N38: 0.04 | O38: 0.039 | P38: 0.038
A39: Trade payables / revenue | B39: =IFERROR('Raw Financials'!$B$97/'Annual P&L'!$B$6,"") -> 0.069408772 | C39: =IFERROR('Raw Financials'!$C$97/'Annual P&L'!$C$6,"") -> 0.041579777 | D39: =IFERROR('Raw Financials'!$D$97/'Annual P&L'!$D$6,"") -> 0.041379646 | E39: =IFERROR('Raw Financials'!$E$97/'Annual P&L'!$E$6,"") -> 0.042959655 | F39: =IFERROR('Raw Financials'!$F$97/'Annual P&L'!$F$6,"") -> 0.042943886 | G39: =IFERROR('Raw Financials'!$G$97/'Annual P&L'!$G$6,"") -> 0.047875159 | H39: =IFERROR('Raw Financials'!$H$97/'Annual P&L'!$H$6,"") -> 0.041954796 | I39: =IFERROR('Raw Financials'!$I$97/'Annual P&L'!$I$6,"") -> 0.046638398 | J39: =IFERROR('Raw Financials'!$J$97/'Annual P&L'!$J$6,"") -> 0.041433333 | K39: =IFERROR('Raw Financials'!$K$97/'Annual P&L'!$K$6,"") -> 0.054475882 | L39: =IFERROR('Raw Financials'!$L$97/'Annual P&L'!$L$6,"") -> 0.055456312 | M39: 0.055 | N39: 0.055 | O39: 0.055 | P39: 0.055
A40: Other operating current liabilities / revenue | B40: =IFERROR(('Raw Financials'!$B$101+'Raw Financials'!$B$102+'Raw Financials'!$B$103+'Raw Financials'!$B$104+'Raw Financials'!$B$106)/'Annual P&L'!$B$6,"") -> 0.064990762 | C40: =IFERROR(('Raw Financials'!$C$101+'Raw Financials'!$C$102+'Raw Financials'!$C$103+'Raw Financials'!$C$104+'Raw Financials'!$C$106)/'Annual P&L'!$C$6,"") -> 0.067621179 | D40: =IFERROR(('Raw Financials'!$D$101+'Raw Financials'!$D$102+'Raw Financials'!$D$103+'Raw Financials'!$D$104+'Raw Financials'!$D$106)/'Annual P&L'!$D$6,"") -> 0.090330127 | E40: =IFERROR(('Raw Financials'!$E$101+'Raw Financials'!$E$102+'Raw Financials'!$E$103+'Raw Financials'!$E$104+'Raw Financials'!$E$106)/'Annual P&L'!$E$6,"") -> 0.089490178 | F40: =IFERROR(('Raw Financials'!$F$101+'Raw Financials'!$F$102+'Raw Financials'!$F$103+'Raw Financials'!$F$104+'Raw Financials'!$F$106)/'Annual P&L'!$F$6,"") -> 0.097738756 | G40: =IFERROR(('Raw Financials'!$G$101+'Raw Financials'!$G$102+'Raw Financials'!$G$103+'Raw Financials'!$G$104+'Raw Financials'!$G$106)/'Annual P&L'!$G$6,"") -> 0.11426692 | H40: =IFERROR(('Raw Financials'!$H$101+'Raw Financials'!$H$102+'Raw Financials'!$H$103+'Raw Financials'!$H$104+'Raw Financials'!$H$106)/'Annual P&L'!$H$6,"") -> 0.1300364 | I40: =IFERROR(('Raw Financials'!$I$101+'Raw Financials'!$I$102+'Raw Financials'!$I$103+'Raw Financials'!$I$104+'Raw Financials'!$I$106)/'Annual P&L'!$I$6,"") -> 0.098523894 | J40: =IFERROR(('Raw Financials'!$J$101+'Raw Financials'!$J$102+'Raw Financials'!$J$103+'Raw Financials'!$J$104+'Raw Financials'!$J$106)/'Annual P&L'!$J$6,"") -> 0.096246051 | K40: =IFERROR(('Raw Financials'!$K$101+'Raw Financials'!$K$102+'Raw Financials'!$K$103+'Raw Financials'!$K$104+'Raw Financials'!$K$106)/'Annual P&L'!$K$6,"") -> 0.097221569 | L40: =IFERROR(('Raw Financials'!$L$101+'Raw Financials'!$L$102+'Raw Financials'!$L$103+'Raw Financials'!$L$104+'Raw Financials'!$L$106)/'Annual P&L'!$L$6,"") -> 0.11057183 | M40: 0.112 | N40: 0.111 | O40: 0.11 | P40: 0.109
A41: Current tax liabilities / revenue | B41: =IFERROR('Raw Financials'!$B$105/'Annual P&L'!$B$6,"") -> 0.0074093703 | C41: =IFERROR('Raw Financials'!$C$105/'Annual P&L'!$C$6,"") -> 0.011969551 | D41: =IFERROR('Raw Financials'!$D$105/'Annual P&L'!$D$6,"") -> 0.011543086 | E41: =IFERROR('Raw Financials'!$E$105/'Annual P&L'!$E$6,"") -> 0.018209377 | F41: =IFERROR('Raw Financials'!$F$105/'Annual P&L'!$F$6,"") -> 0.023650995 | G41: =IFERROR('Raw Financials'!$G$105/'Annual P&L'!$G$6,"") -> 0.038026033 | H41: =IFERROR('Raw Financials'!$H$105/'Annual P&L'!$H$6,"") -> 0.041308134 | I41: =IFERROR('Raw Financials'!$I$105/'Annual P&L'!$I$6,"") -> 0.041448962 | J41: =IFERROR('Raw Financials'!$J$105/'Annual P&L'!$J$6,"") -> 0.047460906 | K41: =IFERROR('Raw Financials'!$K$105/'Annual P&L'!$K$6,"") -> 0.04979947 | L41: =IFERROR('Raw Financials'!$L$105/'Annual P&L'!$L$6,"") -> 0.055242846 | M41: 0.055 | N41: 0.055 | O41: 0.055 | P41: 0.055
A42: Current lease liabilities / revenue | B42: =IFERROR('Raw Financials'!$B$100/'Annual P&L'!$B$6,"") -> 0 | C42: =IFERROR('Raw Financials'!$C$100/'Annual P&L'!$C$6,"") -> 0 | D42: =IFERROR('Raw Financials'!$D$100/'Annual P&L'!$D$6,"") -> 0 | E42: =IFERROR('Raw Financials'!$E$100/'Annual P&L'!$E$6,"") -> 0 | F42: =IFERROR('Raw Financials'!$F$100/'Annual P&L'!$F$6,"") -> 0.0080790575 | G42: =IFERROR('Raw Financials'!$G$100/'Annual P&L'!$G$6,"") -> 0.0078695554 | H42: =IFERROR('Raw Financials'!$H$100/'Annual P&L'!$H$6,"") -> 0.0075617719 | I42: =IFERROR('Raw Financials'!$I$100/'Annual P&L'!$I$6,"") -> 0.0065865926 | J42: =IFERROR('Raw Financials'!$J$100/'Annual P&L'!$J$6,"") -> 0.0062475871 | K42: =IFERROR('Raw Financials'!$K$100/'Annual P&L'!$K$6,"") -> 0.0060863844 | L42: =IFERROR('Raw Financials'!$L$100/'Annual P&L'!$L$6,"") -> 0.0068533936 | M42: 0.007 | N42: 0.007 | O42: 0.007 | P42: 0.007
A43: Non-current lease liabilities / revenue | B43: =IFERROR('Raw Financials'!$B$110/'Annual P&L'!$B$6,"") -> 0 | C43: =IFERROR('Raw Financials'!$C$110/'Annual P&L'!$C$6,"") -> 0 | D43: =IFERROR('Raw Financials'!$D$110/'Annual P&L'!$D$6,"") -> 0 | E43: =IFERROR('Raw Financials'!$E$110/'Annual P&L'!$E$6,"") -> 0 | F43: =IFERROR('Raw Financials'!$F$110/'Annual P&L'!$F$6,"") -> 0.044001555 | G43: =IFERROR('Raw Financials'!$G$110/'Annual P&L'!$G$6,"") -> 0.03960969 | H43: =IFERROR('Raw Financials'!$H$110/'Annual P&L'!$H$6,"") -> 0.033209216 | I43: =IFERROR('Raw Financials'!$I$110/'Annual P&L'!$I$6,"") -> 0.027512885 | J43: =IFERROR('Raw Financials'!$J$110/'Annual P&L'!$J$6,"") -> 0.027049354 | K43: =IFERROR('Raw Financials'!$K$110/'Annual P&L'!$K$6,"") -> 0.03069825 | L43: =IFERROR('Raw Financials'!$L$110/'Annual P&L'!$L$6,"") -> 0.03540171 | M43: 0.035 | N43: 0.034 | O43: 0.033 | P43: 0.032
A46: Cash-flow assumptions | B46: Cash-flow assumptions | C46: Cash-flow assumptions | D46: Cash-flow assumptions | E46: Cash-flow assumptions | F46: Cash-flow assumptions | G46: Cash-flow assumptions | H46: Cash-flow assumptions | I46: Cash-flow assumptions | J46: Cash-flow assumptions | K46: Cash-flow assumptions | L46: Cash-flow assumptions | M46: Cash-flow assumptions | N46: Cash-flow assumptions | O46: Cash-flow assumptions | P46: Cash-flow assumptions
A47: PPE capex / revenue | B47: =IFERROR(-'Raw Financials'!$B$189/'Annual P&L'!$B$6,"") -> 0 | C47: =IFERROR(-'Raw Financials'!$C$189/'Annual P&L'!$C$6,"") -> 0.01686079 | D47: =IFERROR(-'Raw Financials'!$D$189/'Annual P&L'!$D$6,"") -> 0.015125422 | E47: =IFERROR(-'Raw Financials'!$E$189/'Annual P&L'!$E$6,"") -> 0.014017192 | F47: =IFERROR(-'Raw Financials'!$F$189/'Annual P&L'!$F$6,"") -> 0.016170858 | G47: =IFERROR(-'Raw Financials'!$G$189/'Annual P&L'!$G$6,"") -> 0.016561394 | H47: =IFERROR(-'Raw Financials'!$H$189/'Annual P&L'!$H$6,"") -> 0.012948882 | I47: =IFERROR(-'Raw Financials'!$I$189/'Annual P&L'!$I$6,"") -> 0.011230473 | J47: =IFERROR(-'Raw Financials'!$J$189/'Annual P&L'!$J$6,"") -> 0.0091409879 | K47: =IFERROR(-'Raw Financials'!$K$189/'Annual P&L'!$K$6,"") -> 0.0114247 | L47: =IFERROR(-'Raw Financials'!$L$189/'Annual P&L'!$L$6,"") -> 0.013744237 | M47: 0.014 | N47: 0.0145 | O47: 0.015 | P47: 0.015
A48: ROU capex / revenue | B48: =IFERROR(-'Raw Financials'!$B$190/'Annual P&L'!$B$6,"") -> 0 | C48: =IFERROR(-'Raw Financials'!$C$190/'Annual P&L'!$C$6,"") -> 0 | D48: =IFERROR(-'Raw Financials'!$D$190/'Annual P&L'!$D$6,"") -> 0 | E48: =IFERROR(-'Raw Financials'!$E$190/'Annual P&L'!$E$6,"") -> 0 | F48: =IFERROR(-'Raw Financials'!$F$190/'Annual P&L'!$F$6,"") -> 0.0033068067 | G48: =IFERROR(-'Raw Financials'!$G$190/'Annual P&L'!$G$6,"") -> 0.0006151897 | H48: =IFERROR(-'Raw Financials'!$H$190/'Annual P&L'!$H$6,"") -> 7.8225226e-05 | I48: =IFERROR(-'Raw Financials'!$I$190/'Annual P&L'!$I$6,"") -> 0.00094474359 | J48: =IFERROR(-'Raw Financials'!$J$190/'Annual P&L'!$J$6,"") -> 0.00012453662 | K48: =IFERROR(-'Raw Financials'!$K$190/'Annual P&L'!$K$6,"") -> 0.00029766101 | L48: =IFERROR(-'Raw Financials'!$L$190/'Annual P&L'!$L$6,"") -> 0.00040820759 | M48: 0.0005 | N48: 0.0005 | O48: 0.0005 | P48: 0.0005
A49: Intangible capex / revenue | B49: =IFERROR(-'Raw Financials'!$B$191/'Annual P&L'!$B$6,"") -> 0 | C49: =IFERROR(-'Raw Financials'!$C$191/'Annual P&L'!$C$6,"") -> 8.4770188e-06 | D49: =IFERROR(-'Raw Financials'!$D$191/'Annual P&L'!$D$6,"") -> 0 | E49: =IFERROR(-'Raw Financials'!$E$191/'Annual P&L'!$E$6,"") -> 0.001215324 | F49: =IFERROR(-'Raw Financials'!$F$191/'Annual P&L'!$F$6,"") -> 0.0012233273 | G49: =IFERROR(-'Raw Financials'!$G$191/'Annual P&L'!$G$6,"") -> 0.0021683914 | H49: =IFERROR(-'Raw Financials'!$H$191/'Annual P&L'!$H$6,"") -> 0.0025918625 | I49: =IFERROR(-'Raw Financials'!$I$191/'Annual P&L'!$I$6,"") -> 0.0015745726 | J49: =IFERROR(-'Raw Financials'!$J$191/'Annual P&L'!$J$6,"") -> 0.0018348395 | K49: =IFERROR(-'Raw Financials'!$K$191/'Annual P&L'!$K$6,"") -> 0.0036972631 | L49: =IFERROR(-'Raw Financials'!$L$191/'Annual P&L'!$L$6,"") -> 0.0013744237 | M49: 0.0015 | N49: 0.0015 | O49: 0.0015 | P49: 0.0015
A50: Other non-cash adjustments / revenue | M50: 0.008 | N50: 0.008 | O50: 0.008 | P50: 0.008
A51: Interest & dividend received / revenue | M51: 0.001 | N51: 0.001 | O51: 0.001 | P51: 0.001
A52: Acquisitions (INR m) | M52: 0 | N52: 0 | O52: 0 | P52: 0
A53: Buybacks (INR m) | M53: 0 | N53: 0 | O53: 0 | P53: 0
A54: FX effect / opening cash | M54: 0.0015 | N54: 0.0015 | O54: 0.0015 | P54: 0.0015
A57: Valuation assumptions | B57: Valuation assumptions | C57: Valuation assumptions | D57: Valuation assumptions | E57: Valuation assumptions | F57: Valuation assumptions | G57: Valuation assumptions | H57: Valuation assumptions | I57: Valuation assumptions | J57: Valuation assumptions | K57: Valuation assumptions | L57: Valuation assumptions | M57: Valuation assumptions | N57: Valuation assumptions | O57: Valuation assumptions | P57: Valuation assumptions
A58: Share price assumption (INR) | M58: 2446.6001 | N58: 2446.6001 | O58: 2446.6001 | P58: 2446.6001
A59: Target P/E | M59: 22 | N59: 21.5 | O59: 21 | P59: 20.5
A60: Target EV / EBITDA | M60: 16 | N60: 15.5 | O60: 15 | P60: 14.5
A61: Target P/B | M61: 10 | N61: 9.5 | O61: 9 | P61: 8.5
A64: Currency-mix assumptions | B64: Currency-mix assumptions | C64: Currency-mix assumptions | D64: Currency-mix assumptions | E64: Currency-mix assumptions | F64: Currency-mix assumptions | G64: Currency-mix assumptions | H64: Currency-mix assumptions | I64: Currency-mix assumptions | J64: Currency-mix assumptions | K64: Currency-mix assumptions | L64: Currency-mix assumptions | M64: Currency-mix assumptions | N64: Currency-mix assumptions | O64: Currency-mix assumptions | P64: Currency-mix assumptions
A65: USD mix | B65: ='Raw Financials'!$B$147 -> 0.56992832 | C65: ='Raw Financials'!$C$147 -> 0.57 | D65: ='Raw Financials'!$D$147 -> 0.5458 | E65: ='Raw Financials'!$E$147 -> 0.5362 | F65: ='Raw Financials'!$F$147 -> 0.5299 | G65: ='Raw Financials'!$G$147 -> 0.5201 | H65: ='Raw Financials'!$H$147 -> 0.5297 | I65: ='Raw Financials'!$I$147 -> 0.5595 | J65: ='Raw Financials'!$J$147 -> 0.533 | K65: ='Raw Financials'!$K$147 -> 0.499875 | L65: ='Raw Financials'!$L$147 -> 0.4945125 | M65: 0.492 | N65: 0.488 | O65: 0.484 | P65: 0.48
A66: GBP mix | B66: ='Raw Financials'!$B$148 -> 0.13995193 | C66: ='Raw Financials'!$C$148 -> 0.121 | D66: ='Raw Financials'!$D$148 -> 0.1241 | E66: ='Raw Financials'!$E$148 -> 0.1389 | F66: ='Raw Financials'!$F$148 -> 0.1403 | G66: ='Raw Financials'!$G$148 -> 0.1353 | H66: ='Raw Financials'!$H$148 -> 0.1364 | I66: ='Raw Financials'!$I$148 -> 0.1284 | J66: ='Raw Financials'!$J$148 -> 0.1439 | K66: ='Raw Financials'!$K$148 -> 0.14655 | L66: ='Raw Financials'!$L$148 -> 0.1522625 | M66: 0.153 | N66: 0.154 | O66: 0.155 | P66: 0.156
A67: EUR mix | B67: ='Raw Financials'!$B$149 -> 0.076722587 | C67: ='Raw Financials'!$C$149 -> 0.08 | D67: ='Raw Financials'!$D$149 -> 0.0942 | E67: ='Raw Financials'!$E$149 -> 0.1009 | F67: ='Raw Financials'!$F$149 -> 0.1066 | G67: ='Raw Financials'!$G$149 -> 0.1202 | H67: ='Raw Financials'!$H$149 -> 0.1183 | I67: ='Raw Financials'!$I$149 -> 0.1076 | J67: ='Raw Financials'!$J$149 -> 0.1111 | K67: ='Raw Financials'!$K$149 -> 0.10945 | L67: ='Raw Financials'!$L$149 -> 0.11723 | M67: 0.118 | N67: 0.12 | O67: 0.122 | P67: 0.124
A68: Other currency mix | B68: ='Raw Financials'!$B$150 -> 0.21339716 | C68: ='Raw Financials'!$C$150 -> 0.229 | D68: ='Raw Financials'!$D$150 -> 0.236 | E68: ='Raw Financials'!$E$150 -> 0.224 | F68: ='Raw Financials'!$F$150 -> 0.2232 | G68: ='Raw Financials'!$G$150 -> 0.2244 | H68: ='Raw Financials'!$H$150 -> 0.2156 | I68: ='Raw Financials'!$I$150 -> 0.2045247 | J68: ='Raw Financials'!$J$150 -> 0.21207335 | K68: ='Raw Financials'!$K$150 -> 0.24415 | L68: ='Raw Financials'!$L$150 -> 0.236 | M68: 0.237 | N68: 0.238 | O68: 0.239 | P68: 0.24
A71: Geography-mix assumptions | B71: Geography-mix assumptions | C71: Geography-mix assumptions | D71: Geography-mix assumptions | E71: Geography-mix assumptions | F71: Geography-mix assumptions | G71: Geography-mix assumptions | H71: Geography-mix assumptions | I71: Geography-mix assumptions | J71: Geography-mix assumptions | K71: Geography-mix assumptions | L71: Geography-mix assumptions | M71: Geography-mix assumptions | N71: Geography-mix assumptions | O71: Geography-mix assumptions | P71: Geography-mix assumptions
A72: North America | B72: ='Raw Financials'!$B$140 -> 0.533 | C72: ='Raw Financials'!$C$140 -> 0.54 | D72: ='Raw Financials'!$D$140 -> 0.516 | E72: ='Raw Financials'!$E$140 -> 0.51 | F72: ='Raw Financials'!$F$140 -> 0.504 | G72: ='Raw Financials'!$G$140 -> 0.497 | H72: ='Raw Financials'!$H$140 -> 0.505 | I72: ='Raw Financials'!$I$140 -> 0.534 | J72: ='Raw Financials'!$J$140 -> 0.511 | K72: ='Raw Financials'!$K$140 -> 0.482 | L72: ='Raw Financials'!$L$140 -> 0.486 | M72: 0.483 | N72: 0.48 | O72: 0.477 | P72: 0.474
A73: Latin America | B73: ='Raw Financials'!$B$141 -> 0.019 | C73: ='Raw Financials'!$C$141 -> 0.021 | D73: ='Raw Financials'!$D$141 -> 0.021 | E73: ='Raw Financials'!$E$141 -> 0.02 | F73: ='Raw Financials'!$F$141 -> 0.019 | G73: ='Raw Financials'!$G$141 -> 0.016 | H73: ='Raw Financials'!$H$141 -> 0.017 | I73: ='Raw Financials'!$I$141 -> 0.018 | J73: ='Raw Financials'!$J$141 -> 0.02 | K73: ='Raw Financials'!$K$141 -> 0.019 | L73: ='Raw Financials'!$L$141 -> 0.019 | M73: 0.02 | N73: 0.02 | O73: 0.02 | P73: 0.02
A74: UK | B74: ='Raw Financials'!$B$142 -> 0.158 | C74: ='Raw Financials'!$C$142 -> 0.139 | D74: ='Raw Financials'!$D$142 -> 0.143 | E74: ='Raw Financials'!$E$142 -> 0.156 | F74: ='Raw Financials'!$F$142 -> 0.159 | G74: ='Raw Financials'!$G$142 -> 0.156 | H74: ='Raw Financials'!$H$142 -> 0.159 | I74: ='Raw Financials'!$I$142 -> 0.15 | J74: ='Raw Financials'!$J$142 -> 0.165 | K74: ='Raw Financials'!$K$142 -> 0.168 | L74: ='Raw Financials'!$L$142 -> 0.174 | M74: 0.172 | N74: 0.173 | O74: 0.174 | P74: 0.175
A75: Continental Europe | B75: ='Raw Financials'!$B$143 -> 0.11 | C75: ='Raw Financials'!$C$143 -> 0.115 | D75: ='Raw Financials'!$D$143 -> 0.134 | E75: ='Raw Financials'!$E$143 -> 0.141 | F75: ='Raw Financials'!$F$143 -> 0.147 | G75: ='Raw Financials'!$G$143 -> 0.163 | H75: ='Raw Financials'!$H$143 -> 0.16 | I75: ='Raw Financials'!$I$143 -> 0.149 | J75: ='Raw Financials'!$J$143 -> 0.149 | K75: ='Raw Financials'!$K$143 -> 0.143 | L75: ='Raw Financials'!$L$143 -> 0.154 | M75: 0.154 | N75: 0.155 | O75: 0.156 | P75: 0.157
A76: India | B76: ='Raw Financials'!$B$144 -> 0.062 | C76: ='Raw Financials'!$C$144 -> 0.063 | D76: ='Raw Financials'!$D$144 -> 0.064 | E76: ='Raw Financials'!$E$144 -> 0.057 | F76: ='Raw Financials'!$F$144 -> 0.057 | G76: ='Raw Financials'!$G$144 -> 0.051 | H76: ='Raw Financials'!$H$144 -> 0.051 | I76: ='Raw Financials'!$I$144 -> 0.05 | J76: ='Raw Financials'!$J$144 -> 0.056 | K76: ='Raw Financials'!$K$144 -> 0.086 | L76: ='Raw Financials'!$L$144 -> 0.059 | M76: 0.062 | N76: 0.064 | O76: 0.066 | P76: 0.068
A77: Asia Pacific | B77: ='Raw Financials'!$B$145 -> 0.095 | C77: ='Raw Financials'!$C$145 -> 0.097 | D77: ='Raw Financials'!$D$145 -> 0.097 | E77: ='Raw Financials'!$E$145 -> 0.095 | F77: ='Raw Financials'!$F$145 -> 0.093 | G77: ='Raw Financials'!$G$145 -> 0.096 | H77: ='Raw Financials'!$H$145 -> 0.088 | I77: ='Raw Financials'!$I$145 -> 0.08 | J77: ='Raw Financials'!$J$145 -> 0.078 | K77: ='Raw Financials'!$K$145 -> 0.08 | L77: ='Raw Financials'!$L$145 -> 0.083 | M77: 0.084 | N77: 0.083 | O77: 0.082 | P77: 0.081
A78: MEA | B78: ='Raw Financials'!$B$146 -> 0.023 | C78: ='Raw Financials'!$C$146 -> 0.025 | D78: ='Raw Financials'!$D$146 -> 0.025 | E78: ='Raw Financials'!$E$146 -> 0.021 | F78: ='Raw Financials'!$F$146 -> 0.021 | G78: ='Raw Financials'!$G$146 -> 0.021 | H78: ='Raw Financials'!$H$146 -> 0.02 | I78: ='Raw Financials'!$I$146 -> 0.019 | J78: ='Raw Financials'!$J$146 -> 0.021 | K78: ='Raw Financials'!$K$146 -> 0.022 | L78: ='Raw Financials'!$L$146 -> 0.025 | M78: 0.025 | N78: 0.025 | O78: 0.025 | P78: 0.025
A81: Industry-mix assumptions — latest disclosed classification | B81: Industry-mix assumptions — latest disclosed classification | C81: Industry-mix assumptions — latest disclosed classification | D81: Industry-mix assumptions — latest disclosed classification | E81: Industry-mix assumptions — latest disclosed classification | F81: Industry-mix assumptions — latest disclosed classification | G81: Industry-mix assumptions — latest disclosed classification | H81: Industry-mix assumptions — latest disclosed classification | I81: Industry-mix assumptions — latest disclosed classification | J81: Industry-mix assumptions — latest disclosed classification | K81: Industry-mix assumptions — latest disclosed classification | L81: Industry-mix assumptions — latest disclosed classification | M81: Industry-mix assumptions — latest disclosed classification | N81: Industry-mix assumptions — latest disclosed classification | O81: Industry-mix assumptions — latest disclosed classification | P81: Industry-mix assumptions — latest disclosed classification
A82: BFSI | M82: 0.321 | N82: 0.32 | O82: 0.319 | P82: 0.318
A83: Consumer Business | M83: 0.15 | N83: 0.15 | O83: 0.15 | P83: 0.15
A84: Life Sciences & Healthcare | M84: 0.103 | N84: 0.103 | O84: 0.103 | P84: 0.103
A85: Technology & Services | M85: 0.085 | N85: 0.086 | O85: 0.087 | P85: 0.088
A86: Manufacturing | M86: 0.087 | N86: 0.088 | O86: 0.089 | P86: 0.09
A87: Communication & Media | M87: 0.058 | N87: 0.058 | O87: 0.058 | P87: 0.058
A88: Energy, Resources & Utilities | M88: 0.063 | N88: 0.064 | O88: 0.065 | P88: 0.066
A89: Regional Markets & Others | M89: 0.133 | N89: 0.131 | O89: 0.129 | P89: 0.127

Sheet Raw Financials
A1: Raw Reported Financials — Source Layer | B1: Raw Reported Financials — Source Layer | C1: Raw Reported Financials — Source Layer | D1: Raw Reported Financials — Source Layer | E1: Raw Reported Financials — Source Layer | F1: Raw Reported Financials — Source Layer | G1: Raw Reported Financials — Source Layer | H1: Raw Reported Financials — Source Layer | I1: Raw Reported Financials — Source Layer | J1: Raw Reported Financials — Source Layer | K1: Raw Reported Financials — Source Layer | L1: Raw Reported Financials — Source Layer | M1: Raw Reported Financials — Source Layer | N1: Raw Reported Financials — Source Layer | O1: Raw Reported Financials — Source Layer | P1: Raw Reported Financials — Source Layer | Q1: Raw Reported Financials — Source Layer | R1: Raw Reported Financials — Source Layer | S1: Raw Reported Financials — Source Layer | T1: Raw Reported Financials — Source Layer | U1: Raw Reported Financials — Source Layer | V1: Raw Reported Financials — Source Layer | W1: Raw Reported Financials — Source Layer | X1: Raw Reported Financials — Source Layer | Y1: Raw Reported Financials — Source Layer | Z1: Raw Reported Financials — Source Layer | AA1: Raw Reported Financials — Source Layer | AB1: Raw Reported Financials — Source Layer | AC1: Raw Reported Financials — Source Layer | AD1: Raw Reported Financials — Source Layer | AE1: Raw Reported Financials — Source Layer | AF1: Raw Reported Financials — Source Layer | AG1: Raw Reported Financials — Source Layer | AH1: Raw Reported Financials — Source Layer | AI1: Raw Reported Financials — Source Layer | AJ1: Raw Reported Financials — Source Layer | AK1: Raw Reported Financials — Source Layer | AL1: Raw Reported Financials — Source Layer | AM1: Raw Reported Financials — Source Layer | AN1: Raw Reported Financials — Source Layer | AO1: Raw Reported Financials — Source Layer | AP1: Raw Reported Financials — Source Layer | AQ1: Raw Reported Financials — Source Layer | AR1: Raw Reported Financials — Source Layer | AS1: Raw Reported Financials — Source Layer | AT1: Raw Reported Financials — Source Layer
A2: Raw Reported Financials — Source Layer | B2: Raw Reported Financials — Source Layer | C2: Raw Reported Financials — Source Layer | D2: Raw Reported Financials — Source Layer | E2: Raw Reported Financials — Source Layer | F2: Raw Reported Financials — Source Layer | G2: Raw Reported Financials — Source Layer | H2: Raw Reported Financials — Source Layer | I2: Raw Reported Financials — Source Layer | J2: Raw Reported Financials — Source Layer | K2: Raw Reported Financials — Source Layer | L2: Raw Reported Financials — Source Layer | M2: Raw Reported Financials — Source Layer | N2: Raw Reported Financials — Source Layer | O2: Raw Reported Financials — Source Layer | P2: Raw Reported Financials — Source Layer | Q2: Raw Reported Financials — Source Layer | R2: Raw Reported Financials — Source Layer | S2: Raw Reported Financials — Source Layer | T2: Raw Reported Financials — Source Layer | U2: Raw Reported Financials — Source Layer | V2: Raw Reported Financials — Source Layer | W2: Raw Reported Financials — Source Layer | X2: Raw Reported Financials — Source Layer | Y2: Raw Reported Financials — Source Layer | Z2: Raw Reported Financials — Source Layer | AA2: Raw Reported Financials — Source Layer | AB2: Raw Reported Financials — Source Layer | AC2: Raw Reported Financials — Source Layer | AD2: Raw Reported Financials — Source Layer | AE2: Raw Reported Financials — Source Layer | AF2: Raw Reported Financials — Source Layer | AG2: Raw Reported Financials — Source Layer | AH2: Raw Reported Financials — Source Layer | AI2: Raw Reported Financials — Source Layer | AJ2: Raw Reported Financials — Source Layer | AK2: Raw Reported Financials — Source Layer | AL2: Raw Reported Financials — Source Layer | AM2: Raw Reported Financials — Source Layer | AN2: Raw Reported Financials — Source Layer | AO2: Raw Reported Financials — Source Layer | AP2: Raw Reported Financials — Source Layer | AQ2: Raw Reported Financials — Source Layer | AR2: Raw Reported Financials — Source Layer | AS2: Raw Reported Financials — Source Layer | AT2: Raw Reported Financials — Source Layer
A3: Blue-font cells are sourced values; reported values replace ex-adjusted figures where official cell comments provide the reported number. | B3: Blue-font cells are sourced values; reported values replace ex-adjusted figures where official cell comments provide the reported number. | C3: Blue-font cells are sourced values; reported values replace ex-adjusted figures where official cell comments provide the reported number. | D3: Blue-font cells are sourced values; reported values replace ex-adjusted figures where official cell comments provide the reported number. | E3: Blue-font cells are sourced values; reported values replace ex-adjusted figures where official cell comments provide the reported number. | F3: Blue-font cells are sourced values; reported values replace ex-adjusted figures where official cell comments provide the reported number. | G3: Blue-font cells are sourced values; reported values replace ex-adjusted figures where official cell comments provide the reported number. | H3: Blue-font cells are sourced values; reported values replace ex-adjusted figures where official cell comments provide the reported number. | I3: Blue-font cells are sourced values; reported values replace ex-adjusted figures where official cell comments provide the reported number. | J3: Blue-font cells are sourced values; reported values replace ex-adjusted figures where official cell comments provide the reported number. | K3: Blue-font cells are sourced values; reported values replace ex-adjusted figures where official cell comments provide the reported number. | L3: Blue-font cells are sourced values; reported values replace ex-adjusted figures where official cell comments provide the reported number. | M3: Blue-font cells are sourced values; reported values replace ex-adjusted figures where official cell comments provide the reported number. | N3: Blue-font cells are sourced values; reported values replace ex-adjusted figures where official cell comments provide the reported number. | O3: Blue-font cells are sourced values; reported values replace ex-adjusted figures where official cell comments provide the reported number. | P3: Blue-font cells are sourced values; reported values replace ex-adjusted figures where official cell comments provide the reported number. | Q3: Blue-font cells are sourced values; reported values replace ex-adjusted figures where official cell comments provide the reported number. | R3: Blue-font cells are sourced values; reported values replace ex-adjusted figures where official cell comments provide the reported number. | S3: Blue-font cells are sourced values; reported values replace ex-adjusted figures where official cell comments provide the reported number. | T3: Blue-font cells are sourced values; reported values replace ex-adjusted figures where official cell comments provide the reported number. | U3: Blue-font cells are sourced values; reported values replace ex-adjusted figures where official cell comments provide the reported number. | V3: Blue-font cells are sourced values; reported values replace ex-adjusted figures where official cell comments provide the reported number. | W3: Blue-font cells are sourced values; reported values replace ex-adjusted figures where official cell comments provide the reported number. | X3: Blue-font cells are sourced values; reported values replace ex-adjusted figures where official cell comments provide the reported number. | Y3: Blue-font cells are sourced values; reported values replace ex-adjusted figures where official cell comments provide the reported number. | Z3: Blue-font cells are sourced values; reported values replace ex-adjusted figures where official cell comments provide the reported number. | AA3: Blue-font cells are sourced values; reported values replace ex-adjusted figures where official cell comments provide the reported number. | AB3: Blue-font cells are sourced values; reported values replace ex-adjusted figures where official cell comments provide the reported number. | AC3: Blue-font cells are sourced values; reported values replace ex-adjusted figures where official cell comments provide the reported number. | AD3: Blue-font cells are sourced values; reported values replace ex-adjusted figures where official cell comments provide the reported number. | AE3: Blue-font cells are sourced values; reported values replace ex-adjusted figures where official cell comments provide the reported number. | AF3: Blue-font cells are sourced values; reported values replace ex-adjusted figures where official cell comments provide the reported number. | AG3: Blue-font cells are sourced values; reported values replace ex-adjusted figures where official cell comments provide the reported number. | AH3: Blue-font cells are sourced values; reported values replace ex-adjusted figures where official cell comments provide the reported number. | AI3: Blue-font cells are sourced values; reported values replace ex-adjusted figures where official cell comments provide the reported number. | AJ3: Blue-font cells are sourced values; reported values replace ex-adjusted figures where official cell comments provide the reported number. | AK3: Blue-font cells are sourced values; reported values replace ex-adjusted figures where official cell comments provide the reported number. | AL3: Blue-font cells are sourced values; reported values replace ex-adjusted figures where official cell comments provide the reported number. | AM3: Blue-font cells are sourced values; reported values replace ex-adjusted figures where official cell comments provide the reported number. | AN3: Blue-font cells are sourced values; reported values replace ex-adjusted figures where official cell comments provide the reported number. | AO3: Blue-font cells are sourced values; reported values replace ex-adjusted figures where official cell comments provide the reported number. | AP3: Blue-font cells are sourced values; reported values replace ex-adjusted figures where official cell comments provide the reported number. | AQ3: Blue-font cells are sourced values; reported values replace ex-adjusted figures where official cell comments provide the reported number. | AR3: Blue-font cells are sourced values; reported values replace ex-adjusted figures where official cell comments provide the reported number. | AS3: Blue-font cells are sourced values; reported values replace ex-adjusted figures where official cell comments provide the reported number. | AT3: Blue-font cells are sourced values; reported values replace ex-adjusted figures where official cell comments provide the reported number.
A5: Annual reported P&L (INR m) | B5: Annual reported P&L (INR m) | C5: Annual reported P&L (INR m) | D5: Annual reported P&L (INR m) | E5: Annual reported P&L (INR m) | F5: Annual reported P&L (INR m) | G5: Annual reported P&L (INR m) | H5: Annual reported P&L (INR m) | I5: Annual reported P&L (INR m) | J5: Annual reported P&L (INR m) | K5: Annual reported P&L (INR m) | L5: Annual reported P&L (INR m)
B6: FY16 | C6: FY17 | D6: FY18 | E6: FY19 | F6: FY20 | G6: FY21 | H6: FY22 | I6: FY23 | J6: FY24 | K6: FY25 | L6: FY26
A7: Revenue | B7: 1086462.1 | C7: 1179660 | D7: 1231040 | E7: 1464630 | F7: 1569490 | G7: 1641770 | H7: 1917540 | I7: 2254580 | J7: 2408930 | K7: 2553240 | L7: 2670210
A8: Cost of revenue | B8: 608996.7 | C8: 668870 | D8: 712880 | E8: 851580 | F8: 923220 | G8: 971380 | H8: 1146210 | I8: 1362680 | J8: 1435950 | K8: 1559940 | L8: 1951230
A9: Gross profit | B9: 477465.4 | C9: 510790 | D9: 518160 | E9: 613050 | F9: 646270 | G9: 670390 | H9: 771330 | I9: 891900 | J9: 972980 | K9: 993300 | L9: 718980
A10: Employee cost | B10: 553495.4 | C10: 616220 | D10: 663960 | E10: 782450 | F10: 859520 | G10: 918140 | H10: 1075540 | I10: 1275220 | J10: 1401320 | K10: 1457880 | L10: 1549940
A11: External consultants | B11: 84126.4 | C11: 88540 | D11: 89900 | E11: 113300 | F11: 129370 | G11: 132170 | H11: 174100 | I11: 213350 | J11: 158200 | K11: 116950 | L11: 137090
A12: Equipment & software | B12: 25711.4 | C12: 28080 | D12: 27000 | E12: 22700 | F12: 19050 | G12: 14620 | H12: 11630 | I12: 18810 | J12: 37020 | K12: 116480 | L12: 43980
A13: Project expenses / service delivery software | L13: 91610
A14: D&A | B14: 18879.4 | C14: 19870 | D14: 20140 | E14: 20550 | F14: 35300 | G14: 40650 | H14: 46040 | I14: 50230 | J14: 49840 | K14: 52420 | L14: 47610
A15: Facility | B15: 34061.6 | C15: 36860 | D15: 39370 | E15: 42620 | F15: 27040 | G15: 21300 | H15: 21390 | I15: 26540 | J15: 31000 | K15: 34560 | L15: 36870
A16: Communication | B16: 11073 | C16: 10660 | D16: 10600 | E16: 13220 | F16: 15920 | G16: 18960 | H16: 20510 | I16: 22450 | J16: 22630 | K16: 23650 | L16: 11030
A17: Travel | B17: 26628.9 | C17: 27870 | D17: 28170 | E17: 34740 | F17: 32950 | G17: 10810 | H17: 15880 | I17: 26760 | J17: 29720 | K17: 32120 | L17: 33100
A18: Branding & marketing | L18: 14620
A19: Recruitment & training | L19: 6710
A20: Legal & professional | L20: 8040
A21: Provision for doubtful debts | B21: 1346.7 | C21: 1260 | D21: 2080 | E21: 1870 | F21: 1440 | G21: 2010 | H21: 1350 | I21: 1390 | J21: 1140 | K21: 1280 | L21: 1840
A22: Other operating expenses | B22: 43238.302 | C22: 47060 | D22: 44800 | E22: 58680 | F22: 63100 | G22: 58300 | H22: 66570 | I22: 77460 | J22: 84950 | K22: 96250 | L22: 19390
A23: Total operating expenses | B23: 798561.2 | C23: 876420 | D23: 926020 | E23: 1090130 | F23: 1183690 | G23: 1216960 | H23: 1433010 | I23: 1712210 | J23: 1825400 | K23: 1931590 | L23: 2047090
A24: Operating income | B24: 287900.9 | C24: 303240 | D24: 305020 | E24: 374500 | F24: 385800 | G24: 424810 | H24: 484530 | I24: 542370 | J24: 583530 | K24: 621650 | L24: 623120
A25: Other income / (expense) | B25: 30501.7 | C25: 41890 | D25: 35900 | E25: 41130 | F25: 36680 | G25: 24970 | H25: 32340 | I25: 26700 | J25: 36440 | K25: 31660 | L25: 31750
A26: PBT | B26: 318402.6 | C26: 345130 | D26: 340920 | E26: 415630 | F26: 422480 | G26: 449780 | H26: 516870 | I26: 569070 | J26: 619970 | K26: 653310 | L26: 654870
A27: Income tax | B27: 75026.4 | C27: 81560 | D27: 82120 | E27: 100010 | F27: 98010 | G27: 114580 | H27: 132380 | I27: 146040 | J27: 158980 | K27: 165340 | L27: 160330
A28: Net profit incl. NCI | B28: 243376.2 | C28: 263570 | D28: 258800 | E28: 315620 | F28: 324470 | G28: 335200 | H28: 384490 | I28: 423030 | J28: 460990 | K28: 487970 | L28: 494540
A29: NCI | B29: -1227.4 | C29: -680 | D29: -540 | E29: -900 | F29: -1070 | G29: -1320 | H29: -1220 | I29: -1560 | J29: -1910 | K29: -2440 | L29: -2440
A30: Net income attributable | B30: 242148.8 | C30: 262890 | D30: 258260 | E30: 314720 | F30: 323400 | G30: 333880 | H30: 383270 | I30: 421470 | J30: 459080 | K30: 485530 | L30: 492100
A31: EPS — basic | B31: 123.17 | C31: 133.41 | D31: 134.19 | E31: 83.05 | F31: 86.19 | G31: 89.27 | H31: 103.62 | I31: 115.19 | J31: 125.88 | K31: 134.19 | L31: 136.01
A32: EPS — diluted | B32: 123.17 | C32: 133.41 | D32: 134.19 | E32: 83.05 | F32: 86.19 | G32: 89.27 | H32: 103.62 | I32: 115.19 | J32: 125.88 | K32: 134.19 | L32: 136.01
... A34: Weighted average shares | B34: 1966040455 | C34: 1970427941 | D34: 1924592806 | E34: 3789749350 | F34: 3752384706 | G34: 3.7401107e+09 | H34: 3.6988322e+09 | I34: 3659051373 | J34: 3.6468518e+09 | K34: 3618087518 | L34: 3618087518
A38: Quarterly reported P&L (INR m) | B38: Quarterly reported P&L (INR m) | C38: Quarterly reported P&L (INR m) | D38: Quarterly reported P&L (INR m) | E38: Quarterly reported P&L (INR m) | F38: Quarterly reported P&L (INR m) | G38: Quarterly reported P&L (INR m) | H38: Quarterly reported P&L (INR m) | I38: Quarterly reported P&L (INR m) | J38: Quarterly reported P&L (INR m) | K38: Quarterly reported P&L (INR m) | L38: Quarterly reported P&L (INR m) | M38: Quarterly reported P&L (INR m) | N38: Quarterly reported P&L (INR m) | O38: Quarterly reported P&L (INR m) | P38: Quarterly reported P&L (INR m) | Q38: Quarterly reported P&L (INR m) | R38: Quarterly reported P&L (INR m) | S38: Quarterly reported P&L (INR m) | T38: Quarterly reported P&L (INR m) | U38: Quarterly reported P&L (INR m) | V38: Quarterly reported P&L (INR m) | W38: Quarterly reported P&L (INR m) | X38: Quarterly reported P&L (INR m) | Y38: Quarterly reported P&L (INR m) | Z38: Quarterly reported P&L (INR m) | AA38: Quarterly reported P&L (INR m) | AB38: Quarterly reported P&L (INR m) | AC38: Quarterly reported P&L (INR m) | AD38: Quarterly reported P&L (INR m) | AE38: Quarterly reported P&L (INR m) | AF38: Quarterly reported P&L (INR m) | AG38: Quarterly reported P&L (INR m) | AH38: Quarterly reported P&L (INR m) | AI38: Quarterly reported P&L (INR m) | AJ38: Quarterly reported P&L (INR m) | AK38: Quarterly reported P&L (INR m) | AL38: Quarterly reported P&L (INR m) | AM38: Quarterly reported P&L (INR m) | AN38: Quarterly reported P&L (INR m) | AO38: Quarterly reported P&L (INR m) | AP38: Quarterly reported P&L (INR m) | AQ38: Quarterly reported P&L (INR m) | AR38: Quarterly reported P&L (INR m) | AS38: Quarterly reported P&L (INR m) | AT38: Quarterly reported P&L (INR m)
B39: 1Q16 | C39: 2Q16 | D39: 3Q16 | E39: 4Q16 | F39: 1Q17 | G39: 2Q17 | H39: 3Q17 | I39: 4Q17 | J39: 1Q18 | K39: 2Q18 | L39: 3Q18 | M39: 4Q18 | N39: 1Q19 | O39: 2Q19 | P39: 3Q19 | Q39: 4Q19 | R39: 1Q20 | S39: 2Q20 | T39: 3Q20 | U39: 4Q20 | V39: 1Q21 | W39: 2Q21 | X39: 3Q21 | Y39: 4Q21 | Z39: 1Q22 | AA39: 2Q22 | AB39: 3Q22 | AC39: 4Q22 | AD39: 1Q23 | AE39: 2Q23 | AF39: 3Q23 | AG39: 4Q23 | AH39: 1Q24 | AI39: 2Q24 | AJ39: 3Q24 | AK39: 4Q24 | AL39: 1Q25 | AM39: 2Q25 | AN39: 3Q25 | AO39: 4Q25 | AP39: 1Q26 | AQ39: 2Q26 | AR39: 3Q26 | AS39: 4Q26 | AT39: 1Q27
A40: Revenue | B40: 256681.1 | C40: 271654.8 | D40: 273640.1 | E40: 284486.1 | F40: 293050 | G40: 292840 | H40: 297350 | I40: 296420 | J40: 295840 | K40: 305410 | L40: 309040 | M40: 320750 | N40: 342610 | O40: 368540 | P40: 373380 | Q40: 380100 | R40: 381720 | S40: 389770 | T40: 398540 | U40: 399460 | V40: 383220 | W40: 401350 | X40: 420150 | Y40: 437050 | Z40: 454110 | AA40: 468670 | AB40: 488850 | AC40: 505910 | AD40: 527580 | AE40: 553090 | AF40: 582290 | AG40: 591620 | AH40: 593810 | AI40: 596920 | AJ40: 605830 | AK40: 612370 | AL40: 626130 | AM40: 642590 | AN40: 639730 | AO40: 644790 | AP40: 634370 | AQ40: 657990 | AR40: 670870 | AS40: 706980 | AT40: 722750
A41: Cost of revenue | B41: 144679.5 | C41: 151501.2 | D41: 152193.9 | E41: 160622 | F41: 168020 | G41: 165340 | H41: 168780 | I41: 166730 | J41: 172910 | K41: 176110 | L41: 178620 | M41: 185240 | N41: 200830 | O41: 212000 | P41: 217350 | Q41: 221400 | R41: 227210 | S41: 230630 | T41: 233690 | U41: 231690 | V41: 232140 | W41: 237150 | X41: 245270 | Y41: 256820 | Z41: 270800 | AA41: 279220 | AB41: 293320 | AC41: 302870 | AD41: 324890 | AE41: 334620 | AF41: 349080 | AG41: 354090 | AH41: 359160 | AI41: 357620 | AJ41: 358710 | AK41: 360460 | AL41: 376610 | AM41: 397200 | AN41: 391390 | AO41: 394740 | AP41: 467960 | AQ41: 480960 | AR41: 488910 | AS41: 513400 | AT41: 535800
A42: Gross profit | B42: 112001.7 | C42: 120153.5 | D42: 121446.2 | E42: 123864.1 | F42: 125030 | G42: 127500 | H42: 128570 | I42: 129690 | J42: 122930 | K42: 129300 | L42: 130420 | M42: 135510 | N42: 141780 | O42: 156540 | P42: 156030 | Q42: 158700 | R42: 154510 | S42: 159140 | T42: 164850 | U42: 167770 | V42: 151080 | W42: 164200 | X42: 174880 | Y42: 180230 | Z42: 183310 | AA42: 189450 | AB42: 195530 | AC42: 203040 | AD42: 202690 | AE42: 218470 | AF42: 233210 | AG42: 237530 | AH42: 234650 | AI42: 239300 | AJ42: 247120 | AK42: 251910 | AL42: 249520 | AM42: 245390 | AN42: 248340 | AO42: 250050 | AP42: 166410 | AQ42: 177030 | AR42: 181960 | AS42: 193580 | AT42: 186950
A43: Employee cost | B43: 132918.2 | C43: 136234.5 | D43: 140114.3 | E43: 144228.4 | F43: 153740 | G43: 152800 | H43: 152750 | I43: 156930 | J43: 161830 | K43: 165730 | L43: 164580 | M43: 171820 | N43: 185470 | O43: 195250 | P43: 199940 | Q43: 201790 | R43: 208090 | S43: 214700 | T43: 216230 | U43: 220500 | V43: 220930 | W43: 226650 | X43: 234310 | Y43: 236250 | Z43: 256490 | AA43: 263840 | AB43: 271680 | AC43: 283530 | AD43: 303260 | AE43: 310410 | AF43: 324670 | AG43: 336880 | AH43: 351490 | AI43: 351230 | AJ43: 347220 | AK43: 351380 | AL43: 364160 | AM43: 366540 | AN43: 359560 | AO43: 367620 | AP43: 377150 | AQ43: 386060 | AR43: 385300 | AS43: 401430 | AT43: 421370
A44: External consultants | B44: 18441 | C44: 21580.5 | D44: 21090.3 | E44: 23014.7 | F44: 22950 | G44: 22490 | H44: 22420 | I44: 20680 | J44: 21110 | K44: 22400 | L44: 22320 | M44: 24070 | N44: 25390 | O44: 27670 | P44: 29620 | Q44: 30620 | R44: 31940 | S44: 32790 | T44: 32680 | U44: 31960 | V44: 30630 | W44: 30480 | X44: 32310 | Y44: 38750 | Z44: 39000 | AA44: 41900 | AB44: 45190 | AC44: 48010 | AD44: 52840 | AE44: 55090 | AF44: 54790 | AG44: 50630 | AH44: 45820 | AI44: 42910 | AJ44: 39710 | AK44: 29760 | AL44: 26660 | AM44: 29890 | AN44: 29690 | AO44: 30710 | AP44: 29990 | AQ44: 32480 | AR44: 34910 | AS44: 39710 | AT44: 42930
A45: Equipment & software | B45: 6586.1 | C45: 5605.5 | D45: 5593.6 | E45: 7926.2 | F45: 6780 | G45: 4880 | H45: 9370 | I45: 7050 | J45: 7250 | K45: 6930 | L45: 7490 | M45: 5330 | N45: 6130 | O45: 5220 | P45: 5400 | Q45: 5950 | R45: 5110 | S45: 4650 | T45: 4600 | U45: 4690 | V45: 3460 | W45: 2660 | X45: 3960 | Y45: 4540 | Z45: 2580 | AA45: 2130 | AB45: 4320 | AC45: 2600 | AD45: 2170 | AE45: 4010 | AF45: 6430 | AG45: 6200 | AH45: 5060 | AI45: 4620 | AJ45: 11730 | AK45: 15610 | AL45: 21510 | AM45: 32300 | AN45: 35190 | AO45: 27480 | AP45: 7260 | AQ45: 9670 | AR45: 12620 | AS45: 14430 | AT45: 13540
A46: Project expenses / service delivery software | AP46: 21690 | AQ46: 21260 | AR46: 23990 | AS46: 24670 | AT46: 24090
A47: D&A | B47: 4534.4 | C47: 4688.7 | D47: 4707.5 | E47: 4948.7 | F47: 4910 | G47: 4940 | H47: 4960 | I47: 5060 | J47: 4980 | K47: 5040 | L47: 5070 | M47: 5050 | N47: 4930 | O47: 5070 | P47: 5190 | Q47: 5360 | R47: 8170 | S47: 8650 | T47: 8970 | U47: 9510 | V47: 9770 | W47: 9980 | X47: 10230 | Y47: 10670 | Z47: 10760 | AA47: 11150 | AB47: 11960 | AC47: 12170 | AD47: 12310 | AE47: 12370 | AF47: 12700 | AG47: 12850 | AH47: 12430 | AI47: 12620 | AJ47: 12330 | AK47: 12460 | AL47: 12200 | AM47: 12670 | AN47: 13760 | AO47: 13790 | AP47: 11540 | AQ47: 12060 | AR47: 11820 | AS47: 12190 | AT47: 12060
A48: Facility | B48: 8127.4 | C48: 8532.2 | D48: 8577.5 | E48: 8824.5 | F48: 9290 | G48: 9220 | H48: 9250 | I48: 9100 | J48: 9660 | K48: 9680 | L48: 9890 | M48: 10140 | N48: 10400 | O48: 10930 | P48: 10670 | Q48: 10620 | R48: 6830 | S48: 7050 | T48: 6610 | U48: 6550 | V48: 5360 | W48: 5000 | X48: 5320 | Y48: 5620 | Z48: 5160 | AA48: 4920 | AB48: 5730 | AC48: 5580 | AD48: 6090 | AE48: 6530 | AF48: 6760 | AG48: 7160 | AH48: 7580 | AI48: 7690 | AJ48: 7870 | AK48: 7860 | AL48: 8280 | AM48: 8660 | AN48: 8730 | AO48: 8890 | AP48: 9160 | AQ48: 8860 | AR48: 9410 | AS48: 9440 | AT48: 9750
A49: Communication | B49: 2808.4 | C49: 2654.3 | D49: 2939 | E49: 2671.4 | F49: 2970 | G49: 2660 | H49: 2580 | I49: 2450 | J49: 2730 | K49: 2500 | L49: 2640 | M49: 2730 | N49: 2860 | O49: 3450 | P49: 3260 | Q49: 3640 | R49: 3780 | S49: 4190 | T49: 3850 | U49: 4100 | V49: 4600 | W49: 4800 | X49: 4710 | Y49: 4850 | Z49: 4980 | AA49: 4790 | AB49: 5100 | AC49: 5640 | AD49: 4930 | AE49: 5230 | AF49: 6050 | AG49: 6240 | AH49: 5750 | AI49: 5440 | AJ49: 5650 | AK49: 5790 | AL49: 5500 | AM49: 6020 | AN49: 5960 | AO49: 6170 | AP49: 2780 | AQ49: 2700 | AR49: 2700 | AS49: 2850 | AT49: 2960
A50: Travel | B50: 6025.5 | C50: 6775.7 | D50: 6427.2 | E50: 7400.7 | F50: 7300 | G50: 7040 | H50: 6600 | I50: 6930 | J50: 7550 | K50: 6800 | L50: 6740 | M50: 7080 | N50: 8190 | O50: 9260 | P50: 8550 | Q50: 8740 | R50: 9340 | S50: 8150 | T50: 8200 | U50: 7260 | V50: 2860 | W50: 2820 | X50: 2540 | Y50: 2590 | Z50: 3450 | AA50: 3910 | AB50: 5120 | AC50: 3400 | AD50: 5590 | AE50: 6510 | AF50: 7310 | AG50: 7350 | AH50: 7940 | AI50: 6830 | AJ50: 6830 | AK50: 8120 | AL50: 8410 | AM50: 8140 | AN50: 7290 | AO50: 8280 | AP50: 8390 | AQ50: 7870 | AR50: 8160 | AS50: 8680 | AT50: 9100
A51: Branding & marketing | AP51: 3470 | AQ51: 3090 | AR51: 4220 | AS51: 3840 | AT51: 3930
A52: Recruitment & training | AP52: 1630 | AQ52: 1590 | AR52: 1430 | AS52: 2060 | AT52: 2450
A53: Legal & professional | AP53: 1970 | AQ53: 1850 | AR53: 2010 | AS53: 2210 | AT53: 2100
A54: Provision for doubtful debts | B54: 394.7 | C54: 358.8 | D54: 241 | E54: 352.2 | F54: 490 | G54: 140 | H54: 330 | I54: 300 | J54: 320 | K54: 480 | L54: 660 | M54: 620 | N54: 480 | O54: 500 | P54: 350 | Q54: 540 | R54: 500 | S54: 380 | T54: 170 | U54: 390 | V54: 530 | W54: 770 | X54: 280 | Y54: 430 | Z54: 410 | AA54: 350 | AB54: 420 | AC54: 170 | AD54: 150 | AE54: 400 | AF54: 430 | AG54: 410 | AH54: 180 | AI54: 320 | AJ54: 220 | AK54: 420 | AL54: 430 | AM54: 190 | AN54: 410 | AO54: 250 | AP54: 250 | AQ54: 380 | AR54: 370 | AS54: 840 | AT54: 840
A55: Other operating expenses | B55: 9361.4 | C55: 11689.2 | D55: 11187.5 | E55: 11000.135 | F55: 11150 | G55: 12500 | H55: 11760 | I55: 11650 | J55: 11270 | K55: 9250 | L55: 11840 | M55: 12440 | N55: 12980 | O55: 13480 | P55: 14760 | Q55: 17470 | R55: 15760 | S55: 15600 | T55: 17490 | U55: 14250 | V55: 14600 | W55: 13040 | X55: 14650 | Y55: 16010 | Z55: 15400 | AA55: 15680 | AB55: 16960 | AC55: 18530 | AD55: 18380 | AE55: 19750 | AF55: 20310 | AG55: 19020 | AH55: 20010 | AI55: 20440 | AJ55: 22720 | AK55: 21790 | AL55: 24560 | AM55: 23530 | AN55: 22570 | AO55: 25590 | AP55: 3950 | AQ55: 4470 | AR55: 5040 | AS55: 5930 | AT55: 4460
A56: Total operating expenses | B56: 189197.1 | C56: 198119.4 | D56: 200877.9 | E56: 210366.94 | F56: 219580 | G56: 216670 | H56: 220020 | I56: 220150 | J56: 226700 | K56: 228810 | L56: 231230 | M56: 239280 | N56: 256830 | O56: 270830 | P56: 277740 | Q56: 284730 | R56: 289520 | S56: 296160 | T56: 298800 | U56: 299210 | V56: 292740 | W56: 308380 | X56: 308310 | Y56: 319710 | Z56: 338230 | AA56: 348670 | AB56: 366480 | AC56: 379630 | AD56: 405720 | AE56: 420300 | AF56: 439450 | AG56: 446740 | AH56: 456260 | AI56: 452100 | AJ56: 463860 | AK56: 453190 | AL56: 471710 | AM56: 487940 | AN56: 483160 | AO56: 488780 | AP56: 479230 | AQ56: 503690 | AR56: 535890 | AS56: 528280 | AT56: 556260
A57: Operating income | B57: 67484.1 | C57: 73535.4 | D57: 72762.2 | E57: 74119.2 | F57: 73470 | G57: 76170 | H57: 77330 | I57: 76270 | J57: 69140 | K57: 76600 | L57: 77810 | M57: 81470 | N57: 85780 | O57: 97710 | P57: 95640 | Q57: 95370 | R57: 92200 | S57: 93610 | T57: 99740 | U57: 100250 | V57: 90480 | W57: 92970 | X57: 111840 | Y57: 117340 | Z57: 115880 | AA57: 120000 | AB57: 122370 | AC57: 126280 | AD57: 121860 | AE57: 132790 | AF57: 142840 | AG57: 144880 | AH57: 137550 | AI57: 144820 | AJ57: 141970 | AK57: 159180 | AL57: 154420 | AM57: 154650 | AN57: 156570 | AO57: 156010 | AP57: 155140 | AQ57: 154300 | AR57: 134980 | AS57: 178700 | AT57: 166490
A58: Other income / (expense) | B58: 7710.6 | C58: 6750.4 | D58: 6990.3 | E58: 9050.3 | F58: 9630 | G58: 10520 | H58: 11850 | I58: 9890 | J58: 9320 | K58: 8120 | L58: 8640 | M58: 9820 | N58: 12080 | O58: 5930 | P58: 11470 | Q58: 11650 | R58: 14180 | S58: 11680 | T58: 5950 | U58: 4870 | V58: 4560 | W58: 7400 | X58: 5080 | Y58: 7930 | Z58: 5750 | AA58: 9690 | AB58: 9540 | AC58: 7360 | AD58: 5900 | AE58: 8170 | AF58: 3600 | AG58: 9030 | AH58: 12340 | AI58: 8470 | AJ58: 6320 | AK58: 9310 | AL58: 7890 | AM58: 5670 | AN58: 10090 | AO58: 8010 | AP58: 14650 | AQ58: 6380 | AR58: 5800 | AS58: 4920 | AT58: 12950
A59: PBT | B59: 75194.7 | C59: 80285.8 | D59: 79752.6 | E59: 83169.5 | F59: 83100 | G59: 86690 | H59: 89180 | I59: 86160 | J59: 78460 | K59: 84720 | L59: 86450 | M59: 91290 | N59: 97860 | O59: 103640 | P59: 107110 | Q59: 107020 | R59: 106380 | S59: 105290 | T59: 105690 | U59: 105120 | V59: 95040 | W59: 100370 | X59: 116920 | Y59: 125270 | Z59: 121630 | AA59: 129690 | AB59: 131910 | AC59: 133640 | AD59: 127760 | AE59: 140960 | AF59: 146440 | AG59: 153910 | AH59: 149890 | AI59: 153290 | AJ59: 148290 | AK59: 168490 | AL59: 162310 | AM59: 160320 | AN59: 166660 | AO59: 164020 | AP59: 169790 | AQ59: 160680 | AR59: 140780 | AS59: 183620 | AT59: 179440
A60: Income tax | B60: 17467.6 | C60: 19356.3 | D60: 18500.8 | E60: 19701.7 | F60: 19920 | G60: 20660 | H60: 21040 | I60: 19940 | J60: 18960 | K60: 20120 | L60: 21000 | M60: 22040 | N60: 24240 | O60: 24370 | P60: 25900 | Q60: 25500 | R60: 24850 | S60: 24710 | T60: 24260 | U60: 24190 | V60: 24550 | W60: 25330 | X60: 29650 | Y60: 32450 | Z60: 31320 | AA60: 33160 | AB60: 33850 | AC60: 34050 | AD60: 32570 | AE60: 36310 | AF60: 37610 | AG60: 39550 | AH60: 38690 | AI60: 39500 | AJ60: 37320 | AK60: 43470 | AL60: 41260 | AM60: 40770 | AN60: 42220 | AO60: 41090 | AP60: 41600 | AQ60: 39370 | AR60: 33580 | AS60: 45780 | AT60: 45240
A61: Net profit incl. NCI | B61: 57727.1 | C61: 60929.5 | D61: 61251.8 | E61: 63467.9 | F61: 63180 | G61: 66030 | H61: 68140 | I61: 66220 | J61: 59500 | K61: 64600 | L61: 65450 | M61: 69250 | N61: 73620 | O61: 79270 | P61: 81210 | Q61: 81520 | R61: 81530 | S61: 80580 | T61: 81430 | U61: 80930 | V61: 70490 | W61: 75040 | X61: 87270 | Y61: 92820 | Z61: 90310 | AA61: 96530 | AB61: 98060 | AC61: 99590 | AD61: 95190 | AE61: 104650 | AF61: 108830 | AG61: 114360 | AH61: 111200 | AI61: 113790 | AJ61: 110970 | AK61: 125020 | AL61: 121050 | AM61: 119550 | AN61: 124440 | AO61: 122930 | AP61: 128190 | AQ61: 121310 | AR61: 107200 | AS61: 137840 | AT61: 134200
A62: NCI | B62: -637.6 | C62: -377.5 | D62: -156.4 | E62: -55.8 | F62: -10 | G62: -170 | H62: -360 | I62: -140 | J62: -50 | K62: -140 | L62: -140 | M62: -210 | N62: -220 | O62: -260 | P62: -160 | Q62: -260 | R62: -220 | S62: -160 | T62: -250 | U62: -440 | V62: -410 | W62: -290 | X62: -260 | Y62: -360 | Z62: -230 | AA62: -290 | AB62: -370 | AC62: -330 | AD62: -410 | AE62: -340 | AF62: -370 | AG62: -440 | AH62: -460 | AI62: -380 | AJ62: -390 | AK62: -680 | AL62: -650 | AM62: -460 | AN62: -640 | AO62: -690 | AP62: -590 | AQ62: -560 | AR62: -630 | AS62: -660 | AT62: -710
A63: Net income attributable | B63: 57089.4 | C63: 60552 | D63: 61095.4 | E63: 63412.1 | F63: 63170 | G63: 65860 | H63: 67780 | I63: 66080 | J63: 59450 | K63: 64460 | L63: 65310 | M63: 69040 | N63: 73400 | O63: 79010 | P63: 81050 | Q63: 81260 | R63: 81310 | S63: 80420 | T63: 81180 | U63: 80490 | V63: 70080 | W63: 74750 | X63: 87010 | Y63: 92460 | Z63: 90080 | AA63: 96240 | AB63: 97690 | AC63: 99260 | AD63: 94780 | AE63: 104310 | AF63: 108460 | AG63: 113920 | AH63: 110740 | AI63: 113410 | AJ63: 110580 | AK63: 124340 | AL63: 120400 | AM63: 119090 | AN63: 123800 | AO63: 122240 | AP63: 127600 | AQ63: 120750 | AR63: 106570 | AS63: 137180 | AT63: 133490
A64: EPS — basic | B64: 29.15 | C64: 30.82 | D64: 31.01 | E64: 32.18 | F64: 32.06 | G64: 33.43 | H64: 34.4 | I64: 33.52 | J64: 30.4 | K64: 33.67 | L64: 34.12 | M64: 36.07 | N64: 19.17 | O64: 20.66 | P64: 21.6 | Q64: 21.65 | R64: 21.67 | S64: 21.43 | T64: 21.63 | U64: 21.45 | V64: 18.68 | W64: 19.33 | X64: 23.19 | Y64: 24.97 | Z64: 24.35 | AA64: 26.02 | AB64: 26.41 | AC64: 26.85 | AD64: 25.9 | AE64: 28.51 | AF64: 29.64 | AG64: 31.14 | AH64: 30.26 | AI64: 31 | AJ64: 30.29 | AK64: 34.37 | AL64: 33.28 | AM64: 32.92 | AN64: 34.21 | AO64: 33.79 | AP64: 35.27 | AQ64: 33.37 | AR64: 29.45 | AS64: 37.92 | AT64: 36.9
A65: EPS — diluted | B65: 29.15 | C65: 30.82 | D65: 31.01 | E65: 32.18 | F65: 32.06 | G65: 33.43 | H65: 34.4 | I65: 33.52 | J65: 30.4 | K65: 33.67 | L65: 34.12 | M65: 36.07 | N65: 19.17 | O65: 20.66 | P65: 21.6 | Q65: 21.65 | R65: 21.67 | S65: 21.43 | T65: 21.63 | U65: 21.45 | V65: 18.68 | W65: 19.33 | X65: 23.19 | Y65: 24.97 | Z65: 24.35 | AA65: 26.02 | AB65: 26.41 | AC65: 26.85 | AD65: 25.9 | AE65: 28.51 | AF65: 29.64 | AG65: 31.14 | AH65: 30.26 | AI65: 31 | AJ65: 30.29 | AK65: 34.37 | AL65: 33.28 | AM65: 32.92 | AN65: 34.21 | AO65: 33.79 | AP65: 35.27 | AQ65: 33.37 | AR65: 29.45 | AS65: 37.92 | AT65: 36.9
... A67: Weighted average shares | B67: 1958727979 | C67: 1964577960 | D67: 1970427941 | E67: 1966040455 | F67: 1970427941 | G67: 1970427941 | H67: 1970427941 | I67: 1970427941 | J67: 1955621695 | K67: 1914287591 | L67: 1914287591 | M67: 1914287591 | N67: 3828575182 | O67: 3825262553 | P67: 3752384706 | Q67: 3752384706 | R67: 3752384706 | S67: 3752384706 | T67: 3752384706 | U67: 3752384706 | V67: 3752384706 | W67: 3752384706 | X67: 3752384706 | Y67: 3.7026069e+09 | Z67: 3699051373 | AA67: 3699051373 | AB67: 3699051373 | AC67: 3.6981625e+09 | AD67: 3659051373 | AE67: 3659051373 | AF67: 3659051373 | AG67: 3659051373 | AH67: 3659051373 | AI67: 3659051373 | AJ67: 3.6510367e+09 | AK67: 3618087518 | AL67: 3618087518 | AM67: 3618087518 | AN67: 3618087518 | AO67: 3618087518 | AP67: 3618087518 | AQ67: 3618087518 | AR67: 3618087518 | AS67: 3618087518 | AT67: 3618087518
A72: Annual reported balance sheet (INR m) | B72: Annual reported balance sheet (INR m) | C72: Annual reported balance sheet (INR m) | D72: Annual reported balance sheet (INR m) | E72: Annual reported balance sheet (INR m) | F72: Annual reported balance sheet (INR m) | G72: Annual reported balance sheet (INR m) | H72: Annual reported balance sheet (INR m) | I72: Annual reported balance sheet (INR m) | J72: Annual reported balance sheet (INR m) | K72: Annual reported balance sheet (INR m) | L72: Annual reported balance sheet (INR m)
B73: FY16 | C73: FY17 | D73: FY18 | E73: FY19 | F73: FY20 | G73: FY21 | H73: FY22 | I73: FY23 | J73: FY24 | K73: FY25 | L73: FY26
A74: Cash & cash equivalents | B74: 62950 | C74: 35970 | D74: 48830 | E74: 72240 | F74: 86460 | G74: 68580 | H74: 124880 | I74: 71230 | J74: 90160 | K74: 83420 | L74: 64170
A75: Current bank deposits | B75: 530 | C75: 4300 | D75: 20560 | E75: 54280 | F75: 8050 | G75: 22620 | H75: 55070 | I75: 32240 | J75: 37990 | K75: 62150 | L75: 58820
A76: Trade receivables | B76: 240730 | C76: 226170 | D76: 249430 | E76: 273460 | F76: 305320 | G76: 300790 | H76: 340740 | I76: 410490 | J76: 444340 | K76: 501420 | L76: 576300
A77: Current investments | B77: 224790 | C77: 416360 | D77: 357070 | E77: 290910 | F77: 261400 | G77: 291600 | H77: 302620 | I77: 368970 | J77: 314810 | K77: 306890 | L77: 337700
A78: Other current financial assets | B78: 40990 | C78: 45050 | D78: 43020 | E78: 99940 | F78: 101630 | G78: 130750 | H78: 80610 | I78: 33290 | J78: 26650 | K78: 36570 | L78: 41010
A79: Unbilled receivables | B79: 39920 | C79: 52080 | D79: 66860 | E79: 51570 | F79: 57320 | G79: 65830 | H79: 77360 | I79: 89050 | J79: 91430 | K79: 89040 | L79: 100840
A80: Current tax assets | B80: 320 | C80: 260 | D80: 370 | E80: 18530 | F80: 80 | G80: 190 | H80: 110 | I80: 80 | J80: 1510 | K80: 2570 | L80: 12590
A81: Other current assets | B81: 21900 | C81: 22970 | D81: 26100 | E81: 60380 | F81: 82110 | G81: 112440 | H81: 101710 | I81: 97350 | J81: 122950 | K81: 148050 | L81: 165620
A82: Total current assets | B82: 632130 | C82: 803160 | D82: 812240 | E82: 921310 | F82: 902370 | G82: 992800 | H82: 1083100 | I82: 1102700 | J82: 1129840 | K82: 1230110 | L82: 1357050
A83: Non-current bank deposits | B83: 4150 | C83: 0 | D83: 0 | E83: 0 | F83: 3480 | G83: 7190 | H83: 12320 | I83: 13340 | J83: 22480 | K83: 17090 | L83: 13340
A84: Other non-current financial assets | B84: 33820 | C84: 8340 | D84: 26670 | E84: 7980 | F84: 8650 | G84: 8830 | H84: 13320 | I84: 9880 | J84: 10260 | K84: 10470 | L84: 23850
A85: Non-current tax assets | B85: 44640 | C85: 47890 | D85: 41310 | E85: 40170 | F85: 24620 | G85: 18450 | H85: 19830 | I85: 25830 | J85: 16000 | K85: 15690 | L85: 14390
... A87: PPE, net | B87: 117900 | C87: 117410 | D87: 116000 | E87: 116500 | F87: 119380 | G87: 121350 | H87: 120800 | I87: 115950 | J87: 112240 | K87: 129320 | L87: 141800
A88: Right-of-use assets | F88: 79940 | G88: 76330 | H88: 76360 | I88: 75600 | J88: 78860 | K88: 92750 | L88: 110270
A89: Goodwill | B89: 38120 | C89: 37210 | D89: 38840 | E89: 38340 | F89: 38500 | G89: 39480 | H89: 39350 | I89: 40060 | J89: 39890 | K89: 40240 | L89: 105580
A90: Other intangible assets | B90: 1340 | C90: 470 | D90: 120 | E90: 1790 | F90: 2830 | G90: 4800 | H90: 11010 | I90: 8670 | J90: 5100 | K90: 9400 | L90: 8790
A91: Non-current investments | B91: 3430 | C91: 3440 | D91: 3010 | E91: 2390 | F91: 2160 | G91: 2130 | H91: 2230 | I91: 2660 | J91: 2810 | K91: 2750 | L91: 2180
A92: Non-current trade receivables | C92: 670 | D92: 940 | E92: 950 | F92: 740 | G92: 550 | H92: 1450 | I92: 1490 | J92: 1270 | K92: 910 | L92: 990
A93: Non-current unbilled receivables | C93: 1430 | D93: 2270 | E93: 3910 | F93: 3240 | G93: 2730 | H93: 550 | I93: 1990 | J93: 160 | K93: 380 | L93: 1140
A94: Other non-current assets | B94: 7770 | C94: 5460 | D94: 8460 | E94: 10870 | F94: 16200 | G94: 15140 | H94: 19220 | I94: 26750 | J94: 33120 | K94: 33040 | L94: 21220
A95: Total non-current assets | B95: 279990 | C95: 250370 | D95: 271850 | E95: 249220 | F95: 327760 | G95: 336010 | H95: 353240 | I95: 354990 | J95: 355880 | K95: 387440 | L95: 487820
A96: Total assets | B96: 912120 | C96: 1053530 | D96: 1084090 | E96: 1170530 | F96: 1230130 | G96: 1328810 | H96: 1436340 | I96: 1457690 | J96: 1485720 | K96: 1617550 | L96: 1844870
A97: Trade and other payables | B97: 75410 | C97: 49050 | D97: 50940 | E97: 62920 | F97: 67400 | G97: 78600 | H97: 80450 | I97: 105150 | J97: 99810 | K97: 139090 | L97: 148080
A98: Short-term borrowings | B98: 1620 | C98: 2180 | D98: 1930 | E98: 180 | F98: 0 | G98: 0 | H98: 0 | I98: 0 | J98: 0 | K98: 0 | L98: 0
A99: Redeemable preference shares | B99: 0 | C99: 0 | F99: 0 | G99: 0 | H99: 0
A100: Current lease liabilities | F100: 12680 | G100: 12920 | H100: 14500 | I100: 14850 | J100: 15050 | K100: 15540 | L100: 18300
A101: Other current financial liabilities | B101: 23150 | C101: 29060 | D101: 39010 | E101: 48850 | F101: 61000 | G101: 61500 | H101: 76870 | I101: 90680 | J101: 83620 | K101: 85420 | L101: 111940
A102: Unearned revenue — current | B102: 13590 | C102: 13980 | D102: 20320 | E102: 23920 | F102: 29150 | G102: 36500 | H102: 36350 | I102: 38430 | J102: 36400 | K102: 40280 | L102: 44870
A103: Employee benefits — current | B103: 16350 | C103: 18620 | D103: 20180 | E103: 23560 | F103: 27490 | G103: 34980 | H103: 38100 | I103: 40650 | J103: 45190 | K103: 48850 | L103: 56000
A104: Other provisions — current | B104: 1150 | C104: 660 | D104: 2400 | E104: 2390 | F104: 2930 | G104: 13940 | H104: 14110 | I104: 3450 | J104: 1400 | K104: 1800 | L104: 13780
A105: Current tax liabilities | B105: 8050 | C105: 14120 | D105: 14210 | E105: 26670 | F105: 37120 | G105: 62430 | H105: 79210 | I105: 93450 | J105: 114330 | K105: 127150 | L105: 147510
A106: Accrued & other current liabilities | B106: 16370 | C106: 17450 | D106: 29290 | E106: 32350 | F106: 32830 | G106: 40680 | H106: 83920 | I106: 48920 | J106: 65240 | K106: 71880 | L106: 68660
A107: Total current liabilities | B107: 155690 | C107: 145120 | D107: 178280 | E107: 220840 | F107: 270600 | G107: 341550 | H107: 423510 | I107: 435580 | J107: 461040 | K107: 530010 | L107: 609140
A108: Long-term borrowings | B108: 830 | C108: 710 | D108: 540 | E108: 440 | F108: 0
A109: Class B preference shares | L109: 1260
A110: Non-current lease liabilities | F110: 69060 | G110: 65030 | H110: 63680 | I110: 62030 | J110: 65160 | K110: 78380 | L110: 94530
A111: Other non-current financial liabilities | B111: 4930 | C111: 4540 | D111: 5030 | E111: 2870 | F111: 2910 | G111: 2800 | H111: 5720 | I111: 3530 | J111: 3650 | K111: 6800 | L111: 5880
...

Sheet Quarterly P&L
A1: Quarterly Profit & Loss Statement | B1: Quarterly Profit & Loss Statement | C1: Quarterly Profit & Loss Statement | D1: Quarterly Profit & Loss Statement | E1: Quarterly Profit & Loss Statement | F1: Quarterly Profit & Loss Statement | G1: Quarterly Profit & Loss Statement | H1: Quarterly Profit & Loss Statement | I1: Quarterly Profit & Loss Statement | J1: Quarterly Profit & Loss Statement | K1: Quarterly Profit & Loss Statement | L1: Quarterly Profit & Loss Statement | M1: Quarterly Profit & Loss Statement | N1: Quarterly Profit & Loss Statement | O1: Quarterly Profit & Loss Statement | P1: Quarterly Profit & Loss Statement | Q1: Quarterly Profit & Loss Statement | R1: Quarterly Profit & Loss Statement | S1: Quarterly Profit & Loss Statement | T1: Quarterly Profit & Loss Statement | U1: Quarterly Profit & Loss Statement | V1: Quarterly Profit & Loss Statement | W1: Quarterly Profit & Loss Statement | X1: Quarterly Profit & Loss Statement | Y1: Quarterly Profit & Loss Statement | Z1: Quarterly Profit & Loss Statement | AA1: Quarterly Profit & Loss Statement | AB1: Quarterly Profit & Loss Statement | AC1: Quarterly Profit & Loss Statement | AD1: Quarterly Profit & Loss Statement | AE1: Quarterly Profit & Loss Statement | AF1: Quarterly Profit & Loss Statement | AG1: Quarterly Profit & Loss Statement | AH1: Quarterly Profit & Loss Statement | AI1: Quarterly Profit & Loss Statement | AJ1: Quarterly Profit & Loss Statement | AK1: Quarterly Profit & Loss Statement | AL1: Quarterly Profit & Loss Statement | AM1: Quarterly Profit & Loss Statement | AN1: Quarterly Profit & Loss Statement | AO1: Quarterly Profit & Loss Statement | AP1: Quarterly Profit & Loss Statement | AQ1: Quarterly Profit & Loss Statement | AR1: Quarterly Profit & Loss Statement | AS1: Quarterly Profit & Loss Statement | AT1: Quarterly Profit & Loss Statement | AU1: Quarterly Profit & Loss Statement | AV1: Quarterly Profit & Loss Statement | AW1: Quarterly Profit & Loss Statement | AX1: Quarterly Profit & Loss Statement | AY1: Quarterly Profit & Loss Statement | AZ1: Quarterly Profit & Loss Statement | BA1: Quarterly Profit & Loss Statement | BB1: Quarterly Profit & Loss Statement | BC1: Quarterly Profit & Loss Statement | BD1: Quarterly Profit & Loss Statement | BE1: Quarterly Profit & Loss Statement | BF1: Quarterly Profit & Loss Statement | BG1: Quarterly Profit & Loss Statement | BH1: Quarterly Profit & Loss Statement | BI1: Quarterly Profit & Loss Statement
A2: Quarterly Profit & Loss Statement | B2: Quarterly Profit & Loss Statement | C2: Quarterly Profit & Loss Statement | D2: Quarterly Profit & Loss Statement | E2: Quarterly Profit & Loss Statement | F2: Quarterly Profit & Loss Statement | G2: Quarterly Profit & Loss Statement | H2: Quarterly Profit & Loss Statement | I2: Quarterly Profit & Loss Statement | J2: Quarterly Profit & Loss Statement | K2: Quarterly Profit & Loss Statement | L2: Quarterly Profit & Loss Statement | M2: Quarterly Profit & Loss Statement | N2: Quarterly Profit & Loss Statement | O2: Quarterly Profit & Loss Statement | P2: Quarterly Profit & Loss Statement | Q2: Quarterly Profit & Loss Statement | R2: Quarterly Profit & Loss Statement | S2: Quarterly Profit & Loss Statement | T2: Quarterly Profit & Loss Statement | U2: Quarterly Profit & Loss Statement | V2: Quarterly Profit & Loss Statement | W2: Quarterly Profit & Loss Statement | X2: Quarterly Profit & Loss Statement | Y2: Quarterly Profit & Loss Statement | Z2: Quarterly Profit & Loss Statement | AA2: Quarterly Profit & Loss Statement | AB2: Quarterly Profit & Loss Statement | AC2: Quarterly Profit & Loss Statement | AD2: Quarterly Profit & Loss Statement | AE2: Quarterly Profit & Loss Statement | AF2: Quarterly Profit & Loss Statement | AG2: Quarterly Profit & Loss Statement | AH2: Quarterly Profit & Loss Statement | AI2: Quarterly Profit & Loss Statement | AJ2: Quarterly Profit & Loss Statement | AK2: Quarterly Profit & Loss Statement | AL2: Quarterly Profit & Loss Statement | AM2: Quarterly Profit & Loss Statement | AN2: Quarterly Profit & Loss Statement | AO2: Quarterly Profit & Loss Statement | AP2: Quarterly Profit & Loss Statement | AQ2: Quarterly Profit & Loss Statement | AR2: Quarterly Profit & Loss Statement | AS2: Quarterly Profit & Loss Statement | AT2: Quarterly Profit & Loss Statement | AU2: Quarterly Profit & Loss Statement | AV2: Quarterly Profit & Loss Statement | AW2: Quarterly Profit & Loss Statement | AX2: Quarterly Profit & Loss Statement | AY2: Quarterly Profit & Loss Statement | AZ2: Quarterly Profit & Loss Statement | BA2: Quarterly Profit & Loss Statement | BB2: Quarterly Profit & Loss Statement | BC2: Quarterly Profit & Loss Statement | BD2: Quarterly Profit & Loss Statement | BE2: Quarterly Profit & Loss Statement | BF2: Quarterly Profit & Loss Statement | BG2: Quarterly Profit & Loss Statement | BH2: Quarterly Profit & Loss Statement | BI2: Quarterly Profit & Loss Statement
A3: Only P&L is quarterly. Actuals through Q1 FY27; forecasts roll to the annual P&L. INR million except per-share data. | B3: Only P&L is quarterly. Actuals through Q1 FY27; forecasts roll to the annual P&L. INR million except per-share data. | C3: Only P&L is quarterly. Actuals through Q1 FY27; forecasts roll to the annual P&L. INR million except per-share data. | D3: Only P&L is quarterly. Actuals through Q1 FY27; forecasts roll to the annual P&L. INR million except per-share data. | E3: Only P&L is quarterly. Actuals through Q1 FY27; forecasts roll to the annual P&L. INR million except per-share data. | F3: Only P&L is quarterly. Actuals through Q1 FY27; forecasts roll to the annual P&L. INR million except per-share data. | G3: Only P&L is quarterly. Actuals through Q1 FY27; forecasts roll to the annual P&L. INR million except per-share data. | H3: Only P&L is quarterly. Actuals through Q1 FY27; forecasts roll to the annual P&L. INR million except per-share data. | I3: Only P&L is quarterly. Actuals through Q1 FY27; forecasts roll to the annual P&L. INR million except per-share data. | J3: Only P&L is quarterly. Actuals through Q1 FY27; forecasts roll to the annual P&L. INR million except per-share data. | K3: Only P&L is quarterly. Actuals through Q1 FY27; forecasts roll to the annual P&L. INR million except per-share data. | L3: Only P&L is quarterly. Actuals through Q1 FY27; forecasts roll to the annual P&L. INR million except per-share data. | M3: Only P&L is quarterly. Actuals through Q1 FY27; forecasts roll to the annual P&L. INR million except per-share data. | N3: Only P&L is quarterly. Actuals through Q1 FY27; forecasts roll to the annual P&L. INR million except per-share data. | O3: Only P&L is quarterly. Actuals through Q1 FY27; forecasts roll to the annual P&L. INR million except per-share data. | P3: Only P&L is quarterly. Actuals through Q1 FY27; forecasts roll to the annual P&L. INR million except per-share data. | Q3: Only P&L is quarterly. Actuals through Q1 FY27; forecasts roll to the annual P&L. INR million except per-share data. | R3: Only P&L is quarterly. Actuals through Q1 FY27; forecasts roll to the annual P&L. INR million except per-share data. | S3: Only P&L is quarterly. Actuals through Q1 FY27; forecasts roll to the annual P&L. INR million except per-share data. | T3: Only P&L is quarterly. Actuals through Q1 FY27; forecasts roll to the annual P&L. INR million except per-share data. | U3: Only P&L is quarterly. Actuals through Q1 FY27; forecasts roll to the annual P&L. INR million except per-share data. | V3: Only P&L is quarterly. Actuals through Q1 FY27; forecasts roll to the annual P&L. INR million except per-share data. | W3: Only P&L is quarterly. Actuals through Q1 FY27; forecasts roll to the annual P&L. INR million except per-share data. | X3: Only P&L is quarterly. Actuals through Q1 FY27; forecasts roll to the annual P&L. INR million except per-share data. | Y3: Only P&L is quarterly. Actuals through Q1 FY27; forecasts roll to the annual P&L. INR million except per-share data. | Z3: Only P&L is quarterly. Actuals through Q1 FY27; forecasts roll to the annual P&L. INR million except per-share data. | AA3: Only P&L is quarterly. Actuals through Q1 FY27; forecasts roll to the annual P&L. INR million except per-share data. | AB3: Only P&L is quarterly. Actuals through Q1 FY27; forecasts roll to the annual P&L. INR million except per-share data. | AC3: Only P&L is quarterly. Actuals through Q1 FY27; forecasts roll to the annual P&L. INR million except per-share data. | AD3: Only P&L is quarterly. Actuals through Q1 FY27; forecasts roll to the annual P&L. INR million except per-share data. | AE3: Only P&L is quarterly. Actuals through Q1 FY27; forecasts roll to the annual P&L. INR million except per-share data. | AF3: Only P&L is quarterly. Actuals through Q1 FY27; forecasts roll to the annual P&L. INR million except per-share data. | AG3: Only P&L is quarterly. Actuals through Q1 FY27; forecasts roll to the annual P&L. INR million except per-share data. | AH3: Only P&L is quarterly. Actuals through Q1 FY27; forecasts roll to the annual P&L. INR million except per-share data. | AI3: Only P&L is quarterly. Actuals through Q1 FY27; forecasts roll to the annual P&L. INR million except per-share data. | AJ3: Only P&L is quarterly. Actuals through Q1 FY27; forecasts roll to the annual P&L. INR million except per-share data. | AK3: Only P&L is quarterly. Actuals through Q1 FY27; forecasts roll to the annual P&L. INR million except per-share data. | AL3: Only P&L is quarterly. Actuals through Q1 FY27; forecasts roll to the annual P&L. INR million except per-share data. | AM3: Only P&L is quarterly. Actuals through Q1 FY27; forecasts roll to the annual P&L. INR million except per-share data. | AN3: Only P&L is quarterly. Actuals through Q1 FY27; forecasts roll to the annual P&L. INR million except per-share data. | AO3: Only P&L is quarterly. Actuals through Q1 FY27; forecasts roll to the annual P&L. INR million except per-share data. | AP3: Only P&L is quarterly. Actuals through Q1 FY27; forecasts roll to the annual P&L. INR million except per-share data. | AQ3: Only P&L is quarterly. Actuals through Q1 FY27; forecasts roll to the annual P&L. INR million except per-share data. | AR3: Only P&L is quarterly. Actuals through Q1 FY27; forecasts roll to the annual P&L. INR million except per-share data. | AS3: Only P&L is quarterly. Actuals through Q1 FY27; forecasts roll to the annual P&L. INR million except per-share data. | AT3: Only P&L is quarterly. Actuals through Q1 FY27; forecasts roll to the annual P&L. INR million except per-share data. | AU3: Only P&L is quarterly. Actuals through Q1 FY27; forecasts roll to the annual P&L. INR million except per-share data. | AV3: Only P&L is quarterly. Actuals through Q1 FY27; forecasts roll to the annual P&L. INR million except per-share data. | AW3: Only P&L is quarterly. Actuals through Q1 FY27; forecasts roll to the annual P&L. INR million except per-share data. | AX3: Only P&L is quarterly. Actuals through Q1 FY27; forecasts roll to the annual P&L. INR million except per-share data. | AY3: Only P&L is quarterly. Actuals through Q1 FY27; forecasts roll to the annual P&L. INR million except per-share data. | AZ3: Only P&L is quarterly. Actuals through Q1 FY27; forecasts roll to the annual P&L. INR million except per-share data. | BA3: Only P&L is quarterly. Actuals through Q1 FY27; forecasts roll to the annual P&L. INR million except per-share data. | BB3: Only P&L is quarterly. Actuals through Q1 FY27; forecasts roll to the annual P&L. INR million except per-share data. | BC3: Only P&L is quarterly. Actuals through Q1 FY27; forecasts roll to the annual P&L. INR million except per-share data. | BD3: Only P&L is quarterly. Actuals through Q1 FY27; forecasts roll to the annual P&L. INR million except per-share data. | BE3: Only P&L is quarterly. Actuals through Q1 FY27; forecasts roll to the annual P&L. INR million except per-share data. | BF3: Only P&L is quarterly. Actuals through Q1 FY27; forecasts roll to the annual P&L. INR million except per-share data. | BG3: Only P&L is quarterly. Actuals through Q1 FY27; forecasts roll to the annual P&L. INR million except per-share data. | BH3: Only P&L is quarterly. Actuals through Q1 FY27; forecasts roll to the annual P&L. INR million except per-share data. | BI3: Only P&L is quarterly. Actuals through Q1 FY27; forecasts roll to the annual P&L. INR million except per-share data.
B5: Q1 FY16 | C5: Q2 FY16 | D5: Q3 FY16 | E5: Q4 FY16 | F5: Q1 FY17 | G5: Q2 FY17 | H5: Q3 FY17 | I5: Q4 FY17 | J5: Q1 FY18 | K5: Q2 FY18 | L5: Q3 FY18 | M5: Q4 FY18 | N5: Q1 FY19 | O5: Q2 FY19 | P5: Q3 FY19 | Q5: Q4 FY19 | R5: Q1 FY20 | S5: Q2 FY20 | T5: Q3 FY20 | U5: Q4 FY20 | V5: Q1 FY21 | W5: Q2 FY21 | X5: Q3 FY21 | Y5: Q4 FY21 | Z5: Q1 FY22 | AA5: Q2 FY22 | AB5: Q3 FY22 | AC5: Q4 FY22 | AD5: Q1 FY23 | AE5: Q2 FY23 | AF5: Q3 FY23 | AG5: Q4 FY23 | AH5: Q1 FY24 | AI5: Q2 FY24 | AJ5: Q3 FY24 | AK5: Q4 FY24 | AL5: Q1 FY25 | AM5: Q2 FY25 | AN5: Q3 FY25 | AO5: Q4 FY25 | AP5: Q1 FY26 | AQ5: Q2 FY26 | AR5: Q3 FY26 | AS5: Q4 FY26 | AT5: Q1 FY27 | AU5: Q2 FY27 | AV5: Q3 FY27 | AW5: Q4 FY27 | AX5: Q1 FY28 | AY5: Q2 FY28 | AZ5: Q3 FY28 | BA5: Q4 FY28 | BB5: Q1 FY29 | BC5: Q2 FY29 | BD5: Q3 FY29 | BE5: Q4 FY29 | BF5: Q1 FY30 | BG5: Q2 FY30 | BH5: Q3 FY30 | BI5: Q4 FY30
A6: Revenue | B6: ='Raw Financials'!$B$40 -> 256681.1 | C6: ='Raw Financials'!$C$40 -> 271654.8 | D6: ='Raw Financials'!$D$40 -> 273640.1 | E6: ='Raw Financials'!$E$40 -> 284486.1 | F6: ='Raw Financials'!$F$40 -> 293050 | G6: ='Raw Financials'!$G$40 -> 292840 | H6: ='Raw Financials'!$H$40 -> 297350 | I6: ='Raw Financials'!$I$40 -> 296420 | J6: ='Raw Financials'!$J$40 -> 295840 | K6: ='Raw Financials'!$K$40 -> 305410 | L6: ='Raw Financials'!$L$40 -> 309040 | M6: ='Raw Financials'!$M$40 -> 320750 | N6: ='Raw Financials'!$N$40 -> 342610 | O6: ='Raw Financials'!$O$40 -> 368540 | P6: ='Raw Financials'!$P$40 -> 373380 | Q6: ='Raw Financials'!$Q$40 -> 380100 | R6: ='Raw Financials'!$R$40 -> 381720 | S6: ='Raw Financials'!$S$40 -> 389770 | T6: ='Raw Financials'!$T$40 -> 398540 | U6: ='Raw Financials'!$U$40 -> 399460 | V6: ='Raw Financials'!$V$40 -> 383220 | W6: ='Raw Financials'!$W$40 -> 401350 | X6: ='Raw Financials'!$X$40 -> 420150 | Y6: ='Raw Financials'!$Y$40 -> 437050 | Z6: ='Raw Financials'!$Z$40 -> 454110 | AA6: ='Raw Financials'!$AA$40 -> 468670 | AB6: ='Raw Financials'!$AB$40 -> 488850 | AC6: ='Raw Financials'!$AC$40 -> 505910 | AD6: ='Raw Financials'!$AD$40 -> 527580 | AE6: ='Raw Financials'!$AE$40 -> 553090 | AF6: ='Raw Financials'!$AF$40 -> 582290 | AG6: ='Raw Financials'!$AG$40 -> 591620 | AH6: ='Raw Financials'!$AH$40 -> 593810 | AI6: ='Raw Financials'!$AI$40 -> 596920 | AJ6: ='Raw Financials'!$AJ$40 -> 605830 | AK6: ='Raw Financials'!$AK$40 -> 612370 | AL6: ='Raw Financials'!$AL$40 -> 626130 | AM6: ='Raw Financials'!$AM$40 -> 642590 | AN6: ='Raw Financials'!$AN$40 -> 639730 | AO6: ='Raw Financials'!$AO$40 -> 644790 | AP6: ='Raw Financials'!$AP$40 -> 634370 | AQ6: ='Raw Financials'!$AQ$40 -> 657990 | AR6: ='Raw Financials'!$AR$40 -> 670870 | AS6: ='Raw Financials'!$AS$40 -> 706980 | AT6: ='Raw Financials'!$AT$40 -> 722750 | AU6: =('Annual P&L'!$M$6-'Quarterly P&L'!$AT$6)*IFERROR('Raw Financials'!$AQ$40/SUM('Raw Financials'!$AQ$40,'Raw Financials'!$AR$40,'Raw Financials'!$AS$40),1/3) -> 657114.74 | AV6: =('Annual P&L'!$M$6-'Quarterly P&L'!$AT$6)*IFERROR('Raw Financials'!$AR$40/SUM('Raw Financials'!$AQ$40,'Raw Financials'!$AR$40,'Raw Financials'!$AS$40),1/3) -> 669977.61 | AW6: =('Annual P&L'!$M$6-'Quarterly P&L'!$AT$6)*IFERROR('Raw Financials'!$AS$40/SUM('Raw Financials'!$AQ$40,'Raw Financials'!$AR$40,'Raw Financials'!$AS$40),1/3) -> 706039.58 | AX6: ='Annual P&L'!$N$6*IFERROR('Raw Financials'!$AP$40/'Raw Financials'!$L$7,0.25) -> 689384.76 | AY6: ='Annual P&L'!$N$6*IFERROR('Raw Financials'!$AQ$40/'Raw Financials'!$L$7,0.25) -> 715053.17 | AZ6: ='Annual P&L'!$N$6*IFERROR('Raw Financials'!$AR$40/'Raw Financials'!$L$7,0.25) -> 729050.17 | BA6: ='Annual P&L'!$N$6*IFERROR('Raw Financials'!$AS$40/'Raw Financials'!$L$7,0.25) -> 768291.75 | BB6: ='Annual P&L'!$O$6*IFERROR('Raw Financials'!$AP$40/'Raw Financials'!$L$7,0.25) -> 723677.52 | BC6: ='Annual P&L'!$O$6*IFERROR('Raw Financials'!$AQ$40/'Raw Financials'!$L$7,0.25) -> 750622.77 | BD6: ='Annual P&L'!$O$6*IFERROR('Raw Financials'!$AR$40/'Raw Financials'!$L$7,0.25) -> 765316.04 | BE6: ='Annual P&L'!$O$6*IFERROR('Raw Financials'!$AS$40/'Raw Financials'!$L$7,0.25) -> 806509.66 | BF6: ='Annual P&L'!$P$6*IFERROR('Raw Financials'!$AP$40/'Raw Financials'!$L$7,0.25) -> 759079.46 | BG6: ='Annual P&L'!$P$6*IFERROR('Raw Financials'!$AQ$40/'Raw Financials'!$L$7,0.25) -> 787342.86 | BH6: ='Annual P&L'!$P$6*IFERROR('Raw Financials'!$AR$40/'Raw Financials'!$L$7,0.25) -> 802754.91 | BI6: ='Annual P&L'!$P$6*IFERROR('Raw Financials'!$AS$40/'Raw Financials'!$L$7,0.25) -> 845963.7
A7: QoQ growth | B7: ="" | C7: =IFERROR(C6/B6-1,"") -> 0.05833581 | D7: =IFERROR(D6/C6-1,"") -> 0.007308172 | E7: =IFERROR(E6/D6-1,"") -> 0.039636004 | F7: =IFERROR(F6/E6-1,"") -> 0.030103052 | G7: =IFERROR(G6/F6-1,"") -> -0.00071660126 | H7: =IFERROR(H6/G6-1,"") -> 0.015400902 | I7: =IFERROR(I6/H6-1,"") -> -0.0031276274 | J7: =IFERROR(J6/I6-1,"") -> -0.0019566831 | ... BI7: =IFERROR(BI6/BH6-1,"") -> 0.053825629
A8: YoY growth | B8: ="" | C8: ="" | D8: ="" | E8: ="" | F8: =IFERROR(F6/B6-1,"") -> 0.14168905 | G8: =IFERROR(G6/C6-1,"") -> 0.077985738 | H8: =IFERROR(H6/D6-1,"") -> 0.086646292 | I8: =IFERROR(I6/E6-1,"") -> 0.041948974 | J8: =IFERROR(J6/F6-1,"") -> 0.0095205596 | K8: =IFERROR(K6/G6-1,"") -> 0.042924464 | L8: =IFERROR(L6/H6-1,"") -> 0.03931394 | M8: =IFERROR(M6/I6-1,"") -> 0.082079482 | ... BI8: =IFERROR(BI6/BE6-1,"") -> 0.048919495
A9: Cost of revenue | B9: ='Raw Financials'!$B$41 -> 144679.5 | C9: ='Raw Financials'!$C$41 -> 151501.2 | D9: ='Raw Financials'!$D$41 -> 152193.9 | E9: ='Raw Financials'!$E$41 -> 160622 | F9: ='Raw Financials'!$F$41 -> 168020 | G9: ='Raw Financials'!$G$41 -> 165340 | H9: ='Raw Financials'!$H$41 -> 168780 | I9: ='Raw Financials'!$I$41 -> 166730 | J9: ='Raw Financials'!$J$41 -> 172910 | K9: ='Raw Financials'!$K$41 -> 176110 | L9: ='Raw Financials'!$L$41 -> 178620 | M9: ='Raw Financials'!$M$41 -> 185240 | N9: ='Raw Financials'!$N$41 -> 200830 | O9: ='Raw Financials'!$O$41 -> 212000 | P9: ='Raw Financials'!$P$41 -> 217350 | Q9: ='Raw Financials'!$Q$41 -> 221400 | R9: ='Raw Financials'!$R$41 -> 227210 | S9: ='Raw Financials'!$S$41 -> 230630 | T9: ='Raw Financials'!$T$41 -> 233690 | U9: ='Raw Financials'!$U$41 -> 231690 | V9: ='Raw Financials'!$V$41 -> 232140 | W9: ='Raw Financials'!$W$41 -> 237150 | X9: ='Raw Financials'!$X$41 -> 245270 | Y9: ='Raw Financials'!$Y$41 -> 256820 | Z9: ='Raw Financials'!$Z$41 -> 270800 | AA9: ='Raw Financials'!$AA$41 -> 279220 | AB9: ='Raw Financials'!$AB$41 -> 293320 | AC9: ='Raw Financials'!$AC$41 -> 302870 | AD9: ='Raw Financials'!$AD$41 -> 324890 | AE9: ='Raw Financials'!$AE$41 -> 334620 | AF9: ='Raw Financials'!$AF$41 -> 349080 | AG9: ='Raw Financials'!$AG$41 -> 354090 | AH9: ='Raw Financials'!$AH$41 -> 359160 | AI9: ='Raw Financials'!$AI$41 -> 357620 | AJ9: ='Raw Financials'!$AJ$41 -> 358710 | AK9: ='Raw Financials'!$AK$41 -> 360460 | AL9: ='Raw Financials'!$AL$41 -> 376610 | AM9: ='Raw Financials'!$AM$41 -> 397200 | AN9: ='Raw Financials'!$AN$41 -> 391390 | AO9: ='Raw Financials'!$AO$41 -> 394740 | AP9: ='Raw Financials'!$AP$41 -> 467960 | AQ9: ='Raw Financials'!$AQ$41 -> 480960 | AR9: ='Raw Financials'!$AR$41 -> 488910 | AS9: ='Raw Financials'!$AS$41 -> 513400 | AT9: ='Raw Financials'!$AT$41 -> 535800 | AU9: =('Annual P&L'!$M$8-'Quarterly P&L'!$AT$9)*IFERROR('Raw Financials'!$AQ$41/SUM('Raw Financials'!$AQ$41,'Raw Financials'!$AR$41,'Raw Financials'!$AS$41),1/3) -> 474132.58 | AV9: =('Annual P&L'!$M$8-'Quarterly P&L'!$AT$9)*IFERROR('Raw Financials'!$AR$41/SUM('Raw Financials'!$AQ$41,'Raw Financials'!$AR$41,'Raw Financials'!$AS$41),1/3) -> 481969.73 | AW9: =('Annual P&L'!$M$8-'Quarterly P&L'!$AT$9)*IFERROR('Raw Financials'!$AS$41/SUM('Raw Financials'!$AQ$41,'Raw Financials'!$AR$41,'Raw Financials'!$AS$41),1/3) -> 506112.09 | AX9: ='Annual P&L'!$N$8*IFERROR('Raw Financials'!$AP$41/'Raw Financials'!$L$8,0.25) -> 503156.43 | AY9: ='Annual P&L'!$N$8*IFERROR('Raw Financials'!$AQ$41/'Raw Financials'!$L$8,0.25) -> 517134.19 | AZ9: ='Annual P&L'!$N$8*IFERROR('Raw Financials'!$AR$41/'Raw Financials'!$L$8,0.25) -> 525682.13 | BA9: ='Annual P&L'!$N$8*IFERROR('Raw Financials'!$AS$41/'Raw Financials'!$L$8,0.25) -> 552014.08 | BB9: ='Annual P&L'!$O$8*IFERROR('Raw Financials'!$AP$41/'Raw Financials'!$L$8,0.25) -> 526724.35 | BC9: ='Annual P&L'!$O$8*IFERROR('Raw Financials'!$AQ$41/'Raw Financials'!$L$8,0.25) -> 541356.83 | BD9: ='Annual P&L'!$O$8*IFERROR('Raw Financials'!$AR$41/'Raw Financials'!$L$8,0.25) -> 550305.16 | BE9: ='Annual P&L'!$O$8*IFERROR('Raw Financials'!$AS$41/'Raw Financials'!$L$8,0.25) -> 577870.5 | BF9: ='Annual P&L'!$P$8*IFERROR('Raw Financials'!$AP$41/'Raw Financials'!$L$8,0.25) -> 551725.15 | BG9: ='Annual P&L'!$P$8*IFERROR('Raw Financials'!$AQ$41/'Raw Financials'!$L$8,0.25) -> 567052.16 | BH9: ='Annual P&L'!$P$8*IFERROR('Raw Financials'!$AR$41/'Raw Financials'!$L$8,0.25) -> 576425.22 | BI9: ='Annual P&L'!$P$8*IFERROR('Raw Financials'!$AS$41/'Raw Financials'!$L$8,0.25) -> 605298.94
A10: Gross profit | B10: ='Raw Financials'!$B$42 -> 112001.7 | C10: ='Raw Financials'!$C$42 -> 120153.5 | D10: ='Raw Financials'!$D$42 -> 121446.2 | E10: ='Raw Financials'!$E$42 -> 123864.1 | F10: ='Raw Financials'!$F$42 -> 125030 | G10: ='Raw Financials'!$G$42 -> 127500 | H10: ='Raw Financials'!$H$42 -> 128570 | I10: ='Raw Financials'!$I$42 -> 129690 | J10: ='Raw Financials'!$J$42 -> 122930 | K10: ='Raw Financials'!$K$42 -> 129300 | L10: ='Raw Financials'!$L$42 -> 130420 | M10: ='Raw Financials'!$M$42 -> 135510 | N10: ='Raw Financials'!$N$42 -> 141780 | O10: ='Raw Financials'!$O$42 -> 156540 | P10: ='Raw Financials'!$P$42 -> 156030 | Q10: ='Raw Financials'!$Q$42 -> 158700 | R10: ='Raw Financials'!$R$42 -> 154510 | S10: ='Raw Financials'!$S$42 -> 159140 | T10: ='Raw Financials'!$T$42 -> 164850 | U10: ='Raw Financials'!$U$42 -> 167770 | V10: ='Raw Financials'!$V$42 -> 151080 | W10: ='Raw Financials'!$W$42 -> 164200 | X10: ='Raw Financials'!$X$42 -> 174880 | Y10: ='Raw Financials'!$Y$42 -> 180230 | Z10: ='Raw Financials'!$Z$42 -> 183310 | AA10: ='Raw Financials'!$AA$42 -> 189450 | AB10: ='Raw Financials'!$AB$42 -> 195530 | AC10: ='Raw Financials'!$AC$42 -> 203040 | AD10: ='Raw Financials'!$AD$42 -> 202690 | AE10: ='Raw Financials'!$AE$42 -> 218470 | AF10: ='Raw Financials'!$AF$42 -> 233210 | AG10: ='Raw Financials'!$AG$42 -> 237530 | AH10: ='Raw Financials'!$AH$42 -> 234650 | AI10: ='Raw Financials'!$AI$42 -> 239300 | AJ10: ='Raw Financials'!$AJ$42 -> 247120 | AK10: ='Raw Financials'!$AK$42 -> 251910 | AL10: ='Raw Financials'!$AL$42 -> 249520 | AM10: ='Raw Financials'!$AM$42 -> 245390 | AN10: ='Raw Financials'!$AN$42 -> 248340 | AO10: ='Raw Financials'!$AO$42 -> 250050 | AP10: ='Raw Financials'!$AP$42 -> 166410 | AQ10: ='Raw Financials'!$AQ$42 -> 177030 | AR10: ='Raw Financials'!$AR$42 -> 181960 | AS10: ='Raw Financials'!$AS$42 -> 193580 | AT10: ='Raw Financials'!$AT$42 -> 186950 | AU10: =('Annual P&L'!$M$9-'Quarterly P&L'!$AT$10)*IFERROR('Raw Financials'!$AQ$42/SUM('Raw Financials'!$AQ$42,'Raw Financials'!$AR$42,'Raw Financials'!$AS$42),1/3) -> 182908.1 | AV10: =('Annual P&L'!$M$9-'Quarterly P&L'!$AT$10)*IFERROR('Raw Financials'!$AR$42/SUM('Raw Financials'!$AQ$42,'Raw Financials'!$AR$42,'Raw Financials'!$AS$42),1/3) -> 188001.8 | AW10: =('Annual P&L'!$M$9-'Quarterly P&L'!$AT$10)*IFERROR('Raw Financials'!$AS$42/SUM('Raw Financials'!$AQ$42,'Raw Financials'!$AR$42,'Raw Financials'!$AS$42),1/3) -> 200007.63 | AX10: ='Annual P&L'!$N$9*IFERROR('Raw Financials'!$AP$42/'Raw Financials'!$L$9,0.25) -> 186040.22 | AY10: ='Annual P&L'!$N$9*IFERROR('Raw Financials'!$AQ$42/'Raw Financials'!$L$9,0.25) -> 197912.98 | AZ10: ='Annual P&L'!$N$9*IFERROR('Raw Financials'!$AR$42/'Raw Financials'!$L$9,0.25) -> 203424.54 | BA10: ='Annual P&L'!$N$9*IFERROR('Raw Financials'!$AS$42/'Raw Financials'!$L$9,0.25) -> 216415.27 | BB10: ='Annual P&L'!$O$9*IFERROR('Raw Financials'!$AP$42/'Raw Financials'!$L$9,0.25) -> 196704.67 | BC10: ='Annual P&L'!$O$9*IFERROR('Raw Financials'!$AQ$42/'Raw Financials'!$L$9,0.25) -> 209258.03 | BD10: ='Annual P&L'!$O$9*IFERROR('Raw Financials'!$AR$42/'Raw Financials'!$L$9,0.25) -> 215085.52 | BE10: ='Annual P&L'!$O$9*IFERROR('Raw Financials'!$AS$42/'Raw Financials'!$L$9,0.25) -> 228820.93 | BF10: ='Annual P&L'!$P$9*IFERROR('Raw Financials'!$AP$42/'Raw Financials'!$L$9,0.25) -> 207066.89 | BG10: ='Annual P&L'!$P$9*IFERROR('Raw Financials'!$AQ$42/'Raw Financials'!$L$9,0.25) -> 220281.54 | BH10: ='Annual P&L'!$P$9*IFERROR('Raw Financials'!$AR$42/'Raw Financials'!$L$9,0.25) -> 226416.03 | BI10: ='Annual P&L'!$P$9*IFERROR('Raw Financials'!$AS$42/'Raw Financials'!$L$9,0.25) -> 240875
A11: Gross margin | B11: =IFERROR(B10/B6,"") -> 0.43634572 | C11: =IFERROR(C10/C6,"") -> 0.44230214 | D11: =IFERROR(D10/D6,"") -> 0.44381726 | E11: =IFERROR(E10/E6,"") -> 0.43539596 | F11: =IFERROR(F10/F6,"") -> 0.42665074 | G11: =IFERROR(G10/G6,"") -> 0.43539134 | H11: =IFERROR(H10/H6,"") -> 0.43238608 | I11: =IFERROR(I10/I6,"") -> 0.43752108 | ... BI11: =IFERROR(BI10/BI6,"") -> 0.28473444
A12: Total operating expenses | B12: ='Raw Financials'!$B$56 -> 189197.1 | C12: ='Raw Financials'!$C$56 -> 198119.4 | D12: ='Raw Financials'!$D$56 -> 200877.9 | E12: ='Raw Financials'!$E$56 -> 210366.94 | F12: ='Raw Financials'!$F$56 -> 219580 | G12: ='Raw Financials'!$G$56 -> 216670 | H12: ='Raw Financials'!$H$56 -> 220020 | I12: ='Raw Financials'!$I$56 -> 220150 | J12: ='Raw Financials'!$J$56 -> 226700 | K12: ='Raw Financials'!$K$56 -> 228810 | L12: ='Raw Financials'!$L$56 -> 231230 | M12: ='Raw Financials'!$M$56 -> 239280 | N12: ='Raw Financials'!$N$56 -> 256830 | O12: ='Raw Financials'!$O$56 -> 270830 | P12: ='Raw Financials'!$P$56 -> 277740 | Q12: ='Raw Financials'!$Q$56 -> 284730 | R12: ='Raw Financials'!$R$56 -> 289520 | S12: ='Raw Financials'!$S$56 -> 296160 | T12: ='Raw Financials'!$T$56 -> 298800 | U12: ='Raw Financials'!$U$56 -> 299210 | V12: ='Raw Financials'!$V$56 -> 292740 | W12: ='Raw Financials'!$W$56 -> 308380 | X12: ='Raw Financials'!$X$56 -> 308310 | Y12: ='Raw Financials'!$Y$56 -> 319710 | Z12: ='Raw Financials'!$Z$56 -> 338230 | AA12: ='Raw Financials'!$AA$56 -> 348670 | AB12: ='Raw Financials'!$AB$56 -> 366480 | AC12: ='Raw Financials'!$AC$56 -> 379630 | AD12: ='Raw Financials'!$AD$56 -> 405720 | AE12: ='Raw Financials'!$AE$56 -> 420300 | AF12: ='Raw Financials'!$AF$56 -> 439450 | AG12: ='Raw Financials'!$AG$56 -> 446740 | AH12: ='Raw Financials'!$AH$56 -> 456260 | AI12: ='Raw Financials'!$AI$56 -> 452100 | AJ12: ='Raw Financials'!$AJ$56 -> 463860 | AK12: ='Raw Financials'!$AK$56 -> 453190 | AL12: ='Raw Financials'!$AL$56 -> 471710 | AM12: ='Raw Financials'!$AM$56 -> 487940 | AN12: ='Raw Financials'!$AN$56 -> 483160 | AO12: ='Raw Financials'!$AO$56 -> 488780 | AP12: ='Raw Financials'!$AP$56 -> 479230 | AQ12: ='Raw Financials'!$AQ$56 -> 503690 | AR12: ='Raw Financials'!$AR$56 -> 535890 | AS12: ='Raw Financials'!$AS$56 -> 528280 | AT12: ='Raw Financials'!$AT$56 -> 556260 | AU12: =('Annual P&L'!$M$12-'Quarterly P&L'!$AT$12)*IFERROR('Raw Financials'!$AQ$56/SUM('Raw Financials'!$AQ$56,'Raw Financials'!$AR$56,'Raw Financials'!$AS$56),1/3) -> 492394.03 | AV12: =('Annual P&L'!$M$12-'Quarterly P&L'!$AT$12)*IFERROR('Raw Financials'!$AR$56/SUM('Raw Financials'!$AQ$56,'Raw Financials'!$AR$56,'Raw Financials'!$AS$56),1/3) -> 523871.9 | AW12: =('Annual P&L'!$M$12-'Quarterly P&L'!$AT$12)*IFERROR('Raw Financials'!$AS$56/SUM('Raw Financials'!$AQ$56,'Raw Financials'!$AR$56,'Raw Financials'!$AS$56),1/3) -> 516432.57 | AX12: ='Annual P&L'!$N$12*IFERROR('Raw Financials'!$AP$56/'Raw Financials'!$L$23,0.25) -> 512883.2 | AY12: ='Annual P&L'!$N$12*IFERROR('Raw Financials'!$AQ$56/'Raw Financials'!$L$23,0.25) -> 539060.86 | AZ12: ='Annual P&L'!$N$12*IFERROR('Raw Financials'!$AR$56/'Raw Financials'!$L$23,0.25) -> 573522.06 | BA12: ='Annual P&L'!$N$12*IFERROR('Raw Financials'!$AS$56/'Raw Financials'!$L$23,0.25) -> 565377.66 | BB12: ='Annual P&L'!$O$12*IFERROR('Raw Financials'!$AP$56/'Raw Financials'!$L$23,0.25) -> 536256.74 | BC12: ='Annual P&L'!$O$12*IFERROR('Raw Financials'!$AQ$56/'Raw Financials'!$L$23,0.25) -> 563627.4 | BD12: ='Annual P&L'!$O$12*IFERROR('Raw Financials'!$AR$56/'Raw Financials'!$L$23,0.25) -> 599659.09 | BE12: ='Annual P&L'!$O$12*IFERROR('Raw Financials'!$AS$56/'Raw Financials'!$L$23,0.25) -> 591143.52 | BF12: ='Annual P&L'!$P$12*IFERROR('Raw Financials'!$AP$56/'Raw Financials'!$L$23,0.25) -> 560994.16 | BG12: ='Annual P&L'!$P$12*IFERROR('Raw Financials'!$AQ$56/'Raw Financials'!$L$23,0.25) -> 589627.42 | BH12: ='Annual P&L'!$P$12*IFERROR('Raw Financials'!$AR$56/'Raw Financials'!$L$23,0.25) -> 627321.25 | BI12: ='Annual P&L'!$P$12*IFERROR('Raw Financials'!$AS$56/'Raw Financials'!$L$23,0.25) -> 618412.86
A13: Operating income | B13: ='Raw Financials'!$B$57 -> 67484.1 | C13: ='Raw Financials'!$C$57 -> 73535.4 | D13: ='Raw Financials'!$D$57 -> 72762.2 | E13: ='Raw Financials'!$E$57 -> 74119.2 | F13: ='Raw Financials'!$F$57 -> 73470 | G13: ='Raw Financials'!$G$57 -> 76170 | H13: ='Raw Financials'!$H$57 -> 77330 | I13: ='Raw Financials'!$I$57 -> 76270 | J13: ='Raw Financials'!$J$57 -> 69140 | K13: ='Raw Financials'!$K$57 -> 76600 | L13: ='Raw Financials'!$L$57 -> 77810 | M13: ='Raw Financials'!$M$57 -> 81470 | N13: ='Raw Financials'!$N$57 -> 85780 | O13: ='Raw Financials'!$O$57 -> 97710 | P13: ='Raw Financials'!$P$57 -> 95640 | Q13: ='Raw Financials'!$Q$57 -> 95370 | R13: ='Raw Financials'!$R$57 -> 92200 | S13: ='Raw Financials'!$S$57 -> 93610 | T13: ='Raw Financials'!$T$57 -> 99740 | U13: ='Raw Financials'!$U$57 -> 100250 | V13: ='Raw Financials'!$V$57 -> 90480 | W13: ='Raw Financials'!$W$57 -> 92970 | X13: ='Raw Financials'!$X$57 -> 111840 | Y13: ='Raw Financials'!$Y$57 -> 117340 | Z13: ='Raw Financials'!$Z$57 -> 115880 | AA13: ='Raw Financials'!$AA$57 -> 120000 | AB13: ='Raw Financials'!$AB$57 -> 122370 | AC13: ='Raw Financials'!$AC$57 -> 126280 | AD13: ='Raw Financials'!$AD$57 -> 121860 | AE13: ='Raw Financials'!$AE$57 -> 132790 | AF13: ='Raw Financials'!$AF$57 -> 142840 | AG13: ='Raw Financials'!$AG$57 -> 144880 | AH13: ='Raw Financials'!$AH$57 -> 137550 | AI13: ='Raw Financials'!$AI$57 -> 144820 | AJ13: ='Raw Financials'!$AJ$57 -> 141970 | AK13: ='Raw Financials'!$AK$57 -> 159180 | AL13: ='Raw Financials'!$AL$57 -> 154420 | AM13: ='Raw Financials'!$AM$57 -> 154650 | AN13: ='Raw Financials'!$AN$57 -> 156570 | AO13: ='Raw Financials'!$AO$57 -> 156010 | AP13: ='Raw Financials'!$AP$57 -> 155140 | AQ13: ='Raw Financials'!$AQ$57 -> 154300 | AR13: ='Raw Financials'!$AR$57 -> 134980 | AS13: ='Raw Financials'!$AS$57 -> 178700 | AT13: ='Raw Financials'!$AT$57 -> 166490 | AU13: =('Annual P&L'!$M$13-'Quarterly P&L'!$AT$13)*IFERROR('Raw Financials'!$AQ$57/SUM('Raw Financials'!$AQ$57,'Raw Financials'!$AR$57,'Raw Financials'!$AS$57),1/3) -> 165000.38 | AV13: =('Annual P&L'!$M$13-'Quarterly P&L'!$AT$13)*IFERROR('Raw Financials'!$AR$57/SUM('Raw Financials'!$AQ$57,'Raw Financials'!$AR$57,'Raw Financials'!$AS$57),1/3) -> 144340.58 | AW13: =('Annual P&L'!$M$13-'Quarterly P&L'!$AT$13)*IFERROR('Raw Financials'!$AS$57/SUM('Raw Financials'!$AQ$57,'Raw Financials'!$AR$57,'Raw Financials'!$AS$57),1/3) -> 191092.47 | AX13: ='Annual P&L'!$N$13*IFERROR('Raw Financials'!$AP$57/'Raw Financials'!$L$24,0.25) -> 177003.82 | AY13: ='Annual P&L'!$N$13*IFERROR('Raw Financials'!$AQ$57/'Raw Financials'!$L$24,0.25) -> 176045.44 | AZ13: ='Annual P&L'!$N$13*IFERROR('Raw Financials'!$AR$57/'Raw Financials'!$L$24,0.25) -> 154002.68 | BA13: ='Annual P&L'!$N$13*IFERROR('Raw Financials'!$AS$57/'Raw Financials'!$L$24,0.25) -> 203884.12 | BB13: ='Annual P&L'!$O$13*IFERROR('Raw Financials'!$AP$57/'Raw Financials'!$L$24,0.25) -> 188083.91 | BC13: ='Annual P&L'!$O$13*IFERROR('Raw Financials'!$AQ$57/'Raw Financials'!$L$24,0.25) -> 187065.53 | BD13: ='Annual P&L'!$O$13*IFERROR('Raw Financials'!$AR$57/'Raw Financials'!$L$24,0.25) -> 163642.94 | BE13: ='Annual P&L'!$O$13*IFERROR('Raw Financials'!$AS$57/'Raw Financials'!$L$24,0.25) -> 216646.86 | BF13: ='Annual P&L'!$P$13*IFERROR('Raw Financials'!$AP$57/'Raw Financials'!$L$24,0.25) -> 198875.88 | BG13: ='Annual P&L'!$P$13*IFERROR('Raw Financials'!$AQ$57/'Raw Financials'!$L$24,0.25) -> 197799.08 | BH13: ='Annual P&L'!$P$13*IFERROR('Raw Financials'!$AR$57/'Raw Financials'!$L$24,0.25) -> 173032.53 | BI13: ='Annual P&L'!$P$13*IFERROR('Raw Financials'!$AS$57/'Raw Financials'!$L$24,0.25) -> 229077.74
A14: Operating margin | B14: =IFERROR(B13/B6,"") -> 0.26291028 | C14: =IFERROR(C13/C6,"") -> 0.27069428 | D14: =IFERROR(D13/D6,"") -> 0.26590474 | E14: =IFERROR(E13/E6,"") -> 0.26053716 | F14: =IFERROR(F13/F6,"") -> 0.25070807 | G14: =IFERROR(G13/G6,"") -> 0.26010791 | H14: =IFERROR(H13/H6,"") -> 0.2600639 | I14: =IFERROR(I13/I6,"") -> 0.25730383 | ... BI14: =IFERROR(BI13/BI6,"") -> 0.27078909
A15: Other income / (expense) | B15: ='Raw Financials'!$B$58 -> 7710.6 | C15: ='Raw Financials'!$C$58 -> 6750.4 | D15: ='Raw Financials'!$D$58 -> 6990.3 | E15: ='Raw Financials'!$E$58 -> 9050.3 | F15: ='Raw Financials'!$F$58 -> 9630 | G15: ='Raw Financials'!$G$58 -> 10520 | H15: ='Raw Financials'!$H$58 -> 11850 | I15: ='Raw Financials'!$I$58 -> 9890 | J15: ='Raw Financials'!$J$58 -> 9320 | K15: ='Raw Financials'!$K$58 -> 8120 | L15: ='Raw Financials'!$L$58 -> 8640 | M15: ='Raw Financials'!$M$58 -> 9820 | N15: ='Raw Financials'!$N$58 -> 12080 | O15: ='Raw Financials'!$O$58 -> 5930 | P15: ='Raw Financials'!$P$58 -> 11470 | Q15: ='Raw Financials'!$Q$58 -> 11650 | R15: ='Raw Financials'!$R$58 -> 14180 | S15: ='Raw Financials'!$S$58 -> 11680 | T15: ='Raw Financials'!$T$58 -> 5950 | U15: ='Raw Financials'!$U$58 -> 4870 | V15: ='Raw Financials'!$V$58 -> 4560 | W15: ='Raw Financials'!$W$58 -> 7400 | X15: ='Raw Financials'!$X$58 -> 5080 | Y15: ='Raw Financials'!$Y$58 -> 7930 | Z15: ='Raw Financials'!$Z$58 -> 5750 | AA15: ='Raw Financials'!$AA$58 -> 9690 | AB15: ='Raw Financials'!$AB$58 -> 9540 | AC15: ='Raw Financials'!$AC$58 -> 7360 | AD15: ='Raw Financials'!$AD$58 -> 5900 | AE15: ='Raw Financials'!$AE$58 -> 8170 | AF15: ='Raw Financials'!$AF$58 -> 3600 | AG15: ='Raw Financials'!$AG$58 -> 9030 | AH15: ='Raw Financials'!$AH$58 -> 12340 | AI15: ='Raw Financials'!$AI$58 -> 8470 | AJ15: ='Raw Financials'!$AJ$58 -> 6320 | AK15: ='Raw Financials'!$AK$58 -> 9310 | AL15: ='Raw Financials'!$AL$58 -> 7890 | AM15: ='Raw Financials'!$AM$58 -> 5670 | AN15: ='Raw Financials'!$AN$58 -> 10090 | AO15: ='Raw Financials'!$AO$58 -> 8010 | AP15: ='Raw Financials'!$AP$58 -> 14650 | AQ15: ='Raw Financials'!$AQ$58 -> 6380 | AR15: ='Raw Financials'!$AR$58 -> 5800 | AS15: ='Raw Financials'!$AS$58 -> 4920 | AT15: ='Raw Financials'!$AT$58 -> 12950 | AU15: =('Annual P&L'!$M$15-'Quarterly P&L'!$AT$15)*IFERROR('Raw Financials'!$AQ$58/SUM('Raw Financials'!$AQ$58,'Raw Financials'!$AR$58,'Raw Financials'!$AS$58),1/3) -> 9563.4137 | AV15: =('Annual P&L'!$M$15-'Quarterly P&L'!$AT$15)*IFERROR('Raw Financials'!$AR$58/SUM('Raw Financials'!$AQ$58,'Raw Financials'!$AR$58,'Raw Financials'!$AS$58),1/3) -> 8694.0124 | AW15: =('Annual P&L'!$M$15-'Quarterly P&L'!$AT$15)*IFERROR('Raw Financials'!$AS$58/SUM('Raw Financials'!$AQ$58,'Raw Financials'!$AR$58,'Raw Financials'!$AS$58),1/3) -> 7374.9209 | AX15: ='Annual P&L'!$N$15*IFERROR('Raw Financials'!$AP$58/'Raw Financials'!$L$25,0.25) -> 18745.041 | AY15: ='Annual P&L'!$N$15*IFERROR('Raw Financials'!$AQ$58/'Raw Financials'!$L$25,0.25) -> 8163.3693 | AZ15: ='Annual P&L'!$N$15*IFERROR('Raw Financials'!$AR$58/'Raw Financials'!$L$25,0.25) -> 7421.2448 | BA15: ='Annual P&L'!$N$15*IFERROR('Raw Financials'!$AS$58/'Raw Financials'!$L$25,0.25) -> 6295.2628 | BB15: ='Annual P&L'!$O$15*IFERROR('Raw Financials'!$AP$58/'Raw Financials'!$L$25,0.25) -> 19677.494 | BC15: ='Annual P&L'!$O$15*IFERROR('Raw Financials'!$AQ$58/'Raw Financials'!$L$25,0.25) -> 8569.448 | BD15: ='Annual P&L'!$O$15*IFERROR('Raw Financials'!$AR$58/'Raw Financials'!$L$25,0.25) -> 7790.4072 | BE15: ='Annual P&L'!$O$15*IFERROR('Raw Financials'!$AS$58/'Raw Financials'!$L$25,0.25) -> 6608.4144 | BF15: ='Annual P&L'!$P$15*IFERROR('Raw Financials'!$AP$58/'Raw Financials'!$L$25,0.25) -> 20640.107 | BG15: ='Annual P&L'!$P$15*IFERROR('Raw Financials'!$AQ$58/'Raw Financials'!$L$25,0.25) -> 8988.661 | BH15: ='Annual P&L'!$P$15*IFERROR('Raw Financials'!$AR$58/'Raw Financials'!$L$25,0.25) -> 8171.51 | BI15: ='Annual P&L'!$P$15*IFERROR('Raw Financials'!$AS$58/'Raw Financials'!$L$25,0.25) -> 6931.6947
A16: PBT | B16: ='Raw Financials'!$B$59 -> 75194.7 | C16: ='Raw Financials'!$C$59 -> 80285.8 | D16: ='Raw Financials'!$D$59 -> 79752.6 | E16: ='Raw Financials'!$E$59 -> 83169.5 | F16: ='Raw Financials'!$F$59 -> 83100 | G16: ='Raw Financials'!$G$59 -> 86690 | H16: ='Raw Financials'!$H$59 -> 89180 | I16: ='Raw Financials'!$I$59 -> 86160 | J16: ='Raw Financials'!$J$59 -> 78460 | K16: ='Raw Financials'!$K$59 -> 84720 | L16: ='Raw Financials'!$L$59 -> 86450 | M16: ='Raw Financials'!$M$59 -> 91290 | N16: ='Raw Financials'!$N$59 -> 97860 | O16: ='Raw Financials'!$O$59 -> 103640 | P16: ='Raw Financials'!$P$59 -> 107110 | Q16: ='Raw Financials'!$Q$59 -> 107020 | R16: ='Raw Financials'!$R$59 -> 106380 | S16: ='Raw Financials'!$S$59 -> 105290 | T16: ='Raw Financials'!$T$59 -> 105690 | U16: ='Raw Financials'!$U$59 -> 105120 | V16: ='Raw Financials'!$V$59 -> 95040 | W16: ='Raw Financials'!$W$59 -> 100370 | X16: ='Raw Financials'!$X$59 -> 116920 | Y16: ='Raw Financials'!$Y$59 -> 125270 | Z16: ='Raw Financials'!$Z$59 -> 121630 | AA16: ='Raw Financials'!$AA$59 -> 129690 | AB16: ='Raw Financials'!$AB$59 -> 131910 | AC16: ='Raw Financials'!$AC$59 -> 133640 | AD16: ='Raw Financials'!$AD$59 -> 127760 | AE16: ='Raw Financials'!$AE$59 -> 140960 | AF16: ='Raw Financials'!$AF$59 -> 146440 | AG16: ='Raw Financials'!$AG$59 -> 153910 | AH16: ='Raw Financials'!$AH$59 -> 149890 | AI16: ='Raw Financials'!$AI$59 -> 153290 | AJ16: ='Raw Financials'!$AJ$59 -> 148290 | AK16: ='Raw Financials'!$AK$59 -> 168490 | AL16: ='Raw Financials'!$AL$59 -> 162310 | AM16: ='Raw Financials'!$AM$59 -> 160320 | AN16: ='Raw Financials'!$AN$59 -> 166660 | AO16: ='Raw Financials'!$AO$59 -> 164020 | AP16: ='Raw Financials'!$AP$59 -> 169790 | AQ16: ='Raw Financials'!$AQ$59 -> 160680 | AR16: ='Raw Financials'!$AR$59 -> 140780 | AS16: ='Raw Financials'!$AS$59 -> 183620 | AT16: ='Raw Financials'!$AT$59 -> 179440 | AU16: =('Annual P&L'!$M$16-'Quarterly P&L'!$AT$16)*IFERROR('Raw Financials'!$AQ$59/SUM('Raw Financials'!$AQ$59,'Raw Financials'!$AR$59,'Raw Financials'!$AS$59),1/3) -> 174256.31 | AV16: =('Annual P&L'!$M$16-'Quarterly P&L'!$AT$16)*IFERROR('Raw Financials'!$AR$59/SUM('Raw Financials'!$AQ$59,'Raw Financials'!$AR$59,'Raw Financials'!$AS$59),1/3) -> 152674.9 | AW16: =('Annual P&L'!$M$16-'Quarterly P&L'!$AT$16)*IFERROR('Raw Financials'!$AS$59/SUM('Raw Financials'!$AQ$59,'Raw Financials'!$AR$59,'Raw Financials'!$AS$59),1/3) -> 199134.57 | AX16: ='Annual P&L'!$N$16*IFERROR('Raw Financials'!$AP$59/'Raw Financials'!$L$26,0.25) -> 194859.34 | AY16: ='Annual P&L'!$N$16*IFERROR('Raw Financials'!$AQ$59/'Raw Financials'!$L$26,0.25) -> 184404.26 | AZ16: ='Annual P&L'!$N$16*IFERROR('Raw Financials'!$AR$59/'Raw Financials'!$L$26,0.25) -> 161566.04 | BA16: ='Annual P&L'!$N$16*IFERROR('Raw Financials'!$AS$59/'Raw Financials'!$L$26,0.25) -> 210731.33 | BB16: ='Annual P&L'!$O$16*IFERROR('Raw Financials'!$AP$59/'Raw Financials'!$L$26,0.25) -> 206921.76 | BC16: ='Annual P&L'!$O$16*IFERROR('Raw Financials'!$AQ$59/'Raw Financials'!$L$26,0.25) -> 195819.47 | BD16: ='Annual P&L'!$O$16*IFERROR('Raw Financials'!$AR$59/'Raw Financials'!$L$26,0.25) -> 171567.5 | BE16: ='Annual P&L'!$O$16*IFERROR('Raw Financials'!$AS$59/'Raw Financials'!$L$26,0.25) -> 223776.27 | BF16: ='Annual P&L'!$P$16*IFERROR('Raw Financials'!$AP$59/'Raw Financials'!$L$26,0.25) -> 218701.1 | BG16: ='Annual P&L'!$P$16*IFERROR('Raw Financials'!$AQ$59/'Raw Financials'!$L$26,0.25) -> 206966.79 | BH16: ='Annual P&L'!$P$16*IFERROR('Raw Financials'!$AR$59/'Raw Financials'!$L$26,0.25) -> 181334.24 | BI16: ='Annual P&L'!$P$16*IFERROR('Raw Financials'!$AS$59/'Raw Financials'!$L$26,0.25) -> 236515.08
A17: Income tax | B17: ='Raw Financials'!$B$60 -> 17467.6 | C17: ='Raw Financials'!$C$60 -> 19356.3 | D17: ='Raw Financials'!$D$60 -> 18500.8 | E17: ='Raw Financials'!$E$60 -> 19701.7 | F17: ='Raw Financials'!$F$60 -> 19920 | G17: ='Raw Financials'!$G$60 -> 20660 | H17: ='Raw Financials'!$H$60 -> 21040 | I17: ='Raw Financials'!$I$60 -> 19940 | J17: ='Raw Financials'!$J$60 -> 18960 | K17: ='Raw Financials'!$K$60 -> 20120 | L17: ='Raw Financials'!$L$60 -> 21000 | M17: ='Raw Financials'!$M$60 -> 22040 | N17: ='Raw Financials'!$N$60 -> 24240 | O17: ='Raw Financials'!$O$60 -> 24370 | P17: ='Raw Financials'!$P$60 -> 25900 | Q17: ='Raw Financials'!$Q$60 -> 25500 | R17: ='Raw Financials'!$R$60 -> 24850 | S17: ='Raw Financials'!$S$60 -> 24710 | T17: ='Raw Financials'!$T$60 -> 24260 | U17: ='Raw Financials'!$U$60 -> 24190 | V17: ='Raw Financials'!$V$60 -> 24550 | W17: ='Raw Financials'!$W$60 -> 25330 | X17: ='Raw Financials'!$X$60 -> 29650 | Y17: ='Raw Financials'!$Y$60 -> 32450 | Z17: ='Raw Financials'!$Z$60 -> 31320 | AA17: ='Raw Financials'!$AA$60 -> 33160 | AB17: ='Raw Financials'!$AB$60 -> 33850 | AC17: ='Raw Financials'!$AC$60 -> 34050 | AD17: ='Raw Financials'!$AD$60 -> 32570 | AE17: ='Raw Financials'!$AE$60 -> 36310 | AF17: ='Raw Financials'!$AF$60 -> 37610 | AG17: ='Raw Financials'!$AG$60 -> 39550 | AH17: ='Raw Financials'!$AH$60 -> 38690 | AI17: ='Raw Financials'!$AI$60 -> 39500 | AJ17: ='Raw Financials'!$AJ$60 -> 37320 | AK17: ='Raw Financials'!$AK$60 -> 43470 | AL17: ='Raw Financials'!$AL$60 -> 41260 | AM17: ='Raw Financials'!$AM$60 -> 40770 | AN17: ='Raw Financials'!$AN$60 -> 42220 | AO17: ='Raw Financials'!$AO$60 -> 41090 | AP17: ='Raw Financials'!$AP$60 -> 41600 | AQ17: ='Raw Financials'!$AQ$60 -> 39370 | AR17: ='Raw Financials'!$AR$60 -> 33580 | AS17: ='Raw Financials'!$AS$60 -> 45780 | AT17: ='Raw Financials'!$AT$60 -> 45240 | AU17: =('Annual P&L'!$M$18-'Quarterly P&L'!$AT$17)*IFERROR('Raw Financials'!$AQ$60/SUM('Raw Financials'!$AQ$60,'Raw Financials'!$AR$60,'Raw Financials'!$AS$60),1/3) -> 42314.183 | AV17: =('Annual P&L'!$M$18-'Quarterly P&L'!$AT$17)*IFERROR('Raw Financials'!$AR$60/SUM('Raw Financials'!$AQ$60,'Raw Financials'!$AR$60,'Raw Financials'!$AS$60),1/3) -> 36091.193 | AW17: =('Annual P&L'!$M$18-'Quarterly P&L'!$AT$17)*IFERROR('Raw Financials'!$AS$60/SUM('Raw Financials'!$AQ$60,'Raw Financials'!$AR$60,'Raw Financials'!$AS$60),1/3) -> 49203.538 | AX17: ='Annual P&L'!$N$18*IFERROR('Raw Financials'!$AP$60/'Raw Financials'!$L$27,0.25) -> 47775.897 | AY17: ='Annual P&L'!$N$18*IFERROR('Raw Financials'!$AQ$60/'Raw Financials'!$L$27,0.25) -> 45214.833 | AZ17: ='Annual P&L'!$N$18*IFERROR('Raw Financials'!$AR$60/'Raw Financials'!$L$27,0.25) -> 38565.255 | BA17: ='Annual P&L'!$N$18*IFERROR('Raw Financials'!$AS$60/'Raw Financials'!$L$27,0.25) -> 52576.455 | BB17: ='Annual P&L'!$O$18*IFERROR('Raw Financials'!$AP$60/'Raw Financials'!$L$27,0.25) -> 50733.377 | BC17: ='Annual P&L'!$O$18*IFERROR('Raw Financials'!$AQ$60/'Raw Financials'!$L$27,0.25) -> 48013.776 | BD17: ='Annual P&L'!$O$18*IFERROR('Raw Financials'!$AR$60/'Raw Financials'!$L$27,0.25) -> 40952.568 | BE17: ='Annual P&L'!$O$18*IFERROR('Raw Financials'!$AS$60/'Raw Financials'!$L$27,0.25) -> 55831.106 | BF17: ='Annual P&L'!$P$18*IFERROR('Raw Financials'!$AP$60/'Raw Financials'!$L$27,0.25) -> 53621.452 | BG17: ='Annual P&L'!$P$18*IFERROR('Raw Financials'!$AQ$60/'Raw Financials'!$L$27,0.25) -> 50747.033 | BH17: ='Annual P&L'!$P$18*IFERROR('Raw Financials'!$AR$60/'Raw Financials'!$L$27,0.25) -> 43283.855 | BI17: ='Annual P&L'!$P$18*IFERROR('Raw Financials'!$AS$60/'Raw Financials'!$L$27,0.25) -> 59009.376
A18: Net profit incl. NCI | B18: ='Raw Financials'!$B$61 -> 57727.1 | C18: ='Raw Financials'!$C$61 -> 60929.5 | D18: ='Raw Financials'!$D$61 -> 61251.8 | E18: ='Raw Financials'!$E$61 -> 63467.9 | F18: ='Raw Financials'!$F$61 -> 63180 | G18: ='Raw Financials'!$G$61 -> 66030 | H18: ='Raw Financials'!$H$61 -> 68140 | I18: ='Raw Financials'!$I$61 -> 66220 | J18: ='Raw Financials'!$J$61 -> 59500 | K18: ='Raw Financials'!$K$61 -> 64600 | L18: ='Raw Financials'!$L$61 -> 65450 | M18: ='Raw Financials'!$M$61 -> 69250 | N18: ='Raw Financials'!$N$61 -> 73620 | O18: ='Raw Financials'!$O$61 -> 79270 | P18: ='Raw Financials'!$P$61 -> 81210 | Q18: ='Raw Financials'!$Q$61 -> 81520 | R18: ='Raw Financials'!$R$61 -> 81530 | S18: ='Raw Financials'!$S$61 -> 80580 | T18: ='Raw Financials'!$T$61 -> 81430 | U18: ='Raw Financials'!$U$61 -> 80930 | V18: ='Raw Financials'!$V$61 -> 70490 | W18: ='Raw Financials'!$W$61 -> 75040 | X18: ='Raw Financials'!$X$61 -> 87270 | Y18: ='Raw Financials'!$Y$61 -> 92820 | Z18: ='Raw Financials'!$Z$61 -> 90310 | AA18: ='Raw Financials'!$AA$61 -> 96530 | AB18: ='Raw Financials'!$AB$61 -> 98060 | AC18: ='Raw Financials'!$AC$61 -> 99590 | AD18: ='Raw Financials'!$AD$61 -> 95190 | AE18: ='Raw Financials'!$AE$61 -> 104650 | AF18: ='Raw Financials'!$AF$61 -> 108830 | AG18: ='Raw Financials'!$AG$61 -> 114360 | AH18: ='Raw Financials'!$AH$61 -> 111200 | AI18: ='Raw Financials'!$AI$61 -> 113790 | AJ18: ='Raw Financials'!$AJ$61 -> 110970 | AK18: ='Raw Financials'!$AK$61 -> 125020 | AL18: ='Raw Financials'!$AL$61 -> 121050 | AM18: ='Raw Financials'!$AM$61 -> 119550 | AN18: ='Raw Financials'!$AN$61 -> 124440 | AO18: ='Raw Financials'!$AO$61 -> 122930 | AP18: ='Raw Financials'!$AP$61 -> 128190 | AQ18: ='Raw Financials'!$AQ$61 -> 121310 | AR18: ='Raw Financials'!$AR$61 -> 107200 | AS18: ='Raw Financials'!$AS$61 -> 137840 | AT18: ='Raw Financials'!$AT$61 -> 134200 | AU18: =('Annual P&L'!$M$20-'Quarterly P&L'!$AT$18)*IFERROR('Raw Financials'!$AQ$61/SUM('Raw Financials'!$AQ$61,'Raw Financials'!$AR$61,'Raw Financials'!$AS$61),1/3) -> 131941.59 | AV18: =('Annual P&L'!$M$20-'Quarterly P&L'!$AT$18)*IFERROR('Raw Financials'!$AR$61/SUM('Raw Financials'!$AQ$61,'Raw Financials'!$AR$61,'Raw Financials'!$AS$61),1/3) -> 116594.99 | AW18: =('Annual P&L'!$M$20-'Quarterly P&L'!$AT$18)*IFERROR('Raw Financials'!$AS$61/SUM('Raw Financials'!$AQ$61,'Raw Financials'!$AR$61,'Raw Financials'!$AS$61),1/3) -> 149920.28 | AX18: ='Annual P&L'!$N$20*IFERROR('Raw Financials'!$AP$61/'Raw Financials'!$L$28,0.25) -> 147083.48 | AY18: ='Annual P&L'!$N$20*IFERROR('Raw Financials'!$AQ$61/'Raw Financials'!$L$28,0.25) -> 139189.46 | AZ18: ='Annual P&L'!$N$20*IFERROR('Raw Financials'!$AR$61/'Raw Financials'!$L$28,0.25) -> 122999.84 | BA18: ='Annual P&L'!$N$20*IFERROR('Raw Financials'!$AS$61/'Raw Financials'!$L$28,0.25) -> 158155.76 | BB18: ='Annual P&L'!$O$20*IFERROR('Raw Financials'!$AP$61/'Raw Financials'!$L$28,0.25) -> 156188.42 | BC18: ='Annual P&L'!$O$20*IFERROR('Raw Financials'!$AQ$61/'Raw Financials'!$L$28,0.25) -> 147805.73 | BD18: ='Annual P&L'!$O$20*IFERROR('Raw Financials'!$AR$61/'Raw Financials'!$L$28,0.25) -> 130613.92 | BE18: ='Annual P&L'!$O$20*IFERROR('Raw Financials'!$AS$61/'Raw Financials'!$L$28,0.25) -> 167946.11 | BF18: ='Annual P&L'!$P$20*IFERROR('Raw Financials'!$AP$61/'Raw Financials'!$L$28,0.25) -> 165079.68 | BG18: ='Annual P&L'!$P$20*IFERROR('Raw Financials'!$AQ$61/'Raw Financials'!$L$28,0.25) -> 156219.8 | BH18: ='Annual P&L'!$P$20*IFERROR('Raw Financials'!$AR$61/'Raw Financials'!$L$28,0.25) -> 138049.32 | BI18: ='Annual P&L'!$P$20*IFERROR('Raw Financials'!$AS$61/'Raw Financials'!$L$28,0.25) -> 177506.69
A19: NCI | B19: ='Raw Financials'!$B$62 -> -637.6 | C19: ='Raw Financials'!$C$62 -> -377.5 | D19: ='Raw Financials'!$D$62 -> -156.4 | E19: ='Raw Financials'!$E$62 -> -55.8 | F19: ='Raw Financials'!$F$62 -> -10 | G19: ='Raw Financials'!$G$62 -> -170 | H19: ='Raw Financials'!$H$62 -> -360 | I19: ='Raw Financials'!$I$62 -> -140 | J19: ='Raw Financials'!$J$62 -> -50 | K19: ='Raw Financials'!$K$62 -> -140 | L19: ='Raw Financials'!$L$62 -> -140 | M19: ='Raw Financials'!$M$62 -> -210 | N19: ='Raw Financials'!$N$62 -> -220 | O19: ='Raw Financials'!$O$62 -> -260 | P19: ='Raw Financials'!$P$62 -> -160 | Q19: ='Raw Financials'!$Q$62 -> -260 | R19: ='Raw Financials'!$R$62 -> -220 | S19: ='Raw Financials'!$S$62 -> -160 | T19: ='Raw Financials'!$T$62 -> -250 | U19: ='Raw Financials'!$U$62 -> -440 | V19: ='Raw Financials'!$V$62 -> -410 | W19: ='Raw Financials'!$W$62 -> -290 | X19: ='Raw Financials'!$X$62 -> -260 | Y19: ='Raw Financials'!$Y$62 -> -360 | Z19: ='Raw Financials'!$Z$62 -> -230 | AA19: ='Raw Financials'!$AA$62 -> -290 | AB19: ='Raw Financials'!$AB$62 -> -370 | AC19: ='Raw Financials'!$AC$62 -> -330 | AD19: ='Raw Financials'!$AD$62 -> -410 | AE19: ='Raw Financials'!$AE$62 -> -340 | AF19: ='Raw Financials'!$AF$62 -> -370 | AG19: ='Raw Financials'!$AG$62 -> -440 | AH19: ='Raw Financials'!$AH$62 -> -460 | AI19: ='Raw Financials'!$AI$62 -> -380 | AJ19: ='Raw Financials'!$AJ$62 -> -390 | AK19: ='Raw Financials'!$AK$62 -> -680 | AL19: ='Raw Financials'!$AL$62 -> -650 | AM19: ='Raw Financials'!$AM$62 -> -460 | AN19: ='Raw Financials'!$AN$62 -> -640 | AO19: ='Raw Financials'!$AO$62 -> -690 | AP19: ='Raw Financials'!$AP$62 -> -590 | AQ19: ='Raw Financials'!$AQ$62 -> -560 | AR19: ='Raw Financials'!$AR$62 -> -630 | AS19: ='Raw Financials'!$AS$62 -> -660 | AT19: ='Raw Financials'!$AT$62 -> -710 | AU19: =('Annual P&L'!$M$21-'Quarterly P&L'!$AT$19)*IFERROR('Raw Financials'!$AQ$62/SUM('Raw Financials'!$AQ$62,'Raw Financials'!$AR$62,'Raw Financials'!$AS$62),1/3) -> -591.26444 | AV19: =('Annual P&L'!$M$21-'Quarterly P&L'!$AT$19)*IFERROR('Raw Financials'!$AR$62/SUM('Raw Financials'!$AQ$62,'Raw Financials'!$AR$62,'Raw Financials'!$AS$62),1/3) -> -665.17249 | AW19: =('Annual P&L'!$M$21-'Quarterly P&L'!$AT$19)*IFERROR('Raw Financials'!$AS$62/SUM('Raw Financials'!$AQ$62,'Raw Financials'!$AR$62,'Raw Financials'!$AS$62),1/3) -> -696.84737 | AX19: ='Annual P&L'!$N$21*IFERROR('Raw Financials'!$AP$62/'Raw Financials'!$L$29,0.25) -> -686.03041 | AY19: ='Annual P&L'!$N$21*IFERROR('Raw Financials'!$AQ$62/'Raw Financials'!$L$29,0.25) -> -651.1475 | AZ19: ='Annual P&L'!$N$21*IFERROR('Raw Financials'!$AR$62/'Raw Financials'!$L$29,0.25) -> -732.54094 | BA19: ='Annual P&L'!$N$21*IFERROR('Raw Financials'!$AS$62/'Raw Financials'!$L$29,0.25) -> -767.42384 | BB19: ='Annual P&L'!$O$21*IFERROR('Raw Financials'!$AP$62/'Raw Financials'!$L$29,0.25) -> -728.49788 | BC19: ='Annual P&L'!$O$21*IFERROR('Raw Financials'!$AQ$62/'Raw Financials'!$L$29,0.25) -> -691.45562 | BD19: ='Annual P&L'!$O$21*IFERROR('Raw Financials'!$AR$62/'Raw Financials'!$L$29,0.25) -> -777.88757 | BE19: ='Annual P&L'!$O$21*IFERROR('Raw Financials'!$AS$62/'Raw Financials'!$L$29,0.25) -> -814.92984 | BF19: ='Annual P&L'!$P$21*IFERROR('Raw Financials'!$AP$62/'Raw Financials'!$L$29,0.25) -> -769.96873 | BG19: ='Annual P&L'!$P$21*IFERROR('Raw Financials'!$AQ$62/'Raw Financials'!$L$29,0.25) -> -730.81778 | BH19: ='Annual P&L'!$P$21*IFERROR('Raw Financials'!$AR$62/'Raw Financials'!$L$29,0.25) -> -822.17 | BI19: ='Annual P&L'!$P$21*IFERROR('Raw Financials'!$AS$62/'Raw Financials'!$L$29,0.25) -> -861.32095
A20: Net income attributable | B20: ='Raw Financials'!$B$63 -> 57089.4 | C20: ='Raw Financials'!$C$63 -> 60552 | D20: ='Raw Financials'!$D$63 -> 61095.4 | E20: ='Raw Financials'!$E$63 -> 63412.1 | F20: ='Raw Financials'!$F$63 -> 63170 | G20: ='Raw Financials'!$G$63 -> 65860 | H20: ='Raw Financials'!$H$63 -> 67780 | I20: ='Raw Financials'!$I$63 -> 66080 | J20: ='Raw Financials'!$J$63 -> 59450 | K20: ='Raw Financials'!$K$63 -> 64460 | L20: ='Raw Financials'!$L$63 -> 65310 | M20: ='Raw Financials'!$M$63 -> 69040 | N20: ='Raw Financials'!$N$63 -> 73400 | O20: ='Raw Financials'!$O$63 -> 79010 | P20: ='Raw Financials'!$P$63 -> 81050 | Q20: ='Raw Financials'!$Q$63 -> 81260 | R20: ='Raw Financials'!$R$63 -> 81310 | S20: ='Raw Financials'!$S$63 -> 80420 | T20: ='Raw Financials'!$T$63 -> 81180 | U20: ='Raw Financials'!$U$63 -> 80490 | V20: ='Raw Financials'!$V$63 -> 70080 | W20: ='Raw Financials'!$W$63 -> 74750 | X20: ='Raw Financials'!$X$63 -> 87010 | Y20: ='Raw Financials'!$Y$63 -> 92460 | Z20: ='Raw Financials'!$Z$63 -> 90080 | AA20: ='Raw Financials'!$AA$63 -> 96240 | AB20: ='Raw Financials'!$AB$63 -> 97690 | AC20: ='Raw Financials'!$AC$63 -> 99260 | AD20: ='Raw Financials'!$AD$63 -> 94780 | AE20: ='Raw Financials'!$AE$63 -> 104310 | AF20: ='Raw Financials'!$AF$63 -> 108460 | AG20: ='Raw Financials'!$AG$63 -> 113920 | AH20: ='Raw Financials'!$AH$63 -> 110740 | AI20: ='Raw Financials'!$AI$63 -> 113410 | AJ20: ='Raw Financials'!$AJ$63 -> 110580 | AK20: ='Raw Financials'!$AK$63 -> 124340 | AL20: ='Raw Financials'!$AL$63 -> 120400 | AM20: ='Raw Financials'!$AM$63 -> 119090 | AN20: ='Raw Financials'!$AN$63 -> 123800 | AO20: ='Raw Financials'!$AO$63 -> 122240 | AP20: ='Raw Financials'!$AP$63 -> 127600 | AQ20: ='Raw Financials'!$AQ$63 -> 120750 | AR20: ='Raw Financials'!$AR$63 -> 106570 | AS20: ='Raw Financials'!$AS$63 -> 137180 | AT20: ='Raw Financials'!$AT$63 -> 133490 | AU20: =('Annual P&L'!$M$22-'Quarterly P&L'!$AT$20)*IFERROR('Raw Financials'!$AQ$63/SUM('Raw Financials'!$AQ$63,'Raw Financials'!$AR$63,'Raw Financials'!$AS$63),1/3) -> 131352.01 | AV20: =('Annual P&L'!$M$22-'Quarterly P&L'!$AT$20)*IFERROR('Raw Financials'!$AR$63/SUM('Raw Financials'!$AQ$63,'Raw Financials'!$AR$63,'Raw Financials'!$AS$63),1/3) -> 115926.99 | AW20: =('Annual P&L'!$M$22-'Quarterly P&L'!$AT$20)*IFERROR('Raw Financials'!$AS$63/SUM('Raw Financials'!$AQ$63,'Raw Financials'!$AR$63,'Raw Financials'!$AS$63),1/3) -> 149224.58 | AX20: ='Annual P&L'!$N$22*IFERROR('Raw Financials'!$AP$63/'Raw Financials'!$L$30,0.25) -> 146396.79 | AY20: ='Annual P&L'!$N$22*IFERROR('Raw Financials'!$AQ$63/'Raw Financials'!$L$30,0.25) -> 138537.72 | AZ20: ='Annual P&L'!$N$22*IFERROR('Raw Financials'!$AR$63/'Raw Financials'!$L$30,0.25) -> 122268.86 | BA20: ='Annual P&L'!$N$22*IFERROR('Raw Financials'!$AS$63/'Raw Financials'!$L$30,0.25) -> 157388.03 | BB20: ='Annual P&L'!$O$22*IFERROR('Raw Financials'!$AP$63/'Raw Financials'!$L$30,0.25) -> 155459.22 | BC20: ='Annual P&L'!$O$22*IFERROR('Raw Financials'!$AQ$63/'Raw Financials'!$L$30,0.25) -> 147113.65 | BD20: ='Annual P&L'!$O$22*IFERROR('Raw Financials'!$AR$63/'Raw Financials'!$L$30,0.25) -> 129837.69 | BE20: ='Annual P&L'!$O$22*IFERROR('Raw Financials'!$AS$63/'Raw Financials'!$L$30,0.25) -> 167130.85 | BF20: ='Annual P&L'!$P$22*IFERROR('Raw Financials'!$AP$63/'Raw Financials'!$L$30,0.25) -> 164308.98 | BG20: ='Annual P&L'!$P$22*IFERROR('Raw Financials'!$AQ$63/'Raw Financials'!$L$30,0.25) -> 155488.31 | BH20: ='Annual P&L'!$P$22*IFERROR('Raw Financials'!$AR$63/'Raw Financials'!$L$30,0.25) -> 137228.9 | BI20: ='Annual P&L'!$P$22*IFERROR('Raw Financials'!$AS$63/'Raw Financials'!$L$30,0.25) -> 176645.03
A21: Net margin | B21: =IFERROR(B20/B6,"") -> 0.22241373 | C21: =IFERROR(C20/C6,"") -> 0.22290053 | D21: =IFERROR(D20/D6,"") -> 0.22326918 | E21: =IFERROR(E20/E6,"") -> 0.22290052 | F21: =IFERROR(F20/F6,"") -> 0.21556048 | G21: =IFERROR(G20/G6,"") -> 0.22490097 | H21: =IFERROR(H20/H6,"") -> 0.22794686 | I21: =IFERROR(I20/I6,"") -> 0.22292693 | ... BI21: =IFERROR(BI20/BI6,"") -> 0.20880923
A22: EPS — basic | B22: ='Raw Financials'!$B$64 -> 29.15 | C22: ='Raw Financials'!$C$64 -> 30.82 | D22: ='Raw Financials'!$D$64 -> 31.01 | E22: ='Raw Financials'!$E$64 -> 32.18 | F22: ='Raw Financials'!$F$64 -> 32.06 | G22: ='Raw Financials'!$G$64 -> 33.43 | H22: ='Raw Financials'!$H$64 -> 34.4 | I22: ='Raw Financials'!$I$64 -> 33.52 | J22: ='Raw Financials'!$J$64 -> 30.4 | K22: ='Raw Financials'!$K$64 -> 33.67 | L22: ='Raw Financials'!$L$64 -> 34.12 | M22: ='Raw Financials'!$M$64 -> 36.07 | N22: ='Raw Financials'!$N$64 -> 19.17 | O22: ='Raw Financials'!$O$64 -> 20.66 | P22: ='Raw Financials'!$P$64 -> 21.6 | Q22: ='Raw Financials'!$Q$64 -> 21.65 | R22: ='Raw Financials'!$R$64 -> 21.67 | S22: ='Raw Financials'!$S$64 -> 21.43 | T22: ='Raw Financials'!$T$64 -> 21.63 | U22: ='Raw Financials'!$U$64 -> 21.45 | V22: ='Raw Financials'!$V$64 -> 18.68 | W22: ='Raw Financials'!$W$64 -> 19.33 | X22: ='Raw Financials'!$X$64 -> 23.19 | Y22: ='Raw Financials'!$Y$64 -> 24.97 | Z22: ='Raw Financials'!$Z$64 -> 24.35 | AA22: ='Raw Financials'!$AA$64 -> 26.02 | AB22: ='Raw Financials'!$AB$64 -> 26.41 | AC22: ='Raw Financials'!$AC$64 -> 26.85 | AD22: ='Raw Financials'!$AD$64 -> 25.9 | AE22: ='Raw Financials'!$AE$64 -> 28.51 | AF22: ='Raw Financials'!$AF$64 -> 29.64 | AG22: ='Raw Financials'!$AG$64 -> 31.14 | AH22: ='Raw Financials'!$AH$64 -> 30.26 | AI22: ='Raw Financials'!$AI$64 -> 31 | AJ22: ='Raw Financials'!$AJ$64 -> 30.29 | AK22: ='Raw Financials'!$AK$64 -> 34.37 | AL22: ='Raw Financials'!$AL$64 -> 33.28 | AM22: ='Raw Financials'!$AM$64 -> 32.92 | AN22: ='Raw Financials'!$AN$64 -> 34.21 | AO22: ='Raw Financials'!$AO$64 -> 33.79 | AP22: ='Raw Financials'!$AP$64 -> 35.27 | AQ22: ='Raw Financials'!$AQ$64 -> 33.37 | AR22: ='Raw Financials'!$AR$64 -> 29.45 | AS22: ='Raw Financials'!$AS$64 -> 37.92 | AT22: ='Raw Financials'!$AT$64 -> 36.9 | AU22: =AU20*1000000/AU25 -> 36.304265 | AV22: =AV20*1000000/AV25 -> 32.040957 | AW22: =AW20*1000000/AW25 -> 41.24405 | AX22: =AX20*1000000/AX25 -> 40.46248 | AY22: =AY20*1000000/AY25 -> 38.290317 | AZ22: =AZ20*1000000/AZ25 -> 33.793781 | BA22: =BA20*1000000/BA25 -> 43.500337 | BB22: =BB20*1000000/BB25 -> 42.967237 | ... BI22: =BI20*1000000/BI25 -> 48.822762
A23: EPS — diluted | B23: ='Raw Financials'!$B$65 -> 29.15 | C23: ='Raw Financials'!$C$65 -> 30.82 | D23: ='Raw Financials'!$D$65 -> 31.01 | E23: ='Raw Financials'!$E$65 -> 32.18 | F23: ='Raw Financials'!$F$65 -> 32.06 | G23: ='Raw Financials'!$G$65 -> 33.43 | H23: ='Raw Financials'!$H$65 -> 34.4 | I23: ='Raw Financials'!$I$65 -> 33.52 | J23: ='Raw Financials'!$J$65 -> 30.4 | K23: ='Raw Financials'!$K$65 -> 33.67 | L23: ='Raw Financials'!$L$65 -> 34.12 | M23: ='Raw Financials'!$M$65 -> 36.07 | N23: ='Raw Financials'!$N$65 -> 19.17 | O23: ='Raw Financials'!$O$65 -> 20.66 | P23: ='Raw Financials'!$P$65 -> 21.6 | Q23: ='Raw Financials'!$Q$65 -> 21.65 | R23: ='Raw Financials'!$R$65 -> 21.67 | S23: ='Raw Financials'!$S$65 -> 21.43 | T23: ='Raw Financials'!$T$65 -> 21.63 | U23: ='Raw Financials'!$U$65 -> 21.45 | V23: ='Raw Financials'!$V$65 -> 18.68 | W23: ='Raw Financials'!$W$65 -> 19.33 | X23: ='Raw Financials'!$X$65 -> 23.19 | Y23: ='Raw Financials'!$Y$65 -> 24.97 | Z23: ='Raw Financials'!$Z$65 -> 24.35 | AA23: ='Raw Financials'!$AA$65 -> 26.02 | AB23: ='Raw Financials'!$AB$65 -> 26.41 | AC23: ='Raw Financials'!$AC$65 -> 26.85 | AD23: ='Raw Financials'!$AD$65 -> 25.9 | AE23: ='Raw Financials'!$AE$65 -> 28.51 | AF23: ='Raw Financials'!$AF$65 -> 29.64 | AG23: ='Raw Financials'!$AG$65 -> 31.14 | AH23: ='Raw Financials'!$AH$65 -> 30.26 | AI23: ='Raw Financials'!$AI$65 -> 31 | AJ23: ='Raw Financials'!$AJ$65 -> 30.29 | AK23: ='Raw Financials'!$AK$65 -> 34.37 | AL23: ='Raw Financials'!$AL$65 -> 33.28 | AM23: ='Raw Financials'!$AM$65 -> 32.92 | AN23: ='Raw Financials'!$AN$65 -> 34.21 | AO23: ='Raw Financials'!$AO$65 -> 33.79 | AP23: ='Raw Financials'!$AP$65 -> 35.27 | AQ23: ='Raw Financials'!$AQ$65 -> 33.37 | AR23: ='Raw Financials'!$AR$65 -> 29.45 | AS23: ='Raw Financials'!$AS$65 -> 37.92 | AT23: ='Raw Financials'!$AT$65 -> 36.9 | AU23: =AU22 -> 36.304265 | AV23: =AV22 -> 32.040957 | AW23: =AW22 -> 41.24405 | AX23: =AX22 -> 40.46248 | AY23: =AY22 -> 38.290317 | AZ23: =AZ22 -> 33.793781 | BA23: =BA22 -> 43.500337 | BB23: =BB22 -> 42.967237 | ... BI23: =BI22 -> 48.822762
A24: DPS | B24: ='Raw Financials'!$B$66 -> 5.5 | C24: ='Raw Financials'!$C$66 -> 5.5 | D24: ='Raw Financials'!$D$66 -> 5.5 | E24: ='Raw Financials'!$E$66 -> 27 | F24: ='Raw Financials'!$F$66 -> 6.5 | G24: ='Raw Financials'!$G$66 -> 6.5 | H24: ='Raw Financials'!$H$66 -> 6.5 | I24: ='Raw Financials'!$I$66 -> 27.5 | J24: ='Raw Financials'!$J$66 -> 7 | K24: ='Raw Financials'!$K$66 -> 7 | L24: ='Raw Financials'!$L$66 -> 7 | M24: ='Raw Financials'!$M$66 -> 29 | N24: ='Raw Financials'!$N$66 -> 4 | O24: ='Raw Financials'!$O$66 -> 4 | P24: ='Raw Financials'!$P$66 -> 4 | Q24: ='Raw Financials'!$Q$66 -> 18 | R24: ='Raw Financials'!$R$66 -> 5 | S24: ='Raw Financials'!$S$66 -> 45 | T24: ='Raw Financials'!$T$66 -> 5 | U24: ='Raw Financials'!$U$66 -> 18 | V24: ='Raw Financials'!$V$66 -> 5 | W24: ='Raw Financials'!$W$66 -> 12 | X24: ='Raw Financials'!$X$66 -> 6 | Y24: ='Raw Financials'!$Y$66 -> 15 | Z24: ='Raw Financials'!$Z$66 -> 7 | AA24: ='Raw Financials'!$AA$66 -> 7 | AB24: ='Raw Financials'!$AB$66 -> 7 | AC24: ='Raw Financials'!$AC$66 -> 22 | AD24: ='Raw Financials'!$AD$66 -> 8 | AE24: ='Raw Financials'!$AE$66 -> 8 | AF24: ='Raw Financials'!$AF$66 -> 75 | AG24: ='Raw Financials'!$AG$66 -> 24 | AH24: ='Raw Financials'!$AH$66 -> 9 | AI24: ='Raw Financials'!$AI$66 -> 9 | AJ24: ='Raw Financials'!$AJ$66 -> 27 | AK24: ='Raw Financials'!$AK$66 -> 28 | AL24: ='Raw Financials'!$AL$66 -> 10 | AM24: ='Raw Financials'!$AM$66 -> 10 | AN24: ='Raw Financials'!$AN$66 -> 76 | AO24: ='Raw Financials'!$AO$66 -> 30 | AP24: ='Raw Financials'!$AP$66 -> 11 | AQ24: ='Raw Financials'!$AQ$66 -> 11 | AR24: ='Raw Financials'!$AR$66 -> 57 | AS24: ='Raw Financials'!$AS$66 -> 31 | AT24: ='Raw Financials'!$AT$66 -> 12 | AU24: =('Annual P&L'!$M$27-'Quarterly P&L'!$AT$24)*IFERROR('Raw Financials'!$AQ$66/SUM('Raw Financials'!$AQ$66,'Raw Financials'!$AR$66,'Raw Financials'!$AS$66),1/3) -> 11.687507 | AV24: =('Annual P&L'!$M$27-'Quarterly P&L'!$AT$24)*IFERROR('Raw Financials'!$AR$66/SUM('Raw Financials'!$AQ$66,'Raw Financials'!$AR$66,'Raw Financials'!$AS$66),1/3) -> 60.562537 | AW24: =('Annual P&L'!$M$27-'Quarterly P&L'!$AT$24)*IFERROR('Raw Financials'!$AS$66/SUM('Raw Financials'!$AQ$66,'Raw Financials'!$AR$66,'Raw Financials'!$AS$66),1/3) -> 32.93752 | AX24: ='Annual P&L'!$N$27*IFERROR('Raw Financials'!$AP$66/'Raw Financials'!$L$33,0.25) -> 12.483753 | AY24: ='Annual P&L'!$N$27*IFERROR('Raw Financials'!$AQ$66/'Raw Financials'!$L$33,0.25) -> 12.483753 | AZ24: ='Annual P&L'!$N$27*IFERROR('Raw Financials'!$AR$66/'Raw Financials'!$L$33,0.25) -> 64.688539 | BA24: ='Annual P&L'!$N$27*IFERROR('Raw Financials'!$AS$66/'Raw Financials'!$L$33,0.25) -> 35.181486 | BB24: ='Annual P&L'!$O$27*IFERROR('Raw Financials'!$AP$66/'Raw Financials'!$L$33,0.25) -> 13.256537 | BC24: ='Annual P&L'!$O$27*IFERROR('Raw Financials'!$AQ$66/'Raw Financials'!$L$33,0.25) -> 13.256537 | BD24: ='Annual P&L'!$O$27*IFERROR('Raw Financials'!$AR$66/'Raw Financials'!$L$33,0.25) -> 68.692967 | BE24: ='Annual P&L'!$O$27*IFERROR('Raw Financials'!$AS$66/'Raw Financials'!$L$33,0.25) -> 37.359333 | BF24: ='Annual P&L'!$P$27*IFERROR('Raw Financials'!$AP$66/'Raw Financials'!$L$33,0.25) -> 14.011186 | BG24: ='Annual P&L'!$P$27*IFERROR('Raw Financials'!$AQ$66/'Raw Financials'!$L$33,0.25) -> 14.011186 | BH24: ='Annual P&L'!$P$27*IFERROR('Raw Financials'!$AR$66/'Raw Financials'!$L$33,0.25) -> 72.603418 | BI24: ='Annual P&L'!$P$27*IFERROR('Raw Financials'!$AS$66/'Raw Financials'!$L$33,0.25) -> 39.48607
A25: Weighted average shares | B25: ='Raw Financials'!$B$67 -> 1958727979 | C25: ='Raw Financials'!$C$67 -> 1964577960 | D25: ='Raw Financials'!$D$67 -> 1970427941 | E25: ='Raw Financials'!$E$67 -> 1966040455 | F25: ='Raw Financials'!$F$67 -> 1970427941 | G25: ='Raw Financials'!$G$67 -> 1970427941 | H25: ='Raw Financials'!$H$67 -> 1970427941 | I25: ='Raw Financials'!$I$67 -> 1970427941 | J25: ='Raw Financials'!$J$67 -> 1955621695 | K25: ='Raw Financials'!$K$67 -> 1914287591 | L25: ='Raw Financials'!$L$67 -> 1914287591 | M25: ='Raw Financials'!$M$67 -> 1914287591 | N25: ='Raw Financials'!$N$67 -> 3828575182 | O25: ='Raw Financials'!$O$67 -> 3825262553 | P25: ='Raw Financials'!$P$67 -> 3752384706 | Q25: ='Raw Financials'!$Q$67 -> 3752384706 | R25: ='Raw Financials'!$R$67 -> 3752384706 | S25: ='Raw Financials'!$S$67 -> 3752384706 | T25: ='Raw Financials'!$T$67 -> 3752384706 | U25: ='Raw Financials'!$U$67 -> 3752384706 | V25: ='Raw Financials'!$V$67 -> 3752384706 | W25: ='Raw Financials'!$W$67 -> 3752384706 | X25: ='Raw Financials'!$X$67 -> 3752384706 | Y25: ='Raw Financials'!$Y$67 -> 3.7026069e+09 | Z25: ='Raw Financials'!$Z$67 -> 3699051373 | AA25: ='Raw Financials'!$AA$67 -> 3699051373 | AB25: ='Raw Financials'!$AB$67 -> 3699051373 | AC25: ='Raw Financials'!$AC$67 -> 3.6981625e+09 | AD25: ='Raw Financials'!$AD$67 -> 3659051373 | AE25: ='Raw Financials'!$AE$67 -> 3659051373 | AF25: ='Raw Financials'!$AF$67 -> 3659051373 | AG25: ='Raw Financials'!$AG$67 -> 3659051373 | AH25: ='Raw Financials'!$AH$67 -> 3659051373 | AI25: ='Raw Financials'!$AI$67 -> 3659051373 | AJ25: ='Raw Financials'!$AJ$67 -> 3.6510367e+09 | AK25: ='Raw Financials'!$AK$67 -> 3618087518 | AL25: ='Raw Financials'!$AL$67 -> 3618087518 | AM25: ='Raw Financials'!$AM$67 -> 3618087518 | AN25: ='Raw Financials'!$AN$67 -> 3618087518 | AO25: ='Raw Financials'!$AO$67 -> 3618087518 | AP25: ='Raw Financials'!$AP$67 -> 3618087518 | AQ25: ='Raw Financials'!$AQ$67 -> 3618087518 | AR25: ='Raw Financials'!$AR$67 -> 3618087518 | AS25: ='Raw Financials'!$AS$67 -> 3618087518 | AT25: ='Raw Financials'!$AT$67 -> 3618087518 | AU25: ='Annual P&L'!$M$29 -> 3618087518 | AV25: ='Annual P&L'!$M$29 -> 3618087518 | AW25: ='Annual P&L'!$M$29 -> 3618087518 | AX25: ='Annual P&L'!$N$29 -> 3618087518 | AY25: ='Annual P&L'!$N$29 -> 3618087518 | AZ25: ='Annual P&L'!$N$29 -> 3618087518 | BA25: ='Annual P&L'!$N$29 -> 3618087518 | BB25: ='Annual P&L'!$O$29 -> 3618087518 | BC25: ='Annual P&L'!$O$29 -> 3618087518 | BD25: ='Annual P&L'!$O$29 -> 3618087518 | BE25: ='Annual P&L'!$O$29 -> 3618087518 | BF25: ='Annual P&L'!$P$29 -> 3618087518 | BG25: ='Annual P&L'!$P$29 -> 3618087518 | BH25: ='Annual P&L'!$P$29 -> 3618087518 | BI25: ='Annual P&L'!$P$29 -> 3618087518
A28: Quarterly revenue by currency | B28: Quarterly revenue by currency | C28: Quarterly revenue by currency | D28: Quarterly revenue by currency | E28: Quarterly revenue by currency | F28: Quarterly revenue by currency | G28: Quarterly revenue by currency | H28: Quarterly revenue by currency | I28: Quarterly revenue by currency | J28: Quarterly revenue by currency | K28: Quarterly revenue by currency | L28: Quarterly revenue by currency | M28: Quarterly revenue by currency | N28: Quarterly revenue by currency | O28: Quarterly revenue by currency | P28: Quarterly revenue by currency | Q28: Quarterly revenue by currency | R28: Quarterly revenue by currency | S28: Quarterly revenue by currency | T28: Quarterly revenue by currency | U28: Quarterly revenue by currency | V28: Quarterly revenue by currency | W28: Quarterly revenue by currency | X28: Quarterly revenue by currency | Y28: Quarterly revenue by currency | Z28: Quarterly revenue by currency | AA28: Quarterly revenue by currency | AB28: Quarterly revenue by currency | AC28: Quarterly revenue by currency | AD28: Quarterly revenue by currency | AE28: Quarterly revenue by currency | AF28: Quarterly revenue by currency | AG28: Quarterly revenue by currency | AH28: Quarterly revenue by currency | AI28: Quarterly revenue by currency | AJ28: Quarterly revenue by currency | AK28: Quarterly revenue by currency | AL28: Quarterly revenue by currency | AM28: Quarterly revenue by currency | AN28: Quarterly revenue by currency | AO28: Quarterly revenue by currency | AP28: Quarterly revenue by currency | AQ28: Quarterly revenue by currency | AR28: Quarterly revenue by currency | AS28: Quarterly revenue by currency | AT28: Quarterly revenue by currency | AU28: Quarterly revenue by currency | AV28: Quarterly revenue by currency | AW28: Quarterly revenue by currency | AX28: Quarterly revenue by currency | AY28: Quarterly revenue by currency | AZ28: Quarterly revenue by currency | BA28: Quarterly revenue by currency | BB28: Quarterly revenue by currency | BC28: Quarterly revenue by currency | BD28: Quarterly revenue by currency | BE28: Quarterly revenue by currency | BF28: Quarterly revenue by currency | BG28: Quarterly revenue by currency | BH28: Quarterly revenue by currency | BI28: Quarterly revenue by currency
B29: Q1 FY16 | C29: Q2 FY16 | D29: Q3 FY16 | E29: Q4 FY16 | F29: Q1 FY17 | G29: Q2 FY17 | H29: Q3 FY17 | I29: Q4 FY17 | J29: Q1 FY18 | K29: Q2 FY18 | L29: Q3 FY18 | M29: Q4 FY18 | N29: Q1 FY19 | O29: Q2 FY19 | P29: Q3 FY19 | Q29: Q4 FY19 | R29: Q1 FY20 | S29: Q2 FY20 | T29: Q3 FY20 | U29: Q4 FY20 | V29: Q1 FY21 | W29: Q2 FY21 | X29: Q3 FY21 | Y29: Q4 FY21 | Z29: Q1 FY22 | AA29: Q2 FY22 | AB29: Q3 FY22 | AC29: Q4 FY22 | AD29: Q1 FY23 | AE29: Q2 FY23 | AF29: Q3 FY23 | AG29: Q4 FY23 | AH29: Q1 FY24 | AI29: Q2 FY24 | AJ29: Q3 FY24 | AK29: Q4 FY24 | AL29: Q1 FY25 | AM29: Q2 FY25 | AN29: Q3 FY25 | AO29: Q4 FY25 | AP29: Q1 FY26 | AQ29: Q2 FY26 | AR29: Q3 FY26 | AS29: Q4 FY26 | AT29: Q1 FY27 | AU29: Q2 FY27 | AV29: Q3 FY27 | AW29: Q4 FY27 | AX29: Q1 FY28 | AY29: Q2 FY28 | AZ29: Q3 FY28 | BA29: Q4 FY28 | BB29: Q1 FY29 | BC29: Q2 FY29 | BD29: Q3 FY29 | BE29: Q4 FY29 | BF29: Q1 FY30 | BG29: Q2 FY30 | BH29: Q3 FY30 | BI29: Q4 FY30
A30: Quarterly revenue (INR m) | B30: ='Quarterly P&L'!$B$6 -> 256681.1 | C30: ='Quarterly P&L'!$C$6 -> 271654.8 | D30: ='Quarterly P&L'!$D$6 -> 273640.1 | E30: ='Quarterly P&L'!$E$6 -> 284486.1 | F30: ='Quarterly P&L'!$F$6 -> 293050 | G30: ='Quarterly P&L'!$G$6 -> 292840 | H30: ='Quarterly P&L'!$H$6 -> 297350 | I30: ='Quarterly P&L'!$I$6 -> 296420 | J30: ='Quarterly P&L'!$J$6 -> 295840 | K30: ='Quarterly P&L'!$K$6 -> 305410 | L30: ='Quarterly P&L'!$L$6 -> 309040 | M30: ='Quarterly P&L'!$M$6 -> 320750 | N30: ='Quarterly P&L'!$N$6 -> 342610 | O30: ='Quarterly P&L'!$O$6 -> 368540 | P30: ='Quarterly P&L'!$P$6 -> 373380 | Q30: ='Quarterly P&L'!$Q$6 -> 380100 | R30: ='Quarterly P&L'!$R$6 -> 381720 | S30: ='Quarterly P&L'!$S$6 -> 389770 | T30: ='Quarterly P&L'!$T$6 -> 398540 | U30: ='Quarterly P&L'!$U$6 -> 399460 | V30: ='Quarterly P&L'!$V$6 -> 383220 | W30: ='Quarterly P&L'!$W$6 -> 401350 | X30: ='Quarterly P&L'!$X$6 -> 420150 | Y30: ='Quarterly P&L'!$Y$6 -> 437050 | Z30: ='Quarterly P&L'!$Z$6 -> 454110 | AA30: ='Quarterly P&L'!$AA$6 -> 468670 | AB30: ='Quarterly P&L'!$AB$6 -> 488850 | AC30: ='Quarterly P&L'!$AC$6 -> 505910 | AD30: ='Quarterly P&L'!$AD$6 -> 527580 | AE30: ='Quarterly P&L'!$AE$6 -> 553090 | AF30: ='Quarterly P&L'!$AF$6 -> 582290 | AG30: ='Quarterly P&L'!$AG$6 -> 591620 | AH30: ='Quarterly P&L'!$AH$6 -> 593810 | AI30: ='Quarterly P&L'!$AI$6 -> 596920 | AJ30: ='Quarterly P&L'!$AJ$6 -> 605830 | AK30: ='Quarterly P&L'!$AK$6 -> 612370 | AL30: ='Quarterly P&L'!$AL$6 -> 626130 | AM30: ='Quarterly P&L'!$AM$6 -> 642590 | AN30: ='Quarterly P&L'!$AN$6 -> 639730 | AO30: ='Quarterly P&L'!$AO$6 -> 644790 | AP30: ='Quarterly P&L'!$AP$6 -> 634370 | AQ30: ='Quarterly P&L'!$AQ$6 -> 657990 | AR30: ='Quarterly P&L'!$AR$6 -> 670870 | AS30: ='Quarterly P&L'!$AS$6 -> 706980 | AT30: ='Quarterly P&L'!$AT$6 -> 722750 | AU30: ='Quarterly P&L'!$AU$6 -> 657114.74 | AV30: ='Quarterly P&L'!$AV$6 -> 669977.61 | AW30: ='Quarterly P&L'!$AW$6 -> 706039.58 | AX30: ='Quarterly P&L'!$AX$6 -> 689384.76 | AY30: ='Quarterly P&L'!$AY$6 -> 715053.17 | AZ30: ='Quarterly P&L'!$AZ$6 -> 729050.17 | BA30: ='Quarterly P&L'!$BA$6 -> 768291.75 | BB30: ='Quarterly P&L'!$BB$6 -> 723677.52 | BC30: ='Quarterly P&L'!$BC$6 -> 750622.77 | BD30: ='Quarterly P&L'!$BD$6 -> 765316.04 | BE30: ='Quarterly P&L'!$BE$6 -> 806509.66 | BF30: ='Quarterly P&L'!$BF$6 -> 759079.46 | BG30: ='Quarterly P&L'!$BG$6 -> 787342.86 | BH30: ='Quarterly P&L'!$BH$6 -> 802754.91 | BI30: ='Quarterly P&L'!$BI$6 -> 845963.7
A31: USD mix | B31: ='Raw Financials'!$B$168 -> 0.569 | C31: ='Raw Financials'!$C$168 -> 0.566 | D31: ='Raw Financials'!$D$168 -> 0.571 | E31: ='Raw Financials'!$E$168 -> 0.574 | F31: ='Raw Financials'!$F$168 -> 0.565 | G31: ='Raw Financials'!$G$168 -> 0.569 | H31: ='Raw Financials'!$H$168 -> 0.582 | I31: ='Raw Financials'!$I$168 -> 0.5626 | J31: ='Raw Financials'!$J$168 -> 0.5562 | K31: ='Raw Financials'!$K$168 -> 0.5471 | L31: ='Raw Financials'!$L$168 -> 0.5479 | M31: ='Raw Financials'!$M$168 -> 0.5332 | N31: ='Raw Financials'!$N$168 -> 0.5382 | O31: ='Raw Financials'!$O$168 -> 0.5384 | P31: ='Raw Financials'!$P$168 -> 0.5373 | Q31: ='Raw Financials'!$Q$168 -> 0.5313 | R31: ='Raw Financials'!$R$168 -> 0.5316 | S31: ='Raw Financials'!$S$168 -> 0.5316 | T31: ='Raw Financials'!$T$168 -> 0.527 | U31: ='Raw Financials'!$U$168 -> 0.5293 | V31: ='Raw Financials'!$V$168 -> 0.5404 | W31: ='Raw Financials'!$W$168 -> 0.5207 | X31: ='Raw Financials'!$X$168 -> 0.5123 | Y31: ='Raw Financials'!$Y$168 -> 0.5093 | Z31: ='Raw Financials'!$Z$168 -> 0.5169 | AA31: ='Raw Financials'!$AA$168 -> 0.5286 | AB31: ='Raw Financials'!$AB$168 -> 0.5312 | AC31: ='Raw Financials'!$AC$168 -> 0.5409 | AD31: ='Raw Financials'!$AD$168 -> 0.5559 | AE31: ='Raw Financials'!$AE$168 -> 0.5692 | AF31: ='Raw Financials'!$AF$168 -> 0.5637 | AG31: ='Raw Financials'!$AG$168 -> 0.5494 | AH31: ='Raw Financials'!$AH$168 -> 0.5442 | AI31: ='Raw Financials'!$AI$168 -> 0.5396 | AJ31: ='Raw Financials'!$AJ$168 -> 0.5291 | AK31: ='Raw Financials'!$AK$168 -> 0.5194 | AL31: ='Raw Financials'!$AL$168 -> 0.515 | AM31: ='Raw Financials'!$AM$168 -> 0.4932 | AN31: ='Raw Financials'!$AN$168 -> 0.4943 | AO31: ='Raw Financials'!$AO$168 -> 0.497 | AP31: ='Raw Financials'!$AP$168 -> 0.4973 | AQ31: ='Raw Financials'!$AQ$168 -> 0.4979 | AR31: ='Raw Financials'!$AR$168 -> 0.4934 | AS31: ='Raw Financials'!$AS$168 -> 0.48945 | AT31: ='Raw Financials'!$AT$168 -> 0.48651 | AU31: =AT31 -> 0.48651 | AV31: =AU31 -> 0.48651 | AW31: =AV31 -> 0.48651 | AX31: =AW31 -> 0.48651 | AY31: =AX31 -> 0.48651 | AZ31: =AY31 -> 0.48651 | BA31: =AZ31 -> 0.48651 | BB31: =BA31 -> 0.48651 | ... BI31: =BH31 -> 0.48651
A32: USD revenue (INR m) | B32: =B30*B31 -> 146051.55 | C32: =C30*C31 -> 153756.62 | D32: =D30*D31 -> 156248.5 | E32: =E30*E31 -> 163295.02 | F32: =F30*F31 -> 165573.25 | G32: =G30*G31 -> 166625.96 | H32: =H30*H31 -> 173057.7 | I32: =I30*I31 -> 166765.89 | ... BI32: =BI30*BI31 -> 411569.8
A33: USD revenue growth — YoY | B33: ="" | C33: ="" | D33: ="" | E33: ="" | F33: =IFERROR(F32/B32-1,"") -> 0.13366311 | G33: =IFERROR(G32/C32-1,"") -> 0.083699443 | H33: =IFERROR(H32/D32-1,"") -> 0.10757993 | I33: =IFERROR(I32/E32-1,"") -> 0.021255214 | J33: =IFERROR(J32/F32-1,"") -> -0.0062029464 | K33: =IFERROR(K32/G32-1,"") -> 0.0027837859 | L33: =IFERROR(L32/H32-1,"") -> -0.021580571 | M33: =IFERROR(M32/I32-1,"") -> 0.025532847 | ... BI33: =IFERROR(BI32/BE32-1,"") -> 0.048919495
A34: GBP mix | B34: ='Raw Financials'!$B$169 -> 0.142 | C34: ='Raw Financials'!$C$169 -> 0.145 | D34: ='Raw Financials'!$D$169 -> 0.141 | E34: ='Raw Financials'!$E$169 -> 0.132 | F34: ='Raw Financials'!$F$169 -> 0.13 | G34: ='Raw Financials'!$G$169 -> 0.12 | H34: ='Raw Financials'!$H$169 -> 0.114 | I34: ='Raw Financials'!$I$169 -> 0.1186 | J34: ='Raw Financials'!$J$169 -> 0.1198 | K34: ='Raw Financials'!$K$169 -> 0.122 | L34: ='Raw Financials'!$L$169 -> 0.1228 | M34: ='Raw Financials'!$M$169 -> 0.131 | N34: ='Raw Financials'!$N$169 -> 0.1356 | O34: ='Raw Financials'!$O$169 -> 0.1382 | P34: ='Raw Financials'!$P$169 -> 0.1391 | Q34: ='Raw Financials'!$Q$169 -> 0.1425 | R34: ='Raw Financials'!$R$169 -> 0.1401 | S34: ='Raw Financials'!$S$169 -> 0.1379 | T34: ='Raw Financials'!$T$169 -> 0.1418 | U34: ='Raw Financials'!$U$169 -> 0.1412 | V34: ='Raw Financials'!$V$169 -> 0.133 | W34: ='Raw Financials'!$W$169 -> 0.1352 | X34: ='Raw Financials'!$X$169 -> 0.1345 | Y34: ='Raw Financials'!$Y$169 -> 0.138 | Z34: ='Raw Financials'!$Z$169 -> 0.1402 | AA34: ='Raw Financials'!$AA$169 -> 0.137 | AB34: ='Raw Financials'!$AB$169 -> 0.134 | AC34: ='Raw Financials'!$AC$169 -> 0.1346 | AD34: ='Raw Financials'!$AD$169 -> 0.1276 | AE34: ='Raw Financials'!$AE$169 -> 0.1229 | AF34: ='Raw Financials'!$AF$169 -> 0.1269 | AG34: ='Raw Financials'!$AG$169 -> 0.1356 | AH34: ='Raw Financials'!$AH$169 -> 0.1419 | AI34: ='Raw Financials'!$AI$169 -> 0.1434 | AJ34: ='Raw Financials'!$AJ$169 -> 0.1435 | AK34: ='Raw Financials'!$AK$169 -> 0.1467 | AL34: ='Raw Financials'!$AL$169 -> 0.1463 | AM34: ='Raw Financials'!$AM$169 -> 0.1486 | AN34: ='Raw Financials'!$AN$169 -> 0.1443 | AO34: ='Raw Financials'!$AO$169 -> 0.147 | AP34: ='Raw Financials'!$AP$169 -> 0.1578 | AQ34: ='Raw Financials'!$AQ$169 -> 0.1516 | AR34: ='Raw Financials'!$AR$169 -> 0.1482 | AS34: ='Raw Financials'!$AS$169 -> 0.15145 | AT34: ='Raw Financials'!$AT$169 -> 0.15099 | AU34: =AT34 -> 0.15099 | AV34: =AU34 -> 0.15099 | AW34: =AV34 -> 0.15099 | AX34: =AW34 -> 0.15099 | AY34: =AX34 -> 0.15099 | AZ34: =AY34 -> 0.15099 | BA34: =AZ34 -> 0.15099 | BB34: =BA34 -> 0.15099 | ... BI34: =BH34 -> 0.15099
A35: GBP revenue (INR m) | B35: =B30*B34 -> 36448.716 | C35: =C30*C34 -> 39389.946 | D35: =D30*D34 -> 38583.254 | E35: =E30*E34 -> 37552.165 | F35: =F30*F34 -> 38096.5 | G35: =G30*G34 -> 35140.8 | H35: =H30*H34 -> 33897.9 | I35: =I30*I34 -> 35155.412 | ... BI35: =BI30*BI34 -> 127732.06
A36: GBP revenue growth — YoY | B36: ="" | C36: ="" | D36: ="" | E36: ="" | F36: =IFERROR(F35/B35-1,"") -> 0.045208281 | G36: =IFERROR(G35/C35-1,"") -> -0.10787387 | H36: =IFERROR(H35/D35-1,"") -> -0.12143491 | I36: =IFERROR(I35/E35-1,"") -> -0.063824634 | J36: =IFERROR(J35/F35-1,"") -> -0.069687977 | K36: =IFERROR(K35/G35-1,"") -> 0.060306538 | L36: =IFERROR(L35/H35-1,"") -> 0.11954168 | M36: =IFERROR(M35/I35-1,"") -> 0.19521427 | ... BI36: =IFERROR(BI35/BE35-1,"") -> 0.048919495
A37: EUR mix | B37: ='Raw Financials'!$B$170 -> 0.077 | C37: ='Raw Financials'!$C$170 -> 0.075 | D37: ='Raw Financials'!$D$170 -> 0.076 | E37: ='Raw Financials'!$E$170 -> 0.079 | F37: ='Raw Financials'!$F$170 -> 0.08 | G37: ='Raw Financials'!$G$170 -> 0.082 | H37: ='Raw Financials'!$H$170 -> 0.079 | I37: ='Raw Financials'!$I$170 -> 0.08 | J37: ='Raw Financials'!$J$170 -> 0.0857 | K37: ='Raw Financials'!$K$170 -> 0.0933 | L37: ='Raw Financials'!$L$170 -> 0.0952 | M37: ='Raw Financials'!$M$170 -> 0.1021 | N37: ='Raw Financials'!$N$170 -> 0.1015 | O37: ='Raw Financials'!$O$170 -> 0.1012 | P37: ='Raw Financials'!$P$170 -> 0.0997 | Q37: ='Raw Financials'!$Q$170 -> 0.1013 | R37: ='Raw Financials'!$R$170 -> 0.104 | S37: ='Raw Financials'!$S$170 -> 0.1057 | T37: ='Raw Financials'!$T$170 -> 0.1071 | U37: ='Raw Financials'!$U$170 -> 0.1095 | V37: ='Raw Financials'!$V$170 -> 0.1111 | W37: ='Raw Financials'!$W$170 -> 0.1206 | X37: ='Raw Financials'!$X$170 -> 0.1219 | Y37: ='Raw Financials'!$Y$170 -> 0.1262 | Z37: ='Raw Financials'!$Z$170 -> 0.1252 | AA37: ='Raw Financials'!$AA$170 -> 0.1179 | AB37: ='Raw Financials'!$AB$170 -> 0.118 | AC37: ='Raw Financials'!$AC$170 -> 0.1128 | AD37: ='Raw Financials'!$AD$170 -> 0.1103 | AE37: ='Raw Financials'!$AE$170 -> 0.1031 | AF37: ='Raw Financials'!$AF$170 -> 0.1064 | AG37: ='Raw Financials'!$AG$170 -> 0.1107 | AH37: ='Raw Financials'!$AH$170 -> 0.1099 | AI37: ='Raw Financials'!$AI$170 -> 0.1112 | AJ37: ='Raw Financials'!$AJ$170 -> 0.1114 | AK37: ='Raw Financials'!$AK$170 -> 0.1118 | AL37: ='Raw Financials'!$AL$170 -> 0.1102 | AM37: ='Raw Financials'!$AM$170 -> 0.1115 | AN37: ='Raw Financials'!$AN$170 -> 0.1064 | AO37: ='Raw Financials'!$AO$170 -> 0.1097 | AP37: ='Raw Financials'!$AP$170 -> 0.1165 | AQ37: ='Raw Financials'!$AQ$170 -> 0.1173 | AR37: ='Raw Financials'!$AR$170 -> 0.1165 | AS37: ='Raw Financials'!$AS$170 -> 0.11862 | AT37: ='Raw Financials'!$AT$170 -> 0.11879 | AU37: =AT37 -> 0.11879 | AV37: =AU37 -> 0.11879 | AW37: =AV37 -> 0.11879 | AX37: =AW37 -> 0.11879 | AY37: =AX37 -> 0.11879 | AZ37: =AY37 -> 0.11879 | BA37: =AZ37 -> 0.11879 | BB37: =BA37 -> 0.11879 | ... BI37: =BH37 -> 0.11879
A38: EUR revenue (INR m) | B38: =B30*B37 -> 19764.445 | C38: =C30*C37 -> 20374.11 | D38: =D30*D37 -> 20796.648 | E38: =E30*E37 -> 22474.402 | F38: =F30*F37 -> 23444 | G38: =G30*G37 -> 24012.88 | H38: =H30*H37 -> 23490.65 | I38: =I30*I37 -> 23713.6 | ... BI38: =BI30*BI37 -> 100492.03
A39: EUR revenue growth — YoY | B39: ="" | C39: ="" | D39: ="" | E39: ="" | F39: =IFERROR(F38/B38-1,"") -> 0.18617044 | G39: =IFERROR(G38/C38-1,"") -> 0.17859774 | H39: =IFERROR(H38/D38-1,"") -> 0.12954022 | I39: =IFERROR(I38/E38-1,"") -> 0.055138201 | J39: =IFERROR(J38/F38-1,"") -> 0.0814489 | K39: =IFERROR(K38/G38-1,"") -> 0.18664454 | L39: =IFERROR(L38/H38-1,"") -> 0.25243908 | M39: =IFERROR(M38/I38-1,"") -> 0.38100394 | ... BI39: =IFERROR(BI38/BE38-1,"") -> 0.048919495
A40: Other mix | B40: ='Raw Financials'!$B$171 -> 0.212 | C40: ='Raw Financials'!$C$171 -> 0.214 | D40: ='Raw Financials'!$D$171 -> 0.212 | E40: ='Raw Financials'!$E$171 -> 0.215 | F40: ='Raw Financials'!$F$171 -> 0.225 | G40: ='Raw Financials'!$G$171 -> 0.229 | H40: ='Raw Financials'!$H$171 -> 0.225 | I40: ='Raw Financials'!$I$171 -> 0.2388 | J40: ='Raw Financials'!$J$171 -> 0.2383 | K40: ='Raw Financials'!$K$171 -> 0.2377 | L40: ='Raw Financials'!$L$171 -> 0.2341 | M40: ='Raw Financials'!$M$171 -> 0.2337 | N40: ='Raw Financials'!$N$171 -> 0.2247 | O40: ='Raw Financials'!$O$171 -> 0.2222 | P40: ='Raw Financials'!$P$171 -> 0.2239 | Q40: ='Raw Financials'!$Q$171 -> 0.2249 | R40: ='Raw Financials'!$R$171 -> 0.2243 | S40: ='Raw Financials'!$S$171 -> 0.2248 | T40: ='Raw Financials'!$T$171 -> 0.2241 | U40: ='Raw Financials'!$U$171 -> 0.22 | V40: ='Raw Financials'!$V$171 -> 0.2155 | W40: ='Raw Financials'!$W$171 -> 0.2235 | X40: ='Raw Financials'!$X$171 -> 0.2313 | Y40: ='Raw Financials'!$Y$171 -> 0.2265 | Z40: ='Raw Financials'!$Z$171 -> 0.2176 | AA40: ='Raw Financials'!$AA$171 -> 0.2164 | AB40: ='Raw Financials'!$AB$171 -> 0.2168 | AC40: ='Raw Financials'!$AC$171 -> 0.2117 | AD40: ='Raw Financials'!$AD$171 -> 0.2062 | AE40: ='Raw Financials'!$AE$171 -> 0.2048 | AF40: ='Raw Financials'!$AF$171 -> 0.203 | AG40: ='Raw Financials'!$AG$171 -> 0.2043 | AH40: ='Raw Financials'!$AH$171 -> 0.2039 | AI40: ='Raw Financials'!$AI$171 -> 0.2058 | AJ40: ='Raw Financials'!$AJ$171 -> 0.2161 | AK40: ='Raw Financials'!$AK$171 -> 0.2221 | AL40: ='Raw Financials'!$AL$171 -> 0.2285 | AM40: ='Raw Financials'!$AM$171 -> 0.2468 | AN40: ='Raw Financials'!$AN$171 -> 0.255 | AO40: ='Raw Financials'!$AO$171 -> 0.2463 | AP40: ='Raw Financials'!$AP$171 -> 0.2284 | AQ40: ='Raw Financials'!$AQ$171 -> 0.2332 | AR40: ='Raw Financials'!$AR$171 -> 0.2419 | AS40: ='Raw Financials'!$AS$171 -> 0.2405 | AT40: ='Raw Financials'!$AT$171 -> 0.2437 | AU40: =AT40 -> 0.2437 | AV40: =AU40 -> 0.2437 | AW40: =AV40 -> 0.2437 | AX40: =AW40 -> 0.2437 | AY40: =AX40 -> 0.2437 | AZ40: =AY40 -> 0.2437 | BA40: =AZ40 -> 0.2437 | BB40: =BA40 -> 0.2437 | ... BI40: =BH40 -> 0.2437
A41: Other-currency revenue (INR m) | B41: =B30*B40 -> 54416.393 | C41: =C30*C40 -> 58134.127 | D41: =D30*D40 -> 58011.701 | E41: =E30*E40 -> 61164.511 | F41: =F30*F40 -> 65936.25 | G41: =G30*G40 -> 67060.36 | H41: =H30*H40 -> 66903.75 | I41: =I30*I40 -> 70785.096 | ... BI41: =BI30*BI40 -> 206161.35
A42: Other-currency revenue growth — YoY | B42: ="" | C42: ="" | D42: ="" | E42: ="" | F42: =IFERROR(F41/B41-1,"") -> 0.21169828 | G42: =IFERROR(G41/C41-1,"") -> 0.15354549 | H42: =IFERROR(H41/D41-1,"") -> 0.15328026 | I42: =IFERROR(I41/E41-1,"") -> 0.1572903 | J42: =IFERROR(J41/F41-1,"") -> 0.069194442 | K42: =IFERROR(K41/G41-1,"") -> 0.082546485 | L42: =IFERROR(L41/H41-1,"") -> 0.081348415 | M42: =IFERROR(M41/I41-1,"") -> 0.058969744 | ... BI42: =IFERROR(BI41/BE41-1,"") -> 0.048919495
A43: Mix check | B43: =SUM(B31,B34,B37,B40)-1 -> 0 | C43: =SUM(C31,C34,C37,C40)-1 -> 0 | D43: =SUM(D31,D34,D37,D40)-1 -> 0 | E43: =SUM(E31,E34,E37,E40)-1 -> 0 | F43: =SUM(F31,F34,F37,F40)-1 -> 0 | G43: =SUM(G31,G34,G37,G40)-1 -> 0 | H43: =SUM(H31,H34,H37,H40)-1 -> 0 | I43: =SUM(I31,I34,I37,I40)-1 -> 0 | ... BI43: =SUM(BI31,BI34,BI37,BI40)-1 -> -1e-05

Sheet Annual P&L
A1: Annual Profit & Loss Statement | B1: Annual Profit & Loss Statement | C1: Annual Profit & Loss Statement | D1: Annual Profit & Loss Statement | E1: Annual Profit & Loss Statement | F1: Annual Profit & Loss Statement | G1: Annual Profit & Loss Statement | H1: Annual Profit & Loss Statement | I1: Annual Profit & Loss Statement | J1: Annual Profit & Loss Statement | K1: Annual Profit & Loss Statement | L1: Annual Profit & Loss Statement | M1: Annual Profit & Loss Statement | N1: Annual Profit & Loss Statement | O1: Annual Profit & Loss Statement | P1: Annual Profit & Loss Statement
A2: Annual Profit & Loss Statement | B2: Annual Profit & Loss Statement | C2: Annual Profit & Loss Statement | D2: Annual Profit & Loss Statement | E2: Annual Profit & Loss Statement | F2: Annual Profit & Loss Statement | G2: Annual Profit & Loss Statement | H2: Annual Profit & Loss Statement | I2: Annual Profit & Loss Statement | J2: Annual Profit & Loss Statement | K2: Annual Profit & Loss Statement | L2: Annual Profit & Loss Statement | M2: Annual Profit & Loss Statement | N2: Annual Profit & Loss Statement | O2: Annual Profit & Loss Statement | P2: Annual Profit & Loss Statement
A3: Reported historicals; formula-driven forecast. INR million except per-share data. | B3: Reported historicals; formula-driven forecast. INR million except per-share data. | C3: Reported historicals; formula-driven forecast. INR million except per-share data. | D3: Reported historicals; formula-driven forecast. INR million except per-share data. | E3: Reported historicals; formula-driven forecast. INR million except per-share data. | F3: Reported historicals; formula-driven forecast. INR million except per-share data. | G3: Reported historicals; formula-driven forecast. INR million except per-share data. | H3: Reported historicals; formula-driven forecast. INR million except per-share data. | I3: Reported historicals; formula-driven forecast. INR million except per-share data. | J3: Reported historicals; formula-driven forecast. INR million except per-share data. | K3: Reported historicals; formula-driven forecast. INR million except per-share data. | L3: Reported historicals; formula-driven forecast. INR million except per-share data. | M3: Reported historicals; formula-driven forecast. INR million except per-share data. | N3: Reported historicals; formula-driven forecast. INR million except per-share data. | O3: Reported historicals; formula-driven forecast. INR million except per-share data. | P3: Reported historicals; formula-driven forecast. INR million except per-share data.
B5: FY16 | C5: FY17 | D5: FY18 | E5: FY19 | F5: FY20 | G5: FY21 | H5: FY22 | I5: FY23 | J5: FY24 | K5: FY25 | L5: FY26 | M5: FY27E | N5: FY28E | O5: FY29E | P5: FY30E
A6: Revenue | B6: ='Raw Financials'!$B$7 -> 1086462.1 | C6: ='Raw Financials'!$C$7 -> 1179660 | D6: ='Raw Financials'!$D$7 -> 1231040 | E6: ='Raw Financials'!$E$7 -> 1464630 | F6: ='Raw Financials'!$F$7 -> 1569490 | G6: ='Raw Financials'!$G$7 -> 1641770 | H6: ='Raw Financials'!$H$7 -> 1917540 | I6: ='Raw Financials'!$I$7 -> 2254580 | J6: ='Raw Financials'!$J$7 -> 2408930 | K6: ='Raw Financials'!$K$7 -> 2553240 | L6: ='Raw Financials'!$L$7 -> 2670210 | M6: ='Revenue Drivers'!$M$23 -> 2755881.9 | N6: ='Revenue Drivers'!$N$23 -> 2901779.8 | O6: ='Revenue Drivers'!$O$23 -> 3046126 | P6: ='Revenue Drivers'!$P$23 -> 3195140.9
A7: YoY growth | B7: ="" | C7: =IFERROR(C6/B6-1,"") -> 0.085781087 | D7: =IFERROR(D6/C6-1,"") -> 0.043554923 | E7: =IFERROR(E6/D6-1,"") -> 0.18975013 | F7: =IFERROR(F6/E6-1,"") -> 0.071594874 | G7: =IFERROR(G6/F6-1,"") -> 0.046053177 | H7: =IFERROR(H6/G6-1,"") -> 0.16797115 | I7: =IFERROR(I6/H6-1,"") -> 0.17576687 | J7: =IFERROR(J6/I6-1,"") -> 0.068460645 | ... P7: =IFERROR(P6/O6-1,"") -> 0.048919495
A8: Cost of revenue | B8: ='Raw Financials'!$B$8 -> 608996.7 | C8: ='Raw Financials'!$C$8 -> 668870 | D8: ='Raw Financials'!$D$8 -> 712880 | E8: ='Raw Financials'!$E$8 -> 851580 | F8: ='Raw Financials'!$F$8 -> 923220 | G8: ='Raw Financials'!$G$8 -> 971380 | H8: ='Raw Financials'!$H$8 -> 1146210 | I8: ='Raw Financials'!$I$8 -> 1362680 | J8: ='Raw Financials'!$J$8 -> 1435950 | K8: ='Raw Financials'!$K$8 -> 1559940 | L8: ='Raw Financials'!$L$8 -> 1951230 | M8: =M6*Assumptions!$M$23 -> 1998014.4 | N8: =N6*Assumptions!$N$23 -> 2097986.8 | O8: =O6*Assumptions!$O$23 -> 2196256.8 | P8: =P6*Assumptions!$P$23 -> 2300501.5
A9: Gross profit | B9: ='Raw Financials'!$B$9 -> 477465.4 | C9: ='Raw Financials'!$C$9 -> 510790 | D9: ='Raw Financials'!$D$9 -> 518160 | E9: ='Raw Financials'!$E$9 -> 613050 | F9: ='Raw Financials'!$F$9 -> 646270 | G9: ='Raw Financials'!$G$9 -> 670390 | H9: ='Raw Financials'!$H$9 -> 771330 | I9: ='Raw Financials'!$I$9 -> 891900 | J9: ='Raw Financials'!$J$9 -> 972980 | K9: ='Raw Financials'!$K$9 -> 993300 | L9: ='Raw Financials'!$L$9 -> 718980 | M9: =M6-M8 -> 757867.53 | N9: =N6-N8 -> 803793.02 | O9: =O6-O8 -> 849869.15 | P9: =P6-P8 -> 894639.46
A10: Gross margin | B10: =IFERROR(B9/B6,"") -> 0.43946807 | C10: =IFERROR(C9/C6,"") -> 0.43299764 | D10: =IFERROR(D9/D6,"") -> 0.4209124 | E10: =IFERROR(E9/E6,"") -> 0.41856988 | F10: =IFERROR(F9/F6,"") -> 0.4117707 | G10: =IFERROR(G9/G6,"") -> 0.40833369 | H10: =IFERROR(H9/H6,"") -> 0.40224976 | I10: =IFERROR(I9/I6,"") -> 0.39559474 | ... P10: =IFERROR(P9/P6,"") -> 0.28
A11: SG&A and other operating expenses | B11: =B12-B8 -> 189564.5 | C11: =C12-C8 -> 207550 | D11: =D12-D8 -> 213140 | E11: =E12-E8 -> 238550 | F11: =F12-F8 -> 260470 | G11: =G12-G8 -> 245580 | H11: =H12-H8 -> 286800 | I11: =I12-I8 -> 349530 | ... P11: =P12-P8 -> 95854.228
A12: Total operating expenses | B12: ='Raw Financials'!$B$23 -> 798561.2 | C12: ='Raw Financials'!$C$23 -> 876420 | D12: ='Raw Financials'!$D$23 -> 926020 | E12: ='Raw Financials'!$E$23 -> 1090130 | F12: ='Raw Financials'!$F$23 -> 1183690 | G12: ='Raw Financials'!$G$23 -> 1216960 | H12: ='Raw Financials'!$H$23 -> 1433010 | I12: ='Raw Financials'!$I$23 -> 1712210 | J12: ='Raw Financials'!$J$23 -> 1825400 | K12: ='Raw Financials'!$K$23 -> 1931590 | L12: ='Raw Financials'!$L$23 -> 2047090 | M12: =M6-M13 -> 2088958.5 | N12: =N6-N13 -> 2190843.8 | O12: =O6-O13 -> 2290686.7 | P12: =P6-P13 -> 2396355.7
A13: Operating income | B13: ='Raw Financials'!$B$24 -> 287900.9 | C13: ='Raw Financials'!$C$24 -> 303240 | D13: ='Raw Financials'!$D$24 -> 305020 | E13: ='Raw Financials'!$E$24 -> 374500 | F13: ='Raw Financials'!$F$24 -> 385800 | G13: ='Raw Financials'!$G$24 -> 424810 | H13: ='Raw Financials'!$H$24 -> 484530 | I13: ='Raw Financials'!$I$24 -> 542370 | J13: ='Raw Financials'!$J$24 -> 583530 | K13: ='Raw Financials'!$K$24 -> 621650 | L13: ='Raw Financials'!$L$24 -> 623120 | M13: =M6*Assumptions!$M$22 -> 666923.43 | N13: =N6*Assumptions!$N$22 -> 710936.06 | O13: =O6*Assumptions!$O$22 -> 755439.24 | P13: =P6*Assumptions!$P$22 -> 798785.23
A14: Operating margin | B14: =IFERROR(B13/B6,"") -> 0.26498936 | C14: =IFERROR(C13/C6,"") -> 0.25705712 | D14: =IFERROR(D13/D6,"") -> 0.24777424 | E14: =IFERROR(E13/E6,"") -> 0.25569598 | F14: =IFERROR(F13/F6,"") -> 0.24581233 | G14: =IFERROR(G13/G6,"") -> 0.25875123 | H14: =IFERROR(H13/H6,"") -> 0.25268313 | I14: =IFERROR(I13/I6,"") -> 0.24056365 | ... P14: =IFERROR(P13/P6,"") -> 0.25
A15: Other income / (expense) | B15: ='Raw Financials'!$B$25 -> 30501.7 | C15: ='Raw Financials'!$C$25 -> 41890 | D15: ='Raw Financials'!$D$25 -> 35900 | E15: ='Raw Financials'!$E$25 -> 41130 | F15: ='Raw Financials'!$F$25 -> 36680 | G15: ='Raw Financials'!$G$25 -> 24970 | H15: ='Raw Financials'!$H$25 -> 32340 | I15: ='Raw Financials'!$I$25 -> 26700 | J15: ='Raw Financials'!$J$25 -> 36440 | K15: ='Raw Financials'!$K$25 -> 31660 | L15: ='Raw Financials'!$L$25 -> 31750 | M15: =M6*Assumptions!$M$24 -> 38582.347 | N15: =N6*Assumptions!$N$24 -> 40624.918 | O15: =O6*Assumptions!$O$24 -> 42645.764 | P15: =P6*Assumptions!$P$24 -> 44731.973
A16: PBT | B16: ='Raw Financials'!$B$26 -> 318402.6 | C16: ='Raw Financials'!$C$26 -> 345130 | D16: ='Raw Financials'!$D$26 -> 340920 | E16: ='Raw Financials'!$E$26 -> 415630 | F16: ='Raw Financials'!$F$26 -> 422480 | G16: ='Raw Financials'!$G$26 -> 449780 | H16: ='Raw Financials'!$H$26 -> 516870 | I16: ='Raw Financials'!$I$26 -> 569070 | J16: ='Raw Financials'!$J$26 -> 619970 | K16: ='Raw Financials'!$K$26 -> 653310 | L16: ='Raw Financials'!$L$26 -> 654870 | M16: =M13+M15 -> 705505.77 | N16: =N13+N15 -> 751560.98 | O16: =O13+O15 -> 798085.01 | P16: =P13+P15 -> 843517.21
A17: PBT margin | B17: =IFERROR(B16/B6,"") -> 0.2930637 | C17: =IFERROR(C16/C6,"") -> 0.29256735 | D17: =IFERROR(D16/D6,"") -> 0.27693657 | E17: =IFERROR(E16/E6,"") -> 0.28377816 | F17: =IFERROR(F16/F6,"") -> 0.26918298 | G17: =IFERROR(G16/G6,"") -> 0.27396042 | H17: =IFERROR(H16/H6,"") -> 0.26954848 | I17: =IFERROR(I16/I6,"") -> 0.25240621 | ... P17: =IFERROR(P16/P6,"") -> 0.264
A18: Income tax | B18: ='Raw Financials'!$B$27 -> 75026.4 | C18: ='Raw Financials'!$C$27 -> 81560 | D18: ='Raw Financials'!$D$27 -> 82120 | E18: ='Raw Financials'!$E$27 -> 100010 | F18: ='Raw Financials'!$F$27 -> 98010 | G18: ='Raw Financials'!$G$27 -> 114580 | H18: ='Raw Financials'!$H$27 -> 132380 | I18: ='Raw Financials'!$I$27 -> 146040 | J18: ='Raw Financials'!$J$27 -> 158980 | K18: ='Raw Financials'!$K$27 -> 165340 | L18: ='Raw Financials'!$L$27 -> 160330 | M18: =M16*Assumptions!$M$25 -> 172848.91 | N18: =N16*Assumptions!$N$25 -> 184132.44 | O18: =O16*Assumptions!$O$25 -> 195530.83 | P18: =P16*Assumptions!$P$25 -> 206661.72
A19: Effective tax rate | B19: =IFERROR(B18/B16,"") -> 0.23563375 | C19: =IFERROR(C18/C16,"") -> 0.23631675 | D19: =IFERROR(D18/D16,"") -> 0.24087763 | E19: =IFERROR(E18/E16,"") -> 0.24062267 | F19: =IFERROR(F18/F16,"") -> 0.23198731 | G19: =IFERROR(G18/G16,"") -> 0.25474677 | H19: =IFERROR(H18/H16,"") -> 0.25611856 | I19: =IFERROR(I18/I16,"") -> 0.25662924 | ... P19: =IFERROR(P18/P16,"") -> 0.245
A20: Net profit incl. NCI | B20: ='Raw Financials'!$B$28 -> 243376.2 | C20: ='Raw Financials'!$C$28 -> 263570 | D20: ='Raw Financials'!$D$28 -> 258800 | E20: ='Raw Financials'!$E$28 -> 315620 | F20: ='Raw Financials'!$F$28 -> 324470 | G20: ='Raw Financials'!$G$28 -> 335200 | H20: ='Raw Financials'!$H$28 -> 384490 | I20: ='Raw Financials'!$I$28 -> 423030 | J20: ='Raw Financials'!$J$28 -> 460990 | K20: ='Raw Financials'!$K$28 -> 487970 | L20: ='Raw Financials'!$L$28 -> 494540 | M20: =M16-M18 -> 532656.86 | N20: =N16-N18 -> 567428.54 | O20: =O16-O18 -> 602554.18 | P20: =P16-P18 -> 636855.49
A21: NCI | B21: ='Raw Financials'!$B$29 -> -1227.4 | C21: ='Raw Financials'!$C$29 -> -680 | D21: ='Raw Financials'!$D$29 -> -540 | E21: ='Raw Financials'!$E$29 -> -900 | F21: ='Raw Financials'!$F$29 -> -1070 | G21: ='Raw Financials'!$G$29 -> -1320 | H21: ='Raw Financials'!$H$29 -> -1220 | I21: ='Raw Financials'!$I$29 -> -1560 | J21: ='Raw Financials'!$J$29 -> -1910 | K21: ='Raw Financials'!$K$29 -> -2440 | L21: ='Raw Financials'!$L$29 -> -2440 | M21: =-M20*Assumptions!$M$26 -> -2663.2843 | N21: =-N20*Assumptions!$N$26 -> -2837.1427 | O21: =-O20*Assumptions!$O$26 -> -3012.7709 | P21: =-P20*Assumptions!$P$26 -> -3184.2775
A22: Net income attributable | B22: ='Raw Financials'!$B$30 -> 242148.8 | C22: ='Raw Financials'!$C$30 -> 262890 | D22: ='Raw Financials'!$D$30 -> 258260 | E22: ='Raw Financials'!$E$30 -> 314720 | F22: ='Raw Financials'!$F$30 -> 323400 | G22: ='Raw Financials'!$G$30 -> 333880 | H22: ='Raw Financials'!$H$30 -> 383270 | I22: ='Raw Financials'!$I$30 -> 421470 | J22: ='Raw Financials'!$J$30 -> 459080 | K22: ='Raw Financials'!$K$30 -> 485530 | L22: ='Raw Financials'!$L$30 -> 492100 | M22: =M20+M21 -> 529993.58 | N22: =N20+N21 -> 564591.4 | O22: =O20+O21 -> 599541.41 | P22: =P20+P21 -> 633671.21
A23: Net margin | B23: =IFERROR(B22/B6,"") -> 0.22287828 | C23: =IFERROR(C22/C6,"") -> 0.22285235 | D23: =IFERROR(D22/D6,"") -> 0.2097901 | E23: =IFERROR(E22/E6,"") -> 0.21488021 | F23: =IFERROR(F22/F6,"") -> 0.2060542 | G23: =IFERROR(G22/G6,"") -> 0.20336588 | H23: =IFERROR(H22/H6,"") -> 0.19987588 | I23: =IFERROR(I22/I6,"") -> 0.18693947 | ... P23: =IFERROR(P22/P6,"") -> 0.1983234
A24: EPS — basic | B24: ='Raw Financials'!$B$31 -> 123.17 | C24: ='Raw Financials'!$C$31 -> 133.41 | D24: ='Raw Financials'!$D$31 -> 134.19 | E24: ='Raw Financials'!$E$31 -> 83.05 | F24: ='Raw Financials'!$F$31 -> 86.19 | G24: ='Raw Financials'!$G$31 -> 89.27 | H24: ='Raw Financials'!$H$31 -> 103.62 | I24: ='Raw Financials'!$I$31 -> 115.19 | J24: ='Raw Financials'!$J$31 -> 125.88 | K24: ='Raw Financials'!$K$31 -> 134.19 | L24: ='Raw Financials'!$L$31 -> 136.01 | M24: =M22*1000000/M29 -> 146.48445 | N24: =N22*1000000/N29 -> 156.04692 | O24: =O22*1000000/O29 -> 165.70672 | P24: =P22*1000000/P29 -> 175.13982
A25: EPS — diluted | B25: ='Raw Financials'!$B$32 -> 123.17 | C25: ='Raw Financials'!$C$32 -> 133.41 | D25: ='Raw Financials'!$D$32 -> 134.19 | E25: ='Raw Financials'!$E$32 -> 83.05 | F25: ='Raw Financials'!$F$32 -> 86.19 | G25: ='Raw Financials'!$G$32 -> 89.27 | H25: ='Raw Financials'!$H$32 -> 103.62 | I25: ='Raw Financials'!$I$32 -> 115.19 | J25: ='Raw Financials'!$J$32 -> 125.88 | K25: ='Raw Financials'!$K$32 -> 134.19 | L25: ='Raw Financials'!$L$32 -> 136.01 | M25: =M24 -> 146.48445 | N25: =N24 -> 156.04692 | O25: =O24 -> 165.70672 | P25: =P24 -> 175.13982
A26: EPS growth | B26: ="" | C26: =IFERROR(C24/B24-1,"") -> 0.083137128 | D26: =IFERROR(D24/C24-1,"") -> 0.0058466382 | E26: =IFERROR(E24/D24-1,"") -> -0.38110142 | F26: =IFERROR(F24/E24-1,"") -> 0.037808549 | G26: =IFERROR(G24/F24-1,"") -> 0.035735004 | H26: =IFERROR(H24/G24-1,"") -> 0.16074829 | I26: =IFERROR(I24/H24-1,"") -> 0.11165798 | J26: =IFERROR(J24/I24-1,"") -> 0.092803195 | ... P26: =IFERROR(P24/O24-1,"") -> 0.056926514
A27: Dividend per share | B27: ='Raw Financials'!$B$33 -> 43.5 | C27: ='Raw Financials'!$C$33 -> 47 | D27: ='Raw Financials'!$D$33 -> 50 | E27: ='Raw Financials'!$E$33 -> 30 | F27: ='Raw Financials'!$F$33 -> 73 | G27: ='Raw Financials'!$G$33 -> 38 | H27: ='Raw Financials'!$H$33 -> 43 | I27: ='Raw Financials'!$I$33 -> 115 | J27: ='Raw Financials'!$J$33 -> 73 | K27: ='Raw Financials'!$K$33 -> 126 | L27: ='Raw Financials'!$L$33 -> 110 | M27: =M24*Assumptions!$M$28 -> 117.18756 | N27: =N24*Assumptions!$N$28 -> 124.83753 | O27: =O24*Assumptions!$O$28 -> 132.56537 | P27: =P24*Assumptions!$P$28 -> 140.11186
A28: Dividend payout ratio | B28: =IFERROR(B27/B24,"") -> 0.35317041 | C28: =IFERROR(C27/C24,"") -> 0.35229743 | D28: =IFERROR(D27/D24,"") -> 0.37260601 | E28: =IFERROR(E27/E24,"") -> 0.36122818 | F28: =IFERROR(F27/F24,"") -> 0.84696601 | G28: =IFERROR(G27/G24,"") -> 0.42567492 | H28: =IFERROR(H27/H24,"") -> 0.4149778 | I28: =IFERROR(I27/I24,"") -> 0.99835055 | ... P28: =IFERROR(P27/P24,"") -> 0.8
