Workbook

Sheet Cover
A1: Tech Mahindra Integrated Financial Model
A2: Fresh official-source build | Quarterly P&L FY16–FY26 | Annual three statements FY16–FY30E | INR crore unless stated
A4: Operating model, cash-anchored three statements, client mining, TCV, AI revenue bridge and valuation
A6: Model scope | B6: Quarterly P&L only; annual P&L, balance sheet and detailed cash flow
A7: Historical period | B7: FY16–FY26
A8: Forecast period | B8: Quarterly P&L FY16–Q1 FY27; annual P&L, balance sheet and detailed cash flow FY16–FY30E
A9: Primary source | B9: Tech Mahindra Q4 FY26 official data sheet, with cached reported values from the company workbook
A10: Cash policy | B10: Historical CFS ending cash is reconciled explicitly to reported balance-sheet cash; forecast cash is formula-linked across statements
A11: Forecast revenue | B11: Retained base + billable-capacity expansion − T&M AI deflation + deal realization + client mining + AI uplift
A12: AI disclosure policy | B12: No historical AI revenue is hardcoded because Tech Mahindra did not carve it out in the source data sheet; forecast uplift is an editable assumption
A13: Industry classifications | B13: Legacy, FY22–FY23 recast and current FY24+ classifications remain separate; classifications are not blended
A14: Client policy | B14: Discontinued / unavailable fields remain blank; revenue per client is calculated only on a clearly labelled proxy basis
A15: Formatting | B15: Forecast balance sheet rebuilt with explicit asset, working-capital, debt, lease, equity and cash roll-forwards; no circular references
A16: Model status | B16: =Checks!B6 -> OK

Sheet Summary
A1: Tech Mahindra Summary
A2: Annual investment summary through FY26A; Q1 FY27A detail is on the update tab; forecast balance sheet and cash flow use one-way, no-plug schedules
A5: Metric | B5: Units | C5: FY16A | D5: FY17A | E5: FY18A | F5: FY19A | G5: FY20A | H5: FY21A | I5: FY22A | J5: FY23A | K5: FY24A | L5: FY25A | M5: FY26A | N5: FY27E | O5: FY28E | P5: FY29E | Q5: FY30E
A7: Revenue | B7: ₹ cr | C7: ='Annual P&L'!C7 -> 26494.232 | D7: ='Annual P&L'!D7 -> 29140.841 | E7: ='Annual P&L'!E7 -> 30772.881 | F7: ='Annual P&L'!F7 -> 34742.132 | G7: ='Annual P&L'!G7 -> 36867.679 | H7: ='Annual P&L'!H7 -> 37855.081 | I7: ='Annual P&L'!I7 -> 44645.964 | J7: ='Annual P&L'!J7 -> 53290.167 | ... Q7: ='Annual P&L'!Q7 -> 66753.18
A8: Revenue growth | B8: % | C8: ='Annual P&L'!C8 -> 0 | D8: ='Annual P&L'!D8 -> 0.099893788 | E8: ='Annual P&L'!E8 -> 0.056005236 | F8: ='Annual P&L'!F8 -> 0.12898534 | G8: ='Annual P&L'!G8 -> 0.061180684 | H8: ='Annual P&L'!H8 -> 0.026782321 | I8: ='Annual P&L'!I8 -> 0.17939159 | J8: ='Annual P&L'!J8 -> 0.19361667 | ... Q8: ='Annual P&L'!Q8 -> 0.053920233
A9: USD revenue | B9: $m | C9: ='Geography & Currency'!C40 -> 4037.4553 | D9: ='Geography & Currency'!D40 -> 4351.0924 | E9: ='Geography & Currency'!E40 -> 4770.7659 | F9: ='Geography & Currency'!F40 -> 4970.5229 | G9: ='Geography & Currency'!G40 -> 5181.87 | H9: ='Geography & Currency'!H40 -> 5111.06 | I9: ='Geography & Currency'!I40 -> 5997.79 | J9: ='Geography & Currency'!J40 -> 6606.52 | ... Q9: ='Geography & Currency'!Q40 -> 6811.549
A10: USD revenue growth | B10: % | C10: ='Geography & Currency'!C41 -> 0 | D10: ='Geography & Currency'!D41 -> 0.077681863 | E10: ='Geography & Currency'!E41 -> 0.096452438 | F10: ='Geography & Currency'!F41 -> 0.041871071 | G10: ='Geography & Currency'!G41 -> 0.042520083 | H10: ='Geography & Currency'!H41 -> -0.013664951 | I10: ='Geography & Currency'!I41 -> 0.17349239 | J10: ='Geography & Currency'!J41 -> 0.10149238 | ... Q10: ='Geography & Currency'!Q41 -> 0.043165944
A11: EBITDA | B11: ₹ cr | C11: ='Annual P&L'!C15 -> 4270.6903 | D11: ='Annual P&L'!D15 -> 4184.4348 | E11: ='Annual P&L'!E15 -> 4709.5592 | F11: ='Annual P&L'!F15 -> 6336.9176 | G11: ='Annual P&L'!G15 -> 5726.039 | H11: ='Annual P&L'!H15 -> 6847.047 | I11: ='Annual P&L'!I15 -> 8019.984 | J11: ='Annual P&L'!J15 -> 8028.776 | ... Q11: ='Annual P&L'!Q15 -> 12416.092
A12: EBITDA margin | B12: % | C12: ='Annual P&L'!C16 -> 0.16119321 | D12: ='Annual P&L'!D16 -> 0.14359348 | E12: ='Annual P&L'!E16 -> 0.15304252 | F12: ='Annual P&L'!F16 -> 0.18239864 | G12: ='Annual P&L'!G16 -> 0.15531325 | H12: ='Annual P&L'!H16 -> 0.18087524 | I12: ='Annual P&L'!I16 -> 0.17963514 | J12: ='Annual P&L'!J16 -> 0.15066149 | ... Q12: ='Annual P&L'!Q16 -> 0.186
A13: EBIT | B13: ₹ cr | C13: ='Annual P&L'!C20 -> 3511.7673 | D13: ='Annual P&L'!D20 -> 3206.3796 | E13: ='Annual P&L'!E20 -> 3624.5722 | F13: ='Annual P&L'!F20 -> 5207.7176 | G13: ='Annual P&L'!G20 -> 4280.27 | H13: ='Annual P&L'!H20 -> 5389.337 | I13: ='Annual P&L'!I20 -> 6499.591 | J13: ='Annual P&L'!J20 -> 6072.076 | ... Q13: ='Annual P&L'!Q20 -> 10413.496
A14: EBIT margin | B14: % | C14: ='Annual P&L'!C21 -> 0.13254837 | D14: ='Annual P&L'!D21 -> 0.11003044 | E14: ='Annual P&L'!E21 -> 0.11778462 | F14: ='Annual P&L'!F21 -> 0.14989632 | G14: ='Annual P&L'!G21 -> 0.11609817 | H14: ='Annual P&L'!H21 -> 0.1423676 | I14: ='Annual P&L'!I21 -> 0.14558071 | J14: ='Annual P&L'!J21 -> 0.11394365 | ... Q14: ='Annual P&L'!Q21 -> 0.156
A15: Net income | B15: ₹ cr | C15: ='Annual P&L'!C35 -> 2992.886 | D15: ='Annual P&L'!D35 -> 2812.9331 | E15: ='Annual P&L'!E35 -> 3799.755 | F15: ='Annual P&L'!F35 -> 4297.6165 | G15: ='Annual P&L'!G35 -> 4032.942 | H15: ='Annual P&L'!H35 -> 4428.059 | I15: ='Annual P&L'!I35 -> 5566.113 | J15: ='Annual P&L'!J35 -> 4831.276 | ... Q15: ='Annual P&L'!Q35 -> 8008.9397
A16: Net margin | B16: % | C16: ='Annual P&L'!C36 -> 0.11296368 | D16: ='Annual P&L'!D36 -> 0.09652889 | E16: ='Annual P&L'!E36 -> 0.12347739 | F16: ='Annual P&L'!F36 -> 0.12370043 | G16: ='Annual P&L'!G36 -> 0.10938964 | H16: ='Annual P&L'!H36 -> 0.11697397 | I16: ='Annual P&L'!I36 -> 0.12467225 | J16: ='Annual P&L'!J36 -> 0.090659802 | ... Q16: ='Annual P&L'!Q36 -> 0.1199784
A17: Diluted EPS | B17: ₹ / share | C17: ='Annual P&L'!C40 -> 33.71415 | D17: ='Annual P&L'!D40 -> 31.644762 | E17: ='Annual P&L'!E40 -> 42.664589 | F17: ='Annual P&L'!F40 -> 47.720502 | G17: ='Annual P&L'!G40 -> 45.85 | H17: ='Annual P&L'!H40 -> 50.19 | I17: ='Annual P&L'!I40 -> 62.81 | J17: ='Annual P&L'!J40 -> 54.56 | ... Q17: ='Annual P&L'!Q40 -> 90.211242
A18: CFO | B18: ₹ cr | C18: ='Annual Cash Flow'!C38 -> 3213.1963 | D18: ='Annual Cash Flow'!D38 -> 4071.356 | E18: ='Annual Cash Flow'!E38 -> 3553.6 | F18: ='Annual Cash Flow'!F38 -> 4432.0486 | G18: ='Annual Cash Flow'!G38 -> 4358.058 | H18: ='Annual Cash Flow'!H38 -> 8093.841 | I18: ='Annual Cash Flow'!I38 -> 5285.2743 | J18: ='Annual Cash Flow'!J38 -> 5571.964 | ... Q18: ='Annual Cash Flow'!Q38 -> 9597.0303
A19: FCF | B19: ₹ cr | C19: ='Annual Cash Flow'!C88 -> 2286.6963 | D19: ='Annual Cash Flow'!D88 -> 3303.1643 | E19: ='Annual Cash Flow'!E88 -> 2536.9712 | F19: ='Annual Cash Flow'!F88 -> 3627.4486 | G19: ='Annual Cash Flow'!G88 -> 3513.458 | H19: ='Annual Cash Flow'!H88 -> 7427.841 | I19: ='Annual Cash Flow'!I88 -> 4326.8743 | J19: ='Annual Cash Flow'!J88 -> 4556.794 | ... Q19: ='Annual Cash Flow'!Q88 -> 8729.2389
A20: FCF / net income | B20: % | C20: ='Annual Cash Flow'!C89 -> 0.76404389 | D20: ='Annual Cash Flow'!D89 -> 1.1742776 | E20: ='Annual Cash Flow'!E89 -> 0.66766705 | F20: ='Annual Cash Flow'!F89 -> 0.84406057 | G20: ='Annual Cash Flow'!G89 -> 0.87118982 | H20: ='Annual Cash Flow'!H89 -> 1.6774485 | I20: ='Annual Cash Flow'!I89 -> 0.77736013 | J20: ='Annual Cash Flow'!J89 -> 0.94318644 | ... Q20: ='Annual Cash Flow'!Q89 -> 1.0899369
A21: Cash + investments | B21: ₹ cr | C21: ='Annual Balance Sheet'!C62 -> 6507.1237 | D21: ='Annual Balance Sheet'!D62 -> 5614.1408 | E21: ='Annual Balance Sheet'!E62 -> 7735.0749 | F21: ='Annual Balance Sheet'!F62 -> 9664.4913 | G21: ='Annual Balance Sheet'!G62 -> 8976.8873 | H21: ='Annual Balance Sheet'!H62 -> 13044.901 | I21: ='Annual Balance Sheet'!I62 -> 8661.3736 | J21: ='Annual Balance Sheet'!J62 -> 7469.912 | ... Q21: ='Annual Balance Sheet'!Q62 -> 15595.34
A22: Net cash / (debt) | B22: ₹ cr | C22: ='Annual Balance Sheet'!C63 -> 5504.9222 | D22: ='Annual Balance Sheet'!D63 -> 4394.7052 | E22: ='Annual Balance Sheet'!E63 -> 6009.1218 | F22: ='Annual Balance Sheet'!F63 -> 8259.7913 | G22: ='Annual Balance Sheet'!G63 -> 5348.8873 | H22: ='Annual Balance Sheet'!H63 -> 10175.101 | I22: ='Annual Balance Sheet'!I63 -> 6042.9375 | J22: ='Annual Balance Sheet'!J63 -> 4729.712 | ... Q22: ='Annual Balance Sheet'!Q63 -> 13089.304
A23: Total headcount | B23: # | C23: ='Revenue Drivers'!C6 -> 105432 | D23: ='Revenue Drivers'!D6 -> 117693 | E23: ='Revenue Drivers'!E6 -> 112807 | F23: ='Revenue Drivers'!F6 -> 121082 | G23: ='Revenue Drivers'!G6 -> 125236 | H23: ='Revenue Drivers'!H6 -> 121054 | I23: ='Revenue Drivers'!I6 -> 151173 | J23: ='Revenue Drivers'!J6 -> 152400 | ... Q23: ='Revenue Drivers'!Q6 -> 154362.43
A24: Implied billable IT FTE | B24: # | C24: ='Revenue Drivers'!C11 -> 55886.747 | D24: ='Revenue Drivers'!D11 -> 63339.329 | E24: ='Revenue Drivers'!E11 -> 60718.443 | F24: ='Revenue Drivers'!F11 -> 58468.186 | G24: ='Revenue Drivers'!G11 -> 59472.448 | H24: ='Revenue Drivers'!H11 -> 59805.198 | I24: ='Revenue Drivers'!I11 -> 71324.73 | J24: ='Revenue Drivers'!J11 -> 72461.746 | ... Q24: ='Revenue Drivers'!Q11 -> 70767.457
A25: LTM attrition | B25: % | C25: ='Revenue Drivers'!C35 -> 0.21073297 | D25: ='Revenue Drivers'!D35 -> 0.16516347 | E25: ='Revenue Drivers'!E35 -> 0.18084726 | F25: ='Revenue Drivers'!F35 -> 0.208 | G25: ='Revenue Drivers'!G35 -> 0.191 | H25: ='Revenue Drivers'!H35 -> 0.133 | I25: ='Revenue Drivers'!I35 -> 0.235 | J25: ='Revenue Drivers'!J35 -> 0.148 | ... Q25: ='Revenue Drivers'!Q35 -> 0.105
A26: TCV | B26: $m | C26: ='Revenue Drivers'!C22 -> 0 | D26: ='Revenue Drivers'!D22 -> 0 | E26: ='Revenue Drivers'!E22 -> 0 | F26: ='Revenue Drivers'!F22 -> 1666.9 | G26: ='Revenue Drivers'!G22 -> 3712 | H26: ='Revenue Drivers'!H22 -> 2209.69 | I26: ='Revenue Drivers'!I22 -> 3280 | J26: ='Revenue Drivers'!J22 -> 2905 | ... Q26: ='Revenue Drivers'!Q22 -> 4834.1102
A27: Revenue / $1m+ client proxy | B27: $m | C27: ='Client Data'!C18 -> 12.6566 | D27: ='Client Data'!D18 -> 12.291221 | E27: ='Client Data'!E18 -> 12.170321 | F27: ='Client Data'!F18 -> 11.695348 | G27: ='Client Data'!G18 -> 11.618543 | H27: ='Client Data'!H18 -> 11.332727 | I27: ='Client Data'!I18 -> 11.446164 | J27: ='Client Data'!J18 -> 11.351409 | ... Q27: ='Client Data'!Q18 -> 11.314865
A28: AI uplift | B28: ₹ cr | C28: ='Revenue Drivers'!C29 -> 0 | D28: ='Revenue Drivers'!D29 -> 0 | E28: ='Revenue Drivers'!E29 -> 0 | F28: ='Revenue Drivers'!F29 -> 0 | G28: ='Revenue Drivers'!G29 -> 0 | H28: ='Revenue Drivers'!H29 -> 0 | I28: ='Revenue Drivers'!I29 -> 0 | J28: ='Revenue Drivers'!J29 -> 0 | ... Q28: ='Revenue Drivers'!Q29 -> 1266.7596
A29: AI deflation drag | B29: ₹ cr | C29: ='Revenue Drivers'!C21 -> 0 | D29: ='Revenue Drivers'!D21 -> 0 | E29: ='Revenue Drivers'!E21 -> 0 | F29: ='Revenue Drivers'!F21 -> 0 | G29: ='Revenue Drivers'!G21 -> 0 | H29: ='Revenue Drivers'!H21 -> 0 | I29: ='Revenue Drivers'!I21 -> 0 | J29: ='Revenue Drivers'!J21 -> 0 | ... Q29: ='Revenue Drivers'!Q21 -> -555.70935
A30: Share price / implied target | B30: ₹ / share | C30: =Valuation!C7 -> 474.95001 | D30: =Valuation!D7 -> 459.14999 | E30: =Valuation!E7 -> 638.70001 | F30: =Valuation!F7 -> 771.70001 | G30: =Valuation!G7 -> 565.5 | H30: =Valuation!H7 -> 991.45001 | I30: =Valuation!I7 -> 1499.45 | J30: =Valuation!J7 -> 1101.85 | ... Q30: =Valuation!Q7 -> 2165.0698
A31: P/E | B31: x | C31: =Valuation!C14 -> 14.087557 | D31: =Valuation!D14 -> 14.50951 | E31: =Valuation!E14 -> 14.97026 | F31: =Valuation!F14 -> 16.171247 | G31: =Valuation!G14 -> 12.333697 | H31: =Valuation!H14 -> 19.753935 | I31: =Valuation!I14 -> 23.87279 | J31: =Valuation!J14 -> 20.195197 | ... Q31: =Valuation!Q14 -> 24
A32: EV / EBITDA | B32: x | C32: =Valuation!C15 -> 8.5835142 | D32: =Valuation!D15 -> 8.703583 | E32: =Valuation!E15 -> 10.802327 | F32: =Valuation!F15 -> 9.6636928 | G32: =Valuation!G15 -> 7.7526885 | H32: =Valuation!H15 -> 11.289026 | I32: =Valuation!I15 -> 15.814958 | J32: =Valuation!J15 -> 11.563265 | ... Q32: =Valuation!Q15 -> 14.426863
A33: Dividend yield | B33: % | C33: =Valuation!C18 -> 0.014811757 | D33: =Valuation!D18 -> 0.030361056 | E33: =Valuation!E18 -> 0.016591552 | F33: =Valuation!F18 -> 0.021449595 | G33: =Valuation!G18 -> 0.0500934 | H33: =Valuation!H18 -> 0.020113445 | I33: =Valuation!I18 -> 0.029958222 | J33: =Valuation!J18 -> 0.043695453 | ... Q33: =Valuation!Q18 -> 0.033333333

Sheet Sources
A1: Sources & Data Conventions
A2: Official source register, including the Q1 FY27 Tech Mahindra data sheet used for the latest-quarter update
A5: ID | B5: Data / Period | C5: Units | D5: Primary source | E5: Use in model | F5: Status | G5: Notes
A6: S1 | B6: FY16–FY26 data sheet | C6: ₹ mn / $m / % / # | D6: https://insights.techmahindra.com/investors/tml-q4-fy-26-datasheet.xlsx | E6: Quarterly P&L, annual BS/CFS and operating metrics | F6: Loaded | G6: Official company file; cached values used for external-link cells
A7: S2 | B7: Quarterly earnings archive | C7: mixed | D7: https://www.techmahindra.com/investors/quarterly-earnings/ | E7: Cross-checks and disclosure definitions | F7: Referenced | G7: Company investor archive
A8: S3 | B8: FY26 Q4 earnings presentation | C8: mixed | D8: https://insights.techmahindra.com/investors/tml-q4-fy-26-earnings-presentation.pdf | E8: FY26 strategy and operating context | F8: Loaded | G8: No historical AI revenue hardcoded unless explicitly disclosed
A9: S4 | B9: Annual reports archive | C9: ₹ mn | D9: https://www.techmahindra.com/investors/annual-reports-filings/?report-section=tech-mahindra | E9: Accounting policy and annual cross-checks | F9: Referenced | G9: Official annual reports
A10: S5 | B10: TECHM.NS daily prices | C10: ₹ / share | D10: https://query1.finance.yahoo.com/v8/finance/chart/TECHM.NS | E10: Historical price tab and FY-end prices | F10: Loaded | G10: Market price source only; valuation formulas are model calculations
A11: S6 | B11: Industry classifications | C11: % | D11: Official FY26 data sheet — Operating Metrics | E11: Industry revenue tabs | F11: Loaded | G11: Legacy, FY22–23 recast and FY24+ current classifications kept separate
A12: S7 | B12: Cash-flow dividends | C12: ₹ mn | D12: Official FY26 data sheet — Cash Flow rows 77 and 81 | E12: Dividend paid and payout calculations | F12: Loaded | G12: Both reported dividend rows retained separately; total dividend is their sum
A13: S8 | B13: Unavailable disclosures | C13: n/a | D13: n/a | E13: Blanks retained | F13: Policy | G13: No unreported historical T&M mix or historical AI revenue is invented
A14: S9 | B14: Q1 FY27 data sheet | C14: ₹ mn / $m / % / # | D14: https://insights.techmahindra.com/investors/tml-q1-fy-27-datasheet.xlsx | E14: Q1 FY27 P&L, operating metrics, liquidity and cash-flow snapshot | F14: Loaded | G14: Official company data sheet; Q1 values converted from ₹ million to ₹ crore where applicable

Sheet Assumptions
A1: Forecast Assumptions
A2: Blue text on yellow = editable input; balance-sheet forecasts use explicit drivers and cash is calculated from the cash-flow statement
A5: Driver | B5: Units | C5: FY27E | D5: FY28E | E5: FY29E | F5: FY30E | G5: Rationale / anchor
A6: Total headcount growth | B6: % | C6: 0 | D6: 0.01 | E6: 0.015 | F6: 0.02
A7: Software professional share | B7: % | C7: 0.515 | D7: 0.52 | E7: 0.525 | F7: 0.53
A8: Utilization / billable rate | B8: % | C8: 0.86 | D8: 0.862 | E8: 0.865 | F8: 0.865
A9: Revenue per billable FTE pricing / productivity | B9: % | C9: 0.02 | D9: 0.025 | E9: 0.03 | F9: 0.03
A10: Billable capacity revenue realization | B10: % | C10: 0.5 | D10: 0.5 | E10: 0.5 | F10: 0.5
A11: Core revenue retention | B11: % | C11: 0.96 | D11: 0.96 | E11: 0.96 | F11: 0.96
A12: T&M mix | B12: % | C12: 0.35 | D12: 0.33 | E12: 0.31 | F12: 0.3
A13: AI deflation on T&M revenue | B13: % | C13: 0.015 | D13: 0.02 | E13: 0.025 | F13: 0.03
A14: TCV growth | B14: % | C14: 0.05 | D14: 0.06 | E14: 0.07 | F14: 0.07
A15: TCV current-year revenue realization | B15: % | C15: 0.08 | D15: 0.08 | E15: 0.08 | F15: 0.08
A16: AI revenue uplift / prior-year revenue | B16: % | C16: 0.008 | D16: 0.012 | E16: 0.016 | F16: 0.02
A17: Client-mining uplift / prior-year revenue | B17: % | C17: 0.005 | D17: 0.006 | E17: 0.007 | F17: 0.008
... A33: Current operating liabilities / revenue | B33: % | C33: 0.23 | D33: 0.228 | E33: 0.226 | F33: 0.225
A34: Other non-current liabilities / revenue | B34: % | C34: 0.001 | D34: 0.001 | E34: 0.001 | F34: 0.001 | G34: Reset from 5%+ of revenue; FY26 reported other non-current liabilities were immaterial.
A35: Capex / revenue | B35: % | C35: 0.013 | D35: 0.013 | E35: 0.013 | F35: 0.013
A36: ROU additions / revenue | B36: % | C36: 0.012 | D36: 0.012 | E36: 0.012 | F36: 0.012 | G36: ROU additions calibrated to keep ROU assets and lease liabilities broadly stable relative to revenue.
A37: Lease principal / opening lease liability | B37: % | C37: 0.3 | D37: 0.3 | E37: 0.3 | F37: 0.3 | G37: Lease principal as a percentage of opening total lease liabilities.
A38: Acquisitions / business payments | B38: ₹ cr | C38: 0 | D38: 0 | E38: 0 | F38: 0
A39: Net borrowing change | B39: ₹ cr | C39: 0 | D39: 0 | E39: 0 | F39: 0
A40: Current debt share | B40: % | C40: 0.15 | D40: 0.15 | E40: 0.15 | F40: 0.15
A41: Dividend payout | B41: % | C41: 0.8 | D41: 0.8 | E41: 0.8 | F41: 0.8
A42: Other comprehensive income / reserves | B42: ₹ cr | C42: 0 | D42: 0 | E42: 0 | F42: 0
A43: Diluted share count change | B43: % | C43: 0 | D43: 0 | E43: 0 | F43: 0
A44: Target P/E | B44: x | C44: 22.5 | D44: 23 | E44: 23.5 | F44: 24
A45: LTM attrition | B45: % | C45: 0.12 | D45: 0.115 | E45: 0.11 | F45: 0.105
A46: Current lease liability share | B46: % | C46: 0.25 | D46: 0.25 | E46: 0.25 | F46: 0.25
A47: Current tax liabilities / revenue | B47: % | C47: 0.035 | D47: 0.034 | E47: 0.033 | F47: 0.032
A48: Trade payables / revenue | B48: % | C48: 0.088 | D48: 0.087 | E48: 0.086 | F48: 0.085
A49: Current provisions / revenue | B49: % | C49: 0.022 | D49: 0.021 | E49: 0.02 | F49: 0.02
... A52: Share-based compensation / revenue | B52: % | C52: 0.002 | D52: 0.002 | E52: 0.002 | F52: 0.002
A54: Balance-sheet and cash-flow forecast drivers
A55: D&A allocation — PPE | B55: % | C55: 0.35 | D55: 0.35 | E55: 0.35 | F55: 0.35 | G55: Explicit allocation; forecast D&A allocations sum to 100%.
A56: D&A allocation — ROU assets | B56: % | C56: 0.35 | D56: 0.35 | E56: 0.35 | F56: 0.35 | G56: Explicit allocation; used in the ROU asset roll-forward.
A57: D&A allocation — intangibles | B57: % | C57: 0.3 | D57: 0.3 | E57: 0.3 | F57: 0.3 | G57: Explicit allocation; used in the intangible asset roll-forward.
A58: Intangible additions / revenue | B58: % | C58: 0.003 | D58: 0.003 | E58: 0.003 | F58: 0.003 | G58: Included within total capex; prevents unsupported hardcoded intangible balances.
A59: Closing CWIP / tangible capex | B59: % | C59: 0.04 | D59: 0.04 | E59: 0.04 | F59: 0.04 | G59: Anchored to FY26 CWIP as a share of annual capex.
A60: Inventories / revenue | B60: % | C60: 0.0018 | D60: 0.0018 | E60: 0.0018 | F60: 0.0018 | G60: Anchored to the FY26 reported ratio.
A61: Current investments / revenue | B61: % | C61: 0.06 | D61: 0.06 | E61: 0.06 | F61: 0.06 | G61: Explicit liquidity allocation; replaces the former balance-sheet plug.
A62: Other bank balances / revenue | B62: % | C62: 0.001 | D62: 0.001 | E62: 0.001 | F62: 0.001 | G62: Anchored to the FY26 reported ratio.
A63: Other tax assets / revenue | B63: % | C63: 0.053 | D63: 0.052 | E63: 0.051 | F63: 0.05 | G63: Gradual normalization from the FY26 reported ratio.
A64: Deferred tax assets / revenue | B64: % | C64: 0.038 | D64: 0.037 | E64: 0.036 | F64: 0.035 | G64: Gradual normalization from the FY26 reported ratio.
A65: Other non-current financial assets / revenue | B65: % | C65: 0.006 | D65: 0.006 | E65: 0.006 | F65: 0.006 | G65: Anchored to the FY26 reported ratio.
A66: Non-current provisions / revenue | B66: % | C66: 0.03 | D66: 0.029 | E66: 0.028 | F66: 0.027 | G66: Gradual normalization from the FY26 reported ratio.
... A69: Other non-current financial liabilities / revenue | B69: % | C69: 0.001 | D69: 0.001 | E69: 0.001 | F69: 0.001 | G69: Anchored to the FY26 reported ratio.

Sheet Raw Financials
A1: Raw Reported Financials — Source Layer
A2: Official Tech Mahindra reported inputs only; quarterly P&L updated through Q1 FY27A; annual statements remain FY16–FY30E
A4: Annual reported P&L (INR crore unless stated)
A5: Metric | B5: Units | C5: FY16A | D5: FY17A | E5: FY18A | F5: FY19A | G5: FY20A | H5: FY21A | I5: FY22A | J5: FY23A | K5: FY24A | L5: FY25A | M5: FY26A
A6: Revenue | B6: ₹ cr | C6: 26494.232 | D6: 29140.841 | E6: 30772.881 | F6: 34742.132 | G6: 36867.679 | H6: 37855.081 | I6: 44645.964 | J6: 53290.167 | K6: 51995.541 | L6: 52988.3 | M6: 56815.4
A7: Cost of services | B7: ₹ cr | C7: 18329.038 | D7: 20566.059 | E7: 21530.042 | F7: 23358.982 | G7: 25974.337 | H7: 25855.48 | I7: 30972.015 | J7: 38119.703 | K7: 39114.67 | L7: 38084.794 | M7: 39868.82
A8: Gross profit | B8: ₹ cr | C8: 8165.1946 | D8: 8574.7821 | E8: 9242.8906 | F8: 11383.149 | G8: 10893.442 | H8: 11999.6 | I8: 13673.949 | J8: 15170.464 | K8: 12880.882 | L8: 14903.506 | M8: 16946.579
A9: SG&A | B9: ₹ cr | C9: 3894.5043 | D9: 4390.3473 | E9: 4533.2804 | F9: 5046.2316 | G9: 5167.303 | H9: 5152.554 | I9: 5653.965 | J9: 7141.688 | K9: 7916.272 | L9: 7912.4214 | M9: 7912.4797
A10: EBITDA | B10: ₹ cr | C10: 4270.6903 | D10: 4184.4348 | E10: 4709.6102 | F10: 6336.9176 | G10: 5726.139 | H10: 6847.047 | I10: 8019.984 | J10: 8028.776 | K10: 4964.54 | L10: 6991.1424 | M10: 9034.0995
A11: D&A | B11: ₹ cr | C11: 758.923 | D11: 978.0552 | E11: 1085.038 | F11: 1129.2 | G11: 1445.769 | H11: 1457.71 | I11: 1520.392 | J11: 1956.7 | K11: 1817.098 | L11: 1852.8996 | M11: 1881.6
A12: EBIT | B12: ₹ cr | C12: 3511.7673 | D12: 3206.3796 | E12: 3624.5722 | F12: 5207.7176 | G12: 4280.27 | H12: 5389.337 | I12: 6499.591 | J12: 6072.076 | K12: 3147.511 | L12: 5138.2428 | M12: 7152.4995
A13: Impairment | B13: ₹ cr | G13: 217.5 | H13: 50.7 | I13: 0 | J13: 237 | K13: 458.22 | L13: 27.300702 | M13: 5.3290705e-16
A14: Other income total | B14: ₹ cr | C14: 439.37796 | D14: 777.5589 | E14: 1416.45 | F14: 534.15286 | G14: 1192.39 | H14: 787.116 | I14: 1112.316 | J14: 965 | K14: 916.898 | L14: 855.39962 | M14: 31.9
A15: FX gain / (loss) | B15: ₹ cr | C15: 98.59186 | D15: 387.58728 | E15: 774.95874 | F15: 12.109998 | G15: 302.2 | H15: 97.5 | I15: 564.214 | J15: 299 | K15: -42.099 | L15: -237.60038 | M15: -479.9
A16: Interest, dividend & miscellaneous income | B16: ₹ cr | C16: 340.7861 | D16: 389.97161 | E16: 641.4893 | F16: 522.09286 | G16: 890.19 | H16: 689.616 | I16: 548.102 | J16: 666 | K16: 958.998 | L16: 1093 | M16: 511.8
A17: Interest expense | B17: ₹ cr | C17: 97.037558 | D17: 128.59243 | E17: 162.35364 | F17: 133.161 | G17: 191.878 | H17: 174 | I17: 162.6 | J17: 325.6 | K17: 392.199 | L17: 321.7 | M17: 337.4
A18: Share of associate | B18: ₹ cr | C18: 2.6293348 | D18: -2.3315044 | E18: 0.0699921 | F18: -65.549 | G18: -5.54 | H18: 1.2 | I18: 2.8 | J18: -29 | K18: 10.5 | L18: 8.6 | M18: -1.5
A19: PBT before exceptional | B19: ₹ cr | C19: 3856.737 | D19: 3853.0146 | E19: 4878.7506 | F19: 5543.1605 | G19: 5057.842 | H19: 5952.853 | I19: 7452.107 | J19: 6445.477 | K19: 3224.39 | L19: 5653.2418 | M19: 6845.4995
A20: Exceptional item | B20: ₹ cr | C20: 0 | D20: 0 | E20: 0 | F20: 0 | G20: 0 | I20: 0 | J20: 0 | M20: 272.4
A21: PBT | B21: ₹ cr | G21: 5057.842 | H21: 5952.853 | I21: 7452.107 | J21: 6445.477 | K21: 3224.39 | L21: 5653.2418 | M21: 6573.0995
A22: Tax | B22: ₹ cr | C22: 830.11881 | D22: 1002.1243 | E22: 1092.5615 | F22: 1254.394 | G22: 1160.4 | H22: 1599.894 | I22: 1821.994 | J22: 1588.5 | K22: 827.596 | L22: 1400.2 | M22: 1767.5995
A23: PAT before NCI | B23: ₹ cr | C23: 3026.6182 | D23: 2850.8903 | E23: 3786.1891 | F23: 4288.7665 | G23: 3897.442 | H23: 4352.959 | I23: 5630.113 | J23: 4856.977 | K23: 2396.793 | L23: 4253.0418 | M23: 4805.5
A24: NCI / minority interest | B24: ₹ cr | C24: -33.732182 | D24: -37.957189 | E24: 13.579915 | F24: 8.8 | G24: 135.6 | H24: 75 | I24: -64 | J24: 25.7 | K24: 38.999 | L24: 1.5 | M24: -5.3996265
A25: Net income attributable | B25: ₹ cr | C25: 2992.886 | D25: 2812.9331 | E25: 3799.769 | F25: 4297.5665 | G25: 4033.042 | H25: 4427.959 | I25: 5566.113 | J25: 4831.277 | K25: 2357.793 | L25: 4251.5418 | M25: 4810.8996
A26: Reported basic EPS | B26: ₹ / share | C26: 34.508496 | D26: 32.135676 | E26: 43.020352 | F26: 48.474931 | G26: 46.21 | H26: 50.64 | I26: 63.32 | J26: 54.79 | K26: 26.66 | L26: 48.004796 | M26: 54.279265
A27: Reported diluted EPS | B27: ₹ / share | C27: 33.71415 | D27: 31.644762 | E27: 42.664589 | F27: 47.720502 | G27: 45.85 | H27: 50.19 | I27: 62.81 | J27: 54.56 | K27: 26.57 | L27: 47.906128 | M27: 54.189099
A28: USD revenue | B28: $m | C28: 4037.4553 | D28: 4351.0924 | E28: 4770.7659 | F28: 4970.5229 | G28: 5181.87 | H28: 5111.06 | I28: 5997.79 | J28: 6606.52 | K28: 6277.11 | L28: 6263.9885 | M28: 6384.8643
A32: Quarterly reported P&L (INR crore unless stated)
A33: Metric | B33: Units | C33: Q1 FY16A | D33: Q2 FY16A | E33: Q3 FY16A | F33: Q4 FY16A | G33: Q1 FY17A | H33: Q2 FY17A | I33: Q3 FY17A | J33: Q4 FY17A | K33: Q1 FY18A | L33: Q2 FY18A | M33: Q3 FY18A | N33: Q4 FY18A | O33: Q1 FY19A | P33: Q2 FY19A | Q33: Q3 FY19A | R33: Q4 FY19A | S33: Q1 FY20A | T33: Q2 FY20A | U33: Q3 FY20A | V33: Q4 FY20A | W33: Q1 FY21A | X33: Q2 FY21A | Y33: Q3 FY21A | Z33: Q4 FY21A | AA33: Q1 FY22A | AB33: Q2 FY22A | AC33: Q3 FY22A | AD33: Q4 FY22A | AE33: Q1 FY23A | AF33: Q2 FY23A | AG33: Q3 FY23A | AH33: Q4 FY23A | AI33: Q1 FY24A | AJ33: Q2 FY24A | AK33: Q3 FY24A | AL33: Q4 FY24A | AM33: Q1 FY25A | AN33: Q2 FY25A | AO33: Q3 FY25A | AP33: Q4 FY25A | AQ33: Q1 FY26A | AR33: Q2 FY26A | AS33: Q3 FY26A | AT33: Q4 FY26A | AU33: Q1 FY27A
A34: Revenue | B34: ₹ cr | C34: 6293.8237 | D34: 6615.535 | E34: 6701.1416 | F34: 6883.832 | G34: 6920.9344 | H34: 7167.4101 | I34: 7557.5027 | J34: 7494.9943 | K34: 7336.1015 | L34: 7606.3316 | M34: 7775.9562 | N34: 8054.4918 | O34: 8276.2768 | P34: 8629.8487 | Q34: 8943.7135 | R34: 8892.2925 | S34: 8653.029 | T34: 9069.8861 | U34: 9654.5972 | V34: 9490.1669 | W34: 9106.3485 | X34: 9371.7577 | Y34: 9647.0624 | Z34: 9729.912 | AA34: 10197.569 | AB34: 10881.329 | AC34: 11450.79 | AD34: 12116.276 | AE34: 12707.948 | AF34: 13129.468 | AG34: 13734.561 | AH34: 13718.191 | AI34: 13158.977 | AJ34: 12863.917 | AK34: 13101.337 | AL34: 12871.321 | AM34: 13005.474 | AN34: 13313.222 | AO34: 13285.603 | AP34: 13384.001 | AQ34: 13351.2 | AR34: 13994.9 | AS34: 14393.2 | AT34: 15076.1 | AU34: 15711.9
A35: Cost of services | B35: ₹ cr | C35: 4444.0768 | D35: 4499.8859 | E35: 4606.9072 | F35: 4778.1677 | G35: 4880.6965 | H35: 4971.6661 | I35: 5235.2369 | J35: 5478.4599 | K35: 5281.8369 | L35: 5378.9078 | M35: 5380.7436 | N35: 5488.6133 | O35: 5733.9752 | P35: 5692.3055 | Q35: 5984.5337 | R35: 5948.168 | S35: 6164.1896 | T35: 6389.31 | U35: 6731.1711 | V35: 6689.5661 | W35: 6510.4657 | X35: 6424.5493 | Y35: 6470.7935 | Z35: 6449.6548 | AA35: 6968.2267 | AB35: 7434.6173 | AC35: 8008.8287 | AD35: 8560.3421 | AE35: 9116.1914 | AF35: 9461.3919 | AG35: 9793.742 | AH35: 9748.3781 | AI35: 9780.528 | AJ35: 9975.187 | AK35: 9964.831 | AL35: 9394.124 | AM35: 9553.175 | AN35: 9595.681 | AO35: 9455.913 | AP35: 9480.0253 | AQ35: 9523.6221 | AR35: 9915.8871 | AS35: 10027.556 | AT35: 10401.756 | AU35: 10925.9
A36: Gross profit | B36: ₹ cr | C36: 1849.7469 | D36: 2115.6491 | E36: 2094.2343 | F36: 2105.6642 | G36: 2040.2379 | H36: 2195.744 | I36: 2322.2657 | J36: 2016.5345 | K36: 2054.2646 | L36: 2227.4409 | M36: 2395.2527 | N36: 2565.8784 | O36: 2542.3016 | P36: 2937.5432 | Q36: 2959.1799 | R36: 2944.1245 | S36: 2488.8394 | T36: 2680.5761 | U36: 2923.4261 | V36: 2800.6008 | W36: 2595.8329 | X36: 2947.2514 | Y36: 3176.2688 | Z36: 3280.1573 | AA36: 3229.4422 | AB36: 3446.7121 | AC36: 3441.9608 | AD36: 3556.034 | AE36: 3591.6564 | AF36: 3668.0763 | AG36: 3940.8505 | AH36: 3969.8129 | AI36: 3378.549 | AJ36: 2888.73 | AK36: 3136.489 | AL36: 3477.198 | AM36: 3452.298 | AN36: 3717.541 | AO36: 3829.69 | AP36: 3903.976 | AQ36: 3827.5779 | AR36: 4079.0125 | AS36: 4365.6444 | AT36: 4674.3445 | AU36: 4786
A37: SG&A | B37: ₹ cr | C37: 944.75481 | D37: 1028.8609 | E37: 966.2309 | F37: 954.75776 | G37: 1011.1581 | H37: 1125.6222 | I37: 1135.7654 | J37: 1117.8017 | K37: 1119.6513 | L37: 1121.7821 | M37: 1137.7603 | N37: 1153.9866 | O37: 1185.3942 | P37: 1318.8096 | Q37: 1236.551 | R37: 1305.3767 | S37: 1174.7104 | T37: 1179.7077 | U37: 1360.1441 | V37: 1452.7411 | W37: 1295.341 | X37: 1244.2749 | Y37: 1280.9445 | Z37: 1332.0932 | AA37: 1352.9733 | AB37: 1451.4975 | AC37: 1381.9415 | AD37: 1467.5532 | AE37: 1711.6086 | AF37: 1683.9573 | AG37: 1796.8511 | AH37: 1949.2738 | AI37: 2040.469 | AJ37: 1816.414 | AK37: 1990.042 | AL37: 2069.397 | AM37: 1887.825 | AN37: 1967.304 | AO37: 2020.71 | AP37: 2036.5803 | AQ37: 1892.3779 | AR37: 1911.0129 | AS37: 2000.0444 | AT37: 2109.0445 | AU37: 2043.5
A38: EBITDA | B38: ₹ cr | C38: 904.99209 | D38: 1086.7882 | E38: 1128.0034 | F38: 1150.9065 | G38: 1029.0799 | H38: 1070.1218 | I38: 1186.5003 | J38: 898.73282 | K38: 934.61328 | L38: 1105.6487 | M38: 1257.5003 | N38: 1411.8889 | O38: 1356.9074 | P38: 1618.7336 | Q38: 1722.6288 | R38: 1638.7478 | S38: 1314.129 | T38: 1500.8684 | U38: 1563.282 | V38: 1347.8598 | W38: 1300.5418 | X38: 1702.9765 | Y38: 1895.4243 | Z38: 1948.0641 | AA38: 1876.3688 | AB38: 1995.2146 | AC38: 2060.0194 | AD38: 2088.3809 | AE38: 1880.1477 | AF38: 1984.1191 | AG38: 2143.9704 | AH38: 2020.5391 | AI38: 1337.98 | AJ38: 1072.316 | AK38: 1146.464 | AL38: 1407.8 | AM38: 1564.474 | AN38: 1750.237 | AO38: 1808.98 | AP38: 1867.3957 | AQ38: 1935.2 | AR38: 2167.9996 | AS38: 2365.6 | AT38: 2565.3 | AU38: 2742.5
A39: D&A | B39: ₹ cr | C39: 172.4159 | D39: 196.53226 | E39: 172.65135 | F39: 217.3235 | G39: 201.87768 | H39: 244.74799 | I39: 247.9649 | J39: 283.46462 | K39: 246.84448 | L39: 265.35834 | M39: 274.1945 | N39: 298.64069 | O39: 280.77248 | P39: 294.42932 | Q39: 283.58468 | R39: 270.41352 | S39: 321.3 | T39: 341.45864 | U39: 384.81181 | V39: 398.19855 | W39: 383.2 | X39: 371.67778 | Y39: 358.36199 | Z39: 344.36983 | AA39: 331.1 | AB39: 342.95005 | AC39: 362.10011 | AD39: 484.24203 | AE39: 476.7 | AF39: 491.7 | AG39: 498.10014 | AH39: 490.2 | AI39: 446.6 | AJ39: 465.7 | AK39: 443.4 | AL39: 461.4 | AM39: 462.2 | AN39: 469.8 | AO39: 458.8 | AP39: 462.1 | AQ39: 458.1 | AR39: 468.7 | AS39: 473.7 | AT39: 481.1 | AU39: 478.6
A40: EBIT | B40: ₹ cr | C40: 732.57618 | D40: 890.25595 | E40: 955.35209 | F40: 933.58299 | G40: 827.20218 | H40: 825.37382 | I40: 938.53544 | J40: 615.2682 | K40: 687.75079 | L40: 840.24039 | M40: 983.30584 | N40: 1113.2512 | O40: 1076.1349 | P40: 1324.3043 | Q40: 1439.0441 | R40: 1368.3343 | S40: 992.82896 | T40: 1159.4098 | U40: 1178.4702 | V40: 949.56122 | W40: 917.34183 | X40: 1331.2988 | Y40: 1536.9624 | Z40: 1603.6942 | AA40: 1545.2688 | AB40: 1652.1645 | AC40: 1697.9193 | AD40: 1604.2388 | AE40: 1403.4477 | AF40: 1492.4191 | AG40: 1645.8702 | AH40: 1530.3391 | AI40: 891.38 | AJ40: 606.616 | AK40: 703.064 | AL40: 946.4 | AM40: 1102.274 | AN40: 1280.437 | AO40: 1350.18 | AP40: 1405.2957 | AQ40: 1477.1 | AR40: 1699.2996 | AS40: 1891.9 | AT40: 2084.2 | AU40: 2263.9
A41: Impairment | B41: ₹ cr | V41: 217.5 | W41: 0 | X41: 0 | Y41: 0 | Z41: 50.7 | AA41: 0 | AB41: 0 | AC41: 0 | AD41: 0 | AE41: 0 | AF41: 24.4 | AG41: 0 | AH41: 212.6 | AI41: 0 | AJ41: 149.5 | AK41: 0.000243524 | AL41: 308.7 | AM41: 0 | AN41: 0 | AO41: 0 | AP41: 27.300367 | AQ41: 0 | AR41: 0 | AS41: 0 | AT41: 0 | AU41: 0
A42: Other income total | B42: ₹ cr | C42: 124.44579 | D42: 97.760828 | E42: 61.857079 | F42: 155.31426 | G42: 245.79645 | H42: 138.71927 | I42: 155.19625 | J42: 237.84692 | K42: 410.90054 | L42: 322.15663 | M42: 232.13896 | N42: 451.2539 | O42: 111.39728 | P42: 175.05295 | Q42: 80.55981 | R42: 167.14282 | S42: 341.3 | T42: 216.33868 | U42: 349.592 | V42: 285.15932 | W42: 416.1 | X42: 117.5 | Y42: 220.916 | Z42: 32.6 | AA42: 287.3 | AB42: 282.116 | AC42: 223.1 | AD42: 319.8 | AE42: 122.1 | AF42: 290.20049 | AG42: 247.2 | AH42: 305.5 | AI42: 191.7 | AJ42: 264.2 | AK42: 87.5 | AL42: 373.5 | AM42: 144.7 | AN42: 521.5 | AO42: 16.5 | AP42: 172.7 | AQ42: 218.3 | AR42: 40 | AS42: -21.7 | AT42: -204.7 | AU42: -106.4
A43: FX gain / (loss) | B43: ₹ cr | C43: 79.854662 | D43: -20.448292 | E43: -13.136941 | F43: 52.342432 | G43: 47.890939 | H43: 87.622259 | I43: 90.419583 | J43: 161.6545 | K43: 272.64986 | L43: 226.95068 | M43: 101.14944 | N43: 174.25076 | O43: 14.655578 | P43: 50.051803 | Q43: -77.891057 | R43: 25.193673 | S43: 101.8 | T43: 49.597158 | U43: 143.5 | V43: 7.3028417 | W43: 85.7 | X43: -35.6 | Y43: 110.2 | Z43: -62.8 | AA43: 107.7 | AB43: 121.3 | AC43: 124.41389 | AD43: 210.8 | AE43: 53.6 | AF43: 126.7 | AG43: 125.1 | AH43: -6.4 | AI43: 44.5 | AJ43: -3 | AK43: -43.5 | AL43: -40.1 | AM43: -6.5 | AN43: -101.3 | AO43: -91.4 | AP43: -38.4 | AQ43: 29.7 | AR43: -109.5 | AS43: -115.8 | AT43: -284.3 | AU43: -214
A44: Interest, dividend & miscellaneous income | B44: ₹ cr | C44: 44.591127 | D44: 118.20912 | E44: 74.99402 | F44: 102.97183 | G44: 197.90552 | H44: 51.097014 | I44: 64.776663 | J44: 76.192422 | K44: 138.25068 | L44: 95.205952 | M44: 131.00952 | N44: 276.97314 | O44: 96.741704 | P44: 124.95115 | Q44: 158.45087 | R44: 141.94914 | S44: 239.5 | T44: 166.74152 | U44: 206.092 | V44: 277.85648 | W44: 330.4 | X44: 153.1 | Y44: 110.716 | Z44: 95.4 | AA44: 179.6 | AB44: 160.816 | AC44: 98.686114 | AD44: 109 | AE44: 68.5 | AF44: 163.50049 | AG44: 122.1 | AH44: 311.9 | AI44: 147.2 | AJ44: 267.2 | AK44: 131 | AL44: 413.6 | AM44: 151.2 | AN44: 622.8 | AO44: 107.9 | AP44: 211.1 | AQ44: 188.6 | AR44: 149.5 | AS44: 94.1 | AT44: 79.6 | AU44: 107.6
A45: Interest expense | B45: ₹ cr | C45: 21.463855 | D45: 17.492207 | E45: 24.612005 | F45: 33.449491 | G45: 27.405197 | H45: 34.510163 | I45: 34.887159 | J45: 31.789909 | K45: 36.953496 | L45: 38.627935 | M45: 34.054201 | N45: 52.688013 | O45: 30.519884 | P45: 38.760564 | Q45: 35.848417 | R45: 28.132134 | S45: 45.4 | T45: 38.250848 | U45: 55 | V45: 53.227152 | W45: 50.3 | X45: 39.9 | Y45: 42.1 | Z45: 41.7 | AA45: 38.1 | AB45: 35.4 | AC45: 33.9 | AD45: 55.2 | AE45: 40.3 | AF45: 79 | AG45: 112.90001 | AH45: 93.4 | AI45: 119.699 | AJ45: 97.5 | AK45: 116.5 | AL45: 58.5 | AM45: 71.5 | AN45: 89 | AO45: 75.9 | AP45: 85.3 | AQ45: 77.8 | AR45: 77.2 | AS45: 93.6 | AT45: 88.8 | AU45: 111.3
A46: Share of associate | B46: ₹ cr | C46: 1.0734657 | D46: 0.32416479 | E46: -0.12559858 | F46: 1.2753029 | G46: -2.2679132 | H46: -0.2174587 | I46: 0.1520472 | J46: 0.0018203 | K46: 0.0226153 | L46: 0.0122206 | M46: 0.0131319 | N46: 0.0220243 | O46: -11.829282 | P46: -13.250756 | Q46: -13.24895 | R46: -27.240012 | S46: -7.8 | T46: 0.2986538 | U46: 0.5 | V46: 1.4613462 | W46: 0.1 | X46: 0.4 | Y46: 0.5 | Z46: 0.2 | AA46: -0.2 | AB46: -0.8 | AC46: -0.7 | AD46: 4.5 | AE46: 0.3 | AF46: -15.3 | AG46: -9 | AH46: -5 | AI46: 7.8 | AJ46: -8.5 | AK46: 4.8 | AL46: 6.4 | AM46: 2.6 | AN46: 0.6 | AO46: 6.6 | AP46: -1.2 | AQ46: 0.5 | AR46: -2.8 | AS46: 0.9 | AT46: -0.1 | AU46: -4.3
A47: PBT before exceptional | B47: ₹ cr | C47: 836.63158 | D47: 970.84873 | E47: 992.47157 | F47: 1056.7231 | G47: 1043.3255 | H47: 929.36547 | I47: 1058.9966 | J47: 821.35703 | K47: 1061.7495 | L47: 1123.8513 | M47: 1181.4167 | N47: 1511.8391 | O47: 1145.183 | P47: 1447.3459 | Q47: 1470.5866 | R47: 1480.105 | S47: 1280.929 | T47: 1337.7492 | U47: 1473.5622 | V47: 965.55474 | W47: 1283.2418 | X47: 1409.2518 | Y47: 1716.3784 | Z47: 1544.0942 | AA47: 1794.2688 | AB47: 1898.0805 | AC47: 1886.4193 | AD47: 1873.2388 | AE47: 1485.5477 | AF47: 1663.9196 | AG47: 1771.1702 | AH47: 1524.8391 | AI47: 971.18 | AJ47: 615.296 | AK47: 678.863 | AL47: 959.1 | AM47: 1178.074 | AN47: 1713.536 | AO47: 1297.38 | AP47: 1464.1954 | AQ47: 1618.1 | AR47: 1659.2996 | AS47: 1777.5 | AT47: 1790.6 | AU47: 2041.9
A48: Exceptional item | B48: ₹ cr | C48: 0 | D48: 0 | E48: 0 | F48: 0 | G48: 0 | H48: 0 | I48: 0 | J48: 0 | K48: 0 | L48: 0 | M48: 0 | N48: 0 | O48: 0 | P48: 0 | Q48: 0 | R48: 0 | S48: 0 | T48: 0 | U48: 0 | V48: 0 | W48: 0 | X48: 0 | AI48: 0 | AJ48: 0 | AM48: 0 | AN48: 0 | AQ48: 0 | AR48: 0 | AS48: 272.4 | AT48: 0 | AU48: 0
A49: PBT | B49: ₹ cr | W49: 1283.2418 | X49: 1409.2518 | Y49: 1716.3784 | Z49: 1544.0942 | AA49: 1794.2688 | AB49: 1898.0805 | AC49: 1886.4193 | AD49: 1873.2388 | AE49: 1485.5477 | AF49: 1663.9196 | AG49: 1771.1702 | AH49: 1524.8391 | AI49: 971.18 | AJ49: 615.296 | AK49: 678.863 | AL49: 959.1 | AM49: 1178.074 | AN49: 1713.536 | AO49: 1297.38 | AP49: 1464.1954 | AQ49: 1618.1 | AR49: 1659.2996 | AS49: 1505.1 | AT49: 1790.6 | AU49: 2041.9
A50: Tax | B50: ₹ cr | C50: 214.19506 | D50: 202.31151 | E50: 233.00483 | F50: 180.62042 | G50: 246.79286 | H50: 309.5984 | I50: 214.09446 | J50: 231.63861 | K50: 269.85603 | L50: 284.71281 | M50: 257.03693 | N50: 280.95572 | O50: 245.74899 | P50: 391.37499 | Q50: 263.77961 | R50: 353.49041 | S50: 331.8 | T50: 226.50412 | U50: 362.898 | V50: 239.19788 | W50: 327.6 | X50: 346.198 | Y50: 426.298 | Z50: 499.798 | AA50: 428.6 | AB50: 557.198 | AC50: 508.198 | AD50: 327.998 | AE50: 338 | AF50: 364.7 | AG50: 485.9 | AH50: 399.9 | AI50: 267.6 | AJ50: 110 | AK50: 155.1 | AL50: 294.9 | AM50: 313.3 | AN50: 456 | AO50: 308.6 | AP50: 322.3 | AQ50: 489.3 | AR50: 457.6 | AS50: 386.5 | AT50: 434.19954 | AU50: 555.6
A51: PAT before NCI | B51: ₹ cr | C51: 622.43652 | D51: 768.53722 | E51: 759.46674 | F51: 876.10265 | G51: 796.53266 | H51: 619.76707 | I51: 844.90211 | J51: 589.71843 | K51: 791.84943 | L51: 839.1515 | M51: 924.37981 | N51: 1230.8424 | O51: 899.45104 | P51: 1055.8889 | Q51: 1206.807 | R51: 1126.6145 | S51: 949.12896 | T51: 1111.2451 | U51: 1110.6642 | V51: 726.35686 | W51: 955.64183 | X51: 1063.0538 | Y51: 1290.0804 | Z51: 1044.2962 | AA51: 1365.6688 | AB51: 1340.8825 | AC51: 1378.2213 | AD51: 1545.2408 | AE51: 1147.5477 | AF51: 1299.2196 | AG51: 1285.2702 | AH51: 1124.9391 | AI51: 703.58 | AJ51: 505.296 | AK51: 523.663 | AL51: 664.2 | AM51: 864.774 | AN51: 1257.536 | AO51: 988.78 | AP51: 1141.8954 | AQ51: 1128.8 | AR51: 1201.6996 | AS51: 1118.6 | AT51: 1356.4004 | AU51: 1486.3
A52: NCI / minority interest | B52: ₹ cr | C52: 0.061248338 | D52: -4.1718607 | E52: -8.2590116 | F52: -21.348558 | G52: -47.246114 | H52: 0.89062441 | I52: 10.132511 | J52: -1.7342102 | K52: 6.8196231 | L52: -3.1311891 | M52: 18.721593 | N52: -8.8301115 | O52: -1.6309827 | P52: 8.4295394 | Q52: -3.9199562 | R52: 5.9213995 | S52: 10.2 | T52: 12.736188 | U52: 35.2 | V52: 77.463812 | W52: 16.7 | X52: 1.5 | Y52: 19.7 | Z52: 37.1 | AA52: -12.5 | AB52: -2.2 | AC52: -9.7 | AD52: -39.6 | AE52: 15.9 | AF52: 13.8 | AG52: -11.3 | AH52: 7.3 | AI52: 11.1 | AJ52: 11.4 | AK52: 13.3 | AL52: 3.2 | AM52: 13.3 | AN52: 7.4 | AO52: 5.6 | AP52: -24.8 | AQ52: -11.8 | AR52: 7.2 | AS52: -3.3996265 | AT52: 2.6 | AU52: 21.2
A53: Net income attributable | B53: ₹ cr | C53: 622.49777 | D53: 764.36536 | E53: 751.20773 | F53: 854.75409 | G53: 749.28655 | H53: 620.65769 | I53: 855.03462 | J53: 587.98422 | K53: 798.66905 | L53: 836.02031 | M53: 943.1014 | N53: 1222.0123 | O53: 897.92006 | P53: 1064.2875 | Q53: 1202.887 | R53: 1132.5359 | S53: 959.32896 | T53: 1123.9453 | U53: 1145.8642 | V53: 803.92067 | W53: 972.34183 | X53: 1064.5538 | Y53: 1309.7804 | Z53: 1081.3962 | AA53: 1353.1688 | AB53: 1338.6825 | AC53: 1368.5213 | AD53: 1505.6408 | AE53: 1131.6477 | AF53: 1285.4196 | AG53: 1296.5702 | AH53: 1117.6391 | AI53: 692.48 | AJ53: 493.896 | AK53: 510.363 | AL53: 661 | AM53: 851.474 | AN53: 1250.136 | AO53: 983.18 | AP53: 1166.6954 | AQ53: 1140.6 | AR53: 1194.4996 | AS53: 1121.9996 | AT53: 1353.8004 | AU53: 1465.1
A54: Reported basic EPS | B54: ₹ / share | AQ54: 12.872807 | AR54: 13.476786 | AS54: 12.658045 | AT54: 15.271627 | AU54: 16.53
A55: Reported diluted EPS | B55: ₹ / share | AQ55: 12.858222 | AR55: 13.463072 | AS55: 12.63798 | AT55: 15.239825 | AU55: 16.5
A56: USD revenue | B56: $m | C56: 989.12301 | D56: 1011.0334 | E56: 1014.7137 | F56: 1022.5853 | G56: 1031.4658 | H56: 1072.3792 | I56: 1116.0923 | J56: 1131.1552 | K56: 1138.1446 | L56: 1179.1639 | M56: 1209.1213 | N56: 1244.3361 | O56: 1224.0604 | P56: 1218.1912 | Q56: 1260.7542 | R56: 1267.5172 | S56: 1247.1188 | T56: 1287.2167 | U56: 1352.9836 | V56: 1294.5533 | W56: 1207.4677 | X56: 1265.3794 | Y56: 1308.6505 | Z56: 1329.5656 | AA56: 1383.5987 | AB56: 1472.5784 | AC56: 1533.4751 | AD56: 1608.1356 | AE56: 1632.4504 | AF56: 1638.138 | AG56: 1668.2939 | AH56: 1667.6352 | AI56: 1600.74 | AJ56: 1555.15 | AK56: 1573.02 | AL56: 1548.19 | AM56: 1558.92 | AN56: 1588.72 | AO56: 1567.47 | AP56: 1548.76 | AQ56: 1564.411 | AR56: 1585.9178 | AS56: 1609.8645 | AT56: 1624.671 | AU56: 1660.4
A61: Annual reported balance sheet (INR crore)
A62: Metric | B62: Units | C62: FY16A | D62: FY17A | E62: FY18A | F62: FY19A | G62: FY20A | H62: FY21A | I62: FY22A | J62: FY23A | K62: FY24A | L62: FY25A | M62: FY26A
A63: PPE | B63: ₹ cr | C63: 2517.8151 | D63: 3071.7415 | E63: 2980.9579 | F63: 2622.8669 | G63: 2660.9 | H63: 2463.2 | I63: 2682.3 | J63: 2862.2 | K63: 2557.7 | L63: 2380.5 | M63: 2425.6
A64: Capital work-in-progress | B64: ₹ cr | C64: 629.40472 | D64: 372.86312 | E64: 239.91686 | F64: 276.3 | G64: 50.1 | H64: 118.3 | I64: 165.1 | J64: 83.6 | K64: 101.1 | L64: 20.6 | M64: 26.8
A65: ROU assets | B65: ₹ cr | G65: 1173 | H65: 1007.2 | I65: 937.18565 | J65: 1097.1857 | K65: 960.5 | L65: 1518.6 | M65: 1980.2
A66: Investment property | B66: ₹ cr | D66: 101.06761 | E66: 190.55728 | F66: 170.7845 | G66: 144.42723 | H66: 89.061788 | I66: 79.7 | J66: 74.8 | K66: 71.3 | L66: 34 | M66: 32.3
A67: Goodwill | B67: ₹ cr | C67: 1735.746 | D67: 2627.9102 | E67: 2772.71 | F67: 2816.308 | G67: 3387.7434 | H67: 4008.2094 | I67: 7425.8262 | J67: 7665.6965 | K67: 7510.562 | L67: 7699.3 | M67: 8456
A68: Other intangible assets | B68: ₹ cr | C68: 91.078288 | D68: 659.41414 | E68: 1678.1245 | F68: 1451.2245 | G68: 1506 | H68: 1450.8 | I68: 3658.6 | J68: 3231.6401 | K68: 2802.9 | L68: 2349.0751 | M68: 1969.9
A69: Intangible assets under development | B69: ₹ cr | H69: 0 | I69: 0 | J69: 36.1 | K69: 32.1 | L69: 0 | M69: 0
A70: Equity-method investments | B70: ₹ cr | F70: 36.1 | G70: 19.656531 | H70: 27.938734 | I70: 196.87938 | J70: 172.92985 | K70: 46.108 | L70: 53.9 | M70: 55
A71: Non-current investments | B71: ₹ cr | C71: 1324.3564 | D71: 230.82182 | E71: 1245.8267 | F71: 715.89131 | G71: 216.28728 | H71: 547.80129 | I71: 250.97357 | J71: 432.01203 | K71: 412.226 | L71: 235.4 | M71: 35.2
A72: Non-current billed receivables | B72: ₹ cr | I72: 0.9 | J72: 1.1 | K72: 0.6 | L72: 0 | M72: 0
A73: Non-current unbilled receivables | B73: ₹ cr | I73: 0 | J73: 0 | K73: 0 | L73: 0 | M73: 0
A74: Non-current loans | B74: ₹ cr | D74: 0.9072221 | E74: 5.2392788 | F74: 4.3 | G74: 4.5 | H74: 4.7 | I74: 13.6 | J74: 4.9 | K74: 10.5 | L74: 10.8 | M74: 6.9
A75: Other non-current financial assets | B75: ₹ cr | D75: 432.90512 | E75: 246.79475 | F75: 478.50045 | G75: 428.12805 | H75: 474.38597 | I75: 473.20044 | J75: 331.80044 | K75: 285.9 | L75: 537.4 | M75: 356.3
A76: Other tax assets | B76: ₹ cr | D76: 1313.5218 | E76: 1777.4957 | F76: 2139.7 | G76: 2415.2 | H76: 2028.8 | I76: 2513.7 | J76: 3053.7 | K76: 2999.2 | L76: 3055.7 | M76: 3042.2
A77: Deferred tax assets | B77: ₹ cr | C77: 557.48677 | D77: 267.43874 | E77: 576.55022 | F77: 609.1 | G77: 844.3 | H77: 913.3 | I77: 819.1 | J77: 1296.5 | K77: 1439.6 | L77: 1857.3 | M77: 2186.4
A78: Other non-current assets | B78: ₹ cr | C78: 29.395768 | D78: 645.85063 | E78: 602.23102 | F78: 553.7 | G78: 1327.3 | H78: 1286.5 | I78: 1197.9 | J78: 1376.5 | K78: 768 | L78: 1062.7 | M78: 1221.9
A79: Total non-current assets | B79: ₹ cr | C79: 8561.8587 | D79: 9739.997 | E79: 12330.249 | F79: 11881.076 | G79: 14181.242 | H79: 14422.697 | I79: 20414.965 | J79: 21720.565 | K79: 19998.298 | L79: 20815.275 | M79: 21794.7
A80: Inventories | B80: ₹ cr | C80: 41.439603 | D80: 61.058109 | E80: 65.918365 | F80: 75.2 | G80: 35.8 | H80: 24.2 | I80: 40.5 | J80: 23.6 | K80: 37.5 | L80: 39.4 | M80: 104.2
A81: Current investments | B81: ₹ cr | C81: 1168.9612 | D81: 2164.696 | E81: 3444.9413 | F81: 6589.9 | G81: 5612.3 | H81: 9661.9 | I81: 4435.9 | J81: 2783.2 | K81: 2779.4 | L81: 2892.8 | M81: 3335.5
A82: Billed receivables | B82: ₹ cr | I82: 7467.5552 | J82: 8142.4021 | K82: 7125.585 | L82: 6548.6 | M82: 7536.9
A83: Unbilled receivables | B83: ₹ cr | I83: 4465.8 | J83: 4739.2 | K83: 4275.5 | L83: 4998.4 | M83: 5820.8
A84: Cash and cash equivalents | B84: ₹ cr | C84: 4013.8061 | D84: 2001.2742 | E84: 1966.0827 | F84: 2042.7 | G84: 3016.7 | H84: 2690.4 | I84: 3788.9 | J84: 4056.3 | K84: 4347.1 | L84: 4318.5 | M84: 5046.1
A85: Other bank balances | B85: ₹ cr | D85: 1217.3489 | E85: 1078.2243 | F85: 316 | G85: 131.6 | H85: 144.8 | I85: 185.6 | J85: 198.4 | K85: 388.4 | L85: 223.7 | M85: 59.3
A86: Current loans | B86: ₹ cr | D86: 428.6 | E86: 150 | J86: 0 | K86: 0 | L86: 0 | M86: 0
A87: Other current financial assets | B87: ₹ cr | D87: 2932.1901 | E87: 2941.6708 | F87: 2906.391 | G87: 3735.5 | H87: 3328.1 | I87: 675 | J87: 499.9 | K87: 431.9 | L87: 412.3 | M87: 447.6
A88: Other current assets | B88: ₹ cr | C88: 2241.9937 | D88: 2157.1144 | E88: 1962.2996 | F88: 2677 | G88: 3063.2 | H88: 2933.1 | I88: 3396.4 | J88: 3989.7 | K88: 4039.9 | L88: 4245.5 | M88: 5224.3
A89: Assets held for sale | B89: ₹ cr | D89: 26.5 | E89: 0 | F89: 0 | H89: 0 | J89: 0 | K89: 0 | L89: 0 | M89: 0
A90: Total current assets | B90: ₹ cr | C90: 14945.134 | D90: 16326.5 | E90: 18106.996 | F90: 21565.766 | G90: 23172.268 | H90: 25255.317 | I90: 24455.655 | J90: 24432.702 | K90: 23425.285 | L90: 23679.2 | M90: 27574.7
A91: Total assets | B91: ₹ cr | C91: 23507.013 | D91: 26066.5 | E91: 30437.182 | F91: 33446.851 | G91: 37353.51 | H91: 39678.014 | I91: 44870.72 | J91: 46153.267 | K91: 43423.583 | L91: 44494.475 | M91: 49369.4
A92: Share capital | B92: ₹ cr | C92: 483.90502 | D92: 438.79965 | E92: 441.68731 | F92: 443.73457 | G92: 435.87387 | H92: 436.98959 | I92: 438.8064 | J92: 440 | K92: 441.302 | L92: 442.4 | M92: 442.8
A93: Other equity | B93: ₹ cr | C93: 13882.449 | D93: 15998.419 | E93: 18401.131 | F93: 19840.7 | G93: 21377.2 | H93: 24428 | I93: 26446.9 | J93: 27484.5 | K93: 26228.1 | L93: 26919.1 | M93: 29172.6
A94: Equity attributable to owners | B94: ₹ cr | C94: 14366.349 | D94: 16437.218 | E94: 18842.819 | F94: 20284.435 | G94: 21813.074 | H94: 24864.99 | I94: 26885.706 | J94: 27924.5 | K94: 26669.402 | L94: 27361.5 | M94: 29615.4
A95: NCI | B95: ₹ cr | C95: 201.95269 | D95: 464.12046 | E95: 509.1 | F95: 477.7 | G95: 393.3 | H95: 379.5 | I95: 495.4 | J95: 470.2 | K95: 477.4 | L95: 430.2 | M95: 461.6
A96: Total equity | B96: ₹ cr | C96: 14569.659 | D96: 16901.339 | E96: 19351.919 | F96: 20762.135 | G96: 22206.374 | H96: 25244.49 | I96: 27381.106 | J96: 28394.7 | K96: 27146.802 | L96: 27791.7 | M96: 30077
A97: Long-term borrowings | B97: ₹ cr | C97: 196.69738 | D97: 385.25875 | E97: 771.09718 | F97: 208.6 | G97: 178.7 | H97: 165.8 | I97: 142 | J97: 128.8 | K97: 102.5 | L97: 0 | M97: 0
A98: Non-current lease liabilities | B98: ₹ cr | G98: 853.9 | H98: 807.7 | I98: 720 | J98: 790.3 | K98: 670.9 | L98: 1147.2 | M98: 1588.8
A99: Non-current trade payables | B99: ₹ cr | I99: 0 | J99: 0 | K99: 0 | L99: 0 | M99: 0
A100: Other non-current financial liabilities | B100: ₹ cr | D100: 496.49814 | E100: 572.91769 | F100: 300.9 | G100: 1232.3 | H100: 922.5 | I100: 1478 | J100: 1008.3 | K100: 54.5 | L100: 16 | M100: 54.8
A101: Non-current provisions | B101: ₹ cr | C101: 531.05075 | D101: 620.08084 | E101: 555.13776 | F101: 580.1 | G101: 669.1 | H101: 781.03016 | I101: 881.1 | J101: 928.8 | K101: 1302.1 | L101: 1402.7 | M101: 1715.9
A102: Deferred tax liabilities | B102: ₹ cr | D102: 9.5296524 | E102: 5.8087075 | F102: 1.1 | G102: 35.6 | H102: 76.1 | I102: 455.2 | J102: 326.1 | K102: 274.5 | L102: 227.9 | M102: 201.7
A103: Other non-current liabilities | B103: ₹ cr | C103: 23.133231 | D103: 30.507533 | E103: 33.334566 | F103: 32.5 | G103: 21.4 | H103: 172.46984 | I103: 78.1 | J103: 24.9 | K103: 25.3 | L103: 4.6 | M103: 3.3
A104: Total non-current liabilities | B104: ₹ cr | C104: 750.88136 | D104: 1541.8749 | E104: 1938.2129 | F104: 1123.2 | G104: 2991 | H104: 2925.6 | I104: 3754.4 | J104: 3207.2 | K104: 2429.8 | L104: 2798.4 | M104: 3564.5
A105: Short-term borrowings | B105: ₹ cr | C105: 805.5042 | D105: 834.17692 | E105: 954.8559 | F105: 1196.1 | G105: 2249.5 | H105: 1496 | I105: 1439.7361 | J105: 1449.4 | K105: 1428.5 | L105: 471.4 | M105: 69.6
A106: Current lease liabilities | B106: ₹ cr | G106: 345.9 | H106: 400.3 | I106: 316.7 | J106: 371.7 | K106: 334.8 | L106: 406.6 | M106: 527.8
A107: Trade payables | B107: ₹ cr | C107: 2275.6957 | D107: 2311.6995 | E107: 2036.8357 | F107: 2489.3 | G107: 3256.6 | H107: 2785 | I107: 4094.7 | J107: 4384.6 | K107: 3785.3 | L107: 4410.8 | M107: 5040
A108: Other current financial liabilities | B108: ₹ cr | D108: 422.96501 | E108: 1876.8924 | F108: 3472.6 | G108: 1789.8 | H108: 2091 | I108: 3024.4 | J108: 2961.7 | K108: 2394.3 | L108: 2284.5 | M108: 2992.9
...

Sheet Raw Operating
A1: Raw Reported Operating Metrics
A2: Reported annual / Q4 snapshot inputs from the official Tech Mahindra data sheet
A5: Metric | B5: Units | C5: FY16A | D5: FY17A | E5: FY18A | F5: FY19A | G5: FY20A | H5: FY21A | I5: FY22A | J5: FY23A | K5: FY24A | L5: FY25A | M5: FY26A | N5: FY27E | O5: FY28E | P5: FY29E | Q5: FY30E
A6: USD revenue | B6: $m | C6: 4037.4553 | D6: 4351.0924 | E6: 4770.7659 | F6: 4970.5229 | G6: 5181.87 | H6: 5111.06 | I6: 5997.79 | J6: 6606.52 | K6: 6277.11 | L6: 6263.9885 | M6: 6384.8643
A7: Total headcount | B7: # | C7: 105432 | D7: 117693 | E7: 112807 | F7: 121082 | G7: 125236 | H7: 121054 | I7: 151173 | J7: 152400 | K7: 145455 | L7: 148731 | M7: 147623
A8: Software professionals | B8: # | C8: 72125 | D8: 82403 | E8: 72437 | F8: 71477 | G8: 71515 | H8: 68427 | I8: 85830 | J8: 83789 | K8: 80925 | L8: 80609 | M8: 75377
A9: BPS professionals | B9: # | C9: 27254 | D9: 28414 | E9: 34190 | F9: 43081 | G9: 46816 | H9: 46125 | I9: 57315 | J9: 60102 | K9: 55492 | L9: 59636 | M9: 64330
A10: Sales & support | B10: # | C10: 6053 | D10: 6876 | E10: 6180 | F10: 6524 | G10: 6905 | H10: 6502 | I10: 8028 | J10: 8509 | K10: 9038 | L10: 8486 | M10: 7916
A11: LTM attrition | B11: % | C11: 0.21073297 | D11: 0.16516347 | E11: 0.18084726 | F11: 0.208 | G11: 0.191 | H11: 0.133 | I11: 0.235 | J11: 0.148 | K11: 0.1 | L11: 0.118 | M11: 0.121
A12: IT utilization | B12: % | C12: 0.77485958 | D12: 0.76865319 | E12: 0.83822415 | F12: 0.818 | G12: 0.83160803 | H12: 0.874 | I12: 0.831 | J12: 0.86481216 | K12: 0.8642 | L12: 0.8635 | M12: 0.8612
A13: IT utilization excl. trainees | B13: % | C13: 0.80159829 | D13: 0.80615885 | E13: 0.83973144 | F13: 0.819 | G13: 0.83514897 | H13: 0.874 | I13: 0.842 | J13: 0.86481216 | K13: 0.8641 | L13: 0.8627
A14: Active clients | B14: # | C14: 807 | D14: 843 | E14: 913 | F14: 938 | G14: 973 | H14: 1007 | I14: 1224 | J14: 1297 | K14: 1172 | L14: 1162
A15: Repeat business | B15: % | C15: 0.96275 | D15: 0.93545351 | E15: 0.88397966 | F15: 0.88740007 | G15: 0.86129042 | H15: 0.92220154 | I15: 0.87396636 | J15: 0.91757184 | K15: 0.94038
A16: $1m+ clients | B16: # | C16: 319 | D16: 354 | E16: 392 | F16: 425 | G16: 446 | H16: 451 | I16: 524 | J16: 582 | K16: 553 | L16: 540 | M16: 512
A17: $5m+ clients | B17: # | C17: 112 | D17: 134 | E17: 156 | F17: 156 | G17: 160 | H17: 169 | I17: 174 | J17: 186 | K17: 190 | L17: 195 | M17: 194
A18: $10m+ clients | B18: # | C18: 63 | D18: 71 | E18: 85 | F18: 83 | G18: 85 | H18: 85 | I18: 97 | J18: 112 | K18: 114 | L18: 106 | M18: 112
A19: $20m+ clients | B19: # | C19: 40 | D19: 36 | E19: 44 | F19: 50 | G19: 49 | H19: 50 | I19: 54 | J19: 65 | K19: 63 | L19: 59 | M19: 66
A20: $50m+ clients | B20: # | C20: 14 | D20: 14 | E20: 16 | F20: 20 | G20: 22 | H20: 21 | I20: 23 | J20: 24 | K20: 23 | L20: 25 | M20: 29
A21: Top 5 client concentration | B21: % | C21: 0.30164275 | D21: 0.2790042 | E21: 0.24243633 | F21: 0.22658313 | G21: 0.216888 | H21: 0.2183 | I21: 0.2232 | J21: 0.1846 | K21: 0.1648 | L21: 0.15229953 | M21: 0.15314066
A22: Top 10 client concentration | B22: % | C22: 0.41506312 | D22: 0.38937827 | E22: 0.34286238 | F22: 0.32201796 | G22: 0.3106 | H22: 0.3076 | I22: 0.313 | J22: 0.2789 | K22: 0.2661 | L22: 0.24663735 | M22: 0.24531347
A23: Top 20 client concentration | B23: % | C23: 0.54195308 | D23: 0.5090488 | E23: 0.46295797 | F23: 0.45218498 | G23: 0.432 | H23: 0.4298 | I23: 0.427 | J23: 0.4025 | K23: 0.39056 | L23: 0.38302176 | M23: 0.37931353
A24: TCV | B24: $m | F24: 1666.9 | G24: 3712 | H24: 2209.69 | I24: 3280 | J24: 2905 | K24: 1880.185 | L24: 2680 | M24: 3793.62
A25: DSO incl. unbilled | B25: days | D25: 95 | E25: 102 | F25: 102 | G25: 112 | H25: 92 | I25: 97 | J25: 95.555616 | K25: 92 | L25: 88.03578 | M25: 88.606669
A26: Average INR / USD | B26: ₹ / $ | C26: 65.621115 | D26: 66.973621 | E26: 64.503021 | F26: 69.896331 | G26: 71.147441 | H26: 74.06503 | I26: 74.437358 | J26: 80.662992 | K26: 82.833567 | L26: 84.591951 | M26: 88.984506
A27: Closing INR / USD | B27: ₹ / $ | C27: 66.26 | D27: 64.845 | E27: 65.17 | F27: 69.155 | G27: 75.62 | H27: 73.11 | I27: 75.7925 | J27: 82.17 | K27: 83.41 | L27: 85.475 | M27: 94.835
A28: Free cash flow | B28: $m | C28: 329.32269 | D28: 396.80794 | E28: 428.06914 | F28: 534.50917 | G28: 522.6 | H28: 965.42 | I28: 594.72 | J28: 497.35 | K28: 676.34 | L28: 612.96004 | M28: 616.24421
A29: FCF / PAT | B29: % | C29: 0.72376517 | D29: 0.94601013 | E29: 0.727892 | F29: 0.86966234 | G29: 0.922 | H29: 1.61495 | I29: 0.7967 | J29: 0.8364 | K29: 2.3791 | L29: 1.220272 | M29: 1.1466334
A30: Onsite revenue mix | B30: % | C30: 0.62148793 | D30: 0.63763805 | E30: 0.65070223 | F30: 0.65443059 | G30: 0.6527 | H30: 0.6316 | I30: 0.6163
A31: Offshore revenue mix | B31: % | C31: 0.37851207 | D31: 0.36236195 | E31: 0.34929777 | F31: 0.34556941 | G31: 0.347 | H31: 0.3683 | I31: 0.3836
A32: Onsite IT headcount mix | B32: % | I32: 0.27594087 | J32: 0.2729645 | K32: 0.2619 | L32: 0.23275621 | M32: 0.21875244
A33: Offshore IT headcount mix | B33: % | I33: 0.72405913 | J33: 0.7270355 | K33: 0.7381 | L33: 0.76724379 | M33: 0.78124756
A34: USD revenue mix | B34: % | C34: 0.51051503 | D34: 0.48348981 | E34: 0.48115697 | F34: 0.48217646 | G34: 0.49764 | H34: 0.5121 | I34: 0.5139 | J34: 0.5163 | K34: 0.5325 | L34: 0.52345602 | M34: 0.51447327
A35: GBP revenue mix | B35: % | C35: 0.12022138 | D35: 0.11441514 | E35: 0.11881195 | F35: 0.11551673 | G35: 0.115 | H35: 0.1125 | I35: 0.1085 | J35: 0.101 | K35: 0.0938 | L35: 0.094952509 | M35: 0.093809012
A36: EUR revenue mix | B36: % | C36: 0.1152505 | D36: 0.11689895 | E36: 0.11433922 | F36: 0.10990382 | G36: 0.0941 | H36: 0.0914 | I36: 0.1051 | J36: 0.1134 | K36: 0.1124 | L36: 0.11779954 | M36: 0.1358299
A37: AUD revenue mix | B37: % | C37: 0.046949801 | D37: 0.04584849 | E37: 0.048163994 | F37: 0.049111112 | G37: 0.0463 | H37: 0.0459 | I37: 0.0432 | J37: 0.0387 | K37: 0.0375 | L37: 0.047702174 | M37: 0.05449323
A38: Other currency revenue mix | B38: % | C38: 0.20706329 | D38: 0.23934762 | E38: 0.2375767 | F38: 0.24810053 | G38: 0.247 | H38: 0.2381 | I38: 0.2294 | J38: 0.2306 | K38: 0.2238 | L38: 0.21595326 | M38: 0.20139459
A39: Americas mix | B39: % | C39: 0.47788163 | D39: 0.4721035 | E39: 0.46580473 | F39: 0.47247123 | G39: 0.4805 | H39: 0.474 | I39: 0.4791 | J39: 0.4993 | K39: 0.5183 | L39: 0.50699748 | M39: 0.49811039
A40: Europe mix | B40: % | C40: 0.29038554 | D40: 0.29253597 | E40: 0.29830439 | F40: 0.29272929 | G40: 0.269 | H40: 0.2597 | I40: 0.2624 | J40: 0.2492 | K40: 0.2403 | L40: 0.24110791 | M40: 0.25757022
A41: Rest of world mix | B41: % | C41: 0.23173283 | D41: 0.23536053 | E41: 0.23589089 | F41: 0.23479947 | G41: 0.2501 | H41: 0.2657 | I41: 0.258 | J41: 0.2514 | K41: 0.2414 | L41: 0.2519946 | M41: 0.24430862
A42: Legacy: Communications | B42: % | C42: 0.51958341 | D42: 0.47774846 | E42: 0.43273304 | F42: 0.4122149 | G42: 0.41609801 | H42: 0.39664372
A43: Legacy: Manufacturing | B43: % | C43: 0.17004687 | D43: 0.18730729 | E43: 0.19192741 | F43: 0.2023175 | G43: 0.18099944 | H43: 0.16379366
A44: Legacy: Technology, Media & Entertainment | B44: % | C44: 0.074347679 | D44: 0.067214337 | E44: 0.064500668 | F44: 0.072454242 | G44: 0.076919335 | H44: 0.093544648
A45: Legacy: BFSI | B45: % | C45: 0.1013418 | D45: 0.1264392 | E45: 0.13675168 | F45: 0.13356922 | G45: 0.13558064 | H45: 0.16153576
A46: Legacy: Retail, Transport & Logistics | B46: % | C46: 0.06370376 | D46: 0.068851851 | E46: 0.068326503 | F46: 0.064358118 | G46: 0.069305782 | H46: 0.075729404
A47: Legacy: Others | B47: % | C47: 0.070976471 | D47: 0.072438872 | E47: 0.1057607 | F47: 0.11508602 | G47: 0.12104679 | H47: 0.10875281
A48: FY22–23 recast: CME | B48: % | H48: 0.40467177 | I48: 0.40401735 | J48: 0.39999784 | K48: 0.36865309
A49: FY22–23 recast: Manufacturing | B49: % | H49: 0.16496366 | I49: 0.15809026 | J49: 0.15712794 | K49: 0.17740558
A50: FY22–23 recast: Technology | B50: % | H50: 0.085207268 | I50: 0.088660859 | J50: 0.1008662 | K50: 0.10720559
A51: FY22–23 recast: BFSI | B51: % | H51: 0.16123687 | I51: 0.16387117 | J51: 0.16189809 | K51: 0.1600497
A52: FY22–23 recast: Retail, Transport & Logistics | B52: % | H52: 0.077650755 | I52: 0.078880939 | J52: 0.080159355 | K52: 0.081408027
A53: FY22–23 recast: Others | B53: % | H53: 0.10626968 | I53: 0.10622943 | J53: 0.099950573 | K53: 0.10527802
A54: Current: Communications | B54: % | K54: 0.3471 | L54: 0.3305056 | M54: 0.33264816
A55: Current: Manufacturing | B55: % | K55: 0.1756 | L55: 0.17318661 | M55: 0.17999103
A56: Current: Hi-Tech & Media | B56: % | K56: 0.1392 | L56: 0.13896126 | M56: 0.13261109
A57: Current: BFSI | B57: % | K57: 0.1536 | L57: 0.16053102 | M57: 0.16329254
A58: Current: Retail, Transport & Logistics | B58: % | K58: 0.0757 | L58: 0.079205535 | M58: 0.083342565
A59: Current: Healthcare & Life Sciences | B59: % | K59: 0.0723 | L59: 0.075093682 | M59: 0.073250748
A60: Current: Others | B60: % | K60: 0.0366 | L60: 0.042516301 | M60: 0.034852899

Sheet Quarterly P&L
A1: Quarterly Profit & Loss
A2: Reported quarterly P&L through Q1 FY27A; growth, margins and profit subtotals are formula-driven
A5: Metric | B5: Units | C5: Q1 FY16A | D5: Q2 FY16A | E5: Q3 FY16A | F5: Q4 FY16A | G5: Q1 FY17A | H5: Q2 FY17A | I5: Q3 FY17A | J5: Q4 FY17A | K5: Q1 FY18A | L5: Q2 FY18A | M5: Q3 FY18A | N5: Q4 FY18A | O5: Q1 FY19A | P5: Q2 FY19A | Q5: Q3 FY19A | R5: Q4 FY19A | S5: Q1 FY20A | T5: Q2 FY20A | U5: Q3 FY20A | V5: Q4 FY20A | W5: Q1 FY21A | X5: Q2 FY21A | Y5: Q3 FY21A | Z5: Q4 FY21A | AA5: Q1 FY22A | AB5: Q2 FY22A | AC5: Q3 FY22A | AD5: Q4 FY22A | AE5: Q1 FY23A | AF5: Q2 FY23A | AG5: Q3 FY23A | AH5: Q4 FY23A | AI5: Q1 FY24A | AJ5: Q2 FY24A | AK5: Q3 FY24A | AL5: Q4 FY24A | AM5: Q1 FY25A | AN5: Q2 FY25A | AO5: Q3 FY25A | AP5: Q4 FY25A | AQ5: Q1 FY26A | AR5: Q2 FY26A | AS5: Q3 FY26A | AT5: Q4 FY26A | AU5: Q1 FY27A
A6: Revenue | B6: ₹ cr | C6: ='Raw Financials'!C34 -> 6293.8237 | D6: ='Raw Financials'!D34 -> 6615.535 | E6: ='Raw Financials'!E34 -> 6701.1416 | F6: ='Raw Financials'!F34 -> 6883.832 | G6: ='Raw Financials'!G34 -> 6920.9344 | H6: ='Raw Financials'!H34 -> 7167.4101 | I6: ='Raw Financials'!I34 -> 7557.5027 | J6: ='Raw Financials'!J34 -> 7494.9943 | ... AU6: ='Raw Financials'!AU34 -> 15711.9
A7: QoQ growth | B7: % | D7: =IFERROR(D6/C6-1,"") -> 0.051115405 | E7: =IFERROR(E6/D6-1,"") -> 0.012940235 | F7: =IFERROR(F6/E6-1,"") -> 0.027262577 | G7: =IFERROR(G6/F6-1,"") -> 0.0053897909 | H7: =IFERROR(H6/G6-1,"") -> 0.035613068 | I7: =IFERROR(I6/H6-1,"") -> 0.054425875 | J7: =IFERROR(J6/I6-1,"") -> -0.0082710289 | K7: =IFERROR(K6/J6-1,"") -> -0.021199856 | ... AU7: =IFERROR(AU6/AT6-1,"") -> 0.04217271
A8: YoY growth | B8: % | G8: =IFERROR(G6/C6-1,"") -> 0.099639068 | H8: =IFERROR(H6/D6-1,"") -> 0.083421082 | I8: =IFERROR(I6/E6-1,"") -> 0.12779331 | J8: =IFERROR(J6/F6-1,"") -> 0.08878229 | K8: =IFERROR(K6/G6-1,"") -> 0.059987152 | L8: =IFERROR(L6/H6-1,"") -> 0.061238516 | M8: =IFERROR(M6/I6-1,"") -> 0.028905524 | N8: =IFERROR(N6/J6-1,"") -> 0.074649479 | ... AU8: =IFERROR(AU6/AQ6-1,"") -> 0.17681557
A9: Cost of services | B9: ₹ cr | C9: ='Raw Financials'!C35 -> 4444.0768 | D9: ='Raw Financials'!D35 -> 4499.8859 | E9: ='Raw Financials'!E35 -> 4606.9072 | F9: ='Raw Financials'!F35 -> 4778.1677 | G9: ='Raw Financials'!G35 -> 4880.6965 | H9: ='Raw Financials'!H35 -> 4971.6661 | I9: ='Raw Financials'!I35 -> 5235.2369 | J9: ='Raw Financials'!J35 -> 5478.4599 | ... AU9: ='Raw Financials'!AU35 -> 10925.9
A10: Gross profit | B10: ₹ cr | C10: =C6-C9 -> 1849.7469 | D10: =D6-D9 -> 2115.6491 | E10: =E6-E9 -> 2094.2343 | F10: =F6-F9 -> 2105.6642 | G10: =G6-G9 -> 2040.2379 | H10: =H6-H9 -> 2195.744 | I10: =I6-I9 -> 2322.2657 | J10: =J6-J9 -> 2016.5345 | ... AU10: =AU6-AU9 -> 4786
A11: Gross margin | B11: % | C11: =IFERROR(C10/C6,"") -> 0.29389875 | D11: =IFERROR(D10/D6,"") -> 0.31980015 | E11: =IFERROR(E10/E6,"") -> 0.31251904 | F11: =IFERROR(F10/F6,"") -> 0.30588548 | G11: =IFERROR(G10/G6,"") -> 0.29479227 | H11: =IFERROR(H10/H6,"") -> 0.30635111 | I11: =IFERROR(I10/I6,"") -> 0.30727951 | J11: =IFERROR(J10/J6,"") -> 0.26905083 | ... AU11: =IFERROR(AU10/AU6,"") -> 0.30460988
A12: SG&A | B12: ₹ cr | C12: ='Raw Financials'!C37 -> 944.75481 | D12: ='Raw Financials'!D37 -> 1028.8609 | E12: ='Raw Financials'!E37 -> 966.2309 | F12: ='Raw Financials'!F37 -> 954.75776 | G12: ='Raw Financials'!G37 -> 1011.1581 | H12: ='Raw Financials'!H37 -> 1125.6222 | I12: ='Raw Financials'!I37 -> 1135.7654 | J12: ='Raw Financials'!J37 -> 1117.8017 | ... AU12: ='Raw Financials'!AU37 -> 2043.5
A13: EBITDA | B13: ₹ cr | C13: =C10-C12 -> 904.99209 | D13: =D10-D12 -> 1086.7882 | E13: =E10-E12 -> 1128.0034 | F13: =F10-F12 -> 1150.9065 | G13: =G10-G12 -> 1029.0799 | H13: =H10-H12 -> 1070.1218 | I13: =I10-I12 -> 1186.5003 | J13: =J10-J12 -> 898.73282 | ... AU13: =AU10-AU12 -> 2742.5
A14: EBITDA margin | B14: % | C14: =IFERROR(C13/C6,"") -> 0.14379051 | D14: =IFERROR(D13/D6,"") -> 0.1642782 | E14: =IFERROR(E13/E6,"") -> 0.16833004 | F14: =IFERROR(F13/F6,"") -> 0.1671898 | G14: =IFERROR(G13/G6,"") -> 0.14869088 | H14: =IFERROR(H13/H6,"") -> 0.14930383 | I14: =IFERROR(I13/I6,"") -> 0.15699635 | J14: =IFERROR(J13/J6,"") -> 0.11991107 | ... AU14: =IFERROR(AU13/AU6,"") -> 0.17454923
A15: D&A | B15: ₹ cr | C15: ='Raw Financials'!C39 -> 172.4159 | D15: ='Raw Financials'!D39 -> 196.53226 | E15: ='Raw Financials'!E39 -> 172.65135 | F15: ='Raw Financials'!F39 -> 217.3235 | G15: ='Raw Financials'!G39 -> 201.87768 | H15: ='Raw Financials'!H39 -> 244.74799 | I15: ='Raw Financials'!I39 -> 247.9649 | J15: ='Raw Financials'!J39 -> 283.46462 | ... AU15: ='Raw Financials'!AU39 -> 478.6
A16: EBIT | B16: ₹ cr | C16: =C13-C15 -> 732.57618 | D16: =D13-D15 -> 890.25595 | E16: =E13-E15 -> 955.35209 | F16: =F13-F15 -> 933.58299 | G16: =G13-G15 -> 827.20218 | H16: =H13-H15 -> 825.37382 | I16: =I13-I15 -> 938.53544 | J16: =J13-J15 -> 615.2682 | ... AU16: =AU13-AU15 -> 2263.9
A17: EBIT margin | B17: % | C17: =IFERROR(C16/C6,"") -> 0.11639605 | D17: =IFERROR(D16/D6,"") -> 0.13457051 | E17: =IFERROR(E16/E6,"") -> 0.14256557 | F17: =IFERROR(F16/F6,"") -> 0.13561967 | G17: =IFERROR(G16/G6,"") -> 0.11952175 | H17: =IFERROR(H16/H6,"") -> 0.11515649 | I17: =IFERROR(I16/I6,"") -> 0.12418592 | J17: =IFERROR(J16/J6,"") -> 0.082090549 | ... AU17: =IFERROR(AU16/AU6,"") -> 0.14408824
A18: Impairment | B18: ₹ cr | C18: ='Raw Financials'!C41 -> 0 | D18: ='Raw Financials'!D41 -> 0 | E18: ='Raw Financials'!E41 -> 0 | F18: ='Raw Financials'!F41 -> 0 | G18: ='Raw Financials'!G41 -> 0 | H18: ='Raw Financials'!H41 -> 0 | I18: ='Raw Financials'!I41 -> 0 | J18: ='Raw Financials'!J41 -> 0 | ... AU18: ='Raw Financials'!AU41 -> 0
A19: FX gain / (loss) | B19: ₹ cr | C19: ='Raw Financials'!C43 -> 79.854662 | D19: ='Raw Financials'!D43 -> -20.448292 | E19: ='Raw Financials'!E43 -> -13.136941 | F19: ='Raw Financials'!F43 -> 52.342432 | G19: ='Raw Financials'!G43 -> 47.890939 | H19: ='Raw Financials'!H43 -> 87.622259 | I19: ='Raw Financials'!I43 -> 90.419583 | J19: ='Raw Financials'!J43 -> 161.6545 | ... AU19: ='Raw Financials'!AU43 -> -214
A20: Interest, dividend & miscellaneous income | B20: ₹ cr | C20: ='Raw Financials'!C44 -> 44.591127 | D20: ='Raw Financials'!D44 -> 118.20912 | E20: ='Raw Financials'!E44 -> 74.99402 | F20: ='Raw Financials'!F44 -> 102.97183 | G20: ='Raw Financials'!G44 -> 197.90552 | H20: ='Raw Financials'!H44 -> 51.097014 | I20: ='Raw Financials'!I44 -> 64.776663 | J20: ='Raw Financials'!J44 -> 76.192422 | ... AU20: ='Raw Financials'!AU44 -> 107.6
A21: Interest expense | B21: ₹ cr | C21: ='Raw Financials'!C45 -> 21.463855 | D21: ='Raw Financials'!D45 -> 17.492207 | E21: ='Raw Financials'!E45 -> 24.612005 | F21: ='Raw Financials'!F45 -> 33.449491 | G21: ='Raw Financials'!G45 -> 27.405197 | H21: ='Raw Financials'!H45 -> 34.510163 | I21: ='Raw Financials'!I45 -> 34.887159 | J21: ='Raw Financials'!J45 -> 31.789909 | ... AU21: ='Raw Financials'!AU45 -> 111.3
A22: Share of associate | B22: ₹ cr | C22: ='Raw Financials'!C46 -> 1.0734657 | D22: ='Raw Financials'!D46 -> 0.32416479 | E22: ='Raw Financials'!E46 -> -0.12559858 | F22: ='Raw Financials'!F46 -> 1.2753029 | G22: ='Raw Financials'!G46 -> -2.2679132 | H22: ='Raw Financials'!H46 -> -0.2174587 | I22: ='Raw Financials'!I46 -> 0.1520472 | J22: ='Raw Financials'!J46 -> 0.0018203 | ... AU22: ='Raw Financials'!AU46 -> -4.3
A23: PBT before exceptional | B23: ₹ cr | C23: =SUM(C16,-C18,C19:C20,-C21,C22) -> 836.63158 | D23: =SUM(D16,-D18,D19:D20,-D21,D22) -> 970.84873 | E23: =SUM(E16,-E18,E19:E20,-E21,E22) -> 992.47157 | F23: =SUM(F16,-F18,F19:F20,-F21,F22) -> 1056.7231 | G23: =SUM(G16,-G18,G19:G20,-G21,G22) -> 1043.3255 | H23: =SUM(H16,-H18,H19:H20,-H21,H22) -> 929.36547 | I23: =SUM(I16,-I18,I19:I20,-I21,I22) -> 1058.9966 | J23: =SUM(J16,-J18,J19:J20,-J21,J22) -> 821.32703 | ... AU23: =SUM(AU16,-AU18,AU19:AU20,-AU21,AU22) -> 2041.9
A24: Exceptional item | B24: ₹ cr | C24: ='Raw Financials'!C48 -> 0 | D24: ='Raw Financials'!D48 -> 0 | E24: ='Raw Financials'!E48 -> 0 | F24: ='Raw Financials'!F48 -> 0 | G24: ='Raw Financials'!G48 -> 0 | H24: ='Raw Financials'!H48 -> 0 | I24: ='Raw Financials'!I48 -> 0 | J24: ='Raw Financials'!J48 -> 0 | ... AU24: ='Raw Financials'!AU48 -> 0
A25: PBT | B25: ₹ cr | C25: =C23-C24 -> 836.63158 | D25: =D23-D24 -> 970.84873 | E25: =E23-E24 -> 992.47157 | F25: =F23-F24 -> 1056.7231 | G25: =G23-G24 -> 1043.3255 | H25: =H23-H24 -> 929.36547 | I25: =I23-I24 -> 1058.9966 | J25: =J23-J24 -> 821.32703 | ... AU25: =AU23-AU24 -> 2041.9
A26: Tax | B26: ₹ cr | C26: ='Raw Financials'!C50 -> 214.19506 | D26: ='Raw Financials'!D50 -> 202.31151 | E26: ='Raw Financials'!E50 -> 233.00483 | F26: ='Raw Financials'!F50 -> 180.62042 | G26: ='Raw Financials'!G50 -> 246.79286 | H26: ='Raw Financials'!H50 -> 309.5984 | I26: ='Raw Financials'!I50 -> 214.09446 | J26: ='Raw Financials'!J50 -> 231.63861 | ... AU26: ='Raw Financials'!AU50 -> 555.6
A27: PAT before NCI | B27: ₹ cr | C27: =C25-C26 -> 622.43652 | D27: =D25-D26 -> 768.53722 | E27: =E25-E26 -> 759.46674 | F27: =F25-F26 -> 876.10265 | G27: =G25-G26 -> 796.53266 | H27: =H25-H26 -> 619.76707 | I27: =I25-I26 -> 844.90211 | J27: =J25-J26 -> 589.68843 | ... AU27: =AU25-AU26 -> 1486.3
A28: NCI / minority interest | B28: ₹ cr | C28: ='Raw Financials'!C52 -> 0.061248338 | D28: ='Raw Financials'!D52 -> -4.1718607 | E28: ='Raw Financials'!E52 -> -8.2590116 | F28: ='Raw Financials'!F52 -> -21.348558 | G28: ='Raw Financials'!G52 -> -47.246114 | H28: ='Raw Financials'!H52 -> 0.89062441 | I28: ='Raw Financials'!I52 -> 10.132511 | J28: ='Raw Financials'!J52 -> -1.7342102 | ... AU28: ='Raw Financials'!AU52 -> 21.2
A29: Net income attributable | B29: ₹ cr | C29: =C27+C28 -> 622.49777 | D29: =D27+D28 -> 764.36536 | E29: =E27+E28 -> 751.20773 | F29: =F27+F28 -> 854.75409 | G29: =G27+G28 -> 749.28655 | H29: =H27+H28 -> 620.65769 | I29: =I27+I28 -> 855.03462 | J29: =J27+J28 -> 587.95422 | ... AD29: =AD27+AD28 -> 1505.6408 | AE29: =AE27-AE28 -> 1131.6477 | AF29: =AF27-AF28 -> 1285.4196 | AG29: =AG27-AG28 -> 1296.5672 | AH29: =AH27-AH28 -> 1117.6391 | AI29: =AI27-AI28 -> 692.481 | AJ29: =AJ27-AJ28 -> 493.916 | AK29: =AK27-AK28 -> 510.46376 | AL29: =AL27-AL28 -> 661 | ... AU29: =AU27-AU28 -> 1465.1
A30: Net margin | B30: % | C30: =IFERROR(C29/C6,"") -> 0.098906135 | D30: =IFERROR(D29/D6,"") -> 0.11554097 | E30: =IFERROR(E29/E6,"") -> 0.11210146 | F30: =IFERROR(F29/F6,"") -> 0.12416835 | G30: =IFERROR(G29/G6,"") -> 0.10826378 | H30: =IFERROR(H29/H6,"") -> 0.086594416 | I30: =IFERROR(I29/I6,"") -> 0.11313719 | J30: =IFERROR(J29/J6,"") -> 0.078446252 | ... AU30: =IFERROR(AU29/AU6,"") -> 0.093247793
A31: USD revenue | B31: $m | C31: ='Raw Financials'!C56 -> 989.12301 | D31: ='Raw Financials'!D56 -> 1011.0334 | E31: ='Raw Financials'!E56 -> 1014.7137 | F31: ='Raw Financials'!F56 -> 1022.5853 | G31: ='Raw Financials'!G56 -> 1031.4658 | H31: ='Raw Financials'!H56 -> 1072.3792 | I31: ='Raw Financials'!I56 -> 1116.0923 | J31: ='Raw Financials'!J56 -> 1131.1552 | ... AU31: ='Raw Financials'!AU56 -> 1660.4
A32: USD revenue QoQ growth | B32: % | D32: =IFERROR(D31/C31-1,"") -> 0.022151295 | E32: =IFERROR(E31/D31-1,"") -> 0.0036401436 | F32: =IFERROR(F31/E31-1,"") -> 0.0077574891 | G32: =IFERROR(G31/F31-1,"") -> 0.0086843223 | H32: =IFERROR(H31/G31-1,"") -> 0.039665331 | I32: =IFERROR(I31/H31-1,"") -> 0.040762725 | J32: =IFERROR(J31/I31-1,"") -> 0.013496075 | K32: =IFERROR(K31/J31-1,"") -> 0.0061790026 | ... AU32: =IFERROR(AU31/AT31-1,"") -> 0.021991521
A33: Implied INR / USD | B33: ₹ / $ | C33: =IFERROR(C6*10/C31,"") -> 63.630343 | D33: =IFERROR(D6*10/D31,"") -> 65.433399 | E33: =IFERROR(E6*10/E31,"") -> 66.039729 | F33: =IFERROR(F6*10/F31,"") -> 67.317924 | G33: =IFERROR(G6*10/G31,"") -> 67.098052 | H33: =IFERROR(H6*10/H31,"") -> 66.836527 | I33: =IFERROR(I6*10/I31,"") -> 67.713958 | J33: =IFERROR(J6*10/J31,"") -> 66.259649 | ... AU33: =IFERROR(AU6*10/AU31,"") -> 94.627198

Sheet Annual P&L
A1: Annual Profit & Loss
A2: Actuals link to reported source data; FY27E–FY30E are formula-driven from the operating bridge and assumptions
A5: Metric | B5: Units | C5: FY16A | D5: FY17A | E5: FY18A | F5: FY19A | G5: FY20A | H5: FY21A | I5: FY22A | J5: FY23A | K5: FY24A | L5: FY25A | M5: FY26A | N5: FY27E | O5: FY28E | P5: FY29E | Q5: FY30E
A7: Revenue | B7: ₹ cr | C7: ='Raw Financials'!C6 -> 26494.232 | D7: ='Raw Financials'!D6 -> 29140.841 | E7: ='Raw Financials'!E6 -> 30772.881 | F7: ='Raw Financials'!F6 -> 34742.132 | G7: ='Raw Financials'!G6 -> 36867.679 | H7: ='Raw Financials'!H6 -> 37855.081 | I7: ='Raw Financials'!I6 -> 44645.964 | J7: ='Raw Financials'!J6 -> 53290.167 | ... M7: ='Raw Financials'!M6 -> 56815.4 | N7: ='Revenue Drivers'!N30 -> 58225.878 | O7: ='Revenue Drivers'!O30 -> 60460.105 | P7: ='Revenue Drivers'!P30 -> 63337.982 | Q7: ='Revenue Drivers'!Q30 -> 66753.18
A8: YoY growth | B8: % | D8: =IFERROR(D7/C7-1,"") -> 0.099893788 | E8: =IFERROR(E7/D7-1,"") -> 0.056005236 | F8: =IFERROR(F7/E7-1,"") -> 0.12898534 | G8: =IFERROR(G7/F7-1,"") -> 0.061180684 | H8: =IFERROR(H7/G7-1,"") -> 0.026782321 | I8: =IFERROR(I7/H7-1,"") -> 0.17939159 | J8: =IFERROR(J7/I7-1,"") -> 0.19361667 | K8: =IFERROR(K7/J7-1,"") -> -0.0242939 | ... Q8: =IFERROR(Q7/P7-1,"") -> 0.053920233
A9: Cost of services | B9: ₹ cr | C9: ='Raw Financials'!C7 -> 18329.038 | D9: ='Raw Financials'!D7 -> 20566.059 | E9: ='Raw Financials'!E7 -> 21530.042 | F9: ='Raw Financials'!F7 -> 23358.982 | G9: ='Raw Financials'!G7 -> 25974.337 | H9: ='Raw Financials'!H7 -> 25855.48 | I9: ='Raw Financials'!I7 -> 30972.015 | J9: ='Raw Financials'!J7 -> 38119.703 | ... M9: ='Raw Financials'!M7 -> 39868.82 | N9: =N7*(1-Assumptions!C19) -> 40466.985 | O9: =O7*(1-Assumptions!D19) -> 41717.473 | P9: =P7*(1-Assumptions!E19) -> 43386.517 | Q9: =Q7*(1-Assumptions!F19) -> 45392.163
A10: Gross profit | B10: ₹ cr | C10: =C7-C9 -> 8165.1946 | D10: =D7-D9 -> 8574.7821 | E10: =E7-E9 -> 9242.8396 | F10: =F7-F9 -> 11383.149 | G10: =G7-G9 -> 10893.342 | H10: =H7-H9 -> 11999.601 | I10: =I7-I9 -> 13673.949 | J10: =J7-J9 -> 15170.464 | ... Q10: =Q7-Q9 -> 21361.018
A11: Gross margin | B11: % | C11: =IFERROR(C10/C7,"") -> 0.30818763 | D11: =IFERROR(D10/D7,"") -> 0.29425307 | E11: =IFERROR(E10/E7,"") -> 0.30035665 | F11: =IFERROR(F10/F7,"") -> 0.32764683 | G11: =IFERROR(G10/G7,"") -> 0.29547133 | H11: =IFERROR(H10/H7,"") -> 0.31698786 | I11: =IFERROR(I10/I7,"") -> 0.30627514 | J11: =IFERROR(J10/J7,"") -> 0.28467661 | ... M11: =IFERROR(M10/M7,"") -> 0.2982744 | N11: =N10/N7 -> 0.305 | O11: =O10/O7 -> 0.31 | P11: =P10/P7 -> 0.315 | Q11: =Q10/Q7 -> 0.32
A12: Reported gross profit control | B12: ₹ cr | C12: ='Raw Financials'!C8 -> 8165.1946 | D12: ='Raw Financials'!D8 -> 8574.7821 | E12: ='Raw Financials'!E8 -> 9242.8906 | F12: ='Raw Financials'!F8 -> 11383.149 | G12: ='Raw Financials'!G8 -> 10893.442 | H12: ='Raw Financials'!H8 -> 11999.6 | I12: ='Raw Financials'!I8 -> 13673.949 | J12: ='Raw Financials'!J8 -> 15170.464 | ... M12: ='Raw Financials'!M8 -> 16946.579 | N12: =N10 -> 17758.893 | O12: =O10 -> 18742.633 | P12: =P10 -> 19951.464 | Q12: =Q10 -> 21361.018
A13: Gross profit check | B13: ₹ cr | C13: =C10-C12 -> 0 | D13: =D10-D12 -> 0 | E13: =E10-E12 -> -0.051 | F13: =F10-F12 -> 0 | G13: =G10-G12 -> -0.1 | H13: =H10-H12 -> 0.001 | I13: =I10-I12 -> 0 | J13: =J10-J12 -> 0 | ... M13: =M10-M12 -> 0 | N13: =0 -> 0 | O13: =0 -> 0 | P13: =0 -> 0 | Q13: =0 -> 0
A14: SG&A | B14: ₹ cr | C14: ='Raw Financials'!C9 -> 3894.5043 | D14: ='Raw Financials'!D9 -> 4390.3473 | E14: ='Raw Financials'!E9 -> 4533.2804 | F14: ='Raw Financials'!F9 -> 5046.2316 | G14: ='Raw Financials'!G9 -> 5167.303 | H14: ='Raw Financials'!H9 -> 5152.554 | I14: ='Raw Financials'!I9 -> 5653.965 | J14: ='Raw Financials'!J9 -> 7141.688 | ... M14: ='Raw Financials'!M9 -> 7912.4797 | N14: =N7*Assumptions!C20 -> 8035.1712 | O14: =O7*Assumptions!D20 -> 8283.0344 | P14: =P7*Assumptions!E20 -> 8550.6275 | Q14: =Q7*Assumptions!F20 -> 8944.9262
A15: EBITDA | B15: ₹ cr | C15: =C10-C14 -> 4270.6903 | D15: =D10-D14 -> 4184.4348 | E15: =E10-E14 -> 4709.5592 | F15: =F10-F14 -> 6336.9176 | G15: =G10-G14 -> 5726.039 | H15: =H10-H14 -> 6847.047 | I15: =I10-I14 -> 8019.984 | J15: =J10-J14 -> 8028.776 | ... Q15: =Q10-Q14 -> 12416.092
A16: EBITDA margin | B16: % | C16: =IFERROR(C15/C7,"") -> 0.16119321 | D16: =IFERROR(D15/D7,"") -> 0.14359348 | E16: =IFERROR(E15/E7,"") -> 0.15304252 | F16: =IFERROR(F15/F7,"") -> 0.18239864 | G16: =IFERROR(G15/G7,"") -> 0.15531325 | H16: =IFERROR(H15/H7,"") -> 0.18087524 | I16: =IFERROR(I15/I7,"") -> 0.17963514 | J16: =IFERROR(J15/J7,"") -> 0.15066149 | ... M16: =IFERROR(M15/M7,"") -> 0.15900794 | N16: =N15/N7 -> 0.167 | O16: =O15/O7 -> 0.173 | P16: =P15/P7 -> 0.18 | Q16: =Q15/Q7 -> 0.186
A17: Reported EBITDA control | B17: ₹ cr | C17: ='Raw Financials'!C10 -> 4270.6903 | D17: ='Raw Financials'!D10 -> 4184.4348 | E17: ='Raw Financials'!E10 -> 4709.6102 | F17: ='Raw Financials'!F10 -> 6336.9176 | G17: ='Raw Financials'!G10 -> 5726.139 | H17: ='Raw Financials'!H10 -> 6847.047 | I17: ='Raw Financials'!I10 -> 8019.984 | J17: ='Raw Financials'!J10 -> 8028.776 | ... M17: ='Raw Financials'!M10 -> 9034.0995 | N17: =N15 -> 9723.7216 | O17: =O15 -> 10459.598 | P17: =P15 -> 11400.837 | Q17: =Q15 -> 12416.092
A18: EBITDA check | B18: ₹ cr | C18: =C15-C17 -> 0 | D18: =D15-D17 -> 0 | E18: =E15-E17 -> -0.051 | F18: =F15-F17 -> 0 | G18: =G15-G17 -> -0.1 | H18: =H15-H17 -> 0 | I18: =I15-I17 -> 0 | J18: =J15-J17 -> 0 | ... M18: =M15-M17 -> 0 | N18: =0 -> 0 | O18: =0 -> 0 | P18: =0 -> 0 | Q18: =0 -> 0
A19: D&A | B19: ₹ cr | C19: ='Raw Financials'!C11 -> 758.923 | D19: ='Raw Financials'!D11 -> 978.0552 | E19: ='Raw Financials'!E11 -> 1085.038 | F19: ='Raw Financials'!F11 -> 1129.2 | G19: ='Raw Financials'!G11 -> 1445.769 | H19: ='Raw Financials'!H11 -> 1457.71 | I19: ='Raw Financials'!I11 -> 1520.392 | J19: ='Raw Financials'!J11 -> 1956.7 | ... M19: ='Raw Financials'!M11 -> 1881.6 | N19: =N7*Assumptions!C21 -> 1921.454 | O19: =O7*Assumptions!D21 -> 1934.7234 | P19: =P7*Assumptions!E21 -> 1963.4774 | Q19: =Q7*Assumptions!F21 -> 2002.5954
A20: EBIT | B20: ₹ cr | C20: ='Raw Financials'!C12 -> 3511.7673 | D20: ='Raw Financials'!D12 -> 3206.3796 | E20: ='Raw Financials'!E12 -> 3624.5722 | F20: ='Raw Financials'!F12 -> 5207.7176 | G20: ='Raw Financials'!G12 -> 4280.27 | H20: ='Raw Financials'!H12 -> 5389.337 | I20: ='Raw Financials'!I12 -> 6499.591 | J20: ='Raw Financials'!J12 -> 6072.076 | ... M20: ='Raw Financials'!M12 -> 7152.4995 | N20: =N15-N19 -> 7802.2677 | O20: =O15-O19 -> 8524.8748 | P20: =P15-P19 -> 9437.3593 | Q20: =Q15-Q19 -> 10413.496
A21: EBIT margin | B21: % | C21: =IFERROR(C20/C7,"") -> 0.13254837 | D21: =IFERROR(D20/D7,"") -> 0.11003044 | E21: =IFERROR(E20/E7,"") -> 0.11778462 | F21: =IFERROR(F20/F7,"") -> 0.14989632 | G21: =IFERROR(G20/G7,"") -> 0.11609817 | H21: =IFERROR(H20/H7,"") -> 0.1423676 | I21: =IFERROR(I20/I7,"") -> 0.14558071 | J21: =IFERROR(J20/J7,"") -> 0.11394365 | ... M21: =IFERROR(M20/M7,"") -> 0.12589016 | N21: =N20/N7 -> 0.134 | O21: =O20/O7 -> 0.141 | P21: =P20/P7 -> 0.149 | Q21: =Q20/Q7 -> 0.156
A22: Impairment | B22: ₹ cr | C22: ='Raw Financials'!C13 -> 0 | D22: ='Raw Financials'!D13 -> 0 | E22: ='Raw Financials'!E13 -> 0 | F22: ='Raw Financials'!F13 -> 0 | G22: ='Raw Financials'!G13 -> 217.5 | H22: ='Raw Financials'!H13 -> 50.7 | I22: ='Raw Financials'!I13 -> 0 | J22: ='Raw Financials'!J13 -> 237 | ... M22: ='Raw Financials'!M13 -> 5.3290705e-16 | N22: =Assumptions!C22 -> 0 | O22: =Assumptions!D22 -> 0 | P22: =Assumptions!E22 -> 0 | Q22: =Assumptions!F22 -> 0
A23: FX gain / (loss) | B23: ₹ cr | C23: ='Raw Financials'!C15 -> 98.59186 | D23: ='Raw Financials'!D15 -> 387.58728 | E23: ='Raw Financials'!E15 -> 774.95874 | F23: ='Raw Financials'!F15 -> 12.109998 | G23: ='Raw Financials'!G15 -> 302.2 | H23: ='Raw Financials'!H15 -> 97.5 | I23: ='Raw Financials'!I15 -> 564.214 | J23: ='Raw Financials'!J15 -> 299 | ... M23: ='Raw Financials'!M15 -> -479.9 | N23: =0 -> 0 | O23: =0 -> 0 | P23: =0 -> 0 | Q23: =0 -> 0
A24: Interest, dividend & miscellaneous income | B24: ₹ cr | C24: ='Raw Financials'!C16 -> 340.7861 | D24: ='Raw Financials'!D16 -> 389.97161 | E24: ='Raw Financials'!E16 -> 641.4893 | F24: ='Raw Financials'!F16 -> 522.09286 | G24: ='Raw Financials'!G16 -> 890.19 | H24: ='Raw Financials'!H16 -> 689.616 | I24: ='Raw Financials'!I16 -> 548.102 | J24: ='Raw Financials'!J16 -> 666 | ... M24: ='Raw Financials'!M16 -> 511.8 | N24: ='Annual Balance Sheet'!M62*Assumptions!C23 -> 211.9025 | O24: ='Annual Balance Sheet'!N62*Assumptions!D23 -> 250.40579 | P24: ='Annual Balance Sheet'!O62*Assumptions!E23 -> 295.30029 | Q24: ='Annual Balance Sheet'!P62*Assumptions!F23 -> 340.93447
A25: Interest expense | B25: ₹ cr | C25: ='Raw Financials'!C17 -> 97.037558 | D25: ='Raw Financials'!D17 -> 128.59243 | E25: ='Raw Financials'!E17 -> 162.35364 | F25: ='Raw Financials'!F17 -> 133.161 | G25: ='Raw Financials'!G17 -> 191.878 | H25: ='Raw Financials'!H17 -> 174 | I25: ='Raw Financials'!I17 -> 162.6 | J25: ='Raw Financials'!J17 -> 325.6 | ... M25: ='Raw Financials'!M17 -> 337.4 | N25: =AVERAGE('Annual Balance Sheet'!M60,'Annual Balance Sheet'!N60)*Assumptions!C24 -> 4.176 | O25: =AVERAGE('Annual Balance Sheet'!N60,'Annual Balance Sheet'!O60)*Assumptions!D24 -> 4.176 | P25: =AVERAGE('Annual Balance Sheet'!O60,'Annual Balance Sheet'!P60)*Assumptions!E24 -> 4.176 | Q25: =AVERAGE('Annual Balance Sheet'!P60,'Annual Balance Sheet'!Q60)*Assumptions!F24 -> 4.176
A26: Share of associate | B26: ₹ cr | C26: ='Raw Financials'!C18 -> 2.6293348 | D26: ='Raw Financials'!D18 -> -2.3315044 | E26: ='Raw Financials'!E18 -> 0.0699921 | F26: ='Raw Financials'!F18 -> -65.549 | G26: ='Raw Financials'!G18 -> -5.54 | H26: ='Raw Financials'!H18 -> 1.2 | I26: ='Raw Financials'!I18 -> 2.8 | J26: ='Raw Financials'!J18 -> -29 | ... M26: ='Raw Financials'!M18 -> -1.5 | N26: =0 -> 0 | O26: =0 -> 0 | P26: =0 -> 0 | Q26: =0 -> 0
A27: PBT before exceptional | B27: ₹ cr | C27: =SUM(C20,-C22,C23:C24,-C25,C26) -> 3856.737 | D27: =SUM(D20,-D22,D23:D24,-D25,D26) -> 3853.0146 | E27: =SUM(E20,-E22,E23:E24,-E25,E26) -> 4878.7366 | F27: =SUM(F20,-F22,F23:F24,-F25,F26) -> 5543.2105 | G27: =SUM(G20,-G22,G23:G24,-G25,G26) -> 5057.742 | H27: =SUM(H20,-H22,H23:H24,-H25,H26) -> 5952.953 | I27: =SUM(I20,-I22,I23:I24,-I25,I26) -> 7452.107 | J27: =SUM(J20,-J22,J23:J24,-J25,J26) -> 6445.476 | ... Q27: =SUM(Q20,-Q22,Q23:Q24,-Q25,Q26) -> 10750.255
A28: Exceptional item | B28: ₹ cr | C28: ='Raw Financials'!C20 -> 0 | D28: ='Raw Financials'!D20 -> 0 | E28: ='Raw Financials'!E20 -> 0 | F28: ='Raw Financials'!F20 -> 0 | G28: ='Raw Financials'!G20 -> 0 | H28: ='Raw Financials'!H20 -> 0 | I28: ='Raw Financials'!I20 -> 0 | J28: ='Raw Financials'!J20 -> 0 | ... M28: ='Raw Financials'!M20 -> 272.4 | N28: =0 -> 0 | O28: =0 -> 0 | P28: =0 -> 0 | Q28: =0 -> 0
A29: PBT | B29: ₹ cr | C29: =C27-C28 -> 3856.737 | D29: =D27-D28 -> 3853.0146 | E29: =E27-E28 -> 4878.7366 | F29: =F27-F28 -> 5543.2105 | G29: =G27-G28 -> 5057.742 | H29: =H27-H28 -> 5952.953 | I29: =I27-I28 -> 7452.107 | J29: =J27-J28 -> 6445.476 | ... M29: =M27-M28 -> 6573.0995 | N29: =N27+N28 -> 8009.9942 | O29: =O27+O28 -> 8771.1046 | P29: =P27+P28 -> 9728.4836 | Q29: =Q27+Q28 -> 10750.255
A30: PBT margin | B30: % | C30: =IFERROR(C29/C7,"") -> 0.14556893 | D30: =IFERROR(D29/D7,"") -> 0.13222043 | E30: =IFERROR(E29/E7,"") -> 0.15854013 | F30: =IFERROR(F29/F7,"") -> 0.15955298 | G30: =IFERROR(G29/G7,"") -> 0.13718634 | H30: =IFERROR(H29/H7,"") -> 0.15725638 | I30: =IFERROR(I29/I7,"") -> 0.16691558 | J30: =IFERROR(J29/J7,"") -> 0.12095057 | ... M30: =IFERROR(M29/M7,"") -> 0.11569222 | N30: =N29/N7 -> 0.1375676 | O30: =O29/O7 -> 0.1450726 | P30: =P29/P7 -> 0.15359636 | Q30: =Q29/Q7 -> 0.16104483
A31: Tax | B31: ₹ cr | C31: ='Raw Financials'!C22 -> 830.11881 | D31: ='Raw Financials'!D22 -> 1002.1243 | E31: ='Raw Financials'!E22 -> 1092.5615 | F31: ='Raw Financials'!F22 -> 1254.394 | G31: ='Raw Financials'!G22 -> 1160.4 | H31: ='Raw Financials'!H22 -> 1599.894 | I31: ='Raw Financials'!I22 -> 1821.994 | J31: ='Raw Financials'!J22 -> 1588.5 | ... M31: ='Raw Financials'!M22 -> 1767.5995 | N31: =N29*Assumptions!C25 -> 2066.5785 | O31: =O29*Assumptions!D25 -> 2236.6317 | P31: =P29*Assumptions!E25 -> 2480.7633 | Q31: =Q29*Assumptions!F25 -> 2741.3149
A32: Effective tax rate | B32: % | C32: =IFERROR(C31/C29,"") -> 0.21523864 | D32: =IFERROR(D31/D29,"") -> 0.26008838 | E32: =IFERROR(E31/E29,"") -> 0.22394353 | F32: =IFERROR(F31/F29,"") -> 0.22629377 | G32: =IFERROR(G31/G29,"") -> 0.22943045 | H32: =IFERROR(H31/H29,"") -> 0.26875636 | I32: =IFERROR(I31/I29,"") -> 0.24449381 | J32: =IFERROR(J31/J29,"") -> 0.24645193 | ... M32: =IFERROR(M31/M29,"") -> 0.26891416 | N32: =N31/N29 -> 0.258 | O32: =O31/O29 -> 0.255 | P32: =P31/P29 -> 0.255 | Q32: =Q31/Q29 -> 0.255
A33: PAT before NCI | B33: ₹ cr | C33: =C29-C31 -> 3026.6182 | D33: =D29-D31 -> 2850.8903 | E33: =E29-E31 -> 3786.1751 | F33: =F29-F31 -> 4288.8165 | G33: =G29-G31 -> 3897.342 | H33: =H29-H31 -> 4353.059 | I33: =I29-I31 -> 5630.113 | J33: =J29-J31 -> 4856.976 | ... Q33: =Q29-Q31 -> 8008.9397
A34: NCI / minority interest | B34: ₹ cr | C34: ='Raw Financials'!C24 -> -33.732182 | D34: ='Raw Financials'!D24 -> -37.957189 | E34: ='Raw Financials'!E24 -> 13.579915 | F34: ='Raw Financials'!F24 -> 8.8 | G34: ='Raw Financials'!G24 -> 135.6 | H34: ='Raw Financials'!H24 -> 75 | I34: ='Raw Financials'!I24 -> -64 | J34: ='Raw Financials'!J24 -> 25.7 | ... M34: ='Raw Financials'!M24 -> -5.3996265 | N34: =N33*Assumptions!C26 -> 0 | O34: =O33*Assumptions!D26 -> 0 | P34: =P33*Assumptions!E26 -> 0 | Q34: =Q33*Assumptions!F26 -> 0
A35: Net income attributable | B35: ₹ cr | C35: =C33+C34 -> 2992.886 | D35: =D33+D34 -> 2812.9331 | E35: =E33+E34 -> 3799.755 | F35: =F33+F34 -> 4297.6165 | G35: =G33+G34 -> 4032.942 | H35: =H33+H34 -> 4428.059 | I35: =I33+I34 -> 5566.113 | J35: =J33-J34 -> 4831.276 | K35: =K33-K34 -> 2357.896 | L35: =L33-L34 -> 4251.5418 | M35: =M33-M34 -> 4810.8996 | N35: =N33-N34 -> 5943.4157 | O35: =O33-O34 -> 6534.4729 | P35: =P33-P34 -> 7247.7202 | Q35: =Q33-Q34 -> 8008.9397
A36: Net margin | B36: % | C36: =IFERROR(C35/C7,"") -> 0.11296368 | D36: =IFERROR(D35/D7,"") -> 0.09652889 | E36: =IFERROR(E35/E7,"") -> 0.12347739 | F36: =IFERROR(F35/F7,"") -> 0.12370043 | G36: =IFERROR(G35/G7,"") -> 0.10938964 | H36: =IFERROR(H35/H7,"") -> 0.11697397 | I36: =IFERROR(I35/I7,"") -> 0.12467225 | J36: =IFERROR(J35/J7,"") -> 0.090659802 | ... M36: =IFERROR(M35/M7,"") -> 0.084675979 | N36: =N35/N7 -> 0.10207516 | O36: =O35/O7 -> 0.10807909 | P36: =P35/P7 -> 0.11442929 | Q36: =Q35/Q7 -> 0.1199784
A37: Basic shares | B37: crore | C37: =IFERROR(C35/C41,"") -> 86.72896 | D37: =IFERROR(D35/D41,"") -> 87.533028 | E37: =IFERROR(E35/E41,"") -> 88.324592 | F37: =IFERROR(F35/F41,"") -> 88.656476 | G37: =IFERROR(G35/G41,"") -> 87.274226 | H37: =IFERROR(H35/H41,"") -> 87.441923 | I37: =IFERROR(I35/I41,"") -> 87.904501 | J37: =IFERROR(J35/J41,"") -> 88.178062 | ... M37: =IFERROR(M35/M41,"") -> 88.632364 | N37: =M37 -> 88.632364 | O37: =N37 -> 88.632364 | P37: =O37 -> 88.632364 | Q37: =P37 -> 88.632364
A38: Diluted shares | B38: crore | C38: =IFERROR(C35/C42,"") -> 88.772401 | D38: =IFERROR(D35/D42,"") -> 88.890954 | E38: =IFERROR(E35/E42,"") -> 89.061095 | F38: =IFERROR(F35/F42,"") -> 90.058074 | G38: =IFERROR(G35/G42,"") -> 87.959477 | H38: =IFERROR(H35/H42,"") -> 88.225921 | I38: =IFERROR(I35/I42,"") -> 88.618261 | J38: =IFERROR(J35/J42,"") -> 88.54978 | ... M38: =IFERROR(M35/M42,"") -> 88.779841 | N38: =M38*(1+Assumptions!C43) -> 88.779841 | O38: =N38*(1+Assumptions!D43) -> 88.779841 | P38: =O38*(1+Assumptions!E43) -> 88.779841 | Q38: =P38*(1+Assumptions!F43) -> 88.779841
A39: Basic EPS | B39: ₹ / share | C39: =IFERROR(C35/C37,"") -> 34.508496 | D39: =IFERROR(D35/D37,"") -> 32.135676 | E39: =IFERROR(E35/E37,"") -> 43.020352 | F39: =IFERROR(F35/F37,"") -> 48.474931 | G39: =IFERROR(G35/G37,"") -> 46.21 | H39: =IFERROR(H35/H37,"") -> 50.64 | I39: =IFERROR(I35/I37,"") -> 63.32 | J39: =IFERROR(J35/J37,"") -> 54.79 | ... M39: =IFERROR(M35/M37,"") -> 54.279265 | N39: =N35/N37 -> 67.056946 | O39: =O35/O37 -> 73.725585 | P39: =P35/P37 -> 81.772841 | Q39: =Q35/Q37 -> 90.361345
A40: Diluted EPS | B40: ₹ / share | C40: =IFERROR(C35/C38,"") -> 33.71415 | D40: =IFERROR(D35/D38,"") -> 31.644762 | E40: =IFERROR(E35/E38,"") -> 42.664589 | F40: =IFERROR(F35/F38,"") -> 47.720502 | G40: =IFERROR(G35/G38,"") -> 45.85 | H40: =IFERROR(H35/H38,"") -> 50.19 | I40: =IFERROR(I35/I38,"") -> 62.81 | J40: =IFERROR(J35/J38,"") -> 54.56 | ... M40: =IFERROR(M35/M38,"") -> 54.189099 | N40: =N35/N38 -> 66.945554 | O40: =O35/O38 -> 73.603116 | P40: =P35/P38 -> 81.637004 | Q40: =Q35/Q38 -> 90.211242
A41: Reported basic EPS control | B41: ₹ / share | C41: ='Raw Financials'!C26 -> 34.508496 | D41: ='Raw Financials'!D26 -> 32.135676 | E41: ='Raw Financials'!E26 -> 43.020352 | F41: ='Raw Financials'!F26 -> 48.474931 | G41: ='Raw Financials'!G26 -> 46.21 | H41: ='Raw Financials'!H26 -> 50.64 | I41: ='Raw Financials'!I26 -> 63.32 | J41: ='Raw Financials'!J26 -> 54.79 | ... M41: ='Raw Financials'!M26 -> 54.279265 | N41: =N39 -> 67.056946 | O41: =O39 -> 73.725585 | P41: =P39 -> 81.772841 | Q41: =Q39 -> 90.361345
A42: Reported diluted EPS control | B42: ₹ / share | C42: ='Raw Financials'!C27 -> 33.71415 | D42: ='Raw Financials'!D27 -> 31.644762 | E42: ='Raw Financials'!E27 -> 42.664589 | F42: ='Raw Financials'!F27 -> 47.720502 | G42: ='Raw Financials'!G27 -> 45.85 | H42: ='Raw Financials'!H27 -> 50.19 | I42: ='Raw Financials'!I27 -> 62.81 | J42: ='Raw Financials'!J27 -> 54.56 | ... M42: ='Raw Financials'!M27 -> 54.189099 | N42: =N40 -> 66.945554 | O42: =O40 -> 73.603116 | P42: =P40 -> 81.637004 | Q42: =Q40 -> 90.211242
A43: Diluted EPS check | B43: ₹ / share | C43: =C40-C42 -> 0 | D43: =D40-D42 -> 0 | E43: =E40-E42 -> 0 | F43: =F40-F42 -> 0 | G43: =G40-G42 -> 0 | H43: =H40-H42 -> 0 | I43: =I40-I42 -> 0 | J43: =J40-J42 -> 0 | ... M43: =M40-M42 -> 0 | N43: =0 -> 0 | O43: =0 -> 0 | P43: =0 -> 0 | Q43: =0 -> 0
A44: Dividend per share — cash basis | B44: ₹ / share | C44: =IFERROR(-'Annual Cash Flow'!C65/C38,"") -> 7.0348441 | D44: =IFERROR(-'Annual Cash Flow'!D65/D38,"") -> 13.940279 | E44: =IFERROR(-'Annual Cash Flow'!E65/E38,"") -> 10.597024 | F44: =IFERROR(-'Annual Cash Flow'!F65/F38,"") -> 16.552652 | G44: =IFERROR(-'Annual Cash Flow'!G65/G38,"") -> 28.327818 | H44: =IFERROR(-'Annual Cash Flow'!H65/H38,"") -> 19.941475 | I44: =IFERROR(-'Annual Cash Flow'!I65/I38,"") -> 44.920854 | J44: =IFERROR(-'Annual Cash Flow'!J65/J38,"") -> 48.145834 | ... Q44: =IFERROR(-'Annual Cash Flow'!Q65/Q38,"") -> 72.168993
A45: Dividend payout — cash basis | B45: % | C45: =IFERROR(-'Annual Cash Flow'!C65/C35,"") -> 0.20866147 | D45: =IFERROR(-'Annual Cash Flow'!D65/D35,"") -> 0.44052405 | E45: =IFERROR(-'Annual Cash Flow'!E65/E35,"") -> 0.24837985 | F45: =IFERROR(-'Annual Cash Flow'!F65/F35,"") -> 0.34686669 | G45: =IFERROR(-'Annual Cash Flow'!G65/G35,"") -> 0.6178368 | H45: =IFERROR(-'Annual Cash Flow'!H65/H35,"") -> 0.39731968 | I45: =IFERROR(-'Annual Cash Flow'!I65/I35,"") -> 0.71518634 | J45: =IFERROR(-'Annual Cash Flow'!J65/J35,"") -> 0.8824383 | ... Q45: =IFERROR(-'Annual Cash Flow'!Q65/Q35,"") -> 0.8

Sheet Annual Balance Sheet
A1: Annual Balance Sheet
A2: Historical balances link to reported data; FY27E–FY30E use explicit roll-forwards and forecast cash is the output of the cash-flow statement
A5: Metric | B5: Units | C5: FY16A | D5: FY17A | E5: FY18A | F5: FY19A | G5: FY20A | H5: FY21A | I5: FY22A | J5: FY23A | K5: FY24A | L5: FY25A | M5: FY26A | N5: FY27E | O5: FY28E | P5: FY29E | Q5: FY30E
A7: PPE | B7: ₹ cr | C7: ='Raw Financials'!C63 -> 2517.8151 | D7: ='Raw Financials'!D63 -> 3071.7415 | E7: ='Raw Financials'!E63 -> 2980.9579 | F7: ='Raw Financials'!F63 -> 2622.8669 | G7: ='Raw Financials'!G63 -> 2660.9 | H7: ='Raw Financials'!H63 -> 2463.2 | I7: ='Raw Financials'!I63 -> 2682.3 | J7: ='Raw Financials'!J63 -> 2862.2 | ... M7: ='Raw Financials'!M63 -> 2425.6 | N7: ='BS Forecast Schedules'!D19 -> 2338.8595 | O7: ='BS Forecast Schedules'!E19 -> 2265.4137 | P7: ='BS Forecast Schedules'!F19 -> 2210.4253 | Q7: ='BS Forecast Schedules'!G19 -> 2175.6826
A8: Capital work-in-progress | B8: ₹ cr | C8: ='Raw Financials'!C64 -> 629.40472 | D8: ='Raw Financials'!D64 -> 372.86312 | E8: ='Raw Financials'!E64 -> 239.91686 | F8: ='Raw Financials'!F64 -> 276.3 | G8: ='Raw Financials'!G64 -> 50.1 | H8: ='Raw Financials'!H64 -> 118.3 | I8: ='Raw Financials'!I64 -> 165.1 | J8: ='Raw Financials'!J64 -> 83.6 | ... M8: ='Raw Financials'!M64 -> 26.8 | N8: ='BS Forecast Schedules'!D17 -> 23.290351 | O8: ='BS Forecast Schedules'!E17 -> 24.184042 | P8: ='BS Forecast Schedules'!F17 -> 25.335193 | Q8: ='BS Forecast Schedules'!G17 -> 26.701272
A9: ROU assets | B9: ₹ cr | C9: ='Raw Financials'!C65 -> 0 | D9: ='Raw Financials'!D65 -> 0 | E9: ='Raw Financials'!E65 -> 0 | F9: ='Raw Financials'!F65 -> 0 | G9: ='Raw Financials'!G65 -> 1173 | H9: ='Raw Financials'!H65 -> 1007.2 | I9: ='Raw Financials'!I65 -> 937.18565 | J9: ='Raw Financials'!J65 -> 1097.1857 | ... M9: ='Raw Financials'!M65 -> 1980.2 | N9: ='BS Forecast Schedules'!D26 -> 2006.4016 | O9: ='BS Forecast Schedules'!E26 -> 2054.7697 | P9: ='BS Forecast Schedules'!F26 -> 2127.6084 | Q9: ='BS Forecast Schedules'!G26 -> 2227.7382
A10: Investment property | B10: ₹ cr | C10: ='Raw Financials'!C66 -> 0 | D10: ='Raw Financials'!D66 -> 101.06761 | E10: ='Raw Financials'!E66 -> 190.55728 | F10: ='Raw Financials'!F66 -> 170.7845 | G10: ='Raw Financials'!G66 -> 144.42723 | H10: ='Raw Financials'!H66 -> 89.061788 | I10: ='Raw Financials'!I66 -> 79.7 | J10: ='Raw Financials'!J66 -> 74.8 | ... M10: ='Raw Financials'!M66 -> 32.3 | N10: =M10 -> 32.3 | O10: =N10 -> 32.3 | P10: =O10 -> 32.3 | Q10: =P10 -> 32.3
A11: Goodwill | B11: ₹ cr | C11: ='Raw Financials'!C67 -> 1735.746 | D11: ='Raw Financials'!D67 -> 2627.9102 | E11: ='Raw Financials'!E67 -> 2772.71 | F11: ='Raw Financials'!F67 -> 2816.308 | G11: ='Raw Financials'!G67 -> 3387.7434 | H11: ='Raw Financials'!H67 -> 4008.2094 | I11: ='Raw Financials'!I67 -> 7425.8262 | J11: ='Raw Financials'!J67 -> 7665.6965 | ... M11: ='Raw Financials'!M67 -> 8456 | N11: =MAX(0,M11-'Annual P&L'!N22+Assumptions!C38) -> 8456 | O11: =MAX(0,N11-'Annual P&L'!O22+Assumptions!D38) -> 8456 | P11: =MAX(0,O11-'Annual P&L'!P22+Assumptions!E38) -> 8456 | Q11: =MAX(0,P11-'Annual P&L'!Q22+Assumptions!F38) -> 8456
A12: Other intangible assets | B12: ₹ cr | C12: ='Raw Financials'!C68 -> 91.078288 | D12: ='Raw Financials'!D68 -> 659.41414 | E12: ='Raw Financials'!E68 -> 1678.1245 | F12: ='Raw Financials'!F68 -> 1451.2245 | G12: ='Raw Financials'!G68 -> 1506 | H12: ='Raw Financials'!H68 -> 1450.8 | I12: ='Raw Financials'!I68 -> 3658.6 | J12: ='Raw Financials'!J68 -> 3231.6401 | ... M12: ='Raw Financials'!M68 -> 1969.9 | N12: ='BS Forecast Schedules'!D20 -> 1568.1414 | O12: ='BS Forecast Schedules'!E20 -> 1169.1047 | P12: ='BS Forecast Schedules'!F20 -> 770.07546 | Q12: ='BS Forecast Schedules'!G20 -> 369.55638
A13: Intangibles under development | B13: ₹ cr | C13: ='Raw Financials'!C69 -> 0 | D13: ='Raw Financials'!D69 -> 0 | E13: ='Raw Financials'!E69 -> 0 | F13: ='Raw Financials'!F69 -> 0 | G13: ='Raw Financials'!G69 -> 0 | H13: ='Raw Financials'!H69 -> 0 | I13: ='Raw Financials'!I69 -> 0 | J13: ='Raw Financials'!J69 -> 36.1 | ... M13: ='Raw Financials'!M69 -> 0 | N13: =M13 -> 0 | O13: =N13 -> 0 | P13: =O13 -> 0 | Q13: =P13 -> 0
A14: Equity-method investments | B14: ₹ cr | C14: ='Raw Financials'!C70 -> 0 | D14: ='Raw Financials'!D70 -> 0 | E14: ='Raw Financials'!E70 -> 0 | F14: ='Raw Financials'!F70 -> 36.1 | G14: ='Raw Financials'!G70 -> 19.656531 | H14: ='Raw Financials'!H70 -> 27.938734 | I14: ='Raw Financials'!I70 -> 196.87938 | J14: ='Raw Financials'!J70 -> 172.92985 | ... M14: ='Raw Financials'!M70 -> 55 | N14: =M14 -> 55 | O14: =N14 -> 55 | P14: =O14 -> 55 | Q14: =P14 -> 55
A15: Non-current investments | B15: ₹ cr | C15: ='Raw Financials'!C71 -> 1324.3564 | D15: ='Raw Financials'!D71 -> 230.82182 | E15: ='Raw Financials'!E71 -> 1245.8267 | F15: ='Raw Financials'!F71 -> 715.89131 | G15: ='Raw Financials'!G71 -> 216.28728 | H15: ='Raw Financials'!H71 -> 547.80129 | I15: ='Raw Financials'!I71 -> 250.97357 | J15: ='Raw Financials'!J71 -> 432.01203 | ... M15: ='Raw Financials'!M71 -> 35.2 | N15: =M15 -> 35.2 | O15: =N15 -> 35.2 | P15: =O15 -> 35.2 | Q15: =P15 -> 35.2
A16: Non-current billed receivables | B16: ₹ cr | C16: ='Raw Financials'!C72 -> 0 | D16: ='Raw Financials'!D72 -> 0 | E16: ='Raw Financials'!E72 -> 0 | F16: ='Raw Financials'!F72 -> 0 | G16: ='Raw Financials'!G72 -> 0 | H16: ='Raw Financials'!H72 -> 0 | I16: ='Raw Financials'!I72 -> 0.9 | J16: ='Raw Financials'!J72 -> 1.1 | ... M16: ='Raw Financials'!M72 -> 0 | N16: =0 -> 0 | O16: =0 -> 0 | P16: =0 -> 0 | Q16: =0 -> 0
A17: Non-current unbilled receivables | B17: ₹ cr | C17: ='Raw Financials'!C73 -> 0 | D17: ='Raw Financials'!D73 -> 0 | E17: ='Raw Financials'!E73 -> 0 | F17: ='Raw Financials'!F73 -> 0 | G17: ='Raw Financials'!G73 -> 0 | H17: ='Raw Financials'!H73 -> 0 | I17: ='Raw Financials'!I73 -> 0 | J17: ='Raw Financials'!J73 -> 0 | ... M17: ='Raw Financials'!M73 -> 0 | N17: =0 -> 0 | O17: =0 -> 0 | P17: =0 -> 0 | Q17: =0 -> 0
A18: Non-current loans | B18: ₹ cr | C18: ='Raw Financials'!C74 -> 0 | D18: ='Raw Financials'!D74 -> 0.9072221 | E18: ='Raw Financials'!E74 -> 5.2392788 | F18: ='Raw Financials'!F74 -> 4.3 | G18: ='Raw Financials'!G74 -> 4.5 | H18: ='Raw Financials'!H74 -> 4.7 | I18: ='Raw Financials'!I74 -> 13.6 | J18: ='Raw Financials'!J74 -> 4.9 | ... M18: ='Raw Financials'!M74 -> 6.9 | N18: =M18 -> 6.9 | O18: =N18 -> 6.9 | P18: =O18 -> 6.9 | Q18: =P18 -> 6.9
A19: Other non-current financial assets | B19: ₹ cr | C19: ='Raw Financials'!C75 -> 0 | D19: ='Raw Financials'!D75 -> 432.90512 | E19: ='Raw Financials'!E75 -> 246.79475 | F19: ='Raw Financials'!F75 -> 478.50045 | G19: ='Raw Financials'!G75 -> 428.12805 | H19: ='Raw Financials'!H75 -> 474.38597 | I19: ='Raw Financials'!I75 -> 473.20044 | J19: ='Raw Financials'!J75 -> 331.80044 | ... M19: ='Raw Financials'!M75 -> 356.3 | N19: ='Annual P&L'!N7*Assumptions!C65 -> 349.35527 | O19: ='Annual P&L'!O7*Assumptions!D65 -> 362.76063 | P19: ='Annual P&L'!P7*Assumptions!E65 -> 380.02789 | Q19: ='Annual P&L'!Q7*Assumptions!F65 -> 400.51908
A20: Other tax assets | B20: ₹ cr | C20: ='Raw Financials'!C76 -> 0 | D20: ='Raw Financials'!D76 -> 1313.5218 | E20: ='Raw Financials'!E76 -> 1777.4957 | F20: ='Raw Financials'!F76 -> 2139.7 | G20: ='Raw Financials'!G76 -> 2415.2 | H20: ='Raw Financials'!H76 -> 2028.8 | I20: ='Raw Financials'!I76 -> 2513.7 | J20: ='Raw Financials'!J76 -> 3053.7 | ... M20: ='Raw Financials'!M76 -> 3042.2 | N20: ='Annual P&L'!N7*Assumptions!C63 -> 3085.9715 | O20: ='Annual P&L'!O7*Assumptions!D63 -> 3143.9255 | P20: ='Annual P&L'!P7*Assumptions!E63 -> 3230.2371 | Q20: ='Annual P&L'!Q7*Assumptions!F63 -> 3337.659
A21: Deferred tax assets | B21: ₹ cr | C21: ='Raw Financials'!C77 -> 557.48677 | D21: ='Raw Financials'!D77 -> 267.43874 | E21: ='Raw Financials'!E77 -> 576.55022 | F21: ='Raw Financials'!F77 -> 609.1 | G21: ='Raw Financials'!G77 -> 844.3 | H21: ='Raw Financials'!H77 -> 913.3 | I21: ='Raw Financials'!I77 -> 819.1 | J21: ='Raw Financials'!J77 -> 1296.5 | ... M21: ='Raw Financials'!M77 -> 2186.4 | N21: ='Annual P&L'!N7*Assumptions!C64 -> 2212.5834 | O21: ='Annual P&L'!O7*Assumptions!D64 -> 2237.0239 | P21: ='Annual P&L'!P7*Assumptions!E64 -> 2280.1673 | Q21: ='Annual P&L'!Q7*Assumptions!F64 -> 2336.3613
A22: Other non-current assets | B22: ₹ cr | C22: ='Raw Financials'!C78 -> 29.395768 | D22: ='Raw Financials'!D78 -> 645.85063 | E22: ='Raw Financials'!E78 -> 602.23102 | F22: ='Raw Financials'!F78 -> 553.7 | G22: ='Raw Financials'!G78 -> 1327.3 | H22: ='Raw Financials'!H78 -> 1286.5 | I22: ='Raw Financials'!I78 -> 1197.9 | J22: ='Raw Financials'!J78 -> 1376.5 | ... M22: ='Raw Financials'!M78 -> 1221.9 | N22: ='Annual P&L'!N7*Assumptions!C32 -> 1164.5176 | O22: ='Annual P&L'!O7*Assumptions!D32 -> 1148.742 | P22: ='Annual P&L'!P7*Assumptions!E32 -> 1140.0837 | Q22: ='Annual P&L'!Q7*Assumptions!F32 -> 1134.8041
A23: Total non-current assets | B23: ₹ cr | C23: ='Raw Financials'!C79 -> 8561.8587 | D23: ='Raw Financials'!D79 -> 9739.997 | E23: ='Raw Financials'!E79 -> 12330.249 | F23: ='Raw Financials'!F79 -> 11881.076 | G23: ='Raw Financials'!G79 -> 14181.242 | H23: ='Raw Financials'!H79 -> 14422.697 | I23: ='Raw Financials'!I79 -> 20414.965 | J23: ='Raw Financials'!J79 -> 21720.565 | ... M23: ='Raw Financials'!M79 -> 21794.7 | N23: =SUM(N7:N22) -> 21334.521 | O23: =SUM(O7:O22) -> 20991.324 | P23: =SUM(P7:P22) -> 20749.36 | Q23: =SUM(Q7:Q22) -> 20594.422
A24: Inventories | B24: ₹ cr | C24: ='Raw Financials'!C80 -> 41.439603 | D24: ='Raw Financials'!D80 -> 61.058109 | E24: ='Raw Financials'!E80 -> 65.918365 | F24: ='Raw Financials'!F80 -> 75.2 | G24: ='Raw Financials'!G80 -> 35.8 | H24: ='Raw Financials'!H80 -> 24.2 | I24: ='Raw Financials'!I80 -> 40.5 | J24: ='Raw Financials'!J80 -> 23.6 | ... M24: ='Raw Financials'!M80 -> 104.2 | N24: ='Annual P&L'!N7*Assumptions!C60 -> 104.80658 | O24: ='Annual P&L'!O7*Assumptions!D60 -> 108.82819 | P24: ='Annual P&L'!P7*Assumptions!E60 -> 114.00837 | Q24: ='Annual P&L'!Q7*Assumptions!F60 -> 120.15572
A25: Current investments | B25: ₹ cr | C25: ='Raw Financials'!C81 -> 1168.9612 | D25: ='Raw Financials'!D81 -> 2164.696 | E25: ='Raw Financials'!E81 -> 3444.9413 | F25: ='Raw Financials'!F81 -> 6589.9 | G25: ='Raw Financials'!G81 -> 5612.3 | H25: ='Raw Financials'!H81 -> 9661.9 | I25: ='Raw Financials'!I81 -> 4435.9 | J25: ='Raw Financials'!J81 -> 2783.2 | ... M25: ='Raw Financials'!M81 -> 3335.5 | N25: ='Annual P&L'!N7*Assumptions!C61 -> 3493.5527 | O25: ='Annual P&L'!O7*Assumptions!D61 -> 3627.6063 | P25: ='Annual P&L'!P7*Assumptions!E61 -> 3800.2789 | Q25: ='Annual P&L'!Q7*Assumptions!F61 -> 4005.1908
A26: Billed receivables | B26: ₹ cr | C26: ='Raw Financials'!C82 -> 0 | D26: ='Raw Financials'!D82 -> 0 | E26: ='Raw Financials'!E82 -> 0 | F26: ='Raw Financials'!F82 -> 0 | G26: ='Raw Financials'!G82 -> 0 | H26: ='Raw Financials'!H82 -> 0 | I26: ='Raw Financials'!I82 -> 7467.5552 | J26: ='Raw Financials'!J82 -> 8142.4021 | ... M26: ='Raw Financials'!M82 -> 7536.9 | N26: ='Annual P&L'!N7/365*Assumptions!C27 -> 7816.6247 | O26: ='Annual P&L'!O7/365*Assumptions!D27 -> 7950.9179 | P26: ='Annual P&L'!P7/365*Assumptions!E27 -> 8155.8497 | Q26: ='Annual P&L'!Q7/365*Assumptions!F27 -> 8412.7296
A27: Unbilled receivables | B27: ₹ cr | C27: ='Raw Financials'!C83 -> 0 | D27: ='Raw Financials'!D83 -> 0 | E27: ='Raw Financials'!E83 -> 0 | F27: ='Raw Financials'!F83 -> 0 | G27: ='Raw Financials'!G83 -> 0 | H27: ='Raw Financials'!H83 -> 0 | I27: ='Raw Financials'!I83 -> 4465.8 | J27: ='Raw Financials'!J83 -> 4739.2 | ... M27: ='Raw Financials'!M83 -> 5820.8 | N27: ='Annual P&L'!N7/365*Assumptions!C28 -> 5902.3493 | O27: ='Annual P&L'!O7/365*Assumptions!D28 -> 5963.1885 | P27: ='Annual P&L'!P7/365*Assumptions!E28 -> 6073.5051 | Q27: ='Annual P&L'!Q7/365*Assumptions!F28 -> 6218.1045
A28: Cash and cash equivalents | B28: ₹ cr | C28: ='Raw Financials'!C84 -> 4013.8061 | D28: ='Raw Financials'!D84 -> 2001.2742 | E28: ='Raw Financials'!E84 -> 1966.0827 | F28: ='Raw Financials'!F84 -> 2042.7 | G28: ='Raw Financials'!G84 -> 3016.7 | H28: ='Raw Financials'!H84 -> 2690.4 | I28: ='Raw Financials'!I84 -> 3788.9 | J28: ='Raw Financials'!J84 -> 4056.3 | ... M28: ='Raw Financials'!M84 -> 5046.1 | N28: ='Annual Cash Flow'!N85 -> 6429.2531 | O28: ='Annual Cash Flow'!O85 -> 8088.7452 | P28: ='Annual Cash Flow'!P85 -> 9738.5619 | Q28: ='Annual Cash Flow'!Q85 -> 11488.196
A29: Other bank balances | B29: ₹ cr | C29: ='Raw Financials'!C85 -> 0 | D29: ='Raw Financials'!D85 -> 1217.3489 | E29: ='Raw Financials'!E85 -> 1078.2243 | F29: ='Raw Financials'!F85 -> 316 | G29: ='Raw Financials'!G85 -> 131.6 | H29: ='Raw Financials'!H85 -> 144.8 | I29: ='Raw Financials'!I85 -> 185.6 | J29: ='Raw Financials'!J85 -> 198.4 | ... M29: ='Raw Financials'!M85 -> 59.3 | N29: ='Annual P&L'!N7*Assumptions!C62 -> 58.225878 | O29: ='Annual P&L'!O7*Assumptions!D62 -> 60.460105 | P29: ='Annual P&L'!P7*Assumptions!E62 -> 63.337982 | Q29: ='Annual P&L'!Q7*Assumptions!F62 -> 66.75318
A30: Current loans | B30: ₹ cr | C30: ='Raw Financials'!C86 -> 0 | D30: ='Raw Financials'!D86 -> 428.6 | E30: ='Raw Financials'!E86 -> 150 | F30: ='Raw Financials'!F86 -> 0 | G30: ='Raw Financials'!G86 -> 0 | H30: ='Raw Financials'!H86 -> 0 | I30: ='Raw Financials'!I86 -> 0 | J30: ='Raw Financials'!J86 -> 0 | ... M30: ='Raw Financials'!M86 -> 0 | N30: ='Annual P&L'!N7*Assumptions!C68 -> 0 | O30: ='Annual P&L'!O7*Assumptions!D68 -> 0 | P30: ='Annual P&L'!P7*Assumptions!E68 -> 0 | Q30: ='Annual P&L'!Q7*Assumptions!F68 -> 0
A31: Other current financial assets | B31: ₹ cr | C31: ='Raw Financials'!C87 -> 0 | D31: ='Raw Financials'!D87 -> 2932.1901 | E31: ='Raw Financials'!E87 -> 2941.6708 | F31: ='Raw Financials'!F87 -> 2906.391 | G31: ='Raw Financials'!G87 -> 3735.5 | H31: ='Raw Financials'!H87 -> 3328.1 | I31: ='Raw Financials'!I87 -> 675 | J31: ='Raw Financials'!J87 -> 499.9 | ... M31: ='Raw Financials'!M87 -> 447.6 | N31: ='Annual P&L'!N7*Assumptions!C29 -> 465.80702 | O31: ='Annual P&L'!O7*Assumptions!D29 -> 483.68084 | P31: ='Annual P&L'!P7*Assumptions!E29 -> 506.70385 | Q31: ='Annual P&L'!Q7*Assumptions!F29 -> 534.02544
A32: Other current assets | B32: ₹ cr | C32: ='Raw Financials'!C88 -> 2241.9937 | D32: ='Raw Financials'!D88 -> 2157.1144 | E32: ='Raw Financials'!E88 -> 1962.2996 | F32: ='Raw Financials'!F88 -> 2677 | G32: ='Raw Financials'!G88 -> 3063.2 | H32: ='Raw Financials'!H88 -> 2933.1 | I32: ='Raw Financials'!I88 -> 3396.4 | J32: ='Raw Financials'!J88 -> 3989.7 | ... M32: ='Raw Financials'!M88 -> 5224.3 | N32: ='Annual P&L'!N7*Assumptions!C30 -> 5356.7808 | O32: ='Annual P&L'!O7*Assumptions!D30 -> 5441.4095 | P32: ='Annual P&L'!P7*Assumptions!E30 -> 5573.7424 | Q32: ='Annual P&L'!Q7*Assumptions!F30 -> 5740.7735
A33: Assets held for sale | B33: ₹ cr | C33: ='Raw Financials'!C89 -> 0 | D33: ='Raw Financials'!D89 -> 26.5 | E33: ='Raw Financials'!E89 -> 0 | F33: ='Raw Financials'!F89 -> 0 | G33: ='Raw Financials'!G89 -> 0 | H33: ='Raw Financials'!H89 -> 0 | I33: ='Raw Financials'!I89 -> 0 | J33: ='Raw Financials'!J89 -> 0 | ... M33: ='Raw Financials'!M89 -> 0 | N33: =0 -> 0 | O33: =0 -> 0 | P33: =0 -> 0 | Q33: =0 -> 0
A34: Total current assets | B34: ₹ cr | C34: ='Raw Financials'!C90 -> 14945.134 | D34: ='Raw Financials'!D90 -> 16326.5 | E34: ='Raw Financials'!E90 -> 18106.996 | F34: ='Raw Financials'!F90 -> 21565.766 | G34: ='Raw Financials'!G90 -> 23172.268 | H34: ='Raw Financials'!H90 -> 25255.317 | I34: ='Raw Financials'!I90 -> 24455.655 | J34: ='Raw Financials'!J90 -> 24432.702 | ... M34: ='Raw Financials'!M90 -> 27574.7 | N34: =SUM(N24:N33) -> 29627.4 | O34: =SUM(O24:O33) -> 31724.837 | P34: =SUM(P24:P33) -> 34025.988 | Q34: =SUM(Q24:Q33) -> 36585.928
A35: Total assets | B35: ₹ cr | C35: ='Raw Financials'!C91 -> 23507.013 | D35: ='Raw Financials'!D91 -> 26066.5 | E35: ='Raw Financials'!E91 -> 30437.182 | F35: ='Raw Financials'!F91 -> 33446.851 | G35: ='Raw Financials'!G91 -> 37353.51 | H35: ='Raw Financials'!H91 -> 39678.014 | I35: ='Raw Financials'!I91 -> 44870.72 | J35: ='Raw Financials'!J91 -> 46153.267 | ... M35: ='Raw Financials'!M91 -> 49369.4 | N35: =SUM(N23,N34) -> 50961.921 | O35: =SUM(O23,O34) -> 52716.161 | P35: =SUM(P23,P34) -> 54775.348 | Q35: =SUM(Q23,Q34) -> 57180.35
A36: Share capital | B36: ₹ cr | C36: ='Raw Financials'!C92 -> 483.90502 | D36: ='Raw Financials'!D92 -> 438.79965 | E36: ='Raw Financials'!E92 -> 441.68731 | F36: ='Raw Financials'!F92 -> 443.73457 | G36: ='Raw Financials'!G92 -> 435.87387 | H36: ='Raw Financials'!H92 -> 436.98959 | I36: ='Raw Financials'!I92 -> 438.8064 | J36: ='Raw Financials'!J92 -> 440 | ... M36: ='Raw Financials'!M92 -> 442.8 | N36: =M36 -> 442.8 | O36: =N36 -> 442.8 | P36: =O36 -> 442.8 | Q36: =P36 -> 442.8
A37: Other equity | B37: ₹ cr | C37: ='Raw Financials'!C93 -> 13882.449 | D37: ='Raw Financials'!D93 -> 15998.419 | E37: ='Raw Financials'!E93 -> 18401.131 | F37: ='Raw Financials'!F93 -> 19840.7 | G37: ='Raw Financials'!G93 -> 21377.2 | H37: ='Raw Financials'!H93 -> 24428 | I37: ='Raw Financials'!I93 -> 26446.9 | J37: ='Raw Financials'!J93 -> 27484.5 | ... M37: ='Raw Financials'!M93 -> 29172.6 | N37: ='BS Forecast Schedules'!D46 -> 30477.735 | O37: ='BS Forecast Schedules'!E46 -> 31905.55 | P37: ='BS Forecast Schedules'!F46 -> 33481.77 | Q37: ='BS Forecast Schedules'!G46 -> 35217.064
A38: Equity attributable to owners | B38: ₹ cr | C38: ='Raw Financials'!C94 -> 14366.349 | D38: ='Raw Financials'!D94 -> 16437.218 | E38: ='Raw Financials'!E94 -> 18842.819 | F38: ='Raw Financials'!F94 -> 20284.435 | G38: ='Raw Financials'!G94 -> 21813.074 | H38: ='Raw Financials'!H94 -> 24864.99 | I38: ='Raw Financials'!I94 -> 26885.706 | J38: ='Raw Financials'!J94 -> 27924.5 | ... M38: ='Raw Financials'!M94 -> 29615.4 | N38: =SUM(N36:N37) -> 30920.535 | O38: =SUM(O36:O37) -> 32348.35 | P38: =SUM(P36:P37) -> 33924.57 | Q38: =SUM(Q36:Q37) -> 35659.864
A39: NCI | B39: ₹ cr | C39: ='Raw Financials'!C95 -> 201.95269 | D39: ='Raw Financials'!D95 -> 464.12046 | E39: ='Raw Financials'!E95 -> 509.1 | F39: ='Raw Financials'!F95 -> 477.7 | G39: ='Raw Financials'!G95 -> 393.3 | H39: ='Raw Financials'!H95 -> 379.5 | I39: ='Raw Financials'!I95 -> 495.4 | J39: ='Raw Financials'!J95 -> 470.2 | ... M39: ='Raw Financials'!M95 -> 461.6 | N39: =M39 -> 461.6 | O39: =N39 -> 461.6 | P39: =O39 -> 461.6 | Q39: =P39 -> 461.6
A40: Total equity | B40: ₹ cr | C40: ='Raw Financials'!C96 -> 14569.659 | D40: ='Raw Financials'!D96 -> 16901.339 | E40: ='Raw Financials'!E96 -> 19351.919 | F40: ='Raw Financials'!F96 -> 20762.135 | G40: ='Raw Financials'!G96 -> 22206.374 | H40: ='Raw Financials'!H96 -> 25244.49 | I40: ='Raw Financials'!I96 -> 27381.106 | J40: ='Raw Financials'!J96 -> 28394.7 | ... M40: ='Raw Financials'!M96 -> 30077 | N40: =SUM(N38:N39) -> 31382.135 | O40: =SUM(O38:O39) -> 32809.95 | P40: =SUM(P38:P39) -> 34386.17 | Q40: =SUM(Q38:Q39) -> 36121.464
A41: Long-term borrowings | B41: ₹ cr | C41: ='Raw Financials'!C97 -> 196.69738 | D41: ='Raw Financials'!D97 -> 385.25875 | E41: ='Raw Financials'!E97 -> 771.09718 | F41: ='Raw Financials'!F97 -> 208.6 | G41: ='Raw Financials'!G97 -> 178.7 | H41: ='Raw Financials'!H97 -> 165.8 | I41: ='Raw Financials'!I97 -> 142 | J41: ='Raw Financials'!J97 -> 128.8 | ... M41: ='Raw Financials'!M97 -> 0 | N41: ='BS Forecast Schedules'!D38 -> 59.16 | O41: ='BS Forecast Schedules'!E38 -> 59.16 | P41: ='BS Forecast Schedules'!F38 -> 59.16 | Q41: ='BS Forecast Schedules'!G38 -> 59.16
A42: Non-current lease liabilities | B42: ₹ cr | C42: ='Raw Financials'!C98 -> 0 | D42: ='Raw Financials'!D98 -> 0 | E42: ='Raw Financials'!E98 -> 0 | F42: ='Raw Financials'!F98 -> 0 | G42: ='Raw Financials'!G98 -> 853.9 | H42: ='Raw Financials'!H98 -> 807.7 | I42: ='Raw Financials'!I98 -> 720 | J42: ='Raw Financials'!J98 -> 790.3 | ... M42: ='Raw Financials'!M98 -> 1588.8 | N42: ='BS Forecast Schedules'!D31 -> 1635.2479 | O42: ='BS Forecast Schedules'!E31 -> 1688.8145 | P42: ='BS Forecast Schedules'!F31 -> 1752.212 | Q42: ='BS Forecast Schedules'!G31 -> 1827.327
A43: Non-current trade payables | B43: ₹ cr | C43: ='Raw Financials'!C99 -> 0 | D43: ='Raw Financials'!D99 -> 0 | E43: ='Raw Financials'!E99 -> 0 | F43: ='Raw Financials'!F99 -> 0 | G43: ='Raw Financials'!G99 -> 0 | H43: ='Raw Financials'!H99 -> 0 | I43: ='Raw Financials'!I99 -> 0 | J43: ='Raw Financials'!J99 -> 0 | ... M43: ='Raw Financials'!M99 -> 0 | N43: =M43 -> 0 | O43: =N43 -> 0 | P43: =O43 -> 0 | Q43: =P43 -> 0
A44: Other non-current financial liabilities | B44: ₹ cr | C44: ='Raw Financials'!C100 -> 0 | D44: ='Raw Financials'!D100 -> 496.49814 | E44: ='Raw Financials'!E100 -> 572.91769 | F44: ='Raw Financials'!F100 -> 300.9 | G44: ='Raw Financials'!G100 -> 1232.3 | H44: ='Raw Financials'!H100 -> 922.5 | I44: ='Raw Financials'!I100 -> 1478 | J44: ='Raw Financials'!J100 -> 1008.3 | ... M44: ='Raw Financials'!M100 -> 54.8 | N44: ='Annual P&L'!N7*Assumptions!C69 -> 58.225878 | O44: ='Annual P&L'!O7*Assumptions!D69 -> 60.460105 | P44: ='Annual P&L'!P7*Assumptions!E69 -> 63.337982 | Q44: ='Annual P&L'!Q7*Assumptions!F69 -> 66.75318
A45: Non-current provisions | B45: ₹ cr | C45: ='Raw Financials'!C101 -> 531.05075 | D45: ='Raw Financials'!D101 -> 620.08084 | E45: ='Raw Financials'!E101 -> 555.13776 | F45: ='Raw Financials'!F101 -> 580.1 | G45: ='Raw Financials'!G101 -> 669.1 | H45: ='Raw Financials'!H101 -> 781.03016 | I45: ='Raw Financials'!I101 -> 881.1 | J45: ='Raw Financials'!J101 -> 928.8 | ... M45: ='Raw Financials'!M101 -> 1715.9 | N45: ='Annual P&L'!N7*Assumptions!C66 -> 1746.7763 | O45: ='Annual P&L'!O7*Assumptions!D66 -> 1753.343 | P45: ='Annual P&L'!P7*Assumptions!E66 -> 1773.4635 | Q45: ='Annual P&L'!Q7*Assumptions!F66 -> 1802.3359
A46: Deferred tax liabilities | B46: ₹ cr | C46: ='Raw Financials'!C102 -> 0 | D46: ='Raw Financials'!D102 -> 9.5296524 | E46: ='Raw Financials'!E102 -> 5.8087075 | F46: ='Raw Financials'!F102 -> 1.1 | G46: ='Raw Financials'!G102 -> 35.6 | H46: ='Raw Financials'!H102 -> 76.1 | I46: ='Raw Financials'!I102 -> 455.2 | J46: ='Raw Financials'!J102 -> 326.1 | ... M46: ='Raw Financials'!M102 -> 201.7 | N46: ='Annual P&L'!N7*Assumptions!C67 -> 203.79057 | O46: ='Annual P&L'!O7*Assumptions!D67 -> 211.61037 | P46: ='Annual P&L'!P7*Assumptions!E67 -> 221.68294 | Q46: ='Annual P&L'!Q7*Assumptions!F67 -> 233.63613
A47: Other non-current liabilities | B47: ₹ cr | C47: ='Raw Financials'!C103 -> 23.133231 | D47: ='Raw Financials'!D103 -> 30.507533 | E47: ='Raw Financials'!E103 -> 33.334566 | F47: ='Raw Financials'!F103 -> 32.5 | G47: ='Raw Financials'!G103 -> 21.4 | H47: ='Raw Financials'!H103 -> 172.46984 | I47: ='Raw Financials'!I103 -> 78.1 | J47: ='Raw Financials'!J103 -> 24.9 | ... M47: ='Raw Financials'!M103 -> 3.3 | N47: ='Annual P&L'!N7*Assumptions!C34 -> 58.225878 | O47: ='Annual P&L'!O7*Assumptions!D34 -> 60.460105 | P47: ='Annual P&L'!P7*Assumptions!E34 -> 63.337982 | Q47: ='Annual P&L'!Q7*Assumptions!F34 -> 66.75318
A48: Total non-current liabilities | B48: ₹ cr | C48: ='Raw Financials'!C104 -> 750.88136 | D48: ='Raw Financials'!D104 -> 1541.8749 | E48: ='Raw Financials'!E104 -> 1938.2129 | F48: ='Raw Financials'!F104 -> 1123.2 | G48: ='Raw Financials'!G104 -> 2991 | H48: ='Raw Financials'!H104 -> 2925.6 | I48: ='Raw Financials'!I104 -> 3754.4 | J48: ='Raw Financials'!J104 -> 3207.2 | ... M48: ='Raw Financials'!M104 -> 3564.5 | N48: =SUM(N41:N47) -> 3761.4266 | O48: =SUM(O41:O47) -> 3833.8481 | P48: =SUM(P41:P47) -> 3933.1944 | Q48: =SUM(Q41:Q47) -> 4055.9654
A49: Short-term borrowings | B49: ₹ cr | C49: ='Raw Financials'!C105 -> 805.5042 | D49: ='Raw Financials'!D105 -> 834.17692 | E49: ='Raw Financials'!E105 -> 954.8559 | F49: ='Raw Financials'!F105 -> 1196.1 | G49: ='Raw Financials'!G105 -> 2249.5 | H49: ='Raw Financials'!H105 -> 1496 | I49: ='Raw Financials'!I105 -> 1439.7361 | J49: ='Raw Financials'!J105 -> 1449.4 | ... M49: ='Raw Financials'!M105 -> 69.6 | N49: ='BS Forecast Schedules'!D37 -> 10.44 | O49: ='BS Forecast Schedules'!E37 -> 10.44 | P49: ='BS Forecast Schedules'!F37 -> 10.44 | Q49: ='BS Forecast Schedules'!G37 -> 10.44
A50: Current lease liabilities | B50: ₹ cr | C50: ='Raw Financials'!C106 -> 0 | D50: ='Raw Financials'!D106 -> 0 | E50: ='Raw Financials'!E106 -> 0 | F50: ='Raw Financials'!F106 -> 0 | G50: ='Raw Financials'!G106 -> 345.9 | H50: ='Raw Financials'!H106 -> 400.3 | I50: ='Raw Financials'!I106 -> 316.7 | J50: ='Raw Financials'!J106 -> 371.7 | ... M50: ='Raw Financials'!M106 -> 527.8 | N50: ='BS Forecast Schedules'!D30 -> 545.08263 | O50: ='BS Forecast Schedules'!E30 -> 562.93816 | P50: ='BS Forecast Schedules'!F30 -> 584.07066 | Q50: ='BS Forecast Schedules'!G30 -> 609.109
A51: Trade payables | B51: ₹ cr | C51: ='Raw Financials'!C107 -> 2275.6957 | D51: ='Raw Financials'!D107 -> 2311.6995 | E51: ='Raw Financials'!E107 -> 2036.8357 | F51: ='Raw Financials'!F107 -> 2489.3 | G51: ='Raw Financials'!G107 -> 3256.6 | H51: ='Raw Financials'!H107 -> 2785 | I51: ='Raw Financials'!I107 -> 4094.7 | J51: ='Raw Financials'!J107 -> 4384.6 | ... M51: ='Raw Financials'!M107 -> 5040 | N51: ='Annual P&L'!N7*Assumptions!C48 -> 5123.8773 | O51: ='Annual P&L'!O7*Assumptions!D48 -> 5260.0291 | P51: ='Annual P&L'!P7*Assumptions!E48 -> 5447.0664 | Q51: ='Annual P&L'!Q7*Assumptions!F48 -> 5674.0203
A52: Other current financial liabilities | B52: ₹ cr | C52: ='Raw Financials'!C108 -> 0 | D52: ='Raw Financials'!D108 -> 422.96501 | E52: ='Raw Financials'!E108 -> 1876.8924 | F52: ='Raw Financials'!F108 -> 3472.6 | G52: ='Raw Financials'!G108 -> 1789.8 | H52: ='Raw Financials'!H108 -> 2091 | I52: ='Raw Financials'!I108 -> 3024.4 | J52: ='Raw Financials'!J108 -> 2961.7 | ... M52: ='Raw Financials'!M108 -> 2992.9 | N52: ='Annual P&L'!N7*Assumptions!C51 -> 3027.7457 | O52: ='Annual P&L'!O7*Assumptions!D51 -> 3083.4654 | P52: ='Annual P&L'!P7*Assumptions!E51 -> 3166.8991 | Q52: ='Annual P&L'!Q7*Assumptions!F51 -> 3270.9058
A53: Current provisions | B53: ₹ cr | C53: ='Raw Financials'!C109 -> 2409.2861 | D53: ='Raw Financials'!D109 -> 387.03692 | E53: ='Raw Financials'!E109 -> 403.04641 | F53: ='Raw Financials'!F109 -> 395.2 | G53: ='Raw Financials'!G109 -> 436.4 | H53: ='Raw Financials'!H109 -> 531.1 | I53: ='Raw Financials'!I109 -> 671.6 | J53: ='Raw Financials'!J109 -> 631.3 | ... M53: ='Raw Financials'!M109 -> 1208.6 | N53: ='Annual P&L'!N7*Assumptions!C49 -> 1280.9693 | O53: ='Annual P&L'!O7*Assumptions!D49 -> 1269.6622 | P53: ='Annual P&L'!P7*Assumptions!E49 -> 1266.7596 | Q53: ='Annual P&L'!Q7*Assumptions!F49 -> 1335.0636
A54: Current tax liabilities | B54: ₹ cr | C54: ='Raw Financials'!C110 -> 0 | D54: ='Raw Financials'!D110 -> 824.55693 | E54: ='Raw Financials'!E110 -> 937.87874 | F54: ='Raw Financials'!F110 -> 1017.5 | G54: ='Raw Financials'!G110 -> 1020.5 | H54: ='Raw Financials'!H110 -> 1114.3 | I54: ='Raw Financials'!I110 -> 1044.1 | J54: ='Raw Financials'!J110 -> 1540.5 | ... M54: ='Raw Financials'!M110 -> 2146.7 | N54: ='Annual P&L'!N7*Assumptions!C47 -> 2037.9057 | O54: ='Annual P&L'!O7*Assumptions!D47 -> 2055.6436 | P54: ='Annual P&L'!P7*Assumptions!E47 -> 2090.1534 | Q54: ='Annual P&L'!Q7*Assumptions!F47 -> 2136.1018
A55: Other current liabilities | B55: ₹ cr | C55: ='Raw Financials'!C111 -> 1465.6719 | D55: ='Raw Financials'!D111 -> 1612.4484 | E55: ='Raw Financials'!E111 -> 1707.1954 | F55: ='Raw Financials'!F111 -> 1760.5 | G55: ='Raw Financials'!G111 -> 1827 | H55: ='Raw Financials'!H111 -> 1859.8 | I55: ='Raw Financials'!I111 -> 1913.6 | J55: ='Raw Financials'!J111 -> 1981.8 | ... M55: ='Raw Financials'!M111 -> 2511.9 | N55: ='Annual P&L'!N7*Assumptions!C50 -> 2561.9386 | O55: ='Annual P&L'!O7*Assumptions!D50 -> 2599.7845 | P55: ='Annual P&L'!P7*Assumptions!E50 -> 2660.1952 | Q55: ='Annual P&L'!Q7*Assumptions!F50 -> 2736.8804
A56: Total current liabilities | B56: ₹ cr | C56: ='Raw Financials'!C112 -> 6955.9999 | D56: ='Raw Financials'!D112 -> 6392.8836 | E56: ='Raw Financials'!E112 -> 7916.6635 | F56: ='Raw Financials'!F112 -> 10331.2 | G56: ='Raw Financials'!G112 -> 10925.7 | H56: ='Raw Financials'!H112 -> 10277.5 | I56: ='Raw Financials'!I112 -> 12504.836 | J56: ='Raw Financials'!J112 -> 13321 | ... M56: ='Raw Financials'!M112 -> 14497.5 | N56: =SUM(N49:N55) -> 14587.959 | O56: =SUM(O49:O55) -> 14841.963 | P56: =SUM(P49:P55) -> 15225.584 | Q56: =SUM(Q49:Q55) -> 15772.521
A57: Suspense account | B57: ₹ cr | C57: ='Raw Financials'!C113 -> 1230.4 | D57: ='Raw Financials'!D113 -> 1230.4 | E57: ='Raw Financials'!E113 -> 1230.4 | F57: ='Raw Financials'!F113 -> 1230.4 | G57: ='Raw Financials'!G113 -> 1230.4 | H57: ='Raw Financials'!H113 -> 1230.4 | I57: ='Raw Financials'!I113 -> 1230.4 | J57: ='Raw Financials'!J113 -> 1230.4 | ... M57: ='Raw Financials'!M113 -> 1230.4 | N57: =M57 -> 1230.4 | O57: =N57 -> 1230.4 | P57: =O57 -> 1230.4 | Q57: =P57 -> 1230.4
A58: Total liabilities & equity | B58: ₹ cr | C58: ='Raw Financials'!C114 -> 23506.955 | D58: ='Raw Financials'!D114 -> 26066.497 | E58: ='Raw Financials'!E114 -> 30437.227 | F58: ='Raw Financials'!F114 -> 33446.935 | G58: ='Raw Financials'!G114 -> 37353.474 | H58: ='Raw Financials'!H114 -> 39677.99 | I58: ='Raw Financials'!I114 -> 44870.742 | J58: ='Raw Financials'!J114 -> 46153.3 | ... M58: ='Raw Financials'!M114 -> 49369.4 | N58: =SUM(N40,N48,N56,N57) -> 50961.921 | O58: =SUM(O40,O48,O56,O57) -> 52716.161 | P58: =SUM(P40,P48,P56,P57) -> 54775.348 | Q58: =SUM(Q40,Q48,Q56,Q57) -> 57180.35
A59: Balance check | B59: ₹ cr | C59: =ROUND(C35-C58,1) -> 0.1 | D59: =ROUND(D35-D58,1) -> 0 | E59: =ROUND(E35-E58,1) -> 0 | F59: =ROUND(F35-F58,1) -> -0.1 | G59: =ROUND(G35-G58,1) -> 0 | H59: =ROUND(H35-H58,1) -> 0 | I59: =ROUND(I35-I58,1) -> 0 | J59: =ROUND(J35-J58,1) -> 0 | ... Q59: =ROUND(Q35-Q58,1) -> 0
A60: Total borrowings | B60: ₹ cr | C60: =SUM(C41,C49) -> 1002.2016 | D60: =SUM(D41,D49) -> 1219.4357 | E60: =SUM(E41,E49) -> 1725.9531 | F60: =SUM(F41,F49) -> 1404.7 | G60: =SUM(G41,G49) -> 2428.2 | H60: =SUM(H41,H49) -> 1661.8 | I60: =SUM(I41,I49) -> 1581.7361 | J60: =SUM(J41,J49) -> 1578.2 | ... Q60: =SUM(Q41,Q49) -> 69.6
A61: Total lease liabilities | B61: ₹ cr | C61: =SUM(C42,C50) -> 0 | D61: =SUM(D42,D50) -> 0 | E61: =SUM(E42,E50) -> 0 | F61: =SUM(F42,F50) -> 0 | G61: =SUM(G42,G50) -> 1199.8 | H61: =SUM(H42,H50) -> 1208 | I61: =SUM(I42,I50) -> 1036.7 | J61: =SUM(J42,J50) -> 1162 | ... Q61: =SUM(Q42,Q50) -> 2436.436
A62: Cash + investments | B62: ₹ cr | C62: =SUM(C15,C25,C28:C29) -> 6507.1237 | D62: =SUM(D15,D25,D28:D29) -> 5614.1408 | E62: =SUM(E15,E25,E28:E29) -> 7735.0749 | F62: =SUM(F15,F25,F28:F29) -> 9664.4913 | G62: =SUM(G15,G25,G28:G29) -> 8976.8873 | H62: =SUM(H15,H25,H28:H29) -> 13044.901 | I62: =SUM(I15,I25,I28:I29) -> 8661.3736 | J62: =SUM(J15,J25,J28:J29) -> 7469.912 | ... Q62: =SUM(Q15,Q25,Q28:Q29) -> 15595.34
A63: Net cash / (debt) | B63: ₹ cr | C63: =C62-C60-C61 -> 5504.9222 | D63: =D62-D60-D61 -> 4394.7052 | E63: =E62-E60-E61 -> 6009.1218 | F63: =F62-F60-F61 -> 8259.7913 | G63: =G62-G60-G61 -> 5348.8873 | H63: =H62-H60-H61 -> 10175.101 | I63: =I62-I60-I61 -> 6042.9375 | J63: =J62-J60-J61 -> 4729.712 | ... Q63: =Q62-Q60-Q61 -> 13089.304

Sheet Annual Cash Flow
A1: Annual Cash Flow Statement
A2: Reported historical line items are preserved; FY27E–FY30E cash flow is derived from explicit balance changes with no cash or investment plug
A5: Metric | B5: Units | C5: FY16A | D5: FY17A | E5: FY18A | F5: FY19A | G5: FY20A | H5: FY21A | I5: FY22A | J5: FY23A | K5: FY24A | L5: FY25A | M5: FY26A | N5: FY27E | O5: FY28E | P5: FY29E | Q5: FY30E
A7: Profit before tax | B7: ₹ cr | C7: ='Raw Financials'!C120 -> 4016.9 | D7: ='Raw Financials'!D120 -> 3853.0146 | E7: ='Raw Financials'!E120 -> 4878.8437 | F7: ='Raw Financials'!F120 -> 5543.2346 | G7: ='Raw Financials'!G120 -> 5057.779 | H7: ='Raw Financials'!H120 -> 5952.91 | I7: ='Raw Financials'!I120 -> 7452.076 | J7: ='Raw Financials'!J120 -> 6445.464 | ... M7: ='Raw Financials'!M120 -> 6573.1 | N7: ='Annual P&L'!N29 -> 8009.9942 | O7: ='Annual P&L'!O29 -> 8771.1046 | P7: ='Annual P&L'!P29 -> 9728.4836 | Q7: ='Annual P&L'!Q29 -> 10750.255
A8: D&A | B8: ₹ cr | C8: ='Raw Financials'!C121 -> 762 | D8: ='Raw Financials'!D121 -> 978.0552 | E8: ='Raw Financials'!E121 -> 1084.978 | F8: ='Raw Financials'!F121 -> 1129.2 | G8: ='Raw Financials'!G121 -> 1445.8 | H8: ='Raw Financials'!H121 -> 1457.7 | I8: ='Raw Financials'!I121 -> 1520.4 | J8: ='Raw Financials'!J121 -> 1956.7 | ... M8: ='Raw Financials'!M121 -> 1881.6 | N8: ='Annual P&L'!N19 -> 1921.454 | O8: ='Annual P&L'!O19 -> 1934.7234 | P8: ='Annual P&L'!P19 -> 1963.4774 | Q8: ='Annual P&L'!Q19 -> 2002.5954
A9: Amortization of deferred revenue | B9: ₹ cr | C9: ='Raw Financials'!C122 -> 0 | D9: ='Raw Financials'!D122 -> 0 | E9: ='Raw Financials'!E122 -> 0 | F9: ='Raw Financials'!F122 -> 0 | G9: ='Raw Financials'!G122 -> 0 | H9: ='Raw Financials'!H122 -> 0 | I9: ='Raw Financials'!I122 -> 0 | J9: ='Raw Financials'!J122 -> 0 | ... M9: ='Raw Financials'!M122 -> 0 | N9: =0 -> 0 | O9: =0 -> 0 | P9: =0 -> 0 | Q9: =0 -> 0
A10: Bad debts / allowance | B10: ₹ cr | C10: ='Raw Financials'!C123 -> 149.7 | D10: ='Raw Financials'!D123 -> 151.75129 | E10: ='Raw Financials'!E123 -> 161.79424 | F10: ='Raw Financials'!F123 -> 345.2 | G10: ='Raw Financials'!G123 -> 148.4 | H10: ='Raw Financials'!H123 -> 260.5 | I10: ='Raw Financials'!I123 -> 38.8 | J10: ='Raw Financials'!J123 -> 309.6 | ... M10: ='Raw Financials'!M123 -> 111 | N10: =0 -> 0 | O10: =0 -> 0 | P10: =0 -> 0 | Q10: =0 -> 0
A11: Claims & warranties | B11: ₹ cr | C11: ='Raw Financials'!C125 -> 28.4 | D11: ='Raw Financials'!D125 -> 44.287335 | E11: ='Raw Financials'!E125 -> 0 | F11: ='Raw Financials'!F125 -> 0 | G11: ='Raw Financials'!G125 -> 0 | H11: ='Raw Financials'!H125 -> 0 | I11: ='Raw Financials'!I125 -> 0 | J11: ='Raw Financials'!J125 -> 0 | ... M11: ='Raw Financials'!M125 -> 0 | N11: =0 -> 0 | O11: =0 -> 0 | P11: =0 -> 0 | Q11: =0 -> 0
A12: Associate adjustment | B12: ₹ cr | C12: ='Raw Financials'!C126 -> 0 | D12: ='Raw Financials'!D126 -> 2.3315043 | E12: ='Raw Financials'!E126 -> -0.0799921 | F12: ='Raw Financials'!F126 -> 65.5 | G12: ='Raw Financials'!G126 -> 5.5 | H12: ='Raw Financials'!H126 -> -1.2 | I12: ='Raw Financials'!I126 -> -2.8 | J12: ='Raw Financials'!J126 -> 29 | ... M12: ='Raw Financials'!M126 -> 1.5 | N12: =0 -> 0 | O12: =0 -> 0 | P12: =0 -> 0 | Q12: =0 -> 0
A13: Gain on disposal of PPE | B13: ₹ cr | C13: ='Raw Financials'!C127 -> -10.9 | D13: ='Raw Financials'!D127 -> -3.611997 | E13: ='Raw Financials'!E127 -> -156.35754 | F13: ='Raw Financials'!F127 -> -15.4 | G13: ='Raw Financials'!G127 -> -8 | H13: ='Raw Financials'!H127 -> -1.4 | I13: ='Raw Financials'!I127 -> -6.3 | J13: ='Raw Financials'!J127 -> -4.2 | ... M13: ='Raw Financials'!M127 -> -7.6 | N13: =0 -> 0 | O13: =0 -> 0 | P13: =0 -> 0 | Q13: =0 -> 0
A14: Finance costs | B14: ₹ cr | C14: ='Raw Financials'!C128 -> 96.1 | D14: ='Raw Financials'!D128 -> 128.59243 | E14: ='Raw Financials'!E128 -> 162.38095 | F14: ='Raw Financials'!F128 -> 133.2 | G14: ='Raw Financials'!G128 -> 191.9 | H14: ='Raw Financials'!H128 -> 174 | I14: ='Raw Financials'!I128 -> 162.6 | J14: ='Raw Financials'!J128 -> 325.6 | ... M14: ='Raw Financials'!M128 -> 337.4 | N14: ='Annual P&L'!N25 -> 4.176 | O14: ='Annual P&L'!O25 -> 4.176 | P14: ='Annual P&L'!P25 -> 4.176 | Q14: ='Annual P&L'!Q25 -> 4.176
A15: Onerous contracts | B15: ₹ cr | C15: ='Raw Financials'!C129 -> 0 | D15: ='Raw Financials'!D129 -> 0 | E15: ='Raw Financials'!E129 -> 0 | F15: ='Raw Financials'!F129 -> 0 | G15: ='Raw Financials'!G129 -> 0 | H15: ='Raw Financials'!H129 -> 0 | I15: ='Raw Financials'!I129 -> 0 | J15: ='Raw Financials'!J129 -> 0 | ... M15: ='Raw Financials'!M129 -> 0 | N15: =0 -> 0 | O15: =0 -> 0 | P15: =0 -> 0 | Q15: =0 -> 0
A16: Unrealized FX | B16: ₹ cr | C16: ='Raw Financials'!C130 -> 28.647735 | D16: ='Raw Financials'!D130 -> -382.15414 | E16: ='Raw Financials'!E130 -> -11.862613 | F16: ='Raw Financials'!F130 -> 276.2 | G16: ='Raw Financials'!G130 -> -77.6 | H16: ='Raw Financials'!H130 -> 243.1 | I16: ='Raw Financials'!I130 -> -81.5 | J16: ='Raw Financials'!J130 -> 326.6 | ... M16: ='Raw Financials'!M130 -> 617.1 | N16: =0 -> 0 | O16: =0 -> 0 | P16: =0 -> 0 | Q16: =0 -> 0
A17: Share-based payments | B17: ₹ cr | C17: ='Raw Financials'!C131 -> 160.8 | D17: ='Raw Financials'!D131 -> 134.57978 | E17: ='Raw Financials'!E131 -> 88.700549 | F17: ='Raw Financials'!F131 -> 126.3 | G17: ='Raw Financials'!G131 -> 138.5 | H17: ='Raw Financials'!H131 -> 133 | I17: ='Raw Financials'!I131 -> 90.5 | J17: ='Raw Financials'!J131 -> 86.1 | ... M17: ='Raw Financials'!M131 -> 96.3 | N17: ='Annual P&L'!N7*Assumptions!C52 -> 116.45176 | O17: ='Annual P&L'!O7*Assumptions!D52 -> 120.92021 | P17: ='Annual P&L'!P7*Assumptions!E52 -> 126.67596 | Q17: ='Annual P&L'!Q7*Assumptions!F52 -> 133.50636
A18: Provision / sundry writebacks | B18: ₹ cr | C18: =SUM('Raw Financials'!C132,'Raw Financials'!C133) -> -56.2 | D18: =SUM('Raw Financials'!D132,'Raw Financials'!D133) -> -94.954499 | E18: =SUM('Raw Financials'!E132,'Raw Financials'!E133) -> 0 | F18: =SUM('Raw Financials'!F132,'Raw Financials'!F133) -> 0 | G18: =SUM('Raw Financials'!G132,'Raw Financials'!G133) -> 0 | H18: =SUM('Raw Financials'!H132,'Raw Financials'!H133) -> 0 | I18: =SUM('Raw Financials'!I132,'Raw Financials'!I133) -> 0 | J18: =SUM('Raw Financials'!J132,'Raw Financials'!J133) -> 0 | ... M18: =SUM('Raw Financials'!M132,'Raw Financials'!M133) -> 0 | N18: =0 -> 0 | O18: =0 -> 0 | P18: =0 -> 0 | Q18: =0 -> 0
A19: Interest income adjustment | B19: ₹ cr | C19: ='Raw Financials'!C134 -> -94.4 | D19: ='Raw Financials'!D134 -> -124.8448 | E19: ='Raw Financials'!E134 -> -145.50379 | F19: ='Raw Financials'!F134 -> -207.7 | G19: ='Raw Financials'!G134 -> -243.4 | H19: ='Raw Financials'!H134 -> -188.5 | I19: ='Raw Financials'!I134 -> -90.4 | J19: ='Raw Financials'!J134 -> -105 | ... M19: ='Raw Financials'!M134 -> -98 | N19: =-'Annual P&L'!N24 -> -211.9025 | O19: =-'Annual P&L'!O24 -> -250.40579 | P19: =-'Annual P&L'!P24 -> -295.30029 | Q19: =-'Annual P&L'!Q24 -> -340.93447
A20: Rental income adjustment | B20: ₹ cr | C20: ='Raw Financials'!C135 -> -0.4 | D20: ='Raw Financials'!D135 -> -11.541686 | E20: ='Raw Financials'!E135 -> -26.898407 | F20: ='Raw Financials'!F135 -> -29.2 | G20: ='Raw Financials'!G135 -> -39.2 | H20: ='Raw Financials'!H135 -> -40.7 | I20: ='Raw Financials'!I135 -> -41.5 | J20: ='Raw Financials'!J135 -> -30.4 | ... M20: ='Raw Financials'!M135 -> -18.4 | N20: =0 -> 0 | O20: =0 -> 0 | P20: =0 -> 0 | Q20: =0 -> 0
A21: Dividend income adjustment | B21: ₹ cr | C21: ='Raw Financials'!C136 -> -84.8 | D21: ='Raw Financials'!D136 -> -60.329002 | E21: ='Raw Financials'!E136 -> -58.348962 | F21: ='Raw Financials'!F136 -> -24.3 | G21: ='Raw Financials'!G136 -> -34.1 | H21: ='Raw Financials'!H136 -> -0.2 | I21: ='Raw Financials'!I136 -> -9.1 | J21: ='Raw Financials'!J136 -> -2.8 | ... M21: ='Raw Financials'!M136 -> -0.3 | N21: =0 -> 0 | O21: =0 -> 0 | P21: =0 -> 0 | Q21: =0 -> 0
A22: Investment / property gains | B22: ₹ cr | C22: =SUM('Raw Financials'!C137,'Raw Financials'!C138) -> 0 | D22: =SUM('Raw Financials'!D137,'Raw Financials'!D138) -> -0.9070617 | E22: =SUM('Raw Financials'!E137,'Raw Financials'!E138) -> -49.879797 | F22: =SUM('Raw Financials'!F137,'Raw Financials'!F138) -> -87.1 | G22: =SUM('Raw Financials'!G137,'Raw Financials'!G138) -> -206.3 | H22: =SUM('Raw Financials'!H137,'Raw Financials'!H138) -> -159.3 | I22: =SUM('Raw Financials'!I137,'Raw Financials'!I138) -> -258.3 | J22: =SUM('Raw Financials'!J137,'Raw Financials'!J138) -> -105.2 | ... M22: =SUM('Raw Financials'!M137,'Raw Financials'!M138) -> -153.9 | N22: =0 -> 0 | O22: =0 -> 0 | P22: =0 -> 0 | Q22: =0 -> 0
A23: Goodwill / non-current impairment | B23: ₹ cr | C23: =SUM('Raw Financials'!C139,'Raw Financials'!C143) -> 0 | D23: =SUM('Raw Financials'!D139,'Raw Financials'!D143) -> 9.9213954 | E23: =SUM('Raw Financials'!E139,'Raw Financials'!E143) -> 0 | F23: =SUM('Raw Financials'!F139,'Raw Financials'!F143) -> 0 | G23: =SUM('Raw Financials'!G139,'Raw Financials'!G143) -> 217.5 | H23: =SUM('Raw Financials'!H139,'Raw Financials'!H143) -> 50.7 | I23: =SUM('Raw Financials'!I139,'Raw Financials'!I143) -> 0 | J23: =SUM('Raw Financials'!J139,'Raw Financials'!J143) -> 237 | ... M23: =SUM('Raw Financials'!M139,'Raw Financials'!M143) -> 0 | N23: ='Annual P&L'!N22 -> 0 | O23: ='Annual P&L'!O22 -> 0 | P23: ='Annual P&L'!P22 -> 0 | Q23: ='Annual P&L'!Q22 -> 0
A24: Contractual obligation FV | B24: ₹ cr | C24: ='Raw Financials'!C140 -> 0 | D24: ='Raw Financials'!D140 -> 0 | E24: ='Raw Financials'!E140 -> 0 | F24: ='Raw Financials'!F140 -> 44.5 | G24: ='Raw Financials'!G140 -> -55 | H24: ='Raw Financials'!H140 -> 137.3 | I24: ='Raw Financials'!I140 -> 258.8 | J24: ='Raw Financials'!J140 -> -58.3 | ... M24: ='Raw Financials'!M140 -> -30.4 | N24: =0 -> 0 | O24: =0 -> 0 | P24: =0 -> 0 | Q24: =0 -> 0
A25: Gain on sale of subsidiary | B25: ₹ cr | C25: ='Raw Financials'!C141 -> 0 | D25: ='Raw Financials'!D141 -> 0 | E25: ='Raw Financials'!E141 -> 0 | F25: ='Raw Financials'!F141 -> 0 | G25: ='Raw Financials'!G141 -> -148.8 | H25: ='Raw Financials'!H141 -> -73 | I25: ='Raw Financials'!I141 -> 0 | J25: ='Raw Financials'!J141 -> 0 | ... M25: ='Raw Financials'!M141 -> 0 | N25: =0 -> 0 | O25: =0 -> 0 | P25: =0 -> 0 | Q25: =0 -> 0
A26: Investment FV adjustment | B26: ₹ cr | C26: ='Raw Financials'!C142 -> 0 | D26: ='Raw Financials'!D142 -> 0 | E26: ='Raw Financials'!E142 -> 0 | F26: ='Raw Financials'!F142 -> -149 | G26: ='Raw Financials'!G142 -> 0 | H26: ='Raw Financials'!H142 -> 0 | I26: ='Raw Financials'!I142 -> 0 | J26: ='Raw Financials'!J142 -> 0 | ... M26: ='Raw Financials'!M142 -> 0 | N26: =0 -> 0 | O26: =0 -> 0 | P26: =0 -> 0 | Q26: =0 -> 0
A27: Other operating adjustments / reclassification | B27: ₹ cr | C27: =C36-SUM(C7:C26,C28:C35) -> -0.073030353 | D27: =D36-SUM(D7:D26,D28:D35) -> -17.103494 | E27: =E36-SUM(E7:E26,E28:E35) -> -64.564011 | F27: =F36-SUM(F7:F26,F28:F35) -> -0.01 | G27: =G36-SUM(G7:G26,G28:G35) -> -0.00056205171 | H27: =H36-SUM(H7:H26,H28:H35) -> -0.001 | I27: =I36-SUM(I7:I26,I28:I35) -> -0.001 | J27: =J36-SUM(J7:J26,J28:J35) -> -0.003 | ... M27: =M36-SUM(M7:M26,M28:M35) -> 0 | N27: =-SUM('Annual Balance Sheet'!N24-'Annual Balance Sheet'!M24,'Annual Balance Sheet'!N16-'Annual Balance Sheet'!M16,'Annual Balance Sheet'!N17-'Annual Balance Sheet'!M17,'Annual Balance Sheet'!N18-'Annual Balance Sheet'!M18,'Annual Balance Sheet'!N19-'Annual Balance Sheet'!M19,'Annual Balance Sheet'!N20-'Annual Balance Sheet'!M20,'Annual Balance Sheet'!N21-'Annual Balance Sheet'!M21,'Annual Balance Sheet'!N22-'Annual Balance Sheet'!M22)+SUM('Annual Balance Sheet'!N43-'Annual Balance Sheet'!M43,'Annual Balance Sheet'!N44-'Annual Balance Sheet'!M44,'Annual Balance Sheet'!N45-'Annual Balance Sheet'!M45,'Annual Balance Sheet'!N46-'Annual Balance Sheet'!M46,'Annual Balance Sheet'!N47-'Annual Balance Sheet'!M47) -> 85.084362 | O27: =-SUM('Annual Balance Sheet'!O24-'Annual Balance Sheet'!N24,'Annual Balance Sheet'!O16-'Annual Balance Sheet'!N16,'Annual Balance Sheet'!O17-'Annual Balance Sheet'!N17,'Annual Balance Sheet'!O18-'Annual Balance Sheet'!N18,'Annual Balance Sheet'!O19-'Annual Balance Sheet'!N19,'Annual Balance Sheet'!O20-'Annual Balance Sheet'!N20,'Annual Balance Sheet'!O21-'Annual Balance Sheet'!N21,'Annual Balance Sheet'!O22-'Annual Balance Sheet'!N22)+SUM('Annual Balance Sheet'!O43-'Annual Balance Sheet'!N43,'Annual Balance Sheet'!O44-'Annual Balance Sheet'!N44,'Annual Balance Sheet'!O45-'Annual Balance Sheet'!N45,'Annual Balance Sheet'!O46-'Annual Balance Sheet'!N46,'Annual Balance Sheet'!O47-'Annual Balance Sheet'!N47) -> -65.19091 | P27: =-SUM('Annual Balance Sheet'!P24-'Annual Balance Sheet'!O24,'Annual Balance Sheet'!P16-'Annual Balance Sheet'!O16,'Annual Balance Sheet'!P17-'Annual Balance Sheet'!O17,'Annual Balance Sheet'!P18-'Annual Balance Sheet'!O18,'Annual Balance Sheet'!P19-'Annual Balance Sheet'!O19,'Annual Balance Sheet'!P20-'Annual Balance Sheet'!O20,'Annual Balance Sheet'!P21-'Annual Balance Sheet'!O21,'Annual Balance Sheet'!P22-'Annual Balance Sheet'!O22)+SUM('Annual Balance Sheet'!P43-'Annual Balance Sheet'!O43,'Annual Balance Sheet'!P44-'Annual Balance Sheet'!O44,'Annual Balance Sheet'!P45-'Annual Balance Sheet'!O45,'Annual Balance Sheet'!P46-'Annual Balance Sheet'!O46,'Annual Balance Sheet'!P47-'Annual Balance Sheet'!O47) -> -107.29539 | Q27: =-SUM('Annual Balance Sheet'!Q24-'Annual Balance Sheet'!P24,'Annual Balance Sheet'!Q16-'Annual Balance Sheet'!P16,'Annual Balance Sheet'!Q17-'Annual Balance Sheet'!P17,'Annual Balance Sheet'!Q18-'Annual Balance Sheet'!P18,'Annual Balance Sheet'!Q19-'Annual Balance Sheet'!P19,'Annual Balance Sheet'!Q20-'Annual Balance Sheet'!P20,'Annual Balance Sheet'!Q21-'Annual Balance Sheet'!P21,'Annual Balance Sheet'!Q22-'Annual Balance Sheet'!P22)+SUM('Annual Balance Sheet'!Q43-'Annual Balance Sheet'!P43,'Annual Balance Sheet'!Q44-'Annual Balance Sheet'!P44,'Annual Balance Sheet'!Q45-'Annual Balance Sheet'!P45,'Annual Balance Sheet'!Q46-'Annual Balance Sheet'!P46,'Annual Balance Sheet'!Q47-'Annual Balance Sheet'!P47) -> -137.3189
A28: WC: receivables & other assets — legacy | B28: ₹ cr | C28: ='Raw Financials'!C147 -> -857.76545 | D28: ='Raw Financials'!D147 -> -84.082452 | E28: ='Raw Financials'!E147 -> -1044.1963 | F28: ='Raw Financials'!F147 -> -1619 | G28: ='Raw Financials'!G147 -> -2334.9 | H28: ='Raw Financials'!H147 -> 0 | I28: ='Raw Financials'!I147 -> 0 | J28: ='Raw Financials'!J147 -> 0 | ... M28: ='Raw Financials'!M147 -> 0 | N28: =0 -> 0 | O28: =0 -> 0 | P28: =0 -> 0 | Q28: =0 -> 0
A29: WC: payables, liabilities & provisions — legacy | B29: ₹ cr | C29: ='Raw Financials'!C148 -> 378.5721 | D29: ='Raw Financials'!D148 -> 627.8604 | E29: ='Raw Financials'!E148 -> 260.99401 | F29: ='Raw Financials'!F148 -> 561.62398 | G29: ='Raw Financials'!G148 -> 1813.0796 | H29: ='Raw Financials'!H148 -> 0 | I29: ='Raw Financials'!I148 -> 0 | J29: ='Raw Financials'!J148 -> 0 | ... M29: ='Raw Financials'!M148 -> 0 | N29: =0 -> 0 | O29: =0 -> 0 | P29: =0 -> 0 | Q29: =0 -> 0
A30: WC: trade receivables / contract assets | B30: ₹ cr | C30: ='Raw Financials'!C149 -> 0 | D30: ='Raw Financials'!D149 -> 0 | E30: ='Raw Financials'!E149 -> 0 | F30: ='Raw Financials'!F149 -> 0 | G30: ='Raw Financials'!G149 -> 0 | H30: ='Raw Financials'!H149 -> 852.3 | I30: ='Raw Financials'!I149 -> -2895.1 | J30: ='Raw Financials'!J149 -> -1783.6 | ... M30: ='Raw Financials'!M149 -> -1654.9 | N30: =-('Annual Balance Sheet'!N26-'Annual Balance Sheet'!M26) -> -279.72472 | O30: =-('Annual Balance Sheet'!O26-'Annual Balance Sheet'!N26) -> -134.29322 | P30: =-('Annual Balance Sheet'!P26-'Annual Balance Sheet'!O26) -> -204.93175 | Q30: =-('Annual Balance Sheet'!Q26-'Annual Balance Sheet'!P26) -> -256.87989
A31: WC: unbilled revenue / contract assets | B31: ₹ cr | C31: ='Raw Financials'!C150 -> 0 | D31: ='Raw Financials'!D150 -> 0 | E31: ='Raw Financials'!E150 -> 0 | F31: ='Raw Financials'!F150 -> 0 | G31: ='Raw Financials'!G150 -> 0 | H31: ='Raw Financials'!H150 -> 697.2 | I31: ='Raw Financials'!I150 -> 0 | J31: ='Raw Financials'!J150 -> 0 | ... M31: ='Raw Financials'!M150 -> 0 | N31: =-('Annual Balance Sheet'!N27-'Annual Balance Sheet'!M27) -> -81.549277 | O31: =-('Annual Balance Sheet'!O27-'Annual Balance Sheet'!N27) -> -60.839175 | P31: =-('Annual Balance Sheet'!P27-'Annual Balance Sheet'!O27) -> -110.31663 | Q31: =-('Annual Balance Sheet'!Q27-'Annual Balance Sheet'!P27) -> -144.59938
A32: WC: other financial assets / other assets | B32: ₹ cr | C32: ='Raw Financials'!C151 -> 0 | D32: ='Raw Financials'!D151 -> 0 | E32: ='Raw Financials'!E151 -> 0 | F32: ='Raw Financials'!F151 -> 0 | G32: ='Raw Financials'!G151 -> 0 | H32: ='Raw Financials'!H151 -> 96.8 | I32: ='Raw Financials'!I151 -> -467.1 | J32: ='Raw Financials'!J151 -> -373.9 | ... M32: ='Raw Financials'!M151 -> -1287.1 | N32: =-SUM('Annual Balance Sheet'!N30-'Annual Balance Sheet'!M30,'Annual Balance Sheet'!N31-'Annual Balance Sheet'!M31,'Annual Balance Sheet'!N32-'Annual Balance Sheet'!M32,'Annual Balance Sheet'!N33-'Annual Balance Sheet'!M33) -> -150.6878 | O32: =-SUM('Annual Balance Sheet'!O30-'Annual Balance Sheet'!N30,'Annual Balance Sheet'!O31-'Annual Balance Sheet'!N31,'Annual Balance Sheet'!O32-'Annual Balance Sheet'!N32,'Annual Balance Sheet'!O33-'Annual Balance Sheet'!N33) -> -102.5025 | P32: =-SUM('Annual Balance Sheet'!P30-'Annual Balance Sheet'!O30,'Annual Balance Sheet'!P31-'Annual Balance Sheet'!O31,'Annual Balance Sheet'!P32-'Annual Balance Sheet'!O32,'Annual Balance Sheet'!P33-'Annual Balance Sheet'!O33) -> -155.35593 | Q32: =-SUM('Annual Balance Sheet'!Q30-'Annual Balance Sheet'!P30,'Annual Balance Sheet'!Q31-'Annual Balance Sheet'!P31,'Annual Balance Sheet'!Q32-'Annual Balance Sheet'!P32,'Annual Balance Sheet'!Q33-'Annual Balance Sheet'!P33) -> -194.35271
A33: WC: trade payables | B33: ₹ cr | C33: ='Raw Financials'!C152 -> 0 | D33: ='Raw Financials'!D152 -> 0 | E33: ='Raw Financials'!E152 -> 0 | F33: ='Raw Financials'!F152 -> 0 | G33: ='Raw Financials'!G152 -> 0 | H33: ='Raw Financials'!H152 -> -619.464 | I33: ='Raw Financials'!I152 -> 978.498 | J33: ='Raw Financials'!J152 -> 255.199 | ... M33: ='Raw Financials'!M152 -> 516.6 | N33: ='Annual Balance Sheet'!N51-'Annual Balance Sheet'!M51 -> 83.877264 | O33: ='Annual Balance Sheet'!O51-'Annual Balance Sheet'!N51 -> 136.15188 | P33: ='Annual Balance Sheet'!P51-'Annual Balance Sheet'!O51 -> 187.03727 | Q33: ='Annual Balance Sheet'!Q51-'Annual Balance Sheet'!P51 -> 226.95391
A34: WC: deferred revenue | B34: ₹ cr | C34: ='Raw Financials'!C153 -> 0 | D34: ='Raw Financials'!D153 -> 0 | E34: ='Raw Financials'!E153 -> 0 | F34: ='Raw Financials'!F153 -> 0 | G34: ='Raw Financials'!G153 -> 0 | H34: ='Raw Financials'!H153 -> 125.9 | I34: ='Raw Financials'!I153 -> 377.6 | J34: ='Raw Financials'!J153 -> 21.5 | ... M34: ='Raw Financials'!M153 -> 391.1 | N34: =0 -> 0 | O34: =0 -> 0 | P34: =0 -> 0 | Q34: =0 -> 0
A35: WC: other liabilities / provisions | B35: ₹ cr | C35: ='Raw Financials'!C154 -> 0 | D35: ='Raw Financials'!D154 -> 0 | E35: ='Raw Financials'!E154 -> 0 | F35: ='Raw Financials'!F154 -> 0 | G35: ='Raw Financials'!G154 -> 0 | H35: ='Raw Financials'!H154 -> 410.8 | I35: ='Raw Financials'!I154 -> 571.8 | J35: ='Raw Financials'!J154 -> 35.7 | ... M35: ='Raw Financials'!M154 -> 547.1 | N35: =SUM('Annual Balance Sheet'!N52:N55)-SUM('Annual Balance Sheet'!M52:M55) -> 48.459335 | O35: =SUM('Annual Balance Sheet'!O52:O55)-SUM('Annual Balance Sheet'!N52:N55) -> 99.996331 | P35: =SUM('Annual Balance Sheet'!P52:P55)-SUM('Annual Balance Sheet'!O52:O55) -> 175.45167 | Q35: =SUM('Annual Balance Sheet'!Q52:Q55)-SUM('Annual Balance Sheet'!P52:P55) -> 294.94427
A36: Cash generated before tax | B36: ₹ cr | C36: ='Raw Financials'!C155 -> 4516.5814 | D36: ='Raw Financials'!D155 -> 5150.8648 | E36: ='Raw Financials'!E155 -> 5080 | F36: ='Raw Financials'!F155 -> 6093.2486 | G36: ='Raw Financials'!G155 -> 5871.158 | H36: ='Raw Financials'!H155 -> 9508.445 | I36: ='Raw Financials'!I155 -> 7598.973 | J36: ='Raw Financials'!J155 -> 7565.06 | ... M36: ='Raw Financials'!M155 -> 7822.2 | N36: =SUM(N7:N35) -> 9545.6325 | O36: =SUM(O7:O35) -> 10453.841 | P36: =SUM(P7:P35) -> 11312.102 | Q36: =SUM(Q7:Q35) -> 12338.345
A37: Tax paid | B37: ₹ cr | C37: ='Raw Financials'!C156 -> -1303.4 | D37: ='Raw Financials'!D156 -> -1079.5338 | E37: ='Raw Financials'!E156 -> -1526.3518 | F37: ='Raw Financials'!F156 -> -1661.2 | G37: ='Raw Financials'!G156 -> -1513.1 | H37: ='Raw Financials'!H156 -> -1414.6 | I37: ='Raw Financials'!I156 -> -2313.7 | J37: ='Raw Financials'!J156 -> -1993.1 | ... M37: ='Raw Financials'!M156 -> -1650.2 | N37: =-'Annual P&L'!N31 -> -2066.5785 | O37: =-'Annual P&L'!O31 -> -2236.6317 | P37: =-'Annual P&L'!P31 -> -2480.7633 | Q37: =-'Annual P&L'!Q31 -> -2741.3149
A38: Cash flow from operations | B38: ₹ cr | C38: ='Raw Financials'!C157 -> 3213.1963 | D38: ='Raw Financials'!D157 -> 4071.356 | E38: ='Raw Financials'!E157 -> 3553.6 | F38: ='Raw Financials'!F157 -> 4432.0486 | G38: ='Raw Financials'!G157 -> 4358.058 | H38: ='Raw Financials'!H157 -> 8093.841 | I38: ='Raw Financials'!I157 -> 5285.2743 | J38: ='Raw Financials'!J157 -> 5571.964 | ... M38: ='Raw Financials'!M157 -> 6172 | N38: =SUM(N36:N37) -> 7479.0541 | O38: =SUM(O36:O37) -> 8217.2091 | P38: =SUM(P36:P37) -> 8831.3386 | Q38: =SUM(Q36:Q37) -> 9597.0303
A39: CFO / net income | B39: x | C39: =IFERROR(C38/'Annual P&L'!C35,"") -> 1.0736113 | D39: =IFERROR(D38/'Annual P&L'!D35,"") -> 1.4473704 | E39: =IFERROR(E38/'Annual P&L'!E35,"") -> 0.93521819 | F39: =IFERROR(F38/'Annual P&L'!F35,"") -> 1.0312806 | G39: =IFERROR(G38/'Annual P&L'!G35,"") -> 1.0806151 | H39: =IFERROR(H38/'Annual P&L'!H35,"") -> 1.827853 | I39: =IFERROR(I38/'Annual P&L'!I35,"") -> 0.94954492 | J39: =IFERROR(J38/'Annual P&L'!J35,"") -> 1.1533111 | ... Q39: =IFERROR(Q38/'Annual P&L'!Q35,"") -> 1.1982897
A40: Capex | B40: ₹ cr | C40: ='Raw Financials'!C158 -> -926.5 | D40: ='Raw Financials'!D158 -> -768.19169 | E40: ='Raw Financials'!E158 -> -1016.6288 | F40: ='Raw Financials'!F158 -> -804.6 | G40: ='Raw Financials'!G158 -> -844.6 | H40: ='Raw Financials'!H158 -> -666 | I40: ='Raw Financials'!I158 -> -958.4 | J40: ='Raw Financials'!J158 -> -1015.17 | ... M40: ='Raw Financials'!M158 -> -695.7 | N40: =-'BS Forecast Schedules'!D14 -> -756.93641 | O40: =-'BS Forecast Schedules'!E14 -> -785.98137 | P40: =-'BS Forecast Schedules'!F14 -> -823.39376 | Q40: =-'BS Forecast Schedules'!G14 -> -867.79134
A41: Proceeds from PPE sale | B41: ₹ cr | C41: ='Raw Financials'!C159 -> 47.6 | D41: ='Raw Financials'!D159 -> 7.8601217 | E41: ='Raw Financials'!E159 -> 226.36018 | F41: ='Raw Financials'!F159 -> 25.3 | G41: ='Raw Financials'!G159 -> 15.3 | H41: ='Raw Financials'!H159 -> 93.5 | I41: ='Raw Financials'!I159 -> 123.1 | J41: ='Raw Financials'!J159 -> 46 | ... M41: ='Raw Financials'!M159 -> 149.6 | N41: =0 -> 0 | O41: =0 -> 0 | P41: =0 -> 0 | Q41: =0 -> 0
A42: Purchase of investments | B42: ₹ cr | C42: ='Raw Financials'!C160 -> -10093.1 | D42: ='Raw Financials'!D160 -> -15216.483 | E42: ='Raw Financials'!E160 -> -17856.305 | F42: ='Raw Financials'!F160 -> -23427.2 | G42: ='Raw Financials'!G160 -> -33242.7 | H42: ='Raw Financials'!H160 -> -28538.8 | I42: ='Raw Financials'!I160 -> -21963.8 | J42: ='Raw Financials'!J160 -> -21477.6 | ... M42: ='Raw Financials'!M160 -> -25575.6 | N42: =MIN(0,-SUM('Annual Balance Sheet'!N15-'Annual Balance Sheet'!M15,'Annual Balance Sheet'!N25-'Annual Balance Sheet'!M25)) -> -158.05268 | O42: =MIN(0,-SUM('Annual Balance Sheet'!O15-'Annual Balance Sheet'!N15,'Annual Balance Sheet'!O25-'Annual Balance Sheet'!N25)) -> -134.05363 | P42: =MIN(0,-SUM('Annual Balance Sheet'!P15-'Annual Balance Sheet'!O15,'Annual Balance Sheet'!P25-'Annual Balance Sheet'!O25)) -> -172.67259 | Q42: =MIN(0,-SUM('Annual Balance Sheet'!Q15-'Annual Balance Sheet'!P15,'Annual Balance Sheet'!Q25-'Annual Balance Sheet'!P25)) -> -204.91192
A43: Sale / redemption of investments | B43: ₹ cr | C43: ='Raw Financials'!C161 -> 9815.6 | D43: ='Raw Financials'!D161 -> 14304.695 | E43: ='Raw Financials'!E161 -> 15786.247 | F43: ='Raw Financials'!F161 -> 21105.6 | G43: ='Raw Financials'!G161 -> 35089.1 | H43: ='Raw Financials'!H161 -> 24523.4 | I43: ='Raw Financials'!I161 -> 27740.3 | J43: ='Raw Financials'!J161 -> 23074.8 | ... M43: ='Raw Financials'!M161 -> 25490 | N43: =MAX(0,-SUM('Annual Balance Sheet'!N15-'Annual Balance Sheet'!M15,'Annual Balance Sheet'!N25-'Annual Balance Sheet'!M25)) -> 0 | O43: =MAX(0,-SUM('Annual Balance Sheet'!O15-'Annual Balance Sheet'!N15,'Annual Balance Sheet'!O25-'Annual Balance Sheet'!N25)) -> 0 | P43: =MAX(0,-SUM('Annual Balance Sheet'!P15-'Annual Balance Sheet'!O15,'Annual Balance Sheet'!P25-'Annual Balance Sheet'!O25)) -> 0 | Q43: =MAX(0,-SUM('Annual Balance Sheet'!Q15-'Annual Balance Sheet'!P15,'Annual Balance Sheet'!Q25-'Annual Balance Sheet'!P25)) -> 0
A44: Purchase of treasury bonds / debentures | B44: ₹ cr | C44: =SUM('Raw Financials'!C162,'Raw Financials'!C165) -> -0.6096001 | D44: =SUM('Raw Financials'!D162,'Raw Financials'!D165) -> -151.92023 | E44: =SUM('Raw Financials'!E162,'Raw Financials'!E165) -> 0 | F44: =SUM('Raw Financials'!F162,'Raw Financials'!F165) -> 0 | G44: =SUM('Raw Financials'!G162,'Raw Financials'!G165) -> 0 | H44: =SUM('Raw Financials'!H162,'Raw Financials'!H165) -> 0 | I44: =SUM('Raw Financials'!I162,'Raw Financials'!I165) -> 0 | J44: =SUM('Raw Financials'!J162,'Raw Financials'!J165) -> 0 | ... M44: =SUM('Raw Financials'!M162,'Raw Financials'!M165) -> 0 | N44: =0 -> 0 | O44: =0 -> 0 | P44: =0 -> 0 | Q44: =0 -> 0
A45: Maturity / sale of treasury bonds / debentures | B45: ₹ cr | C45: =SUM('Raw Financials'!C163,'Raw Financials'!C167) -> 0.9496031 | D45: =SUM('Raw Financials'!D163,'Raw Financials'!D167) -> 0.76412078 | E45: =SUM('Raw Financials'!E163,'Raw Financials'!E167) -> 0 | F45: =SUM('Raw Financials'!F163,'Raw Financials'!F167) -> 0 | G45: =SUM('Raw Financials'!G163,'Raw Financials'!G167) -> 0 | H45: =SUM('Raw Financials'!H163,'Raw Financials'!H167) -> 0 | I45: =SUM('Raw Financials'!I163,'Raw Financials'!I167) -> 0 | J45: =SUM('Raw Financials'!J163,'Raw Financials'!J167) -> 0 | ... M45: =SUM('Raw Financials'!M163,'Raw Financials'!M167) -> 0 | N45: =0 -> 0 | O45: =0 -> 0 | P45: =0 -> 0 | Q45: =0 -> 0
A46: Dividend received | B46: ₹ cr | C46: ='Raw Financials'!C164 -> 0 | D46: ='Raw Financials'!D164 -> 0 | E46: ='Raw Financials'!E164 -> 0 | F46: ='Raw Financials'!F164 -> 0 | G46: ='Raw Financials'!G164 -> 0 | H46: ='Raw Financials'!H164 -> 0 | I46: ='Raw Financials'!I164 -> 0 | J46: ='Raw Financials'!J164 -> 0 | ... M46: ='Raw Financials'!M164 -> 0.3 | N46: =0 -> 0 | O46: =0 -> 0 | P46: =0 -> 0 | Q46: =0 -> 0
A47: Acquisition of company | B47: ₹ cr | C47: ='Raw Financials'!C166 -> -6.9570649 | D47: ='Raw Financials'!D166 -> 0 | E47: ='Raw Financials'!E166 -> 0 | F47: ='Raw Financials'!F166 -> 0 | G47: ='Raw Financials'!G166 -> 0 | H47: ='Raw Financials'!H166 -> 0 | I47: ='Raw Financials'!I166 -> 0 | J47: ='Raw Financials'!J166 -> 0 | ... M47: ='Raw Financials'!M166 -> 0 | N47: =0 -> 0 | O47: =0 -> 0 | P47: =0 -> 0 | Q47: =0 -> 0
A48: Sale of subsidiary | B48: ₹ cr | C48: ='Raw Financials'!C168 -> 0 | D48: ='Raw Financials'!D168 -> 0 | E48: ='Raw Financials'!E168 -> 25.77596 | F48: ='Raw Financials'!F168 -> 0 | G48: ='Raw Financials'!G168 -> 80.2233 | H48: ='Raw Financials'!H168 -> 0 | I48: ='Raw Financials'!I168 -> 72.5 | J48: ='Raw Financials'!J168 -> 0 | ... M48: ='Raw Financials'!M168 -> 14.2 | N48: =0 -> 0 | O48: =0 -> 0 | P48: =0 -> 0 | Q48: =0 -> 0
A49: Contingent consideration | B49: ₹ cr | C49: ='Raw Financials'!C169 -> 0 | D49: ='Raw Financials'!D169 -> 0 | E49: ='Raw Financials'!E169 -> 0 | F49: ='Raw Financials'!F169 -> 0 | G49: ='Raw Financials'!G169 -> 0 | H49: ='Raw Financials'!H169 -> 0 | I49: ='Raw Financials'!I169 -> 0 | J49: ='Raw Financials'!J169 -> 0 | ... M49: ='Raw Financials'!M169 -> 0 | N49: =0 -> 0 | O49: =0 -> 0 | P49: =0 -> 0 | Q49: =0 -> 0
A50: Investment in associates | B50: ₹ cr | C50: ='Raw Financials'!C170 -> -0.1 | D50: ='Raw Financials'!D170 -> 0 | E50: ='Raw Financials'!E170 -> 0 | F50: ='Raw Financials'!F170 -> 0 | G50: ='Raw Financials'!G170 -> 0 | H50: ='Raw Financials'!H170 -> 0 | I50: ='Raw Financials'!I170 -> 0 | J50: ='Raw Financials'!J170 -> 0 | ... M50: ='Raw Financials'!M170 -> 0 | N50: =MIN(0,-('Annual Balance Sheet'!N14-'Annual Balance Sheet'!M14)) -> 0 | O50: =MIN(0,-('Annual Balance Sheet'!O14-'Annual Balance Sheet'!N14)) -> 0 | P50: =MIN(0,-('Annual Balance Sheet'!P14-'Annual Balance Sheet'!O14)) -> 0 | Q50: =MIN(0,-('Annual Balance Sheet'!Q14-'Annual Balance Sheet'!P14)) -> 0
A51: Repatriation / liquidation | B51: ₹ cr | C51: ='Raw Financials'!C171 -> 0 | D51: ='Raw Financials'!D171 -> 0 | E51: ='Raw Financials'!E171 -> 0 | F51: ='Raw Financials'!F171 -> 0 | G51: ='Raw Financials'!G171 -> 0 | H51: ='Raw Financials'!H171 -> 0 | I51: ='Raw Financials'!I171 -> 0 | J51: ='Raw Financials'!J171 -> 0 | ... M51: ='Raw Financials'!M171 -> 0 | N51: =0 -> 0 | O51: =0 -> 0 | P51: =0 -> 0 | Q51: =0 -> 0
A52: Business acquisition payments | B52: ₹ cr | C52: ='Raw Financials'!C172 -> -17.9 | D52: ='Raw Financials'!D172 -> -1379.4513 | E52: ='Raw Financials'!E172 -> -1132.0596 | F52: ='Raw Financials'!F172 -> -135 | G52: ='Raw Financials'!G172 -> -548 | H52: ='Raw Financials'!H172 -> -1134 | I52: ='Raw Financials'!I172 -> -4661.3 | J52: ='Raw Financials'!J172 -> -1067.2 | ... M52: ='Raw Financials'!M172 -> -89.9 | N52: =-Assumptions!C38 -> 0 | O52: =-Assumptions!D38 -> 0 | P52: =-Assumptions!E38 -> 0 | Q52: =-Assumptions!F38 -> 0
A53: Rental income received | B53: ₹ cr | C53: ='Raw Financials'!C173 -> 0 | D53: ='Raw Financials'!D173 -> 8.7005731 | E53: ='Raw Financials'!E173 -> 19.603387 | F53: ='Raw Financials'!F173 -> 31.5 | G53: ='Raw Financials'!G173 -> 31.1 | H53: ='Raw Financials'!H173 -> 34.8 | I53: ='Raw Financials'!I173 -> 72.9 | J53: ='Raw Financials'!J173 -> 23.5 | ... M53: ='Raw Financials'!M173 -> 24.9 | N53: =0 -> 0 | O53: =0 -> 0 | P53: =0 -> 0 | Q53: =0 -> 0
A54: Inter-corporate deposits, net | B54: ₹ cr | C54: =SUM('Raw Financials'!C175,'Raw Financials'!C176) -> 0 | D54: =SUM('Raw Financials'!D175,'Raw Financials'!D176) -> -428.6 | E54: =SUM('Raw Financials'!E175,'Raw Financials'!E176) -> 278.6 | F54: =SUM('Raw Financials'!F175,'Raw Financials'!F176) -> 0 | G54: =SUM('Raw Financials'!G175,'Raw Financials'!G176) -> 0 | H54: =SUM('Raw Financials'!H175,'Raw Financials'!H176) -> 0 | I54: =SUM('Raw Financials'!I175,'Raw Financials'!I176) -> 0 | J54: =SUM('Raw Financials'!J175,'Raw Financials'!J176) -> 0 | ... M54: =SUM('Raw Financials'!M175,'Raw Financials'!M176) -> 0 | N54: =0 -> 0 | O54: =0 -> 0 | P54: =0 -> 0 | Q54: =0 -> 0
A55: Purchase-price adjustment | B55: ₹ cr | C55: ='Raw Financials'!C177 -> 39.513236 | D55: ='Raw Financials'!D177 -> 20.543741 | E55: ='Raw Financials'!E177 -> 44.225466 | F55: ='Raw Financials'!F177 -> 0 | G55: ='Raw Financials'!G177 -> 0 | H55: ='Raw Financials'!H177 -> 0 | I55: ='Raw Financials'!I177 -> 0 | J55: ='Raw Financials'!J177 -> 0 | ... M55: ='Raw Financials'!M177 -> 0 | N55: =0 -> 0 | O55: =0 -> 0 | P55: =0 -> 0 | Q55: =0 -> 0
A56: Deposits / margin money, net | B56: ₹ cr | C56: =SUM('Raw Financials'!C178,'Raw Financials'!C179) -> -420.318 | D56: =SUM('Raw Financials'!D178,'Raw Financials'!D179) -> 434.11924 | E56: =SUM('Raw Financials'!E178,'Raw Financials'!E179) -> 140.03738 | F56: =SUM('Raw Financials'!F178,'Raw Financials'!F179) -> 939.8 | G56: =SUM('Raw Financials'!G178,'Raw Financials'!G179) -> 195.6 | H56: =SUM('Raw Financials'!H178,'Raw Financials'!H179) -> 15.7 | I56: =SUM('Raw Financials'!I178,'Raw Financials'!I179) -> -52.2 | J56: =SUM('Raw Financials'!J178,'Raw Financials'!J179) -> -7.6 | ... M56: =SUM('Raw Financials'!M178,'Raw Financials'!M179) -> 147.9 | N56: =-('Annual Balance Sheet'!N29-'Annual Balance Sheet'!M29) -> 1.074122 | O56: =-('Annual Balance Sheet'!O29-'Annual Balance Sheet'!N29) -> -2.2342271 | P56: =-('Annual Balance Sheet'!P29-'Annual Balance Sheet'!O29) -> -2.8778765 | Q56: =-('Annual Balance Sheet'!Q29-'Annual Balance Sheet'!P29) -> -3.4151987
A57: Interest received | B57: ₹ cr | C57: ='Raw Financials'!C180 -> 95.147104 | D57: ='Raw Financials'!D180 -> 117.21267 | E57: ='Raw Financials'!E180 -> 124.52371 | F57: ='Raw Financials'!F180 -> 148.2 | G57: ='Raw Financials'!G180 -> 252.6 | H57: ='Raw Financials'!H180 -> 221.3 | I57: ='Raw Financials'!I180 -> 108.4 | J57: ='Raw Financials'!J180 -> 144.8 | ... M57: ='Raw Financials'!M180 -> 125.1 | N57: ='Annual P&L'!N24 -> 211.9025 | O57: ='Annual P&L'!O24 -> 250.40579 | P57: ='Annual P&L'!P24 -> 295.30029 | Q57: ='Annual P&L'!Q24 -> 340.93447
A58: Other investing / three-statement integration | B58: ₹ cr | C58: =C59-SUM(C40:C57) -> -0.075341191 | D58: =D59-SUM(D40:D57) -> 0 | E58: =E59-SUM(E40:E57) -> -0.031 | F58: =F59-SUM(F40:F57) -> 0 | G58: =G59-SUM(G40:G57) -> -0.003300363 | H58: =H59-SUM(H40:H57) -> 0 | I58: =I59-SUM(I40:I57) -> -4.5474735e-13 | J58: =J59-SUM(J40:J57) -> 1.2505552e-12 | ... M58: =M59-SUM(M40:M57) -> 4.206413e-12 | N58: =-('Annual Balance Sheet'!N10-'Annual Balance Sheet'!M10) -> 0 | O58: =-('Annual Balance Sheet'!O10-'Annual Balance Sheet'!N10) -> 0 | P58: =-('Annual Balance Sheet'!P10-'Annual Balance Sheet'!O10) -> 0 | Q58: =-('Annual Balance Sheet'!Q10-'Annual Balance Sheet'!P10) -> 0
A59: Cash flow from investing | B59: ₹ cr | C59: ='Raw Financials'!C181 -> -1466.7501 | D59: ='Raw Financials'!D181 -> -3050.7507 | E59: ='Raw Financials'!E181 -> -3359.6515 | F59: ='Raw Financials'!F181 -> -2116.4 | G59: ='Raw Financials'!G181 -> 1028.62 | H59: ='Raw Financials'!H181 -> -5450.1 | I59: ='Raw Financials'!I181 -> 481.5 | J59: ='Raw Financials'!J181 -> -278.47 | ... M59: ='Raw Financials'!M181 -> -409.2 | N59: =SUM(N40:N58) -> -702.01247 | O59: =SUM(O40:O58) -> -671.86343 | P59: =SUM(P40:P58) -> -703.64394 | Q59: =SUM(Q40:Q58) -> -735.184
A60: Equity issuance | B60: ₹ cr | C60: ='Raw Financials'!C182 -> 36.242333 | D60: ='Raw Financials'!D182 -> 34.452153 | E60: ='Raw Financials'!E182 -> 25.099331 | F60: ='Raw Financials'!F182 -> 35.9 | G60: ='Raw Financials'!G182 -> 46.8 | H60: ='Raw Financials'!H182 -> 56.9 | I60: ='Raw Financials'!I182 -> 86.8 | J60: ='Raw Financials'!J182 -> 44.2 | ... M60: ='Raw Financials'!M182 -> 0.9 | N60: ='Annual Balance Sheet'!N36-'Annual Balance Sheet'!M36 -> 0 | O60: ='Annual Balance Sheet'!O36-'Annual Balance Sheet'!N36 -> 0 | P60: ='Annual Balance Sheet'!P36-'Annual Balance Sheet'!O36 -> 0 | Q60: ='Annual Balance Sheet'!Q36-'Annual Balance Sheet'!P36 -> 0
A61: Acquisition of NCI | B61: ₹ cr | C61: ='Raw Financials'!C184 -> 0 | D61: ='Raw Financials'!D184 -> 0 | E61: ='Raw Financials'!E184 -> 0 | F61: ='Raw Financials'!F184 -> 0 | G61: ='Raw Financials'!G184 -> 0 | H61: ='Raw Financials'!H184 -> 0 | I61: ='Raw Financials'!I184 -> 0 | J61: ='Raw Financials'!J184 -> 0 | ... M61: ='Raw Financials'!M184 -> 0 | N61: =0 -> 0 | O61: =0 -> 0 | P61: =0 -> 0 | Q61: =0 -> 0
A62: Related-party loan repayment | B62: ₹ cr | C62: ='Raw Financials'!C185 -> 0.6 | D62: ='Raw Financials'!D185 -> 0 | E62: ='Raw Financials'!E185 -> 0 | F62: ='Raw Financials'!F185 -> 0 | G62: ='Raw Financials'!G185 -> 0 | H62: ='Raw Financials'!H185 -> 0 | I62: ='Raw Financials'!I185 -> 0 | J62: ='Raw Financials'!J185 -> 0 | ... M62: ='Raw Financials'!M185 -> 0 | N62: =0 -> 0 | O62: =0 -> 0 | P62: =0 -> 0 | Q62: =0 -> 0
A63: Dividend paid — source line 1 | B63: ₹ cr | C63: ='Raw Financials'!C183 -> 0 | D63: ='Raw Financials'!D183 -> 0 | E63: ='Raw Financials'!E183 -> 0 | F63: ='Raw Financials'!F183 -> 0 | G63: ='Raw Financials'!G183 -> 0 | H63: ='Raw Financials'!H183 -> 0 | I63: ='Raw Financials'!I183 -> 0 | J63: ='Raw Financials'!J183 -> 0 | ... M63: ='Raw Financials'!M183 -> -4025.5 | N63: ='BS Forecast Schedules'!D43 -> -4754.7325 | O63: ='BS Forecast Schedules'!E43 -> -5227.5784 | P63: ='BS Forecast Schedules'!F43 -> -5798.1762 | Q63: ='BS Forecast Schedules'!G43 -> -6407.1517
A64: Dividend paid — source line 2 | B64: ₹ cr | C64: ='Raw Financials'!C186 -> -624.5 | D64: ='Raw Financials'!D186 -> -1239.1647 | E64: ='Raw Financials'!E186 -> -943.78258 | F64: ='Raw Financials'!F186 -> -1490.7 | G64: ='Raw Financials'!G186 -> -2491.7 | H64: ='Raw Financials'!H186 -> -1759.355 | I64: ='Raw Financials'!I186 -> -3980.808 | J64: ='Raw Financials'!J186 -> -4263.303 | ... M64: ='Raw Financials'!M186 -> 0 | N64: =0 -> 0 | O64: =0 -> 0 | P64: =0 -> 0 | Q64: =0 -> 0
A65: Total dividends paid | B65: ₹ cr | C65: =SUM(C63:C64) -> -624.5 | D65: =SUM(D63:D64) -> -1239.1647 | E65: =SUM(E63:E64) -> -943.78258 | F65: =SUM(F63:F64) -> -1490.7 | G65: =SUM(G63:G64) -> -2491.7 | H65: =SUM(H63:H64) -> -1759.355 | I65: =SUM(I63:I64) -> -3980.808 | J65: =SUM(J63:J64) -> -4263.303 | ... Q65: =SUM(Q63:Q64) -> -6407.1517
A66: Buyback deposits | B66: ₹ cr | C66: ='Raw Financials'!C187 -> 0 | D66: ='Raw Financials'!D187 -> 0 | E66: ='Raw Financials'!E187 -> 0 | F66: ='Raw Financials'!F187 -> -210.6 | G66: ='Raw Financials'!G187 -> 0 | H66: ='Raw Financials'!H187 -> 0 | I66: ='Raw Financials'!I187 -> 0 | J66: ='Raw Financials'!J187 -> 0 | ... M66: ='Raw Financials'!M187 -> 0 | N66: =0 -> 0 | O66: =0 -> 0 | P66: =0 -> 0 | Q66: =0 -> 0
A67: NCI transaction | B67: ₹ cr | C67: ='Raw Financials'!C188 -> 0 | D67: ='Raw Financials'!D188 -> 0 | E67: ='Raw Financials'!E188 -> 0 | F67: ='Raw Financials'!F188 -> 0 | G67: ='Raw Financials'!G188 -> 0 | H67: ='Raw Financials'!H188 -> 68.8 | I67: ='Raw Financials'!I188 -> 30.7 | J67: ='Raw Financials'!J188 -> 0 | ... M67: ='Raw Financials'!M188 -> 0 | N67: =0 -> 0 | O67: =0 -> 0 | P67: =0 -> 0 | Q67: =0 -> 0
A68: Buyback | B68: ₹ cr | C68: ='Raw Financials'!C189 -> 0 | D68: ='Raw Financials'!D189 -> 0 | E68: ='Raw Financials'!E189 -> 0 | F68: ='Raw Financials'!F189 -> 0 | G68: ='Raw Financials'!G189 -> -1787.8616 | H68: ='Raw Financials'!H189 -> 0 | I68: ='Raw Financials'!I189 -> 0 | J68: ='Raw Financials'!J189 -> 0 | ... M68: ='Raw Financials'!M189 -> 0 | N68: =0 -> 0 | O68: =0 -> 0 | P68: =0 -> 0 | Q68: =0 -> 0
A69: Proceeds from long-term borrowings | B69: ₹ cr | C69: ='Raw Financials'!C190 -> 42.721331 | D69: ='Raw Financials'!D190 -> 7.0301316 | E69: ='Raw Financials'!E190 -> 954.49485 | F69: ='Raw Financials'!F190 -> 18 | G69: ='Raw Financials'!G190 -> 379.4 | H69: ='Raw Financials'!H190 -> 9.2 | I69: ='Raw Financials'!I190 -> 62.1 | J69: ='Raw Financials'!J190 -> 65.8 | ... M69: ='Raw Financials'!M190 -> 0 | N69: =MAX(0,'BS Forecast Schedules'!D38-'BS Forecast Schedules'!C38) -> 59.16 | O69: =MAX(0,'BS Forecast Schedules'!E38-'BS Forecast Schedules'!D38) -> 0 | P69: =MAX(0,'BS Forecast Schedules'!F38-'BS Forecast Schedules'!E38) -> 0 | Q69: =MAX(0,'BS Forecast Schedules'!G38-'BS Forecast Schedules'!F38) -> 0
A70: Repayment of long-term borrowings | B70: ₹ cr | C70: ='Raw Financials'!C191 -> -65.350019 | D70: ='Raw Financials'!D191 -> -248.03658 | E70: ='Raw Financials'!E191 -> -211.24911 | F70: ='Raw Financials'!F191 -> -665.6 | G70: ='Raw Financials'!G191 -> -1335.4 | H70: ='Raw Financials'!H191 -> -37.6 | I70: ='Raw Financials'!I191 -> -21.6 | J70: ='Raw Financials'!J191 -> -32.1 | ... M70: ='Raw Financials'!M191 -> 0 | N70: =MIN(0,'BS Forecast Schedules'!D38-'BS Forecast Schedules'!C38) -> 0 | O70: =MIN(0,'BS Forecast Schedules'!E38-'BS Forecast Schedules'!D38) -> 0 | P70: =MIN(0,'BS Forecast Schedules'!F38-'BS Forecast Schedules'!E38) -> 0 | Q70: =MIN(0,'BS Forecast Schedules'!G38-'BS Forecast Schedules'!F38) -> 0
A71: Net change in short-term borrowings | B71: ₹ cr | C71: ='Raw Financials'!C192 -> 252.58617 | D71: ='Raw Financials'!D192 -> -14.142517 | E71: ='Raw Financials'!E192 -> 5.2512648 | F71: ='Raw Financials'!F192 -> 197.2 | G71: ='Raw Financials'!G192 -> 1149.4 | H71: ='Raw Financials'!H192 -> -766.5 | I71: ='Raw Financials'!I192 -> -203.02569 | J71: ='Raw Financials'!J192 -> -193.14 | ... M71: ='Raw Financials'!M192 -> -433.8 | N71: ='BS Forecast Schedules'!D37-'BS Forecast Schedules'!C37 -> -59.16 | O71: ='BS Forecast Schedules'!E37-'BS Forecast Schedules'!D37 -> 0 | P71: ='BS Forecast Schedules'!F37-'BS Forecast Schedules'!E37 -> 0 | Q71: ='BS Forecast Schedules'!G37-'BS Forecast Schedules'!F37 -> 0
A72: Repayment of short-term borrowings | B72: ₹ cr | C72: ='Raw Financials'!C194 -> -114.98398 | D72: ='Raw Financials'!D194 -> 0 | E72: ='Raw Financials'!E194 -> 0 | F72: ='Raw Financials'!F194 -> 0 | G72: ='Raw Financials'!G194 -> 0 | H72: ='Raw Financials'!H194 -> 0 | I72: ='Raw Financials'!I194 -> 0 | J72: ='Raw Financials'!J194 -> 0 | ... M72: ='Raw Financials'!M194 -> 0 | N72: =0 -> 0 | O72: =0 -> 0 | P72: =0 -> 0 | Q72: =0 -> 0
A73: Finance costs paid | B73: ₹ cr | C73: ='Raw Financials'!C195 -> -92.546651 | D73: ='Raw Financials'!D195 -> -111.08752 | E73: ='Raw Financials'!E195 -> -159.86322 | F73: ='Raw Financials'!F195 -> -135.4 | G73: ='Raw Financials'!G195 -> -188.3 | H73: ='Raw Financials'!H195 -> -178.9 | I73: ='Raw Financials'!I195 -> -123.05 | J73: ='Raw Financials'!J195 -> -256.95 | ... M73: ='Raw Financials'!M195 -> -208.3 | N73: =-'Annual P&L'!N25 -> -4.176 | O73: =-'Annual P&L'!O25 -> -4.176 | P73: =-'Annual P&L'!P25 -> -4.176 | Q73: =-'Annual P&L'!Q25 -> -4.176
A74: Lease principal paid | B74: ₹ cr | C74: ='Raw Financials'!C196 -> 0 | D74: ='Raw Financials'!D196 -> 0 | E74: ='Raw Financials'!E196 -> 0 | F74: ='Raw Financials'!F196 -> 0 | G74: ='Raw Financials'!G196 -> -237.78 | H74: ='Raw Financials'!H196 -> -379.4 | I74: ='Raw Financials'!I196 -> -517.721 | J74: ='Raw Financials'!J196 -> -442.632 | ... M74: ='Raw Financials'!M196 -> -463.8 | N74: ='BS Forecast Schedules'!D28 -> -634.98 | O74: ='BS Forecast Schedules'!E28 -> -654.09916 | P74: ='BS Forecast Schedules'!F28 -> -675.52579 | Q74: ='BS Forecast Schedules'!G28 -> -700.88479
A75: Share application money from NCI | B75: ₹ cr | C75: ='Raw Financials'!C197 -> 0 | D75: ='Raw Financials'!D197 -> 0 | E75: ='Raw Financials'!E197 -> 60.645564 | F75: ='Raw Financials'!F197 -> 0 | G75: ='Raw Financials'!G197 -> 0 | H75: ='Raw Financials'!H197 -> 0 | I75: ='Raw Financials'!I197 -> 0 | J75: ='Raw Financials'!J197 -> 0 | ... M75: ='Raw Financials'!M197 -> 0 | N75: =0 -> 0 | O75: =0 -> 0 | P75: =0 -> 0 | Q75: =0 -> 0
A76: Other financing / reclassification | B76: ₹ cr | C76: =C77-SUM(C60:C75) -> 624.42222 | D76: =D77-SUM(D60:D75) -> 1239.1647 | E76: =E77-SUM(E60:E75) -> 943.78648 | F76: =F77-SUM(F60:F75) -> 1490.7 | G76: =G77-SUM(G60:G75) -> 2491.5936 | H76: =H77-SUM(H60:H75) -> 1759.355 | I76: =I77-SUM(I60:I75) -> 3980.808 | J76: =J77-SUM(J60:J75) -> 4263.302 | ... M76: =M77-SUM(M60:M75) -> 4025.5 | N76: =0 -> 0 | O76: =0 -> 0 | P76: =0 -> 0 | Q76: =0 -> 0
A77: Cash flow from financing | B77: ₹ cr | C77: ='Raw Financials'!C198 -> -565.30859 | D77: ='Raw Financials'!D198 -> -1570.949 | E77: ='Raw Financials'!E198 -> -269.4 | F77: ='Raw Financials'!F198 -> -2251.2 | G77: ='Raw Financials'!G198 -> -4465.548 | H77: ='Raw Financials'!H198 -> -2986.855 | I77: ='Raw Financials'!I198 -> -4666.6047 | J77: ='Raw Financials'!J198 -> -5078.126 | ... M77: ='Raw Financials'!M198 -> -5130.5 | N77: =SUM(N60:N64,N66:N76) -> -5393.8885 | O77: =SUM(O60:O64,O66:O76) -> -5885.8535 | P77: =SUM(P60:P64,P66:P76) -> -6477.878 | Q77: =SUM(Q60:Q64,Q66:Q76) -> -7112.2125
A78: Net cash before FX | B78: ₹ cr | C78: ='Raw Financials'!C199 -> 1181.1376 | D78: ='Raw Financials'!D199 -> -550.34376 | E78: ='Raw Financials'!E199 -> -75.550937 | F78: ='Raw Financials'!F199 -> 64.448619 | G78: ='Raw Financials'!G199 -> 921.233 | H78: ='Raw Financials'!H199 -> -343.209 | I78: ='Raw Financials'!I199 -> 1100.1696 | J78: ='Raw Financials'!J199 -> 215.367 | ... M78: ='Raw Financials'!M199 -> 632.3 | N78: =SUM(N38,N59,N77) -> 1383.1531 | O78: =SUM(O38,O59,O77) -> 1659.4922 | P78: =SUM(P38,P59,P77) -> 1649.8167 | Q78: =SUM(Q38,Q59,Q77) -> 1749.6338
A79: FX effect on cash | B79: ₹ cr | C79: ='Raw Financials'!C200 -> 0 | D79: ='Raw Financials'!D200 -> 0 | E79: ='Raw Financials'!E200 -> 40.37105 | F79: ='Raw Financials'!F200 -> 12.2 | G79: ='Raw Financials'!G200 -> 52.794656 | H79: ='Raw Financials'!H200 -> 16.9 | I79: ='Raw Financials'!I200 -> -1.7 | J79: ='Raw Financials'!J200 -> 52 | ... M79: ='Raw Financials'!M200 -> 95.3 | N79: =0 -> 0 | O79: =0 -> 0 | P79: =0 -> 0 | Q79: =0 -> 0
A80: Opening cash | B80: ₹ cr | C80: ='Raw Financials'!C201 -> 1205.5523 | D80: ='Raw Financials'!D201 -> 2393.7533 | E80: ='Raw Financials'!E201 -> 2001.2512 | F80: ='Raw Financials'!F201 -> 1966.0827 | G80: ='Raw Financials'!G201 -> 2042.7 | H80: ='Raw Financials'!H201 -> 3016.7 | I80: ='Raw Financials'!I201 -> 2690.4 | J80: ='Raw Financials'!J201 -> 3788.9 | ... M80: ='Raw Financials'!M201 -> 4318.5 | N80: ='Annual Balance Sheet'!M28 -> 5046.1 | O80: ='Annual Balance Sheet'!N28 -> 6429.2531 | P80: ='Annual Balance Sheet'!O28 -> 8088.7452 | Q80: ='Annual Balance Sheet'!P28 -> 9738.5619
A81: Cash acquired | B81: ₹ cr | C81: ='Raw Financials'!C202 -> 6.5651549 | D81: ='Raw Financials'!D202 -> 161.32503 | E81: ='Raw Financials'!E202 -> 0 | F81: ='Raw Financials'!F202 -> 0 | G81: ='Raw Financials'!G202 -> 0 | H81: ='Raw Financials'!H202 -> 0 | I81: ='Raw Financials'!I202 -> 0 | J81: ='Raw Financials'!J202 -> 0 | ... M81: ='Raw Financials'!M202 -> 0 | N81: =0 -> 0 | O81: =0 -> 0 | P81: =0 -> 0 | Q81: =0 -> 0
A82: Cash disposed | B82: ₹ cr | C82: ='Raw Financials'!C203 -> 0 | D82: ='Raw Financials'!D203 -> 0 | E82: ='Raw Financials'!E203 -> 0 | F82: ='Raw Financials'!F203 -> 0 | G82: ='Raw Financials'!G203 -> 0 | H82: ='Raw Financials'!H203 -> 0 | I82: ='Raw Financials'!I203 -> 0 | J82: ='Raw Financials'!J203 -> 0 | ... M82: ='Raw Financials'!M203 -> 0 | N82: =0 -> 0 | O82: =0 -> 0 | P82: =0 -> 0 | Q82: =0 -> 0
A83: Other acquisition cash | B83: ₹ cr | C83: ='Raw Financials'!C204 -> 0 | D83: ='Raw Financials'!D204 -> 0 | E83: ='Raw Financials'!E204 -> 0 | F83: ='Raw Financials'!F204 -> 0 | G83: ='Raw Financials'!G204 -> 0 | H83: ='Raw Financials'!H204 -> 0 | I83: ='Raw Financials'!I204 -> 0 | J83: ='Raw Financials'!J204 -> 0 | ... M83: ='Raw Financials'!M204 -> 0 | N83: =0 -> 0 | O83: =0 -> 0 | P83: =0 -> 0 | Q83: =0 -> 0
A84: Net change in cash | B84: ₹ cr | C84: =C85-C80 -> 1187.7028 | D84: =D85-D80 -> -388.94873 | E84: =E85-E80 -> -35.179887 | F84: =F85-F80 -> 76.648619 | G84: =G85-G80 -> 974.028 | H84: =H85-H80 -> -326.31 | I84: =I85-I80 -> 1098.468 | J84: =J85-J80 -> 267.367 | ... M84: =M85-M80 -> 727.6 | N84: =SUM(N78:N79,N81:N83) -> 1383.1531 | O84: =SUM(O78:O79,O81:O83) -> 1659.4922 | P84: =SUM(P78:P79,P81:P83) -> 1649.8167 | Q84: =SUM(Q78:Q79,Q81:Q83) -> 1749.6338
A85: Reported closing cash per CFS | B85: ₹ cr | C85: ='Raw Financials'!C205 -> 2393.2551 | D85: ='Raw Financials'!D205 -> 2004.8046 | E85: ='Raw Financials'!E205 -> 1966.0713 | F85: ='Raw Financials'!F205 -> 2042.7313 | G85: ='Raw Financials'!G205 -> 3016.728 | H85: ='Raw Financials'!H205 -> 2690.39 | I85: ='Raw Financials'!I205 -> 3788.868 | J85: ='Raw Financials'!J205 -> 4056.267 | ... M85: ='Raw Financials'!M205 -> 5046.1 | N85: =N80+N84 -> 6429.2531 | O85: =O80+O84 -> 8088.7452 | P85: =P80+P84 -> 9738.5619 | Q85: =Q80+Q84 -> 11488.196
A86: Closing cash per balance sheet | B86: ₹ cr | C86: ='Annual Balance Sheet'!C28 -> 4013.8061 | D86: ='Annual Balance Sheet'!D28 -> 2001.2742 | E86: ='Annual Balance Sheet'!E28 -> 1966.0827 | F86: ='Annual Balance Sheet'!F28 -> 2042.7 | G86: ='Annual Balance Sheet'!G28 -> 3016.7 | H86: ='Annual Balance Sheet'!H28 -> 2690.4 | I86: ='Annual Balance Sheet'!I28 -> 3788.9 | J86: ='Annual Balance Sheet'!J28 -> 4056.3 | ... Q86: ='Annual Balance Sheet'!Q28 -> 11488.196
A87: Cash-basis / reporting reconciliation | B87: ₹ cr | C87: =C86-C85 -> 1620.5511 | D87: =D86-D85 -> -3.5303993 | E87: =E86-E85 -> 0.011420094 | F87: =F86-F85 -> -0.031312661 | G87: =G86-G85 -> -0.028 | H87: =H86-H85 -> 0.01 | I87: =I86-I85 -> 0.032 | J87: =J86-J85 -> 0.033 | ... Q87: =Q86-Q85 -> 0
A88: Free cash flow | B88: ₹ cr | C88: =C38+C40 -> 2286.6963 | D88: =D38+D40 -> 3303.1643 | E88: =E38+E40 -> 2536.9712 | F88: =F38+F40 -> 3627.4486 | G88: =G38+G40 -> 3513.458 | H88: =H38+H40 -> 7427.841 | I88: =I38+I40 -> 4326.8743 | J88: =J38+J40 -> 4556.794 | ... Q88: =Q38+Q40 -> 8729.2389
A89: FCF / net income | B89: % | C89: =IFERROR(C88/'Annual P&L'!C35,"") -> 0.76404389 | D89: =IFERROR(D88/'Annual P&L'!D35,"") -> 1.1742776 | E89: =IFERROR(E88/'Annual P&L'!E35,"") -> 0.66766705 | F89: =IFERROR(F88/'Annual P&L'!F35,"") -> 0.84406057 | G89: =IFERROR(G88/'Annual P&L'!G35,"") -> 0.87118982 | H89: =IFERROR(H88/'Annual P&L'!H35,"") -> 1.6774485 | I89: =IFERROR(I88/'Annual P&L'!I35,"") -> 0.77736013 | J89: =IFERROR(J88/'Annual P&L'!J35,"") -> 0.94318644 | ... Q89: =IFERROR(Q88/'Annual P&L'!Q35,"") -> 1.0899369

Sheet Industry Revenue
A1: Revenue by Industry
A2: Reported classifications remain separate; revenue is calculated from reported mix × annual P&L revenue
A5: Metric | B5: Units | C5: FY16A | D5: FY17A | E5: FY18A | F5: FY19A | G5: FY20A | H5: FY21A | I5: FY22A | J5: FY23A | K5: FY24A | L5: FY25A | M5: FY26A | N5: FY27E | O5: FY28E | P5: FY29E | Q5: FY30E
A7: Legacy classification — used through FY21
A8: Communications mix | B8: % | C8: ='Raw Operating'!C42 -> 0.51958341 | D8: ='Raw Operating'!D42 -> 0.47774846 | E8: ='Raw Operating'!E42 -> 0.43273304 | F8: ='Raw Operating'!F42 -> 0.4122149 | G8: ='Raw Operating'!G42 -> 0.41609801 | H8: ='Raw Operating'!H42 -> 0.39664372 | I8: ='Raw Operating'!I42 -> 0 | J8: ='Raw Operating'!J42 -> 0 | ... M8: ='Raw Operating'!M42 -> 0
A9: Communications revenue | B9: ₹ cr | C9: =IF(C8="","",C8*'Annual P&L'!C7) -> 13765.964 | D9: =IF(D8="","",D8*'Annual P&L'!D7) -> 13921.992 | E9: =IF(E8="","",E8*'Annual P&L'!E7) -> 13316.442 | F9: =IF(F8="","",F8*'Annual P&L'!F7) -> 14321.224 | G9: =IF(G8="","",G8*'Annual P&L'!G7) -> 15340.568 | H9: =IF(H8="","",H8*'Annual P&L'!H7) -> 15014.98 | I9: =IF(I8="","",I8*'Annual P&L'!I7) -> 0 | J9: =IF(J8="","",J8*'Annual P&L'!J7) -> 0 | ... Q9: =IF(Q8="","",Q8*'Annual P&L'!Q7)
A10: Manufacturing mix | B10: % | C10: ='Raw Operating'!C43 -> 0.17004687 | D10: ='Raw Operating'!D43 -> 0.18730729 | E10: ='Raw Operating'!E43 -> 0.19192741 | F10: ='Raw Operating'!F43 -> 0.2023175 | G10: ='Raw Operating'!G43 -> 0.18099944 | H10: ='Raw Operating'!H43 -> 0.16379366 | I10: ='Raw Operating'!I43 -> 0 | J10: ='Raw Operating'!J43 -> 0 | ... M10: ='Raw Operating'!M43 -> 0
A11: Manufacturing revenue | B11: ₹ cr | C11: =IF(C10="","",C10*'Annual P&L'!C7) -> 4505.2614 | D11: =IF(D10="","",D10*'Annual P&L'!D7) -> 5458.292 | E11: =IF(E10="","",E10*'Annual P&L'!E7) -> 5906.1594 | F11: =IF(F10="","",F10*'Annual P&L'!F7) -> 7028.9411 | G11: =IF(G10="","",G10*'Annual P&L'!G7) -> 6673.0294 | H11: =IF(H10="","",H10*'Annual P&L'!H7) -> 6200.4221 | I11: =IF(I10="","",I10*'Annual P&L'!I7) -> 0 | J11: =IF(J10="","",J10*'Annual P&L'!J7) -> 0 | ... Q11: =IF(Q10="","",Q10*'Annual P&L'!Q7)
A12: Technology, Media & Entertainment mix | B12: % | C12: ='Raw Operating'!C44 -> 0.074347679 | D12: ='Raw Operating'!D44 -> 0.067214337 | E12: ='Raw Operating'!E44 -> 0.064500668 | F12: ='Raw Operating'!F44 -> 0.072454242 | G12: ='Raw Operating'!G44 -> 0.076919335 | H12: ='Raw Operating'!H44 -> 0.093544648 | I12: ='Raw Operating'!I44 -> 0 | J12: ='Raw Operating'!J44 -> 0 | ... M12: ='Raw Operating'!M44 -> 0
A13: Technology, Media & Entertainment revenue | B13: ₹ cr | C13: =IF(C12="","",C12*'Annual P&L'!C7) -> 1969.7847 | D13: =IF(D12="","",D12*'Annual P&L'!D7) -> 1958.6823 | E13: =IF(E12="","",E12*'Annual P&L'!E7) -> 1984.8714 | F13: =IF(F12="","",F12*'Annual P&L'!F7) -> 2517.2148 | G13: =IF(G12="","",G12*'Annual P&L'!G7) -> 2835.8373 | H13: =IF(H12="","",H12*'Annual P&L'!H7) -> 3541.1402 | I13: =IF(I12="","",I12*'Annual P&L'!I7) -> 0 | J13: =IF(J12="","",J12*'Annual P&L'!J7) -> 0 | ... Q13: =IF(Q12="","",Q12*'Annual P&L'!Q7)
A14: BFSI mix | B14: % | C14: ='Raw Operating'!C45 -> 0.1013418 | D14: ='Raw Operating'!D45 -> 0.1264392 | E14: ='Raw Operating'!E45 -> 0.13675168 | F14: ='Raw Operating'!F45 -> 0.13356922 | G14: ='Raw Operating'!G45 -> 0.13558064 | H14: ='Raw Operating'!H45 -> 0.16153576 | I14: ='Raw Operating'!I45 -> 0 | J14: ='Raw Operating'!J45 -> 0 | ... M14: ='Raw Operating'!M45 -> 0
A15: BFSI revenue | B15: ₹ cr | C15: =IF(C14="","",C14*'Annual P&L'!C7) -> 2684.9732 | D15: =IF(D14="","",D14*'Annual P&L'!D7) -> 3684.5446 | E15: =IF(E14="","",E14*'Annual P&L'!E7) -> 4208.2431 | F15: =IF(F14="","",F14*'Annual P&L'!F7) -> 4640.4795 | G15: =IF(G14="","",G14*'Annual P&L'!G7) -> 4998.5435 | H15: =IF(H14="","",H14*'Annual P&L'!H7) -> 6114.9493 | I15: =IF(I14="","",I14*'Annual P&L'!I7) -> 0 | J15: =IF(J14="","",J14*'Annual P&L'!J7) -> 0 | ... Q15: =IF(Q14="","",Q14*'Annual P&L'!Q7)
A16: Retail, Transport & Logistics mix | B16: % | C16: ='Raw Operating'!C46 -> 0.06370376 | D16: ='Raw Operating'!D46 -> 0.068851851 | E16: ='Raw Operating'!E46 -> 0.068326503 | F16: ='Raw Operating'!F46 -> 0.064358118 | G16: ='Raw Operating'!G46 -> 0.069305782 | H16: ='Raw Operating'!H46 -> 0.075729404 | I16: ='Raw Operating'!I46 -> 0 | J16: ='Raw Operating'!J46 -> 0 | ... M16: ='Raw Operating'!M46 -> 0
A17: Retail, Transport & Logistics revenue | B17: ₹ cr | C17: =IF(C16="","",C16*'Annual P&L'!C7) -> 1687.7822 | D17: =IF(D16="","",D16*'Annual P&L'!D7) -> 2006.4009 | E17: =IF(E16="","",E16*'Annual P&L'!E7) -> 2102.6034 | F17: =IF(F16="","",F16*'Annual P&L'!F7) -> 2235.9382 | G17: =IF(G16="","",G16*'Annual P&L'!G7) -> 2555.1433 | H17: =IF(H16="","",H16*'Annual P&L'!H7) -> 2866.7427 | I17: =IF(I16="","",I16*'Annual P&L'!I7) -> 0 | J17: =IF(J16="","",J16*'Annual P&L'!J7) -> 0 | ... Q17: =IF(Q16="","",Q16*'Annual P&L'!Q7)
A18: Others mix | B18: % | C18: ='Raw Operating'!C47 -> 0.070976471 | D18: ='Raw Operating'!D47 -> 0.072438872 | E18: ='Raw Operating'!E47 -> 0.1057607 | F18: ='Raw Operating'!F47 -> 0.11508602 | G18: ='Raw Operating'!G47 -> 0.12104679 | H18: ='Raw Operating'!H47 -> 0.10875281 | I18: ='Raw Operating'!I47 -> 0 | J18: ='Raw Operating'!J47 -> 0 | ... M18: ='Raw Operating'!M47 -> 0
A19: Others revenue | B19: ₹ cr | C19: =IF(C18="","",C18*'Annual P&L'!C7) -> 1880.4671 | D19: =IF(D18="","",D18*'Annual P&L'!D7) -> 2110.9297 | E19: =IF(E18="","",E18*'Annual P&L'!E7) -> 3254.5614 | F19: =IF(F18="","",F18*'Annual P&L'!F7) -> 3998.3336 | G19: =IF(G18="","",G18*'Annual P&L'!G7) -> 4462.7142 | H19: =IF(H18="","",H18*'Annual P&L'!H7) -> 4116.8464 | I19: =IF(I18="","",I18*'Annual P&L'!I7) -> 0 | J19: =IF(J18="","",J18*'Annual P&L'!J7) -> 0 | ... Q19: =IF(Q18="","",Q18*'Annual P&L'!Q7)
A20: Mix check | B20: % | C20: =IF(COUNT(C8,C10,C12,C14,C16,C18)=0,"",SUM(C8,C10,C12,C14,C16,C18)) -> 1 | D20: =IF(COUNT(D8,D10,D12,D14,D16,D18)=0,"",SUM(D8,D10,D12,D14,D16,D18)) -> 1 | E20: =IF(COUNT(E8,E10,E12,E14,E16,E18)=0,"",SUM(E8,E10,E12,E14,E16,E18)) -> 1 | F20: =IF(COUNT(F8,F10,F12,F14,F16,F18)=0,"",SUM(F8,F10,F12,F14,F16,F18)) -> 1 | G20: =IF(COUNT(G8,G10,G12,G14,G16,G18)=0,"",SUM(G8,G10,G12,G14,G16,G18)) -> 0.99995 | H20: =IF(COUNT(H8,H10,H12,H14,H16,H18)=0,"",SUM(H8,H10,H12,H14,H16,H18)) -> 1 | I20: =IF(COUNT(I8,I10,I12,I14,I16,I18)=0,"",SUM(I8,I10,I12,I14,I16,I18)) -> 0 | J20: =IF(COUNT(J8,J10,J12,J14,J16,J18)=0,"",SUM(J8,J10,J12,J14,J16,J18)) -> 0 | ... Q20: =IF(COUNT(Q8,Q10,Q12,Q14,Q16,Q18)=0,"",SUM(Q8,Q10,Q12,Q14,Q16,Q18))
A21: Calculated industry revenue | B21: ₹ cr | C21: =SUM(C9,C11,C13,C15,C17,C19) -> 26494.232 | D21: =SUM(D9,D11,D13,D15,D17,D19) -> 29140.841 | E21: =SUM(E9,E11,E13,E15,E17,E19) -> 30772.881 | F21: =SUM(F9,F11,F13,F15,F17,F19) -> 34742.132 | G21: =SUM(G9,G11,G13,G15,G17,G19) -> 36865.836 | H21: =SUM(H9,H11,H13,H15,H17,H19) -> 37855.081 | I21: =SUM(I9,I11,I13,I15,I17,I19) -> 0 | J21: =SUM(J9,J11,J13,J15,J17,J19) -> 0 | ... Q21: =SUM(Q9,Q11,Q13,Q15,Q17,Q19) -> 0
A22: Annual P&L revenue | B22: ₹ cr | C22: ='Annual P&L'!C7 -> 26494.232 | D22: ='Annual P&L'!D7 -> 29140.841 | E22: ='Annual P&L'!E7 -> 30772.881 | F22: ='Annual P&L'!F7 -> 34742.132 | G22: ='Annual P&L'!G7 -> 36867.679 | H22: ='Annual P&L'!H7 -> 37855.081 | I22: ='Annual P&L'!I7 -> 44645.964 | J22: ='Annual P&L'!J7 -> 53290.167 | ... Q22: ='Annual P&L'!Q7 -> 66753.18
A23: Revenue check | B23: ₹ cr | C23: =IF(C20="","",C21-C22) -> 3.6379788e-12 | D23: =IF(D20="","",D21-D22) -> 0 | E23: =IF(E20="","",E21-E22) -> 3.6379788e-12 | F23: =IF(F20="","",F21-F22) -> 1.4551915e-11 | G23: =IF(G20="","",G21-G22) -> -1.8433839 | H23: =IF(H20="","",H21-H22) -> -3.6379788e-11 | I23: =IF(I20="","",I21-I22) -> -44645.964 | J23: =IF(J20="","",J21-J22) -> -53290.167 | ... Q23: =IF(Q20="","",Q21-Q22)
A25: FY21–FY24 restated classification
A26: Communications, Media & Entertainment mix | B26: % | C26: ='Raw Operating'!C48 -> 0 | D26: ='Raw Operating'!D48 -> 0 | E26: ='Raw Operating'!E48 -> 0 | F26: ='Raw Operating'!F48 -> 0 | G26: ='Raw Operating'!G48 -> 0 | H26: ='Raw Operating'!H48 -> 0.40467177 | I26: ='Raw Operating'!I48 -> 0.40401735 | J26: ='Raw Operating'!J48 -> 0.39999784 | ... M26: ='Raw Operating'!M48 -> 0
A27: Communications, Media & Entertainment revenue | B27: ₹ cr | C27: =IF(C26="","",C26*'Annual P&L'!C7) -> 0 | D27: =IF(D26="","",D26*'Annual P&L'!D7) -> 0 | E27: =IF(E26="","",E26*'Annual P&L'!E7) -> 0 | F27: =IF(F26="","",F26*'Annual P&L'!F7) -> 0 | G27: =IF(G26="","",G26*'Annual P&L'!G7) -> 0 | H27: =IF(H26="","",H26*'Annual P&L'!H7) -> 15318.883 | I27: =IF(I26="","",I26*'Annual P&L'!I7) -> 18037.744 | J27: =IF(J26="","",J26*'Annual P&L'!J7) -> 21315.952 | ... Q27: =IF(Q26="","",Q26*'Annual P&L'!Q7)
A28: Manufacturing mix | B28: % | C28: ='Raw Operating'!C49 -> 0 | D28: ='Raw Operating'!D49 -> 0 | E28: ='Raw Operating'!E49 -> 0 | F28: ='Raw Operating'!F49 -> 0 | G28: ='Raw Operating'!G49 -> 0 | H28: ='Raw Operating'!H49 -> 0.16496366 | I28: ='Raw Operating'!I49 -> 0.15809026 | J28: ='Raw Operating'!J49 -> 0.15712794 | ... M28: ='Raw Operating'!M49 -> 0
A29: Manufacturing revenue | B29: ₹ cr | C29: =IF(C28="","",C28*'Annual P&L'!C7) -> 0 | D29: =IF(D28="","",D28*'Annual P&L'!D7) -> 0 | E29: =IF(E28="","",E28*'Annual P&L'!E7) -> 0 | F29: =IF(F28="","",F28*'Annual P&L'!F7) -> 0 | G29: =IF(G28="","",G28*'Annual P&L'!G7) -> 0 | H29: =IF(H28="","",H28*'Annual P&L'!H7) -> 6244.7125 | I29: =IF(I28="","",I28*'Annual P&L'!I7) -> 7058.0918 | J29: =IF(J28="","",J28*'Annual P&L'!J7) -> 8373.3743 | ... Q29: =IF(Q28="","",Q28*'Annual P&L'!Q7)
A30: Technology mix | B30: % | C30: ='Raw Operating'!C50 -> 0 | D30: ='Raw Operating'!D50 -> 0 | E30: ='Raw Operating'!E50 -> 0 | F30: ='Raw Operating'!F50 -> 0 | G30: ='Raw Operating'!G50 -> 0 | H30: ='Raw Operating'!H50 -> 0.085207268 | I30: ='Raw Operating'!I50 -> 0.088660859 | J30: ='Raw Operating'!J50 -> 0.1008662 | ... M30: ='Raw Operating'!M50 -> 0
A31: Technology revenue | B31: ₹ cr | C31: =IF(C30="","",C30*'Annual P&L'!C7) -> 0 | D31: =IF(D30="","",D30*'Annual P&L'!D7) -> 0 | E31: =IF(E30="","",E30*'Annual P&L'!E7) -> 0 | F31: =IF(F30="","",F30*'Annual P&L'!F7) -> 0 | G31: =IF(G30="","",G30*'Annual P&L'!G7) -> 0 | H31: =IF(H30="","",H30*'Annual P&L'!H7) -> 3225.528 | I31: =IF(I30="","",I30*'Annual P&L'!I7) -> 3958.3495 | J31: =IF(J30="","",J30*'Annual P&L'!J7) -> 5375.1765 | ... Q31: =IF(Q30="","",Q30*'Annual P&L'!Q7)
A32: BFSI mix | B32: % | C32: ='Raw Operating'!C51 -> 0 | D32: ='Raw Operating'!D51 -> 0 | E32: ='Raw Operating'!E51 -> 0 | F32: ='Raw Operating'!F51 -> 0 | G32: ='Raw Operating'!G51 -> 0 | H32: ='Raw Operating'!H51 -> 0.16123687 | I32: ='Raw Operating'!I51 -> 0.16387117 | J32: ='Raw Operating'!J51 -> 0.16189809 | ... M32: ='Raw Operating'!M51 -> 0
A33: BFSI revenue | B33: ₹ cr | C33: =IF(C32="","",C32*'Annual P&L'!C7) -> 0 | D33: =IF(D32="","",D32*'Annual P&L'!D7) -> 0 | E33: =IF(E32="","",E32*'Annual P&L'!E7) -> 0 | F33: =IF(F32="","",F32*'Annual P&L'!F7) -> 0 | G33: =IF(G32="","",G32*'Annual P&L'!G7) -> 0 | H33: =IF(H32="","",H32*'Annual P&L'!H7) -> 6103.6347 | I33: =IF(I32="","",I32*'Annual P&L'!I7) -> 7316.1864 | J33: =IF(J32="","",J32*'Annual P&L'!J7) -> 8627.5763 | ... Q33: =IF(Q32="","",Q32*'Annual P&L'!Q7)
A34: Retail, Transport & Logistics mix | B34: % | C34: ='Raw Operating'!C52 -> 0 | D34: ='Raw Operating'!D52 -> 0 | E34: ='Raw Operating'!E52 -> 0 | F34: ='Raw Operating'!F52 -> 0 | G34: ='Raw Operating'!G52 -> 0 | H34: ='Raw Operating'!H52 -> 0.077650755 | I34: ='Raw Operating'!I52 -> 0.078880939 | J34: ='Raw Operating'!J52 -> 0.080159355 | ... M34: ='Raw Operating'!M52 -> 0
A35: Retail, Transport & Logistics revenue | B35: ₹ cr | C35: =IF(C34="","",C34*'Annual P&L'!C7) -> 0 | D35: =IF(D34="","",D34*'Annual P&L'!D7) -> 0 | E35: =IF(E34="","",E34*'Annual P&L'!E7) -> 0 | F35: =IF(F34="","",F34*'Annual P&L'!F7) -> 0 | G35: =IF(G34="","",G34*'Annual P&L'!G7) -> 0 | H35: =IF(H34="","",H34*'Annual P&L'!H7) -> 2939.4756 | I35: =IF(I34="","",I34*'Annual P&L'!I7) -> 3521.7156 | J35: =IF(J34="","",J34*'Annual P&L'!J7) -> 4271.7054 | ... Q35: =IF(Q34="","",Q34*'Annual P&L'!Q7)
A36: Others mix | B36: % | C36: ='Raw Operating'!C53 -> 0 | D36: ='Raw Operating'!D53 -> 0 | E36: ='Raw Operating'!E53 -> 0 | F36: ='Raw Operating'!F53 -> 0 | G36: ='Raw Operating'!G53 -> 0 | H36: ='Raw Operating'!H53 -> 0.10626968 | I36: ='Raw Operating'!I53 -> 0.10622943 | J36: ='Raw Operating'!J53 -> 0.099950573 | ... M36: ='Raw Operating'!M53 -> 0
A37: Others revenue | B37: ₹ cr | C37: =IF(C36="","",C36*'Annual P&L'!C7) -> 0 | D37: =IF(D36="","",D36*'Annual P&L'!D7) -> 0 | E37: =IF(E36="","",E36*'Annual P&L'!E7) -> 0 | F37: =IF(F36="","",F36*'Annual P&L'!F7) -> 0 | G37: =IF(G36="","",G36*'Annual P&L'!G7) -> 0 | H37: =IF(H36="","",H36*'Annual P&L'!H7) -> 4022.8473 | I37: =IF(I36="","",I36*'Annual P&L'!I7) -> 4742.7151 | J37: =IF(J36="","",J36*'Annual P&L'!J7) -> 5326.3827 | ... Q37: =IF(Q36="","",Q36*'Annual P&L'!Q7)
A38: Mix check | B38: % | C38: =IF(COUNT(C26,C28,C30,C32,C34,C36)=0,"",SUM(C26,C28,C30,C32,C34,C36)) -> 0 | D38: =IF(COUNT(D26,D28,D30,D32,D34,D36)=0,"",SUM(D26,D28,D30,D32,D34,D36)) -> 0 | E38: =IF(COUNT(E26,E28,E30,E32,E34,E36)=0,"",SUM(E26,E28,E30,E32,E34,E36)) -> 0 | F38: =IF(COUNT(F26,F28,F30,F32,F34,F36)=0,"",SUM(F26,F28,F30,F32,F34,F36)) -> 0 | G38: =IF(COUNT(G26,G28,G30,G32,G34,G36)=0,"",SUM(G26,G28,G30,G32,G34,G36)) -> 0 | H38: =IF(COUNT(H26,H28,H30,H32,H34,H36)=0,"",SUM(H26,H28,H30,H32,H34,H36)) -> 1 | I38: =IF(COUNT(I26,I28,I30,I32,I34,I36)=0,"",SUM(I26,I28,I30,I32,I34,I36)) -> 0.99975 | J38: =IF(COUNT(J26,J28,J30,J32,J34,J36)=0,"",SUM(J26,J28,J30,J32,J34,J36)) -> 1 | ... Q38: =IF(COUNT(Q26,Q28,Q30,Q32,Q34,Q36)=0,"",SUM(Q26,Q28,Q30,Q32,Q34,Q36))
A39: Calculated industry revenue | B39: ₹ cr | C39: =SUM(C27,C29,C31,C33,C35,C37) -> 0 | D39: =SUM(D27,D29,D31,D33,D35,D37) -> 0 | E39: =SUM(E27,E29,E31,E33,E35,E37) -> 0 | F39: =SUM(F27,F29,F31,F33,F35,F37) -> 0 | G39: =SUM(G27,G29,G31,G33,G35,G37) -> 0 | H39: =SUM(H27,H29,H31,H33,H35,H37) -> 37855.081 | I39: =SUM(I27,I29,I31,I33,I35,I37) -> 44634.803 | J39: =SUM(J27,J29,J31,J33,J35,J37) -> 53290.167 | ... Q39: =SUM(Q27,Q29,Q31,Q33,Q35,Q37) -> 0
A40: Annual P&L revenue | B40: ₹ cr | C40: ='Annual P&L'!C7 -> 26494.232 | D40: ='Annual P&L'!D7 -> 29140.841 | E40: ='Annual P&L'!E7 -> 30772.881 | F40: ='Annual P&L'!F7 -> 34742.132 | G40: ='Annual P&L'!G7 -> 36867.679 | H40: ='Annual P&L'!H7 -> 37855.081 | I40: ='Annual P&L'!I7 -> 44645.964 | J40: ='Annual P&L'!J7 -> 53290.167 | ... Q40: ='Annual P&L'!Q7 -> 66753.18
A41: Revenue check | B41: ₹ cr | C41: =IF(C38="","",C39-C40) -> -26494.232 | D41: =IF(D38="","",D39-D40) -> -29140.841 | E41: =IF(E38="","",E39-E40) -> -30772.881 | F41: =IF(F38="","",F39-F40) -> -34742.132 | G41: =IF(G38="","",G39-G40) -> -36867.679 | H41: =IF(H38="","",H39-H40) -> -4.3655746e-11 | I41: =IF(I38="","",I39-I40) -> -11.161491 | J41: =IF(J38="","",J39-J40) -> 0 | ... Q41: =IF(Q38="","",Q39-Q40)
A43: Current classification — FY24 onward
A44: Communications mix | B44: % | C44: ='Raw Operating'!C54 -> 0 | D44: ='Raw Operating'!D54 -> 0 | E44: ='Raw Operating'!E54 -> 0 | F44: ='Raw Operating'!F54 -> 0 | G44: ='Raw Operating'!G54 -> 0 | H44: ='Raw Operating'!H54 -> 0 | I44: ='Raw Operating'!I54 -> 0 | J44: ='Raw Operating'!J54 -> 0 | ... M44: ='Raw Operating'!M54 -> 0.33264816 | N44: =M44 -> 0.33264816 | O44: =N44 -> 0.33264816 | P44: =O44 -> 0.33264816 | Q44: =P44 -> 0.33264816
A45: Communications revenue | B45: ₹ cr | C45: =IF(C44="","",C44*'Annual P&L'!C7) -> 0 | D45: =IF(D44="","",D44*'Annual P&L'!D7) -> 0 | E45: =IF(E44="","",E44*'Annual P&L'!E7) -> 0 | F45: =IF(F44="","",F44*'Annual P&L'!F7) -> 0 | G45: =IF(G44="","",G44*'Annual P&L'!G7) -> 0 | H45: =IF(H44="","",H44*'Annual P&L'!H7) -> 0 | I45: =IF(I44="","",I44*'Annual P&L'!I7) -> 0 | J45: =IF(J44="","",J44*'Annual P&L'!J7) -> 0 | ... Q45: =IF(Q44="","",Q44*'Annual P&L'!Q7) -> 22205.322
A46: Manufacturing mix | B46: % | C46: ='Raw Operating'!C55 -> 0 | D46: ='Raw Operating'!D55 -> 0 | E46: ='Raw Operating'!E55 -> 0 | F46: ='Raw Operating'!F55 -> 0 | G46: ='Raw Operating'!G55 -> 0 | H46: ='Raw Operating'!H55 -> 0 | I46: ='Raw Operating'!I55 -> 0 | J46: ='Raw Operating'!J55 -> 0 | ... M46: ='Raw Operating'!M55 -> 0.17999103 | N46: =M46 -> 0.17999103 | O46: =N46 -> 0.17999103 | P46: =O46 -> 0.17999103 | Q46: =P46 -> 0.17999103
A47: Manufacturing revenue | B47: ₹ cr | C47: =IF(C46="","",C46*'Annual P&L'!C7) -> 0 | D47: =IF(D46="","",D46*'Annual P&L'!D7) -> 0 | E47: =IF(E46="","",E46*'Annual P&L'!E7) -> 0 | F47: =IF(F46="","",F46*'Annual P&L'!F7) -> 0 | G47: =IF(G46="","",G46*'Annual P&L'!G7) -> 0 | H47: =IF(H46="","",H46*'Annual P&L'!H7) -> 0 | I47: =IF(I46="","",I46*'Annual P&L'!I7) -> 0 | J47: =IF(J46="","",J46*'Annual P&L'!J7) -> 0 | ... Q47: =IF(Q46="","",Q46*'Annual P&L'!Q7) -> 12014.974
A48: Hi-Tech & Media mix | B48: % | C48: ='Raw Operating'!C56 -> 0 | D48: ='Raw Operating'!D56 -> 0 | E48: ='Raw Operating'!E56 -> 0 | F48: ='Raw Operating'!F56 -> 0 | G48: ='Raw Operating'!G56 -> 0 | H48: ='Raw Operating'!H56 -> 0 | I48: ='Raw Operating'!I56 -> 0 | J48: ='Raw Operating'!J56 -> 0 | ... M48: ='Raw Operating'!M56 -> 0.13261109 | N48: =M48 -> 0.13261109 | O48: =N48 -> 0.13261109 | P48: =O48 -> 0.13261109 | Q48: =P48 -> 0.13261109
A49: Hi-Tech & Media revenue | B49: ₹ cr | C49: =IF(C48="","",C48*'Annual P&L'!C7) -> 0 | D49: =IF(D48="","",D48*'Annual P&L'!D7) -> 0 | E49: =IF(E48="","",E48*'Annual P&L'!E7) -> 0 | F49: =IF(F48="","",F48*'Annual P&L'!F7) -> 0 | G49: =IF(G48="","",G48*'Annual P&L'!G7) -> 0 | H49: =IF(H48="","",H48*'Annual P&L'!H7) -> 0 | I49: =IF(I48="","",I48*'Annual P&L'!I7) -> 0 | J49: =IF(J48="","",J48*'Annual P&L'!J7) -> 0 | ... Q49: =IF(Q48="","",Q48*'Annual P&L'!Q7) -> 8852.2121
A50: BFSI mix | B50: % | C50: ='Raw Operating'!C57 -> 0 | D50: ='Raw Operating'!D57 -> 0 | E50: ='Raw Operating'!E57 -> 0 | F50: ='Raw Operating'!F57 -> 0 | G50: ='Raw Operating'!G57 -> 0 | H50: ='Raw Operating'!H57 -> 0 | I50: ='Raw Operating'!I57 -> 0 | J50: ='Raw Operating'!J57 -> 0 | ... M50: ='Raw Operating'!M57 -> 0.16329254 | N50: =M50 -> 0.16329254 | O50: =N50 -> 0.16329254 | P50: =O50 -> 0.16329254 | Q50: =P50 -> 0.16329254
A51: BFSI revenue | B51: ₹ cr | C51: =IF(C50="","",C50*'Annual P&L'!C7) -> 0 | D51: =IF(D50="","",D50*'Annual P&L'!D7) -> 0 | E51: =IF(E50="","",E50*'Annual P&L'!E7) -> 0 | F51: =IF(F50="","",F50*'Annual P&L'!F7) -> 0 | G51: =IF(G50="","",G50*'Annual P&L'!G7) -> 0 | H51: =IF(H50="","",H50*'Annual P&L'!H7) -> 0 | I51: =IF(I50="","",I50*'Annual P&L'!I7) -> 0 | J51: =IF(J50="","",J50*'Annual P&L'!J7) -> 0 | ... Q51: =IF(Q50="","",Q50*'Annual P&L'!Q7) -> 10900.296
A52: Retail, Transport & Logistics mix | B52: % | C52: ='Raw Operating'!C58 -> 0 | D52: ='Raw Operating'!D58 -> 0 | E52: ='Raw Operating'!E58 -> 0 | F52: ='Raw Operating'!F58 -> 0 | G52: ='Raw Operating'!G58 -> 0 | H52: ='Raw Operating'!H58 -> 0 | I52: ='Raw Operating'!I58 -> 0 | J52: ='Raw Operating'!J58 -> 0 | ... M52: ='Raw Operating'!M58 -> 0.083342565 | N52: =M52 -> 0.083342565 | O52: =N52 -> 0.083342565 | P52: =O52 -> 0.083342565 | Q52: =P52 -> 0.083342565
A53: Retail, Transport & Logistics revenue | B53: ₹ cr | C53: =IF(C52="","",C52*'Annual P&L'!C7) -> 0 | D53: =IF(D52="","",D52*'Annual P&L'!D7) -> 0 | E53: =IF(E52="","",E52*'Annual P&L'!E7) -> 0 | F53: =IF(F52="","",F52*'Annual P&L'!F7) -> 0 | G53: =IF(G52="","",G52*'Annual P&L'!G7) -> 0 | H53: =IF(H52="","",H52*'Annual P&L'!H7) -> 0 | I53: =IF(I52="","",I52*'Annual P&L'!I7) -> 0 | J53: =IF(J52="","",J52*'Annual P&L'!J7) -> 0 | ... Q53: =IF(Q52="","",Q52*'Annual P&L'!Q7) -> 5563.3813
A54: Healthcare & Life Sciences mix | B54: % | C54: ='Raw Operating'!C59 -> 0 | D54: ='Raw Operating'!D59 -> 0 | E54: ='Raw Operating'!E59 -> 0 | F54: ='Raw Operating'!F59 -> 0 | G54: ='Raw Operating'!G59 -> 0 | H54: ='Raw Operating'!H59 -> 0 | I54: ='Raw Operating'!I59 -> 0 | J54: ='Raw Operating'!J59 -> 0 | ... M54: ='Raw Operating'!M59 -> 0.073250748 | N54: =M54 -> 0.073250748 | O54: =N54 -> 0.073250748 | P54: =O54 -> 0.073250748 | Q54: =P54 -> 0.073250748
A55: Healthcare & Life Sciences revenue | B55: ₹ cr | C55: =IF(C54="","",C54*'Annual P&L'!C7) -> 0 | D55: =IF(D54="","",D54*'Annual P&L'!D7) -> 0 | E55: =IF(E54="","",E54*'Annual P&L'!E7) -> 0 | F55: =IF(F54="","",F54*'Annual P&L'!F7) -> 0 | G55: =IF(G54="","",G54*'Annual P&L'!G7) -> 0 | H55: =IF(H54="","",H54*'Annual P&L'!H7) -> 0 | I55: =IF(I54="","",I54*'Annual P&L'!I7) -> 0 | J55: =IF(J54="","",J54*'Annual P&L'!J7) -> 0 | ... Q55: =IF(Q54="","",Q54*'Annual P&L'!Q7) -> 4889.7204
A56: Others mix | B56: % | C56: ='Raw Operating'!C60 -> 0 | D56: ='Raw Operating'!D60 -> 0 | E56: ='Raw Operating'!E60 -> 0 | F56: ='Raw Operating'!F60 -> 0 | G56: ='Raw Operating'!G60 -> 0 | H56: ='Raw Operating'!H60 -> 0 | I56: ='Raw Operating'!I60 -> 0 | J56: ='Raw Operating'!J60 -> 0 | ... M56: ='Raw Operating'!M60 -> 0.034852899 | N56: =1-SUM(N44,N46,N48,N50,N52,N54) -> 0.034863863 | O56: =1-SUM(O44,O46,O48,O50,O52,O54) -> 0.034863863 | P56: =1-SUM(P44,P46,P48,P50,P52,P54) -> 0.034863863 | Q56: =1-SUM(Q44,Q46,Q48,Q50,Q52,Q54) -> 0.034863863
A57: Others revenue | B57: ₹ cr | C57: =IF(C56="","",C56*'Annual P&L'!C7) -> 0 | D57: =IF(D56="","",D56*'Annual P&L'!D7) -> 0 | E57: =IF(E56="","",E56*'Annual P&L'!E7) -> 0 | F57: =IF(F56="","",F56*'Annual P&L'!F7) -> 0 | G57: =IF(G56="","",G56*'Annual P&L'!G7) -> 0 | H57: =IF(H56="","",H56*'Annual P&L'!H7) -> 0 | I57: =IF(I56="","",I56*'Annual P&L'!I7) -> 0 | J57: =IF(J56="","",J56*'Annual P&L'!J7) -> 0 | ... Q57: =IF(Q56="","",Q56*'Annual P&L'!Q7) -> 2327.2737
A58: Mix check | B58: % | C58: =IF(COUNT(C44,C46,C48,C50,C52,C54,C56)=0,"",SUM(C44,C46,C48,C50,C52,C54,C56)) -> 0 | D58: =IF(COUNT(D44,D46,D48,D50,D52,D54,D56)=0,"",SUM(D44,D46,D48,D50,D52,D54,D56)) -> 0 | E58: =IF(COUNT(E44,E46,E48,E50,E52,E54,E56)=0,"",SUM(E44,E46,E48,E50,E52,E54,E56)) -> 0 | F58: =IF(COUNT(F44,F46,F48,F50,F52,F54,F56)=0,"",SUM(F44,F46,F48,F50,F52,F54,F56)) -> 0 | G58: =IF(COUNT(G44,G46,G48,G50,G52,G54,G56)=0,"",SUM(G44,G46,G48,G50,G52,G54,G56)) -> 0 | H58: =IF(COUNT(H44,H46,H48,H50,H52,H54,H56)=0,"",SUM(H44,H46,H48,H50,H52,H54,H56)) -> 0 | I58: =IF(COUNT(I44,I46,I48,I50,I52,I54,I56)=0,"",SUM(I44,I46,I48,I50,I52,I54,I56)) -> 0 | J58: =IF(COUNT(J44,J46,J48,J50,J52,J54,J56)=0,"",SUM(J44,J46,J48,J50,J52,J54,J56)) -> 0 | ... Q58: =IF(COUNT(Q44,Q46,Q48,Q50,Q52,Q54,Q56)=0,"",SUM(Q44,Q46,Q48,Q50,Q52,Q54,Q56)) -> 1
A59: Calculated industry revenue | B59: ₹ cr | C59: =SUM(C45,C47,C49,C51,C53,C55,C57) -> 0 | D59: =SUM(D45,D47,D49,D51,D53,D55,D57) -> 0 | E59: =SUM(E45,E47,E49,E51,E53,E55,E57) -> 0 | F59: =SUM(F45,F47,F49,F51,F53,F55,F57) -> 0 | G59: =SUM(G45,G47,G49,G51,G53,G55,G57) -> 0 | H59: =SUM(H45,H47,H49,H51,H53,H55,H57) -> 0 | I59: =SUM(I45,I47,I49,I51,I53,I55,I57) -> 0 | J59: =SUM(J45,J47,J49,J51,J53,J55,J57) -> 0 | ... Q59: =SUM(Q45,Q47,Q49,Q51,Q53,Q55,Q57) -> 66753.18
A60: Annual P&L revenue | B60: ₹ cr | C60: ='Annual P&L'!C7 -> 26494.232 | D60: ='Annual P&L'!D7 -> 29140.841 | E60: ='Annual P&L'!E7 -> 30772.881 | F60: ='Annual P&L'!F7 -> 34742.132 | G60: ='Annual P&L'!G7 -> 36867.679 | H60: ='Annual P&L'!H7 -> 37855.081 | I60: ='Annual P&L'!I7 -> 44645.964 | J60: ='Annual P&L'!J7 -> 53290.167 | ... Q60: ='Annual P&L'!Q7 -> 66753.18
A61: Revenue check | B61: ₹ cr | C61: =IF(C58="","",C59-C60) -> -26494.232 | D61: =IF(D58="","",D59-D60) -> -29140.841 | E61: =IF(E58="","",E59-E60) -> -30772.881 | F61: =IF(F58="","",F59-F60) -> -34742.132 | G61: =IF(G58="","",G59-G60) -> -36867.679 | H61: =IF(H58="","",H59-H60) -> -37855.081 | I61: =IF(I58="","",I59-I60) -> -44645.964 | J61: =IF(J58="","",J59-J60) -> -53290.167 | ... Q61: =IF(Q58="","",Q59-Q60) -> -1.4551915e-11

Sheet Geography & Currency
A1: Geography, Delivery Mix and Currency
A2: Reported mix is linked to the source layer; absolute revenue and growth are calculated
A5: Metric | B5: Units | C5: FY16A | D5: FY17A | E5: FY18A | F5: FY19A | G5: FY20A | H5: FY21A | I5: FY22A | J5: FY23A | K5: FY24A | L5: FY25A | M5: FY26A | N5: FY27E | O5: FY28E | P5: FY29E | Q5: FY30E
A7: Geography mix
A8: Americas mix | B8: % | C8: ='Raw Operating'!C39 -> 0.47788163 | D8: ='Raw Operating'!D39 -> 0.4721035 | E8: ='Raw Operating'!E39 -> 0.46580473 | F8: ='Raw Operating'!F39 -> 0.47247123 | G8: ='Raw Operating'!G39 -> 0.4805 | H8: ='Raw Operating'!H39 -> 0.474 | I8: ='Raw Operating'!I39 -> 0.4791 | J8: ='Raw Operating'!J39 -> 0.4993 | ... M8: ='Raw Operating'!M39 -> 0.49811039 | N8: =M8 -> 0.49811039 | O8: =N8 -> 0.49811039 | P8: =O8 -> 0.49811039 | Q8: =P8 -> 0.49811039
A9: Americas revenue | B9: ₹ cr | C9: =C8*'Annual P&L'!C7 -> 12661.107 | D9: =D8*'Annual P&L'!D7 -> 13757.493 | E9: =E8*'Annual P&L'!E7 -> 14334.154 | F9: =F8*'Annual P&L'!F7 -> 16414.658 | G9: =G8*'Annual P&L'!G7 -> 17714.92 | H9: =H8*'Annual P&L'!H7 -> 17943.308 | I9: =I8*'Annual P&L'!I7 -> 21389.881 | J9: =J8*'Annual P&L'!J7 -> 26607.78 | ... Q9: =Q8*'Annual P&L'!Q7 -> 33250.453
A10: Europe mix | B10: % | C10: ='Raw Operating'!C40 -> 0.29038554 | D10: ='Raw Operating'!D40 -> 0.29253597 | E10: ='Raw Operating'!E40 -> 0.29830439 | F10: ='Raw Operating'!F40 -> 0.29272929 | G10: ='Raw Operating'!G40 -> 0.269 | H10: ='Raw Operating'!H40 -> 0.2597 | I10: ='Raw Operating'!I40 -> 0.2624 | J10: ='Raw Operating'!J40 -> 0.2492 | ... M10: ='Raw Operating'!M40 -> 0.25757022 | N10: =M10 -> 0.25757022 | O10: =N10 -> 0.25757022 | P10: =O10 -> 0.25757022 | Q10: =P10 -> 0.25757022
A11: Europe revenue | B11: ₹ cr | C11: =C10*'Annual P&L'!C7 -> 7693.5418 | D11: =D10*'Annual P&L'!D7 -> 8524.7444 | E11: =E10*'Annual P&L'!E7 -> 9179.6855 | F11: =F10*'Annual P&L'!F7 -> 10170.04 | G11: =G10*'Annual P&L'!G7 -> 9917.4057 | H11: =H10*'Annual P&L'!H7 -> 9830.9645 | I11: =I10*'Annual P&L'!I7 -> 11715.101 | J11: =J10*'Annual P&L'!J7 -> 13279.91 | ... Q11: =Q10*'Annual P&L'!Q7 -> 17193.631
A12: Rest of world mix | B12: % | C12: ='Raw Operating'!C41 -> 0.23173283 | D12: ='Raw Operating'!D41 -> 0.23536053 | E12: ='Raw Operating'!E41 -> 0.23589089 | F12: ='Raw Operating'!F41 -> 0.23479947 | G12: ='Raw Operating'!G41 -> 0.2501 | H12: ='Raw Operating'!H41 -> 0.2657 | I12: ='Raw Operating'!I41 -> 0.258 | J12: ='Raw Operating'!J41 -> 0.2514 | ... M12: ='Raw Operating'!M41 -> 0.24430862 | N12: =M12 -> 0.24430862 | O12: =N12 -> 0.24430862 | P12: =O12 -> 0.24430862 | Q12: =P12 -> 0.24430862
A13: Rest of world revenue | B13: ₹ cr | C13: =C12*'Annual P&L'!C7 -> 6139.5834 | D13: =D12*'Annual P&L'!D7 -> 6858.6038 | E13: =E12*'Annual P&L'!E7 -> 7259.0422 | F13: =F12*'Annual P&L'!F7 -> 8157.4343 | G13: =G12*'Annual P&L'!G7 -> 9220.6065 | H13: =H12*'Annual P&L'!H7 -> 10058.095 | I13: =I12*'Annual P&L'!I7 -> 11518.659 | J13: =J12*'Annual P&L'!J7 -> 13397.148 | ... Q13: =Q12*'Annual P&L'!Q7 -> 16308.377
A14: Mix check | B14: % | C14: =SUM(C8,C10,C12) -> 1 | D14: =SUM(D8,D10,D12) -> 1 | E14: =SUM(E8,E10,E12) -> 1 | F14: =SUM(F8,F10,F12) -> 1 | G14: =SUM(G8,G10,G12) -> 0.9996 | H14: =SUM(H8,H10,H12) -> 0.9994 | I14: =SUM(I8,I10,I12) -> 0.9995 | J14: =SUM(J8,J10,J12) -> 0.9999 | ... Q14: =SUM(Q8,Q10,Q12) -> 0.99998923
A16: Onsite / offshore disclosure — revenue mix through FY22; IT headcount mix from FY23
A17: Onsite revenue mix | B17: % | C17: ='Raw Operating'!C30 -> 0.62148793 | D17: ='Raw Operating'!D30 -> 0.63763805 | E17: ='Raw Operating'!E30 -> 0.65070223 | F17: ='Raw Operating'!F30 -> 0.65443059 | G17: ='Raw Operating'!G30 -> 0.6527 | H17: ='Raw Operating'!H30 -> 0.6316 | I17: ='Raw Operating'!I30 -> 0.6163 | J17: ='Raw Operating'!J30 -> 0 | ... M17: ='Raw Operating'!M30 -> 0
A18: Offshore revenue mix | B18: % | C18: ='Raw Operating'!C31 -> 0.37851207 | D18: ='Raw Operating'!D31 -> 0.36236195 | E18: ='Raw Operating'!E31 -> 0.34929777 | F18: ='Raw Operating'!F31 -> 0.34556941 | G18: ='Raw Operating'!G31 -> 0.347 | H18: ='Raw Operating'!H31 -> 0.3683 | I18: ='Raw Operating'!I31 -> 0.3836 | J18: ='Raw Operating'!J31 -> 0 | ... M18: ='Raw Operating'!M31 -> 0
A19: Revenue mix check | B19: % | C19: =IF(COUNT(C17:C18)=0,"",SUM(C17:C18)) -> 1 | D19: =IF(COUNT(D17:D18)=0,"",SUM(D17:D18)) -> 1 | E19: =IF(COUNT(E17:E18)=0,"",SUM(E17:E18)) -> 1 | F19: =IF(COUNT(F17:F18)=0,"",SUM(F17:F18)) -> 1 | G19: =IF(COUNT(G17:G18)=0,"",SUM(G17:G18)) -> 0.9997 | H19: =IF(COUNT(H17:H18)=0,"",SUM(H17:H18)) -> 0.9999 | I19: =IF(COUNT(I17:I18)=0,"",SUM(I17:I18)) -> 0.9999 | J19: =IF(COUNT(J17:J18)=0,"",SUM(J17:J18)) -> 0 | ... Q19: =IF(COUNT(Q17:Q18)=0,"",SUM(Q17:Q18))
A20: Onsite IT headcount mix | B20: % | C20: ='Raw Operating'!C32 -> 0 | D20: ='Raw Operating'!D32 -> 0 | E20: ='Raw Operating'!E32 -> 0 | F20: ='Raw Operating'!F32 -> 0 | G20: ='Raw Operating'!G32 -> 0 | H20: ='Raw Operating'!H32 -> 0 | I20: ='Raw Operating'!I32 -> 0.27594087 | J20: ='Raw Operating'!J32 -> 0.2729645 | ... M20: ='Raw Operating'!M32 -> 0.21875244 | N20: =M20 -> 0.21875244 | O20: =N20 -> 0.21875244 | P20: =O20 -> 0.21875244 | Q20: =P20 -> 0.21875244
A21: Offshore IT headcount mix | B21: % | C21: ='Raw Operating'!C33 -> 0 | D21: ='Raw Operating'!D33 -> 0 | E21: ='Raw Operating'!E33 -> 0 | F21: ='Raw Operating'!F33 -> 0 | G21: ='Raw Operating'!G33 -> 0 | H21: ='Raw Operating'!H33 -> 0 | I21: ='Raw Operating'!I33 -> 0.72405913 | J21: ='Raw Operating'!J33 -> 0.7270355 | ... M21: ='Raw Operating'!M33 -> 0.78124756 | N21: =M21 -> 0.78124756 | O21: =N21 -> 0.78124756 | P21: =O21 -> 0.78124756 | Q21: =P21 -> 0.78124756
A22: Headcount mix check | B22: % | C22: =IF(COUNT(C20:C21)=0,"",SUM(C20:C21)) -> 0 | D22: =IF(COUNT(D20:D21)=0,"",SUM(D20:D21)) -> 0 | E22: =IF(COUNT(E20:E21)=0,"",SUM(E20:E21)) -> 0 | F22: =IF(COUNT(F20:F21)=0,"",SUM(F20:F21)) -> 0 | G22: =IF(COUNT(G20:G21)=0,"",SUM(G20:G21)) -> 0 | H22: =IF(COUNT(H20:H21)=0,"",SUM(H20:H21)) -> 0 | I22: =IF(COUNT(I20:I21)=0,"",SUM(I20:I21)) -> 1 | J22: =IF(COUNT(J20:J21)=0,"",SUM(J20:J21)) -> 1 | ... Q22: =IF(COUNT(Q20:Q21)=0,"",SUM(Q20:Q21)) -> 1
A24: Revenue currency mix and absolute revenue
A25: USD mix | B25: % | C25: ='Raw Operating'!C34 -> 0.51051503 | D25: ='Raw Operating'!D34 -> 0.48348981 | E25: ='Raw Operating'!E34 -> 0.48115697 | F25: ='Raw Operating'!F34 -> 0.48217646 | G25: ='Raw Operating'!G34 -> 0.49764 | H25: ='Raw Operating'!H34 -> 0.5121 | I25: ='Raw Operating'!I34 -> 0.5139 | J25: ='Raw Operating'!J34 -> 0.5163 | ... M25: ='Raw Operating'!M34 -> 0.51447327 | N25: =M25 -> 0.51447327 | O25: =N25 -> 0.51447327 | P25: =O25 -> 0.51447327 | Q25: =P25 -> 0.51447327
