Workbook

Sheet Cover
A1: Wipro Integrated Financial Model
A2: Fresh official-source build | Quarterly P&L FY16–Q1FY27 | Annual three statements FY16–FY30E | INR crore unless stated
A4: Cash-anchored three statements, client mining, bookings, AI revenue bridge and valuation
A6: Model scope | B6: Quarterly P&L only; annual P&L, detailed balance sheet and cash flow
A7: Historical period | B7: FY16–FY26 plus Q1 FY27 actual
A8: Forecast period | B8: FY27E–FY30E
A9: Source policy | B9: Official Wipro annual reports, quarterly IFRS statements and company data sheets; SEC company facts used for standardized history
A10: Cash policy | B10: Historical closing cash is anchored to the reported balance sheet; forecast cash is the output of CFO + CFI + CFF
A11: Forecast revenue | B11: Retained core + billable capacity + bookings realization − T&M AI deflation + explicit AI uplift + acquisitions
A12: AI disclosure policy | B12: No historical AI revenue is invented; forecast AI uplift is an editable scenario assumption
A13: Circularity policy | B13: One-way flow: assumptions / drivers → P&L → non-cash BS schedules → cash flow → cash → balance sheet
A14: Formatting | B14: Aptos Narrow 10; hardcoded actuals medium blue; formulas black; forecast columns pale green
A15: Model status | B15: =Checks!B6 -> OK

Sheet Summary
A1: Wipro Financial Summary
A2: Integrated performance, operating drivers, cash generation and valuation
A5: Metric | B5: Units | C5: FY16A | D5: FY17A | E5: FY18A | F5: FY19A | G5: FY20A | H5: FY21A | I5: FY22A | J5: FY23A | K5: FY24A | L5: FY25A | M5: FY26A | N5: FY27E | O5: FY28E | P5: FY29E | Q5: FY30E
A7: Revenue | B7: ₹ cr | C7: ='Annual P&L'!C7 -> 51244 | D7: ='Annual P&L'!D7 -> 55040.2 | E7: ='Annual P&L'!E7 -> 54487.1 | F7: ='Annual P&L'!F7 -> 58584.5 | G7: ='Annual P&L'!G7 -> 61023.2 | H7: ='Annual P&L'!H7 -> 61943 | I7: ='Annual P&L'!I7 -> 79093.4 | J7: ='Annual P&L'!J7 -> 90487.6 | ... Q7: ='Annual P&L'!Q7 -> 118382.92
A8: Revenue growth | B8: % | C8: ='Annual P&L'!C8 -> 0 | D8: ='Annual P&L'!D8 -> 0.074080868 | E8: ='Annual P&L'!E8 -> -0.010049019 | F8: ='Annual P&L'!F8 -> 0.075199451 | G8: ='Annual P&L'!G8 -> 0.041627052 | H8: ='Annual P&L'!H8 -> 0.015072956 | I8: ='Annual P&L'!I8 -> 0.2768739 | J8: ='Annual P&L'!J8 -> 0.14406006 | ... Q8: ='Annual P&L'!Q8 -> 0.085114922
A9: Gross margin | B9: % | C9: ='Annual P&L'!C11 -> 0.30387167 | D9: ='Annual P&L'!D11 -> 0.28862177 | E9: ='Annual P&L'!E11 -> 0.29235544 | F9: ='Annual P&L'!F11 -> 0.29497905 | G9: ='Annual P&L'!G11 -> 0.28537835 | H9: ='Annual P&L'!H11 -> 0.31678317 | I9: ='Annual P&L'!I11 -> 0.29719547 | J9: ='Annual P&L'!J11 -> 0.28670227 | ... Q9: ='Annual P&L'!Q11 -> 0.3
A10: EBITDA | B10: ₹ cr | C10: ='Annual P&L'!C15 -> 11182.5 | D10: ='Annual P&L'!D15 -> 11698.6 | E10: ='Annual P&L'!E15 -> 10541.8 | F10: ='Annual P&L'!F15 -> 11938.4 | G10: ='Annual P&L'!G15 -> 12659.2 | H10: ='Annual P&L'!H15 -> 15070.9 | I10: ='Annual P&L'!I15 -> 17119.7 | J10: ='Annual P&L'!J15 -> 17300.8 | ... Q10: ='Annual P&L'!Q15 -> 24386.881
A11: EBITDA margin | B11: % | C11: ='Annual P&L'!C16 -> 0.21822067 | D11: ='Annual P&L'!D16 -> 0.21254647 | E11: ='Annual P&L'!E16 -> 0.19347332 | F11: ='Annual P&L'!F16 -> 0.20378086 | G11: ='Annual P&L'!G16 -> 0.20744897 | H11: ='Annual P&L'!H16 -> 0.24330271 | I11: ='Annual P&L'!I16 -> 0.21644916 | J11: ='Annual P&L'!J16 -> 0.19119526 | ... Q11: ='Annual P&L'!Q16 -> 0.206
A12: EBIT | B12: ₹ cr | C12: ='Annual P&L'!C18 -> 9686 | D12: ='Annual P&L'!D18 -> 9387.9 | E12: ='Annual P&L'!E18 -> 8429.4 | F12: ='Annual P&L'!F18 -> 9991 | G12: ='Annual P&L'!G18 -> 10573 | H12: ='Annual P&L'!H18 -> 12305.3 | I12: ='Annual P&L'!I18 -> 14028.6 | J12: ='Annual P&L'!J18 -> 13960.6 | ... Q12: ='Annual P&L'!Q18 -> 21072.159
A13: EBIT margin | B13: % | C13: ='Annual P&L'!C19 -> 0.18901725 | D13: ='Annual P&L'!D19 -> 0.17056442 | E13: ='Annual P&L'!E19 -> 0.15470451 | F13: ='Annual P&L'!F19 -> 0.17053999 | G13: ='Annual P&L'!G19 -> 0.17326197 | H13: ='Annual P&L'!H19 -> 0.19865522 | I13: ='Annual P&L'!I19 -> 0.17736752 | J13: ='Annual P&L'!J19 -> 0.15428191 | ... Q13: ='Annual P&L'!Q19 -> 0.178
A14: Net income | B14: ₹ cr | C14: ='Annual P&L'!C29 -> 8907.5 | D14: ='Annual P&L'!D29 -> 8489.5 | E14: ='Annual P&L'!E29 -> 8008.1 | F14: ='Annual P&L'!F29 -> 9003.1 | G14: ='Annual P&L'!G29 -> 9721.8 | H14: ='Annual P&L'!H29 -> 10794.6 | I14: ='Annual P&L'!I29 -> 12219.1 | J14: ='Annual P&L'!J29 -> 11350 | ... Q14: ='Annual P&L'!Q29 -> 17320.917
A15: Net margin | B15: % | C15: ='Annual P&L'!C30 -> 0.17382523 | D15: ='Annual P&L'!D30 -> 0.15424181 | E15: ='Annual P&L'!E30 -> 0.1469724 | F15: ='Annual P&L'!F30 -> 0.15367717 | G15: ='Annual P&L'!G30 -> 0.15931318 | H15: ='Annual P&L'!H30 -> 0.17426666 | I15: ='Annual P&L'!I30 -> 0.1544895 | J15: ='Annual P&L'!J30 -> 0.12543155 | ... Q15: ='Annual P&L'!Q30 -> 0.14631264
A16: Diluted EPS | B16: ₹ / share | C16: ='Annual P&L'!C34 -> 18.092246 | D16: ='Annual P&L'!D34 -> 13.070563 | E16: ='Annual P&L'!E34 -> 12.622148 | F16: ='Annual P&L'!F34 -> 14.949593 | G16: ='Annual P&L'!G34 -> 16.624648 | H16: ='Annual P&L'!H34 -> 19.066147 | I16: ='Annual P&L'!I34 -> 22.289154 | J16: ='Annual P&L'!J34 -> 10.338876 | ... Q16: ='Annual P&L'!Q34 -> 17.909365
A17: CFO | B17: ₹ cr | C17: ='Annual Cash Flow'!C29 -> 7887.3 | D17: ='Annual Cash Flow'!D29 -> 9277.3 | E17: ='Annual Cash Flow'!E29 -> 8423.3 | F17: ='Annual Cash Flow'!F29 -> 11631.6 | G17: ='Annual Cash Flow'!G29 -> 10064.3 | H17: ='Annual Cash Flow'!H29 -> 14755 | I17: ='Annual Cash Flow'!I29 -> 11079.7 | J17: ='Annual Cash Flow'!J29 -> 13060.1 | ... Q17: ='Annual Cash Flow'!Q29 -> 19814.582
A18: Free cash flow | B18: ₹ cr | C18: ='Annual Cash Flow'!C59 -> 6492.2 | D18: ='Annual Cash Flow'!D59 -> 7192 | E18: ='Annual Cash Flow'!E59 -> 6236.3 | F18: ='Annual Cash Flow'!F59 -> 9353.5 | G18: ='Annual Cash Flow'!G59 -> 7714.6 | H18: ='Annual Cash Flow'!H59 -> 12797.3 | I18: ='Annual Cash Flow'!I59 -> 9064.4 | J18: ='Annual Cash Flow'!J59 -> 11576.7 | ... Q18: ='Annual Cash Flow'!Q59 -> 17683.69
A19: Closing cash | B19: ₹ cr | C19: ='Annual Balance Sheet'!C22 -> 9904.9 | D19: ='Annual Balance Sheet'!D22 -> 5271 | E19: ='Annual Balance Sheet'!E22 -> 4492.5 | F19: ='Annual Balance Sheet'!F22 -> 15852.9 | G19: ='Annual Balance Sheet'!G22 -> 14449.9 | H19: ='Annual Balance Sheet'!H22 -> 16979.3 | I19: ='Annual Balance Sheet'!I22 -> 10383.6 | J19: ='Annual Balance Sheet'!J22 -> 9188 | ... Q19: ='Annual Balance Sheet'!Q22 -> 19893.038
A20: Net cash + investments / debt & lease | B20: ₹ cr | C20: ='Annual Balance Sheet'!C62 -> 11167.9 | D20: ='Annual Balance Sheet'!D62 -> 20232.8 | E20: ='Annual Balance Sheet'!E62 -> 15576 | F20: ='Annual Balance Sheet'!F62 -> 27977.8 | G20: ='Annual Balance Sheet'!G62 -> 23689.4 | H20: ='Annual Balance Sheet'!H62 -> 24098.6 | I20: ='Annual Balance Sheet'!I62 -> 16956.2 | J20: ='Annual Balance Sheet'!J62 -> 22644.6 | ... Q20: ='Annual Balance Sheet'!Q62 -> 46219.439
A21: Headcount | B21: # | C21: ='Revenue Drivers'!C7 -> 172912 | D21: ='Revenue Drivers'!D7 -> 181482 | E21: ='Revenue Drivers'!E7 -> 163827 | F21: ='Revenue Drivers'!F7 -> 171425 | G21: ='Revenue Drivers'!G7 -> 182886 | H21: ='Revenue Drivers'!H7 -> 197712 | I21: ='Revenue Drivers'!I7 -> 243128 | J21: ='Revenue Drivers'!J7 -> 256921 | ... Q21: ='Revenue Drivers'!Q7 -> 268573.23
A22: Billable FTE | B22: # | C22: ='Revenue Drivers'!C12 -> 127657.83 | D22: ='Revenue Drivers'!D12 -> 137454.17 | E22: ='Revenue Drivers'!E12 -> 122835.07 | F22: ='Revenue Drivers'!F12 -> 133191.12 | G22: ='Revenue Drivers'!G12 -> 138245.89 | H22: ='Revenue Drivers'!H12 -> 156633.5 | I22: ='Revenue Drivers'!I12 -> 195679.32 | J22: ='Revenue Drivers'!J12 -> 194827.22 | ... Q22: ='Revenue Drivers'!Q12 -> 216148.81
A23: Total bookings | B23: $m | C23: ='Client Data'!C21 -> 0 | D23: ='Client Data'!D21 -> 0 | E23: ='Client Data'!E21 -> 0 | F23: ='Client Data'!F21 -> 0 | G23: ='Client Data'!G21 -> 0 | H23: ='Client Data'!H21 -> 0 | I23: ='Client Data'!I21 -> 0 | J23: ='Client Data'!J21 -> 0 | ... Q23: ='Client Data'!Q21 -> 21760.89
A24: Large-deal TCV | B24: $m | C24: ='Client Data'!C23 -> 0 | D24: ='Client Data'!D23 -> 0 | E24: ='Client Data'!E23 -> 0 | F24: ='Client Data'!F23 -> 0 | G24: ='Client Data'!G23 -> 0 | H24: ='Client Data'!H23 -> 0 | I24: ='Client Data'!I23 -> 0 | J24: ='Client Data'!J23 -> 0 | ... Q24: ='Client Data'!Q23 -> 10357.226
A25: Revenue per active client | B25: $m | C25: ='Client Data'!C17 -> 6.0067866 | D25: ='Client Data'!D17 -> 5.8235072 | E25: ='Client Data'!E17 -> 6.4584936 | F25: ='Client Data'!F17 -> 7.2827803 | G25: ='Client Data'!G17 -> 7.6873371 | H25: ='Client Data'!H17 -> 7.2647321 | I25: ='Client Data'!I17 -> 7.5645727 | J25: ='Client Data'!J17 -> 7.7444136 | ... Q25: ='Client Data'!Q17 -> 7.7439241
A26: AI revenue uplift | B26: ₹ cr | C26: ='Revenue Drivers'!C28 -> 0 | D26: ='Revenue Drivers'!D28 -> 0 | E26: ='Revenue Drivers'!E28 -> 0 | F26: ='Revenue Drivers'!F28 -> 0 | G26: ='Revenue Drivers'!G28 -> 0 | H26: ='Revenue Drivers'!H28 -> 0 | I26: ='Revenue Drivers'!I28 -> 0 | J26: ='Revenue Drivers'!J28 -> 0 | ... Q26: ='Revenue Drivers'!Q28 -> 1636.4569
A27: Reference share price | B27: ₹ / share | C27: =Valuation!C7 -> 105.7969 | D27: =Valuation!D7 -> 96.693771 | E27: =Valuation!E7 -> 105.43127 | F27: =Valuation!F7 -> 127.375 | G27: =Valuation!G7 -> 98.349998 | H27: =Valuation!H7 -> 207.075 | I27: =Valuation!I7 -> 295.95001 | J27: =Valuation!J7 -> 182.625 | ... Q27: =Valuation!Q7 -> 180.28999
A28: P/E | B28: x | C28: =Valuation!C15 -> 5.8476375 | D28: =Valuation!D15 -> 7.3978275 | E28: =Valuation!E15 -> 8.3528788 | F28: =Valuation!F15 -> 8.5202988 | G28: =Valuation!G15 -> 5.9159148 | H28: =Valuation!H15 -> 10.860873 | I28: =Valuation!I15 -> 13.277759 | J28: =Valuation!J15 -> 17.663912 | ... Q28: =Valuation!Q15 -> 10.0668
A29: EV / EBITDA | B29: x | C29: =Valuation!C17 -> 3.6934561 | D29: =Valuation!D17 -> 3.6232652 | E29: =Valuation!E17 -> 4.8566422 | F29: =Valuation!F17 -> 4.0659688 | G29: =Valuation!G17 -> 2.6606682 | H29: =Valuation!H17 -> 6.1631072 | I29: =Valuation!I17 -> 8.4599009 | J29: =Valuation!J17 -> 10.255009 | ... Q29: =Valuation!Q17 -> 5.3496848
A30: Implied target price | B30: ₹ / share | C30: =Valuation!C23 -> 0 | D30: =Valuation!D23 -> 0 | E30: =Valuation!E23 -> 0 | F30: =Valuation!F23 -> 0 | G30: =Valuation!G23 -> 0 | H30: =Valuation!H23 -> 0 | I30: =Valuation!I23 -> 0 | J30: =Valuation!J23 -> 0 | ... Q30: =Valuation!Q23 -> 367.14198
A31: Upside / (downside) | B31: % | C31: =Valuation!C24 -> 0 | D31: =Valuation!D24 -> 0 | E31: =Valuation!E24 -> 0 | F31: =Valuation!F24 -> 0 | G31: =Valuation!G24 -> 0 | H31: =Valuation!H24 -> 0 | I31: =Valuation!I24 -> 0 | J31: =Valuation!J24 -> 0 | ... Q31: =Valuation!Q24 -> 1.0363969

Sheet Sources
A1: Sources & Data Conventions
A2: Primary-source register; unavailable disclosures stay blank and derived values are explicitly identified
A5: ID | B5: Data / Period | C5: Units | D5: Primary source | E5: Use | F5: Status | G5: Notes
A6: S1 | B6: Annual reports FY16–FY26 | C6: ₹ mn | D6: https://www.wipro.com/investors/annual-reports/ | E6: Audited P&L, balance sheet and cash flow | F6: Loaded | G6: FY26 annual report manually controlled because SEC filing uses extension tags
A7: S2 | B7: Quarterly IFRS financials FY16–Q1FY27 | C7: ₹ mn | D7: https://www.wipro.com/investors/quarterly-results/ | E7: Quarterly consolidated P&L | F7: Loaded | G7: Q4 is annual less Q1–Q3 where needed, ensuring audited annual roll-up
A8: S3 | B8: Quarterly data sheets FY16–Q1FY27 | C8: $m / % / # | D8: https://www.wipro.com/investors/quarterly-results/ | E8: USD revenue, margin, vertical/geography/currency mix, clients, headcount, utilization and bookings | F8: Loaded | G8: Definitions and classifications change over time and are kept separate
A9: S4 | B9: SEC company facts | C9: INR / shares | D9: https://data.sec.gov/api/xbrl/companyfacts/CIK0001123799.json | E9: Standardized FY16–FY25 IFRS history and shares | F9: Loaded | G9: Latest-filed comparative selected for each fiscal period
A10: S5 | B10: WIPRO.NS daily prices | C10: ₹ / share | D10: https://query1.finance.yahoo.com/v8/finance/chart/WIPRO.NS | E10: Market-data tab and historical FY-end valuation | F10: Loaded | G10: No external valuation opinion is imported
A11: S6 | B11: Q1 FY27 Wipro results | C11: ₹ mn / $m | D11: https://www.wipro.com/investors/quarterly-results/ | E11: Q1 FY27 actual P&L and operating metrics | F11: Loaded | G11: Revenue ₹244,786m; IT services revenue $2,614.5m; bookings $3,370m
A12: S7 | B12: Historical AI revenue | C12: n/a | D12: n/a | E12: Forecast policy | F12: Not disclosed | G12: No historical AI revenue is hardcoded; model uses a scenario-driven incremental uplift
A13: S8 | B13: Derived interim D&A | C13: ₹ cr | D13: Audited annual D&A less reported quarters | E13: Quarterly EBITDA bridge | F13: Derived | G13: Only used where the interim D&A table was image-only; allocation is revenue-weighted and annual total is exact
A14: S9 | B14: Cash-flow residual lines | C14: ₹ cr | D14: Audited CFS totals | E14: Historical detailed CFS bridge | F14: Calculated | G14: Other CFO / CFI / CFF is a formula residual, never an invented hardcode

Sheet Assumptions
A1: Forecast Assumptions
A2: Blue text on yellow = editable; every forecast output is formula-linked
A5: Driver | B5: Units | C5: FY27E | D5: FY28E | E5: FY29E | F5: FY30E | G5: Logic / interpretation
A6: Total headcount growth | B6: % | C6: 0.015 | D6: 0.025 | E6: 0.03 | F6: 0.035 | G6: Closing headcount growth
A7: Service employee share | B7: % | C7: 0.935 | D7: 0.936 | E7: 0.937 | F7: 0.938 | G7: Headcount less sales / support
A8: Utilization / billable rate | B8: % | C8: 0.845 | D8: 0.85 | E8: 0.855 | F8: 0.858 | G8: Billable FTE conversion
A9: Pricing / productivity uplift | B9: % | C9: 0.02 | D9: 0.025 | E9: 0.03 | F9: 0.03 | G9: Revenue per billable FTE improvement
A10: Capacity uplift realization | B10: % | C10: 0.65 | D10: 0.7 | E10: 0.75 | F10: 0.75 | G10: Recognized share of billable capacity / productivity uplift
A11: Core revenue retention | B11: % | C11: 0.97 | D11: 0.972 | E11: 0.974 | F11: 0.975 | G11: Prior-year revenue retained before incremental drivers
A12: FPP mix | B12: % | C12: 0.55 | D12: 0.56 | E12: 0.57 | F12: 0.58 | G12: Fixed-price / managed-services mix
A13: AI deflation on T&M revenue | B13: % | C13: 0.01 | D13: 0.013 | E13: 0.016 | F13: 0.018 | G13: Explicit T&M productivity / pricing drag
A14: Total bookings growth | B14: % | C14: 0.06 | D14: 0.07 | E14: 0.08 | F14: 0.08 | G14: Bookings scenario
A15: Bookings current-year realization | B15: % | C15: 0.02 | D15: 0.022 | E15: 0.024 | F15: 0.025 | G15: Incremental recognized revenue from bookings
A16: AI uplift / prior-year revenue | B16: % | C16: 0.006 | D16: 0.01 | E16: 0.013 | F16: 0.015 | G16: Incremental AI-led recognized revenue; not historical disclosure
A17: Acquisition revenue / prior-year revenue | B17: % | C17: 0.004 | D17: 0.003 | E17: 0.002 | F17: 0.002 | G17: Separate acquisition contribution
... A57: FX effect on cash | B57: ₹ cr | C57: 0 | D57: 0 | E57: 0 | F57: 0 | G57: Forecast cash translation adjustment

Sheet Raw Financials
A1: Raw Reported Financials — Source Layer
A2: Hardcoded official reported inputs only; calculations live downstream
A4: Annual reported P&L
A5: Metric | B5: Units | C5: FY16A | D5: FY17A | E5: FY18A | F5: FY19A | G5: FY20A | H5: FY21A | I5: FY22A | J5: FY23A | K5: FY24A | L5: FY25A | M5: FY26A
A6: Revenue | B6: ₹ cr | C6: 51244 | D6: 55040.2 | E6: 54487.1 | F6: 58584.5 | G6: 61023.2 | H6: 61943 | I6: 79093.4 | J6: 90487.6 | K6: 89760.3 | L6: 89088.4 | M6: 92624
A7: Cost of revenue | B7: ₹ cr | C7: 35672.4 | D7: 39154.4 | E7: 38557.5 | F7: 41303.3 | G7: 43608.5 | H7: 42320.5 | I7: 55587.2 | J7: 64544.6 | K7: 63149.7 | L7: 61780.2 | M7: 65619.2
A8: Gross profit | B8: ₹ cr | C8: 15571.6 | D8: 15885.8 | E8: 15929.6 | F8: 17281.2 | G8: 17414.7 | H8: 19622.5 | I8: 23506.2 | J8: 25943 | K8: 26610.6 | L8: 27308.2 | M8: 27004.8
A9: Selling & marketing | B9: ₹ cr | C9: 3409.7 | D9: 4081.7 | E9: 4234.9 | F9: 4451 | G9: 4290.7 | H9: 4140 | I9: 5493.5 | J9: 6515.7 | K9: 6997.2 | L9: 6437.8 | M9: 5921.6
A10: General & administrative | B10: ₹ cr | C10: 2862.6 | D10: 3202.1 | E10: 3414.1 | F10: 3595.1 | G10: 2982.3 | H10: 3468.6 | I10: 4638.2 | J10: 5913.9 | K10: 6037.5 | L10: 5746.5 | M10: 6143.4
A11: Other operating income / FX | B11: ₹ cr
A12: EBITDA | B12: ₹ cr | C12: 11182.5 | D12: 11698.6 | E12: 10541.8 | F12: 11938.4 | G12: 12659.2 | H12: 15070.9 | I12: 17119.7 | J12: 17300.8 | K12: 17017 | L12: 18085 | M12: 18035.8
A13: D&A | B13: ₹ cr | C13: 1496.5 | D13: 2310.7 | E13: 2112.4 | F13: 1947.4 | G13: 2086.2 | H13: 2765.6 | I13: 3091.1 | J13: 3340.2 | K13: 3407.1 | L13: 2957.9 | M13: 2910.7
A14: EBIT | B14: ₹ cr | C14: 9686 | D14: 9387.9 | E14: 8429.4 | F14: 9991 | G14: 10573 | H14: 12305.3 | I14: 14028.6 | J14: 13960.6 | K14: 13609.9 | L14: 15127.1 | M14: 15125.1
A15: Finance expense | B15: ₹ cr | C15: 537.8 | D15: 594.2 | E15: 583 | F15: 737.5 | G15: 732.8 | H15: 508.8 | I15: 532.5 | J15: 1007.7 | K15: 1255.2 | L15: 1477 | M15: 1457.7
A16: Finance & other income | B16: ₹ cr | C16: 2345.1 | D16: 2241.9 | E16: 2399.9 | F16: 2292.3 | G16: 2408.1 | H16: 2091.2 | I16: 1625.7 | J16: 1818.5 | K16: 2389.6 | L16: 3820.2 | M16: 3649.1
A17: Share of associate / JV | B17: ₹ cr | C17: 0 | D17: 0 | E17: 1.1 | F17: -4.3 | G17: 2.9 | H17: 13 | I17: 5.7 | J17: -5.7 | K17: -23.3 | L17: 25.4 | M17: 25.7
A18: PBT | B18: ₹ cr | C18: 11493.3 | D18: 11035.6 | E18: 10247.4 | F18: 11541.5 | G18: 12251.2 | H18: 13900.7 | I18: 15127.5 | J18: 14765.7 | K18: 14721 | L18: 17495.7 | M18: 17342.2
A19: Tax | B19: ₹ cr | C19: 2536.6 | D19: 2521.3 | E19: 2239 | F19: 2524.2 | G19: 2479.9 | H19: 3034.5 | I19: 2894.6 | J19: 3399.2 | K19: 3608.9 | L19: 4277.7 | M19: 4076.7
A20: Profit incl. NCI | B20: ₹ cr | C20: 8956.7 | D20: 8514.3 | E20: 8008.4 | F20: 9017.3 | G20: 9771.3 | H20: 10866.2 | I20: 12232.9 | J20: 11366.5 | K20: 11112.1 | L20: 13218 | M20: 13265.5
A21: NCI | B21: ₹ cr | C21: 49.2 | D21: 24.8 | E21: 0.3 | F21: 14.2 | G21: 49.5 | H21: 71.6 | I21: 13.8 | J21: 16.5 | K21: 66.9 | L21: 82.6 | M21: 68.1
A22: Net income attributable | B22: ₹ cr | C22: 8907.5 | D22: 8489.5 | E22: 8008.1 | F22: 9003.1 | G22: 9721.8 | H22: 10794.6 | I22: 12219.1 | J22: 11350 | K22: 11045.2 | L22: 13135.4 | M22: 13197.4
A23: Basic EPS | B23: ₹ / share | C23: 18.13 | D23: 13.11 | E23: 12.64 | F23: 14.99 | G23: 16.67 | H23: 19.11 | I23: 22.35 | J23: 10.36 | K23: 10.44 | L23: 12.56 | M23: 12.6
... A26: Diluted weighted shares | B26: m | C26: 4923.3798 | D26: 6495.1295 | E26: 6344.4826 | F26: 6022.3044 | G26: 5847.8232 | H26: 5661.6578 | I26: 5482.0834 | J26: 10977.982 | K26: 10611.425 | L26: 10488.939 | M26: 10503.423
A30: Quarterly reported P&L — Q4 derived as annual less Q1–Q3 where required
A31: Metric | B31: Units | C31: Q1 FY16A | D31: Q2 FY16A | E31: Q3 FY16A | F31: Q4 FY16A | G31: Q1 FY17A | H31: Q2 FY17A | I31: Q3 FY17A | J31: Q4 FY17A | K31: Q1 FY18A | L31: Q2 FY18A | M31: Q3 FY18A | N31: Q4 FY18A | O31: Q1 FY19A | P31: Q2 FY19A | Q31: Q3 FY19A | R31: Q4 FY19A | S31: Q1 FY20A | T31: Q2 FY20A | U31: Q3 FY20A | V31: Q4 FY20A | W31: Q1 FY21A | X31: Q2 FY21A | Y31: Q3 FY21A | Z31: Q4 FY21A | AA31: Q1 FY22A | AB31: Q2 FY22A | AC31: Q3 FY22A | AD31: Q4 FY22A | AE31: Q1 FY23A | AF31: Q2 FY23A | AG31: Q3 FY23A | AH31: Q4 FY23A | AI31: Q1 FY24A | AJ31: Q2 FY24A | AK31: Q3 FY24A | AL31: Q4 FY24A | AM31: Q1 FY25A | AN31: Q2 FY25A | AO31: Q3 FY25A | AP31: Q4 FY25A | AQ31: Q1 FY26A | AR31: Q2 FY26A | AS31: Q3 FY26A | AT31: Q4 FY26A | AU31: Q1 FY27A
A32: Revenue | B32: ₹ cr | C32: 12237.6 | D32: 12513.5 | E32: 12860.5 | F32: 13632.4 | G32: 13599.2 | H32: 13765.7 | I32: 13687.8 | J32: 13987.5 | K32: 13626.1 | L32: 13423.4 | M32: 13669 | N32: 13768.6 | O32: 13977.7 | P32: 14541 | Q32: 15059.5 | R32: 15006.3 | S32: 14716.1 | T32: 15125.6 | U32: 15470.5 | V32: 15711 | W32: 14913.1 | X32: 15114.5 | Y32: 15670 | Z32: 16245.4 | AA32: 18252.4 | AB32: 19667.4 | AC32: 20313.6 | AD32: 20860 | AE32: 21528.6 | AF32: 22539.7 | AG32: 23229 | AH32: 23190.3 | AI32: 22831 | AJ32: 22515.9 | AK32: 22205.1 | AL32: 22208.3 | AM32: 21963.8 | AN32: 22301.6 | AO32: 22318.8 | AP32: 22504.2 | AQ32: 22134.6 | AR32: 22697.3 | AS32: 23555.8 | AT32: 24236.3 | AU32: 24478.6
A33: Cost of revenue | B33: ₹ cr | C33: 8478.7 | D33: 8582.4 | E33: 9027 | F33: 9584.3 | G33: 9638.9 | H33: 9780.8 | I33: 9657.6 | J33: 10077.1 | K33: 9711.1 | L33: 9469.4 | M33: 9597.6 | N33: 9779.4 | O33: 10035 | P33: 10177 | Q33: 10397.1 | R33: 10694.2 | S33: 10427.3 | T33: 10800.6 | U33: 10967.3 | V33: 11413.3 | W33: 10370 | X33: 10538.7 | Y33: 10431.3 | Z33: 10980.5 | AA33: 12756.7 | AB33: 13756.2 | AC33: 14277.8 | AD33: 14796.5 | AE33: 15560 | AF33: 16383.5 | AG33: 16327.3 | AH33: 16273.8 | AI33: 16126.1 | AJ33: 15919.1 | AK33: 15382.6 | AL33: 15721.9 | AM33: 15330.6 | AN33: 15504.9 | AO33: 15392.2 | AP33: 15552.5 | AQ33: 15724.7 | AR33: 15983.2 | AS33: 16719.9 | AT33: 17191.4 | AU33: 17490
A34: Gross profit | B34: ₹ cr | C34: 3758.9 | D34: 3931.1 | E34: 3833.5 | F34: 4048.1 | G34: 3960.3 | H34: 3984.9 | I34: 4030.2 | J34: 3910.4 | K34: 3915 | L34: 3954 | M34: 4071.4 | N34: 3989.2 | O34: 3942.7 | P34: 4364 | Q34: 4662.4 | R34: 4312.1 | S34: 4288.8 | T34: 4325 | U34: 4503.2 | V34: 4297.7 | W34: 4543.1 | X34: 4575.8 | Y34: 5238.7 | Z34: 5264.9 | AA34: 5495.7 | AB34: 5911.2 | AC34: 6035.8 | AD34: 6063.5 | AE34: 5968.6 | AF34: 6156.2 | AG34: 6901.7 | AH34: 6916.5 | AI34: 6704.9 | AJ34: 6596.8 | AK34: 6822.5 | AL34: 6486.4 | AM34: 6633.2 | AN34: 6796.7 | AO34: 6926.6 | AP34: 6951.7 | AQ34: 6409.9 | AR34: 6714.1 | AS34: 6835.9 | AT34: 7044.9 | AU34: 6988.6
A35: Selling & marketing | B35: ₹ cr | C35: 804.4 | D35: 870.8 | E35: 836.2 | F35: 898.3 | G35: 1014.1 | H35: 961.4 | I35: 922.6 | J35: 1183.6 | K35: 1014.6 | L35: 986.7 | M35: 1107.3 | N35: 1126.3 | O35: 1081.3 | P35: 1081.4 | Q35: 1188.9 | R35: 1099.4 | S35: 1095.3 | T35: 1062.9 | U35: 1103 | V35: 1029.5 | W35: 978.9 | X35: 960.6 | Y35: 1132.6 | Z35: 1067.9 | AA35: 1301.7 | AB35: 1385.2 | AC35: 1398.8 | AD35: 1407.8 | AE35: 1535.9 | AF35: 1514 | AG35: 1775.2 | AH35: 1690.6 | AI35: 1658.4 | AJ35: 1876.7 | AK35: 1917.8 | AL35: 1544.3 | AM35: 1584.4 | AN35: 1738.8 | AO35: 1608.1 | AP35: 1506.5 | AQ35: 1528.5 | AR35: 1492 | AS35: 1500.8 | AT35: 1400.3 | AU35: 1649.6
A36: General & administrative | B36: ₹ cr | C36: 685.3 | D36: 684.7 | E36: 701 | F36: 791.6 | G36: 759.9 | H36: 854.5 | I36: 861 | J36: 726.7 | K36: 726.4 | L36: 708.5 | M36: 999.1 | N36: 980.1 | O36: 860.8 | P36: 1369.6 | Q36: 697.8 | R36: 666.9 | S36: 811.9 | T36: 652.7 | U36: 749.6 | V36: 768.1 | W36: 1000.6 | X36: 817.7 | Y36: 781.4 | Z36: 868.9 | AA36: 1053 | AB36: 1128.8 | AC36: 1203.6 | AD36: 1252.8 | AE36: 1347.1 | AF36: 1497.6 | AG36: 1502 | AH36: 1567.2 | AI36: 1588.7 | AJ36: 1412.4 | AK36: 1644.4 | AL36: 1392 | AM36: 1421.3 | AN36: 1303.4 | AO36: 1462.9 | AP36: 1558.9 | AQ36: 1327.2 | AR36: 1495 | AS36: 1840.4 | AT36: 1480.8 | AU36: 1496.3
A37: Other operating income / FX | B37: ₹ cr | C37: 133 | D37: 53.3 | E37: 91.1 | F37: 109.3 | G37: 98.4 | H37: 128.1 | I37: 76.7 | J37: 482.7 | K37: 35.3 | L37: 45.3 | M37: 12.5 | N37: 55.7 | O37: 330 | P37: 148.6 | Q37: 91.1 | R37: 186.2 | S37: 155.7 | T37: 64.1 | U37: 72.7 | V37: 138.8 | W37: 130.2 | X37: 16 | Y37: 56.6 | Z37: 88.6 | AA37: 331 | AB37: 94.8 | AC37: 120.1 | AD37: 108.2 | AE37: 103.4 | AF37: 105.7 | AG37: 139.1 | AH37: 99 | AI37: -6.2 | AJ37: 26.8 | AK37: 26.2 | AL37: -12.8 | AM37: -20.6 | AN37: -39.6 | AO37: 41 | AP37: 22.4 | AQ37: 18.2 | AR37: 55.8 | AS37: 78.8 | AT37: 32.5 | AU37: 77.9
A38: EBITDA | B38: ₹ cr | C38: 2738.9 | D38: 2781.9 | E38: 2763.8 | F38: 2897.9 | G38: 2751.2 | H38: 2782 | I38: 2864.5 | J38: 3300.9 | K38: 2703.6 | L38: 2824.1 | M38: 2505.4 | N38: 2508.7 | O38: 2788.3368 | P38: 2498.6 | Q38: 3359.9632 | R38: 3291.5 | S38: 3032.8 | T38: 3154.9 | U38: 3252.8 | V38: 3218.7 | W38: 3359.6326 | X38: 3488.3246 | Y38: 4080.9263 | Z38: 4142.0165 | AA38: 4185.3338 | AB38: 4260.6343 | AC38: 4347.3889 | AD38: 4326.3431 | AE38: 3983.6926 | AF38: 4082.3157 | AG38: 4621.0601 | AH38: 4613.7315 | AI38: 4318.2136 | AJ38: 4189.1531 | AK38: 4129.3559 | AL38: 4380.2773 | AM38: 4336.1389 | AN38: 4455.3545 | AO38: 4637.6255 | AP38: 4655.8812 | AQ38: 4267.9776 | AR38: 4496.1604 | AS38: 4313.7387 | AT38: 4957.9233
A39: D&A | B39: ₹ cr | C39: 336.7 | D39: 353 | E39: 376.4 | F39: 430.4 | G39: 466.5 | H39: 484.9 | I39: 541.2 | J39: 818.1 | K39: 494.3 | L39: 520 | M39: 527.9 | N39: 570.2 | O39: 457.7368 | P39: 437 | Q39: 493.1632 | R39: 559.5 | S39: 495.5 | T39: 481.4 | U39: 529.5 | V39: 579.8 | W39: 665.83261 | X39: 674.82462 | Y39: 699.6263 | Z39: 725.31647 | AA39: 713.33378 | AB39: 768.6343 | AC39: 793.88886 | AD39: 815.24307 | AE39: 794.69264 | AF39: 832.01572 | AG39: 857.46009 | AH39: 856.03155 | AI39: 866.61364 | AJ39: 854.65315 | AK39: 842.85588 | AL39: 842.97734 | AM39: 729.23887 | AN39: 740.45445 | AO39: 741.02553 | AP39: 747.18115 | AQ39: 695.57761 | AR39: 713.2604 | AS39: 740.23868 | AT39: 761.62332
A40: EBIT | B40: ₹ cr | C40: 2402.2 | D40: 2428.9 | E40: 2387.4 | F40: 2467.5 | G40: 2284.7 | H40: 2297.1 | I40: 2323.3 | J40: 2482.8 | K40: 2209.3 | L40: 2304.1 | M40: 1977.5 | N40: 1938.5 | O40: 2330.6 | P40: 2061.6 | Q40: 2866.8 | R40: 2732 | S40: 2537.3 | T40: 2673.5 | U40: 2723.3 | V40: 2638.9 | W40: 2693.8 | X40: 2813.5 | Y40: 3381.3 | Z40: 3416.7 | AA40: 3472 | AB40: 3492 | AC40: 3553.5 | AD40: 3511.1 | AE40: 3189 | AF40: 3250.3 | AG40: 3763.6 | AH40: 3757.7 | AI40: 3451.6 | AJ40: 3334.5 | AK40: 3286.5 | AL40: 3537.3 | AM40: 3606.9 | AN40: 3714.9 | AO40: 3896.6 | AP40: 3908.7 | AQ40: 3572.4 | AR40: 3782.9 | AS40: 3573.5 | AT40: 4196.3 | AU40: 3920.6
A41: Finance expense | B41: ₹ cr | C41: 128.6 | D41: 158.9 | E41: 142.3 | F41: 108 | G41: 133.6 | H41: 142.8 | I41: 136.6 | J41: 181.2 | K41: 147.4 | L41: 138.6 | M41: 120.5 | N41: 176.5 | O41: 164.9 | P41: 156.9 | Q41: 162.7 | R41: 253 | S41: 158.4 | T41: 224.7 | U41: 184.4 | V41: 165.3 | W41: 129.9 | X41: 126.7 | Y41: 140 | Z41: 112.2 | AA41: 74.6 | AB41: 145.9 | AC41: 140.3 | AD41: 171.7 | AE41: 204.5 | AF41: 227 | AG41: 290.2 | AH41: 286 | AI41: 308.6 | AJ41: 303.3 | AK41: 312.5 | AL41: 330.8 | AM41: 328.8 | AN41: 356.9 | AO41: 414.6 | AP41: 376.7 | AQ41: 360.8 | AR41: 361.2 | AS41: 365.6 | AT41: 370.1 | AU41: 472.8
A42: Finance & other income | B42: ₹ cr | C42: 524.2 | D42: 619.4 | E42: 622.7 | F42: 578.8 | G42: 520 | H42: 510.5 | I42: 571.9 | J42: 639.5 | K42: 620 | L42: 666.1 | M42: 613.4 | N42: 500.4 | O42: 519.7 | P42: 513.6 | Q42: 536.2 | R42: 722.8 | S42: 694.7 | T42: 685.7 | U42: 537 | V42: 490.7 | W42: 528.1 | X42: 520.9 | Y42: 597.5 | Z42: 444.7 | AA42: 461.9 | AB42: 411.4 | AC42: 357.8 | AD42: 394.6 | AE42: 369 | AF42: 404 | AG42: 499.2 | AH42: 546.3 | AI42: 654.2 | AJ42: 481 | AK42: 578.5 | AL42: 675.9 | AM42: 748 | AN42: 919.5 | AO42: 970.8 | AP42: 1181.9 | AQ42: 1041.7 | AR42: 845.5 | AS42: 923.2 | AT42: 838.7 | AU42: 887.2
A43: Share of associate / JV | B43: ₹ cr | C43: 0 | D43: 0 | E43: 0 | F43: 0 | G43: 0 | H43: 0 | I43: 0 | J43: 0 | K43: -0.1 | L43: 0.5 | M43: 1 | N43: -0.3 | O43: -5.3 | P43: 2 | Q43: 0.7 | R43: -1.7 | S43: -1.6 | T43: -0.2 | U43: 3.4 | V43: 1.3 | W43: 3.1 | X43: -0.6 | Y43: 10.1 | Z43: 0.4 | AA43: 0.7 | AB43: -1 | AC43: 7.6 | AD43: -1.6 | AE43: -1.5 | AF43: -7.2 | AG43: 2.6 | AH43: 0.4 | AI43: 0.3 | AJ43: -3 | AK43: -0.4 | AL43: -20.2 | AM43: -4.5 | AN43: 0.3 | AO43: 0.5 | AP43: 29.1 | AQ43: 5 | AR43: 15.2 | AS43: 2.8 | AT43: 2.7 | AU43: -0.5
A44: PBT | B44: ₹ cr | C44: 2797.8 | D44: 2889.4 | E44: 2867.8 | F44: 2938.3 | G44: 2671.1 | H44: 2664.8 | I44: 2758.6 | J44: 2941.1 | K44: 2681.8 | L44: 2832.1 | M44: 2471.4 | N44: 2262.1 | O44: 2680.1 | P44: 2420.3 | Q44: 3241 | R44: 3200.1 | S44: 3072 | T44: 3134.3 | U44: 3079.3 | V44: 2965.6 | W44: 3095.1 | X44: 3207.1 | Y44: 3848.9 | Z44: 3749.6 | AA44: 3860 | AB44: 3756.5 | AC44: 3778.6 | AD44: 3732.4 | AE44: 3352 | AF44: 3420.1 | AG44: 3975.2 | AH44: 4018.4 | AI44: 3797.5 | AJ44: 3509.2 | AK44: 3552.1 | AL44: 3862.2 | AM44: 4021.6 | AN44: 4277.8 | AO44: 4453.3 | AP44: 4743 | AQ44: 4258.3 | AR44: 4282.4 | AS44: 4133.9 | AT44: 4667.6 | AU44: 4334.5
A45: Tax | B45: ₹ cr | C45: 594.5 | D45: 648.6 | E45: 624.8 | F45: 668.7 | G45: 612.2 | H45: 590.9 | I45: 644 | J45: 674.2 | K45: 599.4 | L45: 642.6 | M45: 535.5 | N45: 461.5 | O45: 586.5 | P45: 534.7 | Q45: 696.6 | R45: 706.4 | S45: 669.9 | T45: 573.1 | U45: 616.4 | V45: 620.5 | W45: 683.8 | X45: 722.8 | Y45: 852.4 | Z45: 775.5 | AA45: 622.5 | AB45: 825.9 | AC45: 806.3 | AD45: 639.9 | AE45: 793.1 | AF45: 771 | AG45: 910.2 | AH45: 924.9 | AI45: 911.5 | AJ45: 841.9 | AK45: 851.5 | AL45: 1004 | AM45: 985 | AN45: 1051.2 | AO45: 1086.6 | AP45: 1154.9 | AQ45: 921.8 | AR45: 1020 | AS45: 988.9 | AT45: 1146 | AU45: 978.2
A46: Profit incl. NCI | B46: ₹ cr | C46: 2203.3 | D46: 2240.8 | E46: 2243 | F46: 2269.6 | G46: 2058.9 | H46: 2073.9 | I46: 2114.6 | J46: 2266.9 | K46: 2082.4 | L46: 4119 | M46: 1935.9 | N46: -128.9 | O46: 2093.6 | P46: 1885.6 | Q46: 2544.4 | R46: 2493.7 | S46: 2402.1 | T46: 2561.2 | U46: 2462.9 | V46: 2345.1 | W46: 2411.3 | X46: 2484.3 | Y46: 2996.5 | Z46: 2974.1 | AA46: 3237.5 | AB46: 2930.6 | AC46: 2972.3 | AD46: 3092.5 | AE46: 2558.9 | AF46: 2649.1 | AG46: 3065 | AH46: 3093.5 | AI46: 2886 | AJ46: 2667.3 | AK46: 2700.6 | AL46: 2858.2 | AM46: 3036.6 | AN46: 3226.6 | AO46: 3366.7 | AP46: 3588.1 | AQ46: 3336.5 | AR46: 3262.4 | AS46: 3145 | AT46: 3521.6 | AU46: 3356.3
A47: NCI | B47: ₹ cr | C47: 15.6 | D47: 5.4 | E47: 8.9 | F47: 19.3 | G47: 7.1 | H47: 6.7 | I47: 5.2 | J47: 5.8 | K47: 5.9 | L47: 1927.3 | M47: -1.2 | N47: -1931.7 | O47: -27 | P47: -3.3 | Q47: 34.1 | R47: 10.4 | S47: 14.7 | T47: 8.6 | U47: 7.1 | V47: 19.1 | W47: 21.1 | X47: 18.7 | Y47: 29.8 | Z47: 2 | AA47: 5.4 | AB47: -0.1 | AC47: 3.3 | AD47: 5.2 | AE47: -4.7 | AF47: -9.9 | AG47: 12.1 | AH47: 19 | AI47: 15.9 | AJ47: 21 | AK47: 6.4 | AL47: 23.6 | AM47: 33.4 | AN47: 17.8 | AO47: 12.9 | AP47: 18.5 | AQ47: 6.1 | AR47: 16.2 | AS47: 26 | AT47: 19.8 | AU47: 4.3
A48: Net income attributable | B48: ₹ cr | C48: 2187.7 | D48: 2235.4 | E48: 2234.1 | F48: 2250.3 | G48: 2051.8 | H48: 2067.2 | I48: 2109.4 | J48: 2261.1 | K48: 2076.5 | L48: 2191.7 | M48: 1937.1 | N48: 1802.8 | O48: 2120.6 | P48: 1888.9 | Q48: 2510.3 | R48: 2483.3 | S48: 2387.4 | T48: 2552.6 | U48: 2455.8 | V48: 2326 | W48: 2390.2 | X48: 2465.6 | Y48: 2966.7 | Z48: 2972.1 | AA48: 3232.1 | AB48: 2930.7 | AC48: 2969 | AD48: 3087.3 | AE48: 2563.6 | AF48: 2659 | AG48: 3052.9 | AH48: 3074.5 | AI48: 2870.1 | AJ48: 2646.3 | AK48: 2694.2 | AL48: 2834.6 | AM48: 3003.2 | AN48: 3208.8 | AO48: 3353.8 | AP48: 3569.6 | AQ48: 3330.4 | AR48: 3246.2 | AS48: 3119 | AT48: 3501.8 | AU48: 3352
A53: Annual reported balance sheet
A54: Metric | B54: Units | C54: FY16A | D54: FY17A | E54: FY18A | F54: FY19A | G54: FY20A | H54: FY21A | I54: FY22A | J54: FY23A | K54: FY24A | L54: FY25A | M54: FY26A
A55: PPE | B55: ₹ cr | C55: 6495.2 | D55: 6979.4 | E55: 6444.3 | F55: 7060.1 | G55: 8112 | H55: 8519.2 | I55: 9089.8 | J55: 8865.9 | K55: 8160.8 | L55: 8068.4 | M55: 8178.7
A56: ROU assets | B56: ₹ cr | F56: 1326.6 | G56: 1674.8 | H56: 1642 | I56: 1887 | J56: 1870.2 | K56: 1795.5 | L56: 2559.8 | M56: 2828.7
A57: Goodwill | B57: ₹ cr | C57: 10199.1 | D57: 12579.6 | E57: 11758.4 | F57: 11698 | G57: 13101.2 | H57: 13912.7 | I57: 24698.9 | J57: 30797 | K57: 31600.2 | L57: 32501.4 | M57: 38739.9
A58: Intangibles | B58: ₹ cr | C58: 1584.1 | D58: 1592.2 | E58: 1811.3 | F58: 1376.2 | G58: 1636.2 | H58: 1308.5 | I58: 4355.5 | J58: 4304.5 | K58: 3274.8 | L58: 2745 | M58: 2917.6
A59: Non-current investments | B59: ₹ cr | C59: 490.7 | M59: 2805.3
A60: Equity-method investments | B60: ₹ cr | M60: 212.6
A61: Non-current receivables | B61: ₹ cr | D61: 399.8 | E61: 444.6 | F61: 437.3 | G61: 604.9 | H61: 435.8 | I61: 476.5 | J61: 86.3 | K61: 404.5 | L61: 29.9 | M61: 34.9
A62: Non-current unbilled | B62: ₹ cr | M62: 743.3
A63: Other non-current financial assets | B63: ₹ cr | D63: 2.6 | E63: 418.6 | F63: 514.6 | G63: 588.1 | H63: 608.8 | I63: 608.4 | J63: 633 | K63: 555 | L63: 466.4 | M63: 625.9
A64: Deferred tax assets | B64: ₹ cr | C64: 380 | D64: 309.8 | E64: 690.8 | F64: 560.4 | G64: 600.5 | H64: 166.4 | I64: 229.8 | J64: 210 | K64: 181.7 | L64: 256.1 | M64: 524.2
A65: Non-current tax assets | B65: ₹ cr | C65: 1175.1 | D65: 1200.8 | E65: 1834.9 | F65: 2060.3 | G65: 1141.4 | H65: 1432.3 | I65: 1025.6 | J65: 1192.2 | K65: 904.3 | L65: 723 | M65: 778.7
A66: Other non-current assets | B66: ₹ cr | C66: 1582.8 | D66: 1679.3 | E66: 1572.6 | F66: 2101.8 | M66: 901
A67: Total non-current assets | B67: ₹ cr | C67: 21933 | D67: 25461.8 | E67: 25448.4 | F67: 26126.5 | G67: 29721.1 | H67: 30824.8 | I67: 45843 | J67: 51472.6 | K67: 50179.7 | L67: 50874.5 | M67: 59290.8
A68: Inventories | B68: ₹ cr | C68: 539 | D68: 391.5 | E68: 337 | F68: 395.1 | G68: 186.5 | H68: 106.4 | I68: 133.4 | J68: 118.8 | K68: 90.7 | L68: 69.4 | M68: 51.7
A69: Current derivative assets | B69: ₹ cr | C69: 567.5 | D69: 974.7 | E69: 123.2 | F69: 493.1 | G69: 302.5 | H69: 406.4 | I69: 303.2 | J69: 184.4 | K69: 133.3 | L69: 182 | M69: 88.8
A70: Current investments | B70: ₹ cr | C70: 13294.4 | D70: 29203 | E70: 24909.4 | F70: 22071.6 | G70: 18963.5 | H70: 17570.7 | I70: 24165.5 | J70: 30923.2 | K70: 31117.1 | L70: 41147.4 | M70: 43768
A71: Cash & equivalents | B71: ₹ cr | C71: 9904.9 | D71: 5271 | E71: 4492.5 | F71: 15852.9 | G71: 14449.9 | H71: 16979.3 | I71: 10383.6 | J71: 9188 | K71: 9695.3 | L71: 12197.4 | M71: 10555.5
A72: Billed receivables | B72: ₹ cr | C72: 10238 | D72: 9484.6 | E72: 10099 | F72: 10048.9 | G72: 10447.4 | H72: 9429.8 | I72: 11521.9 | J72: 12635 | K72: 11547.7 | L72: 11774.5 | M72: 13590.1
A73: Unbilled receivables | B73: ₹ cr | C73: 4827.3 | M73: 7682.3
A74: Other current financial assets | B74: ₹ cr | D74: 517.7 | E74: 742.9 | F74: 1461.1 | G74: 861.4 | H74: 724.5 | I74: 4291.4 | J74: 909.6 | K74: 1053.6 | L74: 844.8 | M74: 1024.5
A75: Contract assets | B75: ₹ cr | M75: 1481.9
A76: Current tax assets | B76: ₹ cr | C76: 781.2 | D76: 980.4 | E76: 626.2 | F76: 743.5 | G76: 288.2 | H76: 246.1 | I76: 237.3 | J76: 509.1 | K76: 648.4 | L76: 641.7 | M76: 1076.2
A77: Other current assets | B77: ₹ cr | C77: 10406.8 | D77: 3075.1 | E77: 3059.6 | F77: 3769.7 | M77: 3316.4
A78: Total current assets | B78: ₹ cr | C78: 50559.1 | D78: 53889.8 | E78: 50615.6 | F78: 57190.6 | G78: 51985.1 | H78: 52318.6 | I78: 62075.2 | J78: 66109.6 | K78: 65066.2 | L78: 77777.5 | M78: 82635.4
A79: Total assets | B79: ₹ cr | C79: 72492.1 | D79: 79351.6 | E79: 76064 | F79: 83317.1 | G79: 81706.2 | H79: 83143.4 | I79: 107918.2 | J79: 117582.2 | K79: 115245.9 | L79: 128652 | M79: 141926.2
A80: Share capital | B80: ₹ cr | C80: 494.1 | D80: 486.1 | E80: 904.8 | F80: 1206.8 | G80: 1142.7 | H80: 1095.8 | I80: 1096.4 | J80: 1097.6 | K80: 1045 | L80: 2094.4 | M80: 2097.7
A81: Share premium | B81: ₹ cr | C81: 1464.2 | D81: 46.9 | E81: 80 | F81: 53.3 | G81: 127.5 | H81: 71.4 | I81: 156.6 | J81: 368.9 | K81: 329.1 | L81: 262.8 | M81: 615.8
A82: Retained earnings | B82: ₹ cr | C82: 42573.5 | D82: 49093 | E82: 45326.5 | F82: 53470 | G82: 47610.3 | H82: 46669.2 | I82: 55125.2 | J82: 66096.4 | K82: 63093.6 | L82: 71647.7 | M82: 73505.7
A83: Equity attributable | B83: ₹ cr | C83: 46607.8 | D83: 52030.4 | E83: 48293.6 | F83: 56811.6 | G83: 55745.8 | H83: 55309.5 | I83: 65815.8 | J83: 78116.4 | K83: 74988.3 | L83: 82830.9 | M83: 88536.8
A84: NCI | B84: ₹ cr | C84: 222.4 | D84: 239.1 | E84: 241 | F84: 263.7 | G84: 187.5 | H84: 149.8 | I84: 51.5 | J84: 58.9 | K84: 134 | L84: 213.8 | M84: 250.9
A85: Total equity | B85: ₹ cr | C85: 46830.2 | D85: 52269.5 | E85: 48534.6 | F85: 57075.3 | G85: 55933.3 | H85: 55459.3 | I85: 65867.3 | J85: 78175.3 | K85: 75122.3 | L85: 83044.7 | M85: 88787.7
A86: Long-term borrowings | B86: ₹ cr | C86: 1736.1 | D86: 1961.1 | E86: 4526.8 | F86: 2836.8 | G86: 484 | H86: 745.8 | I86: 5646.3 | J86: 6127.2 | K86: 6230 | L86: 6395.4 | M86: 196.2
A87: Non-current lease liabilities | B87: ₹ cr | G87: 656 | H87: 1351.3 | I87: 1517.7 | J87: 1595.3 | K87: 1396.2 | L87: 2219.3 | M87: 2632.7
A88: Other non-current financial liabilities | B88: ₹ cr | E88: 0.7 | G88: 15.1 | H88: 229.1 | I88: 296.1 | J88: 264.9 | K88: 498.5 | L88: 779.3 | M88: 674.3
A89: Deferred tax liabilities | B89: ₹ cr | C89: 510.8 | D89: 661.4 | E89: 305.9 | F89: 341.7 | G89: 282.5 | H89: 463.3 | I89: 1214.1 | J89: 1515.3 | K89: 1746.7 | L89: 1644.3 | M89: 1726.6
A90: Non-current tax liabilities | B90: ₹ cr | C90: 823.1 | D90: 954.7 | E90: 922 | F90: 1102.3 | G90: 1320.5 | H90: 1106.9 | I90: 1781.8 | J90: 2177.7 | K90: 3709 | L90: 4202.4 | M90: 4819.5
A91: Other non-current liabilities | B91: ₹ cr | C91: 722.5 | D91: 550 | E91: 423 | F91: 525.8 | G91: 753.7 | K91: 0 | L91: 4.1 | M91: 2304.2
A92: Non-current provisions | B92: ₹ cr | C92: 1.4 | D92: 0.4 | E92: 0.3 | F92: 0.2 | G92: 0.2 | H92: 0.2 | I92: 0.1 | K92: 0 | L92: 29.4 | M92: 22.4
A93: Total non-current liabilities | B93: ₹ cr | C93: 3805.8 | D93: 4127.8 | E93: 6178.7 | F93: 4806.8 | G93: 4133.6 | H93: 4680.1 | I93: 11218 | J93: 12631.6 | K93: 14877.8 | L93: 16982 | M93: 12815.3
A94: Short-term borrowings | B94: ₹ cr | C94: 10786 | D94: 12280.1 | E94: 9299.1 | F94: 7109.9 | G94: 7320.2 | H94: 7587.4 | I94: 9523.3 | J94: 8882.1 | K94: 7916.6 | L94: 9786.3 | M94: 16591.2
A95: Current lease liabilities | B95: ₹ cr | G95: 1263.8 | H95: 766.9 | I95: 905.6 | J95: 862 | K95: 922.1 | L95: 802.5 | M95: 870.9
A96: Derivative liabilities | B96: ₹ cr | C96: 234 | D96: 270.8 | E96: 221 | F96: 131 | G96: 723.1 | H96: 107 | I96: 58.5 | J96: 282.5 | K96: 55.8 | L96: 96.8 | M96: 1097.8
A97: Trade payables | B97: ₹ cr | C97: 6818.7 | D97: 6548.6 | E97: 6812.9 | F97: 8830.4 | G97: 7812.9 | H97: 7651.2 | I97: 9447.7 | J97: 8905.4 | K97: 8856.6 | L97: 8825.2 | M97: 9492.4
A98: Other current financial liabilities | B98: ₹ cr | E98: 105 | F98: 64.4 | G98: 89.9 | H98: 147 | I98: 3311 | J98: 414.1 | K98: 227.2 | L98: 387.8 | M98: 1135.7
A99: Contract liabilities | B99: ₹ cr | C99: 1807.6 | M99: 2543.4
A100: Current tax liabilities | B100: ₹ cr | C100: 701.5 | D100: 810.1 | E100: 941.7 | F100: 954.1 | G100: 1173.1 | H100: 1732.4 | I100: 1323.1 | J100: 1884.6 | K100: 2175.6 | L100: 3448.1 | M100: 4962.1
A101: Other current liabilities | B101: ₹ cr | C101: 1382.1 | D101: 1302.7 | E101: 1661.3 | F101: 1869 | K101: 0 | L101: 23.4 | M101: 3480.1
A102: Current provisions | B102: ₹ cr | C102: 126.2 | D102: 127 | E102: 79.6 | F102: 63.8 | G102: 61.2 | H102: 303.4 | I102: 277.1 | J102: 254.9 | K102: 197.1 | L102: 163.7 | M102: 149.6
A103: Total current liabilities | B103: ₹ cr | C103: 21856.1 | D103: 22954.3 | E103: 21350.7 | F103: 21435 | G103: 21639.3 | H103: 23004 | I103: 30832.9 | J103: 26775.3 | K103: 25245.8 | L103: 28625.3 | M103: 40323.2
A104: Total liabilities | B104: ₹ cr | C104: 25661.9 | D104: 27082.1 | E104: 27529.4 | F104: 26241.8 | G104: 25772.9 | H104: 27684.1 | I104: 42050.9 | J104: 39406.9 | K104: 40123.6 | L104: 45607.3 | M104: 53138.5
A108: Annual reported cash flow
A109: Metric | B109: Units | C109: FY16A | D109: FY17A | E109: FY18A | F109: FY19A | G109: FY20A | H109: FY21A | I109: FY22A | J109: FY23A | K109: FY24A | L109: FY25A | M109: FY26A
A110: Profit before tax | B110: ₹ cr | C110: 11493.3 | D110: 11035.6 | E110: 10247.4 | F110: 11541.5 | G110: 12251.2 | H110: 13900.7 | I110: 15127.5 | J110: 14765.7 | K110: 14721 | L110: 17495.7 | M110: 17342.2
A111: D&A | B111: ₹ cr | M111: 2910.7
A112: Share-based payments | B112: ₹ cr | C112: 153.4 | D112: 174.2 | E112: 134.7 | F112: 193.8 | G112: 126.2 | H112: 231 | I112: 411 | J112: 396.9 | K112: 558.4 | L112: 555.1 | M112: 446.5
A113: Gain on PPE disposal | B113: ₹ cr | M113: -39.3
...

Sheet Raw Operating
A1: Raw Reported Operating Metrics
A2: Quarter-end operating metrics from official Wipro data sheets; classifications remain separate
A5: Metric | B5: Units | C5: FY16A | D5: FY17A | E5: FY18A | F5: FY19A | G5: FY20A | H5: FY21A | I5: FY22A | J5: FY23A | K5: FY24A | L5: FY25A | M5: FY26A | N5: FY27E | O5: FY28E | P5: FY29E | Q5: FY30E
A7: IT services revenue | B7: $m | C7: 7346.3 | D7: 7704.5 | E7: 8060.2 | F7: 8120.3 | G7: 8256.2 | H7: 8136.5 | I7: 10355.9 | J7: 11159.7 | K7: 10805.3 | L7: 10511.5 | M7: 10478.1
A8: Closing headcount | B8: # | C8: 172912 | D8: 181482 | E8: 163827 | F8: 171425 | G8: 182886 | H8: 197712 | I8: 243128 | J8: 256921 | K8: 234054 | L8: 233346 | M8: 242156
A9: Sales & support staff | B9: # | C9: 13140 | D9: 14466 | E9: 14936 | F9: 14360 | G9: 14908 | H9: 15368 | I9: 17691 | J9: 16986 | K9: 15601 | L9: 15230 | M9: 14574
A10: Net utilization excl. trainees | B10: % | C10: 0.799 | D10: 0.823 | E10: 0.825 | F10: 0.848 | G10: 0.823 | H10: 0.859 | I10: 0.868 | J10: 0.812 | K10: 0.848 | L10: 0.856 | M10: 0.845
A11: Voluntary attrition TTM | B11: % | C11: 0.161 | D11: 0.163 | E11: 0.166 | F11: 0.176 | G11: 0.147 | H11: 0.121 | I11: 0.238 | J11: 0.192 | K11: 0.142 | L11: 0.15 | M11: 0.138
A12: FPP mix | B12: % | C12: 0.552 | D12: 0.571 | E12: 0.581 | F12: 0.594 | G12: 0.624 | H12: 0.62 | I12: 0.628 | J12: 0.594 | K12: 0.592 | L12: 0.566 | M12: 0.543
A13: Active clients | B13: # | C13: 1223 | D13: 1323 | E13: 1248 | F13: 1115 | G13: 1074 | H13: 1120 | I13: 1369 | J13: 1441 | K13: 1371 | L13: 1282 | M13: 1233
A14: $100m+ clients | B14: # | C14: 9 | D14: 9 | E14: 8 | F14: 10 | G14: 15 | H14: 11 | I14: 19 | J14: 19 | K14: 22 | L14: 17 | M14: 16
A15: $50m+ clients | B15: # | C15: 33 | D15: 34 | E15: 39 | F15: 41 | G15: 40 | H15: 40 | I15: 50 | J15: 53 | K15: 45 | L15: 44 | M15: 45
A16: $20m+ clients | B16: # | C16: 89 | D16: 91 | E16: 95 | F16: 96 | G16: 96 | H16: 93 | I16: 117 | J16: 117 | K16: 116 | L16: 111 | M16: 106
A17: $10m+ clients | B17: # | C17: 160 | D17: 163 | E17: 171 | F17: 172 | G17: 166 | H17: 167 | I17: 194 | J17: 208 | K17: 205 | L17: 181 | M17: 183
A18: $5m+ clients | B18: # | C18: 248 | D18: 268 | E18: 277 | F18: 262 | G18: 260 | H18: 257 | I18: 297 | J18: 311 | K18: 301 | L18: 289 | M18: 289
... A22: Top 10 | B22: % | C22: 0.1 | D22: 0.1 | E22: 0.1 | F22: 0.1 | G22: 0.1 | H22: 0.1 | I22: 0.1 | J22: 0.1 | K22: 0.1 | L22: 0.1 | M22: 0.1
A23: Total bookings | B23: $m | K23: 14907 | L23: 14315 | M23: 16449
A24: Large-deal TCV | B24: $m | L24: 5368 | M24: 7829
A25: USD mix | B25: % | C25: 0.6 | D25: 0.61 | E25: 0.58 | F25: 0.61 | G25: 0.63 | H25: 0.61 | I25: 0.59 | J25: 0.61 | K25: 0.6 | L25: 0.62 | M25: 0.61
A26: GBP mix | B26: % | C26: 0.12 | D26: 0.1 | E26: 0.1 | F26: 0.1 | G26: 0.1 | H26: 0.1 | I26: 0.11 | J26: 0.1 | K26: 0.11 | L26: 0.1 | M26: 0.11
A27: EUR mix | B27: % | C27: 0.08 | D27: 0.09 | E27: 0.09 | F27: 0.09 | G27: 0.08 | H27: 0.08 | I27: 0.1 | J27: 0.1 | K27: 0.1 | L27: 0.1 | M27: 0.09
A28: INR mix | B28: % | C28: 0.07 | D28: 0.07 | E28: 0.08 | F28: 0.05 | G28: 0.04 | H28: 0.05 | I28: 0.05 | J28: 0.04 | K28: 0.05 | L28: 0.04 | M28: 0.05
A29: AUD mix | B29: % | C29: 0.04 | D29: 0.04 | E29: 0.05 | F29: 0.05 | G29: 0.05 | H29: 0.05 | I29: 0.05 | J29: 0.05 | K29: 0.04 | L29: 0.04 | M29: 0.04
A30: CAD mix | B30: % | C30: 0.02 | D30: 0.02 | E30: 0.02 | F30: 0.03 | G30: 0.03 | H30: 0.03 | I30: 0.03 | J30: 0.03 | K30: 0.03 | L30: 0.03 | M30: 0.03
A31: Other currency mix | B31: % | C31: 0.07 | D31: 0.07 | E31: 0.08 | F31: 0.07 | G31: 0.07 | H31: 0.08 | I31: 0.07 | J31: 0.07 | K31: 0.07 | L31: 0.07 | M31: 0.07
A34: Legacy vertical and geography mix
A35: BFSI / finance solutions | B35: % | C35: 0.263 | D35: 0.257 | E35: 0.281 | F35: 0.309 | G35: 0.31 | H35: 0.307 | I35: 0.347 | J35: 0.349 | K35: 0.334 | L35: 0.343 | M35: 0.341
A36: Communications / media | B36: % | C36: 0.133 | D36: 0.073 | E36: 0.064 | F36: 0.057 | G36: 0.057 | H36: 0.052 | I36: 0.05 | J36: 0.047 | K36: 0.042 | L36: 0.152 | M36: 0.02
A37: Manufacturing / energy & resources | B37: % | C37: 0.186 | M37: 0.17
A38: Health | B38: % | C38: 0.12 | D38: 0.156 | F38: 0.132 | G38: 0.132 | H38: 0.13 | I38: 0.115 | J38: 0.122 | K38: 0.141 | L38: 0.144 | M38: 0.142
A39: Consumer / retail | B39: % | C39: 0.152 | D39: 0.158 | E39: 0.158 | F39: 0.157 | G39: 0.163 | H39: 0.17 | I39: 0.179 | J39: 0.188 | K39: 0.187 | L39: 0.189 | M39: 0.184
A40: Energy legacy | B40: % | C40: 0.146 | D40: 0.131
A41: Technology & communications | B41: % | L41: 0.153 | M41: 0.16
A42: Americas | B42: % | C42: 0.527 | D42: 0.547 | E42: 0.534 | F42: 0.568 | G42: 0.591 | H42: 0.294 | I42: 0.279 | J42: 0.291 | K42: 0.3 | L42: 0.317 | M42: 0.332
A43: Europe | B43: % | C43: 0.253 | D43: 0.244 | E43: 0.256 | F43: 0.255 | G43: 0.24 | H43: 0.273 | I43: 0.299 | J43: 0.286 | K43: 0.284 | L43: 0.271 | M43: 0.265
A44: India & Middle East | B44: % | C44: 0.108 | D44: 0.101 | E44: 0.099
A45: APAC / other emerging | B45: % | C45: 0.112 | D45: 0.108 | E45: 0.111
A46: Americas 1 | B46: % | H46: 0.294 | I46: 0.279 | J46: 0.291 | K46: 0.3 | L46: 0.317 | M46: 0.332
A47: Americas 2 | B47: % | H47: 0.297 | I47: 0.306 | J47: 0.31 | K47: 0.301 | L47: 0.306 | M47: 0.292
A48: APMEA | B48: % | H48: 0.136 | I48: 0.116 | J48: 0.113 | K48: 0.115 | L48: 0.106 | M48: 0.111

Sheet Quarterly P&L
A1: Quarterly Profit & Loss
A2: FY16–FY26 actual plus Q1 FY27 actual; all lines link to the raw source layer
A5: Metric | B5: Units | C5: Q1 FY16A | D5: Q2 FY16A | E5: Q3 FY16A | F5: Q4 FY16A | G5: Q1 FY17A | H5: Q2 FY17A | I5: Q3 FY17A | J5: Q4 FY17A | K5: Q1 FY18A | L5: Q2 FY18A | M5: Q3 FY18A | N5: Q4 FY18A | O5: Q1 FY19A | P5: Q2 FY19A | Q5: Q3 FY19A | R5: Q4 FY19A | S5: Q1 FY20A | T5: Q2 FY20A | U5: Q3 FY20A | V5: Q4 FY20A | W5: Q1 FY21A | X5: Q2 FY21A | Y5: Q3 FY21A | Z5: Q4 FY21A | AA5: Q1 FY22A | AB5: Q2 FY22A | AC5: Q3 FY22A | AD5: Q4 FY22A | AE5: Q1 FY23A | AF5: Q2 FY23A | AG5: Q3 FY23A | AH5: Q4 FY23A | AI5: Q1 FY24A | AJ5: Q2 FY24A | AK5: Q3 FY24A | AL5: Q4 FY24A | AM5: Q1 FY25A | AN5: Q2 FY25A | AO5: Q3 FY25A | AP5: Q4 FY25A | AQ5: Q1 FY26A | AR5: Q2 FY26A | AS5: Q3 FY26A | AT5: Q4 FY26A | AU5: Q1 FY27A
A6: Revenue | B6: ₹ cr | C6: ='Raw Financials'!C32 -> 12237.6 | D6: ='Raw Financials'!D32 -> 12513.5 | E6: ='Raw Financials'!E32 -> 12860.5 | F6: ='Raw Financials'!F32 -> 13632.4 | G6: ='Raw Financials'!G32 -> 13599.2 | H6: ='Raw Financials'!H32 -> 13765.7 | I6: ='Raw Financials'!I32 -> 13687.8 | J6: ='Raw Financials'!J32 -> 13987.5 | ... AU6: ='Raw Financials'!AU32 -> 24478.6
A7: QoQ growth | B7: % | D7: =IFERROR(D6/C6-1,"") -> 0.02254527 | E7: =IFERROR(E6/D6-1,"") -> 0.027730052 | F7: =IFERROR(F6/E6-1,"") -> 0.060020995 | G7: =IFERROR(G6/F6-1,"") -> -0.0024353745 | H7: =IFERROR(H6/G6-1,"") -> 0.012243367 | I7: =IFERROR(I6/H6-1,"") -> -0.005658993 | J7: =IFERROR(J6/I6-1,"") -> 0.021895411 | K7: =IFERROR(K6/J6-1,"") -> -0.025837355 | ... AU7: =IFERROR(AU6/AT6-1,"") -> 0.0099974006
A8: YoY growth | B8: % | G8: =IFERROR(G6/C6-1,"") -> 0.11126365 | H8: =IFERROR(H6/D6-1,"") -> 0.10006793 | I8: =IFERROR(I6/E6-1,"") -> 0.064328759 | J8: =IFERROR(J6/F6-1,"") -> 0.026048238 | K8: =IFERROR(K6/G6-1,"") -> 0.0019780575 | L8: =IFERROR(L6/H6-1,"") -> -0.024866153 | M8: =IFERROR(M6/I6-1,"") -> -0.0013734859 | N8: =IFERROR(N6/J6-1,"") -> -0.015649687 | ... AU8: =IFERROR(AU6/AQ6-1,"") -> 0.10589755
A9: Cost of revenue | B9: ₹ cr | C9: ='Raw Financials'!C33 -> 8478.7 | D9: ='Raw Financials'!D33 -> 8582.4 | E9: ='Raw Financials'!E33 -> 9027 | F9: ='Raw Financials'!F33 -> 9584.3 | G9: ='Raw Financials'!G33 -> 9638.9 | H9: ='Raw Financials'!H33 -> 9780.8 | I9: ='Raw Financials'!I33 -> 9657.6 | J9: ='Raw Financials'!J33 -> 10077.1 | ... AU9: ='Raw Financials'!AU33 -> 17490
A10: Gross profit | B10: ₹ cr | C10: ='Raw Financials'!C34 -> 3758.9 | D10: ='Raw Financials'!D34 -> 3931.1 | E10: ='Raw Financials'!E34 -> 3833.5 | F10: ='Raw Financials'!F34 -> 4048.1 | G10: ='Raw Financials'!G34 -> 3960.3 | H10: ='Raw Financials'!H34 -> 3984.9 | I10: ='Raw Financials'!I34 -> 4030.2 | J10: ='Raw Financials'!J34 -> 3910.4 | ... AU10: ='Raw Financials'!AU34 -> 6988.6
A11: Gross margin | B11: % | C11: =IFERROR(C10/C6,"") -> 0.3071599 | D11: =IFERROR(D10/D6,"") -> 0.31414872 | E11: =IFERROR(E10/E6,"") -> 0.29808328 | F11: =IFERROR(F10/F6,"") -> 0.29694698 | G11: =IFERROR(G10/G6,"") -> 0.29121566 | H11: =IFERROR(H10/H6,"") -> 0.28948038 | I11: =IFERROR(I10/I6,"") -> 0.29443738 | J11: =IFERROR(J10/J6,"") -> 0.2795639 | ... AU11: =IFERROR(AU10/AU6,"") -> 0.28549835
A12: Selling & marketing | B12: ₹ cr | C12: ='Raw Financials'!C35 -> 804.4 | D12: ='Raw Financials'!D35 -> 870.8 | E12: ='Raw Financials'!E35 -> 836.2 | F12: ='Raw Financials'!F35 -> 898.3 | G12: ='Raw Financials'!G35 -> 1014.1 | H12: ='Raw Financials'!H35 -> 961.4 | I12: ='Raw Financials'!I35 -> 922.6 | J12: ='Raw Financials'!J35 -> 1183.6 | ... AU12: ='Raw Financials'!AU35 -> 1649.6
A13: General & administrative | B13: ₹ cr | C13: ='Raw Financials'!C36 -> 685.3 | D13: ='Raw Financials'!D36 -> 684.7 | E13: ='Raw Financials'!E36 -> 701 | F13: ='Raw Financials'!F36 -> 791.6 | G13: ='Raw Financials'!G36 -> 759.9 | H13: ='Raw Financials'!H36 -> 854.5 | I13: ='Raw Financials'!I36 -> 861 | J13: ='Raw Financials'!J36 -> 726.7 | ... AU13: ='Raw Financials'!AU36 -> 1496.3
A14: Other operating income / FX | B14: ₹ cr | C14: ='Raw Financials'!C37 -> 133 | D14: ='Raw Financials'!D37 -> 53.3 | E14: ='Raw Financials'!E37 -> 91.1 | F14: ='Raw Financials'!F37 -> 109.3 | G14: ='Raw Financials'!G37 -> 98.4 | H14: ='Raw Financials'!H37 -> 128.1 | I14: ='Raw Financials'!I37 -> 76.7 | J14: ='Raw Financials'!J37 -> 482.7 | ... AU14: ='Raw Financials'!AU37 -> 77.9
A15: EBITDA | B15: ₹ cr | C15: ='Raw Financials'!C38 -> 2738.9 | D15: ='Raw Financials'!D38 -> 2781.9 | E15: ='Raw Financials'!E38 -> 2763.8 | F15: ='Raw Financials'!F38 -> 2897.9 | G15: ='Raw Financials'!G38 -> 2751.2 | H15: ='Raw Financials'!H38 -> 2782 | I15: ='Raw Financials'!I38 -> 2864.5 | J15: ='Raw Financials'!J38 -> 3300.9 | ... AU15: ='Raw Financials'!AU38 -> 0
A16: EBITDA margin | B16: % | C16: =IFERROR(C15/C6,"") -> 0.22381022 | D16: =IFERROR(D15/D6,"") -> 0.2223119 | E16: =IFERROR(E15/E6,"") -> 0.21490611 | F16: =IFERROR(F15/F6,"") -> 0.21257445 | G16: =IFERROR(G15/G6,"") -> 0.20230602 | H16: =IFERROR(H15/H6,"") -> 0.20209652 | I16: =IFERROR(I15/I6,"") -> 0.20927395 | J16: =IFERROR(J15/J6,"") -> 0.23598928 | ... AU16: =IFERROR(AU15/AU6,"") -> 0
A17: D&A | B17: ₹ cr | C17: ='Raw Financials'!C39 -> 336.7 | D17: ='Raw Financials'!D39 -> 353 | E17: ='Raw Financials'!E39 -> 376.4 | F17: ='Raw Financials'!F39 -> 430.4 | G17: ='Raw Financials'!G39 -> 466.5 | H17: ='Raw Financials'!H39 -> 484.9 | I17: ='Raw Financials'!I39 -> 541.2 | J17: ='Raw Financials'!J39 -> 818.1 | ... AU17: ='Raw Financials'!AU39 -> 0
A18: EBIT | B18: ₹ cr | C18: ='Raw Financials'!C40 -> 2402.2 | D18: ='Raw Financials'!D40 -> 2428.9 | E18: ='Raw Financials'!E40 -> 2387.4 | F18: ='Raw Financials'!F40 -> 2467.5 | G18: ='Raw Financials'!G40 -> 2284.7 | H18: ='Raw Financials'!H40 -> 2297.1 | I18: ='Raw Financials'!I40 -> 2323.3 | J18: ='Raw Financials'!J40 -> 2482.8 | ... AU18: ='Raw Financials'!AU40 -> 3920.6
A19: EBIT margin | B19: % | C19: =IFERROR(C18/C6,"") -> 0.19629666 | D19: =IFERROR(D18/D6,"") -> 0.19410237 | E19: =IFERROR(E18/E6,"") -> 0.18563819 | F19: =IFERROR(F18/F6,"") -> 0.18100261 | G19: =IFERROR(G18/G6,"") -> 0.16800253 | H19: =IFERROR(H18/H6,"") -> 0.16687128 | I19: =IFERROR(I18/I6,"") -> 0.16973509 | J19: =IFERROR(J18/J6,"") -> 0.17750134 | ... AU19: =IFERROR(AU18/AU6,"") -> 0.16016439
A20: Finance expense | B20: ₹ cr | C20: ='Raw Financials'!C41 -> 128.6 | D20: ='Raw Financials'!D41 -> 158.9 | E20: ='Raw Financials'!E41 -> 142.3 | F20: ='Raw Financials'!F41 -> 108 | G20: ='Raw Financials'!G41 -> 133.6 | H20: ='Raw Financials'!H41 -> 142.8 | I20: ='Raw Financials'!I41 -> 136.6 | J20: ='Raw Financials'!J41 -> 181.2 | ... AU20: ='Raw Financials'!AU41 -> 472.8
A21: Finance & other income | B21: ₹ cr | C21: ='Raw Financials'!C42 -> 524.2 | D21: ='Raw Financials'!D42 -> 619.4 | E21: ='Raw Financials'!E42 -> 622.7 | F21: ='Raw Financials'!F42 -> 578.8 | G21: ='Raw Financials'!G42 -> 520 | H21: ='Raw Financials'!H42 -> 510.5 | I21: ='Raw Financials'!I42 -> 571.9 | J21: ='Raw Financials'!J42 -> 639.5 | ... AU21: ='Raw Financials'!AU42 -> 887.2
A22: Share of associate / JV | B22: ₹ cr | C22: ='Raw Financials'!C43 -> 0 | D22: ='Raw Financials'!D43 -> 0 | E22: ='Raw Financials'!E43 -> 0 | F22: ='Raw Financials'!F43 -> 0 | G22: ='Raw Financials'!G43 -> 0 | H22: ='Raw Financials'!H43 -> 0 | I22: ='Raw Financials'!I43 -> 0 | J22: ='Raw Financials'!J43 -> 0 | ... AU22: ='Raw Financials'!AU43 -> -0.5
A23: PBT | B23: ₹ cr | C23: ='Raw Financials'!C44 -> 2797.8 | D23: ='Raw Financials'!D44 -> 2889.4 | E23: ='Raw Financials'!E44 -> 2867.8 | F23: ='Raw Financials'!F44 -> 2938.3 | G23: ='Raw Financials'!G44 -> 2671.1 | H23: ='Raw Financials'!H44 -> 2664.8 | I23: ='Raw Financials'!I44 -> 2758.6 | J23: ='Raw Financials'!J44 -> 2941.1 | ... AU23: ='Raw Financials'!AU44 -> 4334.5
A24: PBT margin | B24: % | C24: =IFERROR(C23/C6,"") -> 0.22862326 | D24: =IFERROR(D23/D6,"") -> 0.23090263 | E24: =IFERROR(E23/E6,"") -> 0.22299289 | F24: =IFERROR(F23/F6,"") -> 0.21553798 | G24: =IFERROR(G23/G6,"") -> 0.19641597 | H24: =IFERROR(H23/H6,"") -> 0.1935826 | I24: =IFERROR(I23/I6,"") -> 0.20153714 | J24: =IFERROR(J23/J6,"") -> 0.21026631 | ... AU24: =IFERROR(AU23/AU6,"") -> 0.17707304
A25: Tax | B25: ₹ cr | C25: ='Raw Financials'!C45 -> 594.5 | D25: ='Raw Financials'!D45 -> 648.6 | E25: ='Raw Financials'!E45 -> 624.8 | F25: ='Raw Financials'!F45 -> 668.7 | G25: ='Raw Financials'!G45 -> 612.2 | H25: ='Raw Financials'!H45 -> 590.9 | I25: ='Raw Financials'!I45 -> 644 | J25: ='Raw Financials'!J45 -> 674.2 | ... AU25: ='Raw Financials'!AU45 -> 978.2
A26: Effective tax rate | B26: % | C26: =IFERROR(C25/C23,"") -> 0.21248838 | D26: =IFERROR(D25/D23,"") -> 0.22447567 | E26: =IFERROR(E25/E23,"") -> 0.21786735 | F26: =IFERROR(F25/F23,"") -> 0.22758057 | G26: =IFERROR(G25/G23,"") -> 0.22919397 | H26: =IFERROR(H25/H23,"") -> 0.22174272 | I26: =IFERROR(I25/I23,"") -> 0.23345175 | J26: =IFERROR(J25/J23,"") -> 0.22923396 | ... AU26: =IFERROR(AU25/AU23,"") -> 0.2256777
A27: Profit incl. NCI | B27: ₹ cr | C27: ='Raw Financials'!C46 -> 2203.3 | D27: ='Raw Financials'!D46 -> 2240.8 | E27: ='Raw Financials'!E46 -> 2243 | F27: ='Raw Financials'!F46 -> 2269.6 | G27: ='Raw Financials'!G46 -> 2058.9 | H27: ='Raw Financials'!H46 -> 2073.9 | I27: ='Raw Financials'!I46 -> 2114.6 | J27: ='Raw Financials'!J46 -> 2266.9 | ... AU27: ='Raw Financials'!AU46 -> 3356.3
A28: NCI | B28: ₹ cr | C28: ='Raw Financials'!C47 -> 15.6 | D28: ='Raw Financials'!D47 -> 5.4 | E28: ='Raw Financials'!E47 -> 8.9 | F28: ='Raw Financials'!F47 -> 19.3 | G28: ='Raw Financials'!G47 -> 7.1 | H28: ='Raw Financials'!H47 -> 6.7 | I28: ='Raw Financials'!I47 -> 5.2 | J28: ='Raw Financials'!J47 -> 5.8 | ... AU28: ='Raw Financials'!AU47 -> 4.3
A29: Net income attributable | B29: ₹ cr | C29: ='Raw Financials'!C48 -> 2187.7 | D29: ='Raw Financials'!D48 -> 2235.4 | E29: ='Raw Financials'!E48 -> 2234.1 | F29: ='Raw Financials'!F48 -> 2250.3 | G29: ='Raw Financials'!G48 -> 2051.8 | H29: ='Raw Financials'!H48 -> 2067.2 | I29: ='Raw Financials'!I48 -> 2109.4 | J29: ='Raw Financials'!J48 -> 2261.1 | ... AU29: ='Raw Financials'!AU48 -> 3352
A30: Net margin | B30: % | C30: =IFERROR(C29/C6,"") -> 0.17876871 | D30: =IFERROR(D29/D6,"") -> 0.17863907 | E30: =IFERROR(E29/E6,"") -> 0.17371797 | F30: =IFERROR(F29/F6,"") -> 0.16506998 | G30: =IFERROR(G29/G6,"") -> 0.15087652 | H30: =IFERROR(H29/H6,"") -> 0.15017035 | I30: =IFERROR(I29/I6,"") -> 0.15410804 | J30: =IFERROR(J29/J6,"") -> 0.16165147 | ... AU30: =IFERROR(AU29/AU6,"") -> 0.13693594

Sheet Annual P&L
A1: Annual Profit & Loss
A2: Historical values link to official reported data; FY27E–FY30E are calculated
A5: Metric | B5: Units | C5: FY16A | D5: FY17A | E5: FY18A | F5: FY19A | G5: FY20A | H5: FY21A | I5: FY22A | J5: FY23A | K5: FY24A | L5: FY25A | M5: FY26A | N5: FY27E | O5: FY28E | P5: FY29E | Q5: FY30E
A7: Revenue | B7: ₹ cr | C7: ='Raw Financials'!C6 -> 51244 | D7: ='Raw Financials'!D6 -> 55040.2 | E7: ='Raw Financials'!E6 -> 54487.1 | F7: ='Raw Financials'!F6 -> 58584.5 | G7: ='Raw Financials'!G6 -> 61023.2 | H7: ='Raw Financials'!H6 -> 61943 | I7: ='Raw Financials'!I6 -> 79093.4 | J7: ='Raw Financials'!J6 -> 90487.6 | ... M7: ='Raw Financials'!M6 -> 92624 | N7: ='Revenue Drivers'!N31 -> 95426.741 | O7: ='Revenue Drivers'!O31 -> 101167.44 | P7: ='Revenue Drivers'!P31 -> 109097.12 | Q7: ='Revenue Drivers'!Q31 -> 118382.92
A8: YoY growth | B8: % | D8: =IFERROR(D7/C7-1,"") -> 0.074080868 | E8: =IFERROR(E7/D7-1,"") -> -0.010049019 | F8: =IFERROR(F7/E7-1,"") -> 0.075199451 | G8: =IFERROR(G7/F7-1,"") -> 0.041627052 | H8: =IFERROR(H7/G7-1,"") -> 0.015072956 | I8: =IFERROR(I7/H7-1,"") -> 0.2768739 | J8: =IFERROR(J7/I7-1,"") -> 0.14406006 | K8: =IFERROR(K7/J7-1,"") -> -0.0080375654 | ... Q8: =IFERROR(Q7/P7-1,"") -> 0.085114922
A9: Cost of revenue | B9: ₹ cr | C9: ='Raw Financials'!C7 -> 35672.4 | D9: ='Raw Financials'!D7 -> 39154.4 | E9: ='Raw Financials'!E7 -> 38557.5 | F9: ='Raw Financials'!F7 -> 41303.3 | G9: ='Raw Financials'!G7 -> 43608.5 | H9: ='Raw Financials'!H7 -> 42320.5 | I9: ='Raw Financials'!I7 -> 55587.2 | J9: ='Raw Financials'!J7 -> 64544.6 | ... M9: ='Raw Financials'!M7 -> 65619.2 | N9: =N7-N10 -> 67562.133 | O9: =O7-O10 -> 71323.043 | P9: =P7-P10 -> 76586.181 | Q9: =Q7-Q10 -> 82868.042
A10: Gross profit | B10: ₹ cr | C10: ='Raw Financials'!C8 -> 15571.6 | D10: ='Raw Financials'!D8 -> 15885.8 | E10: ='Raw Financials'!E8 -> 15929.6 | F10: ='Raw Financials'!F8 -> 17281.2 | G10: ='Raw Financials'!G8 -> 17414.7 | H10: ='Raw Financials'!H8 -> 19622.5 | I10: ='Raw Financials'!I8 -> 23506.2 | J10: ='Raw Financials'!J8 -> 25943 | ... M10: ='Raw Financials'!M8 -> 27004.8 | N10: =N7*Assumptions!C19 -> 27864.608 | O10: =O7*Assumptions!D19 -> 29844.394 | P10: =P7*Assumptions!E19 -> 32510.943 | Q10: =Q7*Assumptions!F19 -> 35514.875
A11: Gross margin | B11: % | C11: =IFERROR(C10/C7,"") -> 0.30387167 | D11: =IFERROR(D10/D7,"") -> 0.28862177 | E11: =IFERROR(E10/E7,"") -> 0.29235544 | F11: =IFERROR(F10/F7,"") -> 0.29497905 | G11: =IFERROR(G10/G7,"") -> 0.28537835 | H11: =IFERROR(H10/H7,"") -> 0.31678317 | I11: =IFERROR(I10/I7,"") -> 0.29719547 | J11: =IFERROR(J10/J7,"") -> 0.28670227 | ... Q11: =IFERROR(Q10/Q7,"") -> 0.3
A12: Selling & marketing | B12: ₹ cr | C12: ='Raw Financials'!C9 -> 3409.7 | D12: ='Raw Financials'!D9 -> 4081.7 | E12: ='Raw Financials'!E9 -> 4234.9 | F12: ='Raw Financials'!F9 -> 4451 | G12: ='Raw Financials'!G9 -> 4290.7 | H12: ='Raw Financials'!H9 -> 4140 | I12: ='Raw Financials'!I9 -> 5493.5 | J12: ='Raw Financials'!J9 -> 6515.7 | ... M12: ='Raw Financials'!M9 -> 5921.6 | N12: =N7*Assumptions!C20 -> 6107.3114 | O12: =O7*Assumptions!D20 -> 6373.5485 | P12: =P7*Assumptions!E20 -> 6764.0217 | Q12: =Q7*Assumptions!F20 -> 7221.3579
A13: General & administrative | B13: ₹ cr | C13: ='Raw Financials'!C10 -> 2862.6 | D13: ='Raw Financials'!D10 -> 3202.1 | E13: ='Raw Financials'!E10 -> 3414.1 | F13: ='Raw Financials'!F10 -> 3595.1 | G13: ='Raw Financials'!G10 -> 2982.3 | H13: ='Raw Financials'!H10 -> 3468.6 | I13: ='Raw Financials'!I10 -> 4638.2 | J13: ='Raw Financials'!J10 -> 5913.9 | ... M13: ='Raw Financials'!M10 -> 6143.4 | N13: =N7*Assumptions!C21 -> 6298.1649 | O13: =O7*Assumptions!D21 -> 6575.8834 | P13: =P7*Assumptions!E21 -> 6982.2159 | Q13: =Q7*Assumptions!F21 -> 7458.1238
A14: Other operating income / FX | B14: ₹ cr | C14: ='Raw Financials'!C11 -> 0 | D14: ='Raw Financials'!D11 -> 0 | E14: ='Raw Financials'!E11 -> 0 | F14: ='Raw Financials'!F11 -> 0 | G14: ='Raw Financials'!G11 -> 0 | H14: ='Raw Financials'!H11 -> 0 | I14: ='Raw Financials'!I11 -> 0 | J14: ='Raw Financials'!J11 -> 0 | ... M14: ='Raw Financials'!M11 -> 0 | N14: =N7*Assumptions!C22 -> 190.85348 | O14: =O7*Assumptions!D22 -> 202.33487 | P14: =P7*Assumptions!E22 -> 218.19425 | Q14: =Q7*Assumptions!F22 -> 236.76583
A15: EBITDA | B15: ₹ cr | C15: ='Raw Financials'!C12 -> 11182.5 | D15: ='Raw Financials'!D12 -> 11698.6 | E15: ='Raw Financials'!E12 -> 10541.8 | F15: ='Raw Financials'!F12 -> 11938.4 | G15: ='Raw Financials'!G12 -> 12659.2 | H15: ='Raw Financials'!H12 -> 15070.9 | I15: ='Raw Financials'!I12 -> 17119.7 | J15: ='Raw Financials'!J12 -> 17300.8 | ... M15: ='Raw Financials'!M12 -> 18035.8 | N15: =N18+N17 -> 18608.215 | O15: =O18+O17 -> 20132.32 | P15: =P18+P17 -> 22146.716 | Q15: =Q18+Q17 -> 24386.881
A16: EBITDA margin | B16: % | C16: =IFERROR(C15/C7,"") -> 0.21822067 | D16: =IFERROR(D15/D7,"") -> 0.21254647 | E16: =IFERROR(E15/E7,"") -> 0.19347332 | F16: =IFERROR(F15/F7,"") -> 0.20378086 | G16: =IFERROR(G15/G7,"") -> 0.20744897 | H16: =IFERROR(H15/H7,"") -> 0.24330271 | I16: =IFERROR(I15/I7,"") -> 0.21644916 | J16: =IFERROR(J15/J7,"") -> 0.19119526 | ... Q16: =IFERROR(Q15/Q7,"") -> 0.206
A17: D&A | B17: ₹ cr | C17: ='Raw Financials'!C13 -> 1496.5 | D17: ='Raw Financials'!D13 -> 2310.7 | E17: ='Raw Financials'!E13 -> 2112.4 | F17: ='Raw Financials'!F13 -> 1947.4 | G17: ='Raw Financials'!G13 -> 2086.2 | H17: ='Raw Financials'!H13 -> 2765.6 | I17: ='Raw Financials'!I13 -> 3091.1 | J17: ='Raw Financials'!J13 -> 3340.2 | ... M17: ='Raw Financials'!M13 -> 2910.7 | N17: =N7*Assumptions!C23 -> 2958.229 | O17: =O7*Assumptions!D23 -> 3035.0231 | P17: =P7*Assumptions!E23 -> 3163.8166 | Q17: =Q7*Assumptions!F23 -> 3314.7217
A18: EBIT | B18: ₹ cr | C18: ='Raw Financials'!C14 -> 9686 | D18: ='Raw Financials'!D14 -> 9387.9 | E18: ='Raw Financials'!E14 -> 8429.4 | F18: ='Raw Financials'!F14 -> 9991 | G18: ='Raw Financials'!G14 -> 10573 | H18: ='Raw Financials'!H14 -> 12305.3 | I18: ='Raw Financials'!I14 -> 14028.6 | J18: ='Raw Financials'!J14 -> 13960.6 | ... M18: ='Raw Financials'!M14 -> 15125.1 | N18: =N10-N12-N13+N14 -> 15649.986 | O18: =O10-O12-O13+O14 -> 17097.297 | P18: =P10-P12-P13+P14 -> 18982.9 | Q18: =Q10-Q12-Q13+Q14 -> 21072.159
A19: EBIT margin | B19: % | C19: =IFERROR(C18/C7,"") -> 0.18901725 | D19: =IFERROR(D18/D7,"") -> 0.17056442 | E19: =IFERROR(E18/E7,"") -> 0.15470451 | F19: =IFERROR(F18/F7,"") -> 0.17053999 | G19: =IFERROR(G18/G7,"") -> 0.17326197 | H19: =IFERROR(H18/H7,"") -> 0.19865522 | I19: =IFERROR(I18/I7,"") -> 0.17736752 | J19: =IFERROR(J18/J7,"") -> 0.15428191 | ... Q19: =IFERROR(Q18/Q7,"") -> 0.178
A20: Finance expense | B20: ₹ cr | C20: ='Raw Financials'!C15 -> 537.8 | D20: ='Raw Financials'!D15 -> 594.2 | E20: ='Raw Financials'!E15 -> 583 | F20: ='Raw Financials'!F15 -> 737.5 | G20: ='Raw Financials'!G15 -> 732.8 | H20: ='Raw Financials'!H15 -> 508.8 | I20: ='Raw Financials'!I15 -> 532.5 | J20: ='Raw Financials'!J15 -> 1007.7 | ... M20: ='Raw Financials'!M15 -> 1457.7 | N20: =SUM('Annual Balance Sheet'!M60,'Annual Balance Sheet'!M61)*Assumptions!C25 -> 1420.37 | O20: =SUM('Annual Balance Sheet'!N60,'Annual Balance Sheet'!N61)*Assumptions!D25 -> 1439.2155 | P20: =SUM('Annual Balance Sheet'!O60,'Annual Balance Sheet'!O61)*Assumptions!E25 -> 1458.1717 | Q20: =SUM('Annual Balance Sheet'!P60,'Annual Balance Sheet'!P61)*Assumptions!F25 -> 1479.0499
A21: Finance & other income | B21: ₹ cr | C21: ='Raw Financials'!C16 -> 2345.1 | D21: ='Raw Financials'!D16 -> 2241.9 | E21: ='Raw Financials'!E16 -> 2399.9 | F21: ='Raw Financials'!F16 -> 2292.3 | G21: ='Raw Financials'!G16 -> 2408.1 | H21: ='Raw Financials'!H16 -> 2091.2 | I21: ='Raw Financials'!I16 -> 1625.7 | J21: ='Raw Financials'!J16 -> 1818.5 | ... M21: ='Raw Financials'!M16 -> 3649.1 | N21: =SUM('Annual Balance Sheet'!M21:M22,'Annual Balance Sheet'!M11)*Assumptions!C24 -> 3427.728 | O21: =SUM('Annual Balance Sheet'!N21:N22,'Annual Balance Sheet'!N11)*Assumptions!D24 -> 2943.9668 | P21: =SUM('Annual Balance Sheet'!O21:O22,'Annual Balance Sheet'!O11)*Assumptions!E24 -> 3063.5425 | Q21: =SUM('Annual Balance Sheet'!P21:P22,'Annual Balance Sheet'!P11)*Assumptions!F24 -> 3197.571
A22: Share of associate / JV | B22: ₹ cr | C22: ='Raw Financials'!C17 -> 0 | D22: ='Raw Financials'!D17 -> 0 | E22: ='Raw Financials'!E17 -> 1.1 | F22: ='Raw Financials'!F17 -> -4.3 | G22: ='Raw Financials'!G17 -> 2.9 | H22: ='Raw Financials'!H17 -> 13 | I22: ='Raw Financials'!I17 -> 5.7 | J22: ='Raw Financials'!J17 -> -5.7 | ... M22: ='Raw Financials'!M17 -> 25.7 | N22: =0 -> 0 | O22: =0 -> 0 | P22: =0 -> 0 | Q22: =0 -> 0
A23: PBT | B23: ₹ cr | C23: ='Raw Financials'!C18 -> 11493.3 | D23: ='Raw Financials'!D18 -> 11035.6 | E23: ='Raw Financials'!E18 -> 10247.4 | F23: ='Raw Financials'!F18 -> 11541.5 | G23: ='Raw Financials'!G18 -> 12251.2 | H23: ='Raw Financials'!H18 -> 13900.7 | I23: ='Raw Financials'!I18 -> 15127.5 | J23: ='Raw Financials'!J18 -> 14765.7 | ... M23: ='Raw Financials'!M18 -> 17342.2 | N23: =N18-N20+N21+N22 -> 17657.344 | O23: =O18-O20+O21+O22 -> 18602.048 | P23: =P18-P20+P21+P22 -> 20588.27 | Q23: =Q18-Q20+Q21+Q22 -> 22790.68
A24: PBT margin | B24: % | C24: =IFERROR(C23/C7,"") -> 0.22428577 | D24: =IFERROR(D23/D7,"") -> 0.20050072 | E24: =IFERROR(E23/E7,"") -> 0.1880702 | F24: =IFERROR(F23/F7,"") -> 0.19700603 | G24: =IFERROR(G23/G7,"") -> 0.20076299 | H24: =IFERROR(H23/H7,"") -> 0.22441115 | I24: =IFERROR(I23/I7,"") -> 0.19126122 | J24: =IFERROR(J23/J7,"") -> 0.16317926 | ... Q24: =IFERROR(Q23/Q7,"") -> 0.19251663
A25: Tax | B25: ₹ cr | C25: ='Raw Financials'!C19 -> 2536.6 | D25: ='Raw Financials'!D19 -> 2521.3 | E25: ='Raw Financials'!E19 -> 2239 | F25: ='Raw Financials'!F19 -> 2524.2 | G25: ='Raw Financials'!G19 -> 2479.9 | H25: ='Raw Financials'!H19 -> 3034.5 | I25: ='Raw Financials'!I19 -> 2894.6 | J25: ='Raw Financials'!J19 -> 3399.2 | ... M25: ='Raw Financials'!M19 -> 4076.7 | N25: =N23*Assumptions!C26 -> 4237.7625 | O25: =O23*Assumptions!D26 -> 4464.4915 | P25: =P23*Assumptions!E26 -> 4941.1849 | Q25: =Q23*Assumptions!F26 -> 5469.7633
A26: Effective tax rate | B26: % | C26: =IFERROR(C25/C23,"") -> 0.2207025 | D26: =IFERROR(D25/D23,"") -> 0.22846968 | E26: =IFERROR(E25/E23,"") -> 0.21849445 | F26: =IFERROR(F25/F23,"") -> 0.21870641 | G26: =IFERROR(G25/G23,"") -> 0.20242099 | H26: =IFERROR(H25/H23,"") -> 0.21829836 | I26: =IFERROR(I25/I23,"") -> 0.19134688 | J26: =IFERROR(J25/J23,"") -> 0.2302092 | ... Q26: =IFERROR(Q25/Q23,"") -> 0.24
A27: Profit incl. NCI | B27: ₹ cr | C27: ='Raw Financials'!C20 -> 8956.7 | D27: ='Raw Financials'!D20 -> 8514.3 | E27: ='Raw Financials'!E20 -> 8008.4 | F27: ='Raw Financials'!F20 -> 9017.3 | G27: ='Raw Financials'!G20 -> 9771.3 | H27: ='Raw Financials'!H20 -> 10866.2 | I27: ='Raw Financials'!I20 -> 12232.9 | J27: ='Raw Financials'!J20 -> 11366.5 | ... M27: ='Raw Financials'!M20 -> 13265.5 | N27: =N23-N25 -> 13419.581 | O27: =O23-O25 -> 14137.557 | P27: =P23-P25 -> 15647.085 | Q27: =Q23-Q25 -> 17320.917
A28: NCI | B28: ₹ cr | C28: ='Raw Financials'!C21 -> 49.2 | D28: ='Raw Financials'!D21 -> 24.8 | E28: ='Raw Financials'!E21 -> 0.3 | F28: ='Raw Financials'!F21 -> 14.2 | G28: ='Raw Financials'!G21 -> 49.5 | H28: ='Raw Financials'!H21 -> 71.6 | I28: ='Raw Financials'!I21 -> 13.8 | J28: ='Raw Financials'!J21 -> 16.5 | ... M28: ='Raw Financials'!M21 -> 68.1 | N28: =0 -> 0 | O28: =0 -> 0 | P28: =0 -> 0 | Q28: =0 -> 0
A29: Net income attributable | B29: ₹ cr | C29: ='Raw Financials'!C22 -> 8907.5 | D29: ='Raw Financials'!D22 -> 8489.5 | E29: ='Raw Financials'!E22 -> 8008.1 | F29: ='Raw Financials'!F22 -> 9003.1 | G29: ='Raw Financials'!G22 -> 9721.8 | H29: ='Raw Financials'!H22 -> 10794.6 | I29: ='Raw Financials'!I22 -> 12219.1 | J29: ='Raw Financials'!J22 -> 11350 | ... M29: ='Raw Financials'!M22 -> 13197.4 | N29: =N27-N28 -> 13419.581 | O29: =O27-O28 -> 14137.557 | P29: =P27-P28 -> 15647.085 | Q29: =Q27-Q28 -> 17320.917
A30: Net margin | B30: % | C30: =IFERROR(C29/C7,"") -> 0.17382523 | D30: =IFERROR(D29/D7,"") -> 0.15424181 | E30: =IFERROR(E29/E7,"") -> 0.1469724 | F30: =IFERROR(F29/F7,"") -> 0.15367717 | G30: =IFERROR(G29/G7,"") -> 0.15931318 | H30: =IFERROR(H29/H7,"") -> 0.17426666 | I30: =IFERROR(I29/I7,"") -> 0.1544895 | J30: =IFERROR(J29/J7,"") -> 0.12543155 | ... Q30: =IFERROR(Q29/Q7,"") -> 0.14631264
A31: Basic weighted shares | B31: m | C31: ='Raw Financials'!C25 -> 4913.1188 | D31: ='Raw Financials'!D25 -> 6476.108 | E31: ='Raw Financials'!E25 -> 6333.3912 | F31: ='Raw Financials'!F25 -> 6007.3768 | G31: ='Raw Financials'!G25 -> 5833.384 | H31: ='Raw Financials'!H25 -> 5649.2659 | I31: ='Raw Financials'!I25 -> 5466.7058 | J31: ='Raw Financials'!J25 -> 10954.933 | ... M31: ='Raw Financials'!M25 -> 10476.248 | N31: =MAX(0,M31-Assumptions!C47*10/Assumptions!C51) -> 9644.2549 | O31: =MAX(0,N31-Assumptions!D47*10/Assumptions!D51) -> 9644.2549 | P31: =MAX(0,O31-Assumptions!E47*10/Assumptions!E51) -> 9644.2549 | Q31: =MAX(0,P31-Assumptions!F47*10/Assumptions!F51) -> 9644.2549
A32: Diluted weighted shares | B32: m | C32: ='Raw Financials'!C26 -> 4923.3798 | D32: ='Raw Financials'!D26 -> 6495.1295 | E32: ='Raw Financials'!E26 -> 6344.4826 | F32: ='Raw Financials'!F26 -> 6022.3044 | G32: ='Raw Financials'!G26 -> 5847.8232 | H32: ='Raw Financials'!H26 -> 5661.6578 | I32: ='Raw Financials'!I26 -> 5482.0834 | J32: ='Raw Financials'!J26 -> 10977.982 | ... M32: ='Raw Financials'!M26 -> 10503.423 | N32: =MAX(0,M32-Assumptions!C47*10/Assumptions!C51) -> 9671.43 | O32: =MAX(0,N32-Assumptions!D47*10/Assumptions!D51) -> 9671.43 | P32: =MAX(0,O32-Assumptions!E47*10/Assumptions!E51) -> 9671.43 | Q32: =MAX(0,P32-Assumptions!F47*10/Assumptions!F51) -> 9671.43
A33: Basic EPS | B33: ₹ / share | C33: =IFERROR(C29*10/C31,"") -> 18.130032 | D33: =IFERROR(D29*10/D31,"") -> 13.108954 | E33: =IFERROR(E29*10/E31,"") -> 12.644253 | F33: =IFERROR(F29*10/F31,"") -> 14.986741 | G33: =IFERROR(G29*10/G31,"") -> 16.665798 | H33: =IFERROR(H29*10/H31,"") -> 19.107969 | I33: =IFERROR(I29*10/I31,"") -> 22.351852 | J33: =IFERROR(J29*10/J31,"") -> 10.360629 | ... Q33: =IFERROR(Q29*10/Q31,"") -> 17.959829
A34: Diluted EPS | B34: ₹ / share | C34: =IFERROR(C29*10/C32,"") -> 18.092246 | D34: =IFERROR(D29*10/D32,"") -> 13.070563 | E34: =IFERROR(E29*10/E32,"") -> 12.622148 | F34: =IFERROR(F29*10/F32,"") -> 14.949593 | G34: =IFERROR(G29*10/G32,"") -> 16.624648 | H34: =IFERROR(H29*10/H32,"") -> 19.066147 | I34: =IFERROR(I29*10/I32,"") -> 22.289154 | J34: =IFERROR(J29*10/J32,"") -> 10.338876 | ... Q34: =IFERROR(Q29*10/Q32,"") -> 17.909365
A35: Dividend per share | B35: ₹ / share | C35: =IFERROR(-'Annual Cash Flow'!C46*10/C31,"") -> 7.2243317 | D35: =IFERROR(-'Annual Cash Flow'!D46*10/D31,"") -> 1.3486495 | E35: =IFERROR(-'Annual Cash Flow'!E46*10/E31,"") -> 0.85578165 | F35: =IFERROR(-'Annual Cash Flow'!F46*10/F31,"") -> 0.74974488 | G35: =IFERROR(-'Annual Cash Flow'!G46*10/G31,"") -> 0.97524867 | H35: =IFERROR(-'Annual Cash Flow'!H46*10/H31,"") -> 0.96632025 | I35: =IFERROR(-'Annual Cash Flow'!I46*10/I31,"") -> 1.0000538 | J35: =IFERROR(-'Annual Cash Flow'!J46*10/J31,"") -> 2.9953629 | ... M35: =IFERROR(-'Annual Cash Flow'!M46*10/M31,"") -> 10.996876 | N35: =N33*Assumptions!C46 -> 10.435939 | O35: =O33*Assumptions!D46 -> 10.554512 | P35: =P33*Assumptions!E46 -> 11.356979 | Q35: =Q33*Assumptions!F46 -> 12.57188
A36: Dividend payout | B36: % | C36: =IFERROR(C35/C33,"") -> 0.3984732 | D36: =IFERROR(D35/D33,"") -> 0.10288003 | E36: =IFERROR(E35/E33,"") -> 0.067681473 | F36: =IFERROR(F35/F33,"") -> 0.050027213 | G36: =IFERROR(G35/G33,"") -> 0.05851797 | H36: =IFERROR(H35/H33,"") -> 0.050571582 | I36: =IFERROR(I35/I33,"") -> 0.044741429 | J36: =IFERROR(J35/J33,"") -> 0.28911013 | ... Q36: =IFERROR(Q35/Q33,"") -> 0.7

Sheet Annual Balance Sheet
A1: Annual Balance Sheet
A2: Reported history; forecast lines are explicit schedules with cash linked only from the cash-flow statement
A5: Metric | B5: Units | C5: FY16A | D5: FY17A | E5: FY18A | F5: FY19A | G5: FY20A | H5: FY21A | I5: FY22A | J5: FY23A | K5: FY24A | L5: FY25A | M5: FY26A | N5: FY27E | O5: FY28E | P5: FY29E | Q5: FY30E
A7: PPE | B7: ₹ cr | C7: ='Raw Financials'!C55 -> 6495.2 | D7: ='Raw Financials'!D55 -> 6979.4 | E7: ='Raw Financials'!E55 -> 6444.3 | F7: ='Raw Financials'!F55 -> 7060.1 | G7: ='Raw Financials'!G55 -> 8112 | H7: ='Raw Financials'!H55 -> 8519.2 | I7: ='Raw Financials'!I55 -> 9089.8 | J7: ='Raw Financials'!J55 -> 8865.9 | ... M7: ='Raw Financials'!M55 -> 8178.7 | N7: ='BS Forecast Schedules'!D17 -> 8221.642 | O7: ='BS Forecast Schedules'!E17 -> 8312.6927 | P7: ='BS Forecast Schedules'!F17 -> 8459.9738 | Q7: ='BS Forecast Schedules'!G17 -> 8673.0631
A8: ROU assets | B8: ₹ cr | C8: ='Raw Financials'!C56 -> 0 | D8: ='Raw Financials'!D56 -> 0 | E8: ='Raw Financials'!E56 -> 0 | F8: ='Raw Financials'!F56 -> 1326.6 | G8: ='Raw Financials'!G56 -> 1674.8 | H8: ='Raw Financials'!H56 -> 1642 | I8: ='Raw Financials'!I56 -> 1887 | J8: ='Raw Financials'!J56 -> 1870.2 | ... M8: ='Raw Financials'!M56 -> 2828.7 | N8: ='BS Forecast Schedules'!D25 -> 3086.3522 | O8: ='BS Forecast Schedules'!E25 -> 3389.8545 | P8: ='BS Forecast Schedules'!F25 -> 3749.875 | Q8: ='BS Forecast Schedules'!G25 -> 4176.0535
A9: Goodwill | B9: ₹ cr | C9: ='Raw Financials'!C57 -> 10199.1 | D9: ='Raw Financials'!D57 -> 12579.6 | E9: ='Raw Financials'!E57 -> 11758.4 | F9: ='Raw Financials'!F57 -> 11698 | G9: ='Raw Financials'!G57 -> 13101.2 | H9: ='Raw Financials'!H57 -> 13912.7 | I9: ='Raw Financials'!I57 -> 24698.9 | J9: ='Raw Financials'!J57 -> 30797 | ... M9: ='Raw Financials'!M57 -> 38739.9 | N9: =M9 -> 38739.9 | O9: =N9 -> 38739.9 | P9: =O9 -> 38739.9 | Q9: =P9 -> 38739.9
A10: Intangibles | B10: ₹ cr | C10: ='Raw Financials'!C58 -> 1584.1 | D10: ='Raw Financials'!D58 -> 1592.2 | E10: ='Raw Financials'!E58 -> 1811.3 | F10: ='Raw Financials'!F58 -> 1376.2 | G10: ='Raw Financials'!G58 -> 1636.2 | H10: ='Raw Financials'!H58 -> 1308.5 | I10: ='Raw Financials'!I58 -> 4355.5 | J10: ='Raw Financials'!J58 -> 4304.5 | ... M10: ='Raw Financials'!M58 -> 2917.6 | N10: ='BS Forecast Schedules'!D18 -> 2521.579 | O10: ='BS Forecast Schedules'!E18 -> 2127.026 | P10: ='BS Forecast Schedules'!F18 -> 1728.8215 | Q10: ='BS Forecast Schedules'!G18 -> 1326.3196
A11: Non-current investments | B11: ₹ cr | C11: ='Raw Financials'!C59 -> 490.7 | D11: ='Raw Financials'!D59 -> 0 | E11: ='Raw Financials'!E59 -> 0 | F11: ='Raw Financials'!F59 -> 0 | G11: ='Raw Financials'!G59 -> 0 | H11: ='Raw Financials'!H59 -> 0 | I11: ='Raw Financials'!I59 -> 0 | J11: ='Raw Financials'!J59 -> 0 | ... M11: ='Raw Financials'!M59 -> 2805.3 | N11: =M11 -> 2805.3 | O11: =N11 -> 2805.3 | P11: =O11 -> 2805.3 | Q11: =P11 -> 2805.3
A12: Equity-method investments | B12: ₹ cr | C12: ='Raw Financials'!C60 -> 0 | D12: ='Raw Financials'!D60 -> 0 | E12: ='Raw Financials'!E60 -> 0 | F12: ='Raw Financials'!F60 -> 0 | G12: ='Raw Financials'!G60 -> 0 | H12: ='Raw Financials'!H60 -> 0 | I12: ='Raw Financials'!I60 -> 0 | J12: ='Raw Financials'!J60 -> 0 | ... M12: ='Raw Financials'!M60 -> 212.6 | N12: =M12 -> 212.6 | O12: =N12 -> 212.6 | P12: =O12 -> 212.6 | Q12: =P12 -> 212.6
A13: Non-current receivables & unbilled | B13: ₹ cr | C13: =SUM('Raw Financials'!C61,'Raw Financials'!C62) -> 0 | D13: =SUM('Raw Financials'!D61,'Raw Financials'!D62) -> 399.8 | E13: =SUM('Raw Financials'!E61,'Raw Financials'!E62) -> 444.6 | F13: =SUM('Raw Financials'!F61,'Raw Financials'!F62) -> 437.3 | G13: =SUM('Raw Financials'!G61,'Raw Financials'!G62) -> 604.9 | H13: =SUM('Raw Financials'!H61,'Raw Financials'!H62) -> 435.8 | I13: =SUM('Raw Financials'!I61,'Raw Financials'!I62) -> 476.5 | J13: =SUM('Raw Financials'!J61,'Raw Financials'!J62) -> 86.3 | ... M13: =SUM('Raw Financials'!M61,'Raw Financials'!M62) -> 778.2 | N13: =M13 -> 778.2 | O13: =N13 -> 778.2 | P13: =O13 -> 778.2 | Q13: =P13 -> 778.2
A14: Other non-current financial assets | B14: ₹ cr | C14: ='Raw Financials'!C63 -> 0 | D14: ='Raw Financials'!D63 -> 2.6 | E14: ='Raw Financials'!E63 -> 418.6 | F14: ='Raw Financials'!F63 -> 514.6 | G14: ='Raw Financials'!G63 -> 588.1 | H14: ='Raw Financials'!H63 -> 608.8 | I14: ='Raw Financials'!I63 -> 608.4 | J14: ='Raw Financials'!J63 -> 633 | ... M14: ='Raw Financials'!M63 -> 625.9 | N14: ='Annual P&L'!N7*Assumptions!C33*0.25 -> 596.41713 | O14: ='Annual P&L'!O7*Assumptions!D33*0.25 -> 607.00462 | P14: ='Annual P&L'!P7*Assumptions!E33*0.25 -> 627.30846 | Q14: ='Annual P&L'!Q7*Assumptions!F33*0.25 -> 651.10604
A15: Deferred tax assets | B15: ₹ cr | C15: ='Raw Financials'!C64 -> 380 | D15: ='Raw Financials'!D64 -> 309.8 | E15: ='Raw Financials'!E64 -> 690.8 | F15: ='Raw Financials'!F64 -> 560.4 | G15: ='Raw Financials'!G64 -> 600.5 | H15: ='Raw Financials'!H64 -> 166.4 | I15: ='Raw Financials'!I64 -> 229.8 | J15: ='Raw Financials'!J64 -> 210 | ... M15: ='Raw Financials'!M64 -> 524.2 | N15: =M15 -> 524.2 | O15: =N15 -> 524.2 | P15: =O15 -> 524.2 | Q15: =P15 -> 524.2
A16: Non-current tax assets | B16: ₹ cr | C16: ='Raw Financials'!C65 -> 1175.1 | D16: ='Raw Financials'!D65 -> 1200.8 | E16: ='Raw Financials'!E65 -> 1834.9 | F16: ='Raw Financials'!F65 -> 2060.3 | G16: ='Raw Financials'!G65 -> 1141.4 | H16: ='Raw Financials'!H65 -> 1432.3 | I16: ='Raw Financials'!I65 -> 1025.6 | J16: ='Raw Financials'!J65 -> 1192.2 | ... M16: ='Raw Financials'!M65 -> 778.7 | N16: =M16 -> 778.7 | O16: =N16 -> 778.7 | P16: =O16 -> 778.7 | Q16: =P16 -> 778.7
A17: Other non-current assets | B17: ₹ cr | C17: ='Raw Financials'!C66 -> 1582.8 | D17: ='Raw Financials'!D66 -> 1679.3 | E17: ='Raw Financials'!E66 -> 1572.6 | F17: ='Raw Financials'!F66 -> 2101.8 | G17: ='Raw Financials'!G66 -> 0 | H17: ='Raw Financials'!H66 -> 0 | I17: ='Raw Financials'!I66 -> 0 | J17: ='Raw Financials'!J66 -> 0 | ... M17: ='Raw Financials'!M66 -> 901 | N17: ='Annual P&L'!N7*Assumptions!C33*0.75 -> 1789.2514 | O17: ='Annual P&L'!O7*Assumptions!D33*0.75 -> 1821.0139 | P17: ='Annual P&L'!P7*Assumptions!E33*0.75 -> 1881.9254 | Q17: ='Annual P&L'!Q7*Assumptions!F33*0.75 -> 1953.3181
A18: Total non-current assets | B18: ₹ cr | C18: ='Raw Financials'!C67 -> 21933 | D18: ='Raw Financials'!D67 -> 25461.8 | E18: ='Raw Financials'!E67 -> 25448.4 | F18: ='Raw Financials'!F67 -> 26126.5 | G18: ='Raw Financials'!G67 -> 29721.1 | H18: ='Raw Financials'!H67 -> 30824.8 | I18: ='Raw Financials'!I67 -> 45843 | J18: ='Raw Financials'!J67 -> 51472.6 | ... M18: ='Raw Financials'!M67 -> 59290.8 | N18: =SUM(N7:N17) -> 60054.142 | O18: =SUM(O7:O17) -> 60096.492 | P18: =SUM(P7:P17) -> 60286.804 | Q18: =SUM(Q7:Q17) -> 60618.76
A19: Inventories | B19: ₹ cr | C19: ='Raw Financials'!C68 -> 539 | D19: ='Raw Financials'!D68 -> 391.5 | E19: ='Raw Financials'!E68 -> 337 | F19: ='Raw Financials'!F68 -> 395.1 | G19: ='Raw Financials'!G68 -> 186.5 | H19: ='Raw Financials'!H68 -> 106.4 | I19: ='Raw Financials'!I68 -> 133.4 | J19: ='Raw Financials'!J68 -> 118.8 | ... M19: ='Raw Financials'!M68 -> 51.7 | N19: ='Annual P&L'!N7*Assumptions!C29 -> 57.256045 | O19: ='Annual P&L'!O7*Assumptions!D29 -> 60.700462 | P19: ='Annual P&L'!P7*Assumptions!E29 -> 65.458274 | Q19: ='Annual P&L'!Q7*Assumptions!F29 -> 71.02975
A20: Derivative assets | B20: ₹ cr | C20: ='Raw Financials'!C69 -> 567.5 | D20: ='Raw Financials'!D69 -> 974.7 | E20: ='Raw Financials'!E69 -> 123.2 | F20: ='Raw Financials'!F69 -> 493.1 | G20: ='Raw Financials'!G69 -> 302.5 | H20: ='Raw Financials'!H69 -> 406.4 | I20: ='Raw Financials'!I69 -> 303.2 | J20: ='Raw Financials'!J69 -> 184.4 | ... M20: ='Raw Financials'!M69 -> 88.8 | N20: =M20 -> 88.8 | O20: =N20 -> 88.8 | P20: =O20 -> 88.8 | Q20: =P20 -> 88.8
A21: Current investments | B21: ₹ cr | C21: ='Raw Financials'!C70 -> 13294.4 | D21: ='Raw Financials'!D70 -> 29203 | E21: ='Raw Financials'!E70 -> 24909.4 | F21: ='Raw Financials'!F70 -> 22071.6 | G21: ='Raw Financials'!G70 -> 18963.5 | H21: ='Raw Financials'!H70 -> 17570.7 | I21: ='Raw Financials'!I70 -> 24165.5 | J21: ='Raw Financials'!J70 -> 30923.2 | ... M21: ='Raw Financials'!M70 -> 43768 | N21: ='Annual P&L'!N7*Assumptions!C32 -> 41987.766 | O21: ='Annual P&L'!O7*Assumptions!D32 -> 42490.323 | P21: ='Annual P&L'!P7*Assumptions!E32 -> 43638.85 | Q21: ='Annual P&L'!Q7*Assumptions!F32 -> 44985.508
A22: Cash & equivalents | B22: ₹ cr | C22: ='Raw Financials'!C71 -> 9904.9 | D22: ='Raw Financials'!D71 -> 5271 | E22: ='Raw Financials'!E71 -> 4492.5 | F22: ='Raw Financials'!F71 -> 15852.9 | G22: ='Raw Financials'!G71 -> 14449.9 | H22: ='Raw Financials'!H71 -> 16979.3 | I22: ='Raw Financials'!I71 -> 10383.6 | J22: ='Raw Financials'!J71 -> 9188 | ... M22: ='Raw Financials'!M71 -> 10555.5 | N22: ='BS Forecast Schedules'!D58 -> 5964.9826 | O22: ='BS Forecast Schedules'!E58 -> 10405.149 | P22: ='BS Forecast Schedules'!F58 -> 15047.6 | Q22: ='BS Forecast Schedules'!G58 -> 19893.038
A23: Billed receivables | B23: ₹ cr | C23: ='Raw Financials'!C72 -> 10238 | D23: ='Raw Financials'!D72 -> 9484.6 | E23: ='Raw Financials'!E72 -> 10099 | F23: ='Raw Financials'!F72 -> 10048.9 | G23: ='Raw Financials'!G72 -> 10447.4 | H23: ='Raw Financials'!H72 -> 9429.8 | I23: ='Raw Financials'!I72 -> 11521.9 | J23: ='Raw Financials'!J72 -> 12635 | ... M23: ='Raw Financials'!M72 -> 13590.1 | N23: ='Annual P&L'!N7/365*Assumptions!C27 -> 14379.372 | O23: ='Annual P&L'!O7/365*Assumptions!D27 -> 14967.237 | P23: ='Annual P&L'!P7/365*Assumptions!E27 -> 15841.5 | Q23: ='Annual P&L'!Q7/365*Assumptions!F27 -> 16865.511
A24: Unbilled + contract assets | B24: ₹ cr | C24: =SUM('Raw Financials'!C73,'Raw Financials'!C75) -> 4827.3 | D24: =SUM('Raw Financials'!D73,'Raw Financials'!D75) -> 0 | E24: =SUM('Raw Financials'!E73,'Raw Financials'!E75) -> 0 | F24: =SUM('Raw Financials'!F73,'Raw Financials'!F75) -> 0 | G24: =SUM('Raw Financials'!G73,'Raw Financials'!G75) -> 0 | H24: =SUM('Raw Financials'!H73,'Raw Financials'!H75) -> 0 | I24: =SUM('Raw Financials'!I73,'Raw Financials'!I75) -> 0 | J24: =SUM('Raw Financials'!J73,'Raw Financials'!J75) -> 0 | ... M24: =SUM('Raw Financials'!M73,'Raw Financials'!M75) -> 9164.2 | N24: ='Annual P&L'!N7/365*Assumptions!C28 -> 9411.9526 | O24: ='Annual P&L'!O7/365*Assumptions!D28 -> 9700.987 | P24: ='Annual P&L'!P7/365*Assumptions!E28 -> 10162.472 | Q24: ='Annual P&L'!Q7/365*Assumptions!F28 -> 10703.113
A25: Other current financial assets | B25: ₹ cr | C25: ='Raw Financials'!C74 -> 0 | D25: ='Raw Financials'!D74 -> 517.7 | E25: ='Raw Financials'!E74 -> 742.9 | F25: ='Raw Financials'!F74 -> 1461.1 | G25: ='Raw Financials'!G74 -> 861.4 | H25: ='Raw Financials'!H74 -> 724.5 | I25: ='Raw Financials'!I74 -> 4291.4 | J25: ='Raw Financials'!J74 -> 909.6 | ... M25: ='Raw Financials'!M74 -> 1024.5 | N25: ='Annual P&L'!N7*Assumptions!C30 -> 1049.6942 | O25: ='Annual P&L'!O7*Assumptions!D30 -> 1112.8418 | P25: ='Annual P&L'!P7*Assumptions!E30 -> 1090.9712 | Q25: ='Annual P&L'!Q7*Assumptions!F30 -> 1183.8292
A26: Current tax assets | B26: ₹ cr | C26: ='Raw Financials'!C76 -> 781.2 | D26: ='Raw Financials'!D76 -> 980.4 | E26: ='Raw Financials'!E76 -> 626.2 | F26: ='Raw Financials'!F76 -> 743.5 | G26: ='Raw Financials'!G76 -> 288.2 | H26: ='Raw Financials'!H76 -> 246.1 | I26: ='Raw Financials'!I76 -> 237.3 | J26: ='Raw Financials'!J76 -> 509.1 | ... M26: ='Raw Financials'!M76 -> 1076.2 | N26: =M26 -> 1076.2 | O26: =N26 -> 1076.2 | P26: =O26 -> 1076.2 | Q26: =P26 -> 1076.2
A27: Other current assets | B27: ₹ cr | C27: ='Raw Financials'!C77 -> 10406.8 | D27: ='Raw Financials'!D77 -> 3075.1 | E27: ='Raw Financials'!E77 -> 3059.6 | F27: ='Raw Financials'!F77 -> 3769.7 | G27: ='Raw Financials'!G77 -> 0 | H27: ='Raw Financials'!H77 -> 0 | I27: ='Raw Financials'!I77 -> 0 | J27: ='Raw Financials'!J77 -> 0 | ... M27: ='Raw Financials'!M77 -> 3316.4 | N27: ='Annual P&L'!N7*Assumptions!C31 -> 3435.3627 | O27: ='Annual P&L'!O7*Assumptions!D31 -> 3540.8603 | P27: ='Annual P&L'!P7*Assumptions!E31 -> 3709.3022 | Q27: ='Annual P&L'!Q7*Assumptions!F31 -> 3906.6363
A28: Total current assets | B28: ₹ cr | C28: ='Raw Financials'!C78 -> 50559.1 | D28: ='Raw Financials'!D78 -> 53889.8 | E28: ='Raw Financials'!E78 -> 50615.6 | F28: ='Raw Financials'!F78 -> 57190.6 | G28: ='Raw Financials'!G78 -> 51985.1 | H28: ='Raw Financials'!H78 -> 52318.6 | I28: ='Raw Financials'!I78 -> 62075.2 | J28: ='Raw Financials'!J78 -> 66109.6 | ... M28: ='Raw Financials'!M78 -> 82635.4 | N28: =SUM(N19:N27) -> 77451.386 | O28: =SUM(O19:O27) -> 83443.099 | P28: =SUM(P19:P27) -> 90721.153 | Q28: =SUM(Q19:Q27) -> 98773.667
A29: Total assets | B29: ₹ cr | C29: ='Raw Financials'!C79 -> 72492.1 | D29: ='Raw Financials'!D79 -> 79351.6 | E29: ='Raw Financials'!E79 -> 76064 | F29: ='Raw Financials'!F79 -> 83317.1 | G29: ='Raw Financials'!G79 -> 81706.2 | H29: ='Raw Financials'!H79 -> 83143.4 | I29: ='Raw Financials'!I79 -> 107918.2 | J29: ='Raw Financials'!J79 -> 117582.2 | ... M29: ='Raw Financials'!M79 -> 141926.2 | N29: =SUM(N18,N28) -> 137505.53 | O29: =SUM(O18,O28) -> 143539.59 | P29: =SUM(P18,P28) -> 151007.96 | Q29: =SUM(Q18,Q28) -> 159392.43
A31: Share capital | B31: ₹ cr | C31: ='Raw Financials'!C80 -> 494.1 | D31: ='Raw Financials'!D80 -> 486.1 | E31: ='Raw Financials'!E80 -> 904.8 | F31: ='Raw Financials'!F80 -> 1206.8 | G31: ='Raw Financials'!G80 -> 1142.7 | H31: ='Raw Financials'!H80 -> 1095.8 | I31: ='Raw Financials'!I80 -> 1096.4 | J31: ='Raw Financials'!J80 -> 1097.6 | ... M31: ='Raw Financials'!M80 -> 2097.7 | N31: =M31 -> 2097.7 | O31: =N31 -> 2097.7 | P31: =O31 -> 2097.7 | Q31: =P31 -> 2097.7
A32: Share premium | B32: ₹ cr | C32: ='Raw Financials'!C81 -> 1464.2 | D32: ='Raw Financials'!D81 -> 46.9 | E32: ='Raw Financials'!E81 -> 80 | F32: ='Raw Financials'!F81 -> 53.3 | G32: ='Raw Financials'!G81 -> 127.5 | H32: ='Raw Financials'!H81 -> 71.4 | I32: ='Raw Financials'!I81 -> 156.6 | J32: ='Raw Financials'!J81 -> 368.9 | ... M32: ='Raw Financials'!M81 -> 615.8 | N32: =M32 -> 615.8 | O32: =N32 -> 615.8 | P32: =O32 -> 615.8 | Q32: =P32 -> 615.8
A33: Other equity / retained earnings & reserves | B33: ₹ cr | C33: =C34-C31-C32 -> 44649.5 | D33: =D34-D31-D32 -> 51497.4 | E33: =E34-E31-E32 -> 47308.8 | F33: =F34-F31-F32 -> 55551.5 | G33: =G34-G31-G32 -> 54475.6 | H33: =H34-H31-H32 -> 54142.3 | I33: =I34-I31-I32 -> 64562.8 | J33: =J34-J31-J32 -> 76649.9 | ... Q33: =Q34-Q31-Q32 -> 90147.483
A34: Equity attributable | B34: ₹ cr | C34: ='Raw Financials'!C83 -> 46607.8 | D34: ='Raw Financials'!D83 -> 52030.4 | E34: ='Raw Financials'!E83 -> 48293.6 | F34: ='Raw Financials'!F83 -> 56811.6 | G34: ='Raw Financials'!G83 -> 55745.8 | H34: ='Raw Financials'!H83 -> 55309.5 | I34: ='Raw Financials'!I83 -> 65815.8 | J34: ='Raw Financials'!J83 -> 78116.4 | ... M34: ='Raw Financials'!M83 -> 88536.8 | N34: ='BS Forecast Schedules'!D47 -> 77368.829 | O34: ='BS Forecast Schedules'!E47 -> 81833.182 | P34: ='BS Forecast Schedules'!F47 -> 87072.793 | Q34: ='BS Forecast Schedules'!G47 -> 92860.983
A35: NCI | B35: ₹ cr | C35: ='Raw Financials'!C84 -> 222.4 | D35: ='Raw Financials'!D84 -> 239.1 | E35: ='Raw Financials'!E84 -> 241 | F35: ='Raw Financials'!F84 -> 263.7 | G35: ='Raw Financials'!G84 -> 187.5 | H35: ='Raw Financials'!H84 -> 149.8 | I35: ='Raw Financials'!I84 -> 51.5 | J35: ='Raw Financials'!J84 -> 58.9 | ... M35: ='Raw Financials'!M84 -> 250.9 | N35: ='BS Forecast Schedules'!D48 -> 250.9 | O35: ='BS Forecast Schedules'!E48 -> 250.9 | P35: ='BS Forecast Schedules'!F48 -> 250.9 | Q35: ='BS Forecast Schedules'!G48 -> 250.9
A36: Total equity | B36: ₹ cr | C36: ='Raw Financials'!C85 -> 46830.2 | D36: ='Raw Financials'!D85 -> 52269.5 | E36: ='Raw Financials'!E85 -> 48534.6 | F36: ='Raw Financials'!F85 -> 57075.3 | G36: ='Raw Financials'!G85 -> 55933.3 | H36: ='Raw Financials'!H85 -> 55459.3 | I36: ='Raw Financials'!I85 -> 65867.3 | J36: ='Raw Financials'!J85 -> 78175.3 | ... M36: ='Raw Financials'!M85 -> 88787.7 | N36: ='BS Forecast Schedules'!D49 -> 77619.729 | O36: ='BS Forecast Schedules'!E49 -> 82084.082 | P36: ='BS Forecast Schedules'!F49 -> 87323.693 | Q36: ='BS Forecast Schedules'!G49 -> 93111.883
A38: Long-term borrowings | B38: ₹ cr | C38: ='Raw Financials'!C86 -> 1736.1 | D38: ='Raw Financials'!D86 -> 1961.1 | E38: ='Raw Financials'!E86 -> 4526.8 | F38: ='Raw Financials'!F86 -> 2836.8 | G38: ='Raw Financials'!G86 -> 484 | H38: ='Raw Financials'!H86 -> 745.8 | I38: ='Raw Financials'!I86 -> 5646.3 | J38: ='Raw Financials'!J86 -> 6127.2 | ... M38: ='Raw Financials'!M86 -> 196.2 | N38: ='BS Forecast Schedules'!D37 -> 335.748 | O38: ='BS Forecast Schedules'!E37 -> 335.748 | P38: ='BS Forecast Schedules'!F37 -> 335.748 | Q38: ='BS Forecast Schedules'!G37 -> 335.748
A39: Non-current lease liabilities | B39: ₹ cr | C39: ='Raw Financials'!C87 -> 0 | D39: ='Raw Financials'!D87 -> 0 | E39: ='Raw Financials'!E87 -> 0 | F39: ='Raw Financials'!F87 -> 0 | G39: ='Raw Financials'!G87 -> 656 | H39: ='Raw Financials'!H87 -> 1351.3 | I39: ='Raw Financials'!I87 -> 1517.7 | J39: ='Raw Financials'!J87 -> 1595.3 | ... M39: ='Raw Financials'!M87 -> 2632.7 | N39: ='BS Forecast Schedules'!D29*(1-Assumptions!C45) -> 75.456418 | O39: ='BS Forecast Schedules'!E29*(1-Assumptions!D45) -> 80.872498 | P39: ='BS Forecast Schedules'!F29*(1-Assumptions!E45) -> 86.837683 | Q39: ='BS Forecast Schedules'!G29*(1-Assumptions!F45) -> 93.540163
A40: Other non-current financial liabilities | B40: ₹ cr | C40: ='Raw Financials'!C88 -> 0 | D40: ='Raw Financials'!D88 -> 0 | E40: ='Raw Financials'!E88 -> 0.7 | F40: ='Raw Financials'!F88 -> 0 | G40: ='Raw Financials'!G88 -> 15.1 | H40: ='Raw Financials'!H88 -> 229.1 | I40: ='Raw Financials'!I88 -> 296.1 | J40: ='Raw Financials'!J88 -> 264.9 | ... M40: ='Raw Financials'!M88 -> 674.3 | N40: ='Annual P&L'!N7*Assumptions!C36*0.08 -> 610.73114 | O40: ='Annual P&L'!O7*Assumptions!D36*0.08 -> 631.2848 | P40: ='Annual P&L'!P7*Assumptions!E36*0.08 -> 663.31051 | Q40: ='Annual P&L'!Q7*Assumptions!F36*0.08 -> 700.82687
A41: Deferred tax liabilities | B41: ₹ cr | C41: ='Raw Financials'!C89 -> 510.8 | D41: ='Raw Financials'!D89 -> 661.4 | E41: ='Raw Financials'!E89 -> 305.9 | F41: ='Raw Financials'!F89 -> 341.7 | G41: ='Raw Financials'!G89 -> 282.5 | H41: ='Raw Financials'!H89 -> 463.3 | I41: ='Raw Financials'!I89 -> 1214.1 | J41: ='Raw Financials'!J89 -> 1515.3 | ... M41: ='Raw Financials'!M89 -> 1726.6 | N41: =M41 -> 1726.6 | O41: =N41 -> 1726.6 | P41: =O41 -> 1726.6 | Q41: =P41 -> 1726.6
A42: Non-current tax liabilities | B42: ₹ cr | C42: ='Raw Financials'!C90 -> 823.1 | D42: ='Raw Financials'!D90 -> 954.7 | E42: ='Raw Financials'!E90 -> 922 | F42: ='Raw Financials'!F90 -> 1102.3 | G42: ='Raw Financials'!G90 -> 1320.5 | H42: ='Raw Financials'!H90 -> 1106.9 | I42: ='Raw Financials'!I90 -> 1781.8 | J42: ='Raw Financials'!J90 -> 2177.7 | ... M42: ='Raw Financials'!M90 -> 4819.5 | N42: =M42 -> 4819.5 | O42: =N42 -> 4819.5 | P42: =O42 -> 4819.5 | Q42: =P42 -> 4819.5
A43: Other non-current liabilities | B43: ₹ cr | C43: ='Raw Financials'!C93-SUM(C38:C42,C44) -> 734.4 | D43: ='Raw Financials'!D93-SUM(D38:D42,D44) -> 550.2 | E43: ='Raw Financials'!E93-SUM(E38:E42,E44) -> 423 | F43: ='Raw Financials'!F93-SUM(F38:F42,F44) -> 525.8 | G43: ='Raw Financials'!G93-SUM(G38:G42,G44) -> 1375.3 | H43: ='Raw Financials'!H93-SUM(H38:H42,H44) -> 783.5 | I43: ='Raw Financials'!I93-SUM(I38:I42,I44) -> 761.9 | J43: ='Raw Financials'!J93-SUM(J38:J42,J44) -> 951.2 | ... M43: ='Raw Financials'!M93-SUM(M38:M42,M44) -> 2743.6 | N43: ='Annual P&L'!N7*Assumptions!C36-N40-N44 -> 6947.0668 | O43: ='Annual P&L'!O7*Assumptions!D36-O40-O44 -> 7180.8646 | P43: ='Annual P&L'!P7*Assumptions!E36-P40-P44 -> 7545.1571 | Q43: ='Annual P&L'!Q7*Assumptions!F36-Q40-Q44 -> 7971.9056
A44: Non-current provisions | B44: ₹ cr | C44: ='Raw Financials'!C92 -> 1.4 | D44: ='Raw Financials'!D92 -> 0.4 | E44: ='Raw Financials'!E92 -> 0.3 | F44: ='Raw Financials'!F92 -> 0.2 | G44: ='Raw Financials'!G92 -> 0.2 | H44: ='Raw Financials'!H92 -> 0.2 | I44: ='Raw Financials'!I92 -> 0.1 | J44: ='Raw Financials'!J92 -> 0 | ... M44: ='Raw Financials'!M92 -> 22.4 | N44: ='Annual P&L'!N7*Assumptions!C36*Assumptions!C56 -> 76.341393 | O44: ='Annual P&L'!O7*Assumptions!D36*Assumptions!D56 -> 78.9106 | P44: ='Annual P&L'!P7*Assumptions!E36*Assumptions!E56 -> 82.913814 | Q44: ='Annual P&L'!Q7*Assumptions!F36*Assumptions!F56 -> 87.603359
A45: Total non-current liabilities | B45: ₹ cr | C45: ='Raw Financials'!C93 -> 3805.8 | D45: ='Raw Financials'!D93 -> 4127.8 | E45: ='Raw Financials'!E93 -> 6178.7 | F45: ='Raw Financials'!F93 -> 4806.8 | G45: ='Raw Financials'!G93 -> 4133.6 | H45: ='Raw Financials'!H93 -> 4680.1 | I45: ='Raw Financials'!I93 -> 11218 | J45: ='Raw Financials'!J93 -> 12631.6 | ... M45: ='Raw Financials'!M93 -> 12815.3 | N45: =SUM(N38:N44) -> 14591.444 | O45: =SUM(O38:O44) -> 14853.781 | P45: =SUM(P38:P44) -> 15260.067 | Q45: =SUM(Q38:Q44) -> 15735.724
A47: Short-term borrowings | B47: ₹ cr | C47: ='Raw Financials'!C94 -> 10786 | D47: ='Raw Financials'!D94 -> 12280.1 | E47: ='Raw Financials'!E94 -> 9299.1 | F47: ='Raw Financials'!F94 -> 7109.9 | G47: ='Raw Financials'!G94 -> 7320.2 | H47: ='Raw Financials'!H94 -> 7587.4 | I47: ='Raw Financials'!I94 -> 9523.3 | J47: ='Raw Financials'!J94 -> 8882.1 | ... M47: ='Raw Financials'!M94 -> 16591.2 | N47: ='BS Forecast Schedules'!D36 -> 16451.652 | O47: ='BS Forecast Schedules'!E36 -> 16451.652 | P47: ='BS Forecast Schedules'!F36 -> 16451.652 | Q47: ='BS Forecast Schedules'!G36 -> 16451.652
A48: Current lease liabilities | B48: ₹ cr | C48: ='Raw Financials'!C95 -> 0 | D48: ='Raw Financials'!D95 -> 0 | E48: ='Raw Financials'!E95 -> 0 | F48: ='Raw Financials'!F95 -> 0 | G48: ='Raw Financials'!G95 -> 1263.8 | H48: ='Raw Financials'!H95 -> 766.9 | I48: ='Raw Financials'!I95 -> 905.6 | J48: ='Raw Financials'!J95 -> 862 | ... M48: ='Raw Financials'!M95 -> 870.9 | N48: ='BS Forecast Schedules'!D29*Assumptions!C45 -> 3697.3645 | O48: ='BS Forecast Schedules'!E29*Assumptions!D45 -> 3962.7524 | P48: ='BS Forecast Schedules'!F29*Assumptions!E45 -> 4255.0465 | Q48: ='BS Forecast Schedules'!G29*Assumptions!F45 -> 4583.468
A49: Derivative liabilities | B49: ₹ cr | C49: ='Raw Financials'!C96 -> 234 | D49: ='Raw Financials'!D96 -> 270.8 | E49: ='Raw Financials'!E96 -> 221 | F49: ='Raw Financials'!F96 -> 131 | G49: ='Raw Financials'!G96 -> 723.1 | H49: ='Raw Financials'!H96 -> 107 | I49: ='Raw Financials'!I96 -> 58.5 | J49: ='Raw Financials'!J96 -> 282.5 | ... M49: ='Raw Financials'!M96 -> 1097.8 | N49: =M49 -> 1097.8 | O49: =N49 -> 1097.8 | P49: =O49 -> 1097.8 | Q49: =P49 -> 1097.8
A50: Trade payables | B50: ₹ cr | C50: ='Raw Financials'!C97 -> 6818.7 | D50: ='Raw Financials'!D97 -> 6548.6 | E50: ='Raw Financials'!E97 -> 6812.9 | F50: ='Raw Financials'!F97 -> 8830.4 | G50: ='Raw Financials'!G97 -> 7812.9 | H50: ='Raw Financials'!H97 -> 7651.2 | I50: ='Raw Financials'!I97 -> 9447.7 | J50: ='Raw Financials'!J97 -> 8905.4 | ... M50: ='Raw Financials'!M97 -> 9492.4 | N50: ='Annual P&L'!N7*Assumptions!C34 -> 9733.5276 | O50: ='Annual P&L'!O7*Assumptions!D34 -> 10217.911 | P50: ='Annual P&L'!P7*Assumptions!E34 -> 10909.712 | Q50: ='Annual P&L'!Q7*Assumptions!F34 -> 11719.909
A51: Other current financial liabilities | B51: ₹ cr | C51: ='Raw Financials'!C98 -> 0 | D51: ='Raw Financials'!D98 -> 0 | E51: ='Raw Financials'!E98 -> 105 | F51: ='Raw Financials'!F98 -> 64.4 | G51: ='Raw Financials'!G98 -> 89.9 | H51: ='Raw Financials'!H98 -> 147 | I51: ='Raw Financials'!I98 -> 3311 | J51: ='Raw Financials'!J98 -> 414.1 | ... M51: ='Raw Financials'!M98 -> 1135.7 | N51: ='Annual P&L'!N7*Assumptions!C35*(1-Assumptions!C53-Assumptions!C54-Assumptions!C55-24%) -> 5725.6045 | O51: ='Annual P&L'!O7*Assumptions!D35*(1-Assumptions!D53-Assumptions!D54-Assumptions!D55-24%) -> 5948.6453 | P51: ='Annual P&L'!P7*Assumptions!E35*(1-Assumptions!E53-Assumptions!E54-Assumptions!E55-24%) -> 6283.9943 | Q51: ='Annual P&L'!Q7*Assumptions!F35*(1-Assumptions!F53-Assumptions!F54-Assumptions!F55-24%) -> 6676.7965
A52: Contract liabilities | B52: ₹ cr | C52: ='Raw Financials'!C99 -> 1807.6 | D52: ='Raw Financials'!D99 -> 0 | E52: ='Raw Financials'!E99 -> 0 | F52: ='Raw Financials'!F99 -> 0 | G52: ='Raw Financials'!G99 -> 0 | H52: ='Raw Financials'!H99 -> 0 | I52: ='Raw Financials'!I99 -> 0 | J52: ='Raw Financials'!J99 -> 0 | ... M52: ='Raw Financials'!M99 -> 2543.4 | N52: ='Annual P&L'!N7*Assumptions!C35*Assumptions!C53 -> 1717.6813 | O52: ='Annual P&L'!O7*Assumptions!D35*Assumptions!D53 -> 1784.5936 | P52: ='Annual P&L'!P7*Assumptions!E35*Assumptions!E53 -> 1885.1983 | Q52: ='Annual P&L'!Q7*Assumptions!F35*Assumptions!F53 -> 2003.039
A53: Current tax liabilities | B53: ₹ cr | C53: ='Raw Financials'!C100 -> 701.5 | D53: ='Raw Financials'!D100 -> 810.1 | E53: ='Raw Financials'!E100 -> 941.7 | F53: ='Raw Financials'!F100 -> 954.1 | G53: ='Raw Financials'!G100 -> 1173.1 | H53: ='Raw Financials'!H100 -> 1732.4 | I53: ='Raw Financials'!I100 -> 1323.1 | J53: ='Raw Financials'!J100 -> 1884.6 | ... M53: ='Raw Financials'!M100 -> 4962.1 | N53: ='Annual P&L'!N7*Assumptions!C35*Assumptions!C54 -> 3292.2226 | O53: ='Annual P&L'!O7*Assumptions!D35*Assumptions!D54 -> 3420.471 | P53: ='Annual P&L'!P7*Assumptions!E35*Assumptions!E54 -> 3613.2967 | Q53: ='Annual P&L'!Q7*Assumptions!F35*Assumptions!F54 -> 3839.158
A54: Other current liabilities | B54: ₹ cr | C54: ='Raw Financials'!C101 -> 1382.1 | D54: ='Raw Financials'!D101 -> 1302.7 | E54: ='Raw Financials'!E101 -> 1661.3 | F54: ='Raw Financials'!F101 -> 1869 | G54: ='Raw Financials'!G101 -> 0 | H54: ='Raw Financials'!H101 -> 0 | I54: ='Raw Financials'!I101 -> 0 | J54: ='Raw Financials'!J101 -> 0 | ... M54: ='Raw Financials'!M101 -> 3480.1 | N54: ='Annual P&L'!N7*Assumptions!C35*0.24 -> 3435.3627 | O54: ='Annual P&L'!O7*Assumptions!D35*0.24 -> 3569.1872 | P54: ='Annual P&L'!P7*Assumptions!E35*0.24 -> 3770.3966 | Q54: ='Annual P&L'!Q7*Assumptions!F35*0.24 -> 4006.0779
A55: Current provisions | B55: ₹ cr | C55: ='Raw Financials'!C102 -> 126.2 | D55: ='Raw Financials'!D102 -> 127 | E55: ='Raw Financials'!E102 -> 79.6 | F55: ='Raw Financials'!F102 -> 63.8 | G55: ='Raw Financials'!G102 -> 61.2 | H55: ='Raw Financials'!H102 -> 303.4 | I55: ='Raw Financials'!I102 -> 277.1 | J55: ='Raw Financials'!J102 -> 254.9 | ... M55: ='Raw Financials'!M102 -> 149.6 | N55: ='Annual P&L'!N7*Assumptions!C35*Assumptions!C55 -> 143.14011 | O55: ='Annual P&L'!O7*Assumptions!D35*Assumptions!D55 -> 148.71613 | P55: ='Annual P&L'!P7*Assumptions!E35*Assumptions!E55 -> 157.09986 | Q55: ='Annual P&L'!Q7*Assumptions!F35*Assumptions!F55 -> 166.91991
A56: Total current liabilities | B56: ₹ cr | C56: ='Raw Financials'!C103 -> 21856.1 | D56: ='Raw Financials'!D103 -> 22954.3 | E56: ='Raw Financials'!E103 -> 21350.7 | F56: ='Raw Financials'!F103 -> 21435 | G56: ='Raw Financials'!G103 -> 21639.3 | H56: ='Raw Financials'!H103 -> 23004 | I56: ='Raw Financials'!I103 -> 30832.9 | J56: ='Raw Financials'!J103 -> 26775.3 | ... M56: ='Raw Financials'!M103 -> 40323.2 | N56: =SUM(N47:N55) -> 45294.355 | O56: =SUM(O47:O55) -> 46601.729 | P56: =SUM(P47:P55) -> 48424.197 | Q56: =SUM(Q47:Q55) -> 50544.82
A57: Total liabilities | B57: ₹ cr | C57: ='Raw Financials'!C104 -> 25661.9 | D57: ='Raw Financials'!D104 -> 27082.1 | E57: ='Raw Financials'!E104 -> 27529.4 | F57: ='Raw Financials'!F104 -> 26241.8 | G57: ='Raw Financials'!G104 -> 25772.9 | H57: ='Raw Financials'!H104 -> 27684.1 | I57: ='Raw Financials'!I104 -> 42050.9 | J57: ='Raw Financials'!J104 -> 39406.9 | ... M57: ='Raw Financials'!M104 -> 53138.5 | N57: =SUM(N45,N56) -> 59885.799 | O57: =SUM(O45,O56) -> 61455.509 | P57: =SUM(P45,P56) -> 63684.264 | Q57: =SUM(Q45,Q56) -> 66280.544
A58: Total equity & liabilities | B58: ₹ cr | C58: =SUM(C36,C57) -> 72492.1 | D58: =SUM(D36,D57) -> 79351.6 | E58: =SUM(E36,E57) -> 76064 | F58: =SUM(F36,F57) -> 83317.1 | G58: =SUM(G36,G57) -> 81706.2 | H58: =SUM(H36,H57) -> 83143.4 | I58: =SUM(I36,I57) -> 107918.2 | J58: =SUM(J36,J57) -> 117582.2 | ... Q58: =SUM(Q36,Q57) -> 159392.43
A59: Balance sheet check | B59: ₹ cr | C59: =C29-C58 -> 0 | D59: =D29-D58 -> 0 | E59: =E29-E58 -> 0 | F59: =F29-F58 -> 0 | G59: =G29-G58 -> 0 | H59: =H29-H58 -> 0 | I59: =I29-I58 -> 0 | J59: =J29-J58 -> 0 | ... Q59: =Q29-Q58 -> 0
A60: Total borrowings | B60: ₹ cr | C60: =SUM(C38,C47) -> 12522.1 | D60: =SUM(D38,D47) -> 14241.2 | E60: =SUM(E38,E47) -> 13825.9 | F60: =SUM(F38,F47) -> 9946.7 | G60: =SUM(G38,G47) -> 7804.2 | H60: =SUM(H38,H47) -> 8333.2 | I60: =SUM(I38,I47) -> 15169.6 | J60: =SUM(J38,J47) -> 15009.3 | ... Q60: =SUM(Q38,Q47) -> 16787.4
A61: Total lease liabilities | B61: ₹ cr | C61: =SUM(C39,C48) -> 0 | D61: =SUM(D39,D48) -> 0 | E61: =SUM(E39,E48) -> 0 | F61: =SUM(F39,F48) -> 0 | G61: =SUM(G39,G48) -> 1919.8 | H61: =SUM(H39,H48) -> 2118.2 | I61: =SUM(I39,I48) -> 2423.3 | J61: =SUM(J39,J48) -> 2457.3 | ... Q61: =SUM(Q39,Q48) -> 4677.0081
A62: Net cash + investments / (debt + lease) | B62: ₹ cr | C62: =SUM(C21:C22,C11)-C60-C61 -> 11167.9 | D62: =SUM(D21:D22,D11)-D60-D61 -> 20232.8 | E62: =SUM(E21:E22,E11)-E60-E61 -> 15576 | F62: =SUM(F21:F22,F11)-F60-F61 -> 27977.8 | G62: =SUM(G21:G22,G11)-G60-G61 -> 23689.4 | H62: =SUM(H21:H22,H11)-H60-H61 -> 24098.6 | I62: =SUM(I21:I22,I11)-I60-I61 -> 16956.2 | J62: =SUM(J21:J22,J11)-J60-J61 -> 22644.6 | ... Q62: =SUM(Q21:Q22,Q11)-Q60-Q61 -> 46219.439

Sheet Annual Cash Flow
A1: Annual Cash Flow Statement
A2: Historical totals are reported controls; forecast cash is fully derived and closes the balance sheet
A5: Metric | B5: Units | C5: FY16A | D5: FY17A | E5: FY18A | F5: FY19A | G5: FY20A | H5: FY21A | I5: FY22A | J5: FY23A | K5: FY24A | L5: FY25A | M5: FY26A | N5: FY27E | O5: FY28E | P5: FY29E | Q5: FY30E
A7: Profit before tax | B7: ₹ cr | C7: ='Raw Financials'!C110 -> 11493.3 | D7: ='Raw Financials'!D110 -> 11035.6 | E7: ='Raw Financials'!E110 -> 10247.4 | F7: ='Raw Financials'!F110 -> 11541.5 | G7: ='Raw Financials'!G110 -> 12251.2 | H7: ='Raw Financials'!H110 -> 13900.7 | I7: ='Raw Financials'!I110 -> 15127.5 | J7: ='Raw Financials'!J110 -> 14765.7 | ... M7: ='Raw Financials'!M110 -> 17342.2 | N7: ='Annual P&L'!N23 -> 17657.344 | O7: ='Annual P&L'!O23 -> 18602.048 | P7: ='Annual P&L'!P23 -> 20588.27 | Q7: ='Annual P&L'!Q23 -> 22790.68
A8: D&A | B8: ₹ cr | C8: ='Raw Financials'!C111 -> 0 | D8: ='Raw Financials'!D111 -> 0 | E8: ='Raw Financials'!E111 -> 0 | F8: ='Raw Financials'!F111 -> 0 | G8: ='Raw Financials'!G111 -> 0 | H8: ='Raw Financials'!H111 -> 0 | I8: ='Raw Financials'!I111 -> 0 | J8: ='Raw Financials'!J111 -> 0 | ... M8: ='Raw Financials'!M111 -> 2910.7 | N8: ='Annual P&L'!N17 -> 2958.229 | O8: ='Annual P&L'!O17 -> 3035.0231 | P8: ='Annual P&L'!P17 -> 3163.8166 | Q8: ='Annual P&L'!Q17 -> 3314.7217
A9: Share-based compensation | B9: ₹ cr | C9: ='Raw Financials'!C112 -> 153.4 | D9: ='Raw Financials'!D112 -> 174.2 | E9: ='Raw Financials'!E112 -> 134.7 | F9: ='Raw Financials'!F112 -> 193.8 | G9: ='Raw Financials'!G112 -> 126.2 | H9: ='Raw Financials'!H112 -> 231 | I9: ='Raw Financials'!I112 -> 411 | J9: ='Raw Financials'!J112 -> 396.9 | ... M9: ='Raw Financials'!M112 -> 446.5 | N9: ='Annual P&L'!N7*Assumptions!C48 -> 477.13371 | O9: ='Annual P&L'!O7*Assumptions!D48 -> 505.83718 | P9: ='Annual P&L'!P7*Assumptions!E48 -> 545.48562 | Q9: ='Annual P&L'!Q7*Assumptions!F48 -> 591.91459
A10: Gain / (loss) on PPE disposal | B10: ₹ cr | C10: ='Raw Financials'!C113 -> 0 | D10: ='Raw Financials'!D113 -> 0 | E10: ='Raw Financials'!E113 -> 0 | F10: ='Raw Financials'!F113 -> 0 | G10: ='Raw Financials'!G113 -> 0 | H10: ='Raw Financials'!H113 -> 0 | I10: ='Raw Financials'!I113 -> 0 | J10: ='Raw Financials'!J113 -> 0 | ... M10: ='Raw Financials'!M113 -> -39.3 | N10: =0 -> 0 | O10: =0 -> 0 | P10: =0 -> 0 | Q10: =0 -> 0
A11: Finance cost add-back | B11: ₹ cr | C11: ='Raw Financials'!C114 -> 0 | D11: ='Raw Financials'!D114 -> 0 | E11: ='Raw Financials'!E114 -> 0 | F11: ='Raw Financials'!F114 -> 0 | G11: ='Raw Financials'!G114 -> 0 | H11: ='Raw Financials'!H114 -> 0 | I11: ='Raw Financials'!I114 -> 0 | J11: ='Raw Financials'!J114 -> 0 | ... M11: ='Raw Financials'!M114 -> -2191.4 | N11: ='Annual P&L'!N20 -> 1420.37 | O11: ='Annual P&L'!O20 -> 1439.2155 | P11: ='Annual P&L'!P20 -> 1458.1717 | Q11: ='Annual P&L'!Q20 -> 1479.0499
A12: Finance income deduction | B12: ₹ cr | C12: =0 -> 0 | D12: =0 -> 0 | E12: =0 -> 0 | F12: =0 -> 0 | G12: =0 -> 0 | H12: =0 -> 0 | I12: =0 -> 0 | J12: =0 -> 0 | ... M12: =0 -> 0 | N12: =-'Annual P&L'!N21 -> -3427.728 | O12: =-'Annual P&L'!O21 -> -2943.9668 | P12: =-'Annual P&L'!P21 -> -3063.5425 | Q12: =-'Annual P&L'!Q21 -> -3197.571
A13: Associate / JV adjustment | B13: ₹ cr | C13: =0 -> 0 | D13: =0 -> 0 | E13: =0 -> 0 | F13: =0 -> 0 | G13: =0 -> 0 | H13: =0 -> 0 | I13: =0 -> 0 | J13: =0 -> 0 | ... M13: =0 -> 0 | N13: =-'Annual P&L'!N22 -> 0 | O13: =-'Annual P&L'!O22 -> 0 | P13: =-'Annual P&L'!P22 -> 0 | Q13: =-'Annual P&L'!Q22 -> 0
A14: Other non-cash / CFO residual | B14: ₹ cr | C14: =C29-SUM(C7:C13,C15:C26,C28) -> -478.9 | D14: =D29-SUM(D7:D13,D15:D26,D28) -> 86.3 | E14: =E29-SUM(E7:E13,E15:E26,E28) -> 578 | F14: =F29-SUM(F7:F13,F15:F26,F28) -> 2467.8 | G14: =G29-SUM(G7:G13,G15:G26,G28) -> -1883.2 | H14: =H29-SUM(H7:H13,H15:H26,H28) -> 3034.5 | I14: =I29-SUM(I7:I13,I15:I26,I28) -> -1864.6 | J14: =J29-SUM(J7:J13,J15:J26,J28) -> 903.1 | ... M14: =M29-SUM(M7:M13,M15:M26,M28) -> 835.3 | N14: =0 -> 0 | O14: =0 -> 0 | P14: =0 -> 0 | Q14: =0 -> 0
A15: Change in billed receivables | B15: ₹ cr | C15: ='Raw Financials'!C116 -> 0 | D15: ='Raw Financials'!D116 -> 0 | E15: ='Raw Financials'!E116 -> 0 | F15: ='Raw Financials'!F116 -> 0 | G15: ='Raw Financials'!G116 -> 0 | H15: ='Raw Financials'!H116 -> 0 | I15: ='Raw Financials'!I116 -> 0 | J15: ='Raw Financials'!J116 -> 0 | ... M15: ='Raw Financials'!M116 -> -1144.2 | N15: =-('Annual Balance Sheet'!N23-'Annual Balance Sheet'!M23) -> -789.27196 | O15: =-('Annual Balance Sheet'!O23-'Annual Balance Sheet'!N23) -> -587.86519 | P15: =-('Annual Balance Sheet'!P23-'Annual Balance Sheet'!O23) -> -874.26302 | Q15: =-('Annual Balance Sheet'!Q23-'Annual Balance Sheet'!P23) -> -1024.0113
A16: Change in unbilled / contract assets | B16: ₹ cr | C16: ='Raw Financials'!C117 -> -532.9 | D16: ='Raw Financials'!D117 -> 381.3 | E16: ='Raw Financials'!E117 -> 219.2 | F16: ='Raw Financials'!F117 -> 0 | G16: ='Raw Financials'!G117 -> 0 | H16: ='Raw Financials'!H117 -> 0 | I16: ='Raw Financials'!I117 -> 0 | J16: ='Raw Financials'!J117 -> 0 | ... M16: ='Raw Financials'!M117 -> -1449.8 | N16: =-('Annual Balance Sheet'!N24-'Annual Balance Sheet'!M24) -> -247.75256 | O16: =-('Annual Balance Sheet'!O24-'Annual Balance Sheet'!N24) -> -289.03449 | P16: =-('Annual Balance Sheet'!P24-'Annual Balance Sheet'!O24) -> -461.48477 | Q16: =-('Annual Balance Sheet'!Q24-'Annual Balance Sheet'!P24) -> -540.64124
A17: Change in inventories | B17: ₹ cr | C17: ='Raw Financials'!C118 -> -54.1 | D17: ='Raw Financials'!D118 -> 147.5 | E17: ='Raw Financials'!E118 -> 54.5 | F17: ='Raw Financials'!F118 -> -56.6 | G17: ='Raw Financials'!G118 -> 208.5 | H17: ='Raw Financials'!H118 -> 80.3 | I17: ='Raw Financials'!I118 -> -25.6 | J17: ='Raw Financials'!J118 -> 16.2 | ... M17: ='Raw Financials'!M118 -> 18.4 | N17: =-('Annual Balance Sheet'!N19-'Annual Balance Sheet'!M19) -> -5.5560447 | O17: =-('Annual Balance Sheet'!O19-'Annual Balance Sheet'!N19) -> -3.4444171 | P17: =-('Annual Balance Sheet'!P19-'Annual Balance Sheet'!O19) -> -4.7578125 | Q17: =-('Annual Balance Sheet'!Q19-'Annual Balance Sheet'!P19) -> -5.5714759
A18: Change in other current financial assets | B18: ₹ cr | C18: =0 -> 0 | D18: =0 -> 0 | E18: =0 -> 0 | F18: =0 -> 0 | G18: =0 -> 0 | H18: =0 -> 0 | I18: =0 -> 0 | J18: =0 -> 0 | ... M18: =0 -> 0 | N18: =-('Annual Balance Sheet'!N25-'Annual Balance Sheet'!M25) -> -25.194153 | O18: =-('Annual Balance Sheet'!O25-'Annual Balance Sheet'!N25) -> -63.147646 | P18: =-('Annual Balance Sheet'!P25-'Annual Balance Sheet'!O25) -> 21.870561 | Q18: =-('Annual Balance Sheet'!Q25-'Annual Balance Sheet'!P25) -> -92.857932
A19: Change in other current assets | B19: ₹ cr | C19: ='Raw Financials'!C119 -> 0 | D19: ='Raw Financials'!D119 -> 0 | E19: ='Raw Financials'!E119 -> 0 | F19: ='Raw Financials'!F119 -> 0 | G19: ='Raw Financials'!G119 -> 0 | H19: ='Raw Financials'!H119 -> 0 | I19: ='Raw Financials'!I119 -> 0 | J19: ='Raw Financials'!J119 -> 0 | ... M19: ='Raw Financials'!M119 -> -20.5 | N19: =-('Annual Balance Sheet'!N27-'Annual Balance Sheet'!M27) -> -118.96268 | O19: =-('Annual Balance Sheet'!O27-'Annual Balance Sheet'!N27) -> -105.49759 | P19: =-('Annual Balance Sheet'!P27-'Annual Balance Sheet'!O27) -> -168.44194 | Q19: =-('Annual Balance Sheet'!Q27-'Annual Balance Sheet'!P27) -> -197.33405
A20: Change in other non-current operating assets | B20: ₹ cr | C20: =0 -> 0 | D20: =0 -> 0 | E20: =0 -> 0 | F20: =0 -> 0 | G20: =0 -> 0 | H20: =0 -> 0 | I20: =0 -> 0 | J20: =0 -> 0 | ... M20: =0 -> 0 | N20: =-SUM('Annual Balance Sheet'!N13-'Annual Balance Sheet'!M13,'Annual Balance Sheet'!N14-'Annual Balance Sheet'!M14,'Annual Balance Sheet'!N17-'Annual Balance Sheet'!M17) -> -858.76853 | O20: =-SUM('Annual Balance Sheet'!O13-'Annual Balance Sheet'!N13,'Annual Balance Sheet'!O14-'Annual Balance Sheet'!N14,'Annual Balance Sheet'!O17-'Annual Balance Sheet'!N17) -> -42.349942 | P20: =-SUM('Annual Balance Sheet'!P13-'Annual Balance Sheet'!O13,'Annual Balance Sheet'!P14-'Annual Balance Sheet'!O14,'Annual Balance Sheet'!P17-'Annual Balance Sheet'!O17) -> -81.215377 | Q20: =-SUM('Annual Balance Sheet'!Q13-'Annual Balance Sheet'!P13,'Annual Balance Sheet'!Q14-'Annual Balance Sheet'!P14,'Annual Balance Sheet'!Q17-'Annual Balance Sheet'!P17) -> -95.190327
A21: Change in trade payables | B21: ₹ cr | C21: ='Raw Financials'!C120 -> 0 | D21: ='Raw Financials'!D120 -> 0 | E21: ='Raw Financials'!E120 -> 0 | F21: ='Raw Financials'!F120 -> 0 | G21: ='Raw Financials'!G120 -> 0 | H21: ='Raw Financials'!H120 -> 0 | I21: ='Raw Financials'!I120 -> 0 | J21: ='Raw Financials'!J120 -> 0 | ... M21: ='Raw Financials'!M120 -> 848.2 | N21: ='Annual Balance Sheet'!N50-'Annual Balance Sheet'!M50 -> 241.1276 | O21: ='Annual Balance Sheet'!O50-'Annual Balance Sheet'!N50 -> 484.38347 | P21: ='Annual Balance Sheet'!P50-'Annual Balance Sheet'!O50 -> 691.80132 | Q21: ='Annual Balance Sheet'!Q50-'Annual Balance Sheet'!P50 -> 810.19641
A22: Change in other current financial liabilities | B22: ₹ cr | C22: =0 -> 0 | D22: =0 -> 0 | E22: =0 -> 0 | F22: =0 -> 0 | G22: =0 -> 0 | H22: =0 -> 0 | I22: =0 -> 0 | J22: =0 -> 0 | ... M22: =0 -> 0 | N22: ='Annual Balance Sheet'!N51-'Annual Balance Sheet'!M51 -> 4589.9045 | O22: ='Annual Balance Sheet'!O51-'Annual Balance Sheet'!N51 -> 223.04078 | P22: ='Annual Balance Sheet'!P51-'Annual Balance Sheet'!O51 -> 335.34908 | Q22: ='Annual Balance Sheet'!Q51-'Annual Balance Sheet'!P51 -> 392.80219
A23: Change in contract liabilities | B23: ₹ cr | C23: =0 -> 0 | D23: =0 -> 0 | E23: =0 -> 0 | F23: =0 -> 0 | G23: =0 -> 0 | H23: =0 -> 0 | I23: =0 -> 0 | J23: =0 -> 0 | ... M23: =0 -> 0 | N23: ='Annual Balance Sheet'!N52-'Annual Balance Sheet'!M52 -> -825.71866 | O23: ='Annual Balance Sheet'!O52-'Annual Balance Sheet'!N52 -> 66.912235 | P23: ='Annual Balance Sheet'!P52-'Annual Balance Sheet'!O52 -> 100.60472 | Q23: ='Annual Balance Sheet'!Q52-'Annual Balance Sheet'!P52 -> 117.84066
A24: Change in tax assets / liabilities | B24: ₹ cr | C24: =0 -> 0 | D24: =0 -> 0 | E24: =0 -> 0 | F24: =0 -> 0 | G24: =0 -> 0 | H24: =0 -> 0 | I24: =0 -> 0 | J24: =0 -> 0 | ... M24: =0 -> 0 | N24: =('Annual Balance Sheet'!N53-'Annual Balance Sheet'!M53)-('Annual Balance Sheet'!N26-'Annual Balance Sheet'!M26) -> -1669.8774 | O24: =('Annual Balance Sheet'!O53-'Annual Balance Sheet'!N53)-('Annual Balance Sheet'!O26-'Annual Balance Sheet'!N26) -> 128.24845 | P24: =('Annual Balance Sheet'!P53-'Annual Balance Sheet'!O53)-('Annual Balance Sheet'!P26-'Annual Balance Sheet'!O26) -> 192.82572 | Q24: =('Annual Balance Sheet'!Q53-'Annual Balance Sheet'!P53)-('Annual Balance Sheet'!Q26-'Annual Balance Sheet'!P26) -> 225.86126
A25: Change in other current liabilities | B25: ₹ cr | C25: =0 -> 0 | D25: =0 -> 0 | E25: =0 -> 0 | F25: =0 -> 0 | G25: =0 -> 0 | H25: =0 -> 0 | I25: =0 -> 0 | J25: =0 -> 0 | ... M25: =0 -> 0 | N25: ='Annual Balance Sheet'!N54-'Annual Balance Sheet'!M54 -> -44.737317 | O25: ='Annual Balance Sheet'!O54-'Annual Balance Sheet'!N54 -> 133.82447 | P25: ='Annual Balance Sheet'!P54-'Annual Balance Sheet'!O54 -> 201.20945 | Q25: ='Annual Balance Sheet'!Q54-'Annual Balance Sheet'!P54 -> 235.68131
A26: Change in provisions / other NC liabilities | B26: ₹ cr | C26: =0 -> 0 | D26: =0 -> 0 | E26: =0 -> 0 | F26: =0 -> 0 | G26: =0 -> 0 | H26: =0 -> 0 | I26: =0 -> 0 | J26: =0 -> 0 | ... M26: =0 -> 0 | N26: =SUM('Annual Balance Sheet'!N40-'Annual Balance Sheet'!M40,'Annual Balance Sheet'!N43-'Annual Balance Sheet'!M43,'Annual Balance Sheet'!N44-'Annual Balance Sheet'!M44,'Annual Balance Sheet'!N55-'Annual Balance Sheet'!M55) -> 4187.3794 | O26: =SUM('Annual Balance Sheet'!O40-'Annual Balance Sheet'!N40,'Annual Balance Sheet'!O43-'Annual Balance Sheet'!N43,'Annual Balance Sheet'!O44-'Annual Balance Sheet'!N44,'Annual Balance Sheet'!O55-'Annual Balance Sheet'!N55) -> 262.49676 | P26: =SUM('Annual Balance Sheet'!P40-'Annual Balance Sheet'!O40,'Annual Balance Sheet'!P43-'Annual Balance Sheet'!O43,'Annual Balance Sheet'!P44-'Annual Balance Sheet'!O44,'Annual Balance Sheet'!P55-'Annual Balance Sheet'!O55) -> 408.70511 | Q26: =SUM('Annual Balance Sheet'!Q40-'Annual Balance Sheet'!P40,'Annual Balance Sheet'!Q43-'Annual Balance Sheet'!P43,'Annual Balance Sheet'!Q44-'Annual Balance Sheet'!P44,'Annual Balance Sheet'!Q55-'Annual Balance Sheet'!P55) -> 478.77451
A27: Cash generated pre-tax | B27: ₹ cr | C27: =C29-C28 -> 10580.8 | D27: =D29-D28 -> 11824.9 | E27: =E29-E28 -> 11233.8 | F27: =F29-F28 -> 14146.5 | G27: =G29-G28 -> 10702.7 | H27: =H29-H28 -> 17246.5 | I27: =I29-I28 -> 13648.3 | J27: =J29-J28 -> 16081.9 | ... M27: =M29-M28 -> 17556.1 | N27: =SUM(N7:N26) -> 23517.92 | O27: =SUM(O7:O26) -> 20845.724 | P27: =SUM(P7:P26) -> 23054.405 | Q27: =SUM(Q7:Q26) -> 25284.346
A28: Taxes paid | B28: ₹ cr | C28: ='Raw Financials'!C122 -> -2693.5 | D28: ='Raw Financials'!D122 -> -2547.6 | E28: ='Raw Financials'!E122 -> -2810.5 | F28: ='Raw Financials'!F122 -> -2514.9 | G28: ='Raw Financials'!G122 -> -638.4 | H28: ='Raw Financials'!H122 -> -2491.5 | I28: ='Raw Financials'!I122 -> -2568.6 | J28: ='Raw Financials'!J122 -> -3021.8 | ... M28: ='Raw Financials'!M122 -> -2624.5 | N28: =-'Annual P&L'!N25 -> -4237.7625 | O28: =-'Annual P&L'!O25 -> -4464.4915 | P28: =-'Annual P&L'!P25 -> -4941.1849 | Q28: =-'Annual P&L'!Q25 -> -5469.7633
A29: Cash flow from operations | B29: ₹ cr | C29: ='Raw Financials'!C123 -> 7887.3 | D29: ='Raw Financials'!D123 -> 9277.3 | E29: ='Raw Financials'!E123 -> 8423.3 | F29: ='Raw Financials'!F123 -> 11631.6 | G29: ='Raw Financials'!G123 -> 10064.3 | H29: ='Raw Financials'!H123 -> 14755 | I29: ='Raw Financials'!I123 -> 11079.7 | J29: ='Raw Financials'!J123 -> 13060.1 | ... M29: ='Raw Financials'!M123 -> 14931.6 | N29: =SUM(N27:N28) -> 19280.158 | O29: =SUM(O27:O28) -> 16381.232 | P29: =SUM(P27:P28) -> 18113.22 | Q29: =SUM(Q27:Q28) -> 19814.582
A30: CFO / net income | B30: x | C30: =IFERROR(C29/'Annual P&L'!C29,"") -> 0.8854673 | D30: =IFERROR(D29/'Annual P&L'!D29,"") -> 1.092797 | E30: =IFERROR(E29/'Annual P&L'!E29,"") -> 1.0518475 | F30: =IFERROR(F29/'Annual P&L'!F29,"") -> 1.291955 | G30: =IFERROR(G29/'Annual P&L'!G29,"") -> 1.0352301 | H30: =IFERROR(H29/'Annual P&L'!H29,"") -> 1.3668871 | I30: =IFERROR(I29/'Annual P&L'!I29,"") -> 0.90675254 | J30: =IFERROR(J29/'Annual P&L'!J29,"") -> 1.1506696 | ... Q30: =IFERROR(Q29/'Annual P&L'!Q29,"") -> 1.1439684
A31: Capex | B31: ₹ cr | C31: ='Raw Financials'!C124 -> -1395.1 | D31: ='Raw Financials'!D124 -> -2085.3 | E31: ='Raw Financials'!E124 -> -2187 | F31: ='Raw Financials'!F124 -> -2278.1 | G31: ='Raw Financials'!G124 -> -2349.7 | H31: ='Raw Financials'!H124 -> -1957.7 | I31: ='Raw Financials'!I124 -> -2015.3 | J31: ='Raw Financials'!J124 -> -1483.4 | ... M31: ='Raw Financials'!M124 -> -1560.3 | N31: =-'BS Forecast Schedules'!D10 -> -1717.6813 | O31: =-'BS Forecast Schedules'!E10 -> -1821.0139 | P31: =-'BS Forecast Schedules'!F10 -> -1963.7482 | Q31: =-'BS Forecast Schedules'!G10 -> -2130.8925
A32: PPE sale proceeds | B32: ₹ cr | C32: ='Raw Financials'!C125 -> 77.9 | D32: ='Raw Financials'!D125 -> 120.7 | E32: ='Raw Financials'!E125 -> 117.1 | F32: ='Raw Financials'!F125 -> 194 | G32: ='Raw Financials'!G125 -> 127 | H32: ='Raw Financials'!H125 -> 75.3 | I32: ='Raw Financials'!I125 -> 73.6 | J32: ='Raw Financials'!J125 -> 54.6 | ... M32: ='Raw Financials'!M125 -> 75.8 | N32: =0 -> 0 | O32: =0 -> 0 | P32: =0 -> 0 | Q32: =0 -> 0
A33: Acquisitions | B33: ₹ cr | C33: ='Raw Financials'!C128 -> -3937.3 | D33: ='Raw Financials'!D128 -> -3360.8 | E33: ='Raw Financials'!E128 -> -665.2 | F33: ='Raw Financials'!F128 -> 0 | G33: ='Raw Financials'!G128 -> -1000.3 | H33: ='Raw Financials'!H128 -> -987.3 | I33: ='Raw Financials'!I128 -> -12984.6 | J33: ='Raw Financials'!J128 -> -4556.6 | ... M33: ='Raw Financials'!M128 -> -2603.3 | N33: =0 -> 0 | O33: =0 -> 0 | P33: =0 -> 0 | Q33: =0 -> 0
A34: Purchase of investments | B34: ₹ cr | C34: ='Raw Financials'!C126 -> 0 | D34: ='Raw Financials'!D126 -> 0 | E34: ='Raw Financials'!E126 -> 0 | F34: ='Raw Financials'!F126 -> 0 | G34: ='Raw Financials'!G126 -> 0 | H34: ='Raw Financials'!H126 -> 0 | I34: ='Raw Financials'!I126 -> 0 | J34: ='Raw Financials'!J126 -> 0 | ... M34: ='Raw Financials'!M126 -> -83780.6 | N34: =MIN(0,-('Annual Balance Sheet'!N21-'Annual Balance Sheet'!M21)) -> 0 | O34: =MIN(0,-('Annual Balance Sheet'!O21-'Annual Balance Sheet'!N21)) -> -502.55713 | P34: =MIN(0,-('Annual Balance Sheet'!P21-'Annual Balance Sheet'!O21)) -> -1148.5263 | Q34: =MIN(0,-('Annual Balance Sheet'!Q21-'Annual Balance Sheet'!P21)) -> -1346.659
A35: Sale / maturity of investments | B35: ₹ cr | C35: ='Raw Financials'!C127 -> 0 | D35: ='Raw Financials'!D127 -> 0 | E35: ='Raw Financials'!E127 -> 0 | F35: ='Raw Financials'!F127 -> 0 | G35: ='Raw Financials'!G127 -> 0 | H35: ='Raw Financials'!H127 -> 0 | I35: ='Raw Financials'!I127 -> 0 | J35: ='Raw Financials'!J127 -> 0 | ... M35: ='Raw Financials'!M127 -> 81673.2 | N35: =MAX(0,-('Annual Balance Sheet'!N21-'Annual Balance Sheet'!M21)) -> 1780.2339 | O35: =MAX(0,-('Annual Balance Sheet'!O21-'Annual Balance Sheet'!N21)) -> 0 | P35: =MAX(0,-('Annual Balance Sheet'!P21-'Annual Balance Sheet'!O21)) -> 0 | Q35: =MAX(0,-('Annual Balance Sheet'!Q21-'Annual Balance Sheet'!P21)) -> 0
A36: Interest received | B36: ₹ cr | C36: ='Raw Financials'!C129 -> 1836.8 | D36: ='Raw Financials'!D129 -> 1706.9 | E36: ='Raw Financials'!E129 -> 1434.7 | F36: ='Raw Financials'!F129 -> 2016.3 | G36: ='Raw Financials'!G129 -> 2383.7 | H36: ='Raw Financials'!H129 -> 1962.4 | I36: ='Raw Financials'!I129 -> 1227.5 | J36: ='Raw Financials'!J129 -> 1411.2 | ... M36: ='Raw Financials'!M129 -> 2887.8 | N36: ='Annual P&L'!N21 -> 3427.728 | O36: ='Annual P&L'!O21 -> 2943.9668 | P36: ='Annual P&L'!P21 -> 3063.5425 | Q36: ='Annual P&L'!Q21 -> 3197.571
A37: Dividends received | B37: ₹ cr | C37: ='Raw Financials'!C130 -> 6.6 | D37: ='Raw Financials'!D130 -> 31.1 | E37: ='Raw Financials'!E130 -> 60.9 | F37: ='Raw Financials'!F130 -> 36.1 | G37: ='Raw Financials'!G130 -> 36.7 | H37: ='Raw Financials'!H130 -> 0.4 | I37: ='Raw Financials'!I130 -> 0.2 | J37: ='Raw Financials'!J130 -> 0.3 | ... M37: ='Raw Financials'!M130 -> 0.3 | N37: =0 -> 0 | O37: =0 -> 0 | P37: =0 -> 0 | Q37: =0 -> 0
A38: Other investing / residual | B38: ₹ cr | C38: =C39-SUM(C31:C37) -> -10404.5 | D38: =D39-SUM(D31:D37) -> -8040.9 | E38: =E39-SUM(E31:E37) -> 4797.3 | F38: =F39-SUM(F31:F37) -> 5044.3 | G38: =G39-SUM(G31:G37) -> 4203.8 | H38: =H39-SUM(H31:H37) -> 1680.8 | I38: =I39-SUM(I31:I37) -> -8750.9 | J38: =J39-SUM(J31:J37) -> -3832.6 | ... M38: =M39-SUM(M31:M37) -> -35.2 | N38: =0 -> 0 | O38: =0 -> 0 | P38: =0 -> 0 | Q38: =0 -> 0
A39: Cash flow from investing | B39: ₹ cr | C39: ='Raw Financials'!C131 -> -13815.6 | D39: ='Raw Financials'!D131 -> -11628.3 | E39: ='Raw Financials'!E131 -> 3557.8 | F39: ='Raw Financials'!F131 -> 5012.6 | G39: ='Raw Financials'!G131 -> 3401.2 | H39: ='Raw Financials'!H131 -> 773.9 | I39: ='Raw Financials'!I131 -> -22449.5 | J39: ='Raw Financials'!J131 -> -8406.5 | ... M39: ='Raw Financials'!M131 -> -3342.3 | N39: =SUM(N31:N38) -> 3490.2805 | O39: =SUM(O31:O38) -> 620.39584 | P39: =SUM(P31:P38) -> -48.732016 | Q39: =SUM(Q31:Q38) -> -279.98051
A40: Equity issuance | B40: ₹ cr | C40: ='Raw Financials'!C132 -> 0.4 | D40: ='Raw Financials'!D132 -> 0 | E40: ='Raw Financials'!E132 -> 2.4 | F40: ='Raw Financials'!F132 -> 0.4 | G40: ='Raw Financials'!G132 -> 1.4 | H40: ='Raw Financials'!H132 -> 0.6 | I40: ='Raw Financials'!I132 -> 0.6 | J40: ='Raw Financials'!J132 -> 1.2 | ... M40: ='Raw Financials'!M132 -> 3.3 | N40: =0 -> 0 | O40: =0 -> 0 | P40: =0 -> 0 | Q40: =0 -> 0
A41: Borrowing proceeds | B41: ₹ cr | C41: ='Raw Financials'!C133 -> 17254.9 | D41: ='Raw Financials'!D133 -> 12592.2 | E41: ='Raw Financials'!E133 -> 14427.1 | F41: ='Raw Financials'!F133 -> 6516.1 | G41: ='Raw Financials'!G133 -> 10634.2 | H41: ='Raw Financials'!H133 -> 10341.8 | I41: ='Raw Financials'!I133 -> 26012 | J41: ='Raw Financials'!J133 -> 16103.4 | ... M41: ='Raw Financials'!M133 -> 25308.9 | N41: =MAX(0,'BS Forecast Schedules'!D34) -> 0 | O41: =MAX(0,'BS Forecast Schedules'!E34) -> 0 | P41: =MAX(0,'BS Forecast Schedules'!F34) -> 0 | Q41: =MAX(0,'BS Forecast Schedules'!G34) -> 0
A42: Borrowing repayments | B42: ₹ cr | C42: ='Raw Financials'!C134 -> -13729.8 | D42: ='Raw Financials'!D134 -> -11280.3 | E42: ='Raw Financials'!E134 -> -15525.4 | F42: ='Raw Financials'!F134 -> -10403.9 | G42: ='Raw Financials'!G134 -> -13238 | H42: ='Raw Financials'!H134 -> -9720.6 | I42: ='Raw Financials'!I134 -> -19181 | J42: ='Raw Financials'!J134 -> -16891 | ... M42: ='Raw Financials'!M134 -> -25984.1 | N42: =MIN(0,'BS Forecast Schedules'!D34) -> 0 | O42: =MIN(0,'BS Forecast Schedules'!E34) -> 0 | P42: =MIN(0,'BS Forecast Schedules'!F34) -> 0 | Q42: =MIN(0,'BS Forecast Schedules'!G34) -> 0
A43: Net borrowing change / reclassification | B43: ₹ cr | C43: =0 -> 0 | D43: =0 -> 0 | E43: =0 -> 0 | F43: =0 -> 0 | G43: =0 -> 0 | H43: =0 -> 0 | I43: =0 -> 0 | J43: =0 -> 0 | ... Q43: =0 -> 0
A44: Lease principal paid | B44: ₹ cr | C44: ='Raw Financials'!C135 -> 0 | D44: ='Raw Financials'!D135 -> 0 | E44: ='Raw Financials'!E135 -> 0 | F44: ='Raw Financials'!F135 -> 0 | G44: ='Raw Financials'!G135 -> -678.4 | H44: ='Raw Financials'!H135 -> -866 | I44: ='Raw Financials'!I135 -> -973 | J44: ='Raw Financials'!J135 -> -971.1 | ... M44: ='Raw Financials'!M135 -> -1156.1 | N44: ='BS Forecast Schedules'!D28 -> -875.9 | O44: ='BS Forecast Schedules'!E28 -> -943.20522 | P44: ='BS Forecast Schedules'!F28 -> -1010.9062 | Q44: ='BS Forecast Schedules'!G28 -> -1085.471
A45: Finance costs paid | B45: ₹ cr | C45: ='Raw Financials'!C136 -> -134.8 | D45: ='Raw Financials'!D136 -> -199.9 | E45: ='Raw Financials'!E136 -> -312.3 | F45: ='Raw Financials'!F136 -> -479.6 | G45: ='Raw Financials'!G136 -> -460.1 | H45: ='Raw Financials'!H136 -> -333.5 | I45: ='Raw Financials'!I136 -> -508.9 | J45: ='Raw Financials'!J136 -> -870.8 | ... M45: ='Raw Financials'!M136 -> -633.6 | N45: =-'Annual P&L'!N20 -> -1420.37 | O45: =-'Annual P&L'!O20 -> -1439.2155 | P45: =-'Annual P&L'!P20 -> -1458.1717 | Q45: =-'Annual P&L'!Q20 -> -1479.0499
A46: Dividends paid | B46: ₹ cr | C46: ='Raw Financials'!C137 -> -3549.4 | D46: ='Raw Financials'!D137 -> -873.4 | E46: ='Raw Financials'!E137 -> -542 | F46: ='Raw Financials'!F137 -> -450.4 | G46: ='Raw Financials'!G137 -> -568.9 | H46: ='Raw Financials'!H137 -> -545.9 | I46: ='Raw Financials'!I137 -> -546.7 | J46: ='Raw Financials'!J137 -> -3281.4 | ... M46: ='Raw Financials'!M137 -> -11520.6 | N46: =-'Annual P&L'!N29*Assumptions!C46 -> -10064.686 | O46: =-'Annual P&L'!O29*Assumptions!D46 -> -10179.041 | P46: =-'Annual P&L'!P29*Assumptions!E46 -> -10952.96 | Q46: =-'Annual P&L'!Q29*Assumptions!F46 -> -12124.642
A47: Buyback | B47: ₹ cr | C47: ='Raw Financials'!C138 -> 0 | D47: ='Raw Financials'!D138 -> 0 | E47: ='Raw Financials'!E138 -> 0 | F47: ='Raw Financials'!F138 -> 0 | G47: ='Raw Financials'!G138 -> 0 | H47: ='Raw Financials'!H138 -> 0 | I47: ='Raw Financials'!I138 -> 0 | J47: ='Raw Financials'!J138 -> 0 | ... M47: ='Raw Financials'!M138 -> 0 | N47: =-Assumptions!C47 -> -15000 | O47: =-Assumptions!D47 -> 0 | P47: =-Assumptions!E47 -> 0 | Q47: =-Assumptions!F47 -> 0
A48: NCI / other financing | B48: ₹ cr | C48: =0 -> 0 | D48: =0 -> 0 | E48: =0 -> 0 | F48: =0 -> 0 | G48: =0 -> 0 | H48: =0 -> 0 | I48: =0 -> 0 | J48: =0 -> 0 | ... Q48: =0 -> 0
A49: Other financing / residual | B49: ₹ cr | C49: =C50-SUM(C40:C48) -> -3.3537617e-12 | D49: =D50-SUM(D40:D48) -> -2513.8 | E49: =E50-SUM(E40:E48) -> -11047.6 | F49: =F50-SUM(F40:F48) -> -119.5 | G49: =G50-SUM(G40:G48) -> -10790 | H49: =H50-SUM(H40:H48) -> -11760.4 | I49: =I50-SUM(I40:I48) -> -144.4 | J49: =J50-SUM(J40:J48) -> -178.4 | ... M49: =M50-SUM(M40:M48) -> -143.8 | N49: =0 -> 0 | O49: =0 -> 0 | P49: =0 -> 0 | Q49: =0 -> 0
A50: Cash flow from financing | B50: ₹ cr | C50: ='Raw Financials'!C139 -> -158.7 | D50: ='Raw Financials'!D139 -> -2275.2 | E50: ='Raw Financials'!E139 -> -12997.8 | F50: ='Raw Financials'!F139 -> -4936.9 | G50: ='Raw Financials'!G139 -> -15099.8 | H50: ='Raw Financials'!H139 -> -12884 | I50: ='Raw Financials'!I139 -> 4658.6 | J50: ='Raw Financials'!J139 -> -6088.1 | ... M50: ='Raw Financials'!M139 -> -14126 | N50: =SUM(N40:N49) -> -27360.956 | O50: =SUM(O40:O49) -> -12561.461 | P50: =SUM(P40:P49) -> -13422.038 | Q50: =SUM(Q40:Q49) -> -14689.163
A51: Net cash flow before FX | B51: ₹ cr | C51: =SUM(C29,C39,C50) -> -6087 | D51: =SUM(D29,D39,D50) -> -4626.2 | E51: =SUM(E29,E39,E50) -> -1016.7 | F51: =SUM(F29,F39,F50) -> 11707.3 | G51: =SUM(G29,G39,G50) -> -1634.3 | H51: =SUM(H29,H39,H50) -> 2644.9 | I51: =SUM(I29,I39,I50) -> -6711.2 | J51: =SUM(J29,J39,J50) -> -1434.5 | ... Q51: =SUM(Q29,Q39,Q50) -> 4845.4389
A52: FX effect | B52: ₹ cr | C52: ='Raw Financials'!C140 -> 54.9 | D52: ='Raw Financials'!D140 -> -141.2 | E52: ='Raw Financials'!E140 -> 37.5 | F52: ='Raw Financials'!F140 -> 52.6 | G52: ='Raw Financials'!G140 -> 192.2 | H52: ='Raw Financials'!H140 -> -89 | I52: ='Raw Financials'!I140 -> 128.2 | J52: ='Raw Financials'!J140 -> 237.3 | ... M52: ='Raw Financials'!M140 -> 894.8 | N52: =Assumptions!C57 -> 0 | O52: =Assumptions!D57 -> 0 | P52: =Assumptions!E57 -> 0 | Q52: =Assumptions!F57 -> 0
A53: Accounting-basis / cash reconciliation | B53: ₹ cr | C53: =C56-C55-C51-C52 -> 15937 | D53: =D56-D55-D51-D52 -> 133.5 | E53: =E56-E55-E51-E52 -> 200.7 | F53: =F56-F55-F51-F52 -> -399.5 | G53: =G56-G55-G51-G52 -> 39.1 | H53: =H56-H55-H51-H52 -> -26.5 | I53: =I56-I55-I51-I52 -> -12.7 | J53: =J56-J55-J51-J52 -> 1.6 | ... M53: =M56-M55-M51-M52 -> 1.1368684e-12 | N53: =0 -> 0 | O53: =0 -> 0 | P53: =0 -> 0 | Q53: =0 -> 0
A54: Net change in cash | B54: ₹ cr | C54: =SUM(C51:C53) -> 9904.9 | D54: =SUM(D51:D53) -> -4633.9 | E54: =SUM(E51:E53) -> -778.5 | F54: =SUM(F51:F53) -> 11360.4 | G54: =SUM(G51:G53) -> -1403 | H54: =SUM(H51:H53) -> 2529.4 | I54: =SUM(I51:I53) -> -6595.7 | J54: =SUM(J51:J53) -> -1195.6 | ... Q54: =SUM(Q51:Q53) -> 4845.4389
A55: Opening cash | B55: ₹ cr | C55: ='Raw Financials'!C141 -> 0 | D55: ='Raw Financials'!D141 -> 9904.9 | E55: ='Raw Financials'!E141 -> 5271 | F55: ='Raw Financials'!F141 -> 4492.5 | G55: ='Raw Financials'!G141 -> 15852.9 | H55: ='Raw Financials'!H141 -> 14449.9 | I55: ='Raw Financials'!I141 -> 16979.3 | J55: ='Raw Financials'!J141 -> 10383.6 | ... M55: ='Raw Financials'!M141 -> 12197.4 | N55: =M56 -> 10555.5 | O55: =N56 -> 5964.9826 | P55: =O56 -> 10405.149 | Q55: =P56 -> 15047.6
A56: Closing cash per CFS | B56: ₹ cr | C56: ='Raw Financials'!C142 -> 9904.9 | D56: ='Raw Financials'!D142 -> 5271 | E56: ='Raw Financials'!E142 -> 4492.5 | F56: ='Raw Financials'!F142 -> 15852.9 | G56: ='Raw Financials'!G142 -> 14449.9 | H56: ='Raw Financials'!H142 -> 16979.3 | I56: ='Raw Financials'!I142 -> 10383.6 | J56: ='Raw Financials'!J142 -> 9188 | ... M56: ='Raw Financials'!M142 -> 10555.5 | N56: =N55+N54 -> 5964.9826 | O56: =O55+O54 -> 10405.149 | P56: =P55+P54 -> 15047.6 | Q56: =Q55+Q54 -> 19893.038
A57: Closing cash per balance sheet | B57: ₹ cr | C57: ='Annual Balance Sheet'!C22 -> 9904.9 | D57: ='Annual Balance Sheet'!D22 -> 5271 | E57: ='Annual Balance Sheet'!E22 -> 4492.5 | F57: ='Annual Balance Sheet'!F22 -> 15852.9 | G57: ='Annual Balance Sheet'!G22 -> 14449.9 | H57: ='Annual Balance Sheet'!H22 -> 16979.3 | I57: ='Annual Balance Sheet'!I22 -> 10383.6 | J57: ='Annual Balance Sheet'!J22 -> 9188 | ... Q57: ='Annual Balance Sheet'!Q22 -> 19893.038
A58: Cash check | B58: ₹ cr | C58: =C56-C57 -> 0 | D58: =D56-D57 -> 0 | E58: =E56-E57 -> 0 | F58: =F56-F57 -> 0 | G58: =G56-G57 -> 0 | H58: =H56-H57 -> 0 | I58: =I56-I57 -> 0 | J58: =J56-J57 -> 0 | ... Q58: =Q56-Q57 -> 0
A59: Free cash flow | B59: ₹ cr | C59: =C29+C31 -> 6492.2 | D59: =D29+D31 -> 7192 | E59: =E29+E31 -> 6236.3 | F59: =F29+F31 -> 9353.5 | G59: =G29+G31 -> 7714.6 | H59: =H29+H31 -> 12797.3 | I59: =I29+I31 -> 9064.4 | J59: =J29+J31 -> 11576.7 | ... Q59: =Q29+Q31 -> 17683.69
A60: FCF margin | B60: % | C60: =IFERROR(C59/'Annual P&L'!C7,"") -> 0.12669191 | D60: =IFERROR(D59/'Annual P&L'!D7,"") -> 0.13066813 | E60: =IFERROR(E59/'Annual P&L'!E7,"") -> 0.11445461 | F60: =IFERROR(F59/'Annual P&L'!F7,"") -> 0.15965827 | G60: =IFERROR(G59/'Annual P&L'!G7,"") -> 0.12642077 | H60: =IFERROR(H59/'Annual P&L'!H7,"") -> 0.206598 | I60: =IFERROR(I59/'Annual P&L'!I7,"") -> 0.11460375 | J60: =IFERROR(J59/'Annual P&L'!J7,"") -> 0.12793687 | ... Q60: =IFERROR(Q59/'Annual P&L'!Q7,"") -> 0.14937704
A61: Dividend payout | B61: % | C61: =IFERROR(-C46/'Annual P&L'!C29,"") -> 0.3984732 | D61: =IFERROR(-D46/'Annual P&L'!D29,"") -> 0.10288003 | E61: =IFERROR(-E46/'Annual P&L'!E29,"") -> 0.067681473 | F61: =IFERROR(-F46/'Annual P&L'!F29,"") -> 0.050027213 | G61: =IFERROR(-G46/'Annual P&L'!G29,"") -> 0.05851797 | H61: =IFERROR(-H46/'Annual P&L'!H29,"") -> 0.050571582 | I61: =IFERROR(-I46/'Annual P&L'!I29,"") -> 0.044741429 | J61: =IFERROR(-J46/'Annual P&L'!J29,"") -> 0.28911013 | ... Q61: =IFERROR(-Q46/'Annual P&L'!Q29,"") -> 0.7

Sheet BS Forecast Schedules
A1: Balance Sheet Forecast Schedules — No Circular References
A2: P&L / assumptions → non-cash schedules → CFO / CFI / CFF → closing cash → balance sheet
A5: Metric | B5: Units | C5: FY26A | D5: FY27E | E5: FY28E | F5: FY29E | G5: FY30E
A7: Capital asset schedules
A8: Revenue | B8: ₹ cr | C8: ='Annual P&L'!M7 -> 92624 | D8: ='Annual P&L'!N7 -> 95426.741 | E8: ='Annual P&L'!O7 -> 101167.44 | F8: ='Annual P&L'!P7 -> 109097.12 | G8: ='Annual P&L'!Q7 -> 118382.92
A9: Total D&A | B9: ₹ cr | C9: ='Annual P&L'!M17 -> 2910.7 | D9: ='Annual P&L'!N17 -> 2958.229 | E9: ='Annual P&L'!O17 -> 3035.0231 | F9: ='Annual P&L'!P17 -> 3163.8166 | G9: ='Annual P&L'!Q17 -> 3314.7217
A10: Total capex | B10: ₹ cr | D10: =D8*Assumptions!C37 -> 1717.6813 | E10: =E8*Assumptions!D37 -> 1821.0139 | F10: =F8*Assumptions!E37 -> 1963.7482 | G10: =G8*Assumptions!F37 -> 2130.8925
A11: Intangible capex | B11: ₹ cr | D11: =D10*Assumptions!C38 -> 343.53627 | E11: =E10*Assumptions!D38 -> 364.20277 | F11: =F10*Assumptions!E38 -> 392.74965 | G11: =G10*Assumptions!F38 -> 426.1785
A12: Tangible capex | B12: ₹ cr | D12: =D10-D11 -> 1374.1451 | E12: =E10-E11 -> 1456.8111 | F12: =F10-F11 -> 1570.9986 | G12: =G10-G11 -> 1704.714
A13: PPE D&A | B13: ₹ cr | D13: =D9*Assumptions!C40 -> 1331.203 | E13: =E9*Assumptions!D40 -> 1365.7604 | F13: =F9*Assumptions!E40 -> 1423.7175 | G13: =G9*Assumptions!F40 -> 1491.6248
A14: ROU D&A | B14: ₹ cr | D14: =D9*Assumptions!C41 -> 887.46869 | E14: =E9*Assumptions!D41 -> 910.50693 | F14: =F9*Assumptions!E41 -> 949.14498 | G14: =G9*Assumptions!F41 -> 994.4165
A15: Intangible D&A | B15: ₹ cr | D15: =D9*Assumptions!C42 -> 739.55724 | E15: =E9*Assumptions!D42 -> 758.75577 | F15: =F9*Assumptions!E42 -> 790.95415 | G15: =G9*Assumptions!F42 -> 828.68042
A16: D&A allocation check | B16: ₹ cr | D16: =SUM(D13:D15)-D9 -> 0 | E16: =SUM(E13:E15)-E9 -> 0 | F16: =SUM(F13:F15)-F9 -> 0 | G16: =SUM(G13:G15)-G9 -> 0
A17: Closing PPE | B17: ₹ cr | C17: ='Annual Balance Sheet'!M7 -> 8178.7 | D17: =MAX(0,C17+D12-D13) -> 8221.642 | E17: =MAX(0,D17+E12-E13) -> 8312.6927 | F17: =MAX(0,E17+F12-F13) -> 8459.9738 | G17: =MAX(0,F17+G12-G13) -> 8673.0631
A18: Closing intangibles | B18: ₹ cr | C18: ='Annual Balance Sheet'!M10 -> 2917.6 | D18: =MAX(0,C18+D11-D15) -> 2521.579 | E18: =MAX(0,D18+E11-E15) -> 2127.026 | F18: =MAX(0,E18+F11-F15) -> 1728.8215 | G18: =MAX(0,F18+G11-G15) -> 1326.3196
A21: ROU and lease schedule
A22: Opening ROU assets | B22: ₹ cr | D22: =C25 -> 2828.7 | E22: =D25 -> 3086.3522 | F22: =E25 -> 3389.8545 | G22: =F25 -> 3749.875
A23: ROU additions | B23: ₹ cr | D23: =D8*Assumptions!C39 -> 1145.1209 | E23: =E8*Assumptions!D39 -> 1214.0092 | F23: =F8*Assumptions!E39 -> 1309.1655 | G23: =G8*Assumptions!F39 -> 1420.595
A24: ROU D&A | B24: ₹ cr | D24: =D14 -> 887.46869 | E24: =E14 -> 910.50693 | F24: =F14 -> 949.14498 | G24: =G14 -> 994.4165
A25: Closing ROU assets | B25: ₹ cr | C25: ='Annual Balance Sheet'!M8 -> 2828.7 | D25: =MAX(0,D22+D23-D24) -> 3086.3522 | E25: =MAX(0,E22+E23-E24) -> 3389.8545 | F25: =MAX(0,F22+F23-F24) -> 3749.875 | G25: =MAX(0,G22+G23-G24) -> 4176.0535
A26: Opening lease liabilities | B26: ₹ cr | D26: =C29 -> 3503.6 | E26: =D29 -> 3772.8209 | F26: =E29 -> 4043.6249 | G26: =F29 -> 4341.8842
A27: ROU / lease additions | B27: ₹ cr | D27: =D23 -> 1145.1209 | E27: =E23 -> 1214.0092 | F27: =F23 -> 1309.1655 | G27: =G23 -> 1420.595
A28: Lease principal paid | B28: ₹ cr | D28: =-D26*Assumptions!C43 -> -875.9 | E28: =-E26*Assumptions!D43 -> -943.20522 | F28: =-F26*Assumptions!E43 -> -1010.9062 | G28: =-G26*Assumptions!F43 -> -1085.471
A29: Closing lease liabilities | B29: ₹ cr | C29: ='Annual Balance Sheet'!M61 -> 3503.6 | D29: =MAX(0,D26+D27+D28) -> 3772.8209 | E29: =MAX(0,E26+E27+E28) -> 4043.6249 | F29: =MAX(0,F26+F27+F28) -> 4341.8842 | G29: =MAX(0,G26+G27+G28) -> 4677.0081
A32: Borrowing schedule
A33: Opening borrowings | B33: ₹ cr | D33: =C35 -> 16787.4 | E33: =D35 -> 16787.4 | F33: =E35 -> 16787.4 | G33: =F35 -> 16787.4
A34: Net borrowing change | B34: ₹ cr | D34: =Assumptions!C44 -> 0 | E34: =Assumptions!D44 -> 0 | F34: =Assumptions!E44 -> 0 | G34: =Assumptions!F44 -> 0
A35: Closing borrowings | B35: ₹ cr | C35: ='Annual Balance Sheet'!M60 -> 16787.4 | D35: =MAX(0,D33+D34) -> 16787.4 | E35: =MAX(0,E33+E34) -> 16787.4 | F35: =MAX(0,F33+F34) -> 16787.4 | G35: =MAX(0,G33+G34) -> 16787.4
A36: Current borrowings | B36: ₹ cr | D36: =D35*Assumptions!C45 -> 16451.652 | E36: =E35*Assumptions!D45 -> 16451.652 | F36: =F35*Assumptions!E45 -> 16451.652 | G36: =G35*Assumptions!F45 -> 16451.652
A37: Long-term borrowings | B37: ₹ cr | D37: =D35-D36 -> 335.748 | E37: =E35-E36 -> 335.748 | F37: =F35-F36 -> 335.748 | G37: =G35-G36 -> 335.748
A40: Equity roll-forward
A41: Opening equity attributable | B41: ₹ cr | D41: =C47 -> 88536.8 | E41: =D47 -> 77368.829 | F41: =E47 -> 81833.182 | G41: =F47 -> 87072.793
A42: Net income attributable | B42: ₹ cr | D42: ='Annual P&L'!N29 -> 13419.581 | E42: ='Annual P&L'!O29 -> 14137.557 | F42: ='Annual P&L'!P29 -> 15647.085 | G42: ='Annual P&L'!Q29 -> 17320.917
A43: Dividends paid | B43: ₹ cr | D43: =-'Annual P&L'!N29*Assumptions!C46 -> -10064.686 | E43: =-'Annual P&L'!O29*Assumptions!D46 -> -10179.041 | F43: =-'Annual P&L'!P29*Assumptions!E46 -> -10952.96 | G43: =-'Annual P&L'!Q29*Assumptions!F46 -> -12124.642
A44: Buyback | B44: ₹ cr | D44: =-Assumptions!C47 -> -15000 | E44: =-Assumptions!D47 -> 0 | F44: =-Assumptions!E47 -> 0 | G44: =-Assumptions!F47 -> 0
A45: Share-based compensation | B45: ₹ cr | D45: ='Annual P&L'!N7*Assumptions!C48 -> 477.13371 | E45: ='Annual P&L'!O7*Assumptions!D48 -> 505.83718 | F45: ='Annual P&L'!P7*Assumptions!E48 -> 545.48562 | G45: ='Annual P&L'!Q7*Assumptions!F48 -> 591.91459
A46: OCI / other reserves | B46: ₹ cr | D46: =Assumptions!C49 -> 0 | E46: =Assumptions!D49 -> 0 | F46: =Assumptions!E49 -> 0 | G46: =Assumptions!F49 -> 0
A47: Closing equity attributable | B47: ₹ cr | C47: ='Annual Balance Sheet'!M34 -> 88536.8 | D47: =SUM(D41:D46) -> 77368.829 | E47: =SUM(E41:E46) -> 81833.182 | F47: =SUM(F41:F46) -> 87072.793 | G47: =SUM(G41:G46) -> 92860.983
A48: NCI | B48: ₹ cr | C48: ='Annual Balance Sheet'!M35 -> 250.9 | D48: =C48 -> 250.9 | E48: =D48 -> 250.9 | F48: =E48 -> 250.9 | G48: =F48 -> 250.9
A49: Total equity | B49: ₹ cr | C49: ='Annual Balance Sheet'!M36 -> 88787.7 | D49: =SUM(D47:D48) -> 77619.729 | E49: =SUM(E47:E48) -> 82084.082 | F49: =SUM(F47:F48) -> 87323.693 | G49: =SUM(G47:G48) -> 93111.883
A52: Cash roll-forward
A53: Opening cash | B53: ₹ cr | D53: =C58 -> 10555.5 | E53: =D58 -> 5964.9826 | F53: =E58 -> 10405.149 | G53: =F58 -> 15047.6
A54: CFO | B54: ₹ cr | D54: ='Annual Cash Flow'!N29 -> 19280.158 | E54: ='Annual Cash Flow'!O29 -> 16381.232 | F54: ='Annual Cash Flow'!P29 -> 18113.22 | G54: ='Annual Cash Flow'!Q29 -> 19814.582
A55: CFI | B55: ₹ cr | D55: ='Annual Cash Flow'!N39 -> 3490.2805 | E55: ='Annual Cash Flow'!O39 -> 620.39584 | F55: ='Annual Cash Flow'!P39 -> -48.732016 | G55: ='Annual Cash Flow'!Q39 -> -279.98051
A56: CFF | B56: ₹ cr | D56: ='Annual Cash Flow'!N50 -> -27360.956 | E56: ='Annual Cash Flow'!O50 -> -12561.461 | F56: ='Annual Cash Flow'!P50 -> -13422.038 | G56: ='Annual Cash Flow'!Q50 -> -14689.163
A57: FX effect | B57: ₹ cr | D57: ='Annual Cash Flow'!N52 -> 0 | E57: ='Annual Cash Flow'!O52 -> 0 | F57: ='Annual Cash Flow'!P52 -> 0 | G57: ='Annual Cash Flow'!Q52 -> 0
A58: Closing cash | B58: ₹ cr | C58: ='Annual Balance Sheet'!M22 -> 10555.5 | D58: =SUM(D53:D57) -> 5964.9826 | E58: =SUM(E53:E57) -> 10405.149 | F58: =SUM(F53:F57) -> 15047.6 | G58: =SUM(G53:G57) -> 19893.038
A59: Balance-sheet cash | B59: ₹ cr | C59: ='Annual Balance Sheet'!M22 -> 10555.5 | D59: ='Annual Balance Sheet'!N22 -> 5964.9826 | E59: ='Annual Balance Sheet'!O22 -> 10405.149 | F59: ='Annual Balance Sheet'!P22 -> 15047.6 | G59: ='Annual Balance Sheet'!Q22 -> 19893.038
A60: Cash check | B60: ₹ cr | D60: =D58-D59 -> 0 | E60: =E58-E59 -> 0 | F60: =F58-F59 -> 0 | G60: =G58-G59 -> 0

Sheet Vertical Revenue
A1: Revenue by Vertical
A2: Legacy and current Wipro sector classifications are kept in separate sections; revenue = reported mix × annual revenue
A5: Metric | B5: Units | C5: FY16A | D5: FY17A | E5: FY18A | F5: FY19A | G5: FY20A | H5: FY21A | I5: FY22A | J5: FY23A | K5: FY24A | L5: FY25A | M5: FY26A | N5: FY27E | O5: FY28E | P5: FY29E | Q5: FY30E
A7: Legacy classification — FY16 to FY23
A8: Finance solutions / BFSI mix | B8: % | C8: ='Raw Operating'!C35 -> 0.263 | D8: ='Raw Operating'!D35 -> 0.257 | E8: ='Raw Operating'!E35 -> 0.281 | F8: ='Raw Operating'!F35 -> 0.309 | G8: ='Raw Operating'!G35 -> 0.31 | H8: ='Raw Operating'!H35 -> 0.307 | I8: ='Raw Operating'!I35 -> 0.347 | J8: ='Raw Operating'!J35 -> 0.349
A9: Finance solutions / BFSI revenue | B9: ₹ cr | C9: =IF(C8="","",C8*'Annual P&L'!C7) -> 13477.172 | D9: =IF(D8="","",D8*'Annual P&L'!D7) -> 14145.331 | E9: =IF(E8="","",E8*'Annual P&L'!E7) -> 15310.875 | F9: =IF(F8="","",F8*'Annual P&L'!F7) -> 18102.61 | G9: =IF(G8="","",G8*'Annual P&L'!G7) -> 18917.192 | H9: =IF(H8="","",H8*'Annual P&L'!H7) -> 19016.501 | I9: =IF(I8="","",I8*'Annual P&L'!I7) -> 27445.41 | J9: =IF(J8="","",J8*'Annual P&L'!J7) -> 31580.172 | ... Q9: =IF(Q8="","",Q8*'Annual P&L'!Q7)
A10: Media & telecom / communications mix | B10: % | C10: ='Raw Operating'!C36 -> 0.133 | D10: ='Raw Operating'!D36 -> 0.073 | E10: ='Raw Operating'!E36 -> 0.064 | F10: ='Raw Operating'!F36 -> 0.057 | G10: ='Raw Operating'!G36 -> 0.057 | H10: ='Raw Operating'!H36 -> 0.052 | I10: ='Raw Operating'!I36 -> 0.05 | J10: ='Raw Operating'!J36 -> 0.047
A11: Media & telecom / communications revenue | B11: ₹ cr | C11: =IF(C10="","",C10*'Annual P&L'!C7) -> 6815.452 | D11: =IF(D10="","",D10*'Annual P&L'!D7) -> 4017.9346 | E11: =IF(E10="","",E10*'Annual P&L'!E7) -> 3487.1744 | F11: =IF(F10="","",F10*'Annual P&L'!F7) -> 3339.3165 | G11: =IF(G10="","",G10*'Annual P&L'!G7) -> 3478.3224 | H11: =IF(H10="","",H10*'Annual P&L'!H7) -> 3221.036 | I11: =IF(I10="","",I10*'Annual P&L'!I7) -> 3954.67 | J11: =IF(J10="","",J10*'Annual P&L'!J7) -> 4252.9172 | ... Q11: =IF(Q10="","",Q10*'Annual P&L'!Q7)
A12: Manufacturing & hi-tech mix | B12: % | C12: ='Raw Operating'!C37 -> 0.186 | D12: ='Raw Operating'!D37 -> 0 | E12: ='Raw Operating'!E37 -> 0 | F12: ='Raw Operating'!F37 -> 0 | G12: ='Raw Operating'!G37 -> 0 | H12: ='Raw Operating'!H37 -> 0 | I12: ='Raw Operating'!I37 -> 0 | J12: ='Raw Operating'!J37 -> 0
A13: Manufacturing & hi-tech revenue | B13: ₹ cr | C13: =IF(C12="","",C12*'Annual P&L'!C7) -> 9531.384 | D13: =IF(D12="","",D12*'Annual P&L'!D7) -> 0 | E13: =IF(E12="","",E12*'Annual P&L'!E7) -> 0 | F13: =IF(F12="","",F12*'Annual P&L'!F7) -> 0 | G13: =IF(G12="","",G12*'Annual P&L'!G7) -> 0 | H13: =IF(H12="","",H12*'Annual P&L'!H7) -> 0 | I13: =IF(I12="","",I12*'Annual P&L'!I7) -> 0 | J13: =IF(J12="","",J12*'Annual P&L'!J7) -> 0 | ... Q13: =IF(Q12="","",Q12*'Annual P&L'!Q7)
A14: Healthcare & life sciences mix | B14: % | C14: ='Raw Operating'!C38 -> 0.12 | D14: ='Raw Operating'!D38 -> 0.156 | E14: ='Raw Operating'!E38 -> 0 | F14: ='Raw Operating'!F38 -> 0.132 | G14: ='Raw Operating'!G38 -> 0.132 | H14: ='Raw Operating'!H38 -> 0.13 | I14: ='Raw Operating'!I38 -> 0.115 | J14: ='Raw Operating'!J38 -> 0.122
A15: Healthcare & life sciences revenue | B15: ₹ cr | C15: =IF(C14="","",C14*'Annual P&L'!C7) -> 6149.28 | D15: =IF(D14="","",D14*'Annual P&L'!D7) -> 8586.2712 | E15: =IF(E14="","",E14*'Annual P&L'!E7) -> 0 | F15: =IF(F14="","",F14*'Annual P&L'!F7) -> 7733.154 | G15: =IF(G14="","",G14*'Annual P&L'!G7) -> 8055.0624 | H15: =IF(H14="","",H14*'Annual P&L'!H7) -> 8052.59 | I15: =IF(I14="","",I14*'Annual P&L'!I7) -> 9095.741 | J15: =IF(J14="","",J14*'Annual P&L'!J7) -> 11039.487 | ... Q15: =IF(Q14="","",Q14*'Annual P&L'!Q7)
A16: Retail / consumer / transportation mix | B16: % | C16: ='Raw Operating'!C39 -> 0.152 | D16: ='Raw Operating'!D39 -> 0.158 | E16: ='Raw Operating'!E39 -> 0.158 | F16: ='Raw Operating'!F39 -> 0.157 | G16: ='Raw Operating'!G39 -> 0.163 | H16: ='Raw Operating'!H39 -> 0.17 | I16: ='Raw Operating'!I39 -> 0.179 | J16: ='Raw Operating'!J39 -> 0.188
A17: Retail / consumer / transportation revenue | B17: ₹ cr | C17: =IF(C16="","",C16*'Annual P&L'!C7) -> 7789.088 | D17: =IF(D16="","",D16*'Annual P&L'!D7) -> 8696.3516 | E17: =IF(E16="","",E16*'Annual P&L'!E7) -> 8608.9618 | F17: =IF(F16="","",F16*'Annual P&L'!F7) -> 9197.7665 | G17: =IF(G16="","",G16*'Annual P&L'!G7) -> 9946.7816 | H17: =IF(H16="","",H16*'Annual P&L'!H7) -> 10530.31 | I17: =IF(I16="","",I16*'Annual P&L'!I7) -> 14157.719 | J17: =IF(J16="","",J16*'Annual P&L'!J7) -> 17011.669 | ... Q17: =IF(Q16="","",Q16*'Annual P&L'!Q7)
A18: Energy / utilities mix | B18: % | C18: ='Raw Operating'!C40 -> 0.146 | D18: ='Raw Operating'!D40 -> 0.131 | E18: ='Raw Operating'!E40 -> 0 | F18: ='Raw Operating'!F40 -> 0 | G18: ='Raw Operating'!G40 -> 0 | H18: ='Raw Operating'!H40 -> 0 | I18: ='Raw Operating'!I40 -> 0 | J18: ='Raw Operating'!J40 -> 0
A19: Energy / utilities revenue | B19: ₹ cr | C19: =IF(C18="","",C18*'Annual P&L'!C7) -> 7481.624 | D19: =IF(D18="","",D18*'Annual P&L'!D7) -> 7210.2662 | E19: =IF(E18="","",E18*'Annual P&L'!E7) -> 0 | F19: =IF(F18="","",F18*'Annual P&L'!F7) -> 0 | G19: =IF(G18="","",G18*'Annual P&L'!G7) -> 0 | H19: =IF(H18="","",H18*'Annual P&L'!H7) -> 0 | I19: =IF(I18="","",I18*'Annual P&L'!I7) -> 0 | J19: =IF(J18="","",J18*'Annual P&L'!J7) -> 0 | ... Q19: =IF(Q18="","",Q18*'Annual P&L'!Q7)
A20: Mix check | B20: % | C20: =IF(COUNT(C8,C10,C12,C14,C16,C18)=0,"",SUM(C8,C10,C12,C14,C16,C18)) -> 1 | D20: =IF(COUNT(D8,D10,D12,D14,D16,D18)=0,"",SUM(D8,D10,D12,D14,D16,D18)) -> 0.775 | E20: =IF(COUNT(E8,E10,E12,E14,E16,E18)=0,"",SUM(E8,E10,E12,E14,E16,E18)) -> 0.503 | F20: =IF(COUNT(F8,F10,F12,F14,F16,F18)=0,"",SUM(F8,F10,F12,F14,F16,F18)) -> 0.655 | G20: =IF(COUNT(G8,G10,G12,G14,G16,G18)=0,"",SUM(G8,G10,G12,G14,G16,G18)) -> 0.662 | H20: =IF(COUNT(H8,H10,H12,H14,H16,H18)=0,"",SUM(H8,H10,H12,H14,H16,H18)) -> 0.659 | I20: =IF(COUNT(I8,I10,I12,I14,I16,I18)=0,"",SUM(I8,I10,I12,I14,I16,I18)) -> 0.691 | J20: =IF(COUNT(J8,J10,J12,J14,J16,J18)=0,"",SUM(J8,J10,J12,J14,J16,J18)) -> 0.706 | ... Q20: =IF(COUNT(Q8,Q10,Q12,Q14,Q16,Q18)=0,"",SUM(Q8,Q10,Q12,Q14,Q16,Q18))
A21: Calculated revenue | B21: ₹ cr | C21: =SUM(C9,C11,C13,C15,C17,C19) -> 51244 | D21: =SUM(D9,D11,D13,D15,D17,D19) -> 42656.155 | E21: =SUM(E9,E11,E13,E15,E17,E19) -> 27407.011 | F21: =SUM(F9,F11,F13,F15,F17,F19) -> 38372.847 | G21: =SUM(G9,G11,G13,G15,G17,G19) -> 40397.358 | H21: =SUM(H9,H11,H13,H15,H17,H19) -> 40820.437 | I21: =SUM(I9,I11,I13,I15,I17,I19) -> 54653.539 | J21: =SUM(J9,J11,J13,J15,J17,J19) -> 63884.246 | ... Q21: =SUM(Q9,Q11,Q13,Q15,Q17,Q19) -> 0
A22: Annual P&L revenue | B22: ₹ cr | C22: ='Annual P&L'!C7 -> 51244 | D22: ='Annual P&L'!D7 -> 55040.2 | E22: ='Annual P&L'!E7 -> 54487.1 | F22: ='Annual P&L'!F7 -> 58584.5 | G22: ='Annual P&L'!G7 -> 61023.2 | H22: ='Annual P&L'!H7 -> 61943 | I22: ='Annual P&L'!I7 -> 79093.4 | J22: ='Annual P&L'!J7 -> 90487.6 | ... Q22: ='Annual P&L'!Q7 -> 118382.92
A23: Revenue check | B23: ₹ cr | C23: =IF(C20="","",C21-C22) -> 0 | D23: =IF(D20="","",D21-D22) -> -12384.045 | E23: =IF(E20="","",E21-E22) -> -27080.089 | F23: =IF(F20="","",F21-F22) -> -20211.653 | G23: =IF(G20="","",G21-G22) -> -20625.842 | H23: =IF(H20="","",H21-H22) -> -21122.563 | I23: =IF(I20="","",I21-I22) -> -24439.861 | J23: =IF(J20="","",J21-J22) -> -26603.354 | ... Q23: =IF(Q20="","",Q21-Q22)
A26: Current five-sector classification — FY24 onward
A27: BFSI mix | B27: % | K27: ='Raw Operating'!K35 -> 0.334 | L27: ='Raw Operating'!L35 -> 0.343 | M27: ='Raw Operating'!M35 -> 0.341 | N27: =M27 -> 0.341 | O27: =N27 -> 0.341 | P27: =O27 -> 0.341 | Q27: =P27 -> 0.341
A28: BFSI revenue | B28: ₹ cr | C28: =IF(C27="","",C27*'Annual P&L'!C7) | D28: =IF(D27="","",D27*'Annual P&L'!D7) | E28: =IF(E27="","",E27*'Annual P&L'!E7) | F28: =IF(F27="","",F27*'Annual P&L'!F7) | G28: =IF(G27="","",G27*'Annual P&L'!G7) | H28: =IF(H27="","",H27*'Annual P&L'!H7) | I28: =IF(I27="","",I27*'Annual P&L'!I7) | J28: =IF(J27="","",J27*'Annual P&L'!J7) | ... Q28: =IF(Q27="","",Q27*'Annual P&L'!Q7) -> 40368.575
A29: Consumer mix | B29: % | K29: ='Raw Operating'!K39 -> 0.187 | L29: ='Raw Operating'!L39 -> 0.189 | M29: ='Raw Operating'!M39 -> 0.184 | N29: =M29 -> 0.184 | O29: =N29 -> 0.184 | P29: =O29 -> 0.184 | Q29: =P29 -> 0.184
A30: Consumer revenue | B30: ₹ cr | C30: =IF(C29="","",C29*'Annual P&L'!C7) | D30: =IF(D29="","",D29*'Annual P&L'!D7) | E30: =IF(E29="","",E29*'Annual P&L'!E7) | F30: =IF(F29="","",F29*'Annual P&L'!F7) | G30: =IF(G29="","",G29*'Annual P&L'!G7) | H30: =IF(H29="","",H29*'Annual P&L'!H7) | I30: =IF(I29="","",I29*'Annual P&L'!I7) | J30: =IF(J29="","",J29*'Annual P&L'!J7) | ... Q30: =IF(Q29="","",Q29*'Annual P&L'!Q7) -> 21782.457
A31: Energy, Manufacturing & Resources mix | B31: % | K31: ='Raw Operating'!K37 -> 0 | L31: ='Raw Operating'!L37 -> 0 | M31: ='Raw Operating'!M37 -> 0.17 | N31: =M31 -> 0.17 | O31: =N31 -> 0.17 | P31: =O31 -> 0.17 | Q31: =P31 -> 0.17
A32: Energy, Manufacturing & Resources revenue | B32: ₹ cr | C32: =IF(C31="","",C31*'Annual P&L'!C7) | D32: =IF(D31="","",D31*'Annual P&L'!D7) | E32: =IF(E31="","",E31*'Annual P&L'!E7) | F32: =IF(F31="","",F31*'Annual P&L'!F7) | G32: =IF(G31="","",G31*'Annual P&L'!G7) | H32: =IF(H31="","",H31*'Annual P&L'!H7) | I32: =IF(I31="","",I31*'Annual P&L'!I7) | J32: =IF(J31="","",J31*'Annual P&L'!J7) | ... Q32: =IF(Q31="","",Q31*'Annual P&L'!Q7) -> 20125.096
A33: Technology & Communications mix | B33: % | K33: ='Raw Operating'!K41 -> 0 | L33: ='Raw Operating'!L41 -> 0.153 | M33: ='Raw Operating'!M41 -> 0.16 | N33: =M33 -> 0.16 | O33: =N33 -> 0.16 | P33: =O33 -> 0.16 | Q33: =P33 -> 0.16
A34: Technology & Communications revenue | B34: ₹ cr | C34: =IF(C33="","",C33*'Annual P&L'!C7) | D34: =IF(D33="","",D33*'Annual P&L'!D7) | E34: =IF(E33="","",E33*'Annual P&L'!E7) | F34: =IF(F33="","",F33*'Annual P&L'!F7) | G34: =IF(G33="","",G33*'Annual P&L'!G7) | H34: =IF(H33="","",H33*'Annual P&L'!H7) | I34: =IF(I33="","",I33*'Annual P&L'!I7) | J34: =IF(J33="","",J33*'Annual P&L'!J7) | ... Q34: =IF(Q33="","",Q33*'Annual P&L'!Q7) -> 18941.267
A35: Health mix | B35: % | K35: ='Raw Operating'!K38 -> 0.141 | L35: ='Raw Operating'!L38 -> 0.144 | M35: ='Raw Operating'!M38 -> 0.142 | N35: =M35 -> 0.142 | O35: =N35 -> 0.142 | P35: =O35 -> 0.142 | Q35: =P35 -> 0.142
A36: Health revenue | B36: ₹ cr | C36: =IF(C35="","",C35*'Annual P&L'!C7) | D36: =IF(D35="","",D35*'Annual P&L'!D7) | E36: =IF(E35="","",E35*'Annual P&L'!E7) | F36: =IF(F35="","",F35*'Annual P&L'!F7) | G36: =IF(G35="","",G35*'Annual P&L'!G7) | H36: =IF(H35="","",H35*'Annual P&L'!H7) | I36: =IF(I35="","",I35*'Annual P&L'!I7) | J36: =IF(J35="","",J35*'Annual P&L'!J7) | ... Q36: =IF(Q35="","",Q35*'Annual P&L'!Q7) -> 16810.374
A37: Mix check | B37: % | C37: =IF(COUNT(C27,C29,C31,C33,C35)=0,"",SUM(C27,C29,C31,C33,C35)) | D37: =IF(COUNT(D27,D29,D31,D33,D35)=0,"",SUM(D27,D29,D31,D33,D35)) | E37: =IF(COUNT(E27,E29,E31,E33,E35)=0,"",SUM(E27,E29,E31,E33,E35)) | F37: =IF(COUNT(F27,F29,F31,F33,F35)=0,"",SUM(F27,F29,F31,F33,F35)) | G37: =IF(COUNT(G27,G29,G31,G33,G35)=0,"",SUM(G27,G29,G31,G33,G35)) | H37: =IF(COUNT(H27,H29,H31,H33,H35)=0,"",SUM(H27,H29,H31,H33,H35)) | I37: =IF(COUNT(I27,I29,I31,I33,I35)=0,"",SUM(I27,I29,I31,I33,I35)) | J37: =IF(COUNT(J27,J29,J31,J33,J35)=0,"",SUM(J27,J29,J31,J33,J35)) | ... Q37: =IF(COUNT(Q27,Q29,Q31,Q33,Q35)=0,"",SUM(Q27,Q29,Q31,Q33,Q35)) -> 0.997
A38: Calculated revenue | B38: ₹ cr | C38: =SUM(C28,C30,C32,C34,C36) -> 0 | D38: =SUM(D28,D30,D32,D34,D36) -> 0 | E38: =SUM(E28,E30,E32,E34,E36) -> 0 | F38: =SUM(F28,F30,F32,F34,F36) -> 0 | G38: =SUM(G28,G30,G32,G34,G36) -> 0 | H38: =SUM(H28,H30,H32,H34,H36) -> 0 | I38: =SUM(I28,I30,I32,I34,I36) -> 0 | J38: =SUM(J28,J30,J32,J34,J36) -> 0 | ... Q38: =SUM(Q28,Q30,Q32,Q34,Q36) -> 118027.77
A39: Annual P&L revenue | B39: ₹ cr | C39: ='Annual P&L'!C7 -> 51244 | D39: ='Annual P&L'!D7 -> 55040.2 | E39: ='Annual P&L'!E7 -> 54487.1 | F39: ='Annual P&L'!F7 -> 58584.5 | G39: ='Annual P&L'!G7 -> 61023.2 | H39: ='Annual P&L'!H7 -> 61943 | I39: ='Annual P&L'!I7 -> 79093.4 | J39: ='Annual P&L'!J7 -> 90487.6 | ... Q39: ='Annual P&L'!Q7 -> 118382.92
A40: Revenue check | B40: ₹ cr | C40: =IF(C37="","",C38-C39) | D40: =IF(D37="","",D38-D39) | E40: =IF(E37="","",E38-E39) | F40: =IF(F37="","",F38-F39) | G40: =IF(G37="","",G38-G39) | H40: =IF(H37="","",H38-H39) | I40: =IF(I37="","",I38-I39) | J40: =IF(J37="","",J38-J39) | ... Q40: =IF(Q37="","",Q38-Q39) -> -355.14875

Sheet Geography & Currency
A1: Geography and Currency Mix
A2: Legacy and current geographies remain separate; currency revenue is calculated from reported mix
A5: Metric | B5: Units | C5: FY16A | D5: FY17A | E5: FY18A | F5: FY19A | G5: FY20A | H5: FY21A | I5: FY22A | J5: FY23A | K5: FY24A | L5: FY25A | M5: FY26A | N5: FY27E | O5: FY28E | P5: FY29E | Q5: FY30E
A7: Legacy geography — FY16 to FY23
A8: Americas mix | B8: % | C8: ='Raw Operating'!C42 -> 0.527 | D8: ='Raw Operating'!D42 -> 0.547 | E8: ='Raw Operating'!E42 -> 0.534 | F8: ='Raw Operating'!F42 -> 0.568 | G8: ='Raw Operating'!G42 -> 0.591 | H8: ='Raw Operating'!H42 -> 0.294 | I8: ='Raw Operating'!I42 -> 0.279 | J8: ='Raw Operating'!J42 -> 0.291
A9: Americas revenue | B9: ₹ cr | C9: =IF(C8="","",C8*'Annual P&L'!C7) -> 27005.588 | D9: =IF(D8="","",D8*'Annual P&L'!D7) -> 30106.989 | E9: =IF(E8="","",E8*'Annual P&L'!E7) -> 29096.111 | F9: =IF(F8="","",F8*'Annual P&L'!F7) -> 33275.996 | G9: =IF(G8="","",G8*'Annual P&L'!G7) -> 36064.711 | H9: =IF(H8="","",H8*'Annual P&L'!H7) -> 18211.242 | I9: =IF(I8="","",I8*'Annual P&L'!I7) -> 22067.059 | J9: =IF(J8="","",J8*'Annual P&L'!J7) -> 26331.892 | ... Q9: =IF(Q8="","",Q8*'Annual P&L'!Q7)
A10: Europe mix | B10: % | C10: ='Raw Operating'!C43 -> 0.253 | D10: ='Raw Operating'!D43 -> 0.244 | E10: ='Raw Operating'!E43 -> 0.256 | F10: ='Raw Operating'!F43 -> 0.255 | G10: ='Raw Operating'!G43 -> 0.24 | H10: ='Raw Operating'!H43 -> 0.273 | I10: ='Raw Operating'!I43 -> 0.299 | J10: ='Raw Operating'!J43 -> 0.286
A11: Europe revenue | B11: ₹ cr | C11: =IF(C10="","",C10*'Annual P&L'!C7) -> 12964.732 | D11: =IF(D10="","",D10*'Annual P&L'!D7) -> 13429.809 | E11: =IF(E10="","",E10*'Annual P&L'!E7) -> 13948.698 | F11: =IF(F10="","",F10*'Annual P&L'!F7) -> 14939.048 | G11: =IF(G10="","",G10*'Annual P&L'!G7) -> 14645.568 | H11: =IF(H10="","",H10*'Annual P&L'!H7) -> 16910.439 | I11: =IF(I10="","",I10*'Annual P&L'!I7) -> 23648.927 | J11: =IF(J10="","",J10*'Annual P&L'!J7) -> 25879.454 | ... Q11: =IF(Q10="","",Q10*'Annual P&L'!Q7)
A12: India & Middle East mix | B12: % | C12: ='Raw Operating'!C44 -> 0.108 | D12: ='Raw Operating'!D44 -> 0.101 | E12: ='Raw Operating'!E44 -> 0.099 | F12: ='Raw Operating'!F44 -> 0 | G12: ='Raw Operating'!G44 -> 0 | H12: ='Raw Operating'!H44 -> 0 | I12: ='Raw Operating'!I44 -> 0 | J12: ='Raw Operating'!J44 -> 0
A13: India & Middle East revenue | B13: ₹ cr | C13: =IF(C12="","",C12*'Annual P&L'!C7) -> 5534.352 | D13: =IF(D12="","",D12*'Annual P&L'!D7) -> 5559.0602 | E13: =IF(E12="","",E12*'Annual P&L'!E7) -> 5394.2229 | F13: =IF(F12="","",F12*'Annual P&L'!F7) -> 0 | G13: =IF(G12="","",G12*'Annual P&L'!G7) -> 0 | H13: =IF(H12="","",H12*'Annual P&L'!H7) -> 0 | I13: =IF(I12="","",I12*'Annual P&L'!I7) -> 0 | J13: =IF(J12="","",J12*'Annual P&L'!J7) -> 0 | ... Q13: =IF(Q12="","",Q12*'Annual P&L'!Q7)
A14: APAC / other emerging mix | B14: % | C14: ='Raw Operating'!C45 -> 0.112 | D14: ='Raw Operating'!D45 -> 0.108 | E14: ='Raw Operating'!E45 -> 0.111 | F14: ='Raw Operating'!F45 -> 0 | G14: ='Raw Operating'!G45 -> 0 | H14: ='Raw Operating'!H45 -> 0 | I14: ='Raw Operating'!I45 -> 0 | J14: ='Raw Operating'!J45 -> 0
A15: APAC / other emerging revenue | B15: ₹ cr | C15: =IF(C14="","",C14*'Annual P&L'!C7) -> 5739.328 | D15: =IF(D14="","",D14*'Annual P&L'!D7) -> 5944.3416 | E15: =IF(E14="","",E14*'Annual P&L'!E7) -> 6048.0681 | F15: =IF(F14="","",F14*'Annual P&L'!F7) -> 0 | G15: =IF(G14="","",G14*'Annual P&L'!G7) -> 0 | H15: =IF(H14="","",H14*'Annual P&L'!H7) -> 0 | I15: =IF(I14="","",I14*'Annual P&L'!I7) -> 0 | J15: =IF(J14="","",J14*'Annual P&L'!J7) -> 0 | ... Q15: =IF(Q14="","",Q14*'Annual P&L'!Q7)
A16: Mix check | B16: % | C16: =IF(COUNT(C8,C10,C12,C14)=0,"",SUM(C8,C10,C12,C14)) -> 1 | D16: =IF(COUNT(D8,D10,D12,D14)=0,"",SUM(D8,D10,D12,D14)) -> 1 | E16: =IF(COUNT(E8,E10,E12,E14)=0,"",SUM(E8,E10,E12,E14)) -> 1 | F16: =IF(COUNT(F8,F10,F12,F14)=0,"",SUM(F8,F10,F12,F14)) -> 0.823 | G16: =IF(COUNT(G8,G10,G12,G14)=0,"",SUM(G8,G10,G12,G14)) -> 0.831 | H16: =IF(COUNT(H8,H10,H12,H14)=0,"",SUM(H8,H10,H12,H14)) -> 0.567 | I16: =IF(COUNT(I8,I10,I12,I14)=0,"",SUM(I8,I10,I12,I14)) -> 0.578 | J16: =IF(COUNT(J8,J10,J12,J14)=0,"",SUM(J8,J10,J12,J14)) -> 0.577 | ... Q16: =IF(COUNT(Q8,Q10,Q12,Q14)=0,"",SUM(Q8,Q10,Q12,Q14))
A19: Current strategic market units — disclosed years onward
A20: Americas 1 mix | B20: % | H20: ='Raw Operating'!H46 -> 0.294 | I20: ='Raw Operating'!I46 -> 0.279 | J20: ='Raw Operating'!J46 -> 0.291 | K20: ='Raw Operating'!K46 -> 0.3 | L20: ='Raw Operating'!L46 -> 0.317 | M20: ='Raw Operating'!M46 -> 0.332 | N20: =M20 -> 0.332 | O20: =N20 -> 0.332 | P20: =O20 -> 0.332 | Q20: =P20 -> 0.332
A21: Americas 1 revenue | B21: ₹ cr | C21: =IF(C20="","",C20*'Annual P&L'!C7) | D21: =IF(D20="","",D20*'Annual P&L'!D7) | E21: =IF(E20="","",E20*'Annual P&L'!E7) | F21: =IF(F20="","",F20*'Annual P&L'!F7) | G21: =IF(G20="","",G20*'Annual P&L'!G7) | H21: =IF(H20="","",H20*'Annual P&L'!H7) -> 18211.242 | I21: =IF(I20="","",I20*'Annual P&L'!I7) -> 22067.059 | J21: =IF(J20="","",J20*'Annual P&L'!J7) -> 26331.892 | ... Q21: =IF(Q20="","",Q20*'Annual P&L'!Q7) -> 39303.128
A22: Americas 2 mix | B22: % | H22: ='Raw Operating'!H47 -> 0.297 | I22: ='Raw Operating'!I47 -> 0.306 | J22: ='Raw Operating'!J47 -> 0.31 | K22: ='Raw Operating'!K47 -> 0.301 | L22: ='Raw Operating'!L47 -> 0.306 | M22: ='Raw Operating'!M47 -> 0.292 | N22: =M22 -> 0.292 | O22: =N22 -> 0.292 | P22: =O22 -> 0.292 | Q22: =P22 -> 0.292
A23: Americas 2 revenue | B23: ₹ cr | C23: =IF(C22="","",C22*'Annual P&L'!C7) | D23: =IF(D22="","",D22*'Annual P&L'!D7) | E23: =IF(E22="","",E22*'Annual P&L'!E7) | F23: =IF(F22="","",F22*'Annual P&L'!F7) | G23: =IF(G22="","",G22*'Annual P&L'!G7) | H23: =IF(H22="","",H22*'Annual P&L'!H7) -> 18397.071 | I23: =IF(I22="","",I22*'Annual P&L'!I7) -> 24202.58 | J23: =IF(J22="","",J22*'Annual P&L'!J7) -> 28051.156 | ... Q23: =IF(Q22="","",Q22*'Annual P&L'!Q7) -> 34567.812
A24: Europe mix | B24: % | C24: ='Raw Operating'!C43 -> 0.253 | D24: ='Raw Operating'!D43 -> 0.244 | E24: ='Raw Operating'!E43 -> 0.256 | F24: ='Raw Operating'!F43 -> 0.255 | G24: ='Raw Operating'!G43 -> 0.24 | H24: ='Raw Operating'!H43 -> 0.273 | I24: ='Raw Operating'!I43 -> 0.299 | J24: ='Raw Operating'!J43 -> 0.286 | ... M24: ='Raw Operating'!M43 -> 0.265 | N24: =M24 -> 0.265 | O24: =N24 -> 0.265 | P24: =O24 -> 0.265 | Q24: =P24 -> 0.265
A25: Europe revenue | B25: ₹ cr | C25: =IF(C24="","",C24*'Annual P&L'!C7) -> 12964.732 | D25: =IF(D24="","",D24*'Annual P&L'!D7) -> 13429.809 | E25: =IF(E24="","",E24*'Annual P&L'!E7) -> 13948.698 | F25: =IF(F24="","",F24*'Annual P&L'!F7) -> 14939.048 | G25: =IF(G24="","",G24*'Annual P&L'!G7) -> 14645.568 | H25: =IF(H24="","",H24*'Annual P&L'!H7) -> 16910.439 | I25: =IF(I24="","",I24*'Annual P&L'!I7) -> 23648.927 | J25: =IF(J24="","",J24*'Annual P&L'!J7) -> 25879.454 | ... Q25: =IF(Q24="","",Q24*'Annual P&L'!Q7) -> 31371.473
A26: APMEA mix | B26: % | H26: ='Raw Operating'!H48 -> 0.136 | I26: ='Raw Operating'!I48 -> 0.116 | J26: ='Raw Operating'!J48 -> 0.113 | K26: ='Raw Operating'!K48 -> 0.115 | L26: ='Raw Operating'!L48 -> 0.106 | M26: ='Raw Operating'!M48 -> 0.111 | N26: =M26 -> 0.111 | O26: =N26 -> 0.111 | P26: =O26 -> 0.111 | Q26: =P26 -> 0.111
A27: APMEA revenue | B27: ₹ cr | C27: =IF(C26="","",C26*'Annual P&L'!C7) | D27: =IF(D26="","",D26*'Annual P&L'!D7) | E27: =IF(E26="","",E26*'Annual P&L'!E7) | F27: =IF(F26="","",F26*'Annual P&L'!F7) | G27: =IF(G26="","",G26*'Annual P&L'!G7) | H27: =IF(H26="","",H26*'Annual P&L'!H7) -> 8424.248 | I27: =IF(I26="","",I26*'Annual P&L'!I7) -> 9174.8344 | J27: =IF(J26="","",J26*'Annual P&L'!J7) -> 10225.099 | ... Q27: =IF(Q26="","",Q26*'Annual P&L'!Q7) -> 13140.504
A28: Mix check | B28: % | C28: =IF(COUNT(C20,C22,C24,C26)=0,"",SUM(C20,C22,C24,C26)) -> 0.253 | D28: =IF(COUNT(D20,D22,D24,D26)=0,"",SUM(D20,D22,D24,D26)) -> 0.244 | E28: =IF(COUNT(E20,E22,E24,E26)=0,"",SUM(E20,E22,E24,E26)) -> 0.256 | F28: =IF(COUNT(F20,F22,F24,F26)=0,"",SUM(F20,F22,F24,F26)) -> 0.255 | G28: =IF(COUNT(G20,G22,G24,G26)=0,"",SUM(G20,G22,G24,G26)) -> 0.24 | H28: =IF(COUNT(H20,H22,H24,H26)=0,"",SUM(H20,H22,H24,H26)) -> 1 | I28: =IF(COUNT(I20,I22,I24,I26)=0,"",SUM(I20,I22,I24,I26)) -> 1 | J28: =IF(COUNT(J20,J22,J24,J26)=0,"",SUM(J20,J22,J24,J26)) -> 1 | ... Q28: =IF(COUNT(Q20,Q22,Q24,Q26)=0,"",SUM(Q20,Q22,Q24,Q26)) -> 1
A31: Revenue currency mix and absolute revenue
A32: USD mix | B32: % | C32: ='Raw Operating'!C25 -> 0.6 | D32: ='Raw Operating'!D25 -> 0.61 | E32: ='Raw Operating'!E25 -> 0.58 | F32: ='Raw Operating'!F25 -> 0.61 | G32: ='Raw Operating'!G25 -> 0.63 | H32: ='Raw Operating'!H25 -> 0.61 | I32: ='Raw Operating'!I25 -> 0.59 | J32: ='Raw Operating'!J25 -> 0.61 | ... M32: ='Raw Operating'!M25 -> 0.61 | N32: =M32 -> 0.61 | O32: =N32 -> 0.61 | P32: =O32 -> 0.61 | Q32: =P32 -> 0.61
A33: USD revenue | B33: ₹ cr | C33: =IF(C32="","",C32*'Annual P&L'!C7) -> 30746.4 | D33: =IF(D32="","",D32*'Annual P&L'!D7) -> 33574.522 | E33: =IF(E32="","",E32*'Annual P&L'!E7) -> 31602.518 | F33: =IF(F32="","",F32*'Annual P&L'!F7) -> 35736.545 | G33: =IF(G32="","",G32*'Annual P&L'!G7) -> 38444.616 | H33: =IF(H32="","",H32*'Annual P&L'!H7) -> 37785.23 | I33: =IF(I32="","",I32*'Annual P&L'!I7) -> 46665.106 | J33: =IF(J32="","",J32*'Annual P&L'!J7) -> 55197.436 | ... Q33: =IF(Q32="","",Q32*'Annual P&L'!Q7) -> 72213.579
A34: GBP mix | B34: % | C34: ='Raw Operating'!C26 -> 0.12 | D34: ='Raw Operating'!D26 -> 0.1 | E34: ='Raw Operating'!E26 -> 0.1 | F34: ='Raw Operating'!F26 -> 0.1 | G34: ='Raw Operating'!G26 -> 0.1 | H34: ='Raw Operating'!H26 -> 0.1 | I34: ='Raw Operating'!I26 -> 0.11 | J34: ='Raw Operating'!J26 -> 0.1 | ... M34: ='Raw Operating'!M26 -> 0.11 | N34: =M34 -> 0.11 | O34: =N34 -> 0.11 | P34: =O34 -> 0.11 | Q34: =P34 -> 0.11
A35: GBP revenue | B35: ₹ cr | C35: =IF(C34="","",C34*'Annual P&L'!C7) -> 6149.28 | D35: =IF(D34="","",D34*'Annual P&L'!D7) -> 5504.02 | E35: =IF(E34="","",E34*'Annual P&L'!E7) -> 5448.71 | F35: =IF(F34="","",F34*'Annual P&L'!F7) -> 5858.45 | G35: =IF(G34="","",G34*'Annual P&L'!G7) -> 6102.32 | H35: =IF(H34="","",H34*'Annual P&L'!H7) -> 6194.3 | I35: =IF(I34="","",I34*'Annual P&L'!I7) -> 8700.274 | J35: =IF(J34="","",J34*'Annual P&L'!J7) -> 9048.76 | ... Q35: =IF(Q34="","",Q34*'Annual P&L'!Q7) -> 13022.121
A36: EUR mix | B36: % | C36: ='Raw Operating'!C27 -> 0.08 | D36: ='Raw Operating'!D27 -> 0.09 | E36: ='Raw Operating'!E27 -> 0.09 | F36: ='Raw Operating'!F27 -> 0.09 | G36: ='Raw Operating'!G27 -> 0.08 | H36: ='Raw Operating'!H27 -> 0.08 | I36: ='Raw Operating'!I27 -> 0.1 | J36: ='Raw Operating'!J27 -> 0.1 | ... M36: ='Raw Operating'!M27 -> 0.09 | N36: =M36 -> 0.09 | O36: =N36 -> 0.09 | P36: =O36 -> 0.09 | Q36: =P36 -> 0.09
A37: EUR revenue | B37: ₹ cr | C37: =IF(C36="","",C36*'Annual P&L'!C7) -> 4099.52 | D37: =IF(D36="","",D36*'Annual P&L'!D7) -> 4953.618 | E37: =IF(E36="","",E36*'Annual P&L'!E7) -> 4903.839 | F37: =IF(F36="","",F36*'Annual P&L'!F7) -> 5272.605 | G37: =IF(G36="","",G36*'Annual P&L'!G7) -> 4881.856 | H37: =IF(H36="","",H36*'Annual P&L'!H7) -> 4955.44 | I37: =IF(I36="","",I36*'Annual P&L'!I7) -> 7909.34 | J37: =IF(J36="","",J36*'Annual P&L'!J7) -> 9048.76 | ... Q37: =IF(Q36="","",Q36*'Annual P&L'!Q7) -> 10654.463
A38: INR mix | B38: % | C38: ='Raw Operating'!C28 -> 0.07 | D38: ='Raw Operating'!D28 -> 0.07 | E38: ='Raw Operating'!E28 -> 0.08 | F38: ='Raw Operating'!F28 -> 0.05 | G38: ='Raw Operating'!G28 -> 0.04 | H38: ='Raw Operating'!H28 -> 0.05 | I38: ='Raw Operating'!I28 -> 0.05 | J38: ='Raw Operating'!J28 -> 0.04 | ... M38: ='Raw Operating'!M28 -> 0.05 | N38: =M38 -> 0.05 | O38: =N38 -> 0.05 | P38: =O38 -> 0.05 | Q38: =P38 -> 0.05
A39: INR revenue | B39: ₹ cr | C39: =IF(C38="","",C38*'Annual P&L'!C7) -> 3587.08 | D39: =IF(D38="","",D38*'Annual P&L'!D7) -> 3852.814 | E39: =IF(E38="","",E38*'Annual P&L'!E7) -> 4358.968 | F39: =IF(F38="","",F38*'Annual P&L'!F7) -> 2929.225 | G39: =IF(G38="","",G38*'Annual P&L'!G7) -> 2440.928 | H39: =IF(H38="","",H38*'Annual P&L'!H7) -> 3097.15 | I39: =IF(I38="","",I38*'Annual P&L'!I7) -> 3954.67 | J39: =IF(J38="","",J38*'Annual P&L'!J7) -> 3619.504 | ... Q39: =IF(Q38="","",Q38*'Annual P&L'!Q7) -> 5919.1459
A40: AUD mix | B40: % | C40: ='Raw Operating'!C29 -> 0.04 | D40: ='Raw Operating'!D29 -> 0.04 | E40: ='Raw Operating'!E29 -> 0.05 | F40: ='Raw Operating'!F29 -> 0.05 | G40: ='Raw Operating'!G29 -> 0.05 | H40: ='Raw Operating'!H29 -> 0.05 | I40: ='Raw Operating'!I29 -> 0.05 | J40: ='Raw Operating'!J29 -> 0.05 | ... M40: ='Raw Operating'!M29 -> 0.04 | N40: =M40 -> 0.04 | O40: =N40 -> 0.04 | P40: =O40 -> 0.04 | Q40: =P40 -> 0.04
A41: AUD revenue | B41: ₹ cr | C41: =IF(C40="","",C40*'Annual P&L'!C7) -> 2049.76 | D41: =IF(D40="","",D40*'Annual P&L'!D7) -> 2201.608 | E41: =IF(E40="","",E40*'Annual P&L'!E7) -> 2724.355 | F41: =IF(F40="","",F40*'Annual P&L'!F7) -> 2929.225 | G41: =IF(G40="","",G40*'Annual P&L'!G7) -> 3051.16 | H41: =IF(H40="","",H40*'Annual P&L'!H7) -> 3097.15 | I41: =IF(I40="","",I40*'Annual P&L'!I7) -> 3954.67 | J41: =IF(J40="","",J40*'Annual P&L'!J7) -> 4524.38 | ... Q41: =IF(Q40="","",Q40*'Annual P&L'!Q7) -> 4735.3167
A42: CAD mix | B42: % | C42: ='Raw Operating'!C30 -> 0.02 | D42: ='Raw Operating'!D30 -> 0.02 | E42: ='Raw Operating'!E30 -> 0.02 | F42: ='Raw Operating'!F30 -> 0.03 | G42: ='Raw Operating'!G30 -> 0.03 | H42: ='Raw Operating'!H30 -> 0.03 | I42: ='Raw Operating'!I30 -> 0.03 | J42: ='Raw Operating'!J30 -> 0.03 | ... M42: ='Raw Operating'!M30 -> 0.03 | N42: =M42 -> 0.03 | O42: =N42 -> 0.03 | P42: =O42 -> 0.03 | Q42: =P42 -> 0.03
A43: CAD revenue | B43: ₹ cr | C43: =IF(C42="","",C42*'Annual P&L'!C7) -> 1024.88 | D43: =IF(D42="","",D42*'Annual P&L'!D7) -> 1100.804 | E43: =IF(E42="","",E42*'Annual P&L'!E7) -> 1089.742 | F43: =IF(F42="","",F42*'Annual P&L'!F7) -> 1757.535 | G43: =IF(G42="","",G42*'Annual P&L'!G7) -> 1830.696 | H43: =IF(H42="","",H42*'Annual P&L'!H7) -> 1858.29 | I43: =IF(I42="","",I42*'Annual P&L'!I7) -> 2372.802 | J43: =IF(J42="","",J42*'Annual P&L'!J7) -> 2714.628 | ... Q43: =IF(Q42="","",Q42*'Annual P&L'!Q7) -> 3551.4875
A44: Other mix | B44: % | C44: ='Raw Operating'!C31 -> 0.07 | D44: ='Raw Operating'!D31 -> 0.07 | E44: ='Raw Operating'!E31 -> 0.08 | F44: ='Raw Operating'!F31 -> 0.07 | G44: ='Raw Operating'!G31 -> 0.07 | H44: ='Raw Operating'!H31 -> 0.08 | I44: ='Raw Operating'!I31 -> 0.07 | J44: ='Raw Operating'!J31 -> 0.07 | ... M44: ='Raw Operating'!M31 -> 0.07 | N44: =M44 -> 0.07 | O44: =N44 -> 0.07 | P44: =O44 -> 0.07 | Q44: =P44 -> 0.07
A45: Other revenue | B45: ₹ cr | C45: =IF(C44="","",C44*'Annual P&L'!C7) -> 3587.08 | D45: =IF(D44="","",D44*'Annual P&L'!D7) -> 3852.814 | E45: =IF(E44="","",E44*'Annual P&L'!E7) -> 4358.968 | F45: =IF(F44="","",F44*'Annual P&L'!F7) -> 4100.915 | G45: =IF(G44="","",G44*'Annual P&L'!G7) -> 4271.624 | H45: =IF(H44="","",H44*'Annual P&L'!H7) -> 4955.44 | I45: =IF(I44="","",I44*'Annual P&L'!I7) -> 5536.538 | J45: =IF(J44="","",J44*'Annual P&L'!J7) -> 6334.132 | ... Q45: =IF(Q44="","",Q44*'Annual P&L'!Q7) -> 8286.8042
A46: Mix check | B46: % | C46: =IF(COUNT(C32,C34,C36,C38,C40,C42,C44)=0,"",SUM(C32,C34,C36,C38,C40,C42,C44)) -> 1 | D46: =IF(COUNT(D32,D34,D36,D38,D40,D42,D44)=0,"",SUM(D32,D34,D36,D38,D40,D42,D44)) -> 1 | E46: =IF(COUNT(E32,E34,E36,E38,E40,E42,E44)=0,"",SUM(E32,E34,E36,E38,E40,E42,E44)) -> 1 | F46: =IF(COUNT(F32,F34,F36,F38,F40,F42,F44)=0,"",SUM(F32,F34,F36,F38,F40,F42,F44)) -> 1 | G46: =IF(COUNT(G32,G34,G36,G38,G40,G42,G44)=0,"",SUM(G32,G34,G36,G38,G40,G42,G44)) -> 1 | H46: =IF(COUNT(H32,H34,H36,H38,H40,H42,H44)=0,"",SUM(H32,H34,H36,H38,H40,H42,H44)) -> 1 | I46: =IF(COUNT(I32,I34,I36,I38,I40,I42,I44)=0,"",SUM(I32,I34,I36,I38,I40,I42,I44)) -> 1 | J46: =IF(COUNT(J32,J34,J36,J38,J40,J42,J44)=0,"",SUM(J32,J34,J36,J38,J40,J42,J44)) -> 1 | ... Q46: =IF(COUNT(Q32,Q34,Q36,Q38,Q40,Q42,Q44)=0,"",SUM(Q32,Q34,Q36,Q38,Q40,Q42,Q44)) -> 1
A47: Revenue in INR | B47: ₹ cr | C47: ='Annual P&L'!C7 -> 51244 | D47: ='Annual P&L'!D7 -> 55040.2 | E47: ='Annual P&L'!E7 -> 54487.1 | F47: ='Annual P&L'!F7 -> 58584.5 | G47: ='Annual P&L'!G7 -> 61023.2 | H47: ='Annual P&L'!H7 -> 61943 | I47: ='Annual P&L'!I7 -> 79093.4 | J47: ='Annual P&L'!J7 -> 90487.6 | ... Q47: ='Annual P&L'!Q7 -> 118382.92
A48: Revenue growth in INR | B48: % | D48: =IFERROR(D47/C47-1,"") -> 0.074080868 | E48: =IFERROR(E47/D47-1,"") -> -0.010049019 | F48: =IFERROR(F47/E47-1,"") -> 0.075199451 | G48: =IFERROR(G47/F47-1,"") -> 0.041627052 | H48: =IFERROR(H47/G47-1,"") -> 0.015072956 | I48: =IFERROR(I47/H47-1,"") -> 0.2768739 | J48: =IFERROR(J47/I47-1,"") -> 0.14406006 | K48: =IFERROR(K47/J47-1,"") -> -0.0080375654 | ... Q48: =IFERROR(Q47/P47-1,"") -> 0.085114922
A49: Revenue in USD | B49: $m | C49: ='Revenue Drivers'!C34 -> 7346.3 | D49: ='Revenue Drivers'!D34 -> 7704.5 | E49: ='Revenue Drivers'!E34 -> 8060.2 | F49: ='Revenue Drivers'!F34 -> 8120.3 | G49: ='Revenue Drivers'!G34 -> 8256.2 | H49: ='Revenue Drivers'!H34 -> 8136.5 | I49: ='Revenue Drivers'!I34 -> 10355.9 | J49: ='Revenue Drivers'!J34 -> 11159.7 | ... Q49: ='Revenue Drivers'!Q34 -> 12204.424
A50: Revenue growth in USD | B50: % | D50: =IFERROR(D49/C49-1,"") -> 0.048759239 | E50: =IFERROR(E49/D49-1,"") -> 0.046167824 | F50: =IFERROR(F49/E49-1,"") -> 0.0074563907 | G50: =IFERROR(G49/F49-1,"") -> 0.016735835 | H50: =IFERROR(H49/G49-1,"") -> -0.014498195 | I50: =IFERROR(I49/H49-1,"") -> 0.27277085 | J50: =IFERROR(J49/I49-1,"") -> 0.07761759 | K50: =IFERROR(K49/J49-1,"") -> -0.031757126 | ... Q50: =IFERROR(Q49/P49-1,"") -> 0.073928171
A51: Average INR / USD | B51: ₹ / $ | C51: ='Revenue Drivers'!C35 -> 69.754843 | D51: ='Revenue Drivers'!D35 -> 71.439029 | E51: ='Revenue Drivers'!E35 -> 67.600184 | F51: ='Revenue Drivers'!F35 -> 72.145734 | G51: ='Revenue Drivers'!G35 -> 73.911969 | H51: ='Revenue Drivers'!H35 -> 76.129786 | I51: ='Revenue Drivers'!I35 -> 76.375206 | J51: ='Revenue Drivers'!J35 -> 81.084259 | ... Q51: ='Revenue Drivers'!Q35 -> 97

Sheet Client Data
A1: Client Metrics and Deal Bookings
A2: Client bands, concentration, active clients, revenue per client and both total / large-deal TCV
A5: Metric | B5: Units | C5: FY16A | D5: FY17A | E5: FY18A | F5: FY19A | G5: FY20A | H5: FY21A | I5: FY22A | J5: FY23A | K5: FY24A | L5: FY25A | M5: FY26A | N5: FY27E | O5: FY28E | P5: FY29E | Q5: FY30E
A7: Active clients | B7: # | C7: ='Raw Operating'!C13 -> 1223 | D7: ='Raw Operating'!D13 -> 1323 | E7: ='Raw Operating'!E13 -> 1248 | F7: ='Raw Operating'!F13 -> 1115 | G7: ='Raw Operating'!G13 -> 1074 | H7: ='Raw Operating'!H13 -> 1120 | I7: ='Raw Operating'!I13 -> 1369 | J7: ='Raw Operating'!J13 -> 1441 | ... M7: ='Raw Operating'!M13 -> 1233 | N7: =ROUND(M7*(1+'Annual P&L'!N8),0) -> 1270 | O7: =ROUND(N7*(1+'Annual P&L'!O8),0) -> 1346 | P7: =ROUND(O7*(1+'Annual P&L'!P8),0) -> 1452 | Q7: =ROUND(P7*(1+'Annual P&L'!Q8),0) -> 1576
A8: $100m+ clients | B8: # | C8: ='Raw Operating'!C14 -> 9 | D8: ='Raw Operating'!D14 -> 9 | E8: ='Raw Operating'!E14 -> 8 | F8: ='Raw Operating'!F14 -> 10 | G8: ='Raw Operating'!G14 -> 15 | H8: ='Raw Operating'!H14 -> 11 | I8: ='Raw Operating'!I14 -> 19 | J8: ='Raw Operating'!J14 -> 19 | ... M8: ='Raw Operating'!M14 -> 16 | N8: =ROUND(M8*(1+'Annual P&L'!N8),0) -> 16 | O8: =ROUND(N8*(1+'Annual P&L'!O8),0) -> 17 | P8: =ROUND(O8*(1+'Annual P&L'!P8),0) -> 18 | Q8: =ROUND(P8*(1+'Annual P&L'!Q8),0) -> 20
A9: $50m+ clients | B9: # | C9: ='Raw Operating'!C15 -> 33 | D9: ='Raw Operating'!D15 -> 34 | E9: ='Raw Operating'!E15 -> 39 | F9: ='Raw Operating'!F15 -> 41 | G9: ='Raw Operating'!G15 -> 40 | H9: ='Raw Operating'!H15 -> 40 | I9: ='Raw Operating'!I15 -> 50 | J9: ='Raw Operating'!J15 -> 53 | ... M9: ='Raw Operating'!M15 -> 45 | N9: =ROUND(M9*(1+'Annual P&L'!N8),0) -> 46 | O9: =ROUND(N9*(1+'Annual P&L'!O8),0) -> 49 | P9: =ROUND(O9*(1+'Annual P&L'!P8),0) -> 53 | Q9: =ROUND(P9*(1+'Annual P&L'!Q8),0) -> 58
A10: $20m+ clients | B10: # | C10: ='Raw Operating'!C16 -> 89 | D10: ='Raw Operating'!D16 -> 91 | E10: ='Raw Operating'!E16 -> 95 | F10: ='Raw Operating'!F16 -> 96 | G10: ='Raw Operating'!G16 -> 96 | H10: ='Raw Operating'!H16 -> 93 | I10: ='Raw Operating'!I16 -> 117 | J10: ='Raw Operating'!J16 -> 117 | ... M10: ='Raw Operating'!M16 -> 106 | N10: =ROUND(M10*(1+'Annual P&L'!N8),0) -> 109 | O10: =ROUND(N10*(1+'Annual P&L'!O8),0) -> 116 | P10: =ROUND(O10*(1+'Annual P&L'!P8),0) -> 125 | Q10: =ROUND(P10*(1+'Annual P&L'!Q8),0) -> 136
A11: $10m+ clients | B11: # | C11: ='Raw Operating'!C17 -> 160 | D11: ='Raw Operating'!D17 -> 163 | E11: ='Raw Operating'!E17 -> 171 | F11: ='Raw Operating'!F17 -> 172 | G11: ='Raw Operating'!G17 -> 166 | H11: ='Raw Operating'!H17 -> 167 | I11: ='Raw Operating'!I17 -> 194 | J11: ='Raw Operating'!J17 -> 208 | ... M11: ='Raw Operating'!M17 -> 183 | N11: =ROUND(M11*(1+'Annual P&L'!N8),0) -> 189 | O11: =ROUND(N11*(1+'Annual P&L'!O8),0) -> 200 | P11: =ROUND(O11*(1+'Annual P&L'!P8),0) -> 216 | Q11: =ROUND(P11*(1+'Annual P&L'!Q8),0) -> 234
A12: $5m+ clients | B12: # | C12: ='Raw Operating'!C18 -> 248 | D12: ='Raw Operating'!D18 -> 268 | E12: ='Raw Operating'!E18 -> 277 | F12: ='Raw Operating'!F18 -> 262 | G12: ='Raw Operating'!G18 -> 260 | H12: ='Raw Operating'!H18 -> 257 | I12: ='Raw Operating'!I18 -> 297 | J12: ='Raw Operating'!J18 -> 311 | ... M12: ='Raw Operating'!M18 -> 289 | N12: =ROUND(M12*(1+'Annual P&L'!N8),0) -> 298 | O12: =ROUND(N12*(1+'Annual P&L'!O8),0) -> 316 | P12: =ROUND(O12*(1+'Annual P&L'!P8),0) -> 341 | Q12: =ROUND(P12*(1+'Annual P&L'!Q8),0) -> 370
A13: $1m+ clients | B13: # | C13: ='Raw Operating'!C19 -> 550 | D13: ='Raw Operating'!D19 -> 602 | E13: ='Raw Operating'!E19 -> 631 | F13: ='Raw Operating'!F19 -> 571 | G13: ='Raw Operating'!G19 -> 574 | H13: ='Raw Operating'!H19 -> 566 | I13: ='Raw Operating'!I19 -> 679 | J13: ='Raw Operating'!J19 -> 750 | ... M13: ='Raw Operating'!M19 -> 715 | N13: =ROUND(M13*(1+'Annual P&L'!N8),0) -> 737 | O13: =ROUND(N13*(1+'Annual P&L'!O8),0) -> 781 | P13: =ROUND(O13*(1+'Annual P&L'!P8),0) -> 842 | Q13: =ROUND(P13*(1+'Annual P&L'!Q8),0) -> 914
A14: Top client contribution | B14: % | C14: ='Raw Operating'!C20 -> 0.031 | D14: ='Raw Operating'!D20 -> 0.027 | E14: ='Raw Operating'!E20 -> 0.031 | F14: ='Raw Operating'!F20 -> 0.037 | G14: ='Raw Operating'!G20 -> 0.032 | H14: ='Raw Operating'!H20 -> 0.031 | I14: ='Raw Operating'!I20 -> 0.032 | J14: ='Raw Operating'!J20 -> 0.032 | ... M14: ='Raw Operating'!M20 -> 0.046 | N14: =M14 -> 0.046 | O14: =N14 -> 0.046 | P14: =O14 -> 0.046 | Q14: =P14 -> 0.046
A15: Top 5 client contribution | B15: % | C15: ='Raw Operating'!C21 -> 0.05 | D15: ='Raw Operating'!D21 -> 0.05 | E15: ='Raw Operating'!E21 -> 0.05 | F15: ='Raw Operating'!F21 -> 0.05 | G15: ='Raw Operating'!G21 -> 0.05 | H15: ='Raw Operating'!H21 -> 0.05 | I15: ='Raw Operating'!I21 -> 0.05 | J15: ='Raw Operating'!J21 -> 0.05 | ... M15: ='Raw Operating'!M21 -> 0.05 | N15: =M15 -> 0.05 | O15: =N15 -> 0.05 | P15: =O15 -> 0.05 | Q15: =P15 -> 0.05
A16: Top 10 client contribution | B16: % | C16: ='Raw Operating'!C22 -> 0.1 | D16: ='Raw Operating'!D22 -> 0.1 | E16: ='Raw Operating'!E22 -> 0.1 | F16: ='Raw Operating'!F22 -> 0.1 | G16: ='Raw Operating'!G22 -> 0.1 | H16: ='Raw Operating'!H22 -> 0.1 | I16: ='Raw Operating'!I22 -> 0.1 | J16: ='Raw Operating'!J22 -> 0.1 | ... M16: ='Raw Operating'!M22 -> 0.1 | N16: =M16 -> 0.1 | O16: =N16 -> 0.1 | P16: =O16 -> 0.1 | Q16: =P16 -> 0.1
A17: Revenue per active client | B17: $m | C17: =IFERROR('Revenue Drivers'!C34/C7,"") -> 6.0067866 | D17: =IFERROR('Revenue Drivers'!D34/D7,"") -> 5.8235072 | E17: =IFERROR('Revenue Drivers'!E34/E7,"") -> 6.4584936 | F17: =IFERROR('Revenue Drivers'!F34/F7,"") -> 7.2827803 | G17: =IFERROR('Revenue Drivers'!G34/G7,"") -> 7.6873371 | H17: =IFERROR('Revenue Drivers'!H34/H7,"") -> 7.2647321 | I17: =IFERROR('Revenue Drivers'!I34/I7,"") -> 7.5645727 | J17: =IFERROR('Revenue Drivers'!J34/J7,"") -> 7.7444136 | ... Q17: =IFERROR('Revenue Drivers'!Q34/Q7,"") -> 7.7439241
A18: Revenue per $1m+ client proxy | B18: $m | C18: =IFERROR('Revenue Drivers'!C34/C13,"") -> 13.356909 | D18: =IFERROR('Revenue Drivers'!D34/D13,"") -> 12.798173 | E18: =IFERROR('Revenue Drivers'!E34/E13,"") -> 12.773693 | F18: =IFERROR('Revenue Drivers'!F34/F13,"") -> 14.221191 | G18: =IFERROR('Revenue Drivers'!G34/G13,"") -> 14.383624 | H18: =IFERROR('Revenue Drivers'!H34/H13,"") -> 14.375442 | I18: =IFERROR('Revenue Drivers'!I34/I13,"") -> 15.251694 | J18: =IFERROR('Revenue Drivers'!J34/J13,"") -> 14.8796 | ... Q18: =IFERROR('Revenue Drivers'!Q34/Q13,"") -> 13.352762
A19: Incremental active clients | B19: # | D19: =IF(OR(D7="",C7=""),"",D7-C7) -> 100 | E19: =IF(OR(E7="",D7=""),"",E7-D7) -> -75 | F19: =IF(OR(F7="",E7=""),"",F7-E7) -> -133 | G19: =IF(OR(G7="",F7=""),"",G7-F7) -> -41 | H19: =IF(OR(H7="",G7=""),"",H7-G7) -> 46 | I19: =IF(OR(I7="",H7=""),"",I7-H7) -> 249 | J19: =IF(OR(J7="",I7=""),"",J7-I7) -> 72 | K19: =IF(OR(K7="",J7=""),"",K7-J7) -> -70 | ... Q19: =IF(OR(Q7="",P7=""),"",Q7-P7) -> 124
A20: Incremental $1m+ clients | B20: # | D20: =IF(OR(D13="",C13=""),"",D13-C13) -> 52 | E20: =IF(OR(E13="",D13=""),"",E13-D13) -> 29 | F20: =IF(OR(F13="",E13=""),"",F13-E13) -> -60 | G20: =IF(OR(G13="",F13=""),"",G13-F13) -> 3 | H20: =IF(OR(H13="",G13=""),"",H13-G13) -> -8 | I20: =IF(OR(I13="",H13=""),"",I13-H13) -> 113 | J20: =IF(OR(J13="",I13=""),"",J13-I13) -> 71 | K20: =IF(OR(K13="",J13=""),"",K13-J13) -> -9 | ... Q20: =IF(OR(Q13="",P13=""),"",Q13-P13) -> 72
A21: Total bookings | B21: $m | C21: ='Raw Operating'!C23 -> 0 | D21: ='Raw Operating'!D23 -> 0 | E21: ='Raw Operating'!E23 -> 0 | F21: ='Raw Operating'!F23 -> 0 | G21: ='Raw Operating'!G23 -> 0 | H21: ='Raw Operating'!H23 -> 0 | I21: ='Raw Operating'!I23 -> 0 | J21: ='Raw Operating'!J23 -> 0 | ... M21: ='Raw Operating'!M23 -> 16449 | N21: ='Revenue Drivers'!N23 -> 17435.94 | O21: ='Revenue Drivers'!O23 -> 18656.456 | P21: ='Revenue Drivers'!P23 -> 20148.972 | Q21: ='Revenue Drivers'!Q23 -> 21760.89
A22: Total bookings growth | B22: % | D22: =IFERROR(D21/C21-1,"") | E22: =IFERROR(E21/D21-1,"") | F22: =IFERROR(F21/E21-1,"") | G22: =IFERROR(G21/F21-1,"") | H22: =IFERROR(H21/G21-1,"") | I22: =IFERROR(I21/H21-1,"") | J22: =IFERROR(J21/I21-1,"") | K22: =IFERROR(K21/J21-1,"") | ... Q22: =IFERROR(Q21/P21-1,"") -> 0.08
A23: Large-deal TCV | B23: $m | C23: ='Raw Operating'!C24 -> 0 | D23: ='Raw Operating'!D24 -> 0 | E23: ='Raw Operating'!E24 -> 0 | F23: ='Raw Operating'!F24 -> 0 | G23: ='Raw Operating'!G24 -> 0 | H23: ='Raw Operating'!H24 -> 0 | I23: ='Raw Operating'!I24 -> 0 | J23: ='Raw Operating'!J24 -> 0 | ... M23: ='Raw Operating'!M24 -> 7829 | N23: =N21*M25 -> 8298.74 | O23: =O21*N25 -> 8879.6518 | P23: =P21*O25 -> 9590.0239 | Q23: =Q21*P25 -> 10357.226
A24: Large-deal TCV growth | B24: % | D24: =IFERROR(D23/C23-1,"") | E24: =IFERROR(E23/D23-1,"") | F24: =IFERROR(F23/E23-1,"") | G24: =IFERROR(G23/F23-1,"") | H24: =IFERROR(H23/G23-1,"") | I24: =IFERROR(I23/H23-1,"") | J24: =IFERROR(J23/I23-1,"") | K24: =IFERROR(K23/J23-1,"") | ... Q24: =IFERROR(Q23/P23-1,"") -> 0.08
A25: Large-deal / total bookings | B25: % | C25: =IFERROR(C23/C21,"") | D25: =IFERROR(D23/D21,"") | E25: =IFERROR(E23/E21,"") | F25: =IFERROR(F23/F21,"") | G25: =IFERROR(G23/G21,"") | H25: =IFERROR(H23/H21,"") | I25: =IFERROR(I23/I21,"") | J25: =IFERROR(J23/J21,"") | ... Q25: =IFERROR(Q23/Q21,"") -> 0.47595599
A26: Bookings / USD revenue | B26: x | C26: =IFERROR(C21/'Revenue Drivers'!C34,"") -> 0 | D26: =IFERROR(D21/'Revenue Drivers'!D34,"") -> 0 | E26: =IFERROR(E21/'Revenue Drivers'!E34,"") -> 0 | F26: =IFERROR(F21/'Revenue Drivers'!F34,"") -> 0 | G26: =IFERROR(G21/'Revenue Drivers'!G34,"") -> 0 | H26: =IFERROR(H21/'Revenue Drivers'!H34,"") -> 0 | I26: =IFERROR(I21/'Revenue Drivers'!I34,"") -> 0 | J26: =IFERROR(J21/'Revenue Drivers'!J34,"") -> 0 | ... Q26: =IFERROR(Q21/'Revenue Drivers'!Q34,"") -> 1.7830329

Sheet Revenue Drivers
A1: Revenue Drivers
A2: Capacity, bookings, T&M AI deflation and AI uplift are separately carved out
A5: Metric | B5: Units | C5: FY16A | D5: FY17A | E5: FY18A | F5: FY19A | G5: FY20A | H5: FY21A | I5: FY22A | J5: FY23A | K5: FY24A | L5: FY25A | M5: FY26A | N5: FY27E | O5: FY28E | P5: FY29E | Q5: FY30E
A7: Closing headcount | B7: # | C7: ='Raw Operating'!C8 -> 172912 | D7: ='Raw Operating'!D8 -> 181482 | E7: ='Raw Operating'!E8 -> 163827 | F7: ='Raw Operating'!F8 -> 171425 | G7: ='Raw Operating'!G8 -> 182886 | H7: ='Raw Operating'!H8 -> 197712 | I7: ='Raw Operating'!I8 -> 243128 | J7: ='Raw Operating'!J8 -> 256921 | ... M7: ='Raw Operating'!M8 -> 242156 | N7: =M7*(1+Assumptions!C6) -> 245788.34 | O7: =N7*(1+Assumptions!D6) -> 251933.05 | P7: =O7*(1+Assumptions!E6) -> 259491.04 | Q7: =P7*(1+Assumptions!F6) -> 268573.23
A8: Headcount growth | B8: % | D8: =IFERROR(D7/C7-1,"") -> 0.049562783 | E8: =IFERROR(E7/D7-1,"") -> -0.097282375 | F8: =IFERROR(F7/E7-1,"") -> 0.046378192 | G8: =IFERROR(G7/F7-1,"") -> 0.066857226 | H8: =IFERROR(H7/G7-1,"") -> 0.081066894 | I8: =IFERROR(I7/H7-1,"") -> 0.22970786 | J8: =IFERROR(J7/I7-1,"") -> 0.056731434 | K8: =IFERROR(K7/J7-1,"") -> -0.089004013 | ... Q8: =IFERROR(Q7/P7-1,"") -> 0.035
A9: Service employee share | B9: % | C9: =IFERROR(1-'Raw Operating'!C9/C7,"") -> 0.92400759 | D9: =IFERROR(1-'Raw Operating'!D9/D7,"") -> 0.92028962 | E9: =IFERROR(1-'Raw Operating'!E9/E7,"") -> 0.90883066 | F9: =IFERROR(1-'Raw Operating'!F9/F7,"") -> 0.91623159 | G9: =IFERROR(1-'Raw Operating'!G9/G7,"") -> 0.91848474 | H9: =IFERROR(1-'Raw Operating'!H9/H7,"") -> 0.92227078 | I9: =IFERROR(1-'Raw Operating'!I9/I7,"") -> 0.92723586 | J9: =IFERROR(1-'Raw Operating'!J9/J7,"") -> 0.93388629 | ... M9: =IFERROR(1-'Raw Operating'!M9/M7,"") -> 0.93981566 | N9: =Assumptions!C7 -> 0.935 | O9: =Assumptions!D7 -> 0.936 | P9: =Assumptions!E7 -> 0.937 | Q9: =Assumptions!F7 -> 0.938
A10: Service employees | B10: # | C10: =IFERROR(C7*C9,"") -> 159772 | D10: =IFERROR(D7*D9,"") -> 167016 | E10: =IFERROR(E7*E9,"") -> 148891 | F10: =IFERROR(F7*F9,"") -> 157065 | G10: =IFERROR(G7*G9,"") -> 167978 | H10: =IFERROR(H7*H9,"") -> 182344 | I10: =IFERROR(I7*I9,"") -> 225437 | J10: =IFERROR(J7*J9,"") -> 239935 | ... M10: =IFERROR(M7*M9,"") -> 227582 | N10: =N7*N9 -> 229812.1 | O10: =O7*O9 -> 235809.33 | P10: =P7*P9 -> 243143.1 | Q10: =Q7*Q9 -> 251921.69
A11: Utilization / billable rate | B11: % | C11: ='Raw Operating'!C10 -> 0.799 | D11: ='Raw Operating'!D10 -> 0.823 | E11: ='Raw Operating'!E10 -> 0.825 | F11: ='Raw Operating'!F10 -> 0.848 | G11: ='Raw Operating'!G10 -> 0.823 | H11: ='Raw Operating'!H10 -> 0.859 | I11: ='Raw Operating'!I10 -> 0.868 | J11: ='Raw Operating'!J10 -> 0.812 | ... M11: ='Raw Operating'!M10 -> 0.845 | N11: =Assumptions!C8 -> 0.845 | O11: =Assumptions!D8 -> 0.85 | P11: =Assumptions!E8 -> 0.855 | Q11: =Assumptions!F8 -> 0.858
A12: Billable FTE | B12: # | C12: =IFERROR(C10*C11,"") -> 127657.83 | D12: =IFERROR(D10*D11,"") -> 137454.17 | E12: =IFERROR(E10*E11,"") -> 122835.07 | F12: =IFERROR(F10*F11,"") -> 133191.12 | G12: =IFERROR(G10*G11,"") -> 138245.89 | H12: =IFERROR(H10*H11,"") -> 156633.5 | I12: =IFERROR(I10*I11,"") -> 195679.32 | J12: =IFERROR(J10*J11,"") -> 194827.22 | ... M12: =IFERROR(M10*M11,"") -> 192306.79 | N12: =N10*N11 -> 194191.22 | O12: =O10*O11 -> 200437.93 | P12: =P10*P11 -> 207887.35 | Q12: =Q10*Q11 -> 216148.81
A13: Billable FTE growth | B13: % | D13: =IFERROR(D12/C12-1,"") -> 0.076739047 | E13: =IFERROR(E12/D12-1,"") -> -0.10635613 | F13: =IFERROR(F12/E12-1,"") -> 0.084308533 | G13: =IFERROR(G12/F12-1,"") -> 0.037951284 | H13: =IFERROR(H12/G12-1,"") -> 0.1330065 | I13: =IFERROR(I12/H12-1,"") -> 0.24928142 | J13: =IFERROR(J12/I12-1,"") -> -0.0043545532 | K13: =IFERROR(K12/J12-1,"") -> -0.049167031 | ... Q13: =IFERROR(Q12/P12-1,"") -> 0.039740044
A14: FPP mix | B14: % | C14: ='Raw Operating'!C12 -> 0.552 | D14: ='Raw Operating'!D12 -> 0.571 | E14: ='Raw Operating'!E12 -> 0.581 | F14: ='Raw Operating'!F12 -> 0.594 | G14: ='Raw Operating'!G12 -> 0.624 | H14: ='Raw Operating'!H12 -> 0.62 | I14: ='Raw Operating'!I12 -> 0.628 | J14: ='Raw Operating'!J12 -> 0.594 | ... M14: ='Raw Operating'!M12 -> 0.543 | N14: =Assumptions!C12 -> 0.55 | O14: =Assumptions!D12 -> 0.56 | P14: =Assumptions!E12 -> 0.57 | Q14: =Assumptions!F12 -> 0.58
A15: T&M mix | B15: % | C15: =IF(C14="","",1-C14) -> 0.448 | D15: =IF(D14="","",1-D14) -> 0.429 | E15: =IF(E14="","",1-E14) -> 0.419 | F15: =IF(F14="","",1-F14) -> 0.406 | G15: =IF(G14="","",1-G14) -> 0.376 | H15: =IF(H14="","",1-H14) -> 0.38 | I15: =IF(I14="","",1-I14) -> 0.372 | J15: =IF(J14="","",1-J14) -> 0.406 | ... M15: =IF(M14="","",1-M14) -> 0.457 | N15: =1-N14 -> 0.45 | O15: =1-O14 -> 0.44 | P15: =1-P14 -> 0.43 | Q15: =1-Q14 -> 0.42
A16: Core revenue retention | B16: % | C16: =1 -> 1 | D16: =1 -> 1 | E16: =1 -> 1 | F16: =1 -> 1 | G16: =1 -> 1 | H16: =1 -> 1 | I16: =1 -> 1 | J16: =1 -> 1 | ... M16: =1 -> 1 | N16: =Assumptions!C11 -> 0.97 | O16: =Assumptions!D11 -> 0.972 | P16: =Assumptions!E11 -> 0.974 | Q16: =Assumptions!F11 -> 0.975
A17: Retained core revenue | B17: ₹ cr | C17: ='Annual P&L'!C7 -> 51244 | D17: ='Annual P&L'!D7 -> 55040.2 | E17: ='Annual P&L'!E7 -> 54487.1 | F17: ='Annual P&L'!F7 -> 58584.5 | G17: ='Annual P&L'!G7 -> 61023.2 | H17: ='Annual P&L'!H7 -> 61943 | I17: ='Annual P&L'!I7 -> 79093.4 | J17: ='Annual P&L'!J7 -> 90487.6 | ... M17: ='Annual P&L'!M7 -> 92624 | N17: =M31*N16 -> 89845.28 | O17: =N31*O16 -> 92754.792 | P17: =O31*P16 -> 98537.083 | Q17: =P31*Q16 -> 106369.7
A18: Pricing / productivity uplift | B18: % | C18: =0 -> 0 | D18: =0 -> 0 | E18: =0 -> 0 | F18: =0 -> 0 | G18: =0 -> 0 | H18: =0 -> 0 | I18: =0 -> 0 | J18: =0 -> 0 | ... M18: =0 -> 0 | N18: =Assumptions!C9 -> 0.02 | O18: =Assumptions!D9 -> 0.025 | P18: =Assumptions!E9 -> 0.03 | Q18: =Assumptions!F9 -> 0.03
A19: Capacity uplift realization | B19: % | C19: =0 -> 0 | D19: =0 -> 0 | E19: =0 -> 0 | F19: =0 -> 0 | G19: =0 -> 0 | H19: =0 -> 0 | I19: =0 -> 0 | J19: =0 -> 0 | ... M19: =0 -> 0 | N19: =Assumptions!C10 -> 0.65 | O19: =Assumptions!D10 -> 0.7 | P19: =Assumptions!E10 -> 0.75 | Q19: =Assumptions!F10 -> 0.75
A20: Billable capacity + productivity uplift | B20: ₹ cr | C20: =0 -> 0 | D20: =0 -> 0 | E20: =0 -> 0 | F20: =0 -> 0 | G20: =0 -> 0 | H20: =0 -> 0 | I20: =0 -> 0 | J20: =0 -> 0 | ... M20: =0 -> 0 | N20: =M31*(MAX(-1,N13)+N18)*N19 -> 1794.0725 | O20: =N31*(MAX(-1,O13)+O18)*O19 -> 3818.7379 | P20: =O31*(MAX(-1,P13)+P18)*P19 -> 5096.2381 | Q20: =P31*(MAX(-1,Q13)+Q18)*Q19 -> 5706.3286
A21: T&M AI deflation rate | B21: % | C21: =0 -> 0 | D21: =0 -> 0 | E21: =0 -> 0 | F21: =0 -> 0 | G21: =0 -> 0 | H21: =0 -> 0 | I21: =0 -> 0 | J21: =0 -> 0 | ... M21: =0 -> 0 | N21: =Assumptions!C13 -> 0.01 | O21: =Assumptions!D13 -> 0.013 | P21: =Assumptions!E13 -> 0.016 | Q21: =Assumptions!F13 -> 0.018
A22: T&M AI deflation drag | B22: ₹ cr | C22: =0 -> 0 | D22: =0 -> 0 | E22: =0 -> 0 | F22: =0 -> 0 | G22: =0 -> 0 | H22: =0 -> 0 | I22: =0 -> 0 | J22: =0 -> 0 | ... M22: =0 -> 0 | N22: =-M31*N15*N21 -> -416.808 | O22: =-N31*O15*O21 -> -545.84096 | P22: =-O31*P15*P21 -> -696.03196 | Q22: =-P31*Q15*Q21 -> -824.77426
A23: Total bookings | B23: $m | C23: ='Raw Operating'!C23 -> 0 | D23: ='Raw Operating'!D23 -> 0 | E23: ='Raw Operating'!E23 -> 0 | F23: ='Raw Operating'!F23 -> 0 | G23: ='Raw Operating'!G23 -> 0 | H23: ='Raw Operating'!H23 -> 0 | I23: ='Raw Operating'!I23 -> 0 | J23: ='Raw Operating'!J23 -> 0 | ... M23: ='Raw Operating'!M23 -> 16449 | N23: =M23*(1+Assumptions!C14) -> 17435.94 | O23: =N23*(1+Assumptions!D14) -> 18656.456 | P23: =O23*(1+Assumptions!E14) -> 20148.972 | Q23: =P23*(1+Assumptions!F14) -> 21760.89
A24: Bookings growth | B24: % | D24: =IFERROR(D23/C23-1,"") | E24: =IFERROR(E23/D23-1,"") | F24: =IFERROR(F23/E23-1,"") | G24: =IFERROR(G23/F23-1,"") | H24: =IFERROR(H23/G23-1,"") | I24: =IFERROR(I23/H23-1,"") | J24: =IFERROR(J23/I23-1,"") | K24: =IFERROR(K23/J23-1,"") | ... Q24: =IFERROR(Q23/P23-1,"") -> 0.08
A25: Bookings realization | B25: % | C25: =0 -> 0 | D25: =0 -> 0 | E25: =0 -> 0 | F25: =0 -> 0 | G25: =0 -> 0 | H25: =0 -> 0 | I25: =0 -> 0 | J25: =0 -> 0 | ... M25: =0 -> 0 | N25: =Assumptions!C15 -> 0.02 | O25: =Assumptions!D15 -> 0.022 | P25: =Assumptions!E15 -> 0.024 | Q25: =Assumptions!F15 -> 0.025
A26: Bookings revenue uplift | B26: ₹ cr | C26: =0 -> 0 | D26: =0 -> 0 | E26: =0 -> 0 | F26: =0 -> 0 | G26: =0 -> 0 | H26: =0 -> 0 | I26: =0 -> 0 | J26: =0 -> 0 | ... M26: =0 -> 0 | N26: =N23*Assumptions!C18/10*N25 -> 3277.9567 | O26: =O23*Assumptions!D18/10*O25 -> 3899.1993 | P26: =P23*Assumptions!E18/10*P25 -> 4642.3232 | Q26: =Q23*Assumptions!F18/10*Q25 -> 5277.0158
A27: AI uplift rate | B27: % | C27: =0 -> 0 | D27: =0 -> 0 | E27: =0 -> 0 | F27: =0 -> 0 | G27: =0 -> 0 | H27: =0 -> 0 | I27: =0 -> 0 | J27: =0 -> 0 | ... M27: =0 -> 0 | N27: =Assumptions!C16 -> 0.006 | O27: =Assumptions!D16 -> 0.01 | P27: =Assumptions!E16 -> 0.013 | Q27: =Assumptions!F16 -> 0.015
A28: AI revenue uplift | B28: ₹ cr | C28: =0 -> 0 | D28: =0 -> 0 | E28: =0 -> 0 | F28: =0 -> 0 | G28: =0 -> 0 | H28: =0 -> 0 | I28: =0 -> 0 | J28: =0 -> 0 | ... M28: =0 -> 0 | N28: =M31*N27 -> 555.744 | O28: =N31*O27 -> 954.26741 | P28: =O31*P27 -> 1315.1767 | Q28: =P31*Q27 -> 1636.4569
A29: Acquisition revenue rate | B29: % | C29: =0 -> 0 | D29: =0 -> 0 | E29: =0 -> 0 | F29: =0 -> 0 | G29: =0 -> 0 | H29: =0 -> 0 | I29: =0 -> 0 | J29: =0 -> 0 | ... M29: =0 -> 0 | N29: =Assumptions!C17 -> 0.004 | O29: =Assumptions!D17 -> 0.003 | P29: =Assumptions!E17 -> 0.002 | Q29: =Assumptions!F17 -> 0.002
A30: Acquisition contribution | B30: ₹ cr | C30: =0 -> 0 | D30: =0 -> 0 | E30: =0 -> 0 | F30: =0 -> 0 | G30: =0 -> 0 | H30: =0 -> 0 | I30: =0 -> 0 | J30: =0 -> 0 | ... M30: =0 -> 0 | N30: =M31*N29 -> 370.496 | O30: =N31*O29 -> 286.28022 | P30: =O31*P29 -> 202.33487 | Q30: =P31*Q29 -> 218.19425
A31: Calculated revenue | B31: ₹ cr | C31: ='Annual P&L'!C7 -> 51244 | D31: ='Annual P&L'!D7 -> 55040.2 | E31: ='Annual P&L'!E7 -> 54487.1 | F31: ='Annual P&L'!F7 -> 58584.5 | G31: ='Annual P&L'!G7 -> 61023.2 | H31: ='Annual P&L'!H7 -> 61943 | I31: ='Annual P&L'!I7 -> 79093.4 | J31: ='Annual P&L'!J7 -> 90487.6 | ... M31: ='Annual P&L'!M7 -> 92624 | N31: =SUM(N17,N20,N22,N26,N28,N30) -> 95426.741 | O31: =SUM(O17,O20,O22,O26,O28,O30) -> 101167.44 | P31: =SUM(P17,P20,P22,P26,P28,P30) -> 109097.12 | Q31: =SUM(Q17,Q20,Q22,Q26,Q28,Q30) -> 118382.92
A32: Annual P&L revenue | B32: ₹ cr | C32: ='Annual P&L'!C7 -> 51244 | D32: ='Annual P&L'!D7 -> 55040.2 | E32: ='Annual P&L'!E7 -> 54487.1 | F32: ='Annual P&L'!F7 -> 58584.5 | G32: ='Annual P&L'!G7 -> 61023.2 | H32: ='Annual P&L'!H7 -> 61943 | I32: ='Annual P&L'!I7 -> 79093.4 | J32: ='Annual P&L'!J7 -> 90487.6 | ... Q32: ='Annual P&L'!Q7 -> 118382.92
A33: Revenue check | B33: ₹ cr | C33: =0 -> 0 | D33: =0 -> 0 | E33: =0 -> 0 | F33: =0 -> 0 | G33: =0 -> 0 | H33: =0 -> 0 | I33: =0 -> 0 | J33: =0 -> 0 | ... M33: =0 -> 0 | N33: =N31-N32 -> 0 | O33: =O31-O32 -> 0 | P33: =P31-P32 -> 0 | Q33: =Q31-Q32 -> 0
A34: USD revenue | B34: $m | C34: ='Raw Operating'!C7 -> 7346.3 | D34: ='Raw Operating'!D7 -> 7704.5 | E34: ='Raw Operating'!E7 -> 8060.2 | F34: ='Raw Operating'!F7 -> 8120.3 | G34: ='Raw Operating'!G7 -> 8256.2 | H34: ='Raw Operating'!H7 -> 8136.5 | I34: ='Raw Operating'!I7 -> 10355.9 | J34: ='Raw Operating'!J7 -> 11159.7 | ... M34: ='Raw Operating'!M7 -> 10478.1 | N34: =N31*10/Assumptions!C18 -> 10151.781 | O34: =O31*10/Assumptions!D18 -> 10649.204 | P34: =P31*10/Assumptions!E18 -> 11364.284 | Q34: =Q31*10/Assumptions!F18 -> 12204.424
A35: INR / USD | B35: ₹ / $ | C35: =IFERROR(C31*10/C34,"") -> 69.754843 | D35: =IFERROR(D31*10/D34,"") -> 71.439029 | E35: =IFERROR(E31*10/E34,"") -> 67.600184 | F35: =IFERROR(F31*10/F34,"") -> 72.145734 | G35: =IFERROR(G31*10/G34,"") -> 73.911969 | H35: =IFERROR(H31*10/H34,"") -> 76.129786 | I35: =IFERROR(I31*10/I34,"") -> 76.375206 | J35: =IFERROR(J31*10/J34,"") -> 81.084259 | ... M35: =IFERROR(M31*10/M34,"") -> 88.397706 | N35: =Assumptions!C18 -> 94 | O35: =Assumptions!D18 -> 95 | P35: =Assumptions!E18 -> 96 | Q35: =Assumptions!F18 -> 97
A36: Revenue per billable FTE | B36: ₹ cr | C36: =IFERROR(C31/C12,"") -> 0.40141682 | D36: =IFERROR(D31/D12,"") -> 0.40042584 | E36: =IFERROR(E31/E12,"") -> 0.44357933 | F36: =IFERROR(F31/F12,"") -> 0.4398529 | G36: =IFERROR(G31/G12,"") -> 0.44141058 | H36: =IFERROR(H31/H12,"") -> 0.39546458 | I36: =IFERROR(I31/I12,"") -> 0.40419908 | J36: =IFERROR(J31/J12,"") -> 0.4644505 | ... Q36: =IFERROR(Q31/Q12,"") -> 0.54769174
A37: LTM attrition | B37: % | C37: ='Raw Operating'!C11 -> 0.161 | D37: ='Raw Operating'!D11 -> 0.163 | E37: ='Raw Operating'!E11 -> 0.166 | F37: ='Raw Operating'!F11 -> 0.176 | G37: ='Raw Operating'!G11 -> 0.147 | H37: ='Raw Operating'!H11 -> 0.121 | I37: ='Raw Operating'!I11 -> 0.238 | J37: ='Raw Operating'!J11 -> 0.192 | ... M37: ='Raw Operating'!M11 -> 0.138 | N37: =M37 -> 0.138 | O37: =N37 -> 0.138 | P37: =O37 -> 0.138 | Q37: =P37 -> 0.138

Sheet WIPRO Prices
A1: WIPRO Prices
A2: Daily WIPRO.NS close / adjusted close; this is the model market-data tab
A5: Date | B5: Close | C5: Adjusted close | D5: Volume | E5: Fiscal year | F5: Source
A6: 2015-04-01 | B6: 118.72503 | C6: 104.19318 | D6: 6354889 | E6: FY16 | F6: WIPRO.NS
A7: 2015-04-06 | B7: 116.46565 | C7: 102.21036 | D7: 7872158 | E7: FY16 | F7: WIPRO.NS
A8: 2015-04-07 | B8: 115.3219 | C8: 101.2066 | D8: 9890882 | E8: FY16 | F8: WIPRO.NS
A9: 2015-04-08 | B9: 115.55627 | C9: 101.41229 | D9: 9541026 | E9: FY16 | F9: WIPRO.NS
A10: 2015-04-09 | B10: 115.71565 | C10: 101.55215 | D10: 7049918 | E10: FY16 | F10: WIPRO.NS
A11: 2015-04-10 | B11: 115.81878 | C11: 101.64265 | D11: 5738526 | E11: FY16 | F11: WIPRO.NS
A12: 2015-04-13 | B12: 117.03753 | C12: 102.71223 | D12: 4619465 | E12: FY16 | F12: WIPRO.NS
A13: 2015-04-15 | B13: 113.7469 | C13: 99.824364 | D13: 7315918 | E13: FY16 | F13: WIPRO.NS
A14: 2015-04-16 | B14: 112.86565 | C14: 99.050995 | D14: 13076860 | E14: FY16 | F14: WIPRO.NS
A15: 2015-04-17 | B15: 110.0344 | C15: 96.566284 | D15: 8342621 | E15: FY16 | F15: WIPRO.NS
A16: 2015-04-20 | B16: 107.88753 | C16: 94.682182 | D16: 7922147 | E16: FY16 | F16: WIPRO.NS
A17: 2015-04-21 | B17: 108.40315 | C17: 95.134712 | D17: 21048960 | E17: FY16 | F17: WIPRO.NS
... A2826: 2026-08-28 | B2826: 180.28999 | C2826: 180.28999 | D2826: 7375000 | E2826: FY27 | F2826: WIPRO.NS

Sheet Valuation
A1: Valuation
A2: Historical FY-end prices; forecast reference price is editable and implied target = diluted EPS × target P/E
A5: Metric | B5: Units | C5: FY16A | D5: FY17A | E5: FY18A | F5: FY19A | G5: FY20A | H5: FY21A | I5: FY22A | J5: FY23A | K5: FY24A | L5: FY25A | M5: FY26A | N5: FY27E | O5: FY28E | P5: FY29E | Q5: FY30E
A7: Reference / FY-end share price | B7: ₹ / share | C7: 105.7969 | D7: 96.693771 | E7: 105.43127 | F7: 127.375 | G7: 98.349998 | H7: 207.075 | I7: 295.95001 | J7: 182.625 | K7: 240.05 | L7: 262.25 | M7: 187.64 | N7: =Assumptions!C51 -> 180.28999 | O7: =Assumptions!D51 -> 180.28999 | P7: =Assumptions!E51 -> 180.28999 | Q7: =Assumptions!F51 -> 180.28999
A8: Basic shares | B8: m | C8: ='Annual P&L'!C31 -> 4913.1188 | D8: ='Annual P&L'!D31 -> 6476.108 | E8: ='Annual P&L'!E31 -> 6333.3912 | F8: ='Annual P&L'!F31 -> 6007.3768 | G8: ='Annual P&L'!G31 -> 5833.384 | H8: ='Annual P&L'!H31 -> 5649.2659 | I8: ='Annual P&L'!I31 -> 5466.7058 | J8: ='Annual P&L'!J31 -> 10954.933 | ... Q8: ='Annual P&L'!Q31 -> 9644.2549
A9: Diluted shares | B9: m | C9: ='Annual P&L'!C32 -> 4923.3798 | D9: ='Annual P&L'!D32 -> 6495.1295 | E9: ='Annual P&L'!E32 -> 6344.4826 | F9: ='Annual P&L'!F32 -> 6022.3044 | G9: ='Annual P&L'!G32 -> 5847.8232 | H9: ='Annual P&L'!H32 -> 5661.6578 | I9: ='Annual P&L'!I32 -> 5482.0834 | J9: ='Annual P&L'!J32 -> 10977.982 | ... Q9: ='Annual P&L'!Q32 -> 9671.43
A10: Market capitalization | B10: ₹ cr | C10: =C7*C8/10 -> 51979.273 | D10: =D7*D8/10 -> 62619.931 | E10: =E7*E8/10 -> 66773.751 | F10: =F7*F8/10 -> 76518.962 | G10: =G7*G8/10 -> 57371.331 | H10: =H7*H8/10 -> 116982.17 | I10: =I7*I8/10 -> 161787.17 | J10: =J7*J8/10 -> 200064.47 | ... Q10: =Q7*Q8/10 -> 173876.27
A11: Cash + current investments | B11: ₹ cr | C11: =SUM('Annual Balance Sheet'!C21:C22) -> 23199.3 | D11: =SUM('Annual Balance Sheet'!D21:D22) -> 34474 | E11: =SUM('Annual Balance Sheet'!E21:E22) -> 29401.9 | F11: =SUM('Annual Balance Sheet'!F21:F22) -> 37924.5 | G11: =SUM('Annual Balance Sheet'!G21:G22) -> 33413.4 | H11: =SUM('Annual Balance Sheet'!H21:H22) -> 34550 | I11: =SUM('Annual Balance Sheet'!I21:I22) -> 34549.1 | J11: =SUM('Annual Balance Sheet'!J21:J22) -> 40111.2 | ... Q11: =SUM('Annual Balance Sheet'!Q21:Q22) -> 64878.547
A12: Borrowings + lease liabilities | B12: ₹ cr | C12: =SUM('Annual Balance Sheet'!C60:C61) -> 12522.1 | D12: =SUM('Annual Balance Sheet'!D60:D61) -> 14241.2 | E12: =SUM('Annual Balance Sheet'!E60:E61) -> 13825.9 | F12: =SUM('Annual Balance Sheet'!F60:F61) -> 9946.7 | G12: =SUM('Annual Balance Sheet'!G60:G61) -> 9724 | H12: =SUM('Annual Balance Sheet'!H60:H61) -> 10451.4 | I12: =SUM('Annual Balance Sheet'!I60:I61) -> 17592.9 | J12: =SUM('Annual Balance Sheet'!J60:J61) -> 17466.6 | ... Q12: =SUM('Annual Balance Sheet'!Q60:Q61) -> 21464.408
A13: Enterprise value | B13: ₹ cr | C13: =C10-C11+C12 -> 41302.073 | D13: =D10-D11+D12 -> 42387.131 | E13: =E10-E11+E12 -> 51197.751 | F13: =F10-F11+F12 -> 48541.162 | G13: =G10-G11+G12 -> 33681.931 | H13: =H10-H11+H12 -> 92883.572 | I13: =I10-I11+I12 -> 144830.97 | J13: =J10-J11+J12 -> 177419.87 | ... Q13: =Q10-Q11+Q12 -> 130462.13
A14: Diluted EPS | B14: ₹ / share | C14: ='Annual P&L'!C34 -> 18.092246 | D14: ='Annual P&L'!D34 -> 13.070563 | E14: ='Annual P&L'!E34 -> 12.622148 | F14: ='Annual P&L'!F34 -> 14.949593 | G14: ='Annual P&L'!G34 -> 16.624648 | H14: ='Annual P&L'!H34 -> 19.066147 | I14: ='Annual P&L'!I34 -> 22.289154 | J14: ='Annual P&L'!J34 -> 10.338876 | ... Q14: ='Annual P&L'!Q34 -> 17.909365
A15: P/E | B15: x | C15: =IFERROR(C7/C14,"") -> 5.8476375 | D15: =IFERROR(D7/D14,"") -> 7.3978275 | E15: =IFERROR(E7/E14,"") -> 8.3528788 | F15: =IFERROR(F7/F14,"") -> 8.5202988 | G15: =IFERROR(G7/G14,"") -> 5.9159148 | H15: =IFERROR(H7/H14,"") -> 10.860873 | I15: =IFERROR(I7/I14,"") -> 13.277759 | J15: =IFERROR(J7/J14,"") -> 17.663912 | ... Q15: =IFERROR(Q7/Q14,"") -> 10.0668
A16: EBITDA | B16: ₹ cr | C16: ='Annual P&L'!C15 -> 11182.5 | D16: ='Annual P&L'!D15 -> 11698.6 | E16: ='Annual P&L'!E15 -> 10541.8 | F16: ='Annual P&L'!F15 -> 11938.4 | G16: ='Annual P&L'!G15 -> 12659.2 | H16: ='Annual P&L'!H15 -> 15070.9 | I16: ='Annual P&L'!I15 -> 17119.7 | J16: ='Annual P&L'!J15 -> 17300.8 | ... Q16: ='Annual P&L'!Q15 -> 24386.881
A17: EV / EBITDA | B17: x | C17: =IFERROR(C13/C16,"") -> 3.6934561 | D17: =IFERROR(D13/D16,"") -> 3.6232652 | E17: =IFERROR(E13/E16,"") -> 4.8566422 | F17: =IFERROR(F13/F16,"") -> 4.0659688 | G17: =IFERROR(G13/G16,"") -> 2.6606682 | H17: =IFERROR(H13/H16,"") -> 6.1631072 | I17: =IFERROR(I13/I16,"") -> 8.4599009 | J17: =IFERROR(J13/J16,"") -> 10.255009 | ... Q17: =IFERROR(Q13/Q16,"") -> 5.3496848
A18: Book value | B18: ₹ cr | C18: ='Annual Balance Sheet'!C36 -> 46830.2 | D18: ='Annual Balance Sheet'!D36 -> 52269.5 | E18: ='Annual Balance Sheet'!E36 -> 48534.6 | F18: ='Annual Balance Sheet'!F36 -> 57075.3 | G18: ='Annual Balance Sheet'!G36 -> 55933.3 | H18: ='Annual Balance Sheet'!H36 -> 55459.3 | I18: ='Annual Balance Sheet'!I36 -> 65867.3 | J18: ='Annual Balance Sheet'!J36 -> 78175.3 | ... Q18: ='Annual Balance Sheet'!Q36 -> 93111.883
A19: P / book | B19: x | C19: =IFERROR(C10/C18,"") -> 1.109952 | D19: =IFERROR(D10/D18,"") -> 1.1980205 | E19: =IFERROR(E10/E18,"") -> 1.3757969 | F19: =IFERROR(F10/F18,"") -> 1.3406668 | G19: =IFERROR(G10/G18,"") -> 1.0257097 | H19: =IFERROR(H10/H18,"") -> 2.1093337 | I19: =IFERROR(I10/I18,"") -> 2.4562593 | J19: =IFERROR(J10/J18,"") -> 2.5591775 | ... Q19: =IFERROR(Q10/Q18,"") -> 1.8673907
A20: Dividend per share | B20: ₹ / share | C20: ='Annual P&L'!C35 -> 7.2243317 | D20: ='Annual P&L'!D35 -> 1.3486495 | E20: ='Annual P&L'!E35 -> 0.85578165 | F20: ='Annual P&L'!F35 -> 0.74974488 | G20: ='Annual P&L'!G35 -> 0.97524867 | H20: ='Annual P&L'!H35 -> 0.96632025 | I20: ='Annual P&L'!I35 -> 1.0000538 | J20: ='Annual P&L'!J35 -> 2.9953629 | ... Q20: ='Annual P&L'!Q35 -> 12.57188
A21: Dividend yield | B21: % | C21: =IFERROR(C20/C7,"") -> 0.068284911 | D21: =IFERROR(D20/D7,"") -> 0.013947636 | E21: =IFERROR(E20/E7,"") -> 0.0081169621 | F21: =IFERROR(F20/F7,"") -> 0.0058861227 | G21: =IFERROR(G20/G7,"") -> 0.0099161025 | H21: =IFERROR(H20/H7,"") -> 0.004666523 | I21: =IFERROR(I20/I7,"") -> 0.0033791308 | J21: =IFERROR(J20/J7,"") -> 0.016401713 | ... Q21: =IFERROR(Q20/Q7,"") -> 0.069731437
A22: Target P/E | B22: x | N22: =Assumptions!C50 -> 19 | O22: =Assumptions!D50 -> 19.5 | P22: =Assumptions!E50 -> 20 | Q22: =Assumptions!F50 -> 20.5
A23: Implied target price | B23: ₹ / share | N23: =N14*N22 -> 263.63427 | O23: =O14*O22 -> 285.04818 | P23: =P14*P22 -> 323.57336 | Q23: =Q14*Q22 -> 367.14198
A24: Upside / (downside) to reference price | B24: % | N24: =IFERROR(N23/N7-1,"") -> 0.46227901 | O24: =IFERROR(O23/O7-1,"") -> 0.58105381 | P24: =IFERROR(P23/P7-1,"") -> 0.79473831 | Q24: =IFERROR(Q23/Q7-1,"") -> 1.0363969

Sheet Checks
A1: Model Checks
A2: Accounting, cash, quarterly roll-up, operating mix, formula and circularity controls
A5: Check | B5: Status | C5: Calculated | D5: Control | E5: Difference | F5: Tolerance
A6: OVERALL MODEL STATUS | B6: =IF(COUNTIF(B7:B115,"FAIL")=0,"OK","REVIEW") -> OK
